Workbook
Name \0: #REF!
Name \1: #REF!
Name \a: #REF!
Name \b: #REF!
Name \c: #REF!
Name \d: #REF!
Name \e: #REF!
Name \i: #REF!
Name \J: #REF!
Name \k: #REF!
Name \l: #N/A
Name \m: #REF!
Name \o: #REF!
Name \p: #REF!
Name \r: #REF!
Name \T: #REF!
Name \z: #REF!
Name _: #REF!
Name _\0: #REF!
Name _\1: #REF!
Name _\a: #REF!
Name _\b: #REF!
Name _\c: #REF!
Name _\d: #REF!
Name _\e: #REF!
Name _\i: #REF!
Name _\J: #REF!
Name _\k: #REF!
Name _\l: #N/A
Name _\m: #REF!
Name _\o: #REF!
Name _\p: #REF!
Name _\r: #REF!
Name _\T: #REF!
Name _\z: #REF!
Name __: #REF!
Name ______ACR10: #REF!
Name ______ACR15: #REF!
Name ______acr20: #REF!
Name ______acr5: #REF!
Name ______ARQ1: #REF!
Name ______QT100: #REF!
Name ______QT2: #REF!
Name ______QT3: #REF!
Name ______QT4: #REF!
Name ______QT50: #REF!
Name ______QT75: #REF!
Name _____ACR10: #REF!
Name _____ACR15: #REF!
Name _____acr20: #REF!
Name _____acr5: #REF!
Name _____ARQ1: #REF!
Name _____key2: #REF!
Name _____QT100: #REF!
Name _____QT2: #REF!
Name _____QT3: #REF!
Name _____QT4: #REF!
Name _____QT50: #REF!
Name _____QT75: #REF!
Name ____key2: #REF!

Sheet CAPA
A1: DADOS DO EMPREENDIMENTO
B2: Projeto: | C2: Electra Towers | E2: ENDEREÇO DA OBRA: | F2: Rua 254, 215, Meia Praia, Itapema/SC
B3: Empresa: | C3: Thozen Empreendimentos | E3: Cidade/ES: | F3: Itapema, SC
B4: Revisão: | C4: R00 | E4: CNPJ: | F4: 43.339.082/0001-06
B6: Pazo de Obra: | C6: 48 | E6: Nº Unid. Residenciais: | F6: 192 | I6: Imagens
B8: Área do Terreno: | C8: 2095.43 | E8: Nº Unid. Comerciais: | F8: 7
B10: Área Construída: | C10: 37893.89 | E10: Nº Pavimentos: | F10: 57
B12: Área Privativa: | C12: 22778.64 | E12: Total de Dormitórios: | F12: 576
B14: Área de Lazer: | C14: 1736.27 | E14: Nº Subsolos: | F14: 0
B16: Área Comercial: | C16: 500.04 | E16: Nº Vagas: | F16: 399
B18: Torre | C18: Pavimento | D18: Área | E18: Área Privativa | F18: Perímetro | G18: Pé direito
B19: Embasamento | C19: Térreo | D19: 1565.91 | E19: 0 | G19: 4.3
B20: Embasamento | C20: Garagem 01 | D20: 1736.27 | E20: 0
B21: Embasamento | C21: Garagem 02 | D21: 1736.27 | E21: 0
B22: Embasamento | C22: Garagem 03 | D22: 1736.27 | E22: 0
B23: Embasamento | C23: Garagem 04 | D23: 1736.27 | E23: 0
B24: Embasamento | C24: Garagem 05 | D24: 1736.27 | E24: 0
B25: Embasamento | C25: Pavimento diferenciado — Lazer | D25: 1736.27 | E25: 0 | G25: 3.6
B26: Torre A | C26: Pavimento tipo — Torre A (×24) | D26: 12720.48 | E26: 11382.72 | G26: 3.24
B27: Torre B | C27: Pavimento tipo — Torre B (×24) | D27: 12892.32 | E27: 11397.12 | G27: 3.24
B28: Cobertura | C28: Casa de Máquinas | D28: 176.26 | E28: 0
B29: Cobertura | C29: Reservatórios | D29: 121.3 | E29: 0
B37: Torre | C37: Pavimento | D37: Descrição | E37: Área | I37: ETAPA
B38: Áreas Comuns | C38: =_xlfn.XLOOKUP(D38,MOBILIÁRIO!C:C,MOBILIÁRIO!B:B) -> TÉRREO | D38: {=_xlfn.UNIQUE(_xlfn._xlws.FILTER(MOBILIÁRIO!C7:C316,MOBILIÁRIO!C7:C316<>""))} -> Hall Externo | E38: =_xlfn.XLOOKUP(D38,MOBILIÁRIO!C:C,MOBILIÁRIO!F:F) -> 12.33 | I38: GERENCIAMENTO TÉCNICO E ADMINISTRATIVO
B39: Áreas Comuns | C39: =_xlfn.XLOOKUP(D39,MOBILIÁRIO!C:C,MOBILIÁRIO!B:B) -> TÉRREO | D39: Hall Térreo | E39: =_xlfn.XLOOKUP(D39,MOBILIÁRIO!C:C,MOBILIÁRIO!F:F) -> 35.27 | I39: MOVIMENTAÇÃO DE TERRA
B40: Áreas Comuns | C40: =_xlfn.XLOOKUP(D40,MOBILIÁRIO!C:C,MOBILIÁRIO!B:B) -> TÉRREO | D40: Guarita | E40: =_xlfn.XLOOKUP(D40,MOBILIÁRIO!C:C,MOBILIÁRIO!F:F) -> 4.72 | I40: CONTENÇÃO
B41: Áreas Comuns | C41: =_xlfn.XLOOKUP(D41,MOBILIÁRIO!C:C,MOBILIÁRIO!B:B) -> TÉRREO | D41: Lavapés | E41: =_xlfn.XLOOKUP(D41,MOBILIÁRIO!C:C,MOBILIÁRIO!F:F) -> 1 | I41: INFRAESTRUTURA
B42: Áreas Comuns | C42: =_xlfn.XLOOKUP(D42,MOBILIÁRIO!C:C,MOBILIÁRIO!B:B) -> TÉRREO | D42: Lavabo Pne - Térreo | E42: =_xlfn.XLOOKUP(D42,MOBILIÁRIO!C:C,MOBILIÁRIO!F:F) -> 3.77 | I42: SUPRAESTRUTURA
B43: Áreas Comuns | C43: =_xlfn.XLOOKUP(D43,MOBILIÁRIO!C:C,MOBILIÁRIO!B:B) -> TÉRREO | D43: Bicicletário/Box | E43: =_xlfn.XLOOKUP(D43,MOBILIÁRIO!C:C,MOBILIÁRIO!F:F) -> 87.33 | I43: ALVENARIAS E VEDAÇÕES
B44: Áreas Comuns | C44: =_xlfn.XLOOKUP(D44,MOBILIÁRIO!C:C,MOBILIÁRIO!B:B) -> TÉRREO | D44: Antecâmara - Térreo | E44: =_xlfn.XLOOKUP(D44,MOBILIÁRIO!C:C,MOBILIÁRIO!F:F) -> 8.07 | I44: SISTEMAS E INSTALAÇÕES ELÉTRICAS
B45: Áreas Comuns | C45: =_xlfn.XLOOKUP(D45,MOBILIÁRIO!C:C,MOBILIÁRIO!B:B) -> 2º AO 5º PAVIMENTO - GARAGENS (X5) | D45: Antecâmara - Garagens (x5) | E45: =_xlfn.XLOOKUP(D45,MOBILIÁRIO!C:C,MOBILIÁRIO!F:F) -> 33.6 | I45: SISTEMAS E INSTALAÇÕES HIDROSSANITÁRIAS E DRENAGEM
B46: Áreas Comuns | C46: =_xlfn.XLOOKUP(D46,MOBILIÁRIO!C:C,MOBILIÁRIO!B:B) -> 4º PAVIMENTO - LAZER/GARAGENS | D46: Sala de massagem | E46: =_xlfn.XLOOKUP(D46,MOBILIÁRIO!C:C,MOBILIÁRIO!F:F) -> 7.47 | I46: INSTALAÇÕES PREVENTIVAS
B47: Áreas Comuns | C47: =_xlfn.XLOOKUP(D47,MOBILIÁRIO!C:C,MOBILIÁRIO!B:B) -> 4º PAVIMENTO - LAZER/GARAGENS | D47: Banheiro - Lazer/Garagem | E47: =_xlfn.XLOOKUP(D47,MOBILIÁRIO!C:C,MOBILIÁRIO!F:F) -> 3.91 | I47: INSTALAÇÕES DE GÁS
B48: Áreas Comuns | C48: =_xlfn.XLOOKUP(D48,MOBILIÁRIO!C:C,MOBILIÁRIO!B:B) -> 4º PAVIMENTO - LAZER/GARAGENS | D48: Lavabo - Lazer/Garagem | E48: =_xlfn.XLOOKUP(D48,MOBILIÁRIO!C:C,MOBILIÁRIO!F:F) -> 2.61 | I48: EQUIPAMENTOS E SISTEMAS ESPECIAIS
B49: Áreas Comuns | C49: =_xlfn.XLOOKUP(D49,MOBILIÁRIO!C:C,MOBILIÁRIO!B:B) -> 4º PAVIMENTO - LAZER/GARAGENS | D49: Lavabo Pne - Lazer/Garagem | E49: =_xlfn.XLOOKUP(D49,MOBILIÁRIO!C:C,MOBILIÁRIO!F:F) -> 4.33 | I49: CLIMATIZAÇÃO, EXAUSTÃO MECÂNICA
B50: Áreas Comuns | C50: =_xlfn.XLOOKUP(D50,MOBILIÁRIO!C:C,MOBILIÁRIO!B:B) -> 4º PAVIMENTO - LAZER/GARAGENS | D50: Circulação - Lazer/garagem | E50: =_xlfn.XLOOKUP(D50,MOBILIÁRIO!C:C,MOBILIÁRIO!F:F) -> 30.85 | I50: INSTALAÇÕES ESPECIAIS
... B63: Áreas Comuns | C63: =_xlfn.XLOOKUP(D63,MOBILIÁRIO!C:C,MOBILIÁRIO!B:B) -> 5º PAVIMENTO - LAZER | D63: Laje Verde | E63: =_xlfn.XLOOKUP(D63,MOBILIÁRIO!C:C,MOBILIÁRIO!F:F) -> 269.95 | I63: CUB/SC
B64: Áreas Comuns | C64: =_xlfn.XLOOKUP(D64,MOBILIÁRIO!C:C,MOBILIÁRIO!B:B) -> 5º PAVIMENTO - LAZER | D64: Brinquedoteca | E64: =_xlfn.XLOOKUP(D64,MOBILIÁRIO!C:C,MOBILIÁRIO!F:F) -> 16.32
B65: Áreas Comuns | C65: =_xlfn.XLOOKUP(D65,MOBILIÁRIO!C:C,MOBILIÁRIO!B:B) -> 5º PAVIMENTO - LAZER | D65: Game Center | E65: =_xlfn.XLOOKUP(D65,MOBILIÁRIO!C:C,MOBILIÁRIO!F:F) -> 13.09 | I65: DESCRIÇÃO
B66: Áreas Comuns | C66: =_xlfn.XLOOKUP(D66,MOBILIÁRIO!C:C,MOBILIÁRIO!B:B) -> 5º PAVIMENTO - LAZER | D66: Sala de Festas | E66: =_xlfn.XLOOKUP(D66,MOBILIÁRIO!C:C,MOBILIÁRIO!F:F) -> 93.46 | I66: VALOR POR ÁREA PRIVATIVA (R$/m²)
B67: Áreas Comuns | C67: =_xlfn.XLOOKUP(D67,MOBILIÁRIO!C:C,MOBILIÁRIO!B:B) -> 5º PAVIMENTO - LAZER | D67: Terraço | E67: =_xlfn.XLOOKUP(D67,MOBILIÁRIO!C:C,MOBILIÁRIO!F:F) -> 88.11 | I67: Tipo diferenciado Apart. 1
B68: Áreas Comuns | C68: =_xlfn.XLOOKUP(D68,MOBILIÁRIO!C:C,MOBILIÁRIO!B:B) -> 5º PAVIMENTO - LAZER | D68: Wine Bar | E68: =_xlfn.XLOOKUP(D68,MOBILIÁRIO!C:C,MOBILIÁRIO!F:F) -> 29.79 | I68: Tipo diferenciado Apart. 2
B69: Áreas Comuns | C69: =_xlfn.XLOOKUP(D69,MOBILIÁRIO!C:C,MOBILIÁRIO!B:B) -> 5º PAVIMENTO - LAZER | D69: Academia | E69: =_xlfn.XLOOKUP(D69,MOBILIÁRIO!C:C,MOBILIÁRIO!F:F) -> 63.68 | I69: Tipo Apart. 01
B70: Áreas Comuns | C70: =_xlfn.XLOOKUP(D70,MOBILIÁRIO!C:C,MOBILIÁRIO!B:B) -> 5º PAVIMENTO - LAZER | D70: Espaço Crossfit | E70: =_xlfn.XLOOKUP(D70,MOBILIÁRIO!C:C,MOBILIÁRIO!F:F) -> 34.41 | I70: Tipo Apart. 02
B71: Áreas Comuns | C71: =_xlfn.XLOOKUP(D71,MOBILIÁRIO!C:C,MOBILIÁRIO!B:B) -> 5º PAVIMENTO - LAZER | D71: Antecâmara - Lazer | E71: =_xlfn.XLOOKUP(D71,MOBILIÁRIO!C:C,MOBILIÁRIO!F:F) -> 4.15 | I71: Penthouse
B72: Áreas Comuns | C72: =_xlfn.XLOOKUP(D72,MOBILIÁRIO!C:C,MOBILIÁRIO!B:B) -> 6º AO 38º PAVIMENTO - PAVIMENTOS (X33) | D72: Antecâmara - Tipos (x33) | E72: =_xlfn.XLOOKUP(D72,MOBILIÁRIO!C:C,MOBILIÁRIO!F:F) -> 221.76 | I72: Penthouse diferenciado
I73: Duplex
B76: Torre | C76: Apartamentos | D76: Área | E76: Quantidade | F76: Total vagas | G76: Total apartamentos | I76: QUADRO DE ÁREAS
B77: Torre 1 | C77: Tipo 1 | D77: 102.67 | E77: 9 | F77: 18 | G77: =E77 -> 9
B78: Torre 1 | C78: Tipo 2 | D78: 108.38 | E78: 9 | F78: 18 | G78: =E78 -> 9
B79: Torre 1 | C79: Tipo 3 penthouse (outorga) | D79: 202.02 | E79: 9 | F79: 18 | G79: =E79 -> 9
B80: Torre 1 | C80: Tipo 3 penthouse | D80: 202.02 | E80: 12 | F80: 36 | G80: =E80 -> 12
B81: Torre 1 | C81: Tipo 4 penthouse | D81: 199.18 | E81: 1 | F81: 3 | G81: =E81 -> 1
B82: Torre 1 | C82: duplex 1 | D82: 329.41 | E82: 1 | F82: 4 | G82: =E82 -> 1
D83: =SUMPRODUCT(D77:E82) -> 1184.68 | E83: =SUM(E77:E82) -> 41 | F83: =SUM(F77:F82) -> 97 | G83: =SUM(G77:G82) -> 41
B86: Torre | C86: Sala comercial | D86: Área | E86: Total vagas | F86: Total banheiros
B87: Torre 1 | C87: Sala comercial 1 | D87: 176.43 | E87: 2 | F87: 1
B88: Torre 1 | C88: Sala comercial 2 | D88: 84.08 | E88: 1 | F88: 1
B89: Torre 1 | C89: Sala comercial 3 | D89: 60.82 | E89: 1 | F89: 1
B90: Torre 1 | C90: Sala comercial 4 | D90: 132.86 | E90: 2 | F90: 1
B91: Torre 1 | C91: Sala comercial 5 | D91: 83.77 | E91: 1 | F91: 1
D92: =SUM(D87:D91) -> 537.96 | E92: =SUM(E87:E91) -> 7 | F92: =SUM(F87:F91) -> 5

Sheet EAP
A1: EAP DE ORÇAMENTO
A3: Contrutora - Obra
A5: UNIDADE CONSTRUTIVA | B5: 1 | C5: GERENCIAMENTO TÉCNICO E ADMINISTRATIVO
A6: CÉLULA CONSTRUTIVA | B6: 1 | C6: SERVIÇOS TÉCNICOS
A7: ETAPA | B7: 1.001 | C7: ESTUDOS, PROJETOS E CONSULTORIAS
A8: Subetapa | B8: 01.001.001 | C8: Estudos
A9: Subetapa | B9: 01.001.002 | C9: Projetos
A10: Subetapa | B10: 01.001.003 | C10: Consultorias
A11: Subetapa | B11: 01.001.004 | C11: Ensaios
A12: ETAPA | B12: 1.002 | C12: TAXAS E DOCUMENTOS
A13: Subetapa | B13: 01.002.001 | C13: Licenciamentos, Taxas, Impostos, Aprovações e Seguros
A14: Subetapa | B14: 01.002.002 | C14: Documentos
A15: CÉLULA CONSTRUTIVA | B15: 2 | C15: SERVIÇOS INICIAIS
A16: ETAPA | B16: 2.001 | C16: SEGURANÇA, MEIO AMBIENTE, SAÚDE
A17: Subetapa | B17: 02.001.001 | C17: Segurança do trabalho
A18: Subetapa | B18: 02.001.002 | C18: Equipamentos de proteção
A19: Subetapa | B19: 02.001.003 | C19: Meio ambiente
A20: Subetapa | B20: 02.001.004 | C20: Saúde ocupacional
A21: ETAPA | B21: 2.002 | C21: ADMINISTRAÇÃO E CANTEIRO DE OBRA
A22: Subetapa | B22: 02.002.001 | C22: Equipe de Gestão e Apoio
A23: Subetapa | B23: 02.002.002 | C23: Operação inicial de canteiro
A24: Subetapa | B24: 02.002.003 | C24: Despesas de consumo e manutenção
A25: Subetapa | B25: 02.002.004 | C25: Instalações provisórias
A26: Subetapa | B26: 02.002.005 | C26: Ligações Provisórias
A27: ETAPA | B27: 2.003 | C27: SERVIÇOS PRELIMINARES
... A29: Subetapa | B29: 02.003.002 | C29: Limpeza de terreno
A30: CÉLULA CONSTRUTIVA | B30: 3 | C30: EQUIPAMENTOS
A31: ETAPA | B31: 3.001 | C31: EQUIPAMENTOS
A32: Subetapa | B32: 03.001.001 | C32: Equipamentos de Carga e Transporte
A33: Subetapa | B33: 03.001.002 | C33: Equipamentos de obra
A34: Subetapa | B34: 03.001.003 | C34: Balancins e Andaimes
A35: UNIDADE CONSTRUTIVA | B35: 2 | C35: GERENCIAMENTO EXECUTIVO
A36: CÉLULA CONSTRUTIVA | B36: 1 | C36: INFRAESTRUTURA
A37: ETAPA | B37: 1.001 | C37: MOVIMENTAÇÃO DE TERRA
A38: Subetapa | B38: 01.001.001 | C38: Corte e aterro
A39: Subetapa | B39: 01.001.002 | C39: Rebaixamento de lençol
A40: Subetapa | B40: 01.001.003 | C40: Escavação e Reaterro de Valas
A41: Subetapa | B41: 01.001.004 | C41: Lastro de estrutura de concreto
A42: Subetapa | B42: 01.001.005 | C42: Movimentação de bota - fora
A43: ETAPA | B43: 1.002 | C43: FUNDAÇÃO PROFUNDA
A44: Subetapa | B44: 01.002.001 | C44: Perfuração
A45: Subetapa | B45: 01.002.002 | C45: Armadura
A46: Subetapa | B46: 01.002.003 | C46: Acessórios
A47: Subetapa | B47: 01.002.004 | C47: Concreto
A48: Subetapa | B48: 01.002.005 | C48: Mão de obra
... A53: Subetapa | B53: 01.003.004 | C53: Mão de obra
A54: CÉLULA CONSTRUTIVA | B54: 2 | C54: SUPRAESTRUTURA
A55: ETAPA | B55: 2.001 | C55: SUPRAESTRUTURA - EMBASAMENTO
A56: Subetapa | B56: 02.001.001 | C56: Forma
A57: Subetapa | B57: 02.001.002 | C57: Armadura
A58: Subetapa | B58: 02.001.003 | C58: Concreto
A59: Subetapa | B59: 02.001.004 | C59: Complementares
A60: Subetapa | B60: 02.001.005 | C60: Mão de obra
A61: ETAPA | B61: 2.002 | C61: SUPRAESTRUTURA - TORRE A
A62: Subetapa | B62: 02.002.001 | C62: Forma
A63: Subetapa | B63: 02.002.002 | C63: Armadura
A64: Subetapa | B64: 02.002.003 | C64: Concreto
A65: Subetapa | B65: 02.002.004 | C65: Complementares
A66: Subetapa | B66: 02.002.005 | C66: Mão de obra
... A72: Subetapa | B72: 02.003.005 | C72: Mão de obra
A73: CÉLULA CONSTRUTIVA | B73: 3 | C73: PAREDES E PAINÉIS
A74: ETAPA | B74: 3.001 | C74: PAREDES E PAINÉIS - EMBASAMENTO
A75: Subetapa | B75: 03.001.001 | C75: Alvenaria de vedação com blocos cerâmicos
A76: Subetapa | B76: 03.001.002 | C76: Alvenaria de vedação com bocos de concreto
A77: Subetapa | B77: 03.001.003 | C77: Serviços complementares para alvenaria de vedação
A78: Subetapa | B78: 03.001.004 | C78: Drywall
A79: Subetapa | B79: 03.001.005 | C79: Mão de obra
A80: ETAPA | B80: 3.002 | C80: PAREDES E PAINÉIS - TORRE A
A81: Subetapa | B81: 03.002.001 | C81: Alvenaria de vedação com blocos cerâmicos
A82: Subetapa | B82: 03.002.002 | C82: Alvenaria de vedação com bocos de concreto
A83: Subetapa | B83: 03.002.003 | C83: Serviços complementares para alvenaria de vedação
A84: Subetapa | B84: 03.002.004 | C84: Drywall
A85: Subetapa | B85: 03.002.005 | C85: Mão de obra
... A91: Subetapa | B91: 03.003.005 | C91: Mão de obra
A92: CÉLULA CONSTRUTIVA | B92: 4 | C92: IMPERMEABILIZAÇÃO E TRATAMENTOS
A93: ETAPA | B93: 4.001 | C93: IMPERMEABILIZAÇÃO E TRATAMENTOS - EMBASAMENTO
A94: Subetapa | B94: 04.001.001 | C94: Regularização e proteção mecânica
A95: Subetapa | B95: 04.001.002 | C95: Impermeabilização de cisternas
A96: Subetapa | B96: 04.001.003 | C96: Impermeabilização de fundação e contenção
A97: Subetapa | B97: 04.001.004 | C97: Impermeabilização de lajes e terraços
A98: Subetapa | B98: 04.001.005 | C98: Impermeabilização de piscinas e espelhos d´água
A99: Subetapa | B99: 04.001.006 | C99: Impermeabilização de banheiro, cozinha e sacada
A100: Subetapa | B100: 04.001.007 | C100: Impermeabilização de esquadrias
A101: Subetapa | B101: 04.001.008 | C101: Impermeabilização de ralos
A102: Subetapa | B102: 04.001.009 | C102: Impermeabilização de floreiras
A103: Subetapa | B103: 04.001.010 | C103: Impermeabilização de reservatórios
A104: Subetapa | B104: 04.001.011 | C104: Mão de obra
... A128: Subetapa | B128: 04.003.011 | C128: Mão de obra
A129: CÉLULA CONSTRUTIVA | B129: 5 | C129: SISTEMAS E INSTALAÇÕES HIDROSSANITÁRIAS E DRENAGEM
A130: ETAPA | B130: 5.001 | C130: SISTEMAS E INSTALAÇÕES HIDROSSANITÁRIAS E DRENAGEM - EMBASAMENTO
A131: Subetapa | B131: 05.001.001 | C131: Instalações de água fria
A132: Subetapa | B132: 05.001.002 | C132: Instalações de água quente
A133: Subetapa | B133: 05.001.003 | C133: Instalações de esgoto e pluviais
A134: Subetapa | B134: 05.001.004 | C134: Cisterna
A135: Subetapa | B135: 05.001.005 | C135: Hidrômetros
A136: Subetapa | B136: 05.001.006 | C136: Reservatórios
A137: Subetapa | B137: 05.001.007 | C137: Sistema de bombas
A138: Subetapa | B138: 05.001.008 | C138: Mão de obra
A139: ETAPA | B139: 5.002 | C139: SISTEMAS E INSTALAÇÕES HIDROSSANITÁRIAS E DRENAGEM - TORRE A
A140: Subetapa | B140: 05.002.001 | C140: Instalações de água fria
...

Sheet IMPERMEABILIZAÇÃO
E1: DADOS
E2: Titulo
E3: Obra
E4: Cliente
E5: Cidade
E6: Endereço
E7: Descrição
E9: QUANTITATIVOS
A10: EAP | B10: Medição | C10: Pavimento | D10: Apoio | E10: Item | F10: Descrição | G10: Unid. | H10: Quantidade | I10: IMPER | J10: AMBIENTE | K10: Total | M10: Descrição | N10: 0 | O10: Tipo x8 | P10: Penthouse x22 | Q10: TOTAL | R10: OBSERVAÇÕES | T10: Descrição | U10: Referência
A12: =_xlfn.XLOOKUP(C12,$T$13:$T$58,$U$13:$U$58,"") -> 0 | B12: =UPPER(IF(F12="","",IF(IF(E12="","",LEN(E12)-LEN(SUBSTITUTE(E12,".","")))=2,(F12),B11))) | C12: =PROPER(IF(OR(F12="",C11="PAVIMENTO"),"",IF(AND(IF(E12="","",LEN(E12)-LEN(SUBSTITUTE(E12,".","")))=2,H12=""),F12,C11))) | D12: =IF(H12="","","SERVIÇO") | E12: 1. | F12: IMPERMEABILIZAÇÃO E TRATAMENTOS | I12: =IF(B12=F12,SUMIFS($H$12:$H$63964,$B$12:$B$63964,B12),"") | K12: =IF(C12=G12,SUMIFS($H$12:$H$63964,$B$12:$B$63964,C12),"") -> 0
A13: =_xlfn.XLOOKUP(C13,$T$13:$T$58,$U$13:$U$58,"") -> 0 | B13: =UPPER(IF(F13="","",IF(IF(E13="","",LEN(E13)-LEN(SUBSTITUTE(E13,".","")))=2,(F13),B12))) -> IMPERMEABILIZAÇAO E TRATAMENTOS | C13: =PROPER(IF(OR(F13="",C12="PAVIMENTO"),"",IF(AND(IF(E13="","",LEN(E13)-LEN(SUBSTITUTE(E13,".","")))=3,H13=""),F13,C12))) | D13: =IF(H13="","","SERVIÇO") | E13: 1.1. | F13: Impermeabilizaçao e tratamentos | I13: =IF(B13=F13,SUMIFS($H$12:$H$63964,$B$12:$B$63964,B13),"") -> 8265.06 | K13: =IF(C13=G13,SUMIFS($H$12:$H$63964,$B$12:$B$63964,C13),"") -> 0 | L13: TRUE | M13: =F13 -> Impermeabilizaçao e tratamentos | Q13: =SUM(Q14:Q63) -> 8265.06 | T13: {=_xlfn.UNIQUE(C12:C1840)}
A14: =_xlfn.XLOOKUP(C14,$T$13:$T$58,$U$13:$U$58,"") -> 0 | B14: =UPPER(IF(F14="","",IF(IF(E14="","",LEN(E14)-LEN(SUBSTITUTE(E14,".","")))=2,(F14),B13))) -> IMPERMEABILIZAÇAO E TRATAMENTOS | C14: =PROPER(IF(OR(F14="",C13="PAVIMENTO"),"",IF(AND(IF(E14="","",LEN(E14)-LEN(SUBSTITUTE(E14,".","")))=3,H14=""),F14,C13))) -> 01_1º Pav. (Térreo) | D14: =IF(H14="","","SERVIÇO") | E14: 1.1.1. | F14: 01_1º PAV. (TÉRREO) | I14: =IF(C14=F14,SUMIFS($H$12:$H$63964,$C$12:$C$63964,C14),"") -> 899.61 | M14: {=_xlfn.UNIQUE(_xlfn._xlws.FILTER($F$12:$F$10253,($D$12:$D$10253="serviço")*($B$12:$B$10253=M13)))} -> PAREDE: Sistema 2.5.3: Membrana de polímero acrílico com cimento e fibras sintéticas | Revestimento bicomponente à base de polímeros acrílicos com adição de cimento e fibras sintéticas (3,0 kg/m²) + Tela de poliéster nos pontos críticos - BANHEIRO | N14: =SUMIFS($H$13:$H$10253,$A$13:$A$10253,N$10,$F$13:$F$10253,$M14) -> 68.14 | O14: =SUMIFS($H$13:$H$10253,$A$13:$A$10253,O$10,$F$13:$F$10253,$M14) -> 0 | P14: =SUMIFS($H$13:$H$10253,$A$13:$A$10253,P$10,$F$13:$F$10253,$M14) -> 0 | Q14: =SUMIFS($H$13:$H$10253,$F$13:$F$10253,$M14) -> 68.14 | R14: PAREDE: Sistema 2.5.3: Membrana de polímero acrílico com cimento e fibras sintéticas | Revestimento bicomponente à base de polímeros acrílicos com adição de cimento e fibras sintéticas (3,0 kg/m²) + Tela de poliéster nos pontos críticos - BANHEIRO | T14: 01_1º Pav. (Térreo)
A15: =_xlfn.XLOOKUP(C15,$T$13:$T$58,$U$13:$U$58,"") -> 0 | B15: =UPPER(IF(F15="","",IF(IF(E15="","",LEN(E15)-LEN(SUBSTITUTE(E15,".","")))=2,(F15),B14))) -> IMPERMEABILIZAÇAO E TRATAMENTOS | C15: =PROPER(IF(OR(F15="",C14="PAVIMENTO"),"",IF(AND(IF(E15="","",LEN(E15)-LEN(SUBSTITUTE(E15,".","")))=3,H15=""),F15,C14))) -> 01_1º Pav. (Térreo) | D15: =IF(H15="","","SERVIÇO") -> SERVIÇO | E15: 1.1.1.1 | F15: PAREDE: Sistema 2.5.3: Membrana de polímero acrílico com cimento e fibras sintéticas | Revestimento bicomponente à base de polímeros acrílicos com adição de cimento e fibras sintéticas (3,0 kg/m²) + Tela de poliéster nos pontos críticos - BANHEIRO | G15: m² | H15: 39.3 | I15: =_xlfn.XLOOKUP($F15,$M$66:$M$115,$N$66:$N$115) -> 2.5.3 | J15: =TRIM(RIGHT(SUBSTITUTE(SUBSTITUTE(F15,CHAR(10)," ")," ",REPT(" ",100)),100)) -> BANHEIRO | K15: =TRIM(LEFT(SUBSTITUTE(SUBSTITUTE(F15,CHAR(10)," ")," ",REPT(" ",100)),100)) -> PAREDE: | M15: PISO: Sistema 2.5.3: Membrana de polímero acrílico com cimento e fibras sintéticas | Revestimento bicomponente à base de polímeros acrílicos com adição de cimento e fibras sintéticas (3,0 kg/m²) + Tela de poliéster nos pontos críticos - BANHEIRO | N15: =SUMIFS($H$13:$H$10253,$A$13:$A$10253,N$10,$F$13:$F$10253,$M15) -> 45.37 | O15: =SUMIFS($H$13:$H$10253,$A$13:$A$10253,O$10,$F$13:$F$10253,$M15) -> 0 | P15: =SUMIFS($H$13:$H$10253,$A$13:$A$10253,P$10,$F$13:$F$10253,$M15) -> 0 | Q15: =SUMIFS($H$13:$H$10253,$F$13:$F$10253,$M15) -> 45.37 | R15: PISO: Sistema 2.5.3: Membrana de polímero acrílico com cimento e fibras sintéticas | Revestimento bicomponente à base de polímeros acrílicos com adição de cimento e fibras sintéticas (3,0 kg/m²) + Tela de poliéster nos pontos críticos - BANHEIRO | T15: 02_Mez. 1º Pav. / G1
A16: =_xlfn.XLOOKUP(C16,$T$13:$T$58,$U$13:$U$58,"") -> 0 | B16: =UPPER(IF(F16="","",IF(IF(E16="","",LEN(E16)-LEN(SUBSTITUTE(E16,".","")))=2,(F16),B15))) -> IMPERMEABILIZAÇAO E TRATAMENTOS | C16: =PROPER(IF(OR(F16="",C15="PAVIMENTO"),"",IF(AND(IF(E16="","",LEN(E16)-LEN(SUBSTITUTE(E16,".","")))=3,H16=""),F16,C15))) -> 01_1º Pav. (Térreo) | D16: =IF(H16="","","SERVIÇO") -> SERVIÇO | E16: 1.1.1.2 | F16: PISO: Sistema 2.5.3: Membrana de polímero acrílico com cimento e fibras sintéticas | Revestimento bicomponente à base de polímeros acrílicos com adição de cimento e fibras sintéticas (3,0 kg/m²) + Tela de poliéster nos pontos críticos - BANHEIRO | G16: m² | H16: 26.46 | I16: =_xlfn.XLOOKUP($F16,$M$66:$M$115,$N$66:$N$115) -> 2.5.3 | J16: =TRIM(RIGHT(SUBSTITUTE(SUBSTITUTE(F16,CHAR(10)," ")," ",REPT(" ",100)),100)) -> BANHEIRO | K16: =TRIM(LEFT(SUBSTITUTE(SUBSTITUTE(F16,CHAR(10)," ")," ",REPT(" ",100)),100)) -> PISO: | M16: PAREDE: Sistema 2.1.4: Argamassa polimérica para impermeabilização - CASA DE BOMBAS | N16: =SUMIFS($H$13:$H$10253,$A$13:$A$10253,N$10,$F$13:$F$10253,$M16) -> 4.11 | O16: =SUMIFS($H$13:$H$10253,$A$13:$A$10253,O$10,$F$13:$F$10253,$M16) -> 0 | P16: =SUMIFS($H$13:$H$10253,$A$13:$A$10253,P$10,$F$13:$F$10253,$M16) -> 0 | Q16: =SUMIFS($H$13:$H$10253,$F$13:$F$10253,$M16) -> 4.11 | R16: PAREDE: Sistema 2.1.4: Argamassa polimérica para impermeabilização - CASA DE BOMBAS | T16: 03_2º Pav. / G2
A17: =_xlfn.XLOOKUP(C17,$T$13:$T$58,$U$13:$U$58,"") -> 0 | B17: =UPPER(IF(F17="","",IF(IF(E17="","",LEN(E17)-LEN(SUBSTITUTE(E17,".","")))=2,(F17),B16))) -> IMPERMEABILIZAÇAO E TRATAMENTOS | C17: =PROPER(IF(OR(F17="",C16="PAVIMENTO"),"",IF(AND(IF(E17="","",LEN(E17)-LEN(SUBSTITUTE(E17,".","")))=3,H17=""),F17,C16))) -> 01_1º Pav. (Térreo) | D17: =IF(H17="","","SERVIÇO") -> SERVIÇO | E17: 1.1.1.3 | F17: PAREDE: Sistema 2.1.4: Argamassa polimérica para impermeabilização - CASA DE BOMBAS | G17: m² | H17: 4.11 | I17: =_xlfn.XLOOKUP($F17,$M$66:$M$115,$N$66:$N$115) -> 2.1.4 | J17: =TRIM(RIGHT(SUBSTITUTE(SUBSTITUTE(F17,CHAR(10)," ")," ",REPT(" ",100)),100)) -> BOMBAS | K17: =TRIM(LEFT(SUBSTITUTE(SUBSTITUTE(F17,CHAR(10)," ")," ",REPT(" ",100)),100)) -> PAREDE: | M17: PISO: Sistema 2.1.4: Argamassa polimérica para impermeabilização | Argamassa impermeabilizante bicomponente à base de aditivos minerais e polímeros (4,0 kg/m²) + Tela de poliéster nos pontos críticos - CASA DE BOMBAS | N17: =SUMIFS($H$13:$H$10253,$A$13:$A$10253,N$10,$F$13:$F$10253,$M17) -> 7.01 | O17: =SUMIFS($H$13:$H$10253,$A$13:$A$10253,O$10,$F$13:$F$10253,$M17) -> 0 | P17: =SUMIFS($H$13:$H$10253,$A$13:$A$10253,P$10,$F$13:$F$10253,$M17) -> 0 | Q17: =SUMIFS($H$13:$H$10253,$F$13:$F$10253,$M17) -> 7.01 | R17: PISO: Sistema 2.1.4: Argamassa polimérica para impermeabilização | Argamassa impermeabilizante bicomponente à base de aditivos minerais e polímeros (4,0 kg/m²) + Tela de poliéster nos pontos críticos - CASA DE BOMBAS | T17: 04_Mez. 2º Pav. / G3
A18: =_xlfn.XLOOKUP(C18,$T$13:$T$58,$U$13:$U$58,"") -> 0 | B18: =UPPER(IF(F18="","",IF(IF(E18="","",LEN(E18)-LEN(SUBSTITUTE(E18,".","")))=2,(F18),B17))) -> IMPERMEABILIZAÇAO E TRATAMENTOS | C18: =PROPER(IF(OR(F18="",C17="PAVIMENTO"),"",IF(AND(IF(E18="","",LEN(E18)-LEN(SUBSTITUTE(E18,".","")))=3,H18=""),F18,C17))) -> 01_1º Pav. (Térreo) | D18: =IF(H18="","","SERVIÇO") -> SERVIÇO | E18: 1.1.1.4 | F18: PISO: Sistema 2.1.4: Argamassa polimérica para impermeabilização | Argamassa impermeabilizante bicomponente à base de aditivos minerais e polímeros (4,0 kg/m²) + Tela de poliéster nos pontos críticos - CASA DE BOMBAS | G18: m² | H18: 7.01 | I18: =_xlfn.XLOOKUP($F18,$M$66:$M$115,$N$66:$N$115) -> 2.1.4 | J18: =TRIM(RIGHT(SUBSTITUTE(SUBSTITUTE(F18,CHAR(10)," ")," ",REPT(" ",100)),100)) -> BOMBAS | K18: =TRIM(LEFT(SUBSTITUTE(SUBSTITUTE(F18,CHAR(10)," ")," ",REPT(" ",100)),100)) -> PISO: | M18: PISO: Sistema 2.5.3: Membrana de polímero acrílico com cimento e fibras sintéticas | Revestimento bicomponente à base de polímeros acrílicos com adição de cimento e fibras sintéticas (3,0 kg/m²) - ESQUADRIA | N18: =SUMIFS($H$13:$H$10253,$A$13:$A$10253,N$10,$F$13:$F$10253,$M18) -> 37.98 | O18: =SUMIFS($H$13:$H$10253,$A$13:$A$10253,O$10,$F$13:$F$10253,$M18) -> 0 | P18: =SUMIFS($H$13:$H$10253,$A$13:$A$10253,P$10,$F$13:$F$10253,$M18) -> 0 | Q18: =SUMIFS($H$13:$H$10253,$F$13:$F$10253,$M18) -> 37.98 | R18: PISO: Sistema 2.5.3: Membrana de polímero acrílico com cimento e fibras sintéticas | Revestimento bicomponente à base de polímeros acrílicos com adição de cimento e fibras sintéticas (3,0 kg/m²) - ESQUADRIA | T18: 05_3º Pav. / G4
A19: =_xlfn.XLOOKUP(C19,$T$13:$T$58,$U$13:$U$58,"") -> 0 | B19: =UPPER(IF(F19="","",IF(IF(E19="","",LEN(E19)-LEN(SUBSTITUTE(E19,".","")))=2,(F19),B18))) -> IMPERMEABILIZAÇAO E TRATAMENTOS | C19: =PROPER(IF(OR(F19="",C18="PAVIMENTO"),"",IF(AND(IF(E19="","",LEN(E19)-LEN(SUBSTITUTE(E19,".","")))=3,H19=""),F19,C18))) -> 01_1º Pav. (Térreo) | D19: =IF(H19="","","SERVIÇO") -> SERVIÇO | E19: 1.1.1.5 | F19: PISO: Sistema 2.5.3: Membrana de polímero acrílico com cimento e fibras sintéticas | Revestimento bicomponente à base de polímeros acrílicos com adição de cimento e fibras sintéticas (3,0 kg/m²) - ESQUADRIA | G19: m² | H19: 0.57 | I19: =_xlfn.XLOOKUP($F19,$M$66:$M$115,$N$66:$N$115) -> 2.5.3 | J19: =TRIM(RIGHT(SUBSTITUTE(SUBSTITUTE(F19,CHAR(10)," ")," ",REPT(" ",100)),100)) -> ESQUADRIA | K19: =TRIM(LEFT(SUBSTITUTE(SUBSTITUTE(F19,CHAR(10)," ")," ",REPT(" ",100)),100)) -> PISO: | M19: PISO: Argamassa polimérica para impermeabilizaçãoArgamassa impermeabilizante bicomponente à base de aditivos minerais e polímeros (4,0 kg/m²) + Tela depoliéster nos pontos críticos - CENTRAL DE GÁS/LIXEIRA | N19: =SUMIFS($H$13:$H$10253,$A$13:$A$10253,N$10,$F$13:$F$10253,$M19) -> 6.52 | O19: =SUMIFS($H$13:$H$10253,$A$13:$A$10253,O$10,$F$13:$F$10253,$M19) -> 0 | P19: =SUMIFS($H$13:$H$10253,$A$13:$A$10253,P$10,$F$13:$F$10253,$M19) -> 0 | Q19: =SUMIFS($H$13:$H$10253,$F$13:$F$10253,$M19) -> 6.52 | R19: PISO: Argamassa polimérica para impermeabilizaçãoArgamassa impermeabilizante bicomponente à base de aditivos minerais e polímeros (4,0 kg/m²) + Tela depoliéster nos pontos críticos - CENTRAL DE GÁS/LIXEIRA | T19: 06_Mez. 3º Pav. / G5
A20: =_xlfn.XLOOKUP(C20,$T$13:$T$58,$U$13:$U$58,"") -> 0 | B20: =UPPER(IF(F20="","",IF(IF(E20="","",LEN(E20)-LEN(SUBSTITUTE(E20,".","")))=2,(F20),B19))) -> IMPERMEABILIZAÇAO E TRATAMENTOS | C20: =PROPER(IF(OR(F20="",C19="PAVIMENTO"),"",IF(AND(IF(E20="","",LEN(E20)-LEN(SUBSTITUTE(E20,".","")))=3,H20=""),F20,C19))) -> 01_1º Pav. (Térreo) | D20: =IF(H20="","","SERVIÇO") -> SERVIÇO | E20: 1.1.1.6 | F20: PISO: Argamassa polimérica para impermeabilizaçãoArgamassa impermeabilizante bicomponente à base de aditivos minerais e polímeros (4,0 kg/m²) + Tela depoliéster nos pontos críticos - CENTRAL DE GÁS/LIXEIRA | G20: m² | H20: 6.52 | I20: =_xlfn.XLOOKUP($F20,$M$66:$M$115,$N$66:$N$115) -> 1 | J20: =TRIM(RIGHT(SUBSTITUTE(SUBSTITUTE(F20,CHAR(10)," ")," ",REPT(" ",100)),100)) -> GÁS/LIXEIRA | K20: =TRIM(LEFT(SUBSTITUTE(SUBSTITUTE(F20,CHAR(10)," ")," ",REPT(" ",100)),100)) -> PISO: | M20: PAREDE: Sistema 4.5.3: Manta asfáltica 4mm aderida com asfalto oxidado modificado + Emulsão asfáltica antiraiz | Primer asfáltico à base d'água (0,4 L/m²) + Asfalto oxidado modificado (2,5 kg/m²) + Manta asfáltica AA | N20: =SUMIFS($H$13:$H$10253,$A$13:$A$10253,N$10,$F$13:$F$10253,$M20) -> 70.68 | O20: =SUMIFS($H$13:$H$10253,$A$13:$A$10253,O$10,$F$13:$F$10253,$M20) -> 0 | P20: =SUMIFS($H$13:$H$10253,$A$13:$A$10253,P$10,$F$13:$F$10253,$M20) -> 0 | Q20: =SUMIFS($H$13:$H$10253,$F$13:$F$10253,$M20) -> 70.68 | R20: PAREDE: Sistema 4.5.3: Manta asfáltica 4mm aderida com asfalto oxidado modificado + Emulsão asfáltica antiraiz | Primer asfáltico à base d'água (0,4 L/m²) + Asfalto oxidado modificado (2,5 kg/m²) + Manta asfáltica AA 4mm Tipo III Classe B + Banho de asfalto oxidado modificado (2,5 kg/m²) + Emulsão asfáltica antiraiz sobre a proteção mecânica (0,8 L/m²) - FLOREIRA | T20: 07_4º Pav. - Lazer / G6
A21: =_xlfn.XLOOKUP(C21,$T$13:$T$58,$U$13:$U$58,"") -> 0 | B21: =UPPER(IF(F21="","",IF(IF(E21="","",LEN(E21)-LEN(SUBSTITUTE(E21,".","")))=2,(F21),B20))) -> IMPERMEABILIZAÇAO E TRATAMENTOS | C21: =PROPER(IF(OR(F21="",C20="PAVIMENTO"),"",IF(AND(IF(E21="","",LEN(E21)-LEN(SUBSTITUTE(E21,".","")))=3,H21=""),F21,C20))) -> 01_1º Pav. (Térreo) | D21: =IF(H21="","","SERVIÇO") -> SERVIÇO | E21: 1.1.1.7 | F21: PAREDE: Sistema 4.5.3: Manta asfáltica 4mm aderida com asfalto oxidado modificado + Emulsão asfáltica antiraiz | Primer asfáltico à base d'água (0,4 L/m²) + Asfalto oxidado modificado (2,5 kg/m²) + Manta asfáltica AA | G21: m² | H21: 29.9 | I21: 4.5.3 | J21: FLOREIRA | K21: =TRIM(LEFT(SUBSTITUTE(SUBSTITUTE(F21,CHAR(10)," ")," ",REPT(" ",100)),100)) -> PAREDE: | M21: PISO: Sistema 4.5.3: Manta asfáltica 4mm aderida com asfalto oxidado modificado + Emulsão asfáltica antiraiz | Primer asfáltico à base d'água (0,4 L/m²) + Asfalto oxidado modificado (2,5 kg/m²) + Manta asfáltica AA | N21: =SUMIFS($H$13:$H$10253,$A$13:$A$10253,N$10,$F$13:$F$10253,$M21) -> 271.44 | O21: =SUMIFS($H$13:$H$10253,$A$13:$A$10253,O$10,$F$13:$F$10253,$M21) -> 0 | P21: =SUMIFS($H$13:$H$10253,$A$13:$A$10253,P$10,$F$13:$F$10253,$M21) -> 0 | Q21: =SUMIFS($H$13:$H$10253,$F$13:$F$10253,$M21) -> 271.44 | R21: PISO: Sistema 4.5.3: Manta asfáltica 4mm aderida com asfalto oxidado modificado + Emulsão asfáltica antiraiz | Primer asfáltico à base d'água (0,4 L/m²) + Asfalto oxidado modificado (2,5 kg/m²) + Manta asfáltica AA 4mm Tipo III Classe B + Banho de asfalto oxidado modificado (2,5 kg/m²) + Emulsão asfáltica antiraiz sobre a proteção mecânica (0,8 L/m²) - FLOREIRA | T21: 08_5º Pav. - Lazer
A22: =_xlfn.XLOOKUP(C22,$T$13:$T$58,$U$13:$U$58,"") -> 0 | B22: =UPPER(IF(F22="","",IF(IF(E22="","",LEN(E22)-LEN(SUBSTITUTE(E22,".","")))=2,(F22),B21))) -> IMPERMEABILIZAÇAO E TRATAMENTOS | C22: =PROPER(IF(OR(F22="",C21="PAVIMENTO"),"",IF(AND(IF(E22="","",LEN(E22)-LEN(SUBSTITUTE(E22,".","")))=3,H22=""),F22,C21))) -> 01_1º Pav. (Térreo) | D22: =IF(H22="","","SERVIÇO") -> SERVIÇO | E22: 1.1.1.8 | F22: PISO: Sistema 4.5.3: Manta asfáltica 4mm aderida com asfalto oxidado modificado + Emulsão asfáltica antiraiz | Primer asfáltico à base d'água (0,4 L/m²) + Asfalto oxidado modificado (2,5 kg/m²) + Manta asfáltica AA | G22: m² | H22: 6.86 | I22: 4.5.3 | J22: FLOREIRA | K22: =TRIM(LEFT(SUBSTITUTE(SUBSTITUTE(F22,CHAR(10)," ")," ",REPT(" ",100)),100)) -> PISO: | L22: PROTEÇÃO MECANICA | M22: PAREDE: Sistema 2.1.4: Argamassa polimérica para impermeabilização | Argamassa impermeabilizante bicomponente à base de aditivos minerais e polímeros (4,0 kg/m²) + Tela de poliéster nos pontos críticos - FOSSO ELEVADOR | N22: =SUMIFS($H$13:$H$10253,$A$13:$A$10253,N$10,$F$13:$F$10253,$M22) -> 68.86 | O22: =SUMIFS($H$13:$H$10253,$A$13:$A$10253,O$10,$F$13:$F$10253,$M22) -> 0 | P22: =SUMIFS($H$13:$H$10253,$A$13:$A$10253,P$10,$F$13:$F$10253,$M22) -> 0 | Q22: =SUMIFS($H$13:$H$10253,$F$13:$F$10253,$M22) -> 68.86 | R22: PAREDE: Sistema 2.1.4: Argamassa polimérica para impermeabilização | Argamassa impermeabilizante bicomponente à base de aditivos minerais e polímeros (4,0 kg/m²) + Tela de poliéster nos pontos críticos - FOSSO ELEVADOR | T22: 09_6º Pav. - Tipo Dif.
A23: =_xlfn.XLOOKUP(C23,$T$13:$T$58,$U$13:$U$58,"") -> 0 | B23: =UPPER(IF(F23="","",IF(IF(E23="","",LEN(E23)-LEN(SUBSTITUTE(E23,".","")))=2,(F23),B22))) -> IMPERMEABILIZAÇAO E TRATAMENTOS | C23: =PROPER(IF(OR(F23="",C22="PAVIMENTO"),"",IF(AND(IF(E23="","",LEN(E23)-LEN(SUBSTITUTE(E23,".","")))=3,H23=""),F23,C22))) -> 01_1º Pav. (Térreo) | D23: =IF(H23="","","SERVIÇO") -> SERVIÇO | E23: 1.1.1.9 | F23: PAREDE: Sistema 2.1.4: Argamassa polimérica para impermeabilização | Argamassa impermeabilizante bicomponente à base de aditivos minerais e polímeros (4,0 kg/m²) + Tela de poliéster nos pontos críticos - FOSSO ELEVADOR | G23: m² | H23: 68.86 | I23: =_xlfn.XLOOKUP($F23,$M$66:$M$115,$N$66:$N$115) -> 2.1.4 | J23: =TRIM(RIGHT(SUBSTITUTE(SUBSTITUTE(F23,CHAR(10)," ")," ",REPT(" ",100)),100)) -> ELEVADOR | K23: =TRIM(LEFT(SUBSTITUTE(SUBSTITUTE(F23,CHAR(10)," ")," ",REPT(" ",100)),100)) -> PAREDE: | M23: PISO: Sistema 2.1.4: Argamassa polimérica para impermeabilização | Argamassa impermeabilizante bicomponente à base de aditivos minerais e polímeros (4,0 kg/m²) + Tela de poliéster nos pontos críticos - FOSSO ELEVADOR | N23: =SUMIFS($H$13:$H$10253,$A$13:$A$10253,N$10,$F$13:$F$10253,$M23) -> 11.17 | O23: =SUMIFS($H$13:$H$10253,$A$13:$A$10253,O$10,$F$13:$F$10253,$M23) -> 0 | P23: =SUMIFS($H$13:$H$10253,$A$13:$A$10253,P$10,$F$13:$F$10253,$M23) -> 0 | Q23: =SUMIFS($H$13:$H$10253,$F$13:$F$10253,$M23) -> 11.17 | R23: PISO: Sistema 2.1.4: Argamassa polimérica para impermeabilização | Argamassa impermeabilizante bicomponente à base de aditivos minerais e polímeros (4,0 kg/m²) + Tela de poliéster nos pontos críticos - FOSSO ELEVADOR | T23: 10_7º Pav. - Tipo | U23: Tipo x8
A24: =_xlfn.XLOOKUP(C24,$T$13:$T$58,$U$13:$U$58,"") -> 0 | B24: =UPPER(IF(F24="","",IF(IF(E24="","",LEN(E24)-LEN(SUBSTITUTE(E24,".","")))=2,(F24),B23))) -> IMPERMEABILIZAÇAO E TRATAMENTOS | C24: =PROPER(IF(OR(F24="",C23="PAVIMENTO"),"",IF(AND(IF(E24="","",LEN(E24)-LEN(SUBSTITUTE(E24,".","")))=3,H24=""),F24,C23))) -> 01_1º Pav. (Térreo) | D24: =IF(H24="","","SERVIÇO") -> SERVIÇO | E24: 1.1.1.10 | F24: PISO: Sistema 2.1.4: Argamassa polimérica para impermeabilização | Argamassa impermeabilizante bicomponente à base de aditivos minerais e polímeros (4,0 kg/m²) + Tela de poliéster nos pontos críticos - FOSSO ELEVADOR | G24: m² | H24: 11.17 | I24: =_xlfn.XLOOKUP($F24,$M$66:$M$115,$N$66:$N$115) -> 2.1.4 | J24: =TRIM(RIGHT(SUBSTITUTE(SUBSTITUTE(F24,CHAR(10)," ")," ",REPT(" ",100)),100)) -> ELEVADOR | K24: =TRIM(LEFT(SUBSTITUTE(SUBSTITUTE(F24,CHAR(10)," ")," ",REPT(" ",100)),100)) -> PISO: | M24: PAREDE: - VIGA BALDRAME | N24: =SUMIFS($H$13:$H$10253,$A$13:$A$10253,N$10,$F$13:$F$10253,$M24) -> 514.29 | O24: =SUMIFS($H$13:$H$10253,$A$13:$A$10253,O$10,$F$13:$F$10253,$M24) -> 0 | P24: =SUMIFS($H$13:$H$10253,$A$13:$A$10253,P$10,$F$13:$F$10253,$M24) -> 0 | Q24: =SUMIFS($H$13:$H$10253,$F$13:$F$10253,$M24) -> 514.29 | R24: PAREDE: - VIGA BALDRAME | T24: 11_8º Pav. - Tipo | U24: Tipo x8
A25: =_xlfn.XLOOKUP(C25,$T$13:$T$58,$U$13:$U$58,"") -> 0 | B25: =UPPER(IF(F25="","",IF(IF(E25="","",LEN(E25)-LEN(SUBSTITUTE(E25,".","")))=2,(F25),B24))) -> IMPERMEABILIZAÇAO E TRATAMENTOS | C25: =PROPER(IF(OR(F25="",C24="PAVIMENTO"),"",IF(AND(IF(E25="","",LEN(E25)-LEN(SUBSTITUTE(E25,".","")))=3,H25=""),F25,C24))) -> 01_1º Pav. (Térreo) | D25: =IF(H25="","","SERVIÇO") -> SERVIÇO | E25: 1.1.1.11 | F25: PAREDE: - VIGA BALDRAME | G25: m² | H25: 514.29 | I25: =_xlfn.XLOOKUP($F25,$M$66:$M$115,$N$66:$N$115) -> 3 | J25: =TRIM(RIGHT(SUBSTITUTE(SUBSTITUTE(F25,CHAR(10)," ")," ",REPT(" ",100)),100)) -> BALDRAME | K25: =TRIM(LEFT(SUBSTITUTE(SUBSTITUTE(F25,CHAR(10)," ")," ",REPT(" ",100)),100)) -> PAREDE: | M25: PISO: - VIGA BALDRAME | N25: =SUMIFS($H$13:$H$10253,$A$13:$A$10253,N$10,$F$13:$F$10253,$M25) -> 184.56 | O25: =SUMIFS($H$13:$H$10253,$A$13:$A$10253,O$10,$F$13:$F$10253,$M25) -> 0 | P25: =SUMIFS($H$13:$H$10253,$A$13:$A$10253,P$10,$F$13:$F$10253,$M25) -> 0 | Q25: =SUMIFS($H$13:$H$10253,$F$13:$F$10253,$M25) -> 184.56 | R25: PISO: - VIGA BALDRAME | T25: 12_9º Pav. - Tipo | U25: Tipo x8
A26: =_xlfn.XLOOKUP(C26,$T$13:$T$58,$U$13:$U$58,"") -> 0 | B26: =UPPER(IF(F26="","",IF(IF(E26="","",LEN(E26)-LEN(SUBSTITUTE(E26,".","")))=2,(F26),B25))) -> IMPERMEABILIZAÇAO E TRATAMENTOS | C26: =PROPER(IF(OR(F26="",C25="PAVIMENTO"),"",IF(AND(IF(E26="","",LEN(E26)-LEN(SUBSTITUTE(E26,".","")))=3,H26=""),F26,C25))) -> 01_1º Pav. (Térreo) | D26: =IF(H26="","","SERVIÇO") -> SERVIÇO | E26: 1.1.1.12 | F26: PISO: - VIGA BALDRAME | G26: m² | H26: 184.56 | I26: =_xlfn.XLOOKUP($F26,$M$66:$M$115,$N$66:$N$115) -> 3 | J26: =TRIM(RIGHT(SUBSTITUTE(SUBSTITUTE(F26,CHAR(10)," ")," ",REPT(" ",100)),100)) -> BALDRAME | K26: =TRIM(LEFT(SUBSTITUTE(SUBSTITUTE(F26,CHAR(10)," ")," ",REPT(" ",100)),100)) -> PISO: | M26: PAREDE: Sistema 2.5.3: Membrana de polímero acrílico com cimento e fibras sintéticas | Revestimento bicomponente à base de polímeros acrílicos com adição de cimento e fibras sintéticas (3,0 kg/m²) - ESQUADRIA | N26: =SUMIFS($H$13:$H$10253,$A$13:$A$10253,N$10,$F$13:$F$10253,$M26) -> 231.68 | O26: =SUMIFS($H$13:$H$10253,$A$13:$A$10253,O$10,$F$13:$F$10253,$M26) -> 273.44 | P26: =SUMIFS($H$13:$H$10253,$A$13:$A$10253,P$10,$F$13:$F$10253,$M26) -> 626.48 | Q26: =SUMIFS($H$13:$H$10253,$F$13:$F$10253,$M26) -> 1131.6 | R26: PAREDE: Sistema 2.5.3: Membrana de polímero acrílico com cimento e fibras sintéticas | Revestimento bicomponente à base de polímeros acrílicos com adição de cimento e fibras sintéticas (3,0 kg/m²) - ESQUADRIA | T26: 13_10º Pav. - Tipo | U26: Tipo x8
A27: =_xlfn.XLOOKUP(C27,$T$13:$T$58,$U$13:$U$58,"") -> 0 | B27: =UPPER(IF(F27="","",IF(IF(E27="","",LEN(E27)-LEN(SUBSTITUTE(E27,".","")))=2,(F27),B26))) -> IMPERMEABILIZAÇAO E TRATAMENTOS | C27: =PROPER(IF(OR(F27="",C26="PAVIMENTO"),"",IF(AND(IF(E27="","",LEN(E27)-LEN(SUBSTITUTE(E27,".","")))=3,H27=""),F27,C26))) -> 02_Mez. 1º Pav. / G1 | D27: =IF(H27="","","SERVIÇO") | E27: 1.1.2. | F27: 02_MEZ. 1º PAV. / G1 | I27: =IF(C27=F27,SUMIFS($H$12:$H$63964,$C$12:$C$63964,C27),"") -> 12.46 | M27: PAREDE: Sistema 2.8.6: Argamassa polimérica para impermeabilização + Membrana de polímero acrílico com cimento e fibras sintéticas | Argamassa impermeabilizante bicomponente à base de aditivos minerais e polímeros (2,0 kg/m²) + - CISTERNA | N27: =SUMIFS($H$13:$H$10253,$A$13:$A$10253,N$10,$F$13:$F$10253,$M27) -> 15.84 | O27: =SUMIFS($H$13:$H$10253,$A$13:$A$10253,O$10,$F$13:$F$10253,$M27) -> 0 | P27: =SUMIFS($H$13:$H$10253,$A$13:$A$10253,P$10,$F$13:$F$10253,$M27) -> 0 | Q27: =SUMIFS($H$13:$H$10253,$F$13:$F$10253,$M27) -> 15.84 | R27: PAREDE: Sistema 2.8.6: Argamassa polimérica para impermeabilização + Membrana de polímero acrílico com cimento e fibras sintéticas | Argamassa impermeabilizante bicomponente à base de aditivos minerais e polímeros (2,0 kg/m²) + Revestimento bicomponente à base de polímeros acrílicos com adição de cimento e fibras sintéticas (4,5 kg/m²) + Tela de poliéster nos pontos críticos - CISTERNA | T27: 14_11º Pav. - Tipo | U27: Tipo x8
A28: =_xlfn.XLOOKUP(C28,$T$13:$T$58,$U$13:$U$58,"") -> 0 | B28: =UPPER(IF(F28="","",IF(IF(E28="","",LEN(E28)-LEN(SUBSTITUTE(E28,".","")))=2,(F28),B27))) -> IMPERMEABILIZAÇAO E TRATAMENTOS | C28: =PROPER(IF(OR(F28="",C27="PAVIMENTO"),"",IF(AND(IF(E28="","",LEN(E28)-LEN(SUBSTITUTE(E28,".","")))=3,H28=""),F28,C27))) -> 02_Mez. 1º Pav. / G1 | D28: =IF(H28="","","SERVIÇO") -> SERVIÇO | E28: 1.1.2.1 | F28: PAREDE: Sistema 2.5.3: Membrana de polímero acrílico com cimento e fibras sintéticas | Revestimento bicomponente à base de polímeros acrílicos com adição de cimento e fibras sintéticas (3,0 kg/m²) - ESQUADRIA | G28: m² | H28: 7.93 | I28: =_xlfn.XLOOKUP($F28,$M$66:$M$115,$N$66:$N$115) -> 2.5.3 | J28: =TRIM(RIGHT(SUBSTITUTE(SUBSTITUTE(F28,CHAR(10)," ")," ",REPT(" ",100)),100)) -> ESQUADRIA | K28: =TRIM(LEFT(SUBSTITUTE(SUBSTITUTE(F28,CHAR(10)," ")," ",REPT(" ",100)),100)) -> PAREDE: | M28: PISO: Sistema 2.8.6: Argamassa polimérica para impermeabilização + Membrana de polímero acrílico com cimento e fibras sintéticas | Argamassa impermeabilizante bicomponente à base de aditivos minerais e polímeros (2,0 kg/m²) + - CISTERNA | N28: =SUMIFS($H$13:$H$10253,$A$13:$A$10253,N$10,$F$13:$F$10253,$M28) -> 4.99 | O28: =SUMIFS($H$13:$H$10253,$A$13:$A$10253,O$10,$F$13:$F$10253,$M28) -> 0 | P28: =SUMIFS($H$13:$H$10253,$A$13:$A$10253,P$10,$F$13:$F$10253,$M28) -> 0 | Q28: =SUMIFS($H$13:$H$10253,$F$13:$F$10253,$M28) -> 4.99 | R28: PISO: Sistema 2.8.6: Argamassa polimérica para impermeabilização + Membrana de polímero acrílico com cimento e fibras sintéticas | Argamassa impermeabilizante bicomponente à base de aditivos minerais e polímeros (2,0 kg/m²) + Revestimento bicomponente à base de polímeros acrílicos com adição de cimento e fibras sintéticas (4,5 kg/m²) + Tela de poliéster nos pontos críticos - CISTERNA | T28: 15_12º Pav. - Tipo | U28: Tipo x8
A29: =_xlfn.XLOOKUP(C29,$T$13:$T$58,$U$13:$U$58,"") -> 0 | B29: =UPPER(IF(F29="","",IF(IF(E29="","",LEN(E29)-LEN(SUBSTITUTE(E29,".","")))=2,(F29),B28))) -> IMPERMEABILIZAÇAO E TRATAMENTOS | C29: =PROPER(IF(OR(F29="",C28="PAVIMENTO"),"",IF(AND(IF(E29="","",LEN(E29)-LEN(SUBSTITUTE(E29,".","")))=3,H29=""),F29,C28))) -> 02_Mez. 1º Pav. / G1 | D29: =IF(H29="","","SERVIÇO") -> SERVIÇO | E29: 1.1.2.2 | F29: PISO: Sistema 2.5.3: Membrana de polímero acrílico com cimento e fibras sintéticas | Revestimento bicomponente à base de polímeros acrílicos com adição de cimento e fibras sintéticas (3,0 kg/m²) - ESQUADRIA | G29: m² | H29: 4.53 | I29: =_xlfn.XLOOKUP($F29,$M$66:$M$115,$N$66:$N$115) -> 2.5.3 | J29: =TRIM(RIGHT(SUBSTITUTE(SUBSTITUTE(F29,CHAR(10)," ")," ",REPT(" ",100)),100)) -> ESQUADRIA | K29: =TRIM(LEFT(SUBSTITUTE(SUBSTITUTE(F29,CHAR(10)," ")," ",REPT(" ",100)),100)) -> PISO: | M29: TETO: Sistema 7.1.2: Argamassa impermeabilizante sem cimento - MK-FEN 30 (F) | Argamassa não cimentícia com agentes incorporadores de ar (4,0 kg/m²) + Tela de poliéster nos pontos críticos - CISTERNA | N29: =SUMIFS($H$13:$H$10253,$A$13:$A$10253,N$10,$F$13:$F$10253,$M29) -> 4.99 | O29: =SUMIFS($H$13:$H$10253,$A$13:$A$10253,O$10,$F$13:$F$10253,$M29) -> 0 | P29: =SUMIFS($H$13:$H$10253,$A$13:$A$10253,P$10,$F$13:$F$10253,$M29) -> 0 | Q29: =SUMIFS($H$13:$H$10253,$F$13:$F$10253,$M29) -> 4.99 | R29: TETO: Sistema 7.1.2: Argamassa impermeabilizante sem cimento - MK-FEN 30 (F) | Argamassa não cimentícia com agentes incorporadores de ar (4,0 kg/m²) + Tela de poliéster nos pontos críticos - CISTERNA | T29: 16_13º Pav. - Tipo | U29: Tipo x8
A30: =_xlfn.XLOOKUP(C30,$T$13:$T$58,$U$13:$U$58,"") -> 0 | B30: =UPPER(IF(F30="","",IF(IF(E30="","",LEN(E30)-LEN(SUBSTITUTE(E30,".","")))=2,(F30),B29))) -> IMPERMEABILIZAÇAO E TRATAMENTOS | C30: =PROPER(IF(OR(F30="",C29="PAVIMENTO"),"",IF(AND(IF(E30="","",LEN(E30)-LEN(SUBSTITUTE(E30,".","")))=3,H30=""),F30,C29))) -> 03_2º Pav. / G2 | D30: =IF(H30="","","SERVIÇO") | E30: 1.1.3. | F30: 03_2º PAV. / G2 | I30: =IF(C30=F30,SUMIFS($H$12:$H$63964,$C$12:$C$63964,C30),"") -> 30.94 | M30: PAREDE: Sistema 4.2.4: Manta asfáltica 4mm aderida com asfalto oxidado modificado | Primer asfáltico à base d'água (0,4 L/m²) + Asfalto oxidado modificado (2,5 kg/m²) + Manta asfáltica AA 4mm Tipo III Classe B - CIRCULAÇÃO | N30: =SUMIFS($H$13:$H$10253,$A$13:$A$10253,N$10,$F$13:$F$10253,$M30) -> 27.38 | O30: =SUMIFS($H$13:$H$10253,$A$13:$A$10253,O$10,$F$13:$F$10253,$M30) -> 0 | P30: =SUMIFS($H$13:$H$10253,$A$13:$A$10253,P$10,$F$13:$F$10253,$M30) -> 0 | Q30: =SUMIFS($H$13:$H$10253,$F$13:$F$10253,$M30) -> 27.38 | R30: PAREDE: Sistema 4.2.4: Manta asfáltica 4mm aderida com asfalto oxidado modificado | Primer asfáltico à base d'água (0,4 L/m²) + Asfalto oxidado modificado (2,5 kg/m²) + Manta asfáltica AA 4mm Tipo III Classe B + Banho de asfalto oxidado modificado (2,5 kg/m²) - CIRCULAÇÃO | T30: 17_14º Pav. - Penthouse | U30: Tipo x8
A31: =_xlfn.XLOOKUP(C31,$T$13:$T$58,$U$13:$U$58,"") -> 0 | B31: =UPPER(IF(F31="","",IF(IF(E31="","",LEN(E31)-LEN(SUBSTITUTE(E31,".","")))=2,(F31),B30))) -> IMPERMEABILIZAÇAO E TRATAMENTOS | C31: =PROPER(IF(OR(F31="",C30="PAVIMENTO"),"",IF(AND(IF(E31="","",LEN(E31)-LEN(SUBSTITUTE(E31,".","")))=3,H31=""),F31,C30))) -> 03_2º Pav. / G2 | D31: =IF(H31="","","SERVIÇO") -> SERVIÇO | E31: 1.1.3.1 | F31: PAREDE: Sistema 2.5.3: Membrana de polímero acrílico com cimento e fibras sintéticas | Revestimento bicomponente à base de polímeros acrílicos com adição de cimento e fibras sintéticas (3,0 kg/m²) - ESQUADRIA | G31: m² | H31: 23.62 | I31: =_xlfn.XLOOKUP($F31,$M$66:$M$115,$N$66:$N$115) -> 2.5.3 | J31: =TRIM(RIGHT(SUBSTITUTE(SUBSTITUTE(F31,CHAR(10)," ")," ",REPT(" ",100)),100)) -> ESQUADRIA | K31: =TRIM(LEFT(SUBSTITUTE(SUBSTITUTE(F31,CHAR(10)," ")," ",REPT(" ",100)),100)) -> PAREDE: | M31: PISO: Sistema 4.2.4: Manta asfáltica 4mm aderida com asfalto oxidado modificado | Primer asfáltico à base d'água (0,4 L/m²) + Asfalto oxidado modificado (2,5 kg/m²) + Manta asfáltica AA 4mm Tipo III Classe B + - CIRCULAÇÃO | N31: =SUMIFS($H$13:$H$10253,$A$13:$A$10253,N$10,$F$13:$F$10253,$M31) -> 142.23 | O31: =SUMIFS($H$13:$H$10253,$A$13:$A$10253,O$10,$F$13:$F$10253,$M31) -> 0 | P31: =SUMIFS($H$13:$H$10253,$A$13:$A$10253,P$10,$F$13:$F$10253,$M31) -> 0 | Q31: =SUMIFS($H$13:$H$10253,$F$13:$F$10253,$M31) -> 142.23 | R31: PISO: Sistema 4.2.4: Manta asfáltica 4mm aderida com asfalto oxidado modificado | Primer asfáltico à base d'água (0,4 L/m²) + Asfalto oxidado modificado (2,5 kg/m²) + Manta asfáltica AA 4mm Tipo III Classe B + Banho de asfalto oxidado modificado (2,5 kg/m²) - CIRCULAÇÃO | T31: 18_15º Pav. - Penthouse | U31: Penthouse x22
A32: =_xlfn.XLOOKUP(C32,$T$13:$T$58,$U$13:$U$58,"") -> 0 | B32: =UPPER(IF(F32="","",IF(IF(E32="","",LEN(E32)-LEN(SUBSTITUTE(E32,".","")))=2,(F32),B31))) -> IMPERMEABILIZAÇAO E TRATAMENTOS | C32: =PROPER(IF(OR(F32="",C31="PAVIMENTO"),"",IF(AND(IF(E32="","",LEN(E32)-LEN(SUBSTITUTE(E32,".","")))=3,H32=""),F32,C31))) -> 03_2º Pav. / G2 | D32: =IF(H32="","","SERVIÇO") -> SERVIÇO | E32: 1.1.3.2 | F32: PISO: Sistema 2.5.3: Membrana de polímero acrílico com cimento e fibras sintéticas | Revestimento bicomponente à base de polímeros acrílicos com adição de cimento e fibras sintéticas (3,0 kg/m²) - ESQUADRIA | G32: m² | H32: 7.32 | I32: =_xlfn.XLOOKUP($F32,$M$66:$M$115,$N$66:$N$115) -> 2.5.3 | J32: =TRIM(RIGHT(SUBSTITUTE(SUBSTITUTE(F32,CHAR(10)," ")," ",REPT(" ",100)),100)) -> ESQUADRIA | K32: =TRIM(LEFT(SUBSTITUTE(SUBSTITUTE(F32,CHAR(10)," ")," ",REPT(" ",100)),100)) -> PISO: | M32: PAREDE: Sistema 4.9.2: Manta asfáltica 4+4mm aderida com asfalto oxidado modificado + Argamassa polimérica para impermeabilização | Primer asfáltico à base d'água (0,4 L/m²) + Asfalto oxidado modificado (2,5 kg/m² - PISCINA | N32: =SUMIFS($H$13:$H$10253,$A$13:$A$10253,N$10,$F$13:$F$10253,$M32) -> 99.14 | O32: =SUMIFS($H$13:$H$10253,$A$13:$A$10253,O$10,$F$13:$F$10253,$M32) -> 0 | P32: =SUMIFS($H$13:$H$10253,$A$13:$A$10253,P$10,$F$13:$F$10253,$M32) -> 0 | Q32: =SUMIFS($H$13:$H$10253,$F$13:$F$10253,$M32) -> 99.14 | R32: PAREDE: Sistema 4.9.2: Manta asfáltica 4+4mm aderida com asfalto oxidado modificado + Argamassa polimérica para impermeabilização | Primer asfáltico à base d'água (0,4 L/m²) + Asfalto oxidado modificado (2,5 kg/m²) + Manta asfáltica AA 3mm Tipo III Classe B + Asfalto oxidado modificado (2,5 kg/m²) + Manta asfáltica AA 4mm Tipo III Classe B + Argamassa polimérica para impermeabilização sobre a proteção mecânica (2,0 kg/m²) - PISCINA | T32: 19_16º Pav. - Penthouse | U32: Penthouse x22
A33: =_xlfn.XLOOKUP(C33,$T$13:$T$58,$U$13:$U$58,"") -> 0 | B33: =UPPER(IF(F33="","",IF(IF(E33="","",LEN(E33)-LEN(SUBSTITUTE(E33,".","")))=2,(F33),B32))) -> IMPERMEABILIZAÇAO E TRATAMENTOS | C33: =PROPER(IF(OR(F33="",C32="PAVIMENTO"),"",IF(AND(IF(E33="","",LEN(E33)-LEN(SUBSTITUTE(E33,".","")))=3,H33=""),F33,C32))) -> 04_Mez. 2º Pav. / G3 | D33: =IF(H33="","","SERVIÇO") | E33: 1.1.4. | F33: 04_MEZ. 2º PAV. / G3 | I33: =IF(C33=F33,SUMIFS($H$12:$H$63964,$C$12:$C$63964,C33),"") -> 25.3 | M33: PISO: Sistema 4.9.2: Manta asfáltica 4+4mm aderida com asfalto oxidado modificado + Argamassa polimérica para impermeabilização | Primer asfáltico à base d'água (0,4 L/m²) + Asfalto oxidado modificado (2,5 kg/m² - PISCINA | N33: =SUMIFS($H$13:$H$10253,$A$13:$A$10253,N$10,$F$13:$F$10253,$M33) -> 141.99 | O33: =SUMIFS($H$13:$H$10253,$A$13:$A$10253,O$10,$F$13:$F$10253,$M33) -> 0 | P33: =SUMIFS($H$13:$H$10253,$A$13:$A$10253,P$10,$F$13:$F$10253,$M33) -> 0 | Q33: =SUMIFS($H$13:$H$10253,$F$13:$F$10253,$M33) -> 141.99 | R33: PISO: Sistema 4.9.2: Manta asfáltica 4+4mm aderida com asfalto oxidado modificado + Argamassa polimérica para impermeabilização | Primer asfáltico à base d'água (0,4 L/m²) + Asfalto oxidado modificado (2,5 kg/m²) + Manta asfáltica AA 3mm Tipo III Classe B + Asfalto oxidado modificado (2,5 kg/m²) + Manta asfáltica AA 4mm Tipo III Classe B + Argamassa polimérica para impermeabilização sobre a proteção mecânica (2,0 kg/m²) - PISCINA | T33: 20_17º Pav. - Penthouse | U33: Penthouse x22
A34: =_xlfn.XLOOKUP(C34,$T$13:$T$58,$U$13:$U$58,"") -> 0 | B34: =UPPER(IF(F34="","",IF(IF(E34="","",LEN(E34)-LEN(SUBSTITUTE(E34,".","")))=2,(F34),B33))) -> IMPERMEABILIZAÇAO E TRATAMENTOS | C34: =PROPER(IF(OR(F34="",C33="PAVIMENTO"),"",IF(AND(IF(E34="","",LEN(E34)-LEN(SUBSTITUTE(E34,".","")))=3,H34=""),F34,C33))) -> 04_Mez. 2º Pav. / G3 | D34: =IF(H34="","","SERVIÇO") -> SERVIÇO | E34: 1.1.4.1 | F34: PAREDE: Sistema 2.5.3: Membrana de polímero acrílico com cimento e fibras sintéticas | Revestimento bicomponente à base de polímeros acrílicos com adição de cimento e fibras sintéticas (3,0 kg/m²) - ESQUADRIA | G34: m² | H34: 25.3 | I34: =_xlfn.XLOOKUP($F34,$M$66:$M$115,$N$66:$N$115) -> 2.5.3 | J34: =TRIM(RIGHT(SUBSTITUTE(SUBSTITUTE(F34,CHAR(10)," ")," ",REPT(" ",100)),100)) -> ESQUADRIA | K34: =TRIM(LEFT(SUBSTITUTE(SUBSTITUTE(F34,CHAR(10)," ")," ",REPT(" ",100)),100)) -> PAREDE: | M34: PAREDE: Sistema 7.1.6: Argamassa impermeabilizante sem cimento - MK-FEN 30 (F) | Argamassa não cimentícia com agentes incorporadores de ar (8,0 kg/m²) + Tela de poliéster nos pontos críticos - SAUNA | N34: =SUMIFS($H$13:$H$10253,$A$13:$A$10253,N$10,$F$13:$F$10253,$M34) -> 42.22 | O34: =SUMIFS($H$13:$H$10253,$A$13:$A$10253,O$10,$F$13:$F$10253,$M34) -> 0 | P34: =SUMIFS($H$13:$H$10253,$A$13:$A$10253,P$10,$F$13:$F$10253,$M34) -> 0 | Q34: =SUMIFS($H$13:$H$10253,$F$13:$F$10253,$M34) -> 42.22 | R34: PAREDE: Sistema 7.1.6: Argamassa impermeabilizante sem cimento - MK-FEN 30 (F) | Argamassa não cimentícia com agentes incorporadores de ar (8,0 kg/m²) + Tela de poliéster nos pontos críticos - SAUNA | T34: 21_18º Pav. - Penthouse | U34: Penthouse x22
A35: =_xlfn.XLOOKUP(C35,$T$13:$T$58,$U$13:$U$58,"") -> 0 | B35: =UPPER(IF(F35="","",IF(IF(E35="","",LEN(E35)-LEN(SUBSTITUTE(E35,".","")))=2,(F35),B34))) -> IMPERMEABILIZAÇAO E TRATAMENTOS | C35: =PROPER(IF(OR(F35="",C34="PAVIMENTO"),"",IF(AND(IF(E35="","",LEN(E35)-LEN(SUBSTITUTE(E35,".","")))=3,H35=""),F35,C34))) -> 05_3º Pav. / G4 | D35: =IF(H35="","","SERVIÇO") | E35: 1.1.5. | F35: 05_3º PAV. / G4 | I35: =IF(C35=F35,SUMIFS($H$12:$H$63964,$C$12:$C$63964,C35),"") -> 51.12 | M35: PISO: Sistema 7.1.6: Argamassa impermeabilizante sem cimento - MK-FEN 30 (F) | Argamassa não cimentícia com agentes incorporadores de ar (8,0 kg/m²) + Tela de poliéster nos pontos críticos - SAUNA | N35: =SUMIFS($H$13:$H$10253,$A$13:$A$10253,N$10,$F$13:$F$10253,$M35) -> 5.81 | O35: =SUMIFS($H$13:$H$10253,$A$13:$A$10253,O$10,$F$13:$F$10253,$M35) -> 0 | P35: =SUMIFS($H$13:$H$10253,$A$13:$A$10253,P$10,$F$13:$F$10253,$M35) -> 0 | Q35: =SUMIFS($H$13:$H$10253,$F$13:$F$10253,$M35) -> 5.81 | R35: PISO: Sistema 7.1.6: Argamassa impermeabilizante sem cimento - MK-FEN 30 (F) | Argamassa não cimentícia com agentes incorporadores de ar (8,0 kg/m²) + Tela de poliéster nos pontos críticos - SAUNA | T35: 22_19º Pav. - Penthouse | U35: Penthouse x22
A36: =_xlfn.XLOOKUP(C36,$T$13:$T$58,$U$13:$U$58,"") -> 0 | B36: =UPPER(IF(F36="","",IF(IF(E36="","",LEN(E36)-LEN(SUBSTITUTE(E36,".","")))=2,(F36),B35))) -> IMPERMEABILIZAÇAO E TRATAMENTOS | C36: =PROPER(IF(OR(F36="",C35="PAVIMENTO"),"",IF(AND(IF(E36="","",LEN(E36)-LEN(SUBSTITUTE(E36,".","")))=3,H36=""),F36,C35))) -> 05_3º Pav. / G4 | D36: =IF(H36="","","SERVIÇO") -> SERVIÇO | E36: 1.1.5.1 | F36: PAREDE: Sistema 2.8.6: Argamassa polimérica para impermeabilização + Membrana de polímero acrílico com cimento e fibras sintéticas | Argamassa impermeabilizante bicomponente à base de aditivos minerais e polímeros (2,0 kg/m²) + - CISTERNA | G36: m² | H36: 15.84 | I36: 2.8.6 | J36: =TRIM(RIGHT(SUBSTITUTE(SUBSTITUTE(F36,CHAR(10)," ")," ",REPT(" ",100)),100)) -> CISTERNA | K36: =TRIM(LEFT(SUBSTITUTE(SUBSTITUTE(F36,CHAR(10)," ")," ",REPT(" ",100)),100)) -> PAREDE: | M36: PAREDE: Sistema 4.2.4: Manta asfáltica 4mm aderida com asfalto oxidado modificado | Primer asfáltico à base d'água (0,4 L/m²) + Asfalto oxidado modificado (2,5 kg/m²) + Manta asfáltica AA 4mm Tipo III Classe - ESPAÇO CROSSFIT | N36: =SUMIFS($H$13:$H$10253,$A$13:$A$10253,N$10,$F$13:$F$10253,$M36) -> 32.09 | O36: =SUMIFS($H$13:$H$10253,$A$13:$A$10253,O$10,$F$13:$F$10253,$M36) -> 0 | P36: =SUMIFS($H$13:$H$10253,$A$13:$A$10253,P$10,$F$13:$F$10253,$M36) -> 0 | Q36: =SUMIFS($H$13:$H$10253,$F$13:$F$10253,$M36) -> 32.09 | R36: PAREDE: Sistema 4.2.4: Manta asfáltica 4mm aderida com asfalto oxidado modificado | Primer asfáltico à base d'água (0,4 L/m²) + Asfalto oxidado modificado (2,5 kg/m²) + Manta asfáltica AA 4mm Tipo III Classe B + Banho de asfalto oxidado modificado (2,5 kg/m²) - ESPAÇO CROSSFIT | T36: 23_20º Pav. - Penthouse | U36: Penthouse x22
A37: =_xlfn.XLOOKUP(C37,$T$13:$T$58,$U$13:$U$58,"") -> 0 | B37: =UPPER(IF(F37="","",IF(IF(E37="","",LEN(E37)-LEN(SUBSTITUTE(E37,".","")))=2,(F37),B36))) -> IMPERMEABILIZAÇAO E TRATAMENTOS | C37: =PROPER(IF(OR(F37="",C36="PAVIMENTO"),"",IF(AND(IF(E37="","",LEN(E37)-LEN(SUBSTITUTE(E37,".","")))=3,H37=""),F37,C36))) -> 05_3º Pav. / G4 | D37: =IF(H37="","","SERVIÇO") -> SERVIÇO | E37: 1.1.5.2 | F37: PISO: Sistema 2.8.6: Argamassa polimérica para impermeabilização + Membrana de polímero acrílico com cimento e fibras sintéticas | Argamassa impermeabilizante bicomponente à base de aditivos minerais e polímeros (2,0 kg/m²) + - CISTERNA | G37: m² | H37: 4.99 | I37: 2.8.6 | J37: =TRIM(RIGHT(SUBSTITUTE(SUBSTITUTE(F37,CHAR(10)," ")," ",REPT(" ",100)),100)) -> CISTERNA | K37: =TRIM(LEFT(SUBSTITUTE(SUBSTITUTE(F37,CHAR(10)," ")," ",REPT(" ",100)),100)) -> PISO: | M37: PISO: Sistema 4.2.4: Manta asfáltica 4mm aderida com asfalto oxidado modificado | Primer asfáltico à base d'água (0,4 L/m²) - ESPAÇO CROSSFIT | N37: =SUMIFS($H$13:$H$10253,$A$13:$A$10253,N$10,$F$13:$F$10253,$M37) -> 87.98 | O37: =SUMIFS($H$13:$H$10253,$A$13:$A$10253,O$10,$F$13:$F$10253,$M37) -> 0 | P37: =SUMIFS($H$13:$H$10253,$A$13:$A$10253,P$10,$F$13:$F$10253,$M37) -> 0 | Q37: =SUMIFS($H$13:$H$10253,$F$13:$F$10253,$M37) -> 87.98 | R37: PISO: Sistema 4.2.4: Manta asfáltica 4mm aderida com asfalto oxidado modificado | Primer asfáltico à base d'água (0,4 L/m²) - ESPAÇO CROSSFIT | T37: 24_21º Pav. - Penthouse | U37: Penthouse x22
A38: =_xlfn.XLOOKUP(C38,$T$13:$T$58,$U$13:$U$58,"") -> 0 | B38: =UPPER(IF(F38="","",IF(IF(E38="","",LEN(E38)-LEN(SUBSTITUTE(E38,".","")))=2,(F38),B37))) -> IMPERMEABILIZAÇAO E TRATAMENTOS | C38: =PROPER(IF(OR(F38="",C37="PAVIMENTO"),"",IF(AND(IF(E38="","",LEN(E38)-LEN(SUBSTITUTE(E38,".","")))=3,H38=""),F38,C37))) -> 05_3º Pav. / G4 | D38: =IF(H38="","","SERVIÇO") -> SERVIÇO | E38: 1.1.5.3 | F38: TETO: Sistema 7.1.2: Argamassa impermeabilizante sem cimento - MK-FEN 30 (F) | Argamassa não cimentícia com agentes incorporadores de ar (4,0 kg/m²) + Tela de poliéster nos pontos críticos - CISTERNA | G38: m² | H38: 4.99 | I38: =_xlfn.XLOOKUP($F38,$M$66:$M$115,$N$66:$N$115) -> 7.1.2 | J38: =TRIM(RIGHT(SUBSTITUTE(SUBSTITUTE(F38,CHAR(10)," ")," ",REPT(" ",100)),100)) -> CISTERNA | K38: =TRIM(LEFT(SUBSTITUTE(SUBSTITUTE(F38,CHAR(10)," ")," ",REPT(" ",100)),100)) -> TETO: | M38: PAREDE: Sistema 2.5.3: Membrana de polímero acrílico com cimento e fibras sintéticas - ÁREA DE SERVIÇO | N38: =SUMIFS($H$13:$H$10253,$A$13:$A$10253,N$10,$F$13:$F$10253,$M38) -> 27.65 | O38: =SUMIFS($H$13:$H$10253,$A$13:$A$10253,O$10,$F$13:$F$10253,$M38) -> 134.64 | P38: =SUMIFS($H$13:$H$10253,$A$13:$A$10253,P$10,$F$13:$F$10253,$M38) -> 219.87 | Q38: =SUMIFS($H$13:$H$10253,$F$13:$F$10253,$M38) -> 382.16 | R38: PAREDE: Sistema 2.5.3: Membrana de polímero acrílico com cimento e fibras sintéticas | Revestimento bicomponente à base de polímeros acrílicos com adição de cimento e fibras sintéticas (3,0 kg/m²)+ Tela de poliéster nos pontos críticos - ÁREA DE SERVIÇO | T38: 25_22º Pav. - Penthouse | U38: Penthouse x22
A39: =_xlfn.XLOOKUP(C39,$T$13:$T$58,$U$13:$U$58,"") -> 0 | B39: =UPPER(IF(F39="","",IF(IF(E39="","",LEN(E39)-LEN(SUBSTITUTE(E39,".","")))=2,(F39),B38))) -> IMPERMEABILIZAÇAO E TRATAMENTOS | C39: =PROPER(IF(OR(F39="",C38="PAVIMENTO"),"",IF(AND(IF(E39="","",LEN(E39)-LEN(SUBSTITUTE(E39,".","")))=3,H39=""),F39,C38))) -> 05_3º Pav. / G4 | D39: =IF(H39="","","SERVIÇO") -> SERVIÇO | E39: 1.1.5.4 | F39: PAREDE: Sistema 2.5.3: Membrana de polímero acrílico com cimento e fibras sintéticas | Revestimento bicomponente à base de polímeros acrílicos com adição de cimento e fibras sintéticas (3,0 kg/m²) - ESQUADRIA | G39: m² | H39: 25.3 | I39: =_xlfn.XLOOKUP($F39,$M$66:$M$115,$N$66:$N$115) -> 2.5.3 | J39: =TRIM(RIGHT(SUBSTITUTE(SUBSTITUTE(F39,CHAR(10)," ")," ",REPT(" ",100)),100)) -> ESQUADRIA | K39: =TRIM(LEFT(SUBSTITUTE(SUBSTITUTE(F39,CHAR(10)," ")," ",REPT(" ",100)),100)) -> PAREDE: | M39: PISO: Sistema 2.5.3: Membrana de polímero acrílico com cimento e fibras sintéticas | Revestimento bicomponente à base de polímeros acrílicos com adição de cimento e fibras sintéticas (3,0 kg/m²)+ Tela de poliéster nos pontos críticos - ÁREA DE SERVIÇO | N39: =SUMIFS($H$13:$H$10253,$A$13:$A$10253,N$10,$F$13:$F$10253,$M39) -> 12.95 | O39: =SUMIFS($H$13:$H$10253,$A$13:$A$10253,O$10,$F$13:$F$10253,$M39) -> 55.44 | P39: =SUMIFS($H$13:$H$10253,$A$13:$A$10253,P$10,$F$13:$F$10253,$M39) -> 95.76 | Q39: =SUMIFS($H$13:$H$10253,$F$13:$F$10253,$M39) -> 164.15 | R39: PISO: Sistema 2.5.3: Membrana de polímero acrílico com cimento e fibras sintéticas | Revestimento bicomponente à base de polímeros acrílicos com adição de cimento e fibras sintéticas (3,0 kg/m²)+ Tela de poliéster nos pontos críticos - ÁREA DE SERVIÇO | T39: 26_23º Pav. - Penthouse | U39: Penthouse x22
A40: =_xlfn.XLOOKUP(C40,$T$13:$T$58,$U$13:$U$58,"") -> 0 | B40: =UPPER(IF(F40="","",IF(IF(E40="","",LEN(E40)-LEN(SUBSTITUTE(E40,".","")))=2,(F40),B39))) -> IMPERMEABILIZAÇAO E TRATAMENTOS | C40: =PROPER(IF(OR(F40="",C39="PAVIMENTO"),"",IF(AND(IF(E40="","",LEN(E40)-LEN(SUBSTITUTE(E40,".","")))=3,H40=""),F40,C39))) -> 06_Mez. 3º Pav. / G5 | D40: =IF(H40="","","SERVIÇO") | E40: 1.1.6. | F40: 06_MEZ. 3º PAV. / G5 | I40: =IF(C40=F40,SUMIFS($H$12:$H$63964,$C$12:$C$63964,C40),"") -> 30.49 | M40: PAREDE: Sistema 7.1.6: Argamassa impermeabilizante sem cimento - MK-FEN 30 (F) | Argamassa não cimentícia com agentes incorporadores de ar (8,0 kg/m²) + Tela de poliéster nos pontos críticos - ÁREA TÉCNICA | N40: =SUMIFS($H$13:$H$10253,$A$13:$A$10253,N$10,$F$13:$F$10253,$M40) -> 6.08 | O40: =SUMIFS($H$13:$H$10253,$A$13:$A$10253,O$10,$F$13:$F$10253,$M40) -> 52.08 | P40: =SUMIFS($H$13:$H$10253,$A$13:$A$10253,P$10,$F$13:$F$10253,$M40) -> 71.79 | Q40: =SUMIFS($H$13:$H$10253,$F$13:$F$10253,$M40) -> 129.95 | R40: PAREDE: Sistema 7.1.6: Argamassa impermeabilizante sem cimento - MK-FEN 30 (F) | Argamassa não cimentícia com agentes incorporadores de ar (8,0 kg/m²) + Tela de poliéster nos pontos críticos - ÁREA TÉCNICA | T40: 27_24º Pav. - Penthouse | U40: Penthouse x22
A41: =_xlfn.XLOOKUP(C41,$T$13:$T$58,$U$13:$U$58,"") -> 0 | B41: =UPPER(IF(F41="","",IF(IF(E41="","",LEN(E41)-LEN(SUBSTITUTE(E41,".","")))=2,(F41),B40))) -> IMPERMEABILIZAÇAO E TRATAMENTOS | C41: =PROPER(IF(OR(F41="",C40="PAVIMENTO"),"",IF(AND(IF(E41="","",LEN(E41)-LEN(SUBSTITUTE(E41,".","")))=3,H41=""),F41,C40))) -> 06_Mez. 3º Pav. / G5 | D41: =IF(H41="","","SERVIÇO") -> SERVIÇO | E41: 1.1.6.1 | F41: PAREDE: Sistema 2.5.3: Membrana de polímero acrílico com cimento e fibras sintéticas | Revestimento bicomponente à base de polímeros acrílicos com adição de cimento e fibras sintéticas (3,0 kg/m²) - ESQUADRIA | G41: m² | H41: 24.05 | I41: =_xlfn.XLOOKUP($F41,$M$66:$M$115,$N$66:$N$115) -> 2.5.3 | J41: =TRIM(RIGHT(SUBSTITUTE(SUBSTITUTE(F41,CHAR(10)," ")," ",REPT(" ",100)),100)) -> ESQUADRIA | K41: =TRIM(LEFT(SUBSTITUTE(SUBSTITUTE(F41,CHAR(10)," ")," ",REPT(" ",100)),100)) -> PAREDE: | M41: PISO: Sistema 7.1.6: Argamassa impermeabilizante sem cimento - MK-FEN 30 (F) | Argamassa não cimentícia com agentes incorporadores de ar (8,0 kg/m²) + Tela de poliéster nos pontos críticos - ÁREA TÉCNICA | N41: =SUMIFS($H$13:$H$10253,$A$13:$A$10253,N$10,$F$13:$F$10253,$M41) -> 11.34 | O41: =SUMIFS($H$13:$H$10253,$A$13:$A$10253,O$10,$F$13:$F$10253,$M41) -> 86.4 | P41: =SUMIFS($H$13:$H$10253,$A$13:$A$10253,P$10,$F$13:$F$10253,$M41) -> 127.59 | Q41: =SUMIFS($H$13:$H$10253,$F$13:$F$10253,$M41) -> 225.33 | R41: PISO: Sistema 7.1.6: Argamassa impermeabilizante sem cimento - MK-FEN 30 (F) | Argamassa não cimentícia com agentes incorporadores de ar (8,0 kg/m²) + Tela de poliéster nos pontos críticos - ÁREA TÉCNICA | T41: 28_25º Pav. Penthouse | U41: Penthouse x22
A42: =_xlfn.XLOOKUP(C42,$T$13:$T$58,$U$13:$U$58,"") -> 0 | B42: =UPPER(IF(F42="","",IF(IF(E42="","",LEN(E42)-LEN(SUBSTITUTE(E42,".","")))=2,(F42),B41))) -> IMPERMEABILIZAÇAO E TRATAMENTOS | C42: =PROPER(IF(OR(F42="",C41="PAVIMENTO"),"",IF(AND(IF(E42="","",LEN(E42)-LEN(SUBSTITUTE(E42,".","")))=3,H42=""),F42,C41))) -> 06_Mez. 3º Pav. / G5 | D42: =IF(H42="","","SERVIÇO") -> SERVIÇO | E42: 1.1.6.2 | F42: PISO: Sistema 2.5.3: Membrana de polímero acrílico com cimento e fibras sintéticas | Revestimento bicomponente à base de polímeros acrílicos com adição de cimento e fibras sintéticas (3,0 kg/m²) - ESQUADRIA | G42: m² | H42: 6.44 | I42: =_xlfn.XLOOKUP($F42,$M$66:$M$115,$N$66:$N$115) -> 2.5.3 | J42: =TRIM(RIGHT(SUBSTITUTE(SUBSTITUTE(F42,CHAR(10)," ")," ",REPT(" ",100)),100)) -> ESQUADRIA | K42: =TRIM(LEFT(SUBSTITUTE(SUBSTITUTE(F42,CHAR(10)," ")," ",REPT(" ",100)),100)) -> PISO: | M42: PAREDE: Sistema 2.5.3: Membrana de polímero acrílico com cimento e fibras sintéticas | Revestimento bicomponente à base de polímeros acrílicos com adição de cimento e fibras sintéticas (3,0 kg/m²) - BANHEIRO | N42: =SUMIFS($H$13:$H$10253,$A$13:$A$10253,N$10,$F$13:$F$10253,$M42) -> 68.29 | O42: =SUMIFS($H$13:$H$10253,$A$13:$A$10253,O$10,$F$13:$F$10253,$M42) -> 216.48 | P42: =SUMIFS($H$13:$H$10253,$A$13:$A$10253,P$10,$F$13:$F$10253,$M42) -> 498.57 | Q42: =SUMIFS($H$13:$H$10253,$F$13:$F$10253,$M42) -> 783.34 | R42: PAREDE: Sistema 2.5.3: Membrana de polímero acrílico com cimento e fibras sintéticas | Revestimento bicomponente à base de polímeros acrílicos com adição de cimento e fibras sintéticas (3,0 kg/m²) - BANHEIRO | T42: 29_26º Pav. - Penthouse | U42: Penthouse x22
A43: =_xlfn.XLOOKUP(C43,$T$13:$T$58,$U$13:$U$58,"") -> 0 | B43: =UPPER(IF(F43="","",IF(IF(E43="","",LEN(E43)-LEN(SUBSTITUTE(E43,".","")))=2,(F43),B42))) -> IMPERMEABILIZAÇAO E TRATAMENTOS | C43: =PROPER(IF(OR(F43="",C42="PAVIMENTO"),"",IF(AND(IF(E43="","",LEN(E43)-LEN(SUBSTITUTE(E43,".","")))=3,H43=""),F43,C42))) -> 07_4º Pav. - Lazer / G6 | D43: =IF(H43="","","SERVIÇO") | E43: 1.1.7. | F43: 07_4º PAV. - LAZER / G6 | I43: =IF(C43=F43,SUMIFS($H$12:$H$63964,$C$12:$C$63964,C43),"") -> 526.56 | M43: PISO: Sistema 2.5.3: Membrana de polímero acrílico com cimento e fibras sintéticas | Revestimento bicomponente à base de polímeros acrílicos com adição de cimento e fibras sintéticas (3,0 kg/m²)+ Tela de poliéster nos pontos críticos - BANHEIRO | N43: =SUMIFS($H$13:$H$10253,$A$13:$A$10253,N$10,$F$13:$F$10253,$M43) -> 49.07 | O43: =SUMIFS($H$13:$H$10253,$A$13:$A$10253,O$10,$F$13:$F$10253,$M43) -> 128.4 | P43: =SUMIFS($H$13:$H$10253,$A$13:$A$10253,P$10,$F$13:$F$10253,$M43) -> 328.53 | Q43: =SUMIFS($H$13:$H$10253,$F$13:$F$10253,$M43) -> 506 | R43: PISO: Sistema 2.5.3: Membrana de polímero acrílico com cimento e fibras sintéticas | Revestimento bicomponente à base de polímeros acrílicos com adição de cimento e fibras sintéticas (3,0 kg/m²)+ Tela de poliéster nos pontos críticos - BANHEIRO | T43: 30_27º Pav. Penthouse | U43: Penthouse x22
A44: =_xlfn.XLOOKUP(C44,$T$13:$T$58,$U$13:$U$58,"") -> 0 | B44: =UPPER(IF(F44="","",IF(IF(E44="","",LEN(E44)-LEN(SUBSTITUTE(E44,".","")))=2,(F44),B43))) -> IMPERMEABILIZAÇAO E TRATAMENTOS | C44: =PROPER(IF(OR(F44="",C43="PAVIMENTO"),"",IF(AND(IF(E44="","",LEN(E44)-LEN(SUBSTITUTE(E44,".","")))=3,H44=""),F44,C43))) -> 07_4º Pav. - Lazer / G6 | D44: =IF(H44="","","SERVIÇO") -> SERVIÇO | E44: 1.1.7.1 | F44: PAREDE: Sistema 2.5.3: Membrana de polímero acrílico com cimento e fibras sintéticas | Revestimento bicomponente à base de polímeros acrílicos com adição de cimento e fibras sintéticas (3,0 kg/m²) + Tela de poliéster nos pontos críticos - BANHEIRO | G44: m² | H44: 16.27 | I44: =_xlfn.XLOOKUP($F44,$M$66:$M$115,$N$66:$N$115) -> 2.5.3 | J44: =TRIM(RIGHT(SUBSTITUTE(SUBSTITUTE(F44,CHAR(10)," ")," ",REPT(" ",100)),100)) -> BANHEIRO | K44: =TRIM(LEFT(SUBSTITUTE(SUBSTITUTE(F44,CHAR(10)," ")," ",REPT(" ",100)),100)) -> PAREDE: | M44: PAREDE: Sistema 2.5.3: Membrana de polímero acrílico com cimento e fibras sintéticas | Revestimento bicomponente à base de polímeros acrílicos com adição de cimento e fibras sintéticas (3,0 kg/m²) - BOX BANHEIRO | N44: =SUMIFS($H$13:$H$10253,$A$13:$A$10253,N$10,$F$13:$F$10253,$M44) -> 56.38 | O44: =SUMIFS($H$13:$H$10253,$A$13:$A$10253,O$10,$F$13:$F$10253,$M44) -> 194.24 | P44: =SUMIFS($H$13:$H$10253,$A$13:$A$10253,P$10,$F$13:$F$10253,$M44) -> 593.24 | Q44: =SUMIFS($H$13:$H$10253,$F$13:$F$10253,$M44) -> 843.86 | R44: PAREDE: Sistema 2.5.3: Membrana de polímero acrílico com cimento e fibras sintéticas | Revestimento bicomponente à base de polímeros acrílicos com adição de cimento e fibras sintéticas (3,0 kg/m²) - BOX BANHEIRO | T44: 31_28º Pav. - Penthouse | U44: Penthouse x22
A45: =_xlfn.XLOOKUP(C45,$T$13:$T$58,$U$13:$U$58,"") -> 0 | B45: =UPPER(IF(F45="","",IF(IF(E45="","",LEN(E45)-LEN(SUBSTITUTE(E45,".","")))=2,(F45),B44))) -> IMPERMEABILIZAÇAO E TRATAMENTOS | C45: =PROPER(IF(OR(F45="",C44="PAVIMENTO"),"",IF(AND(IF(E45="","",LEN(E45)-LEN(SUBSTITUTE(E45,".","")))=3,H45=""),F45,C44))) -> 07_4º Pav. - Lazer / G6 | D45: =IF(H45="","","SERVIÇO") -> SERVIÇO | E45: 1.1.7.2 | F45: PISO: Sistema 2.5.3: Membrana de polímero acrílico com cimento e fibras sintéticas | Revestimento bicomponente à base de polímeros acrílicos com adição de cimento e fibras sintéticas (3,0 kg/m²) + Tela de poliéster nos pontos críticos - BANHEIRO | G45: m² | H45: 10.14 | I45: =_xlfn.XLOOKUP($F45,$M$66:$M$115,$N$66:$N$115) -> 2.5.3 | J45: =TRIM(RIGHT(SUBSTITUTE(SUBSTITUTE(F45,CHAR(10)," ")," ",REPT(" ",100)),100)) -> BANHEIRO | K45: =TRIM(LEFT(SUBSTITUTE(SUBSTITUTE(F45,CHAR(10)," ")," ",REPT(" ",100)),100)) -> PISO: | M45: PISO: Sistema 2.5.3: Membrana de polímero acrílico com cimento e fibras sintéticas | Revestimento bicomponente à base de polímeros acrílicos com adição de cimento e fibras sintéticas (3,0 kg/m²)+ Tela de poliéster nos pontos críticos - BOX BANHEIRO | N45: =SUMIFS($H$13:$H$10253,$A$13:$A$10253,N$10,$F$13:$F$10253,$M45) -> 16.94 | O45: =SUMIFS($H$13:$H$10253,$A$13:$A$10253,O$10,$F$13:$F$10253,$M45) -> 64.8 | P45: =SUMIFS($H$13:$H$10253,$A$13:$A$10253,P$10,$F$13:$F$10253,$M45) -> 200.22 | Q45: =SUMIFS($H$13:$H$10253,$F$13:$F$10253,$M45) -> 281.96 | R45: PISO: Sistema 2.5.3: Membrana de polímero acrílico com cimento e fibras sintéticas | Revestimento bicomponente à base de polímeros acrílicos com adição de cimento e fibras sintéticas (3,0 kg/m²)+ Tela de poliéster nos pontos críticos - BOX BANHEIRO | T45: 32_29º Pav. - Penthouse | U45: Penthouse x22
A46: =_xlfn.XLOOKUP(C46,$T$13:$T$58,$U$13:$U$58,"") -> 0 | B46: =UPPER(IF(F46="","",IF(IF(E46="","",LEN(E46)-LEN(SUBSTITUTE(E46,".","")))=2,(F46),B45))) -> IMPERMEABILIZAÇAO E TRATAMENTOS | C46: =PROPER(IF(OR(F46="",C45="PAVIMENTO"),"",IF(AND(IF(E46="","",LEN(E46)-LEN(SUBSTITUTE(E46,".","")))=3,H46=""),F46,C45))) -> 07_4º Pav. - Lazer / G6 | D46: =IF(H46="","","SERVIÇO") -> SERVIÇO | E46: 1.1.7.3 | F46: PAREDE: Sistema 4.2.4: Manta asfáltica 4mm aderida com asfalto oxidado modificado | Primer asfáltico à base d'água (0,4 L/m²) + Asfalto oxidado modificado (2,5 kg/m²) + Manta asfáltica AA 4mm Tipo III Classe B - CIRCULAÇÃO | G46: m² | H46: 27.38 | I46: 4.2.4 | J46: =TRIM(RIGHT(SUBSTITUTE(SUBSTITUTE(F46,CHAR(10)," ")," ",REPT(" ",100)),100)) -> CIRCULAÇÃO | K46: =TRIM(LEFT(SUBSTITUTE(SUBSTITUTE(F46,CHAR(10)," ")," ",REPT(" ",100)),100)) -> PAREDE: | M46: PISO: Sistema 2.5.3: Membrana de polímero acrílico com cimento e fibras sintéticas | Revestimento bicomponente à base de polímeros acrílicos com adição de cimento e fibras sintéticas (3,0 kg/m²)+ Tela de poliéster nos pontos críticos - ESQUADRIA | N46: =SUMIFS($H$13:$H$10253,$A$13:$A$10253,N$10,$F$13:$F$10253,$M46) -> 54.86 | O46: =SUMIFS($H$13:$H$10253,$A$13:$A$10253,O$10,$F$13:$F$10253,$M46) -> 165.44 | P46: =SUMIFS($H$13:$H$10253,$A$13:$A$10253,P$10,$F$13:$F$10253,$M46) -> 412.04 | Q46: =SUMIFS($H$13:$H$10253,$F$13:$F$10253,$M46) -> 632.34 | R46: PISO: Sistema 2.5.3: Membrana de polímero acrílico com cimento e fibras sintéticas | Revestimento bicomponente à base de polímeros acrílicos com adição de cimento e fibras sintéticas (3,0 kg/m²)+ Tela de poliéster nos pontos críticos - ESQUADRIA | T46: 33_30º Pav. - Penthouse | U46: Penthouse x22
A47: =_xlfn.XLOOKUP(C47,$T$13:$T$58,$U$13:$U$58,"") -> 0 | B47: =UPPER(IF(F47="","",IF(IF(E47="","",LEN(E47)-LEN(SUBSTITUTE(E47,".","")))=2,(F47),B46))) -> IMPERMEABILIZAÇAO E TRATAMENTOS | C47: =PROPER(IF(OR(F47="",C46="PAVIMENTO"),"",IF(AND(IF(E47="","",LEN(E47)-LEN(SUBSTITUTE(E47,".","")))=3,H47=""),F47,C46))) -> 07_4º Pav. - Lazer / G6 | D47: =IF(H47="","","SERVIÇO") -> SERVIÇO | E47: 1.1.7.4 | F47: PISO: Sistema 4.2.4: Manta asfáltica 4mm aderida com asfalto oxidado modificado | Primer asfáltico à base d'água (0,4 L/m²) + Asfalto oxidado modificado (2,5 kg/m²) + Manta asfáltica AA 4mm Tipo III Classe B + - CIRCULAÇÃO | G47: m² | H47: 142.23 | I47: 4.2.4 | J47: =TRIM(RIGHT(SUBSTITUTE(SUBSTITUTE(F47,CHAR(10)," ")," ",REPT(" ",100)),100)) -> CIRCULAÇÃO | K47: =TRIM(LEFT(SUBSTITUTE(SUBSTITUTE(F47,CHAR(10)," ")," ",REPT(" ",100)),100)) -> PISO: | L47: PROTEÇÃO MECANICA | M47: PISO: Sistema 7.1.6: Argamassa impermeabilizante sem cimento - MK-FEN 30 (F) | Argamassa não cimentícia com agentes incorporadores de ar (8,0 kg/m²) + Tela de poliéster nos pontos críticos - MOLDURA FACHADA | N47: =SUMIFS($H$13:$H$10253,$A$13:$A$10253,N$10,$F$13:$F$10253,$M47) -> 125.19 | O47: =SUMIFS($H$13:$H$10253,$A$13:$A$10253,O$10,$F$13:$F$10253,$M47) -> 160.24 | P47: =SUMIFS($H$13:$H$10253,$A$13:$A$10253,P$10,$F$13:$F$10253,$M47) -> 109.12 | Q47: =SUMIFS($H$13:$H$10253,$F$13:$F$10253,$M47) -> 394.55 | R47: PISO: Sistema 7.1.6: Argamassa impermeabilizante sem cimento - MK-FEN 30 (F) | Argamassa não cimentícia com agentes incorporadores de ar (8,0 kg/m²) + Tela de poliéster nos pontos críticos - MOLDURA FACHADA | T47: 34_31º Pav. - Penthouse | U47: Penthouse x22
A48: =_xlfn.XLOOKUP(C48,$T$13:$T$58,$U$13:$U$58,"") -> 0 | B48: =UPPER(IF(F48="","",IF(IF(E48="","",LEN(E48)-LEN(SUBSTITUTE(E48,".","")))=2,(F48),B47))) -> IMPERMEABILIZAÇAO E TRATAMENTOS | C48: =PROPER(IF(OR(F48="",C47="PAVIMENTO"),"",IF(AND(IF(E48="","",LEN(E48)-LEN(SUBSTITUTE(E48,".","")))=3,H48=""),F48,C47))) -> 07_4º Pav. - Lazer / G6 | D48: =IF(H48="","","SERVIÇO") -> SERVIÇO | E48: 1.1.7.5 | F48: PAREDE: Sistema 2.5.3: Membrana de polímero acrílico com cimento e fibras sintéticas | Revestimento bicomponente à base de polímeros acrílicos com adição de cimento e fibras sintéticas (3,0 kg/m²) - ESQUADRIA | G48: m² | H48: 29.2 | I48: =_xlfn.XLOOKUP($F48,$M$66:$M$115,$N$66:$N$115) -> 2.5.3 | J48: =TRIM(RIGHT(SUBSTITUTE(SUBSTITUTE(F48,CHAR(10)," ")," ",REPT(" ",100)),100)) -> ESQUADRIA | K48: =TRIM(LEFT(SUBSTITUTE(SUBSTITUTE(F48,CHAR(10)," ")," ",REPT(" ",100)),100)) -> PAREDE: | M48: PAREDE: Sistema 4.2.4: Manta asfáltica 4mm aderida com asfalto oxidado modificado | Primer asfáltico à base d'água (0,4 L/m²) - SACADA | N48: =SUMIFS($H$13:$H$10253,$A$13:$A$10253,N$10,$F$13:$F$10253,$M48) -> 8.22 | O48: =SUMIFS($H$13:$H$10253,$A$13:$A$10253,O$10,$F$13:$F$10253,$M48) -> 0 | P48: =SUMIFS($H$13:$H$10253,$A$13:$A$10253,P$10,$F$13:$F$10253,$M48) -> 39.79 | Q48: =SUMIFS($H$13:$H$10253,$F$13:$F$10253,$M48) -> 48.01 | R48: PAREDE: Sistema 4.2.4: Manta asfáltica 4mm aderida com asfalto oxidado modificado | Primer asfáltico à base d'água (0,4 L/m²) + Asfalto oxidado modificado (2,5 kg/m²) + Manta asfáltica AA 4mmTipo III Classe B + Banho de asfalto oxidado modificado (2,5 kg/m²) - SACADA | T48: 35_32º Pav. - Penthouse | U48: Penthouse x22
A49: =_xlfn.XLOOKUP(C49,$T$13:$T$58,$U$13:$U$58,"") -> 0 | B49: =UPPER(IF(F49="","",IF(IF(E49="","",LEN(E49)-LEN(SUBSTITUTE(E49,".","")))=2,(F49),B48))) -> IMPERMEABILIZAÇAO E TRATAMENTOS | C49: =PROPER(IF(OR(F49="",C48="PAVIMENTO"),"",IF(AND(IF(E49="","",LEN(E49)-LEN(SUBSTITUTE(E49,".","")))=3,H49=""),F49,C48))) -> 07_4º Pav. - Lazer / G6 | D49: =IF(H49="","","SERVIÇO") -> SERVIÇO | E49: 1.1.7.6 | F49: PISO: Sistema 2.5.3: Membrana de polímero acrílico com cimento e fibras sintéticas | Revestimento bicomponente à base de polímeros acrílicos com adição de cimento e fibras sintéticas (3,0 kg/m²) - ESQUADRIA | G49: m² | H49: 6.44 | I49: =_xlfn.XLOOKUP($F49,$M$66:$M$115,$N$66:$N$115) -> 2.5.3 | J49: =TRIM(RIGHT(SUBSTITUTE(SUBSTITUTE(F49,CHAR(10)," ")," ",REPT(" ",100)),100)) -> ESQUADRIA | K49: =TRIM(LEFT(SUBSTITUTE(SUBSTITUTE(F49,CHAR(10)," ")," ",REPT(" ",100)),100)) -> PISO: | M49: PISO: Sistema 4.2.4: Manta asfáltica 4mm aderida com asfalto oxidado modificado | - SACADA | N49: =SUMIFS($H$13:$H$10253,$A$13:$A$10253,N$10,$F$13:$F$10253,$M49) -> 55.9 | O49: =SUMIFS($H$13:$H$10253,$A$13:$A$10253,O$10,$F$13:$F$10253,$M49) -> 0 | P49: =SUMIFS($H$13:$H$10253,$A$13:$A$10253,P$10,$F$13:$F$10253,$M49) -> 116.69 | Q49: =SUMIFS($H$13:$H$10253,$F$13:$F$10253,$M49) -> 172.59 | R49: PISO: Sistema 4.2.4: Manta asfáltica 4mm aderida com asfalto oxidado modificado | Primer asfáltico à base d'água (0,4 L/m²) + Asfalto oxidado modificado (2,5 kg/m²) + Manta asfáltica AA 4mmTipo III Classe B + Banho de asfalto oxidado modificado (2,5 kg/m²) - SACADA | T49: 36_33º Pav. Penthouse | U49: Penthouse x22
A50: =_xlfn.XLOOKUP(C50,$T$13:$T$58,$U$13:$U$58,"") -> 0 | B50: =UPPER(IF(F50="","",IF(IF(E50="","",LEN(E50)-LEN(SUBSTITUTE(E50,".","")))=2,(F50),B49))) -> IMPERMEABILIZAÇAO E TRATAMENTOS | C50: =PROPER(IF(OR(F50="",C49="PAVIMENTO"),"",IF(AND(IF(E50="","",LEN(E50)-LEN(SUBSTITUTE(E50,".","")))=3,H50=""),F50,C49))) -> 07_4º Pav. - Lazer / G6 | D50: =IF(H50="","","SERVIÇO") -> SERVIÇO | E50: 1.1.7.7 | F50: PAREDE: Sistema 4.5.3: Manta asfáltica 4mm aderida com asfalto oxidado modificado + Emulsão asfáltica antiraiz | Primer asfáltico à base d'água (0,4 L/m²) + Asfalto oxidado modificado (2,5 kg/m²) + Manta asfáltica AA | G50: m² | H50: 4.89 | I50: 4.5.3 | J50: FLOREIRA | K50: =TRIM(LEFT(SUBSTITUTE(SUBSTITUTE(F50,CHAR(10)," ")," ",REPT(" ",100)),100)) -> PAREDE: | M50: PISO: Sistema 7.1.6: Argamassa impermeabilizante sem cimento - MK-FEN 30 (F) | Argamassa não cimentícia com agentes incorporadores de ar (8,0 kg/m²) + Tela de poliéster nos pontos críticos - CALHA E RUFO | N50: =SUMIFS($H$13:$H$10253,$A$13:$A$10253,N$10,$F$13:$F$10253,$M50) -> 27.15 | O50: =SUMIFS($H$13:$H$10253,$A$13:$A$10253,O$10,$F$13:$F$10253,$M50) -> 0 | P50: =SUMIFS($H$13:$H$10253,$A$13:$A$10253,P$10,$F$13:$F$10253,$M50) -> 0 | Q50: =SUMIFS($H$13:$H$10253,$F$13:$F$10253,$M50) -> 27.15 | R50: PISO: Sistema 7.1.6: Argamassa impermeabilizante sem cimento - MK-FEN 30 (F) | Argamassa não cimentícia com agentes incorporadores de ar (8,0 kg/m²) + Tela de poliéster nos pontos críticos - CALHA E RUFO | T50: 37_34º Pav. Penthouse | U50: Penthouse x22
A51: =_xlfn.XLOOKUP(C51,$T$13:$T$58,$U$13:$U$58,"") -> 0 | B51: =UPPER(IF(F51="","",IF(IF(E51="","",LEN(E51)-LEN(SUBSTITUTE(E51,".","")))=2,(F51),B50))) -> IMPERMEABILIZAÇAO E TRATAMENTOS | C51: =PROPER(IF(OR(F51="",C50="PAVIMENTO"),"",IF(AND(IF(E51="","",LEN(E51)-LEN(SUBSTITUTE(E51,".","")))=3,H51=""),F51,C50))) -> 07_4º Pav. - Lazer / G6 | D51: =IF(H51="","","SERVIÇO") -> SERVIÇO | E51: 1.1.7.8 | F51: PISO: Sistema 4.5.3: Manta asfáltica 4mm aderida com asfalto oxidado modificado + Emulsão asfáltica antiraiz | Primer asfáltico à base d'água (0,4 L/m²) + Asfalto oxidado modificado (2,5 kg/m²) + Manta asfáltica AA | G51: m² | H51: 0.85 | I51: 4.5.3 | J51: FLOREIRA | K51: =TRIM(LEFT(SUBSTITUTE(SUBSTITUTE(F51,CHAR(10)," ")," ",REPT(" ",100)),100)) -> PISO: | L51: PROTEÇÃO MECANICA | M51: PAREDE: Sistema 4.2.4: Manta asfáltica 4mm aderida com asfalto oxidado modificado | Primer asfáltico à base d'água (0,4 L/m²) + Asfalto oxidado modificado (2,5 kg/m² - PISCINA | N51: =SUMIFS($H$13:$H$10253,$A$13:$A$10253,N$10,$F$13:$F$10253,$M51) -> 15.24 | O51: =SUMIFS($H$13:$H$10253,$A$13:$A$10253,O$10,$F$13:$F$10253,$M51) -> 0 | P51: =SUMIFS($H$13:$H$10253,$A$13:$A$10253,P$10,$F$13:$F$10253,$M51) -> 0 | Q51: =SUMIFS($H$13:$H$10253,$F$13:$F$10253,$M51) -> 15.24 | R51: PAREDE: Sistema 4.2.4: Manta asfáltica 4mm aderida com asfalto oxidado modificado | Primer asfáltico à base d'água (0,4 L/m²) + Asfalto oxidado modificado (2,5 kg/m²) + Manta asfáltica AA 4mmTipo III Classe B + Banho de asfalto oxidado modificado (2,5 kg/m²) - PISCINA | T51: 38_35º Pav. Penthouse | U51: Penthouse x22
A52: =_xlfn.XLOOKUP(C52,$T$13:$T$58,$U$13:$U$58,"") -> 0 | B52: =UPPER(IF(F52="","",IF(IF(E52="","",LEN(E52)-LEN(SUBSTITUTE(E52,".","")))=2,(F52),B51))) -> IMPERMEABILIZAÇAO E TRATAMENTOS | C52: =PROPER(IF(OR(F52="",C51="PAVIMENTO"),"",IF(AND(IF(E52="","",LEN(E52)-LEN(SUBSTITUTE(E52,".","")))=3,H52=""),F52,C51))) -> 07_4º Pav. - Lazer / G6 | D52: =IF(H52="","","SERVIÇO") -> SERVIÇO | E52: 1.1.7.9 | F52: PAREDE: Sistema 4.9.2: Manta asfáltica 4+4mm aderida com asfalto oxidado modificado + Argamassa polimérica para impermeabilização | Primer asfáltico à base d'água (0,4 L/m²) + Asfalto oxidado modificado (2,5 kg/m² - PISCINA | G52: m² | H52: 99.14 | I52: 4.9.2 | J52: =TRIM(RIGHT(SUBSTITUTE(SUBSTITUTE(F52,CHAR(10)," ")," ",REPT(" ",100)),100)) -> PISCINA | K52: =TRIM(LEFT(SUBSTITUTE(SUBSTITUTE(F52,CHAR(10)," ")," ",REPT(" ",100)),100)) -> PAREDE: | M52: PISO: Sistema 4.2.4: Manta asfáltica 4mm aderida com asfalto oxidado modificado | Primer asfáltico à base d'água (0,4 L/m²) + Asfalto oxidado modificado (2,5 kg/m² - PISCINA | N52: =SUMIFS($H$13:$H$10253,$A$13:$A$10253,N$10,$F$13:$F$10253,$M52) -> 9.89 | O52: =SUMIFS($H$13:$H$10253,$A$13:$A$10253,O$10,$F$13:$F$10253,$M52) -> 0 | P52: =SUMIFS($H$13:$H$10253,$A$13:$A$10253,P$10,$F$13:$F$10253,$M52) -> 0 | Q52: =SUMIFS($H$13:$H$10253,$F$13:$F$10253,$M52) -> 9.89 | R52: PISO: Sistema 4.2.4: Manta asfáltica 4mm aderida com asfalto oxidado modificado | Primer asfáltico à base d'água (0,4 L/m²) + Asfalto oxidado modificado (2,5 kg/m²) + Manta asfáltica AA 4mmTipo III Classe B + Banho de asfalto oxidado modificado (2,5 kg/m²) - PISCINA | T52: 39_ 36º Pav. - Penthouse Dif. | U52: Penthouse x22
A53: =_xlfn.XLOOKUP(C53,$T$13:$T$58,$U$13:$U$58,"") -> 0 | B53: =UPPER(IF(F53="","",IF(IF(E53="","",LEN(E53)-LEN(SUBSTITUTE(E53,".","")))=2,(F53),B52))) -> IMPERMEABILIZAÇAO E TRATAMENTOS | C53: =PROPER(IF(OR(F53="",C52="PAVIMENTO"),"",IF(AND(IF(E53="","",LEN(E53)-LEN(SUBSTITUTE(E53,".","")))=3,H53=""),F53,C52))) -> 07_4º Pav. - Lazer / G6 | D53: =IF(H53="","","SERVIÇO") -> SERVIÇO | E53: 1.1.7.10 | F53: PISO: Sistema 4.9.2: Manta asfáltica 4+4mm aderida com asfalto oxidado modificado + Argamassa polimérica para impermeabilização | Primer asfáltico à base d'água (0,4 L/m²) + Asfalto oxidado modificado (2,5 kg/m² - PISCINA | G53: m² | H53: 141.99 | I53: 4.9.2 | J53: =TRIM(RIGHT(SUBSTITUTE(SUBSTITUTE(F53,CHAR(10)," ")," ",REPT(" ",100)),100)) -> PISCINA | K53: =TRIM(LEFT(SUBSTITUTE(SUBSTITUTE(F53,CHAR(10)," ")," ",REPT(" ",100)),100)) -> PISO: | L53: PROTEÇÃO MECANICA | M53: PAREDE: Sistema 4.2.4: Manta asfáltica 4mm aderida com asfalto oxidado modificado | Primer asfáltico à base d'água (0,4 L/m²) + Asfalto oxidado modificado (2,5 kg/m² - TERRAÇO | N53: =SUMIFS($H$13:$H$10253,$A$13:$A$10253,N$10,$F$13:$F$10253,$M53) -> 9 | O53: =SUMIFS($H$13:$H$10253,$A$13:$A$10253,O$10,$F$13:$F$10253,$M53) -> 0 | P53: =SUMIFS($H$13:$H$10253,$A$13:$A$10253,P$10,$F$13:$F$10253,$M53) -> 0 | Q53: =SUMIFS($H$13:$H$10253,$F$13:$F$10253,$M53) -> 9 | R53: PAREDE: Sistema 4.2.4: Manta asfáltica 4mm aderida com asfalto oxidado modificado | Primer asfáltico à base d'água (0,4 L/m²) + Asfalto oxidado modificado (2,5 kg/m²) + Manta asfáltica AA 4mmTipo III Classe B + Banho de asfalto oxidado modificado (2,5 kg/m²) - TERRAÇO | T53: 40_37º - Duplex Inferior
A54: =_xlfn.XLOOKUP(C54,$T$13:$T$58,$U$13:$U$58,"") -> 0 | B54: =UPPER(IF(F54="","",IF(IF(E54="","",LEN(E54)-LEN(SUBSTITUTE(E54,".","")))=2,(F54),B53))) -> IMPERMEABILIZAÇAO E TRATAMENTOS | C54: =PROPER(IF(OR(F54="",C53="PAVIMENTO"),"",IF(AND(IF(E54="","",LEN(E54)-LEN(SUBSTITUTE(E54,".","")))=3,H54=""),F54,C53))) -> 07_4º Pav. - Lazer / G6 | D54: =IF(H54="","","SERVIÇO") -> SERVIÇO | E54: 1.1.7.11 | F54: PAREDE: Sistema 7.1.6: Argamassa impermeabilizante sem cimento - MK-FEN 30 (F) | Argamassa não cimentícia com agentes incorporadores de ar (8,0 kg/m²) + Tela de poliéster nos pontos críticos - SAUNA | G54: m² | H54: 42.22 | I54: =_xlfn.XLOOKUP($F54,$M$66:$M$115,$N$66:$N$115) -> 7.1.6 | J54: =TRIM(RIGHT(SUBSTITUTE(SUBSTITUTE(F54,CHAR(10)," ")," ",REPT(" ",100)),100)) -> SAUNA | K54: =TRIM(LEFT(SUBSTITUTE(SUBSTITUTE(F54,CHAR(10)," ")," ",REPT(" ",100)),100)) -> PAREDE: | M54: PISO: Sistema 4.2.4: Manta asfáltica 4mm aderida com asfalto oxidado modificado | Primer asfáltico à base d'água (0,4 L/m²) + Asfalto oxidado modificado (2,5 kg/m² - TERRAÇO | N54: =SUMIFS($H$13:$H$10253,$A$13:$A$10253,N$10,$F$13:$F$10253,$M54) -> 39.1 | O54: =SUMIFS($H$13:$H$10253,$A$13:$A$10253,O$10,$F$13:$F$10253,$M54) -> 0 | P54: =SUMIFS($H$13:$H$10253,$A$13:$A$10253,P$10,$F$13:$F$10253,$M54) -> 0 | Q54: =SUMIFS($H$13:$H$10253,$F$13:$F$10253,$M54) -> 39.1 | R54: PISO: Sistema 4.2.4: Manta asfáltica 4mm aderida com asfalto oxidado modificado | Primer asfáltico à base d'água (0,4 L/m²) + Asfalto oxidado modificado (2,5 kg/m²) + Manta asfáltica AA 4mmTipo III Classe B + Banho de asfalto oxidado modificado (2,5 kg/m²) - TERRAÇO | T54: 41_38º Pav. - Duplex Superior
A55: =_xlfn.XLOOKUP(C55,$T$13:$T$58,$U$13:$U$58,"") -> 0 | B55: =UPPER(IF(F55="","",IF(IF(E55="","",LEN(E55)-LEN(SUBSTITUTE(E55,".","")))=2,(F55),B54))) -> IMPERMEABILIZAÇAO E TRATAMENTOS | C55: =PROPER(IF(OR(F55="",C54="PAVIMENTO"),"",IF(AND(IF(E55="","",LEN(E55)-LEN(SUBSTITUTE(E55,".","")))=3,H55=""),F55,C54))) -> 07_4º Pav. - Lazer / G6 | D55: =IF(H55="","","SERVIÇO") -> SERVIÇO | E55: 1.1.7.12 | F55: PISO: Sistema 7.1.6: Argamassa impermeabilizante sem cimento - MK-FEN 30 (F) | Argamassa não cimentícia com agentes incorporadores de ar (8,0 kg/m²) + Tela de poliéster nos pontos críticos - SAUNA | G55: m² | H55: 5.81 | I55: =_xlfn.XLOOKUP($F55,$M$66:$M$115,$N$66:$N$115) -> 7.1.6 | J55: =TRIM(RIGHT(SUBSTITUTE(SUBSTITUTE(F55,CHAR(10)," ")," ",REPT(" ",100)),100)) -> SAUNA | K55: =TRIM(LEFT(SUBSTITUTE(SUBSTITUTE(F55,CHAR(10)," ")," ",REPT(" ",100)),100)) -> PISO: | M55: PAREDE: Sistema 2.5.3: Membrana de polímero acrílico com cimento e fibras sintéticas | Revestimento bicomponente à base de polímeros acrílicos com adição de cimento e fibras sintéticas (3,0 kg/m²) - CASA DE MÁQUINAS | N55: =SUMIFS($H$13:$H$10253,$A$13:$A$10253,N$10,$F$13:$F$10253,$M55) -> 43.63 | O55: =SUMIFS($H$13:$H$10253,$A$13:$A$10253,O$10,$F$13:$F$10253,$M55) -> 0 | P55: =SUMIFS($H$13:$H$10253,$A$13:$A$10253,P$10,$F$13:$F$10253,$M55) -> 0 | Q55: =SUMIFS($H$13:$H$10253,$F$13:$F$10253,$M55) -> 43.63 | R55: PAREDE: Sistema 2.5.3: Membrana de polímero acrílico com cimento e fibras sintéticas | Revestimento bicomponente à base de polímeros acrílicos com adição de cimento e fibras sintéticas (3,0 kg/m²) - CASA DE MÁQUINAS | T55: 42_Telhado/Casa De Máquinas
A56: =_xlfn.XLOOKUP(C56,$T$13:$T$58,$U$13:$U$58,"") -> 0 | B56: =UPPER(IF(F56="","",IF(IF(E56="","",LEN(E56)-LEN(SUBSTITUTE(E56,".","")))=2,(F56),B55))) -> IMPERMEABILIZAÇAO E TRATAMENTOS | C56: =PROPER(IF(OR(F56="",C55="PAVIMENTO"),"",IF(AND(IF(E56="","",LEN(E56)-LEN(SUBSTITUTE(E56,".","")))=3,H56=""),F56,C55))) -> 08_5º Pav. - Lazer | D56: =IF(H56="","","SERVIÇO") | E56: 1.1.8. | F56: 08_5º PAV. - LAZER | I56: =IF(C56=F56,SUMIFS($H$12:$H$63964,$C$12:$C$63964,C56),"") -> 463.87 | M56: PISO: Sistema 2.5.3: Membrana de polímero acrílico com cimento e fibras sintéticas | Revestimento bicomponente à base de polímeros acrílicos com adição de cimento e fibras sintéticas (3,0 kg/m²) - CASA DE MÁQUINAS | N56: =SUMIFS($H$13:$H$10253,$A$13:$A$10253,N$10,$F$13:$F$10253,$M56) -> 5.22 | O56: =SUMIFS($H$13:$H$10253,$A$13:$A$10253,O$10,$F$13:$F$10253,$M56) -> 0 | P56: =SUMIFS($H$13:$H$10253,$A$13:$A$10253,P$10,$F$13:$F$10253,$M56) -> 0 | Q56: =SUMIFS($H$13:$H$10253,$F$13:$F$10253,$M56) -> 5.22 | R56: PISO: Sistema 2.5.3: Membrana de polímero acrílico com cimento e fibras sintéticas | Revestimento bicomponente à base de polímeros acrílicos com adição de cimento e fibras sintéticas (3,0 kg/m²) - CASA DE MÁQUINAS | T56: 43_Casa De Máquinas
A57: =_xlfn.XLOOKUP(C57,$T$13:$T$58,$U$13:$U$58,"") -> 0 | B57: =UPPER(IF(F57="","",IF(IF(E57="","",LEN(E57)-LEN(SUBSTITUTE(E57,".","")))=2,(F57),B56))) -> IMPERMEABILIZAÇAO E TRATAMENTOS | C57: =PROPER(IF(OR(F57="",C56="PAVIMENTO"),"",IF(AND(IF(E57="","",LEN(E57)-LEN(SUBSTITUTE(E57,".","")))=3,H57=""),F57,C56))) -> 08_5º Pav. - Lazer | D57: =IF(H57="","","SERVIÇO") -> SERVIÇO | E57: 1.1.8.1 | F57: PAREDE: Sistema 2.5.3: Membrana de polímero acrílico com cimento e fibras sintéticas | Revestimento bicomponente à base de polímeros acrílicos com adição de cimento e fibras sintéticas (3,0 kg/m²) + Tela de poliéster nos pontos críticos - BANHEIRO | G57: m² | H57: 12.57 | I57: =_xlfn.XLOOKUP($F57,$M$66:$M$115,$N$66:$N$115) -> 2.5.3 | J57: =TRIM(RIGHT(SUBSTITUTE(SUBSTITUTE(F57,CHAR(10)," ")," ",REPT(" ",100)),100)) -> BANHEIRO | K57: =TRIM(LEFT(SUBSTITUTE(SUBSTITUTE(F57,CHAR(10)," ")," ",REPT(" ",100)),100)) -> PAREDE: | M57: PAREDE: Sistema 4.2.4: Manta asfáltica 4mm aderida com asfalto oxidado modificado | Primer asfáltico à base d'água (0,4 L/m²) + Asfalto oxidado modificado (2,5 kg/m²) + Manta asfáltica AA 4mm - COBERTURA | N57: =SUMIFS($H$13:$H$10253,$A$13:$A$10253,N$10,$F$13:$F$10253,$M57) -> 29.31 | O57: =SUMIFS($H$13:$H$10253,$A$13:$A$10253,O$10,$F$13:$F$10253,$M57) -> 0 | P57: =SUMIFS($H$13:$H$10253,$A$13:$A$10253,P$10,$F$13:$F$10253,$M57) -> 0 | Q57: =SUMIFS($H$13:$H$10253,$F$13:$F$10253,$M57) -> 29.31 | R57: PAREDE: Sistema 4.2.4: Manta asfáltica 4mm aderida com asfalto oxidado modificado | Primer asfáltico à base d'água (0,4 L/m²) + Asfalto oxidado modificado (2,5 kg/m²) + Manta asfáltica AA 4mm - COBERTURA | T57: 45_Reservatório
A58: =_xlfn.XLOOKUP(C58,$T$13:$T$58,$U$13:$U$58,"") -> 0 | B58: =UPPER(IF(F58="","",IF(IF(E58="","",LEN(E58)-LEN(SUBSTITUTE(E58,".","")))=2,(F58),B57))) -> IMPERMEABILIZAÇAO E TRATAMENTOS | C58: =PROPER(IF(OR(F58="",C57="PAVIMENTO"),"",IF(AND(IF(E58="","",LEN(E58)-LEN(SUBSTITUTE(E58,".","")))=3,H58=""),F58,C57))) -> 08_5º Pav. - Lazer | D58: =IF(H58="","","SERVIÇO") -> SERVIÇO | E58: 1.1.8.2 | F58: PISO: Sistema 2.5.3: Membrana de polímero acrílico com cimento e fibras sintéticas | Revestimento bicomponente à base de polímeros acrílicos com adição de cimento e fibras sintéticas (3,0 kg/m²) + Tela de poliéster nos pontos críticos - BANHEIRO | G58: m² | H58: 8.77 | I58: =_xlfn.XLOOKUP($F58,$M$66:$M$115,$N$66:$N$115) -> 2.5.3 | J58: =TRIM(RIGHT(SUBSTITUTE(SUBSTITUTE(F58,CHAR(10)," ")," ",REPT(" ",100)),100)) -> BANHEIRO | K58: =TRIM(LEFT(SUBSTITUTE(SUBSTITUTE(F58,CHAR(10)," ")," ",REPT(" ",100)),100)) -> PISO: | M58: PISO: Sistema 4.2.4: Manta asfáltica 4mm aderida com asfalto oxidado modificado | Primer asfáltico à base d'água (0,4 L/m²) + Asfalto oxidado modificado (2,5 kg/m²) + Manta asfáltica AA 4mm - COBERTURA | N58: =SUMIFS($H$13:$H$10253,$A$13:$A$10253,N$10,$F$13:$F$10253,$M58) -> 144.24 | O58: =SUMIFS($H$13:$H$10253,$A$13:$A$10253,O$10,$F$13:$F$10253,$M58) -> 0 | P58: =SUMIFS($H$13:$H$10253,$A$13:$A$10253,P$10,$F$13:$F$10253,$M58) -> 0 | Q58: =SUMIFS($H$13:$H$10253,$F$13:$F$10253,$M58) -> 144.24 | R58: PISO: Sistema 4.2.4: Manta asfáltica 4mm aderida com asfalto oxidado modificado | Primer asfáltico à base d'água (0,4 L/m²) + Asfalto oxidado modificado (2,5 kg/m²) + Manta asfáltica AA 4mm - COBERTURA | T58: 46_Teto Reservatório
A59: =_xlfn.XLOOKUP(C59,$T$13:$T$58,$U$13:$U$58,"") -> 0 | B59: =UPPER(IF(F59="","",IF(IF(E59="","",LEN(E59)-LEN(SUBSTITUTE(E59,".","")))=2,(F59),B58))) -> IMPERMEABILIZAÇAO E TRATAMENTOS | C59: =PROPER(IF(OR(F59="",C58="PAVIMENTO"),"",IF(AND(IF(E59="","",LEN(E59)-LEN(SUBSTITUTE(E59,".","")))=3,H59=""),F59,C58))) -> 08_5º Pav. - Lazer | D59: =IF(H59="","","SERVIÇO") -> SERVIÇO | E59: 1.1.8.3 | F59: PAREDE: Sistema 4.2.4: Manta asfáltica 4mm aderida com asfalto oxidado modificado | Primer asfáltico à base d'água (0,4 L/m²) + Asfalto oxidado modificado (2,5 kg/m²) + Manta asfáltica AA 4mm Tipo III Classe - ESPAÇO CROSSFIT | G59: m² | H59: 32.09 | I59: 4.2.4 | J59: =TRIM(RIGHT(SUBSTITUTE(SUBSTITUTE(F59,CHAR(10)," ")," ",REPT(" ",100)),100)) -> CROSSFIT | K59: =TRIM(LEFT(SUBSTITUTE(SUBSTITUTE(F59,CHAR(10)," ")," ",REPT(" ",100)),100)) -> PAREDE: | M59: PISO: Sistema 7.1.6: Argamassa impermeabilizante sem cimento - MK-FEN 30 (F) | Argamassa não cimentícia com agentes incorporadores de ar (8,0 kg/m²) + Tela de poliéster nos pontos críticos - MOLDURA DA FACHADA | N59: =SUMIFS($H$13:$H$10253,$A$13:$A$10253,N$10,$F$13:$F$10253,$M59) -> 9.43 | O59: =SUMIFS($H$13:$H$10253,$A$13:$A$10253,O$10,$F$13:$F$10253,$M59) -> 0 | P59: =SUMIFS($H$13:$H$10253,$A$13:$A$10253,P$10,$F$13:$F$10253,$M59) -> 0 | Q59: =SUMIFS($H$13:$H$10253,$F$13:$F$10253,$M59) -> 9.43 | R59: PISO: Sistema 7.1.6: Argamassa impermeabilizante sem cimento - MK-FEN 30 (F) | Argamassa não cimentícia com agentes incorporadores de ar (8,0 kg/m²) + Tela de poliéster nos pontos críticos - MOLDURA DA FACHADA | T59: 0
A60: =_xlfn.XLOOKUP(C60,$T$13:$T$58,$U$13:$U$58,"") -> 0 | B60: =UPPER(IF(F60="","",IF(IF(E60="","",LEN(E60)-LEN(SUBSTITUTE(E60,".","")))=2,(F60),B59))) -> IMPERMEABILIZAÇAO E TRATAMENTOS | C60: =PROPER(IF(OR(F60="",C59="PAVIMENTO"),"",IF(AND(IF(E60="","",LEN(E60)-LEN(SUBSTITUTE(E60,".","")))=3,H60=""),F60,C59))) -> 08_5º Pav. - Lazer | D60: =IF(H60="","","SERVIÇO") -> SERVIÇO | E60: 1.1.8.4 | F60: PISO: Sistema 4.2.4: Manta asfáltica 4mm aderida com asfalto oxidado modificado | Primer asfáltico à base d'água (0,4 L/m²) - ESPAÇO CROSSFIT | G60: m² | H60: 87.98 | I60: =_xlfn.XLOOKUP($F60,$M$66:$M$115,$N$66:$N$115) -> 4.2.4 | J60: =TRIM(RIGHT(SUBSTITUTE(SUBSTITUTE(F60,CHAR(10)," ")," ",REPT(" ",100)),100)) -> CROSSFIT | K60: =TRIM(LEFT(SUBSTITUTE(SUBSTITUTE(F60,CHAR(10)," ")," ",REPT(" ",100)),100)) -> PISO: | L60: PROTEÇÃO MECANICA | M60: PAREDE: Sistema 2.8.6: Argamassa polimérica para impermeabilização + Membrana de polímero acrílico com cimento e fibras sintéticas | Argamassa impermeabilizante bicomponente à base de aditivos minerais e polímeros (2,0 kg/m² - RESERVATÓRIO | N60: =SUMIFS($H$13:$H$10253,$A$13:$A$10253,N$10,$F$13:$F$10253,$M60) -> 149.3 | O60: =SUMIFS($H$13:$H$10253,$A$13:$A$10253,O$10,$F$13:$F$10253,$M60) -> 0 | P60: =SUMIFS($H$13:$H$10253,$A$13:$A$10253,P$10,$F$13:$F$10253,$M60) -> 0 | Q60: =SUMIFS($H$13:$H$10253,$F$13:$F$10253,$M60) -> 149.3 | R60: PAREDE: Sistema 2.8.6: Argamassa polimérica para impermeabilização + Membrana de polímero acrílico com cimento e fibras sintéticas | Argamassa impermeabilizante bicomponente à base de aditivos minerais e polímeros (2,0 kg/m²) + Revestimento bicomponente à base de polímeros acrílicos com adição de cimento e fibras sintéticas (4,5 kg/m²) + Tela de poliéster nos pontos críticos - RESERVATÓRIO
A61: =_xlfn.XLOOKUP(C61,$T$13:$T$58,$U$13:$U$58,"") -> 0 | B61: =UPPER(IF(F61="","",IF(IF(E61="","",LEN(E61)-LEN(SUBSTITUTE(E61,".","")))=2,(F61),B60))) -> IMPERMEABILIZAÇAO E TRATAMENTOS | C61: =PROPER(IF(OR(F61="",C60="PAVIMENTO"),"",IF(AND(IF(E61="","",LEN(E61)-LEN(SUBSTITUTE(E61,".","")))=3,H61=""),F61,C60))) -> 08_5º Pav. - Lazer | D61: =IF(H61="","","SERVIÇO") -> SERVIÇO | E61: 1.1.8.5 | F61: PAREDE: Sistema 2.5.3: Membrana de polímero acrílico com cimento e fibras sintéticas | Revestimento bicomponente à base de polímeros acrílicos com adição de cimento e fibras sintéticas (3,0 kg/m²) - ESQUADRIA | G61: m² | H61: 10.67 | I61: =_xlfn.XLOOKUP($F61,$M$66:$M$115,$N$66:$N$115) -> 2.5.3 | J61: =TRIM(RIGHT(SUBSTITUTE(SUBSTITUTE(F61,CHAR(10)," ")," ",REPT(" ",100)),100)) -> ESQUADRIA | K61: =TRIM(LEFT(SUBSTITUTE(SUBSTITUTE(F61,CHAR(10)," ")," ",REPT(" ",100)),100)) -> PAREDE: | M61: PISO: Sistema 2.8.6: Argamassa polimérica para impermeabilização + Membrana de polímero acrílico com cimento e fibras sintéticas | Argamassa impermeabilizante bicomponente à base de aditivos minerais e polímeros (2,0 kg/m² - RESERVATÓRIO | N61: =SUMIFS($H$13:$H$10253,$A$13:$A$10253,N$10,$F$13:$F$10253,$M61) -> 63.87 | O61: =SUMIFS($H$13:$H$10253,$A$13:$A$10253,O$10,$F$13:$F$10253,$M61) -> 0 | P61: =SUMIFS($H$13:$H$10253,$A$13:$A$10253,P$10,$F$13:$F$10253,$M61) -> 0 | Q61: =SUMIFS($H$13:$H$10253,$F$13:$F$10253,$M61) -> 63.87 | R61: PISO: Sistema 2.8.6: Argamassa polimérica para impermeabilização + Membrana de polímero acrílico com cimento e fibras sintéticas | Argamassa impermeabilizante bicomponente à base de aditivos minerais e polímeros (2,0 kg/m²) + Revestimento bicomponente à base de polímeros acrílicos com adição de cimento e fibras sintéticas (4,5 kg/m²) + Tela de poliéster nos pontos críticos - RESERVATÓRIO
A62: =_xlfn.XLOOKUP(C62,$T$13:$T$58,$U$13:$U$58,"") -> 0 | B62: =UPPER(IF(F62="","",IF(IF(E62="","",LEN(E62)-LEN(SUBSTITUTE(E62,".","")))=2,(F62),B61))) -> IMPERMEABILIZAÇAO E TRATAMENTOS | C62: =PROPER(IF(OR(F62="",C61="PAVIMENTO"),"",IF(AND(IF(E62="","",LEN(E62)-LEN(SUBSTITUTE(E62,".","")))=3,H62=""),F62,C61))) -> 08_5º Pav. - Lazer | D62: =IF(H62="","","SERVIÇO") -> SERVIÇO | E62: 1.1.8.6 | F62: PISO: Sistema 2.5.3: Membrana de polímero acrílico com cimento e fibras sintéticas | Revestimento bicomponente à base de polímeros acrílicos com adição de cimento e fibras sintéticas (3,0 kg/m²) - ESQUADRIA | G62: m² | H62: 12.17 | I62: =_xlfn.XLOOKUP($F62,$M$66:$M$115,$N$66:$N$115) -> 2.5.3 | J62: =TRIM(RIGHT(SUBSTITUTE(SUBSTITUTE(F62,CHAR(10)," ")," ",REPT(" ",100)),100)) -> ESQUADRIA | K62: =TRIM(LEFT(SUBSTITUTE(SUBSTITUTE(F62,CHAR(10)," ")," ",REPT(" ",100)),100)) -> PISO: | M62: TETO: Sistema 7.1.2: Argamassa impermeabilizante sem cimento - MK-FEN 30 (F) | Argamassa não cimentícia com agentes incorporadores de ar (4,0 kg/m²) + Tela de poliéster nos pontos críticos - RESERVATÓRIO | N62: =SUMIFS($H$13:$H$10253,$A$13:$A$10253,N$10,$F$13:$F$10253,$M62) -> 63.21 | O62: =SUMIFS($H$13:$H$10253,$A$13:$A$10253,O$10,$F$13:$F$10253,$M62) -> 0 | P62: =SUMIFS($H$13:$H$10253,$A$13:$A$10253,P$10,$F$13:$F$10253,$M62) -> 0 | Q62: =SUMIFS($H$13:$H$10253,$F$13:$F$10253,$M62) -> 63.21 | R62: TETO: Sistema 7.1.2: Argamassa impermeabilizante sem cimento - MK-FEN 30 (F) | Argamassa não cimentícia com agentes incorporadores de ar (4,0 kg/m²) + Tela de poliéster nos pontos críticos - RESERVATÓRIO
A63: =_xlfn.XLOOKUP(C63,$T$13:$T$58,$U$13:$U$58,"") -> 0 | B63: =UPPER(IF(F63="","",IF(IF(E63="","",LEN(E63)-LEN(SUBSTITUTE(E63,".","")))=2,(F63),B62))) -> IMPERMEABILIZAÇAO E TRATAMENTOS | C63: =PROPER(IF(OR(F63="",C62="PAVIMENTO"),"",IF(AND(IF(E63="","",LEN(E63)-LEN(SUBSTITUTE(E63,".","")))=3,H63=""),F63,C62))) -> 08_5º Pav. - Lazer | D63: =IF(H63="","","SERVIÇO") -> SERVIÇO | E63: 1.1.8.7 | F63: PAREDE: Sistema 4.5.3: Manta asfáltica 4mm aderida com asfalto oxidado modificado + Emulsão asfáltica antiraiz | Primer asfáltico à base d'água (0,4 L/m²) + Asfalto oxidado modificado (2,5 kg/m²) + Manta asfáltica AA | G63: m² | H63: 35.89 | I63: 4.5.3 | J63: FLOREIRA | K63: =TRIM(LEFT(SUBSTITUTE(SUBSTITUTE(F63,CHAR(10)," ")," ",REPT(" ",100)),100)) -> PAREDE: | M63: PISO: Sistema 7.1.6: Argamassa impermeabilizante sem cimento - MK-FEN 30 (F) | Argamassa não cimentícia com agentes incorporadores de ar (8,0 kg/m²) + Tela de poliéster nos pontos críticos - TAMPA DE RESERVATÓRIO | N63: =SUMIFS($H$13:$H$10253,$A$13:$A$10253,N$10,$F$13:$F$10253,$M63) -> 65.84 | O63: =SUMIFS($H$13:$H$10253,$A$13:$A$10253,O$10,$F$13:$F$10253,$M63) -> 0 | P63: =SUMIFS($H$13:$H$10253,$A$13:$A$10253,P$10,$F$13:$F$10253,$M63) -> 0 | Q63: =SUMIFS($H$13:$H$10253,$F$13:$F$10253,$M63) -> 65.84 | R63: PISO: Sistema 7.1.6: Argamassa impermeabilizante sem cimento - MK-FEN 30 (F) | Argamassa não cimentícia com agentes incorporadores de ar (8,0 kg/m²) + Tela de poliéster nos pontos críticos - TAMPA DE RESERVATÓRIO
A64: =_xlfn.XLOOKUP(C64,$T$13:$T$58,$U$13:$U$58,"") -> 0 | B64: =UPPER(IF(F64="","",IF(IF(E64="","",LEN(E64)-LEN(SUBSTITUTE(E64,".","")))=2,(F64),B63))) -> IMPERMEABILIZAÇAO E TRATAMENTOS | C64: =PROPER(IF(OR(F64="",C63="PAVIMENTO"),"",IF(AND(IF(E64="","",LEN(E64)-LEN(SUBSTITUTE(E64,".","")))=3,H64=""),F64,C63))) -> 08_5º Pav. - Lazer | D64: =IF(H64="","","SERVIÇO") -> SERVIÇO | E64: 1.1.8.8 | F64: PISO: Sistema 4.5.3: Manta asfáltica 4mm aderida com asfalto oxidado modificado + Emulsão asfáltica antiraiz | Primer asfáltico à base d'água (0,4 L/m²) + Asfalto oxidado modificado (2,5 kg/m²) + Manta asfáltica AA | G64: m² | H64: 263.73 | I64: 4.5.3 | J64: FLOREIRA | K64: =TRIM(LEFT(SUBSTITUTE(SUBSTITUTE(F64,CHAR(10)," ")," ",REPT(" ",100)),100)) -> PISO: | L64: PROTEÇÃO MECANICA
A65: =_xlfn.XLOOKUP(C65,$T$13:$T$58,$U$13:$U$58,"") -> 0 | B65: =UPPER(IF(F65="","",IF(IF(E65="","",LEN(E65)-LEN(SUBSTITUTE(E65,".","")))=2,(F65),B64))) -> IMPERMEABILIZAÇAO E TRATAMENTOS | C65: =PROPER(IF(OR(F65="",C64="PAVIMENTO"),"",IF(AND(IF(E65="","",LEN(E65)-LEN(SUBSTITUTE(E65,".","")))=3,H65=""),F65,C64))) -> 09_6º Pav. - Tipo Dif. | D65: =IF(H65="","","SERVIÇO") | E65: 1.1.9. | F65: 09_6º PAV. - TIPO DIF. | I65: =IF(C65=F65,SUMIFS($H$12:$H$63964,$C$12:$C$63964,C65),"") -> 247.32 | M65: TIPO DE IMPER | N65: NÚMERO IMPER | O65: TOTAL | P65: ORÇAMENTO
A66: =_xlfn.XLOOKUP(C66,$T$13:$T$58,$U$13:$U$58,"") -> 0 | B66: =UPPER(IF(F66="","",IF(IF(E66="","",LEN(E66)-LEN(SUBSTITUTE(E66,".","")))=2,(F66),B65))) -> IMPERMEABILIZAÇAO E TRATAMENTOS | C66: =PROPER(IF(OR(F66="",C65="PAVIMENTO"),"",IF(AND(IF(E66="","",LEN(E66)-LEN(SUBSTITUTE(E66,".","")))=3,H66=""),F66,C65))) -> 09_6º Pav. - Tipo Dif. | D66: =IF(H66="","","SERVIÇO") -> SERVIÇO | E66: 1.1.9.1 | F66: PAREDE: Sistema 2.5.3: Membrana de polímero acrílico com cimento e fibras sintéticas - ÁREA DE SERVIÇO | G66: m² | H66: 16.81 | I66: 2.5.3 | J66: =TRIM(RIGHT(SUBSTITUTE(SUBSTITUTE(F66,CHAR(10)," ")," ",REPT(" ",100)),100)) -> SERVIÇO | K66: =TRIM(LEFT(SUBSTITUTE(SUBSTITUTE(F66,CHAR(10)," ")," ",REPT(" ",100)),100)) -> PAREDE: | M66: PAREDE: Sistema 2.5.3: Membrana de polímero acrílico com cimento e fibras sintéticas | Revestimento bicomponente à base de polímeros acrílicos com adição de cimento e fibras sintéticas (3,0 kg/m²) + Tela de poliéster nos pontos críticos - BANHEIRO | N66: 2.5.3 | O66: =Q14 -> 68.14 | Q66: =TRIM(RIGHT(SUBSTITUTE(SUBSTITUTE(M66,CHAR(10)," ")," ",REPT(" ",100)),100)) -> BANHEIRO | T66: {=_xlfn.UNIQUE(_xlfn._xlws.FILTER($N$66:$N$10253,$N$66:$N$10253<>""))} -> 2.5.3 | U66: =SUMIF(N$66:N$115,T66,O$66:O$115) -> 4925.75 | V66: Membrana de polímero acrílico com cimento e fibras sintéticas | Revestimento bicomponente à base de polímeros acrílicos com adição de cimento e fibras sintéticas (3,0 kg/m²) + Tela de poliéster nos pontos críticos
A67: =_xlfn.XLOOKUP(C67,$T$13:$T$58,$U$13:$U$58,"") -> 0 | B67: =UPPER(IF(F67="","",IF(IF(E67="","",LEN(E67)-LEN(SUBSTITUTE(E67,".","")))=2,(F67),B66))) -> IMPERMEABILIZAÇAO E TRATAMENTOS | C67: =PROPER(IF(OR(F67="",C66="PAVIMENTO"),"",IF(AND(IF(E67="","",LEN(E67)-LEN(SUBSTITUTE(E67,".","")))=3,H67=""),F67,C66))) -> 09_6º Pav. - Tipo Dif. | D67: =IF(H67="","","SERVIÇO") -> SERVIÇO | E67: 1.1.9.2 | F67: PISO: Sistema 2.5.3: Membrana de polímero acrílico com cimento e fibras sintéticas | Revestimento bicomponente à base de polímeros acrílicos com adição de cimento e fibras sintéticas (3,0 kg/m²)+ Tela de poliéster nos pontos críticos - ÁREA DE SERVIÇO | G67: m² | H67: 6.9 | I67: =_xlfn.XLOOKUP($F67,$M$66:$M$115,$N$66:$N$115) -> 2.5.3 | J67: =TRIM(RIGHT(SUBSTITUTE(SUBSTITUTE(F67,CHAR(10)," ")," ",REPT(" ",100)),100)) -> SERVIÇO | K67: =TRIM(LEFT(SUBSTITUTE(SUBSTITUTE(F67,CHAR(10)," ")," ",REPT(" ",100)),100)) -> PISO: | M67: PISO: Sistema 2.5.3: Membrana de polímero acrílico com cimento e fibras sintéticas | Revestimento bicomponente à base de polímeros acrílicos com adição de cimento e fibras sintéticas (3,0 kg/m²) + Tela de poliéster nos pontos críticos - BANHEIRO | N67: 2.5.3 | O67: =Q15 -> 45.37 | Q67: =TRIM(RIGHT(SUBSTITUTE(SUBSTITUTE(M67,CHAR(10)," ")," ",REPT(" ",100)),100)) -> BANHEIRO | T67: 2.1.4 | U67: =SUMIF(N$66:N$115,T67,O$66:O$115) -> 91.15 | V67: Argamassa polimérica para impermeabilização | Argamassa impermeabilizante bicomponente à base de aditivos minerais e polímeros (4,0 kg/m²) + Tela de poliéster nos pontos críticos
A68: =_xlfn.XLOOKUP(C68,$T$13:$T$58,$U$13:$U$58,"") -> 0 | B68: =UPPER(IF(F68="","",IF(IF(E68="","",LEN(E68)-LEN(SUBSTITUTE(E68,".","")))=2,(F68),B67))) -> IMPERMEABILIZAÇAO E TRATAMENTOS | C68: =PROPER(IF(OR(F68="",C67="PAVIMENTO"),"",IF(AND(IF(E68="","",LEN(E68)-LEN(SUBSTITUTE(E68,".","")))=3,H68=""),F68,C67))) -> 09_6º Pav. - Tipo Dif. | D68: =IF(H68="","","SERVIÇO") -> SERVIÇO | E68: 1.1.9.3 | F68: PAREDE: Sistema 7.1.6: Argamassa impermeabilizante sem cimento - MK-FEN 30 (F) | Argamassa não cimentícia com agentes incorporadores de ar (8,0 kg/m²) + Tela de poliéster nos pontos críticos - ÁREA TÉCNICA | G68: m² | H68: 3.35 | I68: =_xlfn.XLOOKUP($F68,$M$66:$M$115,$N$66:$N$115) -> 7.1.6 | J68: =TRIM(RIGHT(SUBSTITUTE(SUBSTITUTE(F68,CHAR(10)," ")," ",REPT(" ",100)),100)) -> TÉCNICA | K68: =TRIM(LEFT(SUBSTITUTE(SUBSTITUTE(F68,CHAR(10)," ")," ",REPT(" ",100)),100)) -> PAREDE: | M68: PAREDE: Sistema 2.1.4: Argamassa polimérica para impermeabilização - CASA DE BOMBAS | N68: 2.1.4 | O68: =Q16 -> 4.11 | Q68: =TRIM(RIGHT(SUBSTITUTE(SUBSTITUTE(M68,CHAR(10)," ")," ",REPT(" ",100)),100)) -> BOMBAS | T68: 1 | U68: =SUMIF(N$66:N$115,T68,O$66:O$115) -> 6.52 | V68: Argamassa polimérica para impermeabilizaçãoArgamassa impermeabilizante bicomponente à base de aditivos minerais e polímeros (4,0 kg/m²) + Tela depoliéster nos pontos críticos
A69: =_xlfn.XLOOKUP(C69,$T$13:$T$58,$U$13:$U$58,"") -> 0 | B69: =UPPER(IF(F69="","",IF(IF(E69="","",LEN(E69)-LEN(SUBSTITUTE(E69,".","")))=2,(F69),B68))) -> IMPERMEABILIZAÇAO E TRATAMENTOS | C69: =PROPER(IF(OR(F69="",C68="PAVIMENTO"),"",IF(AND(IF(E69="","",LEN(E69)-LEN(SUBSTITUTE(E69,".","")))=3,H69=""),F69,C68))) -> 09_6º Pav. - Tipo Dif. | D69: =IF(H69="","","SERVIÇO") -> SERVIÇO | E69: 1.1.9.4 | F69: PISO: Sistema 7.1.6: Argamassa impermeabilizante sem cimento - MK-FEN 30 (F) | Argamassa não cimentícia com agentes incorporadores de ar (8,0 kg/m²) + Tela de poliéster nos pontos críticos - ÁREA TÉCNICA | G69: m² | H69: 5.64 | I69: =_xlfn.XLOOKUP($F69,$M$66:$M$115,$N$66:$N$115) -> 7.1.6 | J69: =TRIM(RIGHT(SUBSTITUTE(SUBSTITUTE(F69,CHAR(10)," ")," ",REPT(" ",100)),100)) -> TÉCNICA | K69: =TRIM(LEFT(SUBSTITUTE(SUBSTITUTE(F69,CHAR(10)," ")," ",REPT(" ",100)),100)) -> PISO: | M69: PISO: Sistema 2.1.4: Argamassa polimérica para impermeabilização | Argamassa impermeabilizante bicomponente à base de aditivos minerais e polímeros (4,0 kg/m²) + Tela de poliéster nos pontos críticos - CASA DE BOMBAS | N69: 2.1.4 | O69: =Q17 -> 7.01 | Q69: =TRIM(RIGHT(SUBSTITUTE(SUBSTITUTE(M69,CHAR(10)," ")," ",REPT(" ",100)),100)) -> BOMBAS | T69: 4.5.3 | U69: =SUMIF(N$66:N$115,T69,O$66:O$115) -> 342.12 | V69: Manta asfáltica 4mm aderida com asfalto oxidado modificado + Emulsão asfáltica antiraiz | Primer asfáltico à base d'água (0,4 L/m²) + Asfalto oxidado modificado (2,5 kg/m²) + Manta asfáltica AA 4mm Tipo III Classe B + Banho de asfalto oxidado modificado (2,5 kg/m²) + Emulsão asfáltica antiraiz sobre a proteção mecânica (0,8 L/m²)
A70: =_xlfn.XLOOKUP(C70,$T$13:$T$58,$U$13:$U$58,"") -> 0 | B70: =UPPER(IF(F70="","",IF(IF(E70="","",LEN(E70)-LEN(SUBSTITUTE(E70,".","")))=2,(F70),B69))) -> IMPERMEABILIZAÇAO E TRATAMENTOS | C70: =PROPER(IF(OR(F70="",C69="PAVIMENTO"),"",IF(AND(IF(E70="","",LEN(E70)-LEN(SUBSTITUTE(E70,".","")))=3,H70=""),F70,C69))) -> 09_6º Pav. - Tipo Dif. | D70: =IF(H70="","","SERVIÇO") -> SERVIÇO | E70: 1.1.9.5 | F70: PAREDE: Sistema 2.5.3: Membrana de polímero acrílico com cimento e fibras sintéticas | Revestimento bicomponente à base de polímeros acrílicos com adição de cimento e fibras sintéticas (3,0 kg/m²) - BANHEIRO | G70: m² | H70: 26.97 | I70: =_xlfn.XLOOKUP($F70,$M$66:$M$115,$N$66:$N$115) -> 2.5.3 | J70: =TRIM(RIGHT(SUBSTITUTE(SUBSTITUTE(F70,CHAR(10)," ")," ",REPT(" ",100)),100)) -> BANHEIRO | K70: =TRIM(LEFT(SUBSTITUTE(SUBSTITUTE(F70,CHAR(10)," ")," ",REPT(" ",100)),100)) -> PAREDE: | M70: PISO: Sistema 2.5.3: Membrana de polímero acrílico com cimento e fibras sintéticas | Revestimento bicomponente à base de polímeros acrílicos com adição de cimento e fibras sintéticas (3,0 kg/m²) - ESQUADRIA | N70: 2.5.3 | O70: =Q18 -> 37.98 | Q70: =TRIM(RIGHT(SUBSTITUTE(SUBSTITUTE(M70,CHAR(10)," ")," ",REPT(" ",100)),100)) -> ESQUADRIA | T70: 3 | U70: =SUMIF(N$66:N$115,T70,O$66:O$115) -> 698.85 | V70: FUNDAÇÃO
A71: =_xlfn.XLOOKUP(C71,$T$13:$T$58,$U$13:$U$58,"") -> 0 | B71: =UPPER(IF(F71="","",IF(IF(E71="","",LEN(E71)-LEN(SUBSTITUTE(E71,".","")))=2,(F71),B70))) -> IMPERMEABILIZAÇAO E TRATAMENTOS | C71: =PROPER(IF(OR(F71="",C70="PAVIMENTO"),"",IF(AND(IF(E71="","",LEN(E71)-LEN(SUBSTITUTE(E71,".","")))=3,H71=""),F71,C70))) -> 09_6º Pav. - Tipo Dif. | D71: =IF(H71="","","SERVIÇO") -> SERVIÇO | E71: 1.1.9.6 | F71: PISO: Sistema 2.5.3: Membrana de polímero acrílico com cimento e fibras sintéticas | Revestimento bicomponente à base de polímeros acrílicos com adição de cimento e fibras sintéticas (3,0 kg/m²)+ Tela de poliéster nos pontos críticos - BANHEIRO | G71: m² | H71: 19.95 | I71: =_xlfn.XLOOKUP($F71,$M$66:$M$115,$N$66:$N$115) -> 2.5.3 | J71: =TRIM(RIGHT(SUBSTITUTE(SUBSTITUTE(F71,CHAR(10)," ")," ",REPT(" ",100)),100)) -> BANHEIRO | K71: =TRIM(LEFT(SUBSTITUTE(SUBSTITUTE(F71,CHAR(10)," ")," ",REPT(" ",100)),100)) -> PISO: | M71: PISO: Argamassa polimérica para impermeabilizaçãoArgamassa impermeabilizante bicomponente à base de aditivos minerais e polímeros (4,0 kg/m²) + Tela depoliéster nos pontos críticos - CENTRAL DE GÁS/LIXEIRA | N71: 1 | O71: =Q19 -> 6.52 | Q71: =TRIM(RIGHT(SUBSTITUTE(SUBSTITUTE(M71,CHAR(10)," ")," ",REPT(" ",100)),100)) -> GÁS/LIXEIRA | T71: 2.8.6 | U71: =SUMIF(N$66:N$115,T71,O$66:O$115) -> 234 | V71: Argamassa polimérica para impermeabilização + Membrana de polímero acrílico com cimento e fibras sintéticas | Argamassa impermeabilizante bicomponente à base de aditivos minerais e polímeros (2,0 kg/m²) + Revestimento bicomponente à base de polímeros acrílicos com adição de cimento e fibras sintéticas (4,5 kg/m²) + Tela de poliéster nos pontos críticos
A72: =_xlfn.XLOOKUP(C72,$T$13:$T$58,$U$13:$U$58,"") -> 0 | B72: =UPPER(IF(F72="","",IF(IF(E72="","",LEN(E72)-LEN(SUBSTITUTE(E72,".","")))=2,(F72),B71))) -> IMPERMEABILIZAÇAO E TRATAMENTOS | C72: =PROPER(IF(OR(F72="",C71="PAVIMENTO"),"",IF(AND(IF(E72="","",LEN(E72)-LEN(SUBSTITUTE(E72,".","")))=3,H72=""),F72,C71))) -> 09_6º Pav. - Tipo Dif. | D72: =IF(H72="","","SERVIÇO") -> SERVIÇO | E72: 1.1.9.7 | F72: PAREDE: Sistema 2.5.3: Membrana de polímero acrílico com cimento e fibras sintéticas | Revestimento bicomponente à base de polímeros acrílicos com adição de cimento e fibras sintéticas (3,0 kg/m²) - BOX BANHEIRO | G72: m² | H72: 24.3 | I72: =_xlfn.XLOOKUP($F72,$M$66:$M$115,$N$66:$N$115) -> 2.5.3 | J72: =TRIM(RIGHT(SUBSTITUTE(SUBSTITUTE(F72,CHAR(10)," ")," ",REPT(" ",100)),100)) -> BANHEIRO | K72: =TRIM(LEFT(SUBSTITUTE(SUBSTITUTE(F72,CHAR(10)," ")," ",REPT(" ",100)),100)) -> PAREDE: | M72: PAREDE: Sistema 4.5.3: Manta asfáltica 4mm aderida com asfalto oxidado modificado + Emulsão asfáltica antiraiz | Primer asfáltico à base d'água (0,4 L/m²) + Asfalto oxidado modificado (2,5 kg/m²) + Manta asfáltica AA 4mm Tipo III Classe B + Banho de asfalto oxidado modificado (2,5 kg/m²) + Emulsão asfáltica antiraiz sobre a proteção mecânica (0,8 L/m²) - FLOREIRA | N72: 4.5.3 | O72: =Q20 -> 70.68 | Q72: =TRIM(RIGHT(SUBSTITUTE(SUBSTITUTE(M72,CHAR(10)," ")," ",REPT(" ",100)),100)) -> FLOREIRA | T72: 7.1.2 | U72: =SUMIF(N$66:N$115,T72,O$66:O$115) -> 68.2 | V72: Argamassa impermeabilizante sem cimento - MK-FEN 30 (F) | Argamassa não cimentícia com agentes incorporadores de ar (4,0 kg/m²) + Tela de poliéster nos pontos críticos
A73: =_xlfn.XLOOKUP(C73,$T$13:$T$58,$U$13:$U$58,"") -> 0 | B73: =UPPER(IF(F73="","",IF(IF(E73="","",LEN(E73)-LEN(SUBSTITUTE(E73,".","")))=2,(F73),B72))) -> IMPERMEABILIZAÇAO E TRATAMENTOS | C73: =PROPER(IF(OR(F73="",C72="PAVIMENTO"),"",IF(AND(IF(E73="","",LEN(E73)-LEN(SUBSTITUTE(E73,".","")))=3,H73=""),F73,C72))) -> 09_6º Pav. - Tipo Dif. | D73: =IF(H73="","","SERVIÇO") -> SERVIÇO | E73: 1.1.9.8 | F73: PISO: Sistema 2.5.3: Membrana de polímero acrílico com cimento e fibras sintéticas | Revestimento bicomponente à base de polímeros acrílicos com adição de cimento e fibras sintéticas (3,0 kg/m²)+ Tela de poliéster nos pontos críticos - BOX BANHEIRO | G73: m² | H73: 8.08 | I73: =_xlfn.XLOOKUP($F73,$M$66:$M$115,$N$66:$N$115) -> 2.5.3 | J73: =TRIM(RIGHT(SUBSTITUTE(SUBSTITUTE(F73,CHAR(10)," ")," ",REPT(" ",100)),100)) -> BANHEIRO | K73: =TRIM(LEFT(SUBSTITUTE(SUBSTITUTE(F73,CHAR(10)," ")," ",REPT(" ",100)),100)) -> PISO: | M73: PISO: Sistema 4.5.3: Manta asfáltica 4mm aderida com asfalto oxidado modificado + Emulsão asfáltica antiraiz | Primer asfáltico à base d'água (0,4 L/m²) + Asfalto oxidado modificado (2,5 kg/m²) + Manta asfáltica AA 4mm Tipo III Classe B + Banho de asfalto oxidado modificado (2,5 kg/m²) + Emulsão asfáltica antiraiz sobre a proteção mecânica (0,8 L/m²) - FLOREIRA | N73: 4.5.3 | O73: =Q21 -> 271.44 | Q73: =TRIM(RIGHT(SUBSTITUTE(SUBSTITUTE(M73,CHAR(10)," ")," ",REPT(" ",100)),100)) -> FLOREIRA | T73: 4.2.4 | U73: =SUMIF(N$66:N$115,T73,O$66:O$115) -> 757.06 | V73: Manta asfáltica 4mm aderida com asfalto oxidado modificado | Primer asfáltico à base d'água (0,4 L/m²) + Asfalto oxidado modificado (2,5 kg/m²) + Manta asfáltica AA 4mm Tipo III Classe B + Banho de asfalto oxidado modificado (2,5 kg/m²)
A74: =_xlfn.XLOOKUP(C74,$T$13:$T$58,$U$13:$U$58,"") -> 0 | B74: =UPPER(IF(F74="","",IF(IF(E74="","",LEN(E74)-LEN(SUBSTITUTE(E74,".","")))=2,(F74),B73))) -> IMPERMEABILIZAÇAO E TRATAMENTOS | C74: =PROPER(IF(OR(F74="",C73="PAVIMENTO"),"",IF(AND(IF(E74="","",LEN(E74)-LEN(SUBSTITUTE(E74,".","")))=3,H74=""),F74,C73))) -> 09_6º Pav. - Tipo Dif. | D74: =IF(H74="","","SERVIÇO") -> SERVIÇO | E74: 1.1.9.9 | F74: PAREDE: Sistema 2.5.3: Membrana de polímero acrílico com cimento e fibras sintéticas | Revestimento bicomponente à base de polímeros acrílicos com adição de cimento e fibras sintéticas (3,0 kg/m²) - ESQUADRIA | G74: m² | H74: 30.76 | I74: =_xlfn.XLOOKUP($F74,$M$66:$M$115,$N$66:$N$115) -> 2.5.3 | J74: =TRIM(RIGHT(SUBSTITUTE(SUBSTITUTE(F74,CHAR(10)," ")," ",REPT(" ",100)),100)) -> ESQUADRIA | K74: =TRIM(LEFT(SUBSTITUTE(SUBSTITUTE(F74,CHAR(10)," ")," ",REPT(" ",100)),100)) -> PAREDE: | M74: PAREDE: Sistema 2.1.4: Argamassa polimérica para impermeabilização | Argamassa impermeabilizante bicomponente à base de aditivos minerais e polímeros (4,0 kg/m²) + Tela de poliéster nos pontos críticos - FOSSO ELEVADOR | N74: 2.1.4 | O74: =Q22 -> 68.86 | Q74: =TRIM(RIGHT(SUBSTITUTE(SUBSTITUTE(M74,CHAR(10)," ")," ",REPT(" ",100)),100)) -> ELEVADOR | T74: 4.9.2 | U74: =SUMIF(N$66:N$115,T74,O$66:O$115) -> 241.13 | V74: Manta asfáltica 4+4mm aderida com asfalto oxidado modificado + Argamassa polimérica para impermeabilização | Primer asfáltico à base d'água (0,4 L/m²) + Asfalto oxidado modificado (2,5 kg/m²) + Manta asfáltica AA 3mm Tipo III Classe B + Asfalto oxidado modificado (2,5 kg/m²) + Manta asfáltica AA 4mm Tipo III Classe B + Argamassa polimérica para impermeabilização sobre a proteção mecânica (2,0 kg/m²)
A75: =_xlfn.XLOOKUP(C75,$T$13:$T$58,$U$13:$U$58,"") -> 0 | B75: =UPPER(IF(F75="","",IF(IF(E75="","",LEN(E75)-LEN(SUBSTITUTE(E75,".","")))=2,(F75),B74))) -> IMPERMEABILIZAÇAO E TRATAMENTOS | C75: =PROPER(IF(OR(F75="",C74="PAVIMENTO"),"",IF(AND(IF(E75="","",LEN(E75)-LEN(SUBSTITUTE(E75,".","")))=3,H75=""),F75,C74))) -> 09_6º Pav. - Tipo Dif. | D75: =IF(H75="","","SERVIÇO") -> SERVIÇO | E75: 1.1.9.10 | F75: PISO: Sistema 2.5.3: Membrana de polímero acrílico com cimento e fibras sintéticas | Revestimento bicomponente à base de polímeros acrílicos com adição de cimento e fibras sintéticas (3,0 kg/m²)+ Tela de poliéster nos pontos críticos - ESQUADRIA | G75: m² | H75: 19.02 | I75: =_xlfn.XLOOKUP($F75,$M$66:$M$115,$N$66:$N$115) -> 2.5.3 | J75: =TRIM(RIGHT(SUBSTITUTE(SUBSTITUTE(F75,CHAR(10)," ")," ",REPT(" ",100)),100)) -> ESQUADRIA | K75: =TRIM(LEFT(SUBSTITUTE(SUBSTITUTE(F75,CHAR(10)," ")," ",REPT(" ",100)),100)) -> PISO: | M75: PISO: Sistema 2.1.4: Argamassa polimérica para impermeabilização | Argamassa impermeabilizante bicomponente à base de aditivos minerais e polímeros (4,0 kg/m²) + Tela de poliéster nos pontos críticos - FOSSO ELEVADOR | N75: 2.1.4 | O75: =Q23 -> 11.17 | Q75: =TRIM(RIGHT(SUBSTITUTE(SUBSTITUTE(M75,CHAR(10)," ")," ",REPT(" ",100)),100)) -> ELEVADOR | T75: 7.1.6 | U75: =SUMIF(N$66:N$115,T75,O$66:O$115) -> 900.28 | V75: Argamassa impermeabilizante sem cimento - MK-FEN 30 (F) | Argamassa não cimentícia com agentes incorporadores de ar (8,0 kg/m²) + Tela de poliéster nos pontos críticos
A76: =_xlfn.XLOOKUP(C76,$T$13:$T$58,$U$13:$U$58,"") -> 0 | B76: =UPPER(IF(F76="","",IF(IF(E76="","",LEN(E76)-LEN(SUBSTITUTE(E76,".","")))=2,(F76),B75))) -> IMPERMEABILIZAÇAO E TRATAMENTOS | C76: =PROPER(IF(OR(F76="",C75="PAVIMENTO"),"",IF(AND(IF(E76="","",LEN(E76)-LEN(SUBSTITUTE(E76,".","")))=3,H76=""),F76,C75))) -> 09_6º Pav. - Tipo Dif. | D76: =IF(H76="","","SERVIÇO") -> SERVIÇO | E76: 1.1.9.11 | F76: PISO: Sistema 7.1.6: Argamassa impermeabilizante sem cimento - MK-FEN 30 (F) | Argamassa não cimentícia com agentes incorporadores de ar (8,0 kg/m²) + Tela de poliéster nos pontos críticos - MOLDURA FACHADA | G76: m² | H76: 38.38 | I76: =_xlfn.XLOOKUP($F76,$M$66:$M$115,$N$66:$N$115) -> 7.1.6 | J76: =TRIM(RIGHT(SUBSTITUTE(SUBSTITUTE(F76,CHAR(10)," ")," ",REPT(" ",100)),100)) -> FACHADA | K76: =TRIM(LEFT(SUBSTITUTE(SUBSTITUTE(F76,CHAR(10)," ")," ",REPT(" ",100)),100)) -> PISO: | M76: PAREDE: - VIGA BALDRAME | N76: 3 | O76: =Q24 -> 514.29 | Q76: =TRIM(RIGHT(SUBSTITUTE(SUBSTITUTE(M76,CHAR(10)," ")," ",REPT(" ",100)),100)) -> BALDRAME | R76: 13.001.002.001
A77: =_xlfn.XLOOKUP(C77,$T$13:$T$58,$U$13:$U$58,"") -> 0 | B77: =UPPER(IF(F77="","",IF(IF(E77="","",LEN(E77)-LEN(SUBSTITUTE(E77,".","")))=2,(F77),B76))) -> IMPERMEABILIZAÇAO E TRATAMENTOS | C77: =PROPER(IF(OR(F77="",C76="PAVIMENTO"),"",IF(AND(IF(E77="","",LEN(E77)-LEN(SUBSTITUTE(E77,".","")))=3,H77=""),F77,C76))) -> 09_6º Pav. - Tipo Dif. | D77: =IF(H77="","","SERVIÇO") -> SERVIÇO | E77: 1.1.9.12 | F77: PAREDE: Sistema 4.2.4: Manta asfáltica 4mm aderida com asfalto oxidado modificado | Primer asfáltico à base d'água (0,4 L/m²) - SACADA | G77: m² | H77: 2.34 | I77: 4.2.4 | J77: =TRIM(RIGHT(SUBSTITUTE(SUBSTITUTE(F77,CHAR(10)," ")," ",REPT(" ",100)),100)) -> SACADA | K77: =TRIM(LEFT(SUBSTITUTE(SUBSTITUTE(F77,CHAR(10)," ")," ",REPT(" ",100)),100)) -> PAREDE: | M77: PISO: - VIGA BALDRAME | N77: 3 | O77: =Q25 -> 184.56 | Q77: =TRIM(RIGHT(SUBSTITUTE(SUBSTITUTE(M77,CHAR(10)," ")," ",REPT(" ",100)),100)) -> BALDRAME | R77: 13.001.002.001
A78: =_xlfn.XLOOKUP(C78,$T$13:$T$58,$U$13:$U$58,"") -> 0 | B78: =UPPER(IF(F78="","",IF(IF(E78="","",LEN(E78)-LEN(SUBSTITUTE(E78,".","")))=2,(F78),B77))) -> IMPERMEABILIZAÇAO E TRATAMENTOS | C78: =PROPER(IF(OR(F78="",C77="PAVIMENTO"),"",IF(AND(IF(E78="","",LEN(E78)-LEN(SUBSTITUTE(E78,".","")))=3,H78=""),F78,C77))) -> 09_6º Pav. - Tipo Dif. | D78: =IF(H78="","","SERVIÇO") -> SERVIÇO | E78: 1.1.9.13 | F78: PISO: Sistema 4.2.4: Manta asfáltica 4mm aderida com asfalto oxidado modificado | - SACADA | G78: m² | H78: 44.82 | I78: 4.2.4 | J78: =TRIM(RIGHT(SUBSTITUTE(SUBSTITUTE(F78,CHAR(10)," ")," ",REPT(" ",100)),100)) -> SACADA | K78: =TRIM(LEFT(SUBSTITUTE(SUBSTITUTE(F78,CHAR(10)," ")," ",REPT(" ",100)),100)) -> PISO: | L78: PROTEÇÃO MECANICA | M78: PAREDE: Sistema 2.5.3: Membrana de polímero acrílico com cimento e fibras sintéticas | Revestimento bicomponente à base de polímeros acrílicos com adição de cimento e fibras sintéticas (3,0 kg/m²) - ESQUADRIA | N78: 2.5.3 | O78: =Q26 -> 1131.6 | Q78: =TRIM(RIGHT(SUBSTITUTE(SUBSTITUTE(M78,CHAR(10)," ")," ",REPT(" ",100)),100)) -> ESQUADRIA
A79: =_xlfn.XLOOKUP(C79,$T$13:$T$58,$U$13:$U$58,"") -> Tipo x8 | B79: =UPPER(IF(F79="","",IF(IF(E79="","",LEN(E79)-LEN(SUBSTITUTE(E79,".","")))=2,(F79),B78))) -> IMPERMEABILIZAÇAO E TRATAMENTOS | C79: =PROPER(IF(OR(F79="",C78="PAVIMENTO"),"",IF(AND(IF(E79="","",LEN(E79)-LEN(SUBSTITUTE(E79,".","")))=3,H79=""),F79,C78))) -> 10_7º Pav. - Tipo | D79: =IF(H79="","","SERVIÇO") | E79: 1.1.10. | F79: 10_7º PAV. - TIPO | I79: =IF(C79=F79,SUMIFS($H$12:$H$63964,$C$12:$C$63964,C79),"") -> 211.48 | M79: PAREDE: Sistema 2.8.6: Argamassa polimérica para impermeabilização + Membrana de polímero acrílico com cimento e fibras sintéticas | Argamassa impermeabilizante bicomponente à base de aditivos minerais e polímeros (2,0 kg/m²) + Revestimento bicomponente à base de polímeros acrílicos com adição de cimento e fibras sintéticas (4,5 kg/m²) + Tela de poliéster nos pontos críticos - CISTERNA | N79: 2.8.6 | O79: =Q27 -> 15.84 | Q79: =TRIM(RIGHT(SUBSTITUTE(SUBSTITUTE(M79,CHAR(10)," ")," ",REPT(" ",100)),100)) -> CISTERNA
A80: =_xlfn.XLOOKUP(C80,$T$13:$T$58,$U$13:$U$58,"") -> Tipo x8 | B80: =UPPER(IF(F80="","",IF(IF(E80="","",LEN(E80)-LEN(SUBSTITUTE(E80,".","")))=2,(F80),B79))) -> IMPERMEABILIZAÇAO E TRATAMENTOS | C80: =PROPER(IF(OR(F80="",C79="PAVIMENTO"),"",IF(AND(IF(E80="","",LEN(E80)-LEN(SUBSTITUTE(E80,".","")))=3,H80=""),F80,C79))) -> 10_7º Pav. - Tipo | D80: =IF(H80="","","SERVIÇO") -> SERVIÇO | E80: 1.1.10.1 | F80: PAREDE: Sistema 2.5.3: Membrana de polímero acrílico com cimento e fibras sintéticas - ÁREA DE SERVIÇO | G80: m² | H80: 16.83 | I80: 2.5.3 | J80: =TRIM(RIGHT(SUBSTITUTE(SUBSTITUTE(F80,CHAR(10)," ")," ",REPT(" ",100)),100)) -> SERVIÇO | K80: =TRIM(LEFT(SUBSTITUTE(SUBSTITUTE(F80,CHAR(10)," ")," ",REPT(" ",100)),100)) -> PAREDE: | M80: PISO: Sistema 2.8.6: Argamassa polimérica para impermeabilização + Membrana de polímero acrílico com cimento e fibras sintéticas | Argamassa impermeabilizante bicomponente à base de aditivos minerais e polímeros (2,0 kg/m²) + Revestimento bicomponente à base de polímeros acrílicos com adição de cimento e fibras sintéticas (4,5 kg/m²) + Tela de poliéster nos pontos críticos - CISTERNA | N80: 2.8.6 | O80: =Q28 -> 4.99 | Q80: =TRIM(RIGHT(SUBSTITUTE(SUBSTITUTE(M80,CHAR(10)," ")," ",REPT(" ",100)),100)) -> CISTERNA
A81: =_xlfn.XLOOKUP(C81,$T$13:$T$58,$U$13:$U$58,"") -> Tipo x8 | B81: =UPPER(IF(F81="","",IF(IF(E81="","",LEN(E81)-LEN(SUBSTITUTE(E81,".","")))=2,(F81),B80))) -> IMPERMEABILIZAÇAO E TRATAMENTOS | C81: =PROPER(IF(OR(F81="",C80="PAVIMENTO"),"",IF(AND(IF(E81="","",LEN(E81)-LEN(SUBSTITUTE(E81,".","")))=3,H81=""),F81,C80))) -> 10_7º Pav. - Tipo | D81: =IF(H81="","","SERVIÇO") -> SERVIÇO | E81: 1.1.10.2 | F81: PISO: Sistema 2.5.3: Membrana de polímero acrílico com cimento e fibras sintéticas | Revestimento bicomponente à base de polímeros acrílicos com adição de cimento e fibras sintéticas (3,0 kg/m²)+ Tela de poliéster nos pontos críticos - ÁREA DE SERVIÇO | G81: m² | H81: 6.93 | I81: =_xlfn.XLOOKUP($F81,$M$66:$M$115,$N$66:$N$115) -> 2.5.3 | J81: =TRIM(RIGHT(SUBSTITUTE(SUBSTITUTE(F81,CHAR(10)," ")," ",REPT(" ",100)),100)) -> SERVIÇO | K81: =TRIM(LEFT(SUBSTITUTE(SUBSTITUTE(F81,CHAR(10)," ")," ",REPT(" ",100)),100)) -> PISO: | M81: TETO: Sistema 7.1.2: Argamassa impermeabilizante sem cimento - MK-FEN 30 (F) | Argamassa não cimentícia com agentes incorporadores de ar (4,0 kg/m²) + Tela de poliéster nos pontos críticos - CISTERNA | N81: 7.1.2 | O81: =Q29 -> 4.99 | Q81: =TRIM(RIGHT(SUBSTITUTE(SUBSTITUTE(M81,CHAR(10)," ")," ",REPT(" ",100)),100)) -> CISTERNA
A82: =_xlfn.XLOOKUP(C82,$T$13:$T$58,$U$13:$U$58,"") -> Tipo x8 | B82: =UPPER(IF(F82="","",IF(IF(E82="","",LEN(E82)-LEN(SUBSTITUTE(E82,".","")))=2,(F82),B81))) -> IMPERMEABILIZAÇAO E TRATAMENTOS | C82: =PROPER(IF(OR(F82="",C81="PAVIMENTO"),"",IF(AND(IF(E82="","",LEN(E82)-LEN(SUBSTITUTE(E82,".","")))=3,H82=""),F82,C81))) -> 10_7º Pav. - Tipo | D82: =IF(H82="","","SERVIÇO") -> SERVIÇO | E82: 1.1.10.3 | F82: PAREDE: Sistema 7.1.6: Argamassa impermeabilizante sem cimento - MK-FEN 30 (F) | Argamassa não cimentícia com agentes incorporadores de ar (8,0 kg/m²) + Tela de poliéster nos pontos críticos - ÁREA TÉCNICA | G82: m² | H82: 6.51 | I82: =_xlfn.XLOOKUP($F82,$M$66:$M$115,$N$66:$N$115) -> 7.1.6 | J82: =TRIM(RIGHT(SUBSTITUTE(SUBSTITUTE(F82,CHAR(10)," ")," ",REPT(" ",100)),100)) -> TÉCNICA | K82: =TRIM(LEFT(SUBSTITUTE(SUBSTITUTE(F82,CHAR(10)," ")," ",REPT(" ",100)),100)) -> PAREDE: | M82: PAREDE: Sistema 4.2.4: Manta asfáltica 4mm aderida com asfalto oxidado modificado | Primer asfáltico à base d'água (0,4 L/m²) + Asfalto oxidado modificado (2,5 kg/m²) + Manta asfáltica AA 4mm Tipo III Classe B + Banho de asfalto oxidado modificado (2,5 kg/m²) - CIRCULAÇÃO | N82: 4.2.4 | O82: =Q30 -> 27.38 | Q82: =TRIM(RIGHT(SUBSTITUTE(SUBSTITUTE(M82,CHAR(10)," ")," ",REPT(" ",100)),100)) -> CIRCULAÇÃO
A83: =_xlfn.XLOOKUP(C83,$T$13:$T$58,$U$13:$U$58,"") -> Tipo x8 | B83: =UPPER(IF(F83="","",IF(IF(E83="","",LEN(E83)-LEN(SUBSTITUTE(E83,".","")))=2,(F83),B82))) -> IMPERMEABILIZAÇAO E TRATAMENTOS | C83: =PROPER(IF(OR(F83="",C82="PAVIMENTO"),"",IF(AND(IF(E83="","",LEN(E83)-LEN(SUBSTITUTE(E83,".","")))=3,H83=""),F83,C82))) -> 10_7º Pav. - Tipo | D83: =IF(H83="","","SERVIÇO") -> SERVIÇO | E83: 1.1.10.4 | F83: PISO: Sistema 7.1.6: Argamassa impermeabilizante sem cimento - MK-FEN 30 (F) | Argamassa não cimentícia com agentes incorporadores de ar (8,0 kg/m²) + Tela de poliéster nos pontos críticos - ÁREA TÉCNICA | G83: m² | H83: 10.8 | I83: =_xlfn.XLOOKUP($F83,$M$66:$M$115,$N$66:$N$115) -> 7.1.6 | J83: =TRIM(RIGHT(SUBSTITUTE(SUBSTITUTE(F83,CHAR(10)," ")," ",REPT(" ",100)),100)) -> TÉCNICA | K83: =TRIM(LEFT(SUBSTITUTE(SUBSTITUTE(F83,CHAR(10)," ")," ",REPT(" ",100)),100)) -> PISO: | M83: PISO: Sistema 4.2.4: Manta asfáltica 4mm aderida com asfalto oxidado modificado | Primer asfáltico à base d'água (0,4 L/m²) + Asfalto oxidado modificado (2,5 kg/m²) + Manta asfáltica AA 4mm Tipo III Classe B + Banho de asfalto oxidado modificado (2,5 kg/m²) - CIRCULAÇÃO | N83: 4.2.4 | O83: =Q31 -> 142.23 | Q83: =TRIM(RIGHT(SUBSTITUTE(SUBSTITUTE(M83,CHAR(10)," ")," ",REPT(" ",100)),100)) -> CIRCULAÇÃO
A84: =_xlfn.XLOOKUP(C84,$T$13:$T$58,$U$13:$U$58,"") -> Tipo x8 | B84: =UPPER(IF(F84="","",IF(IF(E84="","",LEN(E84)-LEN(SUBSTITUTE(E84,".","")))=2,(F84),B83))) -> IMPERMEABILIZAÇAO E TRATAMENTOS | C84: =PROPER(IF(OR(F84="",C83="PAVIMENTO"),"",IF(AND(IF(E84="","",LEN(E84)-LEN(SUBSTITUTE(E84,".","")))=3,H84=""),F84,C83))) -> 10_7º Pav. - Tipo | D84: =IF(H84="","","SERVIÇO") -> SERVIÇO | E84: 1.1.10.5 | F84: PAREDE: Sistema 2.5.3: Membrana de polímero acrílico com cimento e fibras sintéticas | Revestimento bicomponente à base de polímeros acrílicos com adição de cimento e fibras sintéticas (3,0 kg/m²) - BANHEIRO | G84: m² | H84: 27.06 | I84: =_xlfn.XLOOKUP($F84,$M$66:$M$115,$N$66:$N$115) -> 2.5.3 | J84: =TRIM(RIGHT(SUBSTITUTE(SUBSTITUTE(F84,CHAR(10)," ")," ",REPT(" ",100)),100)) -> BANHEIRO | K84: =TRIM(LEFT(SUBSTITUTE(SUBSTITUTE(F84,CHAR(10)," ")," ",REPT(" ",100)),100)) -> PAREDE: | M84: PAREDE: Sistema 4.9.2: Manta asfáltica 4+4mm aderida com asfalto oxidado modificado + Argamassa polimérica para impermeabilização | Primer asfáltico à base d'água (0,4 L/m²) + Asfalto oxidado modificado (2,5 kg/m²) + Manta asfáltica AA 3mm Tipo III Classe B + Asfalto oxidado modificado (2,5 kg/m²) + Manta asfáltica AA 4mm Tipo III Classe B + Argamassa polimérica para impermeabilização sobre a proteção mecânica (2,0 kg/m²) - PISCINA | N84: 4.9.2 | O84: =Q32 -> 99.14 | Q84: =TRIM(RIGHT(SUBSTITUTE(SUBSTITUTE(M84,CHAR(10)," ")," ",REPT(" ",100)),100)) -> PISCINA
A85: =_xlfn.XLOOKUP(C85,$T$13:$T$58,$U$13:$U$58,"") -> Tipo x8 | B85: =UPPER(IF(F85="","",IF(IF(E85="","",LEN(E85)-LEN(SUBSTITUTE(E85,".","")))=2,(F85),B84))) -> IMPERMEABILIZAÇAO E TRATAMENTOS | C85: =PROPER(IF(OR(F85="",C84="PAVIMENTO"),"",IF(AND(IF(E85="","",LEN(E85)-LEN(SUBSTITUTE(E85,".","")))=3,H85=""),F85,C84))) -> 10_7º Pav. - Tipo | D85: =IF(H85="","","SERVIÇO") -> SERVIÇO | E85: 1.1.10.6 | F85: PISO: Sistema 2.5.3: Membrana de polímero acrílico com cimento e fibras sintéticas | Revestimento bicomponente à base de polímeros acrílicos com adição de cimento e fibras sintéticas (3,0 kg/m²)+ Tela de poliéster nos pontos críticos - BANHEIRO | G85: m² | H85: 16.05 | I85: =_xlfn.XLOOKUP($F85,$M$66:$M$115,$N$66:$N$115) -> 2.5.3 | J85: =TRIM(RIGHT(SUBSTITUTE(SUBSTITUTE(F85,CHAR(10)," ")," ",REPT(" ",100)),100)) -> BANHEIRO | K85: =TRIM(LEFT(SUBSTITUTE(SUBSTITUTE(F85,CHAR(10)," ")," ",REPT(" ",100)),100)) -> PISO: | M85: PISO: Sistema 4.9.2: Manta asfáltica 4+4mm aderida com asfalto oxidado modificado + Argamassa polimérica para impermeabilização | Primer asfáltico à base d'água (0,4 L/m²) + Asfalto oxidado modificado (2,5 kg/m²) + Manta asfáltica AA 3mm Tipo III Classe B + Asfalto oxidado modificado (2,5 kg/m²) + Manta asfáltica AA 4mm Tipo III Classe B + Argamassa polimérica para impermeabilização sobre a proteção mecânica (2,0 kg/m²) - PISCINA | N85: 4.9.2 | O85: =Q33 -> 141.99 | Q85: =TRIM(RIGHT(SUBSTITUTE(SUBSTITUTE(M85,CHAR(10)," ")," ",REPT(" ",100)),100)) -> PISCINA
A86: =_xlfn.XLOOKUP(C86,$T$13:$T$58,$U$13:$U$58,"") -> Tipo x8 | B86: =UPPER(IF(F86="","",IF(IF(E86="","",LEN(E86)-LEN(SUBSTITUTE(E86,".","")))=2,(F86),B85))) -> IMPERMEABILIZAÇAO E TRATAMENTOS | C86: =PROPER(IF(OR(F86="",C85="PAVIMENTO"),"",IF(AND(IF(E86="","",LEN(E86)-LEN(SUBSTITUTE(E86,".","")))=3,H86=""),F86,C85))) -> 10_7º Pav. - Tipo | D86: =IF(H86="","","SERVIÇO") -> SERVIÇO | E86: 1.1.10.7 | F86: PAREDE: Sistema 2.5.3: Membrana de polímero acrílico com cimento e fibras sintéticas | Revestimento bicomponente à base de polímeros acrílicos com adição de cimento e fibras sintéticas (3,0 kg/m²) - BOX BANHEIRO | G86: m² | H86: 24.28 | I86: =_xlfn.XLOOKUP($F86,$M$66:$M$115,$N$66:$N$115) -> 2.5.3 | J86: =TRIM(RIGHT(SUBSTITUTE(SUBSTITUTE(F86,CHAR(10)," ")," ",REPT(" ",100)),100)) -> BANHEIRO | K86: =TRIM(LEFT(SUBSTITUTE(SUBSTITUTE(F86,CHAR(10)," ")," ",REPT(" ",100)),100)) -> PAREDE: | M86: PAREDE: Sistema 7.1.6: Argamassa impermeabilizante sem cimento - MK-FEN 30 (F) | Argamassa não cimentícia com agentes incorporadores de ar (8,0 kg/m²) + Tela de poliéster nos pontos críticos - SAUNA | N86: 7.1.6 | O86: =Q34 -> 42.22 | Q86: =TRIM(RIGHT(SUBSTITUTE(SUBSTITUTE(M86,CHAR(10)," ")," ",REPT(" ",100)),100)) -> SAUNA
A87: =_xlfn.XLOOKUP(C87,$T$13:$T$58,$U$13:$U$58,"") -> Tipo x8 | B87: =UPPER(IF(F87="","",IF(IF(E87="","",LEN(E87)-LEN(SUBSTITUTE(E87,".","")))=2,(F87),B86))) -> IMPERMEABILIZAÇAO E TRATAMENTOS | C87: =PROPER(IF(OR(F87="",C86="PAVIMENTO"),"",IF(AND(IF(E87="","",LEN(E87)-LEN(SUBSTITUTE(E87,".","")))=3,H87=""),F87,C86))) -> 10_7º Pav. - Tipo | D87: =IF(H87="","","SERVIÇO") -> SERVIÇO | E87: 1.1.10.8 | F87: PISO: Sistema 2.5.3: Membrana de polímero acrílico com cimento e fibras sintéticas | Revestimento bicomponente à base de polímeros acrílicos com adição de cimento e fibras sintéticas (3,0 kg/m²)+ Tela de poliéster nos pontos críticos - BOX BANHEIRO | G87: m² | H87: 8.1 | I87: =_xlfn.XLOOKUP($F87,$M$66:$M$115,$N$66:$N$115) -> 2.5.3 | J87: =TRIM(RIGHT(SUBSTITUTE(SUBSTITUTE(F87,CHAR(10)," ")," ",REPT(" ",100)),100)) -> BANHEIRO | K87: =TRIM(LEFT(SUBSTITUTE(SUBSTITUTE(F87,CHAR(10)," ")," ",REPT(" ",100)),100)) -> PISO: | M87: PISO: Sistema 7.1.6: Argamassa impermeabilizante sem cimento - MK-FEN 30 (F) | Argamassa não cimentícia com agentes incorporadores de ar (8,0 kg/m²) + Tela de poliéster nos pontos críticos - SAUNA | N87: 7.1.6 | O87: =Q35 -> 5.81 | Q87: =TRIM(RIGHT(SUBSTITUTE(SUBSTITUTE(M87,CHAR(10)," ")," ",REPT(" ",100)),100)) -> SAUNA
A88: =_xlfn.XLOOKUP(C88,$T$13:$T$58,$U$13:$U$58,"") -> Tipo x8 | B88: =UPPER(IF(F88="","",IF(IF(E88="","",LEN(E88)-LEN(SUBSTITUTE(E88,".","")))=2,(F88),B87))) -> IMPERMEABILIZAÇAO E TRATAMENTOS | C88: =PROPER(IF(OR(F88="",C87="PAVIMENTO"),"",IF(AND(IF(E88="","",LEN(E88)-LEN(SUBSTITUTE(E88,".","")))=3,H88=""),F88,C87))) -> 10_7º Pav. - Tipo | D88: =IF(H88="","","SERVIÇO") -> SERVIÇO | E88: 1.1.10.9 | F88: PAREDE: Sistema 2.5.3: Membrana de polímero acrílico com cimento e fibras sintéticas | Revestimento bicomponente à base de polímeros acrílicos com adição de cimento e fibras sintéticas (3,0 kg/m²) - ESQUADRIA | G88: m² | H88: 34.18 | I88: =_xlfn.XLOOKUP($F88,$M$66:$M$115,$N$66:$N$115) -> 2.5.3 | J88: =TRIM(RIGHT(SUBSTITUTE(SUBSTITUTE(F88,CHAR(10)," ")," ",REPT(" ",100)),100)) -> ESQUADRIA | K88: =TRIM(LEFT(SUBSTITUTE(SUBSTITUTE(F88,CHAR(10)," ")," ",REPT(" ",100)),100)) -> PAREDE: | M88: PAREDE: Sistema 4.2.4: Manta asfáltica 4mm aderida com asfalto oxidado modificado | Primer asfáltico à base d'água (0,4 L/m²) + Asfalto oxidado modificado (2,5 kg/m²) + Manta asfáltica AA 4mm Tipo III Classe B + Banho de asfalto oxidado modificado (2,5 kg/m²) - ESPAÇO CROSSFIT | N88: 4.2.4 | O88: =Q36 -> 32.09 | Q88: =TRIM(RIGHT(SUBSTITUTE(SUBSTITUTE(M88,CHAR(10)," ")," ",REPT(" ",100)),100)) -> CROSSFIT
A89: =_xlfn.XLOOKUP(C89,$T$13:$T$58,$U$13:$U$58,"") -> Tipo x8 | B89: =UPPER(IF(F89="","",IF(IF(E89="","",LEN(E89)-LEN(SUBSTITUTE(E89,".","")))=2,(F89),B88))) -> IMPERMEABILIZAÇAO E TRATAMENTOS | C89: =PROPER(IF(OR(F89="",C88="PAVIMENTO"),"",IF(AND(IF(E89="","",LEN(E89)-LEN(SUBSTITUTE(E89,".","")))=3,H89=""),F89,C88))) -> 10_7º Pav. - Tipo | D89: =IF(H89="","","SERVIÇO") -> SERVIÇO | E89: 1.1.10.10 | F89: PISO: Sistema 2.5.3: Membrana de polímero acrílico com cimento e fibras sintéticas | Revestimento bicomponente à base de polímeros acrílicos com adição de cimento e fibras sintéticas (3,0 kg/m²)+ Tela de poliéster nos pontos críticos - ESQUADRIA | G89: m² | H89: 20.68 | I89: =_xlfn.XLOOKUP($F89,$M$66:$M$115,$N$66:$N$115) -> 2.5.3 | J89: =TRIM(RIGHT(SUBSTITUTE(SUBSTITUTE(F89,CHAR(10)," ")," ",REPT(" ",100)),100)) -> ESQUADRIA | K89: =TRIM(LEFT(SUBSTITUTE(SUBSTITUTE(F89,CHAR(10)," ")," ",REPT(" ",100)),100)) -> PISO: | M89: PISO: Sistema 4.2.4: Manta asfáltica 4mm aderida com asfalto oxidado modificado | Primer asfáltico à base d'água (0,4 L/m²) - ESPAÇO CROSSFIT | N89: 4.2.4 | O89: =Q37 -> 87.98 | Q89: =TRIM(RIGHT(SUBSTITUTE(SUBSTITUTE(M89,CHAR(10)," ")," ",REPT(" ",100)),100)) -> CROSSFIT
A90: =_xlfn.XLOOKUP(C90,$T$13:$T$58,$U$13:$U$58,"") -> Tipo x8 | B90: =UPPER(IF(F90="","",IF(IF(E90="","",LEN(E90)-LEN(SUBSTITUTE(E90,".","")))=2,(F90),B89))) -> IMPERMEABILIZAÇAO E TRATAMENTOS | C90: =PROPER(IF(OR(F90="",C89="PAVIMENTO"),"",IF(AND(IF(E90="","",LEN(E90)-LEN(SUBSTITUTE(E90,".","")))=3,H90=""),F90,C89))) -> 10_7º Pav. - Tipo | D90: =IF(H90="","","SERVIÇO") -> SERVIÇO | E90: 1.1.10.11 | F90: PISO: Sistema 7.1.6: Argamassa impermeabilizante sem cimento - MK-FEN 30 (F) | Argamassa não cimentícia com agentes incorporadores de ar (8,0 kg/m²) + Tela de poliéster nos pontos críticos - MOLDURA FACHADA | G90: m² | H90: 40.06 | I90: =_xlfn.XLOOKUP($F90,$M$66:$M$115,$N$66:$N$115) -> 7.1.6 | J90: =TRIM(RIGHT(SUBSTITUTE(SUBSTITUTE(F90,CHAR(10)," ")," ",REPT(" ",100)),100)) -> FACHADA | K90: =TRIM(LEFT(SUBSTITUTE(SUBSTITUTE(F90,CHAR(10)," ")," ",REPT(" ",100)),100)) -> PISO: | M90: PAREDE: Sistema 2.5.3: Membrana de polímero acrílico com cimento e fibras sintéticas | Revestimento bicomponente à base de polímeros acrílicos com adição de cimento e fibras sintéticas (3,0 kg/m²)+ Tela de poliéster nos pontos críticos - ÁREA DE SERVIÇO | N90: 2.5.3 | O90: =Q38 -> 382.16 | Q90: =TRIM(RIGHT(SUBSTITUTE(SUBSTITUTE(M90,CHAR(10)," ")," ",REPT(" ",100)),100)) -> SERVIÇO
A91: =_xlfn.XLOOKUP(C91,$T$13:$T$58,$U$13:$U$58,"") -> Tipo x8 | B91: =UPPER(IF(F91="","",IF(IF(E91="","",LEN(E91)-LEN(SUBSTITUTE(E91,".","")))=2,(F91),B90))) -> IMPERMEABILIZAÇAO E TRATAMENTOS | C91: =PROPER(IF(OR(F91="",C90="PAVIMENTO"),"",IF(AND(IF(E91="","",LEN(E91)-LEN(SUBSTITUTE(E91,".","")))=3,H91=""),F91,C90))) -> 11_8º Pav. - Tipo | D91: =IF(H91="","","SERVIÇO") | E91: 1.1.11. | F91: 11_8º PAV. - TIPO | I91: =IF(C91=F91,SUMIFS($H$12:$H$63964,$C$12:$C$63964,C91),"") -> 171.42 | M91: PISO: Sistema 2.5.3: Membrana de polímero acrílico com cimento e fibras sintéticas | Revestimento bicomponente à base de polímeros acrílicos com adição de cimento e fibras sintéticas (3,0 kg/m²)+ Tela de poliéster nos pontos críticos - ÁREA DE SERVIÇO | N91: 2.5.3 | O91: =Q39 -> 164.15 | Q91: =TRIM(RIGHT(SUBSTITUTE(SUBSTITUTE(M91,CHAR(10)," ")," ",REPT(" ",100)),100)) -> SERVIÇO
A92: =_xlfn.XLOOKUP(C92,$T$13:$T$58,$U$13:$U$58,"") -> Tipo x8 | B92: =UPPER(IF(F92="","",IF(IF(E92="","",LEN(E92)-LEN(SUBSTITUTE(E92,".","")))=2,(F92),B91))) -> IMPERMEABILIZAÇAO E TRATAMENTOS | C92: =PROPER(IF(OR(F92="",C91="PAVIMENTO"),"",IF(AND(IF(E92="","",LEN(E92)-LEN(SUBSTITUTE(E92,".","")))=3,H92=""),F92,C91))) -> 11_8º Pav. - Tipo | D92: =IF(H92="","","SERVIÇO") -> SERVIÇO | E92: 1.1.11.1 | F92: PAREDE: Sistema 2.5.3: Membrana de polímero acrílico com cimento e fibras sintéticas - ÁREA DE SERVIÇO | G92: m² | H92: 16.83 | I92: 2.5.3 | J92: =TRIM(RIGHT(SUBSTITUTE(SUBSTITUTE(F92,CHAR(10)," ")," ",REPT(" ",100)),100)) -> SERVIÇO | K92: =TRIM(LEFT(SUBSTITUTE(SUBSTITUTE(F92,CHAR(10)," ")," ",REPT(" ",100)),100)) -> PAREDE: | M92: PAREDE: Sistema 7.1.6: Argamassa impermeabilizante sem cimento - MK-FEN 30 (F) | Argamassa não cimentícia com agentes incorporadores de ar (8,0 kg/m²) + Tela de poliéster nos pontos críticos - ÁREA TÉCNICA | N92: 7.1.6 | O92: =Q40 -> 129.95 | Q92: =TRIM(RIGHT(SUBSTITUTE(SUBSTITUTE(M92,CHAR(10)," ")," ",REPT(" ",100)),100)) -> TÉCNICA
A93: =_xlfn.XLOOKUP(C93,$T$13:$T$58,$U$13:$U$58,"") -> Tipo x8 | B93: =UPPER(IF(F93="","",IF(IF(E93="","",LEN(E93)-LEN(SUBSTITUTE(E93,".","")))=2,(F93),B92))) -> IMPERMEABILIZAÇAO E TRATAMENTOS | C93: =PROPER(IF(OR(F93="",C92="PAVIMENTO"),"",IF(AND(IF(E93="","",LEN(E93)-LEN(SUBSTITUTE(E93,".","")))=3,H93=""),F93,C92))) -> 11_8º Pav. - Tipo | D93: =IF(H93="","","SERVIÇO") -> SERVIÇO | E93: 1.1.11.2 | F93: PISO: Sistema 2.5.3: Membrana de polímero acrílico com cimento e fibras sintéticas | Revestimento bicomponente à base de polímeros acrílicos com adição de cimento e fibras sintéticas (3,0 kg/m²)+ Tela de poliéster nos pontos críticos - ÁREA DE SERVIÇO | G93: m² | H93: 6.93 | I93: =_xlfn.XLOOKUP($F93,$M$66:$M$115,$N$66:$N$115) -> 2.5.3 | J93: =TRIM(RIGHT(SUBSTITUTE(SUBSTITUTE(F93,CHAR(10)," ")," ",REPT(" ",100)),100)) -> SERVIÇO | K93: =TRIM(LEFT(SUBSTITUTE(SUBSTITUTE(F93,CHAR(10)," ")," ",REPT(" ",100)),100)) -> PISO: | M93: PISO: Sistema 7.1.6: Argamassa impermeabilizante sem cimento - MK-FEN 30 (F) | Argamassa não cimentícia com agentes incorporadores de ar (8,0 kg/m²) + Tela de poliéster nos pontos críticos - ÁREA TÉCNICA | N93: 7.1.6 | O93: =Q41 -> 225.33 | Q93: =TRIM(RIGHT(SUBSTITUTE(SUBSTITUTE(M93,CHAR(10)," ")," ",REPT(" ",100)),100)) -> TÉCNICA
A94: =_xlfn.XLOOKUP(C94,$T$13:$T$58,$U$13:$U$58,"") -> Tipo x8 | B94: =UPPER(IF(F94="","",IF(IF(E94="","",LEN(E94)-LEN(SUBSTITUTE(E94,".","")))=2,(F94),B93))) -> IMPERMEABILIZAÇAO E TRATAMENTOS | C94: =PROPER(IF(OR(F94="",C93="PAVIMENTO"),"",IF(AND(IF(E94="","",LEN(E94)-LEN(SUBSTITUTE(E94,".","")))=3,H94=""),F94,C93))) -> 11_8º Pav. - Tipo | D94: =IF(H94="","","SERVIÇO") -> SERVIÇO | E94: 1.1.11.3 | F94: PAREDE: Sistema 7.1.6: Argamassa impermeabilizante sem cimento - MK-FEN 30 (F) | Argamassa não cimentícia com agentes incorporadores de ar (8,0 kg/m²) + Tela de poliéster nos pontos críticos - ÁREA TÉCNICA | G94: m² | H94: 6.51 | I94: =_xlfn.XLOOKUP($F94,$M$66:$M$115,$N$66:$N$115) -> 7.1.6 | J94: =TRIM(RIGHT(SUBSTITUTE(SUBSTITUTE(F94,CHAR(10)," ")," ",REPT(" ",100)),100)) -> TÉCNICA | K94: =TRIM(LEFT(SUBSTITUTE(SUBSTITUTE(F94,CHAR(10)," ")," ",REPT(" ",100)),100)) -> PAREDE: | M94: PAREDE: Sistema 2.5.3: Membrana de polímero acrílico com cimento e fibras sintéticas | Revestimento bicomponente à base de polímeros acrílicos com adição de cimento e fibras sintéticas (3,0 kg/m²) - BANHEIRO | N94: 2.5.3 | O94: =Q42 -> 783.34 | Q94: =TRIM(RIGHT(SUBSTITUTE(SUBSTITUTE(M94,CHAR(10)," ")," ",REPT(" ",100)),100)) -> BANHEIRO
A95: =_xlfn.XLOOKUP(C95,$T$13:$T$58,$U$13:$U$58,"") -> Tipo x8 | B95: =UPPER(IF(F95="","",IF(IF(E95="","",LEN(E95)-LEN(SUBSTITUTE(E95,".","")))=2,(F95),B94))) -> IMPERMEABILIZAÇAO E TRATAMENTOS | C95: =PROPER(IF(OR(F95="",C94="PAVIMENTO"),"",IF(AND(IF(E95="","",LEN(E95)-LEN(SUBSTITUTE(E95,".","")))=3,H95=""),F95,C94))) -> 11_8º Pav. - Tipo | D95: =IF(H95="","","SERVIÇO") -> SERVIÇO | E95: 1.1.11.4 | F95: PISO: Sistema 7.1.6: Argamassa impermeabilizante sem cimento - MK-FEN 30 (F) | Argamassa não cimentícia com agentes incorporadores de ar (8,0 kg/m²) + Tela de poliéster nos pontos críticos - ÁREA TÉCNICA | G95: m² | H95: 10.8 | I95: =_xlfn.XLOOKUP($F95,$M$66:$M$115,$N$66:$N$115) -> 7.1.6 | J95: =TRIM(RIGHT(SUBSTITUTE(SUBSTITUTE(F95,CHAR(10)," ")," ",REPT(" ",100)),100)) -> TÉCNICA | K95: =TRIM(LEFT(SUBSTITUTE(SUBSTITUTE(F95,CHAR(10)," ")," ",REPT(" ",100)),100)) -> PISO: | M95: PISO: Sistema 2.5.3: Membrana de polímero acrílico com cimento e fibras sintéticas | Revestimento bicomponente à base de polímeros acrílicos com adição de cimento e fibras sintéticas (3,0 kg/m²)+ Tela de poliéster nos pontos críticos - BANHEIRO | N95: 2.5.3 | O95: =Q43 -> 506 | Q95: =TRIM(RIGHT(SUBSTITUTE(SUBSTITUTE(M95,CHAR(10)," ")," ",REPT(" ",100)),100)) -> BANHEIRO
A96: =_xlfn.XLOOKUP(C96,$T$13:$T$58,$U$13:$U$58,"") -> Tipo x8 | B96: =UPPER(IF(F96="","",IF(IF(E96="","",LEN(E96)-LEN(SUBSTITUTE(E96,".","")))=2,(F96),B95))) -> IMPERMEABILIZAÇAO E TRATAMENTOS | C96: =PROPER(IF(OR(F96="",C95="PAVIMENTO"),"",IF(AND(IF(E96="","",LEN(E96)-LEN(SUBSTITUTE(E96,".","")))=3,H96=""),F96,C95))) -> 11_8º Pav. - Tipo | D96: =IF(H96="","","SERVIÇO") -> SERVIÇO | E96: 1.1.11.5 | F96: PAREDE: Sistema 2.5.3: Membrana de polímero acrílico com cimento e fibras sintéticas | Revestimento bicomponente à base de polímeros acrílicos com adição de cimento e fibras sintéticas (3,0 kg/m²) - BANHEIRO | G96: m² | H96: 27.06 | I96: =_xlfn.XLOOKUP($F96,$M$66:$M$115,$N$66:$N$115) -> 2.5.3 | J96: =TRIM(RIGHT(SUBSTITUTE(SUBSTITUTE(F96,CHAR(10)," ")," ",REPT(" ",100)),100)) -> BANHEIRO | K96: =TRIM(LEFT(SUBSTITUTE(SUBSTITUTE(F96,CHAR(10)," ")," ",REPT(" ",100)),100)) -> PAREDE: | M96: PAREDE: Sistema 2.5.3: Membrana de polímero acrílico com cimento e fibras sintéticas | Revestimento bicomponente à base de polímeros acrílicos com adição de cimento e fibras sintéticas (3,0 kg/m²) - BOX BANHEIRO | N96: 2.5.3 | O96: =Q44 -> 843.86 | Q96: =TRIM(RIGHT(SUBSTITUTE(SUBSTITUTE(M96,CHAR(10)," ")," ",REPT(" ",100)),100)) -> BANHEIRO
A97: =_xlfn.XLOOKUP(C97,$T$13:$T$58,$U$13:$U$58,"") -> Tipo x8 | B97: =UPPER(IF(F97="","",IF(IF(E97="","",LEN(E97)-LEN(SUBSTITUTE(E97,".","")))=2,(F97),B96))) -> IMPERMEABILIZAÇAO E TRATAMENTOS | C97: =PROPER(IF(OR(F97="",C96="PAVIMENTO"),"",IF(AND(IF(E97="","",LEN(E97)-LEN(SUBSTITUTE(E97,".","")))=3,H97=""),F97,C96))) -> 11_8º Pav. - Tipo | D97: =IF(H97="","","SERVIÇO") -> SERVIÇO | E97: 1.1.11.6 | F97: PISO: Sistema 2.5.3: Membrana de polímero acrílico com cimento e fibras sintéticas | Revestimento bicomponente à base de polímeros acrílicos com adição de cimento e fibras sintéticas (3,0 kg/m²)+ Tela de poliéster nos pontos críticos - BANHEIRO | G97: m² | H97: 16.05 | I97: =_xlfn.XLOOKUP($F97,$M$66:$M$115,$N$66:$N$115) -> 2.5.3 | J97: =TRIM(RIGHT(SUBSTITUTE(SUBSTITUTE(F97,CHAR(10)," ")," ",REPT(" ",100)),100)) -> BANHEIRO | K97: =TRIM(LEFT(SUBSTITUTE(SUBSTITUTE(F97,CHAR(10)," ")," ",REPT(" ",100)),100)) -> PISO: | M97: PISO: Sistema 2.5.3: Membrana de polímero acrílico com cimento e fibras sintéticas | Revestimento bicomponente à base de polímeros acrílicos com adição de cimento e fibras sintéticas (3,0 kg/m²)+ Tela de poliéster nos pontos críticos - BOX BANHEIRO | N97: 2.5.3 | O97: =Q45 -> 281.96 | Q97: =TRIM(RIGHT(SUBSTITUTE(SUBSTITUTE(M97,CHAR(10)," ")," ",REPT(" ",100)),100)) -> BANHEIRO
A98: =_xlfn.XLOOKUP(C98,$T$13:$T$58,$U$13:$U$58,"") -> Tipo x8 | B98: =UPPER(IF(F98="","",IF(IF(E98="","",LEN(E98)-LEN(SUBSTITUTE(E98,".","")))=2,(F98),B97))) -> IMPERMEABILIZAÇAO E TRATAMENTOS | C98: =PROPER(IF(OR(F98="",C97="PAVIMENTO"),"",IF(AND(IF(E98="","",LEN(E98)-LEN(SUBSTITUTE(E98,".","")))=3,H98=""),F98,C97))) -> 11_8º Pav. - Tipo | D98: =IF(H98="","","SERVIÇO") -> SERVIÇO | E98: 1.1.11.7 | F98: PAREDE: Sistema 2.5.3: Membrana de polímero acrílico com cimento e fibras sintéticas | Revestimento bicomponente à base de polímeros acrílicos com adição de cimento e fibras sintéticas (3,0 kg/m²) - BOX BANHEIRO | G98: m² | H98: 24.28 | I98: =_xlfn.XLOOKUP($F98,$M$66:$M$115,$N$66:$N$115) -> 2.5.3 | J98: =TRIM(RIGHT(SUBSTITUTE(SUBSTITUTE(F98,CHAR(10)," ")," ",REPT(" ",100)),100)) -> BANHEIRO | K98: =TRIM(LEFT(SUBSTITUTE(SUBSTITUTE(F98,CHAR(10)," ")," ",REPT(" ",100)),100)) -> PAREDE: | M98: PISO: Sistema 2.5.3: Membrana de polímero acrílico com cimento e fibras sintéticas | Revestimento bicomponente à base de polímeros acrílicos com adição de cimento e fibras sintéticas (3,0 kg/m²)+ Tela de poliéster nos pontos críticos - ESQUADRIA | N98: 2.5.3 | O98: =Q46 -> 632.34 | Q98: =TRIM(RIGHT(SUBSTITUTE(SUBSTITUTE(M98,CHAR(10)," ")," ",REPT(" ",100)),100)) -> ESQUADRIA
A99: =_xlfn.XLOOKUP(C99,$T$13:$T$58,$U$13:$U$58,"") -> Tipo x8 | B99: =UPPER(IF(F99="","",IF(IF(E99="","",LEN(E99)-LEN(SUBSTITUTE(E99,".","")))=2,(F99),B98))) -> IMPERMEABILIZAÇAO E TRATAMENTOS | C99: =PROPER(IF(OR(F99="",C98="PAVIMENTO"),"",IF(AND(IF(E99="","",LEN(E99)-LEN(SUBSTITUTE(E99,".","")))=3,H99=""),F99,C98))) -> 11_8º Pav. - Tipo | D99: =IF(H99="","","SERVIÇO") -> SERVIÇO | E99: 1.1.11.8 | F99: PISO: Sistema 2.5.3: Membrana de polímero acrílico com cimento e fibras sintéticas | Revestimento bicomponente à base de polímeros acrílicos com adição de cimento e fibras sintéticas (3,0 kg/m²)+ Tela de poliéster nos pontos críticos - BOX BANHEIRO | G99: m² | H99: 8.1 | I99: =_xlfn.XLOOKUP($F99,$M$66:$M$115,$N$66:$N$115) -> 2.5.3 | J99: =TRIM(RIGHT(SUBSTITUTE(SUBSTITUTE(F99,CHAR(10)," ")," ",REPT(" ",100)),100)) -> BANHEIRO | K99: =TRIM(LEFT(SUBSTITUTE(SUBSTITUTE(F99,CHAR(10)," ")," ",REPT(" ",100)),100)) -> PISO: | M99: PISO: Sistema 7.1.6: Argamassa impermeabilizante sem cimento - MK-FEN 30 (F) | Argamassa não cimentícia com agentes incorporadores de ar (8,0 kg/m²) + Tela de poliéster nos pontos críticos - MOLDURA FACHADA | N99: 7.1.6 | O99: =Q47 -> 394.55 | Q99: =TRIM(RIGHT(SUBSTITUTE(SUBSTITUTE(M99,CHAR(10)," ")," ",REPT(" ",100)),100)) -> FACHADA
A100: =_xlfn.XLOOKUP(C100,$T$13:$T$58,$U$13:$U$58,"") -> Tipo x8 | B100: =UPPER(IF(F100="","",IF(IF(E100="","",LEN(E100)-LEN(SUBSTITUTE(E100,".","")))=2,(F100),B99))) -> IMPERMEABILIZAÇAO E TRATAMENTOS | C100: =PROPER(IF(OR(F100="",C99="PAVIMENTO"),"",IF(AND(IF(E100="","",LEN(E100)-LEN(SUBSTITUTE(E100,".","")))=3,H100=""),F100,C99))) -> 11_8º Pav. - Tipo | D100: =IF(H100="","","SERVIÇO") -> SERVIÇO | E100: 1.1.11.9 | F100: PAREDE: Sistema 2.5.3: Membrana de polímero acrílico com cimento e fibras sintéticas | Revestimento bicomponente à base de polímeros acrílicos com adição de cimento e fibras sintéticas (3,0 kg/m²) - ESQUADRIA | G100: m² | H100: 34.18 | I100: =_xlfn.XLOOKUP($F100,$M$66:$M$115,$N$66:$N$115) -> 2.5.3 | J100: =TRIM(RIGHT(SUBSTITUTE(SUBSTITUTE(F100,CHAR(10)," ")," ",REPT(" ",100)),100)) -> ESQUADRIA | K100: =TRIM(LEFT(SUBSTITUTE(SUBSTITUTE(F100,CHAR(10)," ")," ",REPT(" ",100)),100)) -> PAREDE: | M100: PAREDE: Sistema 4.2.4: Manta asfáltica 4mm aderida com asfalto oxidado modificado | Primer asfáltico à base d'água (0,4 L/m²) + Asfalto oxidado modificado (2,5 kg/m²) + Manta asfáltica AA 4mmTipo III Classe B + Banho de asfalto oxidado modificado (2,5 kg/m²) - SACADA | N100: 4.2.4 | O100: =Q48 -> 48.01 | Q100: =TRIM(RIGHT(SUBSTITUTE(SUBSTITUTE(M100,CHAR(10)," ")," ",REPT(" ",100)),100)) -> SACADA
A101: =_xlfn.XLOOKUP(C101,$T$13:$T$58,$U$13:$U$58,"") -> Tipo x8 | B101: =UPPER(IF(F101="","",IF(IF(E101="","",LEN(E101)-LEN(SUBSTITUTE(E101,".","")))=2,(F101),B100))) -> IMPERMEABILIZAÇAO E TRATAMENTOS | C101: =PROPER(IF(OR(F101="",C100="PAVIMENTO"),"",IF(AND(IF(E101="","",LEN(E101)-LEN(SUBSTITUTE(E101,".","")))=3,H101=""),F101,C100))) -> 11_8º Pav. - Tipo | D101: =IF(H101="","","SERVIÇO") -> SERVIÇO | E101: 1.1.11.10 | F101: PISO: Sistema 2.5.3: Membrana de polímero acrílico com cimento e fibras sintéticas | Revestimento bicomponente à base de polímeros acrílicos com adição de cimento e fibras sintéticas (3,0 kg/m²)+ Tela de poliéster nos pontos críticos - ESQUADRIA | G101: m² | H101: 20.68 | I101: =_xlfn.XLOOKUP($F101,$M$66:$M$115,$N$66:$N$115) -> 2.5.3 | J101: =TRIM(RIGHT(SUBSTITUTE(SUBSTITUTE(F101,CHAR(10)," ")," ",REPT(" ",100)),100)) -> ESQUADRIA | K101: =TRIM(LEFT(SUBSTITUTE(SUBSTITUTE(F101,CHAR(10)," ")," ",REPT(" ",100)),100)) -> PISO: | M101: PISO: Sistema 4.2.4: Manta asfáltica 4mm aderida com asfalto oxidado modificado | Primer asfáltico à base d'água (0,4 L/m²) + Asfalto oxidado modificado (2,5 kg/m²) + Manta asfáltica AA 4mmTipo III Classe B + Banho de asfalto oxidado modificado (2,5 kg/m²) - SACADA | N101: 4.2.4 | O101: =Q49 -> 172.59 | Q101: =TRIM(RIGHT(SUBSTITUTE(SUBSTITUTE(M101,CHAR(10)," ")," ",REPT(" ",100)),100)) -> SACADA
A102: =_xlfn.XLOOKUP(C102,$T$13:$T$58,$U$13:$U$58,"") -> Tipo x8 | B102: =UPPER(IF(F102="","",IF(IF(E102="","",LEN(E102)-LEN(SUBSTITUTE(E102,".","")))=2,(F102),B101))) -> IMPERMEABILIZAÇAO E TRATAMENTOS | C102: =PROPER(IF(OR(F102="",C101="PAVIMENTO"),"",IF(AND(IF(E102="","",LEN(E102)-LEN(SUBSTITUTE(E102,".","")))=3,H102=""),F102,C101))) -> 12_9º Pav. - Tipo | D102: =IF(H102="","","SERVIÇO") | E102: 1.1.12. | F102: 12_9º PAV. - TIPO | I102: =IF(C102=F102,SUMIFS($H$12:$H$63964,$C$12:$C$63964,C102),"") -> 211.48 | M102: PISO: Sistema 7.1.6: Argamassa impermeabilizante sem cimento - MK-FEN 30 (F) | Argamassa não cimentícia com agentes incorporadores de ar (8,0 kg/m²) + Tela de poliéster nos pontos críticos - CALHA E RUFO | N102: 7.1.6 | O102: =Q50 -> 27.15 | Q102: =TRIM(RIGHT(SUBSTITUTE(SUBSTITUTE(M102,CHAR(10)," ")," ",REPT(" ",100)),100)) -> RUFO
...

Sheet Ger_Executivo_Manual
H4: PROJETO: | I4: Electra Towers | O4: REVISÃO: | P4: DATA
H5: EMPRESA: | I5: Thozen | O5: R00
A6: Unidade Construtiva | B6: Célula Construtiva | C6: Etapa | D6: Subetapa | E6: Serviço | G6: GERENCIAMENTO EXECUTIVO
A7: 0 | B7: 0 | C7: 0 | D7: 0 | E7: 0 | G7: EAP | H7: NIVEL | I7: Item | J7: Descrição | K7: Unidade | L7: Quant. | M7: Preço un | N7: Total | O7: Considerações | P7: Situação
A8: 0 | B8: 1 | C8: 0 | D8: 0 | E8: 0 | H8: CÉLULA CONSTRUTIVA | I8: 01 | J8: MOVIMENTAÇÃO DE TERRA
A9: 0 | B9: 1 | C9: 1 | D9: 0 | E9: 0 | H9: ETAPA | I9: 01.001 | J9: DEMOLIÇÕES, LIMPEZA DE TERRENO E LOCAÇÃO DE OBRA | N9: 26235.314 | O9: 1.5663183
A10: 0 | B10: 1 | C10: 1 | D10: 1 | E10: 0 | H10: SUBETAPA | I10: 01.001.001 | J10: Locação e gabarito de obra | N10: 26235.314 | O10: 1.5663183
A11: 0 | B11: 1 | C11: 1 | D11: 1 | E11: 1 | G11: MOVIMENTAÇÃO DE TERRA | H11: SERVIÇO | I11: 01.001.001.001 | J11: Locação da obra | K11: m2 | N11: 26235.314 | P11: Pendente
A12: 0 | B12: 1 | C12: 2 | D12: 0 | E12: 1 | H12: ETAPA | I12: 01.002 | J12: SERVIÇOS PRELIMINARES
A13: 0 | B13: 1 | C13: 2 | D13: 1 | E13: 0 | H13: SUBETAPA | I13: 01.002.001 | J13: Limpeza Permanente e Remoção entulho
A14: 0 | B14: 1 | C14: 2 | D14: 1 | E14: 1 | G14: MOVIMENTAÇÃO DE TERRA | H14: SERVIÇO | I14: 01.002.001.001 | J14: Limpeza da camada vegetal | K14: m2 | P14: Pendente
A15: 0 | B15: 1 | C15: 2 | D15: 1 | E15: 2 | G15: MOVIMENTAÇÃO DE TERRA | H15: SERVIÇO | I15: 01.002.001.002 | J15: Remoção de entulhos e resíduos | P15: Pendente
A16: 0 | B16: 1 | C16: 2 | D16: 2 | E16: 0 | H16: SUBETAPA | I16: 01.002.002 | J16: Mão de Obra de Canteiro
A17: 0 | B17: 1 | C17: 2 | D17: 2 | E17: 1 | G17: MOVIMENTAÇÃO DE TERRA | H17: SERVIÇO | I17: 01.002.002.001 | J17: Mão de Obra de Canteiro | K17: vb | P17: Pendente
A18: 0 | B18: 1 | C18: 3 | D18: 0 | E18: 1 | H18: ETAPA | I18: 01.003 | J18: SERVIÇOS DE TERRAPLANAGEM | N18: 271126.19 | O18: 16.186957
A19: 0 | B19: 1 | C19: 3 | D19: 1 | E19: 0 | H19: SUBETAPA | I19: 01.003.001 | J19: Mao de obra - movimentações de terra | N19: 271126.19 | O19: 16.186957
A20: 0 | B20: 1 | C20: 3 | D20: 1 | E20: 1 | G20: MOVIMENTAÇÃO DE TERRA | H20: SERVIÇO | I20: 01.003.001.001 | J20: Mão de obra movimentação de terra | K20: vb | N20: 233000 | P20: Pendente
A21: 0 | B21: 1 | C21: 4 | D21: 0 | E21: 2 | H21: ETAPA | I21: 01.004 | J21: SERVIÇO DE DRENAGEM | N21: 80000 | O21: 4.7762135
A22: 0 | B22: 1 | C22: 4 | D22: 1 | E22: 0 | H22: SUBETAPA | I22: 01.004.001 | J22: Drenagem | N22: 80000 | O22: 4.7762135
A23: 0 | B23: 1 | C23: 4 | D23: 1 | E23: 1 | G23: MOVIMENTAÇÃO DE TERRA | H23: SERVIÇO | I23: 01.004.001.001 | J23: Rebaixamento de Lençol freático | K23: vb | N23: 80000 | P23: Pendente
A24: 0 | B24: 2 | C24: 0 | D24: 1 | E24: 1 | H24: CÉLULA CONSTRUTIVA | I24: 02 | J24: CONTENÇÃO | N24: 772006.63 | O24: 46.090856
A25: 0 | B25: 2 | C25: 1 | D25: 0 | E25: 1 | H25: ETAPA | I25: 02.001 | J25: MURETA GUIA | N25: 18739.389 | O25: 1.1187915
A26: 0 | B26: 2 | C26: 1 | D26: 1 | E26: 0 | H26: SUBETAPA | I26: 02.001.001 | J26: Forma | N26: 6673.9436 | O26: 0.39845225
A27: 0 | B27: 2 | C27: 1 | D27: 1 | E27: 1 | G27: CONTENÇÃO | H27: SERVIÇO | I27: 02.001.001.001 | J27: Forma para infraestrutura em Tábuas de Madeira Serrada 2x reaproveitamento | K27: m2 | L27: 111.3136 | M27: 59.956229 | N27: 6673.9436 | P27: Pendente
A28: 0 | B28: 2 | C28: 1 | D28: 2 | E28: 0 | H28: SUBETAPA | I28: 02.001.002 | J28: Armadura | N28: 4318.7306 | O28: 0.25783974
A29: 0 | B29: 2 | C29: 1 | D29: 2 | E29: 1 | G29: CONTENÇÃO | H29: SERVIÇO | I29: 02.001.002.001 | J29: Armação aço CA-50 ø 6,3mm para Contenções (corte e dobra em obra) | K29: un | L29: 670.32 | M29: 6.0795674 | N29: 4075.2556 | P29: Pendente
A30: 0 | B30: 2 | C30: 1 | D30: 2 | E30: 2 | G30: CONTENÇÃO | H30: SERVIÇO | I30: 02.001.002.002 | J30: Armação aço CA-50 ø 12,5mm para Contenções (corte e dobra em obra) | K30: un | L30: 41.6016 | M30: 5.8525391 | N30: 243.47499 | P30: Pendente
A31: 0 | B31: 2 | C31: 1 | D31: 3 | E31: 0 | H31: SUBETAPA | I31: 02.001.003 | J31: Concreto | N31: 7746.7147 | O31: 0.46249954
A32: 0 | B32: 2 | C32: 1 | D32: 3 | E32: 1 | G32: CONTENÇÃO | H32: SERVIÇO | I32: 02.001.003.001 | J32: Concreto Usinado bombeável 50MPa para infraestrutura- incluindo serviço de bombeamento | K32: m3 | L32: 11.390452 | M32: 680.106 | N32: 7746.7147 | P32: Pendente
A33: 0 | B33: 2 | C33: 2 | D33: 0 | E33: 1 | H33: ETAPA | I33: 02.002 | J33: LAMELAS | PAREDE DIAFRAGMA | N33: 331865.23 | O33: 19.81324
A34: 0 | B34: 2 | C34: 2 | D34: 1 | E34: 0 | H34: SUBETAPA | I34: 02.002.001 | J34: Armadura | N34: 155967.97 | O34: 9.3117038
A35: 0 | B35: 2 | C35: 2 | D35: 1 | E35: 1 | G35: CONTENÇÃO | H35: SERVIÇO | I35: 02.002.001.001 | J35: Armação aço CA-50 ø 6,3mm para Contenções (corte e dobra em Indústria) | K35: un | L35: 2282 | M35: 8.964145 | N35: 20456.179 | P35: Pendente
A36: 0 | B36: 2 | C36: 2 | D36: 1 | E36: 2 | G36: CONTENÇÃO | H36: SERVIÇO | I36: 02.002.001.002 | J36: Armação aço CA-50 ø 8,0mm para Contenções (corte e dobra em Indústria) | K36: un | L36: 77 | M36: 8.964145 | N36: 690.23916 | P36: Pendente
A37: 0 | B37: 2 | C37: 2 | D37: 1 | E37: 3 | G37: CONTENÇÃO | H37: SERVIÇO | I37: 02.002.001.003 | J37: Armação aço CA-50 ø 12,5mm para Contenções (corte e dobra em Indústria) | K37: un | L37: 3884 | M37: 8.484145 | N37: 32952.419 | P37: Pendente
A38: 0 | B38: 2 | C38: 2 | D38: 1 | E38: 4 | G38: CONTENÇÃO | H38: SERVIÇO | I38: 02.002.001.004 | J38: Armação aço CA-50 ø 25,0mm para Contenções (corte e dobra em Indústria) | K38: un | L38: 12007 | M38: 8.484145 | N38: 101869.13 | P38: Pendente
A39: 0 | B39: 2 | C39: 2 | D39: 2 | E39: 0 | H39: SUBETAPA | I39: 02.002.002 | J39: Concreto | N39: 175897.26 | O39: 10.501536
A40: 0 | B40: 2 | C40: 2 | D40: 2 | E40: 1 | G40: CONTENÇÃO | H40: SERVIÇO | I40: 02.002.002.001 | J40: Concreto Usinado bombeável 50MPa com Penetron para infraestrutura- incluindo serviço de bombeamento | K40: m3 | L40: 210 | M40: 837.606 | N40: 175897.26 | P40: Pendente
A41: 0 | B41: 2 | C41: 3 | D41: 0 | E41: 1 | H41: ETAPA | I41: 02.003 | J41: VIGAS COROAMENTO | N41: 37645.991 | O41: 2.2475661
A42: 0 | B42: 2 | C42: 3 | D42: 1 | E42: 0 | H42: SUBETAPA | I42: 02.003.001 | J42: Forma | N42: 2482.1879 | O42: 0.14819324
A43: 0 | B43: 2 | C43: 3 | D43: 1 | E43: 1 | G43: CONTENÇÃO | H43: SERVIÇO | I43: 02.003.001.001 | J43: Forma para infraestrutura em Tábuas de Madeira Serrada 2x reaproveitamento | K43: m2 | L43: 41.4 | M43: 59.956229 | N43: 2482.1879 | P43: Pendente
A44: 0 | B44: 2 | C44: 3 | D44: 2 | E44: 0 | H44: SUBETAPA | I44: 02.003.002 | J44: Armadura | N44: 23057.916 | O44: 1.3766191
A45: 0 | B45: 2 | C45: 3 | D45: 2 | E45: 1 | G45: CONTENÇÃO | H45: SERVIÇO | I45: 02.003.002.001 | J45: Armação aço CA-50 ø 8,0mm para Contenções (corte e dobra em Indústria) | K45: kg | L45: 913.36364 | M45: 8.964145 | N45: 8187.5241 | P45: Pendente
A46: 0 | B46: 2 | C46: 3 | D46: 2 | E46: 2 | G46: CONTENÇÃO | H46: SERVIÇO | I46: 02.003.002.002 | J46: Armação aço CA-50 ø 12,5mm para Contenções (corte e dobra em Indústria) | K46: kg | L46: 45.363636 | M46: 8.484145 | N46: 384.87167 | P46: Pendente
A47: 0 | B47: 2 | C47: 3 | D47: 2 | E47: 3 | G47: CONTENÇÃO | H47: SERVIÇO | I47: 02.003.002.003 | J47: Armação aço CA-50 ø 16,0mm para Contenções (corte e dobra em Indústria) | K47: kg | L47: 1277.2727 | M47: 8.484145 | N47: 10836.567 | P47: Pendente
A48: 0 | B48: 2 | C48: 3 | D48: 2 | E48: 4 | G48: CONTENÇÃO | H48: SERVIÇO | I48: 02.003.002.004 | J48: Armação aço CA-50 ø 20,0mm para Contenções (corte e dobra em Indústria) | K48: kg | L48: 430.09091 | M48: 8.484145 | N48: 3648.9536 | P48: Pendente
A49: 0 | B49: 2 | C49: 3 | D49: 3 | E49: 0 | H49: SUBETAPA | I49: 02.003.003 | J49: Concreto | N49: 12105.887
A50: 0 | B50: 2 | C50: 3 | D50: 3 | E50: 1 | G50: CONTENÇÃO | H50: SERVIÇO | I50: 02.003.003.001 | J50: Concreto Usinado bombeável 50MPa para infraestrutura- incluindo serviço de bombeamento | K50: m3 | L50: 17.8 | M50: 680.106 | N50: 12105.887 | P50: Pendente
A51: 0 | B51: 2 | C51: 4 | D51: 0 | E51: 1 | H51: ETAPA | I51: 02.004 | J51: ESTACAS PRANCHA METÁLICA | N51: 243756 | O51: 14.552884
A52: 0 | B52: 2 | C52: 4 | D52: 1 | E52: 0 | H52: SUBETAPA | I52: 02.004.001 | J52: Estacas prancha metálica | N52: 243756 | O52: 14.552884
A53: 0 | B53: 2 | C53: 4 | D53: 1 | E53: 1 | G53: CONTENÇÃO | H53: SERVIÇO | I53: 02.004.001.001 | J53: Locação e cravação de estacas prancha EP400 para contenção | K53: m2 | L53: 492.8 | M53: 470.28409 | N53: 231756 | O53: Cotação, considerado 6 meses de locação | P53: Pendente
A54: 0 | B54: 2 | C54: 4 | D54: 1 | E54: 2 | G54: CONTENÇÃO | H54: SERVIÇO | I54: 02.004.001.002 | J54: Mobilização e Desmobilização de equipamento e máquinas considerando serviço de carga e descarga | K54: vb | L54: 1 | M54: 12000 | N54: 12000 | P54: Pendente
A55: 0 | B55: 2 | C55: 5 | D55: 0 | E55: 2 | H55: ETAPA | I55: 02.005 | J55: MÃO DE OBRA CONTENÇÕES | N55: 140000.02 | O55: 8.3583748
A56: 0 | B56: 2 | C56: 5 | D56: 1 | E56: 0 | H56: SUBETAPA | I56: 02.005.001 | J56: Mão de Obra | N56: 140000.02 | O56: 8.3583748
A57: 0 | B57: 2 | C57: 5 | D57: 1 | E57: 1 | G57: CONTENÇÃO | H57: SERVIÇO | I57: 02.005.001.001 | J57: Mão de obra para execução de contenção | K57: m2 | L57: 525 | M57: 266.6667 | N57: 140000.02 | O57: Prosposta Gessele | P57: Pendente
A58: 0 | B58: 3 | C58: 0 | D58: 1 | E58: 1 | H58: CÉLULA CONSTRUTIVA | I58: 03 | J58: INFRAESTRUTURA | N58: 4572490 | O58: 272.98986
A59: 0 | B59: 3 | C59: 1 | D59: 0 | E59: 1 | H59: ETAPA | I59: 03.001 | J59: ESTACA HÉLICE CONTÍNUA | N59: 3041540.5 | O59: 181.58809
A60: 0 | B60: 3 | C60: 1 | D60: 1 | E60: 0 | H60: SUBETAPA | I60: 03.001.001 | J60: Perfuração | N60: 950000 | O60: 56.717535
A61: 0 | B61: 3 | C61: 1 | D61: 1 | E61: 1 | G61: INFRAESTRUTURA | H61: SERVIÇO | I61: 03.001.001.001 | J61: Perfuração de estaca hélice contínua Ø 60cm | K61: m | L61: 6732 | M61: 137.48633 | N61: 925557.99 | O61: Repessado pela Gessele na reunião do dia 05/03/2026 - 950k efeg | P61: Pendente
A62: 0 | B62: 3 | C62: 1 | D62: 1 | E62: 2 | G62: INFRAESTRUTURA | H62: SERVIÇO | I62: 03.001.001.002 | J62: Mobilização e desmobilização de equipamentos - Para execução de estaca hélice monitorada | K62: vb | L62: 1 | M62: 24442.015 | N62: 24442.015 | O62: Repessado pela Gessele na reunião do dia 05/03/2026 - 950k efeg | P62: Pendente
A63: 0 | B63: 3 | C63: 1 | D63: 2 | E63: 0 | H63: SUBETAPA | I63: 03.001.002 | J63: Armadura | N63: 298834.78 | O63: 17.841234
A64: 0 | B64: 3 | C64: 1 | D64: 2 | E64: 1 | G64: INFRAESTRUTURA | H64: SERVIÇO | I64: 03.001.002.001 | J64: Armação aço CA-50 ø 6,3mm para estaca (corte e dobra em indústria) | K64: un | L64: 3495 | M64: 8.964145 | N64: 31329.687 | P64: Pendente
A65: 0 | B65: 3 | C65: 1 | D65: 2 | E65: 2 | G65: INFRAESTRUTURA | H65: SERVIÇO | I65: 03.001.002.002 | J65: Armação aço CA-50 ø 20,0mm para estaca (corte e dobra em indústria) | K65: un | L65: 31530 | M65: 8.484145 | N65: 267505.09 | P65: Pendente
A66: 0 | B66: 3 | C66: 1 | D66: 3 | E66: 0 | H66: SUBETAPA | I66: 03.001.003 | J66: Concreto | N66: 1792705.7 | O66: 107.02932
A67: 0 | B67: 3 | C67: 1 | D67: 3 | E67: 1 | G67: INFRAESTRUTURA | H67: SERVIÇO | I67: 03.001.003.001 | J67: Concreto Usinado bombeável para estacas 50MPa - incluindo serviço de bombeamento | K67: m3 | L67: 1903.4282 | M67: 941.83 | N67: 1792705.7 | P67: Pendente
A68: 0 | B68: 3 | C68: 1 | D68: 4 | E68: 0 | H68: SUBETAPA | I68: 03.001.004 | J68: Mão de Obra | N68: 0 | O68: 0
A69: 0 | B69: 3 | C69: 2 | D69: 0 | E69: 0 | H69: ETAPA | I69: 03.002 | J69: BLOCOS | N69: 1056067.4 | O69: 63.050045
A70: 0 | B70: 3 | C70: 2 | D70: 1 | E70: 0 | H70: SUBETAPA | I70: 03.002.001 | J70: Forma | N70: 15723.521 | O70: 0.93873616
A71: 0 | B71: 3 | C71: 2 | D71: 1 | E71: 1 | G71: INFRAESTRUTURA | H71: SERVIÇO | I71: 03.002.001.001 | J71: Forma para infraestrutura em Tábuas de Madeira Serrada 2x reaproveitamento | K71: m2 | L71: 262.25 | M71: 59.956229 | N71: 15723.521 | O71: Apenas blocos, 2x reaproveitamento | P71: Pendente
A72: 0 | B72: 3 | C72: 2 | D72: 2 | E72: 0 | H72: SUBETAPA | I72: 03.002.002 | J72: Armadura | N72: 592494.12 | O72: 35.37348
A73: 0 | B73: 3 | C73: 2 | D73: 2 | E73: 1 | G73: INFRAESTRUTURA | H73: SERVIÇO | I73: 03.002.002.001 | J73: Armação aço CA-50 ø 12,5mm para infraestrutura (corte e dobra em Indústria) | K73: kg | L73: 528.18182 | M73: 8.484145 | N73: 4481.1711 | P73: Pendente
A74: 0 | B74: 3 | C74: 2 | D74: 2 | E74: 2 | G74: INFRAESTRUTURA | H74: SERVIÇO | I74: 03.002.002.002 | J74: Armação aço CA-50 ø 16,0mm para infraestrutura (corte e dobra em Indústria) | K74: kg | L74: 7331.8182 | M74: 8.484145 | N74: 62204.209 | P74: Pendente
A75: 0 | B75: 3 | C75: 2 | D75: 2 | E75: 3 | G75: INFRAESTRUTURA | H75: SERVIÇO | I75: 03.002.002.003 | J75: Armação aço CA-50 ø 20,0mm para infraestrutura (corte e dobra em Indústria) | K75: kg | L75: 1318.1818 | M75: 8.484145 | N75: 11183.646 | P75: Pendente
A76: 0 | B76: 3 | C76: 2 | D76: 2 | E76: 4 | G76: INFRAESTRUTURA | H76: SERVIÇO | I76: 03.002.002.004 | J76: Armação aço CA-50 ø 25,0mm para infraestrutura (corte e dobra em Indústria) | K76: kg | L76: 60657.273 | M76: 8.484145 | N76: 514625.1 | P76: Pendente
A77: 0 | B77: 3 | C77: 2 | D77: 3 | E77: 0 | H77: SUBETAPA | I77: 03.002.003 | J77: Concreto | N77: 447849.8 | O77: 26.737828
A78: 0 | B78: 3 | C78: 2 | D78: 3 | E78: 1 | G78: INFRAESTRUTURA | H78: SERVIÇO | I78: 03.002.003.001 | J78: Concreto Usinado bombeável 50MPa para infraestrutura- incluindo serviço de bombeamento | K78: m3 | L78: 658.5 | M78: 680.106 | N78: 447849.8 | O78: 5% de perda, fck = 50Mpa | P78: Pendente
A79: 0 | B79: 3 | C79: 2 | D79: 4 | E79: 0 | H79: SUBETAPA | I79: 03.002.004 | J79: Mão de Obra | N79: 0 | O79: 0
A80: 0 | B80: 3 | C80: 3 | D80: 0 | E80: 0 | H80: ETAPA | I80: 03.003 | J80: VIGAS BALDRAMES | PILARES DE ARRANQUE | CISTERNAS E DUTOS | N80: 474882.06 | O80: 28.351727
A81: 0 | B81: 3 | C81: 3 | D81: 1 | E81: 0 | H81: SUBETAPA | I81: 03.003.001 | J81: Forma | N81: 9996.6219 | O81: 0.59682501
A82: 0 | B82: 3 | C82: 3 | D82: 1 | E82: 1 | G82: INFRAESTRUTURA | H82: SERVIÇO | I82: 03.003.001.001 | J82: Forma para infraestrutura em Tábuas de Madeira Serrada 2x reaproveitamento | K82: m2 | L82: 166.732 | M82: 59.956229 | N82: 9996.6219 | O82: Considerado blocos, vigas de fundação, duto, cisterna, lajes e pilares de arranque | P82: Pendente
A83: 0 | B83: 3 | C83: 3 | D83: 2 | E83: 0 | H83: SUBETAPA | I83: 03.003.002 | J83: Armadura | N83: 430167.93 | O83: 25.682173
A84: 0 | B84: 3 | C84: 3 | D84: 2 | E84: 1 | G84: INFRAESTRUTURA | H84: SERVIÇO | I84: 03.003.002.001 | J84: Armação aço CA-50 ø 5,0mm para infraestrutura (corte e dobra em Indústria) | K84: kg | L84: 52 | M84: 8.964145 | N84: 466.13554 | O84: Considerado vigas de fundação, duto, cisterna, lajes e pilares de arranque - 10% de perda | P84: Pendente
A85: 0 | B85: 3 | C85: 3 | D85: 2 | E85: 2 | G85: INFRAESTRUTURA | H85: SERVIÇO | I85: 03.003.002.002 | J85: Armação aço CA-50 ø 6,3mm para infraestrutura (corte e dobra em Indústria) | K85: kg | L85: 130.27273 | M85: 8.964145 | N85: 1167.7836 | O85: Considerado vigas de fundação, duto, cisterna, lajes e pilares de arranque - 10% de perda | P85: Pendente
A86: 0 | B86: 3 | C86: 3 | D86: 2 | E86: 3 | G86: INFRAESTRUTURA | H86: SERVIÇO | I86: 03.003.002.003 | J86: Armação aço CA-50 ø 8,0mm para infraestrutura (corte e dobra em Indústria) | K86: kg | L86: 982.63636 | M86: 8.964145 | N86: 8808.4948 | O86: Considerado vigas de fundação, duto, cisterna, lajes e pilares de arranque - 10% de perda | P86: Pendente
A87: 0 | B87: 3 | C87: 3 | D87: 2 | E87: 4 | G87: INFRAESTRUTURA | H87: SERVIÇO | I87: 03.003.002.004 | J87: Armação aço CA-50 ø 10,0mm para infraestrutura (corte e dobra em Indústria) | K87: kg | L87: 7011.6364 | M87: 8.964145 | N87: 62853.325 | O87: Considerado vigas de fundação, duto, cisterna, lajes e pilares de arranque - 10% de perda | P87: Pendente
A88: 0 | B88: 3 | C88: 3 | D88: 2 | E88: 5 | G88: INFRAESTRUTURA | H88: SERVIÇO | I88: 03.003.002.005 | J88: Armação aço CA-50 ø 12,5mm para infraestrutura (corte e dobra em Indústria) | K88: kg | L88: 6007.8182 | M88: 8.484145 | N88: 50971.201 | O88: Considerado vigas de fundação, duto, cisterna, lajes e pilares de arranque - 10% de perda | P88: Pendente
A89: 0 | B89: 3 | C89: 3 | D89: 2 | E89: 6 | G89: INFRAESTRUTURA | H89: SERVIÇO | I89: 03.003.002.006 | J89: Armação aço CA-50 ø 16,0mm para infraestrutura (corte e dobra em Indústria) | K89: kg | L89: 1269.7273 | M89: 8.484145 | N89: 10772.55 | O89: Considerado vigas de fundação, duto, cisterna, lajes e pilares de arranque - 10% de perda | P89: Pendente
A90: 0 | B90: 3 | C90: 3 | D90: 2 | E90: 7 | G90: INFRAESTRUTURA | H90: SERVIÇO | I90: 03.003.002.007 | J90: Armação aço CA-50 ø 20,0mm para infraestrutura (corte e dobra em Indústria) | K90: kg | L90: 902 | M90: 8.484145 | N90: 7652.6988 | O90: Considerado vigas de fundação, duto, cisterna, lajes e pilares de arranque - 10% de perda | P90: Pendente
A91: 0 | B91: 3 | C91: 3 | D91: 2 | E91: 8 | G91: INFRAESTRUTURA | H91: SERVIÇO | I91: 03.003.002.008 | J91: Armação aço CA-50 ø 25,0mm para infraestrutura (corte e dobra em Indústria) | K91: kg | L91: 4680 | M91: 8.484145 | N91: 39705.799 | O91: Considerado vigas de fundação, duto, cisterna, lajes e pilares de arranque - 10% de perda | P91: Pendente
A92: 0 | B92: 3 | C92: 3 | D92: 2 | E92: 9 | G92: INFRAESTRUTURA | H92: SERVIÇO | I92: 03.003.002.009 | J92: Armação aço CA-50 ø 32,00mm para infraestrutura (corte e dobra em Indústria) | K92: kg | L92: 27316 | M92: 9.0705059 | N92: 247769.94 | O92: Considerado vigas de fundação, duto, cisterna, lajes e pilares de arranque - 10% de perda | P92: Pendente
A93: 0 | B93: 3 | C93: 3 | D93: 3 | E93: 0 | H93: SUBETAPA | I93: 03.003.003 | J93: Concreto | N93: 34717.514 | O93: 2.0727282
A94: 0 | B94: 3 | C94: 3 | D94: 3 | E94: 1 | G94: INFRAESTRUTURA | H94: SERVIÇO | I94: 03.003.003.001 | J94: Concreto Usinado bombeável 50MPa para infraestrutura- incluindo serviço de bombeamento | K94: m3 | L94: 51.04721 | M94: 680.106 | N94: 34717.514 | O94: Cotações recentes do concreto. Considerado vigas de fundação, duto, cisterna, lajes e pilares de arranque - 5% de perda, fck = 50Mpa | P94: Pendente
A95: 0 | B95: 3 | C95: 3 | D95: 4 | E95: 0 | H95: SUBETAPA | I95: 03.003.004 | J95: Mão de Obra | N95: 0 | O95: 0
A96: 0 | B96: 4 | C96: 0 | D96: 4 | E96: 0 | H96: CÉLULA CONSTRUTIVA | I96: 04 | J96: SUPRAESTRUTURA | N96: 20793271 | O96: 1241.4138
A97: 0 | B97: 4 | C97: 1 | D97: 0 | E97: 0 | H97: ETAPA | I97: 04.001 | J97: PISO SOBRE O SOLO - GERAL | N97: 19428.045 | O97: 1.1599061
A98: 0 | B98: 4 | C98: 1 | D98: 1 | E98: 0 | H98: SUBETAPA | I98: 04.001.001 | J98: Piso sobre o solo - Geral | N98: 19428.045 | O98: 1.1599061
A99: 0 | B99: 4 | C99: 1 | D99: 1 | E99: 1 | G99: SUPRAESTRUTURA | H99: SERVIÇO | I99: 04.001.001.001 | J99: Lastro de Concreto Magro, Aplicado em piso sobre solo | K99: m3 | L99: 39.229 | M99: 495.247 | N99: 19428.045 | O99: O concreto e a armadura entraram nos itens referentes ao terreo, conforme lista de materiais do projetista | P99: Pendente
A100: 0 | B100: 4 | C100: 2 | D100: 0 | E100: 1 | H100: ETAPA | I100: 04.002 | J100: FORMA | N100: 1435615 | O100: 85.710046
A101: 0 | B101: 4 | C101: 2 | D101: 1 | E101: 0 | H101: SUBETAPA | I101: 04.002.001 | J101: Forma - Térreo | N101: 529090.67 | O101: 31.588125
A102: 0 | B102: 4 | C102: 2 | D102: 1 | E102: 1 | G102: SUPRAESTRUTURA | H102: SERVIÇO | I102: 04.002.001.001 | J102: Fabricação de Fôrma para Supraestrutura, em Chapa de Madeira Compensada Resinada, E=20mm | K102: m2 | L102: 4874.3226 | M102: 108.03523 | N102: 526598.54 | O102: 8x reaproveitamento - 3 jogos | P102: Pendente
A103: 0 | B103: 4 | C103: 2 | D103: 1 | E103: 2 | G103: SUPRAESTRUTURA | H103: SERVIÇO | I103: 04.002.001.002 | J103: Montagem e Desmontagem de Fôrma de Supraestrutura | K103: m2 | L103: 626.5792 | M103: 3.9773488 | N103: 2492.124 | P103: Pendente
...

Sheet Orçamento
A1: DADOS
A2: Titulo | B2: ORÇAMENTO
A3: Obra | B3: ELECTRA TOWERS
A4: Cliente | B4: THOZEN
A5: Cidade | B5: Porto Belo
A6: Endereço
A7: Descrição
A8: UF | B8: SC
A10: RESUMO
A11: Tipo | C11: Preço | E11: Observação
A12: Total | C12: 21718825 | E12: Geral da edificação
A13: Material | C13: 15467433
A14: Execução | C14: 6251392.4
A16: TABELA DE ORÇAMENTO
A17: Item | B17: Referência | C17: Tipo | D17: Código | E17: Descrição | F17: Unid. | G17: Quantidade | H17: Custo unitário | I17: Preço total | J17: % | K17: Observação
A19: 1. | E19: 03. PAREDES E PAINÉIS | I19: 1964071 | J19: 0.090431735
A20: 1.1. | E20: ARQ_Embasamento | I20: 228660.08 | J20: 0.010528198
A21: 1.1.1. | E21: 03.001. Alvenaria de vedação com blocos cerâmicos | I21: 133087.99 | J21: 0.006127771
A22: 1.1.1.1 | E22: BLOCO CERAMICO, 0,05 (Parede padrão) | F22: m² | G22: 35.77 | H22: 0 | I22: 0
A23: 1.1.1.2 | E23: BLOCO CERAMICO, 0,09 (Parede padrão) | F23: m² | G23: 171.98 | H23: 0 | I23: 0
A24: 1.1.1.3 | B24: Thozen - Electra | C24: COMPOSICAO | D24: 4825 | E24: Alvenaria de vedação de blocos cerâmicos furados na horizontal de 11,5x19x19cm (espessura 11,5cm) com argamassa industrializada de assentamento | F24: m2 | G24: 1262.88 | H24: 25.096 | I24: 31693.236 | J24: 0.0014592519
A25: 1.1.1.4 | B25: Thozen - Electra | C25: COMPOSICAO | D25: 4826 | E25: Alvenaria de vedação de blocos cerâmicos furados na horizontal de 14x19x19cm (espessura 14cm) com argamassa industrializada de assentamento | F25: m2 | G25: 1610.87 | H25: 40.7664 | I25: 65669.371 | J25: 0.0030236152
A26: 1.1.1.5 | B26: Thozen - Electra | C26: COMPOSICAO | D26: 90472 | E26: Alvenaria de vedação de blocos cerâmicos furados na horizontal de 19x19x19cm (espessura 19cm) com argamassa industrializada de assentamento | F26: m2 | G26: 631.36 | H26: 56.5848 | I26: 35725.379 | J26: 0.0016449039
A27: 1.1.2. | E27: 03.002. Alvenaria de vedação com blocos de concreto | I27: 0
A28: 1.1.2.1 | E28: BLOCO CONCRETO, 0,05 (Parede padrão) | F28: m² | G28: 1.49 | H28: 0 | I28: 0
A29: 1.1.2.2 | E29: BLOCO ANTI CHAMAS, 0,125 (Parede padrão) | F29: m² | G29: 252.44 | H29: 0 | I29: 0
A30: 1.1.2.3 | E30: BLOCO ANTI CHAMAS, 0,15 (Parede padrão) | F30: m² | G30: 774.4 | H30: 0 | I30: 0
A31: 1.1.3. | E31: 03.003. Serviços complementares para alvenaria de vedação | I31: 95572.097 | J31: 0.0044004266
A32: 1.1.3.1 | B32: Thozen - Electra | C32: COMPOSICAO | D32: 4831 | E32: Verga/contraverga de concreto, moldada in loco | F32: m | G32: 104.16 | H32: 43.712512 | I32: 4553.0952 | J32: 0.00020963819
A33: 1.1.3.2 | B33: Thozen - Electra | C33: COMPOSICAO | D33: 4828 | E33: Encunhamento de alvenaria de vedação com argamassa expansiva | F33: m | G33: 18470.23 | H33: 3.633798 | I33: 67117.085 | J33: 0.0030902724
A34: 1.1.3.3 | B34: Thozen - Electra | C34: COMPOSICAO | D34: 4829 | E34: Tela soldada para ligação alvenaria/estrutura | F34: m² | G34: 2370.59 | H34: 1.85 | I34: 4385.5915 | J34: 0.00020192582
A35: 1.1.3.4 | B35: Thozen - Electra | C35: COMPOSICAO | D35: 4831 | E35: Verga/contraverga de concreto, moldada in loco | F35: m | G35: 446.47 | H35: 43.712512 | I35: 19516.325 | J35: 0.00089859028
A36: 1.1.4. | E36: 03.005. Mão de obra | I36: 0
A37: 1.1.4.1 | E37: Mão de obra alvenaria cerâmica | F37: m² | G37: 4045.19 | H37: 0 | I37: 0
A38: 1.1.4.2 | E38: Mão de obra blocos sílico calcário (Parede padrão) | F38: m² | G38: 1028.33 | H38: 0 | I38: 0
A39: 1.1.5. | E39: Alvenaria de vedação com tijolo refratário | I39: 0
A40: 1.1.5.1 | E40: TIJOLO REFRATARIO, 0,016 (Parede padrão) | F40: m² | G40: 14.56 | H40: 0 | I40: 0
A41: 1.2. | E41: ARQ_Impermeab | I41: 45754.495 | J41: 0.0021066745
A42: 1.2.1. | E42: 03.003. Serviços complementares para alvenaria de vedação | I42: 45754.495 | J42: 0.0021066745
A43: 1.2.1.1 | B43: Thozen - Electra | C43: COMPOSICAO | D43: 4828 | E43: Encunhamento de alvenaria de vedação com argamassa expansiva | F43: m | G43: 12591.37 | H43: 3.633798 | I43: 45754.495 | J43: 0.0021066745
A44: 1.3. | E44: ARQ_Torre_A | I44: 823378.32 | J44: 0.037910813
A45: 1.3.1. | E45: 03.001. Alvenaria de vedação com blocos cerâmicos | I45: 416102.64 | J45: 0.019158616
A46: 1.3.1.1 | E46: BLOCO CERAMICO, 0,05 (Parede padrão) | F46: m² | G46: 1074.45 | H46: 0 | I46: 0
A47: 1.3.1.2 | E47: BLOCO CERAMICO, 0,09 (Parede padrão) | F47: m² | G47: 1364.5 | H47: 0 | I47: 0
A48: 1.3.1.3 | B48: Thozen - Electra | C48: COMPOSICAO | D48: 4825 | E48: Alvenaria de vedação de blocos cerâmicos furados na horizontal de 11,5x19x19cm (espessura 11,5cm) com argamassa industrializada de assentamento | F48: m2 | G48: 7270.36 | H48: 25.096 | I48: 182456.95 | J48: 0.0084008667
A49: 1.3.1.4 | B49: Thozen - Electra | C49: COMPOSICAO | D49: 4826 | E49: Alvenaria de vedação de blocos cerâmicos furados na horizontal de 14x19x19cm (espessura 14cm) com argamassa industrializada de assentamento | F49: m2 | G49: 4090.42 | H49: 40.7664 | I49: 166751.7 | J49: 0.0076777495
A50: 1.3.1.5 | B50: Thozen - Electra | C50: COMPOSICAO | D50: 90472 | E50: Alvenaria de vedação de blocos cerâmicos furados na horizontal de 19x19x19cm (espessura 19cm) com argamassa industrializada de assentamento | F50: m2 | G50: 1182.19 | H50: 56.5848 | I50: 66893.985 | J50: 0.0030800002
A51: 1.3.2. | E51: 03.002. Alvenaria de vedação com blocos de concreto | I51: 0
A52: 1.3.2.1 | E52: BLOCO CONCRETO, 0,05 (Parede padrão) | F52: m² | G52: 363.8 | H52: 0 | I52: 0
A53: 1.3.2.2 | E53: BLOCO ANTI CHAMAS, 0,125 (Parede padrão) | F53: m² | G53: 128.55 | H53: 0 | I53: 0
A54: 1.3.2.3 | E54: BLOCO ANTI CHAMAS, 0,15 (Parede padrão) | F54: m² | G54: 862.58 | H54: 0 | I54: 0
A55: 1.3.3. | E55: 03.003. Serviços complementares para alvenaria de vedação | I55: 407275.68 | J55: 0.018752197
A56: 1.3.3.1 | B56: Thozen - Electra | C56: COMPOSICAO | D56: 4831 | E56: Verga/contraverga de concreto, moldada in loco | F56: m | G56: 1151.26 | H56: 43.712512 | I56: 50324.467 | J56: 0.0023170897
A57: 1.3.3.2 | B57: Thozen - Electra | C57: COMPOSICAO | D57: 4828 | E57: Encunhamento de alvenaria de vedação com argamassa expansiva | F57: m | G57: 62783.49 | H57: 3.633798 | I57: 228142.52 | J57: 0.010504367
A58: 1.3.3.3 | B58: Thozen - Electra | C58: COMPOSICAO | D58: 4829 | E58: Tela soldada para ligação alvenaria/estrutura | F58: m² | G58: 8168.42 | H58: 1.85 | I58: 15111.577 | J58: 0.00069578243
A59: 1.3.3.4 | B59: Thozen - Electra | C59: COMPOSICAO | D59: 4831 | E59: Verga/contraverga de concreto, moldada in loco | F59: m | G59: 2601.02 | H59: 43.712512 | I59: 113697.12 | J59: 0.0052349571
A60: 1.3.4. | E60: 03.005. Mão de obra | I60: 0
A61: 1.3.4.1 | E61: Mão de obra alvenaria cerâmica | F61: m² | G61: 16873.23 | H61: 0 | I61: 0
A62: 1.3.4.2 | E62: Mão de obra blocos sílico calcário (Parede padrão) | F62: m² | G62: 1354.93 | H62: 0 | I62: 0
A63: 1.3.5. | E63: Alvenaria de vedação com tijolo refratário | I63: 0
A64: 1.3.5.1 | E64: TIJOLO REFRATARIO, 0,016 (Parede padrão) | F64: m² | G64: 287.37 | H64: 0 | I64: 0
A65: 1.4. | E65: ARQ_Torre_B | I65: 866278.14 | J65: 0.03988605
A66: 1.4.1. | E66: 03.001. Alvenaria de vedação com blocos cerâmicos | I66: 489178.45 | J66: 0.022523246
A67: 1.4.1.1 | E67: BLOCO CERAMICO, 0,05 (Parede padrão) | F67: m² | G67: 398.15 | H67: 0 | I67: 0
A68: 1.4.1.2 | E68: BLOCO CERAMICO, 0,09 (Parede padrão) | F68: m² | G68: 3063.66 | H68: 0 | I68: 0
A69: 1.4.1.3 | B69: Thozen - Electra | C69: COMPOSICAO | D69: 4825 | E69: Alvenaria de vedação de blocos cerâmicos furados na horizontal de 11,5x19x19cm (espessura 11,5cm) com argamassa industrializada de assentamento | F69: m2 | G69: 8394.28 | H69: 25.096 | I69: 210662.85 | J69: 0.009699551
A70: 1.4.1.4 | B70: Thozen - Electra | C70: COMPOSICAO | D70: 4826 | E70: Alvenaria de vedação de blocos cerâmicos furados na horizontal de 14x19x19cm (espessura 14cm) com argamassa industrializada de assentamento | F70: m2 | G70: 5416.8 | H70: 40.7664 | I70: 220823.44 | J70: 0.010167375
A71: 1.4.1.5 | B71: Thozen - Electra | C71: COMPOSICAO | D71: 90472 | E71: Alvenaria de vedação de blocos cerâmicos furados na horizontal de 19x19x19cm (espessura 19cm) com argamassa industrializada de assentamento | F71: m2 | G71: 1019.57 | H71: 56.5848 | I71: 57692.165 | J71: 0.0026563207
A72: 1.4.2. | E72: 03.002. Alvenaria de vedação com blocos de concreto | I72: 0
A73: 1.4.2.1 | E73: BLOCO ANTI CHAMAS, 0,125 (Parede padrão) | F73: m² | G73: 245.34 | H73: 0 | I73: 0
A74: 1.4.2.2 | E74: BLOCO ANTI CHAMAS, 0,15 (Parede padrão) | F74: m² | G74: 662.3 | H74: 0 | I74: 0
A75: 1.4.3. | E75: 03.003. Serviços complementares para alvenaria de vedação | I75: 377099.69 | J75: 0.017362803
A76: 1.4.3.1 | B76: Thozen - Electra | C76: COMPOSICAO | D76: 4831 | E76: Verga/contraverga de concreto, moldada in loco | F76: m | G76: 1126.07 | H76: 43.712512 | I76: 49223.348 | J76: 0.0022663909
A77: 1.4.3.2 | B77: Thozen - Electra | C77: COMPOSICAO | D77: 4828 | E77: Encunhamento de alvenaria de vedação com argamassa expansiva | F77: m | G77: 54949.59 | H77: 3.633798 | I77: 199675.71 | J77: 0.00919367
A78: 1.4.3.3 | B78: Thozen - Electra | C78: COMPOSICAO | D78: 4829 | E78: Tela soldada para ligação alvenaria/estrutura | F78: m² | G78: 9600.05 | H78: 1.85 | I78: 17760.092 | J78: 0.00081772805
A79: 1.4.3.4 | B79: Thozen - Electra | C79: COMPOSICAO | D79: 4831 | E79: Verga/contraverga de concreto, moldada in loco | F79: m | G79: 2526.52 | H79: 43.712512 | I79: 110440.54 | J79: 0.0050850143
A80: 1.4.4. | E80: 03.005. Mão de obra | I80: 0
A81: 1.4.4.1 | E81: Mão de obra alvenaria cerâmica | F81: m² | G81: 20189.64 | H81: 0 | I81: 0
A82: 1.4.4.2 | E82: Mão de obra blocos sílico calcário (Parede padrão) | F82: m² | G82: 907.65 | H82: 0 | I82: 0
A83: 1.4.5. | E83: Alvenaria de vedação com tijolo refratário | I83: 0
A84: 1.4.5.1 | E84: TIJOLO REFRATARIO, 0,016 (Parede padrão) | F84: m² | G84: 269.16 | H84: 0 | I84: 0
A85: 2. | E85: 04. IMPERMEABILIZAÇÃO E TRATAMENTOS | I85: 331117.51 | J85: 0.015245646
A86: 2.1. | E86: ARQ_Embasamento | I86: 0
A87: 2.1.1. | E87: 04.007. Impermeabilização de esquadrias | I87: 0
A88: 2.1.1.1 | E88: Peitoril | F88: m² | G88: 84.83 | H88: 0 | I88: 0
A89: 2.2. | E89: ARQ_Impermeab | I89: 331117.51 | J89: 0.015245646
A90: 2.2.1. | E90: 04.004. Impermeabilização de lajes e terraços | I90: 0
A91: 2.2.1.1 | E91: VERIFICAR MATERIAL TERRAÇO (Laje) | F91: m² | G91: 755.42 | H91: 0 | I91: 0
A92: 2.2.1.2 | E92: VERIFICAR MATERIAL - TERRAÇO (Parede padrão) | F92: m² | G92: 55.75 | H92: 0 | I92: 0
A93: 2.2.2. | E93: 04.006. Impermeabilização de banheiro, cozinha e sacada | I93: 331117.51 | J93: 0.015245646
A94: 2.2.2.1 | B94: Thozen - Electra | C94: COMPOSICAO | D94: 4842 | E94: Impermeabilização com argamassa polimérica, 3 demãos | F94: m2 | G94: 9140.58 | H94: 36.225 | I94: 331117.51 | J94: 0.015245646
A95: 2.2.3. | E95: 04.007. Impermeabilização de esquadrias | I95: 0
A96: 2.2.3.1 | E96: Polímero acrílico - janela | F96: m² | G96: 582.79 | H96: 0 | I96: 0
A97: 2.3. | E97: ARQ_Torre_A | I97: 0
A98: 2.3.1. | E98: 04.007. Impermeabilização de esquadrias | I98: 0
A99: 2.3.1.1 | E99: Peitoril | F99: m² | G99: 252.2 | H99: 0 | I99: 0
A100: 2.4. | E100: ARQ_Torre_B | I100: 0
A101: 2.4.1. | E101: 04.007. Impermeabilização de esquadrias | I101: 0
A102: 2.4.1.1 | E102: Peitoril | F102: m² | G102: 234.85 | H102: 0 | I102: 0
A103: 3. | E103: 12. REVESTIMENTOS ARGAMASSADOS INTERNOS DE PAREDE | I103: 4588051.9 | J103: 0.2112477
...

Sheet Composições
A1: DADOS
A2: Titulo | B2: ORÇAMENTO
A3: Obra | B3: ELECTRA TOWERS
A4: Cliente | B4: THOZEN
A5: Cidade | B5: Porto Belo
A6: Endereço
A7: Descrição
A8: UF | B8: SC
A11: TABELA DE COMPOSIÇÕES UTILIZADAS
A12: Código | B12: Referência | C12: Tipo | D12: Tipo | E12: Descrição | F12: Unid. | G12: Multiplicador | H12: Preço | J12: Ref. Tabela | K12: Ref. Código | L12: Justificativa | M12: Grupo de Serviço | N12: Serviço
H13: Unitário | I13: Total
A14: 4825 | B14: Thozen - Electra | D14: Original | E14: Alvenaria de vedação de blocos cerâmicos furados na horizontal de 11,5x19x19cm (espessura 11,5cm) com argamassa industrializada de assentamento | F14: m2 | I14: 25.096 | N14: BLOCOS | O14: =A14&B14&C14 -> 4825Thozen - Electra
A15: 194 | B15: Thozen - Electra | C15: INSUMO | D15: Original | E15: ARGAMASSA ESTABILIZADA PARA ASSENTAMENTO | F15: m3 | G15: 0.0125 | H15: 480 | I15: 6
A16: 228 | B16: Thozen - Electra | C16: INSUMO | D16: Original | E16: BLOCO CERÂMICO 11,5X19X19CM | F16: un | G16: 17.36 | H16: 1.1 | I16: 19.096
A17: 4826 | B17: Thozen - Electra | D17: Original | E17: Alvenaria de vedação de blocos cerâmicos furados na horizontal de 14x19x19cm (espessura 14cm) com argamassa industrializada de assentamento | F17: m2 | I17: 40.7664 | N17: BLOCOS | O17: =A17&B17&C17 -> 4826Thozen - Electra
A18: 194 | B18: Thozen - Electra | C18: INSUMO | D18: Original | E18: ARGAMASSA ESTABILIZADA PARA ASSENTAMENTO | F18: m3 | G18: 0.022 | H18: 480 | I18: 10.56
A19: 232 | B19: Thozen - Electra | C19: INSUMO | D19: Original | E19: BLOCO CERÂMICO 14X19X19CM | F19: un | G19: 17.36 | H19: 1.74 | I19: 30.2064
A20: 90472 | B20: Thozen - Electra | D20: Original | E20: Alvenaria de vedação de blocos cerâmicos furados na horizontal de 19x19x19cm (espessura 19cm) com argamassa industrializada de assentamento | F20: m2 | I20: 56.5848 | N20: BLOCOS | O20: =A20&B20&C20 -> 90472Thozen - Electra
A21: 194 | B21: Thozen - Electra | C21: INSUMO | D21: Original | E21: ARGAMASSA ESTABILIZADA PARA ASSENTAMENTO | F21: m3 | G21: 0.03 | H21: 480 | I21: 14.4
A22: 48433 | B22: Thozen - Electra | C22: INSUMO | D22: Original | E22: BLOCO CERÂMICO 19X19X19CM | F22: un | G22: 17.36 | H22: 2.43 | I22: 42.1848
A23: 4831 | B23: Thozen - Electra | D23: Original | E23: Verga/contraverga de concreto, moldada in loco | F23: m | I23: 43.712512 | O23: =A23&B23&C23 -> 4831Thozen - Electra
A24: 759 | B24: Thozen - Electra | C24: INSUMO | D24: Original | E24: CONCRETO USINADO FCK 20 MPA, SLUMP 14+/-2 | F24: m3 | G24: 0.0264 | H24: 450 | I24: 11.88
A25: 4800 | B25: Thozen - Electra | C25: INSUMO | D25: Original | E25: DESMOLDANTE DE FORMAS PARA CONCRETO | F25: l | G25: 0.007 | H25: 6.45 | I25: 0.04515
A26: 1412 | B26: Thozen - Electra | C26: INSUMO | D26: Original | E26: ESPAÇADOR PLÁSTICO | F26: un | G26: 6 | H26: 0.15 | I26: 0.9
A27: 2324 | B27: Thozen - Electra | C27: INSUMO | D27: Original | E27: PONTALETE 7,5X7,5 CM PINUS | F27: m3 | G27: 0.0012 | H27: 1310 | I27: 1.572
A28: 2362 | B28: Thozen - Electra | C28: INSUMO | D28: Original | E28: PREGO POLIDO COM CABEÇA 17X21 | F28: kg | G28: 0.0512 | H28: 10.91 | I28: 0.558592
A29: 2546 | B29: Thozen - Electra | C29: INSUMO | D29: Original | E29: SARRAFO 2,5X7,5 CM PINUS | F29: m3 | G29: 0.003171 | H29: 1300 | I29: 4.1223
A30: 2611 | B30: Thozen - Electra | C30: INSUMO | D30: Original | E30: TÁBUA 1"X12" 2,5X30CM PINUS | F30: m3 | G30: 0.011676 | H30: 1800 | I30: 21.0168
A31: 32 | B31: Thozen - Electra | C31: INSUMO | D31: Original | E31: AÇO CA-50 DIÂMETRO 6,30 MM | F31: kg | G31: 0.5243 | H31: 6.9 | I31: 3.61767
A32: 4828 | B32: Thozen - Electra | D32: Original | E32: Encunhamento de alvenaria de vedação com argamassa expansiva | F32: m | I32: 3.633798 | N32: ENCUNHAMENTO | O32: =A32&B32&C32 -> 4828Thozen - Electra
A33: 48435 | B33: Thozen - Electra | C33: INSUMO | D33: Original | E33: ARGAMASSA EXPANSIVA PARA ENCUNHAMENTO | F33: Kg | G33: 0.2154 | H33: 16.87 | I33: 3.633798
A34: 4829 | B34: Thozen - Electra | D34: Original | E34: Tela soldada para ligação alvenaria/estrutura | F34: m² | I34: 1.85 | O34: =A34&B34&C34 -> 4829Thozen - Electra
A35: 718 | B35: Thozen - Electra | C35: INSUMO | D35: Original | E35: CARTUCHO 22 - CARGA LEVE PARA FINCA PINO E POLVORA | F35: un | G35: 1 | H35: 0.3 | I35: 0.3
A36: 2260 | B36: Thozen - Electra | C36: INSUMO | D36: Original | E36: PINO LISO EM AÇO GALVANIZADO 1/2 X 22MM COM ARRUELA | F36: un | G36: 1 | H36: 0.3 | I36: 0.3
A37: 2901 | B37: Thozen - Electra | C37: INSUMO | D37: Original | E37: TELA DE ACO SOLDADA, FIO 1,24MM, MALHA 15X15MM | F37: m2 | G37: 0.5 | H37: 2.5 | I37: 1.25
A38: 4842 | B38: Thozen - Electra | D38: Original | E38: Impermeabilização com argamassa polimérica, 3 demãos | F38: m2 | I38: 36.225 | O38: =A38&B38&C38 -> 4842Thozen - Electra
A39: 202 | B39: Thozen - Electra | C39: INSUMO | D39: Original | E39: ARGAMASSA POLIMÉRICA IMPERMEABILIZANTE | F39: kg | G39: 3.15 | H39: 11.5 | I39: 36.225
A40: 90541 | B40: Thozen - Electra | D40: Original | E40: Chapisco adesivo aplicado em concreto, com desempenadeira dentada | F40: m2 | I40: 6.459 | N40: CHAPISCO | O40: =A40&B40&C40 -> 90541Thozen - Electra
A41: 197 | B41: Thozen - Electra | C41: INSUMO | D41: Original | E41: ARGAMASSA ESTABILIZADA PARA REBOCO | F41: m3 | G41: 0.0033 | H41: 480 | I41: 1.584
A42: 48481 | B42: Thozen - Electra | C42: INSUMO | D42: Original | E42: ADITIVO ADESIVO LÍQUIDO PARA ARGAMASSA | F42: L | G42: 0.625 | H42: 7.8 | I42: 4.875
A43: 90507 | B43: Thozen - Electra | D43: Original | E43: Chapisco rolado aplicado em alvenaria, com desempenadeira dentada | F43: m2 | I43: 5.502 | N43: CHAPISCO | O43: =A43&B43&C43 -> 90507Thozen - Electra
A44: 48373 | B44: Thozen - Electra | C44: INSUMO | D44: Original | E44: CHAPISCO COLANTE 20KG | F44: Kg | G44: 4.2 | H44: 1.31 | I44: 5.502
A45: 4861 | B45: Thozen - Electra | D45: Original | E45: Massa única para paredes internas em argamassa estabilizada, aplicação manual, espessura 2cm, com execução de taliscas | F45: m2 | I45: 18.048 | N45: REBOCO | O45: =A45&B45&C45 -> 4861Thozen - Electra
A46: 197 | B46: Thozen - Electra | C46: INSUMO | D46: Original | E46: ARGAMASSA ESTABILIZADA PARA REBOCO | F46: m3 | G46: 0.0376 | H46: 480 | I46: 18.048
A47: 4865 | B47: Thozen - Electra | D47: Original | E47: Mão de obra para reboco interno, incluso chapisco | F47: m2 | I47: 35 | O47: =A47&B47&C47 -> 4865Thozen - Electra
A48: 2154 | B48: Thozen - Electra | C48: INSUMO | D48: Original | E48: MÃO DE OBRA PARA EXECUÇÃO DE CHAPISCO E REBOCO INTERNO EM PAREDES | F48: m2 | G48: 1 | H48: 35 | I48: 35
A49: 4899 | B49: Thozen - Electra | D49: Original | E49: Revestimento interno de parede em porcelanato, placa 30x90cm, aplicação em banheiros e cozinhas | F49: m2 | I49: 97.430075 | O49: =A49&B49&C49 -> 4899Thozen - Electra
A50: 193 | B50: Thozen - Electra | C50: INSUMO | D50: Original | E50: ARGAMASSA COLANTE AC III | F50: kg | G50: 9 | H50: 2.345 | I50: 21.105
A51: 4881 | B51: Thozen - Electra | C51: INSUMO | D51: Original | E51: ESPAÇADOR PARA REVESTIMENTO CERÂMICO TIPO CRUZETA 5 MM | F51: un | G51: 4 | H51: 0.2 | I51: 0.8
A52: 4880 | B52: Thozen - Electra | C52: INSUMO | D52: Original | E52: REJUNTE FLEXÍVEL | F52: m2 | G52: 0.25 | H52: 2.0643 | I52: 0.516075
A53: 48500 | B53: Thozen - Electra | C53: INSUMO | D53: Original | E53: REVESTIMENTO PORCELANATO INTERNO 30X90CM | F53: m2 | G53: 1.1 | H53: 68.19 | I53: 75.009
A54: 90511 | B54: Thozen - Electra | D54: Original | E54: Acabamentos de elevador em granito, acabamento polido, esp. 2cm | F54: m² | I54: 623.4139 | N54: PEITORIL | O54: =A54&B54&C54 -> 90511Thozen - Electra
A55: 193 | B55: Thozen - Electra | C55: INSUMO | D55: Original | E55: ARGAMASSA COLANTE AC III | F55: kg | G55: 8.62 | H55: 2.345 | I55: 20.2139
A56: 1526 | B56: Thozen - Electra | C56: INSUMO | D56: Original | E56: GRANITO POLIDO | F56: m2 | G56: 1.16 | H56: 520 | I56: 603.2
A57: 4902 | B57: Thozen - Electra | D57: Original | E57: Peitoril em granito, acabamento polido, esp. 2cm | F57: m² | I57: 623.4139 | N57: PEITORIL | O57: =A57&B57&C57 -> 4902Thozen - Electra
A58: 193 | B58: Thozen - Electra | C58: INSUMO | D58: Original | E58: ARGAMASSA COLANTE AC III | F58: kg | G58: 8.62 | H58: 2.345 | I58: 20.2139
A59: 1526 | B59: Thozen - Electra | C59: INSUMO | D59: Original | E59: GRANITO POLIDO | F59: m2 | G59: 1.16 | H59: 520 | I59: 603.2
A60: 4872 | B60: Thozen - Electra | D60: Original | E60: Forro de gesso acartonado, aplicação em áreas secas - material e mão de obra | F60: m2 | I60: 126.4 | N60: FORRO EM GESSO | O60: =A60&B60&C60 -> 4872Thozen - Electra
A61: 4874 | B61: Thozen - Electra | C61: INSUMO | D61: Original | E61: FORRO DE GESSO ACARTONADO, APLICAÇÃO EM ÁREAS SECAS - MATERIAL E MÃO DE OBRA | F61: m2 | G61: 1 | H61: 100 | I61: 100
A62: 1514 | B62: Thozen - Electra | C62: INSUMO | D62: Original | E62: GESSO NEGATIVO | F62: m | G62: 1.2 | H62: 22 | I62: 26.4
A63: 4876 | B63: Thozen - Electra | D63: Original | E63: Gesso negativo - material e mão de obra | F63: m | I63: 22 | O63: =A63&B63&C63 -> 4876Thozen - Electra
A64: 1514 | B64: Thozen - Electra | C64: INSUMO | D64: Original | E64: GESSO NEGATIVO | F64: m | G64: 1 | H64: 22 | I64: 22
A65: 1481 | B65: Thozen - Electra | D65: Original | E65: Textura acrilica aplicacao em teto, 1 demão, incluindo aplicação de uma demão de fundo selador látex pva | F65: m2 | I65: 9.171036 | N65: PINTURA TETO | O65: =A65&B65&C65 -> 1481Thozen - Electra
A66: 2940 | B66: Thozen - Electra | C66: INSUMO | D66: Original | E66: TEXTURA ACRÍLICA | F66: kg | G66: 1.1074 | H66: 7.23 | I66: 8.006502
A67: 2553 | B67: Thozen - Electra | C67: INSUMO | D67: Original | E67: SELADOR LÁTEX PVA | F67: l | G67: 0.1666 | H67: 6.99 | I67: 1.164534
A68: 4873 | B68: Thozen - Electra | D68: Original | E68: Forro de gesso acartonado, aplicação em áreas molhadas - material e mão de obra | F68: m2 | I68: 136.4 | N68: FORRO EM GESSO | O68: =A68&B68&C68 -> 4873Thozen - Electra
A69: 4875 | B69: Thozen - Electra | C69: INSUMO | D69: Original | E69: FORRO DE GESSO ACARTONADO, APLICAÇÃO EM ÁREAS ÚMIDAS - MATERIAL E MÃO DE OBRA | F69: m2 | G69: 1 | H69: 110 | I69: 110
A70: 1514 | B70: Thozen - Electra | C70: INSUMO | D70: Original | E70: GESSO NEGATIVO | F70: m | G70: 1.2 | H70: 22 | I70: 26.4
A71: 60 | B71: Thozen - Electra | D71: Original | E71: Contrapiso comum em argamassa estabilizada, nao aderido, espessura 5cm | F71: m2 | I71: 26.4 | N71: CONTRAPISO | O71: =A71&B71&C71 -> 60Thozen - Electra
A72: 458 | B72: Thozen - Electra | C72: INSUMO | D72: Original | E72: ARGAMASSA ESTABILIZADA P/ CONTRAPISO | F72: M3 | G72: 0.055 | H72: 480 | I72: 26.4
A73: 4863 | B73: Thozen - Electra | D73: Original | E73: Mão de obra de execução contrapiso comum | F73: m2 | I73: 32 | O73: =A73&B73&C73 -> 4863Thozen - Electra
A74: 2156 | B74: Thozen - Electra | C74: INSUMO | D74: Original | E74: MÃO DE OBRA PARA EXECUÇÃO DE CONTRAPISO | F74: m2 | G74: 1 | H74: 32 | I74: 32
A75: 4883 | B75: Thozen - Electra | D75: Original | E75: Revestimento interno de piso porcelanato, placa 80x80, aplicação em áreas internas | F75: m2 | I75: 93.8717 | O75: =A75&B75&C75 -> 4883Thozen - Electra
A76: 193 | B76: Thozen - Electra | C76: INSUMO | D76: Original | E76: ARGAMASSA COLANTE AC III | F76: kg | G76: 9 | H76: 2.345 | I76: 21.105
A77: 4881 | B77: Thozen - Electra | C77: INSUMO | D77: Original | E77: ESPAÇADOR PARA REVESTIMENTO CERÂMICO TIPO CRUZETA 5 MM | F77: un | G77: 4 | H77: 0.2 | I77: 0.8
A78: 4884 | B78: Thozen - Electra | C78: INSUMO | D78: Original | E78: PISO PORCELANATO 80X80CM, ACABAMENTO NATURAL, PADRÃO MÉDIO | F78: m2 | G78: 1.1 | H78: 65 | I78: 71.5
A79: 2521 | B79: Thozen - Electra | C79: INSUMO | D79: Original | E79: REJUNTE ACRÍLICO | F79: kg | G79: 0.13 | H79: 3.59 | I79: 0.4667
A80: 90521 | B80: Thozen - Electra | D80: Original | E80: Rodapé em poliestireno, altura 15cm | F80: m | I80: 82.225797 | O80: =A80&B80&C80 -> 90521Thozen - Electra
A81: 417 | B81: Thozen - Electra | C81: INSUMO | D81: Original | E81: BUCHA T PARA RODAPÉ | F81: un | G81: 2.5 | H81: 1.99 | I81: 4.975
A82: 738 | B82: Thozen - Electra | C82: INSUMO | D82: Original | E82: COLA PARA RODAPÉ DE POLIESTIRENO | F82: kg | G82: 0.0694 | H82: 5.0403 | I82: 0.34979682
A83: 48465 | B83: Thozen - Electra | C83: INSUMO | D83: Original | E83: RODAPÉ POLIESTIRENO H=15CM | F83: m | G83: 1.1 | H83: 69.91 | I83: 76.901
A84: 4882 | B84: Thozen - Electra | D84: Original | E84: Rodapé em poliestireno, altura 10cm | F84: m | I84: 17.655797 | O84: =A84&B84&C84 -> 4882Thozen - Electra
A85: 417 | B85: Thozen - Electra | C85: INSUMO | D85: Original | E85: BUCHA T PARA RODAPÉ | F85: un | G85: 2.5 | H85: 1.99 | I85: 4.975
A86: 738 | B86: Thozen - Electra | C86: INSUMO | D86: Original | E86: COLA PARA RODAPÉ DE POLIESTIRENO | F86: kg | G86: 0.0694 | H86: 5.0403 | I86: 0.34979682
A87: 2538 | B87: Thozen - Electra | C87: INSUMO | D87: Original | E87: RODAPÉ POLIESTIRENO H=10CM | F87: m | G87: 1.1 | H87: 11.21 | I87: 12.331
A88: 4891 | B88: Thozen - Electra | D88: Original | E88: Rodapé em porcelanato, altura 10cm, com placa 80x80 | F88: m | I88: 9.7339012 | O88: =A88&B88&C88 -> 4891Thozen - Electra
A89: 193 | B89: Thozen - Electra | C89: INSUMO | D89: Original | E89: ARGAMASSA COLANTE AC III | F89: kg | G89: 0.9 | H89: 2.345 | I89: 2.1105
A90: 1412 | B90: Thozen - Electra | C90: INSUMO | D90: Original | E90: ESPAÇADOR PLÁSTICO | F90: un | G90: 2 | H90: 0.15 | I90: 0.3
A91: 4884 | B91: Thozen - Electra | C91: INSUMO | D91: Original | E91: PISO PORCELANATO 80X80CM, ACABAMENTO NATURAL, PADRÃO MÉDIO | F91: m2 | G91: 0.11 | H91: 65 | I91: 7.15
A92: 4880 | B92: Thozen - Electra | C92: INSUMO | D92: Original | E92: REJUNTE FLEXÍVEL | F92: m2 | G92: 0.084 | H92: 2.0643 | I92: 0.1734012
A93: 4898 | B93: Thozen - Electra | D93: Original | E93: Soleira de granito, acabamento polido, espessura 2cm | F93: m2 | I93: 593.64172 | O93: =A93&B93&C93 -> 4898Thozen - Electra
A94: 193 | B94: Thozen - Electra | C94: INSUMO | D94: Original | E94: ARGAMASSA COLANTE AC III | F94: kg | G94: 9 | H94: 2.345 | I94: 21.105
A95: 1526 | B95: Thozen - Electra | C95: INSUMO | D95: Original | E95: GRANITO POLIDO | F95: m2 | G95: 1.1 | H95: 520 | I95: 572
A96: 4880 | B96: Thozen - Electra | C96: INSUMO | D96: Original | E96: REJUNTE FLEXÍVEL | F96: m2 | G96: 0.26 | H96: 2.0643 | I96: 0.536718
A97: 90559 | B97: Thozen - Electra | D97: Original | E97: Massa latex acrílica em paredes internas 2 demaos | F97: m2 | I97: 11.9703 | N97: MASSA | O97: =A97&B97&C97 -> 90559Thozen - Electra
A98: 1400 | B98: Thozen - Electra | C98: INSUMO | D98: Original | E98: LIXA EM FOLHA PARA PAREDE OU MADEIRA N° 120 | F98: UN | G98: 0.1 | H98: 18.48 | I98: 1.848
A99: 48483 | B99: Thozen - Electra | C99: INSUMO | D99: Original | E99: MASSA ACRÍLICA | F99: kg | G99: 0.8802 | H99: 11.5 | I99: 10.1223
A100: 4926 | B100: Thozen - Electra | D100: Original | E100: Pintura com tinta acrílica em paredes internas, aplicação manual, 3 demãos | F100: m2 | I100: 20.035312 | N100: PINTURA ACRÍLICA | O100: =A100&B100&C100 -> 4926Thozen - Electra
A101: 2944 | B101: Thozen - Electra | C101: INSUMO | D101: Original | E101: TINTA LÁTEX ACRÍLICA | F101: l | G101: 0.34275 | H101: 36.67 | I101: 12.568643
A102: 2186 | B102: Thozen - Electra | C102: INSUMO | D102: Original | E102: MASSA CORRIDA PVA | F102: kg | G102: 1.3389 | H102: 3.6 | I102: 4.82004
...

Sheet Insumos (2)
A1: DADOS
A2: Titulo | B2: Tabela de insumos utilizados no projeto
A3: Obra | B3: ELECTRA TOWERS
A4: Cliente | B4: THOZEN
A5: Cidade | B5: Porto Belo
A6: Endereço
A7: Descrição
A8: UF | B8: SC
A11: INSUMOS UTILIZADOS
A12: Código | B12: Tabela | C12: Tipo | D12: Descrição | E12: Unid. | F12: Preço | G12: Origem custo | H12: Justificativa
A14: 194 | B14: Thozen - Electra | C14: Material | D14: ARGAMASSA ESTABILIZADA PARA ASSENTAMENTO | E14: m3 | F14: 480 | I14: =A14&B14 -> 194Thozen - Electra
A15: 228 | B15: Thozen - Electra | C15: Material | D15: BLOCO CERÂMICO 11,5X19X19CM | E15: un | F15: 1.1 | I15: =A15&B15 -> 228Thozen - Electra
A16: 232 | B16: Thozen - Electra | C16: Material | D16: BLOCO CERÂMICO 14X19X19CM | E16: un | F16: 1.74 | I16: =A16&B16 -> 232Thozen - Electra
A17: 48433 | B17: Thozen - Electra | C17: Material | D17: BLOCO CERÂMICO 19X19X19CM | E17: un | F17: 2.43 | I17: =A17&B17 -> 48433Thozen - Electra
A18: 759 | B18: Thozen - Electra | C18: Material | D18: CONCRETO USINADO FCK 20 MPA, SLUMP 14+/-2 | E18: m3 | F18: 450 | I18: =A18&B18 -> 759Thozen - Electra
A19: 4800 | B19: Thozen - Electra | C19: Material | D19: DESMOLDANTE DE FORMAS PARA CONCRETO | E19: l | F19: 6.45 | I19: =A19&B19 -> 4800Thozen - Electra
A20: 1412 | B20: Thozen - Electra | C20: Material | D20: ESPAÇADOR PLÁSTICO | E20: un | F20: 0.15 | I20: =A20&B20 -> 1412Thozen - Electra
A21: 2324 | B21: Thozen - Electra | C21: Material | D21: PONTALETE 7,5X7,5 CM PINUS | E21: m3 | F21: 1310 | I21: =A21&B21 -> 2324Thozen - Electra
A22: 2362 | B22: Thozen - Electra | C22: Material | D22: PREGO POLIDO COM CABEÇA 17X21 | E22: kg | F22: 10.91 | I22: =A22&B22 -> 2362Thozen - Electra
A23: 2546 | B23: Thozen - Electra | C23: Material | D23: SARRAFO 2,5X7,5 CM PINUS | E23: m3 | F23: 1300 | I23: =A23&B23 -> 2546Thozen - Electra
A24: 2611 | B24: Thozen - Electra | C24: Material | D24: TÁBUA 1"X12" 2,5X30CM PINUS | E24: m3 | F24: 1800 | I24: =A24&B24 -> 2611Thozen - Electra
A25: 32 | B25: Thozen - Electra | C25: Material | D25: AÇO CA-50 DIÂMETRO 6,30 MM | E25: kg | F25: 6.9 | G25: GERDAU | I25: =A25&B25 -> 32Thozen - Electra
A26: 48435 | B26: Thozen - Electra | C26: Material | D26: ARGAMASSA EXPANSIVA PARA ENCUNHAMENTO | E26: Kg | F26: 16.87 | I26: =A26&B26 -> 48435Thozen - Electra
A27: 718 | B27: Thozen - Electra | C27: Material | D27: CARTUCHO 22 - CARGA LEVE PARA FINCA PINO E POLVORA | E27: un | F27: 0.3 | I27: =A27&B27 -> 718Thozen - Electra
A28: 2260 | B28: Thozen - Electra | C28: Material | D28: PINO LISO EM AÇO GALVANIZADO 1/2 X 22MM COM ARRUELA | E28: un | F28: 0.3 | I28: =A28&B28 -> 2260Thozen - Electra
A29: 2901 | B29: Thozen - Electra | C29: Material | D29: TELA DE ACO SOLDADA, FIO 1,24MM, MALHA 15X15MM | E29: m2 | F29: 2.5 | I29: =A29&B29 -> 2901Thozen - Electra
A30: 202 | B30: Thozen - Electra | C30: Material | D30: ARGAMASSA POLIMÉRICA IMPERMEABILIZANTE | E30: kg | F30: 11.5 | I30: =A30&B30 -> 202Thozen - Electra
A31: 197 | B31: Thozen - Electra | C31: Material | D31: ARGAMASSA ESTABILIZADA PARA REBOCO | E31: m3 | F31: 480 | I31: =A31&B31 -> 197Thozen - Electra
A32: 48481 | B32: Thozen - Electra | C32: Material | D32: ADITIVO ADESIVO LÍQUIDO PARA ARGAMASSA | E32: L | F32: 7.8 | I32: =A32&B32 -> 48481Thozen - Electra
A33: 48373 | B33: Thozen - Electra | C33: Material | D33: CHAPISCO COLANTE 20KG | E33: Kg | F33: 1.31 | I33: =A33&B33 -> 48373Thozen - Electra
A34: 2154 | B34: Thozen - Electra | C34: Mao_obra | D34: MÃO DE OBRA PARA EXECUÇÃO DE CHAPISCO E REBOCO INTERNO EM PAREDES | E34: m2 | F34: 35 | I34: =A34&B34 -> 2154Thozen - Electra
A35: 193 | B35: Thozen - Electra | C35: Material | D35: ARGAMASSA COLANTE AC III | E35: kg | F35: 2.345 | I35: =A35&B35 -> 193Thozen - Electra
A36: 4881 | B36: Thozen - Electra | C36: Material | D36: ESPAÇADOR PARA REVESTIMENTO CERÂMICO TIPO CRUZETA 5 MM | E36: un | F36: 0.2 | I36: =A36&B36 -> 4881Thozen - Electra
A37: 4880 | B37: Thozen - Electra | C37: Material | D37: REJUNTE FLEXÍVEL | E37: m2 | F37: 2.0643 | I37: =A37&B37 -> 4880Thozen - Electra
... A61: 2552 | B61: Thozen - Electra | C61: Material | D61: SELADOR ACRÍLICO | E61: l | F61: 9.44 | I61: =A61&B61 -> 2552Thozen - Electra

Sheet PROJETOS
B1: GESTÃO DOS PROJETOS | J1: LEGENDA
A2: Obra | B2: Electra Towers (Rubens Alves) | J2: NÃO SE APLICA
A3: Empresa | B3: Thozen Empreendimentos | J3: PENDENTE
A4: Revisão | B4: R01 | J4: RECEBIDO
B5: PAVIMENTO | C5: DISCIPLINA | D5: PROJETOS | E5: CAMINHO | F5: STATUS | G5: OBSERVAÇÕES | J5: REVISADO
B7: ESTRUTURA
B8: TERRAPLENAGEM | C8: INFRAESTRUTURA | F8: NÃO SE APLICA
B9: MOVIMENTAÇÃO DE TERRA | C9: INFRAESTRUTURA | F9: PENDENTE
B10: FUNDAÇÃO PROFUNDA | C10: INFRAESTRUTURA | D10: 1203 - PREFORMAS - R20.DWG | E10: 01 ESTRUTURA/DWG | F10: RECEBIDO | G10: DWG Pré-formas Rev.20
B11: FUNDAÇÃO RASA | C11: INFRAESTRUTURA | D11: 1203 - THOZEN - RUBENS ALVES - BLOCOS+RAMPAS DE ACESSO - R26.ifc | E11: 01 ESTRUTURA/IFC | F11: RECEBIDO | G11: IFC Blocos + Rampas de Acesso Rev.26
B12: CONTENÇÃO | C12: INFRAESTRUTURA | F12: NÃO SE APLICA
B13: ÁREA – 1º PAVTO. (TÉRREO) | C13: SUPRAESTRUTURA | F13: RECEBIDO | G13: Coberto pelo IFC estrutural completo
B14: ÁREA – MEZANINO DO 1º PAVTO. | C14: SUPRAESTRUTURA | F14: RECEBIDO | G14: Coberto pelo IFC estrutural completo
B15: ÁREA – 2º PAVIMENTO | C15: SUPRAESTRUTURA | F15: RECEBIDO | G15: Coberto pelo IFC estrutural completo
B16: ÁREA – MEZANINO DO 2º PAVTO. | C16: SUPRAESTRUTURA | F16: RECEBIDO | G16: Coberto pelo IFC estrutural completo
B17: ÁREA – 3º PAVIMENTO | C17: SUPRAESTRUTURA | F17: RECEBIDO | G17: Coberto pelo IFC estrutural completo
B18: ÁREA – MEZANINO DO 3º PAVTO. | C18: SUPRAESTRUTURA | F18: RECEBIDO | G18: Coberto pelo IFC estrutural completo
B19: ÁREA – 4º PAVIMENTO GARAGEM/LAZER | C19: SUPRAESTRUTURA | F19: RECEBIDO | G19: Coberto pelo IFC estrutural completo
B20: ÁREA – 5º PAVIMENTO LAZER | C20: SUPRAESTRUTURA | F20: RECEBIDO | G20: Coberto pelo IFC estrutural completo
B21: ÁREA – 6º PAVIMENTO TIPO - DIFERENCIADO | C21: SUPRAESTRUTURA | F21: RECEBIDO | G21: Coberto pelo IFC estrutural completo
B22: ÁREA – 7º AO 14° PAVIMENTO TIPO - X8 | C22: SUPRAESTRUTURA | F22: RECEBIDO | G22: Coberto pelo IFC estrutural completo
B23: ÁREA – 15º AO 35° PAVIMENTO TIPO - X21 | C23: SUPRAESTRUTURA | F23: RECEBIDO | G23: Coberto pelo IFC estrutural completo
B24: ARQUITETURA
B25: TERRAPLENAGEM | C25: ARQUITETURA | F25: NÃO SE APLICA
B26: MOVIMENTAÇÃO DE TERRA | C26: ARQUITETURA | F26: NÃO SE APLICA
B27: FUNDAÇÃO PROFUNDA | C27: ARQUITETURA | F27: NÃO SE APLICA
B28: FUNDAÇÃO RASA | C28: ARQUITETURA | F28: NÃO SE APLICA
B29: CONTENÇÃO | C29: ARQUITETURA | F29: NÃO SE APLICA
B30: TÉRREO 01 | C30: ARQUITETURA | D30: RA_ARQ_EXE_01_TÉRREO_R02.dwg | E30: 02 ARQUITETURA/DWG | F30: RECEBIDO | G30: DWG Executivo Rev.02
B31: TÉRREO 02 | C31: ARQUITETURA | D31: RA_ARQ_EXE_10_CORTE1_R02.dwg + RA_ARQ_EXE_11_CORTE2_R02.dwg | E31: 02 ARQUITETURA/DWG | F31: RECEBIDO | G31: Cortes 1 e 2, Rev.02
