Workbook
Name \0: #REF!
Name \0: #REF!
Name \a: #REF!
Name \a: #REF!
Name \m: #REF!
Name aa: #REF!
Name aa: #REF!
Name aaaa: '[1]M.O.'!#REF!
Name aaaa: '[1]M.O.'!#REF!
Name angelo: [2]Geral!#REF!
Name angelo: [2]Geral!#REF!
Name area: #REF!
Name Areaimpresso: #REF!
Name aux: #REF!
Name aux: #REF!
Name BDA: #REF!
Name BDA: #REF!
Name BDI: #REF!
Name ca: #REF!
Name Capa: #REF!
Name cronograma: #REF!
Name D: #REF!
Name direto: #REF!
Name DRE: #REF!
Name ea: #REF!
Name FFFFFFF: #REF!
Name FFFFFFF: #REF!
Name item_1: #REF!
Name LS: '[1]M.O.'!#REF!
Name MENU: #REF!
Name MENU: #REF!
Name MENU1: #REF!
Name MENU1: #REF!
Name MENU2: #REF!
Name MENU2: #REF!
Name MENU3: #REF!
Name MENU4: #REF!
Name MENU5: #REF!
Name MENU6: #REF!
Name mo: #REF!
Name OAE: #REF!
Name ParamValues1: [3]ParamValues!$A$1:$A$11
Name PAV: #REF!
Name pr: #REF!
Name PRE: #REF!
Name Print_Area: #REF!
Name Print_Area_MI: #REF!
Name Print_Titles: #REF!
Name qe: #REF!
Name qee: #REF!
Name reforsu: #REF!
Name ren: #REF!
Name REV: #REF!
Name sa: #REF!
Name SEG: #REF!
Name SIH: #REF!
Name SIV: #REF!
Name ss: #REF!
Name susref: #REF!
Name tania: #REF!

Sheet CAPA
A1: Obra | B1: GRAN TOWER
A2: Empresa | B2: GRANDEZZA EMPREENDIMENTOS
A3: Revisão | B3: R02
A4: Data | B4: 45503
A26: ORÇAMENTO EXECUTIVO
A28: GRANDEZZA - GRAN TOWER
A55: Itajaí, Julho de 2024

Sheet Resumo
A1: Obra | B1: GRAN TOWER
A2: Empresa | B2: GRANDEZZA EMPREENDIMENTOS
A3: Revisão | B3: R02
A4: Data | B4: 45503
A5: RESUMO
B7: ÁREA CONSTRUÍDA | D7: 6245.48 | E7: m²
B9: ETAPA | C9: VALOR ORÇADO | D9: % | E9: VALOR / m²
B10: GERENCIAMENTO TÉCNICO E ADMINISTRATIVO | C10: =ORÇAMENTO_EXECUTIVO!F13 -> 2384931.9 | D10: =C10/C$27 -> 0.11225506 | E10: =C10/$D$7 -> 381.86527
B11: MOVIMENTAÇÃO DE TERRA | C11: =ORÇAMENTO_EXECUTIVO!F108 -> 230869.63 | D11: =C11/C$27 -> 0.010866677 | E11: =C11/$D$7 -> 36.965875
B12: INFRAESTRUTURA | C12: =ORÇAMENTO_EXECUTIVO!F112 -> 933522.84 | D12: =C12/C$27 -> 0.04393948 | E12: =C12/$D$7 -> 149.47175
B13: SUPRAESTRUTURA | C13: =ORÇAMENTO_EXECUTIVO!F131 -> 4384787.1 | D13: =C13/C$27 -> 0.20638516 | E13: =C13/$D$7 -> 702.07367
B14: PAREDES E PAINEIS | C14: =ORÇAMENTO_EXECUTIVO!F150 -> 863630.83 | D14: =C14/C$27 -> 0.040649771 | E14: =C14/$D$7 -> 138.28094
B15: INSTALAÇÕES ELÉTRICAS, HIDRÁULICAS, GLP E PREVENTIVAS | C15: =ORÇAMENTO_EXECUTIVO!F199+ORÇAMENTO_EXECUTIVO!F214+ORÇAMENTO_EXECUTIVO!F230+ORÇAMENTO_EXECUTIVO!F244+ORÇAMENTO_EXECUTIVO!F254+ORÇAMENTO_EXECUTIVO!F385 -> 1935344.2 | D15: =C15/C$27 -> 0.091093667 | E15: =C15/$D$7 -> 309.87918
B16: EQUIPAMENTOS E SISTEMAS ESPECIAIS | C16: =ORÇAMENTO_EXECUTIVO!F263+ORÇAMENTO_EXECUTIVO!F270 -> 1404690.9 | D16: =C16/C$27 -> 0.066116634 | E16: =C16/$D$7 -> 224.9132
B17: IMPERMEABILIZAÇÃO | C17: =ORÇAMENTO_EXECUTIVO!F169 -> 420004.94 | D17: =C17/C$27 -> 0.019768985 | E17: =C17/$D$7 -> 67.249425
B18: REVESTIMENTOS INTERNOS DE PAREDE | C18: =ORÇAMENTO_EXECUTIVO!F277 -> 1030085.4 | D18: =C18/C$27 -> 0.048484531 | E18: =C18/$D$7 -> 164.93295
B19: REVESTIMENTOS E ACABAMENTOS INTERNOS EM TETO | C19: =ORÇAMENTO_EXECUTIVO!F293 -> 344380.88 | D19: =C19/C$27 -> 0.016209477 | E19: =C19/$D$7 -> 55.140819
B20: PISOS E PAVIMENTAÇÕES | C20: =ORÇAMENTO_EXECUTIVO!F305 -> 1388564.5 | D20: =C20/C$27 -> 0.065357591 | E20: =C20/$D$7 -> 222.33111
B21: PINTURA INTERNA | C21: =ORÇAMENTO_EXECUTIVO!F339 -> 712320.05 | D21: =C21/C$27 -> 0.033527806 | E21: =C21/$D$7 -> 114.05369
B22: ESQUADRIAS, VIDROS E FERRAGENS | C22: =ORÇAMENTO_EXECUTIVO!F358 -> 1623887.7 | D22: =C22/C$27 -> 0.07643389 | E22: =C22/$D$7 -> 260.01007
B23: COBERTURA | C23: =ORÇAMENTO_EXECUTIVO!F393 -> 32717.5 | D23: =C23/C$27 -> 0.0015399623 | E23: =C23/$D$7 -> 5.2385885
B24: REVESTIMENTOS E ACABAMENTOS DE FACHADA | C24: =ORÇAMENTO_EXECUTIVO!F404 -> 1579912.1 | D24: =C24/C$27 -> 0.074364026 | E24: =C24/$D$7 -> 252.96888
B25: SERVIÇOS COMPLEMENTARES | C25: =ORÇAMENTO_EXECUTIVO!F421 -> 1676000 | D25: =C25/C$27 -> 0.078886735 | E25: =C25/$D$7 -> 268.35407
B26: IMPREVISTOS E CONTINGENCIAS | C26: =ORÇAMENTO_EXECUTIVO!F431 -> 300000 | D26: =C26/C$27 -> 0.014120537 | E26: =C26/$D$7 -> 48.034739
B27: TOTAL | C27: =SUM(C10:C26) -> 21245651 | D27: =SUM(D10:D26) -> 1 | E27: =SUM(E10:E26) -> 3401.7642
B28: CUB/SC | C28: 2793.27 | D28: 45474 | E28: =+E27/C28 -> 1.217843
A30: Area privativa
B32: DESCRIÇÃO - 25 APARTAMENTOS (ÁREA TOTAL) | C32: ÁREA | D32: VALOR TOTAL
B33: VALOR POR UNIDADE PRIVATIVA (R$/m²) | C33: 3199.82 | D33: =C27/C33 -> 6639.6393
B34: VALOR POR UNIDADE TIPO 01 | C34: =121 -> 121 | D34: =D33*C34 -> 803396.35
B35: VALOR POR UNIDADE TIPO 02 | C35: =121 -> 121 | D35: =D33*C35 -> 803396.35
B36: VALOR POR UNIDADE DIFERENCIADO | C36: 245.7 | D36: =C36*D33 -> 1631359.4
B37: VALOR POR UNIDADE TIPO 03 | C37: =124.58 -> 124.58 | D37: =C37*D33 -> 827166.26
A39: Comparações
B41: ETAPA | C41: GRAN TOWER | E41: OBRAS DE REFERÊNCIA
C42: VALOR | D42: VALOR / m² | E42: VALOR / m²
B43: =B11 -> MOVIMENTAÇÃO DE TERRA | C43: =C11 -> 230869.63 | D43: =E11 -> 36.965875 | E43: 10,00 -15,00
B44: =B12 -> INFRAESTRUTURA | C44: =C12 -> 933522.84 | D44: =E12 -> 149.47175 | E44: 140,00 -190,00
B45: =B13 -> SUPRAESTRUTURA | C45: =C13 -> 4384787.1 | D45: =E13 -> 702.07367 | E45: 650,00 -695,00
B46: =B14 -> PAREDES E PAINEIS | C46: =C14 -> 863630.83 | D46: =E14 -> 138.28094 | E46: 120,00 -135,00
B47: =B15 -> INSTALAÇÕES ELÉTRICAS, HIDRÁULICAS, GLP E PREVENTIVAS | C47: =C15 -> 1935344.2 | D47: =E15 -> 309.87918 | E47: 270,00 -365,00
B48: =B16 -> EQUIPAMENTOS E SISTEMAS ESPECIAIS | C48: =C16 -> 1404690.9 | D48: =E16 -> 224.9132 | E48: 140,00 -170,00
B49: =B17 -> IMPERMEABILIZAÇÃO | C49: =C17 -> 420004.94 | D49: =E17 -> 67.249425 | E49: 45,00 -80,00
B50: =B18 -> REVESTIMENTOS INTERNOS DE PAREDE | C50: =C18 -> 1030085.4 | D50: =E18 -> 164.93295 | E50: 145,00 -190,00
B51: =B19 -> REVESTIMENTOS E ACABAMENTOS INTERNOS EM TETO | C51: =C19 -> 344380.88 | D51: =E19 -> 55.140819 | E51: 50,00 -70,00
B52: =B20 -> PISOS E PAVIMENTAÇÕES | C52: =C20 -> 1388564.5 | D52: =E20 -> 222.33111 | E52: 170,00 -210,00
B53: =B21 -> PINTURA INTERNA | C53: =C21 -> 712320.05 | D53: =E21 -> 114.05369 | E53: 100,00 -135,00
B54: =B22 -> ESQUADRIAS, VIDROS E FERRAGENS | C54: =C22 -> 1623887.7 | D54: =E22 -> 260.01007 | E54: 250,00 -290,00
... B57: =B25 -> SERVIÇOS COMPLEMENTARES | C57: =C25 -> 1676000 | D57: =E25 -> 268.35407 | E57: 160,00 -220,00
B58: TOTAL | C58: =SUM(C43:C57) -> 18560719 | D58: =SUM(D43:D57) -> 2971.8642 | E58: 2.370,00 -2.910,00

Sheet ORÇAMENTO_EXECUTIVO
A1: ORÇAMENTO EXECUTIVO
A7: Cliente | B7: GRANDEZZA
A8: Obra | B8: GRAN TOWER
A9: Data | B9: 45503
A10: Versão | B10: R02
A12: Código | B12: Descrição | C12: Un. | D12: Quantidade orçada | E12: Preço unitário | F12: Preço total | G12: Considerações
A13: 01 | B13: GERENCIAMENTO TÉCNICO E ADMINISTRATIVO | F13: 2384931.9
A14: 01.01 | B14: GERENCIAMENTO TÉCNICO | F14: =F15+F42 -> 704184.6
A15: 01.01.001 | B15: ESTUDOS | PROJETOS | CONSULTORIAS | F15: =SUM(F16+F23+F40) -> 511004.81
A16: 01.01.001.0001 | B16: Estudos | F16: =SUM(F17:F22) -> 65491
A17: 01.001.001.001 | B17: Memorial descrtivo | C17: VB | D17: 1 | E17: 6789 | F17: =E17*D17 -> 6789 | G17: Valor repassado pelo Grandezza, respondido no formulário de custos indiretos
A18: 01.001.001.002 | B18: Levantamento topográfico | C18: VB | D18: 1 | E18: 6789 | F18: =E18*D18 -> 6789 | G18: Valor repassado pelo Grandezza, respondido no formulário de custos indiretos
A19: 01.001.001.003 | B19: Estudo geológico | C19: VB | D19: 1 | E19: 6789 | F19: =E19*D19 -> 6789 | G19: Valor repassado pelo Grandezza, respondido no formulário de custos indiretos
A20: 01.001.001.004 | B20: Estudo ambiental | C20: VB | D20: 1 | E20: 16158 | F20: =E20*D20 -> 16158 | G20: Valor repassado pelo Grandezza, respondido no formulário de custos indiretos
A21: 01.001.001.005 | B21: Sondagem do terreno | C21: VB | D21: 1 | E21: 22177 | F21: =E21*D21 -> 22177 | G21: Valor repassado pelo Grandezza, respondido no formulário de custos indiretos
A22: 01.001.001.006 | B22: Projeto de canteiro | C22: VB | D22: 1 | E22: 6789 | F22: =E22*D22 -> 6789 | G22: Valor repassado pelo Grandezza, respondido no formulário de custos indiretos
A23: 01.01.001.0002 | B23: Projetos | F23: =SUM(F24:F39) -> 408226.81
A24: 01.01.001.0002.0001 | B24: Legalização de incorporação | C24: vb | D24: 1 | E24: 11611.7 | F24: 11611.7 | G24: Valor repassado pelo Grandezza, respondido no formulário de custos indiretos
A25: 01.01.001.0002.0002 | B25: Projeto arquitetônico legal | C25: vb | D25: 1 | E25: 79546 | F25: 79546 | G25: Valor repassado pelo Grandezza, respondido no formulário de custos indiretos
A26: 01.01.001.0002.0003 | B26: Projeto arquitetônico executivo | C26: vb | D26: 1 | E26: 50000 | F26: 50000 | G26: Valor repassado pelo Grandezza, respondido no formulário de custos indiretos
A27: 01.01.001.0002.0004 | B27: Projeto arquitetônico interiores | C27: vb | D27: 1 | E27: 67889 | F27: 67889 | G27: Valor repassado pelo Grandezza, respondido no formulário de custos indiretos
A28: 01.01.001.0002.0005 | B28: Projeto arquitetônico de fachada | C28: vb | D28: 1 | E28: 2187.34 | F28: 2187.34 | G28: Valor repassado pelo Grandezza, respondido no formulário de custos indiretos
A29: 01.01.001.0002.0006 | B29: Projeto de fundação | C29: vb | D29: 1 | E29: 3729 | F29: 3729 | G29: Valor repassado pelo Grandezza, respondido no formulário de custos indiretos
A30: 01.01.001.0002.0007 | B30: Projeto estrutural de concreto armado | C30: vb | D30: 1 | E30: 41587 | F30: 41587 | G30: Valor repassado pelo Grandezza, respondido no formulário de custos indiretos
A31: 01.01.001.0002.0008 | B31: Projeto de estrutura metálica | C31: vb | D31: 1 | E31: 30000 | F31: 30000 | G31: Valor repassado pelo Grandezza, respondido no formulário de custos indiretos
A32: 01.01.001.0002.0009 | B32: Projeto elétrico | C32: vb | D32: 1 | E32: 33310 | F32: 33310 | G32: Valor repassado pelo Grandezza, respondido no formulário de custos indiretos
A33: 01.01.001.0002.0010 | B33: Projeto de automação | C33: vb | D33: 1 | E33: 2000 | F33: 2000 | G33: Valor repassado pelo Grandezza, respondido no formulário de custos indiretos
A34: 01.01.001.0002.0011 | B34: Projeto hidrossanitário | C34: vb | D34: 1 | E34: 41016 | F34: 41016 | G34: Valor repassado pelo Grandezza, respondido no formulário de custos indiretos
A35: 01.01.001.0002.0012 | B35: Projeto preventivo | C35: vb | D35: 1 | E35: 4972 | F35: 4972 | G35: Valor repassado pelo Grandezza, respondido no formulário de custos indiretos
... A39: 01.01.001.0002.0016 | B39: Projeto de paisagismo | C39: vb | D39: 1 | E39: 1514.48 | F39: 1514.48 | G39: Valor repassado pelo Grandezza, respondido no formulário de custos indiretos
A40: 01.01.001.0003 | B40: Consultorias | F40: =SUM(F41:F41) -> 37287
A41: 01.01.001.0003.0001 | B41: Consultoria técnica de legalização | C41: VB | D41: 1 | E41: 37287 | F41: =E41*D41 -> 37287 | G41: Valor repassado pelo Grandezza, respondido no formulário de custos indiretos
A42: 01.01.002 | B42: TAXAS | DOCUMENTOS | F42: =F43 -> 193179.79
A43: 01.01.002.0001 | B43: Licenciamento - Taxas - Impostos | F43: =SUM(F44:F55) -> 193179.79
A44: 01.01.002.0001.0001 | B44: Despesas de seguro de obra | C44: VB | D44: 1 | E44: 37287 | F44: =E44*D44 -> 37287 | G44: Valor repassado pelo Grandezza, respondido no formulário de custos indiretos
A45: 01.01.002.0001.0003 | B45: Aprovação e legalização ambiental | C45: VB | D45: 1 | E45: 4972 | F45: =E45*D45 -> 4972 | G45: Valor repassado pelo Grandezza, respondido no formulário de custos indiretos
A46: 01.01.002.0001.0004 | B46: Aprovação e legalização prefeitura | C46: VB | D46: 1 | E46: 8883 | F46: =E46*D46 -> 8883 | G46: Valor repassado pelo Grandezza, respondido no formulário de custos indiretos
A47: 01.01.002.0001.0005 | B47: Aprovação e legalização água e esgoto | C47: VB | D47: 1 | E47: 1134 | F47: =E47*D47 -> 1134 | G47: Valor repassado pelo Grandezza, respondido no formulário de custos indiretos
A48: 01.01.002.0001.0006 | B48: Aprovação e legalização elétrico | C48: VB | D48: 1 | E48: 1134 | F48: =E48*D48 -> 1134 | G48: Valor repassado pelo Grandezza, respondido no formulário de custos indiretos
A49: 01.01.002.0001.0007 | B49: Aprovação e legalização bombeiros | C49: VB | D49: 1 | E49: 4972 | F49: =E49*D49 -> 4972 | G49: Valor repassado pelo Grandezza, respondido no formulário de custos indiretos
A50: 01.01.002.0001.0008 | B50: Taxas de ART | C50: VB | D50: 1 | E50: 4535 | F50: =E50*D50 -> 4535 | G50: Valor repassado pelo Grandezza, respondido no formulário de custos indiretos
A51: 01.01.002.0001.0009 | B51: Taxas de alvará | C51: VB | D51: 1 | E51: 19598 | F51: =E51*D51 -> 19598 | G51: Valor repassado pelo Grandezza, respondido no formulário de custos indiretos
A52: 01.01.002.0001.0010 | B52: Despesas de cartório, licenças, certidões e jurídicas | C52: VB | D52: 1 | E52: 39773 | F52: =E52*D52 -> 39773 | G52: Valor repassado pelo Grandezza, respondido no formulário de custos indiretos
A53: 01.01.002.0001.0011 | B53: Incorporação | C53: VB | D53: 1 | E53: 11315 | F53: =E53*D53 -> 11315 | G53: Valor repassado pelo Grandezza, respondido no formulário de custos indiretos
A54: 01.01.002.0001.0012 | B54: IPTU | C54: VB | D54: 1 | E54: 32370.79 | F54: =E54*D54 -> 32370.79 | G54: Valor repassado pelo Grandezza, respondido no formulário de custos indiretos
A55: 01.002.001.012 | B55: Taxa Habite-se | C55: VB | D55: 1 | E55: 27206 | F55: =E55*D55 -> 27206 | G55: Valor repassado pelo Grandezza, respondido no formulário de custos indiretos | V55: 27206 | AB55: 27206
A56: 2 | B56: SERVIÇOS INICIAIS | F56: =F57 -> 2500
A57: 02.001 | B57: SEGURANÇA, MEIO AMBIENTE, SAÚDE | F57: =F58 -> 2500
A58: 02.001.001 | B58: Segurança do trabalho | F58: =SUM(F59) -> 2500
A59: 02.001.001.001 | B59: Projetos de segurança do trabalho | C59: VB | D59: 1 | E59: 2500 | F59: =E59*D59 -> 2500 | G59: Valor repassado pelo Grandezza, respondido no formulário de custos indiretos | V59: 2500 | AB59: 2500
A60: 01.02.001.0002 | B60: Equipamentos de Proteção | F60: =SUM(F61:F68) -> 202456.6
A61: 02.001.002.001 | B61: Equipamentos de proteção individual - EPI | C61: mes | D61: 36 | E61: 250 | F61: 9000 | G61: Valor repassado pelo Grandezza, respondido no formulário de custos indiretos
A62: 02.001.002.002 | B62: Guarda-corpo de vãos, fixado em forma de madeira, em trama de madeira com tela de polipropileno | C62: m | D62: 763.69 | E62: 1.6601 | F62: 1267.8 | G62: Valor repassado pelo Grandezza, respondido no formulário de custos indiretos
A63: 02.001.002.003 | B63: Bandeja de proteção primária | C63: m | D63: 107.43 | E63: 92.4 | F63: 9926.53 | G63: Valor repassado pelo Grandezza, respondido no formulário de custos indiretos
A64: 02.001.002.004 | B64: Bandeja de proteção secundária | C64: m | D64: 71.49 | E64: 92.4 | F64: 6605.68 | G64: Valor repassado pelo Grandezza, respondido no formulário de custos indiretos
A65: 02.001.002.005 | B65: Guarda-corpo de laje após desforma | C65: m | D65: 285.96 | E65: 495.2576 | F65: 141623.86 | G65: Valor repassado pelo Grandezza, respondido no formulário de custos indiretos
A66: 02.001.002.006 | B66: Fechamento removível de vãos de porta de elevador em madeira | C66: m2 | D66: 110.88 | E66: 41.4883 | F66: 4600.22 | G66: Valor repassado pelo Grandezza, respondido no formulário de custos indiretos
A67: 02.001.002.007 | B67: Varal de segurança com cabo de aço | C67: m | D67: 81.6 | E67: 153.9401 | F67: 12561.51 | G67: Valor repassado pelo Grandezza, respondido no formulário de custos indiretos
A68: 02.001.002.008 | B68: Rede de proteção tipo SLQA | C68: m | D68: 71.49 | E68: 235.9911 | F68: 16871 | G68: Valor repassado pelo Grandezza, respondido no formulário de custos indiretos
A69: 02.001.003 | B69: Meio ambiente | F69: =SUM(F70:F73) -> 62081.54
A70: 02.001.003.001 | B70: Elaboração do Programa de Prevenção dos Riscos Ambientais (PPRA) | C70: vb | D70: 1 | E70: 2351.16 | F70: 2351.16 | G70: Valor repassado pelo Grandezza, respondido no formulário de custos indiretos
A71: 02.001.003.002 | B71: Elaboração do Programa de Condições e Meio Ambiente de Trabalho na indústria da construção (PCMAT) | C71: vb | D71: 1 | E71: 2730.38 | F71: 2730.38 | G71: Valor repassado pelo Grandezza, respondido no formulário de custos indiretos
A72: 02.001.003.003 | B72: Elaboração do Programa de Controle Médico de Saúde Ocupacional (PCMSO) | C72: vb | D72: 1 | E72: 3000 | F72: 3000 | G72: Valor repassado pelo Grandezza, respondido no formulário de custos indiretos
A73: 02.001.003.004 | B73: Remoção de entulhos e resíduos | C73: mes | D73: 36 | E73: 1500 | F73: 54000 | G73: Valor repassado pelo Grandezza, respondido no formulário de custos indiretos
A74: 02.002 | B74: ADMINISTRAÇÃO E CANTEIRO DE OBRA | F74: =SUM(F75:F81) -> 224712 | AB74: 285712
A75: 02.002.003.001 | B75: Despesa de consumo - água | C75: mes | D75: 36 | E75: 657 | F75: 23652 | G75: Verba estimada conforme índices históricos de obras similares
A76: 02.002.003.002 | B76: Despesas de consumo - luz | C76: mes | D76: 36 | E76: 860 | F76: 30960 | G76: Verba estimada conforme índices históricos de obras similares
A77: 02.002.003.003 | B77: Despesas de consumo - internet | C77: mes | D77: 36 | E77: 373 | F77: 13428 | G77: Verba estimada conforme índices históricos de obras similares
A78: 02.002.003.004 | B78: Despesas de consumo - alimentação | C78: mes | D78: 36 | E78: 2983 | F78: 107388 | G78: Verba estimada conforme índices históricos de obras similares
A79: 02.002.003.005 | B79: Despesas de consumo - material de expediente | C79: mes | D79: 36 | E79: 498 | F79: 17928 | G79: Verba estimada conforme índices históricos de obras similares
A80: 02.002.003.006 | B80: Despesas de consumo - material de limpeza | C80: mes | D80: 36 | E80: 498 | F80: 17928 | G80: Verba estimada conforme índices históricos de obras similares
A81: 02.002.003.007 | B81: Consumo gerenciamento eletrônico | C81: mes | D81: 36 | E81: 373 | F81: 13428 | G81: Verba estimada conforme índices históricos de obras similares
A82: 02.003 | B82: Instalações provisórias | F82: =F83 -> 61000 | AB82: 61000
A83: 02.003.001 | B83: Despesas de consumo e manutenção | F83: =SUM(F84:F87) -> 61000 | AB83: 224712
A84: 02.002.004.001 | B84: Locação de banheiro químico | C84: mes | D84: 36 | E84: 1500 | F84: 54000 | G84: Valor repassado pelo Grandezza, respondido no formulário de custos indiretos | V84: 500 | AB84: 400000
A85: 02.002.004.002 | B85: Divisórias em madeira compensada simples | C85: vb | D85: 1 | E85: 2500 | F85: 2500 | G85: Verba estimada conforme índices históricos de obras similares
A86: 02.002.004.003 | B86: Mobiliário de apoio a obra | C86: vb | D86: 1 | E86: 4000 | F86: 4000 | G86: Verba estimada conforme índices históricos de obras similares
A87: 02.002.004.004 | B87: Equipamentos de escritório | C87: vb | D87: 1 | E87: 500 | F87: 500 | G87: Verba estimada conforme índices históricos de obras similares
A88: 02.003 | B88: SERVIÇOS PRELIMINARES | F88: =F89+F91 -> 404160 | AB88: 285712
A89: 02.003.001 | B89: Demolições | F89: =SUM(F90) -> 400000 | AB89: 224712
A90: 02.003.001.001 | B90: Demolição | C90: m2 | D90: 800 | E90: 500 | F90: =E90*D90 -> 400000 | G90: Verba estimada conforme índices históricos de obras similares | V90: 500 | AB90: 400000
A91: 02.003.002 | B91: Limpeza de terreno | F91: =SUM(F92) -> 4160 | AB91: 445.61
A92: 02.003.002.001 | B92: Limpeza manual de camada vegetal | C92: m2 | D92: 800 | E92: 5.2 | F92: =E92*D92 -> 4160 | G92: Verba estimada conforme índices históricos de obras similares | V92: 0.52 | AB92: 445.61
A93: 02.003 | B93: EQUIPAMENTOS | F93: =F94 -> 723541 | AB93: 285712
A94: 02.003.001 | B94: EQUIPAMENTOS | F94: =F95+F100 -> 723541 | AB94: 224712
A95: 3001001 | B95: Equipamentos de Obra | F95: =SUM(F96:F99) -> 414800 | AB95: 224712
A96: 03.001.001.001 | B96: Elevador cremalheira - aquisição | C96: vb | D96: 1 | E96: 300000 | F96: =E96*D96 -> 300000 | G96: Valor repassado pelo Grandezza, respondido no formulário de custos indiretos
A97: 03.001.001.002 | B97: Montagem e desmontagem de elevador cremalheira | C97: vb | D97: 1 | E97: 17600 | F97: =E97*D97 -> 17600 | G97: Verba estimada conforme índices históricos de obras similares
A98: 03.001.001.003 | B98: Manutenção de elevador cremalheira | C98: mes | D98: 17 | E98: 1600 | F98: =E98*D98 -> 27200 | G98: Verba estimada conforme índices históricos de obras similares
A99: 03.001.001.004 | B99: Manutenção inicial elevador cremalheira | C99: vb | D99: 1 | E99: 70000 | F99: =E99*D99 -> 70000 | G99: Verba estimada conforme índices históricos de obras similares
A100: 01.02.002.0002 | B100: Operação Inicial do Canteiro | F100: =SUM(F101:F106) -> 308741
A101: 01.02.002.0002.0001 | B101: Limpeza mecanizada de camada vegetal | C101: mes | D101: 3 | E101: 3000 | F101: =E101*D101 -> 9000 | G101: Verba estimada conforme índices históricos de obras similares
A102: 01.02.002.0002.0002 | B102: Sinalizacao geral da obra | C102: vb | D102: 4637.62 | E102: 50 | F102: =E102*D102 -> 231881 | G102: Verba estimada conforme índices históricos de obras similares
A103: 01.02.002.0002.0003 | B103: Demolições | C103: m | D103: 106.4 | E103: 25 | F103: =E103*D103 -> 2660 | G103: Verba estimada conforme índices históricos de obras similares
A104: 01.02.002.0002.0004 | B104: Despesas de Consumo e Manutenção | C104: mes | D104: 2 | E104: 1100 | F104: =E104*D104 -> 2200 | G104: Verba estimada conforme índices históricos de obras similares
A105: 01.02.002.0002.0005 | B105: Despesas de consumo - Agua | C105: mes | D105: 10 | E105: 1800 | F105: =E105*D105 -> 18000 | G105: Verba estimada conforme índices históricos de obras similares
A106: 01.02.002.0002.0006 | B106: Despesas de consumo - Luz | C106: un | D106: 100 | E106: 450 | F106: =E106*D106 -> 45000 | G106: Verba estimada conforme índices históricos de obras similares
A107: 02 | B107: GERENCIAMENTO EXECUTIVO | F107: 18860719
A108: 01 | B108: MOVIMENTAÇÃO DE TERRA | F108: 230869.63 | G108: Custo ajustado conforme solicitação de revisão
A109: 01.001 | B109: MOVIMENTAÇÃO DE TERRA | F109: 230869.63
...
