Workbook
Name \0: #REF!
Name \1: #REF!
Name \a: #REF!
Name \b: #REF!
Name \c: #REF!
Name \d: #REF!
Name \e: #REF!
Name \i: #REF!
Name \J: #REF!
Name \k: #REF!
Name \l: #N/A
Name \m: #REF!
Name \o: #REF!
Name \p: #REF!
Name \r: #REF!
Name \T: #REF!
Name \z: #REF!
Name _: #REF!
Name _\0: #REF!
Name _\1: #REF!
Name _\a: #REF!
Name _\b: #REF!
Name _\c: #REF!
Name _\d: #REF!
Name _\e: #REF!
Name _\i: #REF!
Name _\J: #REF!
Name _\k: #REF!
Name _\l: #N/A
Name _\m: #REF!
Name _\o: #REF!
Name _\p: #REF!
Name _\r: #REF!
Name _\T: #REF!
Name _\z: #REF!
Name __: #REF!
Name ______ACR10: #REF!
Name ______ACR15: #REF!
Name ______acr20: #REF!
Name ______acr5: #REF!
Name ______ARQ1: #REF!
Name ______QT100: #REF!
Name ______QT2: #REF!
Name ______QT3: #REF!
Name ______QT4: #REF!
Name ______QT50: #REF!
Name ______QT75: #REF!
Name _____ACR10: #REF!
Name _____ACR15: #REF!
Name _____acr20: #REF!
Name _____acr5: #REF!
Name _____ARQ1: #REF!
Name _____key2: #REF!
Name _____QT100: #REF!
Name _____QT2: #REF!
Name _____QT3: #REF!
Name _____QT4: #REF!
Name _____QT50: #REF!
Name _____QT75: #REF!
Name ____key2: #REF!

Sheet CAPA
A1: DADOS DO EMPREENDIMENTO
B2: Projeto: | C2: Electra Towers | E2: ENDEREÇO DA OBRA: | F2: Rua 254, 215, Meia Praia, Itapema/SC
B3: Empresa: | C3: Thozen Empreendimentos | E3: Cidade/ES: | F3: Itapema, SC
B4: Revisão: | C4: R00 | E4: CNPJ: | F4: 43.339.082/0001-06
B6: Pazo de Obra: | C6: 48 | E6: Nº Unid. Residenciais: | F6: 192 | I6: Imagens
B8: Área do Terreno: | C8: 2095.43 | E8: Nº Unid. Comerciais: | F8: 7
B10: Área Construída: | C10: 37893.89 | E10: Nº Pavimentos: | F10: 57
B12: Área Privativa: | C12: 22778.64 | E12: Total de Dormitórios: | F12: 576
B14: Área de Lazer: | C14: 1736.27 | E14: Nº Subsolos: | F14: 0
B16: Área Comercial: | C16: 500.04 | E16: Nº Vagas: | F16: 399
B18: Torre | C18: Pavimento | D18: Área | E18: Área Privativa | F18: Perímetro | G18: Pé direito
B19: Embasamento | C19: Térreo | D19: 1565.91 | E19: 0 | G19: 4.3
B20: Embasamento | C20: Garagem 01 | D20: 1736.27 | E20: 0
B21: Embasamento | C21: Garagem 02 | D21: 1736.27 | E21: 0
B22: Embasamento | C22: Garagem 03 | D22: 1736.27 | E22: 0
B23: Embasamento | C23: Garagem 04 | D23: 1736.27 | E23: 0
B24: Embasamento | C24: Garagem 05 | D24: 1736.27 | E24: 0
B25: Embasamento | C25: Pavimento diferenciado — Lazer | D25: 1736.27 | E25: 0 | G25: 3.6
B26: Torre A | C26: Pavimento tipo — Torre A (×24) | D26: 12720.48 | E26: 11382.72 | G26: 3.24
B27: Torre B | C27: Pavimento tipo — Torre B (×24) | D27: 12892.32 | E27: 11397.12 | G27: 3.24
B28: Cobertura | C28: Casa de Máquinas | D28: 176.26 | E28: 0
B29: Cobertura | C29: Reservatórios | D29: 121.3 | E29: 0
B37: Torre | C37: Pavimento | D37: Descrição | E37: Área | I37: ETAPA
B38: Áreas Comuns | C38: =_xlfn.XLOOKUP(D38,MOBILIÁRIO!C:C,MOBILIÁRIO!B:B) -> TÉRREO | D38: {=_xlfn.UNIQUE(_xlfn._xlws.FILTER(MOBILIÁRIO!C7:C316,MOBILIÁRIO!C7:C316<>""))} -> Hall Externo | E38: =_xlfn.XLOOKUP(D38,MOBILIÁRIO!C:C,MOBILIÁRIO!F:F) -> 12.33 | I38: GERENCIAMENTO TÉCNICO E ADMINISTRATIVO
B39: Áreas Comuns | C39: =_xlfn.XLOOKUP(D39,MOBILIÁRIO!C:C,MOBILIÁRIO!B:B) -> TÉRREO | D39: Hall Térreo | E39: =_xlfn.XLOOKUP(D39,MOBILIÁRIO!C:C,MOBILIÁRIO!F:F) -> 35.27 | I39: MOVIMENTAÇÃO DE TERRA
B40: Áreas Comuns | C40: =_xlfn.XLOOKUP(D40,MOBILIÁRIO!C:C,MOBILIÁRIO!B:B) -> TÉRREO | D40: Guarita | E40: =_xlfn.XLOOKUP(D40,MOBILIÁRIO!C:C,MOBILIÁRIO!F:F) -> 4.72 | I40: CONTENÇÃO
B41: Áreas Comuns | C41: =_xlfn.XLOOKUP(D41,MOBILIÁRIO!C:C,MOBILIÁRIO!B:B) -> TÉRREO | D41: Lavapés | E41: =_xlfn.XLOOKUP(D41,MOBILIÁRIO!C:C,MOBILIÁRIO!F:F) -> 1 | I41: INFRAESTRUTURA
B42: Áreas Comuns | C42: =_xlfn.XLOOKUP(D42,MOBILIÁRIO!C:C,MOBILIÁRIO!B:B) -> TÉRREO | D42: Lavabo Pne - Térreo | E42: =_xlfn.XLOOKUP(D42,MOBILIÁRIO!C:C,MOBILIÁRIO!F:F) -> 3.77 | I42: SUPRAESTRUTURA
B43: Áreas Comuns | C43: =_xlfn.XLOOKUP(D43,MOBILIÁRIO!C:C,MOBILIÁRIO!B:B) -> TÉRREO | D43: Bicicletário/Box | E43: =_xlfn.XLOOKUP(D43,MOBILIÁRIO!C:C,MOBILIÁRIO!F:F) -> 87.33 | I43: ALVENARIAS E VEDAÇÕES
B44: Áreas Comuns | C44: =_xlfn.XLOOKUP(D44,MOBILIÁRIO!C:C,MOBILIÁRIO!B:B) -> TÉRREO | D44: Antecâmara - Térreo | E44: =_xlfn.XLOOKUP(D44,MOBILIÁRIO!C:C,MOBILIÁRIO!F:F) -> 8.07 | I44: SISTEMAS E INSTALAÇÕES ELÉTRICAS
B45: Áreas Comuns | C45: =_xlfn.XLOOKUP(D45,MOBILIÁRIO!C:C,MOBILIÁRIO!B:B) -> 2º AO 5º PAVIMENTO - GARAGENS (X5) | D45: Antecâmara - Garagens (x5) | E45: =_xlfn.XLOOKUP(D45,MOBILIÁRIO!C:C,MOBILIÁRIO!F:F) -> 33.6 | I45: SISTEMAS E INSTALAÇÕES HIDROSSANITÁRIAS E DRENAGEM
B46: Áreas Comuns | C46: =_xlfn.XLOOKUP(D46,MOBILIÁRIO!C:C,MOBILIÁRIO!B:B) -> 4º PAVIMENTO - LAZER/GARAGENS | D46: Sala de massagem | E46: =_xlfn.XLOOKUP(D46,MOBILIÁRIO!C:C,MOBILIÁRIO!F:F) -> 7.47 | I46: INSTALAÇÕES PREVENTIVAS
B47: Áreas Comuns | C47: =_xlfn.XLOOKUP(D47,MOBILIÁRIO!C:C,MOBILIÁRIO!B:B) -> 4º PAVIMENTO - LAZER/GARAGENS | D47: Banheiro - Lazer/Garagem | E47: =_xlfn.XLOOKUP(D47,MOBILIÁRIO!C:C,MOBILIÁRIO!F:F) -> 3.91 | I47: INSTALAÇÕES DE GÁS
B48: Áreas Comuns | C48: =_xlfn.XLOOKUP(D48,MOBILIÁRIO!C:C,MOBILIÁRIO!B:B) -> 4º PAVIMENTO - LAZER/GARAGENS | D48: Lavabo - Lazer/Garagem | E48: =_xlfn.XLOOKUP(D48,MOBILIÁRIO!C:C,MOBILIÁRIO!F:F) -> 2.61 | I48: EQUIPAMENTOS E SISTEMAS ESPECIAIS
B49: Áreas Comuns | C49: =_xlfn.XLOOKUP(D49,MOBILIÁRIO!C:C,MOBILIÁRIO!B:B) -> 4º PAVIMENTO - LAZER/GARAGENS | D49: Lavabo Pne - Lazer/Garagem | E49: =_xlfn.XLOOKUP(D49,MOBILIÁRIO!C:C,MOBILIÁRIO!F:F) -> 4.33 | I49: CLIMATIZAÇÃO, EXAUSTÃO MECÂNICA
B50: Áreas Comuns | C50: =_xlfn.XLOOKUP(D50,MOBILIÁRIO!C:C,MOBILIÁRIO!B:B) -> 4º PAVIMENTO - LAZER/GARAGENS | D50: Circulação - Lazer/garagem | E50: =_xlfn.XLOOKUP(D50,MOBILIÁRIO!C:C,MOBILIÁRIO!F:F) -> 30.85 | I50: INSTALAÇÕES ESPECIAIS
... B63: Áreas Comuns | C63: =_xlfn.XLOOKUP(D63,MOBILIÁRIO!C:C,MOBILIÁRIO!B:B) -> 5º PAVIMENTO - LAZER | D63: Laje Verde | E63: =_xlfn.XLOOKUP(D63,MOBILIÁRIO!C:C,MOBILIÁRIO!F:F) -> 269.95 | I63: CUB/SC
B64: Áreas Comuns | C64: =_xlfn.XLOOKUP(D64,MOBILIÁRIO!C:C,MOBILIÁRIO!B:B) -> 5º PAVIMENTO - LAZER | D64: Brinquedoteca | E64: =_xlfn.XLOOKUP(D64,MOBILIÁRIO!C:C,MOBILIÁRIO!F:F) -> 16.32
B65: Áreas Comuns | C65: =_xlfn.XLOOKUP(D65,MOBILIÁRIO!C:C,MOBILIÁRIO!B:B) -> 5º PAVIMENTO - LAZER | D65: Game Center | E65: =_xlfn.XLOOKUP(D65,MOBILIÁRIO!C:C,MOBILIÁRIO!F:F) -> 13.09 | I65: DESCRIÇÃO
B66: Áreas Comuns | C66: =_xlfn.XLOOKUP(D66,MOBILIÁRIO!C:C,MOBILIÁRIO!B:B) -> 5º PAVIMENTO - LAZER | D66: Sala de Festas | E66: =_xlfn.XLOOKUP(D66,MOBILIÁRIO!C:C,MOBILIÁRIO!F:F) -> 93.46 | I66: VALOR POR ÁREA PRIVATIVA (R$/m²)
B67: Áreas Comuns | C67: =_xlfn.XLOOKUP(D67,MOBILIÁRIO!C:C,MOBILIÁRIO!B:B) -> 5º PAVIMENTO - LAZER | D67: Terraço | E67: =_xlfn.XLOOKUP(D67,MOBILIÁRIO!C:C,MOBILIÁRIO!F:F) -> 88.11 | I67: Tipo diferenciado Apart. 1
B68: Áreas Comuns | C68: =_xlfn.XLOOKUP(D68,MOBILIÁRIO!C:C,MOBILIÁRIO!B:B) -> 5º PAVIMENTO - LAZER | D68: Wine Bar | E68: =_xlfn.XLOOKUP(D68,MOBILIÁRIO!C:C,MOBILIÁRIO!F:F) -> 29.79 | I68: Tipo diferenciado Apart. 2
B69: Áreas Comuns | C69: =_xlfn.XLOOKUP(D69,MOBILIÁRIO!C:C,MOBILIÁRIO!B:B) -> 5º PAVIMENTO - LAZER | D69: Academia | E69: =_xlfn.XLOOKUP(D69,MOBILIÁRIO!C:C,MOBILIÁRIO!F:F) -> 63.68 | I69: Tipo Apart. 01
B70: Áreas Comuns | C70: =_xlfn.XLOOKUP(D70,MOBILIÁRIO!C:C,MOBILIÁRIO!B:B) -> 5º PAVIMENTO - LAZER | D70: Espaço Crossfit | E70: =_xlfn.XLOOKUP(D70,MOBILIÁRIO!C:C,MOBILIÁRIO!F:F) -> 34.41 | I70: Tipo Apart. 02
B71: Áreas Comuns | C71: =_xlfn.XLOOKUP(D71,MOBILIÁRIO!C:C,MOBILIÁRIO!B:B) -> 5º PAVIMENTO - LAZER | D71: Antecâmara - Lazer | E71: =_xlfn.XLOOKUP(D71,MOBILIÁRIO!C:C,MOBILIÁRIO!F:F) -> 4.15 | I71: Penthouse
B72: Áreas Comuns | C72: =_xlfn.XLOOKUP(D72,MOBILIÁRIO!C:C,MOBILIÁRIO!B:B) -> 6º AO 38º PAVIMENTO - PAVIMENTOS (X33) | D72: Antecâmara - Tipos (x33) | E72: =_xlfn.XLOOKUP(D72,MOBILIÁRIO!C:C,MOBILIÁRIO!F:F) -> 221.76 | I72: Penthouse diferenciado
I73: Duplex
B76: Torre | C76: Apartamentos | D76: Área | E76: Quantidade | F76: Total vagas | G76: Total apartamentos | I76: QUADRO DE ÁREAS
B77: Torre 1 | C77: Tipo 1 | D77: 102.67 | E77: 9 | F77: 18 | G77: =E77 -> 9
B78: Torre 1 | C78: Tipo 2 | D78: 108.38 | E78: 9 | F78: 18 | G78: =E78 -> 9
B79: Torre 1 | C79: Tipo 3 penthouse (outorga) | D79: 202.02 | E79: 9 | F79: 18 | G79: =E79 -> 9
B80: Torre 1 | C80: Tipo 3 penthouse | D80: 202.02 | E80: 12 | F80: 36 | G80: =E80 -> 12
B81: Torre 1 | C81: Tipo 4 penthouse | D81: 199.18 | E81: 1 | F81: 3 | G81: =E81 -> 1
B82: Torre 1 | C82: duplex 1 | D82: 329.41 | E82: 1 | F82: 4 | G82: =E82 -> 1
D83: =SUMPRODUCT(D77:E82) -> 1184.68 | E83: =SUM(E77:E82) -> 41 | F83: =SUM(F77:F82) -> 97 | G83: =SUM(G77:G82) -> 41
B86: Torre | C86: Sala comercial | D86: Área | E86: Total vagas | F86: Total banheiros
B87: Torre 1 | C87: Sala comercial 1 | D87: 176.43 | E87: 2 | F87: 1
B88: Torre 1 | C88: Sala comercial 2 | D88: 84.08 | E88: 1 | F88: 1
B89: Torre 1 | C89: Sala comercial 3 | D89: 60.82 | E89: 1 | F89: 1
B90: Torre 1 | C90: Sala comercial 4 | D90: 132.86 | E90: 2 | F90: 1
B91: Torre 1 | C91: Sala comercial 5 | D91: 83.77 | E91: 1 | F91: 1
D92: =SUM(D87:D91) -> 537.96 | E92: =SUM(E87:E91) -> 7 | F92: =SUM(F87:F91) -> 5

Sheet EAP
A1: EAP DE ORÇAMENTO
A3: Contrutora - Obra
A5: UNIDADE CONSTRUTIVA | B5: 1 | C5: GERENCIAMENTO TÉCNICO E ADMINISTRATIVO
A6: CÉLULA CONSTRUTIVA | B6: 1 | C6: SERVIÇOS TÉCNICOS
A7: ETAPA | B7: 1.001 | C7: ESTUDOS, PROJETOS E CONSULTORIAS
A8: Subetapa | B8: 01.001.001 | C8: Estudos
A9: Subetapa | B9: 01.001.002 | C9: Projetos
A10: Subetapa | B10: 01.001.003 | C10: Consultorias
A11: Subetapa | B11: 01.001.004 | C11: Ensaios
A12: ETAPA | B12: 1.002 | C12: TAXAS E DOCUMENTOS
A13: Subetapa | B13: 01.002.001 | C13: Licenciamentos, Taxas, Impostos, Aprovações e Seguros
A14: Subetapa | B14: 01.002.002 | C14: Documentos
A15: CÉLULA CONSTRUTIVA | B15: 2 | C15: SERVIÇOS INICIAIS
A16: ETAPA | B16: 2.001 | C16: SEGURANÇA, MEIO AMBIENTE, SAÚDE
A17: Subetapa | B17: 02.001.001 | C17: Segurança do trabalho
A18: Subetapa | B18: 02.001.002 | C18: Equipamentos de proteção
A19: Subetapa | B19: 02.001.003 | C19: Meio ambiente
A20: Subetapa | B20: 02.001.004 | C20: Saúde ocupacional
A21: ETAPA | B21: 2.002 | C21: ADMINISTRAÇÃO E CANTEIRO DE OBRA
A22: Subetapa | B22: 02.002.001 | C22: Equipe de Gestão e Apoio
A23: Subetapa | B23: 02.002.002 | C23: Operação inicial de canteiro
A24: Subetapa | B24: 02.002.003 | C24: Despesas de consumo e manutenção
A25: Subetapa | B25: 02.002.004 | C25: Instalações provisórias
A26: Subetapa | B26: 02.002.005 | C26: Ligações Provisórias
A27: ETAPA | B27: 2.003 | C27: SERVIÇOS PRELIMINARES
... A29: Subetapa | B29: 02.003.002 | C29: Limpeza de terreno
A30: CÉLULA CONSTRUTIVA | B30: 3 | C30: EQUIPAMENTOS
A31: ETAPA | B31: 3.001 | C31: EQUIPAMENTOS
A32: Subetapa | B32: 03.001.001 | C32: Equipamentos de Carga e Transporte
A33: Subetapa | B33: 03.001.002 | C33: Equipamentos de obra
A34: Subetapa | B34: 03.001.003 | C34: Balancins e Andaimes
A35: UNIDADE CONSTRUTIVA | B35: 2 | C35: GERENCIAMENTO EXECUTIVO
A36: CÉLULA CONSTRUTIVA | B36: 1 | C36: INFRAESTRUTURA
A37: ETAPA | B37: 1.001 | C37: MOVIMENTAÇÃO DE TERRA
A38: Subetapa | B38: 01.001.001 | C38: Corte e aterro
A39: Subetapa | B39: 01.001.002 | C39: Rebaixamento de lençol
A40: Subetapa | B40: 01.001.003 | C40: Escavação e Reaterro de Valas
A41: Subetapa | B41: 01.001.004 | C41: Lastro de estrutura de concreto
A42: Subetapa | B42: 01.001.005 | C42: Movimentação de bota - fora
A43: ETAPA | B43: 1.002 | C43: FUNDAÇÃO PROFUNDA
A44: Subetapa | B44: 01.002.001 | C44: Perfuração
A45: Subetapa | B45: 01.002.002 | C45: Armadura
A46: Subetapa | B46: 01.002.003 | C46: Acessórios
A47: Subetapa | B47: 01.002.004 | C47: Concreto
A48: Subetapa | B48: 01.002.005 | C48: Mão de obra
... A53: Subetapa | B53: 01.003.004 | C53: Mão de obra
A54: CÉLULA CONSTRUTIVA | B54: 2 | C54: SUPRAESTRUTURA
A55: ETAPA | B55: 2.001 | C55: SUPRAESTRUTURA - EMBASAMENTO
A56: Subetapa | B56: 02.001.001 | C56: Forma
A57: Subetapa | B57: 02.001.002 | C57: Armadura
A58: Subetapa | B58: 02.001.003 | C58: Concreto
A59: Subetapa | B59: 02.001.004 | C59: Complementares
A60: Subetapa | B60: 02.001.005 | C60: Mão de obra
A61: ETAPA | B61: 2.002 | C61: SUPRAESTRUTURA - TORRE A
A62: Subetapa | B62: 02.002.001 | C62: Forma
A63: Subetapa | B63: 02.002.002 | C63: Armadura
A64: Subetapa | B64: 02.002.003 | C64: Concreto
A65: Subetapa | B65: 02.002.004 | C65: Complementares
A66: Subetapa | B66: 02.002.005 | C66: Mão de obra
... A72: Subetapa | B72: 02.003.005 | C72: Mão de obra
A73: CÉLULA CONSTRUTIVA | B73: 3 | C73: PAREDES E PAINÉIS
A74: ETAPA | B74: 3.001 | C74: PAREDES E PAINÉIS - EMBASAMENTO
A75: Subetapa | B75: 03.001.001 | C75: Alvenaria de vedação com blocos cerâmicos
A76: Subetapa | B76: 03.001.002 | C76: Alvenaria de vedação com bocos de concreto
A77: Subetapa | B77: 03.001.003 | C77: Serviços complementares para alvenaria de vedação
A78: Subetapa | B78: 03.001.004 | C78: Drywall
A79: Subetapa | B79: 03.001.005 | C79: Mão de obra
A80: ETAPA | B80: 3.002 | C80: PAREDES E PAINÉIS - TORRE A
A81: Subetapa | B81: 03.002.001 | C81: Alvenaria de vedação com blocos cerâmicos
A82: Subetapa | B82: 03.002.002 | C82: Alvenaria de vedação com bocos de concreto
A83: Subetapa | B83: 03.002.003 | C83: Serviços complementares para alvenaria de vedação
A84: Subetapa | B84: 03.002.004 | C84: Drywall
A85: Subetapa | B85: 03.002.005 | C85: Mão de obra
... A91: Subetapa | B91: 03.003.005 | C91: Mão de obra
A92: CÉLULA CONSTRUTIVA | B92: 4 | C92: IMPERMEABILIZAÇÃO E TRATAMENTOS
A93: ETAPA | B93: 4.001 | C93: IMPERMEABILIZAÇÃO E TRATAMENTOS - EMBASAMENTO
A94: Subetapa | B94: 04.001.001 | C94: Regularização e proteção mecânica
A95: Subetapa | B95: 04.001.002 | C95: Impermeabilização de cisternas
A96: Subetapa | B96: 04.001.003 | C96: Impermeabilização de fundação e contenção
A97: Subetapa | B97: 04.001.004 | C97: Impermeabilização de lajes e terraços
A98: Subetapa | B98: 04.001.005 | C98: Impermeabilização de piscinas e espelhos d´água
A99: Subetapa | B99: 04.001.006 | C99: Impermeabilização de banheiro, cozinha e sacada
A100: Subetapa | B100: 04.001.007 | C100: Impermeabilização de esquadrias
A101: Subetapa | B101: 04.001.008 | C101: Impermeabilização de ralos
A102: Subetapa | B102: 04.001.009 | C102: Impermeabilização de floreiras
A103: Subetapa | B103: 04.001.010 | C103: Impermeabilização de reservatórios
A104: Subetapa | B104: 04.001.011 | C104: Mão de obra
... A128: Subetapa | B128: 04.003.011 | C128: Mão de obra
A129: CÉLULA CONSTRUTIVA | B129: 5 | C129: SISTEMAS E INSTALAÇÕES HIDROSSANITÁRIAS E DRENAGEM
A130: ETAPA | B130: 5.001 | C130: SISTEMAS E INSTALAÇÕES HIDROSSANITÁRIAS E DRENAGEM - EMBASAMENTO
A131: Subetapa | B131: 05.001.001 | C131: Instalações de água fria
A132: Subetapa | B132: 05.001.002 | C132: Instalações de água quente
A133: Subetapa | B133: 05.001.003 | C133: Instalações de esgoto e pluviais
A134: Subetapa | B134: 05.001.004 | C134: Cisterna
A135: Subetapa | B135: 05.001.005 | C135: Hidrômetros
A136: Subetapa | B136: 05.001.006 | C136: Reservatórios
A137: Subetapa | B137: 05.001.007 | C137: Sistema de bombas
A138: Subetapa | B138: 05.001.008 | C138: Mão de obra
A139: ETAPA | B139: 5.002 | C139: SISTEMAS E INSTALAÇÕES HIDROSSANITÁRIAS E DRENAGEM - TORRE A
A140: Subetapa | B140: 05.002.001 | C140: Instalações de água fria
...

Sheet TELECOMUNICAÇÃO (2)
C1: Projeto | D1: Electra Towers
C2: Empresa | D2: Thozen
C3: Origem | D3: CTN-TZN_ELT-TEL-R02
C4: Revisão | D4: R00
A5: TELECOMUNICAÇÃO
A6: TORRE | B6: PAVIMENTO | C6: GRUPO/EAP | D6: SUBGRUPO | E6: Descrição | F6: Quantidade | G6: Repetição | H6: Perda | I6: Qte com perda | J6: Unidade | K6: Custo unitário | L6: Custo Total | N6: Torre | O6: EAP | P6: TÉRREO | Q6: GARAGEM 01 | R6: GARAGEM 02 | S6: GARAGEM 03 | T6: GARAGEM 04 | U6: GARAGEM 05 | V6: LAZER | W6: PAVIMENTO TIPO | X6: CASA DE MÁQUINAS | Y6: TOTAL
A7: Torre A | B7: TÉRREO | L7: =IF(SUM(F7:K7)=0,SUMIFS($L8:$L$9999,$B8:$B$9999,$B7,$A8:$A$9999,$A7),I7*K7) -> 10533.3 | N7: Torre A | O7: CAIXA OCTOGONAL | P7: 290.6 | Q7: 258 | R7: 173.1 | S7: 173.1 | T7: 182.9 | U7: 192.7 | V7: 280.8 | W7: 1567.2 | Y7: 3118.4
A8: =A7 -> Torre A | B8: =B7 -> TÉRREO | C8: INSTALAÇÕES DE TELECOMUNICAÇÃO | D8: CAIXA OCTOGONAL | E8: Caixa Octogonal Padrão NBR IEC 60670 | F8: 27 | G8: 1 | H8: 0 | I8: =(F8+H8*F8)*G8 -> 27 | J8: pç | K8: 9.8 | L8: =I8*K8 -> 264.6 | N8: Torre A | O8: CAIXA 4x2" E 4x4" | P8: 1548.1 | Q8: 27.6 | R8: 12.8 | S8: 12.8 | V8: 1032.9 | W8: 27196.8 | X8: 55 | Y8: 29886
A9: =A7 -> Torre A | B9: =B7 -> TÉRREO | C9: INSTALAÇÕES DE TELECOMUNICAÇÃO | D9: CAIXA OCTOGONAL | E9: Placa cega para caixa octogonal Padrão NBR IEC 60670 | F9: 4 | G9: 1 | H9: 0 | I9: =(F9+H9*F9)*G9 -> 4 | J9: pç | K9: 6.5 | L9: =I9*K9 -> 26 | N9: Torre A | O9: CAIXA DE PASSAGEM | Q9: 435 | Y9: 435
A10: =A7 -> Torre A | B10: =B7 -> TÉRREO | C10: INSTALAÇÕES DE TELECOMUNICAÇÃO | D10: CAIXA 4x2" E 4x4" | E10: Caixa 4x2" de Embutir em PVC Padrão NBR IEC 60670 | F10: 85 | G10: 1 | H10: 0 | I10: =(F10+H10*F10)*G10 -> 85 | J10: pç | K10: 5.9 | L10: =I10*K10 -> 501.5 | N10: Torre A | O10: ELETRODUTOS | P10: 6633.8 | Q10: 2267.5 | R10: 1026.4 | S10: 1026.4 | T10: 969.5 | U10: 943.9 | V10: 6087 | W10: 132772.8 | X10: 864.5 | Y10: 152591.8
A11: =A7 -> Torre A | B11: =B7 -> TÉRREO | C11: INSTALAÇÕES DE TELECOMUNICAÇÃO | D11: CAIXA 4x2" E 4x4" | E11: Caixa 4x4" de Embutir em PVC Padrão NBR IEC 60670 | F11: 30 | G11: 1 | H11: 0 | I11: =(F11+H11*F11)*G11 -> 30 | J11: pç | K11: 8.9 | L11: =I11*K11 -> 267 | N11: Torre A | O11: MÓDULOS | P11: 800.8 | Q11: 22.9 | V11: 142.7 | W11: 8568 | Y11: 9534.4
A12: =A7 -> Torre A | B12: =B7 -> TÉRREO | C12: INSTALAÇÕES DE TELECOMUNICAÇÃO | D12: CAIXA 4x2" E 4x4" | E12: Placa 4x2" cega Padrão NBR IEC 60670 | F12: 40 | G12: 1 | H12: 0 | I12: =(F12+H12*F12)*G12 -> 40 | J12: pç | K12: 4.5 | L12: =I12*K12 -> 180 | N12: Torre A | O12: QUADROS DE DISTRIBUIÇÃO | P12: 1260 | U12: 465 | V12: 420 | W12: 10080 | Y12: 12225
A13: =A7 -> Torre A | B13: =B7 -> TÉRREO | C13: INSTALAÇÕES DE TELECOMUNICAÇÃO | D13: CAIXA 4x2" E 4x4" | E13: Placa 4x2" para 2 funções Padrão NBR IEC 60670 | F13: 5 | G13: 1 | H13: 0 | I13: =(F13+H13*F13)*G13 -> 5 | J13: pç | K13: 7.8 | L13: =I13*K13 -> 39 | N13: Torre A | O13: COTOVELOS | Y13: 0
A14: =A7 -> Torre A | B14: =B7 -> TÉRREO | C14: INSTALAÇÕES DE TELECOMUNICAÇÃO | D14: CAIXA 4x2" E 4x4" | E14: Placa 4x2" para 3 funções Padrão NBR IEC 60670 | F14: 4 | G14: 1 | H14: 0 | I14: =(F14+H14*F14)*G14 -> 4 | J14: pç | K14: 8.9 | L14: =I14*K14 -> 35.6 | N14: Torre A | O14: CONECTORES E BUCHAS | Y14: 0
A15: =A7 -> Torre A | B15: =B7 -> TÉRREO | C15: INSTALAÇÕES DE TELECOMUNICAÇÃO | D15: CAIXA 4x2" E 4x4" | E15: Placa 4x4" cega Padrão NBR IEC 60670 | F15: 30 | G15: 1 | H15: 0 | I15: =(F15+H15*F15)*G15 -> 30 | J15: pç | K15: 7.5 | L15: =I15*K15 -> 225 | N15: Torre A | O15: CONDUTORES TELECOM | Y15: 0
A16: =A7 -> Torre A | B16: =B7 -> TÉRREO | C16: INSTALAÇÕES DE TELECOMUNICAÇÃO | D16: CAIXA 4x2" E 4x4" | E16: Suporte p/ caixa 4x2" Padrão NBR IEC 60670 | F16: 85 | G16: 1 | H16: 0 | I16: =(F16+H16*F16)*G16 -> 85 | J16: pç | K16: 2.4 | L16: =I16*K16 -> 204 | N16: Torre A | O16: PONTOS DE USO | Y16: 0
A17: =A7 -> Torre A | B17: =B7 -> TÉRREO | C17: INSTALAÇÕES DE TELECOMUNICAÇÃO | D17: CAIXA 4x2" E 4x4" | E17: Suporte p/ caixa 4x4" Padrão NBR IEC 60670 | F17: 30 | G17: 1 | H17: 0 | I17: =(F17+H17*F17)*G17 -> 30 | J17: pç | K17: 3.2 | L17: =I17*K17 -> 96 | N17: Torre B | O17: CAIXA OCTOGONAL | P17: 372.2 | Q17: 362.5 | R17: 238.4 | S17: 238.4 | T17: 202.5 | U17: 192.7 | V17: 310.2 | W17: 1567.2 | Y17: 3484.1
A18: =A7 -> Torre A | B18: =B7 -> TÉRREO | C18: INSTALAÇÕES DE TELECOMUNICAÇÃO | D18: ELETRODUTOS | E18: PVC Flexível Antichama - NBR 15465 ø1" | F18: 277 | G18: 1 | H18: 0 | I18: =(F18+H18*F18)*G18 -> 277 | J18: m | K18: 11.9 | L18: =I18*K18 -> 3296.3 | N18: Torre B | O18: CAIXA 4x2" E 4x4" | P18: 1956.4 | Q18: 38.6 | R18: 12.8 | S18: 12.8 | V18: 1155 | W18: 27196.8 | X18: 42.2 | Y18: 30414.6
A19: =A7 -> Torre A | B19: =B7 -> TÉRREO | C19: INSTALAÇÕES DE TELECOMUNICAÇÃO | D19: ELETRODUTOS | E19: PVC Flexível Antichama - NBR 15465 ø3/4" | F19: 445 | G19: 1 | H19: 0 | I19: =(F19+H19*F19)*G19 -> 445 | J19: m | K19: 7.5 | L19: =I19*K19 -> 3337.5 | N19: Torre B | O19: CAIXA DE PASSAGEM | P19: 145 | Q19: 580 | Y19: 725
A20: =A7 -> Torre A | B20: =B7 -> TÉRREO | C20: INSTALAÇÕES DE TELECOMUNICAÇÃO | D20: MÓDULOS | E20: Módulo Coaxial | F20: 4 | G20: 1 | H20: 0 | I20: =(F20+H20*F20)*G20 -> 4 | J20: pç | K20: 18.5 | L20: =I20*K20 -> 74 | N20: Torre B | O20: ELETRODUTOS | P20: 8945.5 | Q20: 3005.3 | R20: 1419.1 | S20: 1419.1 | T20: 1159.9 | U20: 943.9 | V20: 6942.7 | W20: 133915.2 | X20: 543.2 | Y20: 158293.9
A21: =A7 -> Torre A | B21: =B7 -> TÉRREO | C21: INSTALAÇÕES DE TELECOMUNICAÇÃO | D21: MÓDULOS | E21: Módulo RJ11 | F21: 16 | G21: 1 | H21: 0 | I21: =(F21+H21*F21)*G21 -> 16 | J21: pç | K21: 16.8 | L21: =I21*K21 -> 268.8 | N21: Torre B | O21: MÓDULOS | P21: 1042.4 | Q21: 45.8 | V21: 142.7 | W21: 8568 | Y21: 9798.9
A22: =A7 -> Torre A | B22: =B7 -> TÉRREO | C22: INSTALAÇÕES DE TELECOMUNICAÇÃO | D22: MÓDULOS | E22: Módulo RJ45 | F22: 20 | G22: 1 | H22: 0 | I22: =(F22+H22*F22)*G22 -> 20 | J22: pç | K22: 22.9 | L22: =I22*K22 -> 458 | N22: Torre B | O22: QUADROS DE DISTRIBUIÇÃO | P22: 1260 | Q22: 465 | R22: 465 | S22: 465 | T22: 465 | V22: 420 | W22: 10080 | Y22: 13620
A23: =A7 -> Torre A | B23: =B7 -> TÉRREO | C23: INSTALAÇÕES DE TELECOMUNICAÇÃO | D23: QUADROS DE DISTRIBUIÇÃO | E23: Embutir - 396x510x107mm | F23: 3 | G23: 1 | H23: 0 | I23: =(F23+H23*F23)*G23 -> 3 | J23: pç | K23: 420 | L23: =I23*K23 -> 1260 | N23: Torre B | O23: COTOVELOS | Y23: 0
A24: =A7 -> Torre A | B24: =B7 -> TÉRREO | C24: INSTALAÇÕES DE TELECOMUNICAÇÃO | D24: ELETRODUTOS | E24: PVC Flexível Antichama - NBR 15465 ø1.1/4" | F24: 21 | G24: 1 | H24: 0 | I24: =(F24+H24*F24)*G24 -> 21 | J24: m | K24: 0 | L24: =I24*K24 -> 0 | N24: Torre B | O24: CONECTORES E BUCHAS | Y24: 0
A25: =A7 -> Torre A | B25: =B7 -> TÉRREO | C25: INSTALAÇÕES DE TELECOMUNICAÇÃO | D25: CAIXA DE PASSAGEM | E25: Cx de passagem de embutir com dimensão de 60x60x12cm | F25: 1 | G25: 1 | H25: 0 | I25: =(F25+H25*F25)*G25 -> 1 | J25: pç | K25: 0 | L25: =I25*K25 -> 0 | N25: Torre B | O25: CONDUTORES TELECOM | Y25: 0
A26: =A7 -> Torre A | B26: =B7 -> TÉRREO | C26: INSTALAÇÕES DE TELECOMUNICAÇÃO | D26: CAIXA DE PASSAGEM | E26: Cx de passagem de embutir com dimensão de 80x120x20cm | F26: 2 | G26: 1 | H26: 0 | I26: =(F26+H26*F26)*G26 -> 2 | J26: pç | K26: 0 | L26: =I26*K26 -> 0 | N26: Torre B | O26: PONTOS DE USO | Y26: 0
A27: =A7 -> Torre A | B27: =B7 -> TÉRREO | C27: INSTALAÇÕES DE TELECOMUNICAÇÃO | D27: COTOVELOS | E27: Cotovelo para eletroduto flexível PVC amarelo | F27: 575 | G27: 1 | H27: 0 | I27: =(F27+H27*F27)*G27 -> 575 | J27: un | K27: 0 | L27: =I27*K27 -> 0 | N27: Torre A
A28: =A7 -> Torre A | B28: =B7 -> TÉRREO | C28: INSTALAÇÕES DE TELECOMUNICAÇÃO | D28: CONECTORES E BUCHAS | E28: Conector box e arruela - Alumínio padrão | F28: 42 | G28: 1 | H28: 0 | I28: =(F28+H28*F28)*G28 -> 42 | J28: un | K28: 0 | L28: =I28*K28 -> 0 | N28: Torre A
A29: =A7 -> Torre A | B29: =B7 -> TÉRREO | C29: INSTALAÇÕES DE TELECOMUNICAÇÃO | D29: CONECTORES E BUCHAS | E29: Bucha terminal simples - Alumínio padrão | F29: 19 | G29: 1 | H29: 0 | I29: =(F29+H29*F29)*G29 -> 19 | J29: un | K29: 0 | L29: =I29*K29 -> 0 | N29: Torre A
A30: =A7 -> Torre A | B30: =B7 -> TÉRREO | C30: INSTALAÇÕES DE TELECOMUNICAÇÃO | D30: CONDUTORES TELECOM | E30: Condutor CFTV | F30: 26 | G30: 1 | H30: 0 | I30: =(F30+H30*F30)*G30 -> 26 | J30: un | K30: 0 | L30: =I30*K30 -> 0 | N30: Torre A
A31: =A7 -> Torre A | B31: =B7 -> TÉRREO | C31: INSTALAÇÕES DE TELECOMUNICAÇÃO | D31: CONDUTORES TELECOM | E31: Condutor UTP | F31: 17 | G31: 1 | H31: 0 | I31: =(F31+H31*F31)*G31 -> 17 | J31: un | K31: 0 | L31: =I31*K31 -> 0 | N31: Torre A
A32: =A7 -> Torre A | B32: =B7 -> TÉRREO | C32: INSTALAÇÕES DE TELECOMUNICAÇÃO | D32: CONDUTORES TELECOM | E32: Condutor CCI | F32: 16 | G32: 1 | H32: 0 | I32: =(F32+H32*F32)*G32 -> 16 | J32: un | K32: 0 | L32: =I32*K32 -> 0 | N32: Torre A
A33: =A7 -> Torre A | B33: =B7 -> TÉRREO | C33: INSTALAÇÕES DE TELECOMUNICAÇÃO | D33: CONDUTORES TELECOM | E33: Condutor Cordplast | F33: 26 | G33: 1 | H33: 0 | I33: =(F33+H33*F33)*G33 -> 26 | J33: un | K33: 0 | L33: =I33*K33 -> 0 | N33: Torre A
A34: =A7 -> Torre A | B34: =B7 -> TÉRREO | C34: INSTALAÇÕES DE TELECOMUNICAÇÃO | D34: PONTOS DE USO | E34: Caixa 4x2 - Interfone | F34: 5 | G34: 1 | H34: 0 | I34: =(F34+H34*F34)*G34 -> 5 | J34: un | K34: 0 | L34: =I34*K34 -> 0 | N34: Torre A
A35: =A7 -> Torre A | B35: =B7 -> TÉRREO | C35: INSTALAÇÕES DE TELECOMUNICAÇÃO | D35: PONTOS DE USO | E35: Caixa 4x2 - Câmera CFTV | F35: 1 | G35: 1 | H35: 0 | I35: =(F35+H35*F35)*G35 -> 1 | J35: un | K35: 0 | L35: =I35*K35 -> 0 | N35: Torre A
A36: =A7 -> Torre A | B36: =B7 -> TÉRREO | C36: INSTALAÇÕES DE TELECOMUNICAÇÃO | D36: PONTOS DE USO | E36: Caixa 4x2 - Controle de Acesso | F36: 13 | G36: 1 | H36: 0 | I36: =(F36+H36*F36)*G36 -> 13 | J36: un | K36: 0 | L36: =I36*K36 -> 0 | N36: Torre A
A37: =A7 -> Torre A | B37: =B7 -> TÉRREO | C37: INSTALAÇÕES DE TELECOMUNICAÇÃO | D37: PONTOS DE USO | E37: Caixa 4x4 - Dados/Telefone (RJ45/RJ11) | F37: 14 | G37: 1 | H37: 0 | I37: =(F37+H37*F37)*G37 -> 14 | J37: un | K37: 0 | L37: =I37*K37 -> 0 | N37: Torre A
A38: Torre A | B38: GARAGEM 01 | L38: =IF(SUM(F38:K38)=0,SUMIFS($L39:$L$9999,$B39:$B$9999,$B38,$A39:$A$9999,$A38),I38*K38) -> 3011 | N38: Torre A
A39: =A38 -> Torre A | B39: =B38 -> GARAGEM 01 | C39: INSTALAÇÕES DE TELECOMUNICAÇÃO | D39: CAIXA OCTOGONAL | E39: Caixa Octogonal Padrão NBR IEC 60670 | F39: 25 | G39: 1 | H39: 0 | I39: =(F39+H39*F39)*G39 -> 25 | J39: pç | K39: 9.8 | L39: =I39*K39 -> 245 | N39: Torre A
A40: =A38 -> Torre A | B40: =B38 -> GARAGEM 01 | C40: INSTALAÇÕES DE TELECOMUNICAÇÃO | D40: CAIXA OCTOGONAL | E40: Placa cega para caixa octogonal Padrão NBR IEC 60670 | F40: 2 | G40: 1 | H40: 0 | I40: =(F40+H40*F40)*G40 -> 2 | J40: pç | K40: 6.5 | L40: =I40*K40 -> 13 | N40: Torre A
A41: =A38 -> Torre A | B41: =B38 -> GARAGEM 01 | C41: INSTALAÇÕES DE TELECOMUNICAÇÃO | D41: CAIXA 4x2" E 4x4" | E41: Caixa 4x2" de Embutir em PVC Padrão NBR IEC 60670 | F41: 2 | G41: 1 | H41: 0 | I41: =(F41+H41*F41)*G41 -> 2 | J41: pç | K41: 5.9 | L41: =I41*K41 -> 11.8 | N41: Torre A
A42: =A38 -> Torre A | B42: =B38 -> GARAGEM 01 | C42: INSTALAÇÕES DE TELECOMUNICAÇÃO | D42: CAIXA 4x2" E 4x4" | E42: Placa 4x2" cega Padrão NBR IEC 60670 | F42: 1 | G42: 1 | H42: 0 | I42: =(F42+H42*F42)*G42 -> 1 | J42: pç | K42: 4.5 | L42: =I42*K42 -> 4.5 | N42: Torre A
A43: =A38 -> Torre A | B43: =B38 -> GARAGEM 01 | C43: INSTALAÇÕES DE TELECOMUNICAÇÃO | D43: CAIXA 4x2" E 4x4" | E43: Placa 4x2" para 1 função Padrão NBR IEC 60670 | F43: 1 | G43: 1 | H43: 0 | I43: =(F43+H43*F43)*G43 -> 1 | J43: pç | K43: 6.5 | L43: =I43*K43 -> 6.5 | N43: Torre A
A44: =A38 -> Torre A | B44: =B38 -> GARAGEM 01 | C44: INSTALAÇÕES DE TELECOMUNICAÇÃO | D44: CAIXA 4x2" E 4x4" | E44: Suporte p/ caixa 4x2" Padrão NBR IEC 60670 | F44: 2 | G44: 1 | H44: 0 | I44: =(F44+H44*F44)*G44 -> 2 | J44: pç | K44: 2.4 | L44: =I44*K44 -> 4.8 | N44: Torre A
A45: =A38 -> Torre A | B45: =B38 -> GARAGEM 01 | C45: INSTALAÇÕES DE TELECOMUNICAÇÃO | D45: CAIXA DE PASSAGEM | E45: Cx de passagem de embutir com dimensão de 30x30x12 cm | F45: 3 | G45: 1 | H45: 0 | I45: =(F45+H45*F45)*G45 -> 3 | J45: pç | K45: 145 | L45: =I45*K45 -> 435 | N45: Torre A
A46: =A38 -> Torre A | B46: =B38 -> GARAGEM 01 | C46: INSTALAÇÕES DE TELECOMUNICAÇÃO | D46: ELETRODUTOS | E46: PVC Flexível Antichama - NBR 15465 ø1" | F46: 125 | G46: 1 | H46: 0 | I46: =(F46+H46*F46)*G46 -> 125 | J46: m | K46: 11.9 | L46: =I46*K46 -> 1487.5 | N46: Torre A
A47: =A38 -> Torre A | B47: =B38 -> GARAGEM 01 | C47: INSTALAÇÕES DE TELECOMUNICAÇÃO | D47: ELETRODUTOS | E47: PVC Flexível Antichama - NBR 15465 ø3/4" | F47: 104 | G47: 1 | H47: 0 | I47: =(F47+H47*F47)*G47 -> 104 | J47: m | K47: 7.5 | L47: =I47*K47 -> 780 | N47: Torre A
A48: =A38 -> Torre A | B48: =B38 -> GARAGEM 01 | C48: INSTALAÇÕES DE TELECOMUNICAÇÃO | D48: MÓDULOS | E48: Módulo RJ45 | F48: 1 | G48: 1 | H48: 0 | I48: =(F48+H48*F48)*G48 -> 1 | J48: pç | K48: 22.9 | L48: =I48*K48 -> 22.9 | N48: Torre A
A49: =A38 -> Torre A | B49: =B38 -> GARAGEM 01 | C49: INSTALAÇÕES DE TELECOMUNICAÇÃO | D49: ELETRODUTOS | E49: PVC Flexível Antichama - NBR 15465 ø1.1/4" | F49: 6 | G49: 1 | H49: 0 | I49: =(F49+H49*F49)*G49 -> 6 | J49: m | K49: 0 | L49: =I49*K49 -> 0 | N49: Torre A
A50: =A38 -> Torre A | B50: =B38 -> GARAGEM 01 | C50: INSTALAÇÕES DE TELECOMUNICAÇÃO | D50: ELETRODUTOS | E50: PVC Flexível Antichama - NBR 15465 ø1.1/4" | F50: 6 | G50: 1 | H50: 0 | I50: =(F50+H50*F50)*G50 -> 6 | J50: m | K50: 0 | L50: =I50*K50 -> 0 | N50: Torre A
A51: =A38 -> Torre A | B51: =B38 -> GARAGEM 01 | C51: INSTALAÇÕES DE TELECOMUNICAÇÃO | D51: ELETRODUTOS | E51: PVC Flexível Antichama - NBR 15465 ø3" | F51: 13 | G51: 1 | H51: 0 | I51: =(F51+H51*F51)*G51 -> 13 | J51: m | K51: 0 | L51: =I51*K51 -> 0 | N51: Torre A
A52: =A38 -> Torre A | B52: =B38 -> GARAGEM 01 | C52: INSTALAÇÕES DE TELECOMUNICAÇÃO | D52: CAIXA DE PASSAGEM | E52: Cx de passagem de embutir com dimensão de 60x120x15cm | F52: 1 | G52: 1 | H52: 0 | I52: =(F52+H52*F52)*G52 -> 1 | J52: pç | K52: 0 | L52: =I52*K52 -> 0 | N52: Torre A
A53: =A38 -> Torre A | B53: =B38 -> GARAGEM 01 | C53: INSTALAÇÕES DE TELECOMUNICAÇÃO | D53: COTOVELOS | E53: Cotovelo para eletroduto flexível PVC amarelo | F53: 125 | G53: 1 | H53: 0 | I53: =(F53+H53*F53)*G53 -> 125 | J53: un | K53: 0 | L53: =I53*K53 -> 0 | N53: Torre A
A54: =A38 -> Torre A | B54: =B38 -> GARAGEM 01 | C54: INSTALAÇÕES DE TELECOMUNICAÇÃO | D54: CONECTORES E BUCHAS | E54: Conector box e arruela - Alumínio padrão | F54: 19 | G54: 1 | H54: 0 | I54: =(F54+H54*F54)*G54 -> 19 | J54: un | K54: 0 | L54: =I54*K54 -> 0 | N54: Torre A
A55: =A38 -> Torre A | B55: =B38 -> GARAGEM 01 | C55: INSTALAÇÕES DE TELECOMUNICAÇÃO | D55: CONECTORES E BUCHAS | E55: Bucha terminal simples - Alumínio padrão | F55: 6 | G55: 1 | H55: 0 | I55: =(F55+H55*F55)*G55 -> 6 | J55: un | K55: 0 | L55: =I55*K55 -> 0 | N55: Torre A
A56: =A38 -> Torre A | B56: =B38 -> GARAGEM 01 | C56: INSTALAÇÕES DE TELECOMUNICAÇÃO | D56: CONDUTORES TELECOM | E56: Condutor CFTV | F56: 4 | G56: 1 | H56: 0 | I56: =(F56+H56*F56)*G56 -> 4 | J56: un | K56: 0 | L56: =I56*K56 -> 0 | N56: Torre A
A57: =A38 -> Torre A | B57: =B38 -> GARAGEM 01 | C57: INSTALAÇÕES DE TELECOMUNICAÇÃO | D57: CONDUTORES TELECOM | E57: Condutor Cordplast | F57: 4 | G57: 1 | H57: 0 | I57: =(F57+H57*F57)*G57 -> 4 | J57: un | K57: 0 | L57: =I57*K57 -> 0 | N57: Torre A
A58: =A38 -> Torre A | B58: =B38 -> GARAGEM 01 | C58: INSTALAÇÕES DE TELECOMUNICAÇÃO | D58: PONTOS DE USO | E58: Caixa 4x2 - Interfone | F58: 4 | G58: 1 | H58: 0 | I58: =(F58+H58*F58)*G58 -> 4 | J58: un | K58: 0 | L58: =I58*K58 -> 0 | N58: Torre A
A59: =A38 -> Torre A | B59: =B38 -> GARAGEM 01 | C59: INSTALAÇÕES DE TELECOMUNICAÇÃO | D59: PONTOS DE USO | E59: Caixa 4x2 - Câmera CFTV | F59: 2 | G59: 1 | H59: 0 | I59: =(F59+H59*F59)*G59 -> 2 | J59: un | K59: 0 | L59: =I59*K59 -> 0 | N59: Torre A
A60: Torre A | B60: GARAGEM 02 | L60: =IF(SUM(F60:K60)=0,SUMIFS($L61:$L$9999,$B61:$B$9999,$B60,$A61:$A$9999,$A60),I60*K60) -> 1212.3 | N60: Torre A
A61: =A60 -> Torre A | B61: =B60 -> GARAGEM 02 | C61: INSTALAÇÕES DE TELECOMUNICAÇÃO | D61: CAIXA OCTOGONAL | E61: Caixa Octogonal Padrão NBR IEC 60670 | F61: 17 | G61: 1 | H61: 0 | I61: =(F61+H61*F61)*G61 -> 17 | J61: pç | K61: 9.8 | L61: =I61*K61 -> 166.6 | N61: Torre A
A62: =A60 -> Torre A | B62: =B60 -> GARAGEM 02 | C62: INSTALAÇÕES DE TELECOMUNICAÇÃO | D62: CAIXA OCTOGONAL | E62: Placa cega para caixa octogonal Padrão NBR IEC 60670 | F62: 1 | G62: 1 | H62: 0 | I62: =(F62+H62*F62)*G62 -> 1 | J62: pç | K62: 6.5 | L62: =I62*K62 -> 6.5 | N62: Torre A
A63: =A60 -> Torre A | B63: =B60 -> GARAGEM 02 | C63: INSTALAÇÕES DE TELECOMUNICAÇÃO | D63: CAIXA 4x2" E 4x4" | E63: Caixa 4x2" de Embutir em PVC Padrão NBR IEC 60670 | F63: 1 | G63: 1 | H63: 0 | I63: =(F63+H63*F63)*G63 -> 1 | J63: pç | K63: 5.9 | L63: =I63*K63 -> 5.9 | N63: Torre A
A64: =A60 -> Torre A | B64: =B60 -> GARAGEM 02 | C64: INSTALAÇÕES DE TELECOMUNICAÇÃO | D64: CAIXA 4x2" E 4x4" | E64: Placa 4x2" cega Padrão NBR IEC 60670 | F64: 1 | G64: 1 | H64: 0 | I64: =(F64+H64*F64)*G64 -> 1 | J64: pç | K64: 4.5 | L64: =I64*K64 -> 4.5 | N64: Torre A
A65: =A60 -> Torre A | B65: =B60 -> GARAGEM 02 | C65: INSTALAÇÕES DE TELECOMUNICAÇÃO | D65: CAIXA 4x2" E 4x4" | E65: Suporte p/ caixa 4x2" Padrão NBR IEC 60670 | F65: 1 | G65: 1 | H65: 0 | I65: =(F65+H65*F65)*G65 -> 1 | J65: pç | K65: 2.4 | L65: =I65*K65 -> 2.4 | N65: Torre A
A66: =A60 -> Torre A | B66: =B60 -> GARAGEM 02 | C66: INSTALAÇÕES DE TELECOMUNICAÇÃO | D66: ELETRODUTOS | E66: PVC Flexível Antichama - NBR 15465 ø1" | F66: 56 | G66: 1 | H66: 0 | I66: =(F66+H66*F66)*G66 -> 56 | J66: m | K66: 11.9 | L66: =I66*K66 -> 666.4 | N66: Torre A
A67: =A60 -> Torre A | B67: =B60 -> GARAGEM 02 | C67: INSTALAÇÕES DE TELECOMUNICAÇÃO | D67: ELETRODUTOS | E67: PVC Flexível Antichama - NBR 15465 ø3/4" | F67: 48 | G67: 1 | H67: 0 | I67: =(F67+H67*F67)*G67 -> 48 | J67: m | K67: 7.5 | L67: =I67*K67 -> 360 | N67: Torre A
A68: =A60 -> Torre A | B68: =B60 -> GARAGEM 02 | C68: INSTALAÇÕES DE TELECOMUNICAÇÃO | D68: ELETRODUTOS | E68: PVC Flexível Antichama - NBR 15465 ø3" | F68: 6 | G68: 1 | H68: 0 | I68: =(F68+H68*F68)*G68 -> 6 | J68: m | K68: 0 | L68: =I68*K68 -> 0 | N68: Torre A
A69: =A60 -> Torre A | B69: =B60 -> GARAGEM 02 | C69: INSTALAÇÕES DE TELECOMUNICAÇÃO | D69: CAIXA DE PASSAGEM | E69: Cx de passagem de embutir com dimensão de 40x120x15cm | F69: 1 | G69: 1 | H69: 0 | I69: =(F69+H69*F69)*G69 -> 1 | J69: pç | K69: 0 | L69: =I69*K69 -> 0 | N69: Torre A
A70: =A60 -> Torre A | B70: =B60 -> GARAGEM 02 | C70: INSTALAÇÕES DE TELECOMUNICAÇÃO | D70: COTOVELOS | E70: Cotovelo para eletroduto flexível PVC amarelo | F70: 76 | G70: 1 | H70: 0 | I70: =(F70+H70*F70)*G70 -> 76 | J70: un | K70: 0 | L70: =I70*K70 -> 0 | N70: Torre A
A71: =A60 -> Torre A | B71: =B60 -> GARAGEM 02 | C71: INSTALAÇÕES DE TELECOMUNICAÇÃO | D71: CONECTORES E BUCHAS | E71: Conector box e arruela - Alumínio padrão | F71: 21 | G71: 1 | H71: 0 | I71: =(F71+H71*F71)*G71 -> 21 | J71: un | K71: 0 | L71: =I71*K71 -> 0 | N71: Torre A
A72: =A60 -> Torre A | B72: =B60 -> GARAGEM 02 | C72: INSTALAÇÕES DE TELECOMUNICAÇÃO | D72: CONECTORES E BUCHAS | E72: Bucha terminal simples - Alumínio padrão | F72: 2 | G72: 1 | H72: 0 | I72: =(F72+H72*F72)*G72 -> 2 | J72: un | K72: 0 | L72: =I72*K72 -> 0 | N72: Torre A
A73: =A60 -> Torre A | B73: =B60 -> GARAGEM 02 | C73: INSTALAÇÕES DE TELECOMUNICAÇÃO | D73: CONDUTORES TELECOM | E73: Condutor CFTV | F73: 4 | G73: 1 | H73: 0 | I73: =(F73+H73*F73)*G73 -> 4 | J73: un | K73: 0 | L73: =I73*K73 -> 0 | N73: Torre A
A74: =A60 -> Torre A | B74: =B60 -> GARAGEM 02 | C74: INSTALAÇÕES DE TELECOMUNICAÇÃO | D74: CONDUTORES TELECOM | E74: Condutor Cordplast | F74: 4 | G74: 1 | H74: 0 | I74: =(F74+H74*F74)*G74 -> 4 | J74: un | K74: 0 | L74: =I74*K74 -> 0 | N74: Torre A
A75: =A60 -> Torre A | B75: =B60 -> GARAGEM 02 | C75: INSTALAÇÕES DE TELECOMUNICAÇÃO | D75: PONTOS DE USO | E75: Caixa 4x2 - Interfone | F75: 4 | G75: 1 | H75: 0 | I75: =(F75+H75*F75)*G75 -> 4 | J75: un | K75: 0 | L75: =I75*K75 -> 0 | N75: Torre A
A76: =A60 -> Torre A | B76: =B60 -> GARAGEM 02 | C76: INSTALAÇÕES DE TELECOMUNICAÇÃO | D76: PONTOS DE USO | E76: Caixa 4x2 - Câmera CFTV | F76: 2 | G76: 1 | H76: 0 | I76: =(F76+H76*F76)*G76 -> 2 | J76: un | K76: 0 | L76: =I76*K76 -> 0 | N76: Torre A
A77: Torre A | B77: GARAGEM 03 | L77: =IF(SUM(F77:K77)=0,SUMIFS($L78:$L$9999,$B78:$B$9999,$B77,$A78:$A$9999,$A77),I77*K77) -> 1212.3 | N77: Torre A
A78: =A77 -> Torre A | B78: =B77 -> GARAGEM 03 | C78: INSTALAÇÕES DE TELECOMUNICAÇÃO | D78: CAIXA OCTOGONAL | E78: Caixa Octogonal Padrão NBR IEC 60670 | F78: 17 | G78: 1 | H78: 0 | I78: =(F78+H78*F78)*G78 -> 17 | J78: pç | K78: 9.8 | L78: =I78*K78 -> 166.6 | N78: Torre A
A79: =A77 -> Torre A | B79: =B77 -> GARAGEM 03 | C79: INSTALAÇÕES DE TELECOMUNICAÇÃO | D79: CAIXA OCTOGONAL | E79: Placa cega para caixa octogonal Padrão NBR IEC 60670 | F79: 1 | G79: 1 | H79: 0 | I79: =(F79+H79*F79)*G79 -> 1 | J79: pç | K79: 6.5 | L79: =I79*K79 -> 6.5 | N79: Torre A
A80: =A77 -> Torre A | B80: =B77 -> GARAGEM 03 | C80: INSTALAÇÕES DE TELECOMUNICAÇÃO | D80: CAIXA 4x2" E 4x4" | E80: Caixa 4x2" de Embutir em PVC Padrão NBR IEC 60670 | F80: 1 | G80: 1 | H80: 0 | I80: =(F80+H80*F80)*G80 -> 1 | J80: pç | K80: 5.9 | L80: =I80*K80 -> 5.9 | N80: Torre A
A81: =A77 -> Torre A | B81: =B77 -> GARAGEM 03 | C81: INSTALAÇÕES DE TELECOMUNICAÇÃO | D81: CAIXA 4x2" E 4x4" | E81: Placa 4x2" cega Padrão NBR IEC 60670 | F81: 1 | G81: 1 | H81: 0 | I81: =(F81+H81*F81)*G81 -> 1 | J81: pç | K81: 4.5 | L81: =I81*K81 -> 4.5 | N81: Torre A
A82: =A77 -> Torre A | B82: =B77 -> GARAGEM 03 | C82: INSTALAÇÕES DE TELECOMUNICAÇÃO | D82: CAIXA 4x2" E 4x4" | E82: Suporte p/ caixa 4x2" Padrão NBR IEC 60670 | F82: 1 | G82: 1 | H82: 0 | I82: =(F82+H82*F82)*G82 -> 1 | J82: pç | K82: 2.4 | L82: =I82*K82 -> 2.4 | N82: Torre A
A83: =A77 -> Torre A | B83: =B77 -> GARAGEM 03 | C83: INSTALAÇÕES DE TELECOMUNICAÇÃO | D83: ELETRODUTOS | E83: PVC Flexível Antichama - NBR 15465 ø1" | F83: 56 | G83: 1 | H83: 0 | I83: =(F83+H83*F83)*G83 -> 56 | J83: m | K83: 11.9 | L83: =I83*K83 -> 666.4 | N83: Torre A
A84: =A77 -> Torre A | B84: =B77 -> GARAGEM 03 | C84: INSTALAÇÕES DE TELECOMUNICAÇÃO | D84: ELETRODUTOS | E84: PVC Flexível Antichama - NBR 15465 ø3/4" | F84: 48 | G84: 1 | H84: 0 | I84: =(F84+H84*F84)*G84 -> 48 | J84: m | K84: 7.5 | L84: =I84*K84 -> 360 | N84: Torre A
A85: =A77 -> Torre A | B85: =B77 -> GARAGEM 03 | C85: INSTALAÇÕES DE TELECOMUNICAÇÃO | D85: ELETRODUTOS | E85: PVC Flexível Antichama - NBR 15465 ø3" | F85: 6 | G85: 1 | H85: 0 | I85: =(F85+H85*F85)*G85 -> 6 | J85: m | K85: 0 | L85: =I85*K85 -> 0 | N85: Torre A
A86: =A77 -> Torre A | B86: =B77 -> GARAGEM 03 | C86: INSTALAÇÕES DE TELECOMUNICAÇÃO | D86: CAIXA DE PASSAGEM | E86: Cx de passagem de embutir com dimensão de 40x120x15cm | F86: 1 | G86: 1 | H86: 0 | I86: =(F86+H86*F86)*G86 -> 1 | J86: pç | K86: 0 | L86: =I86*K86 -> 0 | N86: Torre A
A87: =A77 -> Torre A | B87: =B77 -> GARAGEM 03 | C87: INSTALAÇÕES DE TELECOMUNICAÇÃO | D87: COTOVELOS | E87: Cotovelo para eletroduto flexível PVC amarelo | F87: 71 | G87: 1 | H87: 0 | I87: =(F87+H87*F87)*G87 -> 71 | J87: un | K87: 0 | L87: =I87*K87 -> 0 | N87: Torre A
A88: =A77 -> Torre A | B88: =B77 -> GARAGEM 03 | C88: INSTALAÇÕES DE TELECOMUNICAÇÃO | D88: CONECTORES E BUCHAS | E88: Conector box e arruela - Alumínio padrão | F88: 15 | G88: 1 | H88: 0 | I88: =(F88+H88*F88)*G88 -> 15 | J88: un | K88: 0 | L88: =I88*K88 -> 0 | N88: Torre A
A89: =A77 -> Torre A | B89: =B77 -> GARAGEM 03 | C89: INSTALAÇÕES DE TELECOMUNICAÇÃO | D89: CONECTORES E BUCHAS | E89: Bucha terminal simples - Alumínio padrão | F89: 6 | G89: 1 | H89: 0 | I89: =(F89+H89*F89)*G89 -> 6 | J89: un | K89: 0 | L89: =I89*K89 -> 0 | N89: Torre A
A90: =A77 -> Torre A | B90: =B77 -> GARAGEM 03 | C90: INSTALAÇÕES DE TELECOMUNICAÇÃO | D90: CONDUTORES TELECOM | E90: Condutor CFTV | F90: 4 | G90: 1 | H90: 0 | I90: =(F90+H90*F90)*G90 -> 4 | J90: un | K90: 0 | L90: =I90*K90 -> 0 | N90: Torre A
A91: =A77 -> Torre A | B91: =B77 -> GARAGEM 03 | C91: INSTALAÇÕES DE TELECOMUNICAÇÃO | D91: CONDUTORES TELECOM | E91: Condutor Cordplast | F91: 4 | G91: 1 | H91: 0 | I91: =(F91+H91*F91)*G91 -> 4 | J91: un | K91: 0 | L91: =I91*K91 -> 0 | N91: Torre A
A92: =A77 -> Torre A | B92: =B77 -> GARAGEM 03 | C92: INSTALAÇÕES DE TELECOMUNICAÇÃO | D92: PONTOS DE USO | E92: Caixa 4x2 - Interfone | F92: 4 | G92: 1 | H92: 0 | I92: =(F92+H92*F92)*G92 -> 4 | J92: un | K92: 0 | L92: =I92*K92 -> 0 | N92: Torre A
A93: =A77 -> Torre A | B93: =B77 -> GARAGEM 03 | C93: INSTALAÇÕES DE TELECOMUNICAÇÃO | D93: PONTOS DE USO | E93: Caixa 4x2 - Câmera CFTV | F93: 2 | G93: 1 | H93: 0 | I93: =(F93+H93*F93)*G93 -> 2 | J93: un | K93: 0 | L93: =I93*K93 -> 0 | N93: Torre A
A94: Torre A | B94: GARAGEM 04 | L94: =IF(SUM(F94:K94)=0,SUMIFS($L95:$L$9999,$B95:$B$9999,$B94,$A95:$A$9999,$A94),I94*K94) -> 1152.4 | N94: Torre A
A95: =A94 -> Torre A | B95: =B94 -> GARAGEM 04 | C95: INSTALAÇÕES DE TELECOMUNICAÇÃO | D95: CAIXA OCTOGONAL | E95: Caixa Octogonal Padrão NBR IEC 60670 | F95: 18 | G95: 1 | H95: 0 | I95: =(F95+H95*F95)*G95 -> 18 | J95: pç | K95: 9.8 | L95: =I95*K95 -> 176.4 | N95: Torre A
A96: =A94 -> Torre A | B96: =B94 -> GARAGEM 04 | C96: INSTALAÇÕES DE TELECOMUNICAÇÃO | D96: CAIXA OCTOGONAL | E96: Placa cega para caixa octogonal Padrão NBR IEC 60670 | F96: 1 | G96: 1 | H96: 0 | I96: =(F96+H96*F96)*G96 -> 1 | J96: pç | K96: 6.5 | L96: =I96*K96 -> 6.5 | N96: Torre A
A97: =A94 -> Torre A | B97: =B94 -> GARAGEM 04 | C97: INSTALAÇÕES DE TELECOMUNICAÇÃO | D97: ELETRODUTOS | E97: PVC Flexível Antichama - NBR 15465 ø1" | F97: 55 | G97: 1 | H97: 0 | I97: =(F97+H97*F97)*G97 -> 55 | J97: m | K97: 11.9 | L97: =I97*K97 -> 654.5 | N97: Torre A
A98: =A94 -> Torre A | B98: =B94 -> GARAGEM 04 | C98: INSTALAÇÕES DE TELECOMUNICAÇÃO | D98: ELETRODUTOS | E98: PVC Flexível Antichama - NBR 15465 ø3/4" | F98: 42 | G98: 1 | H98: 0 | I98: =(F98+H98*F98)*G98 -> 42 | J98: m | K98: 7.5 | L98: =I98*K98 -> 315 | N98: Torre A
A99: =A94 -> Torre A | B99: =B94 -> GARAGEM 04 | C99: INSTALAÇÕES DE TELECOMUNICAÇÃO | D99: ELETRODUTOS | E99: PVC Flexível Antichama - NBR 15465 ø3" | F99: 6 | G99: 1 | H99: 0 | I99: =(F99+H99*F99)*G99 -> 6 | J99: m | K99: 0 | L99: =I99*K99 -> 0 | N99: Torre A
A100: =A94 -> Torre A | B100: =B94 -> GARAGEM 04 | C100: INSTALAÇÕES DE TELECOMUNICAÇÃO | D100: CAIXA DE PASSAGEM | E100: Cx de passagem de embutir com dimensão de 40x120x15cm | F100: 1 | G100: 1 | H100: 0 | I100: =(F100+H100*F100)*G100 -> 1 | J100: pç | K100: 0 | L100: =I100*K100 -> 0 | N100: Torre A
...

Sheet Ger_Executivo_Manual
H4: PROJETO: | I4: Electra Towers | O4: REVISÃO: | P4: DATA
H5: EMPRESA: | I5: Thozen | O5: R00
A6: Unidade Construtiva | B6: Célula Construtiva | C6: Etapa | D6: Subetapa | E6: Serviço | G6: GERENCIAMENTO EXECUTIVO
A7: 0 | B7: 0 | C7: 0 | D7: 0 | E7: 0 | G7: EAP | H7: NIVEL | I7: Item | J7: Descrição | K7: Unidade | L7: Quant. | M7: Preço un | N7: Total | O7: Considerações | P7: Situação
A8: 0 | B8: 1 | C8: 0 | D8: 0 | E8: 0 | H8: CÉLULA CONSTRUTIVA | I8: 01 | J8: MOVIMENTAÇÃO DE TERRA
A9: 0 | B9: 1 | C9: 1 | D9: 0 | E9: 0 | H9: ETAPA | I9: 01.001 | J9: DEMOLIÇÕES, LIMPEZA DE TERRENO E LOCAÇÃO DE OBRA | N9: 26235.314 | O9: 1.5663183
A10: 0 | B10: 1 | C10: 1 | D10: 1 | E10: 0 | H10: SUBETAPA | I10: 01.001.001 | J10: Locação e gabarito de obra | N10: 26235.314 | O10: 1.5663183
A11: 0 | B11: 1 | C11: 1 | D11: 1 | E11: 1 | G11: MOVIMENTAÇÃO DE TERRA | H11: SERVIÇO | I11: 01.001.001.001 | J11: Locação da obra | K11: m2 | N11: 26235.314 | P11: Pendente
A12: 0 | B12: 1 | C12: 2 | D12: 0 | E12: 1 | H12: ETAPA | I12: 01.002 | J12: SERVIÇOS PRELIMINARES
A13: 0 | B13: 1 | C13: 2 | D13: 1 | E13: 0 | H13: SUBETAPA | I13: 01.002.001 | J13: Limpeza Permanente e Remoção entulho
A14: 0 | B14: 1 | C14: 2 | D14: 1 | E14: 1 | G14: MOVIMENTAÇÃO DE TERRA | H14: SERVIÇO | I14: 01.002.001.001 | J14: Limpeza da camada vegetal | K14: m2 | P14: Pendente
A15: 0 | B15: 1 | C15: 2 | D15: 1 | E15: 2 | G15: MOVIMENTAÇÃO DE TERRA | H15: SERVIÇO | I15: 01.002.001.002 | J15: Remoção de entulhos e resíduos | P15: Pendente
A16: 0 | B16: 1 | C16: 2 | D16: 2 | E16: 0 | H16: SUBETAPA | I16: 01.002.002 | J16: Mão de Obra de Canteiro
A17: 0 | B17: 1 | C17: 2 | D17: 2 | E17: 1 | G17: MOVIMENTAÇÃO DE TERRA | H17: SERVIÇO | I17: 01.002.002.001 | J17: Mão de Obra de Canteiro | K17: vb | P17: Pendente
A18: 0 | B18: 1 | C18: 3 | D18: 0 | E18: 1 | H18: ETAPA | I18: 01.003 | J18: SERVIÇOS DE TERRAPLANAGEM | N18: 271126.19 | O18: 16.186957
A19: 0 | B19: 1 | C19: 3 | D19: 1 | E19: 0 | H19: SUBETAPA | I19: 01.003.001 | J19: Mao de obra - movimentações de terra | N19: 271126.19 | O19: 16.186957
A20: 0 | B20: 1 | C20: 3 | D20: 1 | E20: 1 | G20: MOVIMENTAÇÃO DE TERRA | H20: SERVIÇO | I20: 01.003.001.001 | J20: Mão de obra movimentação de terra | K20: vb | N20: 233000 | P20: Pendente
A21: 0 | B21: 1 | C21: 4 | D21: 0 | E21: 2 | H21: ETAPA | I21: 01.004 | J21: SERVIÇO DE DRENAGEM | N21: 80000 | O21: 4.7762135
A22: 0 | B22: 1 | C22: 4 | D22: 1 | E22: 0 | H22: SUBETAPA | I22: 01.004.001 | J22: Drenagem | N22: 80000 | O22: 4.7762135
A23: 0 | B23: 1 | C23: 4 | D23: 1 | E23: 1 | G23: MOVIMENTAÇÃO DE TERRA | H23: SERVIÇO | I23: 01.004.001.001 | J23: Rebaixamento de Lençol freático | K23: vb | N23: 80000 | P23: Pendente
A24: 0 | B24: 2 | C24: 0 | D24: 1 | E24: 1 | H24: CÉLULA CONSTRUTIVA | I24: 02 | J24: CONTENÇÃO | N24: 772006.63 | O24: 46.090856
A25: 0 | B25: 2 | C25: 1 | D25: 0 | E25: 1 | H25: ETAPA | I25: 02.001 | J25: MURETA GUIA | N25: 18739.389 | O25: 1.1187915
A26: 0 | B26: 2 | C26: 1 | D26: 1 | E26: 0 | H26: SUBETAPA | I26: 02.001.001 | J26: Forma | N26: 6673.9436 | O26: 0.39845225
A27: 0 | B27: 2 | C27: 1 | D27: 1 | E27: 1 | G27: CONTENÇÃO | H27: SERVIÇO | I27: 02.001.001.001 | J27: Forma para infraestrutura em Tábuas de Madeira Serrada 2x reaproveitamento | K27: m2 | L27: 111.3136 | M27: 59.956229 | N27: 6673.9436 | P27: Pendente
A28: 0 | B28: 2 | C28: 1 | D28: 2 | E28: 0 | H28: SUBETAPA | I28: 02.001.002 | J28: Armadura | N28: 4318.7306 | O28: 0.25783974
A29: 0 | B29: 2 | C29: 1 | D29: 2 | E29: 1 | G29: CONTENÇÃO | H29: SERVIÇO | I29: 02.001.002.001 | J29: Armação aço CA-50 ø 6,3mm para Contenções (corte e dobra em obra) | K29: un | L29: 670.32 | M29: 6.0795674 | N29: 4075.2556 | P29: Pendente
A30: 0 | B30: 2 | C30: 1 | D30: 2 | E30: 2 | G30: CONTENÇÃO | H30: SERVIÇO | I30: 02.001.002.002 | J30: Armação aço CA-50 ø 12,5mm para Contenções (corte e dobra em obra) | K30: un | L30: 41.6016 | M30: 5.8525391 | N30: 243.47499 | P30: Pendente
A31: 0 | B31: 2 | C31: 1 | D31: 3 | E31: 0 | H31: SUBETAPA | I31: 02.001.003 | J31: Concreto | N31: 7746.7147 | O31: 0.46249954
A32: 0 | B32: 2 | C32: 1 | D32: 3 | E32: 1 | G32: CONTENÇÃO | H32: SERVIÇO | I32: 02.001.003.001 | J32: Concreto Usinado bombeável 50MPa para infraestrutura- incluindo serviço de bombeamento | K32: m3 | L32: 11.390452 | M32: 680.106 | N32: 7746.7147 | P32: Pendente
A33: 0 | B33: 2 | C33: 2 | D33: 0 | E33: 1 | H33: ETAPA | I33: 02.002 | J33: LAMELAS | PAREDE DIAFRAGMA | N33: 331865.23 | O33: 19.81324
A34: 0 | B34: 2 | C34: 2 | D34: 1 | E34: 0 | H34: SUBETAPA | I34: 02.002.001 | J34: Armadura | N34: 155967.97 | O34: 9.3117038
A35: 0 | B35: 2 | C35: 2 | D35: 1 | E35: 1 | G35: CONTENÇÃO | H35: SERVIÇO | I35: 02.002.001.001 | J35: Armação aço CA-50 ø 6,3mm para Contenções (corte e dobra em Indústria) | K35: un | L35: 2282 | M35: 8.964145 | N35: 20456.179 | P35: Pendente
A36: 0 | B36: 2 | C36: 2 | D36: 1 | E36: 2 | G36: CONTENÇÃO | H36: SERVIÇO | I36: 02.002.001.002 | J36: Armação aço CA-50 ø 8,0mm para Contenções (corte e dobra em Indústria) | K36: un | L36: 77 | M36: 8.964145 | N36: 690.23916 | P36: Pendente
A37: 0 | B37: 2 | C37: 2 | D37: 1 | E37: 3 | G37: CONTENÇÃO | H37: SERVIÇO | I37: 02.002.001.003 | J37: Armação aço CA-50 ø 12,5mm para Contenções (corte e dobra em Indústria) | K37: un | L37: 3884 | M37: 8.484145 | N37: 32952.419 | P37: Pendente
A38: 0 | B38: 2 | C38: 2 | D38: 1 | E38: 4 | G38: CONTENÇÃO | H38: SERVIÇO | I38: 02.002.001.004 | J38: Armação aço CA-50 ø 25,0mm para Contenções (corte e dobra em Indústria) | K38: un | L38: 12007 | M38: 8.484145 | N38: 101869.13 | P38: Pendente
A39: 0 | B39: 2 | C39: 2 | D39: 2 | E39: 0 | H39: SUBETAPA | I39: 02.002.002 | J39: Concreto | N39: 175897.26 | O39: 10.501536
A40: 0 | B40: 2 | C40: 2 | D40: 2 | E40: 1 | G40: CONTENÇÃO | H40: SERVIÇO | I40: 02.002.002.001 | J40: Concreto Usinado bombeável 50MPa com Penetron para infraestrutura- incluindo serviço de bombeamento | K40: m3 | L40: 210 | M40: 837.606 | N40: 175897.26 | P40: Pendente
A41: 0 | B41: 2 | C41: 3 | D41: 0 | E41: 1 | H41: ETAPA | I41: 02.003 | J41: VIGAS COROAMENTO | N41: 37645.991 | O41: 2.2475661
A42: 0 | B42: 2 | C42: 3 | D42: 1 | E42: 0 | H42: SUBETAPA | I42: 02.003.001 | J42: Forma | N42: 2482.1879 | O42: 0.14819324
A43: 0 | B43: 2 | C43: 3 | D43: 1 | E43: 1 | G43: CONTENÇÃO | H43: SERVIÇO | I43: 02.003.001.001 | J43: Forma para infraestrutura em Tábuas de Madeira Serrada 2x reaproveitamento | K43: m2 | L43: 41.4 | M43: 59.956229 | N43: 2482.1879 | P43: Pendente
A44: 0 | B44: 2 | C44: 3 | D44: 2 | E44: 0 | H44: SUBETAPA | I44: 02.003.002 | J44: Armadura | N44: 23057.916 | O44: 1.3766191
A45: 0 | B45: 2 | C45: 3 | D45: 2 | E45: 1 | G45: CONTENÇÃO | H45: SERVIÇO | I45: 02.003.002.001 | J45: Armação aço CA-50 ø 8,0mm para Contenções (corte e dobra em Indústria) | K45: kg | L45: 913.36364 | M45: 8.964145 | N45: 8187.5241 | P45: Pendente
A46: 0 | B46: 2 | C46: 3 | D46: 2 | E46: 2 | G46: CONTENÇÃO | H46: SERVIÇO | I46: 02.003.002.002 | J46: Armação aço CA-50 ø 12,5mm para Contenções (corte e dobra em Indústria) | K46: kg | L46: 45.363636 | M46: 8.484145 | N46: 384.87167 | P46: Pendente
A47: 0 | B47: 2 | C47: 3 | D47: 2 | E47: 3 | G47: CONTENÇÃO | H47: SERVIÇO | I47: 02.003.002.003 | J47: Armação aço CA-50 ø 16,0mm para Contenções (corte e dobra em Indústria) | K47: kg | L47: 1277.2727 | M47: 8.484145 | N47: 10836.567 | P47: Pendente
A48: 0 | B48: 2 | C48: 3 | D48: 2 | E48: 4 | G48: CONTENÇÃO | H48: SERVIÇO | I48: 02.003.002.004 | J48: Armação aço CA-50 ø 20,0mm para Contenções (corte e dobra em Indústria) | K48: kg | L48: 430.09091 | M48: 8.484145 | N48: 3648.9536 | P48: Pendente
A49: 0 | B49: 2 | C49: 3 | D49: 3 | E49: 0 | H49: SUBETAPA | I49: 02.003.003 | J49: Concreto | N49: 12105.887
A50: 0 | B50: 2 | C50: 3 | D50: 3 | E50: 1 | G50: CONTENÇÃO | H50: SERVIÇO | I50: 02.003.003.001 | J50: Concreto Usinado bombeável 50MPa para infraestrutura- incluindo serviço de bombeamento | K50: m3 | L50: 17.8 | M50: 680.106 | N50: 12105.887 | P50: Pendente
A51: 0 | B51: 2 | C51: 4 | D51: 0 | E51: 1 | H51: ETAPA | I51: 02.004 | J51: ESTACAS PRANCHA METÁLICA | N51: 243756 | O51: 14.552884
A52: 0 | B52: 2 | C52: 4 | D52: 1 | E52: 0 | H52: SUBETAPA | I52: 02.004.001 | J52: Estacas prancha metálica | N52: 243756 | O52: 14.552884
A53: 0 | B53: 2 | C53: 4 | D53: 1 | E53: 1 | G53: CONTENÇÃO | H53: SERVIÇO | I53: 02.004.001.001 | J53: Locação e cravação de estacas prancha EP400 para contenção | K53: m2 | L53: 492.8 | M53: 470.28409 | N53: 231756 | O53: Cotação, considerado 6 meses de locação | P53: Pendente
A54: 0 | B54: 2 | C54: 4 | D54: 1 | E54: 2 | G54: CONTENÇÃO | H54: SERVIÇO | I54: 02.004.001.002 | J54: Mobilização e Desmobilização de equipamento e máquinas considerando serviço de carga e descarga | K54: vb | L54: 1 | M54: 12000 | N54: 12000 | P54: Pendente
A55: 0 | B55: 2 | C55: 5 | D55: 0 | E55: 2 | H55: ETAPA | I55: 02.005 | J55: MÃO DE OBRA CONTENÇÕES | N55: 140000.02 | O55: 8.3583748
A56: 0 | B56: 2 | C56: 5 | D56: 1 | E56: 0 | H56: SUBETAPA | I56: 02.005.001 | J56: Mão de Obra | N56: 140000.02 | O56: 8.3583748
A57: 0 | B57: 2 | C57: 5 | D57: 1 | E57: 1 | G57: CONTENÇÃO | H57: SERVIÇO | I57: 02.005.001.001 | J57: Mão de obra para execução de contenção | K57: m2 | L57: 525 | M57: 266.6667 | N57: 140000.02 | O57: Prosposta Gessele | P57: Pendente
A58: 0 | B58: 3 | C58: 0 | D58: 1 | E58: 1 | H58: CÉLULA CONSTRUTIVA | I58: 03 | J58: INFRAESTRUTURA | N58: 4572490 | O58: 272.98986
A59: 0 | B59: 3 | C59: 1 | D59: 0 | E59: 1 | H59: ETAPA | I59: 03.001 | J59: ESTACA HÉLICE CONTÍNUA | N59: 3041540.5 | O59: 181.58809
A60: 0 | B60: 3 | C60: 1 | D60: 1 | E60: 0 | H60: SUBETAPA | I60: 03.001.001 | J60: Perfuração | N60: 950000 | O60: 56.717535
A61: 0 | B61: 3 | C61: 1 | D61: 1 | E61: 1 | G61: INFRAESTRUTURA | H61: SERVIÇO | I61: 03.001.001.001 | J61: Perfuração de estaca hélice contínua Ø 60cm | K61: m | L61: 6732 | M61: 137.48633 | N61: 925557.99 | O61: Repessado pela Gessele na reunião do dia 05/03/2026 - 950k efeg | P61: Pendente
A62: 0 | B62: 3 | C62: 1 | D62: 1 | E62: 2 | G62: INFRAESTRUTURA | H62: SERVIÇO | I62: 03.001.001.002 | J62: Mobilização e desmobilização de equipamentos - Para execução de estaca hélice monitorada | K62: vb | L62: 1 | M62: 24442.015 | N62: 24442.015 | O62: Repessado pela Gessele na reunião do dia 05/03/2026 - 950k efeg | P62: Pendente
A63: 0 | B63: 3 | C63: 1 | D63: 2 | E63: 0 | H63: SUBETAPA | I63: 03.001.002 | J63: Armadura | N63: 298834.78 | O63: 17.841234
A64: 0 | B64: 3 | C64: 1 | D64: 2 | E64: 1 | G64: INFRAESTRUTURA | H64: SERVIÇO | I64: 03.001.002.001 | J64: Armação aço CA-50 ø 6,3mm para estaca (corte e dobra em indústria) | K64: un | L64: 3495 | M64: 8.964145 | N64: 31329.687 | P64: Pendente
A65: 0 | B65: 3 | C65: 1 | D65: 2 | E65: 2 | G65: INFRAESTRUTURA | H65: SERVIÇO | I65: 03.001.002.002 | J65: Armação aço CA-50 ø 20,0mm para estaca (corte e dobra em indústria) | K65: un | L65: 31530 | M65: 8.484145 | N65: 267505.09 | P65: Pendente
A66: 0 | B66: 3 | C66: 1 | D66: 3 | E66: 0 | H66: SUBETAPA | I66: 03.001.003 | J66: Concreto | N66: 1792705.7 | O66: 107.02932
A67: 0 | B67: 3 | C67: 1 | D67: 3 | E67: 1 | G67: INFRAESTRUTURA | H67: SERVIÇO | I67: 03.001.003.001 | J67: Concreto Usinado bombeável para estacas 50MPa - incluindo serviço de bombeamento | K67: m3 | L67: 1903.4282 | M67: 941.83 | N67: 1792705.7 | P67: Pendente
A68: 0 | B68: 3 | C68: 1 | D68: 4 | E68: 0 | H68: SUBETAPA | I68: 03.001.004 | J68: Mão de Obra | N68: 0 | O68: 0
A69: 0 | B69: 3 | C69: 2 | D69: 0 | E69: 0 | H69: ETAPA | I69: 03.002 | J69: BLOCOS | N69: 1056067.4 | O69: 63.050045
A70: 0 | B70: 3 | C70: 2 | D70: 1 | E70: 0 | H70: SUBETAPA | I70: 03.002.001 | J70: Forma | N70: 15723.521 | O70: 0.93873616
A71: 0 | B71: 3 | C71: 2 | D71: 1 | E71: 1 | G71: INFRAESTRUTURA | H71: SERVIÇO | I71: 03.002.001.001 | J71: Forma para infraestrutura em Tábuas de Madeira Serrada 2x reaproveitamento | K71: m2 | L71: 262.25 | M71: 59.956229 | N71: 15723.521 | O71: Apenas blocos, 2x reaproveitamento | P71: Pendente
A72: 0 | B72: 3 | C72: 2 | D72: 2 | E72: 0 | H72: SUBETAPA | I72: 03.002.002 | J72: Armadura | N72: 592494.12 | O72: 35.37348
A73: 0 | B73: 3 | C73: 2 | D73: 2 | E73: 1 | G73: INFRAESTRUTURA | H73: SERVIÇO | I73: 03.002.002.001 | J73: Armação aço CA-50 ø 12,5mm para infraestrutura (corte e dobra em Indústria) | K73: kg | L73: 528.18182 | M73: 8.484145 | N73: 4481.1711 | P73: Pendente
A74: 0 | B74: 3 | C74: 2 | D74: 2 | E74: 2 | G74: INFRAESTRUTURA | H74: SERVIÇO | I74: 03.002.002.002 | J74: Armação aço CA-50 ø 16,0mm para infraestrutura (corte e dobra em Indústria) | K74: kg | L74: 7331.8182 | M74: 8.484145 | N74: 62204.209 | P74: Pendente
A75: 0 | B75: 3 | C75: 2 | D75: 2 | E75: 3 | G75: INFRAESTRUTURA | H75: SERVIÇO | I75: 03.002.002.003 | J75: Armação aço CA-50 ø 20,0mm para infraestrutura (corte e dobra em Indústria) | K75: kg | L75: 1318.1818 | M75: 8.484145 | N75: 11183.646 | P75: Pendente
A76: 0 | B76: 3 | C76: 2 | D76: 2 | E76: 4 | G76: INFRAESTRUTURA | H76: SERVIÇO | I76: 03.002.002.004 | J76: Armação aço CA-50 ø 25,0mm para infraestrutura (corte e dobra em Indústria) | K76: kg | L76: 60657.273 | M76: 8.484145 | N76: 514625.1 | P76: Pendente
A77: 0 | B77: 3 | C77: 2 | D77: 3 | E77: 0 | H77: SUBETAPA | I77: 03.002.003 | J77: Concreto | N77: 447849.8 | O77: 26.737828
A78: 0 | B78: 3 | C78: 2 | D78: 3 | E78: 1 | G78: INFRAESTRUTURA | H78: SERVIÇO | I78: 03.002.003.001 | J78: Concreto Usinado bombeável 50MPa para infraestrutura- incluindo serviço de bombeamento | K78: m3 | L78: 658.5 | M78: 680.106 | N78: 447849.8 | O78: 5% de perda, fck = 50Mpa | P78: Pendente
A79: 0 | B79: 3 | C79: 2 | D79: 4 | E79: 0 | H79: SUBETAPA | I79: 03.002.004 | J79: Mão de Obra | N79: 0 | O79: 0
A80: 0 | B80: 3 | C80: 3 | D80: 0 | E80: 0 | H80: ETAPA | I80: 03.003 | J80: VIGAS BALDRAMES | PILARES DE ARRANQUE | CISTERNAS E DUTOS | N80: 474882.06 | O80: 28.351727
A81: 0 | B81: 3 | C81: 3 | D81: 1 | E81: 0 | H81: SUBETAPA | I81: 03.003.001 | J81: Forma | N81: 9996.6219 | O81: 0.59682501
A82: 0 | B82: 3 | C82: 3 | D82: 1 | E82: 1 | G82: INFRAESTRUTURA | H82: SERVIÇO | I82: 03.003.001.001 | J82: Forma para infraestrutura em Tábuas de Madeira Serrada 2x reaproveitamento | K82: m2 | L82: 166.732 | M82: 59.956229 | N82: 9996.6219 | O82: Considerado blocos, vigas de fundação, duto, cisterna, lajes e pilares de arranque | P82: Pendente
A83: 0 | B83: 3 | C83: 3 | D83: 2 | E83: 0 | H83: SUBETAPA | I83: 03.003.002 | J83: Armadura | N83: 430167.93 | O83: 25.682173
A84: 0 | B84: 3 | C84: 3 | D84: 2 | E84: 1 | G84: INFRAESTRUTURA | H84: SERVIÇO | I84: 03.003.002.001 | J84: Armação aço CA-50 ø 5,0mm para infraestrutura (corte e dobra em Indústria) | K84: kg | L84: 52 | M84: 8.964145 | N84: 466.13554 | O84: Considerado vigas de fundação, duto, cisterna, lajes e pilares de arranque - 10% de perda | P84: Pendente
A85: 0 | B85: 3 | C85: 3 | D85: 2 | E85: 2 | G85: INFRAESTRUTURA | H85: SERVIÇO | I85: 03.003.002.002 | J85: Armação aço CA-50 ø 6,3mm para infraestrutura (corte e dobra em Indústria) | K85: kg | L85: 130.27273 | M85: 8.964145 | N85: 1167.7836 | O85: Considerado vigas de fundação, duto, cisterna, lajes e pilares de arranque - 10% de perda | P85: Pendente
A86: 0 | B86: 3 | C86: 3 | D86: 2 | E86: 3 | G86: INFRAESTRUTURA | H86: SERVIÇO | I86: 03.003.002.003 | J86: Armação aço CA-50 ø 8,0mm para infraestrutura (corte e dobra em Indústria) | K86: kg | L86: 982.63636 | M86: 8.964145 | N86: 8808.4948 | O86: Considerado vigas de fundação, duto, cisterna, lajes e pilares de arranque - 10% de perda | P86: Pendente
A87: 0 | B87: 3 | C87: 3 | D87: 2 | E87: 4 | G87: INFRAESTRUTURA | H87: SERVIÇO | I87: 03.003.002.004 | J87: Armação aço CA-50 ø 10,0mm para infraestrutura (corte e dobra em Indústria) | K87: kg | L87: 7011.6364 | M87: 8.964145 | N87: 62853.325 | O87: Considerado vigas de fundação, duto, cisterna, lajes e pilares de arranque - 10% de perda | P87: Pendente
A88: 0 | B88: 3 | C88: 3 | D88: 2 | E88: 5 | G88: INFRAESTRUTURA | H88: SERVIÇO | I88: 03.003.002.005 | J88: Armação aço CA-50 ø 12,5mm para infraestrutura (corte e dobra em Indústria) | K88: kg | L88: 6007.8182 | M88: 8.484145 | N88: 50971.201 | O88: Considerado vigas de fundação, duto, cisterna, lajes e pilares de arranque - 10% de perda | P88: Pendente
A89: 0 | B89: 3 | C89: 3 | D89: 2 | E89: 6 | G89: INFRAESTRUTURA | H89: SERVIÇO | I89: 03.003.002.006 | J89: Armação aço CA-50 ø 16,0mm para infraestrutura (corte e dobra em Indústria) | K89: kg | L89: 1269.7273 | M89: 8.484145 | N89: 10772.55 | O89: Considerado vigas de fundação, duto, cisterna, lajes e pilares de arranque - 10% de perda | P89: Pendente
A90: 0 | B90: 3 | C90: 3 | D90: 2 | E90: 7 | G90: INFRAESTRUTURA | H90: SERVIÇO | I90: 03.003.002.007 | J90: Armação aço CA-50 ø 20,0mm para infraestrutura (corte e dobra em Indústria) | K90: kg | L90: 902 | M90: 8.484145 | N90: 7652.6988 | O90: Considerado vigas de fundação, duto, cisterna, lajes e pilares de arranque - 10% de perda | P90: Pendente
A91: 0 | B91: 3 | C91: 3 | D91: 2 | E91: 8 | G91: INFRAESTRUTURA | H91: SERVIÇO | I91: 03.003.002.008 | J91: Armação aço CA-50 ø 25,0mm para infraestrutura (corte e dobra em Indústria) | K91: kg | L91: 4680 | M91: 8.484145 | N91: 39705.799 | O91: Considerado vigas de fundação, duto, cisterna, lajes e pilares de arranque - 10% de perda | P91: Pendente
A92: 0 | B92: 3 | C92: 3 | D92: 2 | E92: 9 | G92: INFRAESTRUTURA | H92: SERVIÇO | I92: 03.003.002.009 | J92: Armação aço CA-50 ø 32,00mm para infraestrutura (corte e dobra em Indústria) | K92: kg | L92: 27316 | M92: 9.0705059 | N92: 247769.94 | O92: Considerado vigas de fundação, duto, cisterna, lajes e pilares de arranque - 10% de perda | P92: Pendente
A93: 0 | B93: 3 | C93: 3 | D93: 3 | E93: 0 | H93: SUBETAPA | I93: 03.003.003 | J93: Concreto | N93: 34717.514 | O93: 2.0727282
A94: 0 | B94: 3 | C94: 3 | D94: 3 | E94: 1 | G94: INFRAESTRUTURA | H94: SERVIÇO | I94: 03.003.003.001 | J94: Concreto Usinado bombeável 50MPa para infraestrutura- incluindo serviço de bombeamento | K94: m3 | L94: 51.04721 | M94: 680.106 | N94: 34717.514 | O94: Cotações recentes do concreto. Considerado vigas de fundação, duto, cisterna, lajes e pilares de arranque - 5% de perda, fck = 50Mpa | P94: Pendente
A95: 0 | B95: 3 | C95: 3 | D95: 4 | E95: 0 | H95: SUBETAPA | I95: 03.003.004 | J95: Mão de Obra | N95: 0 | O95: 0
A96: 0 | B96: 4 | C96: 0 | D96: 4 | E96: 0 | H96: CÉLULA CONSTRUTIVA | I96: 04 | J96: SUPRAESTRUTURA | N96: 20793271 | O96: 1241.4138
A97: 0 | B97: 4 | C97: 1 | D97: 0 | E97: 0 | H97: ETAPA | I97: 04.001 | J97: PISO SOBRE O SOLO - GERAL | N97: 19428.045 | O97: 1.1599061
A98: 0 | B98: 4 | C98: 1 | D98: 1 | E98: 0 | H98: SUBETAPA | I98: 04.001.001 | J98: Piso sobre o solo - Geral | N98: 19428.045 | O98: 1.1599061
A99: 0 | B99: 4 | C99: 1 | D99: 1 | E99: 1 | G99: SUPRAESTRUTURA | H99: SERVIÇO | I99: 04.001.001.001 | J99: Lastro de Concreto Magro, Aplicado em piso sobre solo | K99: m3 | L99: 39.229 | M99: 495.247 | N99: 19428.045 | O99: O concreto e a armadura entraram nos itens referentes ao terreo, conforme lista de materiais do projetista | P99: Pendente
A100: 0 | B100: 4 | C100: 2 | D100: 0 | E100: 1 | H100: ETAPA | I100: 04.002 | J100: FORMA | N100: 1435615 | O100: 85.710046
A101: 0 | B101: 4 | C101: 2 | D101: 1 | E101: 0 | H101: SUBETAPA | I101: 04.002.001 | J101: Forma - Térreo | N101: 529090.67 | O101: 31.588125
A102: 0 | B102: 4 | C102: 2 | D102: 1 | E102: 1 | G102: SUPRAESTRUTURA | H102: SERVIÇO | I102: 04.002.001.001 | J102: Fabricação de Fôrma para Supraestrutura, em Chapa de Madeira Compensada Resinada, E=20mm | K102: m2 | L102: 4874.3226 | M102: 108.03523 | N102: 526598.54 | O102: 8x reaproveitamento - 3 jogos | P102: Pendente
A103: 0 | B103: 4 | C103: 2 | D103: 1 | E103: 2 | G103: SUPRAESTRUTURA | H103: SERVIÇO | I103: 04.002.001.002 | J103: Montagem e Desmontagem de Fôrma de Supraestrutura | K103: m2 | L103: 626.5792 | M103: 3.9773488 | N103: 2492.124 | P103: Pendente
...

Sheet Orçamento
A1: DADOS
A2: Titulo | B2: ORÇAMENTO
A3: Obra | B3: ELECTRA TOWERS
A4: Cliente | B4: THOZEN
A5: Cidade | B5: Porto Belo
A6: Endereço
A7: Descrição
A8: UF | B8: SC
A10: RESUMO
A11: Tipo | C11: Preço | E11: Observação
A12: Total | C12: 21718825 | E12: Geral da edificação
A13: Material | C13: 15467433
A14: Execução | C14: 6251392.4
A16: TABELA DE ORÇAMENTO
A17: Item | B17: Referência | C17: Tipo | D17: Código | E17: Descrição | F17: Unid. | G17: Quantidade | H17: Custo unitário | I17: Preço total | J17: % | K17: Observação
A19: 1. | E19: 03. PAREDES E PAINÉIS | I19: 1964071 | J19: 0.090431735
A20: 1.1. | E20: ARQ_Embasamento | I20: 228660.08 | J20: 0.010528198
A21: 1.1.1. | E21: 03.001. Alvenaria de vedação com blocos cerâmicos | I21: 133087.99 | J21: 0.006127771
A22: 1.1.1.1 | E22: BLOCO CERAMICO, 0,05 (Parede padrão) | F22: m² | G22: 35.77 | H22: 0 | I22: 0
A23: 1.1.1.2 | E23: BLOCO CERAMICO, 0,09 (Parede padrão) | F23: m² | G23: 171.98 | H23: 0 | I23: 0
A24: 1.1.1.3 | B24: Thozen - Electra | C24: COMPOSICAO | D24: 4825 | E24: Alvenaria de vedação de blocos cerâmicos furados na horizontal de 11,5x19x19cm (espessura 11,5cm) com argamassa industrializada de assentamento | F24: m2 | G24: 1262.88 | H24: 25.096 | I24: 31693.236 | J24: 0.0014592519
A25: 1.1.1.4 | B25: Thozen - Electra | C25: COMPOSICAO | D25: 4826 | E25: Alvenaria de vedação de blocos cerâmicos furados na horizontal de 14x19x19cm (espessura 14cm) com argamassa industrializada de assentamento | F25: m2 | G25: 1610.87 | H25: 40.7664 | I25: 65669.371 | J25: 0.0030236152
A26: 1.1.1.5 | B26: Thozen - Electra | C26: COMPOSICAO | D26: 90472 | E26: Alvenaria de vedação de blocos cerâmicos furados na horizontal de 19x19x19cm (espessura 19cm) com argamassa industrializada de assentamento | F26: m2 | G26: 631.36 | H26: 56.5848 | I26: 35725.379 | J26: 0.0016449039
A27: 1.1.2. | E27: 03.002. Alvenaria de vedação com blocos de concreto | I27: 0
A28: 1.1.2.1 | E28: BLOCO CONCRETO, 0,05 (Parede padrão) | F28: m² | G28: 1.49 | H28: 0 | I28: 0
A29: 1.1.2.2 | E29: BLOCO ANTI CHAMAS, 0,125 (Parede padrão) | F29: m² | G29: 252.44 | H29: 0 | I29: 0
A30: 1.1.2.3 | E30: BLOCO ANTI CHAMAS, 0,15 (Parede padrão) | F30: m² | G30: 774.4 | H30: 0 | I30: 0
A31: 1.1.3. | E31: 03.003. Serviços complementares para alvenaria de vedação | I31: 95572.097 | J31: 0.0044004266
A32: 1.1.3.1 | B32: Thozen - Electra | C32: COMPOSICAO | D32: 4831 | E32: Verga/contraverga de concreto, moldada in loco | F32: m | G32: 104.16 | H32: 43.712512 | I32: 4553.0952 | J32: 0.00020963819
A33: 1.1.3.2 | B33: Thozen - Electra | C33: COMPOSICAO | D33: 4828 | E33: Encunhamento de alvenaria de vedação com argamassa expansiva | F33: m | G33: 18470.23 | H33: 3.633798 | I33: 67117.085 | J33: 0.0030902724
A34: 1.1.3.3 | B34: Thozen - Electra | C34: COMPOSICAO | D34: 4829 | E34: Tela soldada para ligação alvenaria/estrutura | F34: m² | G34: 2370.59 | H34: 1.85 | I34: 4385.5915 | J34: 0.00020192582
A35: 1.1.3.4 | B35: Thozen - Electra | C35: COMPOSICAO | D35: 4831 | E35: Verga/contraverga de concreto, moldada in loco | F35: m | G35: 446.47 | H35: 43.712512 | I35: 19516.325 | J35: 0.00089859028
A36: 1.1.4. | E36: 03.005. Mão de obra | I36: 0
A37: 1.1.4.1 | E37: Mão de obra alvenaria cerâmica | F37: m² | G37: 4045.19 | H37: 0 | I37: 0
A38: 1.1.4.2 | E38: Mão de obra blocos sílico calcário (Parede padrão) | F38: m² | G38: 1028.33 | H38: 0 | I38: 0
A39: 1.1.5. | E39: Alvenaria de vedação com tijolo refratário | I39: 0
A40: 1.1.5.1 | E40: TIJOLO REFRATARIO, 0,016 (Parede padrão) | F40: m² | G40: 14.56 | H40: 0 | I40: 0
A41: 1.2. | E41: ARQ_Impermeab | I41: 45754.495 | J41: 0.0021066745
A42: 1.2.1. | E42: 03.003. Serviços complementares para alvenaria de vedação | I42: 45754.495 | J42: 0.0021066745
A43: 1.2.1.1 | B43: Thozen - Electra | C43: COMPOSICAO | D43: 4828 | E43: Encunhamento de alvenaria de vedação com argamassa expansiva | F43: m | G43: 12591.37 | H43: 3.633798 | I43: 45754.495 | J43: 0.0021066745
A44: 1.3. | E44: ARQ_Torre_A | I44: 823378.32 | J44: 0.037910813
A45: 1.3.1. | E45: 03.001. Alvenaria de vedação com blocos cerâmicos | I45: 416102.64 | J45: 0.019158616
A46: 1.3.1.1 | E46: BLOCO CERAMICO, 0,05 (Parede padrão) | F46: m² | G46: 1074.45 | H46: 0 | I46: 0
A47: 1.3.1.2 | E47: BLOCO CERAMICO, 0,09 (Parede padrão) | F47: m² | G47: 1364.5 | H47: 0 | I47: 0
A48: 1.3.1.3 | B48: Thozen - Electra | C48: COMPOSICAO | D48: 4825 | E48: Alvenaria de vedação de blocos cerâmicos furados na horizontal de 11,5x19x19cm (espessura 11,5cm) com argamassa industrializada de assentamento | F48: m2 | G48: 7270.36 | H48: 25.096 | I48: 182456.95 | J48: 0.0084008667
A49: 1.3.1.4 | B49: Thozen - Electra | C49: COMPOSICAO | D49: 4826 | E49: Alvenaria de vedação de blocos cerâmicos furados na horizontal de 14x19x19cm (espessura 14cm) com argamassa industrializada de assentamento | F49: m2 | G49: 4090.42 | H49: 40.7664 | I49: 166751.7 | J49: 0.0076777495
A50: 1.3.1.5 | B50: Thozen - Electra | C50: COMPOSICAO | D50: 90472 | E50: Alvenaria de vedação de blocos cerâmicos furados na horizontal de 19x19x19cm (espessura 19cm) com argamassa industrializada de assentamento | F50: m2 | G50: 1182.19 | H50: 56.5848 | I50: 66893.985 | J50: 0.0030800002
A51: 1.3.2. | E51: 03.002. Alvenaria de vedação com blocos de concreto | I51: 0
A52: 1.3.2.1 | E52: BLOCO CONCRETO, 0,05 (Parede padrão) | F52: m² | G52: 363.8 | H52: 0 | I52: 0
A53: 1.3.2.2 | E53: BLOCO ANTI CHAMAS, 0,125 (Parede padrão) | F53: m² | G53: 128.55 | H53: 0 | I53: 0
A54: 1.3.2.3 | E54: BLOCO ANTI CHAMAS, 0,15 (Parede padrão) | F54: m² | G54: 862.58 | H54: 0 | I54: 0
A55: 1.3.3. | E55: 03.003. Serviços complementares para alvenaria de vedação | I55: 407275.68 | J55: 0.018752197
A56: 1.3.3.1 | B56: Thozen - Electra | C56: COMPOSICAO | D56: 4831 | E56: Verga/contraverga de concreto, moldada in loco | F56: m | G56: 1151.26 | H56: 43.712512 | I56: 50324.467 | J56: 0.0023170897
A57: 1.3.3.2 | B57: Thozen - Electra | C57: COMPOSICAO | D57: 4828 | E57: Encunhamento de alvenaria de vedação com argamassa expansiva | F57: m | G57: 62783.49 | H57: 3.633798 | I57: 228142.52 | J57: 0.010504367
A58: 1.3.3.3 | B58: Thozen - Electra | C58: COMPOSICAO | D58: 4829 | E58: Tela soldada para ligação alvenaria/estrutura | F58: m² | G58: 8168.42 | H58: 1.85 | I58: 15111.577 | J58: 0.00069578243
A59: 1.3.3.4 | B59: Thozen - Electra | C59: COMPOSICAO | D59: 4831 | E59: Verga/contraverga de concreto, moldada in loco | F59: m | G59: 2601.02 | H59: 43.712512 | I59: 113697.12 | J59: 0.0052349571
A60: 1.3.4. | E60: 03.005. Mão de obra | I60: 0
A61: 1.3.4.1 | E61: Mão de obra alvenaria cerâmica | F61: m² | G61: 16873.23 | H61: 0 | I61: 0
A62: 1.3.4.2 | E62: Mão de obra blocos sílico calcário (Parede padrão) | F62: m² | G62: 1354.93 | H62: 0 | I62: 0
A63: 1.3.5. | E63: Alvenaria de vedação com tijolo refratário | I63: 0
A64: 1.3.5.1 | E64: TIJOLO REFRATARIO, 0,016 (Parede padrão) | F64: m² | G64: 287.37 | H64: 0 | I64: 0
A65: 1.4. | E65: ARQ_Torre_B | I65: 866278.14 | J65: 0.03988605
A66: 1.4.1. | E66: 03.001. Alvenaria de vedação com blocos cerâmicos | I66: 489178.45 | J66: 0.022523246
A67: 1.4.1.1 | E67: BLOCO CERAMICO, 0,05 (Parede padrão) | F67: m² | G67: 398.15 | H67: 0 | I67: 0
A68: 1.4.1.2 | E68: BLOCO CERAMICO, 0,09 (Parede padrão) | F68: m² | G68: 3063.66 | H68: 0 | I68: 0
A69: 1.4.1.3 | B69: Thozen - Electra | C69: COMPOSICAO | D69: 4825 | E69: Alvenaria de vedação de blocos cerâmicos furados na horizontal de 11,5x19x19cm (espessura 11,5cm) com argamassa industrializada de assentamento | F69: m2 | G69: 8394.28 | H69: 25.096 | I69: 210662.85 | J69: 0.009699551
A70: 1.4.1.4 | B70: Thozen - Electra | C70: COMPOSICAO | D70: 4826 | E70: Alvenaria de vedação de blocos cerâmicos furados na horizontal de 14x19x19cm (espessura 14cm) com argamassa industrializada de assentamento | F70: m2 | G70: 5416.8 | H70: 40.7664 | I70: 220823.44 | J70: 0.010167375
A71: 1.4.1.5 | B71: Thozen - Electra | C71: COMPOSICAO | D71: 90472 | E71: Alvenaria de vedação de blocos cerâmicos furados na horizontal de 19x19x19cm (espessura 19cm) com argamassa industrializada de assentamento | F71: m2 | G71: 1019.57 | H71: 56.5848 | I71: 57692.165 | J71: 0.0026563207
A72: 1.4.2. | E72: 03.002. Alvenaria de vedação com blocos de concreto | I72: 0
A73: 1.4.2.1 | E73: BLOCO ANTI CHAMAS, 0,125 (Parede padrão) | F73: m² | G73: 245.34 | H73: 0 | I73: 0
A74: 1.4.2.2 | E74: BLOCO ANTI CHAMAS, 0,15 (Parede padrão) | F74: m² | G74: 662.3 | H74: 0 | I74: 0
A75: 1.4.3. | E75: 03.003. Serviços complementares para alvenaria de vedação | I75: 377099.69 | J75: 0.017362803
A76: 1.4.3.1 | B76: Thozen - Electra | C76: COMPOSICAO | D76: 4831 | E76: Verga/contraverga de concreto, moldada in loco | F76: m | G76: 1126.07 | H76: 43.712512 | I76: 49223.348 | J76: 0.0022663909
A77: 1.4.3.2 | B77: Thozen - Electra | C77: COMPOSICAO | D77: 4828 | E77: Encunhamento de alvenaria de vedação com argamassa expansiva | F77: m | G77: 54949.59 | H77: 3.633798 | I77: 199675.71 | J77: 0.00919367
A78: 1.4.3.3 | B78: Thozen - Electra | C78: COMPOSICAO | D78: 4829 | E78: Tela soldada para ligação alvenaria/estrutura | F78: m² | G78: 9600.05 | H78: 1.85 | I78: 17760.092 | J78: 0.00081772805
A79: 1.4.3.4 | B79: Thozen - Electra | C79: COMPOSICAO | D79: 4831 | E79: Verga/contraverga de concreto, moldada in loco | F79: m | G79: 2526.52 | H79: 43.712512 | I79: 110440.54 | J79: 0.0050850143
A80: 1.4.4. | E80: 03.005. Mão de obra | I80: 0
A81: 1.4.4.1 | E81: Mão de obra alvenaria cerâmica | F81: m² | G81: 20189.64 | H81: 0 | I81: 0
A82: 1.4.4.2 | E82: Mão de obra blocos sílico calcário (Parede padrão) | F82: m² | G82: 907.65 | H82: 0 | I82: 0
A83: 1.4.5. | E83: Alvenaria de vedação com tijolo refratário | I83: 0
A84: 1.4.5.1 | E84: TIJOLO REFRATARIO, 0,016 (Parede padrão) | F84: m² | G84: 269.16 | H84: 0 | I84: 0
A85: 2. | E85: 04. IMPERMEABILIZAÇÃO E TRATAMENTOS | I85: 331117.51 | J85: 0.015245646
A86: 2.1. | E86: ARQ_Embasamento | I86: 0
A87: 2.1.1. | E87: 04.007. Impermeabilização de esquadrias | I87: 0
A88: 2.1.1.1 | E88: Peitoril | F88: m² | G88: 84.83 | H88: 0 | I88: 0
A89: 2.2. | E89: ARQ_Impermeab | I89: 331117.51 | J89: 0.015245646
A90: 2.2.1. | E90: 04.004. Impermeabilização de lajes e terraços | I90: 0
A91: 2.2.1.1 | E91: VERIFICAR MATERIAL TERRAÇO (Laje) | F91: m² | G91: 755.42 | H91: 0 | I91: 0
A92: 2.2.1.2 | E92: VERIFICAR MATERIAL - TERRAÇO (Parede padrão) | F92: m² | G92: 55.75 | H92: 0 | I92: 0
A93: 2.2.2. | E93: 04.006. Impermeabilização de banheiro, cozinha e sacada | I93: 331117.51 | J93: 0.015245646
A94: 2.2.2.1 | B94: Thozen - Electra | C94: COMPOSICAO | D94: 4842 | E94: Impermeabilização com argamassa polimérica, 3 demãos | F94: m2 | G94: 9140.58 | H94: 36.225 | I94: 331117.51 | J94: 0.015245646
A95: 2.2.3. | E95: 04.007. Impermeabilização de esquadrias | I95: 0
A96: 2.2.3.1 | E96: Polímero acrílico - janela | F96: m² | G96: 582.79 | H96: 0 | I96: 0
A97: 2.3. | E97: ARQ_Torre_A | I97: 0
A98: 2.3.1. | E98: 04.007. Impermeabilização de esquadrias | I98: 0
A99: 2.3.1.1 | E99: Peitoril | F99: m² | G99: 252.2 | H99: 0 | I99: 0
A100: 2.4. | E100: ARQ_Torre_B | I100: 0
A101: 2.4.1. | E101: 04.007. Impermeabilização de esquadrias | I101: 0
A102: 2.4.1.1 | E102: Peitoril | F102: m² | G102: 234.85 | H102: 0 | I102: 0
A103: 3. | E103: 12. REVESTIMENTOS ARGAMASSADOS INTERNOS DE PAREDE | I103: 4588051.9 | J103: 0.2112477
...

Sheet Composições
A1: DADOS
A2: Titulo | B2: ORÇAMENTO
A3: Obra | B3: ELECTRA TOWERS
A4: Cliente | B4: THOZEN
A5: Cidade | B5: Porto Belo
A6: Endereço
A7: Descrição
A8: UF | B8: SC
A11: TABELA DE COMPOSIÇÕES UTILIZADAS
A12: Código | B12: Referência | C12: Tipo | D12: Tipo | E12: Descrição | F12: Unid. | G12: Multiplicador | H12: Preço | J12: Ref. Tabela | K12: Ref. Código | L12: Justificativa | M12: Grupo de Serviço | N12: Serviço
H13: Unitário | I13: Total
A14: 4825 | B14: Thozen - Electra | D14: Original | E14: Alvenaria de vedação de blocos cerâmicos furados na horizontal de 11,5x19x19cm (espessura 11,5cm) com argamassa industrializada de assentamento | F14: m2 | I14: 25.096 | N14: BLOCOS | O14: =A14&B14&C14 -> 4825Thozen - Electra
A15: 194 | B15: Thozen - Electra | C15: INSUMO | D15: Original | E15: ARGAMASSA ESTABILIZADA PARA ASSENTAMENTO | F15: m3 | G15: 0.0125 | H15: 480 | I15: 6
A16: 228 | B16: Thozen - Electra | C16: INSUMO | D16: Original | E16: BLOCO CERÂMICO 11,5X19X19CM | F16: un | G16: 17.36 | H16: 1.1 | I16: 19.096
A17: 4826 | B17: Thozen - Electra | D17: Original | E17: Alvenaria de vedação de blocos cerâmicos furados na horizontal de 14x19x19cm (espessura 14cm) com argamassa industrializada de assentamento | F17: m2 | I17: 40.7664 | N17: BLOCOS | O17: =A17&B17&C17 -> 4826Thozen - Electra
A18: 194 | B18: Thozen - Electra | C18: INSUMO | D18: Original | E18: ARGAMASSA ESTABILIZADA PARA ASSENTAMENTO | F18: m3 | G18: 0.022 | H18: 480 | I18: 10.56
A19: 232 | B19: Thozen - Electra | C19: INSUMO | D19: Original | E19: BLOCO CERÂMICO 14X19X19CM | F19: un | G19: 17.36 | H19: 1.74 | I19: 30.2064
A20: 90472 | B20: Thozen - Electra | D20: Original | E20: Alvenaria de vedação de blocos cerâmicos furados na horizontal de 19x19x19cm (espessura 19cm) com argamassa industrializada de assentamento | F20: m2 | I20: 56.5848 | N20: BLOCOS | O20: =A20&B20&C20 -> 90472Thozen - Electra
A21: 194 | B21: Thozen - Electra | C21: INSUMO | D21: Original | E21: ARGAMASSA ESTABILIZADA PARA ASSENTAMENTO | F21: m3 | G21: 0.03 | H21: 480 | I21: 14.4
A22: 48433 | B22: Thozen - Electra | C22: INSUMO | D22: Original | E22: BLOCO CERÂMICO 19X19X19CM | F22: un | G22: 17.36 | H22: 2.43 | I22: 42.1848
A23: 4831 | B23: Thozen - Electra | D23: Original | E23: Verga/contraverga de concreto, moldada in loco | F23: m | I23: 43.712512 | O23: =A23&B23&C23 -> 4831Thozen - Electra
A24: 759 | B24: Thozen - Electra | C24: INSUMO | D24: Original | E24: CONCRETO USINADO FCK 20 MPA, SLUMP 14+/-2 | F24: m3 | G24: 0.0264 | H24: 450 | I24: 11.88
A25: 4800 | B25: Thozen - Electra | C25: INSUMO | D25: Original | E25: DESMOLDANTE DE FORMAS PARA CONCRETO | F25: l | G25: 0.007 | H25: 6.45 | I25: 0.04515
A26: 1412 | B26: Thozen - Electra | C26: INSUMO | D26: Original | E26: ESPAÇADOR PLÁSTICO | F26: un | G26: 6 | H26: 0.15 | I26: 0.9
A27: 2324 | B27: Thozen - Electra | C27: INSUMO | D27: Original | E27: PONTALETE 7,5X7,5 CM PINUS | F27: m3 | G27: 0.0012 | H27: 1310 | I27: 1.572
A28: 2362 | B28: Thozen - Electra | C28: INSUMO | D28: Original | E28: PREGO POLIDO COM CABEÇA 17X21 | F28: kg | G28: 0.0512 | H28: 10.91 | I28: 0.558592
A29: 2546 | B29: Thozen - Electra | C29: INSUMO | D29: Original | E29: SARRAFO 2,5X7,5 CM PINUS | F29: m3 | G29: 0.003171 | H29: 1300 | I29: 4.1223
A30: 2611 | B30: Thozen - Electra | C30: INSUMO | D30: Original | E30: TÁBUA 1"X12" 2,5X30CM PINUS | F30: m3 | G30: 0.011676 | H30: 1800 | I30: 21.0168
A31: 32 | B31: Thozen - Electra | C31: INSUMO | D31: Original | E31: AÇO CA-50 DIÂMETRO 6,30 MM | F31: kg | G31: 0.5243 | H31: 6.9 | I31: 3.61767
A32: 4828 | B32: Thozen - Electra | D32: Original | E32: Encunhamento de alvenaria de vedação com argamassa expansiva | F32: m | I32: 3.633798 | N32: ENCUNHAMENTO | O32: =A32&B32&C32 -> 4828Thozen - Electra
A33: 48435 | B33: Thozen - Electra | C33: INSUMO | D33: Original | E33: ARGAMASSA EXPANSIVA PARA ENCUNHAMENTO | F33: Kg | G33: 0.2154 | H33: 16.87 | I33: 3.633798
A34: 4829 | B34: Thozen - Electra | D34: Original | E34: Tela soldada para ligação alvenaria/estrutura | F34: m² | I34: 1.85 | O34: =A34&B34&C34 -> 4829Thozen - Electra
A35: 718 | B35: Thozen - Electra | C35: INSUMO | D35: Original | E35: CARTUCHO 22 - CARGA LEVE PARA FINCA PINO E POLVORA | F35: un | G35: 1 | H35: 0.3 | I35: 0.3
A36: 2260 | B36: Thozen - Electra | C36: INSUMO | D36: Original | E36: PINO LISO EM AÇO GALVANIZADO 1/2 X 22MM COM ARRUELA | F36: un | G36: 1 | H36: 0.3 | I36: 0.3
A37: 2901 | B37: Thozen - Electra | C37: INSUMO | D37: Original | E37: TELA DE ACO SOLDADA, FIO 1,24MM, MALHA 15X15MM | F37: m2 | G37: 0.5 | H37: 2.5 | I37: 1.25
A38: 4842 | B38: Thozen - Electra | D38: Original | E38: Impermeabilização com argamassa polimérica, 3 demãos | F38: m2 | I38: 36.225 | O38: =A38&B38&C38 -> 4842Thozen - Electra
A39: 202 | B39: Thozen - Electra | C39: INSUMO | D39: Original | E39: ARGAMASSA POLIMÉRICA IMPERMEABILIZANTE | F39: kg | G39: 3.15 | H39: 11.5 | I39: 36.225
A40: 90541 | B40: Thozen - Electra | D40: Original | E40: Chapisco adesivo aplicado em concreto, com desempenadeira dentada | F40: m2 | I40: 6.459 | N40: CHAPISCO | O40: =A40&B40&C40 -> 90541Thozen - Electra
A41: 197 | B41: Thozen - Electra | C41: INSUMO | D41: Original | E41: ARGAMASSA ESTABILIZADA PARA REBOCO | F41: m3 | G41: 0.0033 | H41: 480 | I41: 1.584
A42: 48481 | B42: Thozen - Electra | C42: INSUMO | D42: Original | E42: ADITIVO ADESIVO LÍQUIDO PARA ARGAMASSA | F42: L | G42: 0.625 | H42: 7.8 | I42: 4.875
A43: 90507 | B43: Thozen - Electra | D43: Original | E43: Chapisco rolado aplicado em alvenaria, com desempenadeira dentada | F43: m2 | I43: 5.502 | N43: CHAPISCO | O43: =A43&B43&C43 -> 90507Thozen - Electra
A44: 48373 | B44: Thozen - Electra | C44: INSUMO | D44: Original | E44: CHAPISCO COLANTE 20KG | F44: Kg | G44: 4.2 | H44: 1.31 | I44: 5.502
A45: 4861 | B45: Thozen - Electra | D45: Original | E45: Massa única para paredes internas em argamassa estabilizada, aplicação manual, espessura 2cm, com execução de taliscas | F45: m2 | I45: 18.048 | N45: REBOCO | O45: =A45&B45&C45 -> 4861Thozen - Electra
A46: 197 | B46: Thozen - Electra | C46: INSUMO | D46: Original | E46: ARGAMASSA ESTABILIZADA PARA REBOCO | F46: m3 | G46: 0.0376 | H46: 480 | I46: 18.048
A47: 4865 | B47: Thozen - Electra | D47: Original | E47: Mão de obra para reboco interno, incluso chapisco | F47: m2 | I47: 35 | O47: =A47&B47&C47 -> 4865Thozen - Electra
A48: 2154 | B48: Thozen - Electra | C48: INSUMO | D48: Original | E48: MÃO DE OBRA PARA EXECUÇÃO DE CHAPISCO E REBOCO INTERNO EM PAREDES | F48: m2 | G48: 1 | H48: 35 | I48: 35
A49: 4899 | B49: Thozen - Electra | D49: Original | E49: Revestimento interno de parede em porcelanato, placa 30x90cm, aplicação em banheiros e cozinhas | F49: m2 | I49: 97.430075 | O49: =A49&B49&C49 -> 4899Thozen - Electra
A50: 193 | B50: Thozen - Electra | C50: INSUMO | D50: Original | E50: ARGAMASSA COLANTE AC III | F50: kg | G50: 9 | H50: 2.345 | I50: 21.105
A51: 4881 | B51: Thozen - Electra | C51: INSUMO | D51: Original | E51: ESPAÇADOR PARA REVESTIMENTO CERÂMICO TIPO CRUZETA 5 MM | F51: un | G51: 4 | H51: 0.2 | I51: 0.8
A52: 4880 | B52: Thozen - Electra | C52: INSUMO | D52: Original | E52: REJUNTE FLEXÍVEL | F52: m2 | G52: 0.25 | H52: 2.0643 | I52: 0.516075
A53: 48500 | B53: Thozen - Electra | C53: INSUMO | D53: Original | E53: REVESTIMENTO PORCELANATO INTERNO 30X90CM | F53: m2 | G53: 1.1 | H53: 68.19 | I53: 75.009
A54: 90511 | B54: Thozen - Electra | D54: Original | E54: Acabamentos de elevador em granito, acabamento polido, esp. 2cm | F54: m² | I54: 623.4139 | N54: PEITORIL | O54: =A54&B54&C54 -> 90511Thozen - Electra
A55: 193 | B55: Thozen - Electra | C55: INSUMO | D55: Original | E55: ARGAMASSA COLANTE AC III | F55: kg | G55: 8.62 | H55: 2.345 | I55: 20.2139
A56: 1526 | B56: Thozen - Electra | C56: INSUMO | D56: Original | E56: GRANITO POLIDO | F56: m2 | G56: 1.16 | H56: 520 | I56: 603.2
A57: 4902 | B57: Thozen - Electra | D57: Original | E57: Peitoril em granito, acabamento polido, esp. 2cm | F57: m² | I57: 623.4139 | N57: PEITORIL | O57: =A57&B57&C57 -> 4902Thozen - Electra
A58: 193 | B58: Thozen - Electra | C58: INSUMO | D58: Original | E58: ARGAMASSA COLANTE AC III | F58: kg | G58: 8.62 | H58: 2.345 | I58: 20.2139
A59: 1526 | B59: Thozen - Electra | C59: INSUMO | D59: Original | E59: GRANITO POLIDO | F59: m2 | G59: 1.16 | H59: 520 | I59: 603.2
A60: 4872 | B60: Thozen - Electra | D60: Original | E60: Forro de gesso acartonado, aplicação em áreas secas - material e mão de obra | F60: m2 | I60: 126.4 | N60: FORRO EM GESSO | O60: =A60&B60&C60 -> 4872Thozen - Electra
A61: 4874 | B61: Thozen - Electra | C61: INSUMO | D61: Original | E61: FORRO DE GESSO ACARTONADO, APLICAÇÃO EM ÁREAS SECAS - MATERIAL E MÃO DE OBRA | F61: m2 | G61: 1 | H61: 100 | I61: 100
A62: 1514 | B62: Thozen - Electra | C62: INSUMO | D62: Original | E62: GESSO NEGATIVO | F62: m | G62: 1.2 | H62: 22 | I62: 26.4
A63: 4876 | B63: Thozen - Electra | D63: Original | E63: Gesso negativo - material e mão de obra | F63: m | I63: 22 | O63: =A63&B63&C63 -> 4876Thozen - Electra
A64: 1514 | B64: Thozen - Electra | C64: INSUMO | D64: Original | E64: GESSO NEGATIVO | F64: m | G64: 1 | H64: 22 | I64: 22
A65: 1481 | B65: Thozen - Electra | D65: Original | E65: Textura acrilica aplicacao em teto, 1 demão, incluindo aplicação de uma demão de fundo selador látex pva | F65: m2 | I65: 9.171036 | N65: PINTURA TETO | O65: =A65&B65&C65 -> 1481Thozen - Electra
A66: 2940 | B66: Thozen - Electra | C66: INSUMO | D66: Original | E66: TEXTURA ACRÍLICA | F66: kg | G66: 1.1074 | H66: 7.23 | I66: 8.006502
A67: 2553 | B67: Thozen - Electra | C67: INSUMO | D67: Original | E67: SELADOR LÁTEX PVA | F67: l | G67: 0.1666 | H67: 6.99 | I67: 1.164534
A68: 4873 | B68: Thozen - Electra | D68: Original | E68: Forro de gesso acartonado, aplicação em áreas molhadas - material e mão de obra | F68: m2 | I68: 136.4 | N68: FORRO EM GESSO | O68: =A68&B68&C68 -> 4873Thozen - Electra
A69: 4875 | B69: Thozen - Electra | C69: INSUMO | D69: Original | E69: FORRO DE GESSO ACARTONADO, APLICAÇÃO EM ÁREAS ÚMIDAS - MATERIAL E MÃO DE OBRA | F69: m2 | G69: 1 | H69: 110 | I69: 110
A70: 1514 | B70: Thozen - Electra | C70: INSUMO | D70: Original | E70: GESSO NEGATIVO | F70: m | G70: 1.2 | H70: 22 | I70: 26.4
A71: 60 | B71: Thozen - Electra | D71: Original | E71: Contrapiso comum em argamassa estabilizada, nao aderido, espessura 5cm | F71: m2 | I71: 26.4 | N71: CONTRAPISO | O71: =A71&B71&C71 -> 60Thozen - Electra
A72: 458 | B72: Thozen - Electra | C72: INSUMO | D72: Original | E72: ARGAMASSA ESTABILIZADA P/ CONTRAPISO | F72: M3 | G72: 0.055 | H72: 480 | I72: 26.4
A73: 4863 | B73: Thozen - Electra | D73: Original | E73: Mão de obra de execução contrapiso comum | F73: m2 | I73: 32 | O73: =A73&B73&C73 -> 4863Thozen - Electra
A74: 2156 | B74: Thozen - Electra | C74: INSUMO | D74: Original | E74: MÃO DE OBRA PARA EXECUÇÃO DE CONTRAPISO | F74: m2 | G74: 1 | H74: 32 | I74: 32
A75: 4883 | B75: Thozen - Electra | D75: Original | E75: Revestimento interno de piso porcelanato, placa 80x80, aplicação em áreas internas | F75: m2 | I75: 93.8717 | O75: =A75&B75&C75 -> 4883Thozen - Electra
A76: 193 | B76: Thozen - Electra | C76: INSUMO | D76: Original | E76: ARGAMASSA COLANTE AC III | F76: kg | G76: 9 | H76: 2.345 | I76: 21.105
A77: 4881 | B77: Thozen - Electra | C77: INSUMO | D77: Original | E77: ESPAÇADOR PARA REVESTIMENTO CERÂMICO TIPO CRUZETA 5 MM | F77: un | G77: 4 | H77: 0.2 | I77: 0.8
A78: 4884 | B78: Thozen - Electra | C78: INSUMO | D78: Original | E78: PISO PORCELANATO 80X80CM, ACABAMENTO NATURAL, PADRÃO MÉDIO | F78: m2 | G78: 1.1 | H78: 65 | I78: 71.5
A79: 2521 | B79: Thozen - Electra | C79: INSUMO | D79: Original | E79: REJUNTE ACRÍLICO | F79: kg | G79: 0.13 | H79: 3.59 | I79: 0.4667
A80: 90521 | B80: Thozen - Electra | D80: Original | E80: Rodapé em poliestireno, altura 15cm | F80: m | I80: 82.225797 | O80: =A80&B80&C80 -> 90521Thozen - Electra
A81: 417 | B81: Thozen - Electra | C81: INSUMO | D81: Original | E81: BUCHA T PARA RODAPÉ | F81: un | G81: 2.5 | H81: 1.99 | I81: 4.975
A82: 738 | B82: Thozen - Electra | C82: INSUMO | D82: Original | E82: COLA PARA RODAPÉ DE POLIESTIRENO | F82: kg | G82: 0.0694 | H82: 5.0403 | I82: 0.34979682
A83: 48465 | B83: Thozen - Electra | C83: INSUMO | D83: Original | E83: RODAPÉ POLIESTIRENO H=15CM | F83: m | G83: 1.1 | H83: 69.91 | I83: 76.901
A84: 4882 | B84: Thozen - Electra | D84: Original | E84: Rodapé em poliestireno, altura 10cm | F84: m | I84: 17.655797 | O84: =A84&B84&C84 -> 4882Thozen - Electra
A85: 417 | B85: Thozen - Electra | C85: INSUMO | D85: Original | E85: BUCHA T PARA RODAPÉ | F85: un | G85: 2.5 | H85: 1.99 | I85: 4.975
A86: 738 | B86: Thozen - Electra | C86: INSUMO | D86: Original | E86: COLA PARA RODAPÉ DE POLIESTIRENO | F86: kg | G86: 0.0694 | H86: 5.0403 | I86: 0.34979682
A87: 2538 | B87: Thozen - Electra | C87: INSUMO | D87: Original | E87: RODAPÉ POLIESTIRENO H=10CM | F87: m | G87: 1.1 | H87: 11.21 | I87: 12.331
A88: 4891 | B88: Thozen - Electra | D88: Original | E88: Rodapé em porcelanato, altura 10cm, com placa 80x80 | F88: m | I88: 9.7339012 | O88: =A88&B88&C88 -> 4891Thozen - Electra
A89: 193 | B89: Thozen - Electra | C89: INSUMO | D89: Original | E89: ARGAMASSA COLANTE AC III | F89: kg | G89: 0.9 | H89: 2.345 | I89: 2.1105
A90: 1412 | B90: Thozen - Electra | C90: INSUMO | D90: Original | E90: ESPAÇADOR PLÁSTICO | F90: un | G90: 2 | H90: 0.15 | I90: 0.3
A91: 4884 | B91: Thozen - Electra | C91: INSUMO | D91: Original | E91: PISO PORCELANATO 80X80CM, ACABAMENTO NATURAL, PADRÃO MÉDIO | F91: m2 | G91: 0.11 | H91: 65 | I91: 7.15
A92: 4880 | B92: Thozen - Electra | C92: INSUMO | D92: Original | E92: REJUNTE FLEXÍVEL | F92: m2 | G92: 0.084 | H92: 2.0643 | I92: 0.1734012
A93: 4898 | B93: Thozen - Electra | D93: Original | E93: Soleira de granito, acabamento polido, espessura 2cm | F93: m2 | I93: 593.64172 | O93: =A93&B93&C93 -> 4898Thozen - Electra
A94: 193 | B94: Thozen - Electra | C94: INSUMO | D94: Original | E94: ARGAMASSA COLANTE AC III | F94: kg | G94: 9 | H94: 2.345 | I94: 21.105
A95: 1526 | B95: Thozen - Electra | C95: INSUMO | D95: Original | E95: GRANITO POLIDO | F95: m2 | G95: 1.1 | H95: 520 | I95: 572
A96: 4880 | B96: Thozen - Electra | C96: INSUMO | D96: Original | E96: REJUNTE FLEXÍVEL | F96: m2 | G96: 0.26 | H96: 2.0643 | I96: 0.536718
A97: 90559 | B97: Thozen - Electra | D97: Original | E97: Massa latex acrílica em paredes internas 2 demaos | F97: m2 | I97: 11.9703 | N97: MASSA | O97: =A97&B97&C97 -> 90559Thozen - Electra
A98: 1400 | B98: Thozen - Electra | C98: INSUMO | D98: Original | E98: LIXA EM FOLHA PARA PAREDE OU MADEIRA N° 120 | F98: UN | G98: 0.1 | H98: 18.48 | I98: 1.848
A99: 48483 | B99: Thozen - Electra | C99: INSUMO | D99: Original | E99: MASSA ACRÍLICA | F99: kg | G99: 0.8802 | H99: 11.5 | I99: 10.1223
A100: 4926 | B100: Thozen - Electra | D100: Original | E100: Pintura com tinta acrílica em paredes internas, aplicação manual, 3 demãos | F100: m2 | I100: 20.035312 | N100: PINTURA ACRÍLICA | O100: =A100&B100&C100 -> 4926Thozen - Electra
A101: 2944 | B101: Thozen - Electra | C101: INSUMO | D101: Original | E101: TINTA LÁTEX ACRÍLICA | F101: l | G101: 0.34275 | H101: 36.67 | I101: 12.568643
A102: 2186 | B102: Thozen - Electra | C102: INSUMO | D102: Original | E102: MASSA CORRIDA PVA | F102: kg | G102: 1.3389 | H102: 3.6 | I102: 4.82004
...

Sheet Insumos (2)
A1: DADOS
A2: Titulo | B2: Tabela de insumos utilizados no projeto
A3: Obra | B3: ELECTRA TOWERS
A4: Cliente | B4: THOZEN
A5: Cidade | B5: Porto Belo
A6: Endereço
A7: Descrição
A8: UF | B8: SC
A11: INSUMOS UTILIZADOS
A12: Código | B12: Tabela | C12: Tipo | D12: Descrição | E12: Unid. | F12: Preço | G12: Origem custo | H12: Justificativa
A14: 194 | B14: Thozen - Electra | C14: Material | D14: ARGAMASSA ESTABILIZADA PARA ASSENTAMENTO | E14: m3 | F14: 480 | I14: =A14&B14 -> 194Thozen - Electra
A15: 228 | B15: Thozen - Electra | C15: Material | D15: BLOCO CERÂMICO 11,5X19X19CM | E15: un | F15: 1.1 | I15: =A15&B15 -> 228Thozen - Electra
A16: 232 | B16: Thozen - Electra | C16: Material | D16: BLOCO CERÂMICO 14X19X19CM | E16: un | F16: 1.74 | I16: =A16&B16 -> 232Thozen - Electra
A17: 48433 | B17: Thozen - Electra | C17: Material | D17: BLOCO CERÂMICO 19X19X19CM | E17: un | F17: 2.43 | I17: =A17&B17 -> 48433Thozen - Electra
A18: 759 | B18: Thozen - Electra | C18: Material | D18: CONCRETO USINADO FCK 20 MPA, SLUMP 14+/-2 | E18: m3 | F18: 450 | I18: =A18&B18 -> 759Thozen - Electra
A19: 4800 | B19: Thozen - Electra | C19: Material | D19: DESMOLDANTE DE FORMAS PARA CONCRETO | E19: l | F19: 6.45 | I19: =A19&B19 -> 4800Thozen - Electra
A20: 1412 | B20: Thozen - Electra | C20: Material | D20: ESPAÇADOR PLÁSTICO | E20: un | F20: 0.15 | I20: =A20&B20 -> 1412Thozen - Electra
A21: 2324 | B21: Thozen - Electra | C21: Material | D21: PONTALETE 7,5X7,5 CM PINUS | E21: m3 | F21: 1310 | I21: =A21&B21 -> 2324Thozen - Electra
A22: 2362 | B22: Thozen - Electra | C22: Material | D22: PREGO POLIDO COM CABEÇA 17X21 | E22: kg | F22: 10.91 | I22: =A22&B22 -> 2362Thozen - Electra
A23: 2546 | B23: Thozen - Electra | C23: Material | D23: SARRAFO 2,5X7,5 CM PINUS | E23: m3 | F23: 1300 | I23: =A23&B23 -> 2546Thozen - Electra
A24: 2611 | B24: Thozen - Electra | C24: Material | D24: TÁBUA 1"X12" 2,5X30CM PINUS | E24: m3 | F24: 1800 | I24: =A24&B24 -> 2611Thozen - Electra
A25: 32 | B25: Thozen - Electra | C25: Material | D25: AÇO CA-50 DIÂMETRO 6,30 MM | E25: kg | F25: 6.9 | G25: GERDAU | I25: =A25&B25 -> 32Thozen - Electra
A26: 48435 | B26: Thozen - Electra | C26: Material | D26: ARGAMASSA EXPANSIVA PARA ENCUNHAMENTO | E26: Kg | F26: 16.87 | I26: =A26&B26 -> 48435Thozen - Electra
A27: 718 | B27: Thozen - Electra | C27: Material | D27: CARTUCHO 22 - CARGA LEVE PARA FINCA PINO E POLVORA | E27: un | F27: 0.3 | I27: =A27&B27 -> 718Thozen - Electra
A28: 2260 | B28: Thozen - Electra | C28: Material | D28: PINO LISO EM AÇO GALVANIZADO 1/2 X 22MM COM ARRUELA | E28: un | F28: 0.3 | I28: =A28&B28 -> 2260Thozen - Electra
A29: 2901 | B29: Thozen - Electra | C29: Material | D29: TELA DE ACO SOLDADA, FIO 1,24MM, MALHA 15X15MM | E29: m2 | F29: 2.5 | I29: =A29&B29 -> 2901Thozen - Electra
A30: 202 | B30: Thozen - Electra | C30: Material | D30: ARGAMASSA POLIMÉRICA IMPERMEABILIZANTE | E30: kg | F30: 11.5 | I30: =A30&B30 -> 202Thozen - Electra
A31: 197 | B31: Thozen - Electra | C31: Material | D31: ARGAMASSA ESTABILIZADA PARA REBOCO | E31: m3 | F31: 480 | I31: =A31&B31 -> 197Thozen - Electra
A32: 48481 | B32: Thozen - Electra | C32: Material | D32: ADITIVO ADESIVO LÍQUIDO PARA ARGAMASSA | E32: L | F32: 7.8 | I32: =A32&B32 -> 48481Thozen - Electra
A33: 48373 | B33: Thozen - Electra | C33: Material | D33: CHAPISCO COLANTE 20KG | E33: Kg | F33: 1.31 | I33: =A33&B33 -> 48373Thozen - Electra
A34: 2154 | B34: Thozen - Electra | C34: Mao_obra | D34: MÃO DE OBRA PARA EXECUÇÃO DE CHAPISCO E REBOCO INTERNO EM PAREDES | E34: m2 | F34: 35 | I34: =A34&B34 -> 2154Thozen - Electra
A35: 193 | B35: Thozen - Electra | C35: Material | D35: ARGAMASSA COLANTE AC III | E35: kg | F35: 2.345 | I35: =A35&B35 -> 193Thozen - Electra
A36: 4881 | B36: Thozen - Electra | C36: Material | D36: ESPAÇADOR PARA REVESTIMENTO CERÂMICO TIPO CRUZETA 5 MM | E36: un | F36: 0.2 | I36: =A36&B36 -> 4881Thozen - Electra
A37: 4880 | B37: Thozen - Electra | C37: Material | D37: REJUNTE FLEXÍVEL | E37: m2 | F37: 2.0643 | I37: =A37&B37 -> 4880Thozen - Electra
... A61: 2552 | B61: Thozen - Electra | C61: Material | D61: SELADOR ACRÍLICO | E61: l | F61: 9.44 | I61: =A61&B61 -> 2552Thozen - Electra

Sheet PROJETOS
B1: GESTÃO DOS PROJETOS | J1: LEGENDA
A2: Obra | B2: Electra Towers (Rubens Alves) | J2: NÃO SE APLICA
A3: Empresa | B3: Thozen Empreendimentos | J3: PENDENTE
A4: Revisão | B4: R01 | J4: RECEBIDO
B5: PAVIMENTO | C5: DISCIPLINA | D5: PROJETOS | E5: CAMINHO | F5: STATUS | G5: OBSERVAÇÕES | J5: REVISADO
B7: ESTRUTURA
B8: TERRAPLENAGEM | C8: INFRAESTRUTURA | F8: NÃO SE APLICA
B9: MOVIMENTAÇÃO DE TERRA | C9: INFRAESTRUTURA | F9: PENDENTE
B10: FUNDAÇÃO PROFUNDA | C10: INFRAESTRUTURA | D10: 1203 - PREFORMAS - R20.DWG | E10: 01 ESTRUTURA/DWG | F10: RECEBIDO | G10: DWG Pré-formas Rev.20
B11: FUNDAÇÃO RASA | C11: INFRAESTRUTURA | D11: 1203 - THOZEN - RUBENS ALVES - BLOCOS+RAMPAS DE ACESSO - R26.ifc | E11: 01 ESTRUTURA/IFC | F11: RECEBIDO | G11: IFC Blocos + Rampas de Acesso Rev.26
B12: CONTENÇÃO | C12: INFRAESTRUTURA | F12: NÃO SE APLICA
B13: ÁREA – 1º PAVTO. (TÉRREO) | C13: SUPRAESTRUTURA | F13: RECEBIDO | G13: Coberto pelo IFC estrutural completo
B14: ÁREA – MEZANINO DO 1º PAVTO. | C14: SUPRAESTRUTURA | F14: RECEBIDO | G14: Coberto pelo IFC estrutural completo
B15: ÁREA – 2º PAVIMENTO | C15: SUPRAESTRUTURA | F15: RECEBIDO | G15: Coberto pelo IFC estrutural completo
B16: ÁREA – MEZANINO DO 2º PAVTO. | C16: SUPRAESTRUTURA | F16: RECEBIDO | G16: Coberto pelo IFC estrutural completo
B17: ÁREA – 3º PAVIMENTO | C17: SUPRAESTRUTURA | F17: RECEBIDO | G17: Coberto pelo IFC estrutural completo
B18: ÁREA – MEZANINO DO 3º PAVTO. | C18: SUPRAESTRUTURA | F18: RECEBIDO | G18: Coberto pelo IFC estrutural completo
B19: ÁREA – 4º PAVIMENTO GARAGEM/LAZER | C19: SUPRAESTRUTURA | F19: RECEBIDO | G19: Coberto pelo IFC estrutural completo
B20: ÁREA – 5º PAVIMENTO LAZER | C20: SUPRAESTRUTURA | F20: RECEBIDO | G20: Coberto pelo IFC estrutural completo
B21: ÁREA – 6º PAVIMENTO TIPO - DIFERENCIADO | C21: SUPRAESTRUTURA | F21: RECEBIDO | G21: Coberto pelo IFC estrutural completo
B22: ÁREA – 7º AO 14° PAVIMENTO TIPO - X8 | C22: SUPRAESTRUTURA | F22: RECEBIDO | G22: Coberto pelo IFC estrutural completo
B23: ÁREA – 15º AO 35° PAVIMENTO TIPO - X21 | C23: SUPRAESTRUTURA | F23: RECEBIDO | G23: Coberto pelo IFC estrutural completo
B24: ARQUITETURA
B25: TERRAPLENAGEM | C25: ARQUITETURA | F25: NÃO SE APLICA
B26: MOVIMENTAÇÃO DE TERRA | C26: ARQUITETURA | F26: NÃO SE APLICA
B27: FUNDAÇÃO PROFUNDA | C27: ARQUITETURA | F27: NÃO SE APLICA
B28: FUNDAÇÃO RASA | C28: ARQUITETURA | F28: NÃO SE APLICA
B29: CONTENÇÃO | C29: ARQUITETURA | F29: NÃO SE APLICA
B30: TÉRREO 01 | C30: ARQUITETURA | D30: RA_ARQ_EXE_01_TÉRREO_R02.dwg | E30: 02 ARQUITETURA/DWG | F30: RECEBIDO | G30: DWG Executivo Rev.02
B31: TÉRREO 02 | C31: ARQUITETURA | D31: RA_ARQ_EXE_10_CORTE1_R02.dwg + RA_ARQ_EXE_11_CORTE2_R02.dwg | E31: 02 ARQUITETURA/DWG | F31: RECEBIDO | G31: Cortes 1 e 2, Rev.02
B32: GARAGEM 01 | C32: ARQUITETURA | D32: RA_ARQ_EXE_02_G1_R02.dwg | E32: 02 ARQUITETURA/DWG | F32: RECEBIDO | G32: DWG Executivo Rev.02
B33: GARAGEM 02 | C33: ARQUITETURA | D33: RA_ARQ_EXE_03_G2_R02.dwg | E33: 02 ARQUITETURA/DWG | F33: RECEBIDO | G33: DWG Executivo Rev.02
B34: GARAGEM 03 | C34: ARQUITETURA | D34: RA_ARQ_EXE_04_G3_R02.dwg | E34: 02 ARQUITETURA/DWG | F34: RECEBIDO | G34: DWG Executivo Rev.02
B35: GARAGEM 04 | C35: ARQUITETURA | D35: RA_ARQ_EXE_05_G4_R02.dwg | E35: 02 ARQUITETURA/DWG | F35: RECEBIDO | G35: DWG Executivo Rev.02
B36: LAZER 01 | C36: ARQUITETURA | D36: RA_ARQ_EXE_06_G5_R02.dwg | E36: 02 ARQUITETURA/DWG | F36: RECEBIDO | G36: DWG Executivo Rev.02
B37: LAZER 02 | C37: ARQUITETURA | D37: RA_ARQ_EXE_07_LAZER_R02.dwg | E37: 02 ARQUITETURA/DWG | F37: RECEBIDO | G37: DWG Executivo Rev.02
B38: TIPO DIFERENCIADO 01 | C38: ARQUITETURA | D38: RA_ARQ_EXE_MODELAGEM EMBASAMENTO + COBERTURA_R08.ifc | E38: 02 ARQUITETURA/IFC | F38: RECEBIDO | G38: IFC Embasamento + Cobertura Rev.08
B39: TIPO DIFERENCIADO 02 | C39: ARQUITETURA | D39: RA_ARQ_EXE_MODELAGEM TIPO_R07.ifc | E39: 02 ARQUITETURA/IFC | F39: RECEBIDO | G39: IFC Tipo Rev.07
B40: TIPO (30x) | C40: ARQUITETURA | D40: RA_ARQ_EXE_08_TIPOS_R02.dwg | E40: 02 ARQUITETURA/DWG | F40: RECEBIDO | G40: DWG Executivo Rev.02
B41: DUPLEX INFERIOR (3x) | C41: ARQUITETURA | F41: NÃO SE APLICA
B42: DUPLEX SUPERIOR (3x) | C42: ARQUITETURA | F42: NÃO SE APLICA
B43: LAZER 3 | C43: ARQUITETURA | F43: NÃO SE APLICA
B44: CASA DE MÁQUINAS | C44: ARQUITETURA | F44: NÃO SE APLICA
B45: BARRILETE | RESERVATÓRIOS | C45: ARQUITETURA | D45: RA_ARQ_EXE_09_RES E COB_R02.dwg | E45: 02 ARQUITETURA/DWG | F45: RECEBIDO | G45: DWG Executivo Rev.02
B46: COMPLEMENTARES
B47: GERAL | C47: INSTALAÇÕES PLUVIAL | F47: NÃO SE APLICA
B48: GERAL | C48: INSTALAÇÕES ELÉTRICA | D48: 348 - E01 [28] rev.01 - EL_R.Rubens Alves - 01° PAVTO. TÉRREO [T. A].dwg; 348 - E02 [28] rev.01 - EL_R.Rubens Alves - 01° PAVTO. TÉRREO [T. B].dwg; 348 - E03 [28] rev.01 - EL_R.Rubens Alves - 02° PAVTO. G1 [T. A].dwg (+24 mais) | E48: 09 ELÉTRICO | F48: RECEBIDO | G48: DWG 18 pranchas + IFC 9 modelos, Rev.01
B49: GERAL | C49: INSTALAÇÕES TELEFONIA | D49: 348 - T02 [24] rev.01 - EL_R.Rubens Alves - 01° PAVTO. TÉRREO [T. A].dwg; 348 - T03 [24] rev.01 - EL_R.Rubens Alves - 01° PAVTO. TÉRREO [T. B].dwg; 348 - T04 [24] rev.01 - EL_R.Rubens Alves - 02° PAVTO. G1 [T. A].dwg (+24 mais) | E49: 10 TELEFONICO | F49: RECEBIDO | G49: DWG 18 pranchas + IFC 9 modelos, Rev.01
B50: GERAL | C50: INSTALAÇÕES POTÁVEL | D50: 348 - H01 [30] rev.01 - EL_R.Rubens Alves - 01° PAVTO. TÉRREO - PISO [T.A].dwg; 348 - H02 [30] rev.01 - EL_R.Rubens Alves - 01° PAVTO. TÉRREO - PISO [T.B].dwg; 348 - H03 [30] rev.01 - EL_R.Rubens Alves - 01° PAVTO. TÉRREO - TETO [T.A].dwg (+18 mais) | E50: 05 HIDRÁULICO | F50: RECEBIDO | G50: DWG 20 pranchas + IFC completo, Rev.01
B51: GERAL | C51: INSTALAÇÕES ESGOTO | D51: 348 - S01 [22] rev.01 - EL_R.Rubens Alves - 01° PAVTO. TÉRREO [T.A].dwg; 348 - S02 [22] rev.01 - EL_R.Rubens Alves - 01° PAVTO. TÉRREO [T.B].dwg; 348 - S03 [22] rev.01 - EL_R.Rubens Alves - 02° PAVTO. G1 [T.A].dwg (+27 mais) | E51: 06 SANITÁRIO | F51: RECEBIDO | G51: DWG 20 pranchas + IFC 10 modelos, Rev.01
B52: GERAL | C52: INSTALAÇÕES PCI | D52: 348 - IGC 01 [08] rev-00 - 01° PAVTO- TÉRREO (T-A).dwg; 348 - IGC 01 [08] rev.00 - 01° PAVTO. TÉRREO (T.A).dwg; 348 - IGC 02 [08] rev.00 - 01° PAVTO. TÉRREO (T.B).dwg (+13 mais) | E52: 07 PREVENTIVO INCENDIO CIVIL | F52: RECEBIDO | G52: DWG 11 pranchas + IFC 5 modelos (IGC+PCI+Dutos), Rev.00-01
B53: GERAL | C53: INST. PREV. INCÊNDIO ELÉTRICO | D53: 27 arquivos (DWG 18 + IFC 9) | E53: 08 PREVENTIVO INCENDIO ELÉTRICO | F53: RECEBIDO | G53: Prev. Incêndio Elétrico, DWG+IFC, Rev.01
B54: GERAL | C54: SPDA | D54: 10 pranchas DWG (SPDA Rev.00) | E54: 11 SPDA | F54: RECEBIDO | G54: SPDA completo, Rev.00
B55: GERAL | C55: VENTILAÇÃO MECÂNICA ESCADA | D55: RA_EVM_LEGAL_PROJETO_R05.dwg | E55: 12 ESCADA VENTILACAO MECANICA | F55: RECEBIDO | G55: Projeto Legal Rev.05
B56: GERAL | C56: EXAUSTÃO CHURRASQUEIRA | D56: RA_CHU_EXE_PROJETO_R00.dwg | E56: 13 CHURRASQUEIRA EXAUSTAO | F56: RECEBIDO | G56: Exaustão Churrasqueiras Rev.00
B57: GERAL | C57: AR-CONDICIONADO | D57: RA_ARC_EXE_00_TODAS CAD_R05.dwg | E57: 14 AR-CONDICIONADO | F57: RECEBIDO | G57: Ar-condicionado completo Rev.05
B58: GERAL | C58: ALVENARIA | D58: 18 pranchas DWG (Alvenaria + Locação, Pré-Executivo Rev.01) | E58: 03 ALVENARIA | F58: RECEBIDO | G58: Alvenaria 9 pavimentos + 9 locações, Rev.01
B59: GERAL | C59: ESQUADRIAS | D59: 4 pranchas DWG (Portas, Janelas, Peles Vidro, Vidro Fixo) | E59: 04 ESQUADRIA | F59: RECEBIDO | G59: Esquadrias Pré-Executivo Rev.01
B60: GERAL | C60: EQUIPAMENTOS HIDROMASSAGEM | F60: NÃO SE APLICA
B61: GERAL | C61: EQUIPAMENTOS PISCINA | F61: NÃO SE APLICA
B62: GERAL | C62: LOUÇAS/ METAIS/ BANCADAS | F62: NÃO SE APLICA
B63: GERAL | C63: MOBILIÁRIO | F63: NÃO SE APLICA
B64: GERAL | C64: INTERIORES | F64: NÃO SE APLICA

Sheet Ger_Tec e Adm
A4: PROJETO: | C4: Electra Towers | I4: REVISÃO: | J4: DATA
A5: EMPRESA: | C5: Thozen | I5: R00
A6: GERENCIAMENTO EXECUTIVO
A7: Atalho | B7: NIVEL | C7: Item | D7: Descrição | E7: Unidade | F7: Quant. | G7: Preço un | H7: Total | I7: Considerações | J7: Situação
B8: CÉLULA CONSTRUTIVA | C8: 01 | D8: SERVIÇOS TÉCNICOS | H8: =H9+H57 -> 3668982.5
B9: ETAPA | C9: 01.001 | D9: ESTUDOS, PROJETOS E CONSULTORIAS | H9: =H10+H20+H41+H46 -> 2273047.4 | J9: -
B10: SUBETAPA | C10: 01.001.001 | D10: Estudos | H10: =H11+H12+H13+H14+H15+H16+H17+H18+H19 -> 260925.31
B11: SERVIÇO | C11: 01.001.001.001 | D11: Memorial descritivo | E11: vb | F11: 1 | G11: 18386.35 | H11: =G11*F11 -> 18386.35 | I11: Estimado | J11: Lançado ERP
B12: SERVIÇO | C12: 01.001.001.002 | D12: Levantamento topográfico | E12: vb | F12: 1 | G12: 3000 | H12: =G12*F12 -> 3000 | I12: Recebido | J12: Lançado ERP
B13: SERVIÇO | C13: 01.001.001.003 | D13: Estudo geológico | E13: vb | F13: 1 | G13: 26930.408 | H13: =G13*F13 -> 26930.408 | I13: Estimado | J13: Lançado ERP
B14: SERVIÇO | C14: 01.001.001.004 | D14: Estudo ambiental | E14: vb | F14: 1 | G14: 4500 | H14: =G14*F14 -> 4500 | I14: Recebido | J14: Lançado ERP
B15: SERVIÇO | C15: 01.001.001.005 | D15: Sondagem do terreno | E15: vb | F15: 1 | G15: 7947.99 | H15: =G15*F15 -> 7947.99 | I15: Recebido | J15: Lançado ERP
B16: SERVIÇO | C16: 01.001.001.006 | D16: Projeto de canteiro | E16: vb | F16: 1 | G16: 11160.563 | H16: =G16*F16 -> 11160.563 | I16: Estimado | J16: Lançado ERP
B17: SERVIÇO | C17: 01.001.001.007 | D17: EFEG - Teste de Carga | E17: vb | F17: 1 | G17: 29000 | H17: =G17*F17 -> 29000 | I17: Recebido | J17: Lançado ERP
B18: SERVIÇO | C18: 01.001.001.008 | D18: Solugeot - Teste de Carga | E18: vb | F18: 1 | G18: 140000 | H18: =G18*F18 -> 140000 | I18: Recebido | J18: Lançado ERP
B19: SERVIÇO | C19: 01.001.001.009 | D19: Concreto - Teste de Carga | E19: vb | F19: 1 | G19: 20000 | H19: =G19*F19 -> 20000 | I19: Recebido | J19: Lançado ERP
B20: SUBETAPA | C20: 01.001.002 | D20: Projetos | H20: =H21+H22+H23+H24+H25+H26+H27+H28+H29+H30+H31+H32+H33+H34+H35+H36+H37+H38+H39+H40 -> 1205079.2
B21: SERVIÇO | C21: 01.001.002.001 | D21: Legalização de incorporação | E21: vb | F21: 1 | G21: 67351.993 | H21: =G21*F21 -> 67351.993 | I21: Estimado | J21: Lançado ERP
B22: SERVIÇO | C22: 01.001.002.002 | D22: Projeto arquitetônico legal | E22: vb | F22: 1 | G22: 237000 | H22: =G22*F22 -> 237000 | I22: Recebido - Considerado junto desse projeto os valores de projeto arquitetônico legal + hidráulico + preventivo + elétrico + arquitetônico | J22: Lançado ERP
B23: SERVIÇO | C23: 01.001.002.003 | D23: Projeto Arquitetônico interiores | E23: vb | F23: 1 | G23: 86773.378 | H23: =G23*F23 -> 86773.378 | I23: Estimado | J23: Lançado ERP
B24: SERVIÇO | C24: 01.001.002.004 | D24: Projeto arquitetônico de fachada | E24: vb | F24: 1 | G24: 58250 | H24: =G24*F24 -> 58250 | I24: Recebido | J24: Lançado ERP
B25: SERVIÇO | C25: 01.001.002.005 | D25: Projeto técnico de fachada | E25: vb | F25: 1 | G25: 75145.12 | H25: =G25*F25 -> 75145.12 | I25: Estimado | J25: Lançado ERP
B26: SERVIÇO | C26: 01.001.002.006 | D26: Projeto de terraplanagem | E26: vb | F26: 1 | G26: 6962.4358 | H26: =G26*F26 -> 6962.4358 | I26: Estimado | J26: Lançado ERP
B27: SERVIÇO | C27: 01.001.002.007 | D27: Projeto estrutural | E27: vb | F27: 1 | G27: 70000 | H27: =G27*F27 -> 70000 | I27: Recebido - Considerado junto desse projeto os valores de projeto estrutural e fundação | J27: Lançado ERP
B28: SERVIÇO | C28: 01.001.002.008 | D28: Projeto de automação | E28: vb | F28: 1 | G28: 96720.281 | H28: =G28*F28 -> 96720.281 | I28: Estimado | J28: Lançado ERP
B29: SERVIÇO | C29: 01.001.002.009 | D29: Projeto de irrigação | E29: vb | F29: 1 | G29: 39550.22 | H29: =G29*F29 -> 39550.22 | I29: Estimado | J29: Lançado ERP
B30: SERVIÇO | C30: 01.001.002.010 | D30: Projeto preventivo (PPCI - Plano de Prevenção e Proteção Contra Incêndios) e Gás | E30: vb | F30: 1 | G30: 27354.018 | H30: =G30*F30 -> 27354.018 | I30: Estimado - Considerado somente o projeto de gás, pois o ppci, conforme informado no formulario, esta nicluso no arquitetônico | J30: Lançado ERP
B31: SERVIÇO | C31: 01.001.002.011 | D31: Projeto de climatização/exaustão | E31: vb | F31: 1 | G31: 91124.893 | H31: =G31*F31 -> 91124.893 | I31: Estimado | J31: Lançado ERP
B32: SERVIÇO | C32: 01.001.002.012 | D32: Projeto de Segurança | E32: vb | F32: 1 | G32: 24827.001 | H32: =G32*F32 -> 24827.001 | I32: Estimado | J32: Lançado ERP
... B40: SERVIÇO | C40: 01.001.002.020 | D40: Projeto de Paisagismo | E40: vb | F40: 1 | G40: 36770.652 | H40: =G40*F40 -> 36770.652 | I40: Estimado | J40: Lançado ERP
B41: SUBETAPA | C41: 01.001.003 | D41: Consultorias | H41: =H42+H43+H44+H45 -> 206589.87
B42: SERVIÇO | C42: 01.001.003.001 | D42: Compatibilização de Projetos BIM | E42: vb | F42: 1 | G42: 144789.87 | H42: =G42*F42 -> 144789.87 | I42: Estimado | J42: Lançado ERP
B43: SERVIÇO | C43: 01.001.003.002 | D43: Tour Virtual | E43: vb | F43: 1 | G43: 11300 | H43: =G43*F43 -> 11300 | I43: Recebido | J43: Lançado ERP
B44: SERVIÇO | C44: 01.001.003.003 | D44: Consultoria técnica de legalização | E44: vb | F44: 1 | G44: 16000 | H44: =G44*F44 -> 16000 | I44: Recebido | J44: Lançado ERP
B45: SERVIÇO | C45: 01.001.003.004 | D45: Orçamento e planejamento | E45: vb | F45: 1 | G45: 34500 | H45: =G45*F45 -> 34500 | I45: Recebido | J45: Lançado ERP
B46: SUBETAPA | C46: 01.001.004 | D46: Ensaios | H46: =H47+H48+H49+H50+H51+H52+H53+H54+H55+H56 -> 600453
B47: SERVIÇO | C47: 01.001.004.001 | D47: Controle tecnológico do concreto | E47: vb | F47: 1 | G47: 238185 | H47: =G47*F47 -> 238185 | I47: Estimado | J47: Lançado ERP
B48: SERVIÇO | C48: 01.001.004.002 | D48: Ensaio de argamassa | E48: vb | F48: 1 | G48: 11200 | H48: =G48*F48 -> 11200 | I48: Estimado | J48: Lançado ERP
B49: SERVIÇO | C49: 01.001.004.003 | D49: Prova de carga | E49: vb | F49: 1 | G49: 5500 | H49: =G49*F49 -> 5500 | I49: Estimado | J49: Lançado ERP
B50: SERVIÇO | C50: 01.001.004.004 | D50: Ensaio de arrancamento de reboco | E50: vb | F50: 1 | G50: 6300 | H50: =G50*F50 -> 6300 | I50: Estimado | J50: Lançado ERP
B51: SERVIÇO | C51: 01.001.004.005 | D51: Ensaio de arrancamento revestimento cerâmico | E51: vb | F51: 1 | G51: 5360 | H51: =G51*F51 -> 5360 | I51: Estimado | J51: Lançado ERP
B52: SERVIÇO | C52: 01.001.004.006 | D52: Ensaio de arrancamento fachada | E52: vb | F52: 1 | G52: 5360 | H52: =G52*F52 -> 5360 | I52: Estimado | J52: Lançado ERP
B53: SERVIÇO | C53: 01.001.004.007 | D53: Ensaio de arrancamento de gancho da cobertura | E53: vb | F53: 1 | G53: 3840 | H53: =G53*F53 -> 3840 | I53: Estimado | J53: Lançado ERP
B54: SERVIÇO | C54: 01.001.004.008 | D54: Laudo de Vizinhança | E54: vb | F54: 1 | G54: 7500 | H54: =G54*F54 -> 7500 | I54: Recebido | J54: Lançado ERP
B55: SERVIÇO | C55: 01.001.004.009 | D55: Laudo Spda | E55: vb | F55: 1 | G55: 4200 | H55: =G55*F55 -> 4200 | I55: Estimado | J55: Lançado ERP
B56: SERVIÇO | C56: 01.001.004.010 | D56: Softwares | E56: vb | F56: 1 | G56: 313008 | H56: =G56*F56 -> 313008 | I56: Estimado | J56: Lançado ERP
B57: ETAPA | C57: 01.002 | D57: TAXAS E DOCUMENTOS | H57: =H58+H75 -> 1395935.1
B58: SUBETAPA | C58: 01.002.001 | D58: Licenciamentos, Taxas, Impostos, Aprovações e Seguros | H58: =H59+H60+H61+H62+H63+H64+H65+H66+H67+H68+H69+H70+H71+H72+H73+H74 -> 1044668.3
B59: SERVIÇO | C59: 01.002.001.001 | D59: Despesas de Seguros | E59: vb | F59: 1 | G59: 71960.851 | H59: =G59*F59 -> 71960.851 | I59: Estimado | J59: Finalizado
B60: SERVIÇO | C60: 01.002.001.002 | D60: Taxas de consulta de viabilidade | E60: vb | F60: 1 | G60: 412.37 | H60: =G60*F60 -> 412.37 | I60: Estimado | J60: Finalizado
B61: SERVIÇO | C61: 01.002.001.003 | D61: Avaliação e Legalização ambiental | E61: vb | F61: 1 | G61: 11955.032 | H61: =G61*F61 -> 11955.032 | I61: Estimado | J61: Finalizado
B62: SERVIÇO | C62: 01.002.001.004 | D62: Aprovação e legalização prefeitura | E62: vb | F62: 1 | G62: 30000 | H62: =G62*F62 -> 30000 | I62: Recebido | J62: Finalizado
B63: SERVIÇO | C63: 01.002.001.005 | D63: Aprovação e legalização água e esgoto | E63: vb | F63: 1 | G63: 16643.349 | H63: =G63*F63 -> 16643.349 | I63: Estimado | J63: Finalizado
B64: SERVIÇO | C64: 01.002.001.006 | D64: Aprovação e legalização elétrico | E64: vb | F64: 1 | G64: 33097.805 | H64: =G64*F64 -> 33097.805 | I64: Estimado | J64: Finalizado
B65: SERVIÇO | C65: 01.002.001.007 | D65: Taxas ART | E65: vb | F65: 1 | G65: 12228.686 | H65: =G65*F65 -> 12228.686 | I65: Estimado | J65: Finalizado
B66: SERVIÇO | C66: 01.002.001.008 | D66: Taxas alvará | E66: vb | F66: 1 | G66: 146127.51 | H66: =G66*F66 -> 146127.51 | I66: Estimado | J66: Finalizado
B67: SERVIÇO | C67: 01.002.001.009 | D67: Taxa Renovação Alvará de Construção | E67: vb | F67: 1 | G67: 3600 | H67: =G67*F67 -> 3600 | I67: Estimado | J67: Finalizado
B68: SERVIÇO | C68: 01.002.001.010 | D68: Taxas de Alvará de Demolição | E68: vb | F68: 1 | G68: 1000 | H68: =G68*F68 -> 1000 | I68: Recebido | J68: Finalizado
B69: SERVIÇO | C69: 01.002.001.011 | D69: Taxa LAP, AUC, LAI e LAO | E69: vb | F69: 1 | G69: 8800 | H69: =G69*F69 -> 8800 | I69: Estimado | J69: Finalizado
B70: SERVIÇO | C70: 01.002.001.012 | D70: Outorga onerosa, compra de índice e obra de arte | E70: vb | F70: 1 | G70: 453148.83 | H70: =G70*F70 -> 453148.83 | I70: Recebido | J70: Finalizado
... B74: SERVIÇO | C74: 01.002.001.016 | D74: Taxa Habite-se | E74: vb | F74: 1 | G74: 31036.411 | H74: =G74*F74 -> 31036.411 | I74: Estimado | J74: Finalizado
B75: SUBETAPA | C75: 01.002.002 | D75: Documentos | H75: =H76+H77+H78+H79 -> 351266.87
B76: SERVIÇO | C76: 01.002.002.001 | D76: As Built | E76: vb | F76: 1 | G76: 41370.448 | H76: =G76*F76 -> 41370.448 | I76: Estimado | J76: Finalizado
B77: SERVIÇO | C77: 01.002.002.002 | D77: Laudo técnico de vistoria de entrega | E77: vb | F77: 1 | G77: 162829.57 | H77: =G77*F77 -> 162829.57 | I77: Estimado | J77: Finalizado
B78: SERVIÇO | C78: 01.002.002.003 | D78: Manuais técnicos condomínio/proprietários | E78: vb | F78: 1 | G78: 105185.05 | H78: =G78*F78 -> 105185.05 | I78: Estimado | J78: Finalizado
B79: SERVIÇO | C79: 01.002.002.004 | D79: Certidão INSS | E79: vb | F79: 1 | G79: 41881.806 | H79: =G79*F79 -> 41881.806 | I79: Estimado | J79: Finalizado
B80: CÉLULA CONSTRUTIVA | C80: 02 | D80: SERVIÇOS INICIAIS | H80: =H81+H106+H148 -> 4925713.3
B81: ETAPA | C81: 02.001 | D81: SEGURANÇA, MEIO AMBIENTE E SAÚDE | H81: =H82+H86+H98+H102 -> 609504.18 | J81: -
B82: SUBETAPA | C82: 02.001.001 | D82: Segurança do Trabalho | H82: =H83+H84+H85 -> 300750
B83: SERVIÇO | C83: 02.001.001.001 | D83: Serviço terceirizado de segurança do trabalho - Valor/mês (R$) | E83: mês | F83: 36 | G83: 2500 | H83: =G83*F83 -> 90000 | I83: Recebido | J83: Finalizado
B84: SERVIÇO | C84: 02.001.001.002 | D84: Equipamentos de proteção individual - EPI | E84: vb | F84: 1 | G84: 204750 | H84: =G84*F84 -> 204750 | I84: Estimado | J84: Finalizado
B85: SERVIÇO | C85: 02.001.001.003 | D85: Projetos de segurança do trabalho | E85: vb | F85: 1 | G85: 6000 | H85: =G85*F85 -> 6000 | I85: Recebido | J85: Finalizado
B86: SUBETAPA | C86: 02.001.002 | D86: Equipamentos de proteção | H86: =H87+H88+H89+H90+H91+H92+H93+H94+H95+H96+H97 -> 213973.14
B87: SERVIÇO | C87: 02.001.002.001 | D87: Bandeja de proteção primária | E87: m | F87: 0 | G87: 243.95615 | H87: =G87*F87 -> 0 | I87: EPC'S | J87: Lançado ERP
B88: SERVIÇO | C88: 02.001.002.002 | D88: Bandeja de proteção secundária | E88: m | F88: 0 | G88: 230.09615 | H88: =G88*F88 -> 0 | I88: EPC'S | J88: Lançado ERP
B89: SERVIÇO | C89: 02.001.002.003 | D89: Guarda-corpo de vãos, fixado em fôrma de madeira, em trama de madeira com tela de polipropileno | E89: m2 | F89: 649.372 | G89: 38.622647 | H89: =G89*F89 -> 25080.466 | I89: EPC'S | J89: Lançado ERP
B90: SERVIÇO | C90: 02.001.002.004 | D90: Guarda-corpo em laje pós-desforma com Escora metálica, travessões e tela | E90: m | F90: 0 | G90: 42.431057 | H90: =G90*F90 -> 0 | I90: EPC'S | J90: Lançado ERP
B91: SERVIÇO | C91: 02.001.002.005 | D91: Tela fachadeira | E91: m2 | F91: 0 | G91: 8.5113 | H91: =G91*F91 -> 0 | I91: EPC'S | J91: Lançado ERP
B92: SERVIÇO | C92: 02.001.002.006 | D92: Fechamento removível de vãos de porta de elevador em madeira | E92: m2 | F92: 211.68 | G92: 49.519651 | H92: =G92*F92 -> 10482.32 | I92: EPC'S | J92: Lançado ERP
B93: SERVIÇO | C93: 02.001.002.007 | D93: Fechamento removível de vãos de porta de entrada dos aptos. em madeira | E93: m2 | F93: 861.84 | G93: 49.519651 | H93: =G93*F93 -> 42678.016 | I93: EPC'S | J93: Lançado ERP
B94: SERVIÇO | C94: 02.001.002.008 | D94: Fechamento removível de abertura no piso do elevador em madeira | E94: m2 | F94: 304.08 | G94: 49.519651 | H94: =G94*F94 -> 15057.935 | I94: EPC'S | J94: Lançado ERP
B95: SERVIÇO | C95: 02.001.002.009 | D95: Cobertura para Proteção de Pedestres | E95: m2 | F95: 137.13 | G95: 880 | H95: =G95*F95 -> 120674.4 | I95: EPC'S | J95: Lançado ERP
B96: SERVIÇO | C96: 02.001.002.010 | D96: Varal de segurança com cabo de aço (linha de vida) | E96: m | F96: 0 | G96: 87.214 | H96: =G96*F96 -> 0 | I96: EPC'S | J96: Lançado ERP
B97: SERVIÇO | C97: 02.001.002.011 | D97: Tela SLQA | E97: m | F97: 0 | G97: 88 | H97: =G97*F97 -> 0 | I97: EPC'S | J97: Lançado ERP
B98: SUBETAPA | C98: 02.001.003 | D98: Meio Ambiente | H98: =H99+H100+H101 -> 85259.856
B99: SERVIÇO | C99: 02.001.003.001 | D99: Elaboração do Programa de Controle Médico de Saúde Ocupacional (PCMSO) | E99: vb | F99: 1 | G99: 8059.8562 | H99: =G99*F99 -> 8059.8562 | I99: Estimado | J99: Finalizado
B100: SERVIÇO | C100: 02.001.003.002 | D100: Elaboração do programa de gerenciamento de riscos (PGR) | E100: vb | F100: 1 | G100: 5200 | H100: =G100*F100 -> 5200 | I100: Recebido | J100: Finalizado
B101: SERVIÇO | C101: 02.001.003.003 | D101: Remoção de entulhos e resíduos | E101: mês | F101: 36 | G101: 2000 | H101: =G101*F101 -> 72000 | I101: Estimado | J101: Finalizado
B102: SUBETAPA | C102: 02.001.004 | D102: Saúde Ocupacional | H102: =H103+H104+H105 -> 9521.1865
B103: SERVIÇO | C103: 02.001.004.001 | D103: Medicamentos preventivos e de emergência | E103: vb | F103: 1 | G103: 3789.0563 | H103: =G103*F103 -> 3789.0563 | I103: Estimado | J103: Finalizado
B104: SERVIÇO | C104: 02.001.004.002 | D104: Kit socorrista | E104: vb | F104: 1 | G104: 1232.1302 | H104: =G104*F104 -> 1232.1302 | I104: Estimado | J104: Finalizado
B105: SERVIÇO | C105: 02.001.004.003 | D105: Dedetização, desratização e sanitização dos ambientes | E105: mês | F105: 18 | G105: 250 | H105: =G105*F105 -> 4500 | I105: Estimado | J105: Finalizado
B106: ETAPA | C106: 02.002 | D106: ADMINISTRAÇÃO E CANTEIRO DE OBRA | H106: =H107+H114+H133+H138 -> 4271209.1
B107: SUBETAPA | C107: 02.002.001 | D107: Equipe de Gestão e Apoio | H107: =H108+H109+H110+H111+H112+H113 -> 2054400
B108: SERVIÇO | C108: 02.002.001.001 | D108: Engenheiro Civil | E108: mês | F108: 48 | G108: 21000 | H108: =G108*F108 -> 1008000 | I108: Recebido | J108: Finalizado
B109: SERVIÇO | C109: 02.002.001.002 | D109: Almoxarife | E109: mês | F109: 24 | G109: 5000 | H109: =G109*F109 -> 120000 | I109: Recebido | J109: Finalizado
B110: SERVIÇO | C110: 02.002.001.003 | D110: Auxiliar de engenharia | E110: mês | F110: 12 | G110: 6800 | H110: =G110*F110 -> 81600 | I110: Recebido | J110: Finalizado
B111: SERVIÇO | C111: 02.002.001.004 | D111: Assistente administrativo | E111: mês | F111: 48 | G111: 4500 | H111: =G111*F111 -> 216000 | I111: Recebido | J111: Finalizado
B112: SERVIÇO | C112: 02.002.001.005 | D112: Estagiário | E112: mês | F112: 36 | G112: 2000 | H112: =G112*F112 -> 72000 | I112: Recebido | J112: Finalizado
B113: SERVIÇO | C113: 02.002.001.006 | D113: Vigilância / portaria | E113: mês | F113: 48 | G113: 11600 | H113: =G113*F113 -> 556800 | I113: Estimado - Vamos contratar o controle da Inmeta (Sistema) e instalar catraca e facial (prever custo) | J113: Finalizado
...

Sheet Ger_Executivo_Cartesian
H4: PROJETO: | I4: Electra Towers | O4: REVISÃO: | P4: DATA
H5: EMPRESA: | I5: Thozen | O5: R00
A6: Unidade Construtiva | B6: Célula Construtiva | C6: Etapa | D6: Subetapa | E6: Serviço | G6: GERENCIAMENTO EXECUTIVO
A7: 0 | B7: 0 | C7: 0 | D7: 0 | E7: 0 | G7: EAP | H7: NIVEL | I7: Item | J7: Descrição | K7: Unidade | L7: Quant. | M7: Preço un | N7: Total | O7: Considerações | P7: Situação
A8: 0 | B8: 1 | C8: 0 | D8: 0 | E8: 0 | H8: CÉLULA CONSTRUTIVA | I8: 01 | J8: MOVIMENTAÇÃO DE TERRA
A9: 0 | B9: 1 | C9: 1 | D9: 0 | E9: 0 | H9: ETAPA | I9: 01.001 | J9: DEMOLIÇÕES, LIMPEZA DE TERRENO E LOCAÇÃO DE OBRA | N9: 26235.314 | O9: 1.5663183
A10: 0 | B10: 1 | C10: 1 | D10: 1 | E10: 0 | H10: SUBETAPA | I10: 01.001.001 | J10: Locação e gabarito de obra | N10: 26235.314 | O10: 1.5663183
A11: 0 | B11: 1 | C11: 1 | D11: 1 | E11: 1 | G11: MOVIMENTAÇÃO DE TERRA | H11: SERVIÇO | I11: 01.001.001.001 | J11: Locação da obra | K11: m2 | N11: 26235.314 | P11: Pendente
A12: 0 | B12: 1 | C12: 2 | D12: 0 | E12: 1 | H12: ETAPA | I12: 01.002 | J12: SERVIÇOS PRELIMINARES
A13: 0 | B13: 1 | C13: 2 | D13: 1 | E13: 0 | H13: SUBETAPA | I13: 01.002.001 | J13: Limpeza Permanente e Remoção entulho
A14: 0 | B14: 1 | C14: 2 | D14: 1 | E14: 1 | G14: MOVIMENTAÇÃO DE TERRA | H14: SERVIÇO | I14: 01.002.001.001 | J14: Limpeza da camada vegetal | K14: m2 | P14: Pendente
A15: 0 | B15: 1 | C15: 2 | D15: 1 | E15: 2 | G15: MOVIMENTAÇÃO DE TERRA | H15: SERVIÇO | I15: 01.002.001.002 | J15: Remoção de entulhos e resíduos | P15: Pendente
A16: 0 | B16: 1 | C16: 2 | D16: 2 | E16: 0 | H16: SUBETAPA | I16: 01.002.002 | J16: Mão de Obra de Canteiro
A17: 0 | B17: 1 | C17: 2 | D17: 2 | E17: 1 | G17: MOVIMENTAÇÃO DE TERRA | H17: SERVIÇO | I17: 01.002.002.001 | J17: Mão de Obra de Canteiro | K17: vb | P17: Pendente
A18: 0 | B18: 1 | C18: 3 | D18: 0 | E18: 1 | H18: ETAPA | I18: 01.003 | J18: SERVIÇOS DE TERRAPLANAGEM | N18: 271126.19 | O18: 16.186957
A19: 0 | B19: 1 | C19: 3 | D19: 1 | E19: 0 | H19: SUBETAPA | I19: 01.003.001 | J19: Mao de obra - movimentações de terra | N19: 271126.19 | O19: 16.186957
A20: 0 | B20: 1 | C20: 3 | D20: 1 | E20: 1 | G20: MOVIMENTAÇÃO DE TERRA | H20: SERVIÇO | I20: 01.003.001.001 | J20: Mão de obra movimentação de terra | K20: vb | N20: 233000 | P20: Pendente
A21: 0 | B21: 1 | C21: 4 | D21: 0 | E21: 2 | H21: ETAPA | I21: 01.004 | J21: SERVIÇO DE DRENAGEM | N21: 80000 | O21: 4.7762135
A22: 0 | B22: 1 | C22: 4 | D22: 1 | E22: 0 | H22: SUBETAPA | I22: 01.004.001 | J22: Drenagem | N22: 80000 | O22: 4.7762135
A23: 0 | B23: 1 | C23: 4 | D23: 1 | E23: 1 | G23: MOVIMENTAÇÃO DE TERRA | H23: SERVIÇO | I23: 01.004.001.001 | J23: Rebaixamento de Lençol freático | K23: vb | N23: 80000 | P23: Pendente
A24: 0 | B24: 2 | C24: 0 | D24: 1 | E24: 1 | H24: CÉLULA CONSTRUTIVA | I24: 02 | J24: CONTENÇÃO | N24: 772006.63 | O24: 46.090856
A25: 0 | B25: 2 | C25: 1 | D25: 0 | E25: 1 | H25: ETAPA | I25: 02.001 | J25: MURETA GUIA | N25: 18739.389 | O25: 1.1187915
A26: 0 | B26: 2 | C26: 1 | D26: 1 | E26: 0 | H26: SUBETAPA | I26: 02.001.001 | J26: Forma | N26: 6673.9436 | O26: 0.39845225
A27: 0 | B27: 2 | C27: 1 | D27: 1 | E27: 1 | G27: CONTENÇÃO | H27: SERVIÇO | I27: 02.001.001.001 | J27: Forma para infraestrutura em Tábuas de Madeira Serrada 2x reaproveitamento | K27: m2 | L27: 111.3136 | M27: 59.956229 | N27: 6673.9436 | P27: Pendente
A28: 0 | B28: 2 | C28: 1 | D28: 2 | E28: 0 | H28: SUBETAPA | I28: 02.001.002 | J28: Armadura | N28: 4318.7306 | O28: 0.25783974
A29: 0 | B29: 2 | C29: 1 | D29: 2 | E29: 1 | G29: CONTENÇÃO | H29: SERVIÇO | I29: 02.001.002.001 | J29: Armação aço CA-50 ø 6,3mm para Contenções (corte e dobra em obra) | K29: un | L29: 670.32 | M29: 6.0795674 | N29: 4075.2556 | P29: Pendente
A30: 0 | B30: 2 | C30: 1 | D30: 2 | E30: 2 | G30: CONTENÇÃO | H30: SERVIÇO | I30: 02.001.002.002 | J30: Armação aço CA-50 ø 12,5mm para Contenções (corte e dobra em obra) | K30: un | L30: 41.6016 | M30: 5.8525391 | N30: 243.47499 | P30: Pendente
A31: 0 | B31: 2 | C31: 1 | D31: 3 | E31: 0 | H31: SUBETAPA | I31: 02.001.003 | J31: Concreto | N31: 7746.7147 | O31: 0.46249954
A32: 0 | B32: 2 | C32: 1 | D32: 3 | E32: 1 | G32: CONTENÇÃO | H32: SERVIÇO | I32: 02.001.003.001 | J32: Concreto Usinado bombeável 50MPa para infraestrutura- incluindo serviço de bombeamento | K32: m3 | L32: 11.390452 | M32: 680.106 | N32: 7746.7147 | P32: Pendente
A33: 0 | B33: 2 | C33: 2 | D33: 0 | E33: 1 | H33: ETAPA | I33: 02.002 | J33: LAMELAS | PAREDE DIAFRAGMA | N33: 331865.23 | O33: 19.81324
A34: 0 | B34: 2 | C34: 2 | D34: 1 | E34: 0 | H34: SUBETAPA | I34: 02.002.001 | J34: Armadura | N34: 155967.97 | O34: 9.3117038
A35: 0 | B35: 2 | C35: 2 | D35: 1 | E35: 1 | G35: CONTENÇÃO | H35: SERVIÇO | I35: 02.002.001.001 | J35: Armação aço CA-50 ø 6,3mm para Contenções (corte e dobra em Indústria) | K35: un | L35: 2282 | M35: 8.964145 | N35: 20456.179 | P35: Pendente
A36: 0 | B36: 2 | C36: 2 | D36: 1 | E36: 2 | G36: CONTENÇÃO | H36: SERVIÇO | I36: 02.002.001.002 | J36: Armação aço CA-50 ø 8,0mm para Contenções (corte e dobra em Indústria) | K36: un | L36: 77 | M36: 8.964145 | N36: 690.23916 | P36: Pendente
A37: 0 | B37: 2 | C37: 2 | D37: 1 | E37: 3 | G37: CONTENÇÃO | H37: SERVIÇO | I37: 02.002.001.003 | J37: Armação aço CA-50 ø 12,5mm para Contenções (corte e dobra em Indústria) | K37: un | L37: 3884 | M37: 8.484145 | N37: 32952.419 | P37: Pendente
A38: 0 | B38: 2 | C38: 2 | D38: 1 | E38: 4 | G38: CONTENÇÃO | H38: SERVIÇO | I38: 02.002.001.004 | J38: Armação aço CA-50 ø 25,0mm para Contenções (corte e dobra em Indústria) | K38: un | L38: 12007 | M38: 8.484145 | N38: 101869.13 | P38: Pendente
A39: 0 | B39: 2 | C39: 2 | D39: 2 | E39: 0 | H39: SUBETAPA | I39: 02.002.002 | J39: Concreto | N39: 175897.26 | O39: 10.501536
A40: 0 | B40: 2 | C40: 2 | D40: 2 | E40: 1 | G40: CONTENÇÃO | H40: SERVIÇO | I40: 02.002.002.001 | J40: Concreto Usinado bombeável 50MPa com Penetron para infraestrutura- incluindo serviço de bombeamento | K40: m3 | L40: 210 | M40: 837.606 | N40: 175897.26 | P40: Pendente
A41: 0 | B41: 2 | C41: 3 | D41: 0 | E41: 1 | H41: ETAPA | I41: 02.003 | J41: VIGAS COROAMENTO | N41: 37645.991 | O41: 2.2475661
A42: 0 | B42: 2 | C42: 3 | D42: 1 | E42: 0 | H42: SUBETAPA | I42: 02.003.001 | J42: Forma | N42: 2482.1879 | O42: 0.14819324
A43: 0 | B43: 2 | C43: 3 | D43: 1 | E43: 1 | G43: CONTENÇÃO | H43: SERVIÇO | I43: 02.003.001.001 | J43: Forma para infraestrutura em Tábuas de Madeira Serrada 2x reaproveitamento | K43: m2 | L43: 41.4 | M43: 59.956229 | N43: 2482.1879 | P43: Pendente
A44: 0 | B44: 2 | C44: 3 | D44: 2 | E44: 0 | H44: SUBETAPA | I44: 02.003.002 | J44: Armadura | N44: 23057.916 | O44: 1.3766191
A45: 0 | B45: 2 | C45: 3 | D45: 2 | E45: 1 | G45: CONTENÇÃO | H45: SERVIÇO | I45: 02.003.002.001 | J45: Armação aço CA-50 ø 8,0mm para Contenções (corte e dobra em Indústria) | K45: kg | L45: 913.36364 | M45: 8.964145 | N45: 8187.5241 | P45: Pendente
A46: 0 | B46: 2 | C46: 3 | D46: 2 | E46: 2 | G46: CONTENÇÃO | H46: SERVIÇO | I46: 02.003.002.002 | J46: Armação aço CA-50 ø 12,5mm para Contenções (corte e dobra em Indústria) | K46: kg | L46: 45.363636 | M46: 8.484145 | N46: 384.87167 | P46: Pendente
A47: 0 | B47: 2 | C47: 3 | D47: 2 | E47: 3 | G47: CONTENÇÃO | H47: SERVIÇO | I47: 02.003.002.003 | J47: Armação aço CA-50 ø 16,0mm para Contenções (corte e dobra em Indústria) | K47: kg | L47: 1277.2727 | M47: 8.484145 | N47: 10836.567 | P47: Pendente
A48: 0 | B48: 2 | C48: 3 | D48: 2 | E48: 4 | G48: CONTENÇÃO | H48: SERVIÇO | I48: 02.003.002.004 | J48: Armação aço CA-50 ø 20,0mm para Contenções (corte e dobra em Indústria) | K48: kg | L48: 430.09091 | M48: 8.484145 | N48: 3648.9536 | P48: Pendente
A49: 0 | B49: 2 | C49: 3 | D49: 3 | E49: 0 | H49: SUBETAPA | I49: 02.003.003 | J49: Concreto | N49: 12105.887
A50: 0 | B50: 2 | C50: 3 | D50: 3 | E50: 1 | G50: CONTENÇÃO | H50: SERVIÇO | I50: 02.003.003.001 | J50: Concreto Usinado bombeável 50MPa para infraestrutura- incluindo serviço de bombeamento | K50: m3 | L50: 17.8 | M50: 680.106 | N50: 12105.887 | P50: Pendente
A51: 0 | B51: 2 | C51: 4 | D51: 0 | E51: 1 | H51: ETAPA | I51: 02.004 | J51: ESTACAS PRANCHA METÁLICA | N51: 243756 | O51: 14.552884
A52: 0 | B52: 2 | C52: 4 | D52: 1 | E52: 0 | H52: SUBETAPA | I52: 02.004.001 | J52: Estacas prancha metálica | N52: 243756 | O52: 14.552884
A53: 0 | B53: 2 | C53: 4 | D53: 1 | E53: 1 | G53: CONTENÇÃO | H53: SERVIÇO | I53: 02.004.001.001 | J53: Locação e cravação de estacas prancha EP400 para contenção | K53: m2 | L53: 492.8 | M53: 470.28409 | N53: 231756 | O53: Cotação, considerado 6 meses de locação | P53: Pendente
A54: 0 | B54: 2 | C54: 4 | D54: 1 | E54: 2 | G54: CONTENÇÃO | H54: SERVIÇO | I54: 02.004.001.002 | J54: Mobilização e Desmobilização de equipamento e máquinas considerando serviço de carga e descarga | K54: vb | L54: 1 | M54: 12000 | N54: 12000 | P54: Pendente
A55: 0 | B55: 2 | C55: 5 | D55: 0 | E55: 2 | H55: ETAPA | I55: 02.005 | J55: MÃO DE OBRA CONTENÇÕES | N55: 140000.02 | O55: 8.3583748
A56: 0 | B56: 2 | C56: 5 | D56: 1 | E56: 0 | H56: SUBETAPA | I56: 02.005.001 | J56: Mão de Obra | N56: 140000.02 | O56: 8.3583748
A57: 0 | B57: 2 | C57: 5 | D57: 1 | E57: 1 | G57: CONTENÇÃO | H57: SERVIÇO | I57: 02.005.001.001 | J57: Mão de obra para execução de contenção | K57: m2 | L57: 525 | M57: 266.6667 | N57: 140000.02 | O57: Prosposta Gessele | P57: Pendente
A58: 0 | B58: 3 | C58: 0 | D58: 1 | E58: 1 | H58: CÉLULA CONSTRUTIVA | I58: 03 | J58: INFRAESTRUTURA | N58: 4572490 | O58: 272.98986
A59: 0 | B59: 3 | C59: 1 | D59: 0 | E59: 1 | H59: ETAPA | I59: 03.001 | J59: ESTACA HÉLICE CONTÍNUA | N59: 3041540.5 | O59: 181.58809
A60: 0 | B60: 3 | C60: 1 | D60: 1 | E60: 0 | H60: SUBETAPA | I60: 03.001.001 | J60: Perfuração | N60: 950000 | O60: 56.717535
A61: 0 | B61: 3 | C61: 1 | D61: 1 | E61: 1 | G61: INFRAESTRUTURA | H61: SERVIÇO | I61: 03.001.001.001 | J61: Perfuração de estaca hélice contínua Ø 60cm | K61: m | L61: 6732 | M61: 137.48633 | N61: 925557.99 | O61: Repessado pela Gessele na reunião do dia 05/03/2026 - 950k efeg | P61: Pendente
A62: 0 | B62: 3 | C62: 1 | D62: 1 | E62: 2 | G62: INFRAESTRUTURA | H62: SERVIÇO | I62: 03.001.001.002 | J62: Mobilização e desmobilização de equipamentos - Para execução de estaca hélice monitorada | K62: vb | L62: 1 | M62: 24442.015 | N62: 24442.015 | O62: Repessado pela Gessele na reunião do dia 05/03/2026 - 950k efeg | P62: Pendente
A63: 0 | B63: 3 | C63: 1 | D63: 2 | E63: 0 | H63: SUBETAPA | I63: 03.001.002 | J63: Armadura | N63: 298834.78 | O63: 17.841234
A64: 0 | B64: 3 | C64: 1 | D64: 2 | E64: 1 | G64: INFRAESTRUTURA | H64: SERVIÇO | I64: 03.001.002.001 | J64: Armação aço CA-50 ø 6,3mm para estaca (corte e dobra em indústria) | K64: un | L64: 3495 | M64: 8.964145 | N64: 31329.687 | P64: Pendente
A65: 0 | B65: 3 | C65: 1 | D65: 2 | E65: 2 | G65: INFRAESTRUTURA | H65: SERVIÇO | I65: 03.001.002.002 | J65: Armação aço CA-50 ø 20,0mm para estaca (corte e dobra em indústria) | K65: un | L65: 31530 | M65: 8.484145 | N65: 267505.09 | P65: Pendente
A66: 0 | B66: 3 | C66: 1 | D66: 3 | E66: 0 | H66: SUBETAPA | I66: 03.001.003 | J66: Concreto | N66: 1792705.7 | O66: 107.02932
A67: 0 | B67: 3 | C67: 1 | D67: 3 | E67: 1 | G67: INFRAESTRUTURA | H67: SERVIÇO | I67: 03.001.003.001 | J67: Concreto Usinado bombeável para estacas 50MPa - incluindo serviço de bombeamento | K67: m3 | L67: 1903.4282 | M67: 941.83 | N67: 1792705.7 | P67: Pendente
A68: 0 | B68: 3 | C68: 1 | D68: 4 | E68: 0 | H68: SUBETAPA | I68: 03.001.004 | J68: Mão de Obra | N68: 0 | O68: 0
A69: 0 | B69: 3 | C69: 2 | D69: 0 | E69: 0 | H69: ETAPA | I69: 03.002 | J69: BLOCOS | N69: 1056067.4 | O69: 63.050045
A70: 0 | B70: 3 | C70: 2 | D70: 1 | E70: 0 | H70: SUBETAPA | I70: 03.002.001 | J70: Forma | N70: 15723.521 | O70: 0.93873616
A71: 0 | B71: 3 | C71: 2 | D71: 1 | E71: 1 | G71: INFRAESTRUTURA | H71: SERVIÇO | I71: 03.002.001.001 | J71: Forma para infraestrutura em Tábuas de Madeira Serrada 2x reaproveitamento | K71: m2 | L71: 262.25 | M71: 59.956229 | N71: 15723.521 | O71: Apenas blocos, 2x reaproveitamento | P71: Pendente
A72: 0 | B72: 3 | C72: 2 | D72: 2 | E72: 0 | H72: SUBETAPA | I72: 03.002.002 | J72: Armadura | N72: 592494.12 | O72: 35.37348
A73: 0 | B73: 3 | C73: 2 | D73: 2 | E73: 1 | G73: INFRAESTRUTURA | H73: SERVIÇO | I73: 03.002.002.001 | J73: Armação aço CA-50 ø 12,5mm para infraestrutura (corte e dobra em Indústria) | K73: kg | L73: 528.18182 | M73: 8.484145 | N73: 4481.1711 | P73: Pendente
A74: 0 | B74: 3 | C74: 2 | D74: 2 | E74: 2 | G74: INFRAESTRUTURA | H74: SERVIÇO | I74: 03.002.002.002 | J74: Armação aço CA-50 ø 16,0mm para infraestrutura (corte e dobra em Indústria) | K74: kg | L74: 7331.8182 | M74: 8.484145 | N74: 62204.209 | P74: Pendente
A75: 0 | B75: 3 | C75: 2 | D75: 2 | E75: 3 | G75: INFRAESTRUTURA | H75: SERVIÇO | I75: 03.002.002.003 | J75: Armação aço CA-50 ø 20,0mm para infraestrutura (corte e dobra em Indústria) | K75: kg | L75: 1318.1818 | M75: 8.484145 | N75: 11183.646 | P75: Pendente
A76: 0 | B76: 3 | C76: 2 | D76: 2 | E76: 4 | G76: INFRAESTRUTURA | H76: SERVIÇO | I76: 03.002.002.004 | J76: Armação aço CA-50 ø 25,0mm para infraestrutura (corte e dobra em Indústria) | K76: kg | L76: 60657.273 | M76: 8.484145 | N76: 514625.1 | P76: Pendente
A77: 0 | B77: 3 | C77: 2 | D77: 3 | E77: 0 | H77: SUBETAPA | I77: 03.002.003 | J77: Concreto | N77: 447849.8 | O77: 26.737828
A78: 0 | B78: 3 | C78: 2 | D78: 3 | E78: 1 | G78: INFRAESTRUTURA | H78: SERVIÇO | I78: 03.002.003.001 | J78: Concreto Usinado bombeável 50MPa para infraestrutura- incluindo serviço de bombeamento | K78: m3 | L78: 658.5 | M78: 680.106 | N78: 447849.8 | O78: 5% de perda, fck = 50Mpa | P78: Pendente
A79: 0 | B79: 3 | C79: 2 | D79: 4 | E79: 0 | H79: SUBETAPA | I79: 03.002.004 | J79: Mão de Obra | N79: 0 | O79: 0
A80: 0 | B80: 3 | C80: 3 | D80: 0 | E80: 0 | H80: ETAPA | I80: 03.003 | J80: VIGAS BALDRAMES | PILARES DE ARRANQUE | CISTERNAS E DUTOS | N80: 474882.06 | O80: 28.351727
A81: 0 | B81: 3 | C81: 3 | D81: 1 | E81: 0 | H81: SUBETAPA | I81: 03.003.001 | J81: Forma | N81: 9996.6219 | O81: 0.59682501
A82: 0 | B82: 3 | C82: 3 | D82: 1 | E82: 1 | G82: INFRAESTRUTURA | H82: SERVIÇO | I82: 03.003.001.001 | J82: Forma para infraestrutura em Tábuas de Madeira Serrada 2x reaproveitamento | K82: m2 | L82: 166.732 | M82: 59.956229 | N82: 9996.6219 | O82: Considerado blocos, vigas de fundação, duto, cisterna, lajes e pilares de arranque | P82: Pendente
A83: 0 | B83: 3 | C83: 3 | D83: 2 | E83: 0 | H83: SUBETAPA | I83: 03.003.002 | J83: Armadura | N83: 430167.93 | O83: 25.682173
A84: 0 | B84: 3 | C84: 3 | D84: 2 | E84: 1 | G84: INFRAESTRUTURA | H84: SERVIÇO | I84: 03.003.002.001 | J84: Armação aço CA-50 ø 5,0mm para infraestrutura (corte e dobra em Indústria) | K84: kg | L84: 52 | M84: 8.964145 | N84: 466.13554 | O84: Considerado vigas de fundação, duto, cisterna, lajes e pilares de arranque - 10% de perda | P84: Pendente
A85: 0 | B85: 3 | C85: 3 | D85: 2 | E85: 2 | G85: INFRAESTRUTURA | H85: SERVIÇO | I85: 03.003.002.002 | J85: Armação aço CA-50 ø 6,3mm para infraestrutura (corte e dobra em Indústria) | K85: kg | L85: 130.27273 | M85: 8.964145 | N85: 1167.7836 | O85: Considerado vigas de fundação, duto, cisterna, lajes e pilares de arranque - 10% de perda | P85: Pendente
A86: 0 | B86: 3 | C86: 3 | D86: 2 | E86: 3 | G86: INFRAESTRUTURA | H86: SERVIÇO | I86: 03.003.002.003 | J86: Armação aço CA-50 ø 8,0mm para infraestrutura (corte e dobra em Indústria) | K86: kg | L86: 982.63636 | M86: 8.964145 | N86: 8808.4948 | O86: Considerado vigas de fundação, duto, cisterna, lajes e pilares de arranque - 10% de perda | P86: Pendente
A87: 0 | B87: 3 | C87: 3 | D87: 2 | E87: 4 | G87: INFRAESTRUTURA | H87: SERVIÇO | I87: 03.003.002.004 | J87: Armação aço CA-50 ø 10,0mm para infraestrutura (corte e dobra em Indústria) | K87: kg | L87: 7011.6364 | M87: 8.964145 | N87: 62853.325 | O87: Considerado vigas de fundação, duto, cisterna, lajes e pilares de arranque - 10% de perda | P87: Pendente
A88: 0 | B88: 3 | C88: 3 | D88: 2 | E88: 5 | G88: INFRAESTRUTURA | H88: SERVIÇO | I88: 03.003.002.005 | J88: Armação aço CA-50 ø 12,5mm para infraestrutura (corte e dobra em Indústria) | K88: kg | L88: 6007.8182 | M88: 8.484145 | N88: 50971.201 | O88: Considerado vigas de fundação, duto, cisterna, lajes e pilares de arranque - 10% de perda | P88: Pendente
A89: 0 | B89: 3 | C89: 3 | D89: 2 | E89: 6 | G89: INFRAESTRUTURA | H89: SERVIÇO | I89: 03.003.002.006 | J89: Armação aço CA-50 ø 16,0mm para infraestrutura (corte e dobra em Indústria) | K89: kg | L89: 1269.7273 | M89: 8.484145 | N89: 10772.55 | O89: Considerado vigas de fundação, duto, cisterna, lajes e pilares de arranque - 10% de perda | P89: Pendente
A90: 0 | B90: 3 | C90: 3 | D90: 2 | E90: 7 | G90: INFRAESTRUTURA | H90: SERVIÇO | I90: 03.003.002.007 | J90: Armação aço CA-50 ø 20,0mm para infraestrutura (corte e dobra em Indústria) | K90: kg | L90: 902 | M90: 8.484145 | N90: 7652.6988 | O90: Considerado vigas de fundação, duto, cisterna, lajes e pilares de arranque - 10% de perda | P90: Pendente
A91: 0 | B91: 3 | C91: 3 | D91: 2 | E91: 8 | G91: INFRAESTRUTURA | H91: SERVIÇO | I91: 03.003.002.008 | J91: Armação aço CA-50 ø 25,0mm para infraestrutura (corte e dobra em Indústria) | K91: kg | L91: 4680 | M91: 8.484145 | N91: 39705.799 | O91: Considerado vigas de fundação, duto, cisterna, lajes e pilares de arranque - 10% de perda | P91: Pendente
A92: 0 | B92: 3 | C92: 3 | D92: 2 | E92: 9 | G92: INFRAESTRUTURA | H92: SERVIÇO | I92: 03.003.002.009 | J92: Armação aço CA-50 ø 32,00mm para infraestrutura (corte e dobra em Indústria) | K92: kg | L92: 27316 | M92: 9.0705059 | N92: 247769.94 | O92: Considerado vigas de fundação, duto, cisterna, lajes e pilares de arranque - 10% de perda | P92: Pendente
A93: 0 | B93: 3 | C93: 3 | D93: 3 | E93: 0 | H93: SUBETAPA | I93: 03.003.003 | J93: Concreto | N93: 34717.514 | O93: 2.0727282
A94: 0 | B94: 3 | C94: 3 | D94: 3 | E94: 1 | G94: INFRAESTRUTURA | H94: SERVIÇO | I94: 03.003.003.001 | J94: Concreto Usinado bombeável 50MPa para infraestrutura- incluindo serviço de bombeamento | K94: m3 | L94: 51.04721 | M94: 680.106 | N94: 34717.514 | O94: Cotações recentes do concreto. Considerado vigas de fundação, duto, cisterna, lajes e pilares de arranque - 5% de perda, fck = 50Mpa | P94: Pendente
A95: 0 | B95: 3 | C95: 3 | D95: 4 | E95: 0 | H95: SUBETAPA | I95: 03.003.004 | J95: Mão de Obra | N95: 0 | O95: 0
A96: 0 | B96: 4 | C96: 0 | D96: 4 | E96: 0 | H96: CÉLULA CONSTRUTIVA | I96: 04 | J96: SUPRAESTRUTURA | N96: 20793271 | O96: 1241.4138
A97: 0 | B97: 4 | C97: 1 | D97: 0 | E97: 0 | H97: ETAPA | I97: 04.001 | J97: PISO SOBRE O SOLO - GERAL | N97: 19428.045 | O97: 1.1599061
A98: 0 | B98: 4 | C98: 1 | D98: 1 | E98: 0 | H98: SUBETAPA | I98: 04.001.001 | J98: Piso sobre o solo - Geral | N98: 19428.045 | O98: 1.1599061
A99: 0 | B99: 4 | C99: 1 | D99: 1 | E99: 1 | G99: SUPRAESTRUTURA | H99: SERVIÇO | I99: 04.001.001.001 | J99: Lastro de Concreto Magro, Aplicado em piso sobre solo | K99: m3 | L99: 39.229 | M99: 495.247 | N99: 19428.045 | O99: O concreto e a armadura entraram nos itens referentes ao terreo, conforme lista de materiais do projetista | P99: Pendente
A100: 0 | B100: 4 | C100: 2 | D100: 0 | E100: 1 | H100: ETAPA | I100: 04.002 | J100: FORMA | N100: 1435615 | O100: 85.710046
A101: 0 | B101: 4 | C101: 2 | D101: 1 | E101: 0 | H101: SUBETAPA | I101: 04.002.001 | J101: Forma - Térreo | N101: 529090.67 | O101: 31.588125
A102: 0 | B102: 4 | C102: 2 | D102: 1 | E102: 1 | G102: SUPRAESTRUTURA | H102: SERVIÇO | I102: 04.002.001.001 | J102: Fabricação de Fôrma para Supraestrutura, em Chapa de Madeira Compensada Resinada, E=20mm | K102: m2 | L102: 4874.3226 | M102: 108.03523 | N102: 526598.54 | O102: 8x reaproveitamento - 3 jogos | P102: Pendente
A103: 0 | B103: 4 | C103: 2 | D103: 1 | E103: 2 | G103: SUPRAESTRUTURA | H103: SERVIÇO | I103: 04.002.001.002 | J103: Montagem e Desmontagem de Fôrma de Supraestrutura | K103: m2 | L103: 626.5792 | M103: 3.9773488 | N103: 2492.124 | P103: Pendente
...

Sheet CPU
A1: Repetição | B1: Tipo | C1: Descrição | D1: Descrição | E1: Und | F1: Quantidade | G1: Custo unit. | H1: Custo Total. | I1: Quantidade | J1: Cuto Total | K1: Observgações
A2: 1 | B2: Etapa | C2: Descrição | D2: CUSTOS INDIRETOS | G2: {=IF(B2="insumo",_xlfn.XLOOKUP($D2,Insumos!$B$1:$B$996,Insumos!$D$1:$D$996),"")} | H2: 0 | I2: 0 | J2: 0
A3: 1 | B3: Subetapa | C3: Descrição | D3: INSTALAÇÕES PROVISÓRIAS | H3: 0 | I3: 0 | J3: 0
A4: 1 | B4: Serviço | C4: Central de aço | D4: Central de aço | E4: M2 | G4: {=IF(B4="insumo",_xlfn.XLOOKUP($D4,Insumos!$B$1:$B$996,Insumos!$D$1:$D$996),"")} | H4: 118.1045 | I4: 0 | J4: 0
A5: 3 | B5: Insumo | C5: Central de aço | D5: LONA PLASTICA 120 MICRAS 4X100M PRETA | E5: {=_xlfn.XLOOKUP(D5,Insumos!B:B,Insumos!C:$C)} -> M2 | F5: 1 | G5: {=IF(B5="insumo",_xlfn.XLOOKUP($D5,Insumos!$B$1:$B$996,Insumos!$D$1:$D$996),"")} -> 1.25 | H5: 1.25 | I5: 0 | J5: 0
A6: 3 | B6: Insumo | C6: Central de aço | D6: TELHA METALICA GALVANIZADA TRAPEZOIDAL 0,43MM NBR 14514 | E6: {=_xlfn.XLOOKUP(D6,Insumos!B:B,Insumos!C:$C)} -> M2 | F6: 1 | G6: {=IF(B6="insumo",_xlfn.XLOOKUP($D6,Insumos!$B$1:$B$996,Insumos!$D$1:$D$996),"")} -> 31 | H6: 31 | I6: 0 | J6: 0
A7: 9 | B7: Insumo | C7: Central de aço | D7: Concreto Usinado bombeável 20MPa Convencional | E7: {=_xlfn.XLOOKUP(D7,Insumos!B:B,Insumos!C:$C)} -> M3 | F7: 0.074 | G7: {=IF(B7="insumo",_xlfn.XLOOKUP($D7,Insumos!$B$1:$B$996,Insumos!$D$1:$D$996),"")} -> 490 | H7: 36.26 | I7: 0 | J7: 0
A8: 3 | B8: Insumo | C8: Central de aço | D8: PREGO GALVANIZADO LISO S/CABECA 17X21 NBR 6627 | E8: {=_xlfn.XLOOKUP(D8,Insumos!B:B,Insumos!C:$C)} -> KG | F8: 0.15 | G8: {=IF(B8="insumo",_xlfn.XLOOKUP($D8,Insumos!$B$1:$B$996,Insumos!$D$1:$D$996),"")} -> 10.03 | H8: 1.5045 | I8: 0 | J8: 0
A9: 3 | B9: Insumo | C9: Central de aço | D9: BLOCO CONCRETO ESTRUTURAL 03MPA 14X19X39CM NBR 6136 | E9: {=_xlfn.XLOOKUP(D9,Insumos!B:B,Insumos!C:$C)} -> UN | F9: 9 | G9: {=IF(B9="insumo",_xlfn.XLOOKUP($D9,Insumos!$B$1:$B$996,Insumos!$D$1:$D$996),"")} -> 2.95 | H9: 26.55 | I9: 0 | J9: 0
A10: 3 | B10: Insumo | C10: Central de aço | D10: ARGAMASSA ENSACADA P/ASSENTAMENTO BLOCO 04MPA NBR 13281 | E10: {=_xlfn.XLOOKUP(D10,Insumos!B:B,Insumos!C:$C)} -> KG | F10: 24 | G10: {=IF(B10="insumo",_xlfn.XLOOKUP($D10,Insumos!$B$1:$B$996,Insumos!$D$1:$D$996),"")} -> 0.46 | H10: 11.04 | I10: 0 | J10: 0
A11: 3 | B11: Insumo | C11: Central de aço | D11: SERVICO EMP. - INST. PROVISORIA - CONFECCAO BAIA P/MATERIAL | E11: {=_xlfn.XLOOKUP(D11,Insumos!B:B,Insumos!C:$C)} -> M2 | F11: 1 | G11: {=IF(B11="insumo",_xlfn.XLOOKUP($D11,Insumos!$B$1:$B$996,Insumos!$D$1:$D$996),"")} -> 10.5 | H11: 10.5 | I11: 0 | J11: 0
A12: 1 | B12: Serviço | C12: Central de fôrmas | D12: Central de fôrmas | E12: M2 | G12: {=IF(B12="insumo",_xlfn.XLOOKUP($D12,Insumos!$B$1:$B$996,Insumos!$D$1:$D$996),"")} | H12: 118.1045 | I12: 0 | J12: 0
A13: 3 | B13: Insumo | C13: Central de fôrmas | D13: LONA PLASTICA 120 MICRAS 4X100M PRETA | E13: {=_xlfn.XLOOKUP(D13,Insumos!B:B,Insumos!C:$C)} -> M2 | F13: 1 | G13: {=IF(B13="insumo",_xlfn.XLOOKUP($D13,Insumos!$B$1:$B$996,Insumos!$D$1:$D$996),"")} -> 1.25 | H13: 1.25 | I13: 0 | J13: 0
A14: 3 | B14: Insumo | C14: Central de fôrmas | D14: TELHA METALICA GALVANIZADA TRAPEZOIDAL 0,43MM NBR 14514 | E14: {=_xlfn.XLOOKUP(D14,Insumos!B:B,Insumos!C:$C)} -> M2 | F14: 1 | G14: {=IF(B14="insumo",_xlfn.XLOOKUP($D14,Insumos!$B$1:$B$996,Insumos!$D$1:$D$996),"")} -> 31 | H14: 31 | I14: 0 | J14: 0
A15: 9 | B15: Insumo | C15: Central de fôrmas | D15: Concreto Usinado bombeável 20MPa Convencional | E15: {=_xlfn.XLOOKUP(D15,Insumos!B:B,Insumos!C:$C)} -> M3 | F15: 0.074 | G15: {=IF(B15="insumo",_xlfn.XLOOKUP($D15,Insumos!$B$1:$B$996,Insumos!$D$1:$D$996),"")} -> 490 | H15: 36.26 | I15: 0 | J15: 0
A16: 3 | B16: Insumo | C16: Central de fôrmas | D16: PREGO GALVANIZADO LISO S/CABECA 17X21 NBR 6627 | E16: {=_xlfn.XLOOKUP(D16,Insumos!B:B,Insumos!C:$C)} -> KG | F16: 0.15 | G16: {=IF(B16="insumo",_xlfn.XLOOKUP($D16,Insumos!$B$1:$B$996,Insumos!$D$1:$D$996),"")} -> 10.03 | H16: 1.5045 | I16: 0 | J16: 0
A17: 3 | B17: Insumo | C17: Central de fôrmas | D17: BLOCO CONCRETO ESTRUTURAL 03MPA 14X19X39CM NBR 6136 | E17: {=_xlfn.XLOOKUP(D17,Insumos!B:B,Insumos!C:$C)} -> UN | F17: 9 | G17: {=IF(B17="insumo",_xlfn.XLOOKUP($D17,Insumos!$B$1:$B$996,Insumos!$D$1:$D$996),"")} -> 2.95 | H17: 26.55 | I17: 0 | J17: 0
A18: 3 | B18: Insumo | C18: Central de fôrmas | D18: ARGAMASSA ENSACADA P/ASSENTAMENTO BLOCO 04MPA NBR 13281 | E18: {=_xlfn.XLOOKUP(D18,Insumos!B:B,Insumos!C:$C)} -> KG | F18: 24 | G18: {=IF(B18="insumo",_xlfn.XLOOKUP($D18,Insumos!$B$1:$B$996,Insumos!$D$1:$D$996),"")} -> 0.46 | H18: 11.04 | I18: 0 | J18: 0
A19: 3 | B19: Insumo | C19: Central de fôrmas | D19: SERVICO EMP. - INST. PROVISORIA - CONFECCAO BAIA P/MATERIAL | E19: {=_xlfn.XLOOKUP(D19,Insumos!B:B,Insumos!C:$C)} -> M2 | F19: 1 | G19: {=IF(B19="insumo",_xlfn.XLOOKUP($D19,Insumos!$B$1:$B$996,Insumos!$D$1:$D$996),"")} -> 10.5 | H19: 10.5 | I19: 0 | J19: 0
A20: 1 | B20: Serviço | C20: Central de Argamassa | D20: Central de Argamassa | E20: M2 | G20: {=IF(B20="insumo",_xlfn.XLOOKUP($D20,Insumos!$B$1:$B$996,Insumos!$D$1:$D$996),"")} | H20: 118.1045 | I20: 0 | J20: 0
A21: 3 | B21: Insumo | C21: Central de Argamassa | D21: LONA PLASTICA 120 MICRAS 4X100M PRETA | E21: {=_xlfn.XLOOKUP(D21,Insumos!B:B,Insumos!C:$C)} -> M2 | F21: 1 | G21: {=IF(B21="insumo",_xlfn.XLOOKUP($D21,Insumos!$B$1:$B$996,Insumos!$D$1:$D$996),"")} -> 1.25 | H21: 1.25 | I21: 0 | J21: 0
A22: 3 | B22: Insumo | C22: Central de Argamassa | D22: TELHA METALICA GALVANIZADA TRAPEZOIDAL 0,43MM NBR 14514 | E22: {=_xlfn.XLOOKUP(D22,Insumos!B:B,Insumos!C:$C)} -> M2 | F22: 1 | G22: {=IF(B22="insumo",_xlfn.XLOOKUP($D22,Insumos!$B$1:$B$996,Insumos!$D$1:$D$996),"")} -> 31 | H22: 31 | I22: 0 | J22: 0
A23: 9 | B23: Insumo | C23: Central de Argamassa | D23: Concreto Usinado bombeável 20MPa Convencional | E23: {=_xlfn.XLOOKUP(D23,Insumos!B:B,Insumos!C:$C)} -> M3 | F23: 0.074 | G23: {=IF(B23="insumo",_xlfn.XLOOKUP($D23,Insumos!$B$1:$B$996,Insumos!$D$1:$D$996),"")} -> 490 | H23: 36.26 | I23: 0 | J23: 0
A24: 3 | B24: Insumo | C24: Central de Argamassa | D24: PREGO GALVANIZADO LISO S/CABECA 17X21 NBR 6627 | E24: {=_xlfn.XLOOKUP(D24,Insumos!B:B,Insumos!C:$C)} -> KG | F24: 0.15 | G24: {=IF(B24="insumo",_xlfn.XLOOKUP($D24,Insumos!$B$1:$B$996,Insumos!$D$1:$D$996),"")} -> 10.03 | H24: 1.5045 | I24: 0 | J24: 0
A25: 3 | B25: Insumo | C25: Central de Argamassa | D25: BLOCO CONCRETO ESTRUTURAL 03MPA 14X19X39CM NBR 6136 | E25: {=_xlfn.XLOOKUP(D25,Insumos!B:B,Insumos!C:$C)} -> UN | F25: 9 | G25: {=IF(B25="insumo",_xlfn.XLOOKUP($D25,Insumos!$B$1:$B$996,Insumos!$D$1:$D$996),"")} -> 2.95 | H25: 26.55 | I25: 0 | J25: 0
A26: 3 | B26: Insumo | C26: Central de Argamassa | D26: ARGAMASSA ENSACADA P/ASSENTAMENTO BLOCO 04MPA NBR 13281 | E26: {=_xlfn.XLOOKUP(D26,Insumos!B:B,Insumos!C:$C)} -> KG | F26: 24 | G26: {=IF(B26="insumo",_xlfn.XLOOKUP($D26,Insumos!$B$1:$B$996,Insumos!$D$1:$D$996),"")} -> 0.46 | H26: 11.04 | I26: 0 | J26: 0
A27: 3 | B27: Insumo | C27: Central de Argamassa | D27: SERVICO EMP. - INST. PROVISORIA - CONFECCAO BAIA P/MATERIAL | E27: {=_xlfn.XLOOKUP(D27,Insumos!B:B,Insumos!C:$C)} -> M2 | F27: 1 | G27: {=IF(B27="insumo",_xlfn.XLOOKUP($D27,Insumos!$B$1:$B$996,Insumos!$D$1:$D$996),"")} -> 10.5 | H27: 10.5 | I27: 0 | J27: 0
A28: 1 | B28: Serviço | C28: Armazenamento de cerâmicas* | D28: Armazenamento de cerâmicas* | E28: M2 | G28: {=IF(B28="insumo",_xlfn.XLOOKUP($D28,Insumos!$B$1:$B$996,Insumos!$D$1:$D$996),"")} | H28: 382.10489 | I28: 0 | J28: 0
A29: 11 | B29: Insumo | C29: Armazenamento de cerâmicas* | D29: MADEIRA PINUS/SIMILAR - TABUA PINUS 200X20MM NBR 11700 | E29: {=_xlfn.XLOOKUP(D29,Insumos!B:B,Insumos!C:$C)} -> M2 | F29: 0.591 | G29: {=IF(B29="insumo",_xlfn.XLOOKUP($D29,Insumos!$B$1:$B$996,Insumos!$D$1:$D$996),"")} -> 46.5 | H29: 27.4815 | I29: 0 | J29: 0
A30: 10 | B30: Insumo | C30: Armazenamento de cerâmicas* | D30: COMPENSADO MADEIRA TIPO RESINADO COLA FENOLICA 2440X1220X10MM | E30: {=_xlfn.XLOOKUP(D30,Insumos!B:B,Insumos!C:$C)} -> UN | F30: 0.404 | G30: {=IF(B30="insumo",_xlfn.XLOOKUP($D30,Insumos!$B$1:$B$996,Insumos!$D$1:$D$996),"")} -> 58.46 | H30: 23.61784 | I30: 0 | J30: 0
A31: 25 | B31: Insumo | C31: Armazenamento de cerâmicas* | D31: MADEIRA PINUS/SIMILAR - PONTALETE 75X75MM NBR 11700/15696 | E31: {=_xlfn.XLOOKUP(D31,Insumos!B:B,Insumos!C:$C)} -> M | F31: 4.39 | G31: {=IF(B31="insumo",_xlfn.XLOOKUP($D31,Insumos!$B$1:$B$996,Insumos!$D$1:$D$996),"")} -> 7 | H31: 30.73 | I31: 0 | J31: 0
A32: 11 | B32: Insumo | C32: Armazenamento de cerâmicas* | D32: MADEIRA PINUS/SIMILAR - SARRAFO PINUS 50X20MM NBR 11700/15696 | E32: {=_xlfn.XLOOKUP(D32,Insumos!B:B,Insumos!C:$C)} -> M2 | F32: 0.15 | G32: {=IF(B32="insumo",_xlfn.XLOOKUP($D32,Insumos!$B$1:$B$996,Insumos!$D$1:$D$996),"")} -> 46.5 | H32: 6.975 | I32: 0 | J32: 0
A33: 10 | B33: Insumo | C33: Armazenamento de cerâmicas* | D33: MADEIRA PINUS/SIMILAR - SARRAFO PINUS 50X10MM NBR 11700 | E33: {=_xlfn.XLOOKUP(D33,Insumos!B:B,Insumos!C:$C)} -> M | F33: 1 | G33: {=IF(B33="insumo",_xlfn.XLOOKUP($D33,Insumos!$B$1:$B$996,Insumos!$D$1:$D$996),"")} -> 7.39 | H33: 7.39 | I33: 0 | J33: 0
A34: 40 | B34: Insumo | C34: Armazenamento de cerâmicas* | D34: PREGO DE ACO POLIDO COM CABECA 17 X 21 (2 X 11) | E34: {=_xlfn.XLOOKUP(D34,Insumos!B:B,Insumos!C:$C)} -> KG | F34: 1 | G34: {=IF(B34="insumo",_xlfn.XLOOKUP($D34,Insumos!$B$1:$B$996,Insumos!$D$1:$D$996),"")} -> 18.13 | H34: 18.13 | I34: 0 | J34: 0
A35: 10 | B35: Insumo | C35: Armazenamento de cerâmicas* | D35: EXTINTOR INCENDIO PO QUIMICO 06KG CLASSE ABC (COMPLETO) NBR 15808 | E35: {=_xlfn.XLOOKUP(D35,Insumos!B:B,Insumos!C:$C)} -> UN | F35: 0.015 | G35: {=IF(B35="insumo",_xlfn.XLOOKUP($D35,Insumos!$B$1:$B$996,Insumos!$D$1:$D$996),"")} -> 185.37 | H35: 2.78055 | I35: 0 | J35: 0
A36: 10 | B36: Insumo | C36: Armazenamento de cerâmicas* | D36: MATERIAL PARA INSTALAÇÃO ELÉTRICA | E36: {=_xlfn.XLOOKUP(D36,Insumos!B:B,Insumos!C:$C)} -> VB | F36: 1 | G36: {=IF(B36="insumo",_xlfn.XLOOKUP($D36,Insumos!$B$1:$B$996,Insumos!$D$1:$D$996),"")} -> 215 | H36: 215 | I36: 0 | J36: 0
A37: 10 | B37: Insumo | C37: Armazenamento de cerâmicas* | D37: SERVICO INSTALAÇÃO BARRACAO ALMOXARIFADO | E37: {=_xlfn.XLOOKUP(D37,Insumos!B:B,Insumos!C:$C)} -> M2 | F37: 1 | G37: {=IF(B37="insumo",_xlfn.XLOOKUP($D37,Insumos!$B$1:$B$996,Insumos!$D$1:$D$996),"")} -> 50 | H37: 50 | I37: 0 | J37: 0
A38: 1 | B38: Serviço | C38: Armazenamento de placas degesso* | D38: Armazenamento de placas degesso* | E38: M2 | G38: {=IF(B38="insumo",_xlfn.XLOOKUP($D38,Insumos!$B$1:$B$996,Insumos!$D$1:$D$996),"")} | H38: 382.10489 | I38: 0 | J38: 0
A39: 11 | B39: Insumo | C39: Armazenamento de placas degesso* | D39: MADEIRA PINUS/SIMILAR - TABUA PINUS 200X20MM NBR 11700 | E39: {=_xlfn.XLOOKUP(D39,Insumos!B:B,Insumos!C:$C)} -> M2 | F39: 0.591 | G39: {=IF(B39="insumo",_xlfn.XLOOKUP($D39,Insumos!$B$1:$B$996,Insumos!$D$1:$D$996),"")} -> 46.5 | H39: 27.4815 | I39: 0 | J39: 0
A40: 10 | B40: Insumo | C40: Armazenamento de placas degesso* | D40: COMPENSADO MADEIRA TIPO RESINADO COLA FENOLICA 2440X1220X10MM | E40: {=_xlfn.XLOOKUP(D40,Insumos!B:B,Insumos!C:$C)} -> UN | F40: 0.404 | G40: {=IF(B40="insumo",_xlfn.XLOOKUP($D40,Insumos!$B$1:$B$996,Insumos!$D$1:$D$996),"")} -> 58.46 | H40: 23.61784 | I40: 0 | J40: 0
A41: 25 | B41: Insumo | C41: Armazenamento de placas degesso* | D41: MADEIRA PINUS/SIMILAR - PONTALETE 75X75MM NBR 11700/15696 | E41: {=_xlfn.XLOOKUP(D41,Insumos!B:B,Insumos!C:$C)} -> M | F41: 4.39 | G41: {=IF(B41="insumo",_xlfn.XLOOKUP($D41,Insumos!$B$1:$B$996,Insumos!$D$1:$D$996),"")} -> 7 | H41: 30.73 | I41: 0 | J41: 0
A42: 11 | B42: Insumo | C42: Armazenamento de placas degesso* | D42: MADEIRA PINUS/SIMILAR - SARRAFO PINUS 50X20MM NBR 11700/15696 | E42: {=_xlfn.XLOOKUP(D42,Insumos!B:B,Insumos!C:$C)} -> M2 | F42: 0.15 | G42: {=IF(B42="insumo",_xlfn.XLOOKUP($D42,Insumos!$B$1:$B$996,Insumos!$D$1:$D$996),"")} -> 46.5 | H42: 6.975 | I42: 0 | J42: 0
A43: 10 | B43: Insumo | C43: Armazenamento de placas degesso* | D43: MADEIRA PINUS/SIMILAR - SARRAFO PINUS 50X10MM NBR 11700 | E43: {=_xlfn.XLOOKUP(D43,Insumos!B:B,Insumos!C:$C)} -> M | F43: 1 | G43: {=IF(B43="insumo",_xlfn.XLOOKUP($D43,Insumos!$B$1:$B$996,Insumos!$D$1:$D$996),"")} -> 7.39 | H43: 7.39 | I43: 0 | J43: 0
A44: 40 | B44: Insumo | C44: Armazenamento de placas degesso* | D44: PREGO DE ACO POLIDO COM CABECA 17 X 21 (2 X 11) | E44: {=_xlfn.XLOOKUP(D44,Insumos!B:B,Insumos!C:$C)} -> KG | F44: 1 | G44: {=IF(B44="insumo",_xlfn.XLOOKUP($D44,Insumos!$B$1:$B$996,Insumos!$D$1:$D$996),"")} -> 18.13 | H44: 18.13 | I44: 0 | J44: 0
A45: 10 | B45: Insumo | C45: Armazenamento de placas degesso* | D45: EXTINTOR INCENDIO PO QUIMICO 06KG CLASSE ABC (COMPLETO) NBR 15808 | E45: {=_xlfn.XLOOKUP(D45,Insumos!B:B,Insumos!C:$C)} -> UN | F45: 0.015 | G45: {=IF(B45="insumo",_xlfn.XLOOKUP($D45,Insumos!$B$1:$B$996,Insumos!$D$1:$D$996),"")} -> 185.37 | H45: 2.78055 | I45: 0 | J45: 0
A46: 10 | B46: Insumo | C46: Armazenamento de placas degesso* | D46: MATERIAL PARA INSTALAÇÃO ELÉTRICA | E46: {=_xlfn.XLOOKUP(D46,Insumos!B:B,Insumos!C:$C)} -> VB | F46: 1 | G46: {=IF(B46="insumo",_xlfn.XLOOKUP($D46,Insumos!$B$1:$B$996,Insumos!$D$1:$D$996),"")} -> 215 | H46: 215 | I46: 0 | J46: 0
A47: 10 | B47: Insumo | C47: Armazenamento de placas degesso* | D47: SERVICO INSTALAÇÃO BARRACAO ALMOXARIFADO | E47: {=_xlfn.XLOOKUP(D47,Insumos!B:B,Insumos!C:$C)} -> M2 | F47: 1 | G47: {=IF(B47="insumo",_xlfn.XLOOKUP($D47,Insumos!$B$1:$B$996,Insumos!$D$1:$D$996),"")} -> 50 | H47: 50 | I47: 0 | J47: 0
A48: 1 | B48: Serviço | C48: Armazenamento de blocos* | D48: Armazenamento de blocos* | E48: M2 | G48: {=IF(B48="insumo",_xlfn.XLOOKUP($D48,Insumos!$B$1:$B$996,Insumos!$D$1:$D$996),"")} | H48: 382.10489 | I48: 0 | J48: 0
A49: 11 | B49: Insumo | C49: Armazenamento de blocos* | D49: MADEIRA PINUS/SIMILAR - TABUA PINUS 200X20MM NBR 11700 | E49: {=_xlfn.XLOOKUP(D49,Insumos!B:B,Insumos!C:$C)} -> M2 | F49: 0.591 | G49: {=IF(B49="insumo",_xlfn.XLOOKUP($D49,Insumos!$B$1:$B$996,Insumos!$D$1:$D$996),"")} -> 46.5 | H49: 27.4815 | I49: 0 | J49: 0
A50: 10 | B50: Insumo | C50: Armazenamento de blocos* | D50: COMPENSADO MADEIRA TIPO RESINADO COLA FENOLICA 2440X1220X10MM | E50: {=_xlfn.XLOOKUP(D50,Insumos!B:B,Insumos!C:$C)} -> UN | F50: 0.404 | G50: {=IF(B50="insumo",_xlfn.XLOOKUP($D50,Insumos!$B$1:$B$996,Insumos!$D$1:$D$996),"")} -> 58.46 | H50: 23.61784 | I50: 0 | J50: 0
A51: 25 | B51: Insumo | C51: Armazenamento de blocos* | D51: MADEIRA PINUS/SIMILAR - PONTALETE 75X75MM NBR 11700/15696 | E51: {=_xlfn.XLOOKUP(D51,Insumos!B:B,Insumos!C:$C)} -> M | F51: 4.39 | G51: {=IF(B51="insumo",_xlfn.XLOOKUP($D51,Insumos!$B$1:$B$996,Insumos!$D$1:$D$996),"")} -> 7 | H51: 30.73 | I51: 0 | J51: 0
A52: 11 | B52: Insumo | C52: Armazenamento de blocos* | D52: MADEIRA PINUS/SIMILAR - SARRAFO PINUS 50X20MM NBR 11700/15696 | E52: {=_xlfn.XLOOKUP(D52,Insumos!B:B,Insumos!C:$C)} -> M2 | F52: 0.15 | G52: {=IF(B52="insumo",_xlfn.XLOOKUP($D52,Insumos!$B$1:$B$996,Insumos!$D$1:$D$996),"")} -> 46.5 | H52: 6.975 | I52: 0 | J52: 0
A53: 10 | B53: Insumo | C53: Armazenamento de blocos* | D53: MADEIRA PINUS/SIMILAR - SARRAFO PINUS 50X10MM NBR 11700 | E53: {=_xlfn.XLOOKUP(D53,Insumos!B:B,Insumos!C:$C)} -> M | F53: 1 | G53: {=IF(B53="insumo",_xlfn.XLOOKUP($D53,Insumos!$B$1:$B$996,Insumos!$D$1:$D$996),"")} -> 7.39 | H53: 7.39 | I53: 0 | J53: 0
A54: 40 | B54: Insumo | C54: Armazenamento de blocos* | D54: PREGO DE ACO POLIDO COM CABECA 17 X 21 (2 X 11) | E54: {=_xlfn.XLOOKUP(D54,Insumos!B:B,Insumos!C:$C)} -> KG | F54: 1 | G54: {=IF(B54="insumo",_xlfn.XLOOKUP($D54,Insumos!$B$1:$B$996,Insumos!$D$1:$D$996),"")} -> 18.13 | H54: 18.13 | I54: 0 | J54: 0
A55: 10 | B55: Insumo | C55: Armazenamento de blocos* | D55: EXTINTOR INCENDIO PO QUIMICO 06KG CLASSE ABC (COMPLETO) NBR 15808 | E55: {=_xlfn.XLOOKUP(D55,Insumos!B:B,Insumos!C:$C)} -> UN | F55: 0.015 | G55: {=IF(B55="insumo",_xlfn.XLOOKUP($D55,Insumos!$B$1:$B$996,Insumos!$D$1:$D$996),"")} -> 185.37 | H55: 2.78055 | I55: 0 | J55: 0
A56: 10 | B56: Insumo | C56: Armazenamento de blocos* | D56: MATERIAL PARA INSTALAÇÃO ELÉTRICA | E56: {=_xlfn.XLOOKUP(D56,Insumos!B:B,Insumos!C:$C)} -> VB | F56: 1 | G56: {=IF(B56="insumo",_xlfn.XLOOKUP($D56,Insumos!$B$1:$B$996,Insumos!$D$1:$D$996),"")} -> 215 | H56: 215 | I56: 0 | J56: 0
A57: 10 | B57: Insumo | C57: Armazenamento de blocos* | D57: SERVICO INSTALAÇÃO BARRACAO ALMOXARIFADO | E57: {=_xlfn.XLOOKUP(D57,Insumos!B:B,Insumos!C:$C)} -> M2 | F57: 1 | G57: {=IF(B57="insumo",_xlfn.XLOOKUP($D57,Insumos!$B$1:$B$996,Insumos!$D$1:$D$996),"")} -> 50 | H57: 50 | I57: 0 | J57: 0
A58: 1 | B58: Serviço | C58: Armazenamento de contramarcos* | D58: Armazenamento de contramarcos* | E58: M2 | G58: {=IF(B58="insumo",_xlfn.XLOOKUP($D58,Insumos!$B$1:$B$996,Insumos!$D$1:$D$996),"")} | H58: 382.10489 | I58: 0 | J58: 0
A59: 11 | B59: Insumo | C59: Armazenamento de contramarcos* | D59: MADEIRA PINUS/SIMILAR - TABUA PINUS 200X20MM NBR 11700 | E59: {=_xlfn.XLOOKUP(D59,Insumos!B:B,Insumos!C:$C)} -> M2 | F59: 0.591 | G59: {=IF(B59="insumo",_xlfn.XLOOKUP($D59,Insumos!$B$1:$B$996,Insumos!$D$1:$D$996),"")} -> 46.5 | H59: 27.4815 | I59: 0 | J59: 0
A60: 10 | B60: Insumo | C60: Armazenamento de contramarcos* | D60: COMPENSADO MADEIRA TIPO RESINADO COLA FENOLICA 2440X1220X10MM | E60: {=_xlfn.XLOOKUP(D60,Insumos!B:B,Insumos!C:$C)} -> UN | F60: 0.404 | G60: {=IF(B60="insumo",_xlfn.XLOOKUP($D60,Insumos!$B$1:$B$996,Insumos!$D$1:$D$996),"")} -> 58.46 | H60: 23.61784 | I60: 0 | J60: 0
A61: 25 | B61: Insumo | C61: Armazenamento de contramarcos* | D61: MADEIRA PINUS/SIMILAR - PONTALETE 75X75MM NBR 11700/15696 | E61: {=_xlfn.XLOOKUP(D61,Insumos!B:B,Insumos!C:$C)} -> M | F61: 4.39 | G61: {=IF(B61="insumo",_xlfn.XLOOKUP($D61,Insumos!$B$1:$B$996,Insumos!$D$1:$D$996),"")} -> 7 | H61: 30.73 | I61: 0 | J61: 0
A62: 11 | B62: Insumo | C62: Armazenamento de contramarcos* | D62: MADEIRA PINUS/SIMILAR - SARRAFO PINUS 50X20MM NBR 11700/15696 | E62: {=_xlfn.XLOOKUP(D62,Insumos!B:B,Insumos!C:$C)} -> M2 | F62: 0.15 | G62: {=IF(B62="insumo",_xlfn.XLOOKUP($D62,Insumos!$B$1:$B$996,Insumos!$D$1:$D$996),"")} -> 46.5 | H62: 6.975 | I62: 0 | J62: 0
A63: 10 | B63: Insumo | C63: Armazenamento de contramarcos* | D63: MADEIRA PINUS/SIMILAR - SARRAFO PINUS 50X10MM NBR 11700 | E63: {=_xlfn.XLOOKUP(D63,Insumos!B:B,Insumos!C:$C)} -> M | F63: 1 | G63: {=IF(B63="insumo",_xlfn.XLOOKUP($D63,Insumos!$B$1:$B$996,Insumos!$D$1:$D$996),"")} -> 7.39 | H63: 7.39 | I63: 0 | J63: 0
A64: 40 | B64: Insumo | C64: Armazenamento de contramarcos* | D64: PREGO DE ACO POLIDO COM CABECA 17 X 21 (2 X 11) | E64: {=_xlfn.XLOOKUP(D64,Insumos!B:B,Insumos!C:$C)} -> KG | F64: 1 | G64: {=IF(B64="insumo",_xlfn.XLOOKUP($D64,Insumos!$B$1:$B$996,Insumos!$D$1:$D$996),"")} -> 18.13 | H64: 18.13 | I64: 0 | J64: 0
A65: 10 | B65: Insumo | C65: Armazenamento de contramarcos* | D65: EXTINTOR INCENDIO PO QUIMICO 06KG CLASSE ABC (COMPLETO) NBR 15808 | E65: {=_xlfn.XLOOKUP(D65,Insumos!B:B,Insumos!C:$C)} -> UN | F65: 0.015 | G65: {=IF(B65="insumo",_xlfn.XLOOKUP($D65,Insumos!$B$1:$B$996,Insumos!$D$1:$D$996),"")} -> 185.37 | H65: 2.78055 | I65: 0 | J65: 0
A66: 10 | B66: Insumo | C66: Armazenamento de contramarcos* | D66: MATERIAL PARA INSTALAÇÃO ELÉTRICA | E66: {=_xlfn.XLOOKUP(D66,Insumos!B:B,Insumos!C:$C)} -> VB | F66: 1 | G66: {=IF(B66="insumo",_xlfn.XLOOKUP($D66,Insumos!$B$1:$B$996,Insumos!$D$1:$D$996),"")} -> 215 | H66: 215 | I66: 0 | J66: 0
A67: 10 | B67: Insumo | C67: Armazenamento de contramarcos* | D67: SERVICO INSTALAÇÃO BARRACAO ALMOXARIFADO | E67: {=_xlfn.XLOOKUP(D67,Insumos!B:B,Insumos!C:$C)} -> M2 | F67: 1 | G67: {=IF(B67="insumo",_xlfn.XLOOKUP($D67,Insumos!$B$1:$B$996,Insumos!$D$1:$D$996),"")} -> 50 | H67: 50 | I67: 0 | J67: 0
A68: 1 | B68: Serviço | C68: Armazenamento de portas e rodapés* | D68: Armazenamento de portas e rodapés* | E68: M2 | G68: {=IF(B68="insumo",_xlfn.XLOOKUP($D68,Insumos!$B$1:$B$996,Insumos!$D$1:$D$996),"")} | H68: 382.10489 | I68: 0 | J68: 0
A69: 11 | B69: Insumo | C69: Armazenamento de portas e rodapés* | D69: MADEIRA PINUS/SIMILAR - TABUA PINUS 200X20MM NBR 11700 | E69: {=_xlfn.XLOOKUP(D69,Insumos!B:B,Insumos!C:$C)} -> M2 | F69: 0.591 | G69: {=IF(B69="insumo",_xlfn.XLOOKUP($D69,Insumos!$B$1:$B$996,Insumos!$D$1:$D$996),"")} -> 46.5 | H69: 27.4815 | I69: 0 | J69: 0
A70: 10 | B70: Insumo | C70: Armazenamento de portas e rodapés* | D70: COMPENSADO MADEIRA TIPO RESINADO COLA FENOLICA 2440X1220X10MM | E70: {=_xlfn.XLOOKUP(D70,Insumos!B:B,Insumos!C:$C)} -> UN | F70: 0.404 | G70: {=IF(B70="insumo",_xlfn.XLOOKUP($D70,Insumos!$B$1:$B$996,Insumos!$D$1:$D$996),"")} -> 58.46 | H70: 23.61784 | I70: 0 | J70: 0
A71: 25 | B71: Insumo | C71: Armazenamento de portas e rodapés* | D71: MADEIRA PINUS/SIMILAR - PONTALETE 75X75MM NBR 11700/15696 | E71: {=_xlfn.XLOOKUP(D71,Insumos!B:B,Insumos!C:$C)} -> M | F71: 4.39 | G71: {=IF(B71="insumo",_xlfn.XLOOKUP($D71,Insumos!$B$1:$B$996,Insumos!$D$1:$D$996),"")} -> 7 | H71: 30.73 | I71: 0 | J71: 0
A72: 11 | B72: Insumo | C72: Armazenamento de portas e rodapés* | D72: MADEIRA PINUS/SIMILAR - SARRAFO PINUS 50X20MM NBR 11700/15696 | E72: {=_xlfn.XLOOKUP(D72,Insumos!B:B,Insumos!C:$C)} -> M2 | F72: 0.15 | G72: {=IF(B72="insumo",_xlfn.XLOOKUP($D72,Insumos!$B$1:$B$996,Insumos!$D$1:$D$996),"")} -> 46.5 | H72: 6.975 | I72: 0 | J72: 0
A73: 10 | B73: Insumo | C73: Armazenamento de portas e rodapés* | D73: MADEIRA PINUS/SIMILAR - SARRAFO PINUS 50X10MM NBR 11700 | E73: {=_xlfn.XLOOKUP(D73,Insumos!B:B,Insumos!C:$C)} -> M | F73: 1 | G73: {=IF(B73="insumo",_xlfn.XLOOKUP($D73,Insumos!$B$1:$B$996,Insumos!$D$1:$D$996),"")} -> 7.39 | H73: 7.39 | I73: 0 | J73: 0
A74: 40 | B74: Insumo | C74: Armazenamento de portas e rodapés* | D74: PREGO DE ACO POLIDO COM CABECA 17 X 21 (2 X 11) | E74: {=_xlfn.XLOOKUP(D74,Insumos!B:B,Insumos!C:$C)} -> KG | F74: 1 | G74: {=IF(B74="insumo",_xlfn.XLOOKUP($D74,Insumos!$B$1:$B$996,Insumos!$D$1:$D$996),"")} -> 18.13 | H74: 18.13 | I74: 0 | J74: 0
A75: 10 | B75: Insumo | C75: Armazenamento de portas e rodapés* | D75: EXTINTOR INCENDIO PO QUIMICO 06KG CLASSE ABC (COMPLETO) NBR 15808 | E75: {=_xlfn.XLOOKUP(D75,Insumos!B:B,Insumos!C:$C)} -> UN | F75: 0.015 | G75: {=IF(B75="insumo",_xlfn.XLOOKUP($D75,Insumos!$B$1:$B$996,Insumos!$D$1:$D$996),"")} -> 185.37 | H75: 2.78055 | I75: 0 | J75: 0
A76: 10 | B76: Insumo | C76: Armazenamento de portas e rodapés* | D76: MATERIAL PARA INSTALAÇÃO ELÉTRICA | E76: {=_xlfn.XLOOKUP(D76,Insumos!B:B,Insumos!C:$C)} -> VB | F76: 1 | G76: {=IF(B76="insumo",_xlfn.XLOOKUP($D76,Insumos!$B$1:$B$996,Insumos!$D$1:$D$996),"")} -> 215 | H76: 215 | I76: 0 | J76: 0
A77: 10 | B77: Insumo | C77: Armazenamento de portas e rodapés* | D77: SERVICO INSTALAÇÃO BARRACAO ALMOXARIFADO | E77: {=_xlfn.XLOOKUP(D77,Insumos!B:B,Insumos!C:$C)} -> M2 | F77: 1 | G77: {=IF(B77="insumo",_xlfn.XLOOKUP($D77,Insumos!$B$1:$B$996,Insumos!$D$1:$D$996),"")} -> 50 | H77: 50 | I77: 0 | J77: 0
A78: 1 | B78: Serviço | C78: Armazenamento de esquadrias* | D78: Armazenamento de esquadrias* | E78: M2 | G78: {=IF(B78="insumo",_xlfn.XLOOKUP($D78,Insumos!$B$1:$B$996,Insumos!$D$1:$D$996),"")} | H78: 382.10489 | I78: 0 | J78: 0
A79: 11 | B79: Insumo | C79: Armazenamento de esquadrias* | D79: MADEIRA PINUS/SIMILAR - TABUA PINUS 200X20MM NBR 11700 | E79: {=_xlfn.XLOOKUP(D79,Insumos!B:B,Insumos!C:$C)} -> M2 | F79: 0.591 | G79: {=IF(B79="insumo",_xlfn.XLOOKUP($D79,Insumos!$B$1:$B$996,Insumos!$D$1:$D$996),"")} -> 46.5 | H79: 27.4815 | I79: 0 | J79: 0
A80: 10 | B80: Insumo | C80: Armazenamento de esquadrias* | D80: COMPENSADO MADEIRA TIPO RESINADO COLA FENOLICA 2440X1220X10MM | E80: {=_xlfn.XLOOKUP(D80,Insumos!B:B,Insumos!C:$C)} -> UN | F80: 0.404 | G80: {=IF(B80="insumo",_xlfn.XLOOKUP($D80,Insumos!$B$1:$B$996,Insumos!$D$1:$D$996),"")} -> 58.46 | H80: 23.61784 | I80: 0 | J80: 0
A81: 25 | B81: Insumo | C81: Armazenamento de esquadrias* | D81: MADEIRA PINUS/SIMILAR - PONTALETE 75X75MM NBR 11700/15696 | E81: {=_xlfn.XLOOKUP(D81,Insumos!B:B,Insumos!C:$C)} -> M | F81: 4.39 | G81: {=IF(B81="insumo",_xlfn.XLOOKUP($D81,Insumos!$B$1:$B$996,Insumos!$D$1:$D$996),"")} -> 7 | H81: 30.73 | I81: 0 | J81: 0
A82: 11 | B82: Insumo | C82: Armazenamento de esquadrias* | D82: MADEIRA PINUS/SIMILAR - SARRAFO PINUS 50X20MM NBR 11700/15696 | E82: {=_xlfn.XLOOKUP(D82,Insumos!B:B,Insumos!C:$C)} -> M2 | F82: 0.15 | G82: {=IF(B82="insumo",_xlfn.XLOOKUP($D82,Insumos!$B$1:$B$996,Insumos!$D$1:$D$996),"")} -> 46.5 | H82: 6.975 | I82: 0 | J82: 0
A83: 10 | B83: Insumo | C83: Armazenamento de esquadrias* | D83: MADEIRA PINUS/SIMILAR - SARRAFO PINUS 50X10MM NBR 11700 | E83: {=_xlfn.XLOOKUP(D83,Insumos!B:B,Insumos!C:$C)} -> M | F83: 1 | G83: {=IF(B83="insumo",_xlfn.XLOOKUP($D83,Insumos!$B$1:$B$996,Insumos!$D$1:$D$996),"")} -> 7.39 | H83: 7.39 | I83: 0 | J83: 0
A84: 40 | B84: Insumo | C84: Armazenamento de esquadrias* | D84: PREGO DE ACO POLIDO COM CABECA 17 X 21 (2 X 11) | E84: {=_xlfn.XLOOKUP(D84,Insumos!B:B,Insumos!C:$C)} -> KG | F84: 1 | G84: {=IF(B84="insumo",_xlfn.XLOOKUP($D84,Insumos!$B$1:$B$996,Insumos!$D$1:$D$996),"")} -> 18.13 | H84: 18.13 | I84: 0 | J84: 0
A85: 10 | B85: Insumo | C85: Armazenamento de esquadrias* | D85: EXTINTOR INCENDIO PO QUIMICO 06KG CLASSE ABC (COMPLETO) NBR 15808 | E85: {=_xlfn.XLOOKUP(D85,Insumos!B:B,Insumos!C:$C)} -> UN | F85: 0.015 | G85: {=IF(B85="insumo",_xlfn.XLOOKUP($D85,Insumos!$B$1:$B$996,Insumos!$D$1:$D$996),"")} -> 185.37 | H85: 2.78055 | I85: 0 | J85: 0
A86: 10 | B86: Insumo | C86: Armazenamento de esquadrias* | D86: MATERIAL PARA INSTALAÇÃO ELÉTRICA | E86: {=_xlfn.XLOOKUP(D86,Insumos!B:B,Insumos!C:$C)} -> VB | F86: 1 | G86: {=IF(B86="insumo",_xlfn.XLOOKUP($D86,Insumos!$B$1:$B$996,Insumos!$D$1:$D$996),"")} -> 215 | H86: 215 | I86: 0 | J86: 0
A87: 10 | B87: Insumo | C87: Armazenamento de esquadrias* | D87: SERVICO INSTALAÇÃO BARRACAO ALMOXARIFADO | E87: {=_xlfn.XLOOKUP(D87,Insumos!B:B,Insumos!C:$C)} -> M2 | F87: 1 | G87: {=IF(B87="insumo",_xlfn.XLOOKUP($D87,Insumos!$B$1:$B$996,Insumos!$D$1:$D$996),"")} -> 50 | H87: 50 | I87: 0 | J87: 0
A88: 1 | B88: Serviço | C88: Armazenamento de instalações complementares* | D88: Armazenamento de instalações complementares* | E88: M2 | G88: {=IF(B88="insumo",_xlfn.XLOOKUP($D88,Insumos!$B$1:$B$996,Insumos!$D$1:$D$996),"")} | H88: 382.10489 | I88: 0 | J88: 0
A89: 11 | B89: Insumo | C89: Armazenamento de instalações complementares* | D89: MADEIRA PINUS/SIMILAR - TABUA PINUS 200X20MM NBR 11700 | E89: {=_xlfn.XLOOKUP(D89,Insumos!B:B,Insumos!C:$C)} -> M2 | F89: 0.591 | G89: {=IF(B89="insumo",_xlfn.XLOOKUP($D89,Insumos!$B$1:$B$996,Insumos!$D$1:$D$996),"")} -> 46.5 | H89: 27.4815 | I89: 0 | J89: 0
A90: 10 | B90: Insumo | C90: Armazenamento de instalações complementares* | D90: COMPENSADO MADEIRA TIPO RESINADO COLA FENOLICA 2440X1220X10MM | E90: {=_xlfn.XLOOKUP(D90,Insumos!B:B,Insumos!C:$C)} -> UN | F90: 0.404 | G90: {=IF(B90="insumo",_xlfn.XLOOKUP($D90,Insumos!$B$1:$B$996,Insumos!$D$1:$D$996),"")} -> 58.46 | H90: 23.61784 | I90: 0 | J90: 0
A91: 25 | B91: Insumo | C91: Armazenamento de instalações complementares* | D91: MADEIRA PINUS/SIMILAR - PONTALETE 75X75MM NBR 11700/15696 | E91: {=_xlfn.XLOOKUP(D91,Insumos!B:B,Insumos!C:$C)} -> M | F91: 4.39 | G91: {=IF(B91="insumo",_xlfn.XLOOKUP($D91,Insumos!$B$1:$B$996,Insumos!$D$1:$D$996),"")} -> 7 | H91: 30.73 | I91: 0 | J91: 0
A92: 11 | B92: Insumo | C92: Armazenamento de instalações complementares* | D92: MADEIRA PINUS/SIMILAR - SARRAFO PINUS 50X20MM NBR 11700/15696 | E92: {=_xlfn.XLOOKUP(D92,Insumos!B:B,Insumos!C:$C)} -> M2 | F92: 0.15 | G92: {=IF(B92="insumo",_xlfn.XLOOKUP($D92,Insumos!$B$1:$B$996,Insumos!$D$1:$D$996),"")} -> 46.5 | H92: 6.975 | I92: 0 | J92: 0
A93: 10 | B93: Insumo | C93: Armazenamento de instalações complementares* | D93: MADEIRA PINUS/SIMILAR - SARRAFO PINUS 50X10MM NBR 11700 | E93: {=_xlfn.XLOOKUP(D93,Insumos!B:B,Insumos!C:$C)} -> M | F93: 1 | G93: {=IF(B93="insumo",_xlfn.XLOOKUP($D93,Insumos!$B$1:$B$996,Insumos!$D$1:$D$996),"")} -> 7.39 | H93: 7.39 | I93: 0 | J93: 0
A94: 40 | B94: Insumo | C94: Armazenamento de instalações complementares* | D94: PREGO DE ACO POLIDO COM CABECA 17 X 21 (2 X 11) | E94: {=_xlfn.XLOOKUP(D94,Insumos!B:B,Insumos!C:$C)} -> KG | F94: 1 | G94: {=IF(B94="insumo",_xlfn.XLOOKUP($D94,Insumos!$B$1:$B$996,Insumos!$D$1:$D$996),"")} -> 18.13 | H94: 18.13 | I94: 0 | J94: 0
A95: 10 | B95: Insumo | C95: Armazenamento de instalações complementares* | D95: EXTINTOR INCENDIO PO QUIMICO 06KG CLASSE ABC (COMPLETO) NBR 15808 | E95: {=_xlfn.XLOOKUP(D95,Insumos!B:B,Insumos!C:$C)} -> UN | F95: 0.015 | G95: {=IF(B95="insumo",_xlfn.XLOOKUP($D95,Insumos!$B$1:$B$996,Insumos!$D$1:$D$996),"")} -> 185.37 | H95: 2.78055 | I95: 0 | J95: 0
A96: 10 | B96: Insumo | C96: Armazenamento de instalações complementares* | D96: MATERIAL PARA INSTALAÇÃO ELÉTRICA | E96: {=_xlfn.XLOOKUP(D96,Insumos!B:B,Insumos!C:$C)} -> VB | F96: 1 | G96: {=IF(B96="insumo",_xlfn.XLOOKUP($D96,Insumos!$B$1:$B$996,Insumos!$D$1:$D$996),"")} -> 215 | H96: 215 | I96: 0 | J96: 0
A97: 10 | B97: Insumo | C97: Armazenamento de instalações complementares* | D97: SERVICO INSTALAÇÃO BARRACAO ALMOXARIFADO | E97: {=_xlfn.XLOOKUP(D97,Insumos!B:B,Insumos!C:$C)} -> M2 | F97: 1 | G97: {=IF(B97="insumo",_xlfn.XLOOKUP($D97,Insumos!$B$1:$B$996,Insumos!$D$1:$D$996),"")} -> 50 | H97: 50 | I97: 0 | J97: 0
A98: 1 | B98: Serviço | C98: Armazenamento para estoque geral* | D98: Armazenamento para estoque geral* | E98: M2 | G98: {=IF(B98="insumo",_xlfn.XLOOKUP($D98,Insumos!$B$1:$B$996,Insumos!$D$1:$D$996),"")} | H98: 382.10489 | I98: 0 | J98: 0
A99: 11 | B99: Insumo | C99: Armazenamento para estoque geral* | D99: MADEIRA PINUS/SIMILAR - TABUA PINUS 200X20MM NBR 11700 | E99: {=_xlfn.XLOOKUP(D99,Insumos!B:B,Insumos!C:$C)} -> M2 | F99: 0.591 | G99: {=IF(B99="insumo",_xlfn.XLOOKUP($D99,Insumos!$B$1:$B$996,Insumos!$D$1:$D$996),"")} -> 46.5 | H99: 27.4815 | I99: 0 | J99: 0
A100: 10 | B100: Insumo | C100: Armazenamento para estoque geral* | D100: COMPENSADO MADEIRA TIPO RESINADO COLA FENOLICA 2440X1220X10MM | E100: {=_xlfn.XLOOKUP(D100,Insumos!B:B,Insumos!C:$C)} -> UN | F100: 0.404 | G100: {=IF(B100="insumo",_xlfn.XLOOKUP($D100,Insumos!$B$1:$B$996,Insumos!$D$1:$D$996),"")} -> 58.46 | H100: 23.61784 | I100: 0 | J100: 0
...

Sheet Insumos
A1: Repetição | B1: Descrição | C1: Und | D1: 1 | E1: Custo Unitário | F1: Grupo insumo | G1: Sub Grupo | H1: Observações | I1: Grupo Sienge
A2: =COUNTIFS($B$2:$B$996,B2) -> 1 | B2: Arame Galvanizado | C2: KG | D2: =E2*$D$1 -> 13.69 | E2: 13.69 | F2: Aço | G2: Arame | I2: Armadura
A3: =COUNTIFS($B$2:$B$996,B3) -> 1 | B3: Arame Recozido BWG 18 | C3: KG | D3: =E3*$D$1 -> 13.73 | E3: 13.73 | F3: Aço | G3: Arame | H3: Custo Incorrido | I3: Armadura
A4: =COUNTIFS($B$2:$B$996,B4) -> 1 | B4: Barras de transferencia lisa 12,5mm 50 cm | C4: pc | D4: =E4*$D$1 -> 3.82 | E4: 3.82 | F4: Aço | G4: Barra de Aço CA50 / CA60 | I4: Armadura
A5: =COUNTIFS($B$2:$B$996,B5) -> 1 | B5: Monocordoalha engraxada CP - 190 RB (12,7mm) | C5: KG | D5: =E5*$D$1 -> 15.5 | E5: 15.5 | F5: Aço | G5: Barra de Aço CA50 / CA60 | I5: Armadura
A6: =COUNTIFS($B$2:$B$996,B6) -> 1 | B6: Armação aço Média para estaca (Corte e Dobra em Obra) | C6: KG | D6: =E6*$D$1 -> 7.6873385 | E6: 7.6873385 | F6: Aço | G6: Barra de Aço CA50 / CA60 | I6: Armadura
A7: =COUNTIFS($B$2:$B$996,B7) -> 1 | B7: Armação aço Média para estaca (Corte e Dobra em Indústria) | C7: KG | D7: =E7*$D$1 -> 8.2873385 | E7: 8.2873385 | F7: Aço | G7: Barra de Aço CA50 / CA60 | I7: Armadura
A8: =COUNTIFS($B$2:$B$996,B8) -> 1 | B8: CORTE E DOBRA ARMADO ESTACA Ø50CM 5F 16,0 4MTS ESP75 PS20 | C8: KG | D8: =E8*$D$1 -> 302.922 | E8: 302.922 | F8: Aço | G8: Barra de Aço CA50 / CA60 | I8: Armadura
A9: =COUNTIFS($B$2:$B$996,B9) -> 1 | B9: CORTE E DOBRA ARMADO ESTACA Ø60CM 5F 20,0 4MTS ESP75 PS20 | C9: KG | D9: =E9*$D$1 -> 466.337 | E9: 466.337 | F9: Aço | G9: Barra de Aço CA50 / CA60 | I9: Armadura
A10: =COUNTIFS($B$2:$B$996,B10) -> 1 | B10: CORTE E DOBRA ARMADO ESTACA Ø60CM 7F 20,0 6MTS ESP75 PS20 | C10: KG | D10: =E10*$D$1 -> 937.639 | E10: 937.639 | F10: Aço | G10: Barra de Aço CA50 / CA60 | I10: Armadura
A11: =COUNTIFS($B$2:$B$996,B11) -> 1 | B11: CORTE E DOBRA ARMADO ESTACA Ø60CM 9F 20,0 8MTS ESP75 PS20 | C11: KG | D11: =E11*$D$1 -> 1609.666 | E11: 1609.666 | F11: Aço | G11: Barra de Aço CA50 / CA60 | I11: Armadura
A12: =COUNTIFS($B$2:$B$996,B12) -> 1 | B12: Aço CA50 10,0 mm | C12: KG | D12: =E12*$D$1 -> 4.8006843 | E12: 4.8006843 | F12: Aço | G12: Barra de Aço CA50 / CA60 | H12: Scaini ferro e Aço | I12: Armadura
A13: =COUNTIFS($B$2:$B$996,B13) -> 1 | B13: Aço CA50 12,5 mm | C13: KG | D13: =E13*$D$1 -> 5.0530855 | E13: 5.0530855 | F13: Aço | G13: Barra de Aço CA50 / CA60 | H13: Scaini ferro e Aço | I13: Armadura
A14: =COUNTIFS($B$2:$B$996,B14) -> 1 | B14: Aço CA50 16,0mm | C14: KG | D14: =E14*$D$1 -> 4.9405604 | E14: 4.9405604 | F14: Aço | G14: Barra de Aço CA50 / CA60 | H14: Scaini ferro e Aço | I14: Armadura
A15: =COUNTIFS($B$2:$B$996,B15) -> 1 | B15: Aço CA50 20,0mm | C15: KG | D15: =E15*$D$1 -> 5.0344353 | E15: 5.0344353 | F15: Aço | G15: Barra de Aço CA50 / CA60 | H15: Scaini ferro e Aço | I15: Armadura
A16: =COUNTIFS($B$2:$B$996,B16) -> 1 | B16: Aço CA50 25,0mm | C16: KG | D16: =E16*$D$1 -> 5.1608662 | E16: 5.1608662 | F16: Aço | G16: Barra de Aço CA50 / CA60 | H16: Scaini ferro e Aço | I16: Armadura
A17: =COUNTIFS($B$2:$B$996,B17) -> 1 | B17: Aço CA50 6,3 mm | C17: KG | D17: =E17*$D$1 -> 5.2594749 | E17: 5.2594749 | F17: Aço | G17: Barra de Aço CA50 / CA60 | H17: Scaini ferro e Aço | I17: Armadura
A18: =COUNTIFS($B$2:$B$996,B18) -> 1 | B18: Aço CA50 8,0 mm | C18: KG | D18: =E18*$D$1 -> 4.924857 | E18: 4.924857 | F18: Aço | G18: Barra de Aço CA50 / CA60 | H18: Scaini ferro e Aço | I18: Armadura
A19: =COUNTIFS($B$2:$B$996,B19) -> 1 | B19: Aço CA60 5,0mm | C19: KG | D19: =E19*$D$1 -> 6.1446197 | E19: 6.1446197 | F19: Aço | G19: Barra de Aço CA50 / CA60 | H19: Scaini ferro e Aço | I19: Armadura
A20: =COUNTIFS($B$2:$B$996,B20) -> 1 | B20: Aço CA60 32,0mm | C20: KG | D20: =E20*$D$1 -> 6.22 | E20: 6.22 | F20: Aço | G20: Barra de Aço CA50 / CA60 | I20: Armadura
A21: =COUNTIFS($B$2:$B$876,B21) -> 1 | B21: Aço CA50 5,0 mm Corte e Dobra em Indústria | C21: UN | D21: =E21*$D$1 -> 8.67 | E21: 8.67 | F21: Aço | G21: Barra de Aço CA50 / CA60 | H21: Proposta Gessele | I21: Armadura
A22: =COUNTIFS($B$2:$B$876,B22) -> 1 | B22: Aço CA50 6,3 mm Corte e Dobra em Indústria | C22: UN | D22: =E22*$D$1 -> 8.67 | E22: 8.67 | F22: Aço | G22: Barra de Aço CA50 / CA60 | H22: Proposta Gessele | I22: Armadura
A23: =COUNTIFS($B$2:$B$876,B23) -> 1 | B23: Aço CA50 8,0 mm Corte e Dobra em Indústria | C23: UN | D23: =E23*$D$1 -> 8.67 | E23: 8.67 | F23: Aço | G23: Barra de Aço CA50 / CA60 | H23: Proposta Gessele | I23: Armadura
A24: =COUNTIFS($B$2:$B$876,B24) -> 1 | B24: Aço CA50 10,0 mm Corte e Dobra em Indústria | C24: UN | D24: =E24*$D$1 -> 8.67 | E24: 8.67 | F24: Aço | G24: Barra de Aço CA50 / CA60 | H24: Proposta Gessele | I24: Armadura
A25: =COUNTIFS($B$2:$B$876,B25) -> 1 | B25: Aço CA50 12,5 mm Corte e Dobra em Indústria | C25: UN | D25: =E25*$D$1 -> 8.19 | E25: 8.19 | F25: Aço | G25: Barra de Aço CA50 / CA60 | H25: Proposta Gessele | I25: Armadura
A26: =COUNTIFS($B$2:$B$876,B26) -> 1 | B26: Aço CA50 16,0 mm Corte e Dobra em Indústria | C26: UN | D26: =E26*$D$1 -> 8.19 | E26: 8.19 | F26: Aço | G26: Barra de Aço CA50 / CA60 | H26: Proposta Gessele | I26: Armadura
A27: =COUNTIFS($B$2:$B$876,B27) -> 1 | B27: Aço CA50 20,0 mm Corte e Dobra em Indústria | C27: UN | D27: =E27*$D$1 -> 8.19 | E27: 8.19 | F27: Aço | G27: Barra de Aço CA50 / CA60 | H27: Proposta Gessele | I27: Armadura
A28: =COUNTIFS($B$2:$B$876,B28) -> 1 | B28: Aço CA50 25,0mm Corte e Dobra em Indústria | C28: UN | D28: =E28*$D$1 -> 8.19 | E28: 8.19 | F28: Aço | G28: Barra de Aço CA50 / CA60 | H28: Proposta Gessele | I28: Armadura
A29: =COUNTIFS($B$2:$B$876,B29) -> 1 | B29: Aço CA50 32,0mm Corte e Dobra em Indústria | C29: UN | D29: =E29*$D$1 -> 8.7763609 | E29: =(E21*E20)/E19 -> 8.7763609 | F29: Aço | G29: Barra de Aço CA50 / CA60 | I29: Armadura
A30: =COUNTIFS($B$2:$B$996,B30) -> 1 | B30: Sistema e Instalação de Fachada Ventilada. Mecanização das peças, arremate das esquadrias e Fretes | C30: UN | D30: =E30*$D$1 -> 305 | E30: =305 -> 305 | F30: Aço | G30: Diversos | I30: Armadura
A31: =COUNTIFS($B$2:$B$996,B31) -> 1 | B31: ESPACADOR / DISTANCIADOR CIRCULAR COM ENTRADA LATERAL, EM PLASTICO, PARA VERGALHAO *4,2 A 12,5* MM, COBRIMENTO 40 MM | C31: M2 | D31: =E31*$D$1 -> 0.43 | E31: 0.43 | F31: Aço | G31: Diversos | I31: Armadura
A32: =COUNTIFS($B$2:$B$996,B32) -> 1 | B32: TELA ACO CARBONO CA60 M.150X150MM F.03,4MM 245X600CM Q61 (14,26KG/UN) | C32: KG | D32: =E32*$D$1 -> 6.1 | E32: 6.1 | F32: Aço | G32: Tela de Aço CA60 | I32: Armadura
A33: =COUNTIFS($B$2:$B$996,B33) -> 1 | B33: TELA ACO CARBONO CA60 M.150X150MM F.04,2MM 245X600CM Q92 (21,8KG/UN) | C33: KG | D33: =E33*$D$1 -> 4.88 | E33: 4.88 | F33: Aço | G33: Tela de Aço CA60 | I33: Armadura
A34: =COUNTIFS($B$2:$B$996,B34) -> 1 | B34: TELA ACO CARBONO CA60 M.100X100MM F.04,2MM 245X600CM Q113 (26,46KG/UN) | C34: KG | D34: =E34*$D$1 -> 8.537037 | E34: =225.89/26.46 -> 8.537037 | F34: Aço | G34: Tela de Aço CA60 | I34: Armadura
A35: =COUNTIFS($B$2:$B$996,B35) -> 1 | B35: TELA ACO CARBONO CA60 M.100X100MM F.04,2MM 245X600CM Q138 (32,34KG/UN) | C35: KG | D35: =E35*$D$1 -> 9.1447124 | E35: 9.1447124 | F35: Aço | G35: Tela de Aço CA60 | I35: Armadura
A36: =COUNTIFS($B$2:$B$996,B36) -> 1 | B36: TELA DE ACO SOLDADA GALVANIZADA/ZINCADA PARA ALVENARIA, FIO D = *1,20 A 1,70* MM, MALHA 15 X 15 MM, (C X L) *50 X 17,5* CM | C36: UN | D36: =E36*$D$1 -> 2.5 | E36: 2.5 | F36: Aço | G36: Tela de Aço Carbono | I36: Armadura
A37: =COUNTIFS($B$2:$B$996,B37) -> 1 | B37: Tela de arame galvanizada, hexagonal, fio 0,56 mm (24 bwg), malha 1/2", h = 1 m | C37: M2 | D37: =E37*$D$1 -> 14.27 | E37: 14.27 | F37: Aço | G37: Tela de Aço Carbono | I37: Armadura
A38: =COUNTIFS($B$2:$B$996,B38) -> 1 | B38: TIJOLO REFRATÁRIO 5 X 11,5 X 23 CM | C38: UN | D38: =E38*$D$1 -> 7 | E38: 7 | F38: Alvenaria | G38: Alvenaria Refratária | I38: Pintura
A39: =COUNTIFS($B$2:$B$996,B39) -> 1 | B39: TIJOLO REFRATÁRIO 2,5 X 11,5 X 23 CM | C39: UN | D39: =E39*$D$1 -> 5.95 | E39: 5.95 | F39: Alvenaria | G39: Alvenaria Refratária | I39: Pintura
A40: =COUNTIFS($B$2:$B$996,B40) -> 1 | B40: BLOCO CONCRETO ESTRUTURAL 03MPA 14X19X39CM NBR 6136 | C40: UN | D40: =E40*$D$1 -> 2.95 | E40: 2.95 | F40: Alvenaria | G40: Alvenaria Estrutural | I40: Elementos de Vedação (Cerâmica)
A41: =COUNTIFS($B$2:$B$996,B41) -> 1 | B41: BLOCO CONCRETO ESTRUTURAL 04MPA 14X19X04CM NBR 6136 | C41: UN | D41: =E41*$D$1 -> 4.1861538 | E41: 4.1861538 | F41: Alvenaria | G41: Alvenaria Estrutural | I41: Elementos de Vedação (Cerâmica)
A42: =COUNTIFS($B$2:$B$996,B42) -> 1 | B42: BLOCO CONCRETO ESTRUTURAL 04MPA 14X19X09CM NBR 6136 | C42: UN | D42: =E42*$D$1 -> 3.9889744 | E42: 3.9889744 | F42: Alvenaria | G42: Alvenaria Estrutural | I42: Elementos de Vedação (Cerâmica)
A43: =COUNTIFS($B$2:$B$996,B43) -> 1 | B43: BLOCO CONCRETO ESTRUTURAL 04MPA 14X19X14CM NBR 6136 | C43: UN | D43: =E43*$D$1 -> 1.376 | E43: 1.376 | F43: Alvenaria | G43: Alvenaria Estrutural | I43: Elementos de Vedação (Cerâmica)
A44: =COUNTIFS($B$2:$B$996,B44) -> 1 | B44: BLOCO CONCRETO ESTRUTURAL 04MPA 11,5X19X29CM NBR 6136 | C44: UN | D44: =E44*$D$1 -> 1.998 | E44: 1.998 | F44: Alvenaria | G44: Alvenaria Estrutural | I44: Elementos de Vedação (Cerâmica)
A45: =COUNTIFS($B$2:$B$996,B45) -> 1 | B45: BLOCO CONCRETO ESTRUTURAL 04MPA 14X19X29CM NBR 6136 | C45: UN | D45: =E45*$D$1 -> 1.998 | E45: 1.998 | F45: Alvenaria | G45: Alvenaria Estrutural | I45: Elementos de Vedação (Cerâmica)
A46: =COUNTIFS($B$2:$B$996,B46) -> 1 | B46: BLOCO CONCRETO ESTRUTURAL 04MPA 14X19X44CM NBR 6136 | C46: UN | D46: =E46*$D$1 -> 4.02 | E46: 4.02 | F46: Alvenaria | G46: Alvenaria Estrutural | I46: Elementos de Vedação (Cerâmica)
... A67: =COUNTIFS($B$2:$B$996,B67) -> 1 | B67: BLOCO CERÂMICO - 9X19X39cm | C67: UN | D67: =E67*$D$1 -> 0.99 | E67: 0.99 | F67: Alvenaria | G67: Alvenaria vedação | I67: Elementos de Vedação (Cerâmica)
A68: =COUNTIFS($B$2:$B$996,B68) -> 1 | B68: BLOCO CERÂMICO - 11,5X19X39cm | C68: UN | D68: =E68*$D$1 -> 1.15 | E68: =E66*11.5/14 -> 1.15 | F68: Alvenaria | G68: Alvenaria vedação | I68: Elementos de Vedação (Cerâmica)
A69: =COUNTIFS($B$2:$B$996,B69) -> 1 | B69: BLOCO CERÂMICO - 19X19X39cm | C69: UN | D69: =E69*$D$1 -> 1.9 | E69: =E66*19/14 -> 1.9 | F69: Alvenaria | G69: Alvenaria vedação | I69: Elementos de Vedação (Cerâmica)
A70: =COUNTIFS($B$2:$B$996,B70) -> 1 | B70: BLOCO CERÂMICO - 9X19X19cm | C70: UN | D70: =E70*$D$1 -> 0.99 | E70: 0.99 | F70: Alvenaria | G70: Alvenaria vedação | I70: Elementos de Vedação (Cerâmica)
A71: =COUNTIFS($B$2:$B$996,B71) -> 1 | B71: BLOCO CERÂMICO - 11,5X19X19cm | C71: UN | D71: =E71*$D$1 -> 1.24 | E71: 1.24 | F71: Alvenaria | G71: Alvenaria vedação | I71: Elementos de Vedação (Cerâmica)
A72: =COUNTIFS($B$2:$B$996,B72) -> 1 | B72: BLOCO CERÂMICO - 14X19X19cm | C72: UN | D72: =E72*$D$1 -> 2.6 | E72: 2.6 | F72: Alvenaria | G72: Alvenaria vedação | I72: Elementos de Vedação (Cerâmica)
A73: =COUNTIFS($B$2:$B$996,B73) -> 1 | B73: BLOCO CERÂMICO - 19X19X19cm | C73: UN | D73: =E73*$D$1 -> 1.59 | E73: 1.59 | F73: Alvenaria | G73: Alvenaria vedação | I73: Elementos de Vedação (Cerâmica)
A74: =COUNTIFS($B$2:$B$996,B74) -> 1 | B74: BLOCO DE VEDACAO CONCRETO 09X19X39 CM | C74: UN | D74: =E74*$D$1 -> 2.7 | E74: 2.7 | F74: Alvenaria | G74: Alvenaria vedação | I74: Elementos de Vedação (Cerâmica)
A75: =COUNTIFS($B$2:$B$996,B75) -> 1 | B75: BLOCO DE VEDACAO CONCRETO 11,5X19X39 CM | C75: UN | D75: =E75*$D$1 -> 3.45 | E75: =E74/9*11.5 -> 3.45 | F75: Alvenaria | G75: Alvenaria vedação | I75: Elementos de Vedação (Cerâmica)
A76: =COUNTIFS($B$2:$B$996,B76) -> 1 | B76: BLOCO DE VEDACAO CONCRETO 19X19X39 CM | C76: UN | D76: =E76*$D$1 -> 5.7 | E76: =E74/9*19 -> 5.7 | F76: Alvenaria | G76: Alvenaria vedação | I76: Elementos de Vedação (Cerâmica)
A77: =COUNTIFS($B$2:$B$996,B77) -> 1 | B77: ELEMENTO VAZADO CONCRETO QUADRADO | C77: UN | D77: =E77*$D$1 -> 15 | E77: 15 | F77: Alvenaria | G77: Alvenaria vedação | I77: Elementos de Vedação (Cerâmica)
A78: =COUNTIFS($B$2:$B$996,B78) -> 1 | B78: ELEMENTO VAZADO CERAMICO QUADRADO | C78: UN | D78: =E78*$D$1 -> 11.99 | E78: 11.99 | F78: Alvenaria | G78: Alvenaria vedação | I78: Elementos de Vedação (Cerâmica)
A79: =COUNTIFS($B$2:$B$996,B79) -> 1 | B79: BLOCO DE VEDACAO CERAMICO MACIÇO 5,5X11,5X24 CM | C79: UN | D79: =E79*$D$1 -> 1.05 | E79: 1.05 | F79: Alvenaria | G79: Alvenaria vedação | I79: Elementos de Vedação (Cerâmica)
A80: =COUNTIFS($B$2:$B$996,B80) -> 1 | B80: BLOCO DE VEDACAO CERAMICO 09X19X29 CM | C80: UN | D80: =E80*$D$1 -> 1.18 | E80: 1.18 | F80: Alvenaria | G80: Alvenaria vedação | I80: Elementos de Vedação (Cerâmica)
A81: =COUNTIFS($B$2:$B$996,B81) -> 1 | B81: BLOCO DE VEDACAO CERAMICO 11,5X19X29 CM | C81: UN | D81: =E81*$D$1 -> 1.43 | E81: 1.43 | F81: Alvenaria | G81: Alvenaria vedação | I81: Elementos de Vedação (Cerâmica)
A82: =COUNTIFS($B$2:$B$996,B82) -> 1 | B82: BLOCO DE VEDACAO CERAMICO 14X19X29 CM | C82: UN | D82: =E82*$D$1 -> 1.72 | E82: 1.72 | F82: Alvenaria | G82: Alvenaria vedação | I82: Elementos de Vedação (Cerâmica)
A83: =COUNTIFS($B$2:$B$996,B83) -> 1 | B83: BLOCO DE VEDACAO CERAMICO 19X19X29 CM | C83: UN | D83: =E83*$D$1 -> 2.3342857 | E83: =E82/14*19 -> 2.3342857 | F83: Alvenaria | G83: Alvenaria vedação | I83: Elementos de Vedação (Cerâmica)
A84: =COUNTIFS($B$2:$B$996,B84) -> 1 | B84: Bloco Concreto Celular 7,5x30x60 | C84: M3 | D84: =E84*$D$1 -> 10.71 | E84: 10.71 | F84: Argamassa | G84: Sical | I84: Argamassa
A85: =COUNTIFS($B$2:$B$996,B85) -> 1 | B85: Bloco Concreto Celular 10x30x60 | C85: M3 | D85: =E85*$D$1 -> 12.41 | E85: 12.41 | F85: Argamassa | G85: Sical | I85: Argamassa
A86: =COUNTIFS($B$2:$B$996,B86) -> 1 | B86: Bloco Concreto Celular 12,5x30x60 | C86: M3 | D86: =E86*$D$1 -> 17.91 | E86: 17.91 | F86: Argamassa | G86: Sical | I86: Argamassa
A87: =COUNTIFS($B$2:$B$996,B87) -> 1 | B87: Bloco Concreto Celular 15x30x60 | C87: M3 | D87: =E87*$D$1 -> 16.44 | E87: 16.44 | F87: Argamassa | G87: Sical | I87: Argamassa
A88: =COUNTIFS($B$2:$B$996,B88) -> 1 | B88: ARGAMASSA TRAÇO 1:3 (EM VOLUME DE CIMENTO E AREIA GROSSA ÚMIDA) PARA CONTRAPISO TIPO FAROFA | C88: M3 | D88: =E88*$D$1 -> 43.48 | E88: 43.48 | F88: Argamassa | G88: Argamassa de Assentamento de Revestimentos | I88: Argamassa
A89: =COUNTIFS($B$2:$B$996,B89) -> 1 | B89: ARGAMASSA TRAÇO 1:4 (EM VOLUME DE CIMENTO E AREIA GROSSA ÚMIDA) PARA CHAPISCO CONVENCIONAL, PREPARO MANUAL. | C89: M3 | D89: =E89*$D$1 -> 657.89 | E89: 657.89 | F89: Argamassa | G89: Argamassa de Assentamento de Revestimentos | I89: Argamassa
A90: =COUNTIFS($B$2:$B$996,B90) -> 1 | B90: ARGAMASSA TRAÇO 1:5 (EM VOLUME DE CIMENTO E AREIA GROSSA ÚMIDA) PARA CHAPISCO CONVENCIONAL, PREPARO MANUAL. | C90: M3 | D90: =E90*$D$1 -> 633.27 | E90: 633.27 | F90: Argamassa | G90: Argamassa de Assentamento de Revestimentos | I90: Argamassa
A91: =COUNTIFS($B$2:$B$996,B91) -> 1 | B91: ARGAMASSA ENSACADA P/ASSENTAMENTO BLOCO 04MPA NBR 13281 | C91: KG | D91: =E91*$D$1 -> 0.46 | E91: 0.46 | F91: Argamassa | G91: Argamassa de Assentamento Bloco | I91: Argamassa
A92: =COUNTIFS($B$2:$B$996,B92) -> 1 | B92: Massa cimentícia armada | C92: KG | D92: =E92*$D$1 -> 18.326667 | E92: =274.9/15 -> 18.326667 | F92: Argamassa | G92: Argamassa de Assentamento Bloco | I92: Argamassa
A93: =COUNTIFS($B$2:$B$996,B93) -> 1 | B93: Argamassa para encunhamento | C93: kg | D93: =E93*$D$1 -> 2.562 | E93: 2.562 | F93: Argamassa | G93: Argamassa Diversas | I93: Argamassa
A94: =COUNTIFS($B$2:$B$996,B94) -> 1 | B94: Argamassa ACIII | C94: KG | D94: =E94*$D$1 -> 1.0645 | E94: =21.29/20 -> 1.0645 | F94: Argamassa | G94: Argamassa de Assentamento de Revestimentos | I94: Argamassa
A95: =COUNTIFS($B$2:$B$996,B95) -> 1 | B95: Argamassa ACII | C95: KG | D95: =E95*$D$1 -> 0.95 | E95: =19/20 -> 0.95 | F95: Argamassa | G95: Argamassa de Assentamento de Revestimentos | I95: Argamassa
A96: =COUNTIFS($B$2:$B$996,B96) -> 1 | B96: ARGAMASSA ENSACADA PARA CONTRAPISO | C96: KG | D96: =E96*$D$1 -> 4 | E96: 4 | F96: Argamassa | G96: Argamassa de Assentamento de Revestimentos | I96: Argamassa
A97: =COUNTIFS($B$2:$B$996,B97) -> 1 | B97: ARGAMASSA COLANTE AC II | C97: KG | D97: =E97*$D$1 -> 1.36 | E97: 1.36 | F97: Argamassa | G97: Argamassa de Assentamento de Revestimentos | I97: Argamassa
A98: =COUNTIFS($B$2:$B$996,B98) -> 1 | B98: Argamassa industrializada para Para Chapisco Colante | C98: KG | D98: =E98*$D$1 -> 0.8 | E98: 0.8 | F98: Argamassa | G98: Argamassa Diversas | I98: Argamassa
A99: =COUNTIFS($B$2:$B$996,B99) -> 1 | B99: Argamassa industrializada para Para Reboco | C99: KG | D99: =E99*$D$1 -> 0.95 | E99: 0.95 | F99: Argamassa | G99: Argamassa Diversas | I99: Argamassa
A100: =COUNTIFS($B$2:$B$996,B100) -> 1 | B100: Massa Dundun Para Assentamento De Tijolos E Blocos | C100: KG | D100: =E100*$D$1 -> 19.116 | E100: 19.116 | F100: Argamassa | G100: Argamassa Diversas | I100: Argamassa
A101: =COUNTIFS($B$2:$B$996,B101) -> 1 | B101: ARGAMASSA REFRATÁRIA | C101: M3 | D101: =E101*$D$1 -> 1.75 | E101: 1.75 | F101: Argamassa | G101: Argamassa Diversas | I101: Argamassa
A102: =COUNTIFS($B$2:$B$996,B102) -> 1 | B102: Argamassa Usinada para emboço/massa única | C102: M3 | D102: =E102*$D$1 -> 415 | E102: 415 | F102: Argamassa | G102: Argamassa Diversas | H102: VALOR GESSELE | I102: Argamassa
A103: =COUNTIFS($B$2:$B$996,B103) -> 1 | B103: Bombeamento Argamassa Usinada para emboço/massa única | C103: M3 | D103: =E103*$D$1 -> 45 | E103: 45 | F103: Argamassa | G103: Argamassa Diversas | H103: VALOR GESSELE | I103: Argamassa
A104: =COUNTIFS($B$2:$B$996,B104) -> 1 | B104: Argamassa usninada para contrapiso | C104: M3 | D104: =E104*$D$1 -> 550 | E104: 550 | F104: Argamassa | G104: Argamassa Diversas | I104: Argamassa
A105: =COUNTIFS($B$2:$B$996,B105) -> 1 | B105: Argamassa usninada para contrapiso nivelada | C105: M3 | D105: =E105*$D$1 -> 515 | E105: 515 | F105: Argamassa | G105: Argamassa Diversas | H105: VALOR GESSELE | I105: Argamassa
A106: =COUNTIFS($B$2:$B$996,B106) -> 1 | B106: Argila expandida | C106: KG | D106: =E106*$D$1 -> 2.945 | E106: 2.945 | F106: Argamassa | G106: Argamassa Diversas | I106: Argamassa
A107: =COUNTIFS($B$2:$B$996,B107) -> 1 | B107: ARGAMASSA ESTABILIZADA PARA ASSENTAMENTO | C107: M3 | D107: =E107*$D$1 -> 425 | E107: 425 | F107: Argamassa | G107: Argamassa Usinada | I107: Argamassa
A108: =COUNTIFS($B$2:$B$996,B108) -> 1 | B108: ARGAMASSA ESTABILIZADA PARA CHAPISCO | C108: M3 | D108: =E108*$D$1 -> 480 | E108: 480 | F108: Argamassa | G108: Argamassa Usinada | I108: Argamassa
A109: =COUNTIFS($B$2:$B$996,B109) -> 1 | B109: ARGAMASSA INDUSTRIALIZADA MULTIUSO, PARA REVESTIMENTO INTERNO E EXTERNO E ASSENTAMENTO DE BLOCOS DIVERSOS | C109: M3 | D109: =E109*$D$1 -> 425 | E109: 425 | F109: Argamassa | G109: Argamassa Usinada | I109: Argamassa
A110: =COUNTIFS($B$2:$B$996,B110) -> 1 | B110: PISO INTERTRAVADO CONCRETO SEXTAVADO 35MPA 30X30X06CM NATURAL | C110: M2 | D110: =E110*$D$1 -> 75.9 | E110: 75.9 | F110: Artefatos de concreto | G110: Artefatos de concreto | I110: Concretos
A111: =COUNTIFS($B$2:$B$996,B111) -> 1 | B111: Ladrilho hidráulico 20x20 cm | C111: M2 | D111: =E111*$D$1 -> 180 | E111: 180 | F111: Artefatos de concreto | G111: Artefatos de concreto | I111: Concretos
A112: =COUNTIFS($B$2:$B$996,B112) -> 1 | B112: Piso Intertravado Retangular 10x20x08 | C112: M2 | D112: =E112*$D$1 -> 65.9 | E112: 65.9 | F112: Artefatos de concreto | G112: Artefatos de concreto | I112: Concretos
A113: =COUNTIFS($B$2:$B$996,B113) -> 1 | B113: Piso Podotátil Alerta Amarelo 20x20cm Cimartex | C113: M2 | D113: =E113*$D$1 -> 102.9 | E113: 102.9 | F113: Artefatos de concreto | G113: Artefatos de concreto | I113: Concretos
A114: =COUNTIFS($B$2:$B$996,B114) -> 1 | B114: Tampo de Granito, para Lavatório com saia e rodamão | C114: M² | D114: =E114*$D$1 -> 750 | E114: 750 | F114: Bancadas | G114: Bancadas | I114: Louças e Acessórios
A115: =COUNTIFS($B$2:$B$996,B115) -> 1 | B115: Tampo de Granito, para pia com saia e rodamão | C115: M² | D115: =E115*$D$1 -> 750 | E115: 750 | F115: Bancadas | G115: Bancadas | I115: Louças e Acessórios
A116: =COUNTIFS($B$2:$B$996,B116) -> 1 | B116: Tampo de Granito, para tanque com saia e rodamão | C116: M² | D116: =E116*$D$1 -> 750 | E116: 750 | F116: Bancadas | G116: Bancadas | I116: Louças e Acessórios
A117: =COUNTIFS($B$2:$B$996,B117) -> 1 | B117: Calha Beiral Alumínio Com 2 Tampas Corte 13 | C117: M | D117: =E117*$D$1 -> 18.7148 | E117: 18.7148 | F117: Cobertura | G117: Calha | I117: Calhas e Acessórios
... A138: =COUNTIFS($B$2:$B$996,B138) -> 1 | B138: Concreto Usinado bombeável 30MPa para estacas | C138: M3 | D138: =E138*$D$1 -> 517.65 | E138: 517.65 | F138: Concreto | G138: Concreto | I138: Concretos
A139: =COUNTIFS($B$2:$B$996,B139) -> 1 | B139: Concreto Usinado bombeável 35MPa Convencional | C139: M3 | D139: =E139*$D$1 -> 604.73 | E139: 604.73 | F139: Concreto | G139: Concreto | H139: Proposta Gessele | I139: Concretos
A140: =COUNTIFS($B$2:$B$996,B140) -> 1 | B140: Concreto Usinado bombeável 35MPa para estacas | C140: M3 | D140: =E140*$D$1 -> 565 | E140: 565 | F140: Concreto | G140: Concreto | I140: Concretos
...
