Workbook
Name \0: #REF!
Name \0: #REF!
Name \0: #REF!
Name \0: #REF!
Name \0: #REF!
Name \0: #REF!
Name \0: #REF!
Name \0: #REF!
Name \1: #REF!
Name \1: #REF!
Name \a: #REF!
Name \a: #REF!
Name \a: #REF!
Name \a: #REF!
Name \a: #REF!
Name \a: #REF!
Name \a: #REF!
Name \a: #REF!
Name \k: #REF!
Name \m: #REF!
Name \m: #REF!
Name \m: #REF!
Name \m: #REF!
Name \m: #REF!
Name \m: #REF!
Name \m: #REF!
Name \m: #REF!
Name \z: #REF!
Name _1: #REF!
Name _2: #REF!
Name aa: #REF!
Name aa: #REF!
Name aa: #REF!
Name aa: #REF!
Name aa: #REF!
Name aa: #REF!
Name aa: #REF!
Name aaaa: '[2]M.O.'!#REF!
Name aaaa: '[2]M.O.'!#REF!
Name aaaa: '[2]M.O.'!#REF!
Name aaaa: '[2]M.O.'!#REF!
Name AB: #REF!
Name AB: #REF!
Name ALUMÍNIO_2: #REF!
Name ALUMÍNIO_2: #REF!
Name angelo: [3]Geral!#REF!
Name angelo: [3]Geral!#REF!
Name angelo: [3]Geral!#REF!
Name angelo: [3]Geral!#REF!
Name angelo: [3]Geral!#REF!
Name angelo: [3]Geral!#REF!
Name angelo: [3]Geral!#REF!
Name area: #REF!
Name area: #REF!
Name area: #REF!
Name Área_Construída: #REF!
Name Área_Construída: #REF!
Name Área_Construída: #REF!
Name Área_impressão_IM: #REF!
Name Área_Privativa: #REF!

Sheet Obra
C1: Projeto | D1: =Ger_Executivo!C4 -> Playa Negra
C2: Empresa | D2: =Ger_Executivo!C5 -> GDI
C3: Revisão | D3: R00 - Patricia Bragato
A4: QUADRO DE ÁREAS
B6: Descrição | C6: Unidade | E6: Quantidade
B7: MESES DE OBRA | C7: MÊS | E7: 30
B8: ÁREA DO TERRENO | C8: M2 | E8: 1440.91
B9: ÁREA CONSTRUÍDA | C9: M2 | E9: =SUM(E10:E18) -> 8518.6
B10: SUBSOLO 2 | C10: M2 | E10: 1143.68
B11: SUBSOLO 1 | C11: M2 | E11: 1143.68
B12: TERREO | C12: M2 | E12: 1056.79
B13: SOBRELOJA | C13: M2 | E13: 174.32
B14: 2º PAVIMENTO | C14: M2 | E14: 612.42
B15: TIPO (X6) | C15: M2 | E15: =612.42*6 -> 3674.52
B16: ÁTICO | C16: M2 | E16: 633.25
B17: BARRILETE | C17: M2 | E17: 39.97
B18: RESERVATÓRIO | C18: M2 | E18: 39.97
B19: NÚMERO DE UNIDADES HABITACIONAIS | C19: UN | E19: 69
B20: ÁREA PRIVATIVA | C20: M2 | E20: =79.19+690.9+661.85+329.91+283.78+308.98+303.66+303.66+296.94+267.05+284.06 -> 3809.98
B21: ÁREA COMERCIAL | C21: M2 | E21: =166.88+149.33 -> 316.21
B22: NÚMERO DE PAVIMENTOS | C22: UN | E22: 12
B24: ETAPA | C24: VALOR ORÇADO | D24: % | E24: VALOR / m²
B25: GERENCIAMENTO TÉCNICO E ADMINISTRATIVO | C25: ='Ger_Tec e Adm'!H228 -> 12288227 | D25: =C25/C$46 -> 0.33187185 | E25: =C25/$E$9 -> 1442.5172
B26: MOVIMENTAÇÃO DE TERRA | C26: =Ger_Executivo!H33 -> 748566.23 | D26: =C26/C$46 -> 0.020216753 | E26: =C26/$E$9 -> 87.874325
B27: CONTENÇÃO | C27: =Ger_Executivo!H42 -> 785740.88 | D27: =C27/C$46 -> 0.02122074 | E27: =C27/$E$9 -> 92.238264
B28: INFRAESTRUTURA | C28: =Ger_Executivo!H69 -> 425508.35 | D28: =C28/C$46 -> 0.011491832 | E28: =C28/$E$9 -> 49.950502
B29: SUPRAESTRUTURA | C29: =Ger_Executivo!H83 -> 5968880.7 | D29: =C29/C$46 -> 0.16120335 | E29: =C29/$E$9 -> 700.68798
B30: ALVENARIA | C30: =Ger_Executivo!H286 -> 1143407.1 | D30: =C30/C$46 -> 0.030880339 | E30: =C30/$E$9 -> 134.22477
B31: INSTALAÇÕES ELÉTRICAS, HIDRÁULICAS, GLP E PREVENTIVAS | C31: =Ger_Executivo!H410+Ger_Executivo!H533+Ger_Executivo!H543+Ger_Executivo!H632 -> 2834254.8 | D31: =C31/C$46 -> 0.07654557 | E31: =C31/$E$9 -> 332.71368
B32: REVESTIMENTOS ARGAMASSADOS | C32: =Ger_Executivo!H670 -> 1844309.9 | D32: =C32/C$46 -> 0.049809833 | E32: =C32/$E$9 -> 216.50388
B33: IMPERMEABILIZAÇÃO E TRATAMENTOS | C33: =Ger_Executivo!H817 -> 855401.26 | D33: =C33/C$46 -> 0.023102079 | E33: =C33/$E$9 -> 100.41571
B34: ACABAMENTOS INETRNOS EM PAREDE | C34: =Ger_Executivo!H853 -> 834243.15 | D34: =C34/C$46 -> 0.022530655 | E34: =C34/$E$9 -> 97.931955
B35: ACABAMENTOS EM PISOS E PAVIMENTAÇÕES | C35: =Ger_Executivo!H917 -> 1691413.4 | D35: =C35/C$46 -> 0.045680509 | E35: =C35/$E$9 -> 198.55532
B36: ACABAMENTOS INTERNOS EM TETO | C36: =Ger_Executivo!H1040 -> 490056.09 | D36: =C36/C$46 -> 0.013235092 | E36: =C36/$E$9 -> 57.527773
B37: PINTURA INTERNA | C37: =Ger_Executivo!H1084 -> 997118.86 | D37: =C37/C$46 -> 0.026929489 | E37: =C37/$E$9 -> 117.05196
B38: REVESTIMENTOS E ACABAMENTOS DE FACHADA | C38: =Ger_Executivo!H1223 -> 1415697.1 | D38: =C38/C$46 -> 0.038234156 | E38: =C38/$E$9 -> 166.18893
B39: ESQUADRIAS, VIDROS E FERRAGENS | C39: =Ger_Executivo!H1320 -> 2272243 | D39: =C39/C$46 -> 0.061367148 | E39: =C39/$E$9 -> 266.73901
B40: LOUÇAS E METAIS | C40: =Ger_Executivo!H1356 -> 283803.98 | D40: =C40/C$46 -> 0.0076647793 | E40: =C40/$E$9 -> 33.3158
B41: CLIMATIZAÇÃO, EQUIPAMENTOS E SISTEMAS ESPECIAIS | C41: =Ger_Executivo!H658+Ger_Executivo!H1366 -> 847698.1 | D41: =C41/C$46 -> 0.022894037 | E41: =C41/$E$9 -> 99.511434
B42: COBERTURA | C42: =Ger_Executivo!H1375 -> 56125.701 | D42: =C42/C$46 -> 0.0015158037 | E42: =C42/$E$9 -> 6.5886062
B43: LIMPEZA DE OBRA | C43: =Ger_Executivo!H1379 -> 220745.68 | D43: =C43/C$46 -> 0.0059617448 | E43: =C43/$E$9 -> 25.913375
B44: SERVIÇOS COMPLEMENTARES | C44: =Ger_Executivo!H1405 -> 659778.99 | D44: =C44/C$46 -> 0.017818849 | E44: =C44/$E$9 -> 77.451575
B45: IMPREVISTOS E CONTINGENCIAS | C45: =Ger_Executivo!H1418 -> 363805 | D45: =C45/C$46 -> 0.0098253909 | E45: =C45/$E$9 -> 42.707135 | G45: =SUM(C26:C45) -> 24738798
B46: TOTAL | C46: =SUM(C25:C45) -> 37027025 | D46: =SUM(D25:D45) -> 1 | E46: =SUM(E25:E45) -> 4346.6092
B47: CUB/SC | C47: 2841.51 | D47: 45505 | E47: =ROUNDUP(+E46/C47,2)&" CUB" -> 1,53 CUB

Sheet Canteiro
C1: Projeto | D1: =Ger_Executivo!C4 -> Playa Negra
C2: Empresa | D2: =Ger_Executivo!C5 -> GDI
C3: Revisão | D3: R00 - Patricia Bragato
A4: INSTALAÇÕES DE CANTEIRO
A5: Instalações de canteiro
B7: Descrição | C7: Unidade | D7: Quantidade
B8: Produtividade média | C8: m2 / mês | D8: =Obra!E9/Obra!E7 -> 283.95333
B9: Pm | C9: h/m2 | D9: 48
B10: Numero de funcionários | C10: un | D10: 98
B11: Equipe administrativa | C11: un | D11: 4
B12: Ferramentas | C12: R$ | D12: =800*D10 -> 78400 | E12: 800,00/func.
B13: EPI | C13: R$ | D13: =500*(D10+D11) -> 51000 | E13: 500,00/func.
B14: Banheiro | C14: un | D14: =ROUNDUP(($D$10+D11)/20,0) -> 6 | E14: 1/20 func

Sheet EPC's
C1: Projeto | D1: =Ger_Executivo!C4 -> Playa Negra
C2: Empresa | D2: =Ger_Executivo!C5 -> GDI
C3: Revisão | D3: R00 - Patricia Bragato
A4: EQUIPAMENTOS DE PROTEÇÃO COLETIVA
A6: Bandejas de proteção
B8: Descrição | C8: Unidade | D8: Quantidade
B9: Perímetro de projeção torre | C9: m | D9: 104.43
B10: Bandeja de proteção primária | C10: m | D10: =D9 -> 104.43
B11: Bandeja de proteção secundária | C11: m | D11: =D9 -> 104.43
A13: Guarda - corpo de desforma
B15: Descrição | C15: Unidade | D15: Quantidade
B16: Perímetro de projeção da torre | C16: m | D16: =D9 -> 104.43
B17: Repetições de pavimentos** | C17: un | D17: 4
B18: Proteção de periferia pós desforma torre | C18: m | D18: =(D16*D17) -> 417.72
A20: Tela fachadeira
B22: Descrição | C22: Unidade | D22: Quantidade
B23: Perímetro de projeção da torre | C23: m | D23: =D9 -> 104.43
B24: Altura de cobrimento da tela | C24: m | D24: =27.36-5.94 -> 21.42
B25: Tela fachadeira | C25: m2 | D25: =D23*D24 -> 2236.8906 | E25: =D23/D25 -> 0.046685341
A27: Fechamento removível de vãos em madeira
B29: Descrição | C29: Unidade | D29: Quantidade
B30: Área das portas de elevadores | C30: m2 | D30: =1*2.4 -> 2.4
B31: Quantidade de elevadores | C31: un | D31: 2
B32: Quantidade de portas de elevadores | C32: un | D32: =D30*D31*Obra!E22 -> 57.6
B33: Fechamento removível de vãos em madeira | C33: m2 | D33: =D30*D32 -> 138.24
A35: Guarda - corpo de vãos
B37: Descrição | C37: Unidade | D37: Quantidade
B38: Perímetro de vãos | C38: m | D38: =Corrimão!E20 -> 909.25818
B39: Guarda - corpo de vãos | C39: m | D39: =D38 -> 909.25818
A41: Tapume
B43: Descrição | C43: Unidade | D43: Quantidade
B44: Perímetro de encontro com pavimentação | C44: m | D44: =31.07+26.65 -> 57.72
B45: Altura do tapume | C45: m | D45: 2.4
B46: Área de tapume | C46: m2 | D46: =D45*D44 -> 138.528
A48: Linha de vida
B50: Descrição | C50: Unidade | D50: Quantidade
B51: Perímetro de projeção da torre | C51: m | D51: =D9 -> 104.43
B52: Linha de vida | C52: m | D52: =D51 -> 104.43
A54: SQLA Leve
B56: Descrição | C56: Unidade | D56: Quantidade
B57: Perímetro de projeção torre | C57: m | D57: =D9 -> 104.43
B58: Tela SQLA | C58: m | D58: =D57 -> 104.43

Sheet Controle Tecnologico
E5: COND.01
A6: Item | B6: Descrição/Especificação | C6: Unid. | D6: V. Unit. (R$) | E6: Qtde. | F6: V. Total (R$) | G6: Observações
B7: CONTROLE TECNOLÓGICO - CONCRETO
A8: 1 | B8: Laudo e ART | C8: vb | D8: 1450 | E8: 1 | F8: =$D8*E8 -> 1450
A9: =A8+1 -> 2 | B9: Controle Tecnologico - Coleta materiais da obra | C9: unid. | D9: 20 | E9: =ROUNDUP(Estrutura!M98/8,0)*4 -> 1068 | F9: =$D9*E9 -> 21360 | G9: 4 CPs por caminhão betoneira de 8m³
A10: =A9+1 -> 3 | B10: Controle Tecnológico - Ensaio de concreto endurecido/grouth - compressão simples / Detalhe: Concreto | C10: cps | D10: 12.5 | E10: =E9 -> 1068 | F10: =$D10*E10 -> 13350 | G10: 4 CPs por caminhão betoneira de 8m³
A11: =A10+1 -> 4 | B11: Determinação do módulo de deformação tangente inicial (Eci) (módulo de elasticidade), Incluindo Avaliação Estática dos Resultados (NBR 8522 e NBR 12655) | C11: ensaio | D11: 480 | E11: 2 | F11: =$D11*E11 -> 960 | G11: A cada 5 pav. (e quando houver troca de fornecedor)
C12: SUBTOTAL: | F12: =SUM(F8:F11) -> 37120
C14: VALOR/M3 | F14: =F12/Estrutura!M98 -> 17.413169

Sheet Ger_Tec e Adm
B4: PROJETO: | C4: Playa Negra | I4: REVISÃO: | J4: DATA
B5: EMPRESA: | C5: GDI | I5: R00 - Patricia Bragato | J5: 45519
B6: GERENCIAMENTO TÉCNICO E ADMINISTRATIVO
B7: Atalho | C7: Item | D7: Descrição | E7: Unidade | F7: Quant. | G7: Preço un | H7: Total | I7: Considerações | J7: Situação
C8: 01 | D8: TERRENOS E SERVIÇOS TÉCNICOS | H8: =H9+H21+H59+H63+H75+H84+H87+H101 -> 10192608
C9: 01.001 | D9: TERRENO | H9: =H10+H17 -> 4048500 | J9: -
C10: 01.001.001 | D10: AQUISIÇÃO DO TERRENO | H10: =SUM(H11:H16) -> 3988000
C11: 01.001.001.001 | D11: Analise Jurídica da Documentação do Terreno | E11: vb | F11: 1 | G11: 16000 | H11: =F11*G11 -> 16000 | I11: Mantido conforme lançamento inicial pela GDI - SUGERIDO REAPROPRIAÇÃO | J11: N/A
C12: 01.001.001.002 | D12: TERRENO 3 - Jordan Martins e João Martins | E12: vb | F12: 1 | G12: 3300000 | H12: =F12*G12 -> 3300000 | I12: Mantido conforme lançamento inicial pela GDI - SUGERIDO REAPROPRIAÇÃO | J12: N/A
C13: 01.001.001.003 | D13: TERRENO 3 - Torna financeira - Jordan Martins e João Martins | E13: vb | F13: 1 | G13: 565000 | H13: =F13*G13 -> 565000 | I13: Mantido conforme lançamento inicial pela GDI - SUGERIDO REAPROPRIAÇÃO | J13: N/A
C14: 01.001.001.004 | D14: TERRENO 2 - Margarete Valli e Francisco Valli (permuta) | E14: vb | F14: 1 | G14: 2500 | H14: =F14*G14 -> 2500 | I14: Mantido conforme lançamento inicial pela GDI - SUGERIDO REAPROPRIAÇÃO | J14: N/A
C15: 01.001.001.005 | D15: TERRENO 2 - Margarete Valli e Francisco Valli (torna financeira) | E15: vb | F15: 1 | G15: 22000 | H15: =F15*G15 -> 22000 | I15: Mantido conforme lançamento inicial pela GDI - SUGERIDO REAPROPRIAÇÃO | J15: N/A
C16: 01.001.001.006 | D16: Corretagem Imobiliária pela intermeadiação do Terreno | E16: vb | F16: 1 | G16: 82500 | H16: =F16*G16 -> 82500 | I16: Mantido conforme lançamento inicial pela GDI - SUGERIDO REAPROPRIAÇÃO | J16: N/A
C17: 01.001.002 | D17: TRANSFERÊNCIA DE PROPRIEDADE DOS TERRENOS | H17: =SUM(H18:H20) -> 60500
C18: 01.001.002.001 | D18: ITBI / FRJ - Terreno 1 | E18: vb | F18: 1 | G18: 55500 | H18: =F18*G18 -> 55500 | I18: Mantido conforme lançamento inicial pela GDI - SUGERIDO REAPROPRIAÇÃO | J18: N/A
C19: 01.001.002.002 | D19: ITBI / FRJ - Terreno 2 | E19: vb | F19: 1 | G19: 3000 | H19: =F19*G19 -> 3000 | I19: Mantido conforme lançamento inicial pela GDI - SUGERIDO REAPROPRIAÇÃO | J19: N/A
C20: 01.001.002.003 | D20: Escritura - Terreno 1 | E20: vb | F20: 1 | G20: 2000 | H20: =F20*G20 -> 2000 | I20: Mantido conforme lançamento inicial pela GDI - SUGERIDO REAPROPRIAÇÃO | J20: N/A
C21: 01.002 | D21: PROJETOS E SERVICOS TECNICOS | H21: =H22+H30+H43 -> 1277956.6 | J21: -
C22: 01.002.001 | D22: LEVANTAMENTOS E ESTUDOS TÉCNICOS | H22: =SUM(H23:H29) -> 86622.901
C23: 01.002.001.001 | D23: Levantamento Topográfico | E23: m2 | F23: 8790.63 | G23: 1.97 | H23: =F23*G23 -> 17317.541 | I23: Mantido conforme lançamento inicial pela GDI | J23: Lançado ERP
C24: 01.002.001.002 | D24: Sondagem SPT | E24: m | F24: 200 | G24: 40 | H24: =F24*G24 -> 8000 | I24: Mantido conforme lançamento inicial pela GDI | J24: Lançado ERP
C25: 01.002.001.003 | D25: Imagens Aéreas - Drone | E25: vb | F25: 2 | G25: 600 | H25: =F25*G25 -> 1200 | I25: Mantido conforme lançamento inicial pela GDI | J25: Lançado ERP
C26: 01.002.001.004 | D26: Estudos de Impacto de Vizinhança | E26: m2 | F26: 8790 | G26: 3.95 | H26: =F26*G26 -> 34720.5 | I26: Mantido conforme lançamento inicial pela GDI | J26: Lançado ERP
C27: 01.002.001.005 | D27: Estudo de impactos ambientais | E27: m2 | F27: 1 | G27: 3.6 | H27: =F27*G27 -> 3.6 | I27: Mantido conforme lançamento inicial pela GDI | J27: Lançado ERP
C28: 01.002.001.006 | D28: Inventário Florestal | E28: vb | F28: 1 | G28: 7800 | H28: =F28*G28 -> 7800 | I28: Mantido conforme lançamento inicial pela GDI | J28: Lançado ERP
C29: 01.002.001.007 | D29: Sondagem Geofísica | E29: vb | F29: 8790.63 | G29: 2 | H29: =F29*G29 -> 17581.26 | I29: Mantido conforme lançamento inicial pela GDI | J29: Lançado ERP
C30: 01.002.002 | D30: PROJETO ARQUITETÔNICO E GERAÇÃO DE IMAGENS | H30: =SUM(H31:H42) -> 600480.37 | J30: -
C31: 01.002.002.001 | D31: Projeto Arquitetônico - Projeto Legal (4.573,24m²) | E31: m2 | F31: 8790.63 | G31: 40 | H31: =G31*F31 -> 351625.2 | I31: Mantido conforme lançamento inicial pela GDI | J31: Lançado ERP
C32: 01.002.002.002 | D32: Projeto Arquitetônico de Interiores - Áreas Comuns | E32: m2 | F32: 8790.63 | G32: 10 | H32: =F32*G32 -> 87906.3 | I32: Mantido conforme lançamento inicial pela GDI | J32: Lançado ERP
C33: 01.002.002.003 | D33: Projeto Arquitetônico de Interiores - Áreas Privativas | E33: m2 | F33: 0 | G33: 10 | H33: =F33*G33 -> 0 | I33: Mantido conforme lançamento inicial pela GDI | J33: Lançado ERP
C34: 01.002.002.004 | D34: Projeto Arquitetônico Áreas Externas/Paisagismo | E34: m2 | F34: 7 | G34: 12.175 | H34: =F34*G34 -> 85.225 | I34: Mantido conforme lançamento inicial pela GDI | J34: Lançado ERP
C35: 01.002.002.005 | D35: Cena extra - Bona Studio | E35: vb | F35: 1 | G35: 5000 | H35: =F35*G35 -> 5000 | I35: Mantido conforme lançamento inicial pela GDI | J35: Lançado ERP
C36: 01.002.002.006 | D36: Fotografia e cinematografia - R2 Imagens | E36: m2 | F36: 8790.63 | G36: 3.98 | H36: =F36*G36 -> 34986.707 | I36: Mantido conforme lançamento inicial pela GDI | J36: Lançado ERP
C37: 01.002.002.007 | D37: Adequação do Projeto Arquitetônico das fachadas e área de lazer | E37: m2 | F37: 8790.63 | G37: 3.95 | H37: =F37*G37 -> 34722.988 | I37: Mantido conforme lançamento inicial pela GDI | J37: Lançado ERP
C38: 01.002.002.008 | D38: Desenvolvimento de Imagens - Interiores e Paisagismo | E38: m2 | F38: 8790.63 | G38: 3.6 | H38: =F38*G38 -> 31646.268 | I38: Mantido conforme lançamento inicial pela GDI | J38: Lançado ERP
C39: 01.002.002.009 | D39: Serviços de arquitetura - Contrato Espaço Livre | E39: m2 | F39: 3939.28 | G39: 7.39 | H39: =F39*G39 -> 29111.279 | I39: Mantido conforme lançamento inicial pela GDI | J39: Lançado ERP
C40: 01.002.002.010 | D40: Impressão de Imagens e Plotagem de Projetos | E40: m2 | F40: 3939.28 | G40: 5 | H40: =F40*G40 -> 19696.4 | I40: Mantido conforme lançamento inicial pela GDI | J40: Lançado ERP
C41: 01.002.002.011 | D41: Evento de Apresentação do Projeto | E41: vb | F41: 1 | G41: 700 | H41: =F41*G41 -> 700 | I41: Mantido conforme lançamento inicial pela GDI | J41: Lançado ERP
C42: 01.002.002.012 | D42: Adequação do Projeto Arquitetônico das Fachadas | E42: m2 | F42: 1000 | G42: 5 | H42: =F42*G42 -> 5000 | I42: Mantido conforme lançamento inicial pela GDI | J42: Lançado ERP
C43: 01.002.003 | D43: PROJETOS COMPLEMENTARES DE ENGENHARIA | H43: =SUM(H44:H58) -> 590853.31
C44: 01.002.003.001 | D44: Projeto Estrutural | E44: m2 | F44: 8790.63 | G44: 9.1829 | H44: =F44*G44 -> 80723.476 | I44: Mantido conforme lançamento inicial pela GDI | J44: Lançado ERP
C45: 01.002.003.002 | D45: Projeto Hidrossanitário | E45: m2 | F45: 8790.63 | G45: 3.98 | H45: =F45*G45 -> 34986.707 | I45: Mantido conforme lançamento inicial pela GDI | J45: Lançado ERP
C46: 01.002.003.003 | D46: Projeto Elétrico / Telecom / Automação | E46: m2 | F46: 8790.63 | G46: 7.39 | H46: =F46*G46 -> 64962.756 | I46: Mantido conforme lançamento inicial pela GDI | J46: Lançado ERP
C47: 01.002.003.004 | D47: Projeto Preventivo | E47: vb | F47: 8790.63 | G47: 4.3 | H47: =F47*G47 -> 37799.709 | I47: Mantido conforme lançamento inicial pela GDI | J47: Lançado ERP
C48: 01.002.003.005 | D48: Projeto de Ar condicionado e Ventilação Mecânica | E48: m2 | F48: 8790.63 | G48: 3.75 | H48: =F48*G48 -> 32964.862 | I48: Mantido conforme lançamento inicial pela GDI | J48: Lançado ERP
C49: 01.002.003.006 | D49: Projeto de impermeabilização | E49: m2 | F49: 8790.63 | G49: 3.6 | H49: =F49*G49 -> 31646.268 | I49: Mantido conforme lançamento inicial pela GDI | J49: Lançado ERP
C50: 01.002.003.007 | D50: Revisão normativa e Análise de Desempenho | E50: m2 | F50: 8790.63 | G50: 6.35 | H50: =F50*G50 -> 55820.5 | I50: Mantido conforme lançamento inicial pela GDI | J50: Lançado ERP
C51: 01.002.003.008 | D51: Projeto Executivo Compatibilização | E51: m2 | F51: 8790.63 | G51: 17.4957 | H51: =F51*G51 -> 153798.23 | I51: Mantido conforme lançamento inicial pela GDI | J51: Lançado ERP
C52: 01.002.003.009 | D52: Projeto do canteiro de Obras - PGR | E52: m2 | F52: 8790.63 | G52: 1.5 | H52: =F52*G52 -> 13185.945 | I52: Mantido conforme lançamento inicial pela GDI | J52: Lançado ERP
C53: 01.002.003.010 | D53: Projeto de Piscina | E53: un | F53: 1 | G53: 30000 | H53: =F53*G53 -> 30000 | I53: Mantido conforme lançamento inicial pela GDI | J53: Lançado ERP
C54: 01.002.003.011 | D54: Projeto executivo Áres externas/Paisagismo | E54: vb | F54: 8790.63 | G54: 1.7 | H54: =F54*G54 -> 14944.071 | I54: Mantido conforme lançamento inicial pela GDI | J54: Lançado ERP
C55: 01.002.003.012 | D55: Projeto Elétrico Provisório de Canteiro | E55: vb | F55: 1 | G55: 8000 | H55: =F55*G55 -> 8000 | I55: Mantido conforme lançamento inicial pela GDI | J55: Lançado ERP
... C58: 01.002.003.015 | D58: Projeto de Irrigação Automática | E58: un | F58: 1 | G58: 6000 | H58: =F58*G58 -> 6000 | I58: Mantido conforme lançamento inicial pela GDI | J58: Lançado ERP
C59: 01.003 | D59: CONSULTAS DE VIABILIADE | H59: =H60 -> 179.34
C60: 01.003.001 | D60: CONSULTAS DE VIABILIADE PARA APROVAÇÃO DE PROJETOS | H60: =SUM(H61:H62) -> 179.34
C61: 01.003.001.001 | D61: Consulta de Viabilidade - Prefeitura Municipal | E61: vb | F61: 1 | G61: 87.28 | H61: =F61*G61 -> 87.28 | I61: Mantido conforme lançamento inicial pela GDI | J61: Lançado ERP
C62: 01.003.001.002 | D62: Consulta de Viabilidade - CASAN (agua e esgoto) | E62: vb | F62: 1 | G62: 92.06 | H62: =F62*G62 -> 92.06 | I62: Mantido conforme lançamento inicial pela GDI | J62: Lançado ERP
C63: 01.004 | D63: APROVACAO DE PROJETOS E LICENCIAMENTO | H63: =H64+H73 -> 1280189
C64: 01.004.001 | D64: PREFEITURA MUNICIPAL DE FLORIANÓPOLIS - SMDU | H64: =SUM(H65:H72) -> 1270262
C65: 01.004.001.001 | D65: Processo de Aprovação de Projeto Arquiteônico - PMF | E65: mês | F65: 1 | G65: 2000 | H65: =F65*G65 -> 2000 | I65: Mantido conforme lançamento inicial pela GDI | J65: Lançado ERP
C66: 01.004.001.002 | D66: Compra de TDC (Transferência de Direito de Construir) | E66: m2 | F66: 406.53 | G66: 3000 | H66: =F66*G66 -> 1219590 | I66: Mantido conforme lançamento inicial pela GDI - SUGERIDO REAPROPRIAÇÃO | J66: N/A
C67: 01.004.001.003 | D67: Taxa de Solo Criado (Outorga Onerosa) | E67: vb | F67: 1 | G67: 30548.85 | H67: =F67*G67 -> 30548.85 | I67: Mantido conforme lançamento inicial pela GDI | J67: Lançado ERP
C68: 01.004.001.004 | D68: Alvará de Construção - Taxa de Licensa de Obra - TLO/PMF | E68: m2 | F68: 8790.63 | G68: 1.8 | H68: =F68*G68 -> 15823.134 | I68: Mantido conforme lançamento inicial pela GDI | J68: Lançado ERP
C69: 01.004.001.005 | D69: Certidão de Atingimento Viário | E69: vb | F69: 1 | G69: 200 | H69: =F69*G69 -> 200 | I69: Mantido conforme lançamento inicial pela GDI | J69: Lançado ERP
C70: 01.004.001.006 | D70: Alvará de Construção - PMF | E70: vb | F70: 1 | G70: 2000 | H70: =F70*G70 -> 2000 | I70: Mantido conforme lançamento inicial pela GDI | J70: Lançado ERP
C71: 01.004.001.007 | D71: Renovação de Alvará de Construção - 1 | E71: vb | F71: 1 | G71: 50 | H71: =F71*G71 -> 50 | I71: Mantido conforme lançamento inicial pela GDI | J71: Lançado ERP
C72: 01.004.001.008 | D72: Renovação de Alvará de Construção - 2 | E72: vb | F72: 1 | G72: 50 | H72: =F72*G72 -> 50 | I72: Mantido conforme lançamento inicial pela GDI | J72: Lançado ERP
C73: 01.004.002 | D73: PREFEITURA MUNICIPAL DE FLORIANÓPOLIS - FLORAM | H73: =SUM(H74:H74) -> 9926.9856
C74: 01.004.002.001 | D74: Processo de Licenciamento Ambiental - LAP/LAI/LAO - FLORAM/FATMA | E74: m2 | F74: 3939.28 | G74: 2.52 | H74: =F74*G74 -> 9926.9856 | I74: Mantido conforme lançamento inicial pela GDI | J74: Lançado ERP
C75: 01.005 | D75: PREFEITURA MUNICIPAL DE FLORIANÓPOLIS - IPUF | H75: =H76+H78+H80+H82 -> 8000
C76: 01.005.001 | D76: PREFEITURA MUNICIPAL DE FLORIANÓPOLIS - VISA | H76: =H77 -> 2000
C77: 01.005.001.001 | D77: Processo de Aprovação de Projeto Hidrossanitário - PMF | E77: vb | F77: 1 | G77: 2000 | H77: =F77*G77 -> 2000 | I77: Mantido conforme lançamento inicial pela GDI | J77: Lançado ERP
C78: 01.005.002 | D78: CASAN | H78: =H79 -> 2000
C79: 01.005.002.001 | D79: Processo de Aprovação de Projeto Hidrossanitário - CASAN | E79: vb | F79: 1 | G79: 2000 | H79: =F79*G79 -> 2000 | I79: Mantido conforme lançamento inicial pela GDI | J79: Lançado ERP
C80: 01.005.003 | D80: CELESC | H80: =SUM(H81:H81) -> 2000
C81: 01.005.003.001 | D81: Processo de Aprovação de Projeto Elétrico - CELESC | E81: vb | F81: 1 | G81: 2000 | H81: =F81*G81 -> 2000 | I81: Mantido conforme lançamento inicial pela GDI | J81: Lançado ERP
C82: 01.005.004 | D82: CORPO DE BOMBEIROS DA POLÍCIA MILITAR | H82: =SUM(H83:H83) -> 2000
C83: 01.005.004.001 | D83: Processo de Aprovação do Projeto Preventivo Contra Incêndio - CBPM | E83: vb | F83: 1 | G83: 2000 | H83: =F83*G83 -> 2000 | I83: Mantido conforme lançamento inicial pela GDI | J83: Lançado ERP
C84: 01.006 | D84: SEGUROS | H84: =H85 -> 25000
C85: 01.006.001 | D85: SEGUROS | H85: =SUM(H86:H86) -> 25000
C86: 01.006.001.001 | D86: Seguro para Obras Civis em Construção (OCC) | E86: vb | F86: 1 | G86: 25000 | H86: =F86*G86 -> 25000 | I86: Mantido conforme lançamento inicial pela GDI | J86: Lançado ERP
C87: 01.007 | D87: PLANEJAMENTO E GESTÃO DO EMPREENDIMENTO | H87: =H88+H90+H99 -> 1591494.8
C88: 01.007.001 | D88: ORÇAMENTO E PLANEJAMENTO DO EMPREENDIMENTO | H88: =H89 -> 31000
C89: 01.007.001.001 | D89: Orçamento e Planejamento Play Negra (Cartesian) | E89: vb | F89: 1 | G89: 31000 | H89: =F89*G89 -> 31000 | I89: Mantido conforme lançamento inicial pela GDI | J89: Lançado ERP
C90: 01.007.002 | D90: ASSESSORIA CONTÁBIL E JURÍDICA | H90: =SUM(H91:H98) -> 94150
C91: 01.007.002.001 | D91: Abertura da SPE | E91: vb | F91: 1 | G91: 24000 | H91: =F91*G91 -> 24000 | I91: Mantido conforme lançamento inicial pela GDI - SUGERIDO REAPROPRIAÇÃO | J91: N/A
C92: 01.007.002.002 | D92: Serviços advocatícios 1 | E92: vb | F92: 1 | G92: 60000 | H92: =F92*G92 -> 60000 | I92: Mantido conforme lançamento inicial pela GDI - SUGERIDO REAPROPRIAÇÃO | J92: N/A
C93: 01.007.002.003 | D93: Serviços advocatícios 2 | E93: vb | F93: 1 | G93: 9000 | H93: =F93*G93 -> 9000 | I93: Mantido conforme lançamento inicial pela GDI - SUGERIDO REAPROPRIAÇÃO | J93: N/A
C94: 01.007.002.004 | D94: Contabilidade | E94: mês | F94: 25 | G94: 0 | H94: =F94*G94 -> 0 | I94: Mantido conforme lançamento inicial pela GDI - SUGERIDO REAPROPRIAÇÃO | J94: N/A
C95: 01.007.002.005 | D95: Despesas de Cartório | E95: vb | F95: 500 | G95: 1.8 | H95: =F95*G95 -> 900 | I95: Mantido conforme lançamento inicial pela GDI - SUGERIDO REAPROPRIAÇÃO | J95: N/A
C96: 01.007.002.006 | D96: Desenvolvimento Imobiliário | E96: vb | F96: 1 | G96: 200 | H96: =F96*G96 -> 200 | I96: Mantido conforme lançamento inicial pela GDI - SUGERIDO REAPROPRIAÇÃO | J96: N/A
C97: 01.007.002.007 | D97: Taxa de Viabilização do Empreendimento | E97: vb | F97: 1 | G97: 50 | H97: =F97*G97 -> 50 | I97: Mantido conforme lançamento inicial pela GDI - SUGERIDO REAPROPRIAÇÃO | J97: N/A
C98: 01.007.002.008 | D98: Assembléias e Reuniões de Conselho Fiscal | E98: vb | F98: 1 | G98: 0 | H98: =F98*G98 -> 0 | I98: Mantido conforme lançamento inicial pela GDI - SUGERIDO REAPROPRIAÇÃO | J98: N/A
C99: 01.007.003 | D99: ADMINISTRAÇÃO DO EMPREENDIMENTO | H99: =H100 -> 1466344.8
C100: 01.007.003.001 | D100: Administração do Empreendimento | E100: mês | F100: 48 | G100: 30548.85 | H100: =F100*G100 -> 1466344.8 | I100: Mantido conforme lançamento inicial pela GDI - SUGERIDO REAPROPRIAÇÃO | J100: N/A
C101: 01.008 | D101: IDENTIFICAÇÃO DE INVESTIDORES | H101: =H102 -> 1961288.7
C102: 01.008.001 | D102: IDENTIFICAÇÃO DE INVESTIDORES | H102: =SUM(H103:H170) -> 1961288.7
C103: 01.008.001.001 | D103: 101 | E103: un | F103: 1 | G103: 32104.53 | H103: =F103*G103 -> 32104.53 | J103: Lançado ERP
C104: 01.008.001.002 | D104: 102 | E104: un | F104: 1 | G104: 0 | H104: =F104*G104 -> 0 | J104: Lançado ERP
C105: 01.008.001.003 | D105: 103 | E105: un | F105: 1 | G105: 29162.47 | H105: =F105*G105 -> 29162.47 | J105: Lançado ERP
...

Sheet Ger_Executivo
B4: PROJETO: | C4: Playa Negra | I4: REVISÃO: | J4: DATA
B5: EMPRESA: | C5: GDI | I5: R00 - Patricia Bragato | J5: 45519
B6: GERENCIAMENTO EXECUTIVO
B7: Atalho | C7: Item | D7: Descrição | E7: Unidade | F7: Quant. | G7: Preço un | H7: Total | I7: Considerações | J7: Situação
C8: 01 | D8: EMPREITADA GLOBAL | H8: =H9 -> 9356622.6
C9: 01.001 | D9: EMPREITADA GLOBAL | H9: =H10 -> 9356622.6 | J9: -
C10: 01.002 | D10: EMPREITADA GLOBAL | H10: =H11 -> 9356622.6
C11: 01.002.000.001 | D11: Empreitada global | E11: vb | F11: 1 | G11: 9356622.6 | H11: =F11*G11 -> 9356622.6 | J11: Lançado ERP
C12: 02 | D12: SERVICOS PRELIMINARES | H12: =H13 -> 918379.52
C13: 02.001 | D13: SERVICOS PRELIMINARES | H13: =H14+H16+H28 -> 918379.52 | J13: -
C14: 02.001.001 | D14: SUPRESSAO VEGETAL | H14: =H15 -> 6000
C15: 02.001.001.001 | D15: Corte de Arvores conforme licenciamento ambiental | E15: vb | F15: 1 | G15: 6000 | H15: =F15*G15 -> 6000 | I15: Mantido conforme lançamento inicial pela GDI - SUGERIDO REAPROPRIAÇÃO | J15: Lançado ERP
C16: 02.001.002 | D16: IMPLANTACAO DO CANTEIRO DE OBRAS - FASE 1 - ESCAVACAO | H16: =SUM(H17:H27) -> 642473.95
C17: 02.001.002.001 | D17: Fornecimento de internet | E17: un | F17: 1 | G17: 5000 | H17: =F17*G17 -> 5000 | I17: Mantido conforme lançamento inicial pela GDI - SUGERIDO REAPROPRIAÇÃO | J17: Lançado ERP
C18: 02.001.002.002 | D18: Mão de Obra - Implantação do canteiros de Obras | E18: un | F18: 1 | G18: 449117.89 | H18: =F18*G18 -> 449117.89 | I18: Mantido conforme lançamento inicial pela GDI - SUGERIDO REAPROPRIAÇÃO | J18: Lançado ERP
C19: 02.001.002.003 | D19: Organização canteiro de obras | E19: vb | F19: 1 | G19: 15000 | H19: =F19*G19 -> 15000 | I19: Mantido conforme lançamento inicial pela GDI - SUGERIDO REAPROPRIAÇÃO | J19: Lançado ERP
C20: 02.001.002.004 | D20: Implantação do canteiro de obras | E20: un | F20: 1 | G20: 60000 | H20: =F20*G20 -> 60000 | I20: Mantido conforme lançamento inicial pela GDI - SUGERIDO REAPROPRIAÇÃO | J20: Lançado ERP
C21: 02.001.002.005 | D21: Container | E21: un | F21: 2 | G21: 24000 | H21: =F21*G21 -> 48000 | I21: Mantido conforme lançamento inicial pela GDI - SUGERIDO REAPROPRIAÇÃO | J21: Lançado ERP
C22: 02.001.002.006 | D22: Locação de sanitários químicos | E22: un | F22: 10 | G22: 4306.45 | H22: =F22*G22 -> 43064.5 | I22: Mantido conforme lançamento inicial pela GDI - SUGERIDO REAPROPRIAÇÃO | J22: Lançado ERP
C23: 02.001.002.007 | D23: Ligacao de Energia para o Canteiro de Obras | E23: vb | F23: 1 | G23: 0 | H23: =F23*G23 -> 0 | I23: Mantido conforme lançamento inicial pela GDI - SUGERIDO REAPROPRIAÇÃO | J23: Lançado ERP
C24: 02.001.002.008 | D24: Ligação de Água para o Canteiro de Obras | E24: vb | F24: 1 | G24: 0 | H24: =F24*G24 -> 0 | I24: Mantido conforme lançamento inicial pela GDI - SUGERIDO REAPROPRIAÇÃO | J24: Lançado ERP
C25: 02.001.002.009 | D25: Banheiros | E25: vb | F25: 1 | G25: 0 | H25: =F25*G25 -> 0 | I25: Mantido conforme lançamento inicial pela GDI - SUGERIDO REAPROPRIAÇÃO | J25: Lançado ERP
C26: 02.001.002.010 | D26: Refeitorio | E26: vb | F26: 1 | G26: 0 | H26: =F26*G26 -> 0 | I26: Mantido conforme lançamento inicial pela GDI - SUGERIDO REAPROPRIAÇÃO | J26: Lançado ERP
C27: 02.001.002.011 | D27: Instalações de Segurança para Canteiros de Obras | E27: un | F27: 36 | G27: 619.21 | H27: =F27*G27 -> 22291.56 | I27: Mantido conforme lançamento inicial pela GDI - SUGERIDO REAPROPRIAÇÃO | J27: Lançado ERP
C28: 02.001.003 | D28: SEGURANÇA DO TRABALHO | H28: =SUM(H29:H32) -> 269905.57
C29: 02.001.003.001 | D29: Acompanhamento Técnico em Segurança no Trabalho | E29: mes | F29: 30 | G29: 1200 | H29: =F29*G29 -> 36000 | I29: Mantido conforme lançamento inicial pela GDI - SUGERIDO REAPROPRIAÇÃO | J29: Lançado ERP
C30: 02.001.003.002 | D30: Mão de obra - itens de segurança | E30: vb | F30: 1 | G30: 46783.11 | H30: =F30*G30 -> 46783.11 | J30: Lançado ERP
C31: 02.001.003.003 | D31: Mão de obra - instalações provisórias | E31: vb | F31: 1 | G31: 93566.23 | H31: =F31*G31 -> 93566.23 | J31: Lançado ERP
C32: 02.001.003.004 | D32: Mão de obra - guarda corpo e proteções | E32: vb | F32: 1 | G32: 93556.23 | H32: =F32*G32 -> 93556.23 | J32: Lançado ERP
C33: 03 | D33: MOVIMENTAÇÃO DE TERRA | H33: =H34 -> 748566.23 | I33: Mantido conforme lançamento inicial pela GDI
C34: 03.001 | D34: MOVIMENTAÇÃO DE TERRA | H34: =H35+H37+H39 -> 748566.23 | J34: -
C35: 03.001.001 | D35: ESCAVAÇÃO | H35: =H36 -> 605000
C36: 03.001.001.001 | D36: Escavação dos Subsolos e Remoção do Solo | E36: un | F36: 1 | G36: 605000 | H36: =F36*G36 -> 605000 | J36: Lançado ERP
C37: 03.001.002 | D37: RETIRADA DE ENTULHO E LIMPEZA DA OBRA | H37: =H38 -> 50000
C38: 03.001.002.001 | D38: Caçamba para remoção de entulho | E38: un | F38: 1 | G38: 50000 | H38: =F38*G38 -> 50000 | J38: Lançado ERP
C39: 03.001.003 | D39: MÃO DE OBRA | H39: =SUM(H40:H41) -> 93566.226
C40: 03.001.003.001 | D40: Mão de obra - movimentação de terra | E40: vb | F40: 1 | G40: ='MÃO DE OBRA '!E25 -> 46783.113 | H40: =F40*G40 -> 46783.113 | J40: Lançado ERP
C41: 03.001.003.002 | D41: Mão de obra - locação | E41: vb | F41: 1 | G41: ='MÃO DE OBRA '!E27 -> 46783.113 | H41: =F41*G41 -> 46783.113 | J41: Lançado ERP
C42: 04 | D42: CONTENÇÕES | H42: =H43+H49 -> 785740.88 | I42: Mantido conforme lançamento inicial pela GDI
C43: 04.001 | D43: PAREDE CORTINA | H43: =H44 -> 275000 | J43: -
C44: 04.001.001 | D44: PAREDE CORTINA | H44: =SUM(H45:H48) -> 275000
C45: 04.001.001.001 | D45: Concreto - C40 com Impermeabilizante | E45: un | F45: 1 | G45: 100000 | H45: =F45*G45 -> 100000 | J45: Lançado ERP
C46: 04.001.001.002 | D46: Controle tecnológico do Concreto - Cortina de contenção | E46: un | F46: 1 | G46: 60000 | H46: =F46*G46 -> 60000 | J46: Lançado ERP
C47: 04.001.001.003 | D47: Cortina de Contenção | E47: un | F47: 1 | G47: 100000 | H47: =F47*G47 -> 100000 | J47: Lançado ERP
C48: 04.001.001.004 | D48: Forma da Viga Baldrame | E48: un | F48: 1 | G48: 15000 | H48: =F48*G48 -> 15000 | J48: Lançado ERP
C49: 04.002 | D49: PAREDE DIAFRAGMA | H49: =H50+H52+H55+H60 -> 510740.88 | J49: -
C50: 04.002.001 | D50: PAREDE DIAFRAGMA | H50: =H51 -> 153856.8
C51: 04.002.001.001 | D51: Concreto Fck: 30 MPa | E51: un | F51: 301.68 | G51: 510 | H51: =F51*G51 -> 153856.8 | J51: Lançado ERP
C52: 04.002.002 | D52: MURETA GUIA | H52: =SUM(H53:H54) -> 66750
C53: 04.002.002.001 | D53: Forma de compensado plastificado | E53: un | F53: 120 | G53: 0 | H53: =F53*G53 -> 0 | J53: Lançado ERP
C54: 04.002.002.002 | D54: Concreto Fck: 15MPa | E54: m3 | F54: 150 | G54: 445 | H54: =F54*G54 -> 66750 | J54: Lançado ERP
C55: 04.002.003 | D55: EXECUCAO DAS LAMELAS | H55: =SUM(H56:H59) -> 290134.08
C56: 04.002.003.001 | D56: Mão de obra - Mobilização das lamelas | E56: un | F56: 1 | G56: 14000 | H56: =F56*G56 -> 14000 | J56: Lançado ERP
C57: 04.002.003.002 | D57: Armadura das Lamelas | E57: kg | F57: 1 | G57: 179743.28 | H57: =F57*G57 -> 179743.28 | J57: Lançado ERP
C58: 04.002.003.003 | D58: Mao de Obra para corte, dobra e montagem da armadura das Lamelas | E58: kg | F58: 29463.6 | G58: 3 | H58: =F58*G58 -> 88390.8 | J58: Lançado ERP
C59: 04.002.003.004 | D59: Locação | E59: un | F59: 1 | G59: 8000 | H59: =F59*G59 -> 8000 | J59: Lançado ERP
C60: 04.002.004 | D60: VIGA DE SOLIDARIZACAO | H60: =H61 -> 0
C61: 04.002.004.001 | D61: Mão de obra para da viga de solidarização | E61: vb | F61: 0 | G61: 0 | H61: =F61*G61 -> 0 | J61: Lançado ERP
C62: 05 | D62: INFRAESTRUTURA | H62: =H63+H69 -> 789129.75
C63: 05.001 | D63: INFRAESTRUTURA | H63: =SUM(H65:H68) -> 363621.4
C64: 05.001.001 | D64: FUNDAÇÃO RASA | H64: =SUM(H65:H68) -> 363621.4
C65: 05.001.001.001 | D65: locação das sapatas | E65: un | F65: 1 | G65: 8000 | H65: =F65*G65 -> 8000 | I65: Mantido conforme lançamento inicial pela GDI - SUGERIDO REAPROPRIAÇÃO | J65: Lançado ERP
C66: 05.001.001.002 | D66: Mão de Obra - Execução das sapatas | E66: un | F66: 1 | G66: 200000 | H66: =F66*G66 -> 200000 | I66: Mantido conforme lançamento inicial pela GDI - SUGERIDO REAPROPRIAÇÃO | J66: Lançado ERP
C67: 05.001.001.003 | D67: AÇO | E67: un | F67: 1 | G67: 55621.4 | H67: =F67*G67 -> 55621.4 | I67: Mantido conforme lançamento inicial pela GDI - SUGERIDO REAPROPRIAÇÃO | J67: Lançado ERP
C68: 05.001.001.004 | D68: Concreto fck40 | E68: un | F68: 1 | G68: 100000 | H68: =F68*G68 -> 100000 | I68: Mantido conforme lançamento inicial pela GDI - SUGERIDO REAPROPRIAÇÃO | J68: Lançado ERP
C69: 05.002 | D69: FUNDAÇÃO RASA (CARTESIAN) | H69: =H70+H72+H77+H80 -> 425508.35 | J69: -
C70: 05.002.001 | D70: FORMA | H70: =H71 -> 8608.9492
C71: 05.002.001.001 | D71: Fabricação, montagem e desmontagem de fôrma para sapatas, em madeira serrada | E71: m2 | F71: =Estrutura!N10 -> 143.6 | G71: 59.9509 | H71: =F71*G71 -> 8608.9492 | J71: Lançado ERP
C72: 05.002.002 | D72: ARMADURA | H72: =SUM(H73:H76) -> 78400.359
C73: 05.002.002.001 | D73: Armação aço CA-50 ø 10,0mm para infraestrutura (corte e dobra em obra) | E73: kg | F73: =Estrutura!E10 -> 157 | G73: 7.2387 | H73: =F73*G73 -> 1136.4759 | I73: Conforme quantitativo do projetista, custo cotação encaminhada pela GDI, 10% de perda | J73: Lançado ERP
C74: 05.002.002.002 | D74: Armação aço CA-50 ø 12,5mm para infraestrutura (corte e dobra em obra) | E74: kg | F74: =Estrutura!F10 -> 1013 | G74: 7.1947 | H74: =F74*G74 -> 7288.2311 | I74: Conforme quantitativo do projetista, custo cotação encaminhada pela GDI, 10% de perda | J74: Lançado ERP
C75: 05.002.002.003 | D75: Armação aço CA-50 ø 16,0mm para infraestrutura (corte e dobra em obra) | E75: kg | F75: =Estrutura!G10 -> 7426 | G75: 7.1947 | H75: =F75*G75 -> 53427.842 | I75: Conforme quantitativo do projetista, custo cotação encaminhada pela GDI, 10% de perda | J75: Lançado ERP
C76: 05.002.002.004 | D76: Armação aço CA-50 ø 20,0mm para infraestrutura (corte e dobra em obra) | E76: kg | F76: =Estrutura!H10 -> 2300 | G76: 7.1947 | H76: =F76*G76 -> 16547.81 | I76: Conforme quantitativo do projetista, custo cotação encaminhada pela GDI, 10% de perda | J76: Lançado ERP
C77: 05.002.003 | D77: CONCRETO | H77: =SUM(H78:H79) -> 148580.56
C78: 05.002.003.001 | D78: Concreto usinado bombeável, para sapatas, fck 40MPa, slump 22+/- 3, incluindo serviço de bombeamento | E78: m3 | F78: =Estrutura!M10 -> 240.8 | G78: 599.6189 | H78: =F78*G78 -> 144388.23 | J78: Lançado ERP
C79: 05.002.003.002 | D79: Controle tecnológico do concreto | E79: m3 | F79: =F78 -> 240.8 | G79: 17.41 | H79: =F79*G79 -> 4192.328 | J79: Lançado ERP
C80: 05.002.004 | D80: MÃO DE OBRA | H80: =SUM(H81:H82) -> 189918.48 | K80: =H81+H110+H135+H160+H185+H210+H235+H260+H284 -> 2769560.3
C81: 05.002.004.001 | D81: Mão de obra - execução de infraestrutura | E81: vb | F81: 1 | G81: 181518.48 | H81: =F81*G81 -> 181518.48 | I81: Ajuste realizado conforme alinhamento da reunião do dia 18/12/2024. | J81: Lançado ERP
C82: 05.002.004.002 | D82: Acompanhamento topográfico para locação | E82: dia | F82: 6 | G82: 1400 | H82: =F82*G82 -> 8400 | J82: Lançado ERP
C83: 06 | D83: SUPRAESTRUTURA | H83: =H84+H112+H137+H162+H187+H212+H237+H262 -> 5968880.7
C84: 06.001 | D84: SUPRAESTRUTURA - SUBSOLO 2 | H84: =H85+H94+H104+H107+H110 -> 448921.1
C85: 06.001.001 | D85: FORMA | H85: =SUM(H86:H93) -> 211424.09
C86: 06.001.001.001 | D86: Fabricação de fôrma para pilares em chapa de madeira compensada plastificada e=14 mm - 2 jogos | E86: m2 | F86: =Estrutura!N41*2 -> 437.4 | G86: 149.3967 | H86: =F86*G86 -> 65346.117 | I86: Consideração de 2 jogos referentes ao pavimento tipo | J86: Lançado ERP
C87: 06.001.001.002 | D87: Fabricação de fôrma para escadarias em chapa de madeira compensada plastificada e=14 mm - 2 jogos | E87: m2 | F87: =Estrutura!N44*2 -> 59.40766 | G87: 179.9145 | H87: =F87*G87 -> 10688.299 | I87: Consideração de 2 jogos referentes ao pavimento tipo | J87: Lançado ERP
C88: 06.001.001.003 | D88: Fabricação de fôrma para vigas em chapa de madeira compensada plastificada e=14 mm - 2 jogos | E88: m2 | F88: =Estrutura!N42*2 -> 545 | G88: 96.8794 | H88: =F88*G88 -> 52799.273 | I88: Consideração de 2 jogos referentes ao pavimento tipo | J88: Lançado ERP
C89: 06.001.001.004 | D89: Fabricação de fôrma para laje em chapa de madeira compensada plastificada e=14 mm - 2 jogos | E89: m2 | F89: =Estrutura!N43*2 -> 1141 | G89: 71.5501 | H89: =F89*G89 -> 81638.664 | I89: Consideração de 2 jogos referentes ao pavimento tipo | J89: Lançado ERP
C90: 06.001.001.005 | D90: Montagem e desmontagem de fôrma para pilares em chapa de madeira compensada plastificada | E90: m2 | F90: =Estrutura!N16 -> 89.1 | G90: 0.8509 | H90: =F90*G90 -> 75.81519 | I90: Conforme quantitativo do projetista | J90: Lançado ERP
C91: 06.001.001.006 | D91: Montagem e desmontagem de fôrma para escadarias em chapa de madeira compensada plastificada | E91: m2 | F91: =Estrutura!N19 -> 12.9024 | G91: 1.4884 | H91: =F91*G91 -> 19.203932 | I91: Conforme quantitativo do projetista | J91: Lançado ERP
C92: 06.001.001.007 | D92: Montagem e desmontagem de fôrma para vigas em chapa de madeira compensada plastificada | E92: m2 | F92: =Estrutura!N17 -> 284.8 | G92: 2.9099 | H92: =F92*G92 -> 828.73952 | I92: Conforme quantitativo do projetista | J92: Lançado ERP
C93: 06.001.001.008 | D93: Montagem e desmontagem de fôrma para laje em chapa de madeira compensada plastificada | E93: m2 | F93: =Estrutura!N18 -> 52 | G93: 0.538 | H93: =F93*G93 -> 27.976 | I93: Conforme quantitativo do projetista | J93: Lançado ERP
C94: 06.001.002 | D94: ARMADURA | H94: =SUM(H95:H103) -> 88864.275
C95: 06.001.002.001 | D95: Armação aço CA-60 ø 5.0mm para supraestrutura (corte e dobra em indústria) | E95: kg | F95: =Estrutura!B15 -> 236 | G95: 7.2244 | H95: =F95*G95 -> 1704.9584 | I95: Conforme quantitativo do projetista, custo cotação encaminhada pela GDI, sem perda | J95: Lançado ERP
C96: 06.001.002.002 | D96: Armacao aco CA-50 ø 6.3mm para supraestrutura (corte e dobra em indústria) | E96: kg | F96: =Estrutura!C15 -> 660 | G96: 7.3449 | H96: =F96*G96 -> 4847.634 | I96: Conforme quantitativo do projetista, custo cotação encaminhada pela GDI, sem perda | J96: Lançado ERP
C97: 06.001.002.003 | D97: Armacao aco CA-50 ø 8.0mm para supraestrutura (corte e dobra em indústria) | E97: kg | F97: =Estrutura!D15 -> 175 | G97: 6.8668 | H97: =F97*G97 -> 1201.69 | I97: Conforme quantitativo do projetista, custo cotação encaminhada pela GDI, sem perda | J97: Lançado ERP
C98: 06.001.002.004 | D98: Armacao aco CA-50 ø 10.0mm para supraestrutura (corte e dobra em indústria) | E98: kg | F98: =Estrutura!E15 -> 1415 | G98: 6.5303 | H98: =F98*G98 -> 9240.3745 | I98: Conforme quantitativo do projetista, custo cotação encaminhada pela GDI, sem perda | J98: Lançado ERP
C99: 06.001.002.005 | D99: Armacao aco CA-50 ø 12.5mm para supraestrutura (corte e dobra em indústria) | E99: kg | F99: =Estrutura!F15 -> 1119 | G99: 6.4609 | H99: =F99*G99 -> 7229.7471 | I99: Conforme quantitativo do projetista, custo cotação encaminhada pela GDI, sem perda | J99: Lançado ERP
C100: 06.001.002.006 | D100: Armacao aco CA-50 ø 16.0mm para supraestrutura (corte e dobra em indústria) | E100: kg | F100: =Estrutura!G15 -> 990 | G100: 6.5351 | H100: =F100*G100 -> 6469.749 | I100: Conforme quantitativo do projetista, custo cotação encaminhada pela GDI, sem perda | J100: Lançado ERP
C101: 06.001.002.007 | D101: Armacao aco CA-50 ø 20.0mm para supraestrutura, (corte e dobra em indústria) | E101: kg | F101: =Estrutura!H15 -> 1748 | G101: 6.3851 | H101: =F101*G101 -> 11161.155 | I101: Conforme quantitativo do projetista, custo cotação encaminhada pela GDI, sem perda | J101: Lançado ERP
C102: 06.001.002.008 | D102: Armacao aco CA-50 ø 25.0mm para supraestrutura (corte e dobra em indústria) | E102: kg | F102: =Estrutura!I15 -> 620 | G102: 6.3851 | H102: =F102*G102 -> 3958.762 | I102: Conforme quantitativo do projetista, custo cotação encaminhada pela GDI, sem perda | J102: Lançado ERP
C103: 06.001.002.009 | D103: Armacao aco tela Q138 para supraestrutura (corte e dobra em obra) | E103: kg | F103: =Estrutura!L15 -> 4510 | G103: 9.5455 | H103: =F103*G103 -> 43050.205 | I103: Conforme quantitativo do projetista, 10% de perda | J103: Lançado ERP
...

Sheet ORÇ MAO DE OBRA
B4: PROJETO: | C4: Playa Negra | I4: REVISÃO: | J4: DATA
B5: EMPRESA: | C5: GDI | I5: R00 - Patricia Bragato | J5: 45519
B6: Atalho | C6: Item | D6: Descrição | E6: Unidade | F6: Quant. | G6: Preço un | H6: Total | I6: Considerações | J6: Situação
B7: GERENCIAMENTO TECNICO E ADMINISTRATIVO
C8: 02 | D8: SERVIÇOS INICIAIS | H8: =H9 -> 449117.89
C9: 02.002 | D9: ADMINISTRAÇÃO E CANTEIRO DE OBRA | H9: =H10 -> 449117.89 | J9: -
C10: 02.002.004 | D10: Instalações provisórias | H10: =H11 -> 449117.89
C11: 02.002.004.007 | D11: Mão de Obra - Implantação do canteiros de Obras | E11: un | F11: 1 | G11: 449117.89 | H11: =F11*G11 -> 449117.89 | I11: Mantido conforme lançamento inicial pela GDI, ajuste de unidade e alocação na estrutura | J11: Lançado ERP
B12: GERENCIAMENTO EXECUTIVO
C13: 03 | D13: MOVIMENTAÇÃO DE TERRA | H13: =H14 -> 93566.226 | I13: Mantido conforme lançamento inicial pela GDI
C14: 03.001 | D14: MOVIMENTAÇÃO DE TERRA | H14: =H15 -> 93566.226 | J14: -
C15: 03.001.003 | D15: MÃO DE OBRA | H15: =SUM(H16:H17) -> 93566.226
C16: 03.001.003.001 | D16: Mão de obra - movimentação de terra | E16: vb | F16: 1 | G16: ='MÃO DE OBRA '!E25 -> 46783.113 | H16: =F16*G16 -> 46783.113 | J16: Lançado ERP
C17: 03.001.003.002 | D17: Mão de obra - locação | E17: vb | F17: 1 | G17: ='MÃO DE OBRA '!E27 -> 46783.113 | H17: =F17*G17 -> 46783.113 | J17: Lançado ERP
C18: 05 | D18: INFRAESTRUTURA | H18: =H19 -> 189918.48 | K18: =H21+H23 -> 2769560.3
C19: 05.001 | D19: INFRAESTRUTURA | H19: =H20 -> 189918.48
C20: 05.002.004 | D20: MÃO DE OBRA | H20: =SUM(H21:H22) -> 189918.48
C21: 05.002.004.001 | D21: Mão de obra - execução de infraestrutura | E21: vb | F21: 1 | G21: 181518.48 | H21: =F21*G21 -> 181518.48 | I21: Ajuste realizado conforme alinhamento da reunião do dia 18/12/2024. | J21: Lançado ERP
C22: 05.002.004.002 | D22: Acompanhamento topográfico para locação | E22: dia | F22: 6 | G22: 1400 | H22: =F22*G22 -> 8400 | J22: Lançado ERP
C23: 06 | D23: SUPRAESTRUTURA | H23: =H24+H27+H30+H33+H36+H39+H42+H45 -> 2588041.8
C24: 06.001 | D24: SUPRAESTRUTURA - SUBSOLO 2 | H24: =H25 -> 112279.47
C25: 06.001.005 | D25: MÃO DE OBRA | H25: =H26 -> 112279.47
C26: 06.001.005.001 | D26: Mão de obra - execução de supraestrutura | E26: vb | F26: 1 | G26: 112279.47 | H26: =F26*G26 -> 112279.47 | I26: Ajuste realizado conforme alinhamento da reunião do dia 18/12/2024. | J26: Lançado ERP
C27: 06.002 | D27: SUPRAESTRUTURA - SUBSOLO 1 | H27: =H28 -> 318125.17
C28: 06.002.005 | D28: MÃO DE OBRA | H28: =H29 -> 318125.17
C29: 06.002.005.001 | D29: Mão de obra - execução de supraestrutura | E29: vb | F29: 1 | G29: 318125.17 | H29: =F29*G29 -> 318125.17 | I29: Ajuste realizado conforme alinhamento da reunião do dia 18/12/2024. | J29: Lançado ERP
C30: 06.003 | D30: SUPRAESTRUTURA - TÉRREO | H30: =H31 -> 435082.95
C31: 06.003.005 | D31: MÃO DE OBRA | H31: =H32 -> 435082.95
C32: 06.003.005.001 | D32: Mão de obra - execução de supraestrutura | E32: vb | F32: 1 | G32: 435082.95 | H32: =F32*G32 -> 435082.95 | I32: Ajuste realizado conforme alinhamento da reunião do dia 18/12/2024. | J32: Lançado ERP
C33: 06.004 | D33: SUPRAESTRUTURA - SOBRELOJA | H33: =H34 -> 56139.74
C34: 06.004.005 | D34: MÃO DE OBRA | H34: =H35 -> 56139.74
C35: 06.004.005.001 | D35: Mão de obra - execução de supraestrutura | E35: vb | F35: 1 | G35: 56139.74 | H35: =F35*G35 -> 56139.74 | I35: Ajuste realizado conforme alinhamento da reunião do dia 18/12/2024. | J35: Lançado ERP
C36: 06.005 | D36: SUPRAESTRUTURA - TIPO 1 | H36: =H37 -> 182454.14
C37: 06.005.005 | D37: MÃO DE OBRA | H37: =H38 -> 182454.14
C38: 06.005.005.001 | D38: Mão de obra - execução de supraestrutura | E38: vb | F38: 1 | G38: 182454.14 | H38: =F38*G38 -> 182454.14 | I38: Ajuste realizado conforme alinhamento da reunião do dia 18/12/2024. | J38: Lançado ERP
C39: 06.006 | D39: SUPRAESTRUTURA - TIPO 2 (x6) | H39: =H40 -> 1094724.9
C40: 06.006.005 | D40: MÃO DE OBRA | H40: =H41 -> 1094724.9
C41: 06.006.005.001 | D41: Mão de obra - execução de supraestrutura | E41: vb | F41: 1 | G41: 1094724.9 | H41: =F41*G41 -> 1094724.9 | I41: Ajuste realizado conforme alinhamento da reunião do dia 18/12/2024. | J41: Lançado ERP
C42: 06.007 | D42: SUPRAESTRUTURA - ÁTICO | H42: =H43 -> 182454.14
C43: 06.007.005 | D43: MÃO DE OBRA | H43: =H44 -> 182454.14
C44: 06.007.005.001 | D44: Mão de obra - execução de supraestrutura | E44: vb | F44: 1 | G44: 182454.14 | H44: =F44*G44 -> 182454.14 | I44: Ajuste realizado conforme alinhamento da reunião do dia 18/12/2024. | J44: Lançado ERP
C45: 06.008 | D45: SUPRAESTRUTURA - BARRILETE/RESERVATÓRIO | H45: =H46 -> 206781.36
C46: 06.008.005 | D46: MÃO DE OBRA | H46: =H47 -> 206781.36
C47: 06.008.005.001 | D47: Mão de obra - execução de supraestrutura | E47: vb | F47: 1 | G47: 206781.36 | H47: =F47*G47 -> 206781.36 | I47: Ajuste realizado conforme alinhamento da reunião do dia 18/12/2024. | J47: Lançado ERP
C48: 07 | D48: ALVENARIA E VEDAÇÕES | H48: =H49+H54+H59+H65+H70+H76+H82+H87 -> 650285.27 | I48: Distribuição por pavimento não bate com separação previa da empreitada pela distribuição de uqantitativos, porém soma da etapa é equivalente
C49: 07.001 | D49: ALVENARIA E VEDAÇÕES - SUBSOLO 2 | H49: =H50 -> 9752.5573
C50: 07.001.004 | D50: MÃO DE OBRA | H50: =SUM(H51:H53) -> 9752.5573 | L50: =H50+H55+H60+H66+H71+H77+H83+H88 -> 650285.27
C51: 07.001.004.001 | D51: Mão de obra - salpico ou pinos colunas e vigas / marcação | E51: m2 | F51: 125.33 | G51: ='MÃO DE OBRA '!$E$166 -> 9.1990689 | H51: =F51*G51 -> 1152.9193 | J51: Lançado ERP | L51: =H51+H56+H61+H67+H72+H78+H84 -> 65496.358
C52: 07.001.004.002 | D52: Mão de obra - paredes / vergas e contra-vergas | E52: m2 | F52: 125.33 | G52: ='MÃO DE OBRA '!$E$168 -> 56.508566 | H52: =F52*G52 -> 7082.2186 | J52: Lançado ERP | L52: =H52+H57+H62+H68+H73+H79+H85 -> 402334.77
C53: 07.001.004.003 | D53: Mão de obra - muchetas / encunhamento | E53: m2 | F53: 14.59 | G53: ='MÃO DE OBRA '!$E$170 -> 104.00408 | H53: =F53*G53 -> 1517.4195 | J53: Lançado ERP | L53: =H53+H58+H63+H69+H74+H80+H86 -> 93566.226
C54: 07.002 | D54: ALVENARIA E VEDAÇÕES - SUBSOLO 1 | H54: =H55 -> 13108.506 | L54: =H75+H81 -> 28069.868
C55: 07.002.004 | D55: MÃO DE OBRA | H55: =SUM(H56:H58) -> 13108.506
C56: 07.002.004.001 | D56: Mão de obra - salpico ou pinos colunas e vigas / marcação | E56: m2 | F56: 170.5 | G56: ='MÃO DE OBRA '!$E$166 -> 9.1990689 | H56: =F56*G56 -> 1568.4412 | J56: Lançado ERP
C57: 07.002.004.002 | D57: Mão de obra - paredes / vergas e contra-vergas | E57: m2 | F57: 170.5 | G57: ='MÃO DE OBRA '!$E$168 -> 56.508566 | H57: =F57*G57 -> 9634.7105 | J57: Lançado ERP
C58: 07.002.004.003 | D58: Mão de obra - muchetas / encunhamento | E58: m2 | F58: 18.32 | G58: ='MÃO DE OBRA '!$E$170 -> 104.00408 | H58: =F58*G58 -> 1905.3547 | J58: Lançado ERP
C59: 07.003 | D59: ALVENARIA E VEDAÇÕES - TÉRREO | H59: =H60 -> 63144.417
C60: 07.003.004 | D60: MÃO DE OBRA | H60: =SUM(H61:H64) -> 63144.417
C61: 07.003.004.001 | D61: Mão de obra - salpico ou pinos colunas e vigas / marcação | E61: m2 | F61: 620.97 | G61: ='MÃO DE OBRA '!$E$166 -> 9.1990689 | H61: =F61*G61 -> 5712.3458 | J61: Lançado ERP
C62: 07.003.004.002 | D62: Mão de obra - paredes / vergas e contra-vergas | E62: m2 | F62: 620.97 | G62: ='MÃO DE OBRA '!$E$168 -> 56.508566 | H62: =F62*G62 -> 35090.124 | J62: Lançado ERP
C63: 07.003.004.003 | D63: Mão de obra - muchetas / encunhamento | E63: m2 | F63: 34.89 | G63: ='MÃO DE OBRA '!$E$170 -> 104.00408 | H63: =F63*G63 -> 3628.7022 | J63: Lançado ERP
C64: 07.003.004.004 | D64: Mão de obra - serviços de alvenaria em áreas externa (central de gás, guarita, lixeira, floreiras) | E64: vb | F64: 1 | G64: ='MÃO DE OBRA '!E120 -> 18713.245 | H64: =F64*G64 -> 18713.245 | J64: Lançado ERP
C65: 07.004 | D65: ALVENARIA E VEDAÇÕES - SOBRELOJA | H65: =H66 -> 26100.642
C66: 07.004.004 | D66: MÃO DE OBRA | H66: =SUM(H67:H69) -> 26100.642
C67: 07.004.004.001 | D67: Mão de obra - salpico ou pinos colunas e vigas / marcação | E67: m2 | F67: 338.58 | G67: ='MÃO DE OBRA '!$E$166 -> 9.1990689 | H67: =F67*G67 -> 3114.6207 | J67: Lançado ERP
C68: 07.004.004.002 | D68: Mão de obra - paredes / vergas e contra-vergas | E68: m2 | F68: 338.58 | G68: ='MÃO DE OBRA '!$E$168 -> 56.508566 | H68: =F68*G68 -> 19132.67 | J68: Lançado ERP
C69: 07.004.004.003 | D69: Mão de obra - muchetas / encunhamento | E69: m2 | F69: 37.05 | G69: ='MÃO DE OBRA '!$E$170 -> 104.00408 | H69: =F69*G69 -> 3853.351 | J69: Lançado ERP
C70: 07.005 | D70: ALVENARIA E VEDAÇÕES - TIPO 1 | H70: =H71 -> 67618.842
C71: 07.005.004 | D71: MÃO DE OBRA | H71: =SUM(H72:H75) -> 67618.842
C72: 07.005.004.001 | D72: Mão de obra - salpico ou pinos colunas e vigas / marcação | E72: m2 | F72: 791.32 | G72: ='MÃO DE OBRA '!$E$166 -> 9.1990689 | H72: =F72*G72 -> 7279.4072 | J72: Lançado ERP
C73: 07.005.004.002 | D73: Mão de obra - paredes / vergas e contra-vergas | E73: m2 | F73: 791.32 | G73: ='MÃO DE OBRA '!$E$168 -> 56.508566 | H73: =F73*G73 -> 44716.358 | J73: Lançado ERP
C74: 07.005.004.003 | D74: Mão de obra - muchetas / encunhamento | E74: m2 | F74: 111.66 | G74: ='MÃO DE OBRA '!$E$170 -> 104.00408 | H74: =F74*G74 -> 11613.095 | J74: Lançado ERP
C75: 07.005.004.004 | D75: Mão de obra - assentamento de tijolos refratários | E75: m2 | F75: 12.6915 | G75: ='MÃO DE OBRA '!$E$172 -> 315.95801 | H75: =F75*G75 -> 4009.9811 | J75: Lançado ERP
C76: 07.006 | D76: ALVENARIA E VEDAÇÕES - TIPO 2 (x6) | H76: =H77 -> 401310.55
C77: 07.006.004 | D77: MÃO DE OBRA | H77: =SUM(H78:H81) -> 401310.55
C78: 07.006.004.001 | D78: Mão de obra - salpico ou pinos colunas e vigas / marcação | E78: m2 | F78: 4708.08 | G78: ='MÃO DE OBRA '!$E$166 -> 9.1990689 | H78: =F78*G78 -> 43309.952 | J78: Lançado ERP
C79: 07.006.004.002 | D79: Mão de obra - paredes / vergas e contra-vergas | E79: m2 | F79: 4708.08 | G79: ='MÃO DE OBRA '!$E$168 -> 56.508566 | H79: =F79*G79 -> 266046.85 | J79: Lançado ERP
C80: 07.006.004.003 | D80: Mão de obra - muchetas / encunhamento | E80: m2 | F80: 652.8 | G80: ='MÃO DE OBRA '!$E$170 -> 104.00408 | H80: =F80*G80 -> 67893.86 | J80: Lançado ERP
C81: 07.006.004.004 | D81: Mão de obra - assentamento de tijolos refratários | E81: m2 | F81: 76.149 | G81: ='MÃO DE OBRA '!$E$172 -> 315.95801 | H81: =F81*G81 -> 24059.887 | J81: Lançado ERP
C82: 07.007 | D82: ALVENARIA E VEDAÇÕES - ÁTICO | H82: =H83 -> 27144.958
C83: 07.007.004 | D83: MÃO DE OBRA | H83: =SUM(H84:H86) -> 27144.958
C84: 07.007.004.001 | D84: Mão de obra - salpico ou pinos colunas e vigas / marcação | E84: m2 | F84: 365.11 | G84: ='MÃO DE OBRA '!$E$166 -> 9.1990689 | H84: =F84*G84 -> 3358.672 | J84: Lançado ERP
C85: 07.007.004.002 | D85: Mão de obra - paredes / vergas e contra-vergas | E85: m2 | F85: 365.11 | G85: ='MÃO DE OBRA '!$E$168 -> 56.508566 | H85: =F85*G85 -> 20631.842 | J85: Lançado ERP
C86: 07.007.004.003 | D86: Mão de obra - muchetas / encunhamento | E86: m2 | F86: 30.33 | G86: ='MÃO DE OBRA '!$E$170 -> 104.00408 | H86: =F86*G86 -> 3154.4436 | J86: Lançado ERP
C87: 07.008 | D87: ALVENARIA E VEDAÇÕES - BARRILETE/RESERVATÓRIO | H87: =H88 -> 42104.802
C88: 07.008.004 | D88: MÃO DE OBRA | H88: =H89 -> 42104.802
C89: 07.008.004.001 | D89: Mão de obra - alvenaria de reservatórios | E89: vb | F89: 1 | G89: ='MÃO DE OBRA '!E158 -> 42104.802 | H89: =F89*G89 -> 42104.802 | J89: Lançado ERP
C90: 08 | D90: SISTEMAS E INSTALAÇÕES ELÉTRICAS | H90: =H91+H95+H99+H104+H108+H112+H116+H120 -> 535141.91 | I90: Distribuição por pavimento não bate com separação previa da empreitada pela distribuição de uqantitativos, porém soma da etapa é equivalente | K90: =SUM(H93,H97,H101,H103,H106,H110,H114,H118,H122) -> 458474.51
C91: 08.001 | D91: SISTEMAS E INSTALAÇÕES ELÉTRICAS - SUBSOLO 2 | H91: =H92 -> 70590.251
C92: 08.001.006 | D92: MÃO DE OBRA | H92: =SUM(H93:H94) -> 70590.251
C93: 08.001.006.001 | D93: Mão de obra - Sistemas e instalações elétricas | E93: m2 | F93: =Obra!E10 -> 1143.68 | G93: ='MÃO DE OBRA '!E249 -> 52.72203 | H93: =F93*G93 -> 60297.131 | J93: Lançado ERP
C94: 08.001.006.001 | D94: Mão de obra - Cabeamentos elétricos | E94: m2 | F94: =F93 -> 1143.68 | G94: 9 | H94: =F94*G94 -> 10293.12 | I94: Ajuste realizado conforme alinhamento da reunião do dia 04/10/2024 | J94: Lançado ERP
C95: 08.002 | D95: SISTEMAS E INSTALAÇÕES ELÉTRICAS - SUBSOLO 1 | H95: =H96 -> 70590.251
C96: 08.002.006 | D96: MÃO DE OBRA | H96: =SUM(H97:H98) -> 70590.251
C97: 08.002.006.001 | D97: Mão de obra - Sistemas e instalações elétricas | E97: m2 | F97: =Obra!E11 -> 1143.68 | G97: ='MÃO DE OBRA '!E249 -> 52.72203 | H97: =F97*G97 -> 60297.131 | J97: Lançado ERP
C98: 08.001.006.001 | D98: Mão de obra - Cabeamentos elétricos | E98: m2 | F98: =F97 -> 1143.68 | G98: 9 | H98: =F98*G98 -> 10293.12 | I98: Ajuste realizado conforme alinhamento da reunião do dia 04/10/2024 | J98: Lançado ERP
C99: 08.003 | D99: SISTEMAS E INSTALAÇÕES ELÉTRICAS - TÉRREO | H99: =H100 -> 74583.847
C100: 08.003.007 | D100: MÃO DE OBRA | H100: =SUM(H101:H103) -> 74583.847
C101: 08.003.007.001 | D101: Mão de obra - Sistemas e instalações elétricas | E101: m2 | F101: =Obra!E12 -> 1056.79 | G101: ='MÃO DE OBRA '!E249 -> 52.72203 | H101: =F101*G101 -> 55716.114 | J101: Lançado ERP
C102: 08.001.006.001 | D102: Mão de obra - Cabeamentos elétricos | E102: m2 | F102: =F101 -> 1056.79 | G102: 9 | H102: =F102*G102 -> 9511.11 | I102: Ajuste realizado conforme alinhamento da reunião do dia 04/10/2024 | J102: Lançado ERP
C103: 08.003.007.002 | D103: Mão de obra - Entrada de energia | E103: vb | F103: 1 | G103: ='MÃO DE OBRA '!E247 -> 9356.6226 | H103: =F103*G103 -> 9356.6226 | J103: Lançado ERP
...

Sheet MÃO DE OBRA 
A1: Obra | B1: Playa Negra
A2: Empresa | B2: GDI
A3: Revisão | B3: R00
A4: Data | B4: 45499
A5: Arquivo de origem
A6: DISTRIBUIÇÃO DE VERBAS
A8: MÃO DE OBRA
A10: Indiretos
C12: Etapa | D12: Porcentagem (%) | E12: Total
B13: Instalações provisórias | C13: Mão de Obra - Implantação do canteiros de Obras
B14: =B13 -> Instalações provisórias | C14: Garda corpo e proteções | D14: 0.01 | E14: =D14*$K$20 -> 93566.226
B15: =B14 -> Instalações provisórias | C15: instalações e ligações provisórias (barracos/banheiros/estações de trabalho/tapume/sinalizações/etc) | D15: 0.01 | E15: =D15*$K$20 -> 93566.226
B16: =B15 -> Instalações provisórias | C16: Itens de Segurança | D16: 0.005 | E16: =D16*$K$20 -> 46783.113
B17: =B16 -> Instalações provisórias | C17: LIMPEZA PERIÓDICA | D17: 0.023 | E17: =D17*$K$20 -> 215202.32
D18: Total (Vb) | E18: =SUM(E14:E17) -> 449117.89
A20: Movimentação de terra | J20: VALOR TOTAL | K20: 9356622.6
K22: =E18+E28+E39+E100+E162+E415+E302+E243+E270+E331+E322+E824+E858+E490+E569+E768+E686+E442+E878+E595 -> 9356622.6
C23: Etapa | D23: Porcentagem (%) | E23: Total | K23: =K22-K20 -> 0
B24: Movimentação de terra | C24: Mão de obra - movimentação de terra
B25: =B24 -> Movimentação de terra | C25: ESCAVAÇÃO E REATERRO | D25: 0.005 | E25: 46783.113 | J25: SOMA PROPORÇÕES | K25: =E18+E28+E39+E100+E162+E415+E302+E243+E270+E331+E322+E824+E858+E490+E569+E768+E686+E442+E878+E591 -> 9440846.3
B26: Movimentação de terra | C26: Mão de obra - locação
B27: =B26 -> Movimentação de terra | C27: FÔRMAS | D27: 0.005 | E27: 46783.113
D28: Total (Vb) | E28: =SUM(E25:E27) -> 93566.226
A30: Infraestrutura
C33: Etapa | D33: Porcentagem (%) | E33: Total
B34: Infraestrutura | C34: Mão de obra - execução de infraraestrutura
B35: =B34 -> Infraestrutura | C35: BLOCOS DE FUNDAÇÃO E PESCOÇOS | D35: 0.0087 | E35: =D35*$K$20 -> 81402.617 | F35: forma
B36: =B35 -> Infraestrutura | C36: BLOCOS DE FUNDAÇÃO E PESCOÇOS | D36: 0.003 | E36: =D36*$K$20 -> 28069.868 | F36: armadura
B37: =B36 -> Infraestrutura | C37: BLOCOS DE FUNDAÇÃO E PESCOÇOS | D37: 0.002 | E37: =D37*$K$20 -> 18713.245 | F37: laje
B38: =B37 -> Infraestrutura | C38: BLOCOS DE FUNDAÇÃO E PESCOÇOS | D38: 0.002 | E38: =D38*$K$20 -> 18713.245 | F38: concreto
D39: Total (Vb) | E39: =SUM(E35:E38) -> 146898.98
A41: Supraestrutura
B45: PAVIMENTO | C45: Etapa | D45: Porcentagem (%) | E45: Total
B46: Subsolo | C46: Mão de obra - execução de supraestrutura | E46: =SUM(E47:E50) -> 219880.63
B47: =B46 -> Subsolo | C47: SUBSOLO VIGAS BALDRAME E DESFÔRMA | D47: 0.01 | E47: =D47*$K$20 -> 93566.226 | F47: forma
B48: =B47 -> Subsolo | C48: SUBSOLO VIGAS BALDRAME E DESFÔRMA | D48: 0.0065 | E48: =D48*$K$20 -> 60818.047 | F48: armadura
B49: =B48 -> Subsolo | C49: SUBSOLO VIGAS BALDRAME E DESFÔRMA | D49: 0.003 | E49: =D49*$K$20 -> 28069.868 | F49: laje
B50: =B49 -> Subsolo | C50: SUBSOLO VIGAS BALDRAME E DESFÔRMA | D50: 0.004 | E50: =D50*$K$20 -> 37426.49 | F50: concreto
B51: Térreo | C51: Mão de obra - execução de supraestrutura | E51: =SUM(E52:E59) -> 407013.08
B52: =B51 -> Térreo | C52: TERREO VIGAS, PILARES MEZANINO, ESCORAMENTO E DESFORMA | D52: 0.014 | E52: =D52*$K$20 -> 130992.72
B53: =B52 -> Térreo | C53: TERREO VIGAS, PILARES MEZANINO, ESCORAMENTO E DESFORMA | D53: 0.0085 | E53: =D53*$K$20 -> 79531.292
B54: =B53 -> Térreo | C54: TERREO VIGAS, PILARES MEZANINO, ESCORAMENTO E DESFORMA | D54: 0.003 | E54: =D54*$K$20 -> 28069.868
B55: =B54 -> Térreo | C55: TERREO VIGAS, PILARES MEZANINO, ESCORAMENTO E DESFORMA | D55: 0.003 | E55: =D55*$K$20 -> 28069.868
B56: =B55 -> Térreo | C56: GUARITA, LIXEIRA, CENTRAL GÁS. | D56: 0.006 | E56: =D56*$K$20 -> 56139.736
B57: =B56 -> Térreo | C57: GUARITA, LIXEIRA, CENTRAL GÁS. | D57: 0.003 | E57: =D57*$K$20 -> 28069.868
B58: =B57 -> Térreo | C58: GUARITA, LIXEIRA, CENTRAL GÁS. | D58: 0.004 | E58: =D58*$K$20 -> 37426.49
B59: =B58 -> Térreo | C59: GUARITA, LIXEIRA, CENTRAL GÁS. | D59: 0.002 | E59: =D59*$K$20 -> 18713.245
B60: Mezanino | C60: Mão de obra - execução de supraestrutura | E60: =SUM(E61:E64) -> 185261.13
B61: =B60 -> Mezanino | C61: MEZANINO VIGAS, PILARES SUBS, ESCORAMENTO E DESFORMA | D61: 0.0108 | E61: =D61*$K$20 -> 101051.52
B62: =B61 -> Mezanino | C62: MEZANINO VIGAS, PILARES SUBS, ESCORAMENTO E DESFORMA | D62: 0.004 | E62: =D62*$K$20 -> 37426.49
B63: =B62 -> Mezanino | C63: MEZANINO VIGAS, PILARES SUBS, ESCORAMENTO E DESFORMA | D63: 0.002 | E63: =D63*$K$20 -> 18713.245
B64: =B63 -> Mezanino | C64: MEZANINO VIGAS, PILARES SUBS, ESCORAMENTO E DESFORMA | D64: 0.003 | E64: =D64*$K$20 -> 28069.868
B65: Tipo 1 | C65: Mão de obra - execução de supraestrutura | E65: =SUM(E66:E69) -> 285376.99
B66: =B65 -> Tipo 1 | C66: TIPO 1 VIGAS, PILARES TERREO, ESCORAMENTO e DESFÔRMA | D66: 0.014 | E66: =D66*$K$20 -> 130992.72
B67: =B66 -> Tipo 1 | C67: TIPO 1 VIGAS, PILARES TERREO, ESCORAMENTO e DESFÔRMA | D67: 0.0085 | E67: =D67*$K$20 -> 79531.292
B68: =B67 -> Tipo 1 | C68: TIPO 1 VIGAS, PILARES TERREO, ESCORAMENTO e DESFÔRMA | D68: 0.004 | E68: =D68*$K$20 -> 37426.49
B69: =B68 -> Tipo 1 | C69: TIPO 1 VIGAS, PILARES TERREO, ESCORAMENTO e DESFÔRMA | D69: 0.004 | E69: =D69*$K$20 -> 37426.49
B70: Tipo 2 | C70: Mão de obra - execução de supraestrutura | E70: =SUM(E71:E74) -> 285376.99
B71: =B70 -> Tipo 2 | C71: TIPO 2 VIGAS, PILARES T1, ESCORAMENTO e DESFÔRMA | D71: 0.014 | E71: =D71*$K$20 -> 130992.72
B72: =B71 -> Tipo 2 | C72: TIPO 2 VIGAS, PILARES T1, ESCORAMENTO e DESFÔRMA | D72: 0.0085 | E72: =D72*$K$20 -> 79531.292
B73: =B72 -> Tipo 2 | C73: TIPO 2 VIGAS, PILARES T1, ESCORAMENTO e DESFÔRMA | D73: 0.004 | E73: =D73*$K$20 -> 37426.49
B74: =B73 -> Tipo 2 | C74: TIPO 2 VIGAS, PILARES T1, ESCORAMENTO e DESFÔRMA | D74: 0.004 | E74: =D74*$K$20 -> 37426.49
B75: Tipo 3 | C75: Mão de obra - execução de supraestrutura | E75: =SUM(E76:E79) -> 285376.99
B76: =B75 -> Tipo 3 | C76: TIPO 3 VIGAS, PILARES T2, ESCORAMENTO e DESFÔRMA | D76: 0.014 | E76: =D76*$K$20 -> 130992.72
B77: =B76 -> Tipo 3 | C77: TIPO 3 VIGAS, PILARES T2, ESCORAMENTO e DESFÔRMA | D77: 0.0085 | E77: =D77*$K$20 -> 79531.292
B78: =B77 -> Tipo 3 | C78: TIPO 3 VIGAS, PILARES T2, ESCORAMENTO e DESFÔRMA | D78: 0.004 | E78: =D78*$K$20 -> 37426.49
B79: =B78 -> Tipo 3 | C79: TIPO 3 VIGAS, PILARES T2, ESCORAMENTO e DESFÔRMA | D79: 0.004 | E79: =D79*$K$20 -> 37426.49
B80: Ático | C80: Mão de obra - execução de supraestrutura | E80: =SUM(E81:E84) -> 285376.99
B81: =B80 -> Ático | C81: TIPO ATICO, PILARES T3, ESCORAMENTO e DESFÔRMA | D81: 0.014 | E81: =D81*$K$20 -> 130992.72
B82: =B81 -> Ático | C82: TIPO ATICO, PILARES T3, ESCORAMENTO e DESFÔRMA | D82: 0.0085 | E82: =D82*$K$20 -> 79531.292
B83: =B82 -> Ático | C83: TIPO ATICO, PILARES T3, ESCORAMENTO e DESFÔRMA | D83: 0.004 | E83: =D83*$K$20 -> 37426.49
B84: =B83 -> Ático | C84: TIPO ATICO, PILARES T3, ESCORAMENTO e DESFÔRMA | D84: 0.004 | E84: =D84*$K$20 -> 37426.49
B85: Cobertura | C85: Mão de obra - execução de supraestrutura | E85: =SUM(E86:E89) -> 285376.99
B86: =B85 -> Cobertura | C86: COBERTURA, PILARES ATICO, ESCORAMENTO e DESFÔRMA | D86: 0.014 | E86: =D86*$K$20 -> 130992.72
B87: =B86 -> Cobertura | C87: COBERTURA, PILARES ATICO, ESCORAMENTO e DESFÔRMA | D87: 0.0085 | E87: =D87*$K$20 -> 79531.292
B88: =B87 -> Cobertura | C88: COBERTURA, PILARES ATICO, ESCORAMENTO e DESFÔRMA | D88: 0.004 | E88: =D88*$K$20 -> 37426.49
B89: =B88 -> Cobertura | C89: COBERTURA, PILARES ATICO, ESCORAMENTO e DESFÔRMA | D89: 0.004 | E89: =D89*$K$20 -> 37426.49
B90: Barrilete | C90: Mão de obra - execução de supraestrutura | E90: =SUM(E91:E94) -> 247950.5
B91: =B90 -> Barrilete | C91: BARRILETE VIGAS, PILARES COB., ESCORAMENTO E DESFÔRMA | D91: 0.01 | E91: =D91*$K$20 -> 93566.226
B92: =B91 -> Barrilete | C92: BARRILETE VIGAS, PILARES COB., ESCORAMENTO E DESFÔRMA | D92: 0.0085 | E92: =D92*$K$20 -> 79531.292
B93: =B92 -> Barrilete | C93: BARRILETE VIGAS, PILARES COB., ESCORAMENTO E DESFÔRMA | D93: 0.004 | E93: =D93*$K$20 -> 37426.49
B94: =B93 -> Barrilete | C94: BARRILETE VIGAS, PILARES COB., ESCORAMENTO E DESFÔRMA | D94: 0.004 | E94: =D94*$K$20 -> 37426.49
B95: Reservatório | C95: Mão de obra - execução de supraestrutura | E95: =SUM(E96:E99) -> 135671.03
B96: =B95 -> Reservatório | C96: RESERVATÓRIO FUNDO, PILARES, PAREDES, TAMPA, ESCORAMENTO E DESFÔRMA | D96: 0.0065 | E96: =D96*$K$20 -> 60818.047
B97: =B96 -> Reservatório | C97: RESERVATÓRIO FUNDO, PILARES, PAREDES, TAMPA, ESCORAMENTO E DESFÔRMA | D97: 0.004 | E97: =D97*$K$20 -> 37426.49
B98: =B97 -> Reservatório | C98: RESERVATÓRIO FUNDO, PILARES, PAREDES, TAMPA, ESCORAMENTO E DESFÔRMA | D98: 0.002 | E98: =D98*$K$20 -> 18713.245
B99: =B98 -> Reservatório | C99: RESERVATÓRIO FUNDO, PILARES, PAREDES, TAMPA, ESCORAMENTO E DESFÔRMA | D99: 0.002 | E99: =D99*$K$20 -> 18713.245
D100: Total (vb) | E100: =E60+E51+E65+E70+E75+E80+E85+E90+E46+E95 -> 2622661.3
A102: Alvenaria
B105: PAVIMENTO | C105: Etapa | D105: Porcentagem (%) | E105: Total
B106: SUBSOLO | C106: Mão de obra - salpico ou pinos colunas e vigas / marcação | E106: =SUM(E107:E111) -> 46783.113
B107: =B106 -> SUBSOLO | C107: SUBSOLO salpico ou pinos colunas e vigas / marcação | D107: 0.001 | E107: =D107*$K$20 -> 9356.6226
B108: =B107 -> SUBSOLO | C108: Mão de obra - paredes / vergas e contra-vergas
B109: =B108 -> SUBSOLO | C109: SUBSOLO paredes / vergas e contra-vergas | D109: 0.0025 | E109: =D109*$K$20 -> 23391.557
B110: =B109 -> SUBSOLO | C110: Mão de obra - muchetas / encunhamento
B111: =B110 -> SUBSOLO | C111: SUBSOLO muchetas / encunhamento | D111: 0.0015 | E111: =D111*$K$20 -> 14034.934
B112: TERREO | C112: Mão de obra - salpico ou pinos colunas e vigas / marcação | E112: =SUM(E113:E120) -> 112279.47
B113: =B112 -> TERREO | C113: TERREO salpico ou pinos colunas e vigas / marcação | D113: 0.001 | E113: =D113*$K$20 -> 9356.6226
B114: =B113 -> TERREO | C114: Mão de obra - paredes / vergas e contra-vergas
B115: =B113 -> TERREO | C115: TERREO paredes / vergas e contra-vergas | D115: 0.007 | E115: =D115*$K$20 -> 65496.358
...

Sheet Planilha2
B2: Mão de obra para reboco interno | C2: m2 | D2: 14224.12 | E2: 734495.15
B3: Mão de obra - limpeza grossa - 2º pavimento | C3: vb | D3: 1 | E3: 6726.67
B4: Mão de obra - limpeza grossa - Ático | C4: vb | D4: 1 | E4: 6955.46
B5: Mão de obra - limpeza grossa - Barrilete | C5: vb | D5: 1 | E5: 878.04
B6: Mão de obra - limpeza grossa - Subsolo 1 | C6: vb | D6: 1 | E6: 12561.9
B7: Mão de obra - limpeza grossa - Subsolo 2 | C7: vb | D7: 1 | E7: 12561.9
B8: Mão de obra - limpeza grossa - Térreo | C8: vb | D8: 1 | E8: 11607.52
B9: Mão de obra - limpeza grossa - Tipo | C9: vb | D9: 1 | E9: 40360.03
B10: Mão d eobra para instalação de louças e metais | C10: vb | D10: 1 | E10: 93566.23
B11: Mão de obra - Entrada de energia | C11: vb | D11: 1 | E11: 9356.62
B12: Mão de obra - Execução de supraestrutura / Ático | C12: vb | D12: 1 | E12: 285376.99
B13: Mão de obra - Execução de supraestrutura / Barrilete | C13: vb | D13: 1 | E13: 668998.52
... B73: Mão de obra textura externa | C73: m2 | D73: 483.74 | E73: 93566.25

Sheet MO Infra
L6: =(92273.31+12957.46+45908+7494) -> 158632.77 | M6: =L6/(259.53*2+288.02) -> 196.55148

Sheet Composição forma blocos
A24: *composição mais próxima do serviço solicitado

Sheet Cotações
B1: Projeto | C1: =Ger_Executivo!C4 -> Playa Negra
B2: Empresa | C2: =Ger_Executivo!C5 -> GDI
B3: Revisão | C3: R00 - Michelle Furlan - 06/02/24
A4: CONTROLE DE COTAÇÕES
A5: INFORMAÇÕES IMPORTANTES: CNPJ XXXX / XXXXX / Endereço da obra: XXXX
A6: Item | B6: Data | C6: Site | D6: Status | E6: E-mail

Sheet Sapatas
B1: Projeto | C1: =Ger_Executivo!C4 -> Playa Negra
B2: Empresa | C2: =Ger_Executivo!C5 -> GDI
B3: Revisão | C3: R00 - Michelle Furlan -
A4: SAPATAS
A5: Peça | B5: Quant. | C5: Dimensões Unitárias - m | I5: Adição | J5: Adição | K5: Quantidade de Serviços
C6: A | D6: B | E6: H0 | F6: C | G6: D | H6: H1 | I6: largura | J6: altura | K6: Escav | L6: Apiloam | M6: Reaterro | N6: Bota-fora | O6: Lastro Concreto | Q6: Fôrma | R6: Concreto | S6: Imperm
C7: m | D7: m | E7: m | F7: m | G7: m | H7: m | I7: m | J7: m | K7: m3 | L7: m2 | M7: m3 | N7: m3 | O7: esp | P7: m3 | Q7: m2 | R7: m3 | S7: m2
A8: PROJETO: | K8: =(C8+I8)*(D8+I8)*(E8+H8+O8+J8)*B8 -> 0 | L8: =$C8*$D8*$B8 -> 0 | M8: =$K8-$R8-P8 -> 0 | N8: =(K8-M8)*1.3 -> 0 | P8: =($C8*$D8*$O8)*$B8 -> 0 | Q8: =(((($C8+$D8)*2)*$E8)*$B8)+(((J8-0.1)*4*F8)*B8) -> 0 | R8: =((($C8*$D8*$E8)+(($H8/6)*(($C8*$D8)+($F8*$G8)+(($C8+$F8)*($D8+$G8)))))*$B8)+((J8-0.1)*F8*G8*B8) -> 0
I9: =IF((C9+D9)<=1,0.6,1.2) -> 0.6 | K9: =(C9+I9)*(D9+I9)*(E9+H9+O9+J9)*B9 -> 0 | L9: =$C9*$D9*$B9 -> 0 | M9: =$K9-$R9-P9 -> 0 | N9: =(K9-M9)*1.3 -> 0 | O9: 0.1 | P9: =($C9*$D9*$O9)*$B9 -> 0 | Q9: =(((($C9+$D9)*2)*$E9)*$B9)+(((J9-0.1)*4*F9)*B9) -> 0 | R9: =((($C9*$D9*$E9)+(($H9/6)*(($C9*$D9)+($F9*$G9)+(($C9+$F9)*($D9+$G9)))))*$B9)+((J9-0.1)*F9*G9*B9) -> 0
I10: =IF((C10+D10)<=1,0.6,1.2) -> 0.6 | K10: =(C10+I10)*(D10+I10)*(E10+H10+O10+J10)*B10 -> 0 | L10: =$C10*$D10*$B10 -> 0 | M10: =$K10-$R10-P10 -> 0 | N10: =(K10-M10)*1.3 -> 0 | O10: 0.1 | P10: =($C10*$D10*$O10)*$B10 -> 0 | Q10: =(((($C10+$D10)*2)*$E10)*$B10)+(((J10-0.1)*4*F10)*B10) -> 0 | R10: =((($C10*$D10*$E10)+(($H10/6)*(($C10*$D10)+($F10*$G10)+(($C10+$F10)*($D10+$G10)))))*$B10)+((J10-0.1)*F10*G10*B10) -> 0
I11: =IF((C11+D11)<=1,0.6,1.2) -> 0.6 | K11: =(C11+I11)*(D11+I11)*(E11+H11+O11+J11)*B11 -> 0 | L11: =$C11*$D11*$B11 -> 0 | M11: =$K11-$R11-P11 -> 0 | N11: =(K11-M11)*1.3 -> 0 | O11: 0.1 | P11: =($C11*$D11*$O11)*$B11 -> 0 | Q11: =(((($C11+$D11)*2)*$E11)*$B11)+(((J11-0.1)*4*F11)*B11) -> 0 | R11: =((($C11*$D11*$E11)+(($H11/6)*(($C11*$D11)+($F11*$G11)+(($C11+$F11)*($D11+$G11)))))*$B11)+((J11-0.1)*F11*G11*B11) -> 0
I12: =IF((C12+D12)<=1,0.6,1.2) -> 0.6 | K12: =(C12+I12)*(D12+I12)*(E12+H12+O12+J12)*B12 -> 0 | L12: =$C12*$D12*$B12 -> 0 | M12: =$K12-$R12-P12 -> 0 | N12: =(K12-M12)*1.3 -> 0 | O12: 0.1 | P12: =($C12*$D12*$O12)*$B12 -> 0 | Q12: =(((($C12+$D12)*2)*$E12)*$B12)+(((J12-0.1)*4*F12)*B12) -> 0 | R12: =((($C12*$D12*$E12)+(($H12/6)*(($C12*$D12)+($F12*$G12)+(($C12+$F12)*($D12+$G12)))))*$B12)+((J12-0.1)*F12*G12*B12) -> 0
I13: =IF((C13+D13)<=1,0.6,1.2) -> 0.6 | K13: =(C13+I13)*(D13+I13)*(E13+H13+O13+J13)*B13 -> 0 | L13: =$C13*$D13*$B13 -> 0 | M13: =$K13-$R13-P13 -> 0 | N13: =(K13-M13)*1.3 -> 0 | O13: 0.1 | P13: =($C13*$D13*$O13)*$B13 -> 0 | Q13: =(((($C13+$D13)*2)*$E13)*$B13)+(((J13-0.1)*4*F13)*B13) -> 0 | R13: =((($C13*$D13*$E13)+(($H13/6)*(($C13*$D13)+($F13*$G13)+(($C13+$F13)*($D13+$G13)))))*$B13)+((J13-0.1)*F13*G13*B13) -> 0
I14: =IF((C14+D14)<=1,0.6,1.2) -> 0.6 | K14: =(C14+I14)*(D14+I14)*(E14+H14+O14+J14)*B14 -> 0 | L14: =$C14*$D14*$B14 -> 0 | M14: =$K14-$R14-P14 -> 0 | N14: =(K14-M14)*1.3 -> 0 | O14: 0.1 | P14: =($C14*$D14*$O14)*$B14 -> 0 | Q14: =(((($C14+$D14)*2)*$E14)*$B14)+(((J14-0.1)*4*F14)*B14) -> 0 | R14: =((($C14*$D14*$E14)+(($H14/6)*(($C14*$D14)+($F14*$G14)+(($C14+$F14)*($D14+$G14)))))*$B14)+((J14-0.1)*F14*G14*B14) -> 0
I15: =IF((C15+D15)<=1,0.6,1.2) -> 0.6 | K15: =(C15+I15)*(D15+I15)*(E15+H15+O15+J15)*B15 -> 0 | L15: =$C15*$D15*$B15 -> 0 | M15: =$K15-$R15-P15 -> 0 | N15: =(K15-M15)*1.3 -> 0 | O15: 0.1 | P15: =($C15*$D15*$O15)*$B15 -> 0 | Q15: =(((($C15+$D15)*2)*$E15)*$B15)+(((J15-0.1)*4*F15)*B15) -> 0 | R15: =((($C15*$D15*$E15)+(($H15/6)*(($C15*$D15)+($F15*$G15)+(($C15+$F15)*($D15+$G15)))))*$B15)+((J15-0.1)*F15*G15*B15) -> 0
I16: =IF((C16+D16)<=1,0.6,1.2) -> 0.6 | K16: =(C16+I16)*(D16+I16)*(E16+H16+O16+J16)*B16 -> 0 | L16: =$C16*$D16*$B16 -> 0 | M16: =$K16-$R16-P16 -> 0 | N16: =(K16-M16)*1.3 -> 0 | O16: 0.1 | P16: =($C16*$D16*$O16)*$B16 -> 0 | Q16: =(((($C16+$D16)*2)*$E16)*$B16)+(((J16-0.1)*4*F16)*B16) -> 0 | R16: =((($C16*$D16*$E16)+(($H16/6)*(($C16*$D16)+($F16*$G16)+(($C16+$F16)*($D16+$G16)))))*$B16)+((J16-0.1)*F16*G16*B16) -> 0
I17: =IF((C17+D17)<=1,0.6,1.2) -> 0.6 | K17: =(C17+I17)*(D17+I17)*(E17+H17+O17+J17)*B17 -> 0 | L17: =$C17*$D17*$B17 -> 0 | M17: =$K17-$R17-P17 -> 0 | N17: =(K17-M17)*1.3 -> 0 | O17: 0.1 | P17: =($C17*$D17*$O17)*$B17 -> 0 | Q17: =(((($C17+$D17)*2)*$E17)*$B17)+(((J17-0.1)*4*F17)*B17) -> 0 | R17: =((($C17*$D17*$E17)+(($H17/6)*(($C17*$D17)+($F17*$G17)+(($C17+$F17)*($D17+$G17)))))*$B17)+((J17-0.1)*F17*G17*B17) -> 0
I18: =IF((C18+D18)<=1,0.6,1.2) -> 0.6 | K18: =(C18+I18)*(D18+I18)*(E18+H18+O18+J18)*B18 -> 0 | L18: =$C18*$D18*$B18 -> 0 | M18: =$K18-$R18-P18 -> 0 | N18: =(K18-M18)*1.3 -> 0 | O18: 0.1 | P18: =($C18*$D18*$O18)*$B18 -> 0 | Q18: =(((($C18+$D18)*2)*$E18)*$B18)+(((J18-0.1)*4*F18)*B18) -> 0 | R18: =((($C18*$D18*$E18)+(($H18/6)*(($C18*$D18)+($F18*$G18)+(($C18+$F18)*($D18+$G18)))))*$B18)+((J18-0.1)*F18*G18*B18) -> 0
I19: =IF((C19+D19)<=1,0.6,1.2) -> 0.6 | K19: =(C19+I19)*(D19+I19)*(E19+H19+O19+J19)*B19 -> 0 | L19: =$C19*$D19*$B19 -> 0 | M19: =$K19-$R19-P19 -> 0 | N19: =(K19-M19)*1.3 -> 0 | O19: 0.1 | P19: =($C19*$D19*$O19)*$B19 -> 0 | Q19: =(((($C19+$D19)*2)*$E19)*$B19)+(((J19-0.1)*4*F19)*B19) -> 0 | R19: =((($C19*$D19*$E19)+(($H19/6)*(($C19*$D19)+($F19*$G19)+(($C19+$F19)*($D19+$G19)))))*$B19)+((J19-0.1)*F19*G19*B19) -> 0
I20: =IF((C20+D20)<=1,0.6,1.2) -> 0.6 | K20: =(C20+I20)*(D20+I20)*(E20+H20+O20+J20)*B20 -> 0 | L20: =$C20*$D20*$B20 -> 0 | M20: =$K20-$R20-P20 -> 0 | N20: =(K20-M20)*1.3 -> 0 | O20: 0.1 | P20: =($C20*$D20*$O20)*$B20 -> 0 | Q20: =(((($C20+$D20)*2)*$E20)*$B20)+(((J20-0.1)*4*F20)*B20) -> 0 | R20: =((($C20*$D20*$E20)+(($H20/6)*(($C20*$D20)+($F20*$G20)+(($C20+$F20)*($D20+$G20)))))*$B20)+((J20-0.1)*F20*G20*B20) -> 0
... I26: =IF((C26+D26)<=1,0.6,1.2) -> 0.6 | K26: =(C26+I26)*(D26+I26)*(E26+H26+O26+J26)*B26 -> 0 | L26: =$C26*$D26*$B26 -> 0 | M26: =$K26-$R26-P26 -> 0 | N26: =(K26-M26)*1.3 -> 0 | O26: 0.1 | P26: =($C26*$D26*$O26)*$B26 -> 0 | Q26: =(((($C26+$D26)*2)*$E26)*$B26)+(((J26-0.1)*4*F26)*B26) -> 0 | R26: =((($C26*$D26*$E26)+(($H26/6)*(($C26*$D26)+($F26*$G26)+(($C26+$F26)*($D26+$G26)))))*$B26)+((J26-0.1)*F26*G26*B26) -> 0
B27: TOTAL GERAL | K27: =SUM(K8:K26) -> 0 | L27: =SUM(L8:L26) -> 0 | M27: =SUM(M8:M26) -> 0 | N27: =SUM(N8:N26) -> 0 | P27: =SUM(P8:P26) -> 0 | Q27: =SUM(Q8:Q26) -> 0 | R27: =SUM(R8:R26) -> 0 | S27: =SUM(S8:S26) -> 0
K28: Vol. tronco pirâmide = (H2/6) * [ (A*B) + (C*D) + (A+C)*(B+D) ]

Sheet Tabela de Aço
A1: TABELA DE AÇO
A2: CA-50 | D2: CA-60
A3: Ø - mm | B3: kg/m | C3: pol | D3: Ø - mm | E3: kg/m
A4: 6.3 | B4: 0.245 | C4: 1/4" | D4: 3.4 | E4: 0.079
A5: 8 | B5: 0.395 | C5: 5/16" | D5: 4.2 | E5: 0.109
A6: 10 | B6: 0.617 | C6: 3/8" | D6: 5 | E6: 0.154
A7: 12.5 | B7: 0.963 | C7: 1/2" | D7: 6 | E7: 0.222
A8: 16 | B8: 1.578 | C8: 5/8" | D8: 7 | E8: 0.302
A9: 20 | B9: 2.466 | C9: 3/4" | D9: 8 | E9: 0.395
A10: 25 | B10: 3.853 | C10: 1" | D10: 9.5 | E10: 0.558
A11: 32 | B11: 6.313 | C11: 1 1/4" | D11: 0
A12: 40 | B12: 9.865 | C12: 1 5/8" | D12: 0

Sheet Estrutura
D1: Projeto | E1: =Obra!D1 -> Playa Negra
D2: Empresa | E2: =Obra!D2 -> GDI
D3: Origem | E3: PROJETO: PNEG-EST-PE-QUANTITATIVO-R00 (CTN & GDI - Pasta Compartilhada\04. GDI - PLAYA NEGRA (compartilhamento)\03. FN ESTRUTURAS)
D4: Revisão | E4: R00 - Patricia Bragato
A5: INFRAESTRUTURA
A6: ITEM | B6: 5 | C6: 6.3 | D6: 8 | E6: 10 | F6: 12.5 | G6: 16 | H6: 20 | I6: 25 | J6: Aço | K6: Q92 | L6: Q138 | M6: Concreto C40 | N6: Forma | O6: Area | P6: Enchimento EPS | R6: Cubetas Atex 800
B7: kgf | C7: kgf | D7: kgf | E7: kgf | F7: kgf | G7: kgf | H7: kgf | I7: kgf | J7: kgf | K7: kgf | L7: kgf | M7: (m³) | N7: (m²) | O7: (m²) | P7: 50x50x15 | Q7: 50x50x20 | R7: Forma Inteira 80x80x20 | S7: Meia Forma 40x80x20
A8: INFRAESTRUTURA
A9: Sapatas | B9: 0 | C9: 0 | D9: 0 | E9: 157 | F9: 1013 | G9: 7426 | H9: 2300 | I9: 0 | J9: =SUM(B9:I9) -> 10896 | K9: 0 | L9: 0 | M9: 240.8 | N9: 143.6 | O9: 0 | P9: 0 | Q9: 0 | R9: 0 | S9: 0
A10: TOTAL | B10: =SUM(B7:B9) -> 0 | C10: =SUM(C7:C9) -> 0 | D10: =SUM(D7:D9) -> 0 | E10: =SUM(E7:E9) -> 157 | F10: =SUM(F7:F9) -> 1013 | G10: =SUM(G7:G9) -> 7426 | H10: =SUM(H7:H9) -> 2300 | I10: =SUM(I7:I9) -> 0 | ... S10: =SUM(S7:S9) -> 0
A12: SUPRAESTRUTURA
A13: ITEM | B13: 5 | C13: 6.3 | D13: 8 | E13: 10 | F13: 12.5 | G13: 16 | H13: 20 | I13: 25 | J13: Aço | K13: Q92 | L13: Q138 | M13: Concreto C40 | N13: Forma | O13: Area | P13: Enchimento EPS | R13: Cubetas Atex 800
B14: kgf | C14: kgf | D14: kgf | E14: kgf | F14: kgf | G14: kgf | H14: kgf | I14: kgf | J14: kgf | K14: kgf | L14: kgf | M14: (m³) | N14: (m²) | O14: (m²) | P14: 50x50x15 | Q14: 50x50x20 | R14: Forma Inteira 80x80x20 | S14: Meia Forma 40x80x20
A15: SUBSOLO 2 | B15: =SUM(B16:B19) -> 236 | C15: =SUM(C16:C19) -> 660 | D15: =SUM(D16:D19) -> 175 | E15: =SUM(E16:E19) -> 1415 | F15: =SUM(F16:F19) -> 1119 | G15: =SUM(G16:G19) -> 990 | H15: =SUM(H16:H19) -> 1748 | I15: =SUM(I16:I19) -> 620 | ... N15: =SUM(N16:N19) -> 438.8024 | O15: 126.31 | P15: =SUM(P16:P19) -> 0
A16: Pilares | B16: 178 | C16: 173 | E16: 13 | F16: 257 | G16: 743 | H16: 1715 | I16: 620 | J16: 3699 | M16: 8.8 | N16: 89.1 | P16: 0 | Q16: 0 | R16: 0 | S16: 0
A17: Vigas | B17: 58 | C17: 472 | D17: 64 | E17: 620 | F17: 153 | G17: 247 | H17: 33 | J17: 1647 | M17: 27.3 | N17: 284.8 | P17: 0 | Q17: 0 | R17: 0 | S17: 0
A18: Lajes | D18: 106 | E18: 782 | F18: 610 | J18: 1498 | K18: 0 | L18: 4510 | M18: 12.7 | N18: 52 | P18: 0 | Q18: 0 | R18: 0 | S18: 0
A19: Escada | B19: =Escadas!K10 -> 0 | C19: =Escadas!L10 -> 15 | D19: =Escadas!M10 -> 5 | F19: =Escadas!N10 -> 99 | J19: =SUM(B19:I19) -> 119 | M19: =Escadas!P10 -> 1.650682 | N19: =Escadas!O10 -> 12.9024 | R19: 0 | S19: 0
A20: SUBSOLO 1 | B20: =SUM(B21:B24) -> 419 | C20: =SUM(C21:C24) -> 533 | D20: =SUM(D21:D24) -> 2086 | E20: =SUM(E21:E24) -> 2345 | F20: =SUM(F21:F24) -> 2813 | G20: =SUM(G21:G24) -> 3797 | H20: =SUM(H21:H24) -> 3150 | I20: =SUM(I21:I24) -> 1196 | ... N20: =SUM(N21:N24) -> 695.4256 | O20: 1111.93 | P20: =SUM(P21:P24) -> 0
A21: Pilares | B21: 264 | C21: 239 | E21: 20 | F21: 310 | G21: 1032 | H21: 1624 | I21: 670 | J21: 4159 | M21: 25.2 | N21: 256.7 | P21: 0 | Q21: 0 | R21: 0 | S21: 0
A22: Vigas | B22: 155 | C22: 21 | D22: 70 | E22: 178 | F22: 130 | G22: 219 | H22: 119 | J22: 892 | M22: 36.7 | N22: 331.2 | P22: 0 | Q22: 0 | R22: 0 | S22: 0
A23: Lajes | C23: 256 | D23: 2009 | E23: 2147 | F23: 2264 | G23: 2546 | H23: 1407 | I23: 526 | J23: 11155 | K23: 1460 | L23: 0 | M23: 156.8 | N23: 91.1 | P23: 0 | Q23: 0 | R23: 1185 | S23: 94
A24: Escada | B24: =Escadas!K11 -> 0 | C24: =Escadas!L11 -> 17 | D24: =Escadas!M11 -> 7 | F24: =Escadas!N11 -> 109 | J24: =SUM(B24:I24) -> 133 | M24: =Escadas!P11 -> 2.073698 | N24: =Escadas!O11 -> 16.4256 | R24: 0 | S24: 0
A25: TERREO | B25: =SUM(B26:B29) -> 469 | C25: =SUM(C26:C29) -> 667 | D25: =SUM(D26:D29) -> 6623 | E25: =SUM(E26:E29) -> 4592 | F25: =SUM(F26:F29) -> 6705 | G25: =SUM(G26:G29) -> 5015 | H25: =SUM(H26:H29) -> 5611 | I25: =SUM(I26:I29) -> 22149 | ... N25: =SUM(N26:N29) -> 1285.6262 | O25: 1111.85 | P25: =SUM(P26:P29) -> 0
A26: Pilares | B26: 330 | C26: 289 | E26: 54 | F26: 477 | G26: 717 | H26: 1808 | I26: 601 | J26: 4276 | M26: 32 | N26: 327 | P26: 0 | Q26: 0 | R26: 0 | S26: 0
A27: Vigas | B27: 129 | C27: 202 | D27: 5358 | E27: 2194 | F27: 4375 | G27: 2623 | H27: 2380 | I27: 21166 | J27: 38427 | M27: 229.2 | N27: 822.6 | P27: 0 | Q27: 0 | R27: 0 | S27: 0
A28: Lajes | B28: 8 | C28: 176 | D28: 1218 | E28: 2344 | F28: 1775 | G28: 1675 | H28: 1423 | I28: 382 | J28: 9001 | K28: 1123 | M28: 135.6 | N28: 107.2 | P28: 0 | Q28: 0 | R28: 806 | S28: 141
A29: Escada | B29: =Escadas!K12 -> 2 | C29: =Escadas!L12 -> 0 | D29: =Escadas!M12 -> 47 | F29: =Escadas!N12 -> 78 | J29: =SUM(B29:I29) -> 127 | M29: =Escadas!P12 -> 4.6170057 | N29: =Escadas!O12 -> 28.82623 | P29: 0 | Q29: 0 | R29: 0 | S29: 0
A30: SOBRELOJA | B30: =SUM(B31:B34) -> 306 | C30: =SUM(C31:C34) -> 299 | D30: =SUM(D31:D34) -> 525 | E30: =SUM(E31:E34) -> 631 | F30: =SUM(F31:F34) -> 736 | G30: =SUM(G31:G34) -> 1064 | H30: =SUM(H31:H34) -> 2834 | I30: =SUM(I31:I34) -> 662 | ... N30: =SUM(N31:N34) -> 508.00383 | O30: 180.29 | P30: =SUM(P31:P34) -> 183
A31: Pilares | B31: 124 | C31: 180 | E31: 67 | F31: 121 | G31: 194 | H31: 2373 | J31: 3059 | M31: 22.5 | N31: 236.1 | P31: 0 | Q31: 0 | R31: 0 | S31: 0
A32: Vigas | B32: 180 | C32: 36 | D32: 103 | E32: 62 | F32: 209 | G32: 344 | H32: 223 | I32: 477 | J32: 1634 | M32: 8.4 | N32: 88.5 | P32: 0 | Q32: 0 | R32: 0 | S32: 0
A33: Lajes | C33: 83 | D33: 365 | E33: 502 | F33: 349 | G33: 526 | H33: 238 | I33: 185 | J33: 2248 | K33: 152 | M33: 22.3 | N33: 153.7 | P33: 183 | Q33: 0 | R33: 0 | S33: 0
A34: Escada | B34: =Escadas!K13 -> 2 | C34: =Escadas!L13 -> 0 | D34: =Escadas!M13 -> 57 | F34: =Escadas!M13 -> 57 | J34: =SUM(B34:I34) -> 116 | M34: =Escadas!P13 -> 4.7223227 | N34: =Escadas!O13 -> 29.70383 | P34: 0 | Q34: 0 | R34: 0 | S34: 0
A35: 2º PAVIMENTO | B35: =SUM(B36:B39) -> 569 | C35: =SUM(C36:C39) -> 512 | D35: =SUM(D36:D39) -> 2286 | E35: =SUM(E36:E39) -> 1857 | F35: =SUM(F36:F39) -> 2367 | G35: =SUM(G36:G39) -> 3217 | H35: =SUM(H36:H39) -> 6014 | I35: =SUM(I36:I39) -> 2149 | ... N35: =SUM(N36:N39) -> 1107.9038 | O35: 615.06 | P35: =SUM(P36:P39) -> 942
A36: Pilares | B36: 418 | C36: 157 | F36: 160 | G36: 1121 | H36: 4510 | I36: 962 | J36: 7328 | M36: 22.8 | N36: 231.7 | P36: 0 | Q36: 0 | R36: 0 | S36: 0
A37: Vigas | B37: 149 | C37: 316 | D37: 527 | E37: 381 | F37: 237 | G37: 535 | H37: 410 | I37: 809 | J37: 3364 | M37: 25.6 | N37: 272 | P37: 0 | Q37: 0 | R37: 0 | S37: 0
A38: Lajes | C38: 39 | D38: 1702 | E38: 1476 | F38: 1884 | G38: 1561 | H38: 1094 | I38: 378 | J38: 8134 | K38: 787 | M38: 78.7 | N38: 574.5 | P38: 942 | Q38: 0 | R38: 0 | S38: 0
A39: Escada | B39: =Escadas!$K$14/6 -> 2 | C39: =Escadas!$L$14/6 -> 0 | D39: =Escadas!$M$14/6 -> 57 | F39: =Escadas!$N$14/6 -> 86 | J39: =SUM(B39:I39) -> 145 | M39: =Escadas!$P$14/6 -> 4.7223227 | N39: =Escadas!$O$14/6 -> 29.70383 | P39: 0 | Q39: 0 | R39: 0 | S39: 0
A40: 3º PAVIMENTO | B40: =SUM(B41:B44) -> 523 | C40: =SUM(C41:C44) -> 496 | D40: =SUM(D41:D44) -> 2419 | E40: =SUM(E41:E44) -> 1870 | F40: =SUM(F41:F44) -> 2614 | G40: =SUM(G41:G44) -> 2385 | H40: =SUM(H41:H44) -> 3124 | I40: =SUM(I41:I44) -> 803 | ... N40: =SUM(N41:N44) -> 1091.4038 | O40: 619.9 | P40: =SUM(P41:P44) -> 906
A41: Pilares | B41: 336 | C41: 16 | E41: 43 | F41: 405 | G41: 556 | H41: 1491 | I41: 219 | J41: 3066 | M41: 17.7 | N41: 218.7 | P41: 0 | Q41: 0 | R41: 0 | S41: 0
A42: Vigas | B42: 185 | C42: 398 | D42: 410 | E42: 431 | F42: 404 | G42: 430 | H42: 525 | I42: 234 | J42: 3017 | M42: 25.7 | N42: 272.5 | P42: 0 | Q42: 0 | R42: 0 | S42: 0
A43: Lajes | C43: 82 | D43: 1952 | E43: 1396 | F43: 1719 | G43: 1399 | H43: 1108 | I43: 350 | J43: 8006 | K43: 746 | M43: 79.1 | N43: 570.5 | P43: 906 | Q43: 0 | R43: 0 | S43: 0
A44: Escada | B44: =Escadas!$K$14/6 -> 2 | C44: =Escadas!$L$14/6 -> 0 | D44: =Escadas!$M$14/6 -> 57 | F44: =Escadas!$N$14/6 -> 86 | J44: =SUM(B44:I44) -> 145 | M44: =Escadas!$P$14/6 -> 4.7223227 | N44: =Escadas!$O$14/6 -> 29.70383 | P44: 0 | Q44: 0 | R44: 0 | S44: 0
A45: 4º PAVIMENTO | B45: =SUM(B46:B49) -> 525 | C45: =SUM(C46:C49) -> 480 | D45: =SUM(D46:D49) -> 2419 | E45: =SUM(E46:E49) -> 1917 | F45: =SUM(F46:F49) -> 2908 | G45: =SUM(G46:G49) -> 2203 | H45: =SUM(H46:H49) -> 2033 | I45: =SUM(I46:I49) -> 584 | ... N45: =SUM(N46:N49) -> 1091.4038 | O45: 619.9 | P45: =SUM(P46:P49) -> 906
A46: Pilares | B46: 338 | E46: 90 | F46: 699 | G46: 374 | H46: 400 | J46: 1901 | M46: 17.7 | N46: 218.7 | P46: 0 | Q46: 0 | R46: 0 | S46: 0
A47: Vigas | B47: 185 | C47: 398 | D47: 410 | E47: 431 | F47: 404 | G47: 430 | H47: 525 | I47: 234 | J47: 3017 | M47: 25.7 | N47: 272.5 | P47: 0 | Q47: 0 | R47: 0 | S47: 0
A48: Lajes | C48: 82 | D48: 1952 | E48: 1396 | F48: 1719 | G48: 1399 | H48: 1108 | I48: 350 | J48: 8006 | K48: 746 | M48: 79.1 | N48: 570.5 | P48: 906 | Q48: 0 | R48: 0 | S48: 0
A49: Escada | B49: =Escadas!$K$14/6 -> 2 | C49: =Escadas!$L$14/6 -> 0 | D49: =Escadas!$M$14/6 -> 57 | F49: =Escadas!$N$14/6 -> 86 | J49: =SUM(B49:I49) -> 145 | M49: =Escadas!$P$14/6 -> 4.7223227 | N49: =Escadas!$O$14/6 -> 29.70383 | P49: 0 | Q49: 0 | R49: 0 | S49: 0
A50: 5º PAVIMENTO | B50: =SUM(B51:B54) -> 529 | C50: =SUM(C51:C54) -> 480 | D50: =SUM(D51:D54) -> 2419 | E50: =SUM(E51:E54) -> 1929 | F50: =SUM(F51:F54) -> 3128 | G50: =SUM(G51:G54) -> 1992 | H50: =SUM(H51:H54) -> 1633 | I50: =SUM(I51:I54) -> 584 | ... N50: =SUM(N51:N54) -> 1091.4038 | O50: 619.9 | P50: =SUM(P51:P54) -> 906
A51: Pilares | B51: 342 | E51: 102 | F51: 919 | G51: 163 | J51: 1526 | M51: 17.7 | N51: 218.7 | P51: 0 | Q51: 0 | R51: 0 | S51: 0
A52: Vigas | B52: 185 | C52: 398 | D52: 410 | E52: 431 | F52: 404 | G52: 430 | H52: 525 | I52: 234 | J52: 3017 | M52: 25.7 | N52: 272.5 | P52: 0 | Q52: 0 | R52: 0 | S52: 0
A53: Lajes | C53: 82 | D53: 1952 | E53: 1396 | F53: 1719 | G53: 1399 | H53: 1108 | I53: 350 | J53: 8006 | K53: 746 | M53: 79.1 | N53: 570.5 | P53: 906 | Q53: 0 | R53: 0 | S53: 0
A54: Escada | B54: =Escadas!$K$14/6 -> 2 | C54: =Escadas!$L$14/6 -> 0 | D54: =Escadas!$M$14/6 -> 57 | F54: =Escadas!$N$14/6 -> 86 | J54: =SUM(B54:I54) -> 145 | M54: =Escadas!$P$14/6 -> 4.7223227 | N54: =Escadas!$O$14/6 -> 29.70383 | P54: 0 | Q54: 0 | R54: 0 | S54: 0
A55: 6º PAVIMENTO | B55: =SUM(B56:B59) -> 540 | C55: =SUM(C56:C59) -> 480 | D55: =SUM(D56:D59) -> 2419 | E55: =SUM(E56:E59) -> 1994 | F55: =SUM(F56:F59) -> 3114 | G55: =SUM(G56:G59) -> 1829 | H55: =SUM(H56:H59) -> 1633 | I55: =SUM(I56:I59) -> 584 | ... N55: =SUM(N56:N59) -> 1091.4038 | O55: 619.9 | P55: =SUM(P56:P59) -> 906
A56: Pilares | B56: 353 | E56: 167 | F56: 905 | J56: 1425 | M56: 17.7 | N56: 218.7 | P56: 0 | Q56: 0 | R56: 0 | S56: 0
A57: Vigas | B57: 185 | C57: 398 | D57: 410 | E57: 431 | F57: 404 | G57: 430 | H57: 525 | I57: 234 | J57: 3017 | M57: 25.7 | N57: 272.5 | P57: 0 | Q57: 0 | R57: 0 | S57: 0
A58: Lajes | C58: 82 | D58: 1952 | E58: 1396 | F58: 1719 | G58: 1399 | H58: 1108 | I58: 350 | J58: 8006 | K58: 746 | M58: 79.1 | N58: 570.5 | P58: 906 | Q58: 0 | R58: 0 | S58: 0
A59: Escada | B59: =Escadas!$K$14/6 -> 2 | C59: =Escadas!$L$14/6 -> 0 | D59: =Escadas!$M$14/6 -> 57 | F59: =Escadas!$N$14/6 -> 86 | J59: =SUM(B59:I59) -> 145 | M59: =Escadas!$P$14/6 -> 4.7223227 | N59: =Escadas!$O$14/6 -> 29.70383 | P59: 0 | Q59: 0 | R59: 0 | S59: 0
A60: 7º PAVIMENTO | B60: =SUM(B61:B64) -> 539 | C60: =SUM(C61:C64) -> 480 | D60: =SUM(D61:D64) -> 2419 | E60: =SUM(E61:E64) -> 1994 | F60: =SUM(F61:F64) -> 3107 | G60: =SUM(G61:G64) -> 1829 | H60: =SUM(H61:H64) -> 1633 | I60: =SUM(I61:I64) -> 584 | ... N60: =SUM(N61:N64) -> 1091.4038 | O60: 619.9 | P60: =SUM(P61:P64) -> 906
A61: Pilares | B61: 352 | E61: 167 | F61: 898 | J61: 1417 | M61: 17.7 | N61: 218.7 | P61: 0 | Q61: 0 | R61: 0 | S61: 0
A62: Vigas | B62: 185 | C62: 398 | D62: 410 | E62: 431 | F62: 404 | G62: 430 | H62: 525 | I62: 234 | J62: 3017 | M62: 25.7 | N62: 272.5 | P62: 0 | Q62: 0 | R62: 0 | S62: 0
A63: Lajes | C63: 82 | D63: 1952 | E63: 1396 | F63: 1719 | G63: 1399 | H63: 1108 | I63: 350 | J63: 8006 | K63: 746 | M63: 79.1 | N63: 570.5 | P63: 906 | Q63: 0 | R63: 0 | S63: 0
A64: Escada | B64: =Escadas!$K$14/6 -> 2 | C64: =Escadas!$L$14/6 -> 0 | D64: =Escadas!$M$14/6 -> 57 | F64: =Escadas!$N$14/6 -> 86 | J64: =SUM(B64:I64) -> 145 | M64: =Escadas!$P$14/6 -> 4.7223227 | N64: =Escadas!$O$14/6 -> 29.70383 | P64: 0 | Q64: 0 | R64: 0 | S64: 0
A65: 8º PAVIMENTO | B65: =SUM(B66:B69) -> 539 | C65: =SUM(C66:C69) -> 480 | D65: =SUM(D66:D69) -> 2419 | E65: =SUM(E66:E69) -> 1982 | F65: =SUM(F66:F69) -> 3101 | G65: =SUM(G66:G69) -> 1873 | H65: =SUM(H66:H69) -> 1842 | I65: =SUM(I66:I69) -> 661 | ... N65: =SUM(N66:N69) -> 1091.4038 | O65: 619.9 | P65: =SUM(P66:P69) -> 906
A66: Pilares | B66: 352 | E66: 155 | F66: 892 | G66: 44 | H66: 209 | I66: 77 | J66: 1729 | M66: 17.7 | N66: 218.7 | P66: 0 | Q66: 0 | R66: 0 | S66: 0
A67: Vigas | B67: 185 | C67: 398 | D67: 410 | E67: 431 | F67: 404 | G67: 430 | H67: 525 | I67: 234 | J67: 3017 | M67: 25.7 | N67: 272.5 | P67: 0 | Q67: 0 | R67: 0 | S67: 0
A68: Lajes | C68: 82 | D68: 1952 | E68: 1396 | F68: 1719 | G68: 1399 | H68: 1108 | I68: 350 | J68: 8006 | K68: 746 | M68: 79.1 | N68: 570.5 | P68: 906 | Q68: 0 | R68: 0 | S68: 0
A69: Escada | B69: =Escadas!K15 -> 2 | C69: =Escadas!L15 -> 0 | D69: =Escadas!M15 -> 57 | F69: =Escadas!N15 -> 86 | J69: =SUM(B69:I69) -> 145 | M69: =Escadas!P15 -> 4.7223227 | N69: =Escadas!O15 -> 29.70383 | P69: 0 | Q69: 0 | R69: 0 | S69: 0
A70: TOTAL | B70: =B65+B60+B55+B50+B45+B40 -> 3195 | C70: =C65+C60+C55+C50+C45+C40 -> 2896 | D70: =D65+D60+D55+D50+D45+D40 -> 14514 | E70: =E65+E60+E55+E50+E45+E40 -> 11686 | F70: =F65+F60+F55+F50+F45+F40 -> 17972 | G70: =G65+G60+G55+G50+G45+G40 -> 12111 | H70: =H65+H60+H55+H50+H45+H40 -> 11898 | I70: =I65+I60+I55+I50+I45+I40 -> 3800 | ... S70: =S65+S60+S55+S50+S45+S40 -> 0
A71: ÁTICO | B71: =SUM(B72:B74) -> 525 | C71: =SUM(C72:C74) -> 761 | D71: =SUM(D72:D74) -> 3187 | E71: =SUM(E72:E74) -> 1839 | F71: =SUM(F72:F74) -> 2651 | G71: =SUM(G72:G74) -> 2507 | H71: =SUM(H72:H74) -> 1694 | I71: =SUM(I72:I74) -> 465 | ... N71: =SUM(N72:N74) -> 1177.8 | O71: 614.48 | P71: =SUM(P72:P74) -> 0 | Q71: =SUM(Q72:Q74) -> 845
A72: Pilares | B72: 349 | C72: 19 | E72: 64 | F72: 782 | G72: 105 | H72: 485 | I72: 157 | J72: 1961 | M72: 17.7 | N72: 218.7 | P72: 0 | Q72: 0 | R72: 0 | S72: 0
A73: Vigas | B73: 176 | C73: 588 | D73: 729 | E73: 496 | F73: 360 | G73: 990 | H73: 340 | I73: 95 | J73: 3774 | M73: 38.7 | N73: 395 | P73: 0 | Q73: 0 | R73: 0 | S73: 0
A74: Lajes | C74: 154 | D74: 2458 | E74: 1279 | F74: 1509 | G74: 1412 | H74: 869 | I74: 213 | J74: 7894 | K74: 737 | M74: 95.4 | N74: 564.1 | P74: 0 | Q74: 845 | R74: 0 | S74: 0
A75: PISCINA | B75: =SUM(B76:B78) -> 91 | C75: =SUM(C76:C78) -> 151 | D75: =SUM(D76:D78) -> 885 | E75: =SUM(E76:E78) -> 626 | F75: =SUM(F76:F78) -> 328 | G75: =SUM(G76:G78) -> 38 | H75: =SUM(H76:H78) -> 138 | I75: =SUM(I76:I78) -> 0 | ... N75: =SUM(N76:N78) -> 367.7 | O75: 138.42 | P75: =SUM(P76:P78) -> 0 | Q75: =SUM(Q76:Q78) -> 0
A76: Pilares | B76: 13 | E76: 20 | F76: 15 | G76: 17 | H76: 69 | J76: 134 | M76: 3.3 | N76: 43.7 | P76: 0 | Q76: 0 | R76: 0 | S76: 0
A77: Vigas | B77: 78 | C77: 20 | D77: 74 | E77: 109 | F77: 73 | G77: 21 | H77: 69 | J77: 444 | M77: 19.8 | N77: 205.9 | P77: 0 | Q77: 0 | R77: 0 | S77: 0
A78: Lajes | C78: 131 | D78: 811 | E78: 497 | F78: 240 | J78: 1679 | M78: 18 | N78: 118.1 | P78: 0 | Q78: 0 | R78: 0 | S78: 0
A79: TOTAL | B79: =B71+B75 -> 616 | C79: =C71+C75 -> 912 | D79: =D71+D75 -> 4072 | E79: =E71+E75 -> 2465 | F79: =F71+F75 -> 2979 | G79: =G71+G75 -> 2545 | H79: =H71+H75 -> 1832 | I79: =I71+I75 -> 465 | ... S79: =S71+S75 -> 0
A80: BARRILETE | B80: =SUM(B81:B83) -> 319 | C80: =SUM(C81:C83) -> 86 | D80: =SUM(D81:D83) -> 498 | E80: =SUM(E81:E83) -> 466 | F80: =SUM(F81:F83) -> 1101 | G80: =SUM(G81:G83) -> 493 | H80: =SUM(H81:H83) -> 192 | I80: =SUM(I81:I83) -> 31 | ... N80: =SUM(N81:N83) -> 382.7 | O80: 199.57 | P80: =SUM(P81:P83) -> 344 | Q80: =SUM(Q81:Q83) -> 0
A81: Pilares | B81: 178 | E81: 45 | F81: 468 | G81: 169 | J81: 860 | M81: 6.4 | N81: 84.4 | P81: 0 | Q81: 0 | R81: 0 | S81: 0
A82: Vigas | B82: 141 | C82: 22 | D82: 214 | E82: 54 | F82: 295 | G82: 209 | H82: 27 | J82: 962 | M82: 9.2 | N82: 115.1 | P82: 0 | Q82: 0 | R82: 0 | S82: 0
A83: Lajes | C83: 64 | D83: 284 | E83: 367 | F83: 338 | G83: 115 | H83: 165 | I83: 31 | J83: 1364 | K83: 244 | M83: 22.1 | N83: 183.2 | P83: 344 | Q83: 0 | R83: 0 | S83: 0
A84: CASA DE MÁQUINAS | B84: =SUM(B85:B87) -> 152 | C84: =SUM(C85:C87) -> 67 | D84: =SUM(D85:D87) -> 103 | E84: =SUM(E85:E87) -> 155 | F84: =SUM(F85:F87) -> 262 | G84: =SUM(G85:G87) -> 17 | H84: =SUM(H85:H87) -> 69 | I84: =SUM(I85:I87) -> 106 | ... N84: =SUM(N85:N87) -> 97.5 | O84: 20.42 | P84: =SUM(P85:P87) -> 0 | Q84: =SUM(Q85:Q87) -> 0
A85: Pilares | B85: 109 | E85: 67 | F85: 191 | J85: 367 | M85: 4.9 | N85: 57.5 | P85: 0 | Q85: 0 | R85: 0 | S85: 0
A86: Vigas | B86: 43 | C86: 10 | E86: 37 | F86: 71 | G86: 17 | H86: 69 | I86: 106 | J86: 353 | M86: 2.3 | N86: 26.2 | P86: 0 | Q86: 0 | R86: 0 | S86: 0
A87: Lajes | C87: 57 | D87: 103 | E87: 51 | J87: 211 | M87: 2.8 | N87: 13.8 | P87: 0 | Q87: 0 | R87: 0 | S87: 0
A88: RESERVATÓRIO | B88: =SUM(B89:B91) -> 135 | C88: =SUM(C89:C91) -> 76 | D88: =SUM(D89:D91) -> 196 | E88: =SUM(E89:E91) -> 271 | F88: =SUM(F89:F91) -> 260 | G88: =SUM(G89:G91) -> 130 | H88: =SUM(H89:H91) -> 120 | I88: =SUM(I89:I91) -> 0 | ... N88: =SUM(N89:N91) -> 113.8 | O88: 39.1 | P88: =SUM(P89:P91) -> 0 | Q88: =SUM(Q89:Q91) -> 0
A89: Pilares | B89: 77 | E89: 37 | F89: 189 | J89: 303 | M89: 4.4 | N89: 53.6 | P89: 0 | Q89: 0 | R89: 0 | S89: 0
A90: Vigas | B90: 58 | C90: 3 | D90: 5 | E90: 36 | G90: 130 | H90: 120 | J90: 352 | M90: 2.6 | N90: 27.7 | P90: 0 | Q90: 0 | R90: 0 | S90: 0
A91: Lajes | C91: 73 | D91: 191 | E91: 198 | F91: 71 | J91: 533 | M91: 6.5 | N91: 32.5 | P91: 0 | Q91: 0 | R91: 0 | S91: 0
A92: COBERTURA RESERVATÓRIO | B92: =SUM(B93:B95) -> 165 | C92: =SUM(C93:C95) -> 73 | D92: =SUM(D93:D95) -> 177 | E92: =SUM(E93:E95) -> 90 | F92: =SUM(F93:F95) -> 236 | G92: =SUM(G93:G95) -> 0 | H92: =SUM(H93:H95) -> 0 | I92: =SUM(I93:I95) -> 0 | ... N92: =SUM(N93:N95) -> 118.4 | O92: 40.22 | P92: =SUM(P93:P95) -> 0 | Q92: =SUM(Q93:Q95) -> 0
A93: Pilares | B93: 94 | E93: 39 | F93: 184 | J93: 317 | M93: 5 | N93: 61.7 | P93: 0 | Q93: 0 | R93: 0 | S93: 0
A94: Vigas | B94: 41 | E94: 51 | F94: 52 | J94: 144 | M94: 1.9 | N94: 21.7 | P94: 0 | Q94: 0 | R94: 0 | S94: 0
A95: Lajes | B95: 30 | C95: 73 | D95: 177 | J95: 280 | M95: 4.2 | N95: 35 | P95: 0 | Q95: 0 | R95: 0 | S95: 0
A96: TOTAL | B96: =B80+B84+B88+B92 -> 771 | C96: =C80+C84+C88+C92 -> 302 | D96: =D80+D84+D88+D92 -> 974 | E96: =E80+E84+E88+E92 -> 982 | F96: =F80+F84+F88+F92 -> 1859 | G96: =G80+G84+G88+G92 -> 640 | H96: =H80+H84+H88+H92 -> 381 | I96: =I80+I84+I88+I92 -> 137 | ... S96: =S80+S84+S88+S92 -> 0
A97: TOTAL SUPRA | B97: =B96+B79+B70+B35+B30+B25+B20+B15 -> 6581 | C97: =C96+C79+C70+C35+C30+C25+C20+C15 -> 6781 | D97: =D96+D79+D70+D35+D30+D25+D20+D15 -> 31255 | E97: =E96+E79+E70+E35+E30+E25+E20+E15 -> 25973 | F97: =F96+F79+F70+F35+F30+F25+F20+F15 -> 36550 | G97: =G96+G79+G70+G35+G30+G25+G20+G15 -> 29379 | H97: =H96+H79+H70+H35+H30+H25+H20+H15 -> 33468 | I97: =I96+I79+I70+I35+I30+I25+I20+I15 -> 31178 | ... S97: =S96+S79+S70+S35+S30+S25+S20+S15 -> 0
A98: TOTAL GERAL | B98: =B97+B10 -> 6581 | C98: =C97+C10 -> 6781 | D98: =D97+D10 -> 31255 | E98: =E97+E10 -> 26130 | F98: =F97+F10 -> 37563 | G98: =G97+G10 -> 36805 | H98: =H97+H10 -> 35768 | I98: =I97+I10 -> 31178 | ... S98: =S97+S10 -> 0

Sheet Escadas
D1: Projeto | E1: =Obra!D1 -> Playa Negra
D2: Empresa | E2: =Obra!D2 -> GDI
D3: Origem | E3: 04. GDI - PLAYA NEGRA (compartilhamento)\03. FN ESTRUTURAS\500 - DETALHES
D4: Revisão | E4: R00 - Patricia Bragato
A5: ESCADAS
A6: PAVIMENTO | B6: CÓDIGO DA ESCADA | C6: NÚMERO DE PATAMARES | D6: LADO 1 DO PATAMAR | E6: LADO 2 DO PATAMAR | F6: NÚMERO DE DEGRAUS | G6: COMPRIMENTO DO DEGRAU | H6: LARGURA DO DEGRAU | I6: ALTURA DO ESPELHO DO DEGRAU | J6: ESPESSURA MÉDIA DO DEGRAU | K6: Ø5,00 | L6: Ø6,30 | M6: Ø8,00 | N6: Ø12,00 | O6: FORMA DE COMPENSADO | P6: VOLUME DE CONCRETO | Q6: TAXA DE ARMADURA | R6: ESCORAMENTO
B7: COD. | C7: PATAMARES | F7: DEGRAUS | K7: F | L7: F | M7: C | N7: T | O7: F | P7: C | Q7: T | R7: Aesc
C8: NP | D8: L1 | E8: L2 | F8: ND | G8: D | H8: d | I8: e | J8: B | K8: kgf | L8: kgf | M8: kgf | N8: kgf | O8: (m²) | P8: (m³) | Q8: kg/m3 | R8: m2
A9: Projeto: PNEG-EST-PE-502-ESCA-R00 até PNEG-EST-PE-507-ESCA-R00
A10: Subsolo 02 | C10: 1 | D10: 1.21 | E10: 1.2 | F10: 13 | G10: 1.21 | H10: 0.28 | I10: 0.18 | J10: 0.19 | L10: 15 | M10: 5 | N10: 99 | O10: =C10*D10*E10+F10*G10*H10+G10*I10*F10*2+2*H10*F10*J10 -> 12.9024 | P10: =C10*D10*E10*J10+F10*G10*H10*J10+F10*G10*I10*J10 -> 1.650682 | Q10: =SUM(K10:N10)/P10 -> 72.091414 | R10: =C10*D10*E10+F10*G10*H10 -> 5.8564
A11: Subsolo 01 | C11: 1 | D11: 1.21 | E11: 1.2 | F11: 17 | G11: 1.21 | H11: 0.28 | I11: 0.18 | J11: 0.19 | L11: 17 | M11: 7 | N11: 109 | O11: =C11*D11*E11+F11*G11*H11+G11*I11*F11*2+2*H11*F11*J11 -> 16.4256 | P11: =C11*D11*E11*J11+F11*G11*H11*J11+F11*G11*I11*J11 -> 2.073698 | Q11: =SUM(K11:N11)/P11 -> 64.136629 | R11: =C11*D11*E11+F11*G11*H11 -> 7.2116
A12: Térreo | C12: 1 | D12: =2.2265+1.205 -> 3.4315 | E12: =(1.205*2)*2 -> 4.82 | F12: 14 | G12: 1.205 | H12: 0.28 | I12: 0.18 | J12: 0.19 | K12: 2 | M12: 47 | N12: 78 | O12: =C12*D12*E12+F12*G12*H12+G12*I12*F12*2+2*H12*F12*J12 -> 28.82623 | P12: =C12*D12*E12*J12+F12*G12*H12*J12+F12*G12*I12*J12 -> 4.6170057 | Q12: =SUM(K12:N12)/P12 -> 27.507005 | R12: =C12*D12*E12+F12*G12*H12 -> 21.26343
A13: Sobreloja | C13: 1 | D13: =2.2265+1.205 -> 3.4315 | E13: =(1.205*2)*2 -> 4.82 | F13: 15 | G13: 1.205 | H13: 0.28 | I13: 0.18 | J13: 0.19 | K13: 2 | M13: 57 | N13: 86 | O13: =C13*D13*E13+F13*G13*H13+G13*I13*F13*2+2*H13*F13*J13 -> 29.70383 | P13: =C13*D13*E13*J13+F13*G13*H13*J13+F13*G13*I13*J13 -> 4.7223227 | Q13: =SUM(K13:N13)/P13 -> 30.705229 | R13: =C13*D13*E13+F13*G13*H13 -> 21.60083
A14: Pav tipo x6 | C14: 1 | D14: =2.2265+1.205 -> 3.4315 | E14: =(1.205*2)*2 -> 4.82 | F14: 15 | G14: 1.205 | H14: 0.28 | I14: 0.18 | J14: 0.19 | K14: =2*6 -> 12 | M14: =57*6 -> 342 | N14: =86*6 -> 516 | O14: =(C14*D14*E14+F14*G14*H14+G14*I14*F14*2+2*H14*F14*J14)*6 -> 178.22298 | P14: =(C14*D14*E14*J14+F14*G14*H14*J14+F14*G14*I14*J14)*6 -> 28.333936 | Q14: =SUM(K14:N14)/P14 -> 30.705229 | R14: =(C14*D14*E14+F14*G14*H14)*6 -> 129.60498
A15: 8º Pavimento | C15: 1 | D15: =2.2265+1.205 -> 3.4315 | E15: =(1.205*2)*2 -> 4.82 | F15: 15 | G15: 1.205 | H15: 0.28 | I15: 0.18 | J15: 0.19 | K15: 2 | M15: 57 | N15: 86 | O15: =C15*D15*E15+F15*G15*H15+G15*I15*F15*2+2*H15*F15*J15 -> 29.70383 | P15: =C15*D15*E15*J15+F15*G15*H15*J15+F15*G15*I15*J15 -> 4.7223227 | Q15: =SUM(K15:N15)/P15 -> 30.705229 | R15: =C15*D15*E15+F15*G15*H15 -> 21.60083
A16: TOTAL | C16: =SUM(C10:C15) -> 6 | D16: =SUM(D10:D15) -> 16.146 | E16: =SUM(E10:E15) -> 21.68 | F16: =SUM(F10:F15) -> 89 | G16: =SUM(G10:G15) -> 7.24 | H16: =SUM(H10:H15) -> 1.68 | I16: =SUM(I10:I15) -> 1.08 | J16: =SUM(J10:J15) -> 1.14 | ... P16: =SUM(P10:P15) -> 46.119967 | Q16: =SUM(K16:N16)/P16 -> 33.369495 | R16: =SUM(R8:R15) -> 207.13807

Sheet ARQ
A1: DADOS
A2: Titulo | B2: QUANTITATIVO
A3: Obra | B3: PLAYA NEGRA
A4: Cliente | B4: GDI
A5: Cidade
A6: Endereço
A7: Descrição
A9: QUANTITATIVOS
A10: Item | B10: Descrição | C10: Unid. | D10: Quantidade
A12: 1. | B12: ALVENARIA E VEDAÇÕES
A13: 1.1. | B13: -2_SUB 2
A14: 1.1.1 | B14: BLOCO ANTI-CHAMAS, 15 cm | C14: m² | D14: 50.28
A15: 1.1.2 | B15: BLOCO CERAMICO, 09 cm | C15: m² | D15: 14.59
A16: 1.1.3 | B16: BLOCO CONCRETO, 14 cm | C16: m² | D16: 66.54
A17: 1.1.4 | B17: BLOCO DE COBOGO | C17: m² | D17: 12.65
A18: 1.1.5 | B18: ENCUNHAMENTO | C18: m | D18: 69.82
A19: 1.1.6. | B19: Porta
A20: 1.1.6.1 | B20: VERGAS+CONTRAVERGAS | C20: m | D20: 3.52
A21: 1.2. | B21: -1_SUB 1
A22: 1.2.1 | B22: BLOCO ANTI-CHAMAS, 15 cm | C22: m² | D22: 70.78
A23: 1.2.2 | B23: BLOCO CERAMICO, 09 cm | C23: m² | D23: 18.32
A24: 1.2.3 | B24: BLOCO CERAMICO, 11,5 cm | C24: m² | D24: 13.07
A25: 1.2.4 | B25: BLOCO CONCRETO, 14 cm | C25: m² | D25: 67.55
A26: 1.2.5 | B26: BLOCO DE COBOGO | C26: m² | D26: 19.1
A27: 1.2.6 | B27: DESCONSIDERAR | C27: m² | D27: 21.32
A28: 1.2.7 | B28: ENCUNHAMENTO | C28: m | D28: 62.31
A29: 1.2.8. | B29: Porta
A30: 1.2.8.1 | B30: VERGAS+CONTRAVERGAS | C30: m | D30: 2.44
A31: 1.3. | B31: 00_TER
A32: 1.3.1 | B32: BLOCO ANTI-CHAMAS, 15 cm | C32: m² | D32: 180.7
A33: 1.3.2 | B33: BLOCO CERAMICO, 09 cm | C33: m² | D33: 34.89
A34: 1.3.3 | B34: BLOCO CERAMICO, 11,5 cm | C34: m² | D34: 20.3
A35: 1.3.4 | B35: BLOCO CERAMICO, 14 cm | C35: m² | D35: 414.61
A36: 1.3.5 | B36: BLOCO CONCRETO, 15 cm | C36: m² | D36: 5.36
A37: 1.3.6 | B37: ENCUNHAMENTO | C37: m | D37: 147.24
A38: 1.3.7. | B38: Janela
A39: 1.3.7.1 | B39: VERGAS+CONTRAVERGAS | C39: m | D39: 1.6
A40: 1.3.8. | B40: Porta
A41: 1.3.8.1 | B41: VERGAS+CONTRAVERGAS | C41: m | D41: 11.4
A42: 1.4. | B42: 01_SLOJA
A43: 1.4.1 | B43: BLOCO ANTI-CHAMAS, 15 cm | C43: m² | D43: 52.33
A44: 1.4.2 | B44: BLOCO CERAMICO, 09 cm | C44: m² | D44: 37.05
A45: 1.4.3 | B45: BLOCO CERAMICO, 14 cm | C45: m² | D45: 286.25
A46: 1.4.4 | B46: ENCUNHAMENTO | C46: m | D46: 137.71
A47: 1.4.5. | B47: Janela
A48: 1.4.5.1 | B48: VERGAS+CONTRAVERGAS | C48: m | D48: 1.6
A49: 1.4.6. | B49: Porta
A50: 1.4.6.1 | B50: VERGAS+CONTRAVERGAS | C50: m | D50: 2.2
A51: 1.5. | B51: 2_2º PAV
A52: 1.5.1 | B52: BLOCO ANTI-CHAMAS, 15 cm | C52: m² | D52: 61.22
A53: 1.5.2 | B53: BLOCO CERAMICO, 09 cm | C53: m² | D53: 111.66
A54: 1.5.3 | B54: BLOCO CERAMICO, 11,5 cm | C54: m² | D54: 339.17
A55: 1.5.4 | B55: BLOCO CERAMICO, 14 cm | C55: m² | D55: 390.93
A56: 1.5.5 | B56: ENCUNHAMENTO | C56: m | D56: 406
A57: 1.5.6. | B57: Janela
A58: 1.5.6.1 | B58: VERGAS+CONTRAVERGAS | C58: m | D58: 23.56
A59: 1.5.7. | B59: Porta
A60: 1.5.7.1 | B60: VERGAS+CONTRAVERGAS | C60: m | D60: 47.29
A61: 1.6. | B61: 03_TIPO 1
A62: 1.6.1 | B62: BLOCO ANTI-CHAMAS, 15 cm | C62: m² | D62: 61.24
A63: 1.6.2 | B63: BLOCO CERAMICO, 09 cm | C63: m² | D63: 108.8
A64: 1.6.3 | B64: BLOCO CERAMICO, 11,5 cm | C64: m² | D64: 330.7
A65: 1.6.4 | B65: BLOCO CERAMICO, 14 cm | C65: m² | D65: 392.74
A66: 1.6.5 | B66: ENCUNHAMENTO | C66: m | D66: 400.26
A67: 1.6.6. | B67: Janela
A68: 1.6.6.1 | B68: VERGAS+CONTRAVERGAS | C68: m | D68: 23.56
A69: 1.6.7. | B69: Porta
A70: 1.6.7.1 | B70: VERGAS+CONTRAVERGAS | C70: m | D70: 46.39
A71: 1.7. | B71: 04_TIPO 1
A72: 1.7.1 | B72: BLOCO ANTI-CHAMAS, 15 cm | C72: m² | D72: 61.24
A73: 1.7.2 | B73: BLOCO CERAMICO, 09 cm | C73: m² | D73: 108.8
A74: 1.7.3 | B74: BLOCO CERAMICO, 11,5 cm | C74: m² | D74: 330.7
A75: 1.7.4 | B75: BLOCO CERAMICO, 14 cm | C75: m² | D75: 392.74
A76: 1.7.5 | B76: ENCUNHAMENTO | C76: m | D76: 400.26
A77: 1.7.6. | B77: Janela
A78: 1.7.6.1 | B78: VERGAS+CONTRAVERGAS | C78: m | D78: 23.56
A79: 1.7.7. | B79: Porta
A80: 1.7.7.1 | B80: VERGAS+CONTRAVERGAS | C80: m | D80: 46.39
A81: 1.8. | B81: 05_TIPO 1
A82: 1.8.1 | B82: BLOCO ANTI-CHAMAS, 15 cm | C82: m² | D82: 61.24
A83: 1.8.2 | B83: BLOCO CERAMICO, 09 cm | C83: m² | D83: 108.8
A84: 1.8.3 | B84: BLOCO CERAMICO, 11,5 cm | C84: m² | D84: 330.7
A85: 1.8.4 | B85: BLOCO CERAMICO, 14 cm | C85: m² | D85: 392.74
A86: 1.8.5 | B86: ENCUNHAMENTO | C86: m | D86: 400.26
A87: 1.8.6. | B87: Janela
A88: 1.8.6.1 | B88: VERGAS+CONTRAVERGAS | C88: m | D88: 23.56
A89: 1.8.7. | B89: Porta
A90: 1.8.7.1 | B90: VERGAS+CONTRAVERGAS | C90: m | D90: 46.39
A91: 1.9. | B91: 06_TIPO 1
A92: 1.9.1 | B92: BLOCO ANTI-CHAMAS, 15 cm | C92: m² | D92: 61.24
A93: 1.9.2 | B93: BLOCO CERAMICO, 09 cm | C93: m² | D93: 108.8
A94: 1.9.3 | B94: BLOCO CERAMICO, 11,5 cm | C94: m² | D94: 330.7
A95: 1.9.4 | B95: BLOCO CERAMICO, 14 cm | C95: m² | D95: 392.74
A96: 1.9.5 | B96: ENCUNHAMENTO | C96: m | D96: 400.26
A97: 1.9.6. | B97: Janela
A98: 1.9.6.1 | B98: VERGAS+CONTRAVERGAS | C98: m | D98: 23.56
A99: 1.9.7. | B99: Porta
A100: 1.9.7.1 | B100: VERGAS+CONTRAVERGAS | C100: m | D100: 46.39
A101: 1.10. | B101: 07_TIPO 1
A102: 1.10.1 | B102: BLOCO ANTI-CHAMAS, 15 cm | C102: m² | D102: 61.24
...

Sheet Tijolos refratários
D1: Projeto | E1: =Obra!D1 -> Playa Negra
D2: Empresa | E2: =Obra!D2 -> GDI
D3: Origem | E3: 04. GDI - PLAYA NEGRA (compartilhamento)\02. ARQUITETURA (GDI)\DWG\R09
D4: Revisão | E4: R00 - Patricia Bragato
A5: CHURRASQUERIA
A6: PAVIMENTO | B6: CÓDIGO DA CHURRASQUEIRA | C6: NUMERO DE CHURRASQUEIRAS | D6: LADO A | E6: LADO B | F6: PERIMETRO | G6: ALTURA | H6: AREA DE PISO | I6: AREA DA ABERTURA | J6: AREA DE REFRATÁRIO
B7: COD. | C7: NC | D7: L1 | E7: L2 | F7: P | G7: a | H7: AP | I7: AA | J7: AR
A8: Projeto: PN_REV09_ARQ_ANTEPROJETOo-Folha - 06-15 - PLANTA BAIXA - 2º PAVTO | J8: =SUM(J9:J11) -> 12.6915
A9: Tipo 1 | B9: A | C9: 1 | D9: 0.49 | E9: 0.7 | F9: =2*D9+2*E9 -> 2.38 | G9: 1.2 | H9: =E9*D9 -> 0.343 | I9: =0.6*0.6 -> 0.36 | J9: =(H9+F9*G9-I9)*C9 -> 2.839
A10: Tipo 1 | B10: B | C10: 2 | D10: 0.55 | E10: 0.65 | F10: =2*D10+2*E10 -> 2.4 | G10: 1.2 | H10: =E10*D10 -> 0.3575 | I10: =0.5*0.6 -> 0.3 | J10: =(H10+F10*G10-I10)*C10 -> 5.875
A11: Tipo 1 | B11: C | C11: 1 | D11: 0.95 | E11: 0.65 | F11: =2*D11+2*E11 -> 3.2 | G11: 1.2 | H11: =E11*D11 -> 0.6175 | I11: =0.8*0.6 -> 0.48 | J11: =(H11+F11*G11-I11)*C11 -> 3.9775
A12: Projeto: PN_REV09_ARQ_ANTEPROJETOo-Folha - 07-15 - PLANTA BAIXA - PAVTO TIPO (3º AO 8º) | J12: =SUM(J13:J15) -> 76.149
A13: Tipo (x6) | B13: A | C13: =1*6 -> 6 | D13: 0.49 | E13: 0.7 | F13: =2*D13+2*E13 -> 2.38 | G13: 1.2 | H13: =E13*D13 -> 0.343 | I13: =0.6*0.6 -> 0.36 | J13: =(H13+F13*G13-I13)*C13 -> 17.034
A14: Tipo (x6) | B14: B | C14: =2*6 -> 12 | D14: 0.55 | E14: 0.65 | F14: =2*D14+2*E14 -> 2.4 | G14: 1.2 | H14: =E14*D14 -> 0.3575 | I14: =0.5*0.6 -> 0.3 | J14: =(H14+F14*G14-I14)*C14 -> 35.25
A15: Tipo (x6) | B15: C | C15: =1*6 -> 6 | D15: 0.95 | E15: 0.65 | F15: =2*D15+2*E15 -> 3.2 | G15: 1.2 | H15: =E15*D15 -> 0.6175 | I15: =0.8*0.6 -> 0.48 | J15: =(H15+F15*G15-I15)*C15 -> 23.865
A16: TOTAL | C16: =SUM(C9:C15) -> 28 | J16: =J8+J12 -> 88.8405

Sheet Resumo impermeabilização
B1: Projeto | C1: =Obra!D1 -> Playa Negra
B2: Empresa | C2: =Obra!D2 -> GDI
B3: Origem | C3: PN_R0_IMP_PRANCHA 01 - PLANTA BAIXA SUBSOLO 2, DETALHES ELEVADOR, CISTERNA E ESCADA SS2; PN_R0_IMP_PRANCHA 02 - PLANTA BAIXA SUBSOLO 1 E DETALHES SUBSOLO 1 (1) ; PN_R0_IMP_PRANCHA 03 - PLANTA BAIXA TÉRREO, DETALHES CALÇADA EXTERNA E LAVABO PCD
B4: Revisão | C4: R00 - Patricia Bragato
A5: IMPERMEABILIZAÇÃO
A6: LOCAIS | B6: Descrição orçamento | D6: Area
D7: m2
A8: CISTERNAS | B8: Impermeabilizacao com argamassa polimerica impermeabilizante | D8: =Impermeabilização!$H$13+Impermeabilização!$H$41 -> 161.6
A9: PISCINAS E ESPELHOS DÁGUA | B9: Impermeabilizacao com aditivo cristalizante e membrana PU 2 camadas | D9: =SUMIF(Impermeabilização!$E$160:$E$174,B9,Impermeabilização!$H$160:$H$174) -> 123.975
A10: PISCINAS E ESPELHOS DÁGUA | B10: Impermeabilizacao com aditivo cristalizante e membrana PU potável 2 camadas | D10: =SUMIF(Impermeabilização!$E$160:$E$174,B10,Impermeabilização!$H$160:$H$174) -> 119.1
A11: BANHEIROS, COZINHAS E SACADAS | B11: Impermeabilizacao com argamassa polimerica impermeabilizante | D11: =SUMIF(Impermeabilização!$E$50:$E$158,B11,Impermeabilização!$H$50:$H$158)+Impermeabilização!$H$26 +Impermeabilização!H178+Impermeabilização!H181+Impermeabilização!H188+Impermeabilização!H191+Impermeabilização!H43 -> 2528.312
A12: FLOREIRAS | B12: Impermeabilizacao com aditivo cristalizante, com membrana antiraiz e geomembrana | D12: =SUMIF(Impermeabilização!$E$11:$E$224,B12,Impermeabilização!$H$11:$H$224) -> 80.91
A13: RESERVATÓRIO | B13: Impermeabilizacao com argamassa polimerica impermeabilizante | D13: =Impermeabilização!H212+Impermeabilização!H216 -> 63.889
A14: RESERVATÓRIO | B14: Impermeabilizacao com aditivo cristalizante e membrana PU híbrida | D14: =Impermeabilização!H221 -> 42.021
A15: RALOS | B15: Tratamento de ralo com manta de poliester | D15: =SUMIF(Impermeabilização!$E$11:$E$224,B15,Impermeabilização!$H$11:$H$224) -> 190.621
A16: JANELAS/PEITORIS | B16: Impermeabilização com membranas em peitoris | D16: =SUMIF(Impermeabilização!$E$11:$E$224,B16,Impermeabilização!$H$11:$H$224) -> 109.402
A17: LAJES E TERRAÇOS | B17: Impermeabilizacao com argamassa polimerica impermeabilizante | D17: 260.974
A18: LAJES E TERRAÇOS | B18: Impermeabilizacao com aditivo cristalizante e membrana PU 2 camadas | D18: 223.952
A19: LAJES E TERRAÇOS | B19: Impermeabilizacao com aditivo cristalizante e membrana PU híbrida | D19: 205.326
A20: LAJES E TERRAÇOS | B20: Impermeabilizacao com aditivo cristalizante e membrana PU | D20: 101.714
A21: LAJES E TERRAÇOS | B21: Impermeabilizacao com aditivo cristalizante e membrana PU de alto trânsito | D21: 1771.9984
A22: LAJES E TERRAÇOS | B22: Impermeabilizacao com aditivo cristalizante | D22: 35.725
A23: TOTAL | D23: =SUM(D8:D22) -> 6019.5194

Sheet Impermeabilização
B2: IMPERMEABILIZAÇÃO
B4: Obra | C4: Playa Negra
B5: Empresa | C5: GDI Empreendimentos
B6: Revisão | C6: R00
B7: Data | C7: 45526
B8: Acesso aos projetos | C8: PN_R0_IMP_PRANCHA 01 - PLANTA BAIXA SUBSOLO 2, DETALHES ELEVADOR, CISTERNA E ESCADA SS2; PN_R0_IMP_PRANCHA 02 - PLANTA BAIXA SUBSOLO 1 E DETALHES SUBSOLO 1 (1) ; PN_R0_IMP_PRANCHA 03 - PLANTA BAIXA TÉRREO, DETALHES CALÇADA EXTERNA E LAVABO PCD
B10: Pavimento | C10: Locais | D10: Descrição | E10: Descrição orçamento | F10: Area(m²) | G10: Repetições | H10: Total
B11: SUBSOLO 2 | C11: POÇO DO ELEVADOR | D11: Membrana cimentícia semiflexível | E11: Impermeabilizacao com aditivo cristalizante | F11: 35.725 | G11: 1 | H11: =G11*F11 -> 35.725
C12: Parede cobogó | D12: Cristalização + membrana PU alto trânsito | E12: Impermeabilizacao com aditivo cristalizante e membrana PU de alto trânsito | F12: =2.42*0.02 -> 0.0484 | G12: 1 | H12: =G12*F12 -> 0.0484
C13: CISTERNA | D13: Membrana cimentícia semiflexível | E13: Impermeabilizacao com argamassa polimerica impermeabilizante | F13: 114.118 | G13: 1 | H13: =G13*F13 -> 114.118
D14: Membrana cimentícia flexível | F14: 113.556 | G14: 1 | H14: =G14*F14 -> 113.556
D15: Reforço com tela poliester de 10cm | E15: Tratamento de ralo com manta de poliester | F15: 0.12 | G15: 1 | H15: =G15*F15 -> 0.12
C16: ESCADA | D16: Membrana cimentícia semiflexível | E16: Impermeabilizacao com argamassa polimerica impermeabilizante | F16: 6.583 | G16: 1 | H16: =G16*F16 -> 6.583
D17: Membrana cimentícia flexível | F17: 6.583 | G17: 1 | H17: =G17*F17 -> 6.583
C18: TOTAL | F18: =SUM(F11:F17) -> 276.7334
B19: SUBSOLO 1 | C19: GARAGEM | D19: Prime cimentício de correção de substrato | E19: Impermeabilizacao com aditivo cristalizante e membrana PU de alto trânsito | F19: =4.719+2.768+7.16+1034.31 -> 1048.957 | G19: 1 | H19: =G19*F19 -> 1048.957
D20: Membrana de alto trânsito | F20: =4.766+2.779+7.18+1033.9719 -> 1048.6969 | G20: 1 | H20: =G20*F20 -> 1048.6969
D21: Reforço com tela poliester de 10cm | E21: Tratamento de ralo com manta de poliester | F21: 0.72 | G21: 1 | H21: =G21*F21 -> 0.72
C22: TOTAL | F22: =SUM(F19:F21) -> 2098.3739
B23: TÉRREO | C23: Calçada externa | D23: Prime cimentício de correção de substrato | E23: Impermeabilizacao com aditivo cristalizante e membrana PU | F23: =56.363+1.771+1.673+0.217 -> 60.024 | G23: 1 | H23: =G23*F23 -> 60.024
D24: Membrana de PU | F24: =56.363+1.781+1.665+0.216 -> 60.025 | G24: 1 | H24: =G24*F24 -> 60.025
D25: Quartzo | F25: =53.777+1.241+1.657+0.224 -> 56.899 | G25: 1 | H25: =G25*F25 -> 56.899
C26: Lavabo PCD | D26: Membrana cimentícia semiflexível | E26: Impermeabilizacao com argamassa polimerica impermeabilizante | F26: =2*4.274 -> 8.548 | G26: 1 | H26: =G26*F26 -> 8.548
D27: Membrana cimentícia flexível | F27: =2*3.261 -> 6.522 | G27: 1 | H27: =G27*F27 -> 6.522
D28: Reforço com tela poliester de 10cm | E28: Tratamento de ralo com manta de poliester | F28: =2*0.169 -> 0.338 | G28: 1 | H28: =G28*F28 -> 0.338
C29: Garagem | D29: Prime cimentício de correção de substrato | E29: Impermeabilizacao com aditivo cristalizante e membrana PU de alto trânsito | F29: =720.886+2.107 -> 722.993 | G29: 1 | H29: =G29*F29 -> 722.993
D30: Membrana de alto trânsito | F30: =723.155+2.116 -> 725.271 | G30: 1 | H30: =G30*F30 -> 725.271
D31: Reforço com tela poliester de 10cm | E31: Tratamento de ralo com manta de poliester | F31: 0.174 | G31: 1 | H31: =G31*F31 -> 0.174
C32: Janela (dep. Int. lixo) | D32: Membrana Sikafill | E32: Impermeabilização com membranas em peitoris | F32: 1.07 | G32: 1 | H32: =G32*F32 -> 1.07
C33: Acesso ao subsolo | D33: Prime cimentício de correção de substrato | E33: Impermeabilizacao com aditivo cristalizante e membrana PU | F33: 41.69 | G33: 1 | H33: =G33*F33 -> 41.69
D34: Membrana de alto trânsito | F34: 41.679 | G34: 1 | H34: =G34*F34 -> 41.679
C35: Dep. Int. lixo | D35: Membrana cimentícia semiflexível | E35: Impermeabilizacao com argamassa polimerica impermeabilizante | F35: 43.852 | G35: 1 | H35: =G35*F35 -> 43.852
D36: Membrana cimentícia flexível | F36: 7.855 | G36: 1 | H36: =G36*F36 -> 7.855
D37: Reforço com tela poliester de 10cm | E37: Tratamento de ralo com manta de poliester | F37: 0.106 | G37: 1 | H37: =G37*F37 -> 0.106
C38: Dep. Tem. Lixo | D38: Membrana cimentícia semiflexível | E38: Impermeabilizacao com argamassa polimerica impermeabilizante | F38: 23.022 | G38: 1 | H38: =G38*F38 -> 23.022
D39: Membrana cimentícia flexível | F39: 4.458 | G39: 1 | H39: =G39*F39 -> 4.458
C40: TOTAL | F40: =SUM(F23:F39) -> 1804.526
B41: SOBRELOJA | C41: Cisterna pluvial | D41: Membrana cimentícia semiflexível | E41: Impermeabilizacao com argamassa polimerica impermeabilizante | F41: =47.159+0.323 -> 47.482 | G41: 1 | H41: =G41*F41 -> 47.482
D42: Membrana cimentícia flexível | F42: =17.376+0.323 -> 17.699 | G42: 1 | H42: =G42*F42 -> 17.699
C43: Lavabo Loja - sobreloja | D43: Membrana cimentícia semiflexível | E43: Impermeabilizacao com argamassa polimerica impermeabilizante | F43: =4.202 -> 4.202 | G43: 1 | H43: =G43*F43 -> 4.202
D44: Membrana cimentícia flexível | F44: 2.193 | G44: 1 | H44: =G44*F44 -> 2.193
D45: Reforço com tela poliester de 10cm | E45: Tratamento de ralo com manta de poliester | F45: 0.166 | G45: 1 | H45: =G45*F45 -> 0.166
C46: Janela (cisterna) | D46: Membrana Sikafill | E46: Impermeabilização com membranas em peitoris | F46: 1.069 | G46: 1 | H46: =G46*F46 -> 1.069
C47: Cobertura Glp | D47: Prime cimentício de correção de substrato | E47: Impermeabilizacao com aditivo cristalizante e membrana PU híbrida | F47: 1.744 | G47: 1 | H47: =G47*F47 -> 1.744
D48: Membrana de PU híbrida | F48: 1.741 | G48: 1 | H48: =G48*F48 -> 1.741
C49: TOTAL | F49: =SUM(F41:F48) -> 76.296
B50: TIPOS | C50: SACADA (APTOS 209, 309 AO 809) | D50: Membrana cimentícia semiflexível | E50: Impermeabilizacao com argamassa polimerica impermeabilizante | F50: 2.966 | G50: =3*6 -> 18 | H50: =G50*F50 -> 53.388
D51: Membrana cimentícia flexível | F51: 2.882 | G51: =3*6 -> 18 | H51: =G51*F51 -> 51.876
D52: Reforço com tela poliester de 10cm | E52: Tratamento de ralo com manta de poliester | F52: 2.882 | G52: =3*6 -> 18 | H52: =G52*F52 -> 51.876
C53: SACADA (APTOS 209, 310 AO 810) | D53: Membrana cimentícia semiflexível | E53: Impermeabilizacao com argamassa polimerica impermeabilizante | F53: 6.468 | G53: =3*6 -> 18 | H53: =G53*F53 -> 116.424
D54: Membrana cimentícia flexível | F54: 4.245 | G54: =3*6 -> 18 | H54: =G54*F54 -> 76.41
D55: Reforço com tela poliester de 10cm | E55: Tratamento de ralo com manta de poliester | F55: 4.245 | G55: =3*6 -> 18 | H55: =G55*F55 -> 76.41
C56: LAVABO (APTO 209) | D56: Membrana cimentícia semiflexível | E56: Impermeabilizacao com argamassa polimerica impermeabilizante | F56: 2.588 | G56: 1 | H56: =G56*F56 -> 2.588
D57: Membrana cimentícia flexível | F57: 2.58 | G57: 1 | H57: =G57*F57 -> 2.58
D58: Reforço com tela poliester de 10cm | E58: Tratamento de ralo com manta de poliester | F58: 0.162 | G58: 1 | H58: =G58*F58 -> 0.162
C59: JANELAS TIPOS E BWC | D59: Membrana Sikafill | E59: Impermeabilização com membranas em peitoris | F59: =1.248+0.479 -> 1.727 | G59: =5*10+9 -> 59 | H59: =G59*F59 -> 101.893
C60: ÁREA DE SERVIÇO (APTOS 209,310 AO 810) | D60: Membrana cimentícia semiflexível | E60: Impermeabilizacao com argamassa polimerica impermeabilizante | F60: 5.025 | G60: =3*6 -> 18 | H60: =G60*F60 -> 90.45
D61: Membrana cimentícia flexível | F61: 2.214 | G61: =3*6 -> 18 | H61: =G61*F61 -> 39.852
D62: Reforço com tela poliester de 10cm | E62: Tratamento de ralo com manta de poliester | F62: 0.103 | G62: =3*6 -> 18 | H62: =G62*F62 -> 1.854
C63: BWC (APTO 209) | D63: Membrana cimentícia semiflexível | E63: Impermeabilizacao com argamassa polimerica impermeabilizante | F63: 6.125 | G63: 1 | H63: =G63*F63 -> 6.125
D64: Membrana cimentícia flexível | F64: 3.511 | G64: 1 | H64: =G64*F64 -> 3.511
D65: Reforço com tela poliester de 10cm | E65: Tratamento de ralo com manta de poliester | F65: 0.244 | G65: 1 | H65: =G65*F65 -> 0.244
C66: BWC (APTO 209, 309 A 809) | D66: Membrana cimentícia semiflexível | E66: Impermeabilizacao com argamassa polimerica impermeabilizante | F66: 8.605 | G66: =3*6 -> 18 | H66: =G66*F66 -> 154.89
D67: Membrana cimentícia flexível | F67: 4.183 | G67: =3*6 -> 18 | H67: =G67*F67 -> 75.294
D68: Reforço com tela poliester de 10cm | E68: Tratamento de ralo com manta de poliester | F68: 0.26 | G68: =3*6 -> 18 | H68: =G68*F68 -> 4.68
C69: ÁREA DE SERVIÇO (APTOS 309 A 809) | D69: Membrana cimentícia semiflexível | E69: Impermeabilizacao com argamassa polimerica impermeabilizante | F69: 2.503 | G69: 10 | H69: =G69*F69 -> 25.03
D70: Membrana cimentícia flexível | F70: 1.033 | G70: 10 | H70: =G70*F70 -> 10.33
D71: Reforço com tela poliester de 10cm | E71: Tratamento de ralo com manta de poliester | F71: 0.11 | G71: 10 | H71: =G71*F71 -> 1.1
C72: BWC (APTOS 310 AO 810) | D72: Membrana cimentícia semiflexível | E72: Impermeabilizacao com argamassa polimerica impermeabilizante | F72: 8.388 | G72: 10 | H72: =G72*F72 -> 83.88
D73: Membrana cimentícia flexível | F73: 4.066 | G73: 10 | H73: =G73*F73 -> 40.66
D74: Reforço com tela poliester de 10cm | E74: Tratamento de ralo com manta de poliester | F74: 0.271 | G74: 10 | H74: =G74*F74 -> 2.71
C75: ÁREA DE SERVIÇO (APTOS 201 AO 801) | D75: Membrana cimentícia semiflexível | E75: Impermeabilizacao com argamassa polimerica impermeabilizante | F75: 5.015 | G75: 12 | H75: =G75*F75 -> 60.18
D76: Membrana cimentícia flexível | F76: 2.187 | G76: 12 | H76: =G76*F76 -> 26.244
D77: Reforço com tela poliester de 10cm | E77: Tratamento de ralo com manta de poliester | F77: 0.103 | G77: 12 | H77: =G77*F77 -> 1.236
C78: BWC (APTOS 201 AO 801) | D78: Membrana cimentícia semiflexível | E78: Impermeabilizacao com argamassa polimerica impermeabilizante | F78: =6.282 -> 6.282 | G78: 12 | H78: =G78*F78 -> 75.384
D79: Membrana cimentícia flexível | F79: 6.623 | G79: 12 | H79: =G79*F79 -> 79.476
D80: Reforço com tela poliester de 10cm | E80: Tratamento de ralo com manta de poliester | F80: 0.236 | G80: 12 | H80: =G80*F80 -> 2.832
C81: SACADA (APTOS 201 A 801) | D81: Membrana cimentícia semiflexível | E81: Impermeabilizacao com argamassa polimerica impermeabilizante | F81: 13.915 | G81: 12 | H81: =G81*F81 -> 166.98
D82: Membrana cimentícia flexível | F82: 6.211 | G82: 12 | H82: =G82*F82 -> 74.532
D83: Reforço com tela poliester de 10cm | E83: Tratamento de ralo com manta de poliester | F83: 0.061 | G83: 12 | H83: =G83*F83 -> 0.732
C84: LAVABO (APTOS 201 A 801) | D84: Membrana cimentícia semiflexível | E84: Impermeabilizacao com argamassa polimerica impermeabilizante | F84: 2.322 | G84: 12 | H84: =G84*F84 -> 27.864
D85: Membrana cimentícia flexível | F85: 2.197 | G85: 12 | H85: =G85*F85 -> 26.364
D86: Reforço com tela poliester de 10cm | E86: Tratamento de ralo com manta de poliester | F86: 0.169 | G86: 12 | H86: =G86*F86 -> 2.028
C87: ÁREA DE SERVIÇO (APTOS 202 A 802) | D87: Membrana cimentícia semiflexível | E87: Impermeabilizacao com argamassa polimerica impermeabilizante | F87: 4.998 | G87: 12 | H87: =G87*F87 -> 59.976
D88: Membrana cimentícia flexível | F88: 2.188 | G88: 12 | H88: =G88*F88 -> 26.256
D89: Reforço com tela poliester de 10cm | E89: Tratamento de ralo com manta de poliester | F89: 0.103 | G89: 12 | H89: =G89*F89 -> 1.236
C90: SACADA (APTOS 202 A 802) | D90: Membrana cimentícia semiflexível | E90: Impermeabilizacao com argamassa polimerica impermeabilizante | F90: 12.606 | G90: 12 | H90: =G90*F90 -> 151.272
D91: Membrana cimentícia flexível | F91: 6.029 | G91: 12 | H91: =G91*F91 -> 72.348
D92: Reforço com tela poliester de 10cm | E92: Tratamento de ralo com manta de poliester | F92: 0.068 | G92: 12 | H92: =G92*F92 -> 0.816
C93: LAVABO (APTOS 202 A 802) | D93: Membrana cimentícia semiflexível | E93: Impermeabilizacao com argamassa polimerica impermeabilizante | F93: 2.027 | G93: 12 | H93: =G93*F93 -> 24.324
D94: Membrana cimentícia flexível | F94: 2.028 | G94: 12 | H94: =G94*F94 -> 24.336
D95: Reforço com tela poliester de 10cm | E95: Tratamento de ralo com manta de poliester | F95: 0.163 | G95: 12 | H95: =G95*F95 -> 1.956
C96: BWC (APTOS 202 AO 802) | D96: Membrana cimentícia semiflexível | E96: Impermeabilizacao com argamassa polimerica impermeabilizante | F96: 8.511 | G96: 12 | H96: =G96*F96 -> 102.132
D97: Membrana cimentícia flexível | F97: 4.278 | G97: 12 | H97: =G97*F97 -> 51.336
D98: Reforço com tela poliester de 10cm | E98: Tratamento de ralo com manta de poliester | F98: 0.265 | G98: 12 | H98: =G98*F98 -> 3.18
C99: ÁREA DE SERVIÇO (APTOS 203 A 803) | D99: Membrana cimentícia semiflexível | E99: Impermeabilizacao com argamassa polimerica impermeabilizante | F99: 5.088 | G99: 12 | H99: =G99*F99 -> 61.056
D100: Membrana cimentícia flexível | F100: 2.368 | G100: 12 | H100: =G100*F100 -> 28.416
D101: Reforço com tela poliester de 10cm | E101: Tratamento de ralo com manta de poliester | F101: 0.106 | G101: 12 | H101: =G101*F101 -> 1.272
C102: SACADA (APTOS 203 A 803) | D102: Membrana cimentícia semiflexível | E102: Impermeabilizacao com argamassa polimerica impermeabilizante | F102: 5.373 | G102: 12 | H102: =G102*F102 -> 64.476
D103: Membrana cimentícia flexível | F103: 3.467 | G103: 12 | H103: =G103*F103 -> 41.604
...

Sheet INTERFONIA
A1: Obra | B1: =Obra!D1 -> Playa Negra
A2: Empresa | B2: =Obra!D2 -> GDI
A3: Revisão | B3: =Obra!D3 -> R00 - Patricia Bragato
A4: QUANTIFICAÇÃO
A6: Interfonia
A8: Interfonia
B10: Descrição quantitativo | C10: Quantidade | D10: unidade | E10: Preço unitário | F10: Preço total
B11: Aparelho interfone | C11: =Obra!E19+3+4 -> 76 | D11: pç | E11: 72 | F11: =E11*C11 -> 5472
B12: Porteiro externo | C12: 1 | D12: pç | E12: 492 | F12: =E12*C12 -> 492
B13: Centro de acesso digital | C13: 2 | D13: pç | E13: 1310 | F13: =E13*C13 -> 2620
B14: Fechadura solenoide | C14: =C12 -> 1 | D14: pç | E14: 169 | F14: =E14*C14 -> 169
B15: Fechadura eletromagnetica | C15: =C13 -> 2 | D15: pç | E15: 179 | F15: =E15*C15 -> 358
B16: Fonte alimentação | C16: =C14 -> 1 | D16: pç | E16: 269 | F16: =E16*C16 -> 269
B17: no Break | C17: =C14 -> 1 | D17: pç | E17: 520 | F17: =E17*C17 -> 520
B18: Bateria | C18: =C14 -> 1 | D18: pç | E18: 95 | F18: =E18*C18 -> 95
B19: Botão de saida | C19: =C13+C12 -> 3 | D19: pç | E19: 65 | F19: =E19*C19 -> 195
B20: Tag id | C20: =Obra!E18+1 -> 40.97 | D20: pç | E20: 2.2 | F20: =E20*C20 -> 90.134
B21: Mão de obra para instlação de interfonia | C21: =Obra!E9 -> 8518.6 | D21: m² | E21: 3.8 | F21: =E21*C21 -> 32370.68
B22: Total | F22: =SUM(F11:F21) -> 42650.814

Sheet PISCINA
A1: Obra | B1: =Obra!D1 -> Playa Negra
A2: Empresa | B2: =Obra!D2 -> GDI
A3: Revisão | B3: =Obra!D3 -> R00 - Patricia Bragato
A4: QUANTIFICAÇÃO
A6: Piscina
A8: Piscina
B10: Descrição quantitativo | C10: Quantidade | D10: unidade | E10: Preço unitário | F10: Preço total
B11: RALO DE FUNDO QUADRA ANTI-TURBILHÃO (16X16cm) E ANTI-APRISIONAMENTO COM DIFUSOR DE SOBREPOR EM AÇO INOX CRISTAL LED | C11: 2 | D11: un | E11: 169 | F11: =E11*C11 -> 338
B12: BOCAL DE ASPIRAÇÃO QUADRA ANTI-TURBILHÃO E ANTI-APRISIONAMENTO AÇO INOX 316-L CRISTAL LED ENCAIXE P/ TUBO DE 50mm | C12: 1 | D12: un | E12: 199 | F12: =E12*C12 -> 199
B13: BR - BOCAL DE RETORNO QUADRA AÇO INOX 316-L CRISTAL LED ENCAIXE P/ TUBO DE 50mm | C13: 2 | D13: un | E13: 199 | F13: =E13*C13 -> 398
B14: COADEIRA COMPACTA CRISTAL LED EM ABS C/ ACABAMENTO FRENTE EM INOX | C14: 1 | D14: un | E14: 889 | F14: =E14*C14 -> 889
B15: FILTRO SODRAMAR FM-50 – COM 125kg areia | C15: 1 | D15: un | E15: 1162 | F15: =E15*C15 -> 1162
B16: MOTOBOMBA SYLLENT AUTO ESCORVANTE 3/4CV Mono | C16: 2 | D16: un | E16: 1699 | F16: =E16*C16 -> 3398
B17: GERADOR DE COLORO BZ -30 | C17: 1 | D17: un | E17: 3656.75 | F17: =E17*C17 -> 3656.75
B18: TAMPA ARTICULADA GDA 110X110cm CÓDIGO 3140 | C18: 1 | D18: un | E18: 3200 | F18: =E18*C18 -> 3200
B19: RALO DE FUNDO QUADRA ANTI-TURBILHÃO (21X21cm) E ANTI-APRISIONAMENTO COM DIFUSOR DE SOBREPOR EM AÇO INOX CRISTAL LED. | C19: 4 | D19: un | E19: 169 | F19: =E19*C19 -> 676
B20: BOCAL DE ASPIRAÇÃO QUADRA ANTI-TURBILHÃO E ANTI-APRISIONAMENTO AÇO INOX 316-L CRISTAL LED ENCAIXE P/ TUBO DE 50mm | C20: 2 | D20: un | E20: 199 | F20: =E20*C20 -> 398
B21: BR - BOCAL DE RETORNO QUADRA AÇO INOX 316-L CRISTAL LED ENCAIXE P/ TUBO DE 50mm | C21: 4 | D21: un | E21: 199 | F21: =E21*C21 -> 796
B22: COADEIRA COMPACTA CRISTAL LED EM ABS C/ ACABAMENTO FRENTE EM INOX | C22: 2 | D22: un | E22: 889 | F22: =E22*C22 -> 1778
... B27: TAMPA GDA REBAIXADA C/ GRELHA 80X80cm CÓDIGO 3078 | C27: 2 | D27: un | E27: 1850 | F27: =E27*C27 -> 3700
B28: Total | F28: =SUM(F11:F27) -> 33364.59

Sheet PORTÕES
A1: Obra | B1: =Obra!D1 -> Playa Negra
A2: Empresa | B2: =Obra!D2 -> GDI
A3: Revisão | B3: =Obra!D3 -> R00 - Patricia Bragato
A4: QUANTIFICAÇÃO
A6: PORTÕES
A8: Automatização de portões
B10: Descrição quantitativo | C10: Quantidade | D10: unidade | E10: Preço unitário | F10: Preço total
B11: MOTOR BASCULANTE BV HOME CUSTON CALHA 1,4 M | C11: 2 | D11: pç | E11: 900 | F11: =E11*C11 -> 1800
B12: MOTOR DZ STARK 400 | C12: 1 | D12: pç | E12: 800 | F12: =E12*C12 -> 800
B13: No break portão | C13: =C11+C12 -> 3 | D13: pç | E13: 890 | F13: =E13*C13 -> 2670
B14: BATERIA MOURA 12MN45 ESTACIONARIA | C14: =C11+C12 -> 3 | D14: pç | E14: 399 | F14: =E14*C14 -> 1197
B15: CABO PARA BATERIA EXTERNA | C15: =C14 -> 3 | D15: pç | E15: 115 | F15: =E15*C15 -> 345
B16: SENSOR ANTI ESMAGAMENTO | C16: =C14 -> 3 | D16: pç | E16: 220 | F16: =E16*C16 -> 660
B17: PLACA CONTROLADORA IP 01 PORTAS - C3-200 | C17: =C14 -> 3 | D17: pç | E17: 1134 | F17: =E17*C17 -> 3402
B18: Total | F18: =SUM(F11:F17) -> 10874

Sheet Esquadrias
C1: Projeto | D1: =Obra!D1 -> Playa Negra
C2: Empresa | D2: =Obra!D2 -> GDI
C3: Origem | D3: 04. GDI - PLAYA NEGRA (compartilhamento)\02. ARQUITETURA (GDI)\DWG\R09
C4: Revisão | D4: R00 - Patricia Bragato
A5: ESQUADRIAS
A6: CÓDIGO DA ESQUADRIA | B6: DESCRIÇÃO | C6: MATERIAL | D6: TIPO | E6: LARGURA | F6: ALTURA | G6: QUANTIDADE | H6: CONTRAMARCOS | I6: AREA TOTAL | J6: CUSTO UNITÁRIO | K6: CUSTO TOTAL
A7: COD. | B7: DESC | C7: MAT | D7: TIP | E7: L (cm) | F7: A (cm) | G7: QTE | H7: (m) | I7: AT (m²) | J7: CU | K7: CT
A8: PORTAS UNITÁRIAS | H8: =SUM(H9:H18) -> 168.4 | I8: =SUM(I9:I18) -> 512.25 | J8: =K8/I8 -> 451.20519 | K8: =SUM(K9:K18) -> 231129.86
A9: P01 | B9: P01 - PORTA DE ABRIR, 1 FOLHA, MADEIRA, 80 x 210 cm | C9: MADEIRA | D9: PORTA | E9: 80 | F9: 210 | G9: 160 | I9: =(E9/100*F9/100)*G9 -> 268.8 | J9: =611.2+196.65 -> 807.85 | K9: =J9*G9 -> 129256
A10: P02 | B10: P02 - PORTA DE ABRIR, 1 FOLHA, MADEIRA, 90 x 210 cm | C10: MADEIRA | D10: PORTA | E10: 90 | F10: 210 | G10: 74 | I10: =(E10/100*F10/100)*G10 -> 139.86 | J10: =611.2+196.65 -> 807.85 | K10: =J10*G10 -> 59780.9
A11: P03 | B11: P03 - PORTA DE CORRER, 1 FOLHA, MADEIRA, 100 x 210 cm | C11: MADEIRA | D11: PORTA | E11: 100 | F11: 210 | G11: 2 | I11: =(E11/100*F11/100)*G11 -> 4.2 | J11: =891.59+196.65+75.89 -> 1164.13 | K11: =J11*G11 -> 2328.26
A12: P08 | B12: P08 - PORTA DE ABRIR, 1 FOLHA, MADEIRA, 70 x 210 cm | C12: MADEIRA | D12: PORTA | E12: 70 | F12: 210 | G12: 22 | I12: =(E12/100*F12/100)*G12 -> 32.34 | J12: =611.2+196.65 -> 807.85 | K12: =J12*G12 -> 17772.7
A13: P35 | B13: P35 - PORTA DE ABRIR, 1 FOLHA, CORTA FOGO, MADEIRA, 100 x 220 cm | C13: MADEIRA | D13: PCF | E13: 100 | F13: 220 | G13: 1 | H13: =(2*F13/100+2*E13/100)*G13 -> 6.4 | I13: =(E13/100*F13/100)*G13 -> 2.2 | K13: =J13*G13 -> 0
A14: PCF | B14: PCF - PORTA DE ABRIR, 1 FOLHA, CORTA FOGO, 90 x 210 cm | C14: METALICA | D14: PCF | E14: 90 | F14: 210 | G14: 20 | H14: =(2*F14/100+2*E14/100)*G14 -> 120 | I14: =(E14/100*F14/100)*G14 -> 37.8 | J14: =21992/20 -> 1099.6 | K14: =J14*G14 -> 21992
A15: POR1 | B15: PORTÃO 01 - PORTÃO CORRER, 1 FOLHA, FERRO, 400 x 220 cm | C15: METALICA | D15: PORTÃO | E15: 400 | F15: 220 | G15: 1 | H15: =(2*F15/100+2*E15/100)*G15 -> 12.4 | I15: =(E15/100*F15/100)*G15 -> 8.8 | K15: =J15*G15 -> 0
A16: POR2 | B16: PORTÃO 02 - PORTÃO BASCULANTE, 1 FOLHA, FERRO, 300 x 230 cm | C16: METALICA | D16: PORTÃO | E16: 300 | F16: 230 | G16: 1 | H16: =(2*F16/100+2*E16/100)*G16 -> 10.6 | I16: =(E16/100*F16/100)*G16 -> 6.9 | K16: =J16*G16 -> 0
A17: POR3 | B17: PORTÃO 03 - PORTÃO BASCULANTE, 1 FOLHA, FERRO, 350 x 230 cm | C17: METALICA | D17: PORTÃO | E17: 350 | F17: 230 | G17: 1 | H17: =(2*F17/100+2*E17/100)*G17 -> 11.6 | I17: =(E17/100*F17/100)*G17 -> 8.05 | K17: =J17*G17 -> 0
A18: POR5 | B18: PORTÃO 05 - PORTAO DE ABRIR, 2 FOLHAS, ALUMÍNIO, 150 x 220 cm | C18: ALUMINIO | D18: PORTA | E18: 150 | F18: 220 | G18: 1 | H18: =(2*F18/100+2*E18/100)*G18 -> 7.4 | I18: =(E18/100*F18/100)*G18 -> 3.3 | K18: =J18*G18 -> 0
A19: ESQUADRIAS DE ALUMINIO | H19: =SUM(H20:H42) -> 392.38 | I19: =SUM(I20:I42) -> 725.9282 | J19: =K19/I19 -> 924.15392 | K19: 670869.39
A20: J02 | B20: J02 - JANELA MAXIM-AIR, 2 FOLHAS + PEITORIL FIXO, ALUMÍNIO E VIDRO, 200 x 175 cm | C20: ALUMINIO | D20: JANELA | E20: 200 | F20: 175 | G20: 43 | H20: 0 | I20: =(E20/100*F20/100)*G20 -> 150.5 | K20: =J20*I20 -> 0
A21: J03 | B21: J03 - JANELA MAXIM-AIR, 1 FOLHA, ALUMÍNIO E VIDRO, 60 x 60 cm | C21: ALUMINIO | D21: JANELA | E21: 60 | F21: 60 | G21: 7 | H21: =(2*F21/100+2*E21/100)*G21 -> 16.8 | I21: =(E21/100*F21/100)*G21 -> 2.52 | K21: =J21*I21 -> 0
A22: J04 | B22: J04 - JANELA MAXIM-AIR, 2 FOLHAS + PEITORIL FIXO, ALUMÍNIO E VIDRO, 260 x 175 cm | C22: ALUMINIO | D22: JANELA | E22: 260 | F22: 175 | G22: 28 | H22: 0 | I22: =(E22/100*F22/100)*G22 -> 127.4 | K22: =J22*I22 -> 0
A23: J06 | B23: J06 - JANELA MAXIM-AIR, 1 FOLHA, ALUMÍNIO E VIDRO, 80 x 120 cm | C23: ALUMINIO | D23: JANELA | E23: 80 | F23: 120 | G23: 7 | H23: =(2*F23/100+2*E23/100)*G23 -> 28 | I23: =(E23/100*F23/100)*G23 -> 6.72 | K23: =J23*I23 -> 0
A24: J07 | B24: J07 - JANELA MAXIM-AIR, 2 FOLHAS + PEITORIL FIXO, ALUMÍNIO E VIDRO, 120 x 175 cm | C24: ALUMINIO | D24: JANELA | E24: 120 | F24: 175 | G24: 6 | H24: 0 | I24: =(E24/100*F24/100)*G24 -> 12.6 | K24: =J24*I24 -> 0
A25: J11 | B25: J11 - JANELA MAXIM-AIR, 1 FOLHA, ALUMÍNIO E VIDRO, 160 x 175 cm | C25: ALUMINIO | D25: JANELA | E25: 160 | F25: 175 | G25: 1 | H25: 0 | I25: =(E25/100*F25/100)*G25 -> 2.8 | K25: =J25*I25 -> 0
A26: J14 | B26: J14 - JANELA MAXIM-AIR, 1 FOLHA, ALUMÍNIO E VIDRO, 60 x 100 cm | C26: ALUMINIO | D26: JANELA | E26: 60 | F26: 100 | G26: 7 | H26: =(2*F26/100+2*E26/100)*G26 -> 22.4 | I26: =(E26/100*F26/100)*G26 -> 4.2 | K26: =J26*I26 -> 0
A27: J15 | B27: J15 - JANELA MAXIM-AIR, 1 FOLHAS, ALUMÍNIO E VIDRO, 80 x 130 cm | C27: ALUMINIO | D27: JANELA | E27: 80 | F27: 130 | G27: 28 | H27: =(2*F27/100+2*E27/100)*G27 -> 117.6 | I27: =(E27/100*F27/100)*G27 -> 29.12 | K27: =J27*I27 -> 0
A28: J16 | B28: J16 - JANELA MAXIM-AIR, 1 FOLHAS + PEITORIL FIXO, ALUMÍNIO E VIDRO, 90 x 180 cm | C28: ALUMINIO | D28: JANELA | E28: 90 | F28: 180 | G28: 7 | H28: =(2*F28/100+2*E28/100)*G28 -> 37.8 | I28: =(E28/100*F28/100)*G28 -> 11.34 | K28: =J28*I28 -> 0
A29: J24 | B29: J24 - JANELA FIXA, 1 FOLHA, ALUMÍNIO E VIDRO, 200 x 60 cm | C29: ALUMINIO | D29: JANELA | E29: 200 | F29: 60 | G29: 2 | H29: =(2*F29/100+2*E29/100)*G29 -> 10.4 | I29: =(E29/100*F29/100)*G29 -> 2.4 | K29: =J29*I29 -> 0
A30: J26 | B30: J26 - JANELA MAXIM-AIR, 1 FOLHAS, ALUMÍNIO E VIDRO, 80 x 80 cm | C30: ALUMINIO | D30: JANELA | E30: 80 | F30: 80 | G30: 14 | H30: =(2*F30/100+2*E30/100)*G30 -> 44.8 | I30: =(E30/100*F30/100)*G30 -> 8.96 | K30: =J30*I30 -> 0
A31: - | B31: JANELA TELADA FIXA, 1 FOLHA, ALUMINIO, 110 x 100 cm | C31: ALUMINIO | D31: JANELA | E31: 110 | F31: 100 | G31: 2 | H31: =(2*F31/100+2*E31/100)*G31 -> 8.4 | I31: =(E31/100*F31/100)*G31 -> 2.2 | K31: =J31*I31 -> 0
A32: P05 | B32: P05 - PORTA PIVOTANTE, 1 FOLHA, VIDRO, 144 x 220 cm | C32: ALUMINIO | D32: PORTA | E32: 144 | F32: 220 | G32: 1 | H32: =(2*F32/100+2*E32/100)*G32 -> 7.28 | I32: =(E32/100*F32/100)*G32 -> 3.168 | K32: =J32*I32 -> 0
A33: P07 | B33: P07 - PORTA PIVOTANTE, 1 FOLHA, VIDRO, 114 x 210 cm | C33: ALUMINIO | D33: PORTA | E33: 114 | F33: 210 | G33: 2 | H33: =(2*F33/100+2*E33/100)*G33 -> 12.96 | I33: =(E33/100*F33/100)*G33 -> 4.788 | K33: =J33*I33 -> 0
A34: P4 | B34: P4 - PORTA DE CORRER, 2 FOLHAS, VIDRO, 240 x 240 cm | C34: ALUMINIO | D34: PORTA | E34: 240 | F34: 240 | G34: 2 | I34: =(E34/100*F34/100)*G34 -> 11.52 | K34: =J34*I34 -> 0
A35: PJ01 | B35: PJ01 - PORTA DE CORRER, 2 FOLHAS, VIDRO TEMPERADO, 200 x 225 cm | C35: ALUMINIO | D35: PORTA | E35: 200 | F35: 225 | G35: 49 | I35: =(E35/100*F35/100)*G35 -> 220.5 | K35: =J35*I35 -> 0
A36: PJ02 | B36: PJ02 - PORTA DE CORRER, 2 FOLHAS, VIDRO TEMPERADO, 150 x 225 cm | C36: ALUMINIO | D36: PORTA | E36: 150 | F36: 225 | G36: 14 | I36: =(E36/100*F36/100)*G36 -> 47.25 | K36: =J36*I36 -> 0
A37: PJ03 | B37: PJ03 - PORTA DE CORRER, 4 FOLHAS, VIDRO, 380 x 225 cm | C37: ALUMINIO | D37: PORTA | E37: 380 | F37: 225 | G37: 3 | I37: =(E37/100*F37/100)*G37 -> 25.65 | K37: =J37*I37 -> 0
A38: PJ04 | B38: PJ04 - PORTA DE CORRER, 3 FOLHAS, VIDRO TEMPERADO, 293 x 225 cm | C38: ALUMINIO | D38: PORTA | E38: 293 | F38: 225 | G38: 2 | H38: =(2*F38/100+2*E38/100)*G38 -> 20.72 | I38: =(E38/100*F38/100)*G38 -> 13.185 | K38: =J38*I38 -> 0
A39: PJ05 | B39: PJ05 - PORTA DE CORRER, 2 FOLHAS, VIDRO TEMPERADO, 300 x 225 cm | C39: ALUMINIO | D39: PORTA | E39: 300 | F39: 225 | G39: 1 | H39: =(2*F39/100+2*E39/100)*G39 -> 10.5 | I39: =(E39/100*F39/100)*G39 -> 6.75 | K39: =J39*I39 -> 0
A40: PJ06 | B40: PJ06 - PORTA DE CORRER, 2 FOLHAS, VIDRO TEMPERADO, 500 x 225 cm | C40: ALUMINIO | D40: PORTA | E40: 500 | F40: 225 | G40: 1 | I40: =(E40/100*F40/100)*G40 -> 11.25 | K40: =J40*I40 -> 0
A41: PJ24 | B41: PJ24 - PORTA VENEZIANA DE ABRIR PARA FORA, 1 FOLHA, ALUMINIO, 88 x 216 cm | C41: ALUMINIO | D41: PORTA | E41: 88 | F41: 216 | G41: 9 | H41: =(2*F41/100+2*E41/100)*G41 -> 54.72 | I41: =(E41/100*F41/100)*G41 -> 17.1072 | K41: =J41*I41 -> 0
A42: - | B42: PORTA DE CORRER, 2 FOLHAS, VIDRO, 200 x 100 cm | C42: ALUMINIO | D42: PORTA | E42: 200 | F42: 100 | G42: 2 | I42: =(E42/100*F42/100)*G42 -> 4 | K42: =J42*I42 -> 0
A43: PELE | I43: =SUM(I44) -> 103.5 | J43: =K43/I43 -> 1288.3233 | K43: =K44 -> 133341.46
A44: - | B44: PELE DE VIDRO | C44: VIDRO | D44: PELE | E44: 0 | F44: 0 | G44: 1 | H44: 0 | I44: 103.5 | J44: =12816.24/(3.316*3) -> 1288.3233 | K44: =J44*I44 -> 133341.46
B45: TOTAL | K45: =K19+K8 -> 901999.25

Sheet Corrimão
C1: Projeto | D1: =Obra!D1 -> Playa Negra
C2: Empresa | D2: =Obra!D2 -> GDI
C3: Origem | D3: 04. GDI - PLAYA NEGRA (compartilhamento)\02. ARQUITETURA (GDI)\DWG\R09
C4: Revisão | D4: R00 - Patricia Bragato
A5: CORRIMÃOS, GUARDA CORPOS E SERRALHERIA
A6: CÓDIGO DA ESQUADRIA | B6: DESCRIÇÃO | C6: MATERIAL | D6: TIPO | E6: COMPRIMENTO | F6: ALTURA | G6: QUANTIDADE | H6: AREA TOTAL | I6: CUSTO UNITÁRIO | J6: CUSTO TOTAL
A7: COD. | B7: DESC | C7: MAT | D7: TIP | E7: C (m) | F7: A (m) | G7: QTE | H7: AT (m²) | I7: CU | J7: CT
A8: CORRIMÃO E SERRALHERIAS | J8: =SUM(J9:J11) -> 0
A9: COR | B9: CORRIMAO DE MADEIRA ESCADA, 90cm | D9: CORRIMÃO | E9: 158.09 | F9: 90 | G9: 1 | H9: 0 | J9: =I9*H9 -> 0
A10: SER | B10: ESCADA MARINHEIRO | C10: METALICA | D10: ESCADA | E10: 0 | F10: 3 | G10: 5 | H10: =(E10/100*F10/100)*G10 -> 0 | J10: =I10*H10 -> 0
A11: SER | B11: ESCADA MARINHEIRO | C11: METALICA | D11: ESCADA | E11: 0 | F11: 5 | G11: 1 | H11: =(E11/100*F11/100)*G11 -> 0 | J11: =I11*H11 -> 0
A12: GUARDA CORPOS | H12: =SUM(H13:H19) -> 742.912 | I12: =J12/H12 -> 916.56763 | J12: =SUM(J13:J19) -> 680929.09
A13: - | B13: GUARDA-CORPO DE VIDRO H=1,1M | C13: VIDRO | D13: GUARDA-CORPO | E13: =H13/F13 -> 63.418182 | F13: 1.1 | G13: 1 | H13: 69.76 | I13: =58281.28/(21.419*1.15) -> 2366.0943 | J13: =I13*H13 -> 165058.74
A14: - | B14: GUARDA-CORPO DE VIDRO H=1M | C14: VIDRO | D14: GUARDA-CORPO | E14: =H14/F14 -> 15.13 | F14: 1 | G14: 1 | H14: 15.13 | I14: =58281.28/(21.419*1.15) -> 2366.0943 | J14: =I14*H14 -> 35799.007
A15: - | B15: GUARDA-CORPO ALUMINIO H=1,1M | C15: ALUMINIO | D15: GUARDA-CORPO | E15: 114.5 | F15: 1.1 | G15: 1 | H15: =(E15*F15)*G15 -> 125.95 | I15: =1835.3/2.8971 -> 633.49556 | J15: =I15*H15 -> 79788.766
A16: - | B16: GUARDA-CORPO ALUMINIO H=0,7M | C16: ALUMINIO | D16: GUARDA-CORPO | E16: 605.76 | F16: 0.7 | G16: 1 | H16: =(E16*F16)*G16 -> 424.032 | I16: =1835.3/2.8971 -> 633.49556 | J16: =I16*H16 -> 268622.39
A17: - | B17: GUARDA-CORPO ALUMINIO H=0,84M | C17: ALUMINIO | D17: GUARDA-CORPO | E17: 51.75 | F17: 0.84 | G17: 1 | H17: =(E17*F17)*G17 -> 43.47 | I17: =1835.3/2.8971 -> 633.49556 | J17: =I17*H17 -> 27538.052
A18: - | B18: GUARDA-CORPO DE ALUMINIO H=1,1M | C18: ALUMINIO | D18: GUARDA-CORPO | E18: 25.53 | F18: 1.1 | G18: 1 | H18: =(E18*F18)*G18 -> 28.083 | I18: =1835.3/2.8971 -> 633.49556 | J18: =I18*H18 -> 17790.456
A19: - | B19: GUARDA-CORPO DE VIDRO H=1,1M | C19: VIDRO | D19: GUARDA-CORPO | E19: 33.17 | F19: 1.1 | G19: 1 | H19: =(E19*F19)*G19 -> 36.487 | I19: =58281.28/(21.419*1.15) -> 2366.0943 | J19: =I19*H19 -> 86331.683
B20: TOTAL | E20: =SUM(E13:E19) -> 909.25818 | J20: =J12+J8 -> 680929.09

Sheet Louças e metais
C1: Projeto | D1: =Obra!D1 -> Playa Negra
C2: Empresa | D2: =Obra!D2 -> GDI
C3: Origem | D3: 04. GDI - PLAYA NEGRA (compartilhamento)\02. ARQUITETURA (GDI)\DWG\R09
C4: Revisão | D4: R00 - Patricia Bragato
A5: LOUÇAS E METAIS
A6: AMBIENTE | B6: DESCRIÇÃO | C6: UNIDADE | D6: QUANTIDADE | E6: REPETIÇÃO | F6: TOTAL
A7: TERREO
A8: Lavabo PCD | B8: Vaso sanitário deca branco PNE | C8: un | D8: 1 | E8: 2 | F8: =E8*D8 -> 2
A9: Lavabo PCD | B9: Lavatório PNE de canto | C9: un | D9: 1 | E9: 2 | F9: =E9*D9 -> 2
A10: Lavabo PCD | B10: Torneira banheiro PNE | C10: un | D10: 1 | E10: 2 | F10: =E10*D10 -> 2
A11: Lavabo PCD | B11: Acabamento metálico para registro de gaveta | C11: un | D11: 1 | E11: 2 | F11: =E11*D11 -> 2
A12: Lavabo PCD | B12: Barra de apoio PNE | C12: un | D12: 2 | E12: 2 | F12: =E12*D12 -> 4
A13: Lavabo PCD | B13: Anel de vedação, 100 mm, para saíde de bacia sanitária | C13: un | D13: 1 | E13: 2 | F13: =E13*D13 -> 2
A14: Lavabo PCD | B14: Engate/ rabicho flexível inóx 1/2"x40mm | C14: un | D14: 1 | E14: 2 | F14: =E14*D14 -> 2
A15: Lavabo PCD | B15: Parafuso niquelado para fixação de bacia sanitária - tamanho S-10 | C15: un | D15: 2 | E15: 2 | F15: =E15*D15 -> 4
A16: Lavabo PCD | B16: Sifão ajustável multiuso | C16: un | D16: 1 | E16: 2 | F16: =E16*D16 -> 2
A17: Lavabo PCD | B17: Válvula de escoamento para lavatório | C17: un | D17: 1 | E17: 2 | F17: =E17*D17 -> 2
A18: SOBRELOJA
A19: Lavabo | B19: Acabamento metálico para registro de gaveta | C19: un | D19: 2 | E19: 2 | F19: =E19*D19 -> 4
A20: Lavabo | B20: Anel de vedação, 100 mm, para saíde de bacia sanitária | C20: un | D20: 1 | E20: 2 | F20: =E20*D20 -> 2
A21: Lavabo | B21: Cuba de embutir | C21: un | D21: 1 | E21: 2 | F21: =E21*D21 -> 2
A22: Lavabo | B22: Engate/ rabicho flexível inóx 1/2"x40mm | C22: un | D22: 2 | E22: 2 | F22: =E22*D22 -> 4
A23: Lavabo | B23: Bancada em granito | C23: m2 | D23: =0.45*1.5 -> 0.675 | E23: 2 | F23: =E23*D23 -> 1.35
A24: Lavabo | B24: Parafuso niquelado para fixação de bacia sanitária - tamanho S-10 | C24: un | D24: 2 | E24: 2 | F24: =E24*D24 -> 4
A25: Lavabo | B25: Sifão ajustável multiuso | C25: un | D25: 1 | E25: 2 | F25: =E25*D25 -> 2
A26: Lavabo | B26: Válvula de escoamento para lavatório | C26: un | D26: 1 | E26: 2 | F26: =E26*D26 -> 2
A27: Lavabo | B27: Vaso sanitário deca branco | C27: un | D27: 1 | E27: 2 | F27: =E27*D27 -> 2
A28: TIPO 1
A29: Lavabo | B29: Vaso sanitário deca branco | C29: un | D29: 1 | E29: 3 | F29: =E29*D29 -> 3
A30: Lavabo | B30: Anel de vedação, 100 mm, para saíde de bacia sanitária | C30: un | D30: 1 | E30: 3 | F30: =E30*D30 -> 3
A31: Lavabo | B31: Engate/ rabicho flexível inóx 1/2"x40mm | C31: un | D31: 1 | E31: 3 | F31: =E31*D31 -> 3
A32: Lavabo | B32: Parafuso niquelado para fixação de bacia sanitária - tamanho S-10 | C32: un | D32: 2 | E32: 3 | F32: =E32*D32 -> 6
A33: Lavabo | B33: Acabamento metálico para registro de gaveta | C33: un | D33: 1 | E33: 3 | F33: =E33*D33 -> 3
A34: BWC | B34: Vaso sanitário deca branco | C34: un | D34: 1 | E34: 12 | F34: =E34*D34 -> 12
A35: BWC | B35: Anel de vedação, 100 mm, para saíde de bacia sanitária | C35: un | D35: 1 | E35: 12 | F35: =E35*D35 -> 12
A36: BWC | B36: Engate/ rabicho flexível inóx 1/2"x40mm | C36: un | D36: 1 | E36: 12 | F36: =E36*D36 -> 12
A37: BWC | B37: Parafuso niquelado para fixação de bacia sanitária - tamanho S-10 | C37: un | D37: 2 | E37: 12 | F37: =E37*D37 -> 24
A38: BWC | B38: Acabamento metálico para registro de gaveta | C38: un | D38: 1 | E38: 12 | F38: =E38*D38 -> 12
A39: Cozinhas/areas de serviço | B39: Acabamento metálico para registro de gaveta | C39: un | D39: 2 | E39: 9 | F39: =E39*D39 -> 18
A40: Sacadas | B40: Acabamento metálico para registro de gaveta | C40: un | D40: 1 | E40: 3 | F40: =E40*D40 -> 3
A41: TIPO 2 (x6)
A42: Lavabo | B42: Vaso sanitário deca branco | C42: un | D42: 1 | E42: =6*4 -> 24 | F42: =E42*D42 -> 24
A43: Lavabo | B43: Anel de vedação, 100 mm, para saíde de bacia sanitária | C43: un | D43: 1 | E43: =6*4 -> 24 | F43: =E43*D43 -> 24
A44: Lavabo | B44: Engate/ rabicho flexível inóx 1/2"x40mm | C44: un | D44: 1 | E44: =6*4 -> 24 | F44: =E44*D44 -> 24
A45: Lavabo | B45: Parafuso niquelado para fixação de bacia sanitária - tamanho S-10 | C45: un | D45: 2 | E45: =6*4 -> 24 | F45: =E45*D45 -> 48
A46: Lavabo | B46: Acabamento metálico para registro de gaveta | C46: un | D46: 1 | E46: =6*4 -> 24 | F46: =E46*D46 -> 24
A47: BWC | B47: Vaso sanitário deca branco | C47: un | D47: 1 | E47: =6*12 -> 72 | F47: =E47*D47 -> 72
A48: BWC | B48: Anel de vedação, 100 mm, para saíde de bacia sanitária | C48: un | D48: 1 | E48: =6*12 -> 72 | F48: =E48*D48 -> 72
A49: BWC | B49: Engate/ rabicho flexível inóx 1/2"x40mm | C49: un | D49: 1 | E49: =6*12 -> 72 | F49: =E49*D49 -> 72
A50: BWC | B50: Parafuso niquelado para fixação de bacia sanitária - tamanho S-10 | C50: un | D50: 2 | E50: =6*12 -> 72 | F50: =E50*D50 -> 144
A51: BWC | B51: Acabamento metálico para registro de gaveta | C51: un | D51: 1 | E51: =6*12 -> 72 | F51: =E51*D51 -> 72
A52: Cozinhas/areas de serviço | B52: Acabamento metálico para registro de gaveta | C52: un | D52: 2 | E52: =10*6 -> 60 | F52: =E52*D52 -> 120
A53: Sacadas | B53: Acabamento metálico para registro de gaveta | C53: un | D53: 1 | E53: =6*3 -> 18 | F53: =E53*D53 -> 18
A54: ATICO
A55: Lavabo | B55: Acabamento metálico para registro de gaveta | C55: un | D55: 2 | E55: 3 | F55: =E55*D55 -> 6
A56: Lavabo | B56: Anel de vedação, 100 mm, para saíde de bacia sanitária | C56: un | D56: 1 | E56: 3 | F56: =E56*D56 -> 3
A57: Lavabo | B57: Cuba de embutir | C57: un | D57: 1 | E57: 3 | F57: =E57*D57 -> 3
A58: Lavabo | B58: Engate/ rabicho flexível inóx 1/2"x40mm | C58: un | D58: 2 | E58: 3 | F58: =E58*D58 -> 6
A59: Lavabo | B59: Bancada em granito | C59: m2 | D59: =0.45*1.5 -> 0.675 | E59: 3 | F59: =E59*D59 -> 2.025
A60: Lavabo | B60: Parafuso niquelado para fixação de bacia sanitária - tamanho S-10 | C60: un | D60: 2 | E60: 3 | F60: =E60*D60 -> 6
A61: Lavabo | B61: Sifão ajustável multiuso | C61: un | D61: 1 | E61: 3 | F61: =E61*D61 -> 3
A62: Lavabo | B62: Válvula de escoamento para lavatório | C62: un | D62: 1 | E62: 3 | F62: =E62*D62 -> 3
A63: Lavabo | B63: Vaso sanitário deca branco | C63: un | D63: 1 | E63: 3 | F63: =E63*D63 -> 3
A64: Lavabo PCD | B64: Vaso sanitário deca branco PNE | C64: un | D64: 1 | E64: 1 | F64: =E64*D64 -> 1
A65: Lavabo PCD | B65: Lavatório PNE de canto | C65: un | D65: 1 | E65: 1 | F65: =E65*D65 -> 1
A66: Lavabo PCD | B66: Torneira banheiro PNE | C66: un | D66: 1 | E66: 1 | F66: =E66*D66 -> 1
A67: Lavabo PCD | B67: Acabamento metálico para registro de gaveta | C67: un | D67: 1 | E67: 1 | F67: =E67*D67 -> 1
A68: Lavabo PCD | B68: Barra de apoio PNE | C68: un | D68: 2 | E68: 1 | F68: =E68*D68 -> 2
A69: Lavabo PCD | B69: Anel de vedação, 100 mm, para saíde de bacia sanitária | C69: un | D69: 1 | E69: 1 | F69: =E69*D69 -> 1
A70: Lavabo PCD | B70: Engate/ rabicho flexível inóx 1/2"x40mm | C70: un | D70: 1 | E70: 1 | F70: =E70*D70 -> 1
A71: Lavabo PCD | B71: Parafuso niquelado para fixação de bacia sanitária - tamanho S-10 | C71: un | D71: 2 | E71: 1 | F71: =E71*D71 -> 2
... A85: Grill e Pizza | B85: Acabamento metálico para registro de gaveta | C85: un | D85: 1 | E85: 1 | F85: =E85*D85 -> 1
B86: TOTAL | F86: =SUM(F8:F85) -> 937.375
A89: TIPO | B89: DESCRIÇÃO | C89: UNIDADE | D89: QUANTIDADE | E89: CUSTO UNITÁRIO | F89: CUSTO TOTAL
A90: LOUÇAS | B90: Cuba de cozinha | C90: un | D90: =SUMIF($B$8:$B$85,B90,$F$8:$F$85) -> 5 | E90: 1222.18 | F90: =E90*D90 -> 6110.9
B91: Cuba de embutir | C91: un | D91: =SUMIF($B$8:$B$85,B91,$F$8:$F$85) -> 5 | E91: 1222.18 | F91: =E91*D91 -> 6110.9
B92: Lavatório PNE de canto | C92: un | D92: =SUMIF($B$8:$B$85,B92,$F$8:$F$85) -> 3 | E92: 265.9 | F92: =E92*D92 -> 797.7
B93: Vaso sanitário deca branco | C93: un | D93: =SUMIF($B$8:$B$85,B93,$F$8:$F$85) -> 116 | E93: 1199.9 | F93: =E93*D93 -> 139188.4
B94: Vaso sanitário deca branco PNE | C94: un | D94: =SUMIF($B$8:$B$85,B94,$F$8:$F$85) -> 3 | E94: 1199.9 | F94: =E94*D94 -> 3599.7
B95: TOTAL | F95: =SUM(F90:F94) -> 155807.6
A96: METAIS | B96: Acabamento metálico para registro de gaveta | C96: un | D96: =SUMIF($B$8:$B$85,B96,$F$8:$F$85) -> 286 | E96: 62.34 | F96: =E96*D96 -> 17829.24
B97: Anel de vedação, 100 mm, para saíde de bacia sanitária | C97: un | D97: =SUMIF($B$8:$B$85,B97,$F$8:$F$85) -> 119 | E97: 13.3 | F97: =E97*D97 -> 1582.7
B98: Barra de apoio PNE | C98: un | D98: =SUMIF($B$8:$B$85,B98,$F$8:$F$85) -> 6 | E98: 518.66 | F98: =E98*D98 -> 3111.96
B99: Engate/ rabicho flexível inóx 1/2"x40mm | C99: un | D99: =SUMIF($B$8:$B$85,B99,$F$8:$F$85) -> 124 | E99: 14.75 | F99: =E99*D99 -> 1829
B100: Parafuso niquelado para fixação de bacia sanitária - tamanho S-10 | C100: un | D100: =SUMIF($B$8:$B$85,B100,$F$8:$F$85) -> 238 | E100: 24.95 | F100: =E100*D100 -> 5938.1
B101: Sifão ajustável multiuso | C101: un | D101: =SUMIF($B$8:$B$85,B101,$F$8:$F$85) -> 13 | E101: 13.9 | F101: =E101*D101 -> 180.7
B102: Torneira banheiro PNE | C102: un | D102: =SUMIF($B$8:$B$85,B102,$F$8:$F$85) -> 3 | E102: 229.9 | F102: =E102*D102 -> 689.7
B103: Torneira de jardim | C103: un | D103: =SUMIF($B$8:$B$85,B103,$F$8:$F$85) -> 0 | E103: 55 | F103: =E103*D103 -> 0
B104: Válvula de escoamento para cuba | C104: un | D104: =SUMIF($B$8:$B$85,B104,$F$8:$F$85) -> 5 | E104: 54.25 | F104: =E104*D104 -> 271.25
B105: Válvula de escoamento para lavatório | C105: un | D105: =SUMIF($B$8:$B$85,B105,$F$8:$F$85) -> 8 | E105: 21.9 | F105: =E105*D105 -> 175.2
B106: TOTAL | F106: =SUM(F96:F105) -> 31607.85
A107: BANCADA | B107: Bancada em granito | C107: m2 | D107: =SUMIF($B$8:$B$85,B107,$F$8:$F$85) -> 3.375 | E107: 835 | F107: =E107*D107 -> 2818.125
B108: TOTAL | F108: =SUM(F104:F107) -> 34872.425

Sheet DRENAGEM
B2: DRENAGEM
B4: Obra | C4: Playa Negra
B5: Empresa | C5: GDI Empreendimentos
B6: Revisão | C6: R00
B7: Data | C7: 45527
B8: Acesso aos projetos | C8: 20230817_PN_PROJETO DE DRENAGEM
B10: PRANCHA DE ORIGEM | C10: Descrição | D10: Quantidade | E10: Unidade | F10: Custo unitário | G10: Origem | H10: Custo Total
C11: McDrain TD (1x20) para Trincheira Drenante | D11: 320 | E11: m2 | F11: 47.79 | G11: Ammos | H11: =F11*D11 -> 15292.8
C12: McDrain FP (2x30) para Cortina Drenante | D12: 1020 | E12: m2 | F12: 42.54 | G12: Ammos | H12: =F12*D12 -> 43390.8
C13: McDrain FP (2x30) para Colchãortina Drenante | D13: 1140 | E13: m2 | F13: 42.54 | G13: Ammos | H13: =F13*D13 -> 48495.6
C14: Tubo perfurado McPipe 100mm | D14: 400 | E14: m | F14: =195.26/10 -> 19.526 | G14: Isocom | H14: =F14*D14 -> 7810.4
C15: Tubo perfurado McPipe 160mm | D15: 50 | E15: m | F15: =1946.21/50 -> 38.9242 | G15: Isocom | H15: =F15*D15 -> 1946.21
C16: Caixa de passagem | D16: 1 | F16: 233.97331 | H16: =F16*D16 -> 233.97331
C17: Poço de recalque | D17: 1 | F17: 443.41051 | H17: =F17*D17 -> 443.41051
H18: =F18*D18 -> 0
H19: =SUM(H11:H18) -> 117613.19

Sheet MOBILIÁRIO
B2: MOBILIÁRIO
B4: Obra | C4: Playa Negra
B5: Empresa | C5: GDI Empreendimentos
B6: Revisão | C6: R00
B7: Data | C7: 45538
B8: Acesso aos projetos | C8: 20231005_PN_REV08_ARQ_PROJETO LEGAL // PN_RE02_ARQ_ANTEPROJETO_- HV Arq Paisagistica Pavto Tipo // PN_RE02_ARQ_ANTEPROJETO_- HV Arq Paisagistica Pavto Tipo Primo 20mar24 // PN_RE02_ARQ_ANTEPROJETO_- HV Arq Paisagistica Atico 20mar24 // 20230516_PN_REV07_ARQ_P LEGAL_terreo Arq Paisag 7jun23
B10: Pavimento | C10: Ambiente | D10: Área | E10: Descrição | F10: Quantidade (un) | G10: Preço Unitário | H10: Preço Total
B11: TÉRREO | C11: HALL | D11: =33.34+30.8 -> 64.14 | E11: Iluminação | F11: 1 | G11: 2000 | H11: =F11*G11 -> 2000
E12: Quadros | F12: 2 | G12: 1500 | H12: =F12*G12 -> 3000
C13: TOTAL HALL | F13: =SUM(F12:F12) -> 2 | H13: =SUM(H11:H12) -> 5000
C14: ACABAMENTOS TÉRREO | F14: =D11 -> 64.14 | G14: 120 | H14: =G14*F14 -> 7696.8
B15: ÁTICO | C15: CIRCULAÇÃO | D15: 23.06 | E15: Quadros | F15: 6 | G15: 200 | H15: =F15*G15 -> 1200
E16: Iluminação | F16: 1 | G16: 500 | H16: =F16*G16 -> 500
C17: TOTAL CIRCULAÇÃO | F17: =SUM(F15:F16) -> 7 | H17: =SUM(H15:H16) -> 1700
C18: LAVABOS | D18: =2.24+2.02 -> 4.26 | E18: Marcenaria - armário | F18: 2 | G18: 500 | H18: =F18*G18 -> 1000
E19: Iluminação | F19: 2 | G19: 250 | H19: =F19*G19 -> 500
C20: TOTAL LAVABOS | F20: =SUM(F15:F18) -> 16 | H20: =SUM(H18:H19) -> 1500
C21: ESPAÇO GOURMET | D21: 60.88 | E21: Mesas redondas 4 cadeiras | F21: 2 | G21: 1500 | H21: =F21*G21 -> 3000
E22: Cadeira mesa redonda | F22: =4*F21 -> 8 | G22: 500 | H22: =F22*G22 -> 4000
E23: Poltrona de tecido copacabana | F23: 2 | G23: 1780 | H23: =F23*G23 -> 3560
E24: Sofá lounge redondo | F24: 1 | G24: 6500 | H24: =F24*G24 -> 6500
E25: Pufe redondo estofado cinza | F25: 2 | G25: 325 | H25: =F25*G25 -> 650
E26: Tapete redondo corda nautica | F26: 1 | G26: 850 | H26: =F26*G26 -> 850
E27: Luminárias pendentes em fio | F27: 2 | G27: 450 | H27: =F27*G27 -> 900
E28: Televisão 50" Samsung | F28: 1 | G28: 2500 | H28: =F28*G28 -> 2500
E29: Aparador | F29: 1 | G29: 1200 | H29: =F29*G29 -> 1200
E30: Mesa de madeira rustica | F30: 1 | G30: 2500 | H30: =F30*G30 -> 2500
E31: Cadeiras marcenaria | F31: 6 | G31: 550 | H31: =F31*G31 -> 3300
E32: Geladeira Brastemp Frost Free Duplex 375 litros cor Inox com Espaço Adapt - BRM45JK • 110V | F32: 1 | G32: 3650 | H32: =F32*G32 -> 3650
E33: Cooktop indução | F33: 1 | G33: 3600 | H33: =F33*G33 -> 3600
E34: Coifa inox | F34: 1 | G34: 1200 | H34: =F34*G34 -> 1200
... E39: Marcenaria | F39: 1 | G39: 30000 | H39: =F39*G39 -> 30000
C40: TOTAL ESPAÇO GOURMET | F40: =SUM(F21:F39) -> 37 | H40: =SUM(H21:H39) -> 77586.53
C41: OUTDOOR BAR | D41: 30.66 | E41: Cadeiras de fio metálicas | F41: 4 | G41: 500 | H41: =F41*G41 -> 2000
E42: Banco de fio metálico | F42: 2 | G42: 2980 | H42: =F42*G42 -> 5960
E43: Mesa de centro retangular de madeira | F43: 2 | G43: 690 | H43: =F43*G43 -> 1380
E44: Balanço suspenso rendondo lua | F44: 1 | G44: 6800 | H44: =F44*G44 -> 6800
E45: Banqueta alta | F45: 5 | G45: 750 | H45: =F45*G45 -> 3750
E46: Almofadas e enchiementos banco | F46: 1 | G46: 700 | H46: =F46*G46 -> 700
E47: Marcenaria/marmoaria | F47: 1 | G47: 12000 | H47: =F47*G47 -> 12000
E48: Luminárias pendentes em fio | F48: 2 | G48: 450 | H48: =F48*G48 -> 900
C49: TOTAL OUTDOOR BAR | F49: =SUM(F41:F48) -> 18 | H49: =SUM(H41:H48) -> 33490
C50: FITNESS | D50: =36.77+19.116 -> 55.886 | E50: Esteiras | F50: 2 | G50: 9000 | H50: =F50*G50 -> 18000
E51: Bicicleta ergométrica | F51: 2 | G51: 3245 | H51: =F51*G51 -> 6490
E52: Bola de pilatees | F52: 2 | G52: 78.9 | H52: =F52*G52 -> 157.8
E53: Espelho | F53: 1 | G53: 3500 | H53: =F53*G53 -> 3500
E54: Marcenaria | F54: 1 | G54: 2000 | H54: =F54*G54 -> 2000
E55: SUPORTE TORRE EXPOSITOR PARA 20 HALTERES DE 01KG A 10KG | F55: 1 | G55: 298.94 | H55: =F55*G55 -> 298.94
E56: Suporte Bola Suiça Pilates Para Parede - Branco OnlyforShop | F56: 2 | G56: 20.9 | H56: =F56*G56 -> 41.8
E57: Kit Halteres Ajustáveis Com Rosca 20kg - Top! | F57: 10 | G57: 319 | H57: =F57*G57 -> 3190
E58: Kit Banco Supino Reto Inclinado + 2x Barras 40cm + Barra 1,50m + 80kg anilhas em PVC | F58: 2 | G58: 3250 | H58: =F58*G58 -> 6500
E59: Kit Fitness 20kg + 2 Barras 40cm Rosca + 1 Barra 120cm Presilhas | F59: 1 | G59: 339.8 | H59: =F59*G59 -> 339.8
E60: ESTAÇÃO DE MUSCULAÇÃO ATHLETIC POWER PLUS | F60: 1 | G60: 7440 | H60: =F60*G60 -> 7440
E61: Trilho luminária de teto | F61: 2 | G61: 140 | H61: =F61*G61 -> 280
E62: Televisão 50" Samsung | F62: 1 | G62: 2500 | H62: =F62*G62 -> 2500
... E65: Jump profissional | F65: 1 | G65: 200 | H65: =F65*G65 -> 200
C66: TOTAL FITNESS | F66: =SUM(F50:F63) -> 33 | H66: =SUM(H50:H63) -> 51988.34
C67: OUTDOOR LOUNGE | D67: 20.19 | E67: Cadeiras de fio metálicas | F67: 8 | G67: 1500 | H67: =F67*G67 -> 12000
E68: Mesa de vidro redonda | F68: 2 | G68: 950 | H68: =F68*G68 -> 1900
E69: Poltronas de fio metálicas | F69: 4 | G69: 500 | H69: =F69*G69 -> 2000
E70: Banco de fio metálico | F70: 2 | G70: 2980 | H70: =F70*G70 -> 5960
E71: Luminárias pendentes em fio | F71: 1 | G71: 450 | H71: =F71*G71 -> 450
E72: Mesa de centro de madeira | F72: 4 | G72: 500 | H72: =F72*G72 -> 2000
E73: Vasos decorativos | F73: 2 | G73: 200 | H73: =F73*G73 -> 400
C74: TOTAL OUTDOOR LOUNGE | F74: =SUM(F67:F73) -> 23 | H74: =SUM(H67:H73) -> 24710
C75: CONFRARIA | D75: 27.2 | E75: Poltronas de tecido azul | F75: 2 | G75: 2100 | H75: =F75*G75 -> 4200
E76: Mesa de centro circular preto em metal | F76: 3 | G76: 345 | H76: =F76*G76 -> 1035
E77: Banqueta alta | F77: 4 | G77: 750 | H77: =F77*G77 -> 3000
E78: Mesa redonda | F78: 1 | G78: 2100 | H78: =F78*G78 -> 2100
E79: Cadeiras | F79: 6 | G79: 180 | H79: =F79*G79 -> 1080
E80: Televisão 50" Samsung | F80: 1 | G80: 2500 | H80: =F80*G80 -> 2500
E81: Vasos decorativos | F81: 2 | G81: 200 | H81: =F81*G81 -> 400
E82: Luminárias pendentes em fio | F82: 1 | G82: 450 | H82: =F82*G82 -> 450
E83: Tapete de fio verde | F83: 1 | G83: 1800 | H83: =F83*G83 -> 1800
E84: Marcenaria | F84: 1 | G84: 50000 | H84: =F84*G84 -> 50000
E85: Geladeira Brastemp Frost Free Duplex 375 litros cor Inox com Espaço Adapt - BRM45JK • 110V | F85: 1 | G85: 3650 | H85: =F85*G85 -> 3650
E86: Cooktop indução | F86: 1 | G86: 3600 | H86: =F86*G86 -> 3600
E87: Coifa inox | F87: 1 | G87: 1200 | H87: =F87*G87 -> 1200
... E92: Estojo e Faqueiro C/ 101 Pçs Lace Inox St James | F92: 1 | G92: 1672.28 | H92: =F92*G92 -> 1672.28
C93: TOTAL CONFRARIA | F93: =SUM(F75:F92) -> 32 | H93: =SUM(H75:H92) -> 82876.8
C94: GRILL E PIZZA | D94: 19.91 | E94: Luminárias pendentes em fio | F94: 2 | G94: 450 | H94: =F94*G94 -> 900
E95: Mesa alta circular | F95: 1 | G95: 350 | H95: =F95*G95 -> 350
E96: Banqueta alta | F96: 2 | G96: 750 | H96: =F96*G96 -> 1500
E97: Mesa tampo de madeira | F97: 1 | G97: 2000 | H97: =F97*G97 -> 2000
E98: Cadeiras | F98: 2 | G98: 500 | H98: =F98*G98 -> 1000
E99: Banco de madeira sem encosto | F99: 2 | G99: 900 | H99: =F99*G99 -> 1800
E100: Almofadas e enchiementos banco | F100: 1 | G100: 700 | H100: =F100*G100 -> 700
E101: Tapete retangular | F101: 1 | G101: 1800 | H101: =F101*G101 -> 1800
E102: Jogo churrasqueira | F102: 1 | G102: 400 | H102: =F102*G102 -> 400
E103: Marcenaria e pizza | F103: 1 | G103: 2000 | H103: =F103*G103 -> 2000
C104: TOTAL GRILL E PIZZA | F104: =SUM(F94:F103) -> 14 | H104: =SUM(H94:H103) -> 12450
C105: ESTAR | D105: 28.33 | E105: Cadeiras de fio metálicas | F105: 2 | G105: 500 | H105: =F105*G105 -> 1000
E106: Banco de fio metálico | F106: 1 | G106: 2980 | H106: =F106*G106 -> 2980
E107: Mesa de centro retangular de madeira | F107: 1 | G107: 690 | H107: =F107*G107 -> 690
E108: Poltronas de fio metálicas | F108: 4 | G108: 500 | H108: =F108*G108 -> 2000
E109: Rede de dormir | F109: 1 | G109: 1500 | H109: =F109*G109 -> 1500
E110: Espreguiçadeiras azuis | F110: 4 | G110: 2500 | H110: =F110*G110 -> 10000
E111: Sofá estrutura de madeira | F111: 1 | G111: 5000 | H111: =F111*G111 -> 5000
E112: Mesa de lateral madeira | F112: 2 | G112: 800 | H112: =F112*G112 -> 1600
C113: TOTAL ESTAR | F113: =SUM(F105:F109) -> 9 | H113: =SUM(H105:H112) -> 24770
...

Sheet PAISAGISMO
B2: MOBILIÁRIO
B4: Obra | C4: Playa Negra
B5: Empresa | C5: GDI Empreendimentos
B6: Revisão | C6: R00
B7: Data | C7: 45538
B8: Acesso aos projetos | C8: 20231005_PN_REV08_ARQ_PROJETO LEGAL // PN_RE02_ARQ_ANTEPROJETO_- HV Arq Paisagistica Pavto Tipo // PN_RE02_ARQ_ANTEPROJETO_- HV Arq Paisagistica Pavto Tipo Primo 20mar24 // PN_RE02_ARQ_ANTEPROJETO_- HV Arq Paisagistica Atico 20mar24 // 20230516_PN_REV07_ARQ_P LEGAL_terreo Arq Paisag 7jun23
B10: Pavimento | C10: Ambiente | D10: Área | E10: Descrição | F10: Quantidade (un) | G10: Preço Unitário | H10: Preço Total
B11: TERREO | C11: PAISAGISMO TÉRREO | D11: 150.97 | E11: Grama amendoin | F11: 1500 | G11: =1.12 -> 1.12 | H11: =F11*G11 -> 1680
E12: Grama batatais | F12: 15 | G12: =45*2.5 -> 112.5 | H12: =F12*G12 -> 1687.5
E13: Lírio-do-zéfiro | F13: 1000 | G13: 3 | H13: =F13*G13 -> 3000
E14: Filodendro | F14: 15 | G14: 15 | H14: =F14*G14 -> 225
E15: Maranta charuto | F15: 2 | G15: 50 | H15: =F15*G15 -> 100
E16: Aroeira salsa | F16: 2 | G16: 60 | H16: =F16*G16 -> 120
E17: Palmito 3m | F17: 3 | G17: 490 | H17: =F17*G17 -> 1470
E18: Palmito 4m | F18: 4 | G18: 500 | H18: =F18*G18 -> 2000
E19: Pau-ferro | F19: 2 | G19: 300 | H19: =F19*G19 -> 600
E20: Babosa de pau | F20: 10 | G20: 20 | H20: =F20*G20 -> 200
E21: Suinã | F21: 1 | G21: 220 | H21: =F21*G21 -> 220
E22: Banana de macaco | F22: 61 | G22: 50 | H22: =F22*G22 -> 3050
E23: Jasmin amarelo | F23: 6 | G23: 8 | H23: =F23*G23 -> 48
C24: TOTAL PAISAGISMO TÉRREO | F24: =SUM(F11:F23) -> 2621 | H24: =SUM(H11:H23) -> 14400.5
B25: 2º PAV | C25: PAISAGISMO 2º PAV | D25: 6.32 | E25: Liriope | F25: 1.24 | G25: =45*2.5 -> 112.5 | H25: =F25*G25 -> 139.5
E26: Boldo rasteiro | F26: 0.23 | G26: =45*3 -> 135 | H26: =F26*G26 -> 31.05
E27: Linho-da-nova-zelandia | F27: 3 | G27: 50 | H27: =F27*G27 -> 150
E28: Zâmia | F28: 3 | G28: 50 | H28: =F28*G28 -> 150
E29: Bela emilia | F29: 13 | G29: 15 | H29: =F29*G29 -> 195
E30: Jasmim amarelo | F30: 4 | G30: 8 | H30: =F30*G30 -> 32
E31: Jibóia | F31: 2 | G31: 200 | H31: =F31*G31 -> 400
E32: Jabuticabeira | F32: 1 | G32: 50 | H32: =F32*G32 -> 50
E33: Babosa de pau | F33: 1 | G33: 20 | H33: =F33*G33 -> 20
E34: Pleomele verde | F34: 2 | G34: 130 | H34: =F34*G34 -> 260
E35: Heliconia-papagaio 30 cm | F35: 3 | G35: 20 | H35: =F35*G35 -> 60
E36: Banana de macaco 60 cm | F36: 6 | G36: 60 | H36: =F36*G36 -> 360
E37: Luca elefante | F37: 1 | G37: =0.8*600 -> 480 | H37: =F37*G37 -> 480
E38: Agave dragão | F38: 1 | G38: 30 | H38: =F38*G38 -> 30
C39: TOTAL PAISAGISMO 2º PAV | F39: =SUM(F25:F38) -> 41.47 | H39: =SUM(H25:H38) -> 2357.55
B40: 3º AO 8º PAV | C40: PAISAGISMO TIPO | D40: =6.32*6 -> 37.92 | E40: Liriope | F40: =5*0.73 -> 3.65 | G40: =45*2.5 -> 112.5 | H40: =F40*G40 -> 410.625
E41: Boldo rasteiro | F41: =5*0.23 -> 1.15 | G41: =45*3 -> 135 | H41: =F41*G41 -> 155.25
E42: Linho-da-nova-zelandia | F42: =5*3 -> 15 | G42: 50 | H42: =F42*G42 -> 750
E43: Espada de são jorge | F43: =5*3 -> 15 | G43: 15 | H43: =F43*G43 -> 225
E44: Zâmia | F44: =5*3 -> 15 | G44: 50 | H44: =F44*G44 -> 750
E45: Areca-bambu | F45: =5*1 -> 5 | G45: 60 | H45: =F45*G45 -> 300
E46: Bela emilia | F46: =5*8 -> 40 | G46: 15 | H46: =F46*G46 -> 600
E47: Jasmim amarelo | F47: =5*9 -> 45 | G47: 8 | H47: =F47*G47 -> 360
E48: Jibóia | F48: =5*2 -> 10 | G48: 200 | H48: =F48*G48 -> 2000
E49: Flor de coral | F49: =5*3 -> 15 | G49: 15 | H49: =F49*G49 -> 225
E50: Tamandeira anã | F50: =5*2 -> 10 | G50: 220 | H50: =F50*G50 -> 2200
E51: Babosa de pau | F51: =5*1 -> 5 | G51: 20 | H51: =F51*G51 -> 100
E52: Banana de macaco 60 cm | F52: =5*6 -> 30 | G52: 60 | H52: =F52*G52 -> 1800
C53: TOTAL PAISAGISMO TIPO | F53: =SUM(F40:F52) -> 209.8 | H53: =SUM(H40:H52) -> 9875.875
B54: ÁTICO | C54: PAISAGISMO ÁTICO | D54: 49.26 | E54: Grama amendoin | F54: 3.63 | G54: =90*1.12 -> 100.8 | H54: =F54*G54 -> 365.904
E55: Liriope | F55: 1.53 | G55: =45*2.5 -> 112.5 | H55: =F55*G55 -> 172.125
E56: Boldo rasteiro | F56: 3.23 | G56: =45*3 -> 135 | H56: =F56*G56 -> 436.05
E57: Linho-da-nova-zelandia | F57: 30 | G57: 50 | H57: =F57*G57 -> 1500
E58: Espada de são jorge | F58: 35 | G58: 15 | H58: =F58*G58 -> 525
E59: Heliconia-papagaio 30 cm | F59: 2 | G59: 20 | H59: =F59*G59 -> 40
E60: Ciúsia | F60: 14 | G60: 20 | H60: =F60*G60 -> 280
E61: Maranta charuto | F61: 6 | G61: 50 | H61: =F61*G61 -> 300
E62: Bela emilia | F62: 22 | G62: 15 | H62: =F62*G62 -> 330
E63: Pitósporo | F63: 23 | G63: 30 | H63: =F63*G63 -> 690
E64: Aroeira salsa | F64: 6 | G64: 60 | H64: =F64*G64 -> 360
E65: Banana de macaco | F65: 7 | G65: 50 | H65: =F65*G65 -> 350
E66: Jasmin amarelo | F66: 37 | G66: 8 | H66: =F66*G66 -> 296
E67: Flor de coral | F67: 36 | G67: 15 | H67: =F67*G67 -> 540
E68: Filodendro | F68: 24 | G68: 15 | H68: =F68*G68 -> 360
E69: Palmeira triangular | F69: 10 | G69: 110 | H69: =F69*G69 -> 1100
E70: Heliconia-papagaio 30 cm | F70: 25 | G70: =G59 -> 20 | H70: =F70*G70 -> 500
E71: Banana de macaco 60 cm | F71: 17 | G71: 60 | H71: =F71*G71 -> 1020
E72: Jasmins manga | F72: 6 | G72: 130 | H72: =F72*G72 -> 780
E73: Capentária | F73: 3 | G73: 250 | H73: =F73*G73 -> 750
E74: Agave dragão | F74: 5 | G74: 30 | H74: =F74*G74 -> 150
C75: TOTAL PAISAGISMO ÁTICO | F75: =SUM(F54:F74) -> 316.39 | H75: =SUM(H54:H74) -> 10845.079
E76: INSUMOS COMPLEMENTAES | F76: =D54+D40+D25+D11 -> 244.47 | G76: 90 | H76: =G76*F76 -> 22002.3
C77: TOTAL PAISAGISMO | H77: =H75+H53+H39+H24+H76 -> 59481.304
C78: TOTAL COM 25% | H78: =(H77*1.1457045) -> 68147.998

Sheet Piso Arm.Térreo
B1: Obra | C1: Lausanne
B2: Empresa | C2: Santo André
B3: Revisão | C3: R00
A4: ESTRUTURA - PISO ARMADO
A5: PROJETO | B5: PEÇA | C5: DIMENSÕES UNITÁRIAS | G5: FORMA | I5: LONA m² | J5: LASTRO DE BRITA m³ | K5: CONCRETO m³ | N5: LAJE / MOLDE | Q5: IMAGENS LEVANTAMENTO | S5: RESUMO - CONCRETO
C6: ÁREA | D6: PERÍMETRO | E6: ALT | F6: QUANT | G6: UNIT | H6: TOTAL | K6: UNIT | L6: TOTAL | M6: RESISTÊNCIA | N6: TIPO | O6: UNIT | P6: TOTAL | S6: m3 | T6: TIPO
A7: PROJETO: | S7: =SUMIF($M$7:$M$16,T7,$L$7:$L$16) -> 0 | T7: 25 MPa
B8: Piso térreo | F8: 1 | G8: =IF(C8="","",IF(F8<0,(D8*(E8+0.02)),(D8*(E8+0.02)))) | H8: =IF(C8="","",IF(F8>0,F8*G8,F8*-G8)) | I8: =IF(C8="","",C8*F8) | J8: =IF(C8="","",C8*F8*0.05) | K8: =IF(C8="","",IF(F8<0,-C8*E8,C8*E8)) | L8: =IF(C8="","",IF(F8>0,K8*F8,-K8*F8)) | N8: MOLDADA IN LOCO | O8: =IF(C8="","",IF(F8<0,-C8,C8)) | P8: =IF(C8="","",C8*F8) | S8: =SUMIF($M$7:$M$16,T8,$L$7:$L$16) -> 0 | T8: 30 MPa
B9: Descontos | F9: -1 | G9: =IF(C9="","",IF(F9<0,(D9*(E9+0.02)),(D9*(E9+0.02)))) | H9: =IF(C9="","",IF(F9>0,F9*G9,F9*-G9)) | I9: =IF(C9="","",C9*F9) | J9: =IF(C9="","",C9*F9*0.05) | K9: =IF(C9="","",IF(F9<0,-C9*E9,C9*E9)) | L9: =IF(C9="","",IF(F9>0,K9*F9,-K9*F9)) | N9: MOLDADA IN LOCO | O9: =IF(C9="","",IF(F9<0,-C9,C9)) | P9: =IF(C9="","",C9*F9) | S9: =SUMIF($M$7:$M$16,T9,$L$7:$L$16) -> 0 | T9: 35 MPa
G10: =IF(C10="","",IF(F10<0,(D10*(E10+0.02)),(D10*(E10+0.02)))) | H10: =IF(C10="","",IF(F10>0,F10*G10,F10*-G10)) | I10: =IF(C10="","",C10*F10) | J10: =IF(C10="","",C10*F10*0.05) | K10: =IF(C10="","",IF(F10<0,-C10*E10,C10*E10)) | L10: =IF(C10="","",IF(F10>0,K10*F10,-K10*F10)) | O10: =IF(C10="","",IF(F10<0,-C10,C10)) | P10: =IF(C10="","",C10*F10) | S10: =SUMIF($M$7:$M$16,T10,$L$7:$L$16) -> 0 | T10: 40 MPa
G11: =IF(C11="","",IF(F11<0,(D11*(E11+0.02)),(D11*(E11+0.02)))) | H11: =IF(C11="","",IF(F11>0,F11*G11,F11*-G11)) | I11: =IF(C11="","",C11*F11) | J11: =IF(C11="","",C11*F11*0.05) | K11: =IF(C11="","",IF(F11<0,-C11*E11,C11*E11)) | L11: =IF(C11="","",IF(F11>0,K11*F11,-K11*F11)) | O11: =IF(C11="","",IF(F11<0,-C11,C11)) | P11: =IF(C11="","",C11*F11) | S11: =SUMIF($M$7:$M$16,T11,$L$7:$L$16) -> 0
B12: TOTAL GERAL | C12: =SUMPRODUCT(C7:C11,F7:F11) -> 0 | G12: =SUM(G7:G11) -> 0 | H12: =SUM(H7:H11) -> 0 | I12: =SUM(I7:I11) -> 0 | J12: =SUM(J7:J11) -> 0 | K12: =SUM(K7:K11) -> 0 | L12: =SUM(L7:L11) -> 0 | O12: =SUM(O7:O11) -> 0 | P12: =SUM(P7:P11) -> 0 | S12: =SUMIF($M$7:$M$16,T12,$L$7:$L$16) -> 0
S13: =SUM(S7:S12) -> 0 | T13: =IF(L12=S13,"OK","Conferir") -> OK

Sheet Pilares
A2: EMPREENDIMENTO: | H2: REVISÃO: | K2: DATA:
A3: =Ger_Executivo!B5 -> EMPRESA: | H3: R00 -
A5: PEÇA | B5: DIMENSÕES UNITÁRIAS - METROS | E5: QUANT | F5: FORMA | I5: CONCRETO | M5: RESUMO - CONCRETO
B6: SEÇÃO 1 | C6: SEÇÃO 2 | D6: ALTURA | F6: LADOS | G6: UNIT | H6: TOTAL | I6: UNIT | J6: TOTAL | K6: RESISTÊNCIA | M6: QUANT. m3 | N6: RESISTÊNCIA
A7: PROJETO: | M7: =IF(N7="","",SUMIF($K$7:$K$60,N7,$J$7:$J$60)) -> 0 | N7: 20MPa
F8: 4 | G8: =IF(F8=2,C8*2*D8,IF(F8=4,(B8+C8)*2*D8,0)) -> 0 | H8: =G8*E8 -> 0 | I8: =B8*D8*C8 -> 0 | J8: =I8*E8 -> 0 | K8: 40MPa | M8: =IF(N8="","",SUMIF($K$7:$K$60,N8,$J$7:$J$60)) -> 0 | N8: 25MPa
F9: 4 | G9: =IF(F9=2,C9*2*D9,IF(F9=4,(B9+C9)*2*D9,0)) -> 0 | H9: =G9*E9 -> 0 | I9: =B9*D9*C9 -> 0 | J9: =I9*E9 -> 0 | K9: 40MPa | M9: =IF(N9="","",SUMIF($K$7:$K$60,N9,$J$7:$J$60)) -> 0 | N9: 30MPa
F10: 4 | G10: =IF(F10=2,C10*2*D10,IF(F10=4,(B10+C10)*2*D10,0)) -> 0 | H10: =G10*E10 -> 0 | I10: =B10*D10*C10 -> 0 | J10: =I10*E10 -> 0 | K10: 40MPa | M10: =IF(N10="","",SUMIF($K$7:$K$60,N10,$J$7:$J$60)) -> 0 | N10: 35MPa
F11: 4 | G11: =IF(F11=2,C11*2*D11,IF(F11=4,(B11+C11)*2*D11,0)) -> 0 | H11: =G11*E11 -> 0 | I11: =B11*D11*C11 -> 0 | J11: =I11*E11 -> 0 | K11: 40MPa | M11: =IF(N11="","",SUMIF($K$7:$K$60,N11,$J$7:$J$60)) -> 0 | N11: 40MPa
F12: 4 | G12: =IF(F12=2,C12*2*D12,IF(F12=4,(B12+C12)*2*D12,0)) -> 0 | H12: =G12*E12 -> 0 | I12: =B12*D12*C12 -> 0 | J12: =I12*E12 -> 0 | K12: 40MPa | M12: =IF(N12="","",SUMIF($K$7:$K$60,N12,$J$7:$J$60))
F13: 4 | G13: =IF(F13=2,C13*2*D13,IF(F13=4,(B13+C13)*2*D13,0)) -> 0 | H13: =G13*E13 -> 0 | I13: =B13*D13*C13 -> 0 | J13: =I13*E13 -> 0 | K13: 40MPa | M13: =IF(N13="","",SUMIF($K$7:$K$60,N13,$J$7:$J$60))
F14: 4 | G14: =IF(F14=2,C14*2*D14,IF(F14=4,(B14+C14)*2*D14,0)) -> 0 | H14: =G14*E14 -> 0 | I14: =B14*D14*C14 -> 0 | J14: =I14*E14 -> 0 | K14: 40MPa | M14: =IF(N14="","",SUMIF($K$7:$K$60,N14,$J$7:$J$60))
F15: 4 | G15: =IF(F15=2,C15*2*D15,IF(F15=4,(B15+C15)*2*D15,0)) -> 0 | H15: =G15*E15 -> 0 | I15: =B15*D15*C15 -> 0 | J15: =I15*E15 -> 0 | K15: 40MPa | M15: =SUM(M7:M14) -> 0 | N15: =IF(J60=M15,"OK","Conferir") -> OK
F16: 4 | G16: =IF(F16=2,C16*2*D16,IF(F16=4,(B16+C16)*2*D16,0)) -> 0 | H16: =G16*E16 -> 0 | I16: =B16*D16*C16 -> 0 | J16: =I16*E16 -> 0 | K16: 40MPa
F17: 4 | G17: =IF(F17=2,C17*2*D17,IF(F17=4,(B17+C17)*2*D17,0)) -> 0 | H17: =G17*E17 -> 0 | I17: =B17*D17*C17 -> 0 | J17: =I17*E17 -> 0 | K17: 40MPa
A18: PROJETO:
F19: 4 | G19: =IF(F19=2,C19*2*D19,IF(F19=4,(B19+C19)*2*D19,0)) -> 0 | H19: =G19*E19 -> 0 | I19: =B19*D19*C19 -> 0 | J19: =I19*E19 -> 0 | K19: 40MPa
F20: 4 | G20: =IF(F20=2,C20*2*D20,IF(F20=4,(B20+C20)*2*D20,0)) -> 0 | H20: =G20*E20 -> 0 | I20: =B20*D20*C20 -> 0 | J20: =I20*E20 -> 0 | K20: 40MPa
F21: 4 | G21: =IF(F21=2,C21*2*D21,IF(F21=4,(B21+C21)*2*D21,0)) -> 0 | H21: =G21*E21 -> 0 | I21: =B21*D21*C21 -> 0 | J21: =I21*E21 -> 0 | K21: 40MPa
F22: 4 | G22: =IF(F22=2,C22*2*D22,IF(F22=4,(B22+C22)*2*D22,0)) -> 0 | H22: =G22*E22 -> 0 | I22: =B22*D22*C22 -> 0 | J22: =I22*E22 -> 0 | K22: 40MPa
F23: 4 | G23: =IF(F23=2,C23*2*D23,IF(F23=4,(B23+C23)*2*D23,0)) -> 0 | H23: =G23*E23 -> 0 | I23: =B23*D23*C23 -> 0 | J23: =I23*E23 -> 0 | K23: 40MPa
F24: 4 | G24: =IF(F24=2,C24*2*D24,IF(F24=4,(B24+C24)*2*D24,0)) -> 0 | H24: =G24*E24 -> 0 | I24: =B24*D24*C24 -> 0 | J24: =I24*E24 -> 0 | K24: 40MPa
F25: 4 | G25: =IF(F25=2,C25*2*D25,IF(F25=4,(B25+C25)*2*D25,0)) -> 0 | H25: =G25*E25 -> 0 | I25: =B25*D25*C25 -> 0 | J25: =I25*E25 -> 0 | K25: 40MPa
F26: 4 | G26: =IF(F26=2,C26*2*D26,IF(F26=4,(B26+C26)*2*D26,0)) -> 0 | H26: =G26*E26 -> 0 | I26: =B26*D26*C26 -> 0 | J26: =I26*E26 -> 0 | K26: 40MPa
F27: 4 | G27: =IF(F27=2,C27*2*D27,IF(F27=4,(B27+C27)*2*D27,0)) -> 0 | H27: =G27*E27 -> 0 | I27: =B27*D27*C27 -> 0 | J27: =I27*E27 -> 0 | K27: 40MPa
F28: 4 | G28: =IF(F28=2,C28*2*D28,IF(F28=4,(B28+C28)*2*D28,0)) -> 0 | H28: =G28*E28 -> 0 | I28: =B28*D28*C28 -> 0 | J28: =I28*E28 -> 0 | K28: 40MPa
A29: PROJETO:
F30: 4 | G30: =IF(F30=2,C30*2*D30,IF(F30=4,(B30+C30)*2*D30,0)) -> 0 | H30: =G30*E30 -> 0 | I30: =B30*D30*C30 -> 0 | J30: =I30*E30 -> 0 | K30: 40MPa
F31: 4 | G31: =IF(F31=2,C31*2*D31,IF(F31=4,(B31+C31)*2*D31,0)) -> 0 | H31: =G31*E31 -> 0 | I31: =B31*D31*C31 -> 0 | J31: =I31*E31 -> 0 | K31: 40MPa
F32: 4 | G32: =IF(F32=2,C32*2*D32,IF(F32=4,(B32+C32)*2*D32,0)) -> 0 | H32: =G32*E32 -> 0 | I32: =B32*D32*C32 -> 0 | J32: =I32*E32 -> 0 | K32: 40MPa
F33: 4 | G33: =IF(F33=2,C33*2*D33,IF(F33=4,(B33+C33)*2*D33,0)) -> 0 | H33: =G33*E33 -> 0 | I33: =B33*D33*C33 -> 0 | J33: =I33*E33 -> 0 | K33: 40MPa
F34: 4 | G34: =IF(F34=2,C34*2*D34,IF(F34=4,(B34+C34)*2*D34,0)) -> 0 | H34: =G34*E34 -> 0 | I34: =B34*D34*C34 -> 0 | J34: =I34*E34 -> 0 | K34: 40MPa
F35: 4 | G35: =IF(F35=2,C35*2*D35,IF(F35=4,(B35+C35)*2*D35,0)) -> 0 | H35: =G35*E35 -> 0 | I35: =B35*D35*C35 -> 0 | J35: =I35*E35 -> 0 | K35: 40MPa
F36: 4 | G36: =IF(F36=2,C36*2*D36,IF(F36=4,(B36+C36)*2*D36,0)) -> 0 | H36: =G36*E36 -> 0 | I36: =B36*D36*C36 -> 0 | J36: =I36*E36 -> 0 | K36: 40MPa
F37: 4 | G37: =IF(F37=2,C37*2*D37,IF(F37=4,(B37+C37)*2*D37,0)) -> 0 | H37: =G37*E37 -> 0 | I37: =B37*D37*C37 -> 0 | J37: =I37*E37 -> 0 | K37: 40MPa
F38: 4 | G38: =IF(F38=2,C38*2*D38,IF(F38=4,(B38+C38)*2*D38,0)) -> 0 | H38: =G38*E38 -> 0 | I38: =B38*D38*C38 -> 0 | J38: =I38*E38 -> 0 | K38: 40MPa
F39: 4 | G39: =IF(F39=2,C39*2*D39,IF(F39=4,(B39+C39)*2*D39,0)) -> 0 | H39: =G39*E39 -> 0 | I39: =B39*D39*C39 -> 0 | J39: =I39*E39 -> 0 | K39: 40MPa
F40: 4 | G40: =IF(F40=2,C40*2*D40,IF(F40=4,(B40+C40)*2*D40,0)) -> 0 | H40: =G40*E40 -> 0 | I40: =B40*D40*C40 -> 0 | J40: =I40*E40 -> 0 | K40: 40MPa
F41: 4 | G41: =IF(F41=2,C41*2*D41,IF(F41=4,(B41+C41)*2*D41,0)) -> 0 | H41: =G41*E41 -> 0 | I41: =B41*D41*C41 -> 0 | J41: =I41*E41 -> 0 | K41: 40MPa
... F43: 4 | G43: =IF(F43=2,C43*2*D43,IF(F43=4,(B43+C43)*2*D43,0)) -> 0 | H43: =G43*E43 -> 0 | I43: =B43*D43*C43 -> 0 | J43: =I43*E43 -> 0 | K43: 40MPa
A44: PROJETO:
F45: 4 | G45: =IF(F45=2,C45*2*D45,IF(F45=4,(B45+C45)*2*D45,0)) -> 0 | H45: =G45*E45 -> 0 | I45: =B45*D45*C45 -> 0 | J45: =I45*E45 -> 0 | K45: 40MPa
F46: 4 | G46: =IF(F46=2,C46*2*D46,IF(F46=4,(B46+C46)*2*D46,0)) -> 0 | H46: =G46*E46 -> 0 | I46: =B46*D46*C46 -> 0 | J46: =I46*E46 -> 0 | K46: 40MPa
F47: 4 | G47: =IF(F47=2,C47*2*D47,IF(F47=4,(B47+C47)*2*D47,0)) -> 0 | H47: =G47*E47 -> 0 | I47: =B47*D47*C47 -> 0 | J47: =I47*E47 -> 0 | K47: 40MPa
F48: 4 | G48: =IF(F48=2,C48*2*D48,IF(F48=4,(B48+C48)*2*D48,0)) -> 0 | H48: =G48*E48 -> 0 | I48: =B48*D48*C48 -> 0 | J48: =I48*E48 -> 0 | K48: 40MPa
F49: 4 | G49: =IF(F49=2,C49*2*D49,IF(F49=4,(B49+C49)*2*D49,0)) -> 0 | H49: =G49*E49 -> 0 | I49: =B49*D49*C49 -> 0 | J49: =I49*E49 -> 0 | K49: 40MPa
F50: 4 | G50: =IF(F50=2,C50*2*D50,IF(F50=4,(B50+C50)*2*D50,0)) -> 0 | H50: =G50*E50 -> 0 | I50: =B50*D50*C50 -> 0 | J50: =I50*E50 -> 0 | K50: 40MPa
F51: 4 | G51: =IF(F51=2,C51*2*D51,IF(F51=4,(B51+C51)*2*D51,0)) -> 0 | H51: =G51*E51 -> 0 | I51: =B51*D51*C51 -> 0 | J51: =I51*E51 -> 0 | K51: 40MPa
F52: 4 | G52: =IF(F52=2,C52*2*D52,IF(F52=4,(B52+C52)*2*D52,0)) -> 0 | H52: =G52*E52 -> 0 | I52: =B52*D52*C52 -> 0 | J52: =I52*E52 -> 0 | K52: 40MPa
F53: 4 | G53: =IF(F53=2,C53*2*D53,IF(F53=4,(B53+C53)*2*D53,0)) -> 0 | H53: =G53*E53 -> 0 | I53: =B53*D53*C53 -> 0 | J53: =I53*E53 -> 0 | K53: 40MPa
F54: 4 | G54: =IF(F54=2,C54*2*D54,IF(F54=4,(B54+C54)*2*D54,0)) -> 0 | H54: =G54*E54 -> 0 | I54: =B54*D54*C54 -> 0 | J54: =I54*E54 -> 0 | K54: 40MPa
F55: 4 | G55: =IF(F55=2,C55*2*D55,IF(F55=4,(B55+C55)*2*D55,0)) -> 0 | H55: =G55*E55 -> 0 | I55: =B55*D55*C55 -> 0 | J55: =I55*E55 -> 0 | K55: 40MPa
F56: 4 | G56: =IF(F56=2,C56*2*D56,IF(F56=4,(B56+C56)*2*D56,0)) -> 0 | H56: =G56*E56 -> 0 | I56: =B56*D56*C56 -> 0 | J56: =I56*E56 -> 0 | K56: 40MPa
A57: PROJETO:
F58: 4 | G58: =IF(F58=2,C58*2*D58,IF(F58=4,(B58+C58)*2*D58,0)) -> 0 | H58: =G58*E58 -> 0 | I58: =B58*D58*C58 -> 0 | J58: =I58*E58 -> 0 | K58: 40MPa
F59: 4 | G59: =IF(F59=2,C59*2*D59,IF(F59=4,(B59+C59)*2*D59,0)) -> 0 | H59: =G59*E59 -> 0 | I59: =B59*D59*C59 -> 0 | J59: =I59*E59 -> 0 | K59: 40MPa
A60: TOTAL GERAL | H60: =SUM(H7:H59) -> 0 | I60: m² | J60: =SUM(J7:J59) -> 0 | K60: m³
D62: JOGO DE FORMA PARA O RESUMO: | H62: =SUM(H30:H43) -> 0 | I62: m²

Sheet Vigas - T1 
A2: EMPREENDIMENTO: | I2: REVISÃO: | L2: DATA:
A3: =Ger_Executivo!B5 -> EMPRESA: | I3: R00 -
A4: PEÇA | B4: DIMENSÕES UNITÁRIAS | E4: QUANT | F4: FORMA | J4: CONCRETO | N4: RESUMO - CONCRETO
B5: LARG | C5: ALT | D5: COMP | F5: FUNDO S/N | G5: Lados | H5: UNIT | I5: TOTAL | J5: UNIT | K5: TOTAL | L5: RESISTÊNCIA | N5: m3 | O5: RESISTÊNCIA
A6: PROJETO: | N6: =IF(O6="","",SUMIF($L$6:$L$32,O6,$K$6:$K$32)) -> 0 | O6: 20MPa
F7: S | G7: 2 | H7: =IF(F7="s",(B7+(C7*G7))*D7+C7*B7*2,C7*G7*D7+B7*C7*2) -> 0 | I7: =H7*E7 -> 0 | J7: =B7*C7*D7 -> 0 | K7: =J7*E7 -> 0 | L7: 40MPa | N7: =IF(O7="","",SUMIF($L$6:$L$32,O7,$K$6:$K$32)) -> 0 | O7: 25MPa
F8: S | G8: 2 | H8: =IF(F8="s",(B8+(C8*G8))*D8+C8*B8*2,C8*G8*D8+B8*C8*2) -> 0 | I8: =H8*E8 -> 0 | J8: =B8*C8*D8 -> 0 | K8: =J8*E8 -> 0 | L8: 40MPa | N8: =IF(O8="","",SUMIF($L$6:$L$32,O8,$K$6:$K$32)) -> 0 | O8: 30MPa
F9: S | G9: 2 | H9: =IF(F9="s",(B9+(C9*G9))*D9+C9*B9*2,C9*G9*D9+B9*C9*2) -> 0 | I9: =H9*E9 -> 0 | J9: =B9*C9*D9 -> 0 | K9: =J9*E9 -> 0 | L9: 40MPa | N9: =IF(O9="","",SUMIF($L$6:$L$32,O9,$K$6:$K$32)) -> 0 | O9: 35MPa
F10: S | G10: 2 | H10: =IF(F10="s",(B10+(C10*G10))*D10+C10*B10*2,C10*G10*D10+B10*C10*2) -> 0 | I10: =H10*E10 -> 0 | J10: =B10*C10*D10 -> 0 | K10: =J10*E10 -> 0 | L10: 40MPa | N10: =IF(O10="","",SUMIF($L$6:$L$32,O10,$K$6:$K$32)) -> 0 | O10: 40MPa
H11: =IF(F11="s",(B11+(C11*G11))*D11+C11*B11*2,C11*G11*D11+B11*C11*2) -> 0 | I11: =H11*E11 -> 0 | J11: =B11*C11*D11 -> 0 | K11: =J11*E11 -> 0 | L11: 40MPa | N11: =IF(O11="","",SUMIF($L$6:$L$32,O11,$K$6:$K$32))
A12: PROJETO: | N12: =IF(O12="","",SUMIF($L$6:$L$32,O12,$K$6:$K$32))
F13: S | G13: 2 | H13: =IF(F13="s",(B13+(C13*G13))*D13+C13*B13*2,C13*G13*D13+B13*C13*2) -> 0 | I13: =H13*E13 -> 0 | J13: =B13*C13*D13 -> 0 | K13: =J13*E13 -> 0 | L13: 40MPa | N13: =SUM(N6:N12) -> 0 | O13: =IF(K33=N13,"OK","Conferir") -> OK
F14: S | G14: 2 | H14: =IF(F14="s",(B14+(C14*G14))*D14+C14*B14*2,C14*G14*D14+B14*C14*2) -> 0 | I14: =H14*E14 -> 0 | J14: =B14*C14*D14 -> 0 | K14: =J14*E14 -> 0 | L14: 40MPa
F15: S | G15: 2 | H15: =IF(F15="s",(B15+(C15*G15))*D15+C15*B15*2,C15*G15*D15+B15*C15*2) -> 0 | I15: =H15*E15 -> 0 | J15: =B15*C15*D15 -> 0 | K15: =J15*E15 -> 0 | L15: 40MPa
F16: S | G16: 2 | H16: =IF(F16="s",(B16+(C16*G16))*D16+C16*B16*2,C16*G16*D16+B16*C16*2) -> 0 | I16: =H16*E16 -> 0 | J16: =B16*C16*D16 -> 0 | K16: =J16*E16 -> 0 | L16: 40MPa
F17: S | G17: 2 | H17: =IF(F17="s",(B17+(C17*G17))*D17+C17*B17*2,C17*G17*D17+B17*C17*2) -> 0 | I17: =H17*E17 -> 0 | J17: =B17*C17*D17 -> 0 | K17: =J17*E17 -> 0 | L17: 40MPa
A18: PROJETO:
F19: S | G19: 2 | H19: =IF(F19="s",(B19+(C19*G19))*D19+C19*B19*2,C19*G19*D19+B19*C19*2) -> 0 | I19: =H19*E19 -> 0 | J19: =B19*C19*D19 -> 0 | K19: =J19*E19 -> 0 | L19: 25MPa
F20: S | G20: 2 | H20: =IF(F20="s",(B20+(C20*G20))*D20+C20*B20*2,C20*G20*D20+B20*C20*2) -> 0 | I20: =H20*E20 -> 0 | J20: =B20*C20*D20 -> 0 | K20: =J20*E20 -> 0 | L20: 25MPa
F21: S | G21: 2 | H21: =IF(F21="s",(B21+(C21*G21))*D21+C21*B21*2,C21*G21*D21+B21*C21*2) -> 0 | I21: =H21*E21 -> 0 | J21: =B21*C21*D21 -> 0 | K21: =J21*E21 -> 0 | L21: 25MPa
F22: S | G22: 2 | H22: =IF(F22="s",(B22+(C22*G22))*D22+C22*B22*2,C22*G22*D22+B22*C22*2) -> 0 | I22: =H22*E22 -> 0 | J22: =B22*C22*D22 -> 0 | K22: =J22*E22 -> 0 | L22: 25MPa
F23: S | G23: 2 | H23: =IF(F23="s",(B23+(C23*G23))*D23+C23*B23*2,C23*G23*D23+B23*C23*2) -> 0 | I23: =H23*E23 -> 0 | J23: =B23*C23*D23 -> 0 | K23: =J23*E23 -> 0 | L23: 25MPa
F24: S | G24: 2 | H24: =IF(F24="s",(B24+(C24*G24))*D24+C24*B24*2,C24*G24*D24+B24*C24*2) -> 0 | I24: =H24*E24 -> 0 | J24: =B24*C24*D24 -> 0 | K24: =J24*E24 -> 0 | L24: 25MPa
A25: PROJETO:
F26: S | G26: 2 | H26: =IF(F26="s",(B26+(C26*G26))*D26+C26*B26*2,C26*G26*D26+B26*C26*2) -> 0 | I26: =H26*E26 -> 0 | J26: =B26*C26*D26 -> 0 | K26: =J26*E26 -> 0 | L26: 25MPa
A28: PROJETO:
F29: S | G29: 2 | H29: =IF(F29="s",(B29+(C29*G29))*D29+C29*B29*2,C29*G29*D29+B29*C29*2) -> 0 | I29: =H29*E29 -> 0 | J29: =B29*C29*D29 -> 0 | K29: =J29*E29 -> 0 | L29: 40MPa
F30: S | G30: 2 | H30: =IF(F30="s",(B30+(C30*G30))*D30+C30*B30*2,C30*G30*D30+B30*C30*2) -> 0 | I30: =H30*E30 -> 0 | J30: =B30*C30*D30 -> 0 | K30: =J30*E30 -> 0 | L30: 40MPa
F31: S | G31: 2 | H31: =IF(F31="s",(B31+(C31*G31))*D31+C31*B31*2,C31*G31*D31+B31*C31*2) -> 0 | I31: =H31*E31 -> 0 | J31: =B31*C31*D31 -> 0 | K31: =J31*E31 -> 0 | L31: 40MPa
A33: TOTAL | I33: =SUM(I6:I32) -> 0 | K33: =SUM(K6:K32) -> 0
E35: JOGO DE FORMA PARA O RESUMO: | I35: =SUM(I13:I17) -> 0 | J35: m²

Sheet Lajes - T1 
A2: EMPREENDIMENTO: | N2: REVISÃO: | R2: DATA:
A3: =Ger_Executivo!B5 -> EMPRESA: | N3: R00 -
A4: PROJETO | B4: PEÇA | C4: DIMENSÕES UNITÁRIAS | G4: FORMA | J4: CONCRETO | M4: LAJE / MOLDE | P4: ESCORAMENTO | R4: IMAGENS LEVANTAMENTO | T4: RESUMO - CONCRETO
C5: ÁREA m² | D5: PERÍMETRO m | E5: ALT m | F5: QUANT | G5: COEF | H5: UNIT m² | I5: TOTAL m² | J5: UNIT m³ | K5: TOTAL m³ | L5: RESISTÊNCIA | M5: TIPO | N5: UNIT m² | O5: TOTAL m² | P5: PD | Q5: TOTAL | T5: m3 | U5: RESISTÊNCIA
A6: PROJETO: | T6: =IF(U6="","",SUMIF($L$6:$L$22,U6,$K$6:$K$22)) -> 0 | U6: 20MPa
A7: Laje Piso 1º Pav | B7: L10cm | F7: 1 | G7: 1 | H7: =IF(C7="","",IF(F7<0,-C7+(D7*(E7+0.02)),C7+(D7*(E7+0.02)))) | I7: =IF(C7="","",IF(F7>0,F7*H7,F7*-H7)) | J7: =IF(C7="","",IF(F7<0,-C7*E7,C7*E7)) | K7: =IF(C7="","",IF(F7>0,J7*F7,-J7*F7)) | L7: 40MPa | M7: MOLDADA IN LOCO | N7: =IF(C7="","",C7) | O7: =IF(C7="","",N7*F7) | Q7: =(C7*D7)*P7*F7 -> 0 | T7: =IF(U7="","",SUMIF($L$6:$L$22,U7,$K$6:$K$22)) -> 0 | U7: 25MPa
A8: Descontos | B8: L10cm | F8: -1 | G8: 1 | H8: =IF(C8="","",IF(F8<0,-C8+(D8*(E8+0.02)),C8+(D8*(E8+0.02)))) | I8: =IF(C8="","",IF(F8>0,F8*H8,F8*-H8)) | J8: =IF(C8="","",IF(F8<0,-C8*E8,C8*E8)) | K8: =IF(C8="","",IF(F8>0,J8*F8,-J8*F8)) | L8: 40MPa | M8: MOLDADA IN LOCO | N8: =IF(C8="","",C8) | O8: =IF(C8="","",N8*F8) | Q8: =(C8*D8)*P8*F8 -> 0 | T8: =IF(U8="","",SUMIF($L$6:$L$22,U8,$K$6:$K$22)) -> 0 | U8: 30MPa
H9: =IF(C9="","",IF(F9<0,-C9+(D9*(E9+0.02)),C9+(D9*(E9+0.02)))) | I9: =IF(C9="","",IF(F9>0,F9*H9,F9*-H9)) | J9: =IF(C9="","",IF(F9<0,-C9*E9,C9*E9)) | K9: =IF(C9="","",IF(F9>0,J9*F9,-J9*F9)) | N9: =IF(C9="","",C9) | O9: =IF(C9="","",N9*F9) | Q9: =(C9*D9)*P9*F9 -> 0 | T9: =IF(U9="","",SUMIF($L$6:$L$22,U9,$K$6:$K$22)) -> 0 | U9: 35MPa
A10: PROJETO: | H10: =IF(C10="","",IF(F10<0,-C10+(D10*(E10+0.02)),C10+(D10*(E10+0.02)))) | I10: =IF(C10="","",IF(F10>0,F10*H10,F10*-H10)) | J10: =IF(C10="","",IF(F10<0,-C10*E10,C10*E10)) | K10: =IF(C10="","",IF(F10>0,J10*F10,-J10*F10)) | N10: =IF(C10="","",C10) | O10: =IF(C10="","",N10*F10) | T10: =IF(U10="","",SUMIF($L$6:$L$22,U10,$K$6:$K$22)) -> 0 | U10: 40MPa
A11: Laje Tipo | B11: L10cm | F11: 20 | G11: 1 | H11: =IF(C11="","",IF(F11<0,-C11+(D11*(E11+0.02)),C11+(D11*(E11+0.02)))) | I11: =IF(C11="","",IF(F11>0,F11*H11,F11*-H11)) | J11: =IF(C11="","",IF(F11<0,-C11*E11,C11*E11)) | K11: =IF(C11="","",IF(F11>0,J11*F11,-J11*F11)) | L11: 25MPa | M11: MOLDADA IN LOCO | N11: =IF(C11="","",C11) | O11: =IF(C11="","",N11*F11) | Q11: =(C11*D11)*P11*F11 -> 0 | T11: =IF(U11="","",SUMIF($L$6:$L$22,U11,$K$6:$K$22))
A12: Descontos | B12: L10cm | F12: -20 | G12: 1 | H12: =IF(C12="","",IF(F12<0,-C12+(D12*(E12+0.02)),C12+(D12*(E12+0.02)))) | I12: =IF(C12="","",IF(F12>0,F12*H12,F12*-H12)) | J12: =IF(C12="","",IF(F12<0,-C12*E12,C12*E12)) | K12: =IF(C12="","",IF(F12>0,J12*F12,-J12*F12)) | L12: 25MPa | M12: MOLDADA IN LOCO | N12: =IF(C12="","",C12) | O12: =IF(C12="","",N12*F12) | Q12: =(C12*D12)*P12*F12 -> 0 | T12: =IF(U12="","",SUMIF($L$6:$L$22,U12,$K$6:$K$22))
H13: =IF(C13="","",IF(F13<0,-C13+(D13*(E13+0.02)),C13+(D13*(E13+0.02)))) | I13: =IF(C13="","",IF(F13>0,F13*H13,F13*-H13)) | J13: =IF(C13="","",IF(F13<0,-C13*E13,C13*E13)) | K13: =IF(C13="","",IF(F13>0,J13*F13,-J13*F13)) | N13: =IF(C13="","",C13) | O13: =IF(C13="","",N13*F13) | Q13: =(C13*D13)*P13*F13 -> 0 | T13: =SUM(T6:T12) -> 0 | U13: =IF(K23=T13,"OK","Conferir") -> OK
A14: PROJETO: | H14: =IF(C14="","",IF(F14<0,-C14+(D14*(E14+0.02)),C14+(D14*(E14+0.02)))) | I14: =IF(C14="","",IF(F14>0,F14*H14,F14*-H14)) | J14: =IF(C14="","",IF(F14<0,-C14*E14,C14*E14)) | K14: =IF(C14="","",IF(F14>0,J14*F14,-J14*F14)) | N14: =IF(C14="","",C14) | O14: =IF(C14="","",N14*F14)
A15: Laje barrilete | B15: L10cm | F15: 1 | G15: 1 | H15: =IF(C15="","",IF(F15<0,-C15+(D15*(E15+0.02)),C15+(D15*(E15+0.02)))) | I15: =IF(C15="","",IF(F15>0,F15*H15,F15*-H15)) | J15: =IF(C15="","",IF(F15<0,-C15*E15,C15*E15)) | K15: =IF(C15="","",IF(F15>0,J15*F15,-J15*F15)) | L15: 25MPa | M15: MOLDADA IN LOCO | N15: =IF(C15="","",C15) | O15: =IF(C15="","",N15*F15) | Q15: =(C15*D15)*P15*F15 -> 0
A16: Laje barrilete | B16: L15cm | F16: 1 | G16: 1 | H16: =IF(C16="","",IF(F16<0,-C16+(D16*(E16+0.02)),C16+(D16*(E16+0.02)))) | I16: =IF(C16="","",IF(F16>0,F16*H16,F16*-H16)) | J16: =IF(C16="","",IF(F16<0,-C16*E16,C16*E16)) | K16: =IF(C16="","",IF(F16>0,J16*F16,-J16*F16)) | L16: 25MPa | M16: MOLDADA IN LOCO | N16: =IF(C16="","",C16) | O16: =IF(C16="","",N16*F16) | Q16: =(C16*D16)*P16*F16 -> 0
A17: Descontos | B17: L15cm | F17: -1 | G17: 1 | H17: =IF(C17="","",IF(F17<0,-C17+(D17*(E17+0.02)),C17+(D17*(E17+0.02)))) | I17: =IF(C17="","",IF(F17>0,F17*H17,F17*-H17)) | J17: =IF(C17="","",IF(F17<0,-C17*E17,C17*E17)) | K17: =IF(C17="","",IF(F17>0,J17*F17,-J17*F17)) | L17: 25MPa | M17: MOLDADA IN LOCO | N17: =IF(C17="","",C17) | O17: =IF(C17="","",N17*F17) | Q17: =(C17*D17)*P17*F17 -> 0
H18: =IF(C18="","",IF(F18<0,-C18+(D18*(E18+0.02)),C18+(D18*(E18+0.02)))) | I18: =IF(C18="","",IF(F18>0,F18*H18,F18*-H18)) | J18: =IF(C18="","",IF(F18<0,-C18*E18,C18*E18)) | K18: =IF(C18="","",IF(F18>0,J18*F18,-J18*F18)) | N18: =IF(C18="","",C18) | O18: =IF(C18="","",N18*F18) | Q18: =(C18*D18)*P18*F18 -> 0
A19: PROJETO: | H19: =IF(C19="","",IF(F19<0,-C19+(D19*(E19+0.02)),C19+(D19*(E19+0.02)))) | I19: =IF(C19="","",IF(F19>0,F19*H19,F19*-H19)) | J19: =IF(C19="","",IF(F19<0,-C19*E19,C19*E19)) | K19: =IF(C19="","",IF(F19>0,J19*F19,-J19*F19)) | N19: =IF(C19="","",C19) | O19: =IF(C19="","",N19*F19)
A20: Laje Cobertura | B20: L10cm | F20: 1 | G20: 1 | H20: =IF(C20="","",IF(F20<0,-C20+(D20*(E20+0.02)),C20+(D20*(E20+0.02)))) | I20: =IF(C20="","",IF(F20>0,F20*H20,F20*-H20)) | J20: =IF(C20="","",IF(F20<0,-C20*E20,C20*E20)) | K20: =IF(C20="","",IF(F20>0,J20*F20,-J20*F20)) | L20: 25MPa | M20: MOLDADA IN LOCO | N20: =IF(C20="","",C20) | O20: =IF(C20="","",N20*F20) | Q20: =(C20*D20)*P20*F20 -> 0
B21: L20cm | F21: 1 | G21: 1 | H21: =IF(C21="","",IF(F21<0,-C21+(D21*(E21+0.02)),C21+(D21*(E21+0.02)))) | I21: =IF(C21="","",IF(F21>0,F21*H21,F21*-H21)) | J21: =IF(C21="","",IF(F21<0,-C21*E21,C21*E21)) | K21: =IF(C21="","",IF(F21>0,J21*F21,-J21*F21)) | L21: 25MPa | M21: MOLDADA IN LOCO | N21: =IF(C21="","",C21) | O21: =IF(C21="","",N21*F21) | Q21: =(C21*D21)*P21*F21 -> 0
H22: =IF(C22="","",IF(F22<0,-C22+(D22*(E22+0.02)),C22+(D22*(E22+0.02)))) | I22: =IF(C22="","",IF(F22>0,F22*H22,F22*-H22)) | J22: =IF(C22="","",IF(F22<0,-C22*E22,C22*E22)) | K22: =IF(C22="","",IF(F22>0,J22*F22,-J22*F22)) | N22: =IF(C22="","",C22) | O22: =IF(C22="","",N22*F22)
B23: TOTAL | C23: =SUMPRODUCT(C6:C22,F6:F22) -> 0 | I23: =SUM(I6:I22) -> 0 | K23: =SUM(K6:K22) -> 0 | O23: =SUM(O6:O22) -> 0
E25: JOGO DE FORMA PARA O RESUMO: | I25: =SUM(H11:H12,H20:H21,H7:H8) -> 0 | J25: m²

Sheet Escada - T1
A2: EMPREENDIMENTO: | P2: REVISÃO: | R2: DATA:
A3: =Ger_Executivo!B5 -> EMPRESA: | P3: R00 -
A4: PROJETO | B4: PEÇA | C4: LAJE PISO | G4: DEGRAUS / ESPELHO | K4: QUANT | L4: FORMA | O4: CONCRETO | T4: RESUMO - CONCRETO
C5: LARG | D5: COMPR | E5: ESPESS | F5: QUANT | G5: LARG | H5: ALT | I5: BASE | J5: QUANT | L5: LAJE PISO | M5: DEGRAUS | N5: TOTAL | O5: LAJE PISO | P5: DEGRAUS | Q5: TOTAL | R5: RESISTÊNCIA
C6: A | D6: B | E6: C | F6: D | G6: E | H6: F | I6: G | J6: H | L6: m2 | M6: m2 | N6: m2 | O6: m3 | P6: m3 | Q6: m3 | T6: m3 | U6: RESISTÊNCIA
A7: PROJETO: 0002-PD01-EST-EX-612-TOR-ESC_R00 | T7: =IF(U7="","",SUMIF($R$7:$R$20,U7,$Q$7:$Q$20)) -> 0 | U7: 20MPa
A8: Térreo - 1° pavto | B8: 1º lance | C8: 1.26 | D8: 1.147 | E8: 0.14 | F8: 1 | G8: 0.28 | H8: 0.18 | I8: =SQRT((G8^2)+(H8^2)) -> 0.33286634 | J8: 3 | K8: 1 | L8: =(((C8*D8)+(((C8+D8)*2)*E8))*F8)*K8 -> 2.11918 | M8: =(((H8*C8)+(((G8*H8)/2)*2))*J8)*K8 -> 0.8316 | N8: =SUM(L8:M8) -> 2.95078 | O8: =(((C8*D8)*E8)*F8)*K8 -> 0.2023308 | P8: =((((G8*H8)/2)*C8)*J8)*K8 -> 0.095256 | Q8: =SUM(O8:P8) -> 0.2975868 | R8: 40MPa | T8: =IF(U8="","",SUMIF($R$7:$R$20,U8,$Q$7:$Q$20)) -> 28.085495 | U8: 25MPa
B9: Patamar | C9: 1.35 | D9: 1.31 | E9: 0.14 | F9: 1 | I9: =SQRT((G9^2)+(H9^2)) -> 0 | K9: 1 | L9: =(((C9*D9)+(((C9+D9)*2)*E9))*F9)*K9 -> 2.5133 | M9: =(((H9*C9)+(((G9*H9)/2)*2))*J9)*K9 -> 0 | N9: =SUM(L9:M9) -> 2.5133 | O9: =(((C9*D9)*E9)*F9)*K9 -> 0.24759 | P9: =((((G9*H9)/2)*C9)*J9)*K9 -> 0 | Q9: =SUM(O9:P9) -> 0.24759 | R9: 40MPa | T9: =IF(U9="","",SUMIF($R$7:$R$20,U9,$Q$7:$Q$20)) -> 0 | U9: 30MPa
B10: 2º lance | C10: 1.26 | D10: 3.66 | E10: 0.14 | F10: 1 | G10: 0.28 | H10: 0.18 | I10: =SQRT((G10^2)+(H10^2)) -> 0.33286634 | J10: 10 | K10: 1 | L10: =(((C10*D10)+(((C10+D10)*2)*E10))*F10)*K10 -> 5.9892 | M10: =(((H10*C10)+(((G10*H10)/2)*2))*J10)*K10 -> 2.772 | N10: =SUM(L10:M10) -> 8.7612 | O10: =(((C10*D10)*E10)*F10)*K10 -> 0.645624 | P10: =((((G10*H10)/2)*C10)*J10)*K10 -> 0.31752 | Q10: =SUM(O10:P10) -> 0.963144 | R10: 40MPa | T10: =IF(U10="","",SUMIF($R$7:$R$20,U10,$Q$7:$Q$20)) -> 0 | U10: 35MPa
B11: Patamar | C11: 2.66 | D11: 1.26 | E11: 0.14 | F11: 1 | I11: =SQRT((G11^2)+(H11^2)) -> 0 | K11: 1 | L11: =(((C11*D11)+(((C11+D11)*2)*E11))*F11)*K11 -> 4.4492 | M11: =(((H11*C11)+(((G11*H11)/2)*2))*J11)*K11 -> 0 | N11: =SUM(L11:M11) -> 4.4492 | O11: =(((C11*D11)*E11)*F11)*K11 -> 0.469224 | P11: =((((G11*H11)/2)*C11)*J11)*K11 -> 0 | Q11: =SUM(O11:P11) -> 0.469224 | R11: 40MPa | T11: =IF(U11="","",SUMIF($R$7:$R$20,U11,$Q$7:$Q$20)) -> 2.6231688 | U11: 40MPa
B12: 3º lance | C12: 1.26 | D12: 2.4 | E12: 0.14 | F12: 1 | G12: 0.28 | H12: 0.18 | I12: =SQRT((G12^2)+(H12^2)) -> 0.33286634 | J12: 7 | K12: 1 | L12: =(((C12*D12)+(((C12+D12)*2)*E12))*F12)*K12 -> 4.0488 | M12: =(((H12*C12)+(((G12*H12)/2)*2))*J12)*K12 -> 1.9404 | N12: =SUM(L12:M12) -> 5.9892 | O12: =(((C12*D12)*E12)*F12)*K12 -> 0.42336 | P12: =((((G12*H12)/2)*C12)*J12)*K12 -> 0.222264 | Q12: =SUM(O12:P12) -> 0.645624 | R12: 40MPa | T12: =IF(U12="","",SUMIF($R$7:$R$20,U12,$Q$7:$Q$20))
A13: PROJETO: 0002-PD01-EST-EX-802-TOR-ESC_R00 | T13: =IF(U13="","",SUMIF($R$7:$R$20,U13,$Q$7:$Q$20))
A14: 1° pavto - 2º pvto | B14: 1º lance | C14: 1.26 | D14: 2.663 | E14: 0.1 | F14: 1 | G14: 0.28 | H14: 0.18 | I14: =SQRT((G14^2)+(H14^2)) -> 0.33286634 | J14: 7 | K14: 1 | L14: =(((C14*D14)+(((C14+D14)*2)*E14))*F14)*K14 -> 4.13998 | M14: =(((H14*C14)+(((G14*H14)/2)*2))*J14)*K14 -> 1.9404 | N14: =SUM(L14:M14) -> 6.08038 | O14: =(((C14*D14)*E14)*F14)*K14 -> 0.335538 | P14: =((((G14*H14)/2)*C14)*J14)*K14 -> 0.222264 | Q14: =SUM(O14:P14) -> 0.557802 | R14: 25MPa | T14: =SUM(T7:T13) -> 30.708663 | U14: =IF(Q21=T14,"OK","Conferir") -> OK
B15: Patamar | C15: 2.66 | D15: 1.26 | E15: 0.1 | F15: 1 | I15: =SQRT((G15^2)+(H15^2)) -> 0 | K15: 1 | L15: =(((C15*D15)+(((C15+D15)*2)*E15))*F15)*K15 -> 4.1356 | M15: =(((H15*C15)+(((G15*H15)/2)*2))*J15)*K15 -> 0 | N15: =SUM(L15:M15) -> 4.1356 | O15: =(((C15*D15)*E15)*F15)*K15 -> 0.33516 | P15: =((((G15*H15)/2)*C15)*J15)*K15 -> 0 | Q15: =SUM(O15:P15) -> 0.33516 | R15: 25MPa
B16: 2º lance | C16: 1.26 | D16: 2.33 | E16: 0.1 | F16: 1 | G16: 0.28 | H16: 0.18125 | I16: =SQRT((G16^2)+(H16^2)) -> 0.33354394 | J16: 7 | K16: 1 | L16: =(((C16*D16)+(((C16+D16)*2)*E16))*F16)*K16 -> 3.6538 | M16: =(((H16*C16)+(((G16*H16)/2)*2))*J16)*K16 -> 1.953875 | N16: =SUM(L16:M16) -> 5.607675 | O16: =(((C16*D16)*E16)*F16)*K16 -> 0.29358 | P16: =((((G16*H16)/2)*C16)*J16)*K16 -> 0.2238075 | Q16: =SUM(O16:P16) -> 0.5173875 | R16: 25MPa
A17: PROJETO: 0002-PD01-EST-EX-806-TOR-ESC_R00
A18: Tipo | B18: 1º lance | C18: 1.26 | D18: 2.663 | E18: 0.1 | F18: 1 | G18: 0.28 | H18: 0.18 | I18: =SQRT((G18^2)+(H18^2)) -> 0.33286634 | J18: 7 | K18: 19 | L18: =(((C18*D18)+(((C18+D18)*2)*E18))*F18)*K18 -> 78.65962 | M18: =(((H18*C18)+(((G18*H18)/2)*2))*J18)*K18 -> 36.8676 | N18: =SUM(L18:M18) -> 115.52722 | O18: =(((C18*D18)*E18)*F18)*K18 -> 6.375222 | P18: =((((G18*H18)/2)*C18)*J18)*K18 -> 4.223016 | Q18: =SUM(O18:P18) -> 10.598238 | R18: 25MPa
B19: Patamar | C19: 2.66 | D19: 1.26 | E19: 0.1 | F19: 1 | I19: =SQRT((G19^2)+(H19^2)) -> 0 | K19: 19 | L19: =(((C19*D19)+(((C19+D19)*2)*E19))*F19)*K19 -> 78.5764 | M19: =(((H19*C19)+(((G19*H19)/2)*2))*J19)*K19 -> 0 | N19: =SUM(L19:M19) -> 78.5764 | O19: =(((C19*D19)*E19)*F19)*K19 -> 6.36804 | P19: =((((G19*H19)/2)*C19)*J19)*K19 -> 0 | Q19: =SUM(O19:P19) -> 6.36804 | R19: 25MPa
B20: 2º lance | C20: 1.26 | D20: 2.33 | E20: 0.1 | F20: 1 | G20: 0.29 | H20: 0.17 | I20: =SQRT((G20^2)+(H20^2)) -> 0.33615473 | J20: 7 | K20: 19 | L20: =(((C20*D20)+(((C20+D20)*2)*E20))*F20)*K20 -> 69.4222 | M20: =(((H20*C20)+(((G20*H20)/2)*2))*J20)*K20 -> 35.0455 | N20: =SUM(L20:M20) -> 104.4677 | O20: =(((C20*D20)*E20)*F20)*K20 -> 5.57802 | P20: =((((G20*H20)/2)*C20)*J20)*K20 -> 4.130847 | Q20: =SUM(O20:P20) -> 9.708867 | R20: 25MPa
B21: TOTAL | N21: =SUM(N7:N20) -> 339.05865 | Q21: =SUM(Q7:Q20) -> 30.708663
B22: QUANTITATIVO PROJETISTA
J24: JOGO DE FORMA PARA O RESUMO: | N24: =SUM(N8:N12) -> 24.66368 | O24: m²
B26: DETALHE DA ESCADA MEDIDAS A SEREM FORNECIDAS
E29: E | H29: C
C34: F
F37: B

Sheet Indices de Bloco
A2: EMPREENDIMENTO: | L2: REVISÃO: | N2: DATA:
A3: =Ger_Executivo!B5 -> EMPRESA: | L3: R00 -
A5: Pavimentos Tipo - Torre 1 | I5: Pavimentos Tipo - Torre 2
A6: Tipo | B6: Dimensões | C6: Quantidade | D6: Área | E6: Indice | F6: Perda | G6: Indice + Perda | I6: Tipo | J6: Dimensões | K6: Quantidade | L6: Área | M6: Indice | N6: Perda | O6: Indice + Perda
A7: Bloco | B7: 14x19x04 | C7: 335 | D7: =(SUM(#REF!)/21) -> #REF! | E7: =C7/D7 -> #REF! | F7: 0.03 | G7: =E7*(1+F7) -> #REF! | I7: Bloco | J7: 14x19x04 | K7: 335 | L7: =SUM(#REF!)/21 -> #REF! | M7: =K7/L7 -> #REF! | N7: 0.03 | O7: =M7*(1+N7) -> #REF!
A8: Bloco | B8: 14x19x09 | C8: 4 | D8: =$D$7 -> #REF! | E8: =C8/D8 -> #REF! | F8: 0.03 | G8: =E8*(1+F8) -> #REF! | I8: Bloco | J8: 14x19x09 | K8: 4 | L8: =$D$7 -> #REF! | M8: =K8/L8 -> #REF! | N8: 0.03 | O8: =M8*(1+N8) -> #REF!
A9: Bloco | B9: 14x19x19 | C9: 951 | D9: =$D$7 -> #REF! | E9: =C9/D9 -> #REF! | F9: 0.03 | G9: =E9*(1+F9) -> #REF! | I9: Bloco | J9: 14x19x19 | K9: 951 | L9: =$D$7 -> #REF! | M9: =K9/L9 -> #REF! | N9: 0.03 | O9: =M9*(1+N9) -> #REF!
A10: Bloco | B10: 14x19x34 | C10: 3125 | D10: =$D$7 -> #REF! | E10: =C10/D10 -> #REF! | F10: 0.03 | G10: =E10*(1+F10) -> #REF! | I10: Bloco | J10: 14x19x34 | K10: 3125 | L10: =$D$7 -> #REF! | M10: =K10/L10 -> #REF! | N10: 0.03 | O10: =M10*(1+N10) -> #REF!
A11: Bloco | B11: 14x19x39 | C11: 6608 | D11: =$D$7 -> #REF! | E11: =C11/D11 -> #REF! | F11: 0.03 | G11: =E11*(1+F11) -> #REF! | I11: Bloco | J11: 14x19x39 | K11: 6608 | L11: =$D$7 -> #REF! | M11: =K11/L11 -> #REF! | N11: 0.03 | O11: =M11*(1+N11) -> #REF!
A12: Bloco | B12: 14x19x54 | C12: 479 | D12: =$D$7 -> #REF! | E12: =C12/D12 -> #REF! | F12: 0.03 | G12: =E12*(1+F12) -> #REF! | I12: Bloco | J12: 14x19x54 | K12: 479 | L12: =$D$7 -> #REF! | M12: =K12/L12 -> #REF! | N12: 0.03 | O12: =M12*(1+N12) -> #REF!
A13: canaleta | B13: 14x19x04 | C13: 2 | D13: =$D$7 -> #REF! | E13: =C13/D13 -> #REF! | F13: 0.05 | G13: =E13*(1+F13) -> #REF! | I13: canaleta | J13: 14x19x04 | K13: 2 | L13: =$D$7 -> #REF! | M13: =K13/L13 -> #REF! | N13: 0.05 | O13: =M13*(1+N13) -> #REF!
A14: canaleta | B14: 14x19x14 | C14: 15 | D14: =$D$7 -> #REF! | E14: =C14/D14 -> #REF! | F14: 0.05 | G14: =E14*(1+F14) -> #REF! | I14: canaleta | J14: 14x19x14 | K14: 15 | L14: =$D$7 -> #REF! | M14: =K14/L14 -> #REF! | N14: 0.05 | O14: =M14*(1+N14) -> #REF!
A15: canaleta | B15: 14x19x34 | C15: 540 | D15: =$D$7 -> #REF! | E15: =C15/D15 -> #REF! | F15: 0.05 | G15: =E15*(1+F15) -> #REF! | I15: canaleta | J15: 14x19x34 | K15: 540 | L15: =$D$7 -> #REF! | M15: =K15/L15 -> #REF! | N15: 0.05 | O15: =M15*(1+N15) -> #REF!
A16: canaleta | B16: 14x19x19 | C16: 206 | D16: =$D$7 -> #REF! | E16: =C16/D16 -> #REF! | F16: 0.05 | G16: =E16*(1+F16) -> #REF! | I16: canaleta | J16: 14x19x19 | K16: 206 | L16: =$D$7 -> #REF! | M16: =K16/L16 -> #REF! | N16: 0.05 | O16: =M16*(1+N16) -> #REF!
A17: canaleta | B17: 14x19x39 | C17: 1222 | D17: =$D$7 -> #REF! | E17: =C17/D17 -> #REF! | F17: 0.05 | G17: =E17*(1+F17) -> #REF! | I17: canaleta | J17: 14x19x39 | K17: 1222 | L17: =$D$7 -> #REF! | M17: =K17/L17 -> #REF! | N17: 0.05 | O17: =M17*(1+N17) -> #REF!
E18: =SUM(E7:E17) -> #REF! | G18: =SUM(G7:G17) -> #REF! | M18: =SUM(M7:M17) -> #REF! | O18: =SUM(O7:O17) -> #REF!

Sheet Resumo Esquadrias - T1
A2: EMPREENDIMENTO: | F2: REVISÃO: | J2: DATA:
A3: =Ger_Executivo!B5 -> EMPRESA: | F3: R00 -
A5: item | B5: código | C5: Descrição | D5: Local | E5: un | F5: comp | G5: x | H5: altura | I5: m | J5: TOTAL | L5: QUANT. PROJETISTA
B6: * | C6: PORTAS DE MADEIRA EM MARCENARIA (BATENTE/FOLHA/GUARNIÇÃO/FERRAGENS)
B7: MA01 | C7: 1 FOLHA DE ABRIR EM MADEIRA COM BATENTE REGULÁVEL DE 15cm + MOLDURA EXTERNA | D7: ENTRADA APTOS (TÉRREO E TIPO) | E7: =IF(B7="","","UN") -> UN | F7: 0.91 | G7: =IF(F7=0,0,"x") -> x | H7: 2.21 | I7: =IF(H7=0,0,"m") -> m | J7: =SUMIF(#REF!,'Resumo Esquadrias - T1'!$B7,#REF!) -> #REF!
B8: MA02 | C8: 1 FOLHA LISA DE ABRIR EM MADEIRA COM BATENTE REGULÁVEL DE 10cm | D8: DORMITÓRIOS (TIPO)/ VEST. MASC E FEM. (TÉRREO TORRE 1)/ SALA DE ENTREGA TÉRREO TORRE 1)/DML (TORRE 1 E 2)/ COPA (SALÃO DE FESTAS) | E8: =IF(B8="","","UN") -> UN | F8: 0.81 | G8: =IF(F8=0,0,"x") -> x | H8: 2.21 | I8: =IF(H8=0,0,"m") -> m | J8: =SUMIF(#REF!,'Resumo Esquadrias - T1'!$B8,#REF!) -> #REF!
B9: MA03 | C9: 1 FOLHA LISA DE ABRIR EM MADEIRA COM BATENTE REGULÁVEL DE 10cm | D9: BANHO APTO PNE (TÉRREO E 1º PAV) | E9: =IF(B9="","","UN") -> UN | F9: 0.91 | G9: =IF(F9=0,0,"x") -> x | H9: 2.21 | I9: =IF(H9=0,0,"m") -> m | J9: =SUMIF(#REF!,'Resumo Esquadrias - T1'!$B9,#REF!) -> #REF!
B10: MA04 | C10: 1 FOLHA LISA DE ABRIR EM MADEIRA COM BATENTE REGULÁVEL DE 15cm | D10: BANHO APTO TIPO / WC PORTARIA/ WC ESPAÇO FLEX/ WCS BRINQUEDOTECA/ WC FEM E MASC. (SALÃO DE FESTAS) | E10: =IF(B10="","","UN") -> UN | F10: 0.71 | G10: =IF(F10=0,0,"x") -> x | H10: 2.21 | I10: =IF(H10=0,0,"m") -> m | J10: =SUMIF(#REF!,'Resumo Esquadrias - T1'!$B10,#REF!) -> #REF!
B11: MA05 | C11: 1 FOLHA LISA DE ABRIR EM MADEIRA COM BATENTE REGULÁVEL DE 15cm | D11: DORMITÓRIO APTO PNE/ APA (TÉRREO TORRE 1)/ HALL DE SERVIÇO (TORRES 1 E 2)/ ADM (TORRE 2) | E11: =IF(B11="","","UN") -> UN | F11: 0.91 | G11: =IF(F11=0,0,"x") -> x | H11: 2.21 | I11: =IF(H11=0,0,"m") -> m | J11: =SUMIF(#REF!,'Resumo Esquadrias - T1'!$B11,#REF!) -> #REF!
A12: 606 | B12: MA06 | C12: 2 FOLHAS DE ABRIR DE 63x200cm (CADA) COM FRISOS DECORATIVOS P/ TÉRREO E SEM FRISOS DEMAIS PAVIMENTOS + BANDEIRA FIXA | D12: SHAFT HIDRÁULICA (TÉRREO TORRE 02 E 1º PAV TORRE 01) | E12: =IF(B12="","","UN") -> UN | F12: 1.36 | G12: =IF(F12=0,0,"x") -> x | H12: =2.63-0.2+0.06 -> 2.49 | I12: =IF(H12=0,0,"m") -> m | J12: =SUMIF(#REF!,'Resumo Esquadrias - T1'!$B12,#REF!) -> #REF!
A13: 607 | B13: MA07 | C13: 2 FOLHAS DE ABRIR DE 63x200cm (CADA) COM FRISOS DECORATIVOS P/ TÉRREO E SEM FRISOS DEMAIS PAVIMENTOS + BANDEIRA FIXA | D13: SHAFT ELÉTRICA / SISTEMAS (TÉRREO TORRE 02 E 1º PAV TORRE 01) | E13: =IF(B13="","","UN") -> UN | F13: 1.36 | G13: =IF(F13=0,0,"x") -> x | H13: =2.63-0.2+0.06 -> 2.49 | I13: =IF(H13=0,0,"m") -> m | J13: =SUMIF(#REF!,'Resumo Esquadrias - T1'!$B13,#REF!) -> #REF!
A14: 608 | B14: MA08 | C14: 1 FOLHA DE ABRIR DE 0,70x200m COM FRISOS DECORATIVOS P/ TÉRREO E SEM FRISOS DEMAIS PAVIMENTOS + BANDEIRA FIXA | D14: SHAFT ELÉTRICA / SISTEMAS (TÉRREO TORRE 02 E 1º PAV TORRE 01) | E14: =IF(B14="","","UN") -> UN | F14: 0.8 | G14: =IF(F14=0,0,"x") -> x | H14: =2.63-0.2+0.06 -> 2.49 | I14: =IF(H14=0,0,"m") -> m | J14: =SUMIF(#REF!,'Resumo Esquadrias - T1'!$B14,#REF!) -> #REF!
A15: 609 | B15: MA09 | C15: 1 FOLHA DE ABRIR DE 57X200cm ABRIR COM FRISOS DECORATIVOS P/ TÉRREO E SEM FRISOS DEMAIS PAVIMENTOS | D15: SHAFT HIDRANTE (TÉRREO TORRE 02 E 1º PAV TORRE 01) | E15: =IF(B15="","","UN") -> UN | F15: 0.71 | G15: =IF(F15=0,0,"x") -> x | H15: =2.63-0.2+0.06 -> 2.49 | I15: =IF(H15=0,0,"m") -> m | J15: =SUMIF(#REF!,'Resumo Esquadrias - T1'!$B15,#REF!) -> #REF!
A16: 610 | B16: MA10 | C16: 1 FOLHA DE ABRIR DE 57X200cm ABRIR COM FRISOS DECORATIVOS P/ TÉRREO E SEM FRISOS DEMAIS PAVIMENTOS | D16: SHAFT ELÉTRICA (TÉRREO TORRE 02 E 1º PAV TORRE 01) | E16: =IF(B16="","","UN") -> UN | F16: 0.61 | G16: =IF(F16=0,0,"x") -> x | H16: =2.63-0.2+0.06 -> 2.49 | I16: =IF(H16=0,0,"m") -> m | J16: =SUMIF(#REF!,'Resumo Esquadrias - T1'!$B16,#REF!) -> #REF!
A17: 606 | B17: MA06A | C17: 2 FOLHAS DE ABRIR DE 63x200cm (CADA) COM FRISOS DECORATIVOS P/ TÉRREO E SEM FRISOS DEMAIS PAVIMENTOS + BANDEIRA FIXA | D17: SHAFT HIDRÁULICA (TIPO) | E17: =IF(B17="","","UN") -> UN | F17: 1.36 | G17: =IF(F17=0,0,"x") -> x | H17: =2.6-0.2+0.06 -> 2.46 | I17: =IF(H17=0,0,"m") -> m | J17: =SUMIF(#REF!,'Resumo Esquadrias - T1'!$B17,#REF!) -> #REF!
A18: 607 | B18: MA07A | C18: 2 FOLHAS DE ABRIR DE 63x200cm (CADA) COM FRISOS DECORATIVOS P/ TÉRREO E SEM FRISOS DEMAIS PAVIMENTOS + BANDEIRA FIXA | D18: SHAFT ELÉTRICA / SISTEMAS (TIPO) | E18: =IF(B18="","","UN") -> UN | F18: 1.36 | G18: =IF(F18=0,0,"x") -> x | H18: =2.6-0.2+0.06 -> 2.46 | I18: =IF(H18=0,0,"m") -> m | J18: =SUMIF(#REF!,'Resumo Esquadrias - T1'!$B18,#REF!) -> #REF!
A19: 608 | B19: MA08A | C19: 1 FOLHA DE ABRIR DE 0,70x200m COM FRISOS DECORATIVOS P/ TÉRREO E SEM FRISOS DEMAIS PAVIMENTOS + BANDEIRA FIXA | D19: SHAFT ELÉTRICA / SISTEMAS (TÉRREO TORRE 01) (TIPO) | E19: =IF(B19="","","UN") -> UN | F19: 0.8 | G19: =IF(F19=0,0,"x") -> x | H19: =2.6-0.2+0.06 -> 2.46 | I19: =IF(H19=0,0,"m") -> m | J19: =SUMIF(#REF!,'Resumo Esquadrias - T1'!$B19,#REF!) -> #REF!
A20: 609 | B20: MA09A | C20: 1 FOLHA DE ABRIR DE 57X200cm ABRIR COM FRISOS DECORATIVOS P/ TÉRREO E SEM FRISOS DEMAIS PAVIMENTOS | D20: SHAFT HIDRANTE (TIPO) | E20: =IF(B20="","","UN") -> UN | F20: 0.71 | G20: =IF(F20=0,0,"x") -> x | H20: =2.6-0.2+0.06 -> 2.46 | I20: =IF(H20=0,0,"m") -> m | J20: =SUMIF(#REF!,'Resumo Esquadrias - T1'!$B20,#REF!) -> #REF!
A21: 610 | B21: MA10A | C21: 1 FOLHA DE ABRIR DE 57X200cm ABRIR COM FRISOS DECORATIVOS P/ TÉRREO E SEM FRISOS DEMAIS PAVIMENTOS | D21: SHAFT ELÉTRICA (TIPO) | E21: =IF(B21="","","UN") -> UN | F21: 0.61 | G21: =IF(F21=0,0,"x") -> x | H21: =2.6-0.2+0.06 -> 2.46 | I21: =IF(H21=0,0,"m") -> m | J21: =SUMIF(#REF!,'Resumo Esquadrias - T1'!$B21,#REF!) -> #REF!
A22: 608 | B22: MA08B | C22: 1 FOLHA DE ABRIR DE 70x200cm COM FRISOS DECORATIVOS P/ TÉRREO E SEM FRISOS DEMAIS PAVIMENTOS + BANDEIRA FIXA | D22: SHAFT ELÉTRICA / SISTEMAS (TÉRREO TORRE 01) | E22: =IF(B22="","","UN") -> UN | F22: 0.8 | G22: =IF(F22=0,0,"x") -> x | H22: =2.8-0.2+0.06 -> 2.66 | I22: =IF(H22=0,0,"m") -> m | J22: =SUMIF(#REF!,'Resumo Esquadrias - T1'!$B22,#REF!) -> #REF!
E23: =IF(B23="","","UN") | G23: =IF(F23=0,0,"x") -> 0 | I23: =IF(H23=0,0,"m") -> 0 | J23: =SUMIF(#REF!,'Resumo Esquadrias - T1'!$B23,#REF!) -> #REF!
E24: =IF(B24="","","UN") | G24: =IF(F24=0,0,"x") -> 0 | I24: =IF(H24=0,0,"m") -> 0 | J24: =SUMIF(#REF!,'Resumo Esquadrias - T1'!$B24,#REF!) -> #REF!
E25: =IF(B25="","","UN") | G25: =IF(F25=0,0,"x") -> 0 | I25: =IF(H25=0,0,"m") -> 0 | J25: =SUMIF(#REF!,'Resumo Esquadrias - T1'!$B25,#REF!) -> #REF!
E26: =IF(B26="","","UN") | G26: =IF(F26=0,0,"x") -> 0 | I26: =IF(H26=0,0,"m") -> 0 | J26: =SUMIF(#REF!,'Resumo Esquadrias - T1'!$B26,#REF!) -> #REF!
E27: =IF(B27="","","UN") | G27: =IF(F27=0,0,"x") -> 0 | I27: =IF(H27=0,0,"m") -> 0 | J27: =SUMIF(#REF!,'Resumo Esquadrias - T1'!$B27,#REF!) -> #REF!
E28: =IF(B28="","","UN") | G28: =IF(F28=0,0,"x") -> 0 | I28: =IF(H28=0,0,"m") -> 0 | J28: =SUMIF(#REF!,'Resumo Esquadrias - T1'!$B28,#REF!) -> #REF!
E29: =IF(B29="","","UN") | G29: =IF(F29=0,0,"x") -> 0 | I29: =IF(H29=0,0,"m") -> 0 | J29: =SUMIF(#REF!,'Resumo Esquadrias - T1'!$B29,#REF!) -> #REF!
E30: =IF(B30="","","UN") | G30: =IF(F30=0,0,"x") -> 0 | I30: =IF(H30=0,0,"m") -> 0 | J30: =SUMIF(#REF!,'Resumo Esquadrias - T1'!$B30,#REF!) -> #REF!
E31: =IF(B31="","","UN") | G31: =IF(F31=0,0,"x") -> 0 | I31: =IF(H31=0,0,"m") -> 0 | J31: =SUMIF(#REF!,'Resumo Esquadrias - T1'!$B31,#REF!) -> #REF!
E32: =IF(B32="","","UN") | G32: =IF(F32=0,0,"x") -> 0 | I32: =IF(H32=0,0,"m") -> 0 | J32: =SUMIF(#REF!,'Resumo Esquadrias - T1'!$B32,#REF!) -> #REF!
E33: =IF(B33="","","UN") | G33: =IF(F33=0,0,"x") -> 0 | I33: =IF(H33=0,0,"m") -> 0 | J33: =SUMIF(#REF!,'Resumo Esquadrias - T1'!$B33,#REF!) -> #REF!
A34: Inserir Linhas Acima... | I34: =IF(H34=0,0,"m") -> 0 | J34: =SUMIF(#REF!,'Resumo Esquadrias - T1'!$B34,#REF!) -> #REF!
B35: * | C35: FERRAGENS
B36: F1 | C36: FECHADURA EXTERNA - PADO CONCEPT POLIDO 406-30E | E36: =IF(B36="","","UN") -> UN | J36: =SUMIF(#REF!,'Resumo Esquadrias - T1'!$B36,#REF!) -> #REF!
B37: F2 | C37: FECHADURA INTERNA - PADO CONCEPT POLIDO 4061-30I | E37: =IF(B37="","","UN") -> UN | J37: =SUMIF(#REF!,'Resumo Esquadrias - T1'!$B37,#REF!) -> #REF!
B38: F3 | C38: FECHADURA BANHO - PADO CONCEPT POLIDO 406-30B | E38: =IF(B38="","","UN") -> UN | J38: =SUMIF(#REF!,'Resumo Esquadrias - T1'!$B38,#REF!) -> #REF!
E39: =IF(B39="","","UN") | J39: =SUMIF(#REF!,'Resumo Esquadrias - T1'!$B39,#REF!) -> #REF!
E40: =IF(B40="","","UN") | J40: =SUMIF(#REF!,'Resumo Esquadrias - T1'!$B40,#REF!) -> #REF!
