Workbook
Name \0: #REF!
Name \0: #REF!
Name \0: #REF!
Name \0: #REF!
Name \0: #REF!
Name \1: #REF!
Name \1: #REF!
Name \1: #REF!
Name \a: #REF!
Name \a: #REF!
Name \a: #REF!
Name \a: #REF!
Name \a: #REF!
Name \b: #REF!
Name \b: #REF!
Name \b: #REF!
Name \c: #REF!
Name \c: #REF!
Name \c: #REF!
Name \d: #REF!
Name \d: #REF!
Name \d: #REF!
Name \e: #REF!
Name \e: #REF!
Name \e: #REF!
Name \i: #REF!
Name \i: #REF!
Name \i: #REF!
Name \J: #REF!
Name \J: #REF!
Name \J: #REF!
Name \k: #REF!
Name \k: #REF!
Name \k: #REF!
Name \l: #N/A
Name \m: #REF!
Name \m: #REF!
Name \m: #REF!
Name \m: #REF!
Name \m: #REF!
Name \o: #REF!
Name \o: #REF!
Name \o: #REF!
Name \p: #REF!
Name \p: #REF!
Name \p: #REF!
Name \r: #REF!
Name \r: #REF!
Name \r: #REF!
Name \T: #REF!
Name \T: #REF!
Name \T: #REF!
Name \z: #REF!
Name \z: #REF!
Name \z: #REF!
Name \z: #REF!
Name _\0: #REF!
Name _\1: #REF!
Name _\a: #REF!
Name _\b: #REF!

Sheet Obra 
C1: Projeto | D1: Porto Cerro
C2: Empresa | D2: XPCon Empreendimentos
C3: Revisão | D3: R01 - 03/09/2025
A4: QUADRO DE ÁREAS
B6: Descrição | C6: Unidade | E6: Quantidade | G6: Imagens
B7: MESES DE OBRA | C7: MÊS | E7: 36 | I7: PARA EAP CONSIDERADO TIPO X13 COMO QUADRO
B8: ÁREA DO TERRENO | C8: M² | E8: 894.13
B9: ÁREA CONSTRUÍDA | C9: M² | E9: 13188.75
B10: NÚMERO DE UNIDADES HABITACIONAIS | C10: UN | E10: 86
B11: NÚMERO DE UNIDADES COMERCIAIS | C11: UN | E11: 0
B12: ÁREA PRIVATIVA | C12: M² | E12: =SUM(E21:E23) -> 8125.79
B13: NÚMERO DE PAVIMENTOS | C13: UN | E13: 21
B15: Térreo - G01 | C15: M² | E15: 799.52
B16: 2º pavimento - G02 | C16: M² | E16: 803.5
B17: 3º pavimento - G03 | C17: M² | E17: 803.5
B18: 4º pavimento - G04 | C18: M² | E18: 803.5
B19: 5º pavimento - G05 | C19: M² | E19: 748.28
B20: 6º pavimento - Lazer | C20: M² | E20: 796.98
B21: 7º ao 19º pavimento - Tipo (x13) | C21: M² | E21: 7112.56
B22: 20º pavimento - Tipo Diferenciado | C22: M² | E22: 547.12
B23: 21º pavimento - Duplex Superior | C23: M² | E23: 466.11
B24: Área Técnica | C24: M² | E24: 250.06
B25: Reservatório Superior | C25: M² | E25: 57.62
B31: ETAPA | C31: VALOR ORÇADO | D31: % | E31: VALOR / m²
B32: GERENCIAMENTO TÉCNICO E ADMINISTRATIVO | C32: ='Ger_Tec e Adm'!N123 -> 4533686.5 | D32: =C32/C$51 -> 0.12280121 | E32: =C32/$E$9 -> 343.75407
B33: MOVIMENTAÇÃO DE TERRA | C33: =Ger_Executivo!N8 -> 201548.69 | D33: =C33/C$51 -> 0.005459227 | E33: =C33/$E$9 -> 15.281864
B34: INFRAESTRUTURA | C34: =Ger_Executivo!N21 -> 1971424.2 | D34: =C34/C$51 -> 0.05339877 | E34: =C34/$E$9 -> 149.47771
B35: SUPRAESTRUTURA | C35: =Ger_Executivo!N53 -> 6810042.5 | D35: =C35/C$51 -> 0.18445949 | E35: =C35/$E$9 -> 516.35239
B36: ALVENARIA ESTRUTURAL | C36: =Ger_Executivo!N220 -> 1867619.9 | D36: =C36/C$51 -> 0.050587087 | E36: =C36/$E$9 -> 141.60705
B37: ALVENARIA | C37: =Ger_Executivo!N275 -> 743245.34 | D37: =C37/C$51 -> 0.020131835 | E37: =C37/$E$9 -> 56.354495
B38: IMPERMEABILIZAÇÃO E TRATAMENTOS | C38: =Ger_Executivo!N329 -> 570028.95 | D38: =C38/C$51 -> 0.015440028 | E38: =C38/$E$9 -> 43.220848
B39: INSTALAÇÕES ELÉTRICAS, HIDRÁULICAS, GLP E PREVENTIVAS | C39: =Ger_Executivo!N431+Ger_Executivo!N470+Ger_Executivo!N609 -> 3848757 | D39: =C39/C$51 -> 0.10424894 | E39: =C39/$E$9 -> 291.82121
B40: EQUIPAMENTOS E SISTEMAS ESPECIAIS | C40: =Ger_Executivo!N708+Ger_Executivo!N718 -> 1709214.5 | D40: =C40/C$51 -> 0.046296455 | E40: =C40/$E$9 -> 129.5964
B41: REVESTIMENTOS INTERNOS DE PAREDE | C41: =Ger_Executivo!N747 -> 1655202.7 | D41: =C41/C$51 -> 0.044833469 | E41: =C41/$E$9 -> 125.5011
B42: REVESTIMENTOS E ACABAMENTOS EM TETO | C42: =Ger_Executivo!N865 -> 680621.57 | D42: =C42/C$51 -> 0.018435583 | E42: =C42/$E$9 -> 51.606223
B43: PISOS E PAVIMENTAÇÕES | C43: =Ger_Executivo!N912 -> 1992159.7 | D43: =C43/C$51 -> 0.053960421 | E43: =C43/$E$9 -> 151.04993
B44: SISTEMAS DE PINTURA INTERNA | C44: =Ger_Executivo!N1055 -> 2004994 | D44: =C44/C$51 -> 0.054308054 | E44: =C44/$E$9 -> 152.02305
B45: ESQUADRIAS, VIDROS E FERRAGENS | C45: =Ger_Executivo!N1185 -> 4314922.3 | D45: =C45/C$51 -> 0.11687568 | E45: =C45/$E$9 -> 327.16689
B46: LOUÇAS E METAIS | C46: =Ger_Executivo!N1308 -> 390783.28 | D46: =C46/C$51 -> 0.010584909 | E46: =C46/$E$9 -> 29.630047
B47: COBERTURA | C47: =Ger_Executivo!N1342 -> 163256.76 | D47: =C47/C$51 -> 0.0044220368 | E47: =C47/$E$9 -> 12.378486
B48: REVESTIMENTOS E ACABAMENTOS EM FACHADA | C48: =Ger_Executivo!N1353 -> 1305274.1 | D48: =C48/C$51 -> 0.035355166 | E48: =C48/$E$9 -> 98.968748
B49: SERVIÇOS COMPLEMENTARES | C49: =Ger_Executivo!N1367 -> 1521120.1 | D49: =C49/C$51 -> 0.041201656 | E49: =C49/$E$9 -> 115.33467
B50: IMPREVISTOS E CONTINGÊNCIAS | C50: =Ger_Executivo!N1385 -> 635004.31 | D50: =C50/C$51 -> 0.017199976 | E50: =C50/$E$9 -> 48.147422
B51: TOTAL | C51: =SUM(C32:C50) -> 36918906 | D51: =SUM(D32:D50) -> 1 | E51: =SUM(E32:E50) -> 2799.2726
B52: CUB/SC | C52: 2965.54 | D52: 45839 | E52: =ROUNDUP(+E51/C52,2)&" CUB" -> 0,95 CUB

Sheet Comparativo
B2: ETAPA | D2: PORTO CERRO R01 | G2: PORTO CERRO R00 | J2: PORTO CERRO - PRELIMINAR
D3: VALOR | E3: VALOR / m² | G3: VALOR | H3: VALOR / m² | J3: VALOR | K3: VALOR / m²
B4: GERENCIAMENTO TÉCNICO E ADMINISTRATIVO | D4: ='Obra '!C32 -> 4533686.5 | E4: ='Obra '!E32 -> 343.75407 | G4: 4060804.3 | H4: 307.89911 | J4: 3316841.3 | K4: 251.49019 | L4: Adicção de taxas e ajuste de equipamentos
B5: MOVIMENTAÇÃO DE TERRA | D5: ='Obra '!C33 -> 201548.69 | E5: ='Obra '!E33 -> 15.281864 | G5: 201548.69 | H5: 15.281864 | J5: 202605.16 | K5: 15.361969
B6: INFRAESTRUTURA | D6: ='Obra '!C34 -> 1971424.2 | E6: ='Obra '!E34 -> 149.47771 | G6: 1992929.8 | H6: 151.10831 | J6: 1836089.2 | K6: 139.21632 | L6: Retirada ede 1 jogo de forma
B7: SUPRAESTRUTURA | D7: ='Obra '!C35 -> 6810042.5 | E7: ='Obra '!E35 -> 516.35239 | G7: 6950469.5 | H7: 526.99987 | J7: 6497994.5 | K7: 492.69222
B8: ALVENARIA C/ ALVENARIA ESTRUTURAL | D8: ='Obra '!C36 -> 1867619.9 | E8: ='Obra '!E36 -> 141.60705 | G8: 2556087.3 | H8: 193.80815 | J8: 2378567.9 | K8: 180.34824
B9: ALVENARIA | D9: ='Obra '!C37 -> 743245.34 | E9: ='Obra '!E37 -> 56.354495
B10: INSTALAÇÕES ELÉTRICAS, HIDRÁULICAS, GLP, PREVENTIVAS | D10: ='Obra '!C39 -> 3848757 | E10: ='Obra '!E39 -> 291.82121 | G10: 3848757 | H10: 291.82121 | J10: 4956478.4 | K10: 375.81108
B11: EQUIPAMENTOS E SISTEMAS ESPECIAIS | D11: ='Obra '!C40 -> 1709214.5 | E11: ='Obra '!E40 -> 129.5964 | G11: 1528823 | H11: 115.91872 | J11: 1765339.5 | K11: 133.85192 | L11: Adição de sistemas keyless, camera, som, wi-fi e aquecimento de piscina
B12: IMPERMEABILIZAÇÃO | D12: ='Obra '!C38 -> 570028.95 | E12: ='Obra '!E38 -> 43.220848 | G12: 701038.53 | H12: 53.154282 | J12: 594137.8 | K12: 45.048834 | L12: Troca de laje impermeabilizada por telhado
B13: REVESTIMENTOS INTERNOS EM PAREDE | D13: ='Obra '!C41 -> 1655202.7 | E13: ='Obra '!E41 -> 125.5011 | G13: 1484604.3 | H13: 112.56596 | J13: 2016787.3 | K13: 152.91725 | L13: Adição de azulejo em parede dos banheiros e nichos
B14: REVESTIMENTOS E ACABAMENTOS INTERNOS EM TETO | D14: ='Obra '!C42 -> 680621.57 | E14: ='Obra '!E42 -> 51.606223 | G14: 680621.57 | H14: 51.606223 | J14: 862538.2 | K14: 65.399542
B15: PISOS E PAVIMENTAÇÕES | D15: ='Obra '!C43 -> 1992159.7 | E15: ='Obra '!E43 -> 151.04993 | G15: 1983338.7 | H15: 150.3811 | J15: 2353078.9 | K15: 178.41561 | L15: Adição de piso do elevador
B16: PINTURA INTERNA | D16: ='Obra '!C44 -> 2004994 | E16: ='Obra '!E44 -> 152.02305 | G16: 2133154.1 | H16: 161.74043 | J16: 2117102.7 | K16: 160.52338 | L16: Adição de azulejo em parede dos banheiros
B17: ESQUADRIAS, VIDROS E FERRAGENS | D17: ='Obra '!C45 -> 4314922.3 | E17: ='Obra '!E45 -> 327.16689 | G17: 4204046.3 | H17: 318.76002 | J17: 3224819 | K17: 244.51286 | L17: Adição de moldura churrasqueira
B18: COBERTURA | D18: ='Obra '!C47 -> 163256.76 | E18: ='Obra '!E47 -> 12.378486 | G18: 1798.7264 | H18: 0.13638339 | J18: 31796.941 | K18: 2.4109139 | L18: Troca de laje impermeabilizada por telhado
B19: LOUÇAS E METAIS | D19: ='Obra '!C46 -> 390783.28 | E19: ='Obra '!E46 -> 29.630047 | G19: 390783.28 | H19: 29.630047 | J19: 538815.72 | K19: 40.854192
B20: REVESTIMENTOS E ACABAMENTOS DE FACHADA | D20: ='Obra '!C48 -> 1305274.1 | E20: ='Obra '!E48 -> 98.968748 | G20: 1305247 | H20: 98.966695 | J20: 2253614.2 | K20: 170.87398
B21: SERVIÇOS COMPLEMENTARES | D21: ='Obra '!C49 -> 1521120.1 | E21: ='Obra '!E49 -> 115.33467 | G21: 1521120.1 | H21: 115.33467 | J21: 1016211.9 | K21: 77.051421
B22: IMPREVISTOS E CONTINGENCIAS | D22: ='Obra '!C50 -> 635004.31 | E22: ='Obra '!E50 -> 48.147422 | G22: 629687.36 | H22: 47.744279 | K22: 0
B23: TOTAL | D23: =SUM(D4:D22) -> 36918906 | E23: =SUM(E4:E22) -> 2799.2726 | G23: 36174859 | H23: 2742.8573 | J23: 35962819 | K23: 2726.7799

Sheet Ger_Tec e Adm
G4: PROJETO: | I4: Porto Cerro | O4: REVISÃO: | P4: DATA
G5: EMPRESA: | I5: XPCon | O5: ='Obra '!D3 -> R01 - 03/09/2025 | P5: 45860
A6: Unidade Construtiva | B6: Célula Construtiva | C6: Etapa | D6: Subetapa | E6: Serviço | G6: GERENCIAMENTO EXECUTIVO
A7: 0 | B7: 0 | C7: 0 | D7: 0 | E7: 0 | G7: Atalho | H7: NIVEL | I7: Item | J7: Descrição | K7: Unidade | L7: Quant. | M7: Preço un | N7: Total | O7: Considerações | P7: Situação
A8: =IF($H8="UNIDADE CONSTRUTIVA",OFFSET(A8,-1,0)+1,LARGE(A$3:A7,1)) -> 0 | B8: =IF(H8="UNIDADE CONSTRUTIVA",0,IF(H8="CÉLULA CONSTRUTIVA",OFFSET(B8,-1,0)+1,OFFSET(B8,-1,0))) -> 1 | C8: =IF(H8="CÉLULA CONSTRUTIVA",0,IF(H8="ETAPA",OFFSET(C8,-1,0)+1,OFFSET(C8,-1,0))) -> 0 | D8: =IF(H8="ETAPA",0,IF(H8="SUBETAPA",OFFSET(D8,-1,0)+1,OFFSET(D8,-1,0))) -> 0 | E8: =IF(H8="Subetapa",0,IF(H8="serviço",OFFSET(E8,-1,0)+1,OFFSET(E8,-1,0))) -> 0 | H8: CÉLULA CONSTRUTIVA | I8: =IF(H8="Unidade Construtiva",TEXT(A8,"00"),IF(H8="Célula Construtiva",TEXT(B8,"00"),IF(H8="Etapa",CONCATENATE(TEXT(B8,"00"),".",TEXT(C8,"000")),IF(H8="Subetapa",CONCATENATE(TEXT(B8,"00"),".",TEXT(C8,"000"),".",TEXT(D8,"000")),IF(H8="Serviço",CONCATENATE(TEXT(B8,"00"),".",TEXT(C8,"000"),".",TEXT(D8,"000"),".",TEXT(E8,"000")),""))))) -> 01 | J8: SERVIÇOS TÉCNICOS | N8: =IF(H8="Serviço",M8*L8,IF(H8="CÉLULA CONSTRUTIVA",SUMIFS($N$8:$N$420,$B$8:$B$420,B8,$H$8:$H$420,"Serviço"),IF(H8="ETAPA",SUMIFS($N$8:$N$420,$B$8:$B$420,B8,$C$8:$C$420,C8,$H$8:$H$420,"Serviço"),IF(H8="SUBETAPA",SUMIFS($N$8:$N$420,$B$8:$B$420,B8,$C$8:$C$420,C8,$D$8:$D$420,D8,$H$8:$H$420,"Serviço"),0)))) -> 1970733.8 | P8: - | R8: Adicionado/alterado em reivsao
A9: =IF($H9="UNIDADE CONSTRUTIVA",OFFSET(A9,-1,0)+1,LARGE(A$3:A8,1)) -> 0 | B9: =IF(H9="UNIDADE CONSTRUTIVA",0,IF(H9="CÉLULA CONSTRUTIVA",OFFSET(B9,-1,0)+1,OFFSET(B9,-1,0))) -> 1 | C9: =IF(H9="CÉLULA CONSTRUTIVA",0,IF(H9="ETAPA",OFFSET(C9,-1,0)+1,OFFSET(C9,-1,0))) -> 1 | D9: =IF(H9="ETAPA",0,IF(H9="SUBETAPA",OFFSET(D9,-1,0)+1,OFFSET(D9,-1,0))) -> 0 | E9: =IF(H9="Subetapa",0,IF(H9="serviço",OFFSET(E9,-1,0)+1,OFFSET(E9,-1,0))) -> 0 | H9: ETAPA | I9: =IF(H9="Unidade Construtiva",TEXT(A9,"00"),IF(H9="Célula Construtiva",TEXT(B9,"00"),IF(H9="Etapa",CONCATENATE(TEXT(B9,"00"),".",TEXT(C9,"000")),IF(H9="Subetapa",CONCATENATE(TEXT(B9,"00"),".",TEXT(C9,"000"),".",TEXT(D9,"000")),IF(H9="Serviço",CONCATENATE(TEXT(B9,"00"),".",TEXT(C9,"000"),".",TEXT(D9,"000"),".",TEXT(E9,"000")),""))))) -> 01.001 | J9: ESTUDOS, PROJETOS, CONSULTORIA E ENSAIOS | N9: =IF(H9="Serviço",M9*L9,IF(H9="CÉLULA CONSTRUTIVA",SUMIFS($N$8:$N$420,$B$8:$B$420,B9,$H$8:$H$420,"Serviço"),IF(H9="ETAPA",SUMIFS($N$8:$N$420,$B$8:$B$420,B9,$C$8:$C$420,C9,$H$8:$H$420,"Serviço"),IF(H9="SUBETAPA",SUMIFS($N$8:$N$420,$B$8:$B$420,B9,$C$8:$C$420,C9,$D$8:$D$420,D9,$H$8:$H$420,"Serviço"),0)))) -> 921014.53 | P9: -
A10: =IF($H10="UNIDADE CONSTRUTIVA",OFFSET(A10,-1,0)+1,LARGE(A$3:A9,1)) -> 0 | B10: =IF(H10="UNIDADE CONSTRUTIVA",0,IF(H10="CÉLULA CONSTRUTIVA",OFFSET(B10,-1,0)+1,OFFSET(B10,-1,0))) -> 1 | C10: =IF(H10="CÉLULA CONSTRUTIVA",0,IF(H10="ETAPA",OFFSET(C10,-1,0)+1,OFFSET(C10,-1,0))) -> 1 | D10: =IF(H10="ETAPA",0,IF(H10="SUBETAPA",OFFSET(D10,-1,0)+1,OFFSET(D10,-1,0))) -> 1 | E10: =IF(H10="Subetapa",0,IF(H10="serviço",OFFSET(E10,-1,0)+1,OFFSET(E10,-1,0))) -> 0 | H10: SUBETAPA | I10: =IF(H10="Unidade Construtiva",TEXT(A10,"00"),IF(H10="Célula Construtiva",TEXT(B10,"00"),IF(H10="Etapa",CONCATENATE(TEXT(B10,"00"),".",TEXT(C10,"000")),IF(H10="Subetapa",CONCATENATE(TEXT(B10,"00"),".",TEXT(C10,"000"),".",TEXT(D10,"000")),IF(H10="Serviço",CONCATENATE(TEXT(B10,"00"),".",TEXT(C10,"000"),".",TEXT(D10,"000"),".",TEXT(E10,"000")),""))))) -> 01.001.001 | J10: Estudos | N10: =IF(H10="Serviço",M10*L10,IF(H10="CÉLULA CONSTRUTIVA",SUMIFS($N$8:$N$420,$B$8:$B$420,B10,$H$8:$H$420,"Serviço"),IF(H10="ETAPA",SUMIFS($N$8:$N$420,$B$8:$B$420,B10,$C$8:$C$420,C10,$H$8:$H$420,"Serviço"),IF(H10="SUBETAPA",SUMIFS($N$8:$N$420,$B$8:$B$420,B10,$C$8:$C$420,C10,$D$8:$D$420,D10,$H$8:$H$420,"Serviço"),0)))) -> 109972.88
A11: =IF($H11="UNIDADE CONSTRUTIVA",OFFSET(A11,-1,0)+1,LARGE(A$3:A10,1)) -> 0 | B11: =IF(H11="UNIDADE CONSTRUTIVA",0,IF(H11="CÉLULA CONSTRUTIVA",OFFSET(B11,-1,0)+1,OFFSET(B11,-1,0))) -> 1 | C11: =IF(H11="CÉLULA CONSTRUTIVA",0,IF(H11="ETAPA",OFFSET(C11,-1,0)+1,OFFSET(C11,-1,0))) -> 1 | D11: =IF(H11="ETAPA",0,IF(H11="SUBETAPA",OFFSET(D11,-1,0)+1,OFFSET(D11,-1,0))) -> 1 | E11: =IF(H11="Subetapa",0,IF(H11="serviço",OFFSET(E11,-1,0)+1,OFFSET(E11,-1,0))) -> 1 | H11: SERVIÇO | I11: =IF(H11="Unidade Construtiva",TEXT(A11,"00"),IF(H11="Célula Construtiva",TEXT(B11,"00"),IF(H11="Etapa",CONCATENATE(TEXT(B11,"00"),".",TEXT(C11,"000")),IF(H11="Subetapa",CONCATENATE(TEXT(B11,"00"),".",TEXT(C11,"000"),".",TEXT(D11,"000")),IF(H11="Serviço",CONCATENATE(TEXT(B11,"00"),".",TEXT(C11,"000"),".",TEXT(D11,"000"),".",TEXT(E11,"000")),""))))) -> 01.001.001.001 | J11: Memorial descritivo | K11: vb | L11: 1 | M11: 6512.1875 | N11: =IF(H11="Serviço",M11*L11,IF(H11="CÉLULA CONSTRUTIVA",SUMIFS($N$8:$N$420,$B$8:$B$420,B11,$H$8:$H$420,"Serviço"),IF(H11="ETAPA",SUMIFS($N$8:$N$420,$B$8:$B$420,B11,$C$8:$C$420,C11,$H$8:$H$420,"Serviço"),IF(H11="SUBETAPA",SUMIFS($N$8:$N$420,$B$8:$B$420,B11,$C$8:$C$420,C11,$D$8:$D$420,D11,$H$8:$H$420,"Serviço"),0)))) -> 6512.1875 | O11: Estimado com base em índices históricos | P11: Lançado ERP
A12: =IF($H12="UNIDADE CONSTRUTIVA",OFFSET(A12,-1,0)+1,LARGE(A$3:A11,1)) -> 0 | B12: =IF(H12="UNIDADE CONSTRUTIVA",0,IF(H12="CÉLULA CONSTRUTIVA",OFFSET(B12,-1,0)+1,OFFSET(B12,-1,0))) -> 1 | C12: =IF(H12="CÉLULA CONSTRUTIVA",0,IF(H12="ETAPA",OFFSET(C12,-1,0)+1,OFFSET(C12,-1,0))) -> 1 | D12: =IF(H12="ETAPA",0,IF(H12="SUBETAPA",OFFSET(D12,-1,0)+1,OFFSET(D12,-1,0))) -> 1 | E12: =IF(H12="Subetapa",0,IF(H12="serviço",OFFSET(E12,-1,0)+1,OFFSET(E12,-1,0))) -> 2 | H12: SERVIÇO | I12: =IF(H12="Unidade Construtiva",TEXT(A12,"00"),IF(H12="Célula Construtiva",TEXT(B12,"00"),IF(H12="Etapa",CONCATENATE(TEXT(B12,"00"),".",TEXT(C12,"000")),IF(H12="Subetapa",CONCATENATE(TEXT(B12,"00"),".",TEXT(C12,"000"),".",TEXT(D12,"000")),IF(H12="Serviço",CONCATENATE(TEXT(B12,"00"),".",TEXT(C12,"000"),".",TEXT(D12,"000"),".",TEXT(E12,"000")),""))))) -> 01.001.001.002 | J12: Levantamento Topográfico | K12: vb | L12: 1 | M12: 9550.2178 | N12: =IF(H12="Serviço",M12*L12,IF(H12="CÉLULA CONSTRUTIVA",SUMIFS($N$8:$N$420,$B$8:$B$420,B12,$H$8:$H$420,"Serviço"),IF(H12="ETAPA",SUMIFS($N$8:$N$420,$B$8:$B$420,B12,$C$8:$C$420,C12,$H$8:$H$420,"Serviço"),IF(H12="SUBETAPA",SUMIFS($N$8:$N$420,$B$8:$B$420,B12,$C$8:$C$420,C12,$D$8:$D$420,D12,$H$8:$H$420,"Serviço"),0)))) -> 9550.2178 | O12: Estimado com base em índices históricos | P12: Lançado ERP
A13: =IF($H13="UNIDADE CONSTRUTIVA",OFFSET(A13,-1,0)+1,LARGE(A$3:A12,1)) -> 0 | B13: =IF(H13="UNIDADE CONSTRUTIVA",0,IF(H13="CÉLULA CONSTRUTIVA",OFFSET(B13,-1,0)+1,OFFSET(B13,-1,0))) -> 1 | C13: =IF(H13="CÉLULA CONSTRUTIVA",0,IF(H13="ETAPA",OFFSET(C13,-1,0)+1,OFFSET(C13,-1,0))) -> 1 | D13: =IF(H13="ETAPA",0,IF(H13="SUBETAPA",OFFSET(D13,-1,0)+1,OFFSET(D13,-1,0))) -> 1 | E13: =IF(H13="Subetapa",0,IF(H13="serviço",OFFSET(E13,-1,0)+1,OFFSET(E13,-1,0))) -> 3 | H13: SERVIÇO | I13: =IF(H13="Unidade Construtiva",TEXT(A13,"00"),IF(H13="Célula Construtiva",TEXT(B13,"00"),IF(H13="Etapa",CONCATENATE(TEXT(B13,"00"),".",TEXT(C13,"000")),IF(H13="Subetapa",CONCATENATE(TEXT(B13,"00"),".",TEXT(C13,"000"),".",TEXT(D13,"000")),IF(H13="Serviço",CONCATENATE(TEXT(B13,"00"),".",TEXT(C13,"000"),".",TEXT(D13,"000"),".",TEXT(E13,"000")),""))))) -> 01.001.001.003 | J13: Estudo ambiental | K13: vb | L13: 1 | M13: 70034.931 | N13: =IF(H13="Serviço",M13*L13,IF(H13="CÉLULA CONSTRUTIVA",SUMIFS($N$8:$N$420,$B$8:$B$420,B13,$H$8:$H$420,"Serviço"),IF(H13="ETAPA",SUMIFS($N$8:$N$420,$B$8:$B$420,B13,$C$8:$C$420,C13,$H$8:$H$420,"Serviço"),IF(H13="SUBETAPA",SUMIFS($N$8:$N$420,$B$8:$B$420,B13,$C$8:$C$420,C13,$D$8:$D$420,D13,$H$8:$H$420,"Serviço"),0)))) -> 70034.931 | O13: Estimado com base em índices históricos | P13: Lançado ERP
A14: =IF($H14="UNIDADE CONSTRUTIVA",OFFSET(A14,-1,0)+1,LARGE(A$3:A13,1)) -> 0 | B14: =IF(H14="UNIDADE CONSTRUTIVA",0,IF(H14="CÉLULA CONSTRUTIVA",OFFSET(B14,-1,0)+1,OFFSET(B14,-1,0))) -> 1 | C14: =IF(H14="CÉLULA CONSTRUTIVA",0,IF(H14="ETAPA",OFFSET(C14,-1,0)+1,OFFSET(C14,-1,0))) -> 1 | D14: =IF(H14="ETAPA",0,IF(H14="SUBETAPA",OFFSET(D14,-1,0)+1,OFFSET(D14,-1,0))) -> 1 | E14: =IF(H14="Subetapa",0,IF(H14="serviço",OFFSET(E14,-1,0)+1,OFFSET(E14,-1,0))) -> 4 | H14: SERVIÇO | I14: =IF(H14="Unidade Construtiva",TEXT(A14,"00"),IF(H14="Célula Construtiva",TEXT(B14,"00"),IF(H14="Etapa",CONCATENATE(TEXT(B14,"00"),".",TEXT(C14,"000")),IF(H14="Subetapa",CONCATENATE(TEXT(B14,"00"),".",TEXT(C14,"000"),".",TEXT(D14,"000")),IF(H14="Serviço",CONCATENATE(TEXT(B14,"00"),".",TEXT(C14,"000"),".",TEXT(D14,"000"),".",TEXT(E14,"000")),""))))) -> 01.001.001.004 | J14: Sondagem do terreno | K14: vb | L14: 1 | M14: 23875.545 | N14: =IF(H14="Serviço",M14*L14,IF(H14="CÉLULA CONSTRUTIVA",SUMIFS($N$8:$N$420,$B$8:$B$420,B14,$H$8:$H$420,"Serviço"),IF(H14="ETAPA",SUMIFS($N$8:$N$420,$B$8:$B$420,B14,$C$8:$C$420,C14,$H$8:$H$420,"Serviço"),IF(H14="SUBETAPA",SUMIFS($N$8:$N$420,$B$8:$B$420,B14,$C$8:$C$420,C14,$D$8:$D$420,D14,$H$8:$H$420,"Serviço"),0)))) -> 23875.545 | O14: Estimado com base em índices históricos | P14: Lançado ERP
A15: =IF($H15="UNIDADE CONSTRUTIVA",OFFSET(A15,-1,0)+1,LARGE(A$3:A14,1)) -> 0 | B15: =IF(H15="UNIDADE CONSTRUTIVA",0,IF(H15="CÉLULA CONSTRUTIVA",OFFSET(B15,-1,0)+1,OFFSET(B15,-1,0))) -> 1 | C15: =IF(H15="CÉLULA CONSTRUTIVA",0,IF(H15="ETAPA",OFFSET(C15,-1,0)+1,OFFSET(C15,-1,0))) -> 1 | D15: =IF(H15="ETAPA",0,IF(H15="SUBETAPA",OFFSET(D15,-1,0)+1,OFFSET(D15,-1,0))) -> 2 | E15: =IF(H15="Subetapa",0,IF(H15="serviço",OFFSET(E15,-1,0)+1,OFFSET(E15,-1,0))) -> 0 | H15: SUBETAPA | I15: =IF(H15="Unidade Construtiva",TEXT(A15,"00"),IF(H15="Célula Construtiva",TEXT(B15,"00"),IF(H15="Etapa",CONCATENATE(TEXT(B15,"00"),".",TEXT(C15,"000")),IF(H15="Subetapa",CONCATENATE(TEXT(B15,"00"),".",TEXT(C15,"000"),".",TEXT(D15,"000")),IF(H15="Serviço",CONCATENATE(TEXT(B15,"00"),".",TEXT(C15,"000"),".",TEXT(D15,"000"),".",TEXT(E15,"000")),""))))) -> 01.001.002 | J15: Projetos | N15: =IF(H15="Serviço",M15*L15,IF(H15="CÉLULA CONSTRUTIVA",SUMIFS($N$8:$N$420,$B$8:$B$420,B15,$H$8:$H$420,"Serviço"),IF(H15="ETAPA",SUMIFS($N$8:$N$420,$B$8:$B$420,B15,$C$8:$C$420,C15,$H$8:$H$420,"Serviço"),IF(H15="SUBETAPA",SUMIFS($N$8:$N$420,$B$8:$B$420,B15,$C$8:$C$420,C15,$D$8:$D$420,D15,$H$8:$H$420,"Serviço"),0)))) -> 556996.27
A16: =IF($H16="UNIDADE CONSTRUTIVA",OFFSET(A16,-1,0)+1,LARGE(A$3:A15,1)) -> 0 | B16: =IF(H16="UNIDADE CONSTRUTIVA",0,IF(H16="CÉLULA CONSTRUTIVA",OFFSET(B16,-1,0)+1,OFFSET(B16,-1,0))) -> 1 | C16: =IF(H16="CÉLULA CONSTRUTIVA",0,IF(H16="ETAPA",OFFSET(C16,-1,0)+1,OFFSET(C16,-1,0))) -> 1 | D16: =IF(H16="ETAPA",0,IF(H16="SUBETAPA",OFFSET(D16,-1,0)+1,OFFSET(D16,-1,0))) -> 2 | E16: =IF(H16="Subetapa",0,IF(H16="serviço",OFFSET(E16,-1,0)+1,OFFSET(E16,-1,0))) -> 1 | H16: SERVIÇO | I16: =IF(H16="Unidade Construtiva",TEXT(A16,"00"),IF(H16="Célula Construtiva",TEXT(B16,"00"),IF(H16="Etapa",CONCATENATE(TEXT(B16,"00"),".",TEXT(C16,"000")),IF(H16="Subetapa",CONCATENATE(TEXT(B16,"00"),".",TEXT(C16,"000"),".",TEXT(D16,"000")),IF(H16="Serviço",CONCATENATE(TEXT(B16,"00"),".",TEXT(C16,"000"),".",TEXT(D16,"000"),".",TEXT(E16,"000")),""))))) -> 01.001.002.001 | J16: Legalização de incorporação | K16: vb | L16: 1 | M16: 19100.436 | N16: =IF(H16="Serviço",M16*L16,IF(H16="CÉLULA CONSTRUTIVA",SUMIFS($N$8:$N$420,$B$8:$B$420,B16,$H$8:$H$420,"Serviço"),IF(H16="ETAPA",SUMIFS($N$8:$N$420,$B$8:$B$420,B16,$C$8:$C$420,C16,$H$8:$H$420,"Serviço"),IF(H16="SUBETAPA",SUMIFS($N$8:$N$420,$B$8:$B$420,B16,$C$8:$C$420,C16,$D$8:$D$420,D16,$H$8:$H$420,"Serviço"),0)))) -> 19100.436 | O16: Estimado com base em índices históricos | P16: Finalizado
A17: =IF($H17="UNIDADE CONSTRUTIVA",OFFSET(A17,-1,0)+1,LARGE(A$3:A16,1)) -> 0 | B17: =IF(H17="UNIDADE CONSTRUTIVA",0,IF(H17="CÉLULA CONSTRUTIVA",OFFSET(B17,-1,0)+1,OFFSET(B17,-1,0))) -> 1 | C17: =IF(H17="CÉLULA CONSTRUTIVA",0,IF(H17="ETAPA",OFFSET(C17,-1,0)+1,OFFSET(C17,-1,0))) -> 1 | D17: =IF(H17="ETAPA",0,IF(H17="SUBETAPA",OFFSET(D17,-1,0)+1,OFFSET(D17,-1,0))) -> 2 | E17: =IF(H17="Subetapa",0,IF(H17="serviço",OFFSET(E17,-1,0)+1,OFFSET(E17,-1,0))) -> 2 | H17: SERVIÇO | I17: =IF(H17="Unidade Construtiva",TEXT(A17,"00"),IF(H17="Célula Construtiva",TEXT(B17,"00"),IF(H17="Etapa",CONCATENATE(TEXT(B17,"00"),".",TEXT(C17,"000")),IF(H17="Subetapa",CONCATENATE(TEXT(B17,"00"),".",TEXT(C17,"000"),".",TEXT(D17,"000")),IF(H17="Serviço",CONCATENATE(TEXT(B17,"00"),".",TEXT(C17,"000"),".",TEXT(D17,"000"),".",TEXT(E17,"000")),""))))) -> 01.001.002.002 | J17: Projeto Arquitetônico legal | K17: vb | L17: 1 | M17: 85156.109 | N17: =IF(H17="Serviço",M17*L17,IF(H17="CÉLULA CONSTRUTIVA",SUMIFS($N$8:$N$420,$B$8:$B$420,B17,$H$8:$H$420,"Serviço"),IF(H17="ETAPA",SUMIFS($N$8:$N$420,$B$8:$B$420,B17,$C$8:$C$420,C17,$H$8:$H$420,"Serviço"),IF(H17="SUBETAPA",SUMIFS($N$8:$N$420,$B$8:$B$420,B17,$C$8:$C$420,C17,$D$8:$D$420,D17,$H$8:$H$420,"Serviço"),0)))) -> 85156.109 | O17: Estimado com base em índices históricos | P17: Finalizado
A18: =IF($H18="UNIDADE CONSTRUTIVA",OFFSET(A18,-1,0)+1,LARGE(A$3:A17,1)) -> 0 | B18: =IF(H18="UNIDADE CONSTRUTIVA",0,IF(H18="CÉLULA CONSTRUTIVA",OFFSET(B18,-1,0)+1,OFFSET(B18,-1,0))) -> 1 | C18: =IF(H18="CÉLULA CONSTRUTIVA",0,IF(H18="ETAPA",OFFSET(C18,-1,0)+1,OFFSET(C18,-1,0))) -> 1 | D18: =IF(H18="ETAPA",0,IF(H18="SUBETAPA",OFFSET(D18,-1,0)+1,OFFSET(D18,-1,0))) -> 2 | E18: =IF(H18="Subetapa",0,IF(H18="serviço",OFFSET(E18,-1,0)+1,OFFSET(E18,-1,0))) -> 3 | H18: SERVIÇO | I18: =IF(H18="Unidade Construtiva",TEXT(A18,"00"),IF(H18="Célula Construtiva",TEXT(B18,"00"),IF(H18="Etapa",CONCATENATE(TEXT(B18,"00"),".",TEXT(C18,"000")),IF(H18="Subetapa",CONCATENATE(TEXT(B18,"00"),".",TEXT(C18,"000"),".",TEXT(D18,"000")),IF(H18="Serviço",CONCATENATE(TEXT(B18,"00"),".",TEXT(C18,"000"),".",TEXT(D18,"000"),".",TEXT(E18,"000")),""))))) -> 01.001.002.003 | J18: Projeto Arquitetônico Executivo | K18: vb | L18: 1 | M18: 85156.109 | N18: =IF(H18="Serviço",M18*L18,IF(H18="CÉLULA CONSTRUTIVA",SUMIFS($N$8:$N$420,$B$8:$B$420,B18,$H$8:$H$420,"Serviço"),IF(H18="ETAPA",SUMIFS($N$8:$N$420,$B$8:$B$420,B18,$C$8:$C$420,C18,$H$8:$H$420,"Serviço"),IF(H18="SUBETAPA",SUMIFS($N$8:$N$420,$B$8:$B$420,B18,$C$8:$C$420,C18,$D$8:$D$420,D18,$H$8:$H$420,"Serviço"),0)))) -> 85156.109 | O18: Estimado com base em índices históricos | P18: Finalizado
A19: =IF($H19="UNIDADE CONSTRUTIVA",OFFSET(A19,-1,0)+1,LARGE(A$3:A18,1)) -> 0 | B19: =IF(H19="UNIDADE CONSTRUTIVA",0,IF(H19="CÉLULA CONSTRUTIVA",OFFSET(B19,-1,0)+1,OFFSET(B19,-1,0))) -> 1 | C19: =IF(H19="CÉLULA CONSTRUTIVA",0,IF(H19="ETAPA",OFFSET(C19,-1,0)+1,OFFSET(C19,-1,0))) -> 1 | D19: =IF(H19="ETAPA",0,IF(H19="SUBETAPA",OFFSET(D19,-1,0)+1,OFFSET(D19,-1,0))) -> 2 | E19: =IF(H19="Subetapa",0,IF(H19="serviço",OFFSET(E19,-1,0)+1,OFFSET(E19,-1,0))) -> 4 | H19: SERVIÇO | I19: =IF(H19="Unidade Construtiva",TEXT(A19,"00"),IF(H19="Célula Construtiva",TEXT(B19,"00"),IF(H19="Etapa",CONCATENATE(TEXT(B19,"00"),".",TEXT(C19,"000")),IF(H19="Subetapa",CONCATENATE(TEXT(B19,"00"),".",TEXT(C19,"000"),".",TEXT(D19,"000")),IF(H19="Serviço",CONCATENATE(TEXT(B19,"00"),".",TEXT(C19,"000"),".",TEXT(D19,"000"),".",TEXT(E19,"000")),""))))) -> 01.001.002.004 | J19: Projeto de Fundação | K19: vb | L19: 1 | M19: 27058.951 | N19: =IF(H19="Serviço",M19*L19,IF(H19="CÉLULA CONSTRUTIVA",SUMIFS($N$8:$N$420,$B$8:$B$420,B19,$H$8:$H$420,"Serviço"),IF(H19="ETAPA",SUMIFS($N$8:$N$420,$B$8:$B$420,B19,$C$8:$C$420,C19,$H$8:$H$420,"Serviço"),IF(H19="SUBETAPA",SUMIFS($N$8:$N$420,$B$8:$B$420,B19,$C$8:$C$420,C19,$D$8:$D$420,D19,$H$8:$H$420,"Serviço"),0)))) -> 27058.951 | O19: Estimado com base em índices históricos | P19: Finalizado
A20: =IF($H20="UNIDADE CONSTRUTIVA",OFFSET(A20,-1,0)+1,LARGE(A$3:A19,1)) -> 0 | B20: =IF(H20="UNIDADE CONSTRUTIVA",0,IF(H20="CÉLULA CONSTRUTIVA",OFFSET(B20,-1,0)+1,OFFSET(B20,-1,0))) -> 1 | C20: =IF(H20="CÉLULA CONSTRUTIVA",0,IF(H20="ETAPA",OFFSET(C20,-1,0)+1,OFFSET(C20,-1,0))) -> 1 | D20: =IF(H20="ETAPA",0,IF(H20="SUBETAPA",OFFSET(D20,-1,0)+1,OFFSET(D20,-1,0))) -> 2 | E20: =IF(H20="Subetapa",0,IF(H20="serviço",OFFSET(E20,-1,0)+1,OFFSET(E20,-1,0))) -> 5 | H20: SERVIÇO | I20: =IF(H20="Unidade Construtiva",TEXT(A20,"00"),IF(H20="Célula Construtiva",TEXT(B20,"00"),IF(H20="Etapa",CONCATENATE(TEXT(B20,"00"),".",TEXT(C20,"000")),IF(H20="Subetapa",CONCATENATE(TEXT(B20,"00"),".",TEXT(C20,"000"),".",TEXT(D20,"000")),IF(H20="Serviço",CONCATENATE(TEXT(B20,"00"),".",TEXT(C20,"000"),".",TEXT(D20,"000"),".",TEXT(E20,"000")),""))))) -> 01.001.002.005 | J20: Projeto Estrutura | K20: vb | L20: 1 | M20: 119696.06 | N20: =IF(H20="Serviço",M20*L20,IF(H20="CÉLULA CONSTRUTIVA",SUMIFS($N$8:$N$420,$B$8:$B$420,B20,$H$8:$H$420,"Serviço"),IF(H20="ETAPA",SUMIFS($N$8:$N$420,$B$8:$B$420,B20,$C$8:$C$420,C20,$H$8:$H$420,"Serviço"),IF(H20="SUBETAPA",SUMIFS($N$8:$N$420,$B$8:$B$420,B20,$C$8:$C$420,C20,$D$8:$D$420,D20,$H$8:$H$420,"Serviço"),0)))) -> 119696.06 | O20: Estimado com base em índices históricos | P20: Finalizado
A21: =IF($H21="UNIDADE CONSTRUTIVA",OFFSET(A21,-1,0)+1,LARGE(A$3:A20,1)) -> 0 | B21: =IF(H21="UNIDADE CONSTRUTIVA",0,IF(H21="CÉLULA CONSTRUTIVA",OFFSET(B21,-1,0)+1,OFFSET(B21,-1,0))) -> 1 | C21: =IF(H21="CÉLULA CONSTRUTIVA",0,IF(H21="ETAPA",OFFSET(C21,-1,0)+1,OFFSET(C21,-1,0))) -> 1 | D21: =IF(H21="ETAPA",0,IF(H21="SUBETAPA",OFFSET(D21,-1,0)+1,OFFSET(D21,-1,0))) -> 2 | E21: =IF(H21="Subetapa",0,IF(H21="serviço",OFFSET(E21,-1,0)+1,OFFSET(E21,-1,0))) -> 6 | H21: SERVIÇO | I21: =IF(H21="Unidade Construtiva",TEXT(A21,"00"),IF(H21="Célula Construtiva",TEXT(B21,"00"),IF(H21="Etapa",CONCATENATE(TEXT(B21,"00"),".",TEXT(C21,"000")),IF(H21="Subetapa",CONCATENATE(TEXT(B21,"00"),".",TEXT(C21,"000"),".",TEXT(D21,"000")),IF(H21="Serviço",CONCATENATE(TEXT(B21,"00"),".",TEXT(C21,"000"),".",TEXT(D21,"000"),".",TEXT(E21,"000")),""))))) -> 01.001.002.006 | J21: Projeto elétrico/comunicação/telefonia/luminotécnico | K21: vb | L21: 1 | M21: 78311.786 | N21: =IF(H21="Serviço",M21*L21,IF(H21="CÉLULA CONSTRUTIVA",SUMIFS($N$8:$N$420,$B$8:$B$420,B21,$H$8:$H$420,"Serviço"),IF(H21="ETAPA",SUMIFS($N$8:$N$420,$B$8:$B$420,B21,$C$8:$C$420,C21,$H$8:$H$420,"Serviço"),IF(H21="SUBETAPA",SUMIFS($N$8:$N$420,$B$8:$B$420,B21,$C$8:$C$420,C21,$D$8:$D$420,D21,$H$8:$H$420,"Serviço"),0)))) -> 78311.786 | O21: Estimado com base em índices históricos | P21: Finalizado
A22: =IF($H22="UNIDADE CONSTRUTIVA",OFFSET(A22,-1,0)+1,LARGE(A$3:A21,1)) -> 0 | B22: =IF(H22="UNIDADE CONSTRUTIVA",0,IF(H22="CÉLULA CONSTRUTIVA",OFFSET(B22,-1,0)+1,OFFSET(B22,-1,0))) -> 1 | C22: =IF(H22="CÉLULA CONSTRUTIVA",0,IF(H22="ETAPA",OFFSET(C22,-1,0)+1,OFFSET(C22,-1,0))) -> 1 | D22: =IF(H22="ETAPA",0,IF(H22="SUBETAPA",OFFSET(D22,-1,0)+1,OFFSET(D22,-1,0))) -> 2 | E22: =IF(H22="Subetapa",0,IF(H22="serviço",OFFSET(E22,-1,0)+1,OFFSET(E22,-1,0))) -> 7 | H22: SERVIÇO | I22: =IF(H22="Unidade Construtiva",TEXT(A22,"00"),IF(H22="Célula Construtiva",TEXT(B22,"00"),IF(H22="Etapa",CONCATENATE(TEXT(B22,"00"),".",TEXT(C22,"000")),IF(H22="Subetapa",CONCATENATE(TEXT(B22,"00"),".",TEXT(C22,"000"),".",TEXT(D22,"000")),IF(H22="Serviço",CONCATENATE(TEXT(B22,"00"),".",TEXT(C22,"000"),".",TEXT(D22,"000"),".",TEXT(E22,"000")),""))))) -> 01.001.002.007 | J22: Projeto hidrossanitário/drenagem/pluvial | K22: vb | L22: 1 | M22: 50329.648 | N22: =IF(H22="Serviço",M22*L22,IF(H22="CÉLULA CONSTRUTIVA",SUMIFS($N$8:$N$420,$B$8:$B$420,B22,$H$8:$H$420,"Serviço"),IF(H22="ETAPA",SUMIFS($N$8:$N$420,$B$8:$B$420,B22,$C$8:$C$420,C22,$H$8:$H$420,"Serviço"),IF(H22="SUBETAPA",SUMIFS($N$8:$N$420,$B$8:$B$420,B22,$C$8:$C$420,C22,$D$8:$D$420,D22,$H$8:$H$420,"Serviço"),0)))) -> 50329.648 | O22: Estimado com base em índices históricos | P22: Finalizado
A23: =IF($H23="UNIDADE CONSTRUTIVA",OFFSET(A23,-1,0)+1,LARGE(A$3:A22,1)) -> 0 | B23: =IF(H23="UNIDADE CONSTRUTIVA",0,IF(H23="CÉLULA CONSTRUTIVA",OFFSET(B23,-1,0)+1,OFFSET(B23,-1,0))) -> 1 | C23: =IF(H23="CÉLULA CONSTRUTIVA",0,IF(H23="ETAPA",OFFSET(C23,-1,0)+1,OFFSET(C23,-1,0))) -> 1 | D23: =IF(H23="ETAPA",0,IF(H23="SUBETAPA",OFFSET(D23,-1,0)+1,OFFSET(D23,-1,0))) -> 2 | E23: =IF(H23="Subetapa",0,IF(H23="serviço",OFFSET(E23,-1,0)+1,OFFSET(E23,-1,0))) -> 8 | H23: SERVIÇO | I23: =IF(H23="Unidade Construtiva",TEXT(A23,"00"),IF(H23="Célula Construtiva",TEXT(B23,"00"),IF(H23="Etapa",CONCATENATE(TEXT(B23,"00"),".",TEXT(C23,"000")),IF(H23="Subetapa",CONCATENATE(TEXT(B23,"00"),".",TEXT(C23,"000"),".",TEXT(D23,"000")),IF(H23="Serviço",CONCATENATE(TEXT(B23,"00"),".",TEXT(C23,"000"),".",TEXT(D23,"000"),".",TEXT(E23,"000")),""))))) -> 01.001.002.008 | J23: Projeto preventivo (PPCI - Plano de Prevenção e Proteção Contra Incêndios) | K23: vb | L23: 1 | M23: 46859.736 | N23: =IF(H23="Serviço",M23*L23,IF(H23="CÉLULA CONSTRUTIVA",SUMIFS($N$8:$N$420,$B$8:$B$420,B23,$H$8:$H$420,"Serviço"),IF(H23="ETAPA",SUMIFS($N$8:$N$420,$B$8:$B$420,B23,$C$8:$C$420,C23,$H$8:$H$420,"Serviço"),IF(H23="SUBETAPA",SUMIFS($N$8:$N$420,$B$8:$B$420,B23,$C$8:$C$420,C23,$D$8:$D$420,D23,$H$8:$H$420,"Serviço"),0)))) -> 46859.736 | O23: Estimado com base em índices históricos | P23: Finalizado
A24: =IF($H24="UNIDADE CONSTRUTIVA",OFFSET(A24,-1,0)+1,LARGE(A$3:A23,1)) -> 0 | B24: =IF(H24="UNIDADE CONSTRUTIVA",0,IF(H24="CÉLULA CONSTRUTIVA",OFFSET(B24,-1,0)+1,OFFSET(B24,-1,0))) -> 1 | C24: =IF(H24="CÉLULA CONSTRUTIVA",0,IF(H24="ETAPA",OFFSET(C24,-1,0)+1,OFFSET(C24,-1,0))) -> 1 | D24: =IF(H24="ETAPA",0,IF(H24="SUBETAPA",OFFSET(D24,-1,0)+1,OFFSET(D24,-1,0))) -> 2 | E24: =IF(H24="Subetapa",0,IF(H24="serviço",OFFSET(E24,-1,0)+1,OFFSET(E24,-1,0))) -> 9 | H24: SERVIÇO | I24: =IF(H24="Unidade Construtiva",TEXT(A24,"00"),IF(H24="Célula Construtiva",TEXT(B24,"00"),IF(H24="Etapa",CONCATENATE(TEXT(B24,"00"),".",TEXT(C24,"000")),IF(H24="Subetapa",CONCATENATE(TEXT(B24,"00"),".",TEXT(C24,"000"),".",TEXT(D24,"000")),IF(H24="Serviço",CONCATENATE(TEXT(B24,"00"),".",TEXT(C24,"000"),".",TEXT(D24,"000"),".",TEXT(E24,"000")),""))))) -> 01.001.002.009 | J24: Projeto de climatização/exaustão | K24: vb | L24: 1 | M24: 15092.528 | N24: =IF(H24="Serviço",M24*L24,IF(H24="CÉLULA CONSTRUTIVA",SUMIFS($N$8:$N$420,$B$8:$B$420,B24,$H$8:$H$420,"Serviço"),IF(H24="ETAPA",SUMIFS($N$8:$N$420,$B$8:$B$420,B24,$C$8:$C$420,C24,$H$8:$H$420,"Serviço"),IF(H24="SUBETAPA",SUMIFS($N$8:$N$420,$B$8:$B$420,B24,$C$8:$C$420,C24,$D$8:$D$420,D24,$H$8:$H$420,"Serviço"),0)))) -> 15092.528 | O24: Estimado com base em índices históricos | P24: Finalizado
A25: =IF($H25="UNIDADE CONSTRUTIVA",OFFSET(A25,-1,0)+1,LARGE(A$3:A24,1)) -> 0 | B25: =IF(H25="UNIDADE CONSTRUTIVA",0,IF(H25="CÉLULA CONSTRUTIVA",OFFSET(B25,-1,0)+1,OFFSET(B25,-1,0))) -> 1 | C25: =IF(H25="CÉLULA CONSTRUTIVA",0,IF(H25="ETAPA",OFFSET(C25,-1,0)+1,OFFSET(C25,-1,0))) -> 1 | D25: =IF(H25="ETAPA",0,IF(H25="SUBETAPA",OFFSET(D25,-1,0)+1,OFFSET(D25,-1,0))) -> 2 | E25: =IF(H25="Subetapa",0,IF(H25="serviço",OFFSET(E25,-1,0)+1,OFFSET(E25,-1,0))) -> 10 | H25: SERVIÇO | I25: =IF(H25="Unidade Construtiva",TEXT(A25,"00"),IF(H25="Célula Construtiva",TEXT(B25,"00"),IF(H25="Etapa",CONCATENATE(TEXT(B25,"00"),".",TEXT(C25,"000")),IF(H25="Subetapa",CONCATENATE(TEXT(B25,"00"),".",TEXT(C25,"000"),".",TEXT(D25,"000")),IF(H25="Serviço",CONCATENATE(TEXT(B25,"00"),".",TEXT(C25,"000"),".",TEXT(D25,"000"),".",TEXT(E25,"000")),""))))) -> 01.001.002.010 | J25: Projeto de Segurança - Furações | K25: vb | L25: 1 | M25: 15092.528 | N25: =IF(H25="Serviço",M25*L25,IF(H25="CÉLULA CONSTRUTIVA",SUMIFS($N$8:$N$420,$B$8:$B$420,B25,$H$8:$H$420,"Serviço"),IF(H25="ETAPA",SUMIFS($N$8:$N$420,$B$8:$B$420,B25,$C$8:$C$420,C25,$H$8:$H$420,"Serviço"),IF(H25="SUBETAPA",SUMIFS($N$8:$N$420,$B$8:$B$420,B25,$C$8:$C$420,C25,$D$8:$D$420,D25,$H$8:$H$420,"Serviço"),0)))) -> 15092.528 | O25: Estimado com base em índices históricos | P25: Finalizado
A26: =IF($H26="UNIDADE CONSTRUTIVA",OFFSET(A26,-1,0)+1,LARGE(A$3:A25,1)) -> 0 | B26: =IF(H26="UNIDADE CONSTRUTIVA",0,IF(H26="CÉLULA CONSTRUTIVA",OFFSET(B26,-1,0)+1,OFFSET(B26,-1,0))) -> 1 | C26: =IF(H26="CÉLULA CONSTRUTIVA",0,IF(H26="ETAPA",OFFSET(C26,-1,0)+1,OFFSET(C26,-1,0))) -> 1 | D26: =IF(H26="ETAPA",0,IF(H26="SUBETAPA",OFFSET(D26,-1,0)+1,OFFSET(D26,-1,0))) -> 2 | E26: =IF(H26="Subetapa",0,IF(H26="serviço",OFFSET(E26,-1,0)+1,OFFSET(E26,-1,0))) -> 11 | H26: SERVIÇO | I26: =IF(H26="Unidade Construtiva",TEXT(A26,"00"),IF(H26="Célula Construtiva",TEXT(B26,"00"),IF(H26="Etapa",CONCATENATE(TEXT(B26,"00"),".",TEXT(C26,"000")),IF(H26="Subetapa",CONCATENATE(TEXT(B26,"00"),".",TEXT(C26,"000"),".",TEXT(D26,"000")),IF(H26="Serviço",CONCATENATE(TEXT(B26,"00"),".",TEXT(C26,"000"),".",TEXT(D26,"000"),".",TEXT(E26,"000")),""))))) -> 01.001.002.011 | J26: Projeto de Impermeabilização | K26: vb | L26: 1 | M26: 15142.38 | N26: =IF(H26="Serviço",M26*L26,IF(H26="CÉLULA CONSTRUTIVA",SUMIFS($N$8:$N$420,$B$8:$B$420,B26,$H$8:$H$420,"Serviço"),IF(H26="ETAPA",SUMIFS($N$8:$N$420,$B$8:$B$420,B26,$C$8:$C$420,C26,$H$8:$H$420,"Serviço"),IF(H26="SUBETAPA",SUMIFS($N$8:$N$420,$B$8:$B$420,B26,$C$8:$C$420,C26,$D$8:$D$420,D26,$H$8:$H$420,"Serviço"),0)))) -> 15142.38 | O26: Estimado com base em índices históricos | P26: Finalizado
A27: =IF($H27="UNIDADE CONSTRUTIVA",OFFSET(A27,-1,0)+1,LARGE(A$3:A26,1)) -> 0 | B27: =IF(H27="UNIDADE CONSTRUTIVA",0,IF(H27="CÉLULA CONSTRUTIVA",OFFSET(B27,-1,0)+1,OFFSET(B27,-1,0))) -> 1 | C27: =IF(H27="CÉLULA CONSTRUTIVA",0,IF(H27="ETAPA",OFFSET(C27,-1,0)+1,OFFSET(C27,-1,0))) -> 1 | D27: =IF(H27="ETAPA",0,IF(H27="SUBETAPA",OFFSET(D27,-1,0)+1,OFFSET(D27,-1,0))) -> 3 | E27: =IF(H27="Subetapa",0,IF(H27="serviço",OFFSET(E27,-1,0)+1,OFFSET(E27,-1,0))) -> 0 | H27: SUBETAPA | I27: =IF(H27="Unidade Construtiva",TEXT(A27,"00"),IF(H27="Célula Construtiva",TEXT(B27,"00"),IF(H27="Etapa",CONCATENATE(TEXT(B27,"00"),".",TEXT(C27,"000")),IF(H27="Subetapa",CONCATENATE(TEXT(B27,"00"),".",TEXT(C27,"000"),".",TEXT(D27,"000")),IF(H27="Serviço",CONCATENATE(TEXT(B27,"00"),".",TEXT(C27,"000"),".",TEXT(D27,"000"),".",TEXT(E27,"000")),""))))) -> 01.001.003 | J27: Consultorias | N27: =IF(H27="Serviço",M27*L27,IF(H27="CÉLULA CONSTRUTIVA",SUMIFS($N$8:$N$420,$B$8:$B$420,B27,$H$8:$H$420,"Serviço"),IF(H27="ETAPA",SUMIFS($N$8:$N$420,$B$8:$B$420,B27,$C$8:$C$420,C27,$H$8:$H$420,"Serviço"),IF(H27="SUBETAPA",SUMIFS($N$8:$N$420,$B$8:$B$420,B27,$C$8:$C$420,C27,$D$8:$D$420,D27,$H$8:$H$420,"Serviço"),0)))) -> 76500
A28: =IF($H28="UNIDADE CONSTRUTIVA",OFFSET(A28,-1,0)+1,LARGE(A$3:A27,1)) -> 0 | B28: =IF(H28="UNIDADE CONSTRUTIVA",0,IF(H28="CÉLULA CONSTRUTIVA",OFFSET(B28,-1,0)+1,OFFSET(B28,-1,0))) -> 1 | C28: =IF(H28="CÉLULA CONSTRUTIVA",0,IF(H28="ETAPA",OFFSET(C28,-1,0)+1,OFFSET(C28,-1,0))) -> 1 | D28: =IF(H28="ETAPA",0,IF(H28="SUBETAPA",OFFSET(D28,-1,0)+1,OFFSET(D28,-1,0))) -> 3 | E28: =IF(H28="Subetapa",0,IF(H28="serviço",OFFSET(E28,-1,0)+1,OFFSET(E28,-1,0))) -> 1 | H28: SERVIÇO | I28: =IF(H28="Unidade Construtiva",TEXT(A28,"00"),IF(H28="Célula Construtiva",TEXT(B28,"00"),IF(H28="Etapa",CONCATENATE(TEXT(B28,"00"),".",TEXT(C28,"000")),IF(H28="Subetapa",CONCATENATE(TEXT(B28,"00"),".",TEXT(C28,"000"),".",TEXT(D28,"000")),IF(H28="Serviço",CONCATENATE(TEXT(B28,"00"),".",TEXT(C28,"000"),".",TEXT(D28,"000"),".",TEXT(E28,"000")),""))))) -> 01.001.003.001 | J28: Orçamento e planejamento | K28: vb | L28: 1 | M28: 22500 | N28: =IF(H28="Serviço",M28*L28,IF(H28="CÉLULA CONSTRUTIVA",SUMIFS($N$8:$N$420,$B$8:$B$420,B28,$H$8:$H$420,"Serviço"),IF(H28="ETAPA",SUMIFS($N$8:$N$420,$B$8:$B$420,B28,$C$8:$C$420,C28,$H$8:$H$420,"Serviço"),IF(H28="SUBETAPA",SUMIFS($N$8:$N$420,$B$8:$B$420,B28,$C$8:$C$420,C28,$D$8:$D$420,D28,$H$8:$H$420,"Serviço"),0)))) -> 22500 | O28: Custo de contratação Cartesian | P28: Finalizado
A29: =IF($H29="UNIDADE CONSTRUTIVA",OFFSET(A29,-1,0)+1,LARGE(A$3:A28,1)) -> 0 | B29: =IF(H29="UNIDADE CONSTRUTIVA",0,IF(H29="CÉLULA CONSTRUTIVA",OFFSET(B29,-1,0)+1,OFFSET(B29,-1,0))) -> 1 | C29: =IF(H29="CÉLULA CONSTRUTIVA",0,IF(H29="ETAPA",OFFSET(C29,-1,0)+1,OFFSET(C29,-1,0))) -> 1 | D29: =IF(H29="ETAPA",0,IF(H29="SUBETAPA",OFFSET(D29,-1,0)+1,OFFSET(D29,-1,0))) -> 3 | E29: =IF(H29="Subetapa",0,IF(H29="serviço",OFFSET(E29,-1,0)+1,OFFSET(E29,-1,0))) -> 2 | H29: SERVIÇO | I29: =IF(H29="Unidade Construtiva",TEXT(A29,"00"),IF(H29="Célula Construtiva",TEXT(B29,"00"),IF(H29="Etapa",CONCATENATE(TEXT(B29,"00"),".",TEXT(C29,"000")),IF(H29="Subetapa",CONCATENATE(TEXT(B29,"00"),".",TEXT(C29,"000"),".",TEXT(D29,"000")),IF(H29="Serviço",CONCATENATE(TEXT(B29,"00"),".",TEXT(C29,"000"),".",TEXT(D29,"000"),".",TEXT(E29,"000")),""))))) -> 01.001.003.002 | J29: Prevision | K29: mês | L29: 36 | M29: 1500 | N29: =IF(H29="Serviço",M29*L29,IF(H29="CÉLULA CONSTRUTIVA",SUMIFS($N$8:$N$420,$B$8:$B$420,B29,$H$8:$H$420,"Serviço"),IF(H29="ETAPA",SUMIFS($N$8:$N$420,$B$8:$B$420,B29,$C$8:$C$420,C29,$H$8:$H$420,"Serviço"),IF(H29="SUBETAPA",SUMIFS($N$8:$N$420,$B$8:$B$420,B29,$C$8:$C$420,C29,$D$8:$D$420,D29,$H$8:$H$420,"Serviço"),0)))) -> 54000 | O29: Fornecido pelo whatsapp | P29: Finalizado
A30: =IF($H30="UNIDADE CONSTRUTIVA",OFFSET(A30,-1,0)+1,LARGE(A$3:A28,1)) -> 0 | B30: =IF(H30="UNIDADE CONSTRUTIVA",0,IF(H30="CÉLULA CONSTRUTIVA",OFFSET(B30,-1,0)+1,OFFSET(B30,-1,0))) -> 1 | C30: =IF(H30="CÉLULA CONSTRUTIVA",0,IF(H30="ETAPA",OFFSET(C30,-1,0)+1,OFFSET(C30,-1,0))) -> 1 | D30: =IF(H30="ETAPA",0,IF(H30="SUBETAPA",OFFSET(D30,-1,0)+1,OFFSET(D30,-1,0))) -> 4 | E30: =IF(H30="Subetapa",0,IF(H30="serviço",OFFSET(E30,-1,0)+1,OFFSET(E30,-1,0))) -> 0 | H30: SUBETAPA | I30: =IF(H30="Unidade Construtiva",TEXT(A30,"00"),IF(H30="Célula Construtiva",TEXT(B30,"00"),IF(H30="Etapa",CONCATENATE(TEXT(B30,"00"),".",TEXT(C30,"000")),IF(H30="Subetapa",CONCATENATE(TEXT(B30,"00"),".",TEXT(C30,"000"),".",TEXT(D30,"000")),IF(H30="Serviço",CONCATENATE(TEXT(B30,"00"),".",TEXT(C30,"000"),".",TEXT(D30,"000"),".",TEXT(E30,"000")),""))))) -> 01.001.004 | J30: Ensaios | N30: =IF(H30="Serviço",M30*L30,IF(H30="CÉLULA CONSTRUTIVA",SUMIFS($N$8:$N$420,$B$8:$B$420,B30,$H$8:$H$420,"Serviço"),IF(H30="ETAPA",SUMIFS($N$8:$N$420,$B$8:$B$420,B30,$C$8:$C$420,C30,$H$8:$H$420,"Serviço"),IF(H30="SUBETAPA",SUMIFS($N$8:$N$420,$B$8:$B$420,B30,$C$8:$C$420,C30,$D$8:$D$420,D30,$H$8:$H$420,"Serviço"),0)))) -> 177545.38
A31: =IF($H31="UNIDADE CONSTRUTIVA",OFFSET(A31,-1,0)+1,LARGE(A$3:A30,1)) -> 0 | B31: =IF(H31="UNIDADE CONSTRUTIVA",0,IF(H31="CÉLULA CONSTRUTIVA",OFFSET(B31,-1,0)+1,OFFSET(B31,-1,0))) -> 1 | C31: =IF(H31="CÉLULA CONSTRUTIVA",0,IF(H31="ETAPA",OFFSET(C31,-1,0)+1,OFFSET(C31,-1,0))) -> 1 | D31: =IF(H31="ETAPA",0,IF(H31="SUBETAPA",OFFSET(D31,-1,0)+1,OFFSET(D31,-1,0))) -> 4 | E31: =IF(H31="Subetapa",0,IF(H31="serviço",OFFSET(E31,-1,0)+1,OFFSET(E31,-1,0))) -> 1 | H31: SERVIÇO | I31: =IF(H31="Unidade Construtiva",TEXT(A31,"00"),IF(H31="Célula Construtiva",TEXT(B31,"00"),IF(H31="Etapa",CONCATENATE(TEXT(B31,"00"),".",TEXT(C31,"000")),IF(H31="Subetapa",CONCATENATE(TEXT(B31,"00"),".",TEXT(C31,"000"),".",TEXT(D31,"000")),IF(H31="Serviço",CONCATENATE(TEXT(B31,"00"),".",TEXT(C31,"000"),".",TEXT(D31,"000"),".",TEXT(E31,"000")),""))))) -> 01.001.004.001 | J31: Controle Tecnologico de Concreto | K31: vb | L31: 1 | M31: 38456.656 | N31: =IF(H31="Serviço",M31*L31,IF(H31="CÉLULA CONSTRUTIVA",SUMIFS($N$8:$N$420,$B$8:$B$420,B31,$H$8:$H$420,"Serviço"),IF(H31="ETAPA",SUMIFS($N$8:$N$420,$B$8:$B$420,B31,$C$8:$C$420,C31,$H$8:$H$420,"Serviço"),IF(H31="SUBETAPA",SUMIFS($N$8:$N$420,$B$8:$B$420,B31,$C$8:$C$420,C31,$D$8:$D$420,D31,$H$8:$H$420,"Serviço"),0)))) -> 38456.656 | O31: Estimado com base em índices históricos | P31: Finalizado
A32: =IF($H32="UNIDADE CONSTRUTIVA",OFFSET(A32,-1,0)+1,LARGE(A$3:A31,1)) -> 0 | B32: =IF(H32="UNIDADE CONSTRUTIVA",0,IF(H32="CÉLULA CONSTRUTIVA",OFFSET(B32,-1,0)+1,OFFSET(B32,-1,0))) -> 1 | C32: =IF(H32="CÉLULA CONSTRUTIVA",0,IF(H32="ETAPA",OFFSET(C32,-1,0)+1,OFFSET(C32,-1,0))) -> 1 | D32: =IF(H32="ETAPA",0,IF(H32="SUBETAPA",OFFSET(D32,-1,0)+1,OFFSET(D32,-1,0))) -> 4 | E32: =IF(H32="Subetapa",0,IF(H32="serviço",OFFSET(E32,-1,0)+1,OFFSET(E32,-1,0))) -> 2 | H32: SERVIÇO | I32: =IF(H32="Unidade Construtiva",TEXT(A32,"00"),IF(H32="Célula Construtiva",TEXT(B32,"00"),IF(H32="Etapa",CONCATENATE(TEXT(B32,"00"),".",TEXT(C32,"000")),IF(H32="Subetapa",CONCATENATE(TEXT(B32,"00"),".",TEXT(C32,"000"),".",TEXT(D32,"000")),IF(H32="Serviço",CONCATENATE(TEXT(B32,"00"),".",TEXT(C32,"000"),".",TEXT(D32,"000"),".",TEXT(E32,"000")),""))))) -> 01.001.004.002 | J32: Laudo de Vizinhança | K32: vb | L32: 1 | M32: =13000+126088.72 -> 139088.72 | N32: =IF(H32="Serviço",M32*L32,IF(H32="CÉLULA CONSTRUTIVA",SUMIFS($N$8:$N$420,$B$8:$B$420,B32,$H$8:$H$420,"Serviço"),IF(H32="ETAPA",SUMIFS($N$8:$N$420,$B$8:$B$420,B32,$C$8:$C$420,C32,$H$8:$H$420,"Serviço"),IF(H32="SUBETAPA",SUMIFS($N$8:$N$420,$B$8:$B$420,B32,$C$8:$C$420,C32,$D$8:$D$420,D32,$H$8:$H$420,"Serviço"),0)))) -> 139088.72 | O32: Fornecido pelo whatsapp | P32: Finalizado
A33: =IF($H33="UNIDADE CONSTRUTIVA",OFFSET(A33,-1,0)+1,LARGE(A$3:A32,1)) -> 0 | B33: =IF(H33="UNIDADE CONSTRUTIVA",0,IF(H33="CÉLULA CONSTRUTIVA",OFFSET(B33,-1,0)+1,OFFSET(B33,-1,0))) -> 1 | C33: =IF(H33="CÉLULA CONSTRUTIVA",0,IF(H33="ETAPA",OFFSET(C33,-1,0)+1,OFFSET(C33,-1,0))) -> 2 | D33: =IF(H33="ETAPA",0,IF(H33="SUBETAPA",OFFSET(D33,-1,0)+1,OFFSET(D33,-1,0))) -> 0 | E33: =IF(H33="Subetapa",0,IF(H33="serviço",OFFSET(E33,-1,0)+1,OFFSET(E33,-1,0))) -> 2 | H33: ETAPA | I33: =IF(H33="Unidade Construtiva",TEXT(A33,"00"),IF(H33="Célula Construtiva",TEXT(B33,"00"),IF(H33="Etapa",CONCATENATE(TEXT(B33,"00"),".",TEXT(C33,"000")),IF(H33="Subetapa",CONCATENATE(TEXT(B33,"00"),".",TEXT(C33,"000"),".",TEXT(D33,"000")),IF(H33="Serviço",CONCATENATE(TEXT(B33,"00"),".",TEXT(C33,"000"),".",TEXT(D33,"000"),".",TEXT(E33,"000")),""))))) -> 01.002 | J33: CONSUMOS, TAXAS E DOCUMENTOS | N33: =IF(H33="Serviço",M33*L33,IF(H33="CÉLULA CONSTRUTIVA",SUMIFS($N$8:$N$420,$B$8:$B$420,B33,$H$8:$H$420,"Serviço"),IF(H33="ETAPA",SUMIFS($N$8:$N$420,$B$8:$B$420,B33,$C$8:$C$420,C33,$H$8:$H$420,"Serviço"),IF(H33="SUBETAPA",SUMIFS($N$8:$N$420,$B$8:$B$420,B33,$C$8:$C$420,C33,$D$8:$D$420,D33,$H$8:$H$420,"Serviço"),0)))) -> 1049719.3 | P33: -
A34: =IF($H34="UNIDADE CONSTRUTIVA",OFFSET(A34,-1,0)+1,LARGE(A$3:A33,1)) -> 0 | B34: =IF(H34="UNIDADE CONSTRUTIVA",0,IF(H34="CÉLULA CONSTRUTIVA",OFFSET(B34,-1,0)+1,OFFSET(B34,-1,0))) -> 1 | C34: =IF(H34="CÉLULA CONSTRUTIVA",0,IF(H34="ETAPA",OFFSET(C34,-1,0)+1,OFFSET(C34,-1,0))) -> 2 | D34: =IF(H34="ETAPA",0,IF(H34="SUBETAPA",OFFSET(D34,-1,0)+1,OFFSET(D34,-1,0))) -> 1 | E34: =IF(H34="Subetapa",0,IF(H34="serviço",OFFSET(E34,-1,0)+1,OFFSET(E34,-1,0))) -> 0 | H34: SUBETAPA | I34: =IF(H34="Unidade Construtiva",TEXT(A34,"00"),IF(H34="Célula Construtiva",TEXT(B34,"00"),IF(H34="Etapa",CONCATENATE(TEXT(B34,"00"),".",TEXT(C34,"000")),IF(H34="Subetapa",CONCATENATE(TEXT(B34,"00"),".",TEXT(C34,"000"),".",TEXT(D34,"000")),IF(H34="Serviço",CONCATENATE(TEXT(B34,"00"),".",TEXT(C34,"000"),".",TEXT(D34,"000"),".",TEXT(E34,"000")),""))))) -> 01.002.001 | J34: Licenciamentos, Taxas, Impostos, Aprovações e Seguros | N34: =IF(H34="Serviço",M34*L34,IF(H34="CÉLULA CONSTRUTIVA",SUMIFS($N$8:$N$420,$B$8:$B$420,B34,$H$8:$H$420,"Serviço"),IF(H34="ETAPA",SUMIFS($N$8:$N$420,$B$8:$B$420,B34,$C$8:$C$420,C34,$H$8:$H$420,"Serviço"),IF(H34="SUBETAPA",SUMIFS($N$8:$N$420,$B$8:$B$420,B34,$C$8:$C$420,C34,$D$8:$D$420,D34,$H$8:$H$420,"Serviço"),0)))) -> 516230.94
A35: =IF($H35="UNIDADE CONSTRUTIVA",OFFSET(A35,-1,0)+1,LARGE(A$3:A34,1)) -> 0 | B35: =IF(H35="UNIDADE CONSTRUTIVA",0,IF(H35="CÉLULA CONSTRUTIVA",OFFSET(B35,-1,0)+1,OFFSET(B35,-1,0))) -> 1 | C35: =IF(H35="CÉLULA CONSTRUTIVA",0,IF(H35="ETAPA",OFFSET(C35,-1,0)+1,OFFSET(C35,-1,0))) -> 2 | D35: =IF(H35="ETAPA",0,IF(H35="SUBETAPA",OFFSET(D35,-1,0)+1,OFFSET(D35,-1,0))) -> 1 | E35: =IF(H35="Subetapa",0,IF(H35="serviço",OFFSET(E35,-1,0)+1,OFFSET(E35,-1,0))) -> 1 | H35: SERVIÇO | I35: =IF(H35="Unidade Construtiva",TEXT(A35,"00"),IF(H35="Célula Construtiva",TEXT(B35,"00"),IF(H35="Etapa",CONCATENATE(TEXT(B35,"00"),".",TEXT(C35,"000")),IF(H35="Subetapa",CONCATENATE(TEXT(B35,"00"),".",TEXT(C35,"000"),".",TEXT(D35,"000")),IF(H35="Serviço",CONCATENATE(TEXT(B35,"00"),".",TEXT(C35,"000"),".",TEXT(D35,"000"),".",TEXT(E35,"000")),""))))) -> 01.002.001.001 | J35: Despesas de Seguros | K35: vb | L35: 1 | M35: 29287.335 | N35: =IF(H35="Serviço",M35*L35,IF(H35="CÉLULA CONSTRUTIVA",SUMIFS($N$8:$N$420,$B$8:$B$420,B35,$H$8:$H$420,"Serviço"),IF(H35="ETAPA",SUMIFS($N$8:$N$420,$B$8:$B$420,B35,$C$8:$C$420,C35,$H$8:$H$420,"Serviço"),IF(H35="SUBETAPA",SUMIFS($N$8:$N$420,$B$8:$B$420,B35,$C$8:$C$420,C35,$D$8:$D$420,D35,$H$8:$H$420,"Serviço"),0)))) -> 29287.335 | O35: Estimado com base em índices históricos | P35: Lançado ERP
A36: =IF($H36="UNIDADE CONSTRUTIVA",OFFSET(A36,-1,0)+1,LARGE(A$3:A35,1)) -> 0 | B36: =IF(H36="UNIDADE CONSTRUTIVA",0,IF(H36="CÉLULA CONSTRUTIVA",OFFSET(B36,-1,0)+1,OFFSET(B36,-1,0))) -> 1 | C36: =IF(H36="CÉLULA CONSTRUTIVA",0,IF(H36="ETAPA",OFFSET(C36,-1,0)+1,OFFSET(C36,-1,0))) -> 2 | D36: =IF(H36="ETAPA",0,IF(H36="SUBETAPA",OFFSET(D36,-1,0)+1,OFFSET(D36,-1,0))) -> 1 | E36: =IF(H36="Subetapa",0,IF(H36="serviço",OFFSET(E36,-1,0)+1,OFFSET(E36,-1,0))) -> 2 | H36: SERVIÇO | I36: =IF(H36="Unidade Construtiva",TEXT(A36,"00"),IF(H36="Célula Construtiva",TEXT(B36,"00"),IF(H36="Etapa",CONCATENATE(TEXT(B36,"00"),".",TEXT(C36,"000")),IF(H36="Subetapa",CONCATENATE(TEXT(B36,"00"),".",TEXT(C36,"000"),".",TEXT(D36,"000")),IF(H36="Serviço",CONCATENATE(TEXT(B36,"00"),".",TEXT(C36,"000"),".",TEXT(D36,"000"),".",TEXT(E36,"000")),""))))) -> 01.002.001.002 | J36: Aprovação e legalização ambiental | K36: vb | L36: 1 | M36: 8368.8559 | N36: =IF(H36="Serviço",M36*L36,IF(H36="CÉLULA CONSTRUTIVA",SUMIFS($N$8:$N$420,$B$8:$B$420,B36,$H$8:$H$420,"Serviço"),IF(H36="ETAPA",SUMIFS($N$8:$N$420,$B$8:$B$420,B36,$C$8:$C$420,C36,$H$8:$H$420,"Serviço"),IF(H36="SUBETAPA",SUMIFS($N$8:$N$420,$B$8:$B$420,B36,$C$8:$C$420,C36,$D$8:$D$420,D36,$H$8:$H$420,"Serviço"),0)))) -> 8368.8559 | O36: Estimado com base em índices históricos | P36: Lançado ERP
A37: =IF($H37="UNIDADE CONSTRUTIVA",OFFSET(A37,-1,0)+1,LARGE(A$3:A36,1)) -> 0 | B37: =IF(H37="UNIDADE CONSTRUTIVA",0,IF(H37="CÉLULA CONSTRUTIVA",OFFSET(B37,-1,0)+1,OFFSET(B37,-1,0))) -> 1 | C37: =IF(H37="CÉLULA CONSTRUTIVA",0,IF(H37="ETAPA",OFFSET(C37,-1,0)+1,OFFSET(C37,-1,0))) -> 2 | D37: =IF(H37="ETAPA",0,IF(H37="SUBETAPA",OFFSET(D37,-1,0)+1,OFFSET(D37,-1,0))) -> 1 | E37: =IF(H37="Subetapa",0,IF(H37="serviço",OFFSET(E37,-1,0)+1,OFFSET(E37,-1,0))) -> 3 | H37: SERVIÇO | I37: =IF(H37="Unidade Construtiva",TEXT(A37,"00"),IF(H37="Célula Construtiva",TEXT(B37,"00"),IF(H37="Etapa",CONCATENATE(TEXT(B37,"00"),".",TEXT(C37,"000")),IF(H37="Subetapa",CONCATENATE(TEXT(B37,"00"),".",TEXT(C37,"000"),".",TEXT(D37,"000")),IF(H37="Serviço",CONCATENATE(TEXT(B37,"00"),".",TEXT(C37,"000"),".",TEXT(D37,"000"),".",TEXT(E37,"000")),""))))) -> 01.002.001.003 | J37: Aprovação e legalização prefeitura | K37: vb | L37: 1 | M37: 32923.365 | N37: =IF(H37="Serviço",M37*L37,IF(H37="CÉLULA CONSTRUTIVA",SUMIFS($N$8:$N$420,$B$8:$B$420,B37,$H$8:$H$420,"Serviço"),IF(H37="ETAPA",SUMIFS($N$8:$N$420,$B$8:$B$420,B37,$C$8:$C$420,C37,$H$8:$H$420,"Serviço"),IF(H37="SUBETAPA",SUMIFS($N$8:$N$420,$B$8:$B$420,B37,$C$8:$C$420,C37,$D$8:$D$420,D37,$H$8:$H$420,"Serviço"),0)))) -> 32923.365 | O37: Estimado com base em índices históricos | P37: Lançado ERP
A38: =IF($H38="UNIDADE CONSTRUTIVA",OFFSET(A38,-1,0)+1,LARGE(A$3:A37,1)) -> 0 | B38: =IF(H38="UNIDADE CONSTRUTIVA",0,IF(H38="CÉLULA CONSTRUTIVA",OFFSET(B38,-1,0)+1,OFFSET(B38,-1,0))) -> 1 | C38: =IF(H38="CÉLULA CONSTRUTIVA",0,IF(H38="ETAPA",OFFSET(C38,-1,0)+1,OFFSET(C38,-1,0))) -> 2 | D38: =IF(H38="ETAPA",0,IF(H38="SUBETAPA",OFFSET(D38,-1,0)+1,OFFSET(D38,-1,0))) -> 1 | E38: =IF(H38="Subetapa",0,IF(H38="serviço",OFFSET(E38,-1,0)+1,OFFSET(E38,-1,0))) -> 4 | H38: SERVIÇO | I38: =IF(H38="Unidade Construtiva",TEXT(A38,"00"),IF(H38="Célula Construtiva",TEXT(B38,"00"),IF(H38="Etapa",CONCATENATE(TEXT(B38,"00"),".",TEXT(C38,"000")),IF(H38="Subetapa",CONCATENATE(TEXT(B38,"00"),".",TEXT(C38,"000"),".",TEXT(D38,"000")),IF(H38="Serviço",CONCATENATE(TEXT(B38,"00"),".",TEXT(C38,"000"),".",TEXT(D38,"000"),".",TEXT(E38,"000")),""))))) -> 01.002.001.004 | J38: Aprovação e legalização água e esgoto | K38: vb | L38: 1 | M38: 2619.0836 | N38: =IF(H38="Serviço",M38*L38,IF(H38="CÉLULA CONSTRUTIVA",SUMIFS($N$8:$N$420,$B$8:$B$420,B38,$H$8:$H$420,"Serviço"),IF(H38="ETAPA",SUMIFS($N$8:$N$420,$B$8:$B$420,B38,$C$8:$C$420,C38,$H$8:$H$420,"Serviço"),IF(H38="SUBETAPA",SUMIFS($N$8:$N$420,$B$8:$B$420,B38,$C$8:$C$420,C38,$D$8:$D$420,D38,$H$8:$H$420,"Serviço"),0)))) -> 2619.0836 | O38: Estimado com base em índices históricos | P38: Lançado ERP
A39: =IF($H39="UNIDADE CONSTRUTIVA",OFFSET(A39,-1,0)+1,LARGE(A$3:A38,1)) -> 0 | B39: =IF(H39="UNIDADE CONSTRUTIVA",0,IF(H39="CÉLULA CONSTRUTIVA",OFFSET(B39,-1,0)+1,OFFSET(B39,-1,0))) -> 1 | C39: =IF(H39="CÉLULA CONSTRUTIVA",0,IF(H39="ETAPA",OFFSET(C39,-1,0)+1,OFFSET(C39,-1,0))) -> 2 | D39: =IF(H39="ETAPA",0,IF(H39="SUBETAPA",OFFSET(D39,-1,0)+1,OFFSET(D39,-1,0))) -> 1 | E39: =IF(H39="Subetapa",0,IF(H39="serviço",OFFSET(E39,-1,0)+1,OFFSET(E39,-1,0))) -> 5 | H39: SERVIÇO | I39: =IF(H39="Unidade Construtiva",TEXT(A39,"00"),IF(H39="Célula Construtiva",TEXT(B39,"00"),IF(H39="Etapa",CONCATENATE(TEXT(B39,"00"),".",TEXT(C39,"000")),IF(H39="Subetapa",CONCATENATE(TEXT(B39,"00"),".",TEXT(C39,"000"),".",TEXT(D39,"000")),IF(H39="Serviço",CONCATENATE(TEXT(B39,"00"),".",TEXT(C39,"000"),".",TEXT(D39,"000"),".",TEXT(E39,"000")),""))))) -> 01.002.001.005 | J39: Aprovação e legalização elétrico | K39: vb | L39: 1 | M39: 18403.978 | N39: =IF(H39="Serviço",M39*L39,IF(H39="CÉLULA CONSTRUTIVA",SUMIFS($N$8:$N$420,$B$8:$B$420,B39,$H$8:$H$420,"Serviço"),IF(H39="ETAPA",SUMIFS($N$8:$N$420,$B$8:$B$420,B39,$C$8:$C$420,C39,$H$8:$H$420,"Serviço"),IF(H39="SUBETAPA",SUMIFS($N$8:$N$420,$B$8:$B$420,B39,$C$8:$C$420,C39,$D$8:$D$420,D39,$H$8:$H$420,"Serviço"),0)))) -> 18403.978 | O39: Estimado com base em índices históricos | P39: Lançado ERP
A40: =IF($H40="UNIDADE CONSTRUTIVA",OFFSET(A40,-1,0)+1,LARGE(A$3:A39,1)) -> 0 | B40: =IF(H40="UNIDADE CONSTRUTIVA",0,IF(H40="CÉLULA CONSTRUTIVA",OFFSET(B40,-1,0)+1,OFFSET(B40,-1,0))) -> 1 | C40: =IF(H40="CÉLULA CONSTRUTIVA",0,IF(H40="ETAPA",OFFSET(C40,-1,0)+1,OFFSET(C40,-1,0))) -> 2 | D40: =IF(H40="ETAPA",0,IF(H40="SUBETAPA",OFFSET(D40,-1,0)+1,OFFSET(D40,-1,0))) -> 1 | E40: =IF(H40="Subetapa",0,IF(H40="serviço",OFFSET(E40,-1,0)+1,OFFSET(E40,-1,0))) -> 6 | H40: SERVIÇO | I40: =IF(H40="Unidade Construtiva",TEXT(A40,"00"),IF(H40="Célula Construtiva",TEXT(B40,"00"),IF(H40="Etapa",CONCATENATE(TEXT(B40,"00"),".",TEXT(C40,"000")),IF(H40="Subetapa",CONCATENATE(TEXT(B40,"00"),".",TEXT(C40,"000"),".",TEXT(D40,"000")),IF(H40="Serviço",CONCATENATE(TEXT(B40,"00"),".",TEXT(C40,"000"),".",TEXT(D40,"000"),".",TEXT(E40,"000")),""))))) -> 01.002.001.006 | J40: Aprovação e legalização bombeiros | K40: vb | L40: 1 | M40: 11485.697 | N40: =IF(H40="Serviço",M40*L40,IF(H40="CÉLULA CONSTRUTIVA",SUMIFS($N$8:$N$420,$B$8:$B$420,B40,$H$8:$H$420,"Serviço"),IF(H40="ETAPA",SUMIFS($N$8:$N$420,$B$8:$B$420,B40,$C$8:$C$420,C40,$H$8:$H$420,"Serviço"),IF(H40="SUBETAPA",SUMIFS($N$8:$N$420,$B$8:$B$420,B40,$C$8:$C$420,C40,$D$8:$D$420,D40,$H$8:$H$420,"Serviço"),0)))) -> 11485.697 | O40: Estimado com base em índices históricos | P40: Lançado ERP
A41: =IF($H41="UNIDADE CONSTRUTIVA",OFFSET(A41,-1,0)+1,LARGE(A$3:A40,1)) -> 0 | B41: =IF(H41="UNIDADE CONSTRUTIVA",0,IF(H41="CÉLULA CONSTRUTIVA",OFFSET(B41,-1,0)+1,OFFSET(B41,-1,0))) -> 1 | C41: =IF(H41="CÉLULA CONSTRUTIVA",0,IF(H41="ETAPA",OFFSET(C41,-1,0)+1,OFFSET(C41,-1,0))) -> 2 | D41: =IF(H41="ETAPA",0,IF(H41="SUBETAPA",OFFSET(D41,-1,0)+1,OFFSET(D41,-1,0))) -> 1 | E41: =IF(H41="Subetapa",0,IF(H41="serviço",OFFSET(E41,-1,0)+1,OFFSET(E41,-1,0))) -> 7 | H41: SERVIÇO | I41: =IF(H41="Unidade Construtiva",TEXT(A41,"00"),IF(H41="Célula Construtiva",TEXT(B41,"00"),IF(H41="Etapa",CONCATENATE(TEXT(B41,"00"),".",TEXT(C41,"000")),IF(H41="Subetapa",CONCATENATE(TEXT(B41,"00"),".",TEXT(C41,"000"),".",TEXT(D41,"000")),IF(H41="Serviço",CONCATENATE(TEXT(B41,"00"),".",TEXT(C41,"000"),".",TEXT(D41,"000"),".",TEXT(E41,"000")),""))))) -> 01.002.001.007 | J41: Taxas de ART | K41: vb | L41: 1 | M41: 4775.1089 | N41: =IF(H41="Serviço",M41*L41,IF(H41="CÉLULA CONSTRUTIVA",SUMIFS($N$8:$N$420,$B$8:$B$420,B41,$H$8:$H$420,"Serviço"),IF(H41="ETAPA",SUMIFS($N$8:$N$420,$B$8:$B$420,B41,$C$8:$C$420,C41,$H$8:$H$420,"Serviço"),IF(H41="SUBETAPA",SUMIFS($N$8:$N$420,$B$8:$B$420,B41,$C$8:$C$420,C41,$D$8:$D$420,D41,$H$8:$H$420,"Serviço"),0)))) -> 4775.1089 | O41: Estimado com base em índices históricos | P41: Lançado ERP
A42: =IF($H42="UNIDADE CONSTRUTIVA",OFFSET(A42,-1,0)+1,LARGE(A$3:A41,1)) -> 0 | B42: =IF(H42="UNIDADE CONSTRUTIVA",0,IF(H42="CÉLULA CONSTRUTIVA",OFFSET(B42,-1,0)+1,OFFSET(B42,-1,0))) -> 1 | C42: =IF(H42="CÉLULA CONSTRUTIVA",0,IF(H42="ETAPA",OFFSET(C42,-1,0)+1,OFFSET(C42,-1,0))) -> 2 | D42: =IF(H42="ETAPA",0,IF(H42="SUBETAPA",OFFSET(D42,-1,0)+1,OFFSET(D42,-1,0))) -> 1 | E42: =IF(H42="Subetapa",0,IF(H42="serviço",OFFSET(E42,-1,0)+1,OFFSET(E42,-1,0))) -> 8 | H42: SERVIÇO | I42: =IF(H42="Unidade Construtiva",TEXT(A42,"00"),IF(H42="Célula Construtiva",TEXT(B42,"00"),IF(H42="Etapa",CONCATENATE(TEXT(B42,"00"),".",TEXT(C42,"000")),IF(H42="Subetapa",CONCATENATE(TEXT(B42,"00"),".",TEXT(C42,"000"),".",TEXT(D42,"000")),IF(H42="Serviço",CONCATENATE(TEXT(B42,"00"),".",TEXT(C42,"000"),".",TEXT(D42,"000"),".",TEXT(E42,"000")),""))))) -> 01.002.001.008 | J42: Alvará Construção | K42: vb | L42: 1 | M42: 51010.067 | N42: =IF(H42="Serviço",M42*L42,IF(H42="CÉLULA CONSTRUTIVA",SUMIFS($N$8:$N$420,$B$8:$B$420,B42,$H$8:$H$420,"Serviço"),IF(H42="ETAPA",SUMIFS($N$8:$N$420,$B$8:$B$420,B42,$C$8:$C$420,C42,$H$8:$H$420,"Serviço"),IF(H42="SUBETAPA",SUMIFS($N$8:$N$420,$B$8:$B$420,B42,$C$8:$C$420,C42,$D$8:$D$420,D42,$H$8:$H$420,"Serviço"),0)))) -> 51010.067 | O42: Estimado com base em índices históricos | P42: Lançado ERP
A43: =IF($H43="UNIDADE CONSTRUTIVA",OFFSET(A43,-1,0)+1,LARGE(A$3:A42,1)) -> 0 | B43: =IF(H43="UNIDADE CONSTRUTIVA",0,IF(H43="CÉLULA CONSTRUTIVA",OFFSET(B43,-1,0)+1,OFFSET(B43,-1,0))) -> 1 | C43: =IF(H43="CÉLULA CONSTRUTIVA",0,IF(H43="ETAPA",OFFSET(C43,-1,0)+1,OFFSET(C43,-1,0))) -> 2 | D43: =IF(H43="ETAPA",0,IF(H43="SUBETAPA",OFFSET(D43,-1,0)+1,OFFSET(D43,-1,0))) -> 1 | E43: =IF(H43="Subetapa",0,IF(H43="serviço",OFFSET(E43,-1,0)+1,OFFSET(E43,-1,0))) -> 9 | H43: SERVIÇO | I43: =IF(H43="Unidade Construtiva",TEXT(A43,"00"),IF(H43="Célula Construtiva",TEXT(B43,"00"),IF(H43="Etapa",CONCATENATE(TEXT(B43,"00"),".",TEXT(C43,"000")),IF(H43="Subetapa",CONCATENATE(TEXT(B43,"00"),".",TEXT(C43,"000"),".",TEXT(D43,"000")),IF(H43="Serviço",CONCATENATE(TEXT(B43,"00"),".",TEXT(C43,"000"),".",TEXT(D43,"000"),".",TEXT(E43,"000")),""))))) -> 01.002.001.009 | J43: Despesas cartório, licenças, certidões e jurídicas | K43: vb | L43: 1 | M43: 54830.62 | N43: =IF(H43="Serviço",M43*L43,IF(H43="CÉLULA CONSTRUTIVA",SUMIFS($N$8:$N$420,$B$8:$B$420,B43,$H$8:$H$420,"Serviço"),IF(H43="ETAPA",SUMIFS($N$8:$N$420,$B$8:$B$420,B43,$C$8:$C$420,C43,$H$8:$H$420,"Serviço"),IF(H43="SUBETAPA",SUMIFS($N$8:$N$420,$B$8:$B$420,B43,$C$8:$C$420,C43,$D$8:$D$420,D43,$H$8:$H$420,"Serviço"),0)))) -> 54830.62 | O43: Estimado com base em índices históricos | P43: Lançado ERP
A44: =IF($H44="UNIDADE CONSTRUTIVA",OFFSET(A44,-1,0)+1,LARGE(A$3:A43,1)) -> 0 | B44: =IF(H44="UNIDADE CONSTRUTIVA",0,IF(H44="CÉLULA CONSTRUTIVA",OFFSET(B44,-1,0)+1,OFFSET(B44,-1,0))) -> 1 | C44: =IF(H44="CÉLULA CONSTRUTIVA",0,IF(H44="ETAPA",OFFSET(C44,-1,0)+1,OFFSET(C44,-1,0))) -> 2 | D44: =IF(H44="ETAPA",0,IF(H44="SUBETAPA",OFFSET(D44,-1,0)+1,OFFSET(D44,-1,0))) -> 1 | E44: =IF(H44="Subetapa",0,IF(H44="serviço",OFFSET(E44,-1,0)+1,OFFSET(E44,-1,0))) -> 10 | H44: SERVIÇO | I44: =IF(H44="Unidade Construtiva",TEXT(A44,"00"),IF(H44="Célula Construtiva",TEXT(B44,"00"),IF(H44="Etapa",CONCATENATE(TEXT(B44,"00"),".",TEXT(C44,"000")),IF(H44="Subetapa",CONCATENATE(TEXT(B44,"00"),".",TEXT(C44,"000"),".",TEXT(D44,"000")),IF(H44="Serviço",CONCATENATE(TEXT(B44,"00"),".",TEXT(C44,"000"),".",TEXT(D44,"000"),".",TEXT(E44,"000")),""))))) -> 01.002.001.010 | J44: Iptu | K44: vb | L44: 1 | M44: 70034.931 | N44: =IF(H44="Serviço",M44*L44,IF(H44="CÉLULA CONSTRUTIVA",SUMIFS($N$8:$N$420,$B$8:$B$420,B44,$H$8:$H$420,"Serviço"),IF(H44="ETAPA",SUMIFS($N$8:$N$420,$B$8:$B$420,B44,$C$8:$C$420,C44,$H$8:$H$420,"Serviço"),IF(H44="SUBETAPA",SUMIFS($N$8:$N$420,$B$8:$B$420,B44,$C$8:$C$420,C44,$D$8:$D$420,D44,$H$8:$H$420,"Serviço"),0)))) -> 70034.931 | O44: Estimado com base em índices históricos | P44: Lançado ERP
A45: =IF($H45="UNIDADE CONSTRUTIVA",OFFSET(A45,-1,0)+1,LARGE(A$3:A44,1)) -> 0 | B45: =IF(H45="UNIDADE CONSTRUTIVA",0,IF(H45="CÉLULA CONSTRUTIVA",OFFSET(B45,-1,0)+1,OFFSET(B45,-1,0))) -> 1 | C45: =IF(H45="CÉLULA CONSTRUTIVA",0,IF(H45="ETAPA",OFFSET(C45,-1,0)+1,OFFSET(C45,-1,0))) -> 2 | D45: =IF(H45="ETAPA",0,IF(H45="SUBETAPA",OFFSET(D45,-1,0)+1,OFFSET(D45,-1,0))) -> 1 | E45: =IF(H45="Subetapa",0,IF(H45="serviço",OFFSET(E45,-1,0)+1,OFFSET(E45,-1,0))) -> 11 | H45: SERVIÇO | I45: =IF(H45="Unidade Construtiva",TEXT(A45,"00"),IF(H45="Célula Construtiva",TEXT(B45,"00"),IF(H45="Etapa",CONCATENATE(TEXT(B45,"00"),".",TEXT(C45,"000")),IF(H45="Subetapa",CONCATENATE(TEXT(B45,"00"),".",TEXT(C45,"000"),".",TEXT(D45,"000")),IF(H45="Serviço",CONCATENATE(TEXT(B45,"00"),".",TEXT(C45,"000"),".",TEXT(D45,"000"),".",TEXT(E45,"000")),""))))) -> 01.002.001.011 | J45: Alvará Habite-se | K45: vb | L45: 1 | M45: 34795.119 | N45: =IF(H45="Serviço",M45*L45,IF(H45="CÉLULA CONSTRUTIVA",SUMIFS($N$8:$N$420,$B$8:$B$420,B45,$H$8:$H$420,"Serviço"),IF(H45="ETAPA",SUMIFS($N$8:$N$420,$B$8:$B$420,B45,$C$8:$C$420,C45,$H$8:$H$420,"Serviço"),IF(H45="SUBETAPA",SUMIFS($N$8:$N$420,$B$8:$B$420,B45,$C$8:$C$420,C45,$D$8:$D$420,D45,$H$8:$H$420,"Serviço"),0)))) -> 34795.119 | O45: Estimado com base em índices históricos | P45: Lançado ERP
A46: =IF($H46="UNIDADE CONSTRUTIVA",OFFSET(A46,-1,0)+1,LARGE(A$3:A45,1)) -> 0 | B46: =IF(H46="UNIDADE CONSTRUTIVA",0,IF(H46="CÉLULA CONSTRUTIVA",OFFSET(B46,-1,0)+1,OFFSET(B46,-1,0))) -> 1 | C46: =IF(H46="CÉLULA CONSTRUTIVA",0,IF(H46="ETAPA",OFFSET(C46,-1,0)+1,OFFSET(C46,-1,0))) -> 2 | D46: =IF(H46="ETAPA",0,IF(H46="SUBETAPA",OFFSET(D46,-1,0)+1,OFFSET(D46,-1,0))) -> 1 | E46: =IF(H46="Subetapa",0,IF(H46="serviço",OFFSET(E46,-1,0)+1,OFFSET(E46,-1,0))) -> 12 | H46: SERVIÇO | I46: =IF(H46="Unidade Construtiva",TEXT(A46,"00"),IF(H46="Célula Construtiva",TEXT(B46,"00"),IF(H46="Etapa",CONCATENATE(TEXT(B46,"00"),".",TEXT(C46,"000")),IF(H46="Subetapa",CONCATENATE(TEXT(B46,"00"),".",TEXT(C46,"000"),".",TEXT(D46,"000")),IF(H46="Serviço",CONCATENATE(TEXT(B46,"00"),".",TEXT(C46,"000"),".",TEXT(D46,"000"),".",TEXT(E46,"000")),""))))) -> 01.002.001.012 | J46: Imposto sobre Serviços | K46: vb | L46: 1 | M46: 197696.78 | N46: =IF(H46="Serviço",M46*L46,IF(H46="CÉLULA CONSTRUTIVA",SUMIFS($N$8:$N$420,$B$8:$B$420,B46,$H$8:$H$420,"Serviço"),IF(H46="ETAPA",SUMIFS($N$8:$N$420,$B$8:$B$420,B46,$C$8:$C$420,C46,$H$8:$H$420,"Serviço"),IF(H46="SUBETAPA",SUMIFS($N$8:$N$420,$B$8:$B$420,B46,$C$8:$C$420,C46,$D$8:$D$420,D46,$H$8:$H$420,"Serviço"),0)))) -> 197696.78 | O46: Fornecido pelo whatsapp | P46: Lançado ERP
A47: =IF($H47="UNIDADE CONSTRUTIVA",OFFSET(A47,-1,0)+1,LARGE(A$3:A45,1)) -> 0 | B47: =IF(H47="UNIDADE CONSTRUTIVA",0,IF(H47="CÉLULA CONSTRUTIVA",OFFSET(B47,-1,0)+1,OFFSET(B47,-1,0))) -> 1 | C47: =IF(H47="CÉLULA CONSTRUTIVA",0,IF(H47="ETAPA",OFFSET(C47,-1,0)+1,OFFSET(C47,-1,0))) -> 2 | D47: =IF(H47="ETAPA",0,IF(H47="SUBETAPA",OFFSET(D47,-1,0)+1,OFFSET(D47,-1,0))) -> 2 | E47: =IF(H47="Subetapa",0,IF(H47="serviço",OFFSET(E47,-1,0)+1,OFFSET(E47,-1,0))) -> 0 | H47: SUBETAPA | I47: =IF(H47="Unidade Construtiva",TEXT(A47,"00"),IF(H47="Célula Construtiva",TEXT(B47,"00"),IF(H47="Etapa",CONCATENATE(TEXT(B47,"00"),".",TEXT(C47,"000")),IF(H47="Subetapa",CONCATENATE(TEXT(B47,"00"),".",TEXT(C47,"000"),".",TEXT(D47,"000")),IF(H47="Serviço",CONCATENATE(TEXT(B47,"00"),".",TEXT(C47,"000"),".",TEXT(D47,"000"),".",TEXT(E47,"000")),""))))) -> 01.002.002 | J47: Documentos | N47: =IF(H47="Serviço",M47*L47,IF(H47="CÉLULA CONSTRUTIVA",SUMIFS($N$8:$N$420,$B$8:$B$420,B47,$H$8:$H$420,"Serviço"),IF(H47="ETAPA",SUMIFS($N$8:$N$420,$B$8:$B$420,B47,$C$8:$C$420,C47,$H$8:$H$420,"Serviço"),IF(H47="SUBETAPA",SUMIFS($N$8:$N$420,$B$8:$B$420,B47,$C$8:$C$420,C47,$D$8:$D$420,D47,$H$8:$H$420,"Serviço"),0)))) -> 533488.33
A48: =IF($H48="UNIDADE CONSTRUTIVA",OFFSET(A48,-1,0)+1,LARGE(A$3:A47,1)) -> 0 | B48: =IF(H48="UNIDADE CONSTRUTIVA",0,IF(H48="CÉLULA CONSTRUTIVA",OFFSET(B48,-1,0)+1,OFFSET(B48,-1,0))) -> 1 | C48: =IF(H48="CÉLULA CONSTRUTIVA",0,IF(H48="ETAPA",OFFSET(C48,-1,0)+1,OFFSET(C48,-1,0))) -> 2 | D48: =IF(H48="ETAPA",0,IF(H48="SUBETAPA",OFFSET(D48,-1,0)+1,OFFSET(D48,-1,0))) -> 2 | E48: =IF(H48="Subetapa",0,IF(H48="serviço",OFFSET(E48,-1,0)+1,OFFSET(E48,-1,0))) -> 1 | H48: SERVIÇO | I48: =IF(H48="Unidade Construtiva",TEXT(A48,"00"),IF(H48="Célula Construtiva",TEXT(B48,"00"),IF(H48="Etapa",CONCATENATE(TEXT(B48,"00"),".",TEXT(C48,"000")),IF(H48="Subetapa",CONCATENATE(TEXT(B48,"00"),".",TEXT(C48,"000"),".",TEXT(D48,"000")),IF(H48="Serviço",CONCATENATE(TEXT(B48,"00"),".",TEXT(C48,"000"),".",TEXT(D48,"000"),".",TEXT(E48,"000")),""))))) -> 01.002.002.001 | J48: Manuais técnicos condomínio/proprietários | K48: vb | L48: 1 | M48: 43366.197 | N48: =IF(H48="Serviço",M48*L48,IF(H48="CÉLULA CONSTRUTIVA",SUMIFS($N$8:$N$420,$B$8:$B$420,B48,$H$8:$H$420,"Serviço"),IF(H48="ETAPA",SUMIFS($N$8:$N$420,$B$8:$B$420,B48,$C$8:$C$420,C48,$H$8:$H$420,"Serviço"),IF(H48="SUBETAPA",SUMIFS($N$8:$N$420,$B$8:$B$420,B48,$C$8:$C$420,C48,$D$8:$D$420,D48,$H$8:$H$420,"Serviço"),0)))) -> 43366.197 | O48: Estimado com base em índices históricos | P48: Lançado ERP
A49: =IF($H49="UNIDADE CONSTRUTIVA",OFFSET(A49,-1,0)+1,LARGE(A$3:A48,1)) -> 0 | B49: =IF(H49="UNIDADE CONSTRUTIVA",0,IF(H49="CÉLULA CONSTRUTIVA",OFFSET(B49,-1,0)+1,OFFSET(B49,-1,0))) -> 1 | C49: =IF(H49="CÉLULA CONSTRUTIVA",0,IF(H49="ETAPA",OFFSET(C49,-1,0)+1,OFFSET(C49,-1,0))) -> 2 | D49: =IF(H49="ETAPA",0,IF(H49="SUBETAPA",OFFSET(D49,-1,0)+1,OFFSET(D49,-1,0))) -> 2 | E49: =IF(H49="Subetapa",0,IF(H49="serviço",OFFSET(E49,-1,0)+1,OFFSET(E49,-1,0))) -> 2 | H49: SERVIÇO | I49: =IF(H49="Unidade Construtiva",TEXT(A49,"00"),IF(H49="Célula Construtiva",TEXT(B49,"00"),IF(H49="Etapa",CONCATENATE(TEXT(B49,"00"),".",TEXT(C49,"000")),IF(H49="Subetapa",CONCATENATE(TEXT(B49,"00"),".",TEXT(C49,"000"),".",TEXT(D49,"000")),IF(H49="Serviço",CONCATENATE(TEXT(B49,"00"),".",TEXT(C49,"000"),".",TEXT(D49,"000"),".",TEXT(E49,"000")),""))))) -> 01.002.002.002 | J49: Certidão INSS | K49: vb | L49: 1 | M49: 14914.771 | N49: =IF(H49="Serviço",M49*L49,IF(H49="CÉLULA CONSTRUTIVA",SUMIFS($N$8:$N$420,$B$8:$B$420,B49,$H$8:$H$420,"Serviço"),IF(H49="ETAPA",SUMIFS($N$8:$N$420,$B$8:$B$420,B49,$C$8:$C$420,C49,$H$8:$H$420,"Serviço"),IF(H49="SUBETAPA",SUMIFS($N$8:$N$420,$B$8:$B$420,B49,$C$8:$C$420,C49,$D$8:$D$420,D49,$H$8:$H$420,"Serviço"),0)))) -> 14914.771 | O49: Estimado com base em índices históricos | P49: Lançado ERP
A50: =IF($H50="UNIDADE CONSTRUTIVA",OFFSET(A50,-1,0)+1,LARGE(A$3:A49,1)) -> 0 | B50: =IF(H50="UNIDADE CONSTRUTIVA",0,IF(H50="CÉLULA CONSTRUTIVA",OFFSET(B50,-1,0)+1,OFFSET(B50,-1,0))) -> 1 | C50: =IF(H50="CÉLULA CONSTRUTIVA",0,IF(H50="ETAPA",OFFSET(C50,-1,0)+1,OFFSET(C50,-1,0))) -> 2 | D50: =IF(H50="ETAPA",0,IF(H50="SUBETAPA",OFFSET(D50,-1,0)+1,OFFSET(D50,-1,0))) -> 2 | E50: =IF(H50="Subetapa",0,IF(H50="serviço",OFFSET(E50,-1,0)+1,OFFSET(E50,-1,0))) -> 3 | H50: SERVIÇO | I50: =IF(H50="Unidade Construtiva",TEXT(A50,"00"),IF(H50="Célula Construtiva",TEXT(B50,"00"),IF(H50="Etapa",CONCATENATE(TEXT(B50,"00"),".",TEXT(C50,"000")),IF(H50="Subetapa",CONCATENATE(TEXT(B50,"00"),".",TEXT(C50,"000"),".",TEXT(D50,"000")),IF(H50="Serviço",CONCATENATE(TEXT(B50,"00"),".",TEXT(C50,"000"),".",TEXT(D50,"000"),".",TEXT(E50,"000")),""))))) -> 01.002.002.003 | J50: Individualização de matriculas (apartamentos e vagas) | K50: un | L50: 90 | M50: 1600 | N50: =IF(H50="Serviço",M50*L50,IF(H50="CÉLULA CONSTRUTIVA",SUMIFS($N$8:$N$420,$B$8:$B$420,B50,$H$8:$H$420,"Serviço"),IF(H50="ETAPA",SUMIFS($N$8:$N$420,$B$8:$B$420,B50,$C$8:$C$420,C50,$H$8:$H$420,"Serviço"),IF(H50="SUBETAPA",SUMIFS($N$8:$N$420,$B$8:$B$420,B50,$C$8:$C$420,C50,$D$8:$D$420,D50,$H$8:$H$420,"Serviço"),0)))) -> 144000 | O50: Fornecido pelo whatsapp | P50: Lançado ERP
A51: =IF($H51="UNIDADE CONSTRUTIVA",OFFSET(A51,-1,0)+1,LARGE(A$3:A47,1)) -> 0 | B51: =IF(H51="UNIDADE CONSTRUTIVA",0,IF(H51="CÉLULA CONSTRUTIVA",OFFSET(B51,-1,0)+1,OFFSET(B51,-1,0))) -> 1 | C51: =IF(H51="CÉLULA CONSTRUTIVA",0,IF(H51="ETAPA",OFFSET(C51,-1,0)+1,OFFSET(C51,-1,0))) -> 2 | D51: =IF(H51="ETAPA",0,IF(H51="SUBETAPA",OFFSET(D51,-1,0)+1,OFFSET(D51,-1,0))) -> 2 | E51: =IF(H51="Subetapa",0,IF(H51="serviço",OFFSET(E51,-1,0)+1,OFFSET(E51,-1,0))) -> 4 | H51: SERVIÇO | I51: =IF(H51="Unidade Construtiva",TEXT(A51,"00"),IF(H51="Célula Construtiva",TEXT(B51,"00"),IF(H51="Etapa",CONCATENATE(TEXT(B51,"00"),".",TEXT(C51,"000")),IF(H51="Subetapa",CONCATENATE(TEXT(B51,"00"),".",TEXT(C51,"000"),".",TEXT(D51,"000")),IF(H51="Serviço",CONCATENATE(TEXT(B51,"00"),".",TEXT(C51,"000"),".",TEXT(D51,"000"),".",TEXT(E51,"000")),""))))) -> 01.002.002.004 | J51: Outorga onerosa | K51: vb | L51: 1 | M51: 304741.36 | N51: =IF(H51="Serviço",M51*L51,IF(H51="CÉLULA CONSTRUTIVA",SUMIFS($N$8:$N$420,$B$8:$B$420,B51,$H$8:$H$420,"Serviço"),IF(H51="ETAPA",SUMIFS($N$8:$N$420,$B$8:$B$420,B51,$C$8:$C$420,C51,$H$8:$H$420,"Serviço"),IF(H51="SUBETAPA",SUMIFS($N$8:$N$420,$B$8:$B$420,B51,$C$8:$C$420,C51,$D$8:$D$420,D51,$H$8:$H$420,"Serviço"),0)))) -> 304741.36 | O51: Fornecido pelo whatsapp | P51: Lançado ERP
A52: =IF($H52="UNIDADE CONSTRUTIVA",OFFSET(A52,-1,0)+1,LARGE(A$3:A48,1)) -> 0 | B52: =IF(H52="UNIDADE CONSTRUTIVA",0,IF(H52="CÉLULA CONSTRUTIVA",OFFSET(B52,-1,0)+1,OFFSET(B52,-1,0))) -> 1 | C52: =IF(H52="CÉLULA CONSTRUTIVA",0,IF(H52="ETAPA",OFFSET(C52,-1,0)+1,OFFSET(C52,-1,0))) -> 2 | D52: =IF(H52="ETAPA",0,IF(H52="SUBETAPA",OFFSET(D52,-1,0)+1,OFFSET(D52,-1,0))) -> 2 | E52: =IF(H52="Subetapa",0,IF(H52="serviço",OFFSET(E52,-1,0)+1,OFFSET(E52,-1,0))) -> 5 | H52: SERVIÇO | I52: =IF(H52="Unidade Construtiva",TEXT(A52,"00"),IF(H52="Célula Construtiva",TEXT(B52,"00"),IF(H52="Etapa",CONCATENATE(TEXT(B52,"00"),".",TEXT(C52,"000")),IF(H52="Subetapa",CONCATENATE(TEXT(B52,"00"),".",TEXT(C52,"000"),".",TEXT(D52,"000")),IF(H52="Serviço",CONCATENATE(TEXT(B52,"00"),".",TEXT(C52,"000"),".",TEXT(D52,"000"),".",TEXT(E52,"000")),""))))) -> 01.002.002.005 | J52: Certidão Negativa de Debitos (Acompanhamento e Emissão Final) | K52: vb | L52: 1 | M52: 26466 | N52: =IF(H52="Serviço",M52*L52,IF(H52="CÉLULA CONSTRUTIVA",SUMIFS($N$8:$N$420,$B$8:$B$420,B52,$H$8:$H$420,"Serviço"),IF(H52="ETAPA",SUMIFS($N$8:$N$420,$B$8:$B$420,B52,$C$8:$C$420,C52,$H$8:$H$420,"Serviço"),IF(H52="SUBETAPA",SUMIFS($N$8:$N$420,$B$8:$B$420,B52,$C$8:$C$420,C52,$D$8:$D$420,D52,$H$8:$H$420,"Serviço"),0)))) -> 26466 | O52: Fornecido pelo whatsapp | P52: Lançado ERP
A53: =IF($H53="UNIDADE CONSTRUTIVA",OFFSET(A53,-1,0)+1,LARGE(A$3:A49,1)) -> 0 | B53: =IF(H53="UNIDADE CONSTRUTIVA",0,IF(H53="CÉLULA CONSTRUTIVA",OFFSET(B53,-1,0)+1,OFFSET(B53,-1,0))) -> 2 | C53: =IF(H53="CÉLULA CONSTRUTIVA",0,IF(H53="ETAPA",OFFSET(C53,-1,0)+1,OFFSET(C53,-1,0))) -> 0 | D53: =IF(H53="ETAPA",0,IF(H53="SUBETAPA",OFFSET(D53,-1,0)+1,OFFSET(D53,-1,0))) -> 2 | E53: =IF(H53="Subetapa",0,IF(H53="serviço",OFFSET(E53,-1,0)+1,OFFSET(E53,-1,0))) -> 5 | H53: CÉLULA CONSTRUTIVA | I53: =IF(H53="Unidade Construtiva",TEXT(A53,"00"),IF(H53="Célula Construtiva",TEXT(B53,"00"),IF(H53="Etapa",CONCATENATE(TEXT(B53,"00"),".",TEXT(C53,"000")),IF(H53="Subetapa",CONCATENATE(TEXT(B53,"00"),".",TEXT(C53,"000"),".",TEXT(D53,"000")),IF(H53="Serviço",CONCATENATE(TEXT(B53,"00"),".",TEXT(C53,"000"),".",TEXT(D53,"000"),".",TEXT(E53,"000")),""))))) -> 02 | J53: SERVIÇOS INICIAIS | N53: =IF(H53="Serviço",M53*L53,IF(H53="CÉLULA CONSTRUTIVA",SUMIFS($N$8:$N$420,$B$8:$B$420,B53,$H$8:$H$420,"Serviço"),IF(H53="ETAPA",SUMIFS($N$8:$N$420,$B$8:$B$420,B53,$C$8:$C$420,C53,$H$8:$H$420,"Serviço"),IF(H53="SUBETAPA",SUMIFS($N$8:$N$420,$B$8:$B$420,B53,$C$8:$C$420,C53,$D$8:$D$420,D53,$H$8:$H$420,"Serviço"),0)))) -> 1628436.7
A54: =IF($H54="UNIDADE CONSTRUTIVA",OFFSET(A54,-1,0)+1,LARGE(A$3:A53,1)) -> 0 | B54: =IF(H54="UNIDADE CONSTRUTIVA",0,IF(H54="CÉLULA CONSTRUTIVA",OFFSET(B54,-1,0)+1,OFFSET(B54,-1,0))) -> 2 | C54: =IF(H54="CÉLULA CONSTRUTIVA",0,IF(H54="ETAPA",OFFSET(C54,-1,0)+1,OFFSET(C54,-1,0))) -> 1 | D54: =IF(H54="ETAPA",0,IF(H54="SUBETAPA",OFFSET(D54,-1,0)+1,OFFSET(D54,-1,0))) -> 0 | E54: =IF(H54="Subetapa",0,IF(H54="serviço",OFFSET(E54,-1,0)+1,OFFSET(E54,-1,0))) -> 5 | H54: ETAPA | I54: =IF(H54="Unidade Construtiva",TEXT(A54,"00"),IF(H54="Célula Construtiva",TEXT(B54,"00"),IF(H54="Etapa",CONCATENATE(TEXT(B54,"00"),".",TEXT(C54,"000")),IF(H54="Subetapa",CONCATENATE(TEXT(B54,"00"),".",TEXT(C54,"000"),".",TEXT(D54,"000")),IF(H54="Serviço",CONCATENATE(TEXT(B54,"00"),".",TEXT(C54,"000"),".",TEXT(D54,"000"),".",TEXT(E54,"000")),""))))) -> 02.001 | J54: SEGURANÇA, MEIO AMBIENTE E SAÚDE | N54: =IF(H54="Serviço",M54*L54,IF(H54="CÉLULA CONSTRUTIVA",SUMIFS($N$8:$N$420,$B$8:$B$420,B54,$H$8:$H$420,"Serviço"),IF(H54="ETAPA",SUMIFS($N$8:$N$420,$B$8:$B$420,B54,$C$8:$C$420,C54,$H$8:$H$420,"Serviço"),IF(H54="SUBETAPA",SUMIFS($N$8:$N$420,$B$8:$B$420,B54,$C$8:$C$420,C54,$D$8:$D$420,D54,$H$8:$H$420,"Serviço"),0)))) -> 471877.49
A55: =IF($H55="UNIDADE CONSTRUTIVA",OFFSET(A55,-1,0)+1,LARGE(A$3:A54,1)) -> 0 | B55: =IF(H55="UNIDADE CONSTRUTIVA",0,IF(H55="CÉLULA CONSTRUTIVA",OFFSET(B55,-1,0)+1,OFFSET(B55,-1,0))) -> 2 | C55: =IF(H55="CÉLULA CONSTRUTIVA",0,IF(H55="ETAPA",OFFSET(C55,-1,0)+1,OFFSET(C55,-1,0))) -> 1 | D55: =IF(H55="ETAPA",0,IF(H55="SUBETAPA",OFFSET(D55,-1,0)+1,OFFSET(D55,-1,0))) -> 1 | E55: =IF(H55="Subetapa",0,IF(H55="serviço",OFFSET(E55,-1,0)+1,OFFSET(E55,-1,0))) -> 0 | H55: SUBETAPA | I55: =IF(H55="Unidade Construtiva",TEXT(A55,"00"),IF(H55="Célula Construtiva",TEXT(B55,"00"),IF(H55="Etapa",CONCATENATE(TEXT(B55,"00"),".",TEXT(C55,"000")),IF(H55="Subetapa",CONCATENATE(TEXT(B55,"00"),".",TEXT(C55,"000"),".",TEXT(D55,"000")),IF(H55="Serviço",CONCATENATE(TEXT(B55,"00"),".",TEXT(C55,"000"),".",TEXT(D55,"000"),".",TEXT(E55,"000")),""))))) -> 02.001.001 | J55: Segurança do Trabalho | N55: =IF(H55="Serviço",M55*L55,IF(H55="CÉLULA CONSTRUTIVA",SUMIFS($N$8:$N$420,$B$8:$B$420,B55,$H$8:$H$420,"Serviço"),IF(H55="ETAPA",SUMIFS($N$8:$N$420,$B$8:$B$420,B55,$C$8:$C$420,C55,$H$8:$H$420,"Serviço"),IF(H55="SUBETAPA",SUMIFS($N$8:$N$420,$B$8:$B$420,B55,$C$8:$C$420,C55,$D$8:$D$420,D55,$H$8:$H$420,"Serviço"),0)))) -> 96344.643
A56: =IF($H56="UNIDADE CONSTRUTIVA",OFFSET(A56,-1,0)+1,LARGE(A$3:A55,1)) -> 0 | B56: =IF(H56="UNIDADE CONSTRUTIVA",0,IF(H56="CÉLULA CONSTRUTIVA",OFFSET(B56,-1,0)+1,OFFSET(B56,-1,0))) -> 2 | C56: =IF(H56="CÉLULA CONSTRUTIVA",0,IF(H56="ETAPA",OFFSET(C56,-1,0)+1,OFFSET(C56,-1,0))) -> 1 | D56: =IF(H56="ETAPA",0,IF(H56="SUBETAPA",OFFSET(D56,-1,0)+1,OFFSET(D56,-1,0))) -> 1 | E56: =IF(H56="Subetapa",0,IF(H56="serviço",OFFSET(E56,-1,0)+1,OFFSET(E56,-1,0))) -> 1 | H56: SERVIÇO | I56: =IF(H56="Unidade Construtiva",TEXT(A56,"00"),IF(H56="Célula Construtiva",TEXT(B56,"00"),IF(H56="Etapa",CONCATENATE(TEXT(B56,"00"),".",TEXT(C56,"000")),IF(H56="Subetapa",CONCATENATE(TEXT(B56,"00"),".",TEXT(C56,"000"),".",TEXT(D56,"000")),IF(H56="Serviço",CONCATENATE(TEXT(B56,"00"),".",TEXT(C56,"000"),".",TEXT(D56,"000"),".",TEXT(E56,"000")),""))))) -> 02.001.001.001 | J56: Serviço de segurança do trabalho - Terceirizado | K56: mes | L56: ='Obra '!E7 -> 36 | M56: 1329.0179 | N56: =IF(H56="Serviço",M56*L56,IF(H56="CÉLULA CONSTRUTIVA",SUMIFS($N$8:$N$420,$B$8:$B$420,B56,$H$8:$H$420,"Serviço"),IF(H56="ETAPA",SUMIFS($N$8:$N$420,$B$8:$B$420,B56,$C$8:$C$420,C56,$H$8:$H$420,"Serviço"),IF(H56="SUBETAPA",SUMIFS($N$8:$N$420,$B$8:$B$420,B56,$C$8:$C$420,C56,$D$8:$D$420,D56,$H$8:$H$420,"Serviço"),0)))) -> 47844.643 | O56: Estimado com base em índices históricos | P56: Finalizado
A57: =IF($H57="UNIDADE CONSTRUTIVA",OFFSET(A57,-1,0)+1,LARGE(A$3:A56,1)) -> 0 | B57: =IF(H57="UNIDADE CONSTRUTIVA",0,IF(H57="CÉLULA CONSTRUTIVA",OFFSET(B57,-1,0)+1,OFFSET(B57,-1,0))) -> 2 | C57: =IF(H57="CÉLULA CONSTRUTIVA",0,IF(H57="ETAPA",OFFSET(C57,-1,0)+1,OFFSET(C57,-1,0))) -> 1 | D57: =IF(H57="ETAPA",0,IF(H57="SUBETAPA",OFFSET(D57,-1,0)+1,OFFSET(D57,-1,0))) -> 1 | E57: =IF(H57="Subetapa",0,IF(H57="serviço",OFFSET(E57,-1,0)+1,OFFSET(E57,-1,0))) -> 2 | H57: SERVIÇO | I57: =IF(H57="Unidade Construtiva",TEXT(A57,"00"),IF(H57="Célula Construtiva",TEXT(B57,"00"),IF(H57="Etapa",CONCATENATE(TEXT(B57,"00"),".",TEXT(C57,"000")),IF(H57="Subetapa",CONCATENATE(TEXT(B57,"00"),".",TEXT(C57,"000"),".",TEXT(D57,"000")),IF(H57="Serviço",CONCATENATE(TEXT(B57,"00"),".",TEXT(C57,"000"),".",TEXT(D57,"000"),".",TEXT(E57,"000")),""))))) -> 02.001.001.002 | J57: Equipamentos de proteção individual - EPI | K57: vb | L57: 1 | M57: 48500 | N57: =IF(H57="Serviço",M57*L57,IF(H57="CÉLULA CONSTRUTIVA",SUMIFS($N$8:$N$420,$B$8:$B$420,B57,$H$8:$H$420,"Serviço"),IF(H57="ETAPA",SUMIFS($N$8:$N$420,$B$8:$B$420,B57,$C$8:$C$420,C57,$H$8:$H$420,"Serviço"),IF(H57="SUBETAPA",SUMIFS($N$8:$N$420,$B$8:$B$420,B57,$C$8:$C$420,C57,$D$8:$D$420,D57,$H$8:$H$420,"Serviço"),0)))) -> 48500 | O57: Confrome cálculo da aba "Canteiro" | P57: Finalizado
A58: =IF($H58="UNIDADE CONSTRUTIVA",OFFSET(A58,-1,0)+1,LARGE(A$3:A57,1)) -> 0 | B58: =IF(H58="UNIDADE CONSTRUTIVA",0,IF(H58="CÉLULA CONSTRUTIVA",OFFSET(B58,-1,0)+1,OFFSET(B58,-1,0))) -> 2 | C58: =IF(H58="CÉLULA CONSTRUTIVA",0,IF(H58="ETAPA",OFFSET(C58,-1,0)+1,OFFSET(C58,-1,0))) -> 1 | D58: =IF(H58="ETAPA",0,IF(H58="SUBETAPA",OFFSET(D58,-1,0)+1,OFFSET(D58,-1,0))) -> 2 | E58: =IF(H58="Subetapa",0,IF(H58="serviço",OFFSET(E58,-1,0)+1,OFFSET(E58,-1,0))) -> 0 | H58: SUBETAPA | I58: =IF(H58="Unidade Construtiva",TEXT(A58,"00"),IF(H58="Célula Construtiva",TEXT(B58,"00"),IF(H58="Etapa",CONCATENATE(TEXT(B58,"00"),".",TEXT(C58,"000")),IF(H58="Subetapa",CONCATENATE(TEXT(B58,"00"),".",TEXT(C58,"000"),".",TEXT(D58,"000")),IF(H58="Serviço",CONCATENATE(TEXT(B58,"00"),".",TEXT(C58,"000"),".",TEXT(D58,"000"),".",TEXT(E58,"000")),""))))) -> 02.001.002 | J58: Equipamentos de proteção de canteiro | N58: =IF(H58="Serviço",M58*L58,IF(H58="CÉLULA CONSTRUTIVA",SUMIFS($N$8:$N$420,$B$8:$B$420,B58,$H$8:$H$420,"Serviço"),IF(H58="ETAPA",SUMIFS($N$8:$N$420,$B$8:$B$420,B58,$C$8:$C$420,C58,$H$8:$H$420,"Serviço"),IF(H58="SUBETAPA",SUMIFS($N$8:$N$420,$B$8:$B$420,B58,$C$8:$C$420,C58,$D$8:$D$420,D58,$H$8:$H$420,"Serviço"),0)))) -> 290250.03
A59: =IF($H59="UNIDADE CONSTRUTIVA",OFFSET(A59,-1,0)+1,LARGE(A$3:A58,1)) -> 0 | B59: =IF(H59="UNIDADE CONSTRUTIVA",0,IF(H59="CÉLULA CONSTRUTIVA",OFFSET(B59,-1,0)+1,OFFSET(B59,-1,0))) -> 2 | C59: =IF(H59="CÉLULA CONSTRUTIVA",0,IF(H59="ETAPA",OFFSET(C59,-1,0)+1,OFFSET(C59,-1,0))) -> 1 | D59: =IF(H59="ETAPA",0,IF(H59="SUBETAPA",OFFSET(D59,-1,0)+1,OFFSET(D59,-1,0))) -> 2 | E59: =IF(H59="Subetapa",0,IF(H59="serviço",OFFSET(E59,-1,0)+1,OFFSET(E59,-1,0))) -> 1 | H59: SERVIÇO | I59: =IF(H59="Unidade Construtiva",TEXT(A59,"00"),IF(H59="Célula Construtiva",TEXT(B59,"00"),IF(H59="Etapa",CONCATENATE(TEXT(B59,"00"),".",TEXT(C59,"000")),IF(H59="Subetapa",CONCATENATE(TEXT(B59,"00"),".",TEXT(C59,"000"),".",TEXT(D59,"000")),IF(H59="Serviço",CONCATENATE(TEXT(B59,"00"),".",TEXT(C59,"000"),".",TEXT(D59,"000"),".",TEXT(E59,"000")),""))))) -> 02.001.002.001 | J59: Bandeja de Proteção Primária com trama de madeira forrada com painel compensado | K59: m | L59: =EPCs!D11 -> 237.16345 | M59: 293.1196 | N59: =IF(H59="Serviço",M59*L59,IF(H59="CÉLULA CONSTRUTIVA",SUMIFS($N$8:$N$420,$B$8:$B$420,B59,$H$8:$H$420,"Serviço"),IF(H59="ETAPA",SUMIFS($N$8:$N$420,$B$8:$B$420,B59,$C$8:$C$420,C59,$H$8:$H$420,"Serviço"),IF(H59="SUBETAPA",SUMIFS($N$8:$N$420,$B$8:$B$420,B59,$C$8:$C$420,C59,$D$8:$D$420,D59,$H$8:$H$420,"Serviço"),0)))) -> 69517.256 | O59: Estimado com base em índices históricos | P59: Finalizado
A60: =IF($H60="UNIDADE CONSTRUTIVA",OFFSET(A60,-1,0)+1,LARGE(A$3:A59,1)) -> 0 | B60: =IF(H60="UNIDADE CONSTRUTIVA",0,IF(H60="CÉLULA CONSTRUTIVA",OFFSET(B60,-1,0)+1,OFFSET(B60,-1,0))) -> 2 | C60: =IF(H60="CÉLULA CONSTRUTIVA",0,IF(H60="ETAPA",OFFSET(C60,-1,0)+1,OFFSET(C60,-1,0))) -> 1 | D60: =IF(H60="ETAPA",0,IF(H60="SUBETAPA",OFFSET(D60,-1,0)+1,OFFSET(D60,-1,0))) -> 2 | E60: =IF(H60="Subetapa",0,IF(H60="serviço",OFFSET(E60,-1,0)+1,OFFSET(E60,-1,0))) -> 2 | H60: SERVIÇO | I60: =IF(H60="Unidade Construtiva",TEXT(A60,"00"),IF(H60="Célula Construtiva",TEXT(B60,"00"),IF(H60="Etapa",CONCATENATE(TEXT(B60,"00"),".",TEXT(C60,"000")),IF(H60="Subetapa",CONCATENATE(TEXT(B60,"00"),".",TEXT(C60,"000"),".",TEXT(D60,"000")),IF(H60="Serviço",CONCATENATE(TEXT(B60,"00"),".",TEXT(C60,"000"),".",TEXT(D60,"000"),".",TEXT(E60,"000")),""))))) -> 02.001.002.002 | J60: Bandeja de Proteção Seundária com trama de madeira forrada com painel compensado | K60: m | L60: =EPCs!D12 -> 205.84025 | M60: 288.1284 | N60: =IF(H60="Serviço",M60*L60,IF(H60="CÉLULA CONSTRUTIVA",SUMIFS($N$8:$N$420,$B$8:$B$420,B60,$H$8:$H$420,"Serviço"),IF(H60="ETAPA",SUMIFS($N$8:$N$420,$B$8:$B$420,B60,$C$8:$C$420,C60,$H$8:$H$420,"Serviço"),IF(H60="SUBETAPA",SUMIFS($N$8:$N$420,$B$8:$B$420,B60,$C$8:$C$420,C60,$D$8:$D$420,D60,$H$8:$H$420,"Serviço"),0)))) -> 59308.422 | O60: Estimado com base em índices históricos | P60: Finalizado
A61: =IF($H61="UNIDADE CONSTRUTIVA",OFFSET(A61,-1,0)+1,LARGE(A$3:A60,1)) -> 0 | B61: =IF(H61="UNIDADE CONSTRUTIVA",0,IF(H61="CÉLULA CONSTRUTIVA",OFFSET(B61,-1,0)+1,OFFSET(B61,-1,0))) -> 2 | C61: =IF(H61="CÉLULA CONSTRUTIVA",0,IF(H61="ETAPA",OFFSET(C61,-1,0)+1,OFFSET(C61,-1,0))) -> 1 | D61: =IF(H61="ETAPA",0,IF(H61="SUBETAPA",OFFSET(D61,-1,0)+1,OFFSET(D61,-1,0))) -> 2 | E61: =IF(H61="Subetapa",0,IF(H61="serviço",OFFSET(E61,-1,0)+1,OFFSET(E61,-1,0))) -> 3 | H61: SERVIÇO | I61: =IF(H61="Unidade Construtiva",TEXT(A61,"00"),IF(H61="Célula Construtiva",TEXT(B61,"00"),IF(H61="Etapa",CONCATENATE(TEXT(B61,"00"),".",TEXT(C61,"000")),IF(H61="Subetapa",CONCATENATE(TEXT(B61,"00"),".",TEXT(C61,"000"),".",TEXT(D61,"000")),IF(H61="Serviço",CONCATENATE(TEXT(B61,"00"),".",TEXT(C61,"000"),".",TEXT(D61,"000"),".",TEXT(E61,"000")),""))))) -> 02.001.002.003 | J61: Guarda-corpo de vãos, fixado em fôrma de madeira, em trama de madeira com tela de polipropileno | K61: m | L61: =EPCs!D18 -> 732.16312 | M61: 18.3067 | N61: =IF(H61="Serviço",M61*L61,IF(H61="CÉLULA CONSTRUTIVA",SUMIFS($N$8:$N$420,$B$8:$B$420,B61,$H$8:$H$420,"Serviço"),IF(H61="ETAPA",SUMIFS($N$8:$N$420,$B$8:$B$420,B61,$C$8:$C$420,C61,$H$8:$H$420,"Serviço"),IF(H61="SUBETAPA",SUMIFS($N$8:$N$420,$B$8:$B$420,B61,$C$8:$C$420,C61,$D$8:$D$420,D61,$H$8:$H$420,"Serviço"),0)))) -> 13403.491 | O61: Estimado com base em índices históricos | P61: Finalizado
A62: =IF($H62="UNIDADE CONSTRUTIVA",OFFSET(A62,-1,0)+1,LARGE(A$3:A61,1)) -> 0 | B62: =IF(H62="UNIDADE CONSTRUTIVA",0,IF(H62="CÉLULA CONSTRUTIVA",OFFSET(B62,-1,0)+1,OFFSET(B62,-1,0))) -> 2 | C62: =IF(H62="CÉLULA CONSTRUTIVA",0,IF(H62="ETAPA",OFFSET(C62,-1,0)+1,OFFSET(C62,-1,0))) -> 1 | D62: =IF(H62="ETAPA",0,IF(H62="SUBETAPA",OFFSET(D62,-1,0)+1,OFFSET(D62,-1,0))) -> 2 | E62: =IF(H62="Subetapa",0,IF(H62="serviço",OFFSET(E62,-1,0)+1,OFFSET(E62,-1,0))) -> 4 | H62: SERVIÇO | I62: =IF(H62="Unidade Construtiva",TEXT(A62,"00"),IF(H62="Célula Construtiva",TEXT(B62,"00"),IF(H62="Etapa",CONCATENATE(TEXT(B62,"00"),".",TEXT(C62,"000")),IF(H62="Subetapa",CONCATENATE(TEXT(B62,"00"),".",TEXT(C62,"000"),".",TEXT(D62,"000")),IF(H62="Serviço",CONCATENATE(TEXT(B62,"00"),".",TEXT(C62,"000"),".",TEXT(D62,"000"),".",TEXT(E62,"000")),""))))) -> 02.001.002.004 | J62: Guarda corpo de laje após desforma com escora metálica, travessões e tela | K62: m | L62: =EPCs!D25 -> 411.6805 | M62: 19.4843 | N62: =IF(H62="Serviço",M62*L62,IF(H62="CÉLULA CONSTRUTIVA",SUMIFS($N$8:$N$420,$B$8:$B$420,B62,$H$8:$H$420,"Serviço"),IF(H62="ETAPA",SUMIFS($N$8:$N$420,$B$8:$B$420,B62,$C$8:$C$420,C62,$H$8:$H$420,"Serviço"),IF(H62="SUBETAPA",SUMIFS($N$8:$N$420,$B$8:$B$420,B62,$C$8:$C$420,C62,$D$8:$D$420,D62,$H$8:$H$420,"Serviço"),0)))) -> 8021.3064 | O62: Estimado com base em índices históricos | P62: Finalizado
A63: =IF($H63="UNIDADE CONSTRUTIVA",OFFSET(A63,-1,0)+1,LARGE(A$3:A62,1)) -> 0 | B63: =IF(H63="UNIDADE CONSTRUTIVA",0,IF(H63="CÉLULA CONSTRUTIVA",OFFSET(B63,-1,0)+1,OFFSET(B63,-1,0))) -> 2 | C63: =IF(H63="CÉLULA CONSTRUTIVA",0,IF(H63="ETAPA",OFFSET(C63,-1,0)+1,OFFSET(C63,-1,0))) -> 1 | D63: =IF(H63="ETAPA",0,IF(H63="SUBETAPA",OFFSET(D63,-1,0)+1,OFFSET(D63,-1,0))) -> 2 | E63: =IF(H63="Subetapa",0,IF(H63="serviço",OFFSET(E63,-1,0)+1,OFFSET(E63,-1,0))) -> 5 | H63: SERVIÇO | I63: =IF(H63="Unidade Construtiva",TEXT(A63,"00"),IF(H63="Célula Construtiva",TEXT(B63,"00"),IF(H63="Etapa",CONCATENATE(TEXT(B63,"00"),".",TEXT(C63,"000")),IF(H63="Subetapa",CONCATENATE(TEXT(B63,"00"),".",TEXT(C63,"000"),".",TEXT(D63,"000")),IF(H63="Serviço",CONCATENATE(TEXT(B63,"00"),".",TEXT(C63,"000"),".",TEXT(D63,"000"),".",TEXT(E63,"000")),""))))) -> 02.001.002.005 | J63: Fechamento removível de vãos de porta de elevador em madeira | K63: m2 | L63: =EPCs!D33 -> 166.95 | M63: 97.7994 | N63: =IF(H63="Serviço",M63*L63,IF(H63="CÉLULA CONSTRUTIVA",SUMIFS($N$8:$N$420,$B$8:$B$420,B63,$H$8:$H$420,"Serviço"),IF(H63="ETAPA",SUMIFS($N$8:$N$420,$B$8:$B$420,B63,$C$8:$C$420,C63,$H$8:$H$420,"Serviço"),IF(H63="SUBETAPA",SUMIFS($N$8:$N$420,$B$8:$B$420,B63,$C$8:$C$420,C63,$D$8:$D$420,D63,$H$8:$H$420,"Serviço"),0)))) -> 16327.61 | O63: Estimado com base em índices históricos | P63: Finalizado
A64: =IF($H64="UNIDADE CONSTRUTIVA",OFFSET(A64,-1,0)+1,LARGE(A$3:A63,1)) -> 0 | B64: =IF(H64="UNIDADE CONSTRUTIVA",0,IF(H64="CÉLULA CONSTRUTIVA",OFFSET(B64,-1,0)+1,OFFSET(B64,-1,0))) -> 2 | C64: =IF(H64="CÉLULA CONSTRUTIVA",0,IF(H64="ETAPA",OFFSET(C64,-1,0)+1,OFFSET(C64,-1,0))) -> 1 | D64: =IF(H64="ETAPA",0,IF(H64="SUBETAPA",OFFSET(D64,-1,0)+1,OFFSET(D64,-1,0))) -> 2 | E64: =IF(H64="Subetapa",0,IF(H64="serviço",OFFSET(E64,-1,0)+1,OFFSET(E64,-1,0))) -> 6 | H64: SERVIÇO | I64: =IF(H64="Unidade Construtiva",TEXT(A64,"00"),IF(H64="Célula Construtiva",TEXT(B64,"00"),IF(H64="Etapa",CONCATENATE(TEXT(B64,"00"),".",TEXT(C64,"000")),IF(H64="Subetapa",CONCATENATE(TEXT(B64,"00"),".",TEXT(C64,"000"),".",TEXT(D64,"000")),IF(H64="Serviço",CONCATENATE(TEXT(B64,"00"),".",TEXT(C64,"000"),".",TEXT(D64,"000"),".",TEXT(E64,"000")),""))))) -> 02.001.002.006 | J64: Tela fachadeira de polietileno reforçada com impressão digital | K64: m2 | L64: =EPCs!D42 -> 7170.7992 | M64: 10.585 | N64: =IF(H64="Serviço",M64*L64,IF(H64="CÉLULA CONSTRUTIVA",SUMIFS($N$8:$N$420,$B$8:$B$420,B64,$H$8:$H$420,"Serviço"),IF(H64="ETAPA",SUMIFS($N$8:$N$420,$B$8:$B$420,B64,$C$8:$C$420,C64,$H$8:$H$420,"Serviço"),IF(H64="SUBETAPA",SUMIFS($N$8:$N$420,$B$8:$B$420,B64,$C$8:$C$420,C64,$D$8:$D$420,D64,$H$8:$H$420,"Serviço"),0)))) -> 75902.909 | O64: Estimado com base em índices históricos | P64: Finalizado
A65: =IF($H65="UNIDADE CONSTRUTIVA",OFFSET(A65,-1,0)+1,LARGE(A$3:A64,1)) -> 0 | B65: =IF(H65="UNIDADE CONSTRUTIVA",0,IF(H65="CÉLULA CONSTRUTIVA",OFFSET(B65,-1,0)+1,OFFSET(B65,-1,0))) -> 2 | C65: =IF(H65="CÉLULA CONSTRUTIVA",0,IF(H65="ETAPA",OFFSET(C65,-1,0)+1,OFFSET(C65,-1,0))) -> 1 | D65: =IF(H65="ETAPA",0,IF(H65="SUBETAPA",OFFSET(D65,-1,0)+1,OFFSET(D65,-1,0))) -> 2 | E65: =IF(H65="Subetapa",0,IF(H65="serviço",OFFSET(E65,-1,0)+1,OFFSET(E65,-1,0))) -> 7 | H65: SERVIÇO | I65: =IF(H65="Unidade Construtiva",TEXT(A65,"00"),IF(H65="Célula Construtiva",TEXT(B65,"00"),IF(H65="Etapa",CONCATENATE(TEXT(B65,"00"),".",TEXT(C65,"000")),IF(H65="Subetapa",CONCATENATE(TEXT(B65,"00"),".",TEXT(C65,"000"),".",TEXT(D65,"000")),IF(H65="Serviço",CONCATENATE(TEXT(B65,"00"),".",TEXT(C65,"000"),".",TEXT(D65,"000"),".",TEXT(E65,"000")),""))))) -> 02.001.002.007 | J65: Linha de vida | K65: m | L65: =EPCs!D63 -> 411.6805 | M65: 87.2015 | N65: =IF(H65="Serviço",M65*L65,IF(H65="CÉLULA CONSTRUTIVA",SUMIFS($N$8:$N$420,$B$8:$B$420,B65,$H$8:$H$420,"Serviço"),IF(H65="ETAPA",SUMIFS($N$8:$N$420,$B$8:$B$420,B65,$C$8:$C$420,C65,$H$8:$H$420,"Serviço"),IF(H65="SUBETAPA",SUMIFS($N$8:$N$420,$B$8:$B$420,B65,$C$8:$C$420,C65,$D$8:$D$420,D65,$H$8:$H$420,"Serviço"),0)))) -> 35899.157 | O65: Estimado com base em índices históricos | P65: Finalizado
A66: =IF($H66="UNIDADE CONSTRUTIVA",OFFSET(A66,-1,0)+1,LARGE(A$3:A65,1)) -> 0 | B66: =IF(H66="UNIDADE CONSTRUTIVA",0,IF(H66="CÉLULA CONSTRUTIVA",OFFSET(B66,-1,0)+1,OFFSET(B66,-1,0))) -> 2 | C66: =IF(H66="CÉLULA CONSTRUTIVA",0,IF(H66="ETAPA",OFFSET(C66,-1,0)+1,OFFSET(C66,-1,0))) -> 1 | D66: =IF(H66="ETAPA",0,IF(H66="SUBETAPA",OFFSET(D66,-1,0)+1,OFFSET(D66,-1,0))) -> 2 | E66: =IF(H66="Subetapa",0,IF(H66="serviço",OFFSET(E66,-1,0)+1,OFFSET(E66,-1,0))) -> 8 | H66: SERVIÇO | I66: =IF(H66="Unidade Construtiva",TEXT(A66,"00"),IF(H66="Célula Construtiva",TEXT(B66,"00"),IF(H66="Etapa",CONCATENATE(TEXT(B66,"00"),".",TEXT(C66,"000")),IF(H66="Subetapa",CONCATENATE(TEXT(B66,"00"),".",TEXT(C66,"000"),".",TEXT(D66,"000")),IF(H66="Serviço",CONCATENATE(TEXT(B66,"00"),".",TEXT(C66,"000"),".",TEXT(D66,"000"),".",TEXT(E66,"000")),""))))) -> 02.001.002.008 | J66: Sinalizacao geral da obra | K66: vb | L66: 1 | M66: 11869.875 | N66: =IF(H66="Serviço",M66*L66,IF(H66="CÉLULA CONSTRUTIVA",SUMIFS($N$8:$N$420,$B$8:$B$420,B66,$H$8:$H$420,"Serviço"),IF(H66="ETAPA",SUMIFS($N$8:$N$420,$B$8:$B$420,B66,$C$8:$C$420,C66,$H$8:$H$420,"Serviço"),IF(H66="SUBETAPA",SUMIFS($N$8:$N$420,$B$8:$B$420,B66,$C$8:$C$420,C66,$D$8:$D$420,D66,$H$8:$H$420,"Serviço"),0)))) -> 11869.875 | O66: Estimado com base em índices históricos | P66: Finalizado
A67: =IF($H67="UNIDADE CONSTRUTIVA",OFFSET(A67,-1,0)+1,LARGE(A$3:A66,1)) -> 0 | B67: =IF(H67="UNIDADE CONSTRUTIVA",0,IF(H67="CÉLULA CONSTRUTIVA",OFFSET(B67,-1,0)+1,OFFSET(B67,-1,0))) -> 2 | C67: =IF(H67="CÉLULA CONSTRUTIVA",0,IF(H67="ETAPA",OFFSET(C67,-1,0)+1,OFFSET(C67,-1,0))) -> 1 | D67: =IF(H67="ETAPA",0,IF(H67="SUBETAPA",OFFSET(D67,-1,0)+1,OFFSET(D67,-1,0))) -> 3 | E67: =IF(H67="Subetapa",0,IF(H67="serviço",OFFSET(E67,-1,0)+1,OFFSET(E67,-1,0))) -> 0 | H67: SUBETAPA | I67: =IF(H67="Unidade Construtiva",TEXT(A67,"00"),IF(H67="Célula Construtiva",TEXT(B67,"00"),IF(H67="Etapa",CONCATENATE(TEXT(B67,"00"),".",TEXT(C67,"000")),IF(H67="Subetapa",CONCATENATE(TEXT(B67,"00"),".",TEXT(C67,"000"),".",TEXT(D67,"000")),IF(H67="Serviço",CONCATENATE(TEXT(B67,"00"),".",TEXT(C67,"000"),".",TEXT(D67,"000"),".",TEXT(E67,"000")),""))))) -> 02.001.003 | J67: Meio Ambiente | N67: =IF(H67="Serviço",M67*L67,IF(H67="CÉLULA CONSTRUTIVA",SUMIFS($N$8:$N$420,$B$8:$B$420,B67,$H$8:$H$420,"Serviço"),IF(H67="ETAPA",SUMIFS($N$8:$N$420,$B$8:$B$420,B67,$C$8:$C$420,C67,$H$8:$H$420,"Serviço"),IF(H67="SUBETAPA",SUMIFS($N$8:$N$420,$B$8:$B$420,B67,$C$8:$C$420,C67,$D$8:$D$420,D67,$H$8:$H$420,"Serviço"),0)))) -> 85282.82
A68: =IF($H68="UNIDADE CONSTRUTIVA",OFFSET(A68,-1,0)+1,LARGE(A$3:A67,1)) -> 0 | B68: =IF(H68="UNIDADE CONSTRUTIVA",0,IF(H68="CÉLULA CONSTRUTIVA",OFFSET(B68,-1,0)+1,OFFSET(B68,-1,0))) -> 2 | C68: =IF(H68="CÉLULA CONSTRUTIVA",0,IF(H68="ETAPA",OFFSET(C68,-1,0)+1,OFFSET(C68,-1,0))) -> 1 | D68: =IF(H68="ETAPA",0,IF(H68="SUBETAPA",OFFSET(D68,-1,0)+1,OFFSET(D68,-1,0))) -> 3 | E68: =IF(H68="Subetapa",0,IF(H68="serviço",OFFSET(E68,-1,0)+1,OFFSET(E68,-1,0))) -> 1 | H68: SERVIÇO | I68: =IF(H68="Unidade Construtiva",TEXT(A68,"00"),IF(H68="Célula Construtiva",TEXT(B68,"00"),IF(H68="Etapa",CONCATENATE(TEXT(B68,"00"),".",TEXT(C68,"000")),IF(H68="Subetapa",CONCATENATE(TEXT(B68,"00"),".",TEXT(C68,"000"),".",TEXT(D68,"000")),IF(H68="Serviço",CONCATENATE(TEXT(B68,"00"),".",TEXT(C68,"000"),".",TEXT(D68,"000"),".",TEXT(E68,"000")),""))))) -> 02.001.003.001 | J68: Elaboração do Programa de Gerenciamento de Riscos (PGR) | K68: vb | L68: 1 | M68: 5188.7928 | N68: =IF(H68="Serviço",M68*L68,IF(H68="CÉLULA CONSTRUTIVA",SUMIFS($N$8:$N$420,$B$8:$B$420,B68,$H$8:$H$420,"Serviço"),IF(H68="ETAPA",SUMIFS($N$8:$N$420,$B$8:$B$420,B68,$C$8:$C$420,C68,$H$8:$H$420,"Serviço"),IF(H68="SUBETAPA",SUMIFS($N$8:$N$420,$B$8:$B$420,B68,$C$8:$C$420,C68,$D$8:$D$420,D68,$H$8:$H$420,"Serviço"),0)))) -> 5188.7928 | O68: Estimado com base em índices históricos | P68: Finalizado
A69: =IF($H69="UNIDADE CONSTRUTIVA",OFFSET(A69,-1,0)+1,LARGE(A$3:A68,1)) -> 0 | B69: =IF(H69="UNIDADE CONSTRUTIVA",0,IF(H69="CÉLULA CONSTRUTIVA",OFFSET(B69,-1,0)+1,OFFSET(B69,-1,0))) -> 2 | C69: =IF(H69="CÉLULA CONSTRUTIVA",0,IF(H69="ETAPA",OFFSET(C69,-1,0)+1,OFFSET(C69,-1,0))) -> 1 | D69: =IF(H69="ETAPA",0,IF(H69="SUBETAPA",OFFSET(D69,-1,0)+1,OFFSET(D69,-1,0))) -> 3 | E69: =IF(H69="Subetapa",0,IF(H69="serviço",OFFSET(E69,-1,0)+1,OFFSET(E69,-1,0))) -> 2 | H69: SERVIÇO | I69: =IF(H69="Unidade Construtiva",TEXT(A69,"00"),IF(H69="Célula Construtiva",TEXT(B69,"00"),IF(H69="Etapa",CONCATENATE(TEXT(B69,"00"),".",TEXT(C69,"000")),IF(H69="Subetapa",CONCATENATE(TEXT(B69,"00"),".",TEXT(C69,"000"),".",TEXT(D69,"000")),IF(H69="Serviço",CONCATENATE(TEXT(B69,"00"),".",TEXT(C69,"000"),".",TEXT(D69,"000"),".",TEXT(E69,"000")),""))))) -> 02.001.003.002 | J69: Elaboração do Programa de Controle Médico de Saúde Ocupacional (PCMSO) | K69: vb | L69: 1 | M69: 3457.777 | N69: =IF(H69="Serviço",M69*L69,IF(H69="CÉLULA CONSTRUTIVA",SUMIFS($N$8:$N$420,$B$8:$B$420,B69,$H$8:$H$420,"Serviço"),IF(H69="ETAPA",SUMIFS($N$8:$N$420,$B$8:$B$420,B69,$C$8:$C$420,C69,$H$8:$H$420,"Serviço"),IF(H69="SUBETAPA",SUMIFS($N$8:$N$420,$B$8:$B$420,B69,$C$8:$C$420,C69,$D$8:$D$420,D69,$H$8:$H$420,"Serviço"),0)))) -> 3457.777 | O69: Estimado com base em índices históricos | P69: Finalizado
A70: =IF($H70="UNIDADE CONSTRUTIVA",OFFSET(A70,-1,0)+1,LARGE(A$3:A69,1)) -> 0 | B70: =IF(H70="UNIDADE CONSTRUTIVA",0,IF(H70="CÉLULA CONSTRUTIVA",OFFSET(B70,-1,0)+1,OFFSET(B70,-1,0))) -> 2 | C70: =IF(H70="CÉLULA CONSTRUTIVA",0,IF(H70="ETAPA",OFFSET(C70,-1,0)+1,OFFSET(C70,-1,0))) -> 1 | D70: =IF(H70="ETAPA",0,IF(H70="SUBETAPA",OFFSET(D70,-1,0)+1,OFFSET(D70,-1,0))) -> 3 | E70: =IF(H70="Subetapa",0,IF(H70="serviço",OFFSET(E70,-1,0)+1,OFFSET(E70,-1,0))) -> 3 | H70: SERVIÇO | I70: =IF(H70="Unidade Construtiva",TEXT(A70,"00"),IF(H70="Célula Construtiva",TEXT(B70,"00"),IF(H70="Etapa",CONCATENATE(TEXT(B70,"00"),".",TEXT(C70,"000")),IF(H70="Subetapa",CONCATENATE(TEXT(B70,"00"),".",TEXT(C70,"000"),".",TEXT(D70,"000")),IF(H70="Serviço",CONCATENATE(TEXT(B70,"00"),".",TEXT(C70,"000"),".",TEXT(D70,"000"),".",TEXT(E70,"000")),""))))) -> 02.001.003.003 | J70: Projetos de Segurança do Trabalho | K70: vb | L70: 1 | M70: 4636.2504 | N70: =IF(H70="Serviço",M70*L70,IF(H70="CÉLULA CONSTRUTIVA",SUMIFS($N$8:$N$420,$B$8:$B$420,B70,$H$8:$H$420,"Serviço"),IF(H70="ETAPA",SUMIFS($N$8:$N$420,$B$8:$B$420,B70,$C$8:$C$420,C70,$H$8:$H$420,"Serviço"),IF(H70="SUBETAPA",SUMIFS($N$8:$N$420,$B$8:$B$420,B70,$C$8:$C$420,C70,$D$8:$D$420,D70,$H$8:$H$420,"Serviço"),0)))) -> 4636.2504 | O70: Estimado com base em índices históricos | P70: Finalizado
A71: =IF($H71="UNIDADE CONSTRUTIVA",OFFSET(A71,-1,0)+1,LARGE(A$3:A70,1)) -> 0 | B71: =IF(H71="UNIDADE CONSTRUTIVA",0,IF(H71="CÉLULA CONSTRUTIVA",OFFSET(B71,-1,0)+1,OFFSET(B71,-1,0))) -> 2 | C71: =IF(H71="CÉLULA CONSTRUTIVA",0,IF(H71="ETAPA",OFFSET(C71,-1,0)+1,OFFSET(C71,-1,0))) -> 1 | D71: =IF(H71="ETAPA",0,IF(H71="SUBETAPA",OFFSET(D71,-1,0)+1,OFFSET(D71,-1,0))) -> 3 | E71: =IF(H71="Subetapa",0,IF(H71="serviço",OFFSET(E71,-1,0)+1,OFFSET(E71,-1,0))) -> 4 | H71: SERVIÇO | I71: =IF(H71="Unidade Construtiva",TEXT(A71,"00"),IF(H71="Célula Construtiva",TEXT(B71,"00"),IF(H71="Etapa",CONCATENATE(TEXT(B71,"00"),".",TEXT(C71,"000")),IF(H71="Subetapa",CONCATENATE(TEXT(B71,"00"),".",TEXT(C71,"000"),".",TEXT(D71,"000")),IF(H71="Serviço",CONCATENATE(TEXT(B71,"00"),".",TEXT(C71,"000"),".",TEXT(D71,"000"),".",TEXT(E71,"000")),""))))) -> 02.001.003.004 | J71: Remoção de entulhos e resíduos | K71: mes | L71: ='Obra '!E7 -> 36 | M71: 2000 | N71: =IF(H71="Serviço",M71*L71,IF(H71="CÉLULA CONSTRUTIVA",SUMIFS($N$8:$N$420,$B$8:$B$420,B71,$H$8:$H$420,"Serviço"),IF(H71="ETAPA",SUMIFS($N$8:$N$420,$B$8:$B$420,B71,$C$8:$C$420,C71,$H$8:$H$420,"Serviço"),IF(H71="SUBETAPA",SUMIFS($N$8:$N$420,$B$8:$B$420,B71,$C$8:$C$420,C71,$D$8:$D$420,D71,$H$8:$H$420,"Serviço"),0)))) -> 72000 | O71: Consideração de 4 caçambas de 5m³ ao mês - prevendo custo de 500,00/caçamba | P71: Finalizado
A72: =IF($H72="UNIDADE CONSTRUTIVA",OFFSET(A72,-1,0)+1,LARGE(A$3:A71,1)) -> 0 | B72: =IF(H72="UNIDADE CONSTRUTIVA",0,IF(H72="CÉLULA CONSTRUTIVA",OFFSET(B72,-1,0)+1,OFFSET(B72,-1,0))) -> 2 | C72: =IF(H72="CÉLULA CONSTRUTIVA",0,IF(H72="ETAPA",OFFSET(C72,-1,0)+1,OFFSET(C72,-1,0))) -> 2 | D72: =IF(H72="ETAPA",0,IF(H72="SUBETAPA",OFFSET(D72,-1,0)+1,OFFSET(D72,-1,0))) -> 0 | E72: =IF(H72="Subetapa",0,IF(H72="serviço",OFFSET(E72,-1,0)+1,OFFSET(E72,-1,0))) -> 4 | H72: ETAPA | I72: =IF(H72="Unidade Construtiva",TEXT(A72,"00"),IF(H72="Célula Construtiva",TEXT(B72,"00"),IF(H72="Etapa",CONCATENATE(TEXT(B72,"00"),".",TEXT(C72,"000")),IF(H72="Subetapa",CONCATENATE(TEXT(B72,"00"),".",TEXT(C72,"000"),".",TEXT(D72,"000")),IF(H72="Serviço",CONCATENATE(TEXT(B72,"00"),".",TEXT(C72,"000"),".",TEXT(D72,"000"),".",TEXT(E72,"000")),""))))) -> 02.002 | J72: ADMINISTRAÇÃO E CANTEIRO DE OBRA | N72: =IF(H72="Serviço",M72*L72,IF(H72="CÉLULA CONSTRUTIVA",SUMIFS($N$8:$N$420,$B$8:$B$420,B72,$H$8:$H$420,"Serviço"),IF(H72="ETAPA",SUMIFS($N$8:$N$420,$B$8:$B$420,B72,$C$8:$C$420,C72,$H$8:$H$420,"Serviço"),IF(H72="SUBETAPA",SUMIFS($N$8:$N$420,$B$8:$B$420,B72,$C$8:$C$420,C72,$D$8:$D$420,D72,$H$8:$H$420,"Serviço"),0)))) -> 1156559.2
A73: =IF($H73="UNIDADE CONSTRUTIVA",OFFSET(A73,-1,0)+1,LARGE(A$3:A72,1)) -> 0 | B73: =IF(H73="UNIDADE CONSTRUTIVA",0,IF(H73="CÉLULA CONSTRUTIVA",OFFSET(B73,-1,0)+1,OFFSET(B73,-1,0))) -> 2 | C73: =IF(H73="CÉLULA CONSTRUTIVA",0,IF(H73="ETAPA",OFFSET(C73,-1,0)+1,OFFSET(C73,-1,0))) -> 2 | D73: =IF(H73="ETAPA",0,IF(H73="SUBETAPA",OFFSET(D73,-1,0)+1,OFFSET(D73,-1,0))) -> 1 | E73: =IF(H73="Subetapa",0,IF(H73="serviço",OFFSET(E73,-1,0)+1,OFFSET(E73,-1,0))) -> 0 | H73: SUBETAPA | I73: =IF(H73="Unidade Construtiva",TEXT(A73,"00"),IF(H73="Célula Construtiva",TEXT(B73,"00"),IF(H73="Etapa",CONCATENATE(TEXT(B73,"00"),".",TEXT(C73,"000")),IF(H73="Subetapa",CONCATENATE(TEXT(B73,"00"),".",TEXT(C73,"000"),".",TEXT(D73,"000")),IF(H73="Serviço",CONCATENATE(TEXT(B73,"00"),".",TEXT(C73,"000"),".",TEXT(D73,"000"),".",TEXT(E73,"000")),""))))) -> 02.002.001 | J73: Equipe de Gestão e Apoio | N73: =IF(H73="Serviço",M73*L73,IF(H73="CÉLULA CONSTRUTIVA",SUMIFS($N$8:$N$420,$B$8:$B$420,B73,$H$8:$H$420,"Serviço"),IF(H73="ETAPA",SUMIFS($N$8:$N$420,$B$8:$B$420,B73,$C$8:$C$420,C73,$H$8:$H$420,"Serviço"),IF(H73="SUBETAPA",SUMIFS($N$8:$N$420,$B$8:$B$420,B73,$C$8:$C$420,C73,$D$8:$D$420,D73,$H$8:$H$420,"Serviço"),0)))) -> 588536
A74: =IF($H74="UNIDADE CONSTRUTIVA",OFFSET(A74,-1,0)+1,LARGE(A$3:A73,1)) -> 0 | B74: =IF(H74="UNIDADE CONSTRUTIVA",0,IF(H74="CÉLULA CONSTRUTIVA",OFFSET(B74,-1,0)+1,OFFSET(B74,-1,0))) -> 2 | C74: =IF(H74="CÉLULA CONSTRUTIVA",0,IF(H74="ETAPA",OFFSET(C74,-1,0)+1,OFFSET(C74,-1,0))) -> 2 | D74: =IF(H74="ETAPA",0,IF(H74="SUBETAPA",OFFSET(D74,-1,0)+1,OFFSET(D74,-1,0))) -> 1 | E74: =IF(H74="Subetapa",0,IF(H74="serviço",OFFSET(E74,-1,0)+1,OFFSET(E74,-1,0))) -> 1 | H74: SERVIÇO | I74: =IF(H74="Unidade Construtiva",TEXT(A74,"00"),IF(H74="Célula Construtiva",TEXT(B74,"00"),IF(H74="Etapa",CONCATENATE(TEXT(B74,"00"),".",TEXT(C74,"000")),IF(H74="Subetapa",CONCATENATE(TEXT(B74,"00"),".",TEXT(C74,"000"),".",TEXT(D74,"000")),IF(H74="Serviço",CONCATENATE(TEXT(B74,"00"),".",TEXT(C74,"000"),".",TEXT(D74,"000"),".",TEXT(E74,"000")),""))))) -> 02.002.001.001 | J74: Engenheiro | K74: mes | L74: 33 | M74: 7392 | N74: =IF(H74="Serviço",M74*L74,IF(H74="CÉLULA CONSTRUTIVA",SUMIFS($N$8:$N$420,$B$8:$B$420,B74,$H$8:$H$420,"Serviço"),IF(H74="ETAPA",SUMIFS($N$8:$N$420,$B$8:$B$420,B74,$C$8:$C$420,C74,$H$8:$H$420,"Serviço"),IF(H74="SUBETAPA",SUMIFS($N$8:$N$420,$B$8:$B$420,B74,$C$8:$C$420,C74,$D$8:$D$420,D74,$H$8:$H$420,"Serviço"),0)))) -> 243936 | O74: Valor informado em formulário Marena | P74: Finalizado
A75: =IF($H75="UNIDADE CONSTRUTIVA",OFFSET(A75,-1,0)+1,LARGE(A$3:A74,1)) -> 0 | B75: =IF(H75="UNIDADE CONSTRUTIVA",0,IF(H75="CÉLULA CONSTRUTIVA",OFFSET(B75,-1,0)+1,OFFSET(B75,-1,0))) -> 2 | C75: =IF(H75="CÉLULA CONSTRUTIVA",0,IF(H75="ETAPA",OFFSET(C75,-1,0)+1,OFFSET(C75,-1,0))) -> 2 | D75: =IF(H75="ETAPA",0,IF(H75="SUBETAPA",OFFSET(D75,-1,0)+1,OFFSET(D75,-1,0))) -> 1 | E75: =IF(H75="Subetapa",0,IF(H75="serviço",OFFSET(E75,-1,0)+1,OFFSET(E75,-1,0))) -> 2 | H75: SERVIÇO | I75: =IF(H75="Unidade Construtiva",TEXT(A75,"00"),IF(H75="Célula Construtiva",TEXT(B75,"00"),IF(H75="Etapa",CONCATENATE(TEXT(B75,"00"),".",TEXT(C75,"000")),IF(H75="Subetapa",CONCATENATE(TEXT(B75,"00"),".",TEXT(C75,"000"),".",TEXT(D75,"000")),IF(H75="Serviço",CONCATENATE(TEXT(B75,"00"),".",TEXT(C75,"000"),".",TEXT(D75,"000"),".",TEXT(E75,"000")),""))))) -> 02.002.001.002 | J75: Mestre de Obras | K75: mes | L75: 27 | M75: 8500 | N75: =IF(H75="Serviço",M75*L75,IF(H75="CÉLULA CONSTRUTIVA",SUMIFS($N$8:$N$420,$B$8:$B$420,B75,$H$8:$H$420,"Serviço"),IF(H75="ETAPA",SUMIFS($N$8:$N$420,$B$8:$B$420,B75,$C$8:$C$420,C75,$H$8:$H$420,"Serviço"),IF(H75="SUBETAPA",SUMIFS($N$8:$N$420,$B$8:$B$420,B75,$C$8:$C$420,C75,$D$8:$D$420,D75,$H$8:$H$420,"Serviço"),0)))) -> 229500 | O75: Valor informado em formulário Marena | P75: Finalizado
A76: =IF($H76="UNIDADE CONSTRUTIVA",OFFSET(A76,-1,0)+1,LARGE(A$3:A75,1)) -> 0 | B76: =IF(H76="UNIDADE CONSTRUTIVA",0,IF(H76="CÉLULA CONSTRUTIVA",OFFSET(B76,-1,0)+1,OFFSET(B76,-1,0))) -> 2 | C76: =IF(H76="CÉLULA CONSTRUTIVA",0,IF(H76="ETAPA",OFFSET(C76,-1,0)+1,OFFSET(C76,-1,0))) -> 2 | D76: =IF(H76="ETAPA",0,IF(H76="SUBETAPA",OFFSET(D76,-1,0)+1,OFFSET(D76,-1,0))) -> 1 | E76: =IF(H76="Subetapa",0,IF(H76="serviço",OFFSET(E76,-1,0)+1,OFFSET(E76,-1,0))) -> 3 | H76: SERVIÇO | I76: =IF(H76="Unidade Construtiva",TEXT(A76,"00"),IF(H76="Célula Construtiva",TEXT(B76,"00"),IF(H76="Etapa",CONCATENATE(TEXT(B76,"00"),".",TEXT(C76,"000")),IF(H76="Subetapa",CONCATENATE(TEXT(B76,"00"),".",TEXT(C76,"000"),".",TEXT(D76,"000")),IF(H76="Serviço",CONCATENATE(TEXT(B76,"00"),".",TEXT(C76,"000"),".",TEXT(D76,"000"),".",TEXT(E76,"000")),""))))) -> 02.002.001.003 | J76: Almoxarife | K76: mes | L76: 27 | M76: 3300 | N76: =IF(H76="Serviço",M76*L76,IF(H76="CÉLULA CONSTRUTIVA",SUMIFS($N$8:$N$420,$B$8:$B$420,B76,$H$8:$H$420,"Serviço"),IF(H76="ETAPA",SUMIFS($N$8:$N$420,$B$8:$B$420,B76,$C$8:$C$420,C76,$H$8:$H$420,"Serviço"),IF(H76="SUBETAPA",SUMIFS($N$8:$N$420,$B$8:$B$420,B76,$C$8:$C$420,C76,$D$8:$D$420,D76,$H$8:$H$420,"Serviço"),0)))) -> 89100 | O76: Valor informado em formulário Marena | P76: Finalizado
A77: =IF($H77="UNIDADE CONSTRUTIVA",OFFSET(A77,-1,0)+1,LARGE(A$3:A76,1)) -> 0 | B77: =IF(H77="UNIDADE CONSTRUTIVA",0,IF(H77="CÉLULA CONSTRUTIVA",OFFSET(B77,-1,0)+1,OFFSET(B77,-1,0))) -> 2 | C77: =IF(H77="CÉLULA CONSTRUTIVA",0,IF(H77="ETAPA",OFFSET(C77,-1,0)+1,OFFSET(C77,-1,0))) -> 2 | D77: =IF(H77="ETAPA",0,IF(H77="SUBETAPA",OFFSET(D77,-1,0)+1,OFFSET(D77,-1,0))) -> 1 | E77: =IF(H77="Subetapa",0,IF(H77="serviço",OFFSET(E77,-1,0)+1,OFFSET(E77,-1,0))) -> 4 | H77: SERVIÇO | I77: =IF(H77="Unidade Construtiva",TEXT(A77,"00"),IF(H77="Célula Construtiva",TEXT(B77,"00"),IF(H77="Etapa",CONCATENATE(TEXT(B77,"00"),".",TEXT(C77,"000")),IF(H77="Subetapa",CONCATENATE(TEXT(B77,"00"),".",TEXT(C77,"000"),".",TEXT(D77,"000")),IF(H77="Serviço",CONCATENATE(TEXT(B77,"00"),".",TEXT(C77,"000"),".",TEXT(D77,"000"),".",TEXT(E77,"000")),""))))) -> 02.002.001.004 | J77: Estagiário | K77: mes | L77: 13 | M77: 2000 | N77: =IF(H77="Serviço",M77*L77,IF(H77="CÉLULA CONSTRUTIVA",SUMIFS($N$8:$N$420,$B$8:$B$420,B77,$H$8:$H$420,"Serviço"),IF(H77="ETAPA",SUMIFS($N$8:$N$420,$B$8:$B$420,B77,$C$8:$C$420,C77,$H$8:$H$420,"Serviço"),IF(H77="SUBETAPA",SUMIFS($N$8:$N$420,$B$8:$B$420,B77,$C$8:$C$420,C77,$D$8:$D$420,D77,$H$8:$H$420,"Serviço"),0)))) -> 26000 | O77: Valor informado em formulário Marena | P77: Finalizado
A78: =IF($H78="UNIDADE CONSTRUTIVA",OFFSET(A78,-1,0)+1,LARGE(A$3:A77,1)) -> 0 | B78: =IF(H78="UNIDADE CONSTRUTIVA",0,IF(H78="CÉLULA CONSTRUTIVA",OFFSET(B78,-1,0)+1,OFFSET(B78,-1,0))) -> 2 | C78: =IF(H78="CÉLULA CONSTRUTIVA",0,IF(H78="ETAPA",OFFSET(C78,-1,0)+1,OFFSET(C78,-1,0))) -> 2 | D78: =IF(H78="ETAPA",0,IF(H78="SUBETAPA",OFFSET(D78,-1,0)+1,OFFSET(D78,-1,0))) -> 2 | E78: =IF(H78="Subetapa",0,IF(H78="serviço",OFFSET(E78,-1,0)+1,OFFSET(E78,-1,0))) -> 0 | H78: SUBETAPA | I78: =IF(H78="Unidade Construtiva",TEXT(A78,"00"),IF(H78="Célula Construtiva",TEXT(B78,"00"),IF(H78="Etapa",CONCATENATE(TEXT(B78,"00"),".",TEXT(C78,"000")),IF(H78="Subetapa",CONCATENATE(TEXT(B78,"00"),".",TEXT(C78,"000"),".",TEXT(D78,"000")),IF(H78="Serviço",CONCATENATE(TEXT(B78,"00"),".",TEXT(C78,"000"),".",TEXT(D78,"000"),".",TEXT(E78,"000")),""))))) -> 02.002.002 | J78: Despesas de Consumo e Manutenção | N78: =IF(H78="Serviço",M78*L78,IF(H78="CÉLULA CONSTRUTIVA",SUMIFS($N$8:$N$420,$B$8:$B$420,B78,$H$8:$H$420,"Serviço"),IF(H78="ETAPA",SUMIFS($N$8:$N$420,$B$8:$B$420,B78,$C$8:$C$420,C78,$H$8:$H$420,"Serviço"),IF(H78="SUBETAPA",SUMIFS($N$8:$N$420,$B$8:$B$420,B78,$C$8:$C$420,C78,$D$8:$D$420,D78,$H$8:$H$420,"Serviço"),0)))) -> 272807.7
A79: =IF($H79="UNIDADE CONSTRUTIVA",OFFSET(A79,-1,0)+1,LARGE(A$3:A78,1)) -> 0 | B79: =IF(H79="UNIDADE CONSTRUTIVA",0,IF(H79="CÉLULA CONSTRUTIVA",OFFSET(B79,-1,0)+1,OFFSET(B79,-1,0))) -> 2 | C79: =IF(H79="CÉLULA CONSTRUTIVA",0,IF(H79="ETAPA",OFFSET(C79,-1,0)+1,OFFSET(C79,-1,0))) -> 2 | D79: =IF(H79="ETAPA",0,IF(H79="SUBETAPA",OFFSET(D79,-1,0)+1,OFFSET(D79,-1,0))) -> 2 | E79: =IF(H79="Subetapa",0,IF(H79="serviço",OFFSET(E79,-1,0)+1,OFFSET(E79,-1,0))) -> 1 | H79: SERVIÇO | I79: =IF(H79="Unidade Construtiva",TEXT(A79,"00"),IF(H79="Célula Construtiva",TEXT(B79,"00"),IF(H79="Etapa",CONCATENATE(TEXT(B79,"00"),".",TEXT(C79,"000")),IF(H79="Subetapa",CONCATENATE(TEXT(B79,"00"),".",TEXT(C79,"000"),".",TEXT(D79,"000")),IF(H79="Serviço",CONCATENATE(TEXT(B79,"00"),".",TEXT(C79,"000"),".",TEXT(D79,"000"),".",TEXT(E79,"000")),""))))) -> 02.002.002.001 | J79: Consumo de água e esgoto | K79: mes | L79: ='Obra '!$E$7 -> 36 | M79: 254.67248 | N79: =IF(H79="Serviço",M79*L79,IF(H79="CÉLULA CONSTRUTIVA",SUMIFS($N$8:$N$420,$B$8:$B$420,B79,$H$8:$H$420,"Serviço"),IF(H79="ETAPA",SUMIFS($N$8:$N$420,$B$8:$B$420,B79,$C$8:$C$420,C79,$H$8:$H$420,"Serviço"),IF(H79="SUBETAPA",SUMIFS($N$8:$N$420,$B$8:$B$420,B79,$C$8:$C$420,C79,$D$8:$D$420,D79,$H$8:$H$420,"Serviço"),0)))) -> 9168.2091 | O79: Estimado com base em índices históricos | P79: Finalizado
A80: =IF($H80="UNIDADE CONSTRUTIVA",OFFSET(A80,-1,0)+1,LARGE(A$3:A79,1)) -> 0 | B80: =IF(H80="UNIDADE CONSTRUTIVA",0,IF(H80="CÉLULA CONSTRUTIVA",OFFSET(B80,-1,0)+1,OFFSET(B80,-1,0))) -> 2 | C80: =IF(H80="CÉLULA CONSTRUTIVA",0,IF(H80="ETAPA",OFFSET(C80,-1,0)+1,OFFSET(C80,-1,0))) -> 2 | D80: =IF(H80="ETAPA",0,IF(H80="SUBETAPA",OFFSET(D80,-1,0)+1,OFFSET(D80,-1,0))) -> 2 | E80: =IF(H80="Subetapa",0,IF(H80="serviço",OFFSET(E80,-1,0)+1,OFFSET(E80,-1,0))) -> 2 | H80: SERVIÇO | I80: =IF(H80="Unidade Construtiva",TEXT(A80,"00"),IF(H80="Célula Construtiva",TEXT(B80,"00"),IF(H80="Etapa",CONCATENATE(TEXT(B80,"00"),".",TEXT(C80,"000")),IF(H80="Subetapa",CONCATENATE(TEXT(B80,"00"),".",TEXT(C80,"000"),".",TEXT(D80,"000")),IF(H80="Serviço",CONCATENATE(TEXT(B80,"00"),".",TEXT(C80,"000"),".",TEXT(D80,"000"),".",TEXT(E80,"000")),""))))) -> 02.002.002.002 | J80: Consumo de luz/energia | K80: mes | L80: ='Obra '!$E$7 -> 36 | M80: 1910.0436 | N80: =IF(H80="Serviço",M80*L80,IF(H80="CÉLULA CONSTRUTIVA",SUMIFS($N$8:$N$420,$B$8:$B$420,B80,$H$8:$H$420,"Serviço"),IF(H80="ETAPA",SUMIFS($N$8:$N$420,$B$8:$B$420,B80,$C$8:$C$420,C80,$H$8:$H$420,"Serviço"),IF(H80="SUBETAPA",SUMIFS($N$8:$N$420,$B$8:$B$420,B80,$C$8:$C$420,C80,$D$8:$D$420,D80,$H$8:$H$420,"Serviço"),0)))) -> 68761.568 | O80: Estimado com base em índices históricos | P80: Finalizado
A81: =IF($H81="UNIDADE CONSTRUTIVA",OFFSET(A81,-1,0)+1,LARGE(A$3:A80,1)) -> 0 | B81: =IF(H81="UNIDADE CONSTRUTIVA",0,IF(H81="CÉLULA CONSTRUTIVA",OFFSET(B81,-1,0)+1,OFFSET(B81,-1,0))) -> 2 | C81: =IF(H81="CÉLULA CONSTRUTIVA",0,IF(H81="ETAPA",OFFSET(C81,-1,0)+1,OFFSET(C81,-1,0))) -> 2 | D81: =IF(H81="ETAPA",0,IF(H81="SUBETAPA",OFFSET(D81,-1,0)+1,OFFSET(D81,-1,0))) -> 2 | E81: =IF(H81="Subetapa",0,IF(H81="serviço",OFFSET(E81,-1,0)+1,OFFSET(E81,-1,0))) -> 3 | H81: SERVIÇO | I81: =IF(H81="Unidade Construtiva",TEXT(A81,"00"),IF(H81="Célula Construtiva",TEXT(B81,"00"),IF(H81="Etapa",CONCATENATE(TEXT(B81,"00"),".",TEXT(C81,"000")),IF(H81="Subetapa",CONCATENATE(TEXT(B81,"00"),".",TEXT(C81,"000"),".",TEXT(D81,"000")),IF(H81="Serviço",CONCATENATE(TEXT(B81,"00"),".",TEXT(C81,"000"),".",TEXT(D81,"000"),".",TEXT(E81,"000")),""))))) -> 02.002.002.003 | J81: Consumo internet | K81: mes | L81: ='Obra '!$E$7 -> 36 | M81: 150 | N81: =IF(H81="Serviço",M81*L81,IF(H81="CÉLULA CONSTRUTIVA",SUMIFS($N$8:$N$420,$B$8:$B$420,B81,$H$8:$H$420,"Serviço"),IF(H81="ETAPA",SUMIFS($N$8:$N$420,$B$8:$B$420,B81,$C$8:$C$420,C81,$H$8:$H$420,"Serviço"),IF(H81="SUBETAPA",SUMIFS($N$8:$N$420,$B$8:$B$420,B81,$C$8:$C$420,C81,$D$8:$D$420,D81,$H$8:$H$420,"Serviço"),0)))) -> 5400 | O81: Estimado com base em índices históricos | P81: Finalizado
A82: =IF($H82="UNIDADE CONSTRUTIVA",OFFSET(A82,-1,0)+1,LARGE(A$3:A81,1)) -> 0 | B82: =IF(H82="UNIDADE CONSTRUTIVA",0,IF(H82="CÉLULA CONSTRUTIVA",OFFSET(B82,-1,0)+1,OFFSET(B82,-1,0))) -> 2 | C82: =IF(H82="CÉLULA CONSTRUTIVA",0,IF(H82="ETAPA",OFFSET(C82,-1,0)+1,OFFSET(C82,-1,0))) -> 2 | D82: =IF(H82="ETAPA",0,IF(H82="SUBETAPA",OFFSET(D82,-1,0)+1,OFFSET(D82,-1,0))) -> 2 | E82: =IF(H82="Subetapa",0,IF(H82="serviço",OFFSET(E82,-1,0)+1,OFFSET(E82,-1,0))) -> 4 | H82: SERVIÇO | I82: =IF(H82="Unidade Construtiva",TEXT(A82,"00"),IF(H82="Célula Construtiva",TEXT(B82,"00"),IF(H82="Etapa",CONCATENATE(TEXT(B82,"00"),".",TEXT(C82,"000")),IF(H82="Subetapa",CONCATENATE(TEXT(B82,"00"),".",TEXT(C82,"000"),".",TEXT(D82,"000")),IF(H82="Serviço",CONCATENATE(TEXT(B82,"00"),".",TEXT(C82,"000"),".",TEXT(D82,"000"),".",TEXT(E82,"000")),""))))) -> 02.002.002.004 | J82: Coleta de lixo | K82: mes | L82: ='Obra '!$E$7 -> 36 | M82: 382.00871 | N82: =IF(H82="Serviço",M82*L82,IF(H82="CÉLULA CONSTRUTIVA",SUMIFS($N$8:$N$420,$B$8:$B$420,B82,$H$8:$H$420,"Serviço"),IF(H82="ETAPA",SUMIFS($N$8:$N$420,$B$8:$B$420,B82,$C$8:$C$420,C82,$H$8:$H$420,"Serviço"),IF(H82="SUBETAPA",SUMIFS($N$8:$N$420,$B$8:$B$420,B82,$C$8:$C$420,C82,$D$8:$D$420,D82,$H$8:$H$420,"Serviço"),0)))) -> 13752.314 | O82: Estimado com base em índices históricos | P82: Finalizado
A83: =IF($H83="UNIDADE CONSTRUTIVA",OFFSET(A83,-1,0)+1,LARGE(A$3:A82,1)) -> 0 | B83: =IF(H83="UNIDADE CONSTRUTIVA",0,IF(H83="CÉLULA CONSTRUTIVA",OFFSET(B83,-1,0)+1,OFFSET(B83,-1,0))) -> 2 | C83: =IF(H83="CÉLULA CONSTRUTIVA",0,IF(H83="ETAPA",OFFSET(C83,-1,0)+1,OFFSET(C83,-1,0))) -> 2 | D83: =IF(H83="ETAPA",0,IF(H83="SUBETAPA",OFFSET(D83,-1,0)+1,OFFSET(D83,-1,0))) -> 2 | E83: =IF(H83="Subetapa",0,IF(H83="serviço",OFFSET(E83,-1,0)+1,OFFSET(E83,-1,0))) -> 5 | H83: SERVIÇO | I83: =IF(H83="Unidade Construtiva",TEXT(A83,"00"),IF(H83="Célula Construtiva",TEXT(B83,"00"),IF(H83="Etapa",CONCATENATE(TEXT(B83,"00"),".",TEXT(C83,"000")),IF(H83="Subetapa",CONCATENATE(TEXT(B83,"00"),".",TEXT(C83,"000"),".",TEXT(D83,"000")),IF(H83="Serviço",CONCATENATE(TEXT(B83,"00"),".",TEXT(C83,"000"),".",TEXT(D83,"000"),".",TEXT(E83,"000")),""))))) -> 02.002.002.005 | J83: Alimentação | K83: mes | L83: ='Obra '!$E$7 -> 36 | M83: 100 | N83: =IF(H83="Serviço",M83*L83,IF(H83="CÉLULA CONSTRUTIVA",SUMIFS($N$8:$N$420,$B$8:$B$420,B83,$H$8:$H$420,"Serviço"),IF(H83="ETAPA",SUMIFS($N$8:$N$420,$B$8:$B$420,B83,$C$8:$C$420,C83,$H$8:$H$420,"Serviço"),IF(H83="SUBETAPA",SUMIFS($N$8:$N$420,$B$8:$B$420,B83,$C$8:$C$420,C83,$D$8:$D$420,D83,$H$8:$H$420,"Serviço"),0)))) -> 3600 | O83: Estimado com base em índices históricos | P83: Finalizado
A84: =IF($H84="UNIDADE CONSTRUTIVA",OFFSET(A84,-1,0)+1,LARGE(A$3:A83,1)) -> 0 | B84: =IF(H84="UNIDADE CONSTRUTIVA",0,IF(H84="CÉLULA CONSTRUTIVA",OFFSET(B84,-1,0)+1,OFFSET(B84,-1,0))) -> 2 | C84: =IF(H84="CÉLULA CONSTRUTIVA",0,IF(H84="ETAPA",OFFSET(C84,-1,0)+1,OFFSET(C84,-1,0))) -> 2 | D84: =IF(H84="ETAPA",0,IF(H84="SUBETAPA",OFFSET(D84,-1,0)+1,OFFSET(D84,-1,0))) -> 2 | E84: =IF(H84="Subetapa",0,IF(H84="serviço",OFFSET(E84,-1,0)+1,OFFSET(E84,-1,0))) -> 6 | H84: SERVIÇO | I84: =IF(H84="Unidade Construtiva",TEXT(A84,"00"),IF(H84="Célula Construtiva",TEXT(B84,"00"),IF(H84="Etapa",CONCATENATE(TEXT(B84,"00"),".",TEXT(C84,"000")),IF(H84="Subetapa",CONCATENATE(TEXT(B84,"00"),".",TEXT(C84,"000"),".",TEXT(D84,"000")),IF(H84="Serviço",CONCATENATE(TEXT(B84,"00"),".",TEXT(C84,"000"),".",TEXT(D84,"000"),".",TEXT(E84,"000")),""))))) -> 02.002.002.006 | J84: Consumo de material de expediente/escritório | K84: vb | L84: 1 | M84: 13486.329 | N84: =IF(H84="Serviço",M84*L84,IF(H84="CÉLULA CONSTRUTIVA",SUMIFS($N$8:$N$420,$B$8:$B$420,B84,$H$8:$H$420,"Serviço"),IF(H84="ETAPA",SUMIFS($N$8:$N$420,$B$8:$B$420,B84,$C$8:$C$420,C84,$H$8:$H$420,"Serviço"),IF(H84="SUBETAPA",SUMIFS($N$8:$N$420,$B$8:$B$420,B84,$C$8:$C$420,C84,$D$8:$D$420,D84,$H$8:$H$420,"Serviço"),0)))) -> 13486.329 | O84: Estimado com base em índices históricos | P84: Finalizado
A85: =IF($H85="UNIDADE CONSTRUTIVA",OFFSET(A85,-1,0)+1,LARGE(A$3:A84,1)) -> 0 | B85: =IF(H85="UNIDADE CONSTRUTIVA",0,IF(H85="CÉLULA CONSTRUTIVA",OFFSET(B85,-1,0)+1,OFFSET(B85,-1,0))) -> 2 | C85: =IF(H85="CÉLULA CONSTRUTIVA",0,IF(H85="ETAPA",OFFSET(C85,-1,0)+1,OFFSET(C85,-1,0))) -> 2 | D85: =IF(H85="ETAPA",0,IF(H85="SUBETAPA",OFFSET(D85,-1,0)+1,OFFSET(D85,-1,0))) -> 2 | E85: =IF(H85="Subetapa",0,IF(H85="serviço",OFFSET(E85,-1,0)+1,OFFSET(E85,-1,0))) -> 7 | H85: SERVIÇO | I85: =IF(H85="Unidade Construtiva",TEXT(A85,"00"),IF(H85="Célula Construtiva",TEXT(B85,"00"),IF(H85="Etapa",CONCATENATE(TEXT(B85,"00"),".",TEXT(C85,"000")),IF(H85="Subetapa",CONCATENATE(TEXT(B85,"00"),".",TEXT(C85,"000"),".",TEXT(D85,"000")),IF(H85="Serviço",CONCATENATE(TEXT(B85,"00"),".",TEXT(C85,"000"),".",TEXT(D85,"000"),".",TEXT(E85,"000")),""))))) -> 02.002.002.007 | J85: Consumo de material de higiene e limpeza | K85: vb | L85: 1 | M85: 19957.859 | N85: =IF(H85="Serviço",M85*L85,IF(H85="CÉLULA CONSTRUTIVA",SUMIFS($N$8:$N$420,$B$8:$B$420,B85,$H$8:$H$420,"Serviço"),IF(H85="ETAPA",SUMIFS($N$8:$N$420,$B$8:$B$420,B85,$C$8:$C$420,C85,$H$8:$H$420,"Serviço"),IF(H85="SUBETAPA",SUMIFS($N$8:$N$420,$B$8:$B$420,B85,$C$8:$C$420,C85,$D$8:$D$420,D85,$H$8:$H$420,"Serviço"),0)))) -> 19957.859 | O85: Estimado com base em índices históricos | P85: Finalizado
A86: =IF($H86="UNIDADE CONSTRUTIVA",OFFSET(A86,-1,0)+1,LARGE(A$3:A85,1)) -> 0 | B86: =IF(H86="UNIDADE CONSTRUTIVA",0,IF(H86="CÉLULA CONSTRUTIVA",OFFSET(B86,-1,0)+1,OFFSET(B86,-1,0))) -> 2 | C86: =IF(H86="CÉLULA CONSTRUTIVA",0,IF(H86="ETAPA",OFFSET(C86,-1,0)+1,OFFSET(C86,-1,0))) -> 2 | D86: =IF(H86="ETAPA",0,IF(H86="SUBETAPA",OFFSET(D86,-1,0)+1,OFFSET(D86,-1,0))) -> 2 | E86: =IF(H86="Subetapa",0,IF(H86="serviço",OFFSET(E86,-1,0)+1,OFFSET(E86,-1,0))) -> 8 | H86: SERVIÇO | I86: =IF(H86="Unidade Construtiva",TEXT(A86,"00"),IF(H86="Célula Construtiva",TEXT(B86,"00"),IF(H86="Etapa",CONCATENATE(TEXT(B86,"00"),".",TEXT(C86,"000")),IF(H86="Subetapa",CONCATENATE(TEXT(B86,"00"),".",TEXT(C86,"000"),".",TEXT(D86,"000")),IF(H86="Serviço",CONCATENATE(TEXT(B86,"00"),".",TEXT(C86,"000"),".",TEXT(D86,"000"),".",TEXT(E86,"000")),""))))) -> 02.002.002.008 | J86: Frete | K86: vb | L86: 1 | M86: 13088.857 | N86: =IF(H86="Serviço",M86*L86,IF(H86="CÉLULA CONSTRUTIVA",SUMIFS($N$8:$N$420,$B$8:$B$420,B86,$H$8:$H$420,"Serviço"),IF(H86="ETAPA",SUMIFS($N$8:$N$420,$B$8:$B$420,B86,$C$8:$C$420,C86,$H$8:$H$420,"Serviço"),IF(H86="SUBETAPA",SUMIFS($N$8:$N$420,$B$8:$B$420,B86,$C$8:$C$420,C86,$D$8:$D$420,D86,$H$8:$H$420,"Serviço"),0)))) -> 13088.857 | O86: Estimado com base em índices históricos | P86: Finalizado
A87: =IF($H87="UNIDADE CONSTRUTIVA",OFFSET(A87,-1,0)+1,LARGE(A$3:A86,1)) -> 0 | B87: =IF(H87="UNIDADE CONSTRUTIVA",0,IF(H87="CÉLULA CONSTRUTIVA",OFFSET(B87,-1,0)+1,OFFSET(B87,-1,0))) -> 2 | C87: =IF(H87="CÉLULA CONSTRUTIVA",0,IF(H87="ETAPA",OFFSET(C87,-1,0)+1,OFFSET(C87,-1,0))) -> 2 | D87: =IF(H87="ETAPA",0,IF(H87="SUBETAPA",OFFSET(D87,-1,0)+1,OFFSET(D87,-1,0))) -> 2 | E87: =IF(H87="Subetapa",0,IF(H87="serviço",OFFSET(E87,-1,0)+1,OFFSET(E87,-1,0))) -> 9 | H87: SERVIÇO | I87: =IF(H87="Unidade Construtiva",TEXT(A87,"00"),IF(H87="Célula Construtiva",TEXT(B87,"00"),IF(H87="Etapa",CONCATENATE(TEXT(B87,"00"),".",TEXT(C87,"000")),IF(H87="Subetapa",CONCATENATE(TEXT(B87,"00"),".",TEXT(C87,"000"),".",TEXT(D87,"000")),IF(H87="Serviço",CONCATENATE(TEXT(B87,"00"),".",TEXT(C87,"000"),".",TEXT(D87,"000"),".",TEXT(E87,"000")),""))))) -> 02.002.002.009 | J87: Fotocópias e Heliográficas | K87: vb | L87: 1 | M87: 4379.8343 | N87: =IF(H87="Serviço",M87*L87,IF(H87="CÉLULA CONSTRUTIVA",SUMIFS($N$8:$N$420,$B$8:$B$420,B87,$H$8:$H$420,"Serviço"),IF(H87="ETAPA",SUMIFS($N$8:$N$420,$B$8:$B$420,B87,$C$8:$C$420,C87,$H$8:$H$420,"Serviço"),IF(H87="SUBETAPA",SUMIFS($N$8:$N$420,$B$8:$B$420,B87,$C$8:$C$420,C87,$D$8:$D$420,D87,$H$8:$H$420,"Serviço"),0)))) -> 4379.8343 | O87: Estimado com base em índices históricos | P87: Finalizado
A88: =IF($H88="UNIDADE CONSTRUTIVA",OFFSET(A88,-1,0)+1,LARGE(A$3:A87,1)) -> 0 | B88: =IF(H88="UNIDADE CONSTRUTIVA",0,IF(H88="CÉLULA CONSTRUTIVA",OFFSET(B88,-1,0)+1,OFFSET(B88,-1,0))) -> 2 | C88: =IF(H88="CÉLULA CONSTRUTIVA",0,IF(H88="ETAPA",OFFSET(C88,-1,0)+1,OFFSET(C88,-1,0))) -> 2 | D88: =IF(H88="ETAPA",0,IF(H88="SUBETAPA",OFFSET(D88,-1,0)+1,OFFSET(D88,-1,0))) -> 2 | E88: =IF(H88="Subetapa",0,IF(H88="serviço",OFFSET(E88,-1,0)+1,OFFSET(E88,-1,0))) -> 10 | H88: SERVIÇO | I88: =IF(H88="Unidade Construtiva",TEXT(A88,"00"),IF(H88="Célula Construtiva",TEXT(B88,"00"),IF(H88="Etapa",CONCATENATE(TEXT(B88,"00"),".",TEXT(C88,"000")),IF(H88="Subetapa",CONCATENATE(TEXT(B88,"00"),".",TEXT(C88,"000"),".",TEXT(D88,"000")),IF(H88="Serviço",CONCATENATE(TEXT(B88,"00"),".",TEXT(C88,"000"),".",TEXT(D88,"000"),".",TEXT(E88,"000")),""))))) -> 02.002.002.010 | J88: Despesas com vizinhos | K88: vb | L88: 1 | M88: 17712.451 | N88: =IF(H88="Serviço",M88*L88,IF(H88="CÉLULA CONSTRUTIVA",SUMIFS($N$8:$N$420,$B$8:$B$420,B88,$H$8:$H$420,"Serviço"),IF(H88="ETAPA",SUMIFS($N$8:$N$420,$B$8:$B$420,B88,$C$8:$C$420,C88,$H$8:$H$420,"Serviço"),IF(H88="SUBETAPA",SUMIFS($N$8:$N$420,$B$8:$B$420,B88,$C$8:$C$420,C88,$D$8:$D$420,D88,$H$8:$H$420,"Serviço"),0)))) -> 17712.451 | O88: Estimado com base em índices históricos | P88: Finalizado
A89: =IF($H89="UNIDADE CONSTRUTIVA",OFFSET(A89,-1,0)+1,LARGE(A$3:A88,1)) -> 0 | B89: =IF(H89="UNIDADE CONSTRUTIVA",0,IF(H89="CÉLULA CONSTRUTIVA",OFFSET(B89,-1,0)+1,OFFSET(B89,-1,0))) -> 2 | C89: =IF(H89="CÉLULA CONSTRUTIVA",0,IF(H89="ETAPA",OFFSET(C89,-1,0)+1,OFFSET(C89,-1,0))) -> 2 | D89: =IF(H89="ETAPA",0,IF(H89="SUBETAPA",OFFSET(D89,-1,0)+1,OFFSET(D89,-1,0))) -> 2 | E89: =IF(H89="Subetapa",0,IF(H89="serviço",OFFSET(E89,-1,0)+1,OFFSET(E89,-1,0))) -> 11 | H89: SERVIÇO | I89: =IF(H89="Unidade Construtiva",TEXT(A89,"00"),IF(H89="Célula Construtiva",TEXT(B89,"00"),IF(H89="Etapa",CONCATENATE(TEXT(B89,"00"),".",TEXT(C89,"000")),IF(H89="Subetapa",CONCATENATE(TEXT(B89,"00"),".",TEXT(C89,"000"),".",TEXT(D89,"000")),IF(H89="Serviço",CONCATENATE(TEXT(B89,"00"),".",TEXT(C89,"000"),".",TEXT(D89,"000"),".",TEXT(E89,"000")),""))))) -> 02.002.002.011 | J89: Esgotamento de sistema sanitário temporário | K89: mes | L89: 3 | M89: 2028.0914 | N89: =IF(H89="Serviço",M89*L89,IF(H89="CÉLULA CONSTRUTIVA",SUMIFS($N$8:$N$420,$B$8:$B$420,B89,$H$8:$H$420,"Serviço"),IF(H89="ETAPA",SUMIFS($N$8:$N$420,$B$8:$B$420,B89,$C$8:$C$420,C89,$H$8:$H$420,"Serviço"),IF(H89="SUBETAPA",SUMIFS($N$8:$N$420,$B$8:$B$420,B89,$C$8:$C$420,C89,$D$8:$D$420,D89,$H$8:$H$420,"Serviço"),0)))) -> 6084.2743 | O89: Estimado com base em índices históricos | P89: Finalizado
A90: =IF($H90="UNIDADE CONSTRUTIVA",OFFSET(A90,-1,0)+1,LARGE(A$3:A89,1)) -> 0 | B90: =IF(H90="UNIDADE CONSTRUTIVA",0,IF(H90="CÉLULA CONSTRUTIVA",OFFSET(B90,-1,0)+1,OFFSET(B90,-1,0))) -> 2 | C90: =IF(H90="CÉLULA CONSTRUTIVA",0,IF(H90="ETAPA",OFFSET(C90,-1,0)+1,OFFSET(C90,-1,0))) -> 2 | D90: =IF(H90="ETAPA",0,IF(H90="SUBETAPA",OFFSET(D90,-1,0)+1,OFFSET(D90,-1,0))) -> 2 | E90: =IF(H90="Subetapa",0,IF(H90="serviço",OFFSET(E90,-1,0)+1,OFFSET(E90,-1,0))) -> 12 | H90: SERVIÇO | I90: =IF(H90="Unidade Construtiva",TEXT(A90,"00"),IF(H90="Célula Construtiva",TEXT(B90,"00"),IF(H90="Etapa",CONCATENATE(TEXT(B90,"00"),".",TEXT(C90,"000")),IF(H90="Subetapa",CONCATENATE(TEXT(B90,"00"),".",TEXT(C90,"000"),".",TEXT(D90,"000")),IF(H90="Serviço",CONCATENATE(TEXT(B90,"00"),".",TEXT(C90,"000"),".",TEXT(D90,"000"),".",TEXT(E90,"000")),""))))) -> 02.002.002.012 | J90: Contador | K90: mes | L90: 36 | M90: =1804*1.5 -> 2706 | N90: =IF(H90="Serviço",M90*L90,IF(H90="CÉLULA CONSTRUTIVA",SUMIFS($N$8:$N$420,$B$8:$B$420,B90,$H$8:$H$420,"Serviço"),IF(H90="ETAPA",SUMIFS($N$8:$N$420,$B$8:$B$420,B90,$C$8:$C$420,C90,$H$8:$H$420,"Serviço"),IF(H90="SUBETAPA",SUMIFS($N$8:$N$420,$B$8:$B$420,B90,$C$8:$C$420,C90,$D$8:$D$420,D90,$H$8:$H$420,"Serviço"),0)))) -> 97416 | O90: Estimado com base em índices históricos | P90: Finalizado
A91: =IF($H91="UNIDADE CONSTRUTIVA",OFFSET(A91,-1,0)+1,LARGE(A$3:A89,1)) -> 0 | B91: =IF(H91="UNIDADE CONSTRUTIVA",0,IF(H91="CÉLULA CONSTRUTIVA",OFFSET(B91,-1,0)+1,OFFSET(B91,-1,0))) -> 2 | C91: =IF(H91="CÉLULA CONSTRUTIVA",0,IF(H91="ETAPA",OFFSET(C91,-1,0)+1,OFFSET(C91,-1,0))) -> 2 | D91: =IF(H91="ETAPA",0,IF(H91="SUBETAPA",OFFSET(D91,-1,0)+1,OFFSET(D91,-1,0))) -> 3 | E91: =IF(H91="Subetapa",0,IF(H91="serviço",OFFSET(E91,-1,0)+1,OFFSET(E91,-1,0))) -> 0 | H91: SUBETAPA | I91: =IF(H91="Unidade Construtiva",TEXT(A91,"00"),IF(H91="Célula Construtiva",TEXT(B91,"00"),IF(H91="Etapa",CONCATENATE(TEXT(B91,"00"),".",TEXT(C91,"000")),IF(H91="Subetapa",CONCATENATE(TEXT(B91,"00"),".",TEXT(C91,"000"),".",TEXT(D91,"000")),IF(H91="Serviço",CONCATENATE(TEXT(B91,"00"),".",TEXT(C91,"000"),".",TEXT(D91,"000"),".",TEXT(E91,"000")),""))))) -> 02.002.003 | J91: Instalações Provisórias de Canteiro de Obra | N91: =IF(H91="Serviço",M91*L91,IF(H91="CÉLULA CONSTRUTIVA",SUMIFS($N$8:$N$420,$B$8:$B$420,B91,$H$8:$H$420,"Serviço"),IF(H91="ETAPA",SUMIFS($N$8:$N$420,$B$8:$B$420,B91,$C$8:$C$420,C91,$H$8:$H$420,"Serviço"),IF(H91="SUBETAPA",SUMIFS($N$8:$N$420,$B$8:$B$420,B91,$C$8:$C$420,C91,$D$8:$D$420,D91,$H$8:$H$420,"Serviço"),0)))) -> 201531.41
A92: =IF($H92="UNIDADE CONSTRUTIVA",OFFSET(A92,-1,0)+1,LARGE(A$3:A91,1)) -> 0 | B92: =IF(H92="UNIDADE CONSTRUTIVA",0,IF(H92="CÉLULA CONSTRUTIVA",OFFSET(B92,-1,0)+1,OFFSET(B92,-1,0))) -> 2 | C92: =IF(H92="CÉLULA CONSTRUTIVA",0,IF(H92="ETAPA",OFFSET(C92,-1,0)+1,OFFSET(C92,-1,0))) -> 2 | D92: =IF(H92="ETAPA",0,IF(H92="SUBETAPA",OFFSET(D92,-1,0)+1,OFFSET(D92,-1,0))) -> 3 | E92: =IF(H92="Subetapa",0,IF(H92="serviço",OFFSET(E92,-1,0)+1,OFFSET(E92,-1,0))) -> 1 | H92: SERVIÇO | I92: =IF(H92="Unidade Construtiva",TEXT(A92,"00"),IF(H92="Célula Construtiva",TEXT(B92,"00"),IF(H92="Etapa",CONCATENATE(TEXT(B92,"00"),".",TEXT(C92,"000")),IF(H92="Subetapa",CONCATENATE(TEXT(B92,"00"),".",TEXT(C92,"000"),".",TEXT(D92,"000")),IF(H92="Serviço",CONCATENATE(TEXT(B92,"00"),".",TEXT(C92,"000"),".",TEXT(D92,"000"),".",TEXT(E92,"000")),""))))) -> 02.002.003.001 | J92: Instalações Provisórias (central de aço, formas, argamassa, almoxarifado geral, construções temporárias) | K92: vb | L92: 1 | M92: 100896.43 | N92: =IF(H92="Serviço",M92*L92,IF(H92="CÉLULA CONSTRUTIVA",SUMIFS($N$8:$N$420,$B$8:$B$420,B92,$H$8:$H$420,"Serviço"),IF(H92="ETAPA",SUMIFS($N$8:$N$420,$B$8:$B$420,B92,$C$8:$C$420,C92,$H$8:$H$420,"Serviço"),IF(H92="SUBETAPA",SUMIFS($N$8:$N$420,$B$8:$B$420,B92,$C$8:$C$420,C92,$D$8:$D$420,D92,$H$8:$H$420,"Serviço"),0)))) -> 100896.43 | O92: Conforme definido em aba "Canteiro" | P92: Finalizado
A93: =IF($H93="UNIDADE CONSTRUTIVA",OFFSET(A93,-1,0)+1,LARGE(A$3:A92,1)) -> 0 | B93: =IF(H93="UNIDADE CONSTRUTIVA",0,IF(H93="CÉLULA CONSTRUTIVA",OFFSET(B93,-1,0)+1,OFFSET(B93,-1,0))) -> 2 | C93: =IF(H93="CÉLULA CONSTRUTIVA",0,IF(H93="ETAPA",OFFSET(C93,-1,0)+1,OFFSET(C93,-1,0))) -> 2 | D93: =IF(H93="ETAPA",0,IF(H93="SUBETAPA",OFFSET(D93,-1,0)+1,OFFSET(D93,-1,0))) -> 3 | E93: =IF(H93="Subetapa",0,IF(H93="serviço",OFFSET(E93,-1,0)+1,OFFSET(E93,-1,0))) -> 2 | H93: SERVIÇO | I93: =IF(H93="Unidade Construtiva",TEXT(A93,"00"),IF(H93="Célula Construtiva",TEXT(B93,"00"),IF(H93="Etapa",CONCATENATE(TEXT(B93,"00"),".",TEXT(C93,"000")),IF(H93="Subetapa",CONCATENATE(TEXT(B93,"00"),".",TEXT(C93,"000"),".",TEXT(D93,"000")),IF(H93="Serviço",CONCATENATE(TEXT(B93,"00"),".",TEXT(C93,"000"),".",TEXT(D93,"000"),".",TEXT(E93,"000")),""))))) -> 02.002.003.002 | J93: Locação de container | K93: mes | L93: 11 | M93: 1600 | N93: =IF(H93="Serviço",M93*L93,IF(H93="CÉLULA CONSTRUTIVA",SUMIFS($N$8:$N$420,$B$8:$B$420,B93,$H$8:$H$420,"Serviço"),IF(H93="ETAPA",SUMIFS($N$8:$N$420,$B$8:$B$420,B93,$C$8:$C$420,C93,$H$8:$H$420,"Serviço"),IF(H93="SUBETAPA",SUMIFS($N$8:$N$420,$B$8:$B$420,B93,$C$8:$C$420,C93,$D$8:$D$420,D93,$H$8:$H$420,"Serviço"),0)))) -> 17600 | O93: Previsão de 1 unidade para engenharia - Até a alvenaria do lazer | P93: Finalizado
A94: =IF($H94="UNIDADE CONSTRUTIVA",OFFSET(A94,-1,0)+1,LARGE(A$3:A93,1)) -> 0 | B94: =IF(H94="UNIDADE CONSTRUTIVA",0,IF(H94="CÉLULA CONSTRUTIVA",OFFSET(B94,-1,0)+1,OFFSET(B94,-1,0))) -> 2 | C94: =IF(H94="CÉLULA CONSTRUTIVA",0,IF(H94="ETAPA",OFFSET(C94,-1,0)+1,OFFSET(C94,-1,0))) -> 2 | D94: =IF(H94="ETAPA",0,IF(H94="SUBETAPA",OFFSET(D94,-1,0)+1,OFFSET(D94,-1,0))) -> 3 | E94: =IF(H94="Subetapa",0,IF(H94="serviço",OFFSET(E94,-1,0)+1,OFFSET(E94,-1,0))) -> 3 | H94: SERVIÇO | I94: =IF(H94="Unidade Construtiva",TEXT(A94,"00"),IF(H94="Célula Construtiva",TEXT(B94,"00"),IF(H94="Etapa",CONCATENATE(TEXT(B94,"00"),".",TEXT(C94,"000")),IF(H94="Subetapa",CONCATENATE(TEXT(B94,"00"),".",TEXT(C94,"000"),".",TEXT(D94,"000")),IF(H94="Serviço",CONCATENATE(TEXT(B94,"00"),".",TEXT(C94,"000"),".",TEXT(D94,"000"),".",TEXT(E94,"000")),""))))) -> 02.002.003.003 | J94: Locação de banheiro químico | K94: mes | L94: 6 | M94: 980 | N94: =IF(H94="Serviço",M94*L94,IF(H94="CÉLULA CONSTRUTIVA",SUMIFS($N$8:$N$420,$B$8:$B$420,B94,$H$8:$H$420,"Serviço"),IF(H94="ETAPA",SUMIFS($N$8:$N$420,$B$8:$B$420,B94,$C$8:$C$420,C94,$H$8:$H$420,"Serviço"),IF(H94="SUBETAPA",SUMIFS($N$8:$N$420,$B$8:$B$420,B94,$C$8:$C$420,C94,$D$8:$D$420,D94,$H$8:$H$420,"Serviço"),0)))) -> 5880 | O94: Previsão de 1 unidade para o período da infraestrutura | P94: Finalizado
A95: =IF($H95="UNIDADE CONSTRUTIVA",OFFSET(A95,-1,0)+1,LARGE(A$3:A94,1)) -> 0 | B95: =IF(H95="UNIDADE CONSTRUTIVA",0,IF(H95="CÉLULA CONSTRUTIVA",OFFSET(B95,-1,0)+1,OFFSET(B95,-1,0))) -> 2 | C95: =IF(H95="CÉLULA CONSTRUTIVA",0,IF(H95="ETAPA",OFFSET(C95,-1,0)+1,OFFSET(C95,-1,0))) -> 2 | D95: =IF(H95="ETAPA",0,IF(H95="SUBETAPA",OFFSET(D95,-1,0)+1,OFFSET(D95,-1,0))) -> 3 | E95: =IF(H95="Subetapa",0,IF(H95="serviço",OFFSET(E95,-1,0)+1,OFFSET(E95,-1,0))) -> 4 | H95: SERVIÇO | I95: =IF(H95="Unidade Construtiva",TEXT(A95,"00"),IF(H95="Célula Construtiva",TEXT(B95,"00"),IF(H95="Etapa",CONCATENATE(TEXT(B95,"00"),".",TEXT(C95,"000")),IF(H95="Subetapa",CONCATENATE(TEXT(B95,"00"),".",TEXT(C95,"000"),".",TEXT(D95,"000")),IF(H95="Serviço",CONCATENATE(TEXT(B95,"00"),".",TEXT(C95,"000"),".",TEXT(D95,"000"),".",TEXT(E95,"000")),""))))) -> 02.002.003.004 | J95: Mobiliário de apoio a obra | K95: vb | L95: 1 | M95: 20200 | N95: =IF(H95="Serviço",M95*L95,IF(H95="CÉLULA CONSTRUTIVA",SUMIFS($N$8:$N$420,$B$8:$B$420,B95,$H$8:$H$420,"Serviço"),IF(H95="ETAPA",SUMIFS($N$8:$N$420,$B$8:$B$420,B95,$C$8:$C$420,C95,$H$8:$H$420,"Serviço"),IF(H95="SUBETAPA",SUMIFS($N$8:$N$420,$B$8:$B$420,B95,$C$8:$C$420,C95,$D$8:$D$420,D95,$H$8:$H$420,"Serviço"),0)))) -> 20200 | O95: Conforme estimativa da aba "Canteiro" | P95: Finalizado
A96: =IF($H96="UNIDADE CONSTRUTIVA",OFFSET(A96,-1,0)+1,LARGE(A$3:A95,1)) -> 0 | B96: =IF(H96="UNIDADE CONSTRUTIVA",0,IF(H96="CÉLULA CONSTRUTIVA",OFFSET(B96,-1,0)+1,OFFSET(B96,-1,0))) -> 2 | C96: =IF(H96="CÉLULA CONSTRUTIVA",0,IF(H96="ETAPA",OFFSET(C96,-1,0)+1,OFFSET(C96,-1,0))) -> 2 | D96: =IF(H96="ETAPA",0,IF(H96="SUBETAPA",OFFSET(D96,-1,0)+1,OFFSET(D96,-1,0))) -> 3 | E96: =IF(H96="Subetapa",0,IF(H96="serviço",OFFSET(E96,-1,0)+1,OFFSET(E96,-1,0))) -> 5 | H96: SERVIÇO | I96: =IF(H96="Unidade Construtiva",TEXT(A96,"00"),IF(H96="Célula Construtiva",TEXT(B96,"00"),IF(H96="Etapa",CONCATENATE(TEXT(B96,"00"),".",TEXT(C96,"000")),IF(H96="Subetapa",CONCATENATE(TEXT(B96,"00"),".",TEXT(C96,"000"),".",TEXT(D96,"000")),IF(H96="Serviço",CONCATENATE(TEXT(B96,"00"),".",TEXT(C96,"000"),".",TEXT(D96,"000"),".",TEXT(E96,"000")),""))))) -> 02.002.003.005 | J96: Equipamentos de apoio a obra | K96: vb | L96: 1 | M96: 35500 | N96: =IF(H96="Serviço",M96*L96,IF(H96="CÉLULA CONSTRUTIVA",SUMIFS($N$8:$N$420,$B$8:$B$420,B96,$H$8:$H$420,"Serviço"),IF(H96="ETAPA",SUMIFS($N$8:$N$420,$B$8:$B$420,B96,$C$8:$C$420,C96,$H$8:$H$420,"Serviço"),IF(H96="SUBETAPA",SUMIFS($N$8:$N$420,$B$8:$B$420,B96,$C$8:$C$420,C96,$D$8:$D$420,D96,$H$8:$H$420,"Serviço"),0)))) -> 35500 | O96: Conforme estimativa da aba "Canteiro" | P96: Finalizado
A97: =IF($H97="UNIDADE CONSTRUTIVA",OFFSET(A97,-1,0)+1,LARGE(A$3:A96,1)) -> 0 | B97: =IF(H97="UNIDADE CONSTRUTIVA",0,IF(H97="CÉLULA CONSTRUTIVA",OFFSET(B97,-1,0)+1,OFFSET(B97,-1,0))) -> 2 | C97: =IF(H97="CÉLULA CONSTRUTIVA",0,IF(H97="ETAPA",OFFSET(C97,-1,0)+1,OFFSET(C97,-1,0))) -> 2 | D97: =IF(H97="ETAPA",0,IF(H97="SUBETAPA",OFFSET(D97,-1,0)+1,OFFSET(D97,-1,0))) -> 3 | E97: =IF(H97="Subetapa",0,IF(H97="serviço",OFFSET(E97,-1,0)+1,OFFSET(E97,-1,0))) -> 6 | H97: SERVIÇO | I97: =IF(H97="Unidade Construtiva",TEXT(A97,"00"),IF(H97="Célula Construtiva",TEXT(B97,"00"),IF(H97="Etapa",CONCATENATE(TEXT(B97,"00"),".",TEXT(C97,"000")),IF(H97="Subetapa",CONCATENATE(TEXT(B97,"00"),".",TEXT(C97,"000"),".",TEXT(D97,"000")),IF(H97="Serviço",CONCATENATE(TEXT(B97,"00"),".",TEXT(C97,"000"),".",TEXT(D97,"000"),".",TEXT(E97,"000")),""))))) -> 02.002.003.006 | J97: Tapume de telha metálica trapezoidal | K97: m2 | L97: =EPCs!D57 -> 303.336 | M97: 70.7301 | N97: =IF(H97="Serviço",M97*L97,IF(H97="CÉLULA CONSTRUTIVA",SUMIFS($N$8:$N$420,$B$8:$B$420,B97,$H$8:$H$420,"Serviço"),IF(H97="ETAPA",SUMIFS($N$8:$N$420,$B$8:$B$420,B97,$C$8:$C$420,C97,$H$8:$H$420,"Serviço"),IF(H97="SUBETAPA",SUMIFS($N$8:$N$420,$B$8:$B$420,B97,$C$8:$C$420,C97,$D$8:$D$420,D97,$H$8:$H$420,"Serviço"),0)))) -> 21454.986 | O97: Fechamento frontal da obra e dos fundos da obra | P97: Finalizado
A98: =IF($H98="UNIDADE CONSTRUTIVA",OFFSET(A98,-1,0)+1,LARGE(A$3:A97,1)) -> 0 | B98: =IF(H98="UNIDADE CONSTRUTIVA",0,IF(H98="CÉLULA CONSTRUTIVA",OFFSET(B98,-1,0)+1,OFFSET(B98,-1,0))) -> 2 | C98: =IF(H98="CÉLULA CONSTRUTIVA",0,IF(H98="ETAPA",OFFSET(C98,-1,0)+1,OFFSET(C98,-1,0))) -> 2 | D98: =IF(H98="ETAPA",0,IF(H98="SUBETAPA",OFFSET(D98,-1,0)+1,OFFSET(D98,-1,0))) -> 4 | E98: =IF(H98="Subetapa",0,IF(H98="serviço",OFFSET(E98,-1,0)+1,OFFSET(E98,-1,0))) -> 0 | H98: SUBETAPA | I98: =IF(H98="Unidade Construtiva",TEXT(A98,"00"),IF(H98="Célula Construtiva",TEXT(B98,"00"),IF(H98="Etapa",CONCATENATE(TEXT(B98,"00"),".",TEXT(C98,"000")),IF(H98="Subetapa",CONCATENATE(TEXT(B98,"00"),".",TEXT(C98,"000"),".",TEXT(D98,"000")),IF(H98="Serviço",CONCATENATE(TEXT(B98,"00"),".",TEXT(C98,"000"),".",TEXT(D98,"000"),".",TEXT(E98,"000")),""))))) -> 02.002.004 | J98: Ligações Provisórias | N98: =IF(H98="Serviço",M98*L98,IF(H98="CÉLULA CONSTRUTIVA",SUMIFS($N$8:$N$420,$B$8:$B$420,B98,$H$8:$H$420,"Serviço"),IF(H98="ETAPA",SUMIFS($N$8:$N$420,$B$8:$B$420,B98,$C$8:$C$420,C98,$H$8:$H$420,"Serviço"),IF(H98="SUBETAPA",SUMIFS($N$8:$N$420,$B$8:$B$420,B98,$C$8:$C$420,C98,$D$8:$D$420,D98,$H$8:$H$420,"Serviço"),0)))) -> 37503.505
A99: =IF($H99="UNIDADE CONSTRUTIVA",OFFSET(A99,-1,0)+1,LARGE(A$3:A98,1)) -> 0 | B99: =IF(H99="UNIDADE CONSTRUTIVA",0,IF(H99="CÉLULA CONSTRUTIVA",OFFSET(B99,-1,0)+1,OFFSET(B99,-1,0))) -> 2 | C99: =IF(H99="CÉLULA CONSTRUTIVA",0,IF(H99="ETAPA",OFFSET(C99,-1,0)+1,OFFSET(C99,-1,0))) -> 2 | D99: =IF(H99="ETAPA",0,IF(H99="SUBETAPA",OFFSET(D99,-1,0)+1,OFFSET(D99,-1,0))) -> 4 | E99: =IF(H99="Subetapa",0,IF(H99="serviço",OFFSET(E99,-1,0)+1,OFFSET(E99,-1,0))) -> 1 | H99: SERVIÇO | I99: =IF(H99="Unidade Construtiva",TEXT(A99,"00"),IF(H99="Célula Construtiva",TEXT(B99,"00"),IF(H99="Etapa",CONCATENATE(TEXT(B99,"00"),".",TEXT(C99,"000")),IF(H99="Subetapa",CONCATENATE(TEXT(B99,"00"),".",TEXT(C99,"000"),".",TEXT(D99,"000")),IF(H99="Serviço",CONCATENATE(TEXT(B99,"00"),".",TEXT(C99,"000"),".",TEXT(D99,"000"),".",TEXT(E99,"000")),""))))) -> 02.002.004.001 | J99: Rede de água fria, esgoto e drenagem | K99: vb | L99: 1 | M99: 19775.424 | N99: =IF(H99="Serviço",M99*L99,IF(H99="CÉLULA CONSTRUTIVA",SUMIFS($N$8:$N$420,$B$8:$B$420,B99,$H$8:$H$420,"Serviço"),IF(H99="ETAPA",SUMIFS($N$8:$N$420,$B$8:$B$420,B99,$C$8:$C$420,C99,$H$8:$H$420,"Serviço"),IF(H99="SUBETAPA",SUMIFS($N$8:$N$420,$B$8:$B$420,B99,$C$8:$C$420,C99,$D$8:$D$420,D99,$H$8:$H$420,"Serviço"),0)))) -> 19775.424 | O99: Estimado com base em índices históricos | P99: Finalizado
A100: =IF($H100="UNIDADE CONSTRUTIVA",OFFSET(A100,-1,0)+1,LARGE(A$3:A99,1)) -> 0 | B100: =IF(H100="UNIDADE CONSTRUTIVA",0,IF(H100="CÉLULA CONSTRUTIVA",OFFSET(B100,-1,0)+1,OFFSET(B100,-1,0))) -> 2 | C100: =IF(H100="CÉLULA CONSTRUTIVA",0,IF(H100="ETAPA",OFFSET(C100,-1,0)+1,OFFSET(C100,-1,0))) -> 2 | D100: =IF(H100="ETAPA",0,IF(H100="SUBETAPA",OFFSET(D100,-1,0)+1,OFFSET(D100,-1,0))) -> 4 | E100: =IF(H100="Subetapa",0,IF(H100="serviço",OFFSET(E100,-1,0)+1,OFFSET(E100,-1,0))) -> 2 | H100: SERVIÇO | I100: =IF(H100="Unidade Construtiva",TEXT(A100,"00"),IF(H100="Célula Construtiva",TEXT(B100,"00"),IF(H100="Etapa",CONCATENATE(TEXT(B100,"00"),".",TEXT(C100,"000")),IF(H100="Subetapa",CONCATENATE(TEXT(B100,"00"),".",TEXT(C100,"000"),".",TEXT(D100,"000")),IF(H100="Serviço",CONCATENATE(TEXT(B100,"00"),".",TEXT(C100,"000"),".",TEXT(D100,"000"),".",TEXT(E100,"000")),""))))) -> 02.002.004.002 | J100: Redes elétricas, comunicação e dados | K100: vb | L100: 1 | M100: 17728.081 | N100: =IF(H100="Serviço",M100*L100,IF(H100="CÉLULA CONSTRUTIVA",SUMIFS($N$8:$N$420,$B$8:$B$420,B100,$H$8:$H$420,"Serviço"),IF(H100="ETAPA",SUMIFS($N$8:$N$420,$B$8:$B$420,B100,$C$8:$C$420,C100,$H$8:$H$420,"Serviço"),IF(H100="SUBETAPA",SUMIFS($N$8:$N$420,$B$8:$B$420,B100,$C$8:$C$420,C100,$D$8:$D$420,D100,$H$8:$H$420,"Serviço"),0)))) -> 17728.081 | O100: Estimado com base em índices históricos | P100: Finalizado
A101: =IF($H101="UNIDADE CONSTRUTIVA",OFFSET(A101,-1,0)+1,LARGE(A$3:A100,1)) -> 0 | B101: =IF(H101="UNIDADE CONSTRUTIVA",0,IF(H101="CÉLULA CONSTRUTIVA",OFFSET(B101,-1,0)+1,OFFSET(B101,-1,0))) -> 2 | C101: =IF(H101="CÉLULA CONSTRUTIVA",0,IF(H101="ETAPA",OFFSET(C101,-1,0)+1,OFFSET(C101,-1,0))) -> 2 | D101: =IF(H101="ETAPA",0,IF(H101="SUBETAPA",OFFSET(D101,-1,0)+1,OFFSET(D101,-1,0))) -> 5 | E101: =IF(H101="Subetapa",0,IF(H101="serviço",OFFSET(E101,-1,0)+1,OFFSET(E101,-1,0))) -> 0 | H101: SUBETAPA | I101: =IF(H101="Unidade Construtiva",TEXT(A101,"00"),IF(H101="Célula Construtiva",TEXT(B101,"00"),IF(H101="Etapa",CONCATENATE(TEXT(B101,"00"),".",TEXT(C101,"000")),IF(H101="Subetapa",CONCATENATE(TEXT(B101,"00"),".",TEXT(C101,"000"),".",TEXT(D101,"000")),IF(H101="Serviço",CONCATENATE(TEXT(B101,"00"),".",TEXT(C101,"000"),".",TEXT(D101,"000"),".",TEXT(E101,"000")),""))))) -> 02.002.005 | J101: Serviços Iniciais | N101: =IF(H101="Serviço",M101*L101,IF(H101="CÉLULA CONSTRUTIVA",SUMIFS($N$8:$N$420,$B$8:$B$420,B101,$H$8:$H$420,"Serviço"),IF(H101="ETAPA",SUMIFS($N$8:$N$420,$B$8:$B$420,B101,$C$8:$C$420,C101,$H$8:$H$420,"Serviço"),IF(H101="SUBETAPA",SUMIFS($N$8:$N$420,$B$8:$B$420,B101,$C$8:$C$420,C101,$D$8:$D$420,D101,$H$8:$H$420,"Serviço"),0)))) -> 56180.63
A102: =IF($H102="UNIDADE CONSTRUTIVA",OFFSET(A102,-1,0)+1,LARGE(A$3:A100,1)) -> 0 | B102: =IF(H102="UNIDADE CONSTRUTIVA",0,IF(H102="CÉLULA CONSTRUTIVA",OFFSET(B102,-1,0)+1,OFFSET(B102,-1,0))) -> 2 | C102: =IF(H102="CÉLULA CONSTRUTIVA",0,IF(H102="ETAPA",OFFSET(C102,-1,0)+1,OFFSET(C102,-1,0))) -> 2 | D102: =IF(H102="ETAPA",0,IF(H102="SUBETAPA",OFFSET(D102,-1,0)+1,OFFSET(D102,-1,0))) -> 5 | E102: =IF(H102="Subetapa",0,IF(H102="serviço",OFFSET(E102,-1,0)+1,OFFSET(E102,-1,0))) -> 1 | H102: SERVIÇO | I102: =IF(H102="Unidade Construtiva",TEXT(A102,"00"),IF(H102="Célula Construtiva",TEXT(B102,"00"),IF(H102="Etapa",CONCATENATE(TEXT(B102,"00"),".",TEXT(C102,"000")),IF(H102="Subetapa",CONCATENATE(TEXT(B102,"00"),".",TEXT(C102,"000"),".",TEXT(D102,"000")),IF(H102="Serviço",CONCATENATE(TEXT(B102,"00"),".",TEXT(C102,"000"),".",TEXT(D102,"000"),".",TEXT(E102,"000")),""))))) -> 02.002.005.001 | J102: Demolições | K102: vb | L102: 1 | M102: 35379.243 | N102: =IF(H102="Serviço",M102*L102,IF(H102="CÉLULA CONSTRUTIVA",SUMIFS($N$8:$N$420,$B$8:$B$420,B102,$H$8:$H$420,"Serviço"),IF(H102="ETAPA",SUMIFS($N$8:$N$420,$B$8:$B$420,B102,$C$8:$C$420,C102,$H$8:$H$420,"Serviço"),IF(H102="SUBETAPA",SUMIFS($N$8:$N$420,$B$8:$B$420,B102,$C$8:$C$420,C102,$D$8:$D$420,D102,$H$8:$H$420,"Serviço"),0)))) -> 35379.243 | O102: Estimado com base em índices históricos | P102: Finalizado
A103: =IF($H103="UNIDADE CONSTRUTIVA",OFFSET(A103,-1,0)+1,LARGE(A$3:A101,1)) -> 0 | B103: =IF(H103="UNIDADE CONSTRUTIVA",0,IF(H103="CÉLULA CONSTRUTIVA",OFFSET(B103,-1,0)+1,OFFSET(B103,-1,0))) -> 2 | C103: =IF(H103="CÉLULA CONSTRUTIVA",0,IF(H103="ETAPA",OFFSET(C103,-1,0)+1,OFFSET(C103,-1,0))) -> 2 | D103: =IF(H103="ETAPA",0,IF(H103="SUBETAPA",OFFSET(D103,-1,0)+1,OFFSET(D103,-1,0))) -> 5 | E103: =IF(H103="Subetapa",0,IF(H103="serviço",OFFSET(E103,-1,0)+1,OFFSET(E103,-1,0))) -> 2 | H103: SERVIÇO | I103: =IF(H103="Unidade Construtiva",TEXT(A103,"00"),IF(H103="Célula Construtiva",TEXT(B103,"00"),IF(H103="Etapa",CONCATENATE(TEXT(B103,"00"),".",TEXT(C103,"000")),IF(H103="Subetapa",CONCATENATE(TEXT(B103,"00"),".",TEXT(C103,"000"),".",TEXT(D103,"000")),IF(H103="Serviço",CONCATENATE(TEXT(B103,"00"),".",TEXT(C103,"000"),".",TEXT(D103,"000"),".",TEXT(E103,"000")),""))))) -> 02.002.005.002 | J103: Limpeza da camada vegetal Mecanizada | K103: m2 | L103: ='Obra '!E8 -> 894.13 | M103: 13.5 | N103: =IF(H103="Serviço",M103*L103,IF(H103="CÉLULA CONSTRUTIVA",SUMIFS($N$8:$N$420,$B$8:$B$420,B103,$H$8:$H$420,"Serviço"),IF(H103="ETAPA",SUMIFS($N$8:$N$420,$B$8:$B$420,B103,$C$8:$C$420,C103,$H$8:$H$420,"Serviço"),IF(H103="SUBETAPA",SUMIFS($N$8:$N$420,$B$8:$B$420,B103,$C$8:$C$420,C103,$D$8:$D$420,D103,$H$8:$H$420,"Serviço"),0)))) -> 12070.755 | O103: Estimado com base em índices históricos | P103: Finalizado
...

Sheet Ger_Executivo
G4: PROJETO: | I4: ='Obra '!D1 -> Porto Cerro | O4: REVISÃO: | P4: DATA
G5: EMPRESA: | I5: ='Obra '!D2 -> XPCon Empreendimentos | O5: R01 | P5: 45887
A6: Unidade Construtiva | B6: Célula Construtiva | C6: Etapa | D6: Subetapa | E6: Serviço | G6: GERENCIAMENTO EXECUTIVO
A7: 0 | B7: 0 | C7: 0 | D7: 0 | E7: 0 | G7: Atalho | H7: NIVEL | I7: Item | J7: Descrição | K7: Unidade | L7: Quant. | M7: Preço un | N7: Total | O7: Considerações | P7: Situação
A8: =IF($H8="UNIDADE CONSTRUTIVA",OFFSET(A8,-1,0)+1,LARGE(A$3:A7,1)) -> 0 | B8: =IF(H8="UNIDADE CONSTRUTIVA",0,IF(H8="CÉLULA CONSTRUTIVA",OFFSET(B8,-1,0)+1,OFFSET(B8,-1,0))) -> 1 | C8: =IF(H8="CÉLULA CONSTRUTIVA",0,IF(H8="ETAPA",OFFSET(C8,-1,0)+1,OFFSET(C8,-1,0))) -> 0 | D8: =IF(H8="ETAPA",0,IF(H8="SUBETAPA",OFFSET(D8,-1,0)+1,OFFSET(D8,-1,0))) -> 0 | E8: =IF(H8="Subetapa",0,IF(H8="serviço",OFFSET(E8,-1,0)+1,OFFSET(E8,-1,0))) -> 0 | H8: CÉLULA CONSTRUTIVA | I8: =IF(H8="Unidade Construtiva",TEXT(A8,"00"),IF(H8="Célula Construtiva",TEXT(B8,"00"),IF(H8="Etapa",CONCATENATE(TEXT(B8,"00"),".",TEXT(C8,"000")),IF(H8="Subetapa",CONCATENATE(TEXT(B8,"00"),".",TEXT(C8,"000"),".",TEXT(D8,"000")),IF(H8="Serviço",CONCATENATE(TEXT(B8,"00"),".",TEXT(C8,"000"),".",TEXT(D8,"000"),".",TEXT(E8,"000")),""))))) -> 01 | J8: MOVIMENTAÇÃO DE TERRA | N8: =IF(H8="Serviço",M8*L8,IF(H8="CÉLULA CONSTRUTIVA",SUMIFS($N$8:$N$1393,$B$8:$B$1393,B8,$H$8:$H$1393,"Serviço"),IF(H8="ETAPA",SUMIFS($N$8:$N$1393,$B$8:$B$1393,B8,$C$8:$C$1393,C8,$H$8:$H$1393,"Serviço"),IF(H8="SUBETAPA",SUMIFS($N$8:$N$1393,$B$8:$B$1393,B8,$C$8:$C$1393,C8,$D$8:$D$1393,D8,$H$8:$H$1393,"Serviço"),0)))) -> 201548.69
A9: =IF($H9="UNIDADE CONSTRUTIVA",OFFSET(A9,-1,0)+1,LARGE(A$3:A8,1)) -> 0 | B9: =IF(H9="UNIDADE CONSTRUTIVA",0,IF(H9="CÉLULA CONSTRUTIVA",OFFSET(B9,-1,0)+1,OFFSET(B9,-1,0))) -> 1 | C9: =IF(H9="CÉLULA CONSTRUTIVA",0,IF(H9="ETAPA",OFFSET(C9,-1,0)+1,OFFSET(C9,-1,0))) -> 1 | D9: =IF(H9="ETAPA",0,IF(H9="SUBETAPA",OFFSET(D9,-1,0)+1,OFFSET(D9,-1,0))) -> 0 | E9: =IF(H9="Subetapa",0,IF(H9="serviço",OFFSET(E9,-1,0)+1,OFFSET(E9,-1,0))) -> 0 | H9: ETAPA | I9: =IF(H9="Unidade Construtiva",TEXT(A9,"00"),IF(H9="Célula Construtiva",TEXT(B9,"00"),IF(H9="Etapa",CONCATENATE(TEXT(B9,"00"),".",TEXT(C9,"000")),IF(H9="Subetapa",CONCATENATE(TEXT(B9,"00"),".",TEXT(C9,"000"),".",TEXT(D9,"000")),IF(H9="Serviço",CONCATENATE(TEXT(B9,"00"),".",TEXT(C9,"000"),".",TEXT(D9,"000"),".",TEXT(E9,"000")),""))))) -> 01.001 | J9: MOVIMENTAÇÃO DE TERRA | N9: =IF(H9="Serviço",M9*L9,IF(H9="CÉLULA CONSTRUTIVA",SUMIFS($N$8:$N$1393,$B$8:$B$1393,B9,$H$8:$H$1393,"Serviço"),IF(H9="ETAPA",SUMIFS($N$8:$N$1393,$B$8:$B$1393,B9,$C$8:$C$1393,C9,$H$8:$H$1393,"Serviço"),IF(H9="SUBETAPA",SUMIFS($N$8:$N$1393,$B$8:$B$1393,B9,$C$8:$C$1393,C9,$D$8:$D$1393,D9,$H$8:$H$1393,"Serviço"),0)))) -> 201548.69
A10: =IF($H10="UNIDADE CONSTRUTIVA",OFFSET(A10,-1,0)+1,LARGE(A$3:A9,1)) -> 0 | B10: =IF(H10="UNIDADE CONSTRUTIVA",0,IF(H10="CÉLULA CONSTRUTIVA",OFFSET(B10,-1,0)+1,OFFSET(B10,-1,0))) -> 1 | C10: =IF(H10="CÉLULA CONSTRUTIVA",0,IF(H10="ETAPA",OFFSET(C10,-1,0)+1,OFFSET(C10,-1,0))) -> 1 | D10: =IF(H10="ETAPA",0,IF(H10="SUBETAPA",OFFSET(D10,-1,0)+1,OFFSET(D10,-1,0))) -> 1 | E10: =IF(H10="Subetapa",0,IF(H10="serviço",OFFSET(E10,-1,0)+1,OFFSET(E10,-1,0))) -> 0 | H10: SUBETAPA | I10: =IF(H10="Unidade Construtiva",TEXT(A10,"00"),IF(H10="Célula Construtiva",TEXT(B10,"00"),IF(H10="Etapa",CONCATENATE(TEXT(B10,"00"),".",TEXT(C10,"000")),IF(H10="Subetapa",CONCATENATE(TEXT(B10,"00"),".",TEXT(C10,"000"),".",TEXT(D10,"000")),IF(H10="Serviço",CONCATENATE(TEXT(B10,"00"),".",TEXT(C10,"000"),".",TEXT(D10,"000"),".",TEXT(E10,"000")),""))))) -> 01.001.001 | J10: Rebaixamento de Lençol Freático | N10: =IF(H10="Serviço",M10*L10,IF(H10="CÉLULA CONSTRUTIVA",SUMIFS($N$8:$N$1393,$B$8:$B$1393,B10,$H$8:$H$1393,"Serviço"),IF(H10="ETAPA",SUMIFS($N$8:$N$1393,$B$8:$B$1393,B10,$C$8:$C$1393,C10,$H$8:$H$1393,"Serviço"),IF(H10="SUBETAPA",SUMIFS($N$8:$N$1393,$B$8:$B$1393,B10,$C$8:$C$1393,C10,$D$8:$D$1393,D10,$H$8:$H$1393,"Serviço"),0)))) -> 34800
A11: =IF($H11="UNIDADE CONSTRUTIVA",OFFSET(A11,-1,0)+1,LARGE(A$3:A10,1)) -> 0 | B11: =IF(H11="UNIDADE CONSTRUTIVA",0,IF(H11="CÉLULA CONSTRUTIVA",OFFSET(B11,-1,0)+1,OFFSET(B11,-1,0))) -> 1 | C11: =IF(H11="CÉLULA CONSTRUTIVA",0,IF(H11="ETAPA",OFFSET(C11,-1,0)+1,OFFSET(C11,-1,0))) -> 1 | D11: =IF(H11="ETAPA",0,IF(H11="SUBETAPA",OFFSET(D11,-1,0)+1,OFFSET(D11,-1,0))) -> 1 | E11: =IF(H11="Subetapa",0,IF(H11="serviço",OFFSET(E11,-1,0)+1,OFFSET(E11,-1,0))) -> 1 | H11: SERVIÇO | I11: =IF(H11="Unidade Construtiva",TEXT(A11,"00"),IF(H11="Célula Construtiva",TEXT(B11,"00"),IF(H11="Etapa",CONCATENATE(TEXT(B11,"00"),".",TEXT(C11,"000")),IF(H11="Subetapa",CONCATENATE(TEXT(B11,"00"),".",TEXT(C11,"000"),".",TEXT(D11,"000")),IF(H11="Serviço",CONCATENATE(TEXT(B11,"00"),".",TEXT(C11,"000"),".",TEXT(D11,"000"),".",TEXT(E11,"000")),""))))) -> 01.001.001.001 | J11: Rebaixamento de Lençol Freático | K11: vb | L11: 1 | M11: 34800 | N11: =IF(H11="Serviço",M11*L11,IF(H11="CÉLULA CONSTRUTIVA",SUMIFS($N$8:$N$1393,$B$8:$B$1393,B11,$H$8:$H$1393,"Serviço"),IF(H11="ETAPA",SUMIFS($N$8:$N$1393,$B$8:$B$1393,B11,$C$8:$C$1393,C11,$H$8:$H$1393,"Serviço"),IF(H11="SUBETAPA",SUMIFS($N$8:$N$1393,$B$8:$B$1393,B11,$C$8:$C$1393,C11,$D$8:$D$1393,D11,$H$8:$H$1393,"Serviço"),0)))) -> 34800 | O11: Considerado 1 bomba para execução dos blocos e vigas baldrames, no prazo de 2 meses. | P11: Finalizado
A12: =IF($H12="UNIDADE CONSTRUTIVA",OFFSET(A12,-1,0)+1,LARGE(A$3:A11,1)) -> 0 | B12: =IF(H12="UNIDADE CONSTRUTIVA",0,IF(H12="CÉLULA CONSTRUTIVA",OFFSET(B12,-1,0)+1,OFFSET(B12,-1,0))) -> 1 | C12: =IF(H12="CÉLULA CONSTRUTIVA",0,IF(H12="ETAPA",OFFSET(C12,-1,0)+1,OFFSET(C12,-1,0))) -> 1 | D12: =IF(H12="ETAPA",0,IF(H12="SUBETAPA",OFFSET(D12,-1,0)+1,OFFSET(D12,-1,0))) -> 2 | E12: =IF(H12="Subetapa",0,IF(H12="serviço",OFFSET(E12,-1,0)+1,OFFSET(E12,-1,0))) -> 0 | H12: SUBETAPA | I12: =IF(H12="Unidade Construtiva",TEXT(A12,"00"),IF(H12="Célula Construtiva",TEXT(B12,"00"),IF(H12="Etapa",CONCATENATE(TEXT(B12,"00"),".",TEXT(C12,"000")),IF(H12="Subetapa",CONCATENATE(TEXT(B12,"00"),".",TEXT(C12,"000"),".",TEXT(D12,"000")),IF(H12="Serviço",CONCATENATE(TEXT(B12,"00"),".",TEXT(C12,"000"),".",TEXT(D12,"000"),".",TEXT(E12,"000")),""))))) -> 01.001.002 | J12: Escavação e Reaterro de Valas | N12: =IF(H12="Serviço",M12*L12,IF(H12="CÉLULA CONSTRUTIVA",SUMIFS($N$8:$N$1393,$B$8:$B$1393,B12,$H$8:$H$1393,"Serviço"),IF(H12="ETAPA",SUMIFS($N$8:$N$1393,$B$8:$B$1393,B12,$C$8:$C$1393,C12,$H$8:$H$1393,"Serviço"),IF(H12="SUBETAPA",SUMIFS($N$8:$N$1393,$B$8:$B$1393,B12,$C$8:$C$1393,C12,$D$8:$D$1393,D12,$H$8:$H$1393,"Serviço"),0)))) -> 61259.767
A13: =IF($H13="UNIDADE CONSTRUTIVA",OFFSET(A13,-1,0)+1,LARGE(A$3:A12,1)) -> 0 | B13: =IF(H13="UNIDADE CONSTRUTIVA",0,IF(H13="CÉLULA CONSTRUTIVA",OFFSET(B13,-1,0)+1,OFFSET(B13,-1,0))) -> 1 | C13: =IF(H13="CÉLULA CONSTRUTIVA",0,IF(H13="ETAPA",OFFSET(C13,-1,0)+1,OFFSET(C13,-1,0))) -> 1 | D13: =IF(H13="ETAPA",0,IF(H13="SUBETAPA",OFFSET(D13,-1,0)+1,OFFSET(D13,-1,0))) -> 2 | E13: =IF(H13="Subetapa",0,IF(H13="serviço",OFFSET(E13,-1,0)+1,OFFSET(E13,-1,0))) -> 1 | H13: SERVIÇO | I13: =IF(H13="Unidade Construtiva",TEXT(A13,"00"),IF(H13="Célula Construtiva",TEXT(B13,"00"),IF(H13="Etapa",CONCATENATE(TEXT(B13,"00"),".",TEXT(C13,"000")),IF(H13="Subetapa",CONCATENATE(TEXT(B13,"00"),".",TEXT(C13,"000"),".",TEXT(D13,"000")),IF(H13="Serviço",CONCATENATE(TEXT(B13,"00"),".",TEXT(C13,"000"),".",TEXT(D13,"000"),".",TEXT(E13,"000")),""))))) -> 01.001.002.001 | J13: Escavação mecanizada para blocos de fundação, vigas de fundação e poço de elevador, com retroescavadeira | K13: m3 | L13: ='Fundação Rasa'!G7 -> 1297.6939 | M13: 36.36 | N13: =IF(H13="Serviço",M13*L13,IF(H13="CÉLULA CONSTRUTIVA",SUMIFS($N$8:$N$1393,$B$8:$B$1393,B13,$H$8:$H$1393,"Serviço"),IF(H13="ETAPA",SUMIFS($N$8:$N$1393,$B$8:$B$1393,B13,$C$8:$C$1393,C13,$H$8:$H$1393,"Serviço"),IF(H13="SUBETAPA",SUMIFS($N$8:$N$1393,$B$8:$B$1393,B13,$C$8:$C$1393,C13,$D$8:$D$1393,D13,$H$8:$H$1393,"Serviço"),0)))) -> 47184.151 | O13: Considerado blocos, vigas de fundação, duto e cisterna | P13: Finalizado
A14: =IF($H14="UNIDADE CONSTRUTIVA",OFFSET(A14,-1,0)+1,LARGE(A$3:A13,1)) -> 0 | B14: =IF(H14="UNIDADE CONSTRUTIVA",0,IF(H14="CÉLULA CONSTRUTIVA",OFFSET(B14,-1,0)+1,OFFSET(B14,-1,0))) -> 1 | C14: =IF(H14="CÉLULA CONSTRUTIVA",0,IF(H14="ETAPA",OFFSET(C14,-1,0)+1,OFFSET(C14,-1,0))) -> 1 | D14: =IF(H14="ETAPA",0,IF(H14="SUBETAPA",OFFSET(D14,-1,0)+1,OFFSET(D14,-1,0))) -> 2 | E14: =IF(H14="Subetapa",0,IF(H14="serviço",OFFSET(E14,-1,0)+1,OFFSET(E14,-1,0))) -> 2 | H14: SERVIÇO | I14: =IF(H14="Unidade Construtiva",TEXT(A14,"00"),IF(H14="Célula Construtiva",TEXT(B14,"00"),IF(H14="Etapa",CONCATENATE(TEXT(B14,"00"),".",TEXT(C14,"000")),IF(H14="Subetapa",CONCATENATE(TEXT(B14,"00"),".",TEXT(C14,"000"),".",TEXT(D14,"000")),IF(H14="Serviço",CONCATENATE(TEXT(B14,"00"),".",TEXT(C14,"000"),".",TEXT(D14,"000"),".",TEXT(E14,"000")),""))))) -> 01.001.002.002 | J14: Reaterro mecanizado de valas para blocos e vigas de fundação, com retroescavadeira | K14: m3 | L14: ='Fundação Rasa'!I7-Aço_Infraestrutura!M26-Aço_Infraestrutura!M28 -> 967.39628 | M14: 14.55 | N14: =IF(H14="Serviço",M14*L14,IF(H14="CÉLULA CONSTRUTIVA",SUMIFS($N$8:$N$1393,$B$8:$B$1393,B14,$H$8:$H$1393,"Serviço"),IF(H14="ETAPA",SUMIFS($N$8:$N$1393,$B$8:$B$1393,B14,$C$8:$C$1393,C14,$H$8:$H$1393,"Serviço"),IF(H14="SUBETAPA",SUMIFS($N$8:$N$1393,$B$8:$B$1393,B14,$C$8:$C$1393,C14,$D$8:$D$1393,D14,$H$8:$H$1393,"Serviço"),0)))) -> 14075.616 | O14: Arbitrado tamanho de cisterna de 3,5x8m com espessura de 10cm | P14: Finalizado
A15: =IF($H15="UNIDADE CONSTRUTIVA",OFFSET(A15,-1,0)+1,LARGE(A$3:A14,1)) -> 0 | B15: =IF(H15="UNIDADE CONSTRUTIVA",0,IF(H15="CÉLULA CONSTRUTIVA",OFFSET(B15,-1,0)+1,OFFSET(B15,-1,0))) -> 1 | C15: =IF(H15="CÉLULA CONSTRUTIVA",0,IF(H15="ETAPA",OFFSET(C15,-1,0)+1,OFFSET(C15,-1,0))) -> 1 | D15: =IF(H15="ETAPA",0,IF(H15="SUBETAPA",OFFSET(D15,-1,0)+1,OFFSET(D15,-1,0))) -> 3 | E15: =IF(H15="Subetapa",0,IF(H15="serviço",OFFSET(E15,-1,0)+1,OFFSET(E15,-1,0))) -> 0 | H15: SUBETAPA | I15: =IF(H15="Unidade Construtiva",TEXT(A15,"00"),IF(H15="Célula Construtiva",TEXT(B15,"00"),IF(H15="Etapa",CONCATENATE(TEXT(B15,"00"),".",TEXT(C15,"000")),IF(H15="Subetapa",CONCATENATE(TEXT(B15,"00"),".",TEXT(C15,"000"),".",TEXT(D15,"000")),IF(H15="Serviço",CONCATENATE(TEXT(B15,"00"),".",TEXT(C15,"000"),".",TEXT(D15,"000"),".",TEXT(E15,"000")),""))))) -> 01.001.003 | J15: Lastro de brita | N15: =IF(H15="Serviço",M15*L15,IF(H15="CÉLULA CONSTRUTIVA",SUMIFS($N$8:$N$1393,$B$8:$B$1393,B15,$H$8:$H$1393,"Serviço"),IF(H15="ETAPA",SUMIFS($N$8:$N$1393,$B$8:$B$1393,B15,$C$8:$C$1393,C15,$H$8:$H$1393,"Serviço"),IF(H15="SUBETAPA",SUMIFS($N$8:$N$1393,$B$8:$B$1393,B15,$C$8:$C$1393,C15,$D$8:$D$1393,D15,$H$8:$H$1393,"Serviço"),0)))) -> 9501.4934
A16: =IF($H16="UNIDADE CONSTRUTIVA",OFFSET(A16,-1,0)+1,LARGE(A$3:A15,1)) -> 0 | B16: =IF(H16="UNIDADE CONSTRUTIVA",0,IF(H16="CÉLULA CONSTRUTIVA",OFFSET(B16,-1,0)+1,OFFSET(B16,-1,0))) -> 1 | C16: =IF(H16="CÉLULA CONSTRUTIVA",0,IF(H16="ETAPA",OFFSET(C16,-1,0)+1,OFFSET(C16,-1,0))) -> 1 | D16: =IF(H16="ETAPA",0,IF(H16="SUBETAPA",OFFSET(D16,-1,0)+1,OFFSET(D16,-1,0))) -> 3 | E16: =IF(H16="Subetapa",0,IF(H16="serviço",OFFSET(E16,-1,0)+1,OFFSET(E16,-1,0))) -> 1 | H16: SERVIÇO | I16: =IF(H16="Unidade Construtiva",TEXT(A16,"00"),IF(H16="Célula Construtiva",TEXT(B16,"00"),IF(H16="Etapa",CONCATENATE(TEXT(B16,"00"),".",TEXT(C16,"000")),IF(H16="Subetapa",CONCATENATE(TEXT(B16,"00"),".",TEXT(C16,"000"),".",TEXT(D16,"000")),IF(H16="Serviço",CONCATENATE(TEXT(B16,"00"),".",TEXT(C16,"000"),".",TEXT(D16,"000"),".",TEXT(E16,"000")),""))))) -> 01.001.003.001 | J16: Lastro de Concreto Magro, Aplicado em Blocos de Fundação, e=5cm | K16: m3 | L16: ='Fundação Rasa'!L7 -> 16.087139 | M16: 452.487 | N16: =IF(H16="Serviço",M16*L16,IF(H16="CÉLULA CONSTRUTIVA",SUMIFS($N$8:$N$1393,$B$8:$B$1393,B16,$H$8:$H$1393,"Serviço"),IF(H16="ETAPA",SUMIFS($N$8:$N$1393,$B$8:$B$1393,B16,$C$8:$C$1393,C16,$H$8:$H$1393,"Serviço"),IF(H16="SUBETAPA",SUMIFS($N$8:$N$1393,$B$8:$B$1393,B16,$C$8:$C$1393,C16,$D$8:$D$1393,D16,$H$8:$H$1393,"Serviço"),0)))) -> 7279.2213 | O16: Considerado sem indicação em projeto, consideração de 13% de perda | P16: Finalizado
A17: =IF($H17="UNIDADE CONSTRUTIVA",OFFSET(A17,-1,0)+1,LARGE(A$3:A16,1)) -> 0 | B17: =IF(H17="UNIDADE CONSTRUTIVA",0,IF(H17="CÉLULA CONSTRUTIVA",OFFSET(B17,-1,0)+1,OFFSET(B17,-1,0))) -> 1 | C17: =IF(H17="CÉLULA CONSTRUTIVA",0,IF(H17="ETAPA",OFFSET(C17,-1,0)+1,OFFSET(C17,-1,0))) -> 1 | D17: =IF(H17="ETAPA",0,IF(H17="SUBETAPA",OFFSET(D17,-1,0)+1,OFFSET(D17,-1,0))) -> 3 | E17: =IF(H17="Subetapa",0,IF(H17="serviço",OFFSET(E17,-1,0)+1,OFFSET(E17,-1,0))) -> 2 | H17: SERVIÇO | I17: =IF(H17="Unidade Construtiva",TEXT(A17,"00"),IF(H17="Célula Construtiva",TEXT(B17,"00"),IF(H17="Etapa",CONCATENATE(TEXT(B17,"00"),".",TEXT(C17,"000")),IF(H17="Subetapa",CONCATENATE(TEXT(B17,"00"),".",TEXT(C17,"000"),".",TEXT(D17,"000")),IF(H17="Serviço",CONCATENATE(TEXT(B17,"00"),".",TEXT(C17,"000"),".",TEXT(D17,"000"),".",TEXT(E17,"000")),""))))) -> 01.001.003.002 | J17: Lastro de Brita, Aplicado em Blocos de Fundação, e= 5cm | K17: m3 | L17: ='Fundação Rasa'!K7 -> 14.314152 | M17: 155.25 | N17: =IF(H17="Serviço",M17*L17,IF(H17="CÉLULA CONSTRUTIVA",SUMIFS($N$8:$N$1393,$B$8:$B$1393,B17,$H$8:$H$1393,"Serviço"),IF(H17="ETAPA",SUMIFS($N$8:$N$1393,$B$8:$B$1393,B17,$C$8:$C$1393,C17,$H$8:$H$1393,"Serviço"),IF(H17="SUBETAPA",SUMIFS($N$8:$N$1393,$B$8:$B$1393,B17,$C$8:$C$1393,C17,$D$8:$D$1393,D17,$H$8:$H$1393,"Serviço"),0)))) -> 2222.2721 | O17: Considerado sem indicação em projeto, consideração de 13% de perda | P17: Finalizado
A18: =IF($H18="UNIDADE CONSTRUTIVA",OFFSET(A18,-1,0)+1,LARGE(A$3:A17,1)) -> 0 | B18: =IF(H18="UNIDADE CONSTRUTIVA",0,IF(H18="CÉLULA CONSTRUTIVA",OFFSET(B18,-1,0)+1,OFFSET(B18,-1,0))) -> 1 | C18: =IF(H18="CÉLULA CONSTRUTIVA",0,IF(H18="ETAPA",OFFSET(C18,-1,0)+1,OFFSET(C18,-1,0))) -> 1 | D18: =IF(H18="ETAPA",0,IF(H18="SUBETAPA",OFFSET(D18,-1,0)+1,OFFSET(D18,-1,0))) -> 4 | E18: =IF(H18="Subetapa",0,IF(H18="serviço",OFFSET(E18,-1,0)+1,OFFSET(E18,-1,0))) -> 0 | H18: SUBETAPA | I18: =IF(H18="Unidade Construtiva",TEXT(A18,"00"),IF(H18="Célula Construtiva",TEXT(B18,"00"),IF(H18="Etapa",CONCATENATE(TEXT(B18,"00"),".",TEXT(C18,"000")),IF(H18="Subetapa",CONCATENATE(TEXT(B18,"00"),".",TEXT(C18,"000"),".",TEXT(D18,"000")),IF(H18="Serviço",CONCATENATE(TEXT(B18,"00"),".",TEXT(C18,"000"),".",TEXT(D18,"000"),".",TEXT(E18,"000")),""))))) -> 01.001.004 | J18: Movimentação de bota - fora | N18: =IF(H18="Serviço",M18*L18,IF(H18="CÉLULA CONSTRUTIVA",SUMIFS($N$8:$N$1393,$B$8:$B$1393,B18,$H$8:$H$1393,"Serviço"),IF(H18="ETAPA",SUMIFS($N$8:$N$1393,$B$8:$B$1393,B18,$C$8:$C$1393,C18,$H$8:$H$1393,"Serviço"),IF(H18="SUBETAPA",SUMIFS($N$8:$N$1393,$B$8:$B$1393,B18,$C$8:$C$1393,C18,$D$8:$D$1393,D18,$H$8:$H$1393,"Serviço"),0)))) -> 95987.43
A19: =IF($H19="UNIDADE CONSTRUTIVA",OFFSET(A19,-1,0)+1,LARGE(A$3:A18,1)) -> 0 | B19: =IF(H19="UNIDADE CONSTRUTIVA",0,IF(H19="CÉLULA CONSTRUTIVA",OFFSET(B19,-1,0)+1,OFFSET(B19,-1,0))) -> 1 | C19: =IF(H19="CÉLULA CONSTRUTIVA",0,IF(H19="ETAPA",OFFSET(C19,-1,0)+1,OFFSET(C19,-1,0))) -> 1 | D19: =IF(H19="ETAPA",0,IF(H19="SUBETAPA",OFFSET(D19,-1,0)+1,OFFSET(D19,-1,0))) -> 4 | E19: =IF(H19="Subetapa",0,IF(H19="serviço",OFFSET(E19,-1,0)+1,OFFSET(E19,-1,0))) -> 1 | H19: SERVIÇO | I19: =IF(H19="Unidade Construtiva",TEXT(A19,"00"),IF(H19="Célula Construtiva",TEXT(B19,"00"),IF(H19="Etapa",CONCATENATE(TEXT(B19,"00"),".",TEXT(C19,"000")),IF(H19="Subetapa",CONCATENATE(TEXT(B19,"00"),".",TEXT(C19,"000"),".",TEXT(D19,"000")),IF(H19="Serviço",CONCATENATE(TEXT(B19,"00"),".",TEXT(C19,"000"),".",TEXT(D19,"000"),".",TEXT(E19,"000")),""))))) -> 01.001.004.001 | J19: Movimentação de terra para bota-fora | K19: m3 | L19: ='Fundação Rasa'!J7 -> 368.16394 | M19: 45.45 | N19: =IF(H19="Serviço",M19*L19,IF(H19="CÉLULA CONSTRUTIVA",SUMIFS($N$8:$N$1393,$B$8:$B$1393,B19,$H$8:$H$1393,"Serviço"),IF(H19="ETAPA",SUMIFS($N$8:$N$1393,$B$8:$B$1393,B19,$C$8:$C$1393,C19,$H$8:$H$1393,"Serviço"),IF(H19="SUBETAPA",SUMIFS($N$8:$N$1393,$B$8:$B$1393,B19,$C$8:$C$1393,C19,$D$8:$D$1393,D19,$H$8:$H$1393,"Serviço"),0)))) -> 16733.051 | O19: Considerado empolamento 30% da escavação | P19: Finalizado
A20: =IF($H20="UNIDADE CONSTRUTIVA",OFFSET(A20,-1,0)+1,LARGE(A$3:A19,1)) -> 0 | B20: =IF(H20="UNIDADE CONSTRUTIVA",0,IF(H20="CÉLULA CONSTRUTIVA",OFFSET(B20,-1,0)+1,OFFSET(B20,-1,0))) -> 1 | C20: =IF(H20="CÉLULA CONSTRUTIVA",0,IF(H20="ETAPA",OFFSET(C20,-1,0)+1,OFFSET(C20,-1,0))) -> 1 | D20: =IF(H20="ETAPA",0,IF(H20="SUBETAPA",OFFSET(D20,-1,0)+1,OFFSET(D20,-1,0))) -> 4 | E20: =IF(H20="Subetapa",0,IF(H20="serviço",OFFSET(E20,-1,0)+1,OFFSET(E20,-1,0))) -> 2 | H20: SERVIÇO | I20: =IF(H20="Unidade Construtiva",TEXT(A20,"00"),IF(H20="Célula Construtiva",TEXT(B20,"00"),IF(H20="Etapa",CONCATENATE(TEXT(B20,"00"),".",TEXT(C20,"000")),IF(H20="Subetapa",CONCATENATE(TEXT(B20,"00"),".",TEXT(C20,"000"),".",TEXT(D20,"000")),IF(H20="Serviço",CONCATENATE(TEXT(B20,"00"),".",TEXT(C20,"000"),".",TEXT(D20,"000"),".",TEXT(E20,"000")),""))))) -> 01.001.004.002 | J20: Movimentação de terra para bota-fora - Estacas | K20: m3 | L20: =Estacas!J13 -> 1162.4286 | M20: 68.18 | N20: =IF(H20="Serviço",M20*L20,IF(H20="CÉLULA CONSTRUTIVA",SUMIFS($N$8:$N$1393,$B$8:$B$1393,B20,$H$8:$H$1393,"Serviço"),IF(H20="ETAPA",SUMIFS($N$8:$N$1393,$B$8:$B$1393,B20,$C$8:$C$1393,C20,$H$8:$H$1393,"Serviço"),IF(H20="SUBETAPA",SUMIFS($N$8:$N$1393,$B$8:$B$1393,B20,$C$8:$C$1393,C20,$D$8:$D$1393,D20,$H$8:$H$1393,"Serviço"),0)))) -> 79254.379 | O20: Considerado empolamento 30% da escavação | P20: Finalizado
A21: =IF($H21="UNIDADE CONSTRUTIVA",OFFSET(A21,-1,0)+1,LARGE(A$3:A20,1)) -> 0 | B21: =IF(H21="UNIDADE CONSTRUTIVA",0,IF(H21="CÉLULA CONSTRUTIVA",OFFSET(B21,-1,0)+1,OFFSET(B21,-1,0))) -> 2 | C21: =IF(H21="CÉLULA CONSTRUTIVA",0,IF(H21="ETAPA",OFFSET(C21,-1,0)+1,OFFSET(C21,-1,0))) -> 0 | D21: =IF(H21="ETAPA",0,IF(H21="SUBETAPA",OFFSET(D21,-1,0)+1,OFFSET(D21,-1,0))) -> 4 | E21: =IF(H21="Subetapa",0,IF(H21="serviço",OFFSET(E21,-1,0)+1,OFFSET(E21,-1,0))) -> 2 | H21: CÉLULA CONSTRUTIVA | I21: =IF(H21="Unidade Construtiva",TEXT(A21,"00"),IF(H21="Célula Construtiva",TEXT(B21,"00"),IF(H21="Etapa",CONCATENATE(TEXT(B21,"00"),".",TEXT(C21,"000")),IF(H21="Subetapa",CONCATENATE(TEXT(B21,"00"),".",TEXT(C21,"000"),".",TEXT(D21,"000")),IF(H21="Serviço",CONCATENATE(TEXT(B21,"00"),".",TEXT(C21,"000"),".",TEXT(D21,"000"),".",TEXT(E21,"000")),""))))) -> 02 | J21: INFRAESTRUTURA | N21: =IF(H21="Serviço",M21*L21,IF(H21="CÉLULA CONSTRUTIVA",SUMIFS($N$8:$N$1393,$B$8:$B$1393,B21,$H$8:$H$1393,"Serviço"),IF(H21="ETAPA",SUMIFS($N$8:$N$1393,$B$8:$B$1393,B21,$C$8:$C$1393,C21,$H$8:$H$1393,"Serviço"),IF(H21="SUBETAPA",SUMIFS($N$8:$N$1393,$B$8:$B$1393,B21,$C$8:$C$1393,C21,$D$8:$D$1393,D21,$H$8:$H$1393,"Serviço"),0)))) -> 1971424.2 | R21: Adicionado/alterado em reivsao
A22: =IF($H22="UNIDADE CONSTRUTIVA",OFFSET(A22,-1,0)+1,LARGE(A$3:A21,1)) -> 0 | B22: =IF(H22="UNIDADE CONSTRUTIVA",0,IF(H22="CÉLULA CONSTRUTIVA",OFFSET(B22,-1,0)+1,OFFSET(B22,-1,0))) -> 2 | C22: =IF(H22="CÉLULA CONSTRUTIVA",0,IF(H22="ETAPA",OFFSET(C22,-1,0)+1,OFFSET(C22,-1,0))) -> 1 | D22: =IF(H22="ETAPA",0,IF(H22="SUBETAPA",OFFSET(D22,-1,0)+1,OFFSET(D22,-1,0))) -> 0 | E22: =IF(H22="Subetapa",0,IF(H22="serviço",OFFSET(E22,-1,0)+1,OFFSET(E22,-1,0))) -> 2 | H22: ETAPA | I22: =IF(H22="Unidade Construtiva",TEXT(A22,"00"),IF(H22="Célula Construtiva",TEXT(B22,"00"),IF(H22="Etapa",CONCATENATE(TEXT(B22,"00"),".",TEXT(C22,"000")),IF(H22="Subetapa",CONCATENATE(TEXT(B22,"00"),".",TEXT(C22,"000"),".",TEXT(D22,"000")),IF(H22="Serviço",CONCATENATE(TEXT(B22,"00"),".",TEXT(C22,"000"),".",TEXT(D22,"000"),".",TEXT(E22,"000")),""))))) -> 02.001 | J22: FUNDAÇÃO PROFUNDA | N22: =IF(H22="Serviço",M22*L22,IF(H22="CÉLULA CONSTRUTIVA",SUMIFS($N$8:$N$1393,$B$8:$B$1393,B22,$H$8:$H$1393,"Serviço"),IF(H22="ETAPA",SUMIFS($N$8:$N$1393,$B$8:$B$1393,B22,$C$8:$C$1393,C22,$H$8:$H$1393,"Serviço"),IF(H22="SUBETAPA",SUMIFS($N$8:$N$1393,$B$8:$B$1393,B22,$C$8:$C$1393,C22,$D$8:$D$1393,D22,$H$8:$H$1393,"Serviço"),0)))) -> 1184530.9
A23: =IF($H23="UNIDADE CONSTRUTIVA",OFFSET(A23,-1,0)+1,LARGE(A$3:A22,1)) -> 0 | B23: =IF(H23="UNIDADE CONSTRUTIVA",0,IF(H23="CÉLULA CONSTRUTIVA",OFFSET(B23,-1,0)+1,OFFSET(B23,-1,0))) -> 2 | C23: =IF(H23="CÉLULA CONSTRUTIVA",0,IF(H23="ETAPA",OFFSET(C23,-1,0)+1,OFFSET(C23,-1,0))) -> 1 | D23: =IF(H23="ETAPA",0,IF(H23="SUBETAPA",OFFSET(D23,-1,0)+1,OFFSET(D23,-1,0))) -> 1 | E23: =IF(H23="Subetapa",0,IF(H23="serviço",OFFSET(E23,-1,0)+1,OFFSET(E23,-1,0))) -> 0 | H23: SUBETAPA | I23: =IF(H23="Unidade Construtiva",TEXT(A23,"00"),IF(H23="Célula Construtiva",TEXT(B23,"00"),IF(H23="Etapa",CONCATENATE(TEXT(B23,"00"),".",TEXT(C23,"000")),IF(H23="Subetapa",CONCATENATE(TEXT(B23,"00"),".",TEXT(C23,"000"),".",TEXT(D23,"000")),IF(H23="Serviço",CONCATENATE(TEXT(B23,"00"),".",TEXT(C23,"000"),".",TEXT(D23,"000"),".",TEXT(E23,"000")),""))))) -> 02.001.001 | J23: Perfuração | N23: =IF(H23="Serviço",M23*L23,IF(H23="CÉLULA CONSTRUTIVA",SUMIFS($N$8:$N$1393,$B$8:$B$1393,B23,$H$8:$H$1393,"Serviço"),IF(H23="ETAPA",SUMIFS($N$8:$N$1393,$B$8:$B$1393,B23,$C$8:$C$1393,C23,$H$8:$H$1393,"Serviço"),IF(H23="SUBETAPA",SUMIFS($N$8:$N$1393,$B$8:$B$1393,B23,$C$8:$C$1393,C23,$D$8:$D$1393,D23,$H$8:$H$1393,"Serviço"),0)))) -> 486380.6
A24: =IF($H24="UNIDADE CONSTRUTIVA",OFFSET(A24,-1,0)+1,LARGE(A$3:A23,1)) -> 0 | B24: =IF(H24="UNIDADE CONSTRUTIVA",0,IF(H24="CÉLULA CONSTRUTIVA",OFFSET(B24,-1,0)+1,OFFSET(B24,-1,0))) -> 2 | C24: =IF(H24="CÉLULA CONSTRUTIVA",0,IF(H24="ETAPA",OFFSET(C24,-1,0)+1,OFFSET(C24,-1,0))) -> 1 | D24: =IF(H24="ETAPA",0,IF(H24="SUBETAPA",OFFSET(D24,-1,0)+1,OFFSET(D24,-1,0))) -> 1 | E24: =IF(H24="Subetapa",0,IF(H24="serviço",OFFSET(E24,-1,0)+1,OFFSET(E24,-1,0))) -> 1 | H24: SERVIÇO | I24: =IF(H24="Unidade Construtiva",TEXT(A24,"00"),IF(H24="Célula Construtiva",TEXT(B24,"00"),IF(H24="Etapa",CONCATENATE(TEXT(B24,"00"),".",TEXT(C24,"000")),IF(H24="Subetapa",CONCATENATE(TEXT(B24,"00"),".",TEXT(C24,"000"),".",TEXT(D24,"000")),IF(H24="Serviço",CONCATENATE(TEXT(B24,"00"),".",TEXT(C24,"000"),".",TEXT(D24,"000"),".",TEXT(E24,"000")),""))))) -> 02.001.001.001 | J24: Perfuração de estaca hélice contínua Ø 40cm | K24: m | L24: =Estacas!H15 -> 184 | M24: 68.4 | N24: =IF(H24="Serviço",M24*L24,IF(H24="CÉLULA CONSTRUTIVA",SUMIFS($N$8:$N$1393,$B$8:$B$1393,B24,$H$8:$H$1393,"Serviço"),IF(H24="ETAPA",SUMIFS($N$8:$N$1393,$B$8:$B$1393,B24,$C$8:$C$1393,C24,$H$8:$H$1393,"Serviço"),IF(H24="SUBETAPA",SUMIFS($N$8:$N$1393,$B$8:$B$1393,B24,$C$8:$C$1393,C24,$D$8:$D$1393,D24,$H$8:$H$1393,"Serviço"),0)))) -> 12585.6 | P24: Finalizado
A25: =IF($H25="UNIDADE CONSTRUTIVA",OFFSET(A25,-1,0)+1,LARGE(A$3:A24,1)) -> 0 | B25: =IF(H25="UNIDADE CONSTRUTIVA",0,IF(H25="CÉLULA CONSTRUTIVA",OFFSET(B25,-1,0)+1,OFFSET(B25,-1,0))) -> 2 | C25: =IF(H25="CÉLULA CONSTRUTIVA",0,IF(H25="ETAPA",OFFSET(C25,-1,0)+1,OFFSET(C25,-1,0))) -> 1 | D25: =IF(H25="ETAPA",0,IF(H25="SUBETAPA",OFFSET(D25,-1,0)+1,OFFSET(D25,-1,0))) -> 1 | E25: =IF(H25="Subetapa",0,IF(H25="serviço",OFFSET(E25,-1,0)+1,OFFSET(E25,-1,0))) -> 2 | H25: SERVIÇO | I25: =IF(H25="Unidade Construtiva",TEXT(A25,"00"),IF(H25="Célula Construtiva",TEXT(B25,"00"),IF(H25="Etapa",CONCATENATE(TEXT(B25,"00"),".",TEXT(C25,"000")),IF(H25="Subetapa",CONCATENATE(TEXT(B25,"00"),".",TEXT(C25,"000"),".",TEXT(D25,"000")),IF(H25="Serviço",CONCATENATE(TEXT(B25,"00"),".",TEXT(C25,"000"),".",TEXT(D25,"000"),".",TEXT(E25,"000")),""))))) -> 02.001.001.002 | J25: Perfuração de estaca hélice contínua Ø 50cm | K25: m | L25: =Estacas!H16 -> 368 | M25: 75 | N25: =IF(H25="Serviço",M25*L25,IF(H25="CÉLULA CONSTRUTIVA",SUMIFS($N$8:$N$1393,$B$8:$B$1393,B25,$H$8:$H$1393,"Serviço"),IF(H25="ETAPA",SUMIFS($N$8:$N$1393,$B$8:$B$1393,B25,$C$8:$C$1393,C25,$H$8:$H$1393,"Serviço"),IF(H25="SUBETAPA",SUMIFS($N$8:$N$1393,$B$8:$B$1393,B25,$C$8:$C$1393,C25,$D$8:$D$1393,D25,$H$8:$H$1393,"Serviço"),0)))) -> 27600 | P25: Finalizado
A26: =IF($H26="UNIDADE CONSTRUTIVA",OFFSET(A26,-1,0)+1,LARGE(A$3:A25,1)) -> 0 | B26: =IF(H26="UNIDADE CONSTRUTIVA",0,IF(H26="CÉLULA CONSTRUTIVA",OFFSET(B26,-1,0)+1,OFFSET(B26,-1,0))) -> 2 | C26: =IF(H26="CÉLULA CONSTRUTIVA",0,IF(H26="ETAPA",OFFSET(C26,-1,0)+1,OFFSET(C26,-1,0))) -> 1 | D26: =IF(H26="ETAPA",0,IF(H26="SUBETAPA",OFFSET(D26,-1,0)+1,OFFSET(D26,-1,0))) -> 1 | E26: =IF(H26="Subetapa",0,IF(H26="serviço",OFFSET(E26,-1,0)+1,OFFSET(E26,-1,0))) -> 3 | H26: SERVIÇO | I26: =IF(H26="Unidade Construtiva",TEXT(A26,"00"),IF(H26="Célula Construtiva",TEXT(B26,"00"),IF(H26="Etapa",CONCATENATE(TEXT(B26,"00"),".",TEXT(C26,"000")),IF(H26="Subetapa",CONCATENATE(TEXT(B26,"00"),".",TEXT(C26,"000"),".",TEXT(D26,"000")),IF(H26="Serviço",CONCATENATE(TEXT(B26,"00"),".",TEXT(C26,"000"),".",TEXT(D26,"000"),".",TEXT(E26,"000")),""))))) -> 02.001.001.003 | J26: Perfuração de estaca hélice contínua Ø 60cm | K26: m | L26: =Estacas!H17 -> 759 | M26: 155 | N26: =IF(H26="Serviço",M26*L26,IF(H26="CÉLULA CONSTRUTIVA",SUMIFS($N$8:$N$1393,$B$8:$B$1393,B26,$H$8:$H$1393,"Serviço"),IF(H26="ETAPA",SUMIFS($N$8:$N$1393,$B$8:$B$1393,B26,$C$8:$C$1393,C26,$H$8:$H$1393,"Serviço"),IF(H26="SUBETAPA",SUMIFS($N$8:$N$1393,$B$8:$B$1393,B26,$C$8:$C$1393,C26,$D$8:$D$1393,D26,$H$8:$H$1393,"Serviço"),0)))) -> 117645 | P26: Finalizado
A27: =IF($H27="UNIDADE CONSTRUTIVA",OFFSET(A27,-1,0)+1,LARGE(A$3:A26,1)) -> 0 | B27: =IF(H27="UNIDADE CONSTRUTIVA",0,IF(H27="CÉLULA CONSTRUTIVA",OFFSET(B27,-1,0)+1,OFFSET(B27,-1,0))) -> 2 | C27: =IF(H27="CÉLULA CONSTRUTIVA",0,IF(H27="ETAPA",OFFSET(C27,-1,0)+1,OFFSET(C27,-1,0))) -> 1 | D27: =IF(H27="ETAPA",0,IF(H27="SUBETAPA",OFFSET(D27,-1,0)+1,OFFSET(D27,-1,0))) -> 1 | E27: =IF(H27="Subetapa",0,IF(H27="serviço",OFFSET(E27,-1,0)+1,OFFSET(E27,-1,0))) -> 4 | H27: SERVIÇO | I27: =IF(H27="Unidade Construtiva",TEXT(A27,"00"),IF(H27="Célula Construtiva",TEXT(B27,"00"),IF(H27="Etapa",CONCATENATE(TEXT(B27,"00"),".",TEXT(C27,"000")),IF(H27="Subetapa",CONCATENATE(TEXT(B27,"00"),".",TEXT(C27,"000"),".",TEXT(D27,"000")),IF(H27="Serviço",CONCATENATE(TEXT(B27,"00"),".",TEXT(C27,"000"),".",TEXT(D27,"000"),".",TEXT(E27,"000")),""))))) -> 02.001.001.004 | J27: Perfuração de estaca hélice contínua Ø 70cm | K27: m | L27: =Estacas!H18 -> 1518 | M27: 175 | N27: =IF(H27="Serviço",M27*L27,IF(H27="CÉLULA CONSTRUTIVA",SUMIFS($N$8:$N$1393,$B$8:$B$1393,B27,$H$8:$H$1393,"Serviço"),IF(H27="ETAPA",SUMIFS($N$8:$N$1393,$B$8:$B$1393,B27,$C$8:$C$1393,C27,$H$8:$H$1393,"Serviço"),IF(H27="SUBETAPA",SUMIFS($N$8:$N$1393,$B$8:$B$1393,B27,$C$8:$C$1393,C27,$D$8:$D$1393,D27,$H$8:$H$1393,"Serviço"),0)))) -> 265650 | P27: Finalizado
A28: =IF($H28="UNIDADE CONSTRUTIVA",OFFSET(A28,-1,0)+1,LARGE(A$3:A27,1)) -> 0 | B28: =IF(H28="UNIDADE CONSTRUTIVA",0,IF(H28="CÉLULA CONSTRUTIVA",OFFSET(B28,-1,0)+1,OFFSET(B28,-1,0))) -> 2 | C28: =IF(H28="CÉLULA CONSTRUTIVA",0,IF(H28="ETAPA",OFFSET(C28,-1,0)+1,OFFSET(C28,-1,0))) -> 1 | D28: =IF(H28="ETAPA",0,IF(H28="SUBETAPA",OFFSET(D28,-1,0)+1,OFFSET(D28,-1,0))) -> 1 | E28: =IF(H28="Subetapa",0,IF(H28="serviço",OFFSET(E28,-1,0)+1,OFFSET(E28,-1,0))) -> 5 | H28: SERVIÇO | I28: =IF(H28="Unidade Construtiva",TEXT(A28,"00"),IF(H28="Célula Construtiva",TEXT(B28,"00"),IF(H28="Etapa",CONCATENATE(TEXT(B28,"00"),".",TEXT(C28,"000")),IF(H28="Subetapa",CONCATENATE(TEXT(B28,"00"),".",TEXT(C28,"000"),".",TEXT(D28,"000")),IF(H28="Serviço",CONCATENATE(TEXT(B28,"00"),".",TEXT(C28,"000"),".",TEXT(D28,"000"),".",TEXT(E28,"000")),""))))) -> 02.001.001.005 | J28: Mobilização e desmobilização de equipamentos - Para execução de estaca hélice | K28: vb | L28: 1 | M28: 26000 | N28: =IF(H28="Serviço",M28*L28,IF(H28="CÉLULA CONSTRUTIVA",SUMIFS($N$8:$N$1393,$B$8:$B$1393,B28,$H$8:$H$1393,"Serviço"),IF(H28="ETAPA",SUMIFS($N$8:$N$1393,$B$8:$B$1393,B28,$C$8:$C$1393,C28,$H$8:$H$1393,"Serviço"),IF(H28="SUBETAPA",SUMIFS($N$8:$N$1393,$B$8:$B$1393,B28,$C$8:$C$1393,C28,$D$8:$D$1393,D28,$H$8:$H$1393,"Serviço"),0)))) -> 26000 | P28: Finalizado
A29: =IF($H29="UNIDADE CONSTRUTIVA",OFFSET(A29,-1,0)+1,LARGE(A$3:A28,1)) -> 0 | B29: =IF(H29="UNIDADE CONSTRUTIVA",0,IF(H29="CÉLULA CONSTRUTIVA",OFFSET(B29,-1,0)+1,OFFSET(B29,-1,0))) -> 2 | C29: =IF(H29="CÉLULA CONSTRUTIVA",0,IF(H29="ETAPA",OFFSET(C29,-1,0)+1,OFFSET(C29,-1,0))) -> 1 | D29: =IF(H29="ETAPA",0,IF(H29="SUBETAPA",OFFSET(D29,-1,0)+1,OFFSET(D29,-1,0))) -> 1 | E29: =IF(H29="Subetapa",0,IF(H29="serviço",OFFSET(E29,-1,0)+1,OFFSET(E29,-1,0))) -> 6 | H29: SERVIÇO | I29: =IF(H29="Unidade Construtiva",TEXT(A29,"00"),IF(H29="Célula Construtiva",TEXT(B29,"00"),IF(H29="Etapa",CONCATENATE(TEXT(B29,"00"),".",TEXT(C29,"000")),IF(H29="Subetapa",CONCATENATE(TEXT(B29,"00"),".",TEXT(C29,"000"),".",TEXT(D29,"000")),IF(H29="Serviço",CONCATENATE(TEXT(B29,"00"),".",TEXT(C29,"000"),".",TEXT(D29,"000"),".",TEXT(E29,"000")),""))))) -> 02.001.001.006 | J29: Corte e Preparo de Cabeça de Estaca | K29: un | L29: =Estacas!C13 -> 123 | M29: 300 | N29: =IF(H29="Serviço",M29*L29,IF(H29="CÉLULA CONSTRUTIVA",SUMIFS($N$8:$N$1393,$B$8:$B$1393,B29,$H$8:$H$1393,"Serviço"),IF(H29="ETAPA",SUMIFS($N$8:$N$1393,$B$8:$B$1393,B29,$C$8:$C$1393,C29,$H$8:$H$1393,"Serviço"),IF(H29="SUBETAPA",SUMIFS($N$8:$N$1393,$B$8:$B$1393,B29,$C$8:$C$1393,C29,$D$8:$D$1393,D29,$H$8:$H$1393,"Serviço"),0)))) -> 36900 | P29: Finalizado
A30: =IF($H30="UNIDADE CONSTRUTIVA",OFFSET(A30,-1,0)+1,LARGE(A$3:A29,1)) -> 0 | B30: =IF(H30="UNIDADE CONSTRUTIVA",0,IF(H30="CÉLULA CONSTRUTIVA",OFFSET(B30,-1,0)+1,OFFSET(B30,-1,0))) -> 2 | C30: =IF(H30="CÉLULA CONSTRUTIVA",0,IF(H30="ETAPA",OFFSET(C30,-1,0)+1,OFFSET(C30,-1,0))) -> 1 | D30: =IF(H30="ETAPA",0,IF(H30="SUBETAPA",OFFSET(D30,-1,0)+1,OFFSET(D30,-1,0))) -> 2 | E30: =IF(H30="Subetapa",0,IF(H30="serviço",OFFSET(E30,-1,0)+1,OFFSET(E30,-1,0))) -> 0 | H30: SUBETAPA | I30: =IF(H30="Unidade Construtiva",TEXT(A30,"00"),IF(H30="Célula Construtiva",TEXT(B30,"00"),IF(H30="Etapa",CONCATENATE(TEXT(B30,"00"),".",TEXT(C30,"000")),IF(H30="Subetapa",CONCATENATE(TEXT(B30,"00"),".",TEXT(C30,"000"),".",TEXT(D30,"000")),IF(H30="Serviço",CONCATENATE(TEXT(B30,"00"),".",TEXT(C30,"000"),".",TEXT(D30,"000"),".",TEXT(E30,"000")),""))))) -> 02.001.002 | J30: Armadura | N30: =IF(H30="Serviço",M30*L30,IF(H30="CÉLULA CONSTRUTIVA",SUMIFS($N$8:$N$1393,$B$8:$B$1393,B30,$H$8:$H$1393,"Serviço"),IF(H30="ETAPA",SUMIFS($N$8:$N$1393,$B$8:$B$1393,B30,$C$8:$C$1393,C30,$H$8:$H$1393,"Serviço"),IF(H30="SUBETAPA",SUMIFS($N$8:$N$1393,$B$8:$B$1393,B30,$C$8:$C$1393,C30,$D$8:$D$1393,D30,$H$8:$H$1393,"Serviço"),0)))) -> 93687.421
A31: =IF($H31="UNIDADE CONSTRUTIVA",OFFSET(A31,-1,0)+1,LARGE(A$3:A30,1)) -> 0 | B31: =IF(H31="UNIDADE CONSTRUTIVA",0,IF(H31="CÉLULA CONSTRUTIVA",OFFSET(B31,-1,0)+1,OFFSET(B31,-1,0))) -> 2 | C31: =IF(H31="CÉLULA CONSTRUTIVA",0,IF(H31="ETAPA",OFFSET(C31,-1,0)+1,OFFSET(C31,-1,0))) -> 1 | D31: =IF(H31="ETAPA",0,IF(H31="SUBETAPA",OFFSET(D31,-1,0)+1,OFFSET(D31,-1,0))) -> 2 | E31: =IF(H31="Subetapa",0,IF(H31="serviço",OFFSET(E31,-1,0)+1,OFFSET(E31,-1,0))) -> 1 | H31: SERVIÇO | I31: =IF(H31="Unidade Construtiva",TEXT(A31,"00"),IF(H31="Célula Construtiva",TEXT(B31,"00"),IF(H31="Etapa",CONCATENATE(TEXT(B31,"00"),".",TEXT(C31,"000")),IF(H31="Subetapa",CONCATENATE(TEXT(B31,"00"),".",TEXT(C31,"000"),".",TEXT(D31,"000")),IF(H31="Serviço",CONCATENATE(TEXT(B31,"00"),".",TEXT(C31,"000"),".",TEXT(D31,"000"),".",TEXT(E31,"000")),""))))) -> 02.001.002.001 | J31: Armação aço CA-50 ø 6,3mm para estaca (corte e dobra em obra) | K31: kg | L31: =Estacas!M13 -> 2654.6364 | M31: 7.1071 | N31: =IF(H31="Serviço",M31*L31,IF(H31="CÉLULA CONSTRUTIVA",SUMIFS($N$8:$N$1393,$B$8:$B$1393,B31,$H$8:$H$1393,"Serviço"),IF(H31="ETAPA",SUMIFS($N$8:$N$1393,$B$8:$B$1393,B31,$C$8:$C$1393,C31,$H$8:$H$1393,"Serviço"),IF(H31="SUBETAPA",SUMIFS($N$8:$N$1393,$B$8:$B$1393,B31,$C$8:$C$1393,C31,$D$8:$D$1393,D31,$H$8:$H$1393,"Serviço"),0)))) -> 18866.766 | P31: Finalizado
A32: =IF($H32="UNIDADE CONSTRUTIVA",OFFSET(A32,-1,0)+1,LARGE(A$3:A31,1)) -> 0 | B32: =IF(H32="UNIDADE CONSTRUTIVA",0,IF(H32="CÉLULA CONSTRUTIVA",OFFSET(B32,-1,0)+1,OFFSET(B32,-1,0))) -> 2 | C32: =IF(H32="CÉLULA CONSTRUTIVA",0,IF(H32="ETAPA",OFFSET(C32,-1,0)+1,OFFSET(C32,-1,0))) -> 1 | D32: =IF(H32="ETAPA",0,IF(H32="SUBETAPA",OFFSET(D32,-1,0)+1,OFFSET(D32,-1,0))) -> 2 | E32: =IF(H32="Subetapa",0,IF(H32="serviço",OFFSET(E32,-1,0)+1,OFFSET(E32,-1,0))) -> 2 | H32: SERVIÇO | I32: =IF(H32="Unidade Construtiva",TEXT(A32,"00"),IF(H32="Célula Construtiva",TEXT(B32,"00"),IF(H32="Etapa",CONCATENATE(TEXT(B32,"00"),".",TEXT(C32,"000")),IF(H32="Subetapa",CONCATENATE(TEXT(B32,"00"),".",TEXT(C32,"000"),".",TEXT(D32,"000")),IF(H32="Serviço",CONCATENATE(TEXT(B32,"00"),".",TEXT(C32,"000"),".",TEXT(D32,"000"),".",TEXT(E32,"000")),""))))) -> 02.001.002.002 | J32: Armação aço CA-50 ø 12,5mm para estaca (corte e dobra em obra) | K32: kg | L32: =Estacas!N13 -> 1171 | M32: 6.6523 | N32: =IF(H32="Serviço",M32*L32,IF(H32="CÉLULA CONSTRUTIVA",SUMIFS($N$8:$N$1393,$B$8:$B$1393,B32,$H$8:$H$1393,"Serviço"),IF(H32="ETAPA",SUMIFS($N$8:$N$1393,$B$8:$B$1393,B32,$C$8:$C$1393,C32,$H$8:$H$1393,"Serviço"),IF(H32="SUBETAPA",SUMIFS($N$8:$N$1393,$B$8:$B$1393,B32,$C$8:$C$1393,C32,$D$8:$D$1393,D32,$H$8:$H$1393,"Serviço"),0)))) -> 7789.8433 | P32: Finalizado
A33: =IF($H33="UNIDADE CONSTRUTIVA",OFFSET(A33,-1,0)+1,LARGE(A$3:A32,1)) -> 0 | B33: =IF(H33="UNIDADE CONSTRUTIVA",0,IF(H33="CÉLULA CONSTRUTIVA",OFFSET(B33,-1,0)+1,OFFSET(B33,-1,0))) -> 2 | C33: =IF(H33="CÉLULA CONSTRUTIVA",0,IF(H33="ETAPA",OFFSET(C33,-1,0)+1,OFFSET(C33,-1,0))) -> 1 | D33: =IF(H33="ETAPA",0,IF(H33="SUBETAPA",OFFSET(D33,-1,0)+1,OFFSET(D33,-1,0))) -> 2 | E33: =IF(H33="Subetapa",0,IF(H33="serviço",OFFSET(E33,-1,0)+1,OFFSET(E33,-1,0))) -> 3 | H33: SERVIÇO | I33: =IF(H33="Unidade Construtiva",TEXT(A33,"00"),IF(H33="Célula Construtiva",TEXT(B33,"00"),IF(H33="Etapa",CONCATENATE(TEXT(B33,"00"),".",TEXT(C33,"000")),IF(H33="Subetapa",CONCATENATE(TEXT(B33,"00"),".",TEXT(C33,"000"),".",TEXT(D33,"000")),IF(H33="Serviço",CONCATENATE(TEXT(B33,"00"),".",TEXT(C33,"000"),".",TEXT(D33,"000"),".",TEXT(E33,"000")),""))))) -> 02.001.002.003 | J33: Armação aço CA-50 ø 16mm para estaca (corte e dobra em obra) | K33: kg | L33: =Estacas!O13 -> 10414.818 | M33: 6.4361 | N33: =IF(H33="Serviço",M33*L33,IF(H33="CÉLULA CONSTRUTIVA",SUMIFS($N$8:$N$1393,$B$8:$B$1393,B33,$H$8:$H$1393,"Serviço"),IF(H33="ETAPA",SUMIFS($N$8:$N$1393,$B$8:$B$1393,B33,$C$8:$C$1393,C33,$H$8:$H$1393,"Serviço"),IF(H33="SUBETAPA",SUMIFS($N$8:$N$1393,$B$8:$B$1393,B33,$C$8:$C$1393,C33,$D$8:$D$1393,D33,$H$8:$H$1393,"Serviço"),0)))) -> 67030.811 | P33: Finalizado
A34: =IF($H34="UNIDADE CONSTRUTIVA",OFFSET(A34,-1,0)+1,LARGE(A$3:A33,1)) -> 0 | B34: =IF(H34="UNIDADE CONSTRUTIVA",0,IF(H34="CÉLULA CONSTRUTIVA",OFFSET(B34,-1,0)+1,OFFSET(B34,-1,0))) -> 2 | C34: =IF(H34="CÉLULA CONSTRUTIVA",0,IF(H34="ETAPA",OFFSET(C34,-1,0)+1,OFFSET(C34,-1,0))) -> 1 | D34: =IF(H34="ETAPA",0,IF(H34="SUBETAPA",OFFSET(D34,-1,0)+1,OFFSET(D34,-1,0))) -> 3 | E34: =IF(H34="Subetapa",0,IF(H34="serviço",OFFSET(E34,-1,0)+1,OFFSET(E34,-1,0))) -> 0 | H34: SUBETAPA | I34: =IF(H34="Unidade Construtiva",TEXT(A34,"00"),IF(H34="Célula Construtiva",TEXT(B34,"00"),IF(H34="Etapa",CONCATENATE(TEXT(B34,"00"),".",TEXT(C34,"000")),IF(H34="Subetapa",CONCATENATE(TEXT(B34,"00"),".",TEXT(C34,"000"),".",TEXT(D34,"000")),IF(H34="Serviço",CONCATENATE(TEXT(B34,"00"),".",TEXT(C34,"000"),".",TEXT(D34,"000"),".",TEXT(E34,"000")),""))))) -> 02.001.003 | J34: Lançamento de Concreto para Estacas (Edifícios) | N34: =IF(H34="Serviço",M34*L34,IF(H34="CÉLULA CONSTRUTIVA",SUMIFS($N$8:$N$1393,$B$8:$B$1393,B34,$H$8:$H$1393,"Serviço"),IF(H34="ETAPA",SUMIFS($N$8:$N$1393,$B$8:$B$1393,B34,$C$8:$C$1393,C34,$H$8:$H$1393,"Serviço"),IF(H34="SUBETAPA",SUMIFS($N$8:$N$1393,$B$8:$B$1393,B34,$C$8:$C$1393,C34,$D$8:$D$1393,D34,$H$8:$H$1393,"Serviço"),0)))) -> 604462.85
A35: =IF($H35="UNIDADE CONSTRUTIVA",OFFSET(A35,-1,0)+1,LARGE(A$3:A34,1)) -> 0 | B35: =IF(H35="UNIDADE CONSTRUTIVA",0,IF(H35="CÉLULA CONSTRUTIVA",OFFSET(B35,-1,0)+1,OFFSET(B35,-1,0))) -> 2 | C35: =IF(H35="CÉLULA CONSTRUTIVA",0,IF(H35="ETAPA",OFFSET(C35,-1,0)+1,OFFSET(C35,-1,0))) -> 1 | D35: =IF(H35="ETAPA",0,IF(H35="SUBETAPA",OFFSET(D35,-1,0)+1,OFFSET(D35,-1,0))) -> 3 | E35: =IF(H35="Subetapa",0,IF(H35="serviço",OFFSET(E35,-1,0)+1,OFFSET(E35,-1,0))) -> 1 | H35: SERVIÇO | I35: =IF(H35="Unidade Construtiva",TEXT(A35,"00"),IF(H35="Célula Construtiva",TEXT(B35,"00"),IF(H35="Etapa",CONCATENATE(TEXT(B35,"00"),".",TEXT(C35,"000")),IF(H35="Subetapa",CONCATENATE(TEXT(B35,"00"),".",TEXT(C35,"000"),".",TEXT(D35,"000")),IF(H35="Serviço",CONCATENATE(TEXT(B35,"00"),".",TEXT(C35,"000"),".",TEXT(D35,"000"),".",TEXT(E35,"000")),""))))) -> 02.001.003.001 | J35: Concreto Usinado bombeável para estacas 40MPa - incluindo serviço de bombeamento | K35: m3 | L35: =Estacas!K18 -> 894.17581 | M35: 676 | N35: =IF(H35="Serviço",M35*L35,IF(H35="CÉLULA CONSTRUTIVA",SUMIFS($N$8:$N$1393,$B$8:$B$1393,B35,$H$8:$H$1393,"Serviço"),IF(H35="ETAPA",SUMIFS($N$8:$N$1393,$B$8:$B$1393,B35,$C$8:$C$1393,C35,$H$8:$H$1393,"Serviço"),IF(H35="SUBETAPA",SUMIFS($N$8:$N$1393,$B$8:$B$1393,B35,$C$8:$C$1393,C35,$D$8:$D$1393,D35,$H$8:$H$1393,"Serviço"),0)))) -> 604462.85 | O35: Qunatitativo do projetista retirado perda de 10% (perda de 30% adicionada na composição de custo) | P35: Finalizado
A36: =IF($H36="UNIDADE CONSTRUTIVA",OFFSET(A36,-1,0)+1,LARGE(A$3:A35,1)) -> 0 | B36: =IF(H36="UNIDADE CONSTRUTIVA",0,IF(H36="CÉLULA CONSTRUTIVA",OFFSET(B36,-1,0)+1,OFFSET(B36,-1,0))) -> 2 | C36: =IF(H36="CÉLULA CONSTRUTIVA",0,IF(H36="ETAPA",OFFSET(C36,-1,0)+1,OFFSET(C36,-1,0))) -> 2 | D36: =IF(H36="ETAPA",0,IF(H36="SUBETAPA",OFFSET(D36,-1,0)+1,OFFSET(D36,-1,0))) -> 0 | E36: =IF(H36="Subetapa",0,IF(H36="serviço",OFFSET(E36,-1,0)+1,OFFSET(E36,-1,0))) -> 1 | H36: ETAPA | I36: =IF(H36="Unidade Construtiva",TEXT(A36,"00"),IF(H36="Célula Construtiva",TEXT(B36,"00"),IF(H36="Etapa",CONCATENATE(TEXT(B36,"00"),".",TEXT(C36,"000")),IF(H36="Subetapa",CONCATENATE(TEXT(B36,"00"),".",TEXT(C36,"000"),".",TEXT(D36,"000")),IF(H36="Serviço",CONCATENATE(TEXT(B36,"00"),".",TEXT(C36,"000"),".",TEXT(D36,"000"),".",TEXT(E36,"000")),""))))) -> 02.002 | J36: FUNDAÇÃO RASA | N36: =IF(H36="Serviço",M36*L36,IF(H36="CÉLULA CONSTRUTIVA",SUMIFS($N$8:$N$1393,$B$8:$B$1393,B36,$H$8:$H$1393,"Serviço"),IF(H36="ETAPA",SUMIFS($N$8:$N$1393,$B$8:$B$1393,B36,$C$8:$C$1393,C36,$H$8:$H$1393,"Serviço"),IF(H36="SUBETAPA",SUMIFS($N$8:$N$1393,$B$8:$B$1393,B36,$C$8:$C$1393,C36,$D$8:$D$1393,D36,$H$8:$H$1393,"Serviço"),0)))) -> 786893.32
A37: =IF($H37="UNIDADE CONSTRUTIVA",OFFSET(A37,-1,0)+1,LARGE(A$3:A36,1)) -> 0 | B37: =IF(H37="UNIDADE CONSTRUTIVA",0,IF(H37="CÉLULA CONSTRUTIVA",OFFSET(B37,-1,0)+1,OFFSET(B37,-1,0))) -> 2 | C37: =IF(H37="CÉLULA CONSTRUTIVA",0,IF(H37="ETAPA",OFFSET(C37,-1,0)+1,OFFSET(C37,-1,0))) -> 2 | D37: =IF(H37="ETAPA",0,IF(H37="SUBETAPA",OFFSET(D37,-1,0)+1,OFFSET(D37,-1,0))) -> 1 | E37: =IF(H37="Subetapa",0,IF(H37="serviço",OFFSET(E37,-1,0)+1,OFFSET(E37,-1,0))) -> 0 | H37: SUBETAPA | I37: =IF(H37="Unidade Construtiva",TEXT(A37,"00"),IF(H37="Célula Construtiva",TEXT(B37,"00"),IF(H37="Etapa",CONCATENATE(TEXT(B37,"00"),".",TEXT(C37,"000")),IF(H37="Subetapa",CONCATENATE(TEXT(B37,"00"),".",TEXT(C37,"000"),".",TEXT(D37,"000")),IF(H37="Serviço",CONCATENATE(TEXT(B37,"00"),".",TEXT(C37,"000"),".",TEXT(D37,"000"),".",TEXT(E37,"000")),""))))) -> 02.002.001 | J37: Forma | N37: =IF(H37="Serviço",M37*L37,IF(H37="CÉLULA CONSTRUTIVA",SUMIFS($N$8:$N$1393,$B$8:$B$1393,B37,$H$8:$H$1393,"Serviço"),IF(H37="ETAPA",SUMIFS($N$8:$N$1393,$B$8:$B$1393,B37,$C$8:$C$1393,C37,$H$8:$H$1393,"Serviço"),IF(H37="SUBETAPA",SUMIFS($N$8:$N$1393,$B$8:$B$1393,B37,$C$8:$C$1393,C37,$D$8:$D$1393,D37,$H$8:$H$1393,"Serviço"),0)))) -> 77154.329
A38: =IF($H38="UNIDADE CONSTRUTIVA",OFFSET(A38,-1,0)+1,LARGE(A$3:A37,1)) -> 0 | B38: =IF(H38="UNIDADE CONSTRUTIVA",0,IF(H38="CÉLULA CONSTRUTIVA",OFFSET(B38,-1,0)+1,OFFSET(B38,-1,0))) -> 2 | C38: =IF(H38="CÉLULA CONSTRUTIVA",0,IF(H38="ETAPA",OFFSET(C38,-1,0)+1,OFFSET(C38,-1,0))) -> 2 | D38: =IF(H38="ETAPA",0,IF(H38="SUBETAPA",OFFSET(D38,-1,0)+1,OFFSET(D38,-1,0))) -> 1 | E38: =IF(H38="Subetapa",0,IF(H38="serviço",OFFSET(E38,-1,0)+1,OFFSET(E38,-1,0))) -> 1 | H38: SERVIÇO | I38: =IF(H38="Unidade Construtiva",TEXT(A38,"00"),IF(H38="Célula Construtiva",TEXT(B38,"00"),IF(H38="Etapa",CONCATENATE(TEXT(B38,"00"),".",TEXT(C38,"000")),IF(H38="Subetapa",CONCATENATE(TEXT(B38,"00"),".",TEXT(C38,"000"),".",TEXT(D38,"000")),IF(H38="Serviço",CONCATENATE(TEXT(B38,"00"),".",TEXT(C38,"000"),".",TEXT(D38,"000"),".",TEXT(E38,"000")),""))))) -> 02.002.001.001 | J38: Forma para infraestrutura em Tábuas de Madeira Serrada - 4 X REAPROVEITAMENTO | K38: m2 | L38: =Aço_Infraestrutura!L29 -> 1381.81 | M38: 55.8357 | N38: =IF(H38="Serviço",M38*L38,IF(H38="CÉLULA CONSTRUTIVA",SUMIFS($N$8:$N$1393,$B$8:$B$1393,B38,$H$8:$H$1393,"Serviço"),IF(H38="ETAPA",SUMIFS($N$8:$N$1393,$B$8:$B$1393,B38,$C$8:$C$1393,C38,$H$8:$H$1393,"Serviço"),IF(H38="SUBETAPA",SUMIFS($N$8:$N$1393,$B$8:$B$1393,B38,$C$8:$C$1393,C38,$D$8:$D$1393,D38,$H$8:$H$1393,"Serviço"),0)))) -> 77154.329 | O38: Considerado blocos, vigas de fundação, duto, cisterna, lajes e pilares de arranque | P38: Finalizado
A39: =IF($H39="UNIDADE CONSTRUTIVA",OFFSET(A39,-1,0)+1,LARGE(A$3:A38,1)) -> 0 | B39: =IF(H39="UNIDADE CONSTRUTIVA",0,IF(H39="CÉLULA CONSTRUTIVA",OFFSET(B39,-1,0)+1,OFFSET(B39,-1,0))) -> 2 | C39: =IF(H39="CÉLULA CONSTRUTIVA",0,IF(H39="ETAPA",OFFSET(C39,-1,0)+1,OFFSET(C39,-1,0))) -> 2 | D39: =IF(H39="ETAPA",0,IF(H39="SUBETAPA",OFFSET(D39,-1,0)+1,OFFSET(D39,-1,0))) -> 2 | E39: =IF(H39="Subetapa",0,IF(H39="serviço",OFFSET(E39,-1,0)+1,OFFSET(E39,-1,0))) -> 0 | H39: SUBETAPA | I39: =IF(H39="Unidade Construtiva",TEXT(A39,"00"),IF(H39="Célula Construtiva",TEXT(B39,"00"),IF(H39="Etapa",CONCATENATE(TEXT(B39,"00"),".",TEXT(C39,"000")),IF(H39="Subetapa",CONCATENATE(TEXT(B39,"00"),".",TEXT(C39,"000"),".",TEXT(D39,"000")),IF(H39="Serviço",CONCATENATE(TEXT(B39,"00"),".",TEXT(C39,"000"),".",TEXT(D39,"000"),".",TEXT(E39,"000")),""))))) -> 02.002.002 | J39: Armadura | N39: =IF(H39="Serviço",M39*L39,IF(H39="CÉLULA CONSTRUTIVA",SUMIFS($N$8:$N$1393,$B$8:$B$1393,B39,$H$8:$H$1393,"Serviço"),IF(H39="ETAPA",SUMIFS($N$8:$N$1393,$B$8:$B$1393,B39,$C$8:$C$1393,C39,$H$8:$H$1393,"Serviço"),IF(H39="SUBETAPA",SUMIFS($N$8:$N$1393,$B$8:$B$1393,B39,$C$8:$C$1393,C39,$D$8:$D$1393,D39,$H$8:$H$1393,"Serviço"),0)))) -> 221730.83
A40: =IF($H40="UNIDADE CONSTRUTIVA",OFFSET(A40,-1,0)+1,LARGE(A$3:A39,1)) -> 0 | B40: =IF(H40="UNIDADE CONSTRUTIVA",0,IF(H40="CÉLULA CONSTRUTIVA",OFFSET(B40,-1,0)+1,OFFSET(B40,-1,0))) -> 2 | C40: =IF(H40="CÉLULA CONSTRUTIVA",0,IF(H40="ETAPA",OFFSET(C40,-1,0)+1,OFFSET(C40,-1,0))) -> 2 | D40: =IF(H40="ETAPA",0,IF(H40="SUBETAPA",OFFSET(D40,-1,0)+1,OFFSET(D40,-1,0))) -> 2 | E40: =IF(H40="Subetapa",0,IF(H40="serviço",OFFSET(E40,-1,0)+1,OFFSET(E40,-1,0))) -> 1 | H40: SERVIÇO | I40: =IF(H40="Unidade Construtiva",TEXT(A40,"00"),IF(H40="Célula Construtiva",TEXT(B40,"00"),IF(H40="Etapa",CONCATENATE(TEXT(B40,"00"),".",TEXT(C40,"000")),IF(H40="Subetapa",CONCATENATE(TEXT(B40,"00"),".",TEXT(C40,"000"),".",TEXT(D40,"000")),IF(H40="Serviço",CONCATENATE(TEXT(B40,"00"),".",TEXT(C40,"000"),".",TEXT(D40,"000"),".",TEXT(E40,"000")),""))))) -> 02.002.002.001 | J40: Armação aço CA-50 ø 6,3mm para infraestrutura (corte e dobra em obra) | K40: kg | L40: =Aço_Infraestrutura!D29 -> 3094.0728 | M40: 6.977 | N40: =IF(H40="Serviço",M40*L40,IF(H40="CÉLULA CONSTRUTIVA",SUMIFS($N$8:$N$1393,$B$8:$B$1393,B40,$H$8:$H$1393,"Serviço"),IF(H40="ETAPA",SUMIFS($N$8:$N$1393,$B$8:$B$1393,B40,$C$8:$C$1393,C40,$H$8:$H$1393,"Serviço"),IF(H40="SUBETAPA",SUMIFS($N$8:$N$1393,$B$8:$B$1393,B40,$C$8:$C$1393,C40,$D$8:$D$1393,D40,$H$8:$H$1393,"Serviço"),0)))) -> 21587.346 | O40: Considerado blocos, vigas de fundação, duto, cisterna, lajes e pilares de arranque - 10% de perda | P40: Finalizado
A41: =IF($H41="UNIDADE CONSTRUTIVA",OFFSET(A41,-1,0)+1,LARGE(A$3:A40,1)) -> 0 | B41: =IF(H41="UNIDADE CONSTRUTIVA",0,IF(H41="CÉLULA CONSTRUTIVA",OFFSET(B41,-1,0)+1,OFFSET(B41,-1,0))) -> 2 | C41: =IF(H41="CÉLULA CONSTRUTIVA",0,IF(H41="ETAPA",OFFSET(C41,-1,0)+1,OFFSET(C41,-1,0))) -> 2 | D41: =IF(H41="ETAPA",0,IF(H41="SUBETAPA",OFFSET(D41,-1,0)+1,OFFSET(D41,-1,0))) -> 2 | E41: =IF(H41="Subetapa",0,IF(H41="serviço",OFFSET(E41,-1,0)+1,OFFSET(E41,-1,0))) -> 2 | H41: SERVIÇO | I41: =IF(H41="Unidade Construtiva",TEXT(A41,"00"),IF(H41="Célula Construtiva",TEXT(B41,"00"),IF(H41="Etapa",CONCATENATE(TEXT(B41,"00"),".",TEXT(C41,"000")),IF(H41="Subetapa",CONCATENATE(TEXT(B41,"00"),".",TEXT(C41,"000"),".",TEXT(D41,"000")),IF(H41="Serviço",CONCATENATE(TEXT(B41,"00"),".",TEXT(C41,"000"),".",TEXT(D41,"000"),".",TEXT(E41,"000")),""))))) -> 02.002.002.002 | J41: Armação aço CA-50 ø 8,0mm para infraestrutura (corte e dobra em obra) | K41: kg | L41: =Aço_Infraestrutura!E29 -> 2423.2132 | M41: 6.7137 | N41: =IF(H41="Serviço",M41*L41,IF(H41="CÉLULA CONSTRUTIVA",SUMIFS($N$8:$N$1393,$B$8:$B$1393,B41,$H$8:$H$1393,"Serviço"),IF(H41="ETAPA",SUMIFS($N$8:$N$1393,$B$8:$B$1393,B41,$C$8:$C$1393,C41,$H$8:$H$1393,"Serviço"),IF(H41="SUBETAPA",SUMIFS($N$8:$N$1393,$B$8:$B$1393,B41,$C$8:$C$1393,C41,$D$8:$D$1393,D41,$H$8:$H$1393,"Serviço"),0)))) -> 16268.727 | O41: Considerado blocos, vigas de fundação, duto, cisterna, lajes e pilares de arranque - 10% de perda | P41: Finalizado
A42: =IF($H42="UNIDADE CONSTRUTIVA",OFFSET(A42,-1,0)+1,LARGE(A$3:A41,1)) -> 0 | B42: =IF(H42="UNIDADE CONSTRUTIVA",0,IF(H42="CÉLULA CONSTRUTIVA",OFFSET(B42,-1,0)+1,OFFSET(B42,-1,0))) -> 2 | C42: =IF(H42="CÉLULA CONSTRUTIVA",0,IF(H42="ETAPA",OFFSET(C42,-1,0)+1,OFFSET(C42,-1,0))) -> 2 | D42: =IF(H42="ETAPA",0,IF(H42="SUBETAPA",OFFSET(D42,-1,0)+1,OFFSET(D42,-1,0))) -> 2 | E42: =IF(H42="Subetapa",0,IF(H42="serviço",OFFSET(E42,-1,0)+1,OFFSET(E42,-1,0))) -> 3 | H42: SERVIÇO | I42: =IF(H42="Unidade Construtiva",TEXT(A42,"00"),IF(H42="Célula Construtiva",TEXT(B42,"00"),IF(H42="Etapa",CONCATENATE(TEXT(B42,"00"),".",TEXT(C42,"000")),IF(H42="Subetapa",CONCATENATE(TEXT(B42,"00"),".",TEXT(C42,"000"),".",TEXT(D42,"000")),IF(H42="Serviço",CONCATENATE(TEXT(B42,"00"),".",TEXT(C42,"000"),".",TEXT(D42,"000"),".",TEXT(E42,"000")),""))))) -> 02.002.002.003 | J42: Armação aço CA-50 ø 10,0mm para infraestrutura (corte e dobra em obra) | K42: kg | L42: =Aço_Infraestrutura!F29 -> 2659.633 | M42: 6.1637 | N42: =IF(H42="Serviço",M42*L42,IF(H42="CÉLULA CONSTRUTIVA",SUMIFS($N$8:$N$1393,$B$8:$B$1393,B42,$H$8:$H$1393,"Serviço"),IF(H42="ETAPA",SUMIFS($N$8:$N$1393,$B$8:$B$1393,B42,$C$8:$C$1393,C42,$H$8:$H$1393,"Serviço"),IF(H42="SUBETAPA",SUMIFS($N$8:$N$1393,$B$8:$B$1393,B42,$C$8:$C$1393,C42,$D$8:$D$1393,D42,$H$8:$H$1393,"Serviço"),0)))) -> 16393.18 | O42: Considerado blocos, vigas de fundação, duto, cisterna, lajes e pilares de arranque - 10% de perda | P42: Finalizado
A43: =IF($H43="UNIDADE CONSTRUTIVA",OFFSET(A43,-1,0)+1,LARGE(A$3:A42,1)) -> 0 | B43: =IF(H43="UNIDADE CONSTRUTIVA",0,IF(H43="CÉLULA CONSTRUTIVA",OFFSET(B43,-1,0)+1,OFFSET(B43,-1,0))) -> 2 | C43: =IF(H43="CÉLULA CONSTRUTIVA",0,IF(H43="ETAPA",OFFSET(C43,-1,0)+1,OFFSET(C43,-1,0))) -> 2 | D43: =IF(H43="ETAPA",0,IF(H43="SUBETAPA",OFFSET(D43,-1,0)+1,OFFSET(D43,-1,0))) -> 2 | E43: =IF(H43="Subetapa",0,IF(H43="serviço",OFFSET(E43,-1,0)+1,OFFSET(E43,-1,0))) -> 4 | H43: SERVIÇO | I43: =IF(H43="Unidade Construtiva",TEXT(A43,"00"),IF(H43="Célula Construtiva",TEXT(B43,"00"),IF(H43="Etapa",CONCATENATE(TEXT(B43,"00"),".",TEXT(C43,"000")),IF(H43="Subetapa",CONCATENATE(TEXT(B43,"00"),".",TEXT(C43,"000"),".",TEXT(D43,"000")),IF(H43="Serviço",CONCATENATE(TEXT(B43,"00"),".",TEXT(C43,"000"),".",TEXT(D43,"000"),".",TEXT(E43,"000")),""))))) -> 02.002.002.004 | J43: Armação aço CA-50 ø 12,5mm para infraestrutura (corte e dobra em obra) | K43: kg | L43: =Aço_Infraestrutura!G29 -> 2977.7342 | M43: 6.3397 | N43: =IF(H43="Serviço",M43*L43,IF(H43="CÉLULA CONSTRUTIVA",SUMIFS($N$8:$N$1393,$B$8:$B$1393,B43,$H$8:$H$1393,"Serviço"),IF(H43="ETAPA",SUMIFS($N$8:$N$1393,$B$8:$B$1393,B43,$C$8:$C$1393,C43,$H$8:$H$1393,"Serviço"),IF(H43="SUBETAPA",SUMIFS($N$8:$N$1393,$B$8:$B$1393,B43,$C$8:$C$1393,C43,$D$8:$D$1393,D43,$H$8:$H$1393,"Serviço"),0)))) -> 18877.942 | O43: Considerado blocos, vigas de fundação, duto, cisterna, lajes e pilares de arranque - 10% de perda | P43: Finalizado
A44: =IF($H44="UNIDADE CONSTRUTIVA",OFFSET(A44,-1,0)+1,LARGE(A$3:A43,1)) -> 0 | B44: =IF(H44="UNIDADE CONSTRUTIVA",0,IF(H44="CÉLULA CONSTRUTIVA",OFFSET(B44,-1,0)+1,OFFSET(B44,-1,0))) -> 2 | C44: =IF(H44="CÉLULA CONSTRUTIVA",0,IF(H44="ETAPA",OFFSET(C44,-1,0)+1,OFFSET(C44,-1,0))) -> 2 | D44: =IF(H44="ETAPA",0,IF(H44="SUBETAPA",OFFSET(D44,-1,0)+1,OFFSET(D44,-1,0))) -> 2 | E44: =IF(H44="Subetapa",0,IF(H44="serviço",OFFSET(E44,-1,0)+1,OFFSET(E44,-1,0))) -> 5 | H44: SERVIÇO | I44: =IF(H44="Unidade Construtiva",TEXT(A44,"00"),IF(H44="Célula Construtiva",TEXT(B44,"00"),IF(H44="Etapa",CONCATENATE(TEXT(B44,"00"),".",TEXT(C44,"000")),IF(H44="Subetapa",CONCATENATE(TEXT(B44,"00"),".",TEXT(C44,"000"),".",TEXT(D44,"000")),IF(H44="Serviço",CONCATENATE(TEXT(B44,"00"),".",TEXT(C44,"000"),".",TEXT(D44,"000"),".",TEXT(E44,"000")),""))))) -> 02.002.002.005 | J44: Armação aço CA-50 ø 16,0mm para infraestrutura (corte e dobra em obra) | K44: kg | L44: =Aço_Infraestrutura!H29 -> 1885.8545 | M44: 6.3067 | N44: =IF(H44="Serviço",M44*L44,IF(H44="CÉLULA CONSTRUTIVA",SUMIFS($N$8:$N$1393,$B$8:$B$1393,B44,$H$8:$H$1393,"Serviço"),IF(H44="ETAPA",SUMIFS($N$8:$N$1393,$B$8:$B$1393,B44,$C$8:$C$1393,C44,$H$8:$H$1393,"Serviço"),IF(H44="SUBETAPA",SUMIFS($N$8:$N$1393,$B$8:$B$1393,B44,$C$8:$C$1393,C44,$D$8:$D$1393,D44,$H$8:$H$1393,"Serviço"),0)))) -> 11893.519 | O44: Considerado blocos, vigas de fundação, duto, cisterna, lajes e pilares de arranque - 10% de perda | P44: Finalizado
A45: =IF($H45="UNIDADE CONSTRUTIVA",OFFSET(A45,-1,0)+1,LARGE(A$3:A44,1)) -> 0 | B45: =IF(H45="UNIDADE CONSTRUTIVA",0,IF(H45="CÉLULA CONSTRUTIVA",OFFSET(B45,-1,0)+1,OFFSET(B45,-1,0))) -> 2 | C45: =IF(H45="CÉLULA CONSTRUTIVA",0,IF(H45="ETAPA",OFFSET(C45,-1,0)+1,OFFSET(C45,-1,0))) -> 2 | D45: =IF(H45="ETAPA",0,IF(H45="SUBETAPA",OFFSET(D45,-1,0)+1,OFFSET(D45,-1,0))) -> 2 | E45: =IF(H45="Subetapa",0,IF(H45="serviço",OFFSET(E45,-1,0)+1,OFFSET(E45,-1,0))) -> 6 | H45: SERVIÇO | I45: =IF(H45="Unidade Construtiva",TEXT(A45,"00"),IF(H45="Célula Construtiva",TEXT(B45,"00"),IF(H45="Etapa",CONCATENATE(TEXT(B45,"00"),".",TEXT(C45,"000")),IF(H45="Subetapa",CONCATENATE(TEXT(B45,"00"),".",TEXT(C45,"000"),".",TEXT(D45,"000")),IF(H45="Serviço",CONCATENATE(TEXT(B45,"00"),".",TEXT(C45,"000"),".",TEXT(D45,"000"),".",TEXT(E45,"000")),""))))) -> 02.002.002.006 | J45: Armação aço CA-50 ø 20,0mm para infraestrutura (corte e dobra em obra) | K45: kg | L45: =Aço_Infraestrutura!I29 -> 7412.0091 | M45: 6.1637 | N45: =IF(H45="Serviço",M45*L45,IF(H45="CÉLULA CONSTRUTIVA",SUMIFS($N$8:$N$1393,$B$8:$B$1393,B45,$H$8:$H$1393,"Serviço"),IF(H45="ETAPA",SUMIFS($N$8:$N$1393,$B$8:$B$1393,B45,$C$8:$C$1393,C45,$H$8:$H$1393,"Serviço"),IF(H45="SUBETAPA",SUMIFS($N$8:$N$1393,$B$8:$B$1393,B45,$C$8:$C$1393,C45,$D$8:$D$1393,D45,$H$8:$H$1393,"Serviço"),0)))) -> 45685.4 | O45: Considerado blocos, vigas de fundação, duto, cisterna, lajes e pilares de arranque - 10% de perda | P45: Finalizado
A46: =IF($H46="UNIDADE CONSTRUTIVA",OFFSET(A46,-1,0)+1,LARGE(A$3:A45,1)) -> 0 | B46: =IF(H46="UNIDADE CONSTRUTIVA",0,IF(H46="CÉLULA CONSTRUTIVA",OFFSET(B46,-1,0)+1,OFFSET(B46,-1,0))) -> 2 | C46: =IF(H46="CÉLULA CONSTRUTIVA",0,IF(H46="ETAPA",OFFSET(C46,-1,0)+1,OFFSET(C46,-1,0))) -> 2 | D46: =IF(H46="ETAPA",0,IF(H46="SUBETAPA",OFFSET(D46,-1,0)+1,OFFSET(D46,-1,0))) -> 2 | E46: =IF(H46="Subetapa",0,IF(H46="serviço",OFFSET(E46,-1,0)+1,OFFSET(E46,-1,0))) -> 7 | H46: SERVIÇO | I46: =IF(H46="Unidade Construtiva",TEXT(A46,"00"),IF(H46="Célula Construtiva",TEXT(B46,"00"),IF(H46="Etapa",CONCATENATE(TEXT(B46,"00"),".",TEXT(C46,"000")),IF(H46="Subetapa",CONCATENATE(TEXT(B46,"00"),".",TEXT(C46,"000"),".",TEXT(D46,"000")),IF(H46="Serviço",CONCATENATE(TEXT(B46,"00"),".",TEXT(C46,"000"),".",TEXT(D46,"000"),".",TEXT(E46,"000")),""))))) -> 02.002.002.007 | J46: Armação aço CA-50 ø 25,0mm para infraestrutura (corte e dobra em obra) | K46: kg | L46: =Aço_Infraestrutura!J29 -> 11885.745 | M46: 7.4177 | N46: =IF(H46="Serviço",M46*L46,IF(H46="CÉLULA CONSTRUTIVA",SUMIFS($N$8:$N$1393,$B$8:$B$1393,B46,$H$8:$H$1393,"Serviço"),IF(H46="ETAPA",SUMIFS($N$8:$N$1393,$B$8:$B$1393,B46,$C$8:$C$1393,C46,$H$8:$H$1393,"Serviço"),IF(H46="SUBETAPA",SUMIFS($N$8:$N$1393,$B$8:$B$1393,B46,$C$8:$C$1393,C46,$D$8:$D$1393,D46,$H$8:$H$1393,"Serviço"),0)))) -> 88164.894 | O46: Considerado blocos, vigas de fundação, duto, cisterna, lajes e pilares de arranque - 10% de perda | P46: Finalizado
A47: =IF($H47="UNIDADE CONSTRUTIVA",OFFSET(A47,-1,0)+1,LARGE(A$3:A46,1)) -> 0 | B47: =IF(H47="UNIDADE CONSTRUTIVA",0,IF(H47="CÉLULA CONSTRUTIVA",OFFSET(B47,-1,0)+1,OFFSET(B47,-1,0))) -> 2 | C47: =IF(H47="CÉLULA CONSTRUTIVA",0,IF(H47="ETAPA",OFFSET(C47,-1,0)+1,OFFSET(C47,-1,0))) -> 2 | D47: =IF(H47="ETAPA",0,IF(H47="SUBETAPA",OFFSET(D47,-1,0)+1,OFFSET(D47,-1,0))) -> 2 | E47: =IF(H47="Subetapa",0,IF(H47="serviço",OFFSET(E47,-1,0)+1,OFFSET(E47,-1,0))) -> 8 | H47: SERVIÇO | I47: =IF(H47="Unidade Construtiva",TEXT(A47,"00"),IF(H47="Célula Construtiva",TEXT(B47,"00"),IF(H47="Etapa",CONCATENATE(TEXT(B47,"00"),".",TEXT(C47,"000")),IF(H47="Subetapa",CONCATENATE(TEXT(B47,"00"),".",TEXT(C47,"000"),".",TEXT(D47,"000")),IF(H47="Serviço",CONCATENATE(TEXT(B47,"00"),".",TEXT(C47,"000"),".",TEXT(D47,"000"),".",TEXT(E47,"000")),""))))) -> 02.002.002.008 | J47: Armação aço CA-60 ø 5,00mm para infraestrutura (corte e dobra em obra) | K47: kg | L47: =Aço_Infraestrutura!K29 -> 372.29091 | M47: 7.6817 | N47: =IF(H47="Serviço",M47*L47,IF(H47="CÉLULA CONSTRUTIVA",SUMIFS($N$8:$N$1393,$B$8:$B$1393,B47,$H$8:$H$1393,"Serviço"),IF(H47="ETAPA",SUMIFS($N$8:$N$1393,$B$8:$B$1393,B47,$C$8:$C$1393,C47,$H$8:$H$1393,"Serviço"),IF(H47="SUBETAPA",SUMIFS($N$8:$N$1393,$B$8:$B$1393,B47,$C$8:$C$1393,C47,$D$8:$D$1393,D47,$H$8:$H$1393,"Serviço"),0)))) -> 2859.8271 | O47: Considerado blocos, vigas de fundação, duto, cisterna, lajes e pilares de arranque - 10% de perda | P47: Finalizado
A48: =IF($H48="UNIDADE CONSTRUTIVA",OFFSET(A48,-1,0)+1,LARGE(A$3:A47,1)) -> 0 | B48: =IF(H48="UNIDADE CONSTRUTIVA",0,IF(H48="CÉLULA CONSTRUTIVA",OFFSET(B48,-1,0)+1,OFFSET(B48,-1,0))) -> 2 | C48: =IF(H48="CÉLULA CONSTRUTIVA",0,IF(H48="ETAPA",OFFSET(C48,-1,0)+1,OFFSET(C48,-1,0))) -> 2 | D48: =IF(H48="ETAPA",0,IF(H48="SUBETAPA",OFFSET(D48,-1,0)+1,OFFSET(D48,-1,0))) -> 3 | E48: =IF(H48="Subetapa",0,IF(H48="serviço",OFFSET(E48,-1,0)+1,OFFSET(E48,-1,0))) -> 0 | H48: SUBETAPA | I48: =IF(H48="Unidade Construtiva",TEXT(A48,"00"),IF(H48="Célula Construtiva",TEXT(B48,"00"),IF(H48="Etapa",CONCATENATE(TEXT(B48,"00"),".",TEXT(C48,"000")),IF(H48="Subetapa",CONCATENATE(TEXT(B48,"00"),".",TEXT(C48,"000"),".",TEXT(D48,"000")),IF(H48="Serviço",CONCATENATE(TEXT(B48,"00"),".",TEXT(C48,"000"),".",TEXT(D48,"000"),".",TEXT(E48,"000")),""))))) -> 02.002.003 | J48: Concreto | N48: =IF(H48="Serviço",M48*L48,IF(H48="CÉLULA CONSTRUTIVA",SUMIFS($N$8:$N$1393,$B$8:$B$1393,B48,$H$8:$H$1393,"Serviço"),IF(H48="ETAPA",SUMIFS($N$8:$N$1393,$B$8:$B$1393,B48,$C$8:$C$1393,C48,$H$8:$H$1393,"Serviço"),IF(H48="SUBETAPA",SUMIFS($N$8:$N$1393,$B$8:$B$1393,B48,$C$8:$C$1393,C48,$D$8:$D$1393,D48,$H$8:$H$1393,"Serviço"),0)))) -> 200180.95
A49: =IF($H49="UNIDADE CONSTRUTIVA",OFFSET(A49,-1,0)+1,LARGE(A$3:A48,1)) -> 0 | B49: =IF(H49="UNIDADE CONSTRUTIVA",0,IF(H49="CÉLULA CONSTRUTIVA",OFFSET(B49,-1,0)+1,OFFSET(B49,-1,0))) -> 2 | C49: =IF(H49="CÉLULA CONSTRUTIVA",0,IF(H49="ETAPA",OFFSET(C49,-1,0)+1,OFFSET(C49,-1,0))) -> 2 | D49: =IF(H49="ETAPA",0,IF(H49="SUBETAPA",OFFSET(D49,-1,0)+1,OFFSET(D49,-1,0))) -> 3 | E49: =IF(H49="Subetapa",0,IF(H49="serviço",OFFSET(E49,-1,0)+1,OFFSET(E49,-1,0))) -> 1 | H49: SERVIÇO | I49: =IF(H49="Unidade Construtiva",TEXT(A49,"00"),IF(H49="Célula Construtiva",TEXT(B49,"00"),IF(H49="Etapa",CONCATENATE(TEXT(B49,"00"),".",TEXT(C49,"000")),IF(H49="Subetapa",CONCATENATE(TEXT(B49,"00"),".",TEXT(C49,"000"),".",TEXT(D49,"000")),IF(H49="Serviço",CONCATENATE(TEXT(B49,"00"),".",TEXT(C49,"000"),".",TEXT(D49,"000"),".",TEXT(E49,"000")),""))))) -> 02.002.003.001 | J49: Concreto Usinado bombeável 35MPa para infraestrutura - incluindo serviço de bombeamento | K49: m3 | L49: =Aço_Infraestrutura!M26 -> 24.9446 | M49: 536.7692 | N49: =IF(H49="Serviço",M49*L49,IF(H49="CÉLULA CONSTRUTIVA",SUMIFS($N$8:$N$1393,$B$8:$B$1393,B49,$H$8:$H$1393,"Serviço"),IF(H49="ETAPA",SUMIFS($N$8:$N$1393,$B$8:$B$1393,B49,$C$8:$C$1393,C49,$H$8:$H$1393,"Serviço"),IF(H49="SUBETAPA",SUMIFS($N$8:$N$1393,$B$8:$B$1393,B49,$C$8:$C$1393,C49,$D$8:$D$1393,D49,$H$8:$H$1393,"Serviço"),0)))) -> 13389.493 | O49: Considerado blocos, vigas de fundação, duto, cisterna, lajes e pilares de arranque - 5% de perda | P49: Finalizado
A50: =IF($H50="UNIDADE CONSTRUTIVA",OFFSET(A50,-1,0)+1,LARGE(A$3:A49,1)) -> 0 | B50: =IF(H50="UNIDADE CONSTRUTIVA",0,IF(H50="CÉLULA CONSTRUTIVA",OFFSET(B50,-1,0)+1,OFFSET(B50,-1,0))) -> 2 | C50: =IF(H50="CÉLULA CONSTRUTIVA",0,IF(H50="ETAPA",OFFSET(C50,-1,0)+1,OFFSET(C50,-1,0))) -> 2 | D50: =IF(H50="ETAPA",0,IF(H50="SUBETAPA",OFFSET(D50,-1,0)+1,OFFSET(D50,-1,0))) -> 3 | E50: =IF(H50="Subetapa",0,IF(H50="serviço",OFFSET(E50,-1,0)+1,OFFSET(E50,-1,0))) -> 2 | H50: SERVIÇO | I50: =IF(H50="Unidade Construtiva",TEXT(A50,"00"),IF(H50="Célula Construtiva",TEXT(B50,"00"),IF(H50="Etapa",CONCATENATE(TEXT(B50,"00"),".",TEXT(C50,"000")),IF(H50="Subetapa",CONCATENATE(TEXT(B50,"00"),".",TEXT(C50,"000"),".",TEXT(D50,"000")),IF(H50="Serviço",CONCATENATE(TEXT(B50,"00"),".",TEXT(C50,"000"),".",TEXT(D50,"000"),".",TEXT(E50,"000")),""))))) -> 02.002.003.002 | J50: Concreto Usinado bombeável 40MPa para infraestrutura- incluindo serviço de bombeamento | K50: m3 | L50: =Aço_Infraestrutura!M29-L49 -> 341.3155 | M50: 547.2692 | N50: =IF(H50="Serviço",M50*L50,IF(H50="CÉLULA CONSTRUTIVA",SUMIFS($N$8:$N$1393,$B$8:$B$1393,B50,$H$8:$H$1393,"Serviço"),IF(H50="ETAPA",SUMIFS($N$8:$N$1393,$B$8:$B$1393,B50,$C$8:$C$1393,C50,$H$8:$H$1393,"Serviço"),IF(H50="SUBETAPA",SUMIFS($N$8:$N$1393,$B$8:$B$1393,B50,$C$8:$C$1393,C50,$D$8:$D$1393,D50,$H$8:$H$1393,"Serviço"),0)))) -> 186791.46 | O50: Considerado blocos, vigas de fundação, duto, cisterna, lajes e pilares de arranque - 5% de perda | P50: Finalizado
A51: =IF($H51="UNIDADE CONSTRUTIVA",OFFSET(A51,-1,0)+1,LARGE(A$3:A50,1)) -> 0 | B51: =IF(H51="UNIDADE CONSTRUTIVA",0,IF(H51="CÉLULA CONSTRUTIVA",OFFSET(B51,-1,0)+1,OFFSET(B51,-1,0))) -> 2 | C51: =IF(H51="CÉLULA CONSTRUTIVA",0,IF(H51="ETAPA",OFFSET(C51,-1,0)+1,OFFSET(C51,-1,0))) -> 2 | D51: =IF(H51="ETAPA",0,IF(H51="SUBETAPA",OFFSET(D51,-1,0)+1,OFFSET(D51,-1,0))) -> 4 | E51: =IF(H51="Subetapa",0,IF(H51="serviço",OFFSET(E51,-1,0)+1,OFFSET(E51,-1,0))) -> 0 | H51: SUBETAPA | I51: =IF(H51="Unidade Construtiva",TEXT(A51,"00"),IF(H51="Célula Construtiva",TEXT(B51,"00"),IF(H51="Etapa",CONCATENATE(TEXT(B51,"00"),".",TEXT(C51,"000")),IF(H51="Subetapa",CONCATENATE(TEXT(B51,"00"),".",TEXT(C51,"000"),".",TEXT(D51,"000")),IF(H51="Serviço",CONCATENATE(TEXT(B51,"00"),".",TEXT(C51,"000"),".",TEXT(D51,"000"),".",TEXT(E51,"000")),""))))) -> 02.002.004 | J51: Mão de Obra | N51: =IF(H51="Serviço",M51*L51,IF(H51="CÉLULA CONSTRUTIVA",SUMIFS($N$8:$N$1393,$B$8:$B$1393,B51,$H$8:$H$1393,"Serviço"),IF(H51="ETAPA",SUMIFS($N$8:$N$1393,$B$8:$B$1393,B51,$C$8:$C$1393,C51,$H$8:$H$1393,"Serviço"),IF(H51="SUBETAPA",SUMIFS($N$8:$N$1393,$B$8:$B$1393,B51,$C$8:$C$1393,C51,$D$8:$D$1393,D51,$H$8:$H$1393,"Serviço"),0)))) -> 287827.2
A52: =IF($H52="UNIDADE CONSTRUTIVA",OFFSET(A52,-1,0)+1,LARGE(A$3:A51,1)) -> 0 | B52: =IF(H52="UNIDADE CONSTRUTIVA",0,IF(H52="CÉLULA CONSTRUTIVA",OFFSET(B52,-1,0)+1,OFFSET(B52,-1,0))) -> 2 | C52: =IF(H52="CÉLULA CONSTRUTIVA",0,IF(H52="ETAPA",OFFSET(C52,-1,0)+1,OFFSET(C52,-1,0))) -> 2 | D52: =IF(H52="ETAPA",0,IF(H52="SUBETAPA",OFFSET(D52,-1,0)+1,OFFSET(D52,-1,0))) -> 4 | E52: =IF(H52="Subetapa",0,IF(H52="serviço",OFFSET(E52,-1,0)+1,OFFSET(E52,-1,0))) -> 1 | H52: SERVIÇO | I52: =IF(H52="Unidade Construtiva",TEXT(A52,"00"),IF(H52="Célula Construtiva",TEXT(B52,"00"),IF(H52="Etapa",CONCATENATE(TEXT(B52,"00"),".",TEXT(C52,"000")),IF(H52="Subetapa",CONCATENATE(TEXT(B52,"00"),".",TEXT(C52,"000"),".",TEXT(D52,"000")),IF(H52="Serviço",CONCATENATE(TEXT(B52,"00"),".",TEXT(C52,"000"),".",TEXT(D52,"000"),".",TEXT(E52,"000")),""))))) -> 02.002.004.001 | J52: Mão de obra para execução de fundação rasa e profunda | K52: m2 | L52: ='Obra '!E15 -> 799.52 | M52: =1.5*M76 -> 360 | N52: =IF(H52="Serviço",M52*L52,IF(H52="CÉLULA CONSTRUTIVA",SUMIFS($N$8:$N$1393,$B$8:$B$1393,B52,$H$8:$H$1393,"Serviço"),IF(H52="ETAPA",SUMIFS($N$8:$N$1393,$B$8:$B$1393,B52,$C$8:$C$1393,C52,$H$8:$H$1393,"Serviço"),IF(H52="SUBETAPA",SUMIFS($N$8:$N$1393,$B$8:$B$1393,B52,$C$8:$C$1393,C52,$D$8:$D$1393,D52,$H$8:$H$1393,"Serviço"),0)))) -> 287827.2 | P52: Finalizado
A53: =IF($H53="UNIDADE CONSTRUTIVA",OFFSET(A53,-1,0)+1,LARGE(A$3:A52,1)) -> 0 | B53: =IF(H53="UNIDADE CONSTRUTIVA",0,IF(H53="CÉLULA CONSTRUTIVA",OFFSET(B53,-1,0)+1,OFFSET(B53,-1,0))) -> 3 | C53: =IF(H53="CÉLULA CONSTRUTIVA",0,IF(H53="ETAPA",OFFSET(C53,-1,0)+1,OFFSET(C53,-1,0))) -> 0 | D53: =IF(H53="ETAPA",0,IF(H53="SUBETAPA",OFFSET(D53,-1,0)+1,OFFSET(D53,-1,0))) -> 4 | E53: =IF(H53="Subetapa",0,IF(H53="serviço",OFFSET(E53,-1,0)+1,OFFSET(E53,-1,0))) -> 1 | H53: CÉLULA CONSTRUTIVA | I53: =IF(H53="Unidade Construtiva",TEXT(A53,"00"),IF(H53="Célula Construtiva",TEXT(B53,"00"),IF(H53="Etapa",CONCATENATE(TEXT(B53,"00"),".",TEXT(C53,"000")),IF(H53="Subetapa",CONCATENATE(TEXT(B53,"00"),".",TEXT(C53,"000"),".",TEXT(D53,"000")),IF(H53="Serviço",CONCATENATE(TEXT(B53,"00"),".",TEXT(C53,"000"),".",TEXT(D53,"000"),".",TEXT(E53,"000")),""))))) -> 03 | J53: SUPRAESTRUTURA | N53: =IF(H53="Serviço",M53*L53,IF(H53="CÉLULA CONSTRUTIVA",SUMIFS($N$8:$N$1393,$B$8:$B$1393,B53,$H$8:$H$1393,"Serviço"),IF(H53="ETAPA",SUMIFS($N$8:$N$1393,$B$8:$B$1393,B53,$C$8:$C$1393,C53,$H$8:$H$1393,"Serviço"),IF(H53="SUBETAPA",SUMIFS($N$8:$N$1393,$B$8:$B$1393,B53,$C$8:$C$1393,C53,$D$8:$D$1393,D53,$H$8:$H$1393,"Serviço"),0)))) -> 6810042.5
A54: =IF($H54="UNIDADE CONSTRUTIVA",OFFSET(A54,-1,0)+1,LARGE(A$3:A53,1)) -> 0 | B54: =IF(H54="UNIDADE CONSTRUTIVA",0,IF(H54="CÉLULA CONSTRUTIVA",OFFSET(B54,-1,0)+1,OFFSET(B54,-1,0))) -> 3 | C54: =IF(H54="CÉLULA CONSTRUTIVA",0,IF(H54="ETAPA",OFFSET(C54,-1,0)+1,OFFSET(C54,-1,0))) -> 1 | D54: =IF(H54="ETAPA",0,IF(H54="SUBETAPA",OFFSET(D54,-1,0)+1,OFFSET(D54,-1,0))) -> 0 | E54: =IF(H54="Subetapa",0,IF(H54="serviço",OFFSET(E54,-1,0)+1,OFFSET(E54,-1,0))) -> 1 | H54: ETAPA | I54: =IF(H54="Unidade Construtiva",TEXT(A54,"00"),IF(H54="Célula Construtiva",TEXT(B54,"00"),IF(H54="Etapa",CONCATENATE(TEXT(B54,"00"),".",TEXT(C54,"000")),IF(H54="Subetapa",CONCATENATE(TEXT(B54,"00"),".",TEXT(C54,"000"),".",TEXT(D54,"000")),IF(H54="Serviço",CONCATENATE(TEXT(B54,"00"),".",TEXT(C54,"000"),".",TEXT(D54,"000"),".",TEXT(E54,"000")),""))))) -> 03.001 | J54: SUPRAESTRUTURA - TÉRREO | N54: =IF(H54="Serviço",M54*L54,IF(H54="CÉLULA CONSTRUTIVA",SUMIFS($N$8:$N$1393,$B$8:$B$1393,B54,$H$8:$H$1393,"Serviço"),IF(H54="ETAPA",SUMIFS($N$8:$N$1393,$B$8:$B$1393,B54,$C$8:$C$1393,C54,$H$8:$H$1393,"Serviço"),IF(H54="SUBETAPA",SUMIFS($N$8:$N$1393,$B$8:$B$1393,B54,$C$8:$C$1393,C54,$D$8:$D$1393,D54,$H$8:$H$1393,"Serviço"),0)))) -> 490966.71
A55: =IF($H55="UNIDADE CONSTRUTIVA",OFFSET(A55,-1,0)+1,LARGE(A$3:A54,1)) -> 0 | B55: =IF(H55="UNIDADE CONSTRUTIVA",0,IF(H55="CÉLULA CONSTRUTIVA",OFFSET(B55,-1,0)+1,OFFSET(B55,-1,0))) -> 3 | C55: =IF(H55="CÉLULA CONSTRUTIVA",0,IF(H55="ETAPA",OFFSET(C55,-1,0)+1,OFFSET(C55,-1,0))) -> 1 | D55: =IF(H55="ETAPA",0,IF(H55="SUBETAPA",OFFSET(D55,-1,0)+1,OFFSET(D55,-1,0))) -> 1 | E55: =IF(H55="Subetapa",0,IF(H55="serviço",OFFSET(E55,-1,0)+1,OFFSET(E55,-1,0))) -> 0 | H55: SUBETAPA | I55: =IF(H55="Unidade Construtiva",TEXT(A55,"00"),IF(H55="Célula Construtiva",TEXT(B55,"00"),IF(H55="Etapa",CONCATENATE(TEXT(B55,"00"),".",TEXT(C55,"000")),IF(H55="Subetapa",CONCATENATE(TEXT(B55,"00"),".",TEXT(C55,"000"),".",TEXT(D55,"000")),IF(H55="Serviço",CONCATENATE(TEXT(B55,"00"),".",TEXT(C55,"000"),".",TEXT(D55,"000"),".",TEXT(E55,"000")),""))))) -> 03.001.001 | J55: Forma | N55: =IF(H55="Serviço",M55*L55,IF(H55="CÉLULA CONSTRUTIVA",SUMIFS($N$8:$N$1393,$B$8:$B$1393,B55,$H$8:$H$1393,"Serviço"),IF(H55="ETAPA",SUMIFS($N$8:$N$1393,$B$8:$B$1393,B55,$C$8:$C$1393,C55,$H$8:$H$1393,"Serviço"),IF(H55="SUBETAPA",SUMIFS($N$8:$N$1393,$B$8:$B$1393,B55,$C$8:$C$1393,C55,$D$8:$D$1393,D55,$H$8:$H$1393,"Serviço"),0)))) -> 78510.057
A56: =IF($H56="UNIDADE CONSTRUTIVA",OFFSET(A56,-1,0)+1,LARGE(A$3:A55,1)) -> 0 | B56: =IF(H56="UNIDADE CONSTRUTIVA",0,IF(H56="CÉLULA CONSTRUTIVA",OFFSET(B56,-1,0)+1,OFFSET(B56,-1,0))) -> 3 | C56: =IF(H56="CÉLULA CONSTRUTIVA",0,IF(H56="ETAPA",OFFSET(C56,-1,0)+1,OFFSET(C56,-1,0))) -> 1 | D56: =IF(H56="ETAPA",0,IF(H56="SUBETAPA",OFFSET(D56,-1,0)+1,OFFSET(D56,-1,0))) -> 1 | E56: =IF(H56="Subetapa",0,IF(H56="serviço",OFFSET(E56,-1,0)+1,OFFSET(E56,-1,0))) -> 1 | H56: SERVIÇO | I56: =IF(H56="Unidade Construtiva",TEXT(A56,"00"),IF(H56="Célula Construtiva",TEXT(B56,"00"),IF(H56="Etapa",CONCATENATE(TEXT(B56,"00"),".",TEXT(C56,"000")),IF(H56="Subetapa",CONCATENATE(TEXT(B56,"00"),".",TEXT(C56,"000"),".",TEXT(D56,"000")),IF(H56="Serviço",CONCATENATE(TEXT(B56,"00"),".",TEXT(C56,"000"),".",TEXT(D56,"000"),".",TEXT(E56,"000")),""))))) -> 03.001.001.001 | J56: Forma para Laje Contrapiso Térreo em Tábuas de Madeira Serrada | K56: m2 | L56: =EPCs!M5*0.2 -> 23.702 | M56: 65.1206 | N56: =IF(H56="Serviço",M56*L56,IF(H56="CÉLULA CONSTRUTIVA",SUMIFS($N$8:$N$1393,$B$8:$B$1393,B56,$H$8:$H$1393,"Serviço"),IF(H56="ETAPA",SUMIFS($N$8:$N$1393,$B$8:$B$1393,B56,$C$8:$C$1393,C56,$H$8:$H$1393,"Serviço"),IF(H56="SUBETAPA",SUMIFS($N$8:$N$1393,$B$8:$B$1393,B56,$C$8:$C$1393,C56,$D$8:$D$1393,D56,$H$8:$H$1393,"Serviço"),0)))) -> 1543.4885 | O56: Considerado Laje do Térreo | P56: Finalizado
