Workbook

Sheet PAINEL
A1: PAINEL DE CONTROLE
A4: Projeto: | B4: =DADOS_PROJETO!B2
A5: Área Construída: | B5: =DADOS_PROJETO!B6&" m²"
A6: Unidades: | B6: =DADOS_PROJETO!B7+DADOS_PROJETO!B8
A8: Custo Total: | B8: =CUSTOS_MACROGRUPO!G20
A9: Custo/m²: | B9: =CUSTOS_MACROGRUPO!G20/DADOS_PROJETO!B6
A10: Custo/Unidade: | B10: =CUSTOS_MACROGRUPO!G20/(DADOS_PROJETO!B7+DADOS_PROJETO!B8)
A12: CUB Atual: | B12: =DADOS_PROJETO!B19
A13: Fator CUB: | B13: =DADOS_PROJETO!B19/DADOS_PROJETO!B20
A15: Top 3 Macrogrupos:
A16: 1º | B16: =INDEX(CUSTOS_MACROGRUPO!B:B,MATCH(LARGE(CUSTOS_MACROGRUPO!H:H,1),CUSTOS_MACROGRUPO!H:H,0))&" ("&TEXT(LARGE(CUSTOS_MACROGRUPO!H:H,1),"0.0%")&")"
A17: 2º | B17: =INDEX(CUSTOS_MACROGRUPO!B:B,MATCH(LARGE(CUSTOS_MACROGRUPO!H:H,2),CUSTOS_MACROGRUPO!H:H,0))&" ("&TEXT(LARGE(CUSTOS_MACROGRUPO!H:H,2),"0.0%")&")"
A18: 3º | B18: =INDEX(CUSTOS_MACROGRUPO!B:B,MATCH(LARGE(CUSTOS_MACROGRUPO!H:H,3),CUSTOS_MACROGRUPO!H:H,0))&" ("&TEXT(LARGE(CUSTOS_MACROGRUPO!H:H,3),"0.0%")&")"

Sheet DADOS_PROJETO
A1: DADOS DO PROJETO
A2: Nome do Projeto | B2: Residencial Alípio Schirmann
A3: Código | B3: BCI-ALIPIO
A4: Cidade | B4: Itapema/SC
A6: Área Construída (m²) | B6: 12033.95
A7: Unidades Residenciais | B7: 43
A8: Unidades Comerciais | B8: 5
A9: Número de Pavimentos | B9: 26
A10: Pavimentos Tipo | B10: 21
A11: Pavimentos Garagem | B11: 3
A12: Elevadores | B12: 3
A13: Vagas | B13: 92
A14: Área Terreno (m²) | B14: 1029.39
A15: Número de Subsolos | B15: 0
A17: Prazo (meses) | B17: 36
A19: CUB Atual (R$/m²) | B19: 3019.26
A20: CUB Base dez/23 (R$/m²) | B20: 2752.67
A21: Data-base | B21: mar/2026

Sheet BRIEFING
A1: # | B1: Pergunta | C1: Resposta | D1: Macrogrupos Afetados
A2: Q1 | B2: Tipo de Fundação | C2: Hélice Contínua | D2: Infraestrutura
A3: Q2 | B3: Tipo de Laje | C3: Cubetas | D3: Supraestrutura
A4: Q3 | B4: Contenção | C4: Não | D4: Infraestrutura
A5: Q4 | B5: Subsolos | C5: 0 | D5: Mov. Terra, Infraestrutura, Impermeabilização
A6: Q5 | B6: Padrão | C6: Alto | D6: Rev. Int. Parede, Teto, Pisos, Pintura, Esquadrias, Fachada, Complementares
A7: Q6 | B7: Esquadria | C7: Pintura eletrostática | D7: Esquadrias
A8: Q7 | B8: Piso | C8: Porcelanato padrão | D8: Pisos
A9: Q8 | B9: Vedação | C9: Alvenaria | D9: Alvenaria
A10: Q9 | B10: Forro | C10: Gesso liso | D10: Teto
A11: Q10 | B11: Fachada | C11: Misto | D11: Fachada
A12: Q11 | B12: MO Fachada | C12: Empreitada | D12: Fachada
... A26: Q25 | B26: Pressurização | C26: Não | D26: Instalações

Sheet FATORES
A1: MATRIZ DE FATORES
A2: Macrogrupo | B2: Q1 | C2: Q2 | D2: Q3 | E2: Q4 | F2: Q5 | G2: Q6 | H2: Q7 | I2: Q8 | J2: Q9 | K2: Q10 | L2: Q11 | M2: Q12 | N2: Q13 | O2: Q14 | P2: Q15 | Q2: Q16 | R2: Q17 | S2: Q18 | T2: Q19 | U2: Q20 | V2: Q21 | W2: Q22 | X2: Q23 | Y2: Q24 | Z2: Q25 | AA2: Fator Briefing
A3: Gerenciamento | B3: =1 | C3: =1 | D3: =1 | E3: =1 | F3: =1 | G3: =1 | H3: =1 | I3: =1 | ... S3: =1 | T3: =IF(BRIEFING!$C$20="18",0.6,IF(BRIEFING!$C$20="24",0.75,IF(BRIEFING!$C$20="30",0.88,IF(BRIEFING!$C$20="36",1.0,IF(BRIEFING!$C$20="42",1.15,IF(BRIEFING!$C$20="48",1.3,1)))))) | U3: =IF(BRIEFING!$C$21="Interior SC",0.95,IF(BRIEFING!$C$21="Litoral SC",1.0,IF(BRIEFING!$C$21="Capital Floripa",1.05,IF(BRIEFING!$C$21="Litoral SP",1.15,IF(BRIEFING!$C$21="Capital SP-RJ",1.25,1))))) | V3: =1 | W3: =1 | X3: =1 | Y3: =1 | Z3: =1 | AA3: =PRODUCT(B3:Z3)
A4: Mov. Terra | B4: =1 | C4: =1 | D4: =1 | E4: =IF(BRIEFING!$C$5="0",1.0,IF(BRIEFING!$C$5="1",2.0,IF(BRIEFING!$C$5="2",3.5,IF(BRIEFING!$C$5="3+",5.0,1)))) | F4: =1 | G4: =1 | H4: =1 | I4: =1 | J4: =1 | K4: =1 | L4: =1 | M4: =1 | ... T4: =1 | U4: =IF(BRIEFING!$C$21="Interior SC",0.95,IF(BRIEFING!$C$21="Litoral SC",1.0,IF(BRIEFING!$C$21="Capital Floripa",1.05,IF(BRIEFING!$C$21="Litoral SP",1.15,IF(BRIEFING!$C$21="Capital SP-RJ",1.25,1))))) | V4: =1 | W4: =1 | X4: =1 | Y4: =1 | Z4: =1 | AA4: =PRODUCT(B4:Z4)
A5: Infraestrutura | B5: =IF(BRIEFING!$C$2="Hélice Contínua",1.0,IF(BRIEFING!$C$2="Estaca Franki",0.9,IF(BRIEFING!$C$2="Tubulão",1.15,IF(BRIEFING!$C$2="Sapata/Radier",0.75,IF(BRIEFING!$C$2="Estaca raiz",1.1,1))))) | C5: =1 | D5: =IF(BRIEFING!$C$4="Não",1.0,IF(BRIEFING!$C$4="Cortina de estacas",1.4,IF(BRIEFING!$C$4="Muro de arrimo",1.2,IF(BRIEFING!$C$4="Solo grampeado",1.3,IF(BRIEFING!$C$4="Tirantes",1.35,1))))) | E5: =IF(BRIEFING!$C$5="0",1.0,IF(BRIEFING!$C$5="1",1.2,IF(BRIEFING!$C$5="2",1.4,IF(BRIEFING!$C$5="3+",1.6,1)))) | F5: =1 | G5: =1 | H5: =1 | I5: =1 | J5: =1 | K5: =1 | L5: =1 | M5: =1 | ... T5: =1 | U5: =IF(BRIEFING!$C$21="Interior SC",0.95,IF(BRIEFING!$C$21="Litoral SC",1.0,IF(BRIEFING!$C$21="Capital Floripa",1.05,IF(BRIEFING!$C$21="Litoral SP",1.15,IF(BRIEFING!$C$21="Capital SP-RJ",1.25,1))))) | V5: =1 | W5: =1 | X5: =1 | Y5: =1 | Z5: =1 | AA5: =PRODUCT(B5:Z5)
A6: Supraestrutura | B6: =1 | C6: =IF(BRIEFING!$C$3="Cubetas",1.0,IF(BRIEFING!$C$3="Protendida",1.05,IF(BRIEFING!$C$3="Maciça",1.1,IF(BRIEFING!$C$3="Mista",1.03,IF(BRIEFING!$C$3="Treliçada",0.95,1))))) | D6: =1 | E6: =1 | F6: =1 | G6: =1 | H6: =1 | I6: =1 | J6: =1 | K6: =1 | ... T6: =1 | U6: =IF(BRIEFING!$C$21="Interior SC",0.95,IF(BRIEFING!$C$21="Litoral SC",1.0,IF(BRIEFING!$C$21="Capital Floripa",1.05,IF(BRIEFING!$C$21="Litoral SP",1.15,IF(BRIEFING!$C$21="Capital SP-RJ",1.25,1))))) | V6: =1 | W6: =1 | X6: =1 | Y6: =1 | Z6: =1 | AA6: =PRODUCT(B6:Z6)
A7: Alvenaria | B7: =1 | C7: =1 | D7: =1 | E7: =1 | F7: =1 | G7: =1 | H7: =1 | I7: =IF(BRIEFING!$C$9="Alvenaria",1.0,IF(BRIEFING!$C$9="Drywall",1.8,IF(BRIEFING!$C$9="Misto",1.3,1))) | J7: =1 | K7: =1 | L7: =1 | M7: =1 | N7: =1 | O7: =1 | P7: =1 | Q7: =1 | ... T7: =1 | U7: =IF(BRIEFING!$C$21="Interior SC",0.95,IF(BRIEFING!$C$21="Litoral SC",1.0,IF(BRIEFING!$C$21="Capital Floripa",1.05,IF(BRIEFING!$C$21="Litoral SP",1.15,IF(BRIEFING!$C$21="Capital SP-RJ",1.25,1))))) | V7: =1 | W7: =1 | X7: =1 | Y7: =1 | Z7: =1 | AA7: =PRODUCT(B7:Z7)
A8: Impermeabilização | B8: =1 | C8: =1 | D8: =1 | E8: =IF(BRIEFING!$C$5="0",1.0,IF(BRIEFING!$C$5="1",1.3,IF(BRIEFING!$C$5="2",1.6,IF(BRIEFING!$C$5="3+",1.9,1)))) | F8: =1 | G8: =1 | H8: =1 | I8: =1 | J8: =1 | K8: =1 | L8: =1 | M8: =1 | ... T8: =1 | U8: =IF(BRIEFING!$C$21="Interior SC",0.95,IF(BRIEFING!$C$21="Litoral SC",1.0,IF(BRIEFING!$C$21="Capital Floripa",1.05,IF(BRIEFING!$C$21="Litoral SP",1.15,IF(BRIEFING!$C$21="Capital SP-RJ",1.25,1))))) | V8: =1 | W8: =1 | X8: =1 | Y8: =1 | Z8: =1 | AA8: =PRODUCT(B8:Z8)
A9: Instalações | B9: =1 | C9: =1 | D9: =1 | E9: =1 | F9: =1 | G9: =1 | H9: =1 | I9: =1 | ... M9: =1 | N9: =IF(BRIEFING!$C$14="Gás individual",1.0,IF(BRIEFING!$C$14="Central",1.15,IF(BRIEFING!$C$14="Solar",1.2,IF(BRIEFING!$C$14="Bomba calor",1.25,IF(BRIEFING!$C$14="Sem",0.9,1))))) | O9: =1 | P9: =1 | Q9: =1 | R9: =1 | S9: =1 | T9: =1 | U9: =IF(BRIEFING!$C$21="Interior SC",0.95,IF(BRIEFING!$C$21="Litoral SC",1.0,IF(BRIEFING!$C$21="Capital Floripa",1.05,IF(BRIEFING!$C$21="Litoral SP",1.15,IF(BRIEFING!$C$21="Capital SP-RJ",1.25,1))))) | V9: =1 | W9: =1 | X9: =1 | Y9: =IF(BRIEFING!$C$25="Sim",1.05,IF(BRIEFING!$C$25="Não",1.0,1)) | Z9: =IF(BRIEFING!$C$26="Sim",1.08,IF(BRIEFING!$C$26="Não",1.0,1)) | AA9: =PRODUCT(B9:Z9)
A10: Sist. Especiais | B10: =1 | C10: =1 | D10: =1 | E10: =1 | F10: =1 | G10: =1 | H10: =1 | I10: =1 | ... N10: =1 | O10: =IF(BRIEFING!$C$15="Mínimo",0.85,IF(BRIEFING!$C$15="Básico",1.0,IF(BRIEFING!$C$15="Completo",1.3,IF(BRIEFING!$C$15="Premium",1.6,1)))) | P10: =IF(BRIEFING!$C$16="Sem",1.0,IF(BRIEFING!$C$16="Solar comum",1.1,IF(BRIEFING!$C$16="Solar completo",1.2,1))) | Q10: =1 | R10: =1 | S10: =1 | T10: =1 | U10: =IF(BRIEFING!$C$21="Interior SC",0.95,IF(BRIEFING!$C$21="Litoral SC",1.0,IF(BRIEFING!$C$21="Capital Floripa",1.05,IF(BRIEFING!$C$21="Litoral SP",1.15,IF(BRIEFING!$C$21="Capital SP-RJ",1.25,1))))) | V10: =IF(BRIEFING!$C$22="Sim",1.15,IF(BRIEFING!$C$22="Não",1.0,1)) | W10: =IF(BRIEFING!$C$23="Sim",1.1,IF(BRIEFING!$C$23="Não",1.0,1)) | X10: =IF(BRIEFING!$C$24="Sim",1.1,IF(BRIEFING!$C$24="Não",1.0,1)) | Y10: =1 | Z10: =1 | AA10: =PRODUCT(B10:Z10)
A11: Climatização | B11: =1 | C11: =1 | D11: =1 | E11: =1 | F11: =1 | G11: =1 | H11: =1 | I11: =1 | ... T11: =1 | U11: =IF(BRIEFING!$C$21="Interior SC",0.95,IF(BRIEFING!$C$21="Litoral SC",1.0,IF(BRIEFING!$C$21="Capital Floripa",1.05,IF(BRIEFING!$C$21="Litoral SP",1.15,IF(BRIEFING!$C$21="Capital SP-RJ",1.25,1))))) | V11: =1 | W11: =1 | X11: =1 | Y11: =1 | Z11: =1 | AA11: =PRODUCT(B11:Z11)
A12: Rev. Int. Parede | B12: =1 | C12: =1 | D12: =1 | E12: =1 | F12: =IF(BRIEFING!$C$6="Econômico",0.65,IF(BRIEFING!$C$6="Standard",0.8,IF(BRIEFING!$C$6="Alto",1.0,IF(BRIEFING!$C$6="Super Alto",1.2,IF(BRIEFING!$C$6="Luxo",1.45,1))))) | G12: =1 | H12: =1 | I12: =1 | J12: =1 | K12: =1 | L12: =1 | M12: =1 | N12: =1 | ... T12: =1 | U12: =IF(BRIEFING!$C$21="Interior SC",0.95,IF(BRIEFING!$C$21="Litoral SC",1.0,IF(BRIEFING!$C$21="Capital Floripa",1.05,IF(BRIEFING!$C$21="Litoral SP",1.15,IF(BRIEFING!$C$21="Capital SP-RJ",1.25,1))))) | V12: =1 | W12: =1 | X12: =1 | Y12: =1 | Z12: =1 | AA12: =PRODUCT(B12:Z12)
A13: Teto | B13: =1 | C13: =1 | D13: =1 | E13: =1 | F13: =IF(BRIEFING!$C$6="Econômico",0.7,IF(BRIEFING!$C$6="Standard",0.8,IF(BRIEFING!$C$6="Alto",1.0,IF(BRIEFING!$C$6="Super Alto",1.2,IF(BRIEFING!$C$6="Luxo",1.4,1))))) | G13: =1 | H13: =1 | I13: =1 | J13: =IF(BRIEFING!$C$10="Estucamento",0.8,IF(BRIEFING!$C$10="Gesso liso",1.0,IF(BRIEFING!$C$10="Gesso negativo",1.15,IF(BRIEFING!$C$10="Gesso sanca",1.2,IF(BRIEFING!$C$10="Mineral",1.1,1))))) | K13: =1 | L13: =1 | M13: =1 | N13: =1 | O13: =1 | P13: =1 | Q13: =1 | R13: =1 | ... T13: =1 | U13: =IF(BRIEFING!$C$21="Interior SC",0.95,IF(BRIEFING!$C$21="Litoral SC",1.0,IF(BRIEFING!$C$21="Capital Floripa",1.05,IF(BRIEFING!$C$21="Litoral SP",1.15,IF(BRIEFING!$C$21="Capital SP-RJ",1.25,1))))) | V13: =1 | W13: =1 | X13: =1 | Y13: =1 | Z13: =1 | AA13: =PRODUCT(B13:Z13)
A14: Pisos | B14: =1 | C14: =1 | D14: =1 | E14: =1 | F14: =IF(BRIEFING!$C$6="Econômico",0.6,IF(BRIEFING!$C$6="Standard",0.75,IF(BRIEFING!$C$6="Alto",1.0,IF(BRIEFING!$C$6="Super Alto",1.3,IF(BRIEFING!$C$6="Luxo",1.7,1))))) | G14: =1 | H14: =IF(BRIEFING!$C$8="Porcelanato padrão",1.0,IF(BRIEFING!$C$8="Cerâmica",0.75,IF(BRIEFING!$C$8="Vinílico",0.85,IF(BRIEFING!$C$8="Importado",1.5,IF(BRIEFING!$C$8="Mármore",2.0,1))))) | I14: =1 | J14: =1 | K14: =1 | L14: =1 | M14: =1 | N14: =1 | O14: =1 | P14: =1 | ... T14: =1 | U14: =IF(BRIEFING!$C$21="Interior SC",0.95,IF(BRIEFING!$C$21="Litoral SC",1.0,IF(BRIEFING!$C$21="Capital Floripa",1.05,IF(BRIEFING!$C$21="Litoral SP",1.15,IF(BRIEFING!$C$21="Capital SP-RJ",1.25,1))))) | V14: =1 | W14: =1 | X14: =1 | Y14: =1 | Z14: =1 | AA14: =PRODUCT(B14:Z14)
A15: Pintura | B15: =1 | C15: =1 | D15: =1 | E15: =1 | F15: =IF(BRIEFING!$C$6="Econômico",0.85,IF(BRIEFING!$C$6="Standard",0.9,IF(BRIEFING!$C$6="Alto",1.0,IF(BRIEFING!$C$6="Super Alto",1.1,IF(BRIEFING!$C$6="Luxo",1.2,1))))) | G15: =1 | H15: =1 | I15: =1 | J15: =1 | K15: =1 | L15: =1 | M15: =1 | N15: =1 | ... T15: =1 | U15: =IF(BRIEFING!$C$21="Interior SC",0.95,IF(BRIEFING!$C$21="Litoral SC",1.0,IF(BRIEFING!$C$21="Capital Floripa",1.05,IF(BRIEFING!$C$21="Litoral SP",1.15,IF(BRIEFING!$C$21="Capital SP-RJ",1.25,1))))) | V15: =1 | W15: =1 | X15: =1 | Y15: =1 | Z15: =1 | AA15: =PRODUCT(B15:Z15)
A16: Esquadrias | B16: =1 | C16: =1 | D16: =1 | E16: =1 | F16: =IF(BRIEFING!$C$6="Econômico",0.55,IF(BRIEFING!$C$6="Standard",0.7,IF(BRIEFING!$C$6="Alto",1.0,IF(BRIEFING!$C$6="Super Alto",1.35,IF(BRIEFING!$C$6="Luxo",1.6,1))))) | G16: =IF(BRIEFING!$C$7="Alumínio anodizado",1.0,IF(BRIEFING!$C$7="Pintura eletrostática",1.15,IF(BRIEFING!$C$7="PVC",0.9,IF(BRIEFING!$C$7="Alto desempenho",1.4,1)))) | H16: =1 | I16: =1 | J16: =1 | K16: =1 | L16: =1 | M16: =1 | N16: =1 | O16: =1 | ... T16: =1 | U16: =IF(BRIEFING!$C$21="Interior SC",0.95,IF(BRIEFING!$C$21="Litoral SC",1.0,IF(BRIEFING!$C$21="Capital Floripa",1.05,IF(BRIEFING!$C$21="Litoral SP",1.15,IF(BRIEFING!$C$21="Capital SP-RJ",1.25,1))))) | V16: =1 | W16: =1 | X16: =1 | Y16: =1 | Z16: =1 | AA16: =PRODUCT(B16:Z16)
A17: Louças e Metais | B17: =1 | C17: =1 | D17: =1 | E17: =1 | F17: =1 | G17: =1 | H17: =1 | I17: =1 | ... T17: =1 | U17: =IF(BRIEFING!$C$21="Interior SC",0.95,IF(BRIEFING!$C$21="Litoral SC",1.0,IF(BRIEFING!$C$21="Capital Floripa",1.05,IF(BRIEFING!$C$21="Litoral SP",1.15,IF(BRIEFING!$C$21="Capital SP-RJ",1.25,1))))) | V17: =1 | W17: =1 | X17: =1 | Y17: =1 | Z17: =1 | AA17: =PRODUCT(B17:Z17)
A18: Fachada | B18: =1 | C18: =1 | D18: =1 | E18: =1 | F18: =IF(BRIEFING!$C$6="Econômico",0.8,IF(BRIEFING!$C$6="Standard",0.85,IF(BRIEFING!$C$6="Alto",1.0,IF(BRIEFING!$C$6="Super Alto",1.25,IF(BRIEFING!$C$6="Luxo",1.5,1))))) | G18: =1 | H18: =1 | I18: =1 | J18: =1 | K18: =IF(BRIEFING!$C$11="Textura + pintura",1.0,IF(BRIEFING!$C$11="Cerâmica/Pastilha",1.4,IF(BRIEFING!$C$11="ACM",1.8,IF(BRIEFING!$C$11="Pele de vidro",2.5,IF(BRIEFING!$C$11="Misto",1.3,1))))) | L18: =IF(BRIEFING!$C$12="Equipe própria",1.0,IF(BRIEFING!$C$12="Empreitada",1.2,1)) | M18: =1 | N18: =1 | O18: =1 | P18: =1 | Q18: =1 | R18: =1 | S18: =1 | T18: =1 | U18: =IF(BRIEFING!$C$21="Interior SC",0.95,IF(BRIEFING!$C$21="Litoral SC",1.0,IF(BRIEFING!$C$21="Capital Floripa",1.05,IF(BRIEFING!$C$21="Litoral SP",1.15,IF(BRIEFING!$C$21="Capital SP-RJ",1.25,1))))) | V18: =1 | W18: =1 | X18: =1 | Y18: =1 | Z18: =1 | AA18: =PRODUCT(B18:Z18)
A19: Complementares | B19: =1 | C19: =1 | D19: =1 | E19: =1 | F19: =IF(BRIEFING!$C$6="Econômico",0.7,IF(BRIEFING!$C$6="Standard",0.85,IF(BRIEFING!$C$6="Alto",1.0,IF(BRIEFING!$C$6="Super Alto",1.2,IF(BRIEFING!$C$6="Luxo",1.5,1))))) | G19: =1 | H19: =1 | I19: =1 | J19: =1 | K19: =1 | L19: =1 | M19: =IF(BRIEFING!$C$13="Não",1.0,IF(BRIEFING!$C$13="Básica",1.1,IF(BRIEFING!$C$13="Completa",1.25,1))) | N19: =1 | O19: =1 | P19: =1 | Q19: =IF(BRIEFING!$C$17="Básico",0.7,IF(BRIEFING!$C$17="Completo",1.0,IF(BRIEFING!$C$17="Premium",1.4,1))) | R19: =IF(BRIEFING!$C$18="Sem",0.85,IF(BRIEFING!$C$18="Básico",1.0,IF(BRIEFING!$C$18="Elaborado",1.2,IF(BRIEFING!$C$18="Premium",1.5,1)))) | S19: =IF(BRIEFING!$C$19="Sem",0.85,IF(BRIEFING!$C$19="Básico",1.0,IF(BRIEFING!$C$19="Completo",1.25,IF(BRIEFING!$C$19="Decorado",1.5,1)))) | T19: =1 | U19: =IF(BRIEFING!$C$21="Interior SC",0.95,IF(BRIEFING!$C$21="Litoral SC",1.0,IF(BRIEFING!$C$21="Capital Floripa",1.05,IF(BRIEFING!$C$21="Litoral SP",1.15,IF(BRIEFING!$C$21="Capital SP-RJ",1.25,1))))) | V19: =1 | W19: =1 | X19: =1 | Y19: =1 | Z19: =1 | AA19: =PRODUCT(B19:Z19)
A20: Imprevistos | B20: =1 | C20: =1 | D20: =1 | E20: =1 | F20: =1 | G20: =1 | H20: =1 | I20: =1 | ... T20: =1 | U20: =IF(BRIEFING!$C$21="Interior SC",0.95,IF(BRIEFING!$C$21="Litoral SC",1.0,IF(BRIEFING!$C$21="Capital Floripa",1.05,IF(BRIEFING!$C$21="Litoral SP",1.15,IF(BRIEFING!$C$21="Capital SP-RJ",1.25,1))))) | V20: =1 | W20: =1 | X20: =1 | Y20: =1 | Z20: =1 | AA20: =PRODUCT(B20:Z20)

Sheet CUSTOS_MACROGRUPO
A1: # | B1: Macrogrupo | C1: Base R$/m² | D1: Fator CUB | E1: Fator Briefing | F1: R$/m² Ajustado | G1: Valor Total | H1: % | I1: Faixa Min | J1: Faixa Max | K1: Status
A2: 1 | B2: Gerenciamento | C2: 408.31 | D2: =DADOS_PROJETO!$B$19/DADOS_PROJETO!$B$20 | E2: =FATORES!$AA$3 | F2: =C2*D2*E2 | G2: =F2*DADOS_PROJETO!$B$6 | H2: =G2/SUM($G$2:$G$19) | I2: 200 | J2: 550 | K2: =IF(AND(F2>=I2,F2<=J2),"✓",IF(OR(F2<I2*0.8,F2>J2*1.2),"✗","⚠"))
A3: 2 | B3: Mov. Terra | C3: 12.4 | D3: =DADOS_PROJETO!$B$19/DADOS_PROJETO!$B$20 | E3: =FATORES!$AA$4 | F3: =C3*D3*E3 | G3: =F3*DADOS_PROJETO!$B$6 | H3: =G3/SUM($G$2:$G$19) | I3: 7 | J3: 60 | K3: =IF(AND(F3>=I3,F3<=J3),"✓",IF(OR(F3<I3*0.8,F3>J3*1.2),"✗","⚠"))
A4: 3 | B4: Infraestrutura | C4: 227.95 | D4: =DADOS_PROJETO!$B$19/DADOS_PROJETO!$B$20 | E4: =FATORES!$AA$5 | F4: =C4*D4*E4 | G4: =F4*DADOS_PROJETO!$B$6 | H4: =G4/SUM($G$2:$G$19) | I4: 120 | J4: 280 | K4: =IF(AND(F4>=I4,F4<=J4),"✓",IF(OR(F4<I4*0.8,F4>J4*1.2),"✗","⚠"))
A5: 4 | B5: Supraestrutura | C5: 726.18 | D5: =DADOS_PROJETO!$B$19/DADOS_PROJETO!$B$20 | E5: =FATORES!$AA$6 | F5: =C5*D5*E5 | G5: =F5*DADOS_PROJETO!$B$6 | H5: =G5/SUM($G$2:$G$19) | I5: 450 | J5: 950 | K5: =IF(AND(F5>=I5,F5<=J5),"✓",IF(OR(F5<I5*0.8,F5>J5*1.2),"✗","⚠"))
A6: 5 | B6: Alvenaria | C6: 147.73 | D6: =DADOS_PROJETO!$B$19/DADOS_PROJETO!$B$20 | E6: =FATORES!$AA$7 | F6: =C6*D6*E6 | G6: =F6*DADOS_PROJETO!$B$6 | H6: =G6/SUM($G$2:$G$19) | I6: 60 | J6: 300 | K6: =IF(AND(F6>=I6,F6<=J6),"✓",IF(OR(F6<I6*0.8,F6>J6*1.2),"✗","⚠"))
A7: 6 | B7: Impermeabilização | C7: 50 | D7: =DADOS_PROJETO!$B$19/DADOS_PROJETO!$B$20 | E7: =FATORES!$AA$8 | F7: =C7*D7*E7 | G7: =F7*DADOS_PROJETO!$B$6 | H7: =G7/SUM($G$2:$G$19) | I7: 36 | J7: 86 | K7: =IF(AND(F7>=I7,F7<=J7),"✓",IF(OR(F7<I7*0.8,F7>J7*1.2),"✗","⚠"))
A8: 7 | B8: Instalações | C8: 365.64 | D8: =DADOS_PROJETO!$B$19/DADOS_PROJETO!$B$20 | E8: =FATORES!$AA$9 | F8: =C8*D8*E8 | G8: =F8*DADOS_PROJETO!$B$6 | H8: =G8/SUM($G$2:$G$19) | I8: 315 | J8: 500 | K8: =IF(AND(F8>=I8,F8<=J8),"✓",IF(OR(F8<I8*0.8,F8>J8*1.2),"✗","⚠"))
A9: 8 | B9: Sist. Especiais | C9: 190.04 | D9: =DADOS_PROJETO!$B$19/DADOS_PROJETO!$B$20 | E9: =FATORES!$AA$10 | F9: =C9*D9*E9 | G9: =F9*DADOS_PROJETO!$B$6 | H9: =G9/SUM($G$2:$G$19) | I9: 100 | J9: 400 | K9: =IF(AND(F9>=I9,F9<=J9),"✓",IF(OR(F9<I9*0.8,F9>J9*1.2),"✗","⚠"))
A10: 9 | B10: Climatização | C10: 0 | D10: =DADOS_PROJETO!$B$19/DADOS_PROJETO!$B$20 | E10: =FATORES!$AA$11 | F10: =C10*D10*E10 | G10: =F10*DADOS_PROJETO!$B$6 | H10: =G10/SUM($G$2:$G$19) | I10: 0 | J10: 80 | K10: =IF(AND(F10>=I10,F10<=J10),"✓",IF(OR(F10<I10*0.8,F10>J10*1.2),"✗","⚠"))
A11: 10 | B11: Rev. Int. Parede | C11: 169.75 | D11: =DADOS_PROJETO!$B$19/DADOS_PROJETO!$B$20 | E11: =FATORES!$AA$12 | F11: =C11*D11*E11 | G11: =F11*DADOS_PROJETO!$B$6 | H11: =G11/SUM($G$2:$G$19) | I11: 100 | J11: 240 | K11: =IF(AND(F11>=I11,F11<=J11),"✓",IF(OR(F11<I11*0.8,F11>J11*1.2),"✗","⚠"))
A12: 11 | B12: Teto | C12: 67.43 | D12: =DADOS_PROJETO!$B$19/DADOS_PROJETO!$B$20 | E12: =FATORES!$AA$13 | F12: =C12*D12*E12 | G12: =F12*DADOS_PROJETO!$B$6 | H12: =G12/SUM($G$2:$G$19) | I12: 45 | J12: 140 | K12: =IF(AND(F12>=I12,F12<=J12),"✓",IF(OR(F12<I12*0.8,F12>J12*1.2),"✗","⚠"))
A13: 12 | B13: Pisos | C13: 189.36 | D13: =DADOS_PROJETO!$B$19/DADOS_PROJETO!$B$20 | E13: =FATORES!$AA$14 | F13: =C13*D13*E13 | G13: =F13*DADOS_PROJETO!$B$6 | H13: =G13/SUM($G$2:$G$19) | I13: 125 | J13: 350 | K13: =IF(AND(F13>=I13,F13<=J13),"✓",IF(OR(F13<I13*0.8,F13>J13*1.2),"✗","⚠"))
A14: 13 | B14: Pintura | C14: 131.49 | D14: =DADOS_PROJETO!$B$19/DADOS_PROJETO!$B$20 | E14: =FATORES!$AA$15 | F14: =C14*D14*E14 | G14: =F14*DADOS_PROJETO!$B$6 | H14: =G14/SUM($G$2:$G$19) | I14: 96 | J14: 200 | K14: =IF(AND(F14>=I14,F14<=J14),"✓",IF(OR(F14<I14*0.8,F14>J14*1.2),"✗","⚠"))
A15: 14 | B15: Esquadrias | C15: 366.05 | D15: =DADOS_PROJETO!$B$19/DADOS_PROJETO!$B$20 | E15: =FATORES!$AA$16 | F15: =C15*D15*E15 | G15: =F15*DADOS_PROJETO!$B$6 | H15: =G15/SUM($G$2:$G$19) | I15: 200 | J15: 700 | K15: =IF(AND(F15>=I15,F15<=J15),"✓",IF(OR(F15<I15*0.8,F15>J15*1.2),"✗","⚠"))
A16: 15 | B16: Louças e Metais | C16: 0 | D16: =DADOS_PROJETO!$B$19/DADOS_PROJETO!$B$20 | E16: =FATORES!$AA$17 | F16: =C16*D16*E16 | G16: =F16*DADOS_PROJETO!$B$6 | H16: =G16/SUM($G$2:$G$19) | I16: 30 | J16: 120 | K16: =IF(AND(F16>=I16,F16<=J16),"✓",IF(OR(F16<I16*0.8,F16>J16*1.2),"✗","⚠"))
A17: 16 | B17: Fachada | C17: 164.53 | D17: =DADOS_PROJETO!$B$19/DADOS_PROJETO!$B$20 | E17: =FATORES!$AA$18 | F17: =C17*D17*E17 | G17: =F17*DADOS_PROJETO!$B$6 | H17: =G17/SUM($G$2:$G$19) | I17: 55 | J17: 275 | K17: =IF(AND(F17>=I17,F17<=J17),"✓",IF(OR(F17<I17*0.8,F17>J17*1.2),"✗","⚠"))
A18: 17 | B18: Complementares | C18: 183.4 | D18: =DADOS_PROJETO!$B$19/DADOS_PROJETO!$B$20 | E18: =FATORES!$AA$19 | F18: =C18*D18*E18 | G18: =F18*DADOS_PROJETO!$B$6 | H18: =G18/SUM($G$2:$G$19) | I18: 100 | J18: 500 | K18: =IF(AND(F18>=I18,F18<=J18),"✓",IF(OR(F18<I18*0.8,F18>J18*1.2),"✗","⚠"))
A19: 18 | B19: Imprevistos | C19: 96.27 | D19: =DADOS_PROJETO!$B$19/DADOS_PROJETO!$B$20 | E19: =FATORES!$AA$20 | F19: =C19*D19*E19 | G19: =F19*DADOS_PROJETO!$B$6 | H19: =G19/SUM($G$2:$G$19) | I19: 35 | J19: 120 | K19: =IF(AND(F19>=I19,F19<=J19),"✓",IF(OR(F19<I19*0.8,F19>J19*1.2),"✗","⚠"))
B20: TOTAL | G20: =SUM(G2:G19) | H20: 100.0%

Sheet ÍNDICES
A1: ÍNDICES DE REFERÊNCIA
A3: A. ÍNDICES ESTRUTURAIS POR TIPO DE LAJE
A4: Parâmetro | B4: Cubetas | C4: Protendida | D4: Maciça | E4: Treliçada
A5: Concreto (m³/m² AC) | B5: 0.22 | C5: 0.2 | D5: 0.25 | E5: 0.19
A6: Aço (kg/m³) | B6: 90 | C6: 110 | D6: 85 | E6: 80
A7: Forma (m²/m³) | B7: 10 | C7: 9 | D7: 11 | E7: 12
A10: B. ÍNDICES DE ACABAMENTOS
A11: Item | B11: Índice (m²/m² AC) | C11: Referência
A12: Chapisco interno | B12: 1.8 | C12: Área de parede interna
A13: Reboco interno | B13: 1.8 | C13: Idem
A14: Estucamento | B14: 1.5 | C14: Área pintável
A15: Cerâmico parede | B15: 0.3 | C15: BWCs + cozinhas
A16: Porcelanato parede | B16: 0.15 | C16: BWCs padrão alto
A17: Contrapiso | B17: 0.85 | C17: Áreas internas
A18: Porcelanato piso | B18: 0.55 | C18: Áreas secas
A19: Cerâmico piso | B19: 0.15 | C19: BWCs + A. serviço
A20: Rodapé | B20: 0.4 | C20: m/m² AC
A21: Forro gesso | B21: 0.7 | C21: Área de teto
A22: Pintura interna | B22: 2.2 | C22: Paredes + teto
A23: Textura externa | B23: 0.45 | C23: Fachada
... A25: Reboco externo | B25: 0.45 | C25: Fachada
A28: C. ÍNDICES DE INSTALAÇÕES
A29: Disciplina | B29: R$/m² típico | C29: % do grupo
A30: Hidrossanitárias | B30: 120 | C30: 0.33
A31: Elétricas | B31: 110 | C31: 0.3
A32: Preventivas | B32: 60 | C32: 0.16
A33: Gás | B33: 35 | C33: 0.1
A34: Telecom | B34: 40 | C34: 0.11
A37: D. VERBAS PARAMÉTRICAS
A38: Item | B38: R$/m² | C38: Observação
A39: Elevadores | B39: 50-80 | C39: Por elevador: R$ 250-400k
A40: Gerador | B40: 15-25 | C40: Prédio alto
A41: Pressurização | B41: 10-18 | C41: Se aplicável
A42: Automação básica | B42: 8-15 | C42: CFTV + interfone

Sheet ESTRUTURAL
A1: DETALHAMENTO ESTRUTURAL — Nível Executivo
A2: Projeto: Residencial Alípio Schirmann — AC: 12,033.95 m²
A4: Item / Serviço | B4: Qtd | C4: Un | D4: Índice | E4: PU Material | F4: PU Mão de Obra | G4: Total Material | H4: Total Mão de Obra | I4: Total
A5: 1. FUNDAÇÕES
A6: Mobilização/desmobilização hélice contínua | B6: 1 | C6: vb | D6: — | E6: =IF(B6>0,G6/B6,0) | F6: =IF(B6>0,H6/B6,0) | G6: =I6*0.2 | H6: =I6*0.80 | I6: =CUSTOS_MACROGRUPO!$G$4*0.65*0.04
A7: Estaca hélice contínua ø40cm — L=14m | B7: =0.22*DADOS_PROJETO!$B$6 | C7: m | D7: 0.22 | E7: =IF(B7>0,G7/B7,0) | F7: =IF(B7>0,H7/B7,0) | G7: =I7*0.55 | H7: =I7*0.45 | I7: =CUSTOS_MACROGRUPO!$G$4*0.65*0.18
A8: Estaca hélice contínua ø50cm — L=16m | B8: =0.3*DADOS_PROJETO!$B$6 | C8: m | D8: 0.3 | E8: =IF(B8>0,G8/B8,0) | F8: =IF(B8>0,H8/B8,0) | G8: =I8*0.55 | H8: =I8*0.45 | I8: =CUSTOS_MACROGRUPO!$G$4*0.65*0.25
A9: Estaca hélice contínua ø60cm — L=18m | B9: =0.12*DADOS_PROJETO!$B$6 | C9: m | D9: 0.12 | E9: =IF(B9>0,G9/B9,0) | F9: =IF(B9>0,H9/B9,0) | G9: =I9*0.55 | H9: =I9*0.45 | I9: =CUSTOS_MACROGRUPO!$G$4*0.65*0.13
A10: Blocos de coroamento (concreto fck 30 MPa) | B10: =0.018*DADOS_PROJETO!$B$6 | C10: m³ | D10: 0.018 | E10: =IF(B10>0,G10/B10,0) | F10: =IF(B10>0,H10/B10,0) | G10: =I10*0.55 | H10: =I10*0.45 | I10: =CUSTOS_MACROGRUPO!$G$4*0.65*0.1
A11: Vigas baldrame (concreto fck 30 MPa) | B11: =0.012*DADOS_PROJETO!$B$6 | C11: m³ | D11: 0.012 | E11: =IF(B11>0,G11/B11,0) | F11: =IF(B11>0,H11/B11,0) | G11: =I11*0.55 | H11: =I11*0.45 | I11: =CUSTOS_MACROGRUPO!$G$4*0.65*0.08
A12: Armação blocos e baldrame (CA-50) | B12: =1.8*DADOS_PROJETO!$B$6 | C12: kg | D12: 1.8 | E12: =IF(B12>0,G12/B12,0) | F12: =IF(B12>0,H12/B12,0) | G12: =I12*0.7 | H12: =I12*0.30 | I12: =CUSTOS_MACROGRUPO!$G$4*0.65*0.08
A13: Forma blocos e baldrame (compensado) | B13: =0.12*DADOS_PROJETO!$B$6 | C13: m² | D13: 0.12 | E13: =IF(B13>0,G13/B13,0) | F13: =IF(B13>0,H13/B13,0) | G13: =I13*0.6 | H13: =I13*0.40 | I13: =CUSTOS_MACROGRUPO!$G$4*0.65*0.05
A14: Impermeabilização fundação | B14: =0.08*DADOS_PROJETO!$B$6 | C14: m² | D14: 0.08 | E14: =IF(B14>0,G14/B14,0) | F14: =IF(B14>0,H14/B14,0) | G14: =I14*0.65 | H14: =I14*0.35 | I14: =CUSTOS_MACROGRUPO!$G$4*0.65*0.03
A15: Escavação mecânica | B15: =0.05*DADOS_PROJETO!$B$6 | C15: m³ | D15: 0.05 | E15: =IF(B15>0,G15/B15,0) | F15: =IF(B15>0,H15/B15,0) | G15: =I15*0.3 | H15: =I15*0.70 | I15: =CUSTOS_MACROGRUPO!$G$4*0.65*0.03
A16: Reaterro compactado | B16: =0.03*DADOS_PROJETO!$B$6 | C16: m³ | D16: 0.03 | E16: =IF(B16>0,G16/B16,0) | F16: =IF(B16>0,H16/B16,0) | G16: =I16*0.4 | H16: =I16*0.60 | I16: =CUSTOS_MACROGRUPO!$G$4*0.65*0.02
A17: Lastro de brita e=5cm | B17: =0.005*DADOS_PROJETO!$B$6 | C17: m³ | D17: 0.005 | E17: =IF(B17>0,G17/B17,0) | F17: =IF(B17>0,H17/B17,0) | G17: =I17*0.8 | H17: =I17*0.20 | I17: =CUSTOS_MACROGRUPO!$G$4*0.65*0.01
A18: Subtotal 1. FUNDAÇÕES | G18: =SUM(G6:G17) | H18: =SUM(H6:H17) | I18: =SUM(I6:I17)
A20: 2. CONTENÇÕES
A21: Cortina de estacas / Perfil metálico | B21: =0.03*DADOS_PROJETO!$B$6 | C21: m² | D21: 0.03 | E21: =IF(B21>0,G21/B21,0) | F21: =IF(B21>0,H21/B21,0) | G21: =I21*0.6 | H21: =I21*0.40 | I21: =CUSTOS_MACROGRUPO!$G$4*0.35*0.35
A22: Tirantes protendidos | B22: =12 | C22: un | D22: 12 | E22: =IF(B22>0,G22/B22,0) | F22: =IF(B22>0,H22/B22,0) | G22: =I22*0.55 | H22: =I22*0.45 | I22: =CUSTOS_MACROGRUPO!$G$4*0.35*0.25
A23: Muro de arrimo concreto armado | B23: =0.008*DADOS_PROJETO!$B$6 | C23: m³ | D23: 0.008 | E23: =IF(B23>0,G23/B23,0) | F23: =IF(B23>0,H23/B23,0) | G23: =I23*0.55 | H23: =I23*0.45 | I23: =CUSTOS_MACROGRUPO!$G$4*0.35*0.15
A24: Drenagem subsuperficial (dreno) | B24: =0.02*DADOS_PROJETO!$B$6 | C24: m | D24: 0.02 | E24: =IF(B24>0,G24/B24,0) | F24: =IF(B24>0,H24/B24,0) | G24: =I24*0.65 | H24: =I24*0.35 | I24: =CUSTOS_MACROGRUPO!$G$4*0.35*0.08
A25: Chumbadores / grampos | B25: =20 | C25: un | D25: 20 | E25: =IF(B25>0,G25/B25,0) | F25: =IF(B25>0,H25/B25,0) | G25: =I25*0.6 | H25: =I25*0.40 | I25: =CUSTOS_MACROGRUPO!$G$4*0.35*0.07
A26: Concreto projetado (se aplicável) | B26: =0.005*DADOS_PROJETO!$B$6 | C26: m² | D26: 0.005 | E26: =IF(B26>0,G26/B26,0) | F26: =IF(B26>0,H26/B26,0) | G26: =I26*0.5 | H26: =I26*0.50 | I26: =CUSTOS_MACROGRUPO!$G$4*0.35*0.05
A27: Monitoramento geotécnico (inclinômetros) | B27: 1 | C27: vb | D27: — | E27: =IF(B27>0,G27/B27,0) | F27: =IF(B27>0,H27/B27,0) | G27: =I27*0.15 | H27: =I27*0.85 | I27: =CUSTOS_MACROGRUPO!$G$4*0.35*0.05
A28: Subtotal 2. CONTENÇÕES | G28: =SUM(G21:G27) | H28: =SUM(H21:H27) | I28: =SUM(I21:I27)
A30: 3. SUPRAESTRUTURA — CONCRETO
A31: Concreto fck 35 MPa — Pilares | B31: =0.047*DADOS_PROJETO!$B$6 | C31: m³ | D31: 0.047 | E31: =IF(B31>0,G31/B31,0) | F31: =IF(B31>0,H31/B31,0) | G31: =I31*0.6 | H31: =I31*0.40 | I31: =CUSTOS_MACROGRUPO!$G$5*0.42*0.24
A32: Concreto fck 30 MPa — Vigas | B32: =0.056*DADOS_PROJETO!$B$6 | C32: m³ | D32: 0.056 | E32: =IF(B32>0,G32/B32,0) | F32: =IF(B32>0,H32/B32,0) | G32: =I32*0.6 | H32: =I32*0.40 | I32: =CUSTOS_MACROGRUPO!$G$5*0.42*0.28
A33: Concreto fck 30 MPa — Lajes nervuradas (cubetas) | B33: =0.065*DADOS_PROJETO!$B$6 | C33: m³ | D33: 0.065 | E33: =IF(B33>0,G33/B33,0) | F33: =IF(B33>0,H33/B33,0) | G33: =I33*0.6 | H33: =I33*0.40 | I33: =CUSTOS_MACROGRUPO!$G$5*0.42*0.3
A34: Concreto fck 25 MPa — Escadas | B34: =0.008*DADOS_PROJETO!$B$6 | C34: m³ | D34: 0.008 | E34: =IF(B34>0,G34/B34,0) | F34: =IF(B34>0,H34/B34,0) | G34: =I34*0.55 | H34: =I34*0.45 | I34: =CUSTOS_MACROGRUPO!$G$5*0.42*0.05
A35: Concreto fck 30 MPa — Reservatórios | B35: =0.004*DADOS_PROJETO!$B$6 | C35: m³ | D35: 0.004 | E35: =IF(B35>0,G35/B35,0) | F35: =IF(B35>0,H35/B35,0) | G35: =I35*0.55 | H35: =I35*0.45 | I35: =CUSTOS_MACROGRUPO!$G$5*0.42*0.04
A36: Concreto fck 25 MPa — Muros/Muretas | B36: =0.003*DADOS_PROJETO!$B$6 | C36: m³ | D36: 0.003 | E36: =IF(B36>0,G36/B36,0) | F36: =IF(B36>0,H36/B36,0) | G36: =I36*0.55 | H36: =I36*0.45 | I36: =CUSTOS_MACROGRUPO!$G$5*0.42*0.02
A37: Bombeamento concreto | B37: =0.189*DADOS_PROJETO!$B$6 | C37: m³ | D37: 0.189 | E37: =IF(B37>0,G37/B37,0) | F37: =IF(B37>0,H37/B37,0) | G37: =I37*0.15 | H37: =I37*0.85 | I37: =CUSTOS_MACROGRUPO!$G$5*0.42*0.04
A38: Lançamento e adensamento | B38: =0.189*DADOS_PROJETO!$B$6 | C38: m³ | D38: 0.189 | E38: =IF(B38>0,G38/B38,0) | F38: =IF(B38>0,H38/B38,0) | G38: =I38*0.1 | H38: =I38*0.90 | I38: =CUSTOS_MACROGRUPO!$G$5*0.42*0.03
A39: Subtotal 3. SUPRAESTRUTURA — CONCRETO | G39: =SUM(G31:G38) | H39: =SUM(H31:H38) | I39: =SUM(I31:I38)
A41: 4. SUPRAESTRUTURA — AÇO
A42: Aço CA-50 — Pilares (taxa ~95 kg/m³) | B42: =4.47*DADOS_PROJETO!$B$6 | C42: kg | D42: 4.47 | E42: =IF(B42>0,G42/B42,0) | F42: =IF(B42>0,H42/B42,0) | G42: =I42*0.72 | H42: =I42*0.28 | I42: =CUSTOS_MACROGRUPO!$G$5*0.28*0.28
A43: Aço CA-50 — Vigas (taxa ~90 kg/m³) | B43: =5.04*DADOS_PROJETO!$B$6 | C43: kg | D43: 5.04 | E43: =IF(B43>0,G43/B43,0) | F43: =IF(B43>0,H43/B43,0) | G43: =I43*0.72 | H43: =I43*0.28 | I43: =CUSTOS_MACROGRUPO!$G$5*0.28*0.3
A44: Aço CA-50 — Lajes (taxa ~88 kg/m³) | B44: =5.72*DADOS_PROJETO!$B$6 | C44: kg | D44: 5.72 | E44: =IF(B44>0,G44/B44,0) | F44: =IF(B44>0,H44/B44,0) | G44: =I44*0.72 | H44: =I44*0.28 | I44: =CUSTOS_MACROGRUPO!$G$5*0.28*0.27
A45: Aço CA-60 (estribos, armadura negativa) | B45: =1.2*DADOS_PROJETO!$B$6 | C45: kg | D45: 1.2 | E45: =IF(B45>0,G45/B45,0) | F45: =IF(B45>0,H45/B45,0) | G45: =I45*0.72 | H45: =I45*0.28 | I45: =CUSTOS_MACROGRUPO!$G$5*0.28*0.06
A46: Tela soldada Q-196/Q-283 | B46: =0.1*DADOS_PROJETO!$B$6 | C46: m² | D46: 0.1 | E46: =IF(B46>0,G46/B46,0) | F46: =IF(B46>0,H46/B46,0) | G46: =I46*0.75 | H46: =I46*0.25 | I46: =CUSTOS_MACROGRUPO!$G$5*0.28*0.04
A47: Espaçadores e acessórios | B47: 1 | C47: vb | D47: — | E47: =IF(B47>0,G47/B47,0) | F47: =IF(B47>0,H47/B47,0) | G47: =I47*0.85 | H47: =I47*0.15 | I47: =CUSTOS_MACROGRUPO!$G$5*0.28*0.02
A48: Corte, dobra e montagem (serviço) | B48: =16.43*DADOS_PROJETO!$B$6 | C48: kg | D48: 16.43 | E48: =IF(B48>0,G48/B48,0) | F48: =IF(B48>0,H48/B48,0) | G48: =I48*0.1 | H48: =I48*0.90 | I48: =CUSTOS_MACROGRUPO!$G$5*0.28*0.03
A49: Subtotal 4. SUPRAESTRUTURA — AÇO | G49: =SUM(G42:G48) | H49: =SUM(H42:H48) | I49: =SUM(I42:I48)
A51: 5. SUPRAESTRUTURA — FORMAS
A52: Forma pilares (compensado plastificado) | B52: =0.35*DADOS_PROJETO!$B$6 | C52: m² | D52: 0.35 | E52: =IF(B52>0,G52/B52,0) | F52: =IF(B52>0,H52/B52,0) | G52: =I52*0.58 | H52: =I52*0.42 | I52: =CUSTOS_MACROGRUPO!$G$5*0.22*0.26
A53: Forma vigas (compensado plastificado) | B53: =0.4*DADOS_PROJETO!$B$6 | C53: m² | D53: 0.4 | E53: =IF(B53>0,G53/B53,0) | F53: =IF(B53>0,H53/B53,0) | G53: =I53*0.58 | H53: =I53*0.42 | I53: =CUSTOS_MACROGRUPO!$G$5*0.22*0.28
A54: Forma lajes (assoalho + longarinas) | B54: =0.45*DADOS_PROJETO!$B$6 | C54: m² | D54: 0.45 | E54: =IF(B54>0,G54/B54,0) | F54: =IF(B54>0,H54/B54,0) | G54: =I54*0.58 | H54: =I54*0.42 | I54: =CUSTOS_MACROGRUPO!$G$5*0.22*0.25
A55: Forma escadas | B55: =0.04*DADOS_PROJETO!$B$6 | C55: m² | D55: 0.04 | E55: =IF(B55>0,G55/B55,0) | F55: =IF(B55>0,H55/B55,0) | G55: =I55*0.55 | H55: =I55*0.45 | I55: =CUSTOS_MACROGRUPO!$G$5*0.22*0.05
A56: Escoramento metálico (locação) | B56: =0.8*DADOS_PROJETO!$B$6 | C56: m² | D56: 0.8 | E56: =IF(B56>0,G56/B56,0) | F56: =IF(B56>0,H56/B56,0) | G56: =I56*0.9 | H56: =I56*0.10 | I56: =CUSTOS_MACROGRUPO!$G$5*0.22*0.1
A57: Desmoldante e acessórios | B57: 1 | C57: vb | D57: — | E57: =IF(B57>0,G57/B57,0) | F57: =IF(B57>0,H57/B57,0) | G57: =I57*0.85 | H57: =I57*0.15 | I57: =CUSTOS_MACROGRUPO!$G$5*0.22*0.03
A58: Cimbramento especial (se aplicável) | B58: =0.02*DADOS_PROJETO!$B$6 | C58: m² | D58: 0.02 | E58: =IF(B58>0,G58/B58,0) | F58: =IF(B58>0,H58/B58,0) | G58: =I58*0.5 | H58: =I58*0.50 | I58: =CUSTOS_MACROGRUPO!$G$5*0.22*0.03
A59: Subtotal 5. SUPRAESTRUTURA — FORMAS | G59: =SUM(G52:G58) | H59: =SUM(H52:H58) | I59: =SUM(I52:I58)
A61: 6. LAJE NERVURADA — CUBETAS
A62: Cubetas plásticas (locação) | B62: =0.55*DADOS_PROJETO!$B$6 | C62: m² | D62: 0.55 | E62: =IF(B62>0,G62/B62,0) | F62: =IF(B62>0,H62/B62,0) | G62: =I62*0.9 | H62: =I62*0.10 | I62: =CUSTOS_MACROGRUPO!$G$5*0.08*0.6
A63: Faixas maciças (concreto adicional) | B63: =0.005*DADOS_PROJETO!$B$6 | C63: m³ | D63: 0.005 | E63: =IF(B63>0,G63/B63,0) | F63: =IF(B63>0,H63/B63,0) | G63: =I63*0.55 | H63: =I63*0.45 | I63: =CUSTOS_MACROGRUPO!$G$5*0.08*0.15
A64: Armadura complementar nervuras | B64: =0.5*DADOS_PROJETO!$B$6 | C64: kg | D64: 0.5 | E64: =IF(B64>0,G64/B64,0) | F64: =IF(B64>0,H64/B64,0) | G64: =I64*0.72 | H64: =I64*0.28 | I64: =CUSTOS_MACROGRUPO!$G$5*0.08*0.15
A65: Capitéis (reforço em pilares) | B65: =0.003*DADOS_PROJETO!$B$6 | C65: m³ | D65: 0.003 | E65: =IF(B65>0,G65/B65,0) | F65: =IF(B65>0,H65/B65,0) | G65: =I65*0.55 | H65: =I65*0.45 | I65: =CUSTOS_MACROGRUPO!$G$5*0.08*0.1
A66: Subtotal 6. LAJE NERVURADA — CUBETAS | G66: =SUM(G62:G65) | H66: =SUM(H62:H65) | I66: =SUM(I62:I65)
A68: 7. ALVENARIA E VEDAÇÕES
A69: Alvenaria bloco cerâmico 14cm — Paredes externas | B69: =0.55*DADOS_PROJETO!$B$6 | C69: m² | D69: 0.55 | E69: =IF(B69>0,G69/B69,0) | F69: =IF(B69>0,H69/B69,0) | G69: =I69*0.52 | H69: =I69*0.48 | I69: =CUSTOS_MACROGRUPO!$G$6*1.0*0.22
A70: Alvenaria bloco cerâmico 19cm — Paredes estruturais | B70: =0.2*DADOS_PROJETO!$B$6 | C70: m² | D70: 0.2 | E70: =IF(B70>0,G70/B70,0) | F70: =IF(B70>0,H70/B70,0) | G70: =I70*0.52 | H70: =I70*0.48 | I70: =CUSTOS_MACROGRUPO!$G$6*1.0*0.12
A71: Alvenaria bloco cerâmico 9cm — Paredes internas | B71: =0.65*DADOS_PROJETO!$B$6 | C71: m² | D71: 0.65 | E71: =IF(B71>0,G71/B71,0) | F71: =IF(B71>0,H71/B71,0) | G71: =I71*0.52 | H71: =I71*0.48 | I71: =CUSTOS_MACROGRUPO!$G$6*1.0*0.2
A72: Alvenaria bloco concreto (garagem/técnicos) | B72: =0.15*DADOS_PROJETO!$B$6 | C72: m² | D72: 0.15 | E72: =IF(B72>0,G72/B72,0) | F72: =IF(B72>0,H72/B72,0) | G72: =I72*0.55 | H72: =I72*0.45 | I72: =CUSTOS_MACROGRUPO!$G$6*1.0*0.08
A73: Vergas e contravergas pré-moldadas | B73: =0.3*DADOS_PROJETO!$B$6 | C73: m | D73: 0.3 | E73: =IF(B73>0,G73/B73,0) | F73: =IF(B73>0,H73/B73,0) | G73: =I73*0.6 | H73: =I73*0.40 | I73: =CUSTOS_MACROGRUPO!$G$6*1.0*0.08
A74: Encunhamento (espuma expansiva) | B74: =0.25*DADOS_PROJETO!$B$6 | C74: m | D74: 0.25 | E74: =IF(B74>0,G74/B74,0) | F74: =IF(B74>0,H74/B74,0) | G74: =I74*0.45 | H74: =I74*0.55 | I74: =CUSTOS_MACROGRUPO!$G$6*1.0*0.05
A75: Chapisco interno (argamassa industrializada) | B75: =1.4*DADOS_PROJETO!$B$6 | C75: m² | D75: 1.4 | E75: =IF(B75>0,G75/B75,0) | F75: =IF(B75>0,H75/B75,0) | G75: =I75*0.55 | H75: =I75*0.45 | I75: =CUSTOS_MACROGRUPO!$G$6*1.0*0.08
A76: Chapisco externo (argamassa industrializada) | B76: =0.45*DADOS_PROJETO!$B$6 | C76: m² | D76: 0.45 | E76: =IF(B76>0,G76/B76,0) | F76: =IF(B76>0,H76/B76,0) | G76: =I76*0.55 | H76: =I76*0.45 | I76: =CUSTOS_MACROGRUPO!$G$6*1.0*0.04
A77: Tela de reforço (encontro alv/estrutura) | B77: =0.2*DADOS_PROJETO!$B$6 | C77: m² | D77: 0.2 | E77: =IF(B77>0,G77/B77,0) | F77: =IF(B77>0,H77/B77,0) | G77: =I77*0.7 | H77: =I77*0.30 | I77: =CUSTOS_MACROGRUPO!$G$6*1.0*0.04
A78: Passagens de tubulações (shafts/rasgos) | B78: 1 | C78: vb | D78: — | E78: =IF(B78>0,G78/B78,0) | F78: =IF(B78>0,H78/B78,0) | G78: =I78*0.3 | H78: =I78*0.70 | I78: =CUSTOS_MACROGRUPO!$G$6*1.0*0.03
A79: Graute para grauteamento de vergas | B79: =0.002*DADOS_PROJETO!$B$6 | C79: m³ | D79: 0.002 | E79: =IF(B79>0,G79/B79,0) | F79: =IF(B79>0,H79/B79,0) | G79: =I79*0.6 | H79: =I79*0.40 | I79: =CUSTOS_MACROGRUPO!$G$6*1.0*0.03
A80: Argamassa de assentamento | B80: =0.015*DADOS_PROJETO!$B$6 | C80: m³ | D80: 0.015 | E80: =IF(B80>0,G80/B80,0) | F80: =IF(B80>0,H80/B80,0) | G80: =I80*0.65 | H80: =I80*0.35 | I80: =CUSTOS_MACROGRUPO!$G$6*1.0*0.03
A81: Subtotal 7. ALVENARIA E VEDAÇÕES | G81: =SUM(G69:G80) | H81: =SUM(H69:H80) | I81: =SUM(I69:I80)
A83: 8. IMPERMEABILIZAÇÃO
A84: Impermeabilização manta asfáltica — Laje cobertura | B84: =0.06*DADOS_PROJETO!$B$6 | C84: m² | D84: 0.06 | E84: =IF(B84>0,G84/B84,0) | F84: =IF(B84>0,H84/B84,0) | G84: =I84*0.58 | H84: =I84*0.42 | I84: =CUSTOS_MACROGRUPO!$G$7*1.0*0.22
A85: Impermeabilização argamassa polimérica — Áreas molhadas | B85: =0.12*DADOS_PROJETO!$B$6 | C85: m² | D85: 0.12 | E85: =IF(B85>0,G85/B85,0) | F85: =IF(B85>0,H85/B85,0) | G85: =I85*0.55 | H85: =I85*0.45 | I85: =CUSTOS_MACROGRUPO!$G$7*1.0*0.2
A86: Impermeabilização manta asfáltica — Sacadas/varandas | B86: =0.04*DADOS_PROJETO!$B$6 | C86: m² | D86: 0.04 | E86: =IF(B86>0,G86/B86,0) | F86: =IF(B86>0,H86/B86,0) | G86: =I86*0.58 | H86: =I86*0.42 | I86: =CUSTOS_MACROGRUPO!$G$7*1.0*0.12
A87: Impermeabilização reservatórios (inferior/superior) | B87: =0.008*DADOS_PROJETO!$B$6 | C87: m² | D87: 0.008 | E87: =IF(B87>0,G87/B87,0) | F87: =IF(B87>0,H87/B87,0) | G87: =I87*0.6 | H87: =I87*0.40 | I87: =CUSTOS_MACROGRUPO!$G$7*1.0*0.08
A88: Impermeabilização jardineiras/floreiras | B88: =0.01*DADOS_PROJETO!$B$6 | C88: m² | D88: 0.01 | E88: =IF(B88>0,G88/B88,0) | F88: =IF(B88>0,H88/B88,0) | G88: =I88*0.55 | H88: =I88*0.45 | I88: =CUSTOS_MACROGRUPO!$G$7*1.0*0.05
A89: Impermeabilização piscina (se aplicável) | B89: =0.003*DADOS_PROJETO!$B$6 | C89: m² | D89: 0.003 | E89: =IF(B89>0,G89/B89,0) | F89: =IF(B89>0,H89/B89,0) | G89: =I89*0.55 | H89: =I89*0.45 | I89: =CUSTOS_MACROGRUPO!$G$7*1.0*0.03
A90: Regularização para impermeabilização (contrapiso) | B90: =0.2*DADOS_PROJETO!$B$6 | C90: m² | D90: 0.2 | E90: =IF(B90>0,G90/B90,0) | F90: =IF(B90>0,H90/B90,0) | G90: =I90*0.5 | H90: =I90*0.50 | I90: =CUSTOS_MACROGRUPO!$G$7*1.0*0.12
A91: Proteção mecânica (argamassa sobre manta) | B91: =0.1*DADOS_PROJETO!$B$6 | C91: m² | D91: 0.1 | E91: =IF(B91>0,G91/B91,0) | F91: =IF(B91>0,H91/B91,0) | G91: =I91*0.55 | H91: =I91*0.45 | I91: =CUSTOS_MACROGRUPO!$G$7*1.0*0.08
A92: Tratamento de juntas de dilatação | B92: =0.01*DADOS_PROJETO!$B$6 | C92: m | D92: 0.01 | E92: =IF(B92>0,G92/B92,0) | F92: =IF(B92>0,H92/B92,0) | G92: =I92*0.6 | H92: =I92*0.40 | I92: =CUSTOS_MACROGRUPO!$G$7*1.0*0.04
A93: Drenos e ralos (cobertura/sacadas) | B93: =120 | C93: un | D93: 120 | E93: =IF(B93>0,G93/B93,0) | F93: =IF(B93>0,H93/B93,0) | G93: =I93*0.7 | H93: =I93*0.30 | I93: =CUSTOS_MACROGRUPO!$G$7*1.0*0.04
A94: Teste de estanqueidade (72h) | B94: 1 | C94: vb | D94: — | E94: =IF(B94>0,G94/B94,0) | F94: =IF(B94>0,H94/B94,0) | G94: =I94*0.1 | H94: =I94*0.90 | I94: =CUSTOS_MACROGRUPO!$G$7*1.0*0.02
A95: Subtotal 8. IMPERMEABILIZAÇÃO | G95: =SUM(G84:G94) | H95: =SUM(H84:H94) | I95: =SUM(I84:I94)
A97: TOTAL ESTRUTURAL (Infraestrutura + Supraestrutura + Alvenaria + Impermeabilização) | G97: =G18+G28+G39+G49+G59+G66+G81+G95 | H97: =H18+H28+H39+H49+H59+H66+H81+H95 | I97: =I18+I28+I39+I49+I59+I66+I81+I95

Sheet INSTALACOES
A1: DETALHAMENTO INSTALAÇÕES — Nível Executivo
A2: Projeto: Residencial Alípio Schirmann — AC: 12,033.95 m²
A4: Item / Serviço | B4: Qtd | C4: Un | D4: Índice | E4: PU Material | F4: PU Mão de Obra | G4: Total Material | H4: Total Mão de Obra | I4: Total
A5: 1. INSTALAÇÕES HIDRÁULICAS
A6: Tubulação água fria PVC soldável (ø20 a ø60) | B6: =2.0*DADOS_PROJETO!$B$6 | C6: m | D6: 2 | E6: =IF(B6>0,G6/B6,0) | F6: =IF(B6>0,H6/B6,0) | G6: =I6*0.5 | H6: =I6*0.50 | I6: =CUSTOS_MACROGRUPO!$G$8*0.33*0.12
A7: Tubulação água quente PPR (ø20 a ø32) | B7: =0.8*DADOS_PROJETO!$B$6 | C7: m | D7: 0.8 | E7: =IF(B7>0,G7/B7,0) | F7: =IF(B7>0,H7/B7,0) | G7: =I7*0.55 | H7: =I7*0.45 | I7: =CUSTOS_MACROGRUPO!$G$8*0.33*0.08
A8: Tubulação esgoto PVC (ø40 a ø150) | B8: =1.5*DADOS_PROJETO!$B$6 | C8: m | D8: 1.5 | E8: =IF(B8>0,G8/B8,0) | F8: =IF(B8>0,H8/B8,0) | G8: =I8*0.5 | H8: =I8*0.50 | I8: =CUSTOS_MACROGRUPO!$G$8*0.33*0.1
A9: Tubulação águas pluviais PVC (ø75 a ø150) | B9: =0.5*DADOS_PROJETO!$B$6 | C9: m | D9: 0.5 | E9: =IF(B9>0,G9/B9,0) | F9: =IF(B9>0,H9/B9,0) | G9: =I9*0.5 | H9: =I9*0.50 | I9: =CUSTOS_MACROGRUPO!$G$8*0.33*0.05
A10: Registros e válvulas (gaveta, pressão, esfera) | B10: =280 | C10: un | D10: 280 | E10: =IF(B10>0,G10/B10,0) | F10: =IF(B10>0,H10/B10,0) | G10: =I10*0.65 | H10: =I10*0.35 | I10: =CUSTOS_MACROGRUPO!$G$8*0.33*0.06
A11: Caixas sifonadas e ralos | B11: =240 | C11: un | D11: 240 | E11: =IF(B11>0,G11/B11,0) | F11: =IF(B11>0,H11/B11,0) | G11: =I11*0.6 | H11: =I11*0.40 | I11: =CUSTOS_MACROGRUPO!$G$8*0.33*0.04
A12: Caixas de inspeção / gordura | B12: =30 | C12: un | D12: 30 | E12: =IF(B12>0,G12/B12,0) | F12: =IF(B12>0,H12/B12,0) | G12: =I12*0.55 | H12: =I12*0.45 | I12: =CUSTOS_MACROGRUPO!$G$8*0.33*0.03
A13: Reservatório superior (fibra/concreto) | B13: =2 | C13: un | D13: 2 | E13: =IF(B13>0,G13/B13,0) | F13: =IF(B13>0,H13/B13,0) | G13: =I13*0.7 | H13: =I13*0.30 | I13: =CUSTOS_MACROGRUPO!$G$8*0.33*0.06
A14: Reservatório inferior | B14: =1 | C14: un | D14: 1 | E14: =IF(B14>0,G14/B14,0) | F14: =IF(B14>0,H14/B14,0) | G14: =I14*0.7 | H14: =I14*0.30 | I14: =CUSTOS_MACROGRUPO!$G$8*0.33*0.05
A15: Bombas de recalque (conjunto) | B15: =2 | C15: cj | D15: 2 | E15: =IF(B15>0,G15/B15,0) | F15: =IF(B15>0,H15/B15,0) | G15: =I15*0.75 | H15: =I15*0.25 | I15: =CUSTOS_MACROGRUPO!$G$8*0.33*0.06
A16: Medição individualizada (hidrômetros) | B16: =43 | C16: un | D16: 43 | E16: =IF(B16>0,G16/B16,0) | F16: =IF(B16>0,H16/B16,0) | G16: =I16*0.7 | H16: =I16*0.30 | I16: =CUSTOS_MACROGRUPO!$G$8*0.33*0.08
A17: Aquecedores de passagem (infraestrutura) | B17: =43 | C17: un | D17: 43 | E17: =IF(B17>0,G17/B17,0) | F17: =IF(B17>0,H17/B17,0) | G17: =I17*0.6 | H17: =I17*0.40 | I17: =CUSTOS_MACROGRUPO!$G$8*0.33*0.05
A18: Conexões, abraçadeiras e suportes | B18: 1 | C18: vb | D18: — | E18: =IF(B18>0,G18/B18,0) | F18: =IF(B18>0,H18/B18,0) | G18: =I18*0.75 | H18: =I18*0.25 | I18: =CUSTOS_MACROGRUPO!$G$8*0.33*0.08
A19: Louças sanitárias — Bacias c/ caixa acoplada | B19: =86 | C19: un | D19: 86 | E19: =IF(B19>0,G19/B19,0) | F19: =IF(B19>0,H19/B19,0) | G19: =I19*0.85 | H19: =I19*0.15 | I19: =CUSTOS_MACROGRUPO!$G$8*0.33*0.06
A20: Louças — Lavatórios e cubas | B20: =86 | C20: un | D20: 86 | E20: =IF(B20>0,G20/B20,0) | F20: =IF(B20>0,H20/B20,0) | G20: =I20*0.85 | H20: =I20*0.15 | I20: =CUSTOS_MACROGRUPO!$G$8*0.33*0.04
A21: Metais — Torneiras e misturadores | B21: =172 | C21: un | D21: 172 | E21: =IF(B21>0,G21/B21,0) | F21: =IF(B21>0,H21/B21,0) | G21: =I21*0.9 | H21: =I21*0.10 | I21: =CUSTOS_MACROGRUPO!$G$8*0.33*0.04
A22: Subtotal 1. INSTALAÇÕES HIDRÁULICAS | G22: =SUM(G6:G21) | H22: =SUM(H6:H21) | I22: =SUM(I6:I21)
A24: 2. INSTALAÇÕES ELÉTRICAS
A25: Quadros de distribuição (QDC apartamentos) | B25: =43 | C25: un | D25: 43 | E25: =IF(B25>0,G25/B25,0) | F25: =IF(B25>0,H25/B25,0) | G25: =I25*0.65 | H25: =I25*0.35 | I25: =CUSTOS_MACROGRUPO!$G$8*0.3*0.06
A26: Quadro geral de baixa tensão (QGBT) | B26: =1 | C26: un | D26: 1 | E26: =IF(B26>0,G26/B26,0) | F26: =IF(B26>0,H26/B26,0) | G26: =I26*0.7 | H26: =I26*0.30 | I26: =CUSTOS_MACROGRUPO!$G$8*0.3*0.04
A27: Fiação e cabos (ø1.5 a ø16mm²) | B27: =12.0*DADOS_PROJETO!$B$6 | C27: m | D27: 12 | E27: =IF(B27>0,G27/B27,0) | F27: =IF(B27>0,H27/B27,0) | G27: =I27*0.55 | H27: =I27*0.45 | I27: =CUSTOS_MACROGRUPO!$G$8*0.3*0.14
A28: Eletrodutos corrugados + rígidos | B28: =8.0*DADOS_PROJETO!$B$6 | C28: m | D28: 8 | E28: =IF(B28>0,G28/B28,0) | F28: =IF(B28>0,H28/B28,0) | G28: =I28*0.5 | H28: =I28*0.50 | I28: =CUSTOS_MACROGRUPO!$G$8*0.3*0.1
A29: Tomadas 2P+T (10A e 20A) | B29: =800 | C29: un | D29: 800 | E29: =IF(B29>0,G29/B29,0) | F29: =IF(B29>0,H29/B29,0) | G29: =I29*0.6 | H29: =I29*0.40 | I29: =CUSTOS_MACROGRUPO!$G$8*0.3*0.08
A30: Interruptores (simples, paralelo, intermediário) | B30: =400 | C30: un | D30: 400 | E30: =IF(B30>0,G30/B30,0) | F30: =IF(B30>0,H30/B30,0) | G30: =I30*0.6 | H30: =I30*0.40 | I30: =CUSTOS_MACROGRUPO!$G$8*0.3*0.05
A31: Luminárias áreas comuns (LED) | B31: =180 | C31: un | D31: 180 | E31: =IF(B31>0,G31/B31,0) | F31: =IF(B31>0,H31/B31,0) | G31: =I31*0.75 | H31: =I31*0.25 | I31: =CUSTOS_MACROGRUPO!$G$8*0.3*0.06
A32: Subestação / entrada de energia | B32: 1 | C32: vb | D32: — | E32: =IF(B32>0,G32/B32,0) | F32: =IF(B32>0,H32/B32,0) | G32: =I32*0.7 | H32: =I32*0.30 | I32: =CUSTOS_MACROGRUPO!$G$8*0.3*0.08
A33: SPDA (para-raios) | B33: 1 | C33: vb | D33: — | E33: =IF(B33>0,G33/B33,0) | F33: =IF(B33>0,H33/B33,0) | G33: =I33*0.55 | H33: =I33*0.45 | I33: =CUSTOS_MACROGRUPO!$G$8*0.3*0.05
A34: Medição individualizada (energia) | B34: =43 | C34: un | D34: 43 | E34: =IF(B34>0,G34/B34,0) | F34: =IF(B34>0,H34/B34,0) | G34: =I34*0.7 | H34: =I34*0.30 | I34: =CUSTOS_MACROGRUPO!$G$8*0.3*0.07
A35: Caixas de passagem e derivação | B35: =350 | C35: un | D35: 350 | E35: =IF(B35>0,G35/B35,0) | F35: =IF(B35>0,H35/B35,0) | G35: =I35*0.55 | H35: =I35*0.45 | I35: =CUSTOS_MACROGRUPO!$G$8*0.3*0.04
A36: Disjuntores e DRs | B36: =250 | C36: un | D36: 250 | E36: =IF(B36>0,G36/B36,0) | F36: =IF(B36>0,H36/B36,0) | G36: =I36*0.8 | H36: =I36*0.20 | I36: =CUSTOS_MACROGRUPO!$G$8*0.3*0.05
A37: Aterramento e equalização | B37: 1 | C37: vb | D37: — | E37: =IF(B37>0,G37/B37,0) | F37: =IF(B37>0,H37/B37,0) | G37: =I37*0.55 | H37: =I37*0.45 | I37: =CUSTOS_MACROGRUPO!$G$8*0.3*0.04
A38: Infraestrutura para ar-condicionado | B38: =86 | C38: pt | D38: 86 | E38: =IF(B38>0,G38/B38,0) | F38: =IF(B38>0,H38/B38,0) | G38: =I38*0.5 | H38: =I38*0.50 | I38: =CUSTOS_MACROGRUPO!$G$8*0.3*0.06
A39: Prumadas elétricas (shafts) | B39: 1 | C39: vb | D39: — | E39: =IF(B39>0,G39/B39,0) | F39: =IF(B39>0,H39/B39,0) | G39: =I39*0.45 | H39: =I39*0.55 | I39: =CUSTOS_MACROGRUPO!$G$8*0.3*0.04
A40: Iluminação de emergência | B40: =60 | C40: un | D40: 60 | E40: =IF(B40>0,G40/B40,0) | F40: =IF(B40>0,H40/B40,0) | G40: =I40*0.7 | H40: =I40*0.30 | I40: =CUSTOS_MACROGRUPO!$G$8*0.3*0.04
A41: Subtotal 2. INSTALAÇÕES ELÉTRICAS | G41: =SUM(G25:G40) | H41: =SUM(H25:H40) | I41: =SUM(I25:I40)
A43: 3. PREVENÇÃO CONTRA INCÊNDIO
A44: Hidrantes completos (mangueira + abrigo) | B44: =26 | C44: un | D44: 26 | E44: =IF(B44>0,G44/B44,0) | F44: =IF(B44>0,H44/B44,0) | G44: =I44*0.65 | H44: =I44*0.35 | I44: =CUSTOS_MACROGRUPO!$G$8*0.16*0.18
A45: Extintores (ABC 6kg + CO2) | B45: =52 | C45: un | D45: 52 | E45: =IF(B45>0,G45/B45,0) | F45: =IF(B45>0,H45/B45,0) | G45: =I45*0.85 | H45: =I45*0.15 | I45: =CUSTOS_MACROGRUPO!$G$8*0.16*0.06
A46: Sprinklers (se aplicável) | B46: =0 | C46: un | D46: 0 | E46: =IF(B46>0,G46/B46,0) | F46: =IF(B46>0,H46/B46,0) | G46: =I46*0.7 | H46: =I46*0.30 | I46: =CUSTOS_MACROGRUPO!$G$8*0.16*0.0
A47: Central de alarme de incêndio | B47: =1 | C47: un | D47: 1 | E47: =IF(B47>0,G47/B47,0) | F47: =IF(B47>0,H47/B47,0) | G47: =I47*0.75 | H47: =I47*0.25 | I47: =CUSTOS_MACROGRUPO!$G$8*0.16*0.1
A48: Detectores de fumaça | B48: =120 | C48: un | D48: 120 | E48: =IF(B48>0,G48/B48,0) | F48: =IF(B48>0,H48/B48,0) | G48: =I48*0.7 | H48: =I48*0.30 | I48: =CUSTOS_MACROGRUPO!$G$8*0.16*0.1
A49: Acionadores manuais | B49: =26 | C49: un | D49: 26 | E49: =IF(B49>0,G49/B49,0) | F49: =IF(B49>0,H49/B49,0) | G49: =I49*0.65 | H49: =I49*0.35 | I49: =CUSTOS_MACROGRUPO!$G$8*0.16*0.05
A50: Sinalização de emergência (placas fotoluminescentes) | B50: =150 | C50: un | D50: 150 | E50: =IF(B50>0,G50/B50,0) | F50: =IF(B50>0,H50/B50,0) | G50: =I50*0.8 | H50: =I50*0.20 | I50: =CUSTOS_MACROGRUPO!$G$8*0.16*0.08
A51: Portas corta-fogo (P-90) | B51: =52 | C51: un | D51: 52 | E51: =IF(B51>0,G51/B51,0) | F51: =IF(B51>0,H51/B51,0) | G51: =I51*0.75 | H51: =I51*0.25 | I51: =CUSTOS_MACROGRUPO!$G$8*0.16*0.15
A52: Tubulação incêndio (ferro galvanizado) | B52: =0.3*DADOS_PROJETO!$B$6 | C52: m | D52: 0.3 | E52: =IF(B52>0,G52/B52,0) | F52: =IF(B52>0,H52/B52,0) | G52: =I52*0.55 | H52: =I52*0.45 | I52: =CUSTOS_MACROGRUPO!$G$8*0.16*0.1
A53: Bomba de incêndio (pressurizadora) | B53: =1 | C53: cj | D53: 1 | E53: =IF(B53>0,G53/B53,0) | F53: =IF(B53>0,H53/B53,0) | G53: =I53*0.7 | H53: =I53*0.30 | I53: =CUSTOS_MACROGRUPO!$G$8*0.16*0.08
A54: Reserva técnica de incêndio (RTI) | B54: =15 | C54: m³ | D54: 15 | E54: =IF(B54>0,G54/B54,0) | F54: =IF(B54>0,H54/B54,0) | G54: =I54*0.55 | H54: =I54*0.45 | I54: =CUSTOS_MACROGRUPO!$G$8*0.16*0.05
A55: Escada pressurizada (se aplicável) | B55: 1 | C55: vb | D55: — | E55: =IF(B55>0,G55/B55,0) | F55: =IF(B55>0,H55/B55,0) | G55: =I55*0.5 | H55: =I55*0.50 | I55: =CUSTOS_MACROGRUPO!$G$8*0.16*0.05
A56: Subtotal 3. PREVENÇÃO CONTRA INCÊNDIO | G56: =SUM(G44:G55) | H56: =SUM(H44:H55) | I56: =SUM(I44:I55)
A58: 4. INSTALAÇÕES DE GÁS
A59: Tubulação cobre gás (ø15 a ø28) | B59: =0.5*DADOS_PROJETO!$B$6 | C59: m | D59: 0.5 | E59: =IF(B59>0,G59/B59,0) | F59: =IF(B59>0,H59/B59,0) | G59: =I59*0.55 | H59: =I59*0.45 | I59: =CUSTOS_MACROGRUPO!$G$8*0.1*0.25
A60: Central de gás (GLP individual) | B60: 1 | C60: vb | D60: — | E60: =IF(B60>0,G60/B60,0) | F60: =IF(B60>0,H60/B60,0) | G60: =I60*0.7 | H60: =I60*0.30 | I60: =CUSTOS_MACROGRUPO!$G$8*0.1*0.15
A61: Reguladores de pressão (1º e 2º estágio) | B61: =45 | C61: un | D61: 45 | E61: =IF(B61>0,G61/B61,0) | F61: =IF(B61>0,H61/B61,0) | G61: =I61*0.75 | H61: =I61*0.25 | I61: =CUSTOS_MACROGRUPO!$G$8*0.1*0.12
A62: Medidores individuais gás | B62: =43 | C62: un | D62: 43 | E62: =IF(B62>0,G62/B62,0) | F62: =IF(B62>0,H62/B62,0) | G62: =I62*0.75 | H62: =I62*0.25 | I62: =CUSTOS_MACROGRUPO!$G$8*0.1*0.15
A63: Válvulas de bloqueio e segurança | B63: =90 | C63: un | D63: 90 | E63: =IF(B63>0,G63/B63,0) | F63: =IF(B63>0,H63/B63,0) | G63: =I63*0.7 | H63: =I63*0.30 | I63: =CUSTOS_MACROGRUPO!$G$8*0.1*0.1
A64: Conexões e abraçadeiras gás | B64: 1 | C64: vb | D64: — | E64: =IF(B64>0,G64/B64,0) | F64: =IF(B64>0,H64/B64,0) | G64: =I64*0.75 | H64: =I64*0.25 | I64: =CUSTOS_MACROGRUPO!$G$8*0.1*0.08
A65: Teste de estanqueidade gás | B65: 1 | C65: vb | D65: — | E65: =IF(B65>0,G65/B65,0) | F65: =IF(B65>0,H65/B65,0) | G65: =I65*0.1 | H65: =I65*0.90 | I65: =CUSTOS_MACROGRUPO!$G$8*0.1*0.05
A66: Projeto e ART gás | B66: 1 | C66: vb | D66: — | E66: =IF(B66>0,G66/B66,0) | F66: =IF(B66>0,H66/B66,0) | G66: =I66*0.05 | H66: =I66*0.95 | I66: =CUSTOS_MACROGRUPO!$G$8*0.1*0.1
A67: Subtotal 4. INSTALAÇÕES DE GÁS | G67: =SUM(G59:G66) | H67: =SUM(H59:H66) | I67: =SUM(I59:I66)
A69: 5. TELECOMUNICAÇÕES E DADOS
A70: Infraestrutura telecom (tubulação seca) | B70: =1.5*DADOS_PROJETO!$B$6 | C70: m | D70: 1.5 | E70: =IF(B70>0,G70/B70,0) | F70: =IF(B70>0,H70/B70,0) | G70: =I70*0.5 | H70: =I70*0.50 | I70: =CUSTOS_MACROGRUPO!$G$8*0.11*0.18
A71: Cabeamento estruturado Cat6 | B71: =2.0*DADOS_PROJETO!$B$6 | C71: m | D71: 2 | E71: =IF(B71>0,G71/B71,0) | F71: =IF(B71>0,H71/B71,0) | G71: =I71*0.6 | H71: =I71*0.40 | I71: =CUSTOS_MACROGRUPO!$G$8*0.11*0.14
A72: Interfone/vídeo porteiro (apartamentos) | B72: =43 | C72: un | D72: 43 | E72: =IF(B72>0,G72/B72,0) | F72: =IF(B72>0,H72/B72,0) | G72: =I72*0.7 | H72: =I72*0.30 | I72: =CUSTOS_MACROGRUPO!$G$8*0.11*0.15
A73: CFTV — Câmeras + DVR | B73: =1 | C73: cj | D73: 1 | E73: =IF(B73>0,G73/B73,0) | F73: =IF(B73>0,H73/B73,0) | G73: =I73*0.75 | H73: =I73*0.25 | I73: =CUSTOS_MACROGRUPO!$G$8*0.11*0.15
A74: Controle de acesso (tags/biometria) | B74: =1 | C74: cj | D74: 1 | E74: =IF(B74>0,G74/B74,0) | F74: =IF(B74>0,H74/B74,0) | G74: =I74*0.7 | H74: =I74*0.30 | I74: =CUSTOS_MACROGRUPO!$G$8*0.11*0.1
A75: DG (distribuidor geral) telecom | B75: =1 | C75: un | D75: 1 | E75: =IF(B75>0,G75/B75,0) | F75: =IF(B75>0,H75/B75,0) | G75: =I75*0.65 | H75: =I75*0.35 | I75: =CUSTOS_MACROGRUPO!$G$8*0.11*0.06
A76: Antena coletiva TV | B76: =1 | C76: cj | D76: 1 | E76: =IF(B76>0,G76/B76,0) | F76: =IF(B76>0,H76/B76,0) | G76: =I76*0.7 | H76: =I76*0.30 | I76: =CUSTOS_MACROGRUPO!$G$8*0.11*0.06
A77: Fibra óptica (backbone vertical) | B77: =0.1*DADOS_PROJETO!$B$6 | C77: m | D77: 0.1 | E77: =IF(B77>0,G77/B77,0) | F77: =IF(B77>0,H77/B77,0) | G77: =I77*0.65 | H77: =I77*0.35 | I77: =CUSTOS_MACROGRUPO!$G$8*0.11*0.08
A78: Rack e patch panel | B78: =2 | C78: un | D78: 2 | E78: =IF(B78>0,G78/B78,0) | F78: =IF(B78>0,H78/B78,0) | G78: =I78*0.75 | H78: =I78*0.25 | I78: =CUSTOS_MACROGRUPO!$G$8*0.11*0.08
A79: Subtotal 5. TELECOMUNICAÇÕES E DADOS | G79: =SUM(G70:G78) | H79: =SUM(H70:H78) | I79: =SUM(I70:I78)
A81: 6. SISTEMAS ESPECIAIS
A82: Elevadores sociais (3 un × 26 paradas) | B82: =3 | C82: un | D82: 3 | E82: =IF(B82>0,G82/B82,0) | F82: =IF(B82>0,H82/B82,0) | G82: =I82*0.8 | H82: =I82*0.20 | I82: =CUSTOS_MACROGRUPO!$G$9*1.0*0.42
A83: Grupo gerador 150 kVA (áreas comuns + elevadores) | B83: =1 | C83: un | D83: 1 | E83: =IF(B83>0,G83/B83,0) | F83: =IF(B83>0,H83/B83,0) | G83: =I83*0.75 | H83: =I83*0.25 | I83: =CUSTOS_MACROGRUPO!$G$9*1.0*0.18
A84: Automação predial (BMS básico) | B84: 1 | C84: vb | D84: — | E84: =IF(B84>0,G84/B84,0) | F84: =IF(B84>0,H84/B84,0) | G84: =I84*0.65 | H84: =I84*0.35 | I84: =CUSTOS_MACROGRUPO!$G$9*1.0*0.12
A85: Pressurização escada de incêndio | B85: =1 | C85: cj | D85: 1 | E85: =IF(B85>0,G85/B85,0) | F85: =IF(B85>0,H85/B85,0) | G85: =I85*0.6 | H85: =I85*0.40 | I85: =CUSTOS_MACROGRUPO!$G$9*1.0*0.1
A86: Bomba pressurizadora (água potável) | B86: =1 | C86: cj | D86: 1 | E86: =IF(B86>0,G86/B86,0) | F86: =IF(B86>0,H86/B86,0) | G86: =I86*0.7 | H86: =I86*0.30 | I86: =CUSTOS_MACROGRUPO!$G$9*1.0*0.06
A87: Sistema de reúso de água (se aplicável) | B87: 1 | C87: vb | D87: — | E87: =IF(B87>0,G87/B87,0) | F87: =IF(B87>0,H87/B87,0) | G87: =I87*0.6 | H87: =I87*0.40 | I87: =CUSTOS_MACROGRUPO!$G$9*1.0*0.04
A88: Aquecimento solar (apoio) | B88: =1 | C88: cj | D88: 1 | E88: =IF(B88>0,G88/B88,0) | F88: =IF(B88>0,H88/B88,0) | G88: =I88*0.7 | H88: =I88*0.30 | I88: =CUSTOS_MACROGRUPO!$G$9*1.0*0.05
A89: Exaustão mecânica garagem | B89: =1 | C89: cj | D89: 1 | E89: =IF(B89>0,G89/B89,0) | F89: =IF(B89>0,H89/B89,0) | G89: =I89*0.55 | H89: =I89*0.45 | I89: =CUSTOS_MACROGRUPO!$G$9*1.0*0.03
A90: Subtotal 6. SISTEMAS ESPECIAIS | G90: =SUM(G82:G89) | H90: =SUM(H82:H89) | I90: =SUM(I82:I89)
A92: 7. CLIMATIZAÇÃO
A93: Infraestrutura split (tubulação + dreno) | B93: =86 | C93: pt | D93: 86 | E93: =IF(B93>0,G93/B93,0) | F93: =IF(B93>0,H93/B93,0) | G93: =I93*0.5 | H93: =I93*0.50 | I93: =CUSTOS_MACROGRUPO!$G$10*1.0*0.35
A94: Ventilação mecânica garagem (insuflação/exaustão) | B94: 1 | C94: vb | D94: — | E94: =IF(B94>0,G94/B94,0) | F94: =IF(B94>0,H94/B94,0) | G94: =I94*0.6 | H94: =I94*0.40 | I94: =CUSTOS_MACROGRUPO!$G$10*1.0*0.2
A95: Exaustão banheiros internos | B95: =43 | C95: un | D95: 43 | E95: =IF(B95>0,G95/B95,0) | F95: =IF(B95>0,H95/B95,0) | G95: =I95*0.55 | H95: =I95*0.45 | I95: =CUSTOS_MACROGRUPO!$G$10*1.0*0.12
A96: Exaustão cozinhas (coifa/depurador) | B96: =43 | C96: un | D96: 43 | E96: =IF(B96>0,G96/B96,0) | F96: =IF(B96>0,H96/B96,0) | G96: =I96*0.55 | H96: =I96*0.45 | I96: =CUSTOS_MACROGRUPO!$G$10*1.0*0.1
A97: Dutos e grelhas (áreas comuns) | B97: =0.02*DADOS_PROJETO!$B$6 | C97: m² | D97: 0.02 | E97: =IF(B97>0,G97/B97,0) | F97: =IF(B97>0,H97/B97,0) | G97: =I97*0.6 | H97: =I97*0.40 | I97: =CUSTOS_MACROGRUPO!$G$10*1.0*0.08
A98: Dampers corta-fogo | B98: =12 | C98: un | D98: 12 | E98: =IF(B98>0,G98/B98,0) | F98: =IF(B98>0,H98/B98,0) | G98: =I98*0.65 | H98: =I98*0.35 | I98: =CUSTOS_MACROGRUPO!$G$10*1.0*0.05
A99: Ventilação hall de elevadores | B99: 1 | C99: vb | D99: — | E99: =IF(B99>0,G99/B99,0) | F99: =IF(B99>0,H99/B99,0) | G99: =I99*0.5 | H99: =I99*0.50 | I99: =CUSTOS_MACROGRUPO!$G$10*1.0*0.05
A100: Ar-condicionado áreas comuns (salão de festas) | B100: =3 | C100: un | D100: 3 | E100: =IF(B100>0,G100/B100,0) | F100: =IF(B100>0,H100/B100,0) | G100: =I100*0.7 | H100: =I100*0.30 | I100: =CUSTOS_MACROGRUPO!$G$10*1.0*0.05
A101: Subtotal 7. CLIMATIZAÇÃO | G101: =SUM(G93:G100) | H101: =SUM(H93:H100) | I101: =SUM(I93:I100)
A103: TOTAL INSTALAÇÕES (Hidro + Elétrica + Incêndio + Gás + Telecom + Especiais + Climatização) | G103: =G22+G41+G56+G67+G79+G90+G101 | H103: =H22+H41+H56+H67+H79+H90+H101 | I103: =I22+I41+I56+I67+I79+I90+I101

Sheet ACABAMENTOS
A1: DETALHAMENTO ACABAMENTOS — Nível Executivo
A2: Projeto: Residencial Alípio Schirmann — AC: 12,033.95 m²
A4: Item / Serviço | B4: Qtd | C4: Un | D4: Índice | E4: PU Material | F4: PU Mão de Obra | G4: Total Material | H4: Total Mão de Obra | I4: Total
A5: 1. REVESTIMENTO INTERNO DE PAREDE
A6: Chapisco rolado (interno) | B6: =1.4*DADOS_PROJETO!$B$6 | C6: m² | D6: 1.4 | E6: =IF(B6>0,G6/B6,0) | F6: =IF(B6>0,H6/B6,0) | G6: =I6*0.4 | H6: =I6*0.60 | I6: =CUSTOS_MACROGRUPO!$G$11*1.0*0.06
A7: Emboço / massa única (espessura média 2cm) | B7: =1.4*DADOS_PROJETO!$B$6 | C7: m² | D7: 1.4 | E7: =IF(B7>0,G7/B7,0) | F7: =IF(B7>0,H7/B7,0) | G7: =I7*0.48 | H7: =I7*0.52 | I7: =CUSTOS_MACROGRUPO!$G$11*1.0*0.18
A8: Reboco fino (espessura 5mm) | B8: =0.8*DADOS_PROJETO!$B$6 | C8: m² | D8: 0.8 | E8: =IF(B8>0,G8/B8,0) | F8: =IF(B8>0,H8/B8,0) | G8: =I8*0.45 | H8: =I8*0.55 | I8: =CUSTOS_MACROGRUPO!$G$11*1.0*0.08
A9: Cerâmica parede — Banheiros (piso ao teto) | B9: =0.25*DADOS_PROJETO!$B$6 | C9: m² | D9: 0.25 | E9: =IF(B9>0,G9/B9,0) | F9: =IF(B9>0,H9/B9,0) | G9: =I9*0.52 | H9: =I9*0.48 | I9: =CUSTOS_MACROGRUPO!$G$11*1.0*0.12
A10: Cerâmica parede — Cozinha (meia-parede) | B10: =0.1*DADOS_PROJETO!$B$6 | C10: m² | D10: 0.1 | E10: =IF(B10>0,G10/B10,0) | F10: =IF(B10>0,H10/B10,0) | G10: =I10*0.52 | H10: =I10*0.48 | I10: =CUSTOS_MACROGRUPO!$G$11*1.0*0.06
A11: Cerâmica parede — Área de serviço | B11: =0.06*DADOS_PROJETO!$B$6 | C11: m² | D11: 0.06 | E11: =IF(B11>0,G11/B11,0) | F11: =IF(B11>0,H11/B11,0) | G11: =I11*0.52 | H11: =I11*0.48 | I11: =CUSTOS_MACROGRUPO!$G$11*1.0*0.04
A12: Porcelanato parede — Lavabos/banheiro suíte | B12: =0.08*DADOS_PROJETO!$B$6 | C12: m² | D12: 0.08 | E12: =IF(B12>0,G12/B12,0) | F12: =IF(B12>0,H12/B12,0) | G12: =I12*0.55 | H12: =I12*0.45 | I12: =CUSTOS_MACROGRUPO!$G$11*1.0*0.06
A13: Massa corrida PVA (paredes lisas) | B13: =0.9*DADOS_PROJETO!$B$6 | C13: m² | D13: 0.9 | E13: =IF(B13>0,G13/B13,0) | F13: =IF(B13>0,H13/B13,0) | G13: =I13*0.42 | H13: =I13*0.58 | I13: =CUSTOS_MACROGRUPO!$G$11*1.0*0.1
A14: Revestimento hall/circulação (porcelanato/pastilha) | B14: =0.05*DADOS_PROJETO!$B$6 | C14: m² | D14: 0.05 | E14: =IF(B14>0,G14/B14,0) | F14: =IF(B14>0,H14/B14,0) | G14: =I14*0.55 | H14: =I14*0.45 | I14: =CUSTOS_MACROGRUPO!$G$11*1.0*0.04
A15: Revestimento áreas comuns (lobby, salão festas) | B15: =0.04*DADOS_PROJETO!$B$6 | C15: m² | D15: 0.04 | E15: =IF(B15>0,G15/B15,0) | F15: =IF(B15>0,H15/B15,0) | G15: =I15*0.55 | H15: =I15*0.45 | I15: =CUSTOS_MACROGRUPO!$G$11*1.0*0.04
A16: Rejunte cerâmicas/porcelanatos | B16: =0.49*DADOS_PROJETO!$B$6 | C16: m² | D16: 0.49 | E16: =IF(B16>0,G16/B16,0) | F16: =IF(B16>0,H16/B16,0) | G16: =I16*0.65 | H16: =I16*0.35 | I16: =CUSTOS_MACROGRUPO!$G$11*1.0*0.04
A17: Cantoneiras e perfis de acabamento | B17: =0.15*DADOS_PROJETO!$B$6 | C17: m | D17: 0.15 | E17: =IF(B17>0,G17/B17,0) | F17: =IF(B17>0,H17/B17,0) | G17: =I17*0.7 | H17: =I17*0.30 | I17: =CUSTOS_MACROGRUPO!$G$11*1.0*0.02
A18: Argamassa colante ACIII (áreas molhadas) | B18: =0.49*DADOS_PROJETO!$B$6 | C18: m² | D18: 0.49 | E18: =IF(B18>0,G18/B18,0) | F18: =IF(B18>0,H18/B18,0) | G18: =I18*0.7 | H18: =I18*0.30 | I18: =CUSTOS_MACROGRUPO!$G$11*1.0*0.05
A19: Argamassa colante ACII (áreas secas) | B19: =0.3*DADOS_PROJETO!$B$6 | C19: m² | D19: 0.3 | E19: =IF(B19>0,G19/B19,0) | F19: =IF(B19>0,H19/B19,0) | G19: =I19*0.7 | H19: =I19*0.30 | I19: =CUSTOS_MACROGRUPO!$G$11*1.0*0.04
A20: Filete/rodameio decorativo | B20: =0.05*DADOS_PROJETO!$B$6 | C20: m | D20: 0.05 | E20: =IF(B20>0,G20/B20,0) | F20: =IF(B20>0,H20/B20,0) | G20: =I20*0.65 | H20: =I20*0.35 | I20: =CUSTOS_MACROGRUPO!$G$11*1.0*0.02
A21: Nicho banheiro (porcelanato) | B21: =86 | C21: un | D21: 86 | E21: =IF(B21>0,G21/B21,0) | F21: =IF(B21>0,H21/B21,0) | G21: =I21*0.55 | H21: =I21*0.45 | I21: =CUSTOS_MACROGRUPO!$G$11*1.0*0.03
A22: Tratamento de juntas (estruturais/dilatação) | B22: =0.02*DADOS_PROJETO!$B$6 | C22: m | D22: 0.02 | E22: =IF(B22>0,G22/B22,0) | F22: =IF(B22>0,H22/B22,0) | G22: =I22*0.5 | H22: =I22*0.50 | I22: =CUSTOS_MACROGRUPO!$G$11*1.0*0.02
A23: Subtotal 1. REVESTIMENTO INTERNO DE PAREDE | G23: =SUM(G6:G22) | H23: =SUM(H6:H22) | I23: =SUM(I6:I22)
A25: 2. TETO / FORRO
A26: Gesso liso — Apartamentos (teto, sancas) | B26: =0.65*DADOS_PROJETO!$B$6 | C26: m² | D26: 0.65 | E26: =IF(B26>0,G26/B26,0) | F26: =IF(B26>0,H26/B26,0) | G26: =I26*0.42 | H26: =I26*0.58 | I26: =CUSTOS_MACROGRUPO!$G$12*1.0*0.32
A27: Forro gesso acartonado — Áreas comuns | B27: =0.08*DADOS_PROJETO!$B$6 | C27: m² | D27: 0.08 | E27: =IF(B27>0,G27/B27,0) | F27: =IF(B27>0,H27/B27,0) | G27: =I27*0.48 | H27: =I27*0.52 | I27: =CUSTOS_MACROGRUPO!$G$12*1.0*0.1
A28: Forro gesso acartonado — Banheiros (resistente umidade) | B28: =0.06*DADOS_PROJETO!$B$6 | C28: m² | D28: 0.06 | E28: =IF(B28>0,G28/B28,0) | F28: =IF(B28>0,H28/B28,0) | G28: =I28*0.48 | H28: =I28*0.52 | I28: =CUSTOS_MACROGRUPO!$G$12*1.0*0.08
A29: Sanca/moldura gesso — Perímetro ambientes | B29: =0.3*DADOS_PROJETO!$B$6 | C29: m | D29: 0.3 | E29: =IF(B29>0,G29/B29,0) | F29: =IF(B29>0,H29/B29,0) | G29: =I29*0.4 | H29: =I29*0.60 | I29: =CUSTOS_MACROGRUPO!$G$12*1.0*0.1
A30: Forro PVC — Áreas técnicas/garagem | B30: =0.05*DADOS_PROJETO!$B$6 | C30: m² | D30: 0.05 | E30: =IF(B30>0,G30/B30,0) | F30: =IF(B30>0,H30/B30,0) | G30: =I30*0.55 | H30: =I30*0.45 | I30: =CUSTOS_MACROGRUPO!$G$12*1.0*0.05
A31: Tabica em gesso | B31: =0.2*DADOS_PROJETO!$B$6 | C31: m | D31: 0.2 | E31: =IF(B31>0,G31/B31,0) | F31: =IF(B31>0,H31/B31,0) | G31: =I31*0.38 | H31: =I31*0.62 | I31: =CUSTOS_MACROGRUPO!$G$12*1.0*0.06
A32: Rebaixo para iluminação (spots embutidos) | B32: =0.04*DADOS_PROJETO!$B$6 | C32: m² | D32: 0.04 | E32: =IF(B32>0,G32/B32,0) | F32: =IF(B32>0,H32/B32,0) | G32: =I32*0.45 | H32: =I32*0.55 | I32: =CUSTOS_MACROGRUPO!$G$12*1.0*0.05
A33: Forro mineral/metálico — Hall elevadores | B33: =0.02*DADOS_PROJETO!$B$6 | C33: m² | D33: 0.02 | E33: =IF(B33>0,G33/B33,0) | F33: =IF(B33>0,H33/B33,0) | G33: =I33*0.55 | H33: =I33*0.45 | I33: =CUSTOS_MACROGRUPO!$G$12*1.0*0.04
A34: Pintura de teto (1ª demão — incluída aqui) | B34: =0.7*DADOS_PROJETO!$B$6 | C34: m² | D34: 0.7 | E34: =IF(B34>0,G34/B34,0) | F34: =IF(B34>0,H34/B34,0) | G34: =I34*0.4 | H34: =I34*0.60 | I34: =CUSTOS_MACROGRUPO!$G$12*1.0*0.08
A35: Tratamento de trincas em teto (tela + massa) | B35: =0.1*DADOS_PROJETO!$B$6 | C35: m² | D35: 0.1 | E35: =IF(B35>0,G35/B35,0) | F35: =IF(B35>0,H35/B35,0) | G35: =I35*0.45 | H35: =I35*0.55 | I35: =CUSTOS_MACROGRUPO!$G$12*1.0*0.04
A36: Cortineiro em gesso | B36: =0.08*DADOS_PROJETO!$B$6 | C36: m | D36: 0.08 | E36: =IF(B36>0,G36/B36,0) | F36: =IF(B36>0,H36/B36,0) | G36: =I36*0.4 | H36: =I36*0.60 | I36: =CUSTOS_MACROGRUPO!$G$12*1.0*0.04
A37: Acabamento shaft/alçapão | B37: =43 | C37: un | D37: 43 | E37: =IF(B37>0,G37/B37,0) | F37: =IF(B37>0,H37/B37,0) | G37: =I37*0.5 | H37: =I37*0.50 | I37: =CUSTOS_MACROGRUPO!$G$12*1.0*0.04
A38: Subtotal 2. TETO / FORRO | G38: =SUM(G26:G37) | H38: =SUM(H26:H37) | I38: =SUM(I26:I37)
A40: 3. PISOS
A41: Contrapiso (argamassa e=4cm) | B41: =0.7*DADOS_PROJETO!$B$6 | C41: m² | D41: 0.7 | E41: =IF(B41>0,G41/B41,0) | F41: =IF(B41>0,H41/B41,0) | G41: =I41*0.48 | H41: =I41*0.52 | I41: =CUSTOS_MACROGRUPO!$G$13*1.0*0.12
A42: Porcelanato retificado — Salas/quartos (60×60 ou 80×80) | B42: =0.35*DADOS_PROJETO!$B$6 | C42: m² | D42: 0.35 | E42: =IF(B42>0,G42/B42,0) | F42: =IF(B42>0,H42/B42,0) | G42: =I42*0.55 | H42: =I42*0.45 | I42: =CUSTOS_MACROGRUPO!$G$13*1.0*0.16
A43: Porcelanato retificado — Áreas molhadas (antiderrapante) | B43: =0.12*DADOS_PROJETO!$B$6 | C43: m² | D43: 0.12 | E43: =IF(B43>0,G43/B43,0) | F43: =IF(B43>0,H43/B43,0) | G43: =I43*0.55 | H43: =I43*0.45 | I43: =CUSTOS_MACROGRUPO!$G$13*1.0*0.06
A44: Porcelanato — Sacadas/varandas | B44: =0.05*DADOS_PROJETO!$B$6 | C44: m² | D44: 0.05 | E44: =IF(B44>0,G44/B44,0) | F44: =IF(B44>0,H44/B44,0) | G44: =I44*0.55 | H44: =I44*0.45 | I44: =CUSTOS_MACROGRUPO!$G$13*1.0*0.04
A45: Porcelanato — Áreas comuns (lobby, circulação) | B45: =0.06*DADOS_PROJETO!$B$6 | C45: m² | D45: 0.06 | E45: =IF(B45>0,G45/B45,0) | F45: =IF(B45>0,H45/B45,0) | G45: =I45*0.55 | H45: =I45*0.45 | I45: =CUSTOS_MACROGRUPO!$G$13*1.0*0.06
A46: Piso cimentício / epóxi — Garagem | B46: =0.1*DADOS_PROJETO!$B$6 | C46: m² | D46: 0.1 | E46: =IF(B46>0,G46/B46,0) | F46: =IF(B46>0,H46/B46,0) | G46: =I46*0.5 | H46: =I46*0.50 | I46: =CUSTOS_MACROGRUPO!$G$13*1.0*0.08
A47: Piso intertravado — Áreas externas | B47: =0.03*DADOS_PROJETO!$B$6 | C47: m² | D47: 0.03 | E47: =IF(B47>0,G47/B47,0) | F47: =IF(B47>0,H47/B47,0) | G47: =I47*0.52 | H47: =I47*0.48 | I47: =CUSTOS_MACROGRUPO!$G$13*1.0*0.03
A48: Soleira granito/porcelanato (portas) | B48: =0.1*DADOS_PROJETO!$B$6 | C48: m | D48: 0.1 | E48: =IF(B48>0,G48/B48,0) | F48: =IF(B48>0,H48/B48,0) | G48: =I48*0.6 | H48: =I48*0.40 | I48: =CUSTOS_MACROGRUPO!$G$13*1.0*0.04
A49: Peitoril granito (janelas) | B49: =0.06*DADOS_PROJETO!$B$6 | C49: m | D49: 0.06 | E49: =IF(B49>0,G49/B49,0) | F49: =IF(B49>0,H49/B49,0) | G49: =I49*0.6 | H49: =I49*0.40 | I49: =CUSTOS_MACROGRUPO!$G$13*1.0*0.03
A50: Rodapé cerâmico/porcelanato | B50: =0.5*DADOS_PROJETO!$B$6 | C50: m | D50: 0.5 | E50: =IF(B50>0,G50/B50,0) | F50: =IF(B50>0,H50/B50,0) | G50: =I50*0.55 | H50: =I50*0.45 | I50: =CUSTOS_MACROGRUPO!$G$13*1.0*0.06
A51: Rodapé madeira/MDF (quartos) | B51: =0.2*DADOS_PROJETO!$B$6 | C51: m | D51: 0.2 | E51: =IF(B51>0,G51/B51,0) | F51: =IF(B51>0,H51/B51,0) | G51: =I51*0.6 | H51: =I51*0.40 | I51: =CUSTOS_MACROGRUPO!$G$13*1.0*0.03
A52: Degraus escada (granito/porcelanato) | B52: =350 | C52: un | D52: 350 | E52: =IF(B52>0,G52/B52,0) | F52: =IF(B52>0,H52/B52,0) | G52: =I52*0.55 | H52: =I52*0.45 | I52: =CUSTOS_MACROGRUPO!$G$13*1.0*0.05
A53: Rejunte pisos (epóxi áreas molhadas + cimentício) | B53: =0.68*DADOS_PROJETO!$B$6 | C53: m² | D53: 0.68 | E53: =IF(B53>0,G53/B53,0) | F53: =IF(B53>0,H53/B53,0) | G53: =I53*0.65 | H53: =I53*0.35 | I53: =CUSTOS_MACROGRUPO!$G$13*1.0*0.04
A54: Argamassa colante para pisos | B54: =0.68*DADOS_PROJETO!$B$6 | C54: m² | D54: 0.68 | E54: =IF(B54>0,G54/B54,0) | F54: =IF(B54>0,H54/B54,0) | G54: =I54*0.7 | H54: =I54*0.30 | I54: =CUSTOS_MACROGRUPO!$G$13*1.0*0.05
A55: Manta acústica sob piso | B55: =0.35*DADOS_PROJETO!$B$6 | C55: m² | D55: 0.35 | E55: =IF(B55>0,G55/B55,0) | F55: =IF(B55>0,H55/B55,0) | G55: =I55*0.8 | H55: =I55*0.20 | I55: =CUSTOS_MACROGRUPO!$G$13*1.0*0.05
A56: Regularização/nivelamento laser | B56: =0.7*DADOS_PROJETO!$B$6 | C56: m² | D56: 0.7 | E56: =IF(B56>0,G56/B56,0) | F56: =IF(B56>0,H56/B56,0) | G56: =I56*0.4 | H56: =I56*0.60 | I56: =CUSTOS_MACROGRUPO!$G$13*1.0*0.06
A57: Junta de dilatação piso garagem | B57: =0.01*DADOS_PROJETO!$B$6 | C57: m | D57: 0.01 | E57: =IF(B57>0,G57/B57,0) | F57: =IF(B57>0,H57/B57,0) | G57: =I57*0.55 | H57: =I57*0.45 | I57: =CUSTOS_MACROGRUPO!$G$13*1.0*0.02
A58: Rampa acessibilidade (piso tátil) | B58: =0.005*DADOS_PROJETO!$B$6 | C58: m² | D58: 0.005 | E58: =IF(B58>0,G58/B58,0) | F58: =IF(B58>0,H58/B58,0) | G58: =I58*0.5 | H58: =I58*0.50 | I58: =CUSTOS_MACROGRUPO!$G$13*1.0*0.02
A59: Subtotal 3. PISOS | G59: =SUM(G41:G58) | H59: =SUM(H41:H58) | I59: =SUM(I41:I58)
A61: 4. PINTURA
A62: Pintura látex PVA — Paredes internas (2 demãos) | B62: =1.4*DADOS_PROJETO!$B$6 | C62: m² | D62: 1.4 | E62: =IF(B62>0,G62/B62,0) | F62: =IF(B62>0,H62/B62,0) | G62: =I62*0.35 | H62: =I62*0.65 | I62: =CUSTOS_MACROGRUPO!$G$14*1.0*0.28
A63: Pintura acrílica — Paredes externas (2 demãos) | B63: =0.3*DADOS_PROJETO!$B$6 | C63: m² | D63: 0.3 | E63: =IF(B63>0,G63/B63,0) | F63: =IF(B63>0,H63/B63,0) | G63: =I63*0.38 | H63: =I63*0.62 | I63: =CUSTOS_MACROGRUPO!$G$14*1.0*0.1
A64: Pintura acrílica — Teto (2 demãos) | B64: =0.65*DADOS_PROJETO!$B$6 | C64: m² | D64: 0.65 | E64: =IF(B64>0,G64/B64,0) | F64: =IF(B64>0,H64/B64,0) | G64: =I64*0.35 | H64: =I64*0.65 | I64: =CUSTOS_MACROGRUPO!$G$14*1.0*0.15
A65: Pintura epóxi — Piso garagem | B65: =0.1*DADOS_PROJETO!$B$6 | C65: m² | D65: 0.1 | E65: =IF(B65>0,G65/B65,0) | F65: =IF(B65>0,H65/B65,0) | G65: =I65*0.42 | H65: =I65*0.58 | I65: =CUSTOS_MACROGRUPO!$G$14*1.0*0.08
A66: Pintura esmalte — Esquadrias metálicas/grades | B66: =0.06*DADOS_PROJETO!$B$6 | C66: m² | D66: 0.06 | E66: =IF(B66>0,G66/B66,0) | F66: =IF(B66>0,H66/B66,0) | G66: =I66*0.4 | H66: =I66*0.60 | I66: =CUSTOS_MACROGRUPO!$G$14*1.0*0.05
A67: Textura acrílica — Áreas comuns selecionadas | B67: =0.04*DADOS_PROJETO!$B$6 | C67: m² | D67: 0.04 | E67: =IF(B67>0,G67/B67,0) | F67: =IF(B67>0,H67/B67,0) | G67: =I67*0.42 | H67: =I67*0.58 | I67: =CUSTOS_MACROGRUPO!$G$14*1.0*0.05
A68: Verniz / stain — Madeiras | B68: =0.03*DADOS_PROJETO!$B$6 | C68: m² | D68: 0.03 | E68: =IF(B68>0,G68/B68,0) | F68: =IF(B68>0,H68/B68,0) | G68: =I68*0.45 | H68: =I68*0.55 | I68: =CUSTOS_MACROGRUPO!$G$14*1.0*0.03
A69: Massa corrida (incluída no revestimento, complemento) | B69: =0.2*DADOS_PROJETO!$B$6 | C69: m² | D69: 0.2 | E69: =IF(B69>0,G69/B69,0) | F69: =IF(B69>0,H69/B69,0) | G69: =I69*0.4 | H69: =I69*0.60 | I69: =CUSTOS_MACROGRUPO!$G$14*1.0*0.06
A70: Selador acrílico (preparação) | B70: =1.5*DADOS_PROJETO!$B$6 | C70: m² | D70: 1.5 | E70: =IF(B70>0,G70/B70,0) | F70: =IF(B70>0,H70/B70,0) | G70: =I70*0.5 | H70: =I70*0.50 | I70: =CUSTOS_MACROGRUPO!$G$14*1.0*0.06
A71: Demarcação vagas garagem (tinta epóxi) | B71: =0.03*DADOS_PROJETO!$B$6 | C71: m | D71: 0.03 | E71: =IF(B71>0,G71/B71,0) | F71: =IF(B71>0,H71/B71,0) | G71: =I71*0.38 | H71: =I71*0.62 | I71: =CUSTOS_MACROGRUPO!$G$14*1.0*0.03
A72: Pintura de tubulações aparentes | B72: =0.05*DADOS_PROJETO!$B$6 | C72: m | D72: 0.05 | E72: =IF(B72>0,G72/B72,0) | F72: =IF(B72>0,H72/B72,0) | G72: =I72*0.35 | H72: =I72*0.65 | I72: =CUSTOS_MACROGRUPO!$G$14*1.0*0.03
A73: Fundo preparador / primer | B73: =0.5*DADOS_PROJETO!$B$6 | C73: m² | D73: 0.5 | E73: =IF(B73>0,G73/B73,0) | F73: =IF(B73>0,H73/B73,0) | G73: =I73*0.5 | H73: =I73*0.50 | I73: =CUSTOS_MACROGRUPO!$G$14*1.0*0.04
A74: Pintura de numeração (portas, vagas) | B74: =180 | C74: un | D74: 180 | E74: =IF(B74>0,G74/B74,0) | F74: =IF(B74>0,H74/B74,0) | G74: =I74*0.3 | H74: =I74*0.70 | I74: =CUSTOS_MACROGRUPO!$G$14*1.0*0.02
A75: Limpeza e proteção (fitas, lonas) | B75: 1 | C75: vb | D75: — | E75: =IF(B75>0,G75/B75,0) | F75: =IF(B75>0,H75/B75,0) | G75: =I75*0.2 | H75: =I75*0.80 | I75: =CUSTOS_MACROGRUPO!$G$14*1.0*0.02
A76: Subtotal 4. PINTURA | G76: =SUM(G62:G75) | H76: =SUM(H62:H75) | I76: =SUM(I62:I75)
A78: 5. ESQUADRIAS
A79: Porta madeira interna (kit pronto 80×210) | B79: =200 | C79: un | D79: 200 | E79: =IF(B79>0,G79/B79,0) | F79: =IF(B79>0,H79/B79,0) | G79: =I79*0.68 | H79: =I79*0.32 | I79: =CUSTOS_MACROGRUPO!$G$15*1.0*0.12
A80: Porta entrada apartamento (acústica/segurança) | B80: =43 | C80: un | D80: 43 | E80: =IF(B80>0,G80/B80,0) | F80: =IF(B80>0,H80/B80,0) | G80: =I80*0.7 | H80: =I80*0.30 | I80: =CUSTOS_MACROGRUPO!$G$15*1.0*0.08
A81: Porta acústica (entre unidades, se aplicável) | B81: =10 | C81: un | D81: 10 | E81: =IF(B81>0,G81/B81,0) | F81: =IF(B81>0,H81/B81,0) | G81: =I81*0.7 | H81: =I81*0.30 | I81: =CUSTOS_MACROGRUPO!$G$15*1.0*0.03
A82: Porta corta-fogo P-90 (escadas) | B82: =52 | C82: un | D82: 52 | E82: =IF(B82>0,G82/B82,0) | F82: =IF(B82>0,H82/B82,0) | G82: =I82*0.72 | H82: =I82*0.28 | I82: =CUSTOS_MACROGRUPO!$G$15*1.0*0.08
A83: Janela alumínio — Quartos (correr 2 folhas) | B83: =0.06*DADOS_PROJETO!$B$6 | C83: m² | D83: 0.06 | E83: =IF(B83>0,G83/B83,0) | F83: =IF(B83>0,H83/B83,0) | G83: =I83*0.72 | H83: =I83*0.28 | I83: =CUSTOS_MACROGRUPO!$G$15*1.0*0.08
A84: Janela alumínio — Salas (correr 3/4 folhas) | B84: =0.04*DADOS_PROJETO!$B$6 | C84: m² | D84: 0.04 | E84: =IF(B84>0,G84/B84,0) | F84: =IF(B84>0,H84/B84,0) | G84: =I84*0.72 | H84: =I84*0.28 | I84: =CUSTOS_MACROGRUPO!$G$15*1.0*0.06
A85: Janela alumínio — Cozinha/serviço (maxim-ar) | B85: =0.03*DADOS_PROJETO!$B$6 | C85: m² | D85: 0.03 | E85: =IF(B85>0,G85/B85,0) | F85: =IF(B85>0,H85/B85,0) | G85: =I85*0.72 | H85: =I85*0.28 | I85: =CUSTOS_MACROGRUPO!$G$15*1.0*0.04
A86: Porta sacada alumínio (correr) | B86: =0.05*DADOS_PROJETO!$B$6 | C86: m² | D86: 0.05 | E86: =IF(B86>0,G86/B86,0) | F86: =IF(B86>0,H86/B86,0) | G86: =I86*0.72 | H86: =I86*0.28 | I86: =CUSTOS_MACROGRUPO!$G$15*1.0*0.07
A87: Vidro temperado (box banheiro) | B87: =0.04*DADOS_PROJETO!$B$6 | C87: m² | D87: 0.04 | E87: =IF(B87>0,G87/B87,0) | F87: =IF(B87>0,H87/B87,0) | G87: =I87*0.75 | H87: =I87*0.25 | I87: =CUSTOS_MACROGRUPO!$G$15*1.0*0.06
A88: Vidro laminado (guarda-corpo sacadas) | B88: =0.03*DADOS_PROJETO!$B$6 | C88: m² | D88: 0.03 | E88: =IF(B88>0,G88/B88,0) | F88: =IF(B88>0,H88/B88,0) | G88: =I88*0.75 | H88: =I88*0.25 | I88: =CUSTOS_MACROGRUPO!$G$15*1.0*0.05
A89: Guarda-corpo alumínio + vidro | B89: =0.04*DADOS_PROJETO!$B$6 | C89: m | D89: 0.04 | E89: =IF(B89>0,G89/B89,0) | F89: =IF(B89>0,H89/B89,0) | G89: =I89*0.68 | H89: =I89*0.32 | I89: =CUSTOS_MACROGRUPO!$G$15*1.0*0.06
A90: Corrimão escada (aço inox/alumínio) | B90: =0.02*DADOS_PROJETO!$B$6 | C90: m | D90: 0.02 | E90: =IF(B90>0,G90/B90,0) | F90: =IF(B90>0,H90/B90,0) | G90: =I90*0.65 | H90: =I90*0.35 | I90: =CUSTOS_MACROGRUPO!$G$15*1.0*0.03
A91: Esquadrias alumínio — Áreas comuns | B91: =0.02*DADOS_PROJETO!$B$6 | C91: m² | D91: 0.02 | E91: =IF(B91>0,G91/B91,0) | F91: =IF(B91>0,H91/B91,0) | G91: =I91*0.72 | H91: =I91*0.28 | I91: =CUSTOS_MACROGRUPO!$G$15*1.0*0.04
A92: Pintura eletrostática (esquadrias alumínio) | B92: =0.15*DADOS_PROJETO!$B$6 | C92: m² | D92: 0.15 | E92: =IF(B92>0,G92/B92,0) | F92: =IF(B92>0,H92/B92,0) | G92: =I92*0.4 | H92: =I92*0.60 | I92: =CUSTOS_MACROGRUPO!$G$15*1.0*0.06
A93: Contramarco alumínio | B93: =0.1*DADOS_PROJETO!$B$6 | C93: m | D93: 0.1 | E93: =IF(B93>0,G93/B93,0) | F93: =IF(B93>0,H93/B93,0) | G93: =I93*0.65 | H93: =I93*0.35 | I93: =CUSTOS_MACROGRUPO!$G$15*1.0*0.04
A94: Ferragens (dobradiças, fechaduras, puxadores) | B94: =250 | C94: cj | D94: 250 | E94: =IF(B94>0,G94/B94,0) | F94: =IF(B94>0,H94/B94,0) | G94: =I94*0.85 | H94: =I94*0.15 | I94: =CUSTOS_MACROGRUPO!$G$15*1.0*0.06
A95: Peitoril/pingadeira (granito/alumínio) | B95: =0.06*DADOS_PROJETO!$B$6 | C95: m | D95: 0.06 | E95: =IF(B95>0,G95/B95,0) | F95: =IF(B95>0,H95/B95,0) | G95: =I95*0.65 | H95: =I95*0.35 | I95: =CUSTOS_MACROGRUPO!$G$15*1.0*0.02
A96: Selante/silicone (vedação esquadrias) | B96: =0.12*DADOS_PROJETO!$B$6 | C96: m | D96: 0.12 | E96: =IF(B96>0,G96/B96,0) | F96: =IF(B96>0,H96/B96,0) | G96: =I96*0.7 | H96: =I96*0.30 | I96: =CUSTOS_MACROGRUPO!$G$15*1.0*0.02
A97: Subtotal 5. ESQUADRIAS | G97: =SUM(G79:G96) | H97: =SUM(H79:H96) | I97: =SUM(I79:I96)
A99: 6. LOUÇAS E METAIS
A100: Bacia sanitária c/ caixa acoplada — Padrão | B100: =43 | C100: un | D100: 43 | E100: =IF(B100>0,G100/B100,0) | F100: =IF(B100>0,H100/B100,0) | G100: =I100*0.88 | H100: =I100*0.12 | I100: =CUSTOS_MACROGRUPO!$G$16*1.0*0.12
A101: Bacia sanitária c/ caixa acoplada — Suíte | B101: =43 | C101: un | D101: 43 | E101: =IF(B101>0,G101/B101,0) | F101: =IF(B101>0,H101/B101,0) | G101: =I101*0.88 | H101: =I101*0.12 | I101: =CUSTOS_MACROGRUPO!$G$16*1.0*0.1
A102: Lavatório de embutir (louça) | B102: =86 | C102: un | D102: 86 | E102: =IF(B102>0,G102/B102,0) | F102: =IF(B102>0,H102/B102,0) | G102: =I102*0.88 | H102: =I102*0.12 | I102: =CUSTOS_MACROGRUPO!$G$16*1.0*0.08
A103: Cuba de embutir cozinha (inox) | B103: =43 | C103: un | D103: 43 | E103: =IF(B103>0,G103/B103,0) | F103: =IF(B103>0,H103/B103,0) | G103: =I103*0.88 | H103: =I103*0.12 | I103: =CUSTOS_MACROGRUPO!$G$16*1.0*0.06
A104: Cuba de apoio lavabo (se aplicável) | B104: =10 | C104: un | D104: 10 | E104: =IF(B104>0,G104/B104,0) | F104: =IF(B104>0,H104/B104,0) | G104: =I104*0.88 | H104: =I104*0.12 | I104: =CUSTOS_MACROGRUPO!$G$16*1.0*0.03
A105: Bancada granito/quartzo — Banheiros | B105: =0.015*DADOS_PROJETO!$B$6 | C105: m | D105: 0.015 | E105: =IF(B105>0,G105/B105,0) | F105: =IF(B105>0,H105/B105,0) | G105: =I105*0.82 | H105: =I105*0.18 | I105: =CUSTOS_MACROGRUPO!$G$16*1.0*0.1
A106: Bancada granito — Cozinha | B106: =0.012*DADOS_PROJETO!$B$6 | C106: m | D106: 0.012 | E106: =IF(B106>0,G106/B106,0) | F106: =IF(B106>0,H106/B106,0) | G106: =I106*0.82 | H106: =I106*0.18 | I106: =CUSTOS_MACROGRUPO!$G$16*1.0*0.08
...

Sheet CI_DETALHADO
A1: CUSTOS INDIRETOS — Detalhamento Executivo
A2: Projeto: Residencial Alípio Schirmann — AC: 12,033.95 m²
A4: Item / Serviço | B4: Qtd | C4: Un | D4: Índice | E4: Preço Unitário | F4: Total | G4: R$/m² AC
A5: 1. PROJETOS E CONSULTORIAS
A6: Projeto Arquitetônico (legal + executivo) | B6: 1 | C6: vb | D6: — | E6: =IF(B6>0,F6/B6,0) | F6: =CUSTOS_MACROGRUPO!$G$2*0.22*0.15 | G6: =F6/DADOS_PROJETO!$B$6
A7: Projeto Estrutural | B7: 1 | C7: vb | D7: — | E7: =IF(B7>0,F7/B7,0) | F7: =CUSTOS_MACROGRUPO!$G$2*0.22*0.14 | G7: =F7/DADOS_PROJETO!$B$6
A8: Projeto Hidrossanitário | B8: 1 | C8: vb | D8: — | E8: =IF(B8>0,F8/B8,0) | F8: =CUSTOS_MACROGRUPO!$G$2*0.22*0.08 | G8: =F8/DADOS_PROJETO!$B$6
A9: Projeto Elétrico | B9: 1 | C9: vb | D9: — | E9: =IF(B9>0,F9/B9,0) | F9: =CUSTOS_MACROGRUPO!$G$2*0.22*0.08 | G9: =F9/DADOS_PROJETO!$B$6
A10: Projeto Preventivo Incêndio | B10: 1 | C10: vb | D10: — | E10: =IF(B10>0,F10/B10,0) | F10: =CUSTOS_MACROGRUPO!$G$2*0.22*0.06 | G10: =F10/DADOS_PROJETO!$B$6
A11: Projeto Fundações | B11: 1 | C11: vb | D11: — | E11: =IF(B11>0,F11/B11,0) | F11: =CUSTOS_MACROGRUPO!$G$2*0.22*0.07 | G11: =F11/DADOS_PROJETO!$B$6
A12: Projeto Ar Condicionado / Ventilação | B12: 1 | C12: vb | D12: — | E12: =IF(B12>0,F12/B12,0) | F12: =CUSTOS_MACROGRUPO!$G$2*0.22*0.05 | G12: =F12/DADOS_PROJETO!$B$6
A13: Projeto Luminotécnico | B13: 1 | C13: vb | D13: — | E13: =IF(B13>0,F13/B13,0) | F13: =CUSTOS_MACROGRUPO!$G$2*0.22*0.03 | G13: =F13/DADOS_PROJETO!$B$6
A14: Projeto Paisagístico | B14: 1 | C14: vb | D14: — | E14: =IF(B14>0,F14/B14,0) | F14: =CUSTOS_MACROGRUPO!$G$2*0.22*0.04 | G14: =F14/DADOS_PROJETO!$B$6
A15: Projeto Interiores (áreas comuns) | B15: 1 | C15: vb | D15: — | E15: =IF(B15>0,F15/B15,0) | F15: =CUSTOS_MACROGRUPO!$G$2*0.22*0.06 | G15: =F15/DADOS_PROJETO!$B$6
A16: Projeto Automação / CFTV / Telecom | B16: 1 | C16: vb | D16: — | E16: =IF(B16>0,F16/B16,0) | F16: =CUSTOS_MACROGRUPO!$G$2*0.22*0.04 | G16: =F16/DADOS_PROJETO!$B$6
A17: Projeto Gás | B17: 1 | C17: vb | D17: — | E17: =IF(B17>0,F17/B17,0) | F17: =CUSTOS_MACROGRUPO!$G$2*0.22*0.03 | G17: =F17/DADOS_PROJETO!$B$6
A18: Compatibilização BIM | B18: 1 | C18: vb | D18: — | E18: =IF(B18>0,F18/B18,0) | F18: =CUSTOS_MACROGRUPO!$G$2*0.22*0.06 | G18: =F18/DADOS_PROJETO!$B$6
A19: Consultoria Geotécnica (SPT + laudo) | B19: 1 | C19: vb | D19: — | E19: =IF(B19>0,F19/B19,0) | F19: =CUSTOS_MACROGRUPO!$G$2*0.22*0.05 | G19: =F19/DADOS_PROJETO!$B$6
A20: Topografia (levantamento + locação) | B20: 1 | C20: vb | D20: — | E20: =IF(B20>0,F20/B20,0) | F20: =CUSTOS_MACROGRUPO!$G$2*0.22*0.04 | G20: =F20/DADOS_PROJETO!$B$6
A21: As-built | B21: 1 | C21: vb | D21: — | E21: =IF(B21>0,F21/B21,0) | F21: =CUSTOS_MACROGRUPO!$G$2*0.22*0.02 | G21: =F21/DADOS_PROJETO!$B$6
A22: Subtotal 1. PROJETOS E CONSULTORIAS | F22: =SUM(F6:F21) | G22: =SUM(G6:G21)
A24: 2. TAXAS, LICENÇAS E SEGUROS
A25: Alvará de construção | B25: 1 | C25: vb | D25: — | E25: =IF(B25>0,F25/B25,0) | F25: =CUSTOS_MACROGRUPO!$G$2*0.05*0.15 | G25: =F25/DADOS_PROJETO!$B$6
A26: Habite-se / CND obra | B26: 1 | C26: vb | D26: — | E26: =IF(B26>0,F26/B26,0) | F26: =CUSTOS_MACROGRUPO!$G$2*0.05*0.12 | G26: =F26/DADOS_PROJETO!$B$6
A27: ART/RRT (acervo técnico) | B27: 1 | C27: vb | D27: — | E27: =IF(B27>0,F27/B27,0) | F27: =CUSTOS_MACROGRUPO!$G$2*0.05*0.08 | G27: =F27/DADOS_PROJETO!$B$6
A28: Licença ambiental (se aplicável) | B28: 1 | C28: vb | D28: — | E28: =IF(B28>0,F28/B28,0) | F28: =CUSTOS_MACROGRUPO!$G$2*0.05*0.08 | G28: =F28/DADOS_PROJETO!$B$6
A29: Seguro de obra (all risks) | B29: 1 | C29: vb | D29: — | E29: =IF(B29>0,F29/B29,0) | F29: =CUSTOS_MACROGRUPO!$G$2*0.05*0.2 | G29: =F29/DADOS_PROJETO!$B$6
A30: INSS obra (contribuição patronal) | B30: 1 | C30: vb | D30: — | E30: =IF(B30>0,F30/B30,0) | F30: =CUSTOS_MACROGRUPO!$G$2*0.05*0.15 | G30: =F30/DADOS_PROJETO!$B$6
A31: ISS sobre serviços | B31: 1 | C31: vb | D31: — | E31: =IF(B31>0,F31/B31,0) | F31: =CUSTOS_MACROGRUPO!$G$2*0.05*0.1 | G31: =F31/DADOS_PROJETO!$B$6
A32: Taxas de ligação (água, energia, gás) | B32: 1 | C32: vb | D32: — | E32: =IF(B32>0,F32/B32,0) | F32: =CUSTOS_MACROGRUPO!$G$2*0.05*0.07 | G32: =F32/DADOS_PROJETO!$B$6
A33: Registro de incorporação (cartório) | B33: 1 | C33: vb | D33: — | E33: =IF(B33>0,F33/B33,0) | F33: =CUSTOS_MACROGRUPO!$G$2*0.05*0.05 | G33: =F33/DADOS_PROJETO!$B$6
A34: Subtotal 2. TAXAS, LICENÇAS E SEGUROS | F34: =SUM(F25:F33) | G34: =SUM(G25:G33)
A36: 3. EQUIPE ADMINISTRATIVA
A37: Engenheiro Residente (36 meses × R$14.000/mês) | B37: =DADOS_PROJETO!$B$17 | C37: mês | D37: Prazo | E37: =IF(B37>0,F37/B37,0) | F37: =CUSTOS_MACROGRUPO!$G$2*0.2*0.25 | G37: =F37/DADOS_PROJETO!$B$6
A38: Mestre de Obras (36 meses × R$12.000/mês) | B38: =DADOS_PROJETO!$B$17 | C38: mês | D38: Prazo | E38: =IF(B38>0,F38/B38,0) | F38: =CUSTOS_MACROGRUPO!$G$2*0.2*0.22 | G38: =F38/DADOS_PROJETO!$B$6
A39: Técnico de Segurança (36 meses × R$7.500/mês) | B39: =DADOS_PROJETO!$B$17 | C39: mês | D39: Prazo | E39: =IF(B39>0,F39/B39,0) | F39: =CUSTOS_MACROGRUPO!$G$2*0.2*0.14 | G39: =F39/DADOS_PROJETO!$B$6
A40: Almoxarife (36 meses × R$5.000/mês) | B40: =DADOS_PROJETO!$B$17 | C40: mês | D40: Prazo | E40: =IF(B40>0,F40/B40,0) | F40: =CUSTOS_MACROGRUPO!$G$2*0.2*0.1 | G40: =F40/DADOS_PROJETO!$B$6
A41: Administrativo/Auxiliar (36 meses × R$4.500/mês) | B41: =DADOS_PROJETO!$B$17 | C41: mês | D41: Prazo | E41: =IF(B41>0,F41/B41,0) | F41: =CUSTOS_MACROGRUPO!$G$2*0.2*0.09 | G41: =F41/DADOS_PROJETO!$B$6
A42: Estagiário Engenharia (24 meses × R$2.500/mês) | B42: =24 | C42: mês | D42: 24 | E42: =IF(B42>0,F42/B42,0) | F42: =CUSTOS_MACROGRUPO!$G$2*0.2*0.05 | G42: =F42/DADOS_PROJETO!$B$6
A43: Apontador (36 meses × R$4.000/mês) | B43: =DADOS_PROJETO!$B$17 | C43: mês | D43: Prazo | E43: =IF(B43>0,F43/B43,0) | F43: =CUSTOS_MACROGRUPO!$G$2*0.2*0.08 | G43: =F43/DADOS_PROJETO!$B$6
A44: Vigia/Porteiro noturno (36 meses × R$4.500/mês) | B44: =DADOS_PROJETO!$B$17 | C44: mês | D44: Prazo | E44: =IF(B44>0,F44/B44,0) | F44: =CUSTOS_MACROGRUPO!$G$2*0.2*0.07 | G44: =F44/DADOS_PROJETO!$B$6
A45: Subtotal 3. EQUIPE ADMINISTRATIVA | F45: =SUM(F37:F44) | G45: =SUM(G37:G44)
A47: 4. EQUIPE TÉCNICA DE CAMPO
A48: Encarregado Geral (36 meses) | B48: =DADOS_PROJETO!$B$17 | C48: mês | D48: Prazo | E48: =IF(B48>0,F48/B48,0) | F48: =CUSTOS_MACROGRUPO!$G$2*0.18*0.22 | G48: =F48/DADOS_PROJETO!$B$6
A49: Encarregado Estrutura (18 meses) | B49: =18 | C49: mês | D49: 18 | E49: =IF(B49>0,F49/B49,0) | F49: =CUSTOS_MACROGRUPO!$G$2*0.18*0.12 | G49: =F49/DADOS_PROJETO!$B$6
A50: Encarregado Acabamento (18 meses) | B50: =18 | C50: mês | D50: 18 | E50: =IF(B50>0,F50/B50,0) | F50: =CUSTOS_MACROGRUPO!$G$2*0.18*0.12 | G50: =F50/DADOS_PROJETO!$B$6
A51: Encarregado Instalações (12 meses) | B51: =12 | C51: mês | D51: 12 | E51: =IF(B51>0,F51/B51,0) | F51: =CUSTOS_MACROGRUPO!$G$2*0.18*0.1 | G51: =F51/DADOS_PROJETO!$B$6
A52: Servente/Ajudante geral (36 meses × 8 un) | B52: =DADOS_PROJETO!$B$17*8 | C52: mês | D52: Prazo×8 | E52: =IF(B52>0,F52/B52,0) | F52: =CUSTOS_MACROGRUPO!$G$2*0.18*0.25 | G52: =F52/DADOS_PROJETO!$B$6
A53: Pedreiro oficial (24 meses × 6 un) | B53: =24*6 | C53: mês | D53: 144 | E53: =IF(B53>0,F53/B53,0) | F53: =CUSTOS_MACROGRUPO!$G$2*0.18*0.12 | G53: =F53/DADOS_PROJETO!$B$6
A54: Carpinteiro (18 meses × 3 un) | B54: =18*3 | C54: mês | D54: 54 | E54: =IF(B54>0,F54/B54,0) | F54: =CUSTOS_MACROGRUPO!$G$2*0.18*0.07 | G54: =F54/DADOS_PROJETO!$B$6
A55: Subtotal 4. EQUIPE TÉCNICA DE CAMPO | F55: =SUM(F48:F54) | G55: =SUM(G48:G54)
A57: 5. EPCs — EQUIPAMENTOS DE PROTEÇÃO COLETIVA
A58: Bandeja salva-vidas (primária + secundária) | B58: =224 | C58: m | D58: 224 | E58: =IF(B58>0,F58/B58,0) | F58: =CUSTOS_MACROGRUPO!$G$2*0.12*0.18 | G58: =F58/DADOS_PROJETO!$B$6
A59: Tela fachadeira (proteção periférica) | B59: =0.65*DADOS_PROJETO!$B$6 | C59: m² | D59: 0.65 | E59: =IF(B59>0,F59/B59,0) | F59: =CUSTOS_MACROGRUPO!$G$2*0.12*0.14 | G59: =F59/DADOS_PROJETO!$B$6
A60: Guarda-corpo perímetro laje (metálico) | B60: =0.06*DADOS_PROJETO!$B$6 | C60: m | D60: 0.06 | E60: =IF(B60>0,F60/B60,0) | F60: =CUSTOS_MACROGRUPO!$G$2*0.12*0.1 | G60: =F60/DADOS_PROJETO!$B$6
A61: Linha de vida (cabo de aço) | B61: =0.03*DADOS_PROJETO!$B$6 | C61: m | D61: 0.03 | E61: =IF(B61>0,F61/B61,0) | F61: =CUSTOS_MACROGRUPO!$G$2*0.12*0.08 | G61: =F61/DADOS_PROJETO!$B$6
A62: Plataforma de proteção (carga/descarga) | B62: =2 | C62: un | D62: 2 | E62: =IF(B62>0,F62/B62,0) | F62: =CUSTOS_MACROGRUPO!$G$2*0.12*0.08 | G62: =F62/DADOS_PROJETO!$B$6
A63: Rede de proteção (aberturas) | B63: =0.05*DADOS_PROJETO!$B$6 | C63: m² | D63: 0.05 | E63: =IF(B63>0,F63/B63,0) | F63: =CUSTOS_MACROGRUPO!$G$2*0.12*0.06 | G63: =F63/DADOS_PROJETO!$B$6
A64: Fechamento shaft/vãos (compensado) | B64: =200 | C64: un | D64: 200 | E64: =IF(B64>0,F64/B64,0) | F64: =CUSTOS_MACROGRUPO!$G$2*0.12*0.06 | G64: =F64/DADOS_PROJETO!$B$6
A65: Sinalização de segurança (placas, cones) | B65: 1 | C65: vb | D65: — | E65: =IF(B65>0,F65/B65,0) | F65: =CUSTOS_MACROGRUPO!$G$2*0.12*0.04 | G65: =F65/DADOS_PROJETO!$B$6
A66: EPI's (capacetes, luvas, cintos, botas) | B66: 1 | C66: vb | D66: — | E66: =IF(B66>0,F66/B66,0) | F66: =CUSTOS_MACROGRUPO!$G$2*0.12*0.1 | G66: =F66/DADOS_PROJETO!$B$6
A67: Treinamentos de segurança (NR-18, NR-35) | B67: 1 | C67: vb | D67: — | E67: =IF(B67>0,F67/B67,0) | F67: =CUSTOS_MACROGRUPO!$G$2*0.12*0.06 | G67: =F67/DADOS_PROJETO!$B$6
A68: Exames médicos (admissional/periódico/demissional) | B68: 1 | C68: vb | D68: — | E68: =IF(B68>0,F68/B68,0) | F68: =CUSTOS_MACROGRUPO!$G$2*0.12*0.05 | G68: =F68/DADOS_PROJETO!$B$6
A69: PCMSO + PPRA + PGR | B69: 1 | C69: vb | D69: — | E69: =IF(B69>0,F69/B69,0) | F69: =CUSTOS_MACROGRUPO!$G$2*0.12*0.05 | G69: =F69/DADOS_PROJETO!$B$6
A70: Subtotal 5. EPCs — EQUIPAMENTOS DE PROTEÇÃO COLETIVA | F70: =SUM(F58:F69) | G70: =SUM(G58:G69)
A72: 6. EQUIPAMENTOS E MÁQUINAS
A73: Cremalheira (elevador de obra) — locação | B73: =DADOS_PROJETO!$B$17 | C73: mês | D73: Prazo | E73: =IF(B73>0,F73/B73,0) | F73: =CUSTOS_MACROGRUPO!$G$2*0.1*0.22 | G73: =F73/DADOS_PROJETO!$B$6
A74: Mini-grua / guincho (locação) | B74: =24 | C74: mês | D74: 24 | E74: =IF(B74>0,F74/B74,0) | F74: =CUSTOS_MACROGRUPO!$G$2*0.1*0.15 | G74: =F74/DADOS_PROJETO!$B$6
A75: Betoneira 400L | B75: =18 | C75: mês | D75: 18 | E75: =IF(B75>0,F75/B75,0) | F75: =CUSTOS_MACROGRUPO!$G$2*0.1*0.06 | G75: =F75/DADOS_PROJETO!$B$6
A76: Serra circular de bancada | B76: =2 | C76: un | D76: 2 | E76: =IF(B76>0,F76/B76,0) | F76: =CUSTOS_MACROGRUPO!$G$2*0.1*0.04 | G76: =F76/DADOS_PROJETO!$B$6
A77: Furadeiras/parafusadeiras | B77: =10 | C77: un | D77: 10 | E77: =IF(B77>0,F77/B77,0) | F77: =CUSTOS_MACROGRUPO!$G$2*0.1*0.03 | G77: =F77/DADOS_PROJETO!$B$6
A78: Vibrador de concreto | B78: =3 | C78: un | D78: 3 | E78: =IF(B78>0,F78/B78,0) | F78: =CUSTOS_MACROGRUPO!$G$2*0.1*0.03 | G78: =F78/DADOS_PROJETO!$B$6
A79: Nível laser / topografia obra | B79: =DADOS_PROJETO!$B$17 | C79: mês | D79: Prazo | E79: =IF(B79>0,F79/B79,0) | F79: =CUSTOS_MACROGRUPO!$G$2*0.1*0.05 | G79: =F79/DADOS_PROJETO!$B$6
A80: Andaimes metálicos (locação) | B80: =24 | C80: mês | D80: 24 | E80: =IF(B80>0,F80/B80,0) | F80: =CUSTOS_MACROGRUPO!$G$2*0.1*0.12 | G80: =F80/DADOS_PROJETO!$B$6
A81: Balancim elétrico (fachada) — locação | B81: =18 | C81: mês | D81: 18 | E81: =IF(B81>0,F81/B81,0) | F81: =CUSTOS_MACROGRUPO!$G$2*0.1*0.12 | G81: =F81/DADOS_PROJETO!$B$6
A82: Bombas submersíveis (drenagem) | B82: =2 | C82: un | D82: 2 | E82: =IF(B82>0,F82/B82,0) | F82: =CUSTOS_MACROGRUPO!$G$2*0.1*0.03 | G82: =F82/DADOS_PROJETO!$B$6
A83: Compactador (placa vibratória) | B83: =6 | C83: mês | D83: 6 | E83: =IF(B83>0,F83/B83,0) | F83: =CUSTOS_MACROGRUPO!$G$2*0.1*0.03 | G83: =F83/DADOS_PROJETO!$B$6
A84: Ferramentas diversas (reposição mensal) | B84: 1 | C84: vb | D84: — | E84: =IF(B84>0,F84/B84,0) | F84: =CUSTOS_MACROGRUPO!$G$2*0.1*0.06 | G84: =F84/DADOS_PROJETO!$B$6
A85: Combustível / energia (gerador provisório) | B85: 1 | C85: vb | D85: — | E85: =IF(B85>0,F85/B85,0) | F85: =CUSTOS_MACROGRUPO!$G$2*0.1*0.06 | G85: =F85/DADOS_PROJETO!$B$6
A86: Subtotal 6. EQUIPAMENTOS E MÁQUINAS | F86: =SUM(F73:F85) | G86: =SUM(G73:G85)
A88: 7. CANTEIRO DE OBRAS
A89: Implantação do canteiro (containers, tapumes) | B89: 1 | C89: vb | D89: — | E89: =IF(B89>0,F89/B89,0) | F89: =CUSTOS_MACROGRUPO!$G$2*0.08*0.15 | G89: =F89/DADOS_PROJETO!$B$6
A90: Instalações provisórias (água, energia, esgoto) | B90: 1 | C90: vb | D90: — | E90: =IF(B90>0,F90/B90,0) | F90: =CUSTOS_MACROGRUPO!$G$2*0.08*0.1 | G90: =F90/DADOS_PROJETO!$B$6
A91: Escritório de obra (container) | B91: =DADOS_PROJETO!$B$17 | C91: mês | D91: Prazo | E91: =IF(B91>0,F91/B91,0) | F91: =CUSTOS_MACROGRUPO!$G$2*0.08*0.1 | G91: =F91/DADOS_PROJETO!$B$6
A92: Refeitório / vestiário | B92: =DADOS_PROJETO!$B$17 | C92: mês | D92: Prazo | E92: =IF(B92>0,F92/B92,0) | F92: =CUSTOS_MACROGRUPO!$G$2*0.08*0.1 | G92: =F92/DADOS_PROJETO!$B$6
A93: Banheiros químicos (fase inicial) | B93: =6 | C93: mês | D93: 6 | E93: =IF(B93>0,F93/B93,0) | F93: =CUSTOS_MACROGRUPO!$G$2*0.08*0.05 | G93: =F93/DADOS_PROJETO!$B$6
A94: Almoxarifado (container) | B94: =DADOS_PROJETO!$B$17 | C94: mês | D94: Prazo | E94: =IF(B94>0,F94/B94,0) | F94: =CUSTOS_MACROGRUPO!$G$2*0.08*0.08 | G94: =F94/DADOS_PROJETO!$B$6
A95: Tapume metálico/madeira | B95: =80 | C95: m | D95: 80 | E95: =IF(B95>0,F95/B95,0) | F95: =CUSTOS_MACROGRUPO!$G$2*0.08*0.08 | G95: =F95/DADOS_PROJETO!$B$6
A96: Limpeza permanente (servente) | B96: =DADOS_PROJETO!$B$17 | C96: mês | D96: Prazo | E96: =IF(B96>0,F96/B96,0) | F96: =CUSTOS_MACROGRUPO!$G$2*0.08*0.1 | G96: =F96/DADOS_PROJETO!$B$6
A97: Caçamba de entulho (remoção) | B97: =250 | C97: un | D97: 250 | E97: =IF(B97>0,F97/B97,0) | F97: =CUSTOS_MACROGRUPO!$G$2*0.08*0.1 | G97: =F97/DADOS_PROJETO!$B$6
A98: Consumo de água/energia (tarifa) | B98: =DADOS_PROJETO!$B$17 | C98: mês | D98: Prazo | E98: =IF(B98>0,F98/B98,0) | F98: =CUSTOS_MACROGRUPO!$G$2*0.08*0.08 | G98: =F98/DADOS_PROJETO!$B$6
A99: Desmobilização canteiro | B99: 1 | C99: vb | D99: — | E99: =IF(B99>0,F99/B99,0) | F99: =CUSTOS_MACROGRUPO!$G$2*0.08*0.06 | G99: =F99/DADOS_PROJETO!$B$6
A100: Subtotal 7. CANTEIRO DE OBRAS | F100: =SUM(F89:F99) | G100: =SUM(G89:G99)
A102: 8. ENSAIOS E CONTROLE TECNOLÓGICO
A103: Ensaio de compressão concreto (CP's) | B103: =400 | C103: un | D103: 400 | E103: =IF(B103>0,F103/B103,0) | F103: =CUSTOS_MACROGRUPO!$G$2*0.05*0.2 | G103: =F103/DADOS_PROJETO!$B$6
A104: Ensaio de estaca (prova de carga) | B104: =3 | C104: un | D104: 3 | E104: =IF(B104>0,F104/B104,0) | F104: =CUSTOS_MACROGRUPO!$G$2*0.05*0.15 | G104: =F104/DADOS_PROJETO!$B$6
A105: Ensaio de aderência revestimento (arrancamento) | B105: =20 | C105: un | D105: 20 | E105: =IF(B105>0,F105/B105,0) | F105: =CUSTOS_MACROGRUPO!$G$2*0.05*0.08 | G105: =F105/DADOS_PROJETO!$B$6
A106: Teste hidrostático tubulações | B106: =30 | C106: un | D106: 30 | E106: =IF(B106>0,F106/B106,0) | F106: =CUSTOS_MACROGRUPO!$G$2*0.05*0.08 | G106: =F106/DADOS_PROJETO!$B$6
A107: Teste de estanqueidade (impermeabilização) | B107: =50 | C107: un | D107: 50 | E107: =IF(B107>0,F107/B107,0) | F107: =CUSTOS_MACROGRUPO!$G$2*0.05*0.08 | G107: =F107/DADOS_PROJETO!$B$6
A108: Ensaio de compactação solo (Proctor) | B108: =10 | C108: un | D108: 10 | E108: =IF(B108>0,F108/B108,0) | F108: =CUSTOS_MACROGRUPO!$G$2*0.05*0.06 | G108: =F108/DADOS_PROJETO!$B$6
...

Sheet BENCHMARK
A1: BENCHMARK — PROJETOS DE REFERÊNCIA
A3: Projeto | B3: Cidade | C3: AC (m²) | D3: NP | E3: Prazo (meses) | F3: CUB (R$/m²) | G3: R$/m² Original | H3: CUB Ratio | I3: R$/m² Atual
A4: Maison Beach | B4: Floripa | C4: 12880 | D4: 25 | E4: 36 | F4: 2753 | G4: 3291 | H4: 1.2 | I4: =H4*DADOS_PROJETO!$B$19
A5: Catena | B5: Floripa | C5: 9242 | D5: 20 | E5: 30 | F5: 3009 | G5: 3376 | H5: 1.12 | I5: =H5*DADOS_PROJETO!$B$19
A6: Connect | B6: Itajaí | C6: 13144 | D6: 28 | E6: 36 | F6: 2900 | G6: 3150 | H6: 1.09 | I6: =H6*DADOS_PROJETO!$B$19
A7: Dlohn | B7: Blumenau | C7: 8500 | D7: 18 | E7: 24 | F7: 2800 | G7: 3080 | H7: 1.1 | I7: =H7*DADOS_PROJETO!$B$19
A8: Eternity | B8: Itajaí | C8: 11200 | D8: 22 | E8: 30 | F8: 2850 | G8: 3420 | H8: 1.2 | I8: =H8*DADOS_PROJETO!$B$19
A9: Lorenzo | B9: Itajaí | C9: 9800 | D9: 20 | E9: 28 | F9: 2780 | G9: 3190 | H9: 1.15 | I9: =H9*DADOS_PROJETO!$B$19
A10: Monolyt | B10: Floripa | C10: 18500 | D10: 32 | E10: 42 | F10: 2900 | G10: 3480 | H10: 1.2 | I10: =H10*DADOS_PROJETO!$B$19
A11: Cota365 | B11: Floripa | C11: 10500 | D11: 24 | E11: 30 | F11: 2850 | G11: 3250 | H11: 1.14 | I11: =H11*DADOS_PROJETO!$B$19
A13: ESTE PROJETO | B13: =DADOS_PROJETO!B4 | C13: =DADOS_PROJETO!B6 | D13: =DADOS_PROJETO!B9 | E13: =DADOS_PROJETO!B17 | F13: =DADOS_PROJETO!B19 | G13: =CUSTOS_MACROGRUPO!G20/DADOS_PROJETO!B6 | H13: =(CUSTOS_MACROGRUPO!G20/DADOS_PROJETO!B6)/DADOS_PROJETO!B19 | I13: =CUSTOS_MACROGRUPO!G20/DADOS_PROJETO!B6
A15: COMPARATIVO POR MACROGRUPO (R$/m²)
A16: Macrogrupo | B16: Média Base | C16: Este Projeto | D16: Diferença %
A17: Gerenciamento | B17: 380 | C17: =CUSTOS_MACROGRUPO!F2 | D17: =(C17-B17)/B17
A18: Infraestrutura | B18: 210 | C18: =CUSTOS_MACROGRUPO!F4 | D18: =(C18-B18)/B18
A19: Supraestrutura | B19: 680 | C19: =CUSTOS_MACROGRUPO!F5 | D19: =(C19-B19)/B19
A20: Instalações | B20: 350 | C20: =CUSTOS_MACROGRUPO!F8 | D20: =(C20-B20)/B20
A21: Pisos | B21: 180 | C21: =CUSTOS_MACROGRUPO!F13 | D21: =(C21-B21)/B21
A22: Esquadrias | B22: 330 | C22: =CUSTOS_MACROGRUPO!F15 | D22: =(C22-B22)/B22
A23: Fachada | B23: 160 | C23: =CUSTOS_MACROGRUPO!F17 | D23: =(C23-B23)/B23

Sheet ANÁLISE_PRODUTO
A1: ANÁLISE DE PRODUTO
A3: Indicador | B3: Este Projeto | C3: Faixa Típica | D3: Status
A4: AC/UR (m²/UR) | B4: =DADOS_PROJETO!B6/DADOS_PROJETO!B7 | C4: 90-160 | D4: =IF(AND(B4>=90,B4<=160),"OK","ATENÇÃO")
A5: Custo/UR (R$) | B5: =CUSTOS_MACROGRUPO!G20/DADOS_PROJETO!B7 | C5: —
A6: R$/m² (R$/m²) | B6: =CUSTOS_MACROGRUPO!G20/DADOS_PROJETO!B6 | C6: —
A7: CUB Ratio | B7: =(CUSTOS_MACROGRUPO!G20/DADOS_PROJETO!B6)/DADOS_PROJETO!B19 | C7: 1.00-1.50 | D7: =IF(AND(B7>=1,B7<=1.5),"OK",IF(B7>1.5,"ALTO","BAIXO"))
A8: Vagas/UR | B8: =DADOS_PROJETO!B13/DADOS_PROJETO!B7 | C8: 1.0-2.0 | D8: =IF(AND(B8>=1,B8<=2),"OK","ATENÇÃO")
A9: % Tipo (NPT/NP) | B9: =DADOS_PROJETO!B10/DADOS_PROJETO!B9 | C9: 60-80% | D9: =IF(AND(B9>=0.6,B9<=0.8),"OK","ATENÇÃO")
A10: Elevador/UR | B10: =DADOS_PROJETO!B12/DADOS_PROJETO!B7 | C10: 0.015-0.030 | D10: =IF(AND(B10>=0.015,B10<=0.03),"OK","ATENÇÃO")

Sheet ALERTAS
A1: ALERTAS E VALIDAÇÕES
A2: Macrogrupo | B2: R$/m² Calculado | C2: Faixa Esperada | D2: Status
A3: =CUSTOS_MACROGRUPO!B2 | B3: =CUSTOS_MACROGRUPO!F2 | C3: =CUSTOS_MACROGRUPO!I2&" - "&CUSTOS_MACROGRUPO!J2 | D3: =CUSTOS_MACROGRUPO!K2
A4: =CUSTOS_MACROGRUPO!B3 | B4: =CUSTOS_MACROGRUPO!F3 | C4: =CUSTOS_MACROGRUPO!I3&" - "&CUSTOS_MACROGRUPO!J3 | D4: =CUSTOS_MACROGRUPO!K3
A5: =CUSTOS_MACROGRUPO!B4 | B5: =CUSTOS_MACROGRUPO!F4 | C5: =CUSTOS_MACROGRUPO!I4&" - "&CUSTOS_MACROGRUPO!J4 | D5: =CUSTOS_MACROGRUPO!K4
A6: =CUSTOS_MACROGRUPO!B5 | B6: =CUSTOS_MACROGRUPO!F5 | C6: =CUSTOS_MACROGRUPO!I5&" - "&CUSTOS_MACROGRUPO!J5 | D6: =CUSTOS_MACROGRUPO!K5
A7: =CUSTOS_MACROGRUPO!B6 | B7: =CUSTOS_MACROGRUPO!F6 | C7: =CUSTOS_MACROGRUPO!I6&" - "&CUSTOS_MACROGRUPO!J6 | D7: =CUSTOS_MACROGRUPO!K6
A8: =CUSTOS_MACROGRUPO!B7 | B8: =CUSTOS_MACROGRUPO!F7 | C8: =CUSTOS_MACROGRUPO!I7&" - "&CUSTOS_MACROGRUPO!J7 | D8: =CUSTOS_MACROGRUPO!K7
A9: =CUSTOS_MACROGRUPO!B8 | B9: =CUSTOS_MACROGRUPO!F8 | C9: =CUSTOS_MACROGRUPO!I8&" - "&CUSTOS_MACROGRUPO!J8 | D9: =CUSTOS_MACROGRUPO!K8
A10: =CUSTOS_MACROGRUPO!B9 | B10: =CUSTOS_MACROGRUPO!F9 | C10: =CUSTOS_MACROGRUPO!I9&" - "&CUSTOS_MACROGRUPO!J9 | D10: =CUSTOS_MACROGRUPO!K9
A11: =CUSTOS_MACROGRUPO!B10 | B11: =CUSTOS_MACROGRUPO!F10 | C11: =CUSTOS_MACROGRUPO!I10&" - "&CUSTOS_MACROGRUPO!J10 | D11: =CUSTOS_MACROGRUPO!K10
A12: =CUSTOS_MACROGRUPO!B11 | B12: =CUSTOS_MACROGRUPO!F11 | C12: =CUSTOS_MACROGRUPO!I11&" - "&CUSTOS_MACROGRUPO!J11 | D12: =CUSTOS_MACROGRUPO!K11
A13: =CUSTOS_MACROGRUPO!B12 | B13: =CUSTOS_MACROGRUPO!F12 | C13: =CUSTOS_MACROGRUPO!I12&" - "&CUSTOS_MACROGRUPO!J12 | D13: =CUSTOS_MACROGRUPO!K12
A14: =CUSTOS_MACROGRUPO!B13 | B14: =CUSTOS_MACROGRUPO!F13 | C14: =CUSTOS_MACROGRUPO!I13&" - "&CUSTOS_MACROGRUPO!J13 | D14: =CUSTOS_MACROGRUPO!K13
... A20: =CUSTOS_MACROGRUPO!B19 | B20: =CUSTOS_MACROGRUPO!F19 | C20: =CUSTOS_MACROGRUPO!I19&" - "&CUSTOS_MACROGRUPO!J19 | D20: =CUSTOS_MACROGRUPO!K19

Sheet NOTAS
A1: PREMISSAS E LIMITAÇÕES
A3: SOBRE ESTE TEMPLATE:
A4: Este orçamento paramétrico foi desenvolvido pela Cartesian Engenharia para estimativas rápidas de custos de obras residenciais/comerciais.
A6: BASE DE CALIBRAÇÃO:
A7: - Mediana calibrada com 18 projetos reais executados entre 2022-2024
A8: - CUB base: R$ 2.752,67 (dez/2023)
A9: - Faixas P10-P90 representam variação observada nos projetos da base
A11: COMO USAR:
A12: 1. Preencha DADOS_PROJETO com informações do empreendimento
A13: 2. Responda as 25 perguntas do BRIEFING (use os dropdowns)
A14: 3. Os custos em CUSTOS_MACROGRUPO são calculados automaticamente
A15: 4. Verifique ALERTAS para validar se os valores estão dentro das faixas esperadas
... A40: www.cartesianengenharia.com
