Workbook
Name \0: #REF!
Name \1: #REF!
Name \a: #REF!
Name \b: #REF!
Name \c: #REF!
Name \d: #REF!
Name \e: #REF!
Name \i: #REF!
Name \J: #REF!
Name \k: #REF!
Name \l: #N/A
Name \m: #REF!
Name \o: #REF!
Name \p: #REF!
Name \r: #REF!
Name \T: #REF!
Name \z: #REF!
Name ______ACR10: #REF!
Name ______ACR15: #REF!
Name ______acr20: #REF!
Name ______acr5: #REF!
Name ______ARQ1: #REF!
Name ______QT100: #REF!
Name ______QT2: #REF!
Name ______QT3: #REF!
Name ______QT4: #REF!
Name ______QT50: #REF!
Name ______QT75: #REF!
Name _____ACR10: #REF!
Name _____ACR15: #REF!
Name _____acr20: #REF!
Name _____acr5: #REF!
Name _____ARQ1: #REF!
Name _____QT100: #REF!
Name _____QT2: #REF!
Name _____QT3: #REF!
Name _____QT4: #REF!
Name _____QT50: #REF!
Name _____QT75: #REF!
Name ___ACR10: #REF!
Name ___ACR15: #REF!
Name ___acr20: #REF!
Name ___acr5: #REF!
Name ___ARQ1: #REF!
Name ___QT100: #REF!
Name ___QT2: #REF!
Name ___QT3: #REF!
Name ___QT4: #REF!
Name ___QT50: #REF!
Name ___QT75: #REF!
Name __ACR10: #REF!
Name __ACR15: #REF!
Name __acr20: #REF!
Name __acr5: #REF!
Name __ARQ1: #REF!
Name __Axe3: #REF!
Name __Axe4: #REF!
Name __htm2: #REF!
Name __htn2: #REF!
Name __iss2: #REF!

Sheet OBRA
A1: ORÇAMENTO PARAMÉTRICO
A5: Obra | B5: NOW Residence
A6: Cliente | B6: Cambert Engenharia
A7: Data | B7: 46107
A8: Versão | B8: R00
B10: Descrição | C10: Unidade | D10: Quantidade
B11: ÁREA DO TERRENO | C11: M2 | D11: 1210.5
B12: ÁREA CONSTRUÍDA | C12: M2 | D12: 13275.29
B13: NÚMERO DE APARTAMENTOS | C13: UN | D13: 144
B14: MESES DE OBRA | C14: MÊS | D14: 48
B15: NÚMERO DE PAVIMENTOS | C15: UN | D15: 24
B17: ETAPA | C17: VALOR ORÇADO | D17: % | E17: VALOR / m²
B18: GERENCIAMENTO TÉCNICO E ADMINISTRATIVO | C18: =ORÇAMENTO!N48 | D18: =C18/C$20 | E18: =C18/OBRA!$D$12
B19: MOVIMENTAÇÃO DE TERRA | C19: =ORÇAMENTO!N107 | D19: =C19/C$20 | E19: =C19/OBRA!$D$12
B20: INFRAESTRUTURA + CONTENÇÃO | C20: =ORÇAMENTO!N117+ORÇAMENTO!N135 | D20: =C20/C$20 | E20: =C20/OBRA!$D$12
B21: SUPRAESTRUTURA | C21: =ORÇAMENTO!N144 | D21: =C21/C$20 | E21: =C21/OBRA!$D$12
B22: ALVENARIA | C22: =ORÇAMENTO!N159 | D22: =C22/C$20 | E22: =C22/OBRA!$D$12
B23: INSTALAÇÕES ELÉTRICAS, HIDRÁULICAS, GLP E PREVENTIVAS | C23: =ORÇAMENTO!N182 | D23: =C23/C$20 | E23: =C23/OBRA!$D$12
B24: EQUIPAMENTOS E SISTEMAS ESPECIAIS | C24: =ORÇAMENTO!N207 | D24: =C24/C$20 | E24: =C24/OBRA!$D$12
B25: IMPERMEABILIZAÇÃO | C25: =ORÇAMENTO!N169 | D25: =C25/C$20 | E25: =C25/OBRA!$D$12
B26: REVESTIMENTOS E ACABAMENTOS INTERNOS EM PAREDE | C26: =ORÇAMENTO!N230 | D26: =C26/C$20 | E26: =C26/OBRA!$D$12
B27: REVESTIMENTOS E ACABAMENTOS INTERNOS EM TETO | C27: =ORÇAMENTO!N241 | D27: =C27/C$20 | E27: =C27/OBRA!$D$12
B28: REVESTIMENTOS E ACABAMENTOS INTERNOS EM PISO | C28: =ORÇAMENTO!N250 | D28: =C28/C$20 | E28: =C28/OBRA!$D$12
B29: PINTURA INTERNA | C29: =ORÇAMENTO!N265 | D29: =C29/C$20 | E29: =C29/OBRA!$D$12
B30: ESQUADRIAS, VIDROS E FERRAGENS | C30: =ORÇAMENTO!N274 | D30: =C30/C$20 | E30: =C30/OBRA!$D$12
B31: COBERTURA | D31: =C31/C$20 | E31: =C31/OBRA!$D$12
B32: REVESTIMENTOS E ACABAMENTOS DE FACHADA | C32: =ORÇAMENTO!N291 | D32: =C32/C$20 | E32: =C32/OBRA!$D$12
B33: SERVIÇOS COMPLEMENTARES | C33: =ORÇAMENTO!N300 | D33: =C33/C$20 | E33: =C33/OBRA!$D$12
B34: IMPREVISTOS E CONTINGENCIAS | C34: =ORÇAMENTO!N309 | D34: =C34/C$20 | E34: =C34/OBRA!$D$12
B35: TOTAL | C35: =SUM(C18:C34) | D35: =SUM(D18:D34) | E35: =SUM(E18:E34)
B36: CUB/SC | C36: 2907.85 | D36: 45689 | E36: =+E35/C36

Sheet EPC's
A1: Obra | B1: =OBRA!B5
A2: Empresa | B2: =OBRA!B6
A3: Revisão | B3: R00
A4: LEVANTAMENTO QUANTITATIVO
A6: Equipamentos de proteção coletiva
A8: Bandejas de proteção
B10: Descrição | C10: Unidade | D10: Quantidade
B11: Perímetro de projeção embasamneto | C11: m | D11: 157.96
B12: Perímetro de projeção torre | C12: m | D12: 132.16
B13: Bandeja de proteção primária | C13: m | D13: =D11+D12
B14: Bandeja de proteção secundária | C14: m | D14: =D12
A16: Guarda - corpo de desforma
B18: Descrição | C18: Unidade | D18: Quantidade
B19: Perímetro de projeção da torre | C19: m | D19: =D12
B20: Repetições de pavimentos** | C20: un | D20: 4
B21: Proteção de periferia pós desforma torre | C21: m | D21: =(D19*D20)
A23: Tela fachadeira
B25: Descrição | C25: Unidade | D25: Quantidade
B26: Perimetro da torre | C26: m | D26: =D12
B27: Altura da torre | C27: m | D27: 44.78
B28: Tela fachadeira | C28: m2 | D28: =D26*D27
A30: Fechamento removível de vãos em madeira
B32: Descrição | C32: Unidade | D32: Quantidade
B33: Área das portas de elevadores | C33: m2 | D33: =0.9*2.4
B34: Quantidade de elevadores | C34: un | D34: 2
B35: Quantidade de portas de elevadores | C35: un | D35: 26
B36: Fechamento removível de vãos em madeira | C36: m2 | D36: =D33*D35
A38: Guarda - corpo de vãos
B40: Descrição | C40: Unidade | D40: Quantidade
B41: Perímetro de vãos | C41: m | D41: 632.2144
B42: Guarda - corpo de vãos | C42: m | D42: =D41
A44: Tapume
B46: Descrição | C46: Unidade | D46: Quantidade
B47: Perímetro de encontro com pavimentação | C47: m | D47: 31
B48: Altura do tapume | C48: m | D48: 2.4
B49: Cobertura para proteção de pedestres | C49: m2 | D49: =D48*D47

Sheet ORÇAMENTO
G1: ORÇAMENTO PRELIMINAR
A4: Unidade Construtiva | B4: Célula Construtiva | C4: Etapa | D4: Subetapa | E4: Serviço | M4: ESCOLHA UMA OPÇÃO:
A5: 0 | B5: 0 | C5: 0 | D5: 0 | E5: 0 | G5: CLIENTE | I5: =OBRA!B6 | M5: FORRO VINILICO
A6: =IF(G6="UNIDADE CONSTRUTIVA",OFFSET(A6,-1,0)+1,LARGE(A$4:A5,1)) | B6: =IF(G6="UNIDADE CONSTRUTIVA",0,IF(G6="CÉLULA CONSTRUTIVA",OFFSET(B6,-1,0)+1,OFFSET(B6,-1,0))) | C6: =IF(G6="CÉLULA CONSTRUTIVA",0,IF(G6="ETAPA",OFFSET(C6,-1,0)+1,OFFSET(C6,-1,0))) | D6: =IF(G6="ETAPA",0,IF(G6="SUBETAPA",OFFSET(D6,-1,0)+1,OFFSET(D6,-1,0))) | E6: =IF(G6="Subetapa",0,IF(G6="serviço",OFFSET(E6,-1,0)+1,OFFSET(E6,-1,0))) | G6: OBRA | I6: =OBRA!B5 | M6: REBOCO
A7: =IF(G7="UNIDADE CONSTRUTIVA",OFFSET(A7,-1,0)+1,LARGE(A$4:A6,1)) | B7: =IF(G7="UNIDADE CONSTRUTIVA",0,IF(G7="CÉLULA CONSTRUTIVA",OFFSET(B7,-1,0)+1,OFFSET(B7,-1,0))) | C7: =IF(G7="CÉLULA CONSTRUTIVA",0,IF(G7="ETAPA",OFFSET(C7,-1,0)+1,OFFSET(C7,-1,0))) | D7: =IF(G7="ETAPA",0,IF(G7="SUBETAPA",OFFSET(D7,-1,0)+1,OFFSET(D7,-1,0))) | E7: =IF(G7="Subetapa",0,IF(G7="serviço",OFFSET(E7,-1,0)+1,OFFSET(E7,-1,0))) | G7: DATA | I7: =OBRA!B7 | M7: BRISE TOTAL
H8: VERSÃO | I8: =OBRA!B8
M9: ESQUADRIAS MAIORES
B10: =IF(G10="UNIDADE CONSTRUTIVA",0,IF(G10="CÉLULA CONSTRUTIVA",OFFSET(B10,-1,0)+1,OFFSET(B10,-1,0))) | C10: =IF(G10="CÉLULA CONSTRUTIVA",0,IF(G10="ETAPA",OFFSET(C10,-1,0)+1,OFFSET(C10,-1,0))) | D10: =IF(G10="ETAPA",0,IF(G10="SUBETAPA",OFFSET(D10,-1,0)+1,OFFSET(D10,-1,0))) | E10: =IF(G10="Subetapa",0,IF(G10="serviço",OFFSET(E10,-1,0)+1,OFFSET(E10,-1,0))) | H10: * IMPORTANTE: Os custos unitários apresentados nessa página possuem majoração ao custo real buscando contemplar aproximações de quantidades, perdas e outras situações previstas através de índices e indexadores no orçamento
A11: =IF(G11="UNIDADE CONSTRUTIVA",OFFSET(A11,-1,0)+1,LARGE(A$4:A10,1)) | B11: =IF(G11="UNIDADE CONSTRUTIVA",0,IF(G11="CÉLULA CONSTRUTIVA",OFFSET(B11,-1,0)+1,OFFSET(B11,-1,0))) | C11: =IF(G11="CÉLULA CONSTRUTIVA",0,IF(G11="ETAPA",OFFSET(C11,-1,0)+1,OFFSET(C11,-1,0))) | D11: =IF(G11="ETAPA",0,IF(G11="SUBETAPA",OFFSET(D11,-1,0)+1,OFFSET(D11,-1,0))) | E11: =IF(G11="Subetapa",0,IF(G11="serviço",OFFSET(E11,-1,0)+1,OFFSET(E11,-1,0))) | G11: Nivel | H11: Código | I11: Descrição | J11: Un. | K11: Quantidade | L11: Preço unitário | M11: Preço total | N11: % | O11: R$/m² | P11: Observação
A12: =IF(G12="UNIDADE CONSTRUTIVA",OFFSET(A12,-1,0)+1,LARGE(A$4:A11,1)) | B12: =IF(G12="UNIDADE CONSTRUTIVA",0,IF(G12="CÉLULA CONSTRUTIVA",OFFSET(B12,-1,0)+1,OFFSET(B12,-1,0))) | C12: =IF(G12="CÉLULA CONSTRUTIVA",0,IF(G12="ETAPA",OFFSET(C12,-1,0)+1,OFFSET(C12,-1,0))) | D12: =IF(G12="ETAPA",0,IF(G12="SUBETAPA",OFFSET(D12,-1,0)+1,OFFSET(D12,-1,0))) | E12: =IF(G12="Subetapa",0,IF(G12="serviço",OFFSET(E12,-1,0)+1,OFFSET(E12,-1,0)))
A13: =IF(G13="UNIDADE CONSTRUTIVA",OFFSET(A13,-1,0)+1,LARGE(A$4:A12,1)) | B13: =IF(G13="UNIDADE CONSTRUTIVA",0,IF(G13="CÉLULA CONSTRUTIVA",OFFSET(B13,-1,0)+1,OFFSET(B13,-1,0))) | C13: =IF(G13="CÉLULA CONSTRUTIVA",0,IF(G13="ETAPA",OFFSET(C13,-1,0)+1,OFFSET(C13,-1,0))) | D13: =IF(G13="ETAPA",0,IF(G13="SUBETAPA",OFFSET(D13,-1,0)+1,OFFSET(D13,-1,0))) | E13: =IF(G13="Subetapa",0,IF(G13="serviço",OFFSET(E13,-1,0)+1,OFFSET(E13,-1,0))) | G13: UNIDADE CONSTRUTIVA | H13: =IF(G13="Unidade Construtiva",CONCATENATE("UC ",TEXT(A13,"00")),IF(G13="Célula Construtiva",TEXT(B13,"00"),IF(G13="Etapa",CONCATENATE(TEXT(B13,"00"),".",TEXT(C13,"000")),IF(G13="Subetapa",CONCATENATE(TEXT(B13,"00"),".",TEXT(C13,"000"),".",TEXT(D13,"000")),IF(G13="Serviço",CONCATENATE(TEXT(B13,"00"),".",TEXT(C13,"000"),".",TEXT(D13,"000"),".",TEXT(E13,"000")),""))))) | I13: DESPESAS INDIRETAS | M13: =M14+M44 | N13: =M13/$M$298 | O13: =M13/OBRA!$D$12
A14: =IF(G14="UNIDADE CONSTRUTIVA",OFFSET(A14,-1,0)+1,LARGE(A$4:A13,1)) | B14: =IF(G14="UNIDADE CONSTRUTIVA",0,IF(G14="CÉLULA CONSTRUTIVA",OFFSET(B14,-1,0)+1,OFFSET(B14,-1,0))) | C14: =IF(G14="CÉLULA CONSTRUTIVA",0,IF(G14="ETAPA",OFFSET(C14,-1,0)+1,OFFSET(C14,-1,0))) | D14: =IF(G14="ETAPA",0,IF(G14="SUBETAPA",OFFSET(D14,-1,0)+1,OFFSET(D14,-1,0))) | E14: =IF(G14="Subetapa",0,IF(G14="serviço",OFFSET(E14,-1,0)+1,OFFSET(E14,-1,0))) | G14: CÉLULA CONSTRUTIVA | H14: =IF(G14="Unidade Construtiva",CONCATENATE("UC ",TEXT(A14,"00")),IF(G14="Célula Construtiva",TEXT(B14,"00"),IF(G14="Etapa",CONCATENATE(TEXT(B14,"00"),".",TEXT(C14,"000")),IF(G14="Subetapa",CONCATENATE(TEXT(B14,"00"),".",TEXT(C14,"000"),".",TEXT(D14,"000")),IF(G14="Serviço",CONCATENATE(TEXT(B14,"00"),".",TEXT(C14,"000"),".",TEXT(D14,"000"),".",TEXT(E14,"000")),""))))) | I14: GERENCIAMENTO TÉCNICO | M14: =M15+M34 | N14: =M14/$M$298 | O14: =M14/OBRA!$D$12
A15: =IF(G15="UNIDADE CONSTRUTIVA",OFFSET(A15,-1,0)+1,LARGE(A$4:A14,1)) | B15: =IF(G15="UNIDADE CONSTRUTIVA",0,IF(G15="CÉLULA CONSTRUTIVA",OFFSET(B15,-1,0)+1,OFFSET(B15,-1,0))) | C15: =IF(G15="CÉLULA CONSTRUTIVA",0,IF(G15="ETAPA",OFFSET(C15,-1,0)+1,OFFSET(C15,-1,0))) | D15: =IF(G15="ETAPA",0,IF(G15="SUBETAPA",OFFSET(D15,-1,0)+1,OFFSET(D15,-1,0))) | E15: =IF(G15="Subetapa",0,IF(G15="serviço",OFFSET(E15,-1,0)+1,OFFSET(E15,-1,0))) | G15: ETAPA | H15: =IF(G15="Unidade Construtiva",CONCATENATE("UC ",TEXT(A15,"00")),IF(G15="Célula Construtiva",TEXT(B15,"00"),IF(G15="Etapa",CONCATENATE(TEXT(B15,"00"),".",TEXT(C15,"000")),IF(G15="Subetapa",CONCATENATE(TEXT(B15,"00"),".",TEXT(C15,"000"),".",TEXT(D15,"000")),IF(G15="Serviço",CONCATENATE(TEXT(B15,"00"),".",TEXT(C15,"000"),".",TEXT(D15,"000"),".",TEXT(E15,"000")),""))))) | I15: SEGURANÇA, MEIO AMBIENTE, SAÚDE | M15: =SUM(M16:M33)/2 | N15: =M15/$M$298 | O15: =M15/OBRA!$D$12
A16: =IF(G16="UNIDADE CONSTRUTIVA",OFFSET(A16,-1,0)+1,LARGE(A$4:A15,1)) | B16: =IF(G16="UNIDADE CONSTRUTIVA",0,IF(G16="CÉLULA CONSTRUTIVA",OFFSET(B16,-1,0)+1,OFFSET(B16,-1,0))) | C16: =IF(G16="CÉLULA CONSTRUTIVA",0,IF(G16="ETAPA",OFFSET(C16,-1,0)+1,OFFSET(C16,-1,0))) | D16: =IF(G16="ETAPA",0,IF(G16="SUBETAPA",OFFSET(D16,-1,0)+1,OFFSET(D16,-1,0))) | E16: =IF(G16="Subetapa",0,IF(G16="serviço",OFFSET(E16,-1,0)+1,OFFSET(E16,-1,0))) | G16: Subetapa | H16: =IF(G16="Unidade Construtiva",CONCATENATE("UC ",TEXT(A16,"00")),IF(G16="Célula Construtiva",TEXT(B16,"00"),IF(G16="Etapa",CONCATENATE(TEXT(B16,"00"),".",TEXT(C16,"000")),IF(G16="Subetapa",CONCATENATE(TEXT(B16,"00"),".",TEXT(C16,"000"),".",TEXT(D16,"000")),IF(G16="Serviço",CONCATENATE(TEXT(B16,"00"),".",TEXT(C16,"000"),".",TEXT(D16,"000"),".",TEXT(E16,"000")),""))))) | I16: Estudos | N16: =M16/$M$298 | O16: =M16/OBRA!$D$12
A17: =IF(G17="UNIDADE CONSTRUTIVA",OFFSET(A17,-1,0)+1,LARGE(A$4:A16,1)) | B17: =IF(G17="UNIDADE CONSTRUTIVA",0,IF(G17="CÉLULA CONSTRUTIVA",OFFSET(B17,-1,0)+1,OFFSET(B17,-1,0))) | C17: =IF(G17="CÉLULA CONSTRUTIVA",0,IF(G17="ETAPA",OFFSET(C17,-1,0)+1,OFFSET(C17,-1,0))) | D17: =IF(G17="ETAPA",0,IF(G17="SUBETAPA",OFFSET(D17,-1,0)+1,OFFSET(D17,-1,0))) | E17: =IF(G17="Subetapa",0,IF(G17="serviço",OFFSET(E17,-1,0)+1,OFFSET(E17,-1,0))) | G17: Subetapa | H17: =IF(G17="Unidade Construtiva",CONCATENATE("UC ",TEXT(A17,"00")),IF(G17="Célula Construtiva",TEXT(B17,"00"),IF(G17="Etapa",CONCATENATE(TEXT(B17,"00"),".",TEXT(C17,"000")),IF(G17="Subetapa",CONCATENATE(TEXT(B17,"00"),".",TEXT(C17,"000"),".",TEXT(D17,"000")),IF(G17="Serviço",CONCATENATE(TEXT(B17,"00"),".",TEXT(C17,"000"),".",TEXT(D17,"000"),".",TEXT(E17,"000")),""))))) | I17: Projetos | M17: =SUM(M18:M27) | N17: =M17/$M$298 | O17: =M17/OBRA!$D$12
A18: =IF(G18="UNIDADE CONSTRUTIVA",OFFSET(A18,-1,0)+1,LARGE(A$4:A17,1)) | B18: =IF(G18="UNIDADE CONSTRUTIVA",0,IF(G18="CÉLULA CONSTRUTIVA",OFFSET(B18,-1,0)+1,OFFSET(B18,-1,0))) | C18: =IF(G18="CÉLULA CONSTRUTIVA",0,IF(G18="ETAPA",OFFSET(C18,-1,0)+1,OFFSET(C18,-1,0))) | D18: =IF(G18="ETAPA",0,IF(G18="SUBETAPA",OFFSET(D18,-1,0)+1,OFFSET(D18,-1,0))) | E18: =IF(G18="Subetapa",0,IF(G18="serviço",OFFSET(E18,-1,0)+1,OFFSET(E18,-1,0))) | G18: Serviço | H18: =IF(G18="Unidade Construtiva",CONCATENATE("UC ",TEXT(A18,"00")),IF(G18="Célula Construtiva",TEXT(B18,"00"),IF(G18="Etapa",CONCATENATE(TEXT(B18,"00"),".",TEXT(C18,"000")),IF(G18="Subetapa",CONCATENATE(TEXT(B18,"00"),".",TEXT(C18,"000"),".",TEXT(D18,"000")),IF(G18="Serviço",CONCATENATE(TEXT(B18,"00"),".",TEXT(C18,"000"),".",TEXT(D18,"000"),".",TEXT(E18,"000")),""))))) | I18: Projeto Arquitetônico | J18: vb | K18: 1 | L18: 412743.05 | M18: =K18*L18 | N18: =M18/$M$298 | O18: =M18/OBRA!$D$12
A19: =IF(G19="UNIDADE CONSTRUTIVA",OFFSET(A19,-1,0)+1,LARGE(A$4:A18,1)) | B19: =IF(G19="UNIDADE CONSTRUTIVA",0,IF(G19="CÉLULA CONSTRUTIVA",OFFSET(B19,-1,0)+1,OFFSET(B19,-1,0))) | C19: =IF(G19="CÉLULA CONSTRUTIVA",0,IF(G19="ETAPA",OFFSET(C19,-1,0)+1,OFFSET(C19,-1,0))) | D19: =IF(G19="ETAPA",0,IF(G19="SUBETAPA",OFFSET(D19,-1,0)+1,OFFSET(D19,-1,0))) | E19: =IF(G19="Subetapa",0,IF(G19="serviço",OFFSET(E19,-1,0)+1,OFFSET(E19,-1,0))) | G19: Serviço | H19: =IF(G19="Unidade Construtiva",CONCATENATE("UC ",TEXT(A19,"00")),IF(G19="Célula Construtiva",TEXT(B19,"00"),IF(G19="Etapa",CONCATENATE(TEXT(B19,"00"),".",TEXT(C19,"000")),IF(G19="Subetapa",CONCATENATE(TEXT(B19,"00"),".",TEXT(C19,"000"),".",TEXT(D19,"000")),IF(G19="Serviço",CONCATENATE(TEXT(B19,"00"),".",TEXT(C19,"000"),".",TEXT(D19,"000"),".",TEXT(E19,"000")),""))))) | I19: Projeto Estrutural | J19: vb | K19: 1 | L19: 343952.54 | M19: =K19*L19 | N19: =M19/$M$298 | O19: =M19/OBRA!$D$12
A20: =IF(G20="UNIDADE CONSTRUTIVA",OFFSET(A20,-1,0)+1,LARGE(A$4:A18,1)) | B20: =IF(G20="UNIDADE CONSTRUTIVA",0,IF(G20="CÉLULA CONSTRUTIVA",OFFSET(B20,-1,0)+1,OFFSET(B20,-1,0))) | C20: =IF(G20="CÉLULA CONSTRUTIVA",0,IF(G20="ETAPA",OFFSET(C20,-1,0)+1,OFFSET(C20,-1,0))) | D20: =IF(G20="ETAPA",0,IF(G20="SUBETAPA",OFFSET(D20,-1,0)+1,OFFSET(D20,-1,0))) | E20: =IF(G20="Subetapa",0,IF(G20="serviço",OFFSET(E20,-1,0)+1,OFFSET(E20,-1,0))) | G20: Serviço | H20: =IF(G20="Unidade Construtiva",CONCATENATE("UC ",TEXT(A20,"00")),IF(G20="Célula Construtiva",TEXT(B20,"00"),IF(G20="Etapa",CONCATENATE(TEXT(B20,"00"),".",TEXT(C20,"000")),IF(G20="Subetapa",CONCATENATE(TEXT(B20,"00"),".",TEXT(C20,"000"),".",TEXT(D20,"000")),IF(G20="Serviço",CONCATENATE(TEXT(B20,"00"),".",TEXT(C20,"000"),".",TEXT(D20,"000"),".",TEXT(E20,"000")),""))))) | I20: Projeto Elétrico | J20: vb | K20: 1 | L20: 206371.52 | M20: =K20*L20 | N20: =M20/$M$298 | O20: =M20/OBRA!$D$12
A21: =IF(G21="UNIDADE CONSTRUTIVA",OFFSET(A21,-1,0)+1,LARGE(A$4:A19,1)) | B21: =IF(G21="UNIDADE CONSTRUTIVA",0,IF(G21="CÉLULA CONSTRUTIVA",OFFSET(B21,-1,0)+1,OFFSET(B21,-1,0))) | C21: =IF(G21="CÉLULA CONSTRUTIVA",0,IF(G21="ETAPA",OFFSET(C21,-1,0)+1,OFFSET(C21,-1,0))) | D21: =IF(G21="ETAPA",0,IF(G21="SUBETAPA",OFFSET(D21,-1,0)+1,OFFSET(D21,-1,0))) | E21: =IF(G21="Subetapa",0,IF(G21="serviço",OFFSET(E21,-1,0)+1,OFFSET(E21,-1,0))) | G21: Serviço | H21: =IF(G21="Unidade Construtiva",CONCATENATE("UC ",TEXT(A21,"00")),IF(G21="Célula Construtiva",TEXT(B21,"00"),IF(G21="Etapa",CONCATENATE(TEXT(B21,"00"),".",TEXT(C21,"000")),IF(G21="Subetapa",CONCATENATE(TEXT(B21,"00"),".",TEXT(C21,"000"),".",TEXT(D21,"000")),IF(G21="Serviço",CONCATENATE(TEXT(B21,"00"),".",TEXT(C21,"000"),".",TEXT(D21,"000"),".",TEXT(E21,"000")),""))))) | I21: Projeto Hidrossanitário | J21: vb | K21: 1 | L21: 206371.52 | M21: =K21*L21 | N21: =M21/$M$298 | O21: =M21/OBRA!$D$12
A22: =IF(G22="UNIDADE CONSTRUTIVA",OFFSET(A22,-1,0)+1,LARGE(A$4:A19,1)) | B22: =IF(G22="UNIDADE CONSTRUTIVA",0,IF(G22="CÉLULA CONSTRUTIVA",OFFSET(B22,-1,0)+1,OFFSET(B22,-1,0))) | C22: =IF(G22="CÉLULA CONSTRUTIVA",0,IF(G22="ETAPA",OFFSET(C22,-1,0)+1,OFFSET(C22,-1,0))) | D22: =IF(G22="ETAPA",0,IF(G22="SUBETAPA",OFFSET(D22,-1,0)+1,OFFSET(D22,-1,0))) | E22: =IF(G22="Subetapa",0,IF(G22="serviço",OFFSET(E22,-1,0)+1,OFFSET(E22,-1,0))) | G22: Serviço | H22: =IF(G22="Unidade Construtiva",CONCATENATE("UC ",TEXT(A22,"00")),IF(G22="Célula Construtiva",TEXT(B22,"00"),IF(G22="Etapa",CONCATENATE(TEXT(B22,"00"),".",TEXT(C22,"000")),IF(G22="Subetapa",CONCATENATE(TEXT(B22,"00"),".",TEXT(C22,"000"),".",TEXT(D22,"000")),IF(G22="Serviço",CONCATENATE(TEXT(B22,"00"),".",TEXT(C22,"000"),".",TEXT(D22,"000"),".",TEXT(E22,"000")),""))))) | I22: Projeto Preventivo | J22: vb | K22: 1 | L22: 110064.81 | M22: =K22*L22 | N22: =M22/$M$298 | O22: =M22/OBRA!$D$12
A23: =IF(G23="UNIDADE CONSTRUTIVA",OFFSET(A23,-1,0)+1,LARGE(A$4:A20,1)) | B23: =IF(G23="UNIDADE CONSTRUTIVA",0,IF(G23="CÉLULA CONSTRUTIVA",OFFSET(B23,-1,0)+1,OFFSET(B23,-1,0))) | C23: =IF(G23="CÉLULA CONSTRUTIVA",0,IF(G23="ETAPA",OFFSET(C23,-1,0)+1,OFFSET(C23,-1,0))) | D23: =IF(G23="ETAPA",0,IF(G23="SUBETAPA",OFFSET(D23,-1,0)+1,OFFSET(D23,-1,0))) | E23: =IF(G23="Subetapa",0,IF(G23="serviço",OFFSET(E23,-1,0)+1,OFFSET(E23,-1,0))) | G23: Serviço | H23: =IF(G23="Unidade Construtiva",CONCATENATE("UC ",TEXT(A23,"00")),IF(G23="Célula Construtiva",TEXT(B23,"00"),IF(G23="Etapa",CONCATENATE(TEXT(B23,"00"),".",TEXT(C23,"000")),IF(G23="Subetapa",CONCATENATE(TEXT(B23,"00"),".",TEXT(C23,"000"),".",TEXT(D23,"000")),IF(G23="Serviço",CONCATENATE(TEXT(B23,"00"),".",TEXT(C23,"000"),".",TEXT(D23,"000"),".",TEXT(E23,"000")),""))))) | I23: Projeto Climatização | J23: vb | K23: 1 | L23: 55032.41 | M23: =K23*L23 | N23: =M23/$M$298 | O23: =M23/OBRA!$D$12
A24: =IF(G24="UNIDADE CONSTRUTIVA",OFFSET(A24,-1,0)+1,LARGE(A$4:A23,1)) | B24: =IF(G24="UNIDADE CONSTRUTIVA",0,IF(G24="CÉLULA CONSTRUTIVA",OFFSET(B24,-1,0)+1,OFFSET(B24,-1,0))) | C24: =IF(G24="CÉLULA CONSTRUTIVA",0,IF(G24="ETAPA",OFFSET(C24,-1,0)+1,OFFSET(C24,-1,0))) | D24: =IF(G24="ETAPA",0,IF(G24="SUBETAPA",OFFSET(D24,-1,0)+1,OFFSET(D24,-1,0))) | E24: =IF(G24="Subetapa",0,IF(G24="serviço",OFFSET(E24,-1,0)+1,OFFSET(E24,-1,0))) | G24: Serviço | H24: =IF(G24="Unidade Construtiva",CONCATENATE("UC ",TEXT(A24,"00")),IF(G24="Célula Construtiva",TEXT(B24,"00"),IF(G24="Etapa",CONCATENATE(TEXT(B24,"00"),".",TEXT(C24,"000")),IF(G24="Subetapa",CONCATENATE(TEXT(B24,"00"),".",TEXT(C24,"000"),".",TEXT(D24,"000")),IF(G24="Serviço",CONCATENATE(TEXT(B24,"00"),".",TEXT(C24,"000"),".",TEXT(D24,"000"),".",TEXT(E24,"000")),""))))) | I24: Projeto Paisagismo | J24: vb | K24: 1 | L24: 31690.77 | M24: =K24*L24 | N24: =M24/$M$298 | O24: =M24/OBRA!$D$12
A25: =IF(G25="UNIDADE CONSTRUTIVA",OFFSET(A25,-1,0)+1,LARGE(A$4:A22,1)) | B25: =IF(G25="UNIDADE CONSTRUTIVA",0,IF(G25="CÉLULA CONSTRUTIVA",OFFSET(B25,-1,0)+1,OFFSET(B25,-1,0))) | C25: =IF(G25="CÉLULA CONSTRUTIVA",0,IF(G25="ETAPA",OFFSET(C25,-1,0)+1,OFFSET(C25,-1,0))) | D25: =IF(G25="ETAPA",0,IF(G25="SUBETAPA",OFFSET(D25,-1,0)+1,OFFSET(D25,-1,0))) | E25: =IF(G25="Subetapa",0,IF(G25="serviço",OFFSET(E25,-1,0)+1,OFFSET(E25,-1,0))) | G25: Serviço | H25: =IF(G25="Unidade Construtiva",CONCATENATE("UC ",TEXT(A25,"00")),IF(G25="Célula Construtiva",TEXT(B25,"00"),IF(G25="Etapa",CONCATENATE(TEXT(B25,"00"),".",TEXT(C25,"000")),IF(G25="Subetapa",CONCATENATE(TEXT(B25,"00"),".",TEXT(C25,"000"),".",TEXT(D25,"000")),IF(G25="Serviço",CONCATENATE(TEXT(B25,"00"),".",TEXT(C25,"000"),".",TEXT(D25,"000"),".",TEXT(E25,"000")),""))))) | I25: Projeto Interiores | J25: vb | K25: 1 | L25: 79226.93 | M25: =K25*L25 | N25: =M25/$M$298 | O25: =M25/OBRA!$D$12
A26: =IF(G26="UNIDADE CONSTRUTIVA",OFFSET(A26,-1,0)+1,LARGE(A$4:A25,1)) | B26: =IF(G26="UNIDADE CONSTRUTIVA",0,IF(G26="CÉLULA CONSTRUTIVA",OFFSET(B26,-1,0)+1,OFFSET(B26,-1,0))) | C26: =IF(G26="CÉLULA CONSTRUTIVA",0,IF(G26="ETAPA",OFFSET(C26,-1,0)+1,OFFSET(C26,-1,0))) | D26: =IF(G26="ETAPA",0,IF(G26="SUBETAPA",OFFSET(D26,-1,0)+1,OFFSET(D26,-1,0))) | E26: =IF(G26="Subetapa",0,IF(G26="serviço",OFFSET(E26,-1,0)+1,OFFSET(E26,-1,0))) | G26: Serviço | H26: =IF(G26="Unidade Construtiva",CONCATENATE("UC ",TEXT(A26,"00")),IF(G26="Célula Construtiva",TEXT(B26,"00"),IF(G26="Etapa",CONCATENATE(TEXT(B26,"00"),".",TEXT(C26,"000")),IF(G26="Subetapa",CONCATENATE(TEXT(B26,"00"),".",TEXT(C26,"000"),".",TEXT(D26,"000")),IF(G26="Serviço",CONCATENATE(TEXT(B26,"00"),".",TEXT(C26,"000"),".",TEXT(D26,"000"),".",TEXT(E26,"000")),""))))) | I26: Projeto Fundações | J26: vb | K26: 1 | L26: 41274.3 | M26: =K26*L26 | N26: =M26/$M$298 | O26: =M26/OBRA!$D$12
A27: =IF(G27="UNIDADE CONSTRUTIVA",OFFSET(A27,-1,0)+1,LARGE(A$4:A26,1)) | B27: =IF(G27="UNIDADE CONSTRUTIVA",0,IF(G27="CÉLULA CONSTRUTIVA",OFFSET(B27,-1,0)+1,OFFSET(B27,-1,0))) | C27: =IF(G27="CÉLULA CONSTRUTIVA",0,IF(G27="ETAPA",OFFSET(C27,-1,0)+1,OFFSET(C27,-1,0))) | D27: =IF(G27="ETAPA",0,IF(G27="SUBETAPA",OFFSET(D27,-1,0)+1,OFFSET(D27,-1,0))) | E27: =IF(G27="Subetapa",0,IF(G27="serviço",OFFSET(E27,-1,0)+1,OFFSET(E27,-1,0))) | G27: Serviço | H27: =IF(G27="Unidade Construtiva",CONCATENATE("UC ",TEXT(A27,"00")),IF(G27="Célula Construtiva",TEXT(B27,"00"),IF(G27="Etapa",CONCATENATE(TEXT(B27,"00"),".",TEXT(C27,"000")),IF(G27="Subetapa",CONCATENATE(TEXT(B27,"00"),".",TEXT(C27,"000"),".",TEXT(D27,"000")),IF(G27="Serviço",CONCATENATE(TEXT(B27,"00"),".",TEXT(C27,"000"),".",TEXT(D27,"000"),".",TEXT(E27,"000")),""))))) | I27: Outros projetos | J27: vb | K27: 1 | L27: 79226.93 | M27: =K27*L27 | N27: =M27/$M$298 | O27: =M27/OBRA!$D$12
A28: =IF(G28="UNIDADE CONSTRUTIVA",OFFSET(A28,-1,0)+1,LARGE(A$4:A17,1)) | B28: =IF(G28="UNIDADE CONSTRUTIVA",0,IF(G28="CÉLULA CONSTRUTIVA",OFFSET(B28,-1,0)+1,OFFSET(B28,-1,0))) | C28: =IF(G28="CÉLULA CONSTRUTIVA",0,IF(G28="ETAPA",OFFSET(C28,-1,0)+1,OFFSET(C28,-1,0))) | D28: =IF(G28="ETAPA",0,IF(G28="SUBETAPA",OFFSET(D28,-1,0)+1,OFFSET(D28,-1,0))) | E28: =IF(G28="Subetapa",0,IF(G28="serviço",OFFSET(E28,-1,0)+1,OFFSET(E28,-1,0))) | G28: Subetapa | H28: =IF(G28="Unidade Construtiva",CONCATENATE("UC ",TEXT(A28,"00")),IF(G28="Célula Construtiva",TEXT(B28,"00"),IF(G28="Etapa",CONCATENATE(TEXT(B28,"00"),".",TEXT(C28,"000")),IF(G28="Subetapa",CONCATENATE(TEXT(B28,"00"),".",TEXT(C28,"000"),".",TEXT(D28,"000")),IF(G28="Serviço",CONCATENATE(TEXT(B28,"00"),".",TEXT(C28,"000"),".",TEXT(D28,"000"),".",TEXT(E28,"000")),""))))) | I28: Consultorias | N28: =M28/$M$298 | O28: =M28/OBRA!$D$12
A29: =IF(G29="UNIDADE CONSTRUTIVA",OFFSET(A29,-1,0)+1,LARGE(A$4:A28,1)) | B29: =IF(G29="UNIDADE CONSTRUTIVA",0,IF(G29="CÉLULA CONSTRUTIVA",OFFSET(B29,-1,0)+1,OFFSET(B29,-1,0))) | C29: =IF(G29="CÉLULA CONSTRUTIVA",0,IF(G29="ETAPA",OFFSET(C29,-1,0)+1,OFFSET(C29,-1,0))) | D29: =IF(G29="ETAPA",0,IF(G29="SUBETAPA",OFFSET(D29,-1,0)+1,OFFSET(D29,-1,0))) | E29: =IF(G29="Subetapa",0,IF(G29="serviço",OFFSET(E29,-1,0)+1,OFFSET(E29,-1,0))) | G29: Subetapa | H29: =IF(G29="Unidade Construtiva",CONCATENATE("UC ",TEXT(A29,"00")),IF(G29="Célula Construtiva",TEXT(B29,"00"),IF(G29="Etapa",CONCATENATE(TEXT(B29,"00"),".",TEXT(C29,"000")),IF(G29="Subetapa",CONCATENATE(TEXT(B29,"00"),".",TEXT(C29,"000"),".",TEXT(D29,"000")),IF(G29="Serviço",CONCATENATE(TEXT(B29,"00"),".",TEXT(C29,"000"),".",TEXT(D29,"000"),".",TEXT(E29,"000")),""))))) | I29: Ensaios e Laudos | M29: =SUM(M30:M33) | N29: =M29/$M$298 | O29: =M29/OBRA!$D$12
A30: =IF(G30="UNIDADE CONSTRUTIVA",OFFSET(A30,-1,0)+1,LARGE(A$4:A29,1)) | B30: =IF(G30="UNIDADE CONSTRUTIVA",0,IF(G30="CÉLULA CONSTRUTIVA",OFFSET(B30,-1,0)+1,OFFSET(B30,-1,0))) | C30: =IF(G30="CÉLULA CONSTRUTIVA",0,IF(G30="ETAPA",OFFSET(C30,-1,0)+1,OFFSET(C30,-1,0))) | D30: =IF(G30="ETAPA",0,IF(G30="SUBETAPA",OFFSET(D30,-1,0)+1,OFFSET(D30,-1,0))) | E30: =IF(G30="Subetapa",0,IF(G30="serviço",OFFSET(E30,-1,0)+1,OFFSET(E30,-1,0))) | G30: Serviço | H30: =IF(G30="Unidade Construtiva",CONCATENATE("UC ",TEXT(A30,"00")),IF(G30="Célula Construtiva",TEXT(B30,"00"),IF(G30="Etapa",CONCATENATE(TEXT(B30,"00"),".",TEXT(C30,"000")),IF(G30="Subetapa",CONCATENATE(TEXT(B30,"00"),".",TEXT(C30,"000"),".",TEXT(D30,"000")),IF(G30="Serviço",CONCATENATE(TEXT(B30,"00"),".",TEXT(C30,"000"),".",TEXT(D30,"000"),".",TEXT(E30,"000")),""))))) | I30: Concreto (CP) | J30: vb | K30: 1 | L30: 412743.05 | M30: =K30*L30 | N30: =M30/$M$298 | O30: =M30/OBRA!$D$12
A31: =IF(G31="UNIDADE CONSTRUTIVA",OFFSET(A31,-1,0)+1,LARGE(A$4:A28,1)) | B31: =IF(G31="UNIDADE CONSTRUTIVA",0,IF(G31="CÉLULA CONSTRUTIVA",OFFSET(B31,-1,0)+1,OFFSET(B31,-1,0))) | C31: =IF(G31="CÉLULA CONSTRUTIVA",0,IF(G31="ETAPA",OFFSET(C31,-1,0)+1,OFFSET(C31,-1,0))) | D31: =IF(G31="ETAPA",0,IF(G31="SUBETAPA",OFFSET(D31,-1,0)+1,OFFSET(D31,-1,0))) | E31: =IF(G31="Subetapa",0,IF(G31="serviço",OFFSET(E31,-1,0)+1,OFFSET(E31,-1,0))) | G31: Serviço | H31: =IF(G31="Unidade Construtiva",CONCATENATE("UC ",TEXT(A31,"00")),IF(G31="Célula Construtiva",TEXT(B31,"00"),IF(G31="Etapa",CONCATENATE(TEXT(B31,"00"),".",TEXT(C31,"000")),IF(G31="Subetapa",CONCATENATE(TEXT(B31,"00"),".",TEXT(C31,"000"),".",TEXT(D31,"000")),IF(G31="Serviço",CONCATENATE(TEXT(B31,"00"),".",TEXT(C31,"000"),".",TEXT(D31,"000"),".",TEXT(E31,"000")),""))))) | I31: Solo/Fundações | J31: vb | K31: 1 | L31: 247645.83 | M31: =K31*L31 | N31: =M31/$M$298 | O31: =M31/OBRA!$D$12
A32: =IF(G32="UNIDADE CONSTRUTIVA",OFFSET(A32,-1,0)+1,LARGE(A$4:A31,1)) | B32: =IF(G32="UNIDADE CONSTRUTIVA",0,IF(G32="CÉLULA CONSTRUTIVA",OFFSET(B32,-1,0)+1,OFFSET(B32,-1,0))) | C32: =IF(G32="CÉLULA CONSTRUTIVA",0,IF(G32="ETAPA",OFFSET(C32,-1,0)+1,OFFSET(C32,-1,0))) | D32: =IF(G32="ETAPA",0,IF(G32="SUBETAPA",OFFSET(D32,-1,0)+1,OFFSET(D32,-1,0))) | E32: =IF(G32="Subetapa",0,IF(G32="serviço",OFFSET(E32,-1,0)+1,OFFSET(E32,-1,0))) | G32: Serviço | H32: =IF(G32="Unidade Construtiva",CONCATENATE("UC ",TEXT(A32,"00")),IF(G32="Célula Construtiva",TEXT(B32,"00"),IF(G32="Etapa",CONCATENATE(TEXT(B32,"00"),".",TEXT(C32,"000")),IF(G32="Subetapa",CONCATENATE(TEXT(B32,"00"),".",TEXT(C32,"000"),".",TEXT(D32,"000")),IF(G32="Serviço",CONCATENATE(TEXT(B32,"00"),".",TEXT(C32,"000"),".",TEXT(D32,"000"),".",TEXT(E32,"000")),""))))) | I32: Estanqueidade | J32: vb | K32: 1 | L32: 12676.31 | M32: =K32*L32 | N32: =M32/$M$298 | O32: =M32/OBRA!$D$12
A33: =IF(G33="UNIDADE CONSTRUTIVA",OFFSET(A33,-1,0)+1,LARGE(A$4:A32,1)) | B33: =IF(G33="UNIDADE CONSTRUTIVA",0,IF(G33="CÉLULA CONSTRUTIVA",OFFSET(B33,-1,0)+1,OFFSET(B33,-1,0))) | C33: =IF(G33="CÉLULA CONSTRUTIVA",0,IF(G33="ETAPA",OFFSET(C33,-1,0)+1,OFFSET(C33,-1,0))) | D33: =IF(G33="ETAPA",0,IF(G33="SUBETAPA",OFFSET(D33,-1,0)+1,OFFSET(D33,-1,0))) | E33: =IF(G33="Subetapa",0,IF(G33="serviço",OFFSET(E33,-1,0)+1,OFFSET(E33,-1,0))) | G33: Serviço | H33: =IF(G33="Unidade Construtiva",CONCATENATE("UC ",TEXT(A33,"00")),IF(G33="Célula Construtiva",TEXT(B33,"00"),IF(G33="Etapa",CONCATENATE(TEXT(B33,"00"),".",TEXT(C33,"000")),IF(G33="Subetapa",CONCATENATE(TEXT(B33,"00"),".",TEXT(C33,"000"),".",TEXT(D33,"000")),IF(G33="Serviço",CONCATENATE(TEXT(B33,"00"),".",TEXT(C33,"000"),".",TEXT(D33,"000"),".",TEXT(E33,"000")),""))))) | I33: Outros ensaios | J33: vb | K33: 1 | L33: 12676.31 | M33: =K33*L33 | N33: =M33/$M$298 | O33: =M33/OBRA!$D$12
A34: =IF(G34="UNIDADE CONSTRUTIVA",OFFSET(A34,-1,0)+1,LARGE(A$4:A29,1)) | B34: =IF(G34="UNIDADE CONSTRUTIVA",0,IF(G34="CÉLULA CONSTRUTIVA",OFFSET(B34,-1,0)+1,OFFSET(B34,-1,0))) | C34: =IF(G34="CÉLULA CONSTRUTIVA",0,IF(G34="ETAPA",OFFSET(C34,-1,0)+1,OFFSET(C34,-1,0))) | D34: =IF(G34="ETAPA",0,IF(G34="SUBETAPA",OFFSET(D34,-1,0)+1,OFFSET(D34,-1,0))) | E34: =IF(G34="Subetapa",0,IF(G34="serviço",OFFSET(E34,-1,0)+1,OFFSET(E34,-1,0))) | G34: ETAPA | H34: =IF(G34="Unidade Construtiva",CONCATENATE("UC ",TEXT(A34,"00")),IF(G34="Célula Construtiva",TEXT(B34,"00"),IF(G34="Etapa",CONCATENATE(TEXT(B34,"00"),".",TEXT(C34,"000")),IF(G34="Subetapa",CONCATENATE(TEXT(B34,"00"),".",TEXT(C34,"000"),".",TEXT(D34,"000")),IF(G34="Serviço",CONCATENATE(TEXT(B34,"00"),".",TEXT(C34,"000"),".",TEXT(D34,"000"),".",TEXT(E34,"000")),""))))) | I34: TAXAS E DOCUMENTOS | M34: =M35+M36+M43 | N34: =M34/$M$298 | O34: =M34/OBRA!$D$12
A35: =IF(G35="UNIDADE CONSTRUTIVA",OFFSET(A35,-1,0)+1,LARGE(A$4:A34,1)) | B35: =IF(G35="UNIDADE CONSTRUTIVA",0,IF(G35="CÉLULA CONSTRUTIVA",OFFSET(B35,-1,0)+1,OFFSET(B35,-1,0))) | C35: =IF(G35="CÉLULA CONSTRUTIVA",0,IF(G35="ETAPA",OFFSET(C35,-1,0)+1,OFFSET(C35,-1,0))) | D35: =IF(G35="ETAPA",0,IF(G35="SUBETAPA",OFFSET(D35,-1,0)+1,OFFSET(D35,-1,0))) | E35: =IF(G35="Subetapa",0,IF(G35="serviço",OFFSET(E35,-1,0)+1,OFFSET(E35,-1,0))) | G35: Subetapa | H35: =IF(G35="Unidade Construtiva",CONCATENATE("UC ",TEXT(A35,"00")),IF(G35="Célula Construtiva",TEXT(B35,"00"),IF(G35="Etapa",CONCATENATE(TEXT(B35,"00"),".",TEXT(C35,"000")),IF(G35="Subetapa",CONCATENATE(TEXT(B35,"00"),".",TEXT(C35,"000"),".",TEXT(D35,"000")),IF(G35="Serviço",CONCATENATE(TEXT(B35,"00"),".",TEXT(C35,"000"),".",TEXT(D35,"000"),".",TEXT(E35,"000")),""))))) | I35: Seguros | M35: 27131.405 | N35: =M35/$M$298 | O35: =M35/OBRA!$D$12
A36: =IF(G36="UNIDADE CONSTRUTIVA",OFFSET(A36,-1,0)+1,LARGE(A$4:A35,1)) | B36: =IF(G36="UNIDADE CONSTRUTIVA",0,IF(G36="CÉLULA CONSTRUTIVA",OFFSET(B36,-1,0)+1,OFFSET(B36,-1,0))) | C36: =IF(G36="CÉLULA CONSTRUTIVA",0,IF(G36="ETAPA",OFFSET(C36,-1,0)+1,OFFSET(C36,-1,0))) | D36: =IF(G36="ETAPA",0,IF(G36="SUBETAPA",OFFSET(D36,-1,0)+1,OFFSET(D36,-1,0))) | E36: =IF(G36="Subetapa",0,IF(G36="serviço",OFFSET(E36,-1,0)+1,OFFSET(E36,-1,0))) | G36: Subetapa | H36: =IF(G36="Unidade Construtiva",CONCATENATE("UC ",TEXT(A36,"00")),IF(G36="Célula Construtiva",TEXT(B36,"00"),IF(G36="Etapa",CONCATENATE(TEXT(B36,"00"),".",TEXT(C36,"000")),IF(G36="Subetapa",CONCATENATE(TEXT(B36,"00"),".",TEXT(C36,"000"),".",TEXT(D36,"000")),IF(G36="Serviço",CONCATENATE(TEXT(B36,"00"),".",TEXT(C36,"000"),".",TEXT(D36,"000"),".",TEXT(E36,"000")),""))))) | I36: Licenciamentos, Taxas, Impostos | M36: =SUM(M37:M42) | N36: =M36/$M$298 | O36: =M36/OBRA!$D$12
A37: =IF(G37="UNIDADE CONSTRUTIVA",OFFSET(A37,-1,0)+1,LARGE(A$4:A36,1)) | B37: =IF(G37="UNIDADE CONSTRUTIVA",0,IF(G37="CÉLULA CONSTRUTIVA",OFFSET(B37,-1,0)+1,OFFSET(B37,-1,0))) | C37: =IF(G37="CÉLULA CONSTRUTIVA",0,IF(G37="ETAPA",OFFSET(C37,-1,0)+1,OFFSET(C37,-1,0))) | D37: =IF(G37="ETAPA",0,IF(G37="SUBETAPA",OFFSET(D37,-1,0)+1,OFFSET(D37,-1,0))) | E37: =IF(G37="Subetapa",0,IF(G37="serviço",OFFSET(E37,-1,0)+1,OFFSET(E37,-1,0))) | G37: Serviço | H37: =IF(G37="Unidade Construtiva",CONCATENATE("UC ",TEXT(A37,"00")),IF(G37="Célula Construtiva",TEXT(B37,"00"),IF(G37="Etapa",CONCATENATE(TEXT(B37,"00"),".",TEXT(C37,"000")),IF(G37="Subetapa",CONCATENATE(TEXT(B37,"00"),".",TEXT(C37,"000"),".",TEXT(D37,"000")),IF(G37="Serviço",CONCATENATE(TEXT(B37,"00"),".",TEXT(C37,"000"),".",TEXT(D37,"000"),".",TEXT(E37,"000")),""))))) | I37: Alvará | J37: vb | K37: 1 | L37: 110064.81 | M37: =K37*L37 | N37: =M37/$M$298 | O37: =M37/OBRA!$D$12
A38: =IF(G38="UNIDADE CONSTRUTIVA",OFFSET(A38,-1,0)+1,LARGE(A$4:A33,1)) | B38: =IF(G38="UNIDADE CONSTRUTIVA",0,IF(G38="CÉLULA CONSTRUTIVA",OFFSET(B38,-1,0)+1,OFFSET(B38,-1,0))) | C38: =IF(G38="CÉLULA CONSTRUTIVA",0,IF(G38="ETAPA",OFFSET(C38,-1,0)+1,OFFSET(C38,-1,0))) | D38: =IF(G38="ETAPA",0,IF(G38="SUBETAPA",OFFSET(D38,-1,0)+1,OFFSET(D38,-1,0))) | E38: =IF(G38="Subetapa",0,IF(G38="serviço",OFFSET(E38,-1,0)+1,OFFSET(E38,-1,0))) | G38: Serviço | H38: =IF(G38="Unidade Construtiva",CONCATENATE("UC ",TEXT(A38,"00")),IF(G38="Célula Construtiva",TEXT(B38,"00"),IF(G38="Etapa",CONCATENATE(TEXT(B38,"00"),".",TEXT(C38,"000")),IF(G38="Subetapa",CONCATENATE(TEXT(B38,"00"),".",TEXT(C38,"000"),".",TEXT(D38,"000")),IF(G38="Serviço",CONCATENATE(TEXT(B38,"00"),".",TEXT(C38,"000"),".",TEXT(D38,"000"),".",TEXT(E38,"000")),""))))) | I38: ARTs/RRTs | J38: vb | K38: 1 | L38: 55032.41 | M38: =K38*L38 | N38: =M38/$M$298 | O38: =M38/OBRA!$D$12
A39: =IF(G39="UNIDADE CONSTRUTIVA",OFFSET(A39,-1,0)+1,LARGE(A$4:A38,1)) | B39: =IF(G39="UNIDADE CONSTRUTIVA",0,IF(G39="CÉLULA CONSTRUTIVA",OFFSET(B39,-1,0)+1,OFFSET(B39,-1,0))) | C39: =IF(G39="CÉLULA CONSTRUTIVA",0,IF(G39="ETAPA",OFFSET(C39,-1,0)+1,OFFSET(C39,-1,0))) | D39: =IF(G39="ETAPA",0,IF(G39="SUBETAPA",OFFSET(D39,-1,0)+1,OFFSET(D39,-1,0))) | E39: =IF(G39="Subetapa",0,IF(G39="serviço",OFFSET(E39,-1,0)+1,OFFSET(E39,-1,0))) | G39: Serviço | H39: =IF(G39="Unidade Construtiva",CONCATENATE("UC ",TEXT(A39,"00")),IF(G39="Célula Construtiva",TEXT(B39,"00"),IF(G39="Etapa",CONCATENATE(TEXT(B39,"00"),".",TEXT(C39,"000")),IF(G39="Subetapa",CONCATENATE(TEXT(B39,"00"),".",TEXT(C39,"000"),".",TEXT(D39,"000")),IF(G39="Serviço",CONCATENATE(TEXT(B39,"00"),".",TEXT(C39,"000"),".",TEXT(D39,"000"),".",TEXT(E39,"000")),""))))) | I39: Bombeiros | J39: vb | K39: 1 | L39: 63381.54 | M39: =K39*L39 | N39: =M39/$M$298 | O39: =M39/OBRA!$D$12
A40: =IF(G40="UNIDADE CONSTRUTIVA",OFFSET(A40,-1,0)+1,LARGE(A$4:A35,1)) | B40: =IF(G40="UNIDADE CONSTRUTIVA",0,IF(G40="CÉLULA CONSTRUTIVA",OFFSET(B40,-1,0)+1,OFFSET(B40,-1,0))) | C40: =IF(G40="CÉLULA CONSTRUTIVA",0,IF(G40="ETAPA",OFFSET(C40,-1,0)+1,OFFSET(C40,-1,0))) | D40: =IF(G40="ETAPA",0,IF(G40="SUBETAPA",OFFSET(D40,-1,0)+1,OFFSET(D40,-1,0))) | E40: =IF(G40="Subetapa",0,IF(G40="serviço",OFFSET(E40,-1,0)+1,OFFSET(E40,-1,0))) | G40: Serviço | H40: =IF(G40="Unidade Construtiva",CONCATENATE("UC ",TEXT(A40,"00")),IF(G40="Célula Construtiva",TEXT(B40,"00"),IF(G40="Etapa",CONCATENATE(TEXT(B40,"00"),".",TEXT(C40,"000")),IF(G40="Subetapa",CONCATENATE(TEXT(B40,"00"),".",TEXT(C40,"000"),".",TEXT(D40,"000")),IF(G40="Serviço",CONCATENATE(TEXT(B40,"00"),".",TEXT(C40,"000"),".",TEXT(D40,"000"),".",TEXT(E40,"000")),""))))) | I40: Habite-se | J40: vb | K40: 1 | L40: 47536.16 | M40: =K40*L40 | N40: =M40/$M$298 | O40: =M40/OBRA!$D$12
A41: =IF(G41="UNIDADE CONSTRUTIVA",OFFSET(A41,-1,0)+1,LARGE(A$4:A40,1)) | B41: =IF(G41="UNIDADE CONSTRUTIVA",0,IF(G41="CÉLULA CONSTRUTIVA",OFFSET(B41,-1,0)+1,OFFSET(B41,-1,0))) | C41: =IF(G41="CÉLULA CONSTRUTIVA",0,IF(G41="ETAPA",OFFSET(C41,-1,0)+1,OFFSET(C41,-1,0))) | D41: =IF(G41="ETAPA",0,IF(G41="SUBETAPA",OFFSET(D41,-1,0)+1,OFFSET(D41,-1,0))) | E41: =IF(G41="Subetapa",0,IF(G41="serviço",OFFSET(E41,-1,0)+1,OFFSET(E41,-1,0))) | G41: Serviço | H41: =IF(G41="Unidade Construtiva",CONCATENATE("UC ",TEXT(A41,"00")),IF(G41="Célula Construtiva",TEXT(B41,"00"),IF(G41="Etapa",CONCATENATE(TEXT(B41,"00"),".",TEXT(C41,"000")),IF(G41="Subetapa",CONCATENATE(TEXT(B41,"00"),".",TEXT(C41,"000"),".",TEXT(D41,"000")),IF(G41="Serviço",CONCATENATE(TEXT(B41,"00"),".",TEXT(C41,"000"),".",TEXT(D41,"000"),".",TEXT(E41,"000")),""))))) | I41: Registro Incorporação | J41: vb | K41: 1 | L41: 31690.77 | M41: =K41*L41 | N41: =M41/$M$298 | O41: =M41/OBRA!$D$12
A42: =IF(G42="UNIDADE CONSTRUTIVA",OFFSET(A42,-1,0)+1,LARGE(A$4:A41,1)) | B42: =IF(G42="UNIDADE CONSTRUTIVA",0,IF(G42="CÉLULA CONSTRUTIVA",OFFSET(B42,-1,0)+1,OFFSET(B42,-1,0))) | C42: =IF(G42="CÉLULA CONSTRUTIVA",0,IF(G42="ETAPA",OFFSET(C42,-1,0)+1,OFFSET(C42,-1,0))) | D42: =IF(G42="ETAPA",0,IF(G42="SUBETAPA",OFFSET(D42,-1,0)+1,OFFSET(D42,-1,0))) | E42: =IF(G42="Subetapa",0,IF(G42="serviço",OFFSET(E42,-1,0)+1,OFFSET(E42,-1,0))) | G42: Serviço | H42: =IF(G42="Unidade Construtiva",CONCATENATE("UC ",TEXT(A42,"00")),IF(G42="Célula Construtiva",TEXT(B42,"00"),IF(G42="Etapa",CONCATENATE(TEXT(B42,"00"),".",TEXT(C42,"000")),IF(G42="Subetapa",CONCATENATE(TEXT(B42,"00"),".",TEXT(C42,"000"),".",TEXT(D42,"000")),IF(G42="Serviço",CONCATENATE(TEXT(B42,"00"),".",TEXT(C42,"000"),".",TEXT(D42,"000"),".",TEXT(E42,"000")),""))))) | I42: Outras taxas | J42: vb | K42: 1 | L42: 31690.77 | M42: =K42*L42 | N42: =M42/$M$298 | O42: =M42/OBRA!$D$12
A43: =IF(G43="UNIDADE CONSTRUTIVA",OFFSET(A43,-1,0)+1,LARGE(A$4:A36,1)) | B43: =IF(G43="UNIDADE CONSTRUTIVA",0,IF(G43="CÉLULA CONSTRUTIVA",OFFSET(B43,-1,0)+1,OFFSET(B43,-1,0))) | C43: =IF(G43="CÉLULA CONSTRUTIVA",0,IF(G43="ETAPA",OFFSET(C43,-1,0)+1,OFFSET(C43,-1,0))) | D43: =IF(G43="ETAPA",0,IF(G43="SUBETAPA",OFFSET(D43,-1,0)+1,OFFSET(D43,-1,0))) | E43: =IF(G43="Subetapa",0,IF(G43="serviço",OFFSET(E43,-1,0)+1,OFFSET(E43,-1,0))) | G43: Subetapa | H43: =IF(G43="Unidade Construtiva",CONCATENATE("UC ",TEXT(A43,"00")),IF(G43="Célula Construtiva",TEXT(B43,"00"),IF(G43="Etapa",CONCATENATE(TEXT(B43,"00"),".",TEXT(C43,"000")),IF(G43="Subetapa",CONCATENATE(TEXT(B43,"00"),".",TEXT(C43,"000"),".",TEXT(D43,"000")),IF(G43="Serviço",CONCATENATE(TEXT(B43,"00"),".",TEXT(C43,"000"),".",TEXT(D43,"000"),".",TEXT(E43,"000")),""))))) | I43: Documentos | M43: 74020.373 | N43: =M43/$M$298 | O43: =M43/OBRA!$D$12
A44: =IF(G44="UNIDADE CONSTRUTIVA",OFFSET(A44,-1,0)+1,LARGE(A$4:A43,1)) | B44: =IF(G44="UNIDADE CONSTRUTIVA",0,IF(G44="CÉLULA CONSTRUTIVA",OFFSET(B44,-1,0)+1,OFFSET(B44,-1,0))) | C44: =IF(G44="CÉLULA CONSTRUTIVA",0,IF(G44="ETAPA",OFFSET(C44,-1,0)+1,OFFSET(C44,-1,0))) | D44: =IF(G44="ETAPA",0,IF(G44="SUBETAPA",OFFSET(D44,-1,0)+1,OFFSET(D44,-1,0))) | E44: =IF(G44="Subetapa",0,IF(G44="serviço",OFFSET(E44,-1,0)+1,OFFSET(E44,-1,0))) | G44: CÉLULA CONSTRUTIVA | H44: =IF(G44="Unidade Construtiva",CONCATENATE("UC ",TEXT(A44,"00")),IF(G44="Célula Construtiva",TEXT(B44,"00"),IF(G44="Etapa",CONCATENATE(TEXT(B44,"00"),".",TEXT(C44,"000")),IF(G44="Subetapa",CONCATENATE(TEXT(B44,"00"),".",TEXT(C44,"000"),".",TEXT(D44,"000")),IF(G44="Serviço",CONCATENATE(TEXT(B44,"00"),".",TEXT(C44,"000"),".",TEXT(D44,"000"),".",TEXT(E44,"000")),""))))) | I44: GERENCIAMENTO ADMINISTRATIVO | M44: =M45+M59+M78 | N44: =M44/$M$298 | O44: =M44/OBRA!$D$12
A45: =IF(G45="UNIDADE CONSTRUTIVA",OFFSET(A45,-1,0)+1,LARGE(A$4:A44,1)) | B45: =IF(G45="UNIDADE CONSTRUTIVA",0,IF(G45="CÉLULA CONSTRUTIVA",OFFSET(B45,-1,0)+1,OFFSET(B45,-1,0))) | C45: =IF(G45="CÉLULA CONSTRUTIVA",0,IF(G45="ETAPA",OFFSET(C45,-1,0)+1,OFFSET(C45,-1,0))) | D45: =IF(G45="ETAPA",0,IF(G45="SUBETAPA",OFFSET(D45,-1,0)+1,OFFSET(D45,-1,0))) | E45: =IF(G45="Subetapa",0,IF(G45="serviço",OFFSET(E45,-1,0)+1,OFFSET(E45,-1,0))) | G45: ETAPA | H45: =IF(G45="Unidade Construtiva",CONCATENATE("UC ",TEXT(A45,"00")),IF(G45="Célula Construtiva",TEXT(B45,"00"),IF(G45="Etapa",CONCATENATE(TEXT(B45,"00"),".",TEXT(C45,"000")),IF(G45="Subetapa",CONCATENATE(TEXT(B45,"00"),".",TEXT(C45,"000"),".",TEXT(D45,"000")),IF(G45="Serviço",CONCATENATE(TEXT(B45,"00"),".",TEXT(C45,"000"),".",TEXT(D45,"000"),".",TEXT(E45,"000")),""))))) | I45: SEGURANÇA, MEIO AMBIENTE, SAÚDE | M45: =M46+M48+M58 | N45: =M45/$M$298 | O45: =M45/OBRA!$D$12
A46: =IF(G46="UNIDADE CONSTRUTIVA",OFFSET(A46,-1,0)+1,LARGE(A$4:A45,1)) | B46: =IF(G46="UNIDADE CONSTRUTIVA",0,IF(G46="CÉLULA CONSTRUTIVA",OFFSET(B46,-1,0)+1,OFFSET(B46,-1,0))) | C46: =IF(G46="CÉLULA CONSTRUTIVA",0,IF(G46="ETAPA",OFFSET(C46,-1,0)+1,OFFSET(C46,-1,0))) | D46: =IF(G46="ETAPA",0,IF(G46="SUBETAPA",OFFSET(D46,-1,0)+1,OFFSET(D46,-1,0))) | E46: =IF(G46="Subetapa",0,IF(G46="serviço",OFFSET(E46,-1,0)+1,OFFSET(E46,-1,0))) | G46: Subetapa | H46: =IF(G46="Unidade Construtiva",CONCATENATE("UC ",TEXT(A46,"00")),IF(G46="Célula Construtiva",TEXT(B46,"00"),IF(G46="Etapa",CONCATENATE(TEXT(B46,"00"),".",TEXT(C46,"000")),IF(G46="Subetapa",CONCATENATE(TEXT(B46,"00"),".",TEXT(C46,"000"),".",TEXT(D46,"000")),IF(G46="Serviço",CONCATENATE(TEXT(B46,"00"),".",TEXT(C46,"000"),".",TEXT(D46,"000"),".",TEXT(E46,"000")),""))))) | I46: Segurança do trabalho | M46: =M47 | N46: =M46/$M$298 | O46: =M46/OBRA!$D$12
A47: =IF(G47="UNIDADE CONSTRUTIVA",OFFSET(A47,-1,0)+1,LARGE(A$4:A46,1)) | B47: =IF(G47="UNIDADE CONSTRUTIVA",0,IF(G47="CÉLULA CONSTRUTIVA",OFFSET(B47,-1,0)+1,OFFSET(B47,-1,0))) | C47: =IF(G47="CÉLULA CONSTRUTIVA",0,IF(G47="ETAPA",OFFSET(C47,-1,0)+1,OFFSET(C47,-1,0))) | D47: =IF(G47="ETAPA",0,IF(G47="SUBETAPA",OFFSET(D47,-1,0)+1,OFFSET(D47,-1,0))) | E47: =IF(G47="Subetapa",0,IF(G47="serviço",OFFSET(E47,-1,0)+1,OFFSET(E47,-1,0))) | G47: Serviço | H47: =IF(G47="Unidade Construtiva",CONCATENATE("UC ",TEXT(A47,"00")),IF(G47="Célula Construtiva",TEXT(B47,"00"),IF(G47="Etapa",CONCATENATE(TEXT(B47,"00"),".",TEXT(C47,"000")),IF(G47="Subetapa",CONCATENATE(TEXT(B47,"00"),".",TEXT(C47,"000"),".",TEXT(D47,"000")),IF(G47="Serviço",CONCATENATE(TEXT(B47,"00"),".",TEXT(C47,"000"),".",TEXT(D47,"000"),".",TEXT(E47,"000")),""))))) | I47: Serviço de segurança do trabalho terceirizados | J47: mês | K47: =OBRA!D14 | L47: 2500 | M47: =K47*L47 | N47: =M47/$M$298 | O47: =M47/OBRA!$D$12
A48: =IF(G48="UNIDADE CONSTRUTIVA",OFFSET(A48,-1,0)+1,LARGE(A$4:A47,1)) | B48: =IF(G48="UNIDADE CONSTRUTIVA",0,IF(G48="CÉLULA CONSTRUTIVA",OFFSET(B48,-1,0)+1,OFFSET(B48,-1,0))) | C48: =IF(G48="CÉLULA CONSTRUTIVA",0,IF(G48="ETAPA",OFFSET(C48,-1,0)+1,OFFSET(C48,-1,0))) | D48: =IF(G48="ETAPA",0,IF(G48="SUBETAPA",OFFSET(D48,-1,0)+1,OFFSET(D48,-1,0))) | E48: =IF(G48="Subetapa",0,IF(G48="serviço",OFFSET(E48,-1,0)+1,OFFSET(E48,-1,0))) | G48: Subetapa | H48: =IF(G48="Unidade Construtiva",CONCATENATE("UC ",TEXT(A48,"00")),IF(G48="Célula Construtiva",TEXT(B48,"00"),IF(G48="Etapa",CONCATENATE(TEXT(B48,"00"),".",TEXT(C48,"000")),IF(G48="Subetapa",CONCATENATE(TEXT(B48,"00"),".",TEXT(C48,"000"),".",TEXT(D48,"000")),IF(G48="Serviço",CONCATENATE(TEXT(B48,"00"),".",TEXT(C48,"000"),".",TEXT(D48,"000"),".",TEXT(E48,"000")),""))))) | I48: Equipamentos de proteção | M48: =SUM(M49:M57) | N48: =M48/$M$298 | O48: =M48/OBRA!$D$12
A49: =IF(G49="UNIDADE CONSTRUTIVA",OFFSET(A49,-1,0)+1,LARGE(A$4:A48,1)) | B49: =IF(G49="UNIDADE CONSTRUTIVA",0,IF(G49="CÉLULA CONSTRUTIVA",OFFSET(B49,-1,0)+1,OFFSET(B49,-1,0))) | C49: =IF(G49="CÉLULA CONSTRUTIVA",0,IF(G49="ETAPA",OFFSET(C49,-1,0)+1,OFFSET(C49,-1,0))) | D49: =IF(G49="ETAPA",0,IF(G49="SUBETAPA",OFFSET(D49,-1,0)+1,OFFSET(D49,-1,0))) | E49: =IF(G49="Subetapa",0,IF(G49="serviço",OFFSET(E49,-1,0)+1,OFFSET(E49,-1,0))) | G49: Serviço | H49: =IF(G49="Unidade Construtiva",CONCATENATE("UC ",TEXT(A49,"00")),IF(G49="Célula Construtiva",TEXT(B49,"00"),IF(G49="Etapa",CONCATENATE(TEXT(B49,"00"),".",TEXT(C49,"000")),IF(G49="Subetapa",CONCATENATE(TEXT(B49,"00"),".",TEXT(C49,"000"),".",TEXT(D49,"000")),IF(G49="Serviço",CONCATENATE(TEXT(B49,"00"),".",TEXT(C49,"000"),".",TEXT(D49,"000"),".",TEXT(E49,"000")),""))))) | I49: Bandeja de protecao primaria - 1 montagem | J49: m | K49: 290 | L49: 569.3 | M49: =K49*L49 | N49: =M49/$M$298 | O49: =M49/OBRA!$D$12
A50: =IF(G50="UNIDADE CONSTRUTIVA",OFFSET(A50,-1,0)+1,LARGE(A$4:A49,1)) | B50: =IF(G50="UNIDADE CONSTRUTIVA",0,IF(G50="CÉLULA CONSTRUTIVA",OFFSET(B50,-1,0)+1,OFFSET(B50,-1,0))) | C50: =IF(G50="CÉLULA CONSTRUTIVA",0,IF(G50="ETAPA",OFFSET(C50,-1,0)+1,OFFSET(C50,-1,0))) | D50: =IF(G50="ETAPA",0,IF(G50="SUBETAPA",OFFSET(D50,-1,0)+1,OFFSET(D50,-1,0))) | E50: =IF(G50="Subetapa",0,IF(G50="serviço",OFFSET(E50,-1,0)+1,OFFSET(E50,-1,0))) | G50: Serviço | H50: =IF(G50="Unidade Construtiva",CONCATENATE("UC ",TEXT(A50,"00")),IF(G50="Célula Construtiva",TEXT(B50,"00"),IF(G50="Etapa",CONCATENATE(TEXT(B50,"00"),".",TEXT(C50,"000")),IF(G50="Subetapa",CONCATENATE(TEXT(B50,"00"),".",TEXT(C50,"000"),".",TEXT(D50,"000")),IF(G50="Serviço",CONCATENATE(TEXT(B50,"00"),".",TEXT(C50,"000"),".",TEXT(D50,"000"),".",TEXT(E50,"000")),""))))) | I50: Bandeja de protecao secundaria - 1 montagem | J50: m | K50: ='EPC''s'!D14 | L50: 210.06 | M50: =K50*L50 | N50: =M50/$M$298 | O50: =M50/OBRA!$D$12
A51: =IF(G51="UNIDADE CONSTRUTIVA",OFFSET(A51,-1,0)+1,LARGE(A$4:A49,1)) | B51: =IF(G51="UNIDADE CONSTRUTIVA",0,IF(G51="CÉLULA CONSTRUTIVA",OFFSET(B51,-1,0)+1,OFFSET(B51,-1,0))) | C51: =IF(G51="CÉLULA CONSTRUTIVA",0,IF(G51="ETAPA",OFFSET(C51,-1,0)+1,OFFSET(C51,-1,0))) | D51: =IF(G51="ETAPA",0,IF(G51="SUBETAPA",OFFSET(D51,-1,0)+1,OFFSET(D51,-1,0))) | E51: =IF(G51="Subetapa",0,IF(G51="serviço",OFFSET(E51,-1,0)+1,OFFSET(E51,-1,0))) | G51: Serviço | H51: =IF(G51="Unidade Construtiva",CONCATENATE("UC ",TEXT(A51,"00")),IF(G51="Célula Construtiva",TEXT(B51,"00"),IF(G51="Etapa",CONCATENATE(TEXT(B51,"00"),".",TEXT(C51,"000")),IF(G51="Subetapa",CONCATENATE(TEXT(B51,"00"),".",TEXT(C51,"000"),".",TEXT(D51,"000")),IF(G51="Serviço",CONCATENATE(TEXT(B51,"00"),".",TEXT(C51,"000"),".",TEXT(D51,"000"),".",TEXT(E51,"000")),""))))) | I51: Guarda corpo em laje pós - desforma | J51: m | K51: ='EPC''s'!D21 | L51: 17.89 | M51: =K51*L51 | N51: =M51/$M$298 | O51: =M51/OBRA!$D$12 | P51: Valor repassado pelo cliente - segurança - Guarda corpo em periferias (risco de queda)
A52: =IF(G52="UNIDADE CONSTRUTIVA",OFFSET(A52,-1,0)+1,LARGE(A$4:A50,1)) | B52: =IF(G52="UNIDADE CONSTRUTIVA",0,IF(G52="CÉLULA CONSTRUTIVA",OFFSET(B52,-1,0)+1,OFFSET(B52,-1,0))) | C52: =IF(G52="CÉLULA CONSTRUTIVA",0,IF(G52="ETAPA",OFFSET(C52,-1,0)+1,OFFSET(C52,-1,0))) | D52: =IF(G52="ETAPA",0,IF(G52="SUBETAPA",OFFSET(D52,-1,0)+1,OFFSET(D52,-1,0))) | E52: =IF(G52="Subetapa",0,IF(G52="serviço",OFFSET(E52,-1,0)+1,OFFSET(E52,-1,0))) | G52: Serviço | H52: =IF(G52="Unidade Construtiva",CONCATENATE("UC ",TEXT(A52,"00")),IF(G52="Célula Construtiva",TEXT(B52,"00"),IF(G52="Etapa",CONCATENATE(TEXT(B52,"00"),".",TEXT(C52,"000")),IF(G52="Subetapa",CONCATENATE(TEXT(B52,"00"),".",TEXT(C52,"000"),".",TEXT(D52,"000")),IF(G52="Serviço",CONCATENATE(TEXT(B52,"00"),".",TEXT(C52,"000"),".",TEXT(D52,"000"),".",TEXT(E52,"000")),""))))) | I52: Guarda corpo em periferias (risco de queda) | J52: m | K52: ='EPC''s'!D42 | L52: 15.38 | M52: =K52*L52 | N52: =M52/$M$298 | O52: =M52/OBRA!$D$12 | P52: Valor repassado pelo cliente - segurança - Guarda corpo em periferias (risco de queda)
A53: =IF(G53="UNIDADE CONSTRUTIVA",OFFSET(A53,-1,0)+1,LARGE(A$4:A50,1)) | B53: =IF(G53="UNIDADE CONSTRUTIVA",0,IF(G53="CÉLULA CONSTRUTIVA",OFFSET(B53,-1,0)+1,OFFSET(B53,-1,0))) | C53: =IF(G53="CÉLULA CONSTRUTIVA",0,IF(G53="ETAPA",OFFSET(C53,-1,0)+1,OFFSET(C53,-1,0))) | D53: =IF(G53="ETAPA",0,IF(G53="SUBETAPA",OFFSET(D53,-1,0)+1,OFFSET(D53,-1,0))) | E53: =IF(G53="Subetapa",0,IF(G53="serviço",OFFSET(E53,-1,0)+1,OFFSET(E53,-1,0))) | G53: Serviço | H53: =IF(G53="Unidade Construtiva",CONCATENATE("UC ",TEXT(A53,"00")),IF(G53="Célula Construtiva",TEXT(B53,"00"),IF(G53="Etapa",CONCATENATE(TEXT(B53,"00"),".",TEXT(C53,"000")),IF(G53="Subetapa",CONCATENATE(TEXT(B53,"00"),".",TEXT(C53,"000"),".",TEXT(D53,"000")),IF(G53="Serviço",CONCATENATE(TEXT(B53,"00"),".",TEXT(C53,"000"),".",TEXT(D53,"000"),".",TEXT(E53,"000")),""))))) | I53: Fechamento removivel de vaos de porta de elevador em madeira | J53: m² | K53: ='EPC''s'!D36 | L53: 47.3 | M53: =K53*L53 | N53: =M53/$M$298 | O53: =M53/OBRA!$D$12
A54: =IF(G54="UNIDADE CONSTRUTIVA",OFFSET(A54,-1,0)+1,LARGE(A$4:A53,1)) | B54: =IF(G54="UNIDADE CONSTRUTIVA",0,IF(G54="CÉLULA CONSTRUTIVA",OFFSET(B54,-1,0)+1,OFFSET(B54,-1,0))) | C54: =IF(G54="CÉLULA CONSTRUTIVA",0,IF(G54="ETAPA",OFFSET(C54,-1,0)+1,OFFSET(C54,-1,0))) | D54: =IF(G54="ETAPA",0,IF(G54="SUBETAPA",OFFSET(D54,-1,0)+1,OFFSET(D54,-1,0))) | E54: =IF(G54="Subetapa",0,IF(G54="serviço",OFFSET(E54,-1,0)+1,OFFSET(E54,-1,0))) | G54: Serviço | H54: =IF(G54="Unidade Construtiva",CONCATENATE("UC ",TEXT(A54,"00")),IF(G54="Célula Construtiva",TEXT(B54,"00"),IF(G54="Etapa",CONCATENATE(TEXT(B54,"00"),".",TEXT(C54,"000")),IF(G54="Subetapa",CONCATENATE(TEXT(B54,"00"),".",TEXT(C54,"000"),".",TEXT(D54,"000")),IF(G54="Serviço",CONCATENATE(TEXT(B54,"00"),".",TEXT(C54,"000"),".",TEXT(D54,"000"),".",TEXT(E54,"000")),""))))) | I54: Varal de seguranca com cabo de aco com cabo de aço instalado junto ao piso | J54: m | K54: ='EPC''s'!D21 | L54: 244 | M54: =K54*L54 | N54: =M54/$M$298 | O54: =M54/OBRA!$D$12
A55: =IF(G55="UNIDADE CONSTRUTIVA",OFFSET(A55,-1,0)+1,LARGE(A$4:A54,1)) | B55: =IF(G55="UNIDADE CONSTRUTIVA",0,IF(G55="CÉLULA CONSTRUTIVA",OFFSET(B55,-1,0)+1,OFFSET(B55,-1,0))) | C55: =IF(G55="CÉLULA CONSTRUTIVA",0,IF(G55="ETAPA",OFFSET(C55,-1,0)+1,OFFSET(C55,-1,0))) | D55: =IF(G55="ETAPA",0,IF(G55="SUBETAPA",OFFSET(D55,-1,0)+1,OFFSET(D55,-1,0))) | E55: =IF(G55="Subetapa",0,IF(G55="serviço",OFFSET(E55,-1,0)+1,OFFSET(E55,-1,0))) | G55: Serviço | H55: =IF(G55="Unidade Construtiva",CONCATENATE("UC ",TEXT(A55,"00")),IF(G55="Célula Construtiva",TEXT(B55,"00"),IF(G55="Etapa",CONCATENATE(TEXT(B55,"00"),".",TEXT(C55,"000")),IF(G55="Subetapa",CONCATENATE(TEXT(B55,"00"),".",TEXT(C55,"000"),".",TEXT(D55,"000")),IF(G55="Serviço",CONCATENATE(TEXT(B55,"00"),".",TEXT(C55,"000"),".",TEXT(D55,"000"),".",TEXT(E55,"000")),""))))) | I55: Tela fachadeira - Tela mosqueteira reforçada com impressão digital | J55: m² | K55: 5310.12 | L55: 31.09 | M55: =K55*L55 | N55: =M55/$M$298 | O55: =M55/OBRA!$D$12
A56: =IF(G56="UNIDADE CONSTRUTIVA",OFFSET(A56,-1,0)+1,LARGE(A$4:A55,1)) | B56: =IF(G56="UNIDADE CONSTRUTIVA",0,IF(G56="CÉLULA CONSTRUTIVA",OFFSET(B56,-1,0)+1,OFFSET(B56,-1,0))) | C56: =IF(G56="CÉLULA CONSTRUTIVA",0,IF(G56="ETAPA",OFFSET(C56,-1,0)+1,OFFSET(C56,-1,0))) | D56: =IF(G56="ETAPA",0,IF(G56="SUBETAPA",OFFSET(D56,-1,0)+1,OFFSET(D56,-1,0))) | E56: =IF(G56="Subetapa",0,IF(G56="serviço",OFFSET(E56,-1,0)+1,OFFSET(E56,-1,0))) | G56: Serviço | H56: =IF(G56="Unidade Construtiva",CONCATENATE("UC ",TEXT(A56,"00")),IF(G56="Célula Construtiva",TEXT(B56,"00"),IF(G56="Etapa",CONCATENATE(TEXT(B56,"00"),".",TEXT(C56,"000")),IF(G56="Subetapa",CONCATENATE(TEXT(B56,"00"),".",TEXT(C56,"000"),".",TEXT(D56,"000")),IF(G56="Serviço",CONCATENATE(TEXT(B56,"00"),".",TEXT(C56,"000"),".",TEXT(D56,"000"),".",TEXT(E56,"000")),""))))) | I56: Equipamento de proteção individual | J56: vb | K56: 1 | L56: 192613.42 | M56: =K56*L56 | N56: =M56/$M$298 | O56: =M56/OBRA!$D$12
A57: =IF(G57="UNIDADE CONSTRUTIVA",OFFSET(A57,-1,0)+1,LARGE(A$4:A56,1)) | B57: =IF(G57="UNIDADE CONSTRUTIVA",0,IF(G57="CÉLULA CONSTRUTIVA",OFFSET(B57,-1,0)+1,OFFSET(B57,-1,0))) | C57: =IF(G57="CÉLULA CONSTRUTIVA",0,IF(G57="ETAPA",OFFSET(C57,-1,0)+1,OFFSET(C57,-1,0))) | D57: =IF(G57="ETAPA",0,IF(G57="SUBETAPA",OFFSET(D57,-1,0)+1,OFFSET(D57,-1,0))) | E57: =IF(G57="Subetapa",0,IF(G57="serviço",OFFSET(E57,-1,0)+1,OFFSET(E57,-1,0))) | G57: Serviço | H57: =IF(G57="Unidade Construtiva",CONCATENATE("UC ",TEXT(A57,"00")),IF(G57="Célula Construtiva",TEXT(B57,"00"),IF(G57="Etapa",CONCATENATE(TEXT(B57,"00"),".",TEXT(C57,"000")),IF(G57="Subetapa",CONCATENATE(TEXT(B57,"00"),".",TEXT(C57,"000"),".",TEXT(D57,"000")),IF(G57="Serviço",CONCATENATE(TEXT(B57,"00"),".",TEXT(C57,"000"),".",TEXT(D57,"000"),".",TEXT(E57,"000")),""))))) | I57: Placas de Sinalização de Obra | J57: vb | K57: 1 | L57: 3615.5038 | M57: =K57*L57 | N57: =M57/$M$298 | O57: =M57/OBRA!$D$12
A58: =IF(G58="UNIDADE CONSTRUTIVA",OFFSET(A58,-1,0)+1,LARGE(A$4:A57,1)) | B58: =IF(G58="UNIDADE CONSTRUTIVA",0,IF(G58="CÉLULA CONSTRUTIVA",OFFSET(B58,-1,0)+1,OFFSET(B58,-1,0))) | C58: =IF(G58="CÉLULA CONSTRUTIVA",0,IF(G58="ETAPA",OFFSET(C58,-1,0)+1,OFFSET(C58,-1,0))) | D58: =IF(G58="ETAPA",0,IF(G58="SUBETAPA",OFFSET(D58,-1,0)+1,OFFSET(D58,-1,0))) | E58: =IF(G58="Subetapa",0,IF(G58="serviço",OFFSET(E58,-1,0)+1,OFFSET(E58,-1,0))) | G58: Subetapa | H58: =IF(G58="Unidade Construtiva",CONCATENATE("UC ",TEXT(A58,"00")),IF(G58="Célula Construtiva",TEXT(B58,"00"),IF(G58="Etapa",CONCATENATE(TEXT(B58,"00"),".",TEXT(C58,"000")),IF(G58="Subetapa",CONCATENATE(TEXT(B58,"00"),".",TEXT(C58,"000"),".",TEXT(D58,"000")),IF(G58="Serviço",CONCATENATE(TEXT(B58,"00"),".",TEXT(C58,"000"),".",TEXT(D58,"000"),".",TEXT(E58,"000")),""))))) | I58: Meio ambiente | M58: 42591.549 | N58: =M58/$M$298 | O58: =M58/OBRA!$D$12
A59: =IF(G59="UNIDADE CONSTRUTIVA",OFFSET(A59,-1,0)+1,LARGE(A$4:A58,1)) | B59: =IF(G59="UNIDADE CONSTRUTIVA",0,IF(G59="CÉLULA CONSTRUTIVA",OFFSET(B59,-1,0)+1,OFFSET(B59,-1,0))) | C59: =IF(G59="CÉLULA CONSTRUTIVA",0,IF(G59="ETAPA",OFFSET(C59,-1,0)+1,OFFSET(C59,-1,0))) | D59: =IF(G59="ETAPA",0,IF(G59="SUBETAPA",OFFSET(D59,-1,0)+1,OFFSET(D59,-1,0))) | E59: =IF(G59="Subetapa",0,IF(G59="serviço",OFFSET(E59,-1,0)+1,OFFSET(E59,-1,0))) | G59: ETAPA | H59: =IF(G59="Unidade Construtiva",CONCATENATE("UC ",TEXT(A59,"00")),IF(G59="Célula Construtiva",TEXT(B59,"00"),IF(G59="Etapa",CONCATENATE(TEXT(B59,"00"),".",TEXT(C59,"000")),IF(G59="Subetapa",CONCATENATE(TEXT(B59,"00"),".",TEXT(C59,"000"),".",TEXT(D59,"000")),IF(G59="Serviço",CONCATENATE(TEXT(B59,"00"),".",TEXT(C59,"000"),".",TEXT(D59,"000"),".",TEXT(E59,"000")),""))))) | I59: ADMINISTRAÇÃO E CANTEIRO DE OBRA | M59: =M60+M66+M68+M77 | N59: =M59/$M$298 | O59: =M59/OBRA!$D$12
A60: =IF(G60="UNIDADE CONSTRUTIVA",OFFSET(A60,-1,0)+1,LARGE(A$4:A59,1)) | B60: =IF(G60="UNIDADE CONSTRUTIVA",0,IF(G60="CÉLULA CONSTRUTIVA",OFFSET(B60,-1,0)+1,OFFSET(B60,-1,0))) | C60: =IF(G60="CÉLULA CONSTRUTIVA",0,IF(G60="ETAPA",OFFSET(C60,-1,0)+1,OFFSET(C60,-1,0))) | D60: =IF(G60="ETAPA",0,IF(G60="SUBETAPA",OFFSET(D60,-1,0)+1,OFFSET(D60,-1,0))) | E60: =IF(G60="Subetapa",0,IF(G60="serviço",OFFSET(E60,-1,0)+1,OFFSET(E60,-1,0))) | G60: Subetapa | H60: =IF(G60="Unidade Construtiva",CONCATENATE("UC ",TEXT(A60,"00")),IF(G60="Célula Construtiva",TEXT(B60,"00"),IF(G60="Etapa",CONCATENATE(TEXT(B60,"00"),".",TEXT(C60,"000")),IF(G60="Subetapa",CONCATENATE(TEXT(B60,"00"),".",TEXT(C60,"000"),".",TEXT(D60,"000")),IF(G60="Serviço",CONCATENATE(TEXT(B60,"00"),".",TEXT(C60,"000"),".",TEXT(D60,"000"),".",TEXT(E60,"000")),""))))) | I60: Equipe de Gestão e Apoio | M60: =SUM(M61:M65) | N60: =M60/$M$298 | O60: =M60/OBRA!$D$12
A61: =IF(G61="UNIDADE CONSTRUTIVA",OFFSET(A61,-1,0)+1,LARGE(A$4:A60,1)) | B61: =IF(G61="UNIDADE CONSTRUTIVA",0,IF(G61="CÉLULA CONSTRUTIVA",OFFSET(B61,-1,0)+1,OFFSET(B61,-1,0))) | C61: =IF(G61="CÉLULA CONSTRUTIVA",0,IF(G61="ETAPA",OFFSET(C61,-1,0)+1,OFFSET(C61,-1,0))) | D61: =IF(G61="ETAPA",0,IF(G61="SUBETAPA",OFFSET(D61,-1,0)+1,OFFSET(D61,-1,0))) | E61: =IF(G61="Subetapa",0,IF(G61="serviço",OFFSET(E61,-1,0)+1,OFFSET(E61,-1,0))) | G61: Serviço | H61: =IF(G61="Unidade Construtiva",CONCATENATE("UC ",TEXT(A61,"00")),IF(G61="Célula Construtiva",TEXT(B61,"00"),IF(G61="Etapa",CONCATENATE(TEXT(B61,"00"),".",TEXT(C61,"000")),IF(G61="Subetapa",CONCATENATE(TEXT(B61,"00"),".",TEXT(C61,"000"),".",TEXT(D61,"000")),IF(G61="Serviço",CONCATENATE(TEXT(B61,"00"),".",TEXT(C61,"000"),".",TEXT(D61,"000"),".",TEXT(E61,"000")),""))))) | I61: Engenheiro Civil | J61: mês | K61: 48 | L61: 12038.34 | M61: =K61*L61 | N61: =M61/$M$298 | O61: =M61/OBRA!$D$12
A62: =IF(G62="UNIDADE CONSTRUTIVA",OFFSET(A62,-1,0)+1,LARGE(A$4:A61,1)) | B62: =IF(G62="UNIDADE CONSTRUTIVA",0,IF(G62="CÉLULA CONSTRUTIVA",OFFSET(B62,-1,0)+1,OFFSET(B62,-1,0))) | C62: =IF(G62="CÉLULA CONSTRUTIVA",0,IF(G62="ETAPA",OFFSET(C62,-1,0)+1,OFFSET(C62,-1,0))) | D62: =IF(G62="ETAPA",0,IF(G62="SUBETAPA",OFFSET(D62,-1,0)+1,OFFSET(D62,-1,0))) | E62: =IF(G62="Subetapa",0,IF(G62="serviço",OFFSET(E62,-1,0)+1,OFFSET(E62,-1,0))) | G62: Serviço | H62: =IF(G62="Unidade Construtiva",CONCATENATE("UC ",TEXT(A62,"00")),IF(G62="Célula Construtiva",TEXT(B62,"00"),IF(G62="Etapa",CONCATENATE(TEXT(B62,"00"),".",TEXT(C62,"000")),IF(G62="Subetapa",CONCATENATE(TEXT(B62,"00"),".",TEXT(C62,"000"),".",TEXT(D62,"000")),IF(G62="Serviço",CONCATENATE(TEXT(B62,"00"),".",TEXT(C62,"000"),".",TEXT(D62,"000"),".",TEXT(E62,"000")),""))))) | I62: Mestre Geral | J62: mês | K62: 48 | L62: 8025.56 | M62: =K62*L62 | N62: =M62/$M$298 | O62: =M62/OBRA!$D$12
A63: =IF(G63="UNIDADE CONSTRUTIVA",OFFSET(A63,-1,0)+1,LARGE(A$4:A62,1)) | B63: =IF(G63="UNIDADE CONSTRUTIVA",0,IF(G63="CÉLULA CONSTRUTIVA",OFFSET(B63,-1,0)+1,OFFSET(B63,-1,0))) | C63: =IF(G63="CÉLULA CONSTRUTIVA",0,IF(G63="ETAPA",OFFSET(C63,-1,0)+1,OFFSET(C63,-1,0))) | D63: =IF(G63="ETAPA",0,IF(G63="SUBETAPA",OFFSET(D63,-1,0)+1,OFFSET(D63,-1,0))) | E63: =IF(G63="Subetapa",0,IF(G63="serviço",OFFSET(E63,-1,0)+1,OFFSET(E63,-1,0))) | G63: Serviço | H63: =IF(G63="Unidade Construtiva",CONCATENATE("UC ",TEXT(A63,"00")),IF(G63="Célula Construtiva",TEXT(B63,"00"),IF(G63="Etapa",CONCATENATE(TEXT(B63,"00"),".",TEXT(C63,"000")),IF(G63="Subetapa",CONCATENATE(TEXT(B63,"00"),".",TEXT(C63,"000"),".",TEXT(D63,"000")),IF(G63="Serviço",CONCATENATE(TEXT(B63,"00"),".",TEXT(C63,"000"),".",TEXT(D63,"000"),".",TEXT(E63,"000")),""))))) | I63: Estagiário de Engenharia | J63: mês | K63: =IFERROR(OBRA!$D$14,0) | L63: 2200 | M63: =K63*L63 | N63: =M63/$M$298 | O63: =M63/OBRA!$D$12
A64: =IF(G64="UNIDADE CONSTRUTIVA",OFFSET(A64,-1,0)+1,LARGE(A$4:A63,1)) | B64: =IF(G64="UNIDADE CONSTRUTIVA",0,IF(G64="CÉLULA CONSTRUTIVA",OFFSET(B64,-1,0)+1,OFFSET(B64,-1,0))) | C64: =IF(G64="CÉLULA CONSTRUTIVA",0,IF(G64="ETAPA",OFFSET(C64,-1,0)+1,OFFSET(C64,-1,0))) | D64: =IF(G64="ETAPA",0,IF(G64="SUBETAPA",OFFSET(D64,-1,0)+1,OFFSET(D64,-1,0))) | E64: =IF(G64="Subetapa",0,IF(G64="serviço",OFFSET(E64,-1,0)+1,OFFSET(E64,-1,0))) | G64: Serviço | H64: =IF(G64="Unidade Construtiva",CONCATENATE("UC ",TEXT(A64,"00")),IF(G64="Célula Construtiva",TEXT(B64,"00"),IF(G64="Etapa",CONCATENATE(TEXT(B64,"00"),".",TEXT(C64,"000")),IF(G64="Subetapa",CONCATENATE(TEXT(B64,"00"),".",TEXT(C64,"000"),".",TEXT(D64,"000")),IF(G64="Serviço",CONCATENATE(TEXT(B64,"00"),".",TEXT(C64,"000"),".",TEXT(D64,"000"),".",TEXT(E64,"000")),""))))) | I64: Operador de Guincho | J64: mês | K64: =K81 | L64: 3500 | M64: =K64*L64 | N64: =M64/$M$298 | O64: =M64/OBRA!$D$12
A65: =IF(G65="UNIDADE CONSTRUTIVA",OFFSET(A65,-1,0)+1,LARGE(A$4:A64,1)) | B65: =IF(G65="UNIDADE CONSTRUTIVA",0,IF(G65="CÉLULA CONSTRUTIVA",OFFSET(B65,-1,0)+1,OFFSET(B65,-1,0))) | C65: =IF(G65="CÉLULA CONSTRUTIVA",0,IF(G65="ETAPA",OFFSET(C65,-1,0)+1,OFFSET(C65,-1,0))) | D65: =IF(G65="ETAPA",0,IF(G65="SUBETAPA",OFFSET(D65,-1,0)+1,OFFSET(D65,-1,0))) | E65: =IF(G65="Subetapa",0,IF(G65="serviço",OFFSET(E65,-1,0)+1,OFFSET(E65,-1,0))) | G65: Serviço | H65: =IF(G65="Unidade Construtiva",CONCATENATE("UC ",TEXT(A65,"00")),IF(G65="Célula Construtiva",TEXT(B65,"00"),IF(G65="Etapa",CONCATENATE(TEXT(B65,"00"),".",TEXT(C65,"000")),IF(G65="Subetapa",CONCATENATE(TEXT(B65,"00"),".",TEXT(C65,"000"),".",TEXT(D65,"000")),IF(G65="Serviço",CONCATENATE(TEXT(B65,"00"),".",TEXT(C65,"000"),".",TEXT(D65,"000"),".",TEXT(E65,"000")),""))))) | I65: Equipe de apoio | J65: mês | K65: =IFERROR(OBRA!$D$14,0) | L65: 6918.4 | M65: =K65*L65 | N65: =M65/$M$298 | O65: =M65/OBRA!$D$12 | P65: 2 seventes (84% de encargos)
A66: =IF(G66="UNIDADE CONSTRUTIVA",OFFSET(A66,-1,0)+1,LARGE(A$4:A65,1)) | B66: =IF(G66="UNIDADE CONSTRUTIVA",0,IF(G66="CÉLULA CONSTRUTIVA",OFFSET(B66,-1,0)+1,OFFSET(B66,-1,0))) | C66: =IF(G66="CÉLULA CONSTRUTIVA",0,IF(G66="ETAPA",OFFSET(C66,-1,0)+1,OFFSET(C66,-1,0))) | D66: =IF(G66="ETAPA",0,IF(G66="SUBETAPA",OFFSET(D66,-1,0)+1,OFFSET(D66,-1,0))) | E66: =IF(G66="Subetapa",0,IF(G66="serviço",OFFSET(E66,-1,0)+1,OFFSET(E66,-1,0))) | G66: Subetapa | H66: =IF(G66="Unidade Construtiva",CONCATENATE("UC ",TEXT(A66,"00")),IF(G66="Célula Construtiva",TEXT(B66,"00"),IF(G66="Etapa",CONCATENATE(TEXT(B66,"00"),".",TEXT(C66,"000")),IF(G66="Subetapa",CONCATENATE(TEXT(B66,"00"),".",TEXT(C66,"000"),".",TEXT(D66,"000")),IF(G66="Serviço",CONCATENATE(TEXT(B66,"00"),".",TEXT(C66,"000"),".",TEXT(D66,"000"),".",TEXT(E66,"000")),""))))) | I66: Operação Inicial do Canteiro | M66: =M67 | N66: =M66/$M$298 | O66: =M66/OBRA!$D$12
A67: =IF(G67="UNIDADE CONSTRUTIVA",OFFSET(A67,-1,0)+1,LARGE(A$4:A66,1)) | B67: =IF(G67="UNIDADE CONSTRUTIVA",0,IF(G67="CÉLULA CONSTRUTIVA",OFFSET(B67,-1,0)+1,OFFSET(B67,-1,0))) | C67: =IF(G67="CÉLULA CONSTRUTIVA",0,IF(G67="ETAPA",OFFSET(C67,-1,0)+1,OFFSET(C67,-1,0))) | D67: =IF(G67="ETAPA",0,IF(G67="SUBETAPA",OFFSET(D67,-1,0)+1,OFFSET(D67,-1,0))) | E67: =IF(G67="Subetapa",0,IF(G67="serviço",OFFSET(E67,-1,0)+1,OFFSET(E67,-1,0))) | G67: Serviço | H67: =IF(G67="Unidade Construtiva",CONCATENATE("UC ",TEXT(A67,"00")),IF(G67="Célula Construtiva",TEXT(B67,"00"),IF(G67="Etapa",CONCATENATE(TEXT(B67,"00"),".",TEXT(C67,"000")),IF(G67="Subetapa",CONCATENATE(TEXT(B67,"00"),".",TEXT(C67,"000"),".",TEXT(D67,"000")),IF(G67="Serviço",CONCATENATE(TEXT(B67,"00"),".",TEXT(C67,"000"),".",TEXT(D67,"000"),".",TEXT(E67,"000")),""))))) | I67: Limpeza mecanizada de camada vegetal | J67: m² | K67: =OBRA!D11 | L67: 12.5 | M67: =K67*L67 | N67: =M67/$M$298 | O67: =M67/OBRA!$D$12
A68: =IF(G68="UNIDADE CONSTRUTIVA",OFFSET(A68,-1,0)+1,LARGE(A$4:A66,1)) | B68: =IF(G68="UNIDADE CONSTRUTIVA",0,IF(G68="CÉLULA CONSTRUTIVA",OFFSET(B68,-1,0)+1,OFFSET(B68,-1,0))) | C68: =IF(G68="CÉLULA CONSTRUTIVA",0,IF(G68="ETAPA",OFFSET(C68,-1,0)+1,OFFSET(C68,-1,0))) | D68: =IF(G68="ETAPA",0,IF(G68="SUBETAPA",OFFSET(D68,-1,0)+1,OFFSET(D68,-1,0))) | E68: =IF(G68="Subetapa",0,IF(G68="serviço",OFFSET(E68,-1,0)+1,OFFSET(E68,-1,0))) | G68: Subetapa | H68: =IF(G68="Unidade Construtiva",CONCATENATE("UC ",TEXT(A68,"00")),IF(G68="Célula Construtiva",TEXT(B68,"00"),IF(G68="Etapa",CONCATENATE(TEXT(B68,"00"),".",TEXT(C68,"000")),IF(G68="Subetapa",CONCATENATE(TEXT(B68,"00"),".",TEXT(C68,"000"),".",TEXT(D68,"000")),IF(G68="Serviço",CONCATENATE(TEXT(B68,"00"),".",TEXT(C68,"000"),".",TEXT(D68,"000"),".",TEXT(E68,"000")),""))))) | I68: Instalações provisórias | M68: =SUM(M69:M76) | N68: =M68/$M$298 | O68: =M68/OBRA!$D$12
A69: =IF(G69="UNIDADE CONSTRUTIVA",OFFSET(A69,-1,0)+1,LARGE(A$4:A68,1)) | B69: =IF(G69="UNIDADE CONSTRUTIVA",0,IF(G69="CÉLULA CONSTRUTIVA",OFFSET(B69,-1,0)+1,OFFSET(B69,-1,0))) | C69: =IF(G69="CÉLULA CONSTRUTIVA",0,IF(G69="ETAPA",OFFSET(C69,-1,0)+1,OFFSET(C69,-1,0))) | D69: =IF(G69="ETAPA",0,IF(G69="SUBETAPA",OFFSET(D69,-1,0)+1,OFFSET(D69,-1,0))) | E69: =IF(G69="Subetapa",0,IF(G69="serviço",OFFSET(E69,-1,0)+1,OFFSET(E69,-1,0))) | G69: Serviço | H69: =IF(G69="Unidade Construtiva",CONCATENATE("UC ",TEXT(A69,"00")),IF(G69="Célula Construtiva",TEXT(B69,"00"),IF(G69="Etapa",CONCATENATE(TEXT(B69,"00"),".",TEXT(C69,"000")),IF(G69="Subetapa",CONCATENATE(TEXT(B69,"00"),".",TEXT(C69,"000"),".",TEXT(D69,"000")),IF(G69="Serviço",CONCATENATE(TEXT(B69,"00"),".",TEXT(C69,"000"),".",TEXT(D69,"000"),".",TEXT(E69,"000")),""))))) | I69: Locação de banheiro químico | J69: mes | K69: 7 | L69: 2850 | M69: =K69*L69 | N69: =M69/$M$298 | O69: =M69/OBRA!$D$12
A70: =IF(G70="UNIDADE CONSTRUTIVA",OFFSET(A70,-1,0)+1,LARGE(A$4:A69,1)) | B70: =IF(G70="UNIDADE CONSTRUTIVA",0,IF(G70="CÉLULA CONSTRUTIVA",OFFSET(B70,-1,0)+1,OFFSET(B70,-1,0))) | C70: =IF(G70="CÉLULA CONSTRUTIVA",0,IF(G70="ETAPA",OFFSET(C70,-1,0)+1,OFFSET(C70,-1,0))) | D70: =IF(G70="ETAPA",0,IF(G70="SUBETAPA",OFFSET(D70,-1,0)+1,OFFSET(D70,-1,0))) | E70: =IF(G70="Subetapa",0,IF(G70="serviço",OFFSET(E70,-1,0)+1,OFFSET(E70,-1,0))) | G70: Serviço | H70: =IF(G70="Unidade Construtiva",CONCATENATE("UC ",TEXT(A70,"00")),IF(G70="Célula Construtiva",TEXT(B70,"00"),IF(G70="Etapa",CONCATENATE(TEXT(B70,"00"),".",TEXT(C70,"000")),IF(G70="Subetapa",CONCATENATE(TEXT(B70,"00"),".",TEXT(C70,"000"),".",TEXT(D70,"000")),IF(G70="Serviço",CONCATENATE(TEXT(B70,"00"),".",TEXT(C70,"000"),".",TEXT(D70,"000"),".",TEXT(E70,"000")),""))))) | I70: Instalações de canteiro | J70: vb | K70: 1 | L70: 385226.85 | M70: =K70*L70 | N70: =M70/$M$298 | O70: =M70/OBRA!$D$12
A71: =IF(G71="UNIDADE CONSTRUTIVA",OFFSET(A71,-1,0)+1,LARGE(A$4:A70,1)) | B71: =IF(G71="UNIDADE CONSTRUTIVA",0,IF(G71="CÉLULA CONSTRUTIVA",OFFSET(B71,-1,0)+1,OFFSET(B71,-1,0))) | C71: =IF(G71="CÉLULA CONSTRUTIVA",0,IF(G71="ETAPA",OFFSET(C71,-1,0)+1,OFFSET(C71,-1,0))) | D71: =IF(G71="ETAPA",0,IF(G71="SUBETAPA",OFFSET(D71,-1,0)+1,OFFSET(D71,-1,0))) | E71: =IF(G71="Subetapa",0,IF(G71="serviço",OFFSET(E71,-1,0)+1,OFFSET(E71,-1,0))) | G71: Serviço | H71: =IF(G71="Unidade Construtiva",CONCATENATE("UC ",TEXT(A71,"00")),IF(G71="Célula Construtiva",TEXT(B71,"00"),IF(G71="Etapa",CONCATENATE(TEXT(B71,"00"),".",TEXT(C71,"000")),IF(G71="Subetapa",CONCATENATE(TEXT(B71,"00"),".",TEXT(C71,"000"),".",TEXT(D71,"000")),IF(G71="Serviço",CONCATENATE(TEXT(B71,"00"),".",TEXT(C71,"000"),".",TEXT(D71,"000"),".",TEXT(E71,"000")),""))))) | I71: Locação de Conteiner | J71: mês | K71: 48 | L71: 6019.17 | M71: =K71*L71 | N71: =M71/$M$298 | O71: =M71/OBRA!$D$12
A72: =IF(G72="UNIDADE CONSTRUTIVA",OFFSET(A72,-1,0)+1,LARGE(A$4:A70,1)) | B72: =IF(G72="UNIDADE CONSTRUTIVA",0,IF(G72="CÉLULA CONSTRUTIVA",OFFSET(B72,-1,0)+1,OFFSET(B72,-1,0))) | C72: =IF(G72="CÉLULA CONSTRUTIVA",0,IF(G72="ETAPA",OFFSET(C72,-1,0)+1,OFFSET(C72,-1,0))) | D72: =IF(G72="ETAPA",0,IF(G72="SUBETAPA",OFFSET(D72,-1,0)+1,OFFSET(D72,-1,0))) | E72: =IF(G72="Subetapa",0,IF(G72="serviço",OFFSET(E72,-1,0)+1,OFFSET(E72,-1,0))) | G72: Serviço | H72: =IF(G72="Unidade Construtiva",CONCATENATE("UC ",TEXT(A72,"00")),IF(G72="Célula Construtiva",TEXT(B72,"00"),IF(G72="Etapa",CONCATENATE(TEXT(B72,"00"),".",TEXT(C72,"000")),IF(G72="Subetapa",CONCATENATE(TEXT(B72,"00"),".",TEXT(C72,"000"),".",TEXT(D72,"000")),IF(G72="Serviço",CONCATENATE(TEXT(B72,"00"),".",TEXT(C72,"000"),".",TEXT(D72,"000"),".",TEXT(E72,"000")),""))))) | I72: Instalações Provisórias: Redes de Água Fria, Esgoto e Drenagem | J72: vb | K72: 1 | L72: 15778.006 | M72: =K72*L72 | N72: =M72/$M$298 | O72: =M72/OBRA!$D$12
A73: =IF(G73="UNIDADE CONSTRUTIVA",OFFSET(A73,-1,0)+1,LARGE(A$4:A71,1)) | B73: =IF(G73="UNIDADE CONSTRUTIVA",0,IF(G73="CÉLULA CONSTRUTIVA",OFFSET(B73,-1,0)+1,OFFSET(B73,-1,0))) | C73: =IF(G73="CÉLULA CONSTRUTIVA",0,IF(G73="ETAPA",OFFSET(C73,-1,0)+1,OFFSET(C73,-1,0))) | D73: =IF(G73="ETAPA",0,IF(G73="SUBETAPA",OFFSET(D73,-1,0)+1,OFFSET(D73,-1,0))) | E73: =IF(G73="Subetapa",0,IF(G73="serviço",OFFSET(E73,-1,0)+1,OFFSET(E73,-1,0))) | G73: Serviço | H73: =IF(G73="Unidade Construtiva",CONCATENATE("UC ",TEXT(A73,"00")),IF(G73="Célula Construtiva",TEXT(B73,"00"),IF(G73="Etapa",CONCATENATE(TEXT(B73,"00"),".",TEXT(C73,"000")),IF(G73="Subetapa",CONCATENATE(TEXT(B73,"00"),".",TEXT(C73,"000"),".",TEXT(D73,"000")),IF(G73="Serviço",CONCATENATE(TEXT(B73,"00"),".",TEXT(C73,"000"),".",TEXT(D73,"000"),".",TEXT(E73,"000")),""))))) | I73: Instalações Provisórias: Redes Elétrica, Comunicação e Dados | J73: vb | K73: 1 | L73: 13809.656 | M73: =K73*L73 | N73: =M73/$M$298 | O73: =M73/OBRA!$D$12
A74: =IF(G74="UNIDADE CONSTRUTIVA",OFFSET(A74,-1,0)+1,LARGE(A$4:A73,1)) | B74: =IF(G74="UNIDADE CONSTRUTIVA",0,IF(G74="CÉLULA CONSTRUTIVA",OFFSET(B74,-1,0)+1,OFFSET(B74,-1,0))) | C74: =IF(G74="CÉLULA CONSTRUTIVA",0,IF(G74="ETAPA",OFFSET(C74,-1,0)+1,OFFSET(C74,-1,0))) | D74: =IF(G74="ETAPA",0,IF(G74="SUBETAPA",OFFSET(D74,-1,0)+1,OFFSET(D74,-1,0))) | E74: =IF(G74="Subetapa",0,IF(G74="serviço",OFFSET(E74,-1,0)+1,OFFSET(E74,-1,0))) | G74: Serviço | H74: =IF(G74="Unidade Construtiva",CONCATENATE("UC ",TEXT(A74,"00")),IF(G74="Célula Construtiva",TEXT(B74,"00"),IF(G74="Etapa",CONCATENATE(TEXT(B74,"00"),".",TEXT(C74,"000")),IF(G74="Subetapa",CONCATENATE(TEXT(B74,"00"),".",TEXT(C74,"000"),".",TEXT(D74,"000")),IF(G74="Serviço",CONCATENATE(TEXT(B74,"00"),".",TEXT(C74,"000"),".",TEXT(D74,"000"),".",TEXT(E74,"000")),""))))) | I74: Mobiliário de apoio a obra | J74: vb | K74: 1 | L74: 15200 | M74: =K74*L74 | N74: =M74/$M$298 | O74: =M74/OBRA!$D$12
A75: =IF(G75="UNIDADE CONSTRUTIVA",OFFSET(A75,-1,0)+1,LARGE(A$4:A71,1)) | B75: =IF(G75="UNIDADE CONSTRUTIVA",0,IF(G75="CÉLULA CONSTRUTIVA",OFFSET(B75,-1,0)+1,OFFSET(B75,-1,0))) | C75: =IF(G75="CÉLULA CONSTRUTIVA",0,IF(G75="ETAPA",OFFSET(C75,-1,0)+1,OFFSET(C75,-1,0))) | D75: =IF(G75="ETAPA",0,IF(G75="SUBETAPA",OFFSET(D75,-1,0)+1,OFFSET(D75,-1,0))) | E75: =IF(G75="Subetapa",0,IF(G75="serviço",OFFSET(E75,-1,0)+1,OFFSET(E75,-1,0))) | G75: Serviço | H75: =IF(G75="Unidade Construtiva",CONCATENATE("UC ",TEXT(A75,"00")),IF(G75="Célula Construtiva",TEXT(B75,"00"),IF(G75="Etapa",CONCATENATE(TEXT(B75,"00"),".",TEXT(C75,"000")),IF(G75="Subetapa",CONCATENATE(TEXT(B75,"00"),".",TEXT(C75,"000"),".",TEXT(D75,"000")),IF(G75="Serviço",CONCATENATE(TEXT(B75,"00"),".",TEXT(C75,"000"),".",TEXT(D75,"000"),".",TEXT(E75,"000")),""))))) | I75: Equipamentos escritório - aquisição | J75: vb | K75: 1 | L75: 9000 | M75: =K75*L75 | N75: =M75/$M$298 | O75: =M75/OBRA!$D$12
A76: =IF(G76="UNIDADE CONSTRUTIVA",OFFSET(A76,-1,0)+1,LARGE(A$4:A75,1)) | B76: =IF(G76="UNIDADE CONSTRUTIVA",0,IF(G76="CÉLULA CONSTRUTIVA",OFFSET(B76,-1,0)+1,OFFSET(B76,-1,0))) | C76: =IF(G76="CÉLULA CONSTRUTIVA",0,IF(G76="ETAPA",OFFSET(C76,-1,0)+1,OFFSET(C76,-1,0))) | D76: =IF(G76="ETAPA",0,IF(G76="SUBETAPA",OFFSET(D76,-1,0)+1,OFFSET(D76,-1,0))) | E76: =IF(G76="Subetapa",0,IF(G76="serviço",OFFSET(E76,-1,0)+1,OFFSET(E76,-1,0))) | G76: Serviço | H76: =IF(G76="Unidade Construtiva",CONCATENATE("UC ",TEXT(A76,"00")),IF(G76="Célula Construtiva",TEXT(B76,"00"),IF(G76="Etapa",CONCATENATE(TEXT(B76,"00"),".",TEXT(C76,"000")),IF(G76="Subetapa",CONCATENATE(TEXT(B76,"00"),".",TEXT(C76,"000"),".",TEXT(D76,"000")),IF(G76="Serviço",CONCATENATE(TEXT(B76,"00"),".",TEXT(C76,"000"),".",TEXT(D76,"000"),".",TEXT(E76,"000")),""))))) | I76: Tapume com telha metálica | J76: m2 | K76: ='EPC''s'!D49 | L76: 119.41 | M76: =K76*L76 | N76: =M76/$M$298 | O76: =M76/OBRA!$D$12
A77: =IF(G77="UNIDADE CONSTRUTIVA",OFFSET(A77,-1,0)+1,LARGE(A$4:A76,1)) | B77: =IF(G77="UNIDADE CONSTRUTIVA",0,IF(G77="CÉLULA CONSTRUTIVA",OFFSET(B77,-1,0)+1,OFFSET(B77,-1,0))) | C77: =IF(G77="CÉLULA CONSTRUTIVA",0,IF(G77="ETAPA",OFFSET(C77,-1,0)+1,OFFSET(C77,-1,0))) | D77: =IF(G77="ETAPA",0,IF(G77="SUBETAPA",OFFSET(D77,-1,0)+1,OFFSET(D77,-1,0))) | E77: =IF(G77="Subetapa",0,IF(G77="serviço",OFFSET(E77,-1,0)+1,OFFSET(E77,-1,0))) | G77: Subetapa | H77: =IF(G77="Unidade Construtiva",CONCATENATE("UC ",TEXT(A77,"00")),IF(G77="Célula Construtiva",TEXT(B77,"00"),IF(G77="Etapa",CONCATENATE(TEXT(B77,"00"),".",TEXT(C77,"000")),IF(G77="Subetapa",CONCATENATE(TEXT(B77,"00"),".",TEXT(C77,"000"),".",TEXT(D77,"000")),IF(G77="Serviço",CONCATENATE(TEXT(B77,"00"),".",TEXT(C77,"000"),".",TEXT(D77,"000"),".",TEXT(E77,"000")),""))))) | I77: Despesas de Consumo e Manutenção | M77: 269939.92 | N77: =M77/$M$298 | O77: =M77/OBRA!$D$12
A78: =IF(G78="UNIDADE CONSTRUTIVA",OFFSET(A78,-1,0)+1,LARGE(A$4:A77,1)) | B78: =IF(G78="UNIDADE CONSTRUTIVA",0,IF(G78="CÉLULA CONSTRUTIVA",OFFSET(B78,-1,0)+1,OFFSET(B78,-1,0))) | C78: =IF(G78="CÉLULA CONSTRUTIVA",0,IF(G78="ETAPA",OFFSET(C78,-1,0)+1,OFFSET(C78,-1,0))) | D78: =IF(G78="ETAPA",0,IF(G78="SUBETAPA",OFFSET(D78,-1,0)+1,OFFSET(D78,-1,0))) | E78: =IF(G78="Subetapa",0,IF(G78="serviço",OFFSET(E78,-1,0)+1,OFFSET(E78,-1,0))) | G78: ETAPA | H78: =IF(G78="Unidade Construtiva",CONCATENATE("UC ",TEXT(A78,"00")),IF(G78="Célula Construtiva",TEXT(B78,"00"),IF(G78="Etapa",CONCATENATE(TEXT(B78,"00"),".",TEXT(C78,"000")),IF(G78="Subetapa",CONCATENATE(TEXT(B78,"00"),".",TEXT(C78,"000"),".",TEXT(D78,"000")),IF(G78="Serviço",CONCATENATE(TEXT(B78,"00"),".",TEXT(C78,"000"),".",TEXT(D78,"000"),".",TEXT(E78,"000")),""))))) | I78: EQUIPAMENTOS | M78: =M79+M87 | N78: =M78/$M$298 | O78: =M78/OBRA!$D$12
A79: =IF(G79="UNIDADE CONSTRUTIVA",OFFSET(A79,-1,0)+1,LARGE(A$4:A78,1)) | B79: =IF(G79="UNIDADE CONSTRUTIVA",0,IF(G79="CÉLULA CONSTRUTIVA",OFFSET(B79,-1,0)+1,OFFSET(B79,-1,0))) | C79: =IF(G79="CÉLULA CONSTRUTIVA",0,IF(G79="ETAPA",OFFSET(C79,-1,0)+1,OFFSET(C79,-1,0))) | D79: =IF(G79="ETAPA",0,IF(G79="SUBETAPA",OFFSET(D79,-1,0)+1,OFFSET(D79,-1,0))) | E79: =IF(G79="Subetapa",0,IF(G79="serviço",OFFSET(E79,-1,0)+1,OFFSET(E79,-1,0))) | G79: Subetapa | H79: =IF(G79="Unidade Construtiva",CONCATENATE("UC ",TEXT(A79,"00")),IF(G79="Célula Construtiva",TEXT(B79,"00"),IF(G79="Etapa",CONCATENATE(TEXT(B79,"00"),".",TEXT(C79,"000")),IF(G79="Subetapa",CONCATENATE(TEXT(B79,"00"),".",TEXT(C79,"000"),".",TEXT(D79,"000")),IF(G79="Serviço",CONCATENATE(TEXT(B79,"00"),".",TEXT(C79,"000"),".",TEXT(D79,"000"),".",TEXT(E79,"000")),""))))) | I79: Equipamentos de carga e transporte | M79: =SUM(M80:M86) | N79: =M79/$M$298 | O79: =M79/OBRA!$D$12
A80: =IF(G80="UNIDADE CONSTRUTIVA",OFFSET(A80,-1,0)+1,LARGE(A$4:A79,1)) | B80: =IF(G80="UNIDADE CONSTRUTIVA",0,IF(G80="CÉLULA CONSTRUTIVA",OFFSET(B80,-1,0)+1,OFFSET(B80,-1,0))) | C80: =IF(G80="CÉLULA CONSTRUTIVA",0,IF(G80="ETAPA",OFFSET(C80,-1,0)+1,OFFSET(C80,-1,0))) | D80: =IF(G80="ETAPA",0,IF(G80="SUBETAPA",OFFSET(D80,-1,0)+1,OFFSET(D80,-1,0))) | E80: =IF(G80="Subetapa",0,IF(G80="serviço",OFFSET(E80,-1,0)+1,OFFSET(E80,-1,0))) | G80: Serviço | H80: =IF(G80="Unidade Construtiva",CONCATENATE("UC ",TEXT(A80,"00")),IF(G80="Célula Construtiva",TEXT(B80,"00"),IF(G80="Etapa",CONCATENATE(TEXT(B80,"00"),".",TEXT(C80,"000")),IF(G80="Subetapa",CONCATENATE(TEXT(B80,"00"),".",TEXT(C80,"000"),".",TEXT(D80,"000")),IF(G80="Serviço",CONCATENATE(TEXT(B80,"00"),".",TEXT(C80,"000"),".",TEXT(D80,"000"),".",TEXT(E80,"000")),""))))) | I80: Ferramentas - aquisição/manutenção | J80: vb | K80: 1 | L80: 73600 | M80: =K80*L80 | N80: =M80/$M$298 | O80: =M80/OBRA!$D$12
A81: =IF(G81="UNIDADE CONSTRUTIVA",OFFSET(A81,-1,0)+1,LARGE(A$4:A80,1)) | B81: =IF(G81="UNIDADE CONSTRUTIVA",0,IF(G81="CÉLULA CONSTRUTIVA",OFFSET(B81,-1,0)+1,OFFSET(B81,-1,0))) | C81: =IF(G81="CÉLULA CONSTRUTIVA",0,IF(G81="ETAPA",OFFSET(C81,-1,0)+1,OFFSET(C81,-1,0))) | D81: =IF(G81="ETAPA",0,IF(G81="SUBETAPA",OFFSET(D81,-1,0)+1,OFFSET(D81,-1,0))) | E81: =IF(G81="Subetapa",0,IF(G81="serviço",OFFSET(E81,-1,0)+1,OFFSET(E81,-1,0))) | G81: Serviço | H81: =IF(G81="Unidade Construtiva",CONCATENATE("UC ",TEXT(A81,"00")),IF(G81="Célula Construtiva",TEXT(B81,"00"),IF(G81="Etapa",CONCATENATE(TEXT(B81,"00"),".",TEXT(C81,"000")),IF(G81="Subetapa",CONCATENATE(TEXT(B81,"00"),".",TEXT(C81,"000"),".",TEXT(D81,"000")),IF(G81="Serviço",CONCATENATE(TEXT(B81,"00"),".",TEXT(C81,"000"),".",TEXT(D81,"000"),".",TEXT(E81,"000")),""))))) | I81: Locação de elevador cremalheira | J81: mês | K81: 30 | L81: 11006.48 | M81: =K81*L81 | N81: =M81/$M$298 | O81: =M81/OBRA!$D$12
A82: =IF(G82="UNIDADE CONSTRUTIVA",OFFSET(A82,-1,0)+1,LARGE(A$4:A81,1)) | B82: =IF(G82="UNIDADE CONSTRUTIVA",0,IF(G82="CÉLULA CONSTRUTIVA",OFFSET(B82,-1,0)+1,OFFSET(B82,-1,0))) | C82: =IF(G82="CÉLULA CONSTRUTIVA",0,IF(G82="ETAPA",OFFSET(C82,-1,0)+1,OFFSET(C82,-1,0))) | D82: =IF(G82="ETAPA",0,IF(G82="SUBETAPA",OFFSET(D82,-1,0)+1,OFFSET(D82,-1,0))) | E82: =IF(G82="Subetapa",0,IF(G82="serviço",OFFSET(E82,-1,0)+1,OFFSET(E82,-1,0))) | G82: Serviço | H82: =IF(G82="Unidade Construtiva",CONCATENATE("UC ",TEXT(A82,"00")),IF(G82="Célula Construtiva",TEXT(B82,"00"),IF(G82="Etapa",CONCATENATE(TEXT(B82,"00"),".",TEXT(C82,"000")),IF(G82="Subetapa",CONCATENATE(TEXT(B82,"00"),".",TEXT(C82,"000"),".",TEXT(D82,"000")),IF(G82="Serviço",CONCATENATE(TEXT(B82,"00"),".",TEXT(C82,"000"),".",TEXT(D82,"000"),".",TEXT(E82,"000")),""))))) | I82: Montagem e desmontagem de elevador cremalheira | J82: vb | K82: 1 | L82: 17600 | M82: =K82*L82 | N82: =M82/$M$298 | O82: =M82/OBRA!$D$12
A83: =IF(G83="UNIDADE CONSTRUTIVA",OFFSET(A83,-1,0)+1,LARGE(A$4:A82,1)) | B83: =IF(G83="UNIDADE CONSTRUTIVA",0,IF(G83="CÉLULA CONSTRUTIVA",OFFSET(B83,-1,0)+1,OFFSET(B83,-1,0))) | C83: =IF(G83="CÉLULA CONSTRUTIVA",0,IF(G83="ETAPA",OFFSET(C83,-1,0)+1,OFFSET(C83,-1,0))) | D83: =IF(G83="ETAPA",0,IF(G83="SUBETAPA",OFFSET(D83,-1,0)+1,OFFSET(D83,-1,0))) | E83: =IF(G83="Subetapa",0,IF(G83="serviço",OFFSET(E83,-1,0)+1,OFFSET(E83,-1,0))) | G83: Serviço | H83: =IF(G83="Unidade Construtiva",CONCATENATE("UC ",TEXT(A83,"00")),IF(G83="Célula Construtiva",TEXT(B83,"00"),IF(G83="Etapa",CONCATENATE(TEXT(B83,"00"),".",TEXT(C83,"000")),IF(G83="Subetapa",CONCATENATE(TEXT(B83,"00"),".",TEXT(C83,"000"),".",TEXT(D83,"000")),IF(G83="Serviço",CONCATENATE(TEXT(B83,"00"),".",TEXT(C83,"000"),".",TEXT(D83,"000"),".",TEXT(E83,"000")),""))))) | I83: Mobilização e desmobilização de elevador cremalheira | J83: vb | K83: 1 | L83: 13000 | M83: =K83*L83 | N83: =M83/$M$298 | O83: =M83/OBRA!$D$12
A84: =IF(G84="UNIDADE CONSTRUTIVA",OFFSET(A84,-1,0)+1,LARGE(A$4:A83,1)) | B84: =IF(G84="UNIDADE CONSTRUTIVA",0,IF(G84="CÉLULA CONSTRUTIVA",OFFSET(B84,-1,0)+1,OFFSET(B84,-1,0))) | C84: =IF(G84="CÉLULA CONSTRUTIVA",0,IF(G84="ETAPA",OFFSET(C84,-1,0)+1,OFFSET(C84,-1,0))) | D84: =IF(G84="ETAPA",0,IF(G84="SUBETAPA",OFFSET(D84,-1,0)+1,OFFSET(D84,-1,0))) | E84: =IF(G84="Subetapa",0,IF(G84="serviço",OFFSET(E84,-1,0)+1,OFFSET(E84,-1,0))) | G84: Serviço | H84: =IF(G84="Unidade Construtiva",CONCATENATE("UC ",TEXT(A84,"00")),IF(G84="Célula Construtiva",TEXT(B84,"00"),IF(G84="Etapa",CONCATENATE(TEXT(B84,"00"),".",TEXT(C84,"000")),IF(G84="Subetapa",CONCATENATE(TEXT(B84,"00"),".",TEXT(C84,"000"),".",TEXT(D84,"000")),IF(G84="Serviço",CONCATENATE(TEXT(B84,"00"),".",TEXT(C84,"000"),".",TEXT(D84,"000"),".",TEXT(E84,"000")),""))))) | I84: Locação de Mini-grua | J84: mês | K84: 15 | L84: 3950 | M84: =K84*L84 | N84: =M84/$M$298 | O84: =M84/OBRA!$D$12
A85: =IF(G85="UNIDADE CONSTRUTIVA",OFFSET(A85,-1,0)+1,LARGE(A$4:A84,1)) | B85: =IF(G85="UNIDADE CONSTRUTIVA",0,IF(G85="CÉLULA CONSTRUTIVA",OFFSET(B85,-1,0)+1,OFFSET(B85,-1,0))) | C85: =IF(G85="CÉLULA CONSTRUTIVA",0,IF(G85="ETAPA",OFFSET(C85,-1,0)+1,OFFSET(C85,-1,0))) | D85: =IF(G85="ETAPA",0,IF(G85="SUBETAPA",OFFSET(D85,-1,0)+1,OFFSET(D85,-1,0))) | E85: =IF(G85="Subetapa",0,IF(G85="serviço",OFFSET(E85,-1,0)+1,OFFSET(E85,-1,0))) | G85: Serviço | H85: =IF(G85="Unidade Construtiva",CONCATENATE("UC ",TEXT(A85,"00")),IF(G85="Célula Construtiva",TEXT(B85,"00"),IF(G85="Etapa",CONCATENATE(TEXT(B85,"00"),".",TEXT(C85,"000")),IF(G85="Subetapa",CONCATENATE(TEXT(B85,"00"),".",TEXT(C85,"000"),".",TEXT(D85,"000")),IF(G85="Serviço",CONCATENATE(TEXT(B85,"00"),".",TEXT(C85,"000"),".",TEXT(D85,"000"),".",TEXT(E85,"000")),""))))) | I85: Montagem e Desmontagem de Mini-grua | J85: vb | K85: 1 | L85: 7000 | M85: =K85*L85 | N85: =M85/$M$298 | O85: =M85/OBRA!$D$12
A86: =IF(G86="UNIDADE CONSTRUTIVA",OFFSET(A86,-1,0)+1,LARGE(A$4:A85,1)) | B86: =IF(G86="UNIDADE CONSTRUTIVA",0,IF(G86="CÉLULA CONSTRUTIVA",OFFSET(B86,-1,0)+1,OFFSET(B86,-1,0))) | C86: =IF(G86="CÉLULA CONSTRUTIVA",0,IF(G86="ETAPA",OFFSET(C86,-1,0)+1,OFFSET(C86,-1,0))) | D86: =IF(G86="ETAPA",0,IF(G86="SUBETAPA",OFFSET(D86,-1,0)+1,OFFSET(D86,-1,0))) | E86: =IF(G86="Subetapa",0,IF(G86="serviço",OFFSET(E86,-1,0)+1,OFFSET(E86,-1,0))) | G86: Serviço | H86: =IF(G86="Unidade Construtiva",CONCATENATE("UC ",TEXT(A86,"00")),IF(G86="Célula Construtiva",TEXT(B86,"00"),IF(G86="Etapa",CONCATENATE(TEXT(B86,"00"),".",TEXT(C86,"000")),IF(G86="Subetapa",CONCATENATE(TEXT(B86,"00"),".",TEXT(C86,"000"),".",TEXT(D86,"000")),IF(G86="Serviço",CONCATENATE(TEXT(B86,"00"),".",TEXT(C86,"000"),".",TEXT(D86,"000"),".",TEXT(E86,"000")),""))))) | I86: Mobilização e desmobilização de Mini-grua | J86: vb | K86: 1 | L86: 9756 | M86: =K86*L86 | N86: =M86/$M$298 | O86: =M86/OBRA!$D$12
A87: =IF(G87="UNIDADE CONSTRUTIVA",OFFSET(A87,-1,0)+1,LARGE(A$4:A85,1)) | B87: =IF(G87="UNIDADE CONSTRUTIVA",0,IF(G87="CÉLULA CONSTRUTIVA",OFFSET(B87,-1,0)+1,OFFSET(B87,-1,0))) | C87: =IF(G87="CÉLULA CONSTRUTIVA",0,IF(G87="ETAPA",OFFSET(C87,-1,0)+1,OFFSET(C87,-1,0))) | D87: =IF(G87="ETAPA",0,IF(G87="SUBETAPA",OFFSET(D87,-1,0)+1,OFFSET(D87,-1,0))) | E87: =IF(G87="Subetapa",0,IF(G87="serviço",OFFSET(E87,-1,0)+1,OFFSET(E87,-1,0))) | G87: Subetapa | H87: =IF(G87="Unidade Construtiva",CONCATENATE("UC ",TEXT(A87,"00")),IF(G87="Célula Construtiva",TEXT(B87,"00"),IF(G87="Etapa",CONCATENATE(TEXT(B87,"00"),".",TEXT(C87,"000")),IF(G87="Subetapa",CONCATENATE(TEXT(B87,"00"),".",TEXT(C87,"000"),".",TEXT(D87,"000")),IF(G87="Serviço",CONCATENATE(TEXT(B87,"00"),".",TEXT(C87,"000"),".",TEXT(D87,"000"),".",TEXT(E87,"000")),""))))) | I87: Balancins e Andaimes | M87: =SUM(M88:M90) | N87: =M87/$M$298 | O87: =M87/OBRA!$D$12
A88: =IF(G88="UNIDADE CONSTRUTIVA",OFFSET(A88,-1,0)+1,LARGE(A$4:A87,1)) | B88: =IF(G88="UNIDADE CONSTRUTIVA",0,IF(G88="CÉLULA CONSTRUTIVA",OFFSET(B88,-1,0)+1,OFFSET(B88,-1,0))) | C88: =IF(G88="CÉLULA CONSTRUTIVA",0,IF(G88="ETAPA",OFFSET(C88,-1,0)+1,OFFSET(C88,-1,0))) | D88: =IF(G88="ETAPA",0,IF(G88="SUBETAPA",OFFSET(D88,-1,0)+1,OFFSET(D88,-1,0))) | E88: =IF(G88="Subetapa",0,IF(G88="serviço",OFFSET(E88,-1,0)+1,OFFSET(E88,-1,0))) | G88: Serviço | H88: =IF(G88="Unidade Construtiva",CONCATENATE("UC ",TEXT(A88,"00")),IF(G88="Célula Construtiva",TEXT(B88,"00"),IF(G88="Etapa",CONCATENATE(TEXT(B88,"00"),".",TEXT(C88,"000")),IF(G88="Subetapa",CONCATENATE(TEXT(B88,"00"),".",TEXT(C88,"000"),".",TEXT(D88,"000")),IF(G88="Serviço",CONCATENATE(TEXT(B88,"00"),".",TEXT(C88,"000"),".",TEXT(D88,"000"),".",TEXT(E88,"000")),""))))) | I88: Locação de balancim motorizado | J88: mês | K88: 9 | L88: 3600 | M88: =K88*L88 | N88: =M88/$M$298 | O88: =M88/OBRA!$D$12
A89: =IF(G89="UNIDADE CONSTRUTIVA",OFFSET(A89,-1,0)+1,LARGE(A$4:A88,1)) | B89: =IF(G89="UNIDADE CONSTRUTIVA",0,IF(G89="CÉLULA CONSTRUTIVA",OFFSET(B89,-1,0)+1,OFFSET(B89,-1,0))) | C89: =IF(G89="CÉLULA CONSTRUTIVA",0,IF(G89="ETAPA",OFFSET(C89,-1,0)+1,OFFSET(C89,-1,0))) | D89: =IF(G89="ETAPA",0,IF(G89="SUBETAPA",OFFSET(D89,-1,0)+1,OFFSET(D89,-1,0))) | E89: =IF(G89="Subetapa",0,IF(G89="serviço",OFFSET(E89,-1,0)+1,OFFSET(E89,-1,0))) | G89: Serviço | H89: =IF(G89="Unidade Construtiva",CONCATENATE("UC ",TEXT(A89,"00")),IF(G89="Célula Construtiva",TEXT(B89,"00"),IF(G89="Etapa",CONCATENATE(TEXT(B89,"00"),".",TEXT(C89,"000")),IF(G89="Subetapa",CONCATENATE(TEXT(B89,"00"),".",TEXT(C89,"000"),".",TEXT(D89,"000")),IF(G89="Serviço",CONCATENATE(TEXT(B89,"00"),".",TEXT(C89,"000"),".",TEXT(D89,"000"),".",TEXT(E89,"000")),""))))) | I89: Montagem e desmontagem de balancim | J89: uni | K89: 148 | L89: 450 | M89: =K89*L89 | N89: =M89/$M$298 | O89: =M89/OBRA!$D$12
A90: =IF(G90="UNIDADE CONSTRUTIVA",OFFSET(A90,-1,0)+1,LARGE(A$4:A89,1)) | B90: =IF(G90="UNIDADE CONSTRUTIVA",0,IF(G90="CÉLULA CONSTRUTIVA",OFFSET(B90,-1,0)+1,OFFSET(B90,-1,0))) | C90: =IF(G90="CÉLULA CONSTRUTIVA",0,IF(G90="ETAPA",OFFSET(C90,-1,0)+1,OFFSET(C90,-1,0))) | D90: =IF(G90="ETAPA",0,IF(G90="SUBETAPA",OFFSET(D90,-1,0)+1,OFFSET(D90,-1,0))) | E90: =IF(G90="Subetapa",0,IF(G90="serviço",OFFSET(E90,-1,0)+1,OFFSET(E90,-1,0))) | G90: Serviço | H90: =IF(G90="Unidade Construtiva",CONCATENATE("UC ",TEXT(A90,"00")),IF(G90="Célula Construtiva",TEXT(B90,"00"),IF(G90="Etapa",CONCATENATE(TEXT(B90,"00"),".",TEXT(C90,"000")),IF(G90="Subetapa",CONCATENATE(TEXT(B90,"00"),".",TEXT(C90,"000"),".",TEXT(D90,"000")),IF(G90="Serviço",CONCATENATE(TEXT(B90,"00"),".",TEXT(C90,"000"),".",TEXT(D90,"000"),".",TEXT(E90,"000")),""))))) | I90: Locação de Andaime | J90: mês | K90: 6 | L90: 1500 | M90: =K90*L90 | N90: =M90/$M$298 | O90: =M90/OBRA!$D$12
A91: =IF(G91="UNIDADE CONSTRUTIVA",OFFSET(A91,-1,0)+1,LARGE(A$4:A90,1)) | B91: =IF(G91="UNIDADE CONSTRUTIVA",0,IF(G91="CÉLULA CONSTRUTIVA",OFFSET(B91,-1,0)+1,OFFSET(B91,-1,0))) | C91: =IF(G91="CÉLULA CONSTRUTIVA",0,IF(G91="ETAPA",OFFSET(C91,-1,0)+1,OFFSET(C91,-1,0))) | D91: =IF(G91="ETAPA",0,IF(G91="SUBETAPA",OFFSET(D91,-1,0)+1,OFFSET(D91,-1,0))) | E91: =IF(G91="Subetapa",0,IF(G91="serviço",OFFSET(E91,-1,0)+1,OFFSET(E91,-1,0))) | G91: UNIDADE CONSTRUTIVA | H91: =IF(G91="Unidade Construtiva",CONCATENATE("UC ",TEXT(A91,"00")),IF(G91="Célula Construtiva",TEXT(B91,"00"),IF(G91="Etapa",CONCATENATE(TEXT(B91,"00"),".",TEXT(C91,"000")),IF(G91="Subetapa",CONCATENATE(TEXT(B91,"00"),".",TEXT(C91,"000"),".",TEXT(D91,"000")),IF(G91="Serviço",CONCATENATE(TEXT(B91,"00"),".",TEXT(C91,"000"),".",TEXT(D91,"000"),".",TEXT(E91,"000")),""))))) | I91: GERENCIAMENTO EXECUTIVO | M91: =M92+M102+M120+M129+M144+M154+M167+M192+M215+M226+M235+M250+M259+M276+M285+M294 | N91: =M91/$M$298 | O91: =M91/OBRA!$D$12
A92: =IF(G92="UNIDADE CONSTRUTIVA",OFFSET(A92,-1,0)+1,LARGE(A$4:A91,1)) | B92: =IF(G92="UNIDADE CONSTRUTIVA",0,IF(G92="CÉLULA CONSTRUTIVA",OFFSET(B92,-1,0)+1,OFFSET(B92,-1,0))) | C92: =IF(G92="CÉLULA CONSTRUTIVA",0,IF(G92="ETAPA",OFFSET(C92,-1,0)+1,OFFSET(C92,-1,0))) | D92: =IF(G92="ETAPA",0,IF(G92="SUBETAPA",OFFSET(D92,-1,0)+1,OFFSET(D92,-1,0))) | E92: =IF(G92="Subetapa",0,IF(G92="serviço",OFFSET(E92,-1,0)+1,OFFSET(E92,-1,0))) | G92: CÉLULA CONSTRUTIVA | H92: =IF(G92="Unidade Construtiva",CONCATENATE("UC ",TEXT(A92,"00")),IF(G92="Célula Construtiva",TEXT(B92,"00"),IF(G92="Etapa",CONCATENATE(TEXT(B92,"00"),".",TEXT(C92,"000")),IF(G92="Subetapa",CONCATENATE(TEXT(B92,"00"),".",TEXT(C92,"000"),".",TEXT(D92,"000")),IF(G92="Serviço",CONCATENATE(TEXT(B92,"00"),".",TEXT(C92,"000"),".",TEXT(D92,"000"),".",TEXT(E92,"000")),""))))) | I92: MOVIMENTAÇÃO DE TERRA | M92: =M93 | N92: =M92/$M$298 | O92: =M92/OBRA!$D$12 | P92: =[1]MOVIMENTAÇÃO_DE_TERRA!$F$34 | Q92: =M92-P92 | R92: =Q92/OBRA!D12
A93: =IF(G93="UNIDADE CONSTRUTIVA",OFFSET(A93,-1,0)+1,LARGE(A$4:A92,1)) | B93: =IF(G93="UNIDADE CONSTRUTIVA",0,IF(G93="CÉLULA CONSTRUTIVA",OFFSET(B93,-1,0)+1,OFFSET(B93,-1,0))) | C93: =IF(G93="CÉLULA CONSTRUTIVA",0,IF(G93="ETAPA",OFFSET(C93,-1,0)+1,OFFSET(C93,-1,0))) | D93: =IF(G93="ETAPA",0,IF(G93="SUBETAPA",OFFSET(D93,-1,0)+1,OFFSET(D93,-1,0))) | E93: =IF(G93="Subetapa",0,IF(G93="serviço",OFFSET(E93,-1,0)+1,OFFSET(E93,-1,0))) | G93: ETAPA | H93: =IF(G93="Unidade Construtiva",CONCATENATE("UC ",TEXT(A93,"00")),IF(G93="Célula Construtiva",TEXT(B93,"00"),IF(G93="Etapa",CONCATENATE(TEXT(B93,"00"),".",TEXT(C93,"000")),IF(G93="Subetapa",CONCATENATE(TEXT(B93,"00"),".",TEXT(C93,"000"),".",TEXT(D93,"000")),IF(G93="Serviço",CONCATENATE(TEXT(B93,"00"),".",TEXT(C93,"000"),".",TEXT(D93,"000"),".",TEXT(E93,"000")),""))))) | I93: MOVIMENTAÇÃO DE TERRA | M93: =M94 | N93: =M93/$M$298 | O93: =M93/OBRA!$D$12
A94: =IF(G94="UNIDADE CONSTRUTIVA",OFFSET(A94,-1,0)+1,LARGE(A$4:A93,1)) | B94: =IF(G94="UNIDADE CONSTRUTIVA",0,IF(G94="CÉLULA CONSTRUTIVA",OFFSET(B94,-1,0)+1,OFFSET(B94,-1,0))) | C94: =IF(G94="CÉLULA CONSTRUTIVA",0,IF(G94="ETAPA",OFFSET(C94,-1,0)+1,OFFSET(C94,-1,0))) | D94: =IF(G94="ETAPA",0,IF(G94="SUBETAPA",OFFSET(D94,-1,0)+1,OFFSET(D94,-1,0))) | E94: =IF(G94="Subetapa",0,IF(G94="serviço",OFFSET(E94,-1,0)+1,OFFSET(E94,-1,0))) | G94: Subetapa | H94: =IF(G94="Unidade Construtiva",CONCATENATE("UC ",TEXT(A94,"00")),IF(G94="Célula Construtiva",TEXT(B94,"00"),IF(G94="Etapa",CONCATENATE(TEXT(B94,"00"),".",TEXT(C94,"000")),IF(G94="Subetapa",CONCATENATE(TEXT(B94,"00"),".",TEXT(C94,"000"),".",TEXT(D94,"000")),IF(G94="Serviço",CONCATENATE(TEXT(B94,"00"),".",TEXT(C94,"000"),".",TEXT(D94,"000"),".",TEXT(E94,"000")),""))))) | I94: Movimentação de Terra | M94: =SUM(M95:M101) | N94: =M94/$M$298 | O94: =M94/OBRA!$D$12
A95: =IF(G95="UNIDADE CONSTRUTIVA",OFFSET(A95,-1,0)+1,LARGE(A$4:A94,1)) | B95: =IF(G95="UNIDADE CONSTRUTIVA",0,IF(G95="CÉLULA CONSTRUTIVA",OFFSET(B95,-1,0)+1,OFFSET(B95,-1,0))) | C95: =IF(G95="CÉLULA CONSTRUTIVA",0,IF(G95="ETAPA",OFFSET(C95,-1,0)+1,OFFSET(C95,-1,0))) | D95: =IF(G95="ETAPA",0,IF(G95="SUBETAPA",OFFSET(D95,-1,0)+1,OFFSET(D95,-1,0))) | E95: =IF(G95="Subetapa",0,IF(G95="serviço",OFFSET(E95,-1,0)+1,OFFSET(E95,-1,0))) | G95: Serviço | H95: =IF(G95="Unidade Construtiva",CONCATENATE("UC ",TEXT(A95,"00")),IF(G95="Célula Construtiva",TEXT(B95,"00"),IF(G95="Etapa",CONCATENATE(TEXT(B95,"00"),".",TEXT(C95,"000")),IF(G95="Subetapa",CONCATENATE(TEXT(B95,"00"),".",TEXT(C95,"000"),".",TEXT(D95,"000")),IF(G95="Serviço",CONCATENATE(TEXT(B95,"00"),".",TEXT(C95,"000"),".",TEXT(D95,"000"),".",TEXT(E95,"000")),""))))) | I95: Escavação | J95: m³ | K95: 2655.06 | L95: 56.07 | M95: =K95*L95 | N95: =M95/$M$298 | O95: =M95/OBRA!$D$12 | P95: Volume determinado pela area e altura dos subsolos
A96: =IF(G96="UNIDADE CONSTRUTIVA",OFFSET(A96,-1,0)+1,LARGE(A$4:A93,1)) | B96: =IF(G96="UNIDADE CONSTRUTIVA",0,IF(G96="CÉLULA CONSTRUTIVA",OFFSET(B96,-1,0)+1,OFFSET(B96,-1,0))) | C96: =IF(G96="CÉLULA CONSTRUTIVA",0,IF(G96="ETAPA",OFFSET(C96,-1,0)+1,OFFSET(C96,-1,0))) | D96: =IF(G96="ETAPA",0,IF(G96="SUBETAPA",OFFSET(D96,-1,0)+1,OFFSET(D96,-1,0))) | E96: =IF(G96="Subetapa",0,IF(G96="serviço",OFFSET(E96,-1,0)+1,OFFSET(E96,-1,0))) | G96: Serviço | H96: =IF(G96="Unidade Construtiva",CONCATENATE("UC ",TEXT(A96,"00")),IF(G96="Célula Construtiva",TEXT(B96,"00"),IF(G96="Etapa",CONCATENATE(TEXT(B96,"00"),".",TEXT(C96,"000")),IF(G96="Subetapa",CONCATENATE(TEXT(B96,"00"),".",TEXT(C96,"000"),".",TEXT(D96,"000")),IF(G96="Serviço",CONCATENATE(TEXT(B96,"00"),".",TEXT(C96,"000"),".",TEXT(D96,"000"),".",TEXT(E96,"000")),""))))) | I96: Movimentação de bota-fora | J96: m³ | K96: 1327.53 | L96: 46.73 | M96: =K96*L96 | N96: =M96/$M$298 | O96: =M96/OBRA!$D$12
A97: =IF(G97="UNIDADE CONSTRUTIVA",OFFSET(A97,-1,0)+1,LARGE(A$4:A96,1)) | B97: =IF(G97="UNIDADE CONSTRUTIVA",0,IF(G97="CÉLULA CONSTRUTIVA",OFFSET(B97,-1,0)+1,OFFSET(B97,-1,0))) | C97: =IF(G97="CÉLULA CONSTRUTIVA",0,IF(G97="ETAPA",OFFSET(C97,-1,0)+1,OFFSET(C97,-1,0))) | D97: =IF(G97="ETAPA",0,IF(G97="SUBETAPA",OFFSET(D97,-1,0)+1,OFFSET(D97,-1,0))) | E97: =IF(G97="Subetapa",0,IF(G97="serviço",OFFSET(E97,-1,0)+1,OFFSET(E97,-1,0))) | G97: Serviço | H97: =IF(G97="Unidade Construtiva",CONCATENATE("UC ",TEXT(A97,"00")),IF(G97="Célula Construtiva",TEXT(B97,"00"),IF(G97="Etapa",CONCATENATE(TEXT(B97,"00"),".",TEXT(C97,"000")),IF(G97="Subetapa",CONCATENATE(TEXT(B97,"00"),".",TEXT(C97,"000"),".",TEXT(D97,"000")),IF(G97="Serviço",CONCATENATE(TEXT(B97,"00"),".",TEXT(C97,"000"),".",TEXT(D97,"000"),".",TEXT(E97,"000")),""))))) | I97: Escavação mecanizada para blocos e baldrames | J97: m3 | K97: 444.98376 | L97: =M97/K97 | M97: 17797.57 | N97: =M97/$M$298 | O97: =M97/OBRA!$D$12
A98: =IF(G98="UNIDADE CONSTRUTIVA",OFFSET(A98,-1,0)+1,LARGE(A$4:A95,1)) | B98: =IF(G98="UNIDADE CONSTRUTIVA",0,IF(G98="CÉLULA CONSTRUTIVA",OFFSET(B98,-1,0)+1,OFFSET(B98,-1,0))) | C98: =IF(G98="CÉLULA CONSTRUTIVA",0,IF(G98="ETAPA",OFFSET(C98,-1,0)+1,OFFSET(C98,-1,0))) | D98: =IF(G98="ETAPA",0,IF(G98="SUBETAPA",OFFSET(D98,-1,0)+1,OFFSET(D98,-1,0))) | E98: =IF(G98="Subetapa",0,IF(G98="serviço",OFFSET(E98,-1,0)+1,OFFSET(E98,-1,0))) | G98: Serviço | H98: =IF(G98="Unidade Construtiva",CONCATENATE("UC ",TEXT(A98,"00")),IF(G98="Célula Construtiva",TEXT(B98,"00"),IF(G98="Etapa",CONCATENATE(TEXT(B98,"00"),".",TEXT(C98,"000")),IF(G98="Subetapa",CONCATENATE(TEXT(B98,"00"),".",TEXT(C98,"000"),".",TEXT(D98,"000")),IF(G98="Serviço",CONCATENATE(TEXT(B98,"00"),".",TEXT(C98,"000"),".",TEXT(D98,"000"),".",TEXT(E98,"000")),""))))) | I98: Reaterro para blocos e baldrames | J98: m³ | K98: 796.52 | L98: 46.73 | M98: =K98*L98 | N98: =M98/$M$298 | O98: =M98/OBRA!$D$12
A99: =IF(G99="UNIDADE CONSTRUTIVA",OFFSET(A99,-1,0)+1,LARGE(A$4:A98,1)) | B99: =IF(G99="UNIDADE CONSTRUTIVA",0,IF(G99="CÉLULA CONSTRUTIVA",OFFSET(B99,-1,0)+1,OFFSET(B99,-1,0))) | C99: =IF(G99="CÉLULA CONSTRUTIVA",0,IF(G99="ETAPA",OFFSET(C99,-1,0)+1,OFFSET(C99,-1,0))) | D99: =IF(G99="ETAPA",0,IF(G99="SUBETAPA",OFFSET(D99,-1,0)+1,OFFSET(D99,-1,0))) | E99: =IF(G99="Subetapa",0,IF(G99="serviço",OFFSET(E99,-1,0)+1,OFFSET(E99,-1,0))) | G99: Serviço | H99: =IF(G99="Unidade Construtiva",CONCATENATE("UC ",TEXT(A99,"00")),IF(G99="Célula Construtiva",TEXT(B99,"00"),IF(G99="Etapa",CONCATENATE(TEXT(B99,"00"),".",TEXT(C99,"000")),IF(G99="Subetapa",CONCATENATE(TEXT(B99,"00"),".",TEXT(C99,"000"),".",TEXT(D99,"000")),IF(G99="Serviço",CONCATENATE(TEXT(B99,"00"),".",TEXT(C99,"000"),".",TEXT(D99,"000"),".",TEXT(E99,"000")),""))))) | I99: Movimentação de terra (30% de empolamento) | J99: m3 | K99: 444.98376 | L99: =M99/K99 | M99: 22246.963 | N99: =M99/$M$298 | O99: =M99/OBRA!$D$12
A100: =IF(G100="UNIDADE CONSTRUTIVA",OFFSET(A100,-1,0)+1,LARGE(A$4:A99,1)) | B100: =IF(G100="UNIDADE CONSTRUTIVA",0,IF(G100="CÉLULA CONSTRUTIVA",OFFSET(B100,-1,0)+1,OFFSET(B100,-1,0))) | C100: =IF(G100="CÉLULA CONSTRUTIVA",0,IF(G100="ETAPA",OFFSET(C100,-1,0)+1,OFFSET(C100,-1,0))) | D100: =IF(G100="ETAPA",0,IF(G100="SUBETAPA",OFFSET(D100,-1,0)+1,OFFSET(D100,-1,0))) | E100: =IF(G100="Subetapa",0,IF(G100="serviço",OFFSET(E100,-1,0)+1,OFFSET(E100,-1,0))) | G100: Serviço | H100: =IF(G100="Unidade Construtiva",CONCATENATE("UC ",TEXT(A100,"00")),IF(G100="Célula Construtiva",TEXT(B100,"00"),IF(G100="Etapa",CONCATENATE(TEXT(B100,"00"),".",TEXT(C100,"000")),IF(G100="Subetapa",CONCATENATE(TEXT(B100,"00"),".",TEXT(C100,"000"),".",TEXT(D100,"000")),IF(G100="Serviço",CONCATENATE(TEXT(B100,"00"),".",TEXT(C100,"000"),".",TEXT(D100,"000"),".",TEXT(E100,"000")),""))))) | I100: Movimentação de terra estacas (30% de empolamento) | J100: m | K100: 1800 | L100: 867.32 | M100: =K100*L100 | N100: =M100/$M$298 | O100: =M100/OBRA!$D$12
A101: =IF(G101="UNIDADE CONSTRUTIVA",OFFSET(A101,-1,0)+1,LARGE(A$4:A100,1)) | B101: =IF(G101="UNIDADE CONSTRUTIVA",0,IF(G101="CÉLULA CONSTRUTIVA",OFFSET(B101,-1,0)+1,OFFSET(B101,-1,0))) | C101: =IF(G101="CÉLULA CONSTRUTIVA",0,IF(G101="ETAPA",OFFSET(C101,-1,0)+1,OFFSET(C101,-1,0))) | D101: =IF(G101="ETAPA",0,IF(G101="SUBETAPA",OFFSET(D101,-1,0)+1,OFFSET(D101,-1,0))) | E101: =IF(G101="Subetapa",0,IF(G101="serviço",OFFSET(E101,-1,0)+1,OFFSET(E101,-1,0))) | G101: Serviço | H101: =IF(G101="Unidade Construtiva",CONCATENATE("UC ",TEXT(A101,"00")),IF(G101="Célula Construtiva",TEXT(B101,"00"),IF(G101="Etapa",CONCATENATE(TEXT(B101,"00"),".",TEXT(C101,"000")),IF(G101="Subetapa",CONCATENATE(TEXT(B101,"00"),".",TEXT(C101,"000"),".",TEXT(D101,"000")),IF(G101="Serviço",CONCATENATE(TEXT(B101,"00"),".",TEXT(C101,"000"),".",TEXT(D101,"000"),".",TEXT(E101,"000")),""))))) | I101: Lastro de concreto magro e= 10cm - Blocos | J101: m3 | K101: 1190.592 | L101: =M101/K101 | M101: 48457.094 | N101: =M101/$M$298 | O101: =M101/OBRA!$D$12
A102: =IF(G102="UNIDADE CONSTRUTIVA",OFFSET(A102,-1,0)+1,LARGE(A$4:A101,1)) | B102: =IF(G102="UNIDADE CONSTRUTIVA",0,IF(G102="CÉLULA CONSTRUTIVA",OFFSET(B102,-1,0)+1,OFFSET(B102,-1,0))) | C102: =IF(G102="CÉLULA CONSTRUTIVA",0,IF(G102="ETAPA",OFFSET(C102,-1,0)+1,OFFSET(C102,-1,0))) | D102: =IF(G102="ETAPA",0,IF(G102="SUBETAPA",OFFSET(D102,-1,0)+1,OFFSET(D102,-1,0))) | E102: =IF(G102="Subetapa",0,IF(G102="serviço",OFFSET(E102,-1,0)+1,OFFSET(E102,-1,0))) | G102: CÉLULA CONSTRUTIVA | H102: =IF(G102="Unidade Construtiva",CONCATENATE("UC ",TEXT(A102,"00")),IF(G102="Célula Construtiva",TEXT(B102,"00"),IF(G102="Etapa",CONCATENATE(TEXT(B102,"00"),".",TEXT(C102,"000")),IF(G102="Subetapa",CONCATENATE(TEXT(B102,"00"),".",TEXT(C102,"000"),".",TEXT(D102,"000")),IF(G102="Serviço",CONCATENATE(TEXT(B102,"00"),".",TEXT(C102,"000"),".",TEXT(D102,"000"),".",TEXT(E102,"000")),""))))) | I102: INFRAESTRUTURA | M102: =M103+M112 | N102: =M102/$M$298 | O102: =M102/OBRA!$D$12 | Q102: =Q120+M102 | R102: =Q102/OBRA!D12
...

Sheet Planilha1
C3: Descrição | D3: Quantidade | E3: Custo
B4: COMPRA CUBETAS
B5: LOCAÇÃO DE CUBETAS | C5: FORRO MADEIRA | D5: 369.9 | E5: 636.9
C6: FORRO PVC IMITA MADEIRA | D6: 369.9 | E6: 81.576
C7: FORRO VINILICO | D7: 369.9 | E7: 253
C8: DECK MADEIRA | D8: 96.22 | E8: 888.8
C9: PORCELANATO QUE IMITA MADEIRA | D9: 96.22 | E9: 324.5
C10: PISO EMBORRACHADO | D10: 126.98 | E10: 385
C11: PISO VINILICO | D11: 126.98 | E11: 165
C12: PISO POLIDO + EPOXI | D12: 2485.44 | E12: 55
C13: PISO LAPIDADO | D13: 2485.44 | E13: 172.7
C14: PINTURA EPOXI | D14: 2485.44 | E14: 132
C15: ESQUADRIAS MAIORES | D15: 2110.7751 | E15: 1375
C16: ESQUADRIAS MENORES | D16: 1649.9751 | E16: 1265
C17: FACHADA ESQ MAIORES | D17: 2854.67
C18: FACHADA ESQ MENORES | D18: 3315.47
C19: CHAPISCO | D19: ='[2]Rev. Internos Piso e Parede'!$B$20 | E19: ='[2]Rev. Internos Piso e Parede'!$G$20/'[2]Rev. Internos Piso e Parede'!$B$20
C20: REBOCO | D20: ='[2]Rev. Internos Piso e Parede'!$B$20 | E20: ='[2]Rev. Internos Piso e Parede'!$G$21/'[2]Rev. Internos Piso e Parede'!$B$21
C21: GESSO SARRAFEADO | D21: ='[2]Rev. Internos Piso e Parede'!$B$20 | E21: ='[2]Rev. Internos Piso e Parede'!$G$38/'[2]Rev. Internos Piso e Parede'!$B$38
C22: BRISE TOTAL | D22: 345.254 | E22: 2310
C23: BRISE FACHADA NORTE | D23: =(2.52*2+3.52+0.89)*(2.8/2)*8 | E23: 2310
