Workbook

Sheet Gerência Consolidada
G4: PROJETO: | I4: =[4]CAPA!C2 | O4: REVISÃO:
G5: EMPRESA: | I5: =[4]CAPA!C3 | O5: =[4]CAPA!C4
A6: Unidade Construtiva | B6: Célula Construtiva | C6: Etapa | D6: Subetapa | E6: Serviço | G6: GERENCIAMENTO TÉCNICO E ADMINISTRATIVO
A7: 0 | B7: 0 | C7: 0 | D7: 0 | E7: 0 | G7: Atalho | H7: NIVEL | I7: Item | J7: Descrição | K7: Unidade | L7: Quant. | M7: Preço un | N7: Total | O7: Considerações
A8: =IF($H8="UNIDADE CONSTRUTIVA",OFFSET(A8,-1,0)+1,LARGE(A$3:A7,1)) | B8: =IF(H8="UNIDADE CONSTRUTIVA",0,IF(H8="CÉLULA CONSTRUTIVA",OFFSET(B8,-1,0)+1,OFFSET(B8,-1,0))) | C8: =IF(H8="CÉLULA CONSTRUTIVA",0,IF(H8="ETAPA",OFFSET(C8,-1,0)+1,OFFSET(C8,-1,0))) | D8: =IF(H8="ETAPA",0,IF(H8="SUBETAPA",OFFSET(D8,-1,0)+1,OFFSET(D8,-1,0))) | E8: =IF(H8="Subetapa",0,IF(H8="serviço",OFFSET(E8,-1,0)+1,OFFSET(E8,-1,0))) | H8: CÉLULA CONSTRUTIVA | I8: =IF(H8="Unidade Construtiva",TEXT(A8,"00"),IF(H8="Célula Construtiva",TEXT(B8,"00"),IF(H8="Etapa",CONCATENATE(TEXT(B8,"00"),".",TEXT(C8,"000")),IF(H8="Subetapa",CONCATENATE(TEXT(B8,"00"),".",TEXT(C8,"000"),".",TEXT(D8,"000")),IF(H8="Serviço",CONCATENATE(TEXT(B8,"00"),".",TEXT(C8,"000"),".",TEXT(D8,"000"),".",TEXT(E8,"000")),""))))) | J8: SERVIÇOS TÉCNICOS | N8: =IF(H8="Serviço",M8*L8,IF(H8="CÉLULA CONSTRUTIVA",SUMIFS($N$8:$N$442,$B$8:$B$442,B8,$H$8:$H$442,"Serviço"),IF(H8="ETAPA",SUMIFS($N$8:$N$442,$B$8:$B$442,B8,$C$8:$C$442,C8,$H$8:$H$442,"Serviço"),IF(H8="SUBETAPA",SUMIFS($N$8:$N$442,$B$8:$B$442,B8,$C$8:$C$442,C8,$D$8:$D$442,D8,$H$8:$H$442,"Serviço"),0))))
A9: =IF($H9="UNIDADE CONSTRUTIVA",OFFSET(A9,-1,0)+1,LARGE(A$3:A8,1)) | B9: =IF(H9="UNIDADE CONSTRUTIVA",0,IF(H9="CÉLULA CONSTRUTIVA",OFFSET(B9,-1,0)+1,OFFSET(B9,-1,0))) | C9: =IF(H9="CÉLULA CONSTRUTIVA",0,IF(H9="ETAPA",OFFSET(C9,-1,0)+1,OFFSET(C9,-1,0))) | D9: =IF(H9="ETAPA",0,IF(H9="SUBETAPA",OFFSET(D9,-1,0)+1,OFFSET(D9,-1,0))) | E9: =IF(H9="Subetapa",0,IF(H9="serviço",OFFSET(E9,-1,0)+1,OFFSET(E9,-1,0))) | H9: ETAPA | I9: =IF(H9="Unidade Construtiva",TEXT(A9,"00"),IF(H9="Célula Construtiva",TEXT(B9,"00"),IF(H9="Etapa",CONCATENATE(TEXT(B9,"00"),".",TEXT(C9,"000")),IF(H9="Subetapa",CONCATENATE(TEXT(B9,"00"),".",TEXT(C9,"000"),".",TEXT(D9,"000")),IF(H9="Serviço",CONCATENATE(TEXT(B9,"00"),".",TEXT(C9,"000"),".",TEXT(D9,"000"),".",TEXT(E9,"000")),""))))) | J9: ESTUDOS, PROJETOS, CONSULTORIA E ENSAIOS | N9: =IF(H9="Serviço",M9*L9,IF(H9="CÉLULA CONSTRUTIVA",SUMIFS($N$8:$N$442,$B$8:$B$442,B9,$H$8:$H$442,"Serviço"),IF(H9="ETAPA",SUMIFS($N$8:$N$442,$B$8:$B$442,B9,$C$8:$C$442,C9,$H$8:$H$442,"Serviço"),IF(H9="SUBETAPA",SUMIFS($N$8:$N$442,$B$8:$B$442,B9,$C$8:$C$442,C9,$D$8:$D$442,D9,$H$8:$H$442,"Serviço"),0))))
A10: =IF($H10="UNIDADE CONSTRUTIVA",OFFSET(A10,-1,0)+1,LARGE(A$3:A9,1)) | B10: =IF(H10="UNIDADE CONSTRUTIVA",0,IF(H10="CÉLULA CONSTRUTIVA",OFFSET(B10,-1,0)+1,OFFSET(B10,-1,0))) | C10: =IF(H10="CÉLULA CONSTRUTIVA",0,IF(H10="ETAPA",OFFSET(C10,-1,0)+1,OFFSET(C10,-1,0))) | D10: =IF(H10="ETAPA",0,IF(H10="SUBETAPA",OFFSET(D10,-1,0)+1,OFFSET(D10,-1,0))) | E10: =IF(H10="Subetapa",0,IF(H10="serviço",OFFSET(E10,-1,0)+1,OFFSET(E10,-1,0))) | H10: SUBETAPA | I10: =IF(H10="Unidade Construtiva",TEXT(A10,"00"),IF(H10="Célula Construtiva",TEXT(B10,"00"),IF(H10="Etapa",CONCATENATE(TEXT(B10,"00"),".",TEXT(C10,"000")),IF(H10="Subetapa",CONCATENATE(TEXT(B10,"00"),".",TEXT(C10,"000"),".",TEXT(D10,"000")),IF(H10="Serviço",CONCATENATE(TEXT(B10,"00"),".",TEXT(C10,"000"),".",TEXT(D10,"000"),".",TEXT(E10,"000")),""))))) | J10: Estudos | N10: =IF(H10="Serviço",M10*L10,IF(H10="CÉLULA CONSTRUTIVA",SUMIFS($N$8:$N$442,$B$8:$B$442,B10,$H$8:$H$442,"Serviço"),IF(H10="ETAPA",SUMIFS($N$8:$N$442,$B$8:$B$442,B10,$C$8:$C$442,C10,$H$8:$H$442,"Serviço"),IF(H10="SUBETAPA",SUMIFS($N$8:$N$442,$B$8:$B$442,B10,$C$8:$C$442,C10,$D$8:$D$442,D10,$H$8:$H$442,"Serviço"),0))))
A11: =IF($H11="UNIDADE CONSTRUTIVA",OFFSET(A11,-1,0)+1,LARGE(A$3:A10,1)) | B11: =IF(H11="UNIDADE CONSTRUTIVA",0,IF(H11="CÉLULA CONSTRUTIVA",OFFSET(B11,-1,0)+1,OFFSET(B11,-1,0))) | C11: =IF(H11="CÉLULA CONSTRUTIVA",0,IF(H11="ETAPA",OFFSET(C11,-1,0)+1,OFFSET(C11,-1,0))) | D11: =IF(H11="ETAPA",0,IF(H11="SUBETAPA",OFFSET(D11,-1,0)+1,OFFSET(D11,-1,0))) | E11: =IF(H11="Subetapa",0,IF(H11="serviço",OFFSET(E11,-1,0)+1,OFFSET(E11,-1,0))) | H11: SERVIÇO | I11: =IF(H11="Unidade Construtiva",TEXT(A11,"00"),IF(H11="Célula Construtiva",TEXT(B11,"00"),IF(H11="Etapa",CONCATENATE(TEXT(B11,"00"),".",TEXT(C11,"000")),IF(H11="Subetapa",CONCATENATE(TEXT(B11,"00"),".",TEXT(C11,"000"),".",TEXT(D11,"000")),IF(H11="Serviço",CONCATENATE(TEXT(B11,"00"),".",TEXT(C11,"000"),".",TEXT(D11,"000"),".",TEXT(E11,"000")),""))))) | J11: Levantamento topográfico | K11: =_xlfn.XLOOKUP($J11,BASES!$A$12:$A$392,BASES!$C$12:$C$392) | L11: =_xlfn.XLOOKUP($J11,BASES!$A$12:$A$392,BASES!$D$12:$D$392) | M11: =_xlfn.XLOOKUP($J11,BASES!$A$1:$A$2289,BASES!$E$1:$E$2289) | N11: =IF(H11="Serviço",M11*L11,IF(H11="CÉLULA CONSTRUTIVA",SUMIFS($N$8:$N$442,$B$8:$B$442,B11,$H$8:$H$442,"Serviço"),IF(H11="ETAPA",SUMIFS($N$8:$N$442,$B$8:$B$442,B11,$C$8:$C$442,C11,$H$8:$H$442,"Serviço"),IF(H11="SUBETAPA",SUMIFS($N$8:$N$442,$B$8:$B$442,B11,$C$8:$C$442,C11,$D$8:$D$442,D11,$H$8:$H$442,"Serviço"),0)))) | O11: =_xlfn.XLOOKUP($J11,BASES!$A$12:$A$392,BASES!$F$12:$F$392)
A12: =IF($H12="UNIDADE CONSTRUTIVA",OFFSET(A12,-1,0)+1,LARGE(A$3:A11,1)) | B12: =IF(H12="UNIDADE CONSTRUTIVA",0,IF(H12="CÉLULA CONSTRUTIVA",OFFSET(B12,-1,0)+1,OFFSET(B12,-1,0))) | C12: =IF(H12="CÉLULA CONSTRUTIVA",0,IF(H12="ETAPA",OFFSET(C12,-1,0)+1,OFFSET(C12,-1,0))) | D12: =IF(H12="ETAPA",0,IF(H12="SUBETAPA",OFFSET(D12,-1,0)+1,OFFSET(D12,-1,0))) | E12: =IF(H12="Subetapa",0,IF(H12="serviço",OFFSET(E12,-1,0)+1,OFFSET(E12,-1,0))) | H12: SERVIÇO | I12: =IF(H12="Unidade Construtiva",TEXT(A12,"00"),IF(H12="Célula Construtiva",TEXT(B12,"00"),IF(H12="Etapa",CONCATENATE(TEXT(B12,"00"),".",TEXT(C12,"000")),IF(H12="Subetapa",CONCATENATE(TEXT(B12,"00"),".",TEXT(C12,"000"),".",TEXT(D12,"000")),IF(H12="Serviço",CONCATENATE(TEXT(B12,"00"),".",TEXT(C12,"000"),".",TEXT(D12,"000"),".",TEXT(E12,"000")),""))))) | J12: Estudo ambiental | K12: =_xlfn.XLOOKUP($J12,BASES!$A$12:$A$392,BASES!$C$12:$C$392) | L12: =_xlfn.XLOOKUP($J12,BASES!$A$12:$A$392,BASES!$D$12:$D$392) | M12: =_xlfn.XLOOKUP($J12,BASES!$A$1:$A$2289,BASES!$E$1:$E$2289) | N12: =IF(H12="Serviço",M12*L12,IF(H12="CÉLULA CONSTRUTIVA",SUMIFS($N$8:$N$442,$B$8:$B$442,B12,$H$8:$H$442,"Serviço"),IF(H12="ETAPA",SUMIFS($N$8:$N$442,$B$8:$B$442,B12,$C$8:$C$442,C12,$H$8:$H$442,"Serviço"),IF(H12="SUBETAPA",SUMIFS($N$8:$N$442,$B$8:$B$442,B12,$C$8:$C$442,C12,$D$8:$D$442,D12,$H$8:$H$442,"Serviço"),0)))) | O12: =_xlfn.XLOOKUP($J12,BASES!$A$12:$A$392,BASES!$F$12:$F$392)
A13: =IF($H13="UNIDADE CONSTRUTIVA",OFFSET(A13,-1,0)+1,LARGE(A$3:A12,1)) | B13: =IF(H13="UNIDADE CONSTRUTIVA",0,IF(H13="CÉLULA CONSTRUTIVA",OFFSET(B13,-1,0)+1,OFFSET(B13,-1,0))) | C13: =IF(H13="CÉLULA CONSTRUTIVA",0,IF(H13="ETAPA",OFFSET(C13,-1,0)+1,OFFSET(C13,-1,0))) | D13: =IF(H13="ETAPA",0,IF(H13="SUBETAPA",OFFSET(D13,-1,0)+1,OFFSET(D13,-1,0))) | E13: =IF(H13="Subetapa",0,IF(H13="serviço",OFFSET(E13,-1,0)+1,OFFSET(E13,-1,0))) | H13: SERVIÇO | I13: =IF(H13="Unidade Construtiva",TEXT(A13,"00"),IF(H13="Célula Construtiva",TEXT(B13,"00"),IF(H13="Etapa",CONCATENATE(TEXT(B13,"00"),".",TEXT(C13,"000")),IF(H13="Subetapa",CONCATENATE(TEXT(B13,"00"),".",TEXT(C13,"000"),".",TEXT(D13,"000")),IF(H13="Serviço",CONCATENATE(TEXT(B13,"00"),".",TEXT(C13,"000"),".",TEXT(D13,"000"),".",TEXT(E13,"000")),""))))) | J13: Sondagem do terreno | K13: =_xlfn.XLOOKUP($J13,BASES!$A$12:$A$392,BASES!$C$12:$C$392) | L13: =_xlfn.XLOOKUP($J13,BASES!$A$12:$A$392,BASES!$D$12:$D$392) | M13: =_xlfn.XLOOKUP($J13,BASES!$A$1:$A$2289,BASES!$E$1:$E$2289) | N13: =IF(H13="Serviço",M13*L13,IF(H13="CÉLULA CONSTRUTIVA",SUMIFS($N$8:$N$442,$B$8:$B$442,B13,$H$8:$H$442,"Serviço"),IF(H13="ETAPA",SUMIFS($N$8:$N$442,$B$8:$B$442,B13,$C$8:$C$442,C13,$H$8:$H$442,"Serviço"),IF(H13="SUBETAPA",SUMIFS($N$8:$N$442,$B$8:$B$442,B13,$C$8:$C$442,C13,$D$8:$D$442,D13,$H$8:$H$442,"Serviço"),0)))) | O13: =_xlfn.XLOOKUP($J13,BASES!$A$12:$A$392,BASES!$F$12:$F$392)
A14: =IF($H14="UNIDADE CONSTRUTIVA",OFFSET(A14,-1,0)+1,LARGE(A$3:A13,1)) | B14: =IF(H14="UNIDADE CONSTRUTIVA",0,IF(H14="CÉLULA CONSTRUTIVA",OFFSET(B14,-1,0)+1,OFFSET(B14,-1,0))) | C14: =IF(H14="CÉLULA CONSTRUTIVA",0,IF(H14="ETAPA",OFFSET(C14,-1,0)+1,OFFSET(C14,-1,0))) | D14: =IF(H14="ETAPA",0,IF(H14="SUBETAPA",OFFSET(D14,-1,0)+1,OFFSET(D14,-1,0))) | E14: =IF(H14="Subetapa",0,IF(H14="serviço",OFFSET(E14,-1,0)+1,OFFSET(E14,-1,0))) | H14: SUBETAPA | I14: =IF(H14="Unidade Construtiva",TEXT(A14,"00"),IF(H14="Célula Construtiva",TEXT(B14,"00"),IF(H14="Etapa",CONCATENATE(TEXT(B14,"00"),".",TEXT(C14,"000")),IF(H14="Subetapa",CONCATENATE(TEXT(B14,"00"),".",TEXT(C14,"000"),".",TEXT(D14,"000")),IF(H14="Serviço",CONCATENATE(TEXT(B14,"00"),".",TEXT(C14,"000"),".",TEXT(D14,"000"),".",TEXT(E14,"000")),""))))) | J14: Projetos | N14: =IF(H14="Serviço",M14*L14,IF(H14="CÉLULA CONSTRUTIVA",SUMIFS($N$8:$N$442,$B$8:$B$442,B14,$H$8:$H$442,"Serviço"),IF(H14="ETAPA",SUMIFS($N$8:$N$442,$B$8:$B$442,B14,$C$8:$C$442,C14,$H$8:$H$442,"Serviço"),IF(H14="SUBETAPA",SUMIFS($N$8:$N$442,$B$8:$B$442,B14,$C$8:$C$442,C14,$D$8:$D$442,D14,$H$8:$H$442,"Serviço"),0))))
A15: =IF($H15="UNIDADE CONSTRUTIVA",OFFSET(A15,-1,0)+1,LARGE(A$3:A14,1)) | B15: =IF(H15="UNIDADE CONSTRUTIVA",0,IF(H15="CÉLULA CONSTRUTIVA",OFFSET(B15,-1,0)+1,OFFSET(B15,-1,0))) | C15: =IF(H15="CÉLULA CONSTRUTIVA",0,IF(H15="ETAPA",OFFSET(C15,-1,0)+1,OFFSET(C15,-1,0))) | D15: =IF(H15="ETAPA",0,IF(H15="SUBETAPA",OFFSET(D15,-1,0)+1,OFFSET(D15,-1,0))) | E15: =IF(H15="Subetapa",0,IF(H15="serviço",OFFSET(E15,-1,0)+1,OFFSET(E15,-1,0))) | H15: SERVIÇO | I15: =IF(H15="Unidade Construtiva",TEXT(A15,"00"),IF(H15="Célula Construtiva",TEXT(B15,"00"),IF(H15="Etapa",CONCATENATE(TEXT(B15,"00"),".",TEXT(C15,"000")),IF(H15="Subetapa",CONCATENATE(TEXT(B15,"00"),".",TEXT(C15,"000"),".",TEXT(D15,"000")),IF(H15="Serviço",CONCATENATE(TEXT(B15,"00"),".",TEXT(C15,"000"),".",TEXT(D15,"000"),".",TEXT(E15,"000")),""))))) | J15: Legalização de incorporação | K15: =_xlfn.XLOOKUP($J15,BASES!$A$12:$A$392,BASES!$C$12:$C$392) | L15: =_xlfn.XLOOKUP($J15,BASES!$A$12:$A$392,BASES!$D$12:$D$392) | M15: =_xlfn.XLOOKUP($J15,BASES!$A$1:$A$2289,BASES!$E$1:$E$2289) | N15: =IF(H15="Serviço",M15*L15,IF(H15="CÉLULA CONSTRUTIVA",SUMIFS($N$8:$N$442,$B$8:$B$442,B15,$H$8:$H$442,"Serviço"),IF(H15="ETAPA",SUMIFS($N$8:$N$442,$B$8:$B$442,B15,$C$8:$C$442,C15,$H$8:$H$442,"Serviço"),IF(H15="SUBETAPA",SUMIFS($N$8:$N$442,$B$8:$B$442,B15,$C$8:$C$442,C15,$D$8:$D$442,D15,$H$8:$H$442,"Serviço"),0)))) | O15: =_xlfn.XLOOKUP($J15,BASES!$A$12:$A$392,BASES!$F$12:$F$392)
A16: =IF($H16="UNIDADE CONSTRUTIVA",OFFSET(A16,-1,0)+1,LARGE(A$3:A15,1)) | B16: =IF(H16="UNIDADE CONSTRUTIVA",0,IF(H16="CÉLULA CONSTRUTIVA",OFFSET(B16,-1,0)+1,OFFSET(B16,-1,0))) | C16: =IF(H16="CÉLULA CONSTRUTIVA",0,IF(H16="ETAPA",OFFSET(C16,-1,0)+1,OFFSET(C16,-1,0))) | D16: =IF(H16="ETAPA",0,IF(H16="SUBETAPA",OFFSET(D16,-1,0)+1,OFFSET(D16,-1,0))) | E16: =IF(H16="Subetapa",0,IF(H16="serviço",OFFSET(E16,-1,0)+1,OFFSET(E16,-1,0))) | H16: SERVIÇO | I16: =IF(H16="Unidade Construtiva",TEXT(A16,"00"),IF(H16="Célula Construtiva",TEXT(B16,"00"),IF(H16="Etapa",CONCATENATE(TEXT(B16,"00"),".",TEXT(C16,"000")),IF(H16="Subetapa",CONCATENATE(TEXT(B16,"00"),".",TEXT(C16,"000"),".",TEXT(D16,"000")),IF(H16="Serviço",CONCATENATE(TEXT(B16,"00"),".",TEXT(C16,"000"),".",TEXT(D16,"000"),".",TEXT(E16,"000")),""))))) | J16: Projeto Arquitetônico Legal | K16: =_xlfn.XLOOKUP($J16,BASES!$A$12:$A$392,BASES!$C$12:$C$392) | L16: =_xlfn.XLOOKUP($J16,BASES!$A$12:$A$392,BASES!$D$12:$D$392) | M16: =_xlfn.XLOOKUP($J16,BASES!$A$1:$A$2289,BASES!$E$1:$E$2289) | N16: =IF(H16="Serviço",M16*L16,IF(H16="CÉLULA CONSTRUTIVA",SUMIFS($N$8:$N$442,$B$8:$B$442,B16,$H$8:$H$442,"Serviço"),IF(H16="ETAPA",SUMIFS($N$8:$N$442,$B$8:$B$442,B16,$C$8:$C$442,C16,$H$8:$H$442,"Serviço"),IF(H16="SUBETAPA",SUMIFS($N$8:$N$442,$B$8:$B$442,B16,$C$8:$C$442,C16,$D$8:$D$442,D16,$H$8:$H$442,"Serviço"),0)))) | O16: =_xlfn.XLOOKUP($J16,BASES!$A$12:$A$392,BASES!$F$12:$F$392)
A17: =IF($H17="UNIDADE CONSTRUTIVA",OFFSET(A17,-1,0)+1,LARGE(A$3:A16,1)) | B17: =IF(H17="UNIDADE CONSTRUTIVA",0,IF(H17="CÉLULA CONSTRUTIVA",OFFSET(B17,-1,0)+1,OFFSET(B17,-1,0))) | C17: =IF(H17="CÉLULA CONSTRUTIVA",0,IF(H17="ETAPA",OFFSET(C17,-1,0)+1,OFFSET(C17,-1,0))) | D17: =IF(H17="ETAPA",0,IF(H17="SUBETAPA",OFFSET(D17,-1,0)+1,OFFSET(D17,-1,0))) | E17: =IF(H17="Subetapa",0,IF(H17="serviço",OFFSET(E17,-1,0)+1,OFFSET(E17,-1,0))) | H17: SERVIÇO | I17: =IF(H17="Unidade Construtiva",TEXT(A17,"00"),IF(H17="Célula Construtiva",TEXT(B17,"00"),IF(H17="Etapa",CONCATENATE(TEXT(B17,"00"),".",TEXT(C17,"000")),IF(H17="Subetapa",CONCATENATE(TEXT(B17,"00"),".",TEXT(C17,"000"),".",TEXT(D17,"000")),IF(H17="Serviço",CONCATENATE(TEXT(B17,"00"),".",TEXT(C17,"000"),".",TEXT(D17,"000"),".",TEXT(E17,"000")),""))))) | J17: Projeto Arquitetônico Executivo | K17: =_xlfn.XLOOKUP($J17,BASES!$A$12:$A$392,BASES!$C$12:$C$392) | L17: =_xlfn.XLOOKUP($J17,BASES!$A$12:$A$392,BASES!$D$12:$D$392) | M17: =_xlfn.XLOOKUP($J17,BASES!$A$1:$A$2289,BASES!$E$1:$E$2289) | N17: =IF(H17="Serviço",M17*L17,IF(H17="CÉLULA CONSTRUTIVA",SUMIFS($N$8:$N$442,$B$8:$B$442,B17,$H$8:$H$442,"Serviço"),IF(H17="ETAPA",SUMIFS($N$8:$N$442,$B$8:$B$442,B17,$C$8:$C$442,C17,$H$8:$H$442,"Serviço"),IF(H17="SUBETAPA",SUMIFS($N$8:$N$442,$B$8:$B$442,B17,$C$8:$C$442,C17,$D$8:$D$442,D17,$H$8:$H$442,"Serviço"),0)))) | O17: =_xlfn.XLOOKUP($J17,BASES!$A$12:$A$392,BASES!$F$12:$F$392)
A18: =IF($H18="UNIDADE CONSTRUTIVA",OFFSET(A18,-1,0)+1,LARGE(A$3:A17,1)) | B18: =IF(H18="UNIDADE CONSTRUTIVA",0,IF(H18="CÉLULA CONSTRUTIVA",OFFSET(B18,-1,0)+1,OFFSET(B18,-1,0))) | C18: =IF(H18="CÉLULA CONSTRUTIVA",0,IF(H18="ETAPA",OFFSET(C18,-1,0)+1,OFFSET(C18,-1,0))) | D18: =IF(H18="ETAPA",0,IF(H18="SUBETAPA",OFFSET(D18,-1,0)+1,OFFSET(D18,-1,0))) | E18: =IF(H18="Subetapa",0,IF(H18="serviço",OFFSET(E18,-1,0)+1,OFFSET(E18,-1,0))) | H18: SERVIÇO | I18: =IF(H18="Unidade Construtiva",TEXT(A18,"00"),IF(H18="Célula Construtiva",TEXT(B18,"00"),IF(H18="Etapa",CONCATENATE(TEXT(B18,"00"),".",TEXT(C18,"000")),IF(H18="Subetapa",CONCATENATE(TEXT(B18,"00"),".",TEXT(C18,"000"),".",TEXT(D18,"000")),IF(H18="Serviço",CONCATENATE(TEXT(B18,"00"),".",TEXT(C18,"000"),".",TEXT(D18,"000"),".",TEXT(E18,"000")),""))))) | J18: Projeto arquitetônico de fachada | K18: =_xlfn.XLOOKUP($J18,BASES!$A$12:$A$392,BASES!$C$12:$C$392) | L18: =_xlfn.XLOOKUP($J18,BASES!$A$12:$A$392,BASES!$D$12:$D$392) | M18: =_xlfn.XLOOKUP($J18,BASES!$A$1:$A$2289,BASES!$E$1:$E$2289) | N18: =IF(H18="Serviço",M18*L18,IF(H18="CÉLULA CONSTRUTIVA",SUMIFS($N$8:$N$442,$B$8:$B$442,B18,$H$8:$H$442,"Serviço"),IF(H18="ETAPA",SUMIFS($N$8:$N$442,$B$8:$B$442,B18,$C$8:$C$442,C18,$H$8:$H$442,"Serviço"),IF(H18="SUBETAPA",SUMIFS($N$8:$N$442,$B$8:$B$442,B18,$C$8:$C$442,C18,$D$8:$D$442,D18,$H$8:$H$442,"Serviço"),0)))) | O18: =_xlfn.XLOOKUP($J18,BASES!$A$12:$A$392,BASES!$F$12:$F$392)
A19: =IF($H19="UNIDADE CONSTRUTIVA",OFFSET(A19,-1,0)+1,LARGE(A$3:A18,1)) | B19: =IF(H19="UNIDADE CONSTRUTIVA",0,IF(H19="CÉLULA CONSTRUTIVA",OFFSET(B19,-1,0)+1,OFFSET(B19,-1,0))) | C19: =IF(H19="CÉLULA CONSTRUTIVA",0,IF(H19="ETAPA",OFFSET(C19,-1,0)+1,OFFSET(C19,-1,0))) | D19: =IF(H19="ETAPA",0,IF(H19="SUBETAPA",OFFSET(D19,-1,0)+1,OFFSET(D19,-1,0))) | E19: =IF(H19="Subetapa",0,IF(H19="serviço",OFFSET(E19,-1,0)+1,OFFSET(E19,-1,0))) | H19: SERVIÇO | I19: =IF(H19="Unidade Construtiva",TEXT(A19,"00"),IF(H19="Célula Construtiva",TEXT(B19,"00"),IF(H19="Etapa",CONCATENATE(TEXT(B19,"00"),".",TEXT(C19,"000")),IF(H19="Subetapa",CONCATENATE(TEXT(B19,"00"),".",TEXT(C19,"000"),".",TEXT(D19,"000")),IF(H19="Serviço",CONCATENATE(TEXT(B19,"00"),".",TEXT(C19,"000"),".",TEXT(D19,"000"),".",TEXT(E19,"000")),""))))) | J19: Projeto estrutural | K19: =_xlfn.XLOOKUP($J19,BASES!$A$12:$A$392,BASES!$C$12:$C$392) | L19: =_xlfn.XLOOKUP($J19,BASES!$A$12:$A$392,BASES!$D$12:$D$392) | M19: =_xlfn.XLOOKUP($J19,BASES!$A$1:$A$2289,BASES!$E$1:$E$2289) | N19: =IF(H19="Serviço",M19*L19,IF(H19="CÉLULA CONSTRUTIVA",SUMIFS($N$8:$N$442,$B$8:$B$442,B19,$H$8:$H$442,"Serviço"),IF(H19="ETAPA",SUMIFS($N$8:$N$442,$B$8:$B$442,B19,$C$8:$C$442,C19,$H$8:$H$442,"Serviço"),IF(H19="SUBETAPA",SUMIFS($N$8:$N$442,$B$8:$B$442,B19,$C$8:$C$442,C19,$D$8:$D$442,D19,$H$8:$H$442,"Serviço"),0)))) | O19: =_xlfn.XLOOKUP($J19,BASES!$A$12:$A$392,BASES!$F$12:$F$392)
A20: =IF($H20="UNIDADE CONSTRUTIVA",OFFSET(A20,-1,0)+1,LARGE(A$3:A19,1)) | B20: =IF(H20="UNIDADE CONSTRUTIVA",0,IF(H20="CÉLULA CONSTRUTIVA",OFFSET(B20,-1,0)+1,OFFSET(B20,-1,0))) | C20: =IF(H20="CÉLULA CONSTRUTIVA",0,IF(H20="ETAPA",OFFSET(C20,-1,0)+1,OFFSET(C20,-1,0))) | D20: =IF(H20="ETAPA",0,IF(H20="SUBETAPA",OFFSET(D20,-1,0)+1,OFFSET(D20,-1,0))) | E20: =IF(H20="Subetapa",0,IF(H20="serviço",OFFSET(E20,-1,0)+1,OFFSET(E20,-1,0))) | H20: SERVIÇO | I20: =IF(H20="Unidade Construtiva",TEXT(A20,"00"),IF(H20="Célula Construtiva",TEXT(B20,"00"),IF(H20="Etapa",CONCATENATE(TEXT(B20,"00"),".",TEXT(C20,"000")),IF(H20="Subetapa",CONCATENATE(TEXT(B20,"00"),".",TEXT(C20,"000"),".",TEXT(D20,"000")),IF(H20="Serviço",CONCATENATE(TEXT(B20,"00"),".",TEXT(C20,"000"),".",TEXT(D20,"000"),".",TEXT(E20,"000")),""))))) | J20: Projeto elétrico/comunicação/telefonia/luminotécnico | K20: =_xlfn.XLOOKUP($J20,BASES!$A$12:$A$392,BASES!$C$12:$C$392) | L20: =_xlfn.XLOOKUP($J20,BASES!$A$12:$A$392,BASES!$D$12:$D$392) | M20: =_xlfn.XLOOKUP($J20,BASES!$A$1:$A$2289,BASES!$E$1:$E$2289) | N20: =IF(H20="Serviço",M20*L20,IF(H20="CÉLULA CONSTRUTIVA",SUMIFS($N$8:$N$442,$B$8:$B$442,B20,$H$8:$H$442,"Serviço"),IF(H20="ETAPA",SUMIFS($N$8:$N$442,$B$8:$B$442,B20,$C$8:$C$442,C20,$H$8:$H$442,"Serviço"),IF(H20="SUBETAPA",SUMIFS($N$8:$N$442,$B$8:$B$442,B20,$C$8:$C$442,C20,$D$8:$D$442,D20,$H$8:$H$442,"Serviço"),0)))) | O20: =_xlfn.XLOOKUP($J20,BASES!$A$12:$A$392,BASES!$F$12:$F$392)
A21: =IF($H21="UNIDADE CONSTRUTIVA",OFFSET(A21,-1,0)+1,LARGE(A$3:A20,1)) | B21: =IF(H21="UNIDADE CONSTRUTIVA",0,IF(H21="CÉLULA CONSTRUTIVA",OFFSET(B21,-1,0)+1,OFFSET(B21,-1,0))) | C21: =IF(H21="CÉLULA CONSTRUTIVA",0,IF(H21="ETAPA",OFFSET(C21,-1,0)+1,OFFSET(C21,-1,0))) | D21: =IF(H21="ETAPA",0,IF(H21="SUBETAPA",OFFSET(D21,-1,0)+1,OFFSET(D21,-1,0))) | E21: =IF(H21="Subetapa",0,IF(H21="serviço",OFFSET(E21,-1,0)+1,OFFSET(E21,-1,0))) | H21: SERVIÇO | I21: =IF(H21="Unidade Construtiva",TEXT(A21,"00"),IF(H21="Célula Construtiva",TEXT(B21,"00"),IF(H21="Etapa",CONCATENATE(TEXT(B21,"00"),".",TEXT(C21,"000")),IF(H21="Subetapa",CONCATENATE(TEXT(B21,"00"),".",TEXT(C21,"000"),".",TEXT(D21,"000")),IF(H21="Serviço",CONCATENATE(TEXT(B21,"00"),".",TEXT(C21,"000"),".",TEXT(D21,"000"),".",TEXT(E21,"000")),""))))) | J21: Projeto de Paisagismo | K21: =_xlfn.XLOOKUP($J21,BASES!$A$12:$A$392,BASES!$C$12:$C$392) | L21: =_xlfn.XLOOKUP($J21,BASES!$A$12:$A$392,BASES!$D$12:$D$392) | M21: =_xlfn.XLOOKUP($J21,BASES!$A$1:$A$2289,BASES!$E$1:$E$2289) | N21: =IF(H21="Serviço",M21*L21,IF(H21="CÉLULA CONSTRUTIVA",SUMIFS($N$8:$N$442,$B$8:$B$442,B21,$H$8:$H$442,"Serviço"),IF(H21="ETAPA",SUMIFS($N$8:$N$442,$B$8:$B$442,B21,$C$8:$C$442,C21,$H$8:$H$442,"Serviço"),IF(H21="SUBETAPA",SUMIFS($N$8:$N$442,$B$8:$B$442,B21,$C$8:$C$442,C21,$D$8:$D$442,D21,$H$8:$H$442,"Serviço"),0)))) | O21: =_xlfn.XLOOKUP($J21,BASES!$A$12:$A$392,BASES!$F$12:$F$392)
A22: =IF($H22="UNIDADE CONSTRUTIVA",OFFSET(A22,-1,0)+1,LARGE(A$3:A21,1)) | B22: =IF(H22="UNIDADE CONSTRUTIVA",0,IF(H22="CÉLULA CONSTRUTIVA",OFFSET(B22,-1,0)+1,OFFSET(B22,-1,0))) | C22: =IF(H22="CÉLULA CONSTRUTIVA",0,IF(H22="ETAPA",OFFSET(C22,-1,0)+1,OFFSET(C22,-1,0))) | D22: =IF(H22="ETAPA",0,IF(H22="SUBETAPA",OFFSET(D22,-1,0)+1,OFFSET(D22,-1,0))) | E22: =IF(H22="Subetapa",0,IF(H22="serviço",OFFSET(E22,-1,0)+1,OFFSET(E22,-1,0))) | H22: SUBETAPA | I22: =IF(H22="Unidade Construtiva",TEXT(A22,"00"),IF(H22="Célula Construtiva",TEXT(B22,"00"),IF(H22="Etapa",CONCATENATE(TEXT(B22,"00"),".",TEXT(C22,"000")),IF(H22="Subetapa",CONCATENATE(TEXT(B22,"00"),".",TEXT(C22,"000"),".",TEXT(D22,"000")),IF(H22="Serviço",CONCATENATE(TEXT(B22,"00"),".",TEXT(C22,"000"),".",TEXT(D22,"000"),".",TEXT(E22,"000")),""))))) | J22: Consultorias | N22: =IF(H22="Serviço",M22*L22,IF(H22="CÉLULA CONSTRUTIVA",SUMIFS($N$8:$N$442,$B$8:$B$442,B22,$H$8:$H$442,"Serviço"),IF(H22="ETAPA",SUMIFS($N$8:$N$442,$B$8:$B$442,B22,$C$8:$C$442,C22,$H$8:$H$442,"Serviço"),IF(H22="SUBETAPA",SUMIFS($N$8:$N$442,$B$8:$B$442,B22,$C$8:$C$442,C22,$D$8:$D$442,D22,$H$8:$H$442,"Serviço"),0))))
A23: =IF($H23="UNIDADE CONSTRUTIVA",OFFSET(A23,-1,0)+1,LARGE(A$3:A22,1)) | B23: =IF(H23="UNIDADE CONSTRUTIVA",0,IF(H23="CÉLULA CONSTRUTIVA",OFFSET(B23,-1,0)+1,OFFSET(B23,-1,0))) | C23: =IF(H23="CÉLULA CONSTRUTIVA",0,IF(H23="ETAPA",OFFSET(C23,-1,0)+1,OFFSET(C23,-1,0))) | D23: =IF(H23="ETAPA",0,IF(H23="SUBETAPA",OFFSET(D23,-1,0)+1,OFFSET(D23,-1,0))) | E23: =IF(H23="Subetapa",0,IF(H23="serviço",OFFSET(E23,-1,0)+1,OFFSET(E23,-1,0))) | H23: SERVIÇO | I23: =IF(H23="Unidade Construtiva",TEXT(A23,"00"),IF(H23="Célula Construtiva",TEXT(B23,"00"),IF(H23="Etapa",CONCATENATE(TEXT(B23,"00"),".",TEXT(C23,"000")),IF(H23="Subetapa",CONCATENATE(TEXT(B23,"00"),".",TEXT(C23,"000"),".",TEXT(D23,"000")),IF(H23="Serviço",CONCATENATE(TEXT(B23,"00"),".",TEXT(C23,"000"),".",TEXT(D23,"000"),".",TEXT(E23,"000")),""))))) | J23: Consultorias Técnicas de esquadrias | K23: =_xlfn.XLOOKUP($J23,BASES!$A$12:$A$392,BASES!$C$12:$C$392) | L23: =_xlfn.XLOOKUP($J23,BASES!$A$12:$A$392,BASES!$D$12:$D$392) | M23: =_xlfn.XLOOKUP($J23,BASES!$A$1:$A$2289,BASES!$E$1:$E$2289) | N23: =IF(H23="Serviço",M23*L23,IF(H23="CÉLULA CONSTRUTIVA",SUMIFS($N$8:$N$442,$B$8:$B$442,B23,$H$8:$H$442,"Serviço"),IF(H23="ETAPA",SUMIFS($N$8:$N$442,$B$8:$B$442,B23,$C$8:$C$442,C23,$H$8:$H$442,"Serviço"),IF(H23="SUBETAPA",SUMIFS($N$8:$N$442,$B$8:$B$442,B23,$C$8:$C$442,C23,$D$8:$D$442,D23,$H$8:$H$442,"Serviço"),0)))) | O23: =_xlfn.XLOOKUP($J23,BASES!$A$12:$A$392,BASES!$F$12:$F$392)
A24: =IF($H24="UNIDADE CONSTRUTIVA",OFFSET(A24,-1,0)+1,LARGE(A$3:A23,1)) | B24: =IF(H24="UNIDADE CONSTRUTIVA",0,IF(H24="CÉLULA CONSTRUTIVA",OFFSET(B24,-1,0)+1,OFFSET(B24,-1,0))) | C24: =IF(H24="CÉLULA CONSTRUTIVA",0,IF(H24="ETAPA",OFFSET(C24,-1,0)+1,OFFSET(C24,-1,0))) | D24: =IF(H24="ETAPA",0,IF(H24="SUBETAPA",OFFSET(D24,-1,0)+1,OFFSET(D24,-1,0))) | E24: =IF(H24="Subetapa",0,IF(H24="serviço",OFFSET(E24,-1,0)+1,OFFSET(E24,-1,0))) | H24: SERVIÇO | I24: =IF(H24="Unidade Construtiva",TEXT(A24,"00"),IF(H24="Célula Construtiva",TEXT(B24,"00"),IF(H24="Etapa",CONCATENATE(TEXT(B24,"00"),".",TEXT(C24,"000")),IF(H24="Subetapa",CONCATENATE(TEXT(B24,"00"),".",TEXT(C24,"000"),".",TEXT(D24,"000")),IF(H24="Serviço",CONCATENATE(TEXT(B24,"00"),".",TEXT(C24,"000"),".",TEXT(D24,"000"),".",TEXT(E24,"000")),""))))) | J24: Consultoria técnica de legalização | K24: =_xlfn.XLOOKUP($J24,BASES!$A$12:$A$392,BASES!$C$12:$C$392) | L24: =_xlfn.XLOOKUP($J24,BASES!$A$12:$A$392,BASES!$D$12:$D$392) | M24: =_xlfn.XLOOKUP($J24,BASES!$A$1:$A$2289,BASES!$E$1:$E$2289) | N24: =IF(H24="Serviço",M24*L24,IF(H24="CÉLULA CONSTRUTIVA",SUMIFS($N$8:$N$442,$B$8:$B$442,B24,$H$8:$H$442,"Serviço"),IF(H24="ETAPA",SUMIFS($N$8:$N$442,$B$8:$B$442,B24,$C$8:$C$442,C24,$H$8:$H$442,"Serviço"),IF(H24="SUBETAPA",SUMIFS($N$8:$N$442,$B$8:$B$442,B24,$C$8:$C$442,C24,$D$8:$D$442,D24,$H$8:$H$442,"Serviço"),0)))) | O24: =_xlfn.XLOOKUP($J24,BASES!$A$12:$A$392,BASES!$F$12:$F$392)
A25: =IF($H25="UNIDADE CONSTRUTIVA",OFFSET(A25,-1,0)+1,LARGE(A$3:A24,1)) | B25: =IF(H25="UNIDADE CONSTRUTIVA",0,IF(H25="CÉLULA CONSTRUTIVA",OFFSET(B25,-1,0)+1,OFFSET(B25,-1,0))) | C25: =IF(H25="CÉLULA CONSTRUTIVA",0,IF(H25="ETAPA",OFFSET(C25,-1,0)+1,OFFSET(C25,-1,0))) | D25: =IF(H25="ETAPA",0,IF(H25="SUBETAPA",OFFSET(D25,-1,0)+1,OFFSET(D25,-1,0))) | E25: =IF(H25="Subetapa",0,IF(H25="serviço",OFFSET(E25,-1,0)+1,OFFSET(E25,-1,0))) | H25: SERVIÇO | I25: =IF(H25="Unidade Construtiva",TEXT(A25,"00"),IF(H25="Célula Construtiva",TEXT(B25,"00"),IF(H25="Etapa",CONCATENATE(TEXT(B25,"00"),".",TEXT(C25,"000")),IF(H25="Subetapa",CONCATENATE(TEXT(B25,"00"),".",TEXT(C25,"000"),".",TEXT(D25,"000")),IF(H25="Serviço",CONCATENATE(TEXT(B25,"00"),".",TEXT(C25,"000"),".",TEXT(D25,"000"),".",TEXT(E25,"000")),""))))) | J25: Orçamento e planejamento | K25: =_xlfn.XLOOKUP($J25,BASES!$A$12:$A$392,BASES!$C$12:$C$392) | L25: =_xlfn.XLOOKUP($J25,BASES!$A$12:$A$392,BASES!$D$12:$D$392) | M25: =_xlfn.XLOOKUP($J25,BASES!$A$1:$A$2289,BASES!$E$1:$E$2289) | N25: =IF(H25="Serviço",M25*L25,IF(H25="CÉLULA CONSTRUTIVA",SUMIFS($N$8:$N$442,$B$8:$B$442,B25,$H$8:$H$442,"Serviço"),IF(H25="ETAPA",SUMIFS($N$8:$N$442,$B$8:$B$442,B25,$C$8:$C$442,C25,$H$8:$H$442,"Serviço"),IF(H25="SUBETAPA",SUMIFS($N$8:$N$442,$B$8:$B$442,B25,$C$8:$C$442,C25,$D$8:$D$442,D25,$H$8:$H$442,"Serviço"),0)))) | O25: =_xlfn.XLOOKUP($J25,BASES!$A$12:$A$392,BASES!$F$12:$F$392)
A26: =IF($H26="UNIDADE CONSTRUTIVA",OFFSET(A26,-1,0)+1,LARGE(A$3:A25,1)) | B26: =IF(H26="UNIDADE CONSTRUTIVA",0,IF(H26="CÉLULA CONSTRUTIVA",OFFSET(B26,-1,0)+1,OFFSET(B26,-1,0))) | C26: =IF(H26="CÉLULA CONSTRUTIVA",0,IF(H26="ETAPA",OFFSET(C26,-1,0)+1,OFFSET(C26,-1,0))) | D26: =IF(H26="ETAPA",0,IF(H26="SUBETAPA",OFFSET(D26,-1,0)+1,OFFSET(D26,-1,0))) | E26: =IF(H26="Subetapa",0,IF(H26="serviço",OFFSET(E26,-1,0)+1,OFFSET(E26,-1,0))) | H26: SERVIÇO | I26: =IF(H26="Unidade Construtiva",TEXT(A26,"00"),IF(H26="Célula Construtiva",TEXT(B26,"00"),IF(H26="Etapa",CONCATENATE(TEXT(B26,"00"),".",TEXT(C26,"000")),IF(H26="Subetapa",CONCATENATE(TEXT(B26,"00"),".",TEXT(C26,"000"),".",TEXT(D26,"000")),IF(H26="Serviço",CONCATENATE(TEXT(B26,"00"),".",TEXT(C26,"000"),".",TEXT(D26,"000"),".",TEXT(E26,"000")),""))))) | J26: Consultoria em Licenciamento Ambiental | K26: =_xlfn.XLOOKUP($J26,BASES!$A$12:$A$392,BASES!$C$12:$C$392) | L26: =_xlfn.XLOOKUP($J26,BASES!$A$12:$A$392,BASES!$D$12:$D$392) | M26: =_xlfn.XLOOKUP($J26,BASES!$A$1:$A$2289,BASES!$E$1:$E$2289) | N26: =IF(H26="Serviço",M26*L26,IF(H26="CÉLULA CONSTRUTIVA",SUMIFS($N$8:$N$442,$B$8:$B$442,B26,$H$8:$H$442,"Serviço"),IF(H26="ETAPA",SUMIFS($N$8:$N$442,$B$8:$B$442,B26,$C$8:$C$442,C26,$H$8:$H$442,"Serviço"),IF(H26="SUBETAPA",SUMIFS($N$8:$N$442,$B$8:$B$442,B26,$C$8:$C$442,C26,$D$8:$D$442,D26,$H$8:$H$442,"Serviço"),0)))) | O26: =_xlfn.XLOOKUP($J26,BASES!$A$12:$A$392,BASES!$F$12:$F$392)
A27: =IF($H27="UNIDADE CONSTRUTIVA",OFFSET(A27,-1,0)+1,LARGE(A$3:A26,1)) | B27: =IF(H27="UNIDADE CONSTRUTIVA",0,IF(H27="CÉLULA CONSTRUTIVA",OFFSET(B27,-1,0)+1,OFFSET(B27,-1,0))) | C27: =IF(H27="CÉLULA CONSTRUTIVA",0,IF(H27="ETAPA",OFFSET(C27,-1,0)+1,OFFSET(C27,-1,0))) | D27: =IF(H27="ETAPA",0,IF(H27="SUBETAPA",OFFSET(D27,-1,0)+1,OFFSET(D27,-1,0))) | E27: =IF(H27="Subetapa",0,IF(H27="serviço",OFFSET(E27,-1,0)+1,OFFSET(E27,-1,0))) | H27: SUBETAPA | I27: =IF(H27="Unidade Construtiva",TEXT(A27,"00"),IF(H27="Célula Construtiva",TEXT(B27,"00"),IF(H27="Etapa",CONCATENATE(TEXT(B27,"00"),".",TEXT(C27,"000")),IF(H27="Subetapa",CONCATENATE(TEXT(B27,"00"),".",TEXT(C27,"000"),".",TEXT(D27,"000")),IF(H27="Serviço",CONCATENATE(TEXT(B27,"00"),".",TEXT(C27,"000"),".",TEXT(D27,"000"),".",TEXT(E27,"000")),""))))) | J27: Ensaios | N27: =IF(H27="Serviço",M27*L27,IF(H27="CÉLULA CONSTRUTIVA",SUMIFS($N$8:$N$442,$B$8:$B$442,B27,$H$8:$H$442,"Serviço"),IF(H27="ETAPA",SUMIFS($N$8:$N$442,$B$8:$B$442,B27,$C$8:$C$442,C27,$H$8:$H$442,"Serviço"),IF(H27="SUBETAPA",SUMIFS($N$8:$N$442,$B$8:$B$442,B27,$C$8:$C$442,C27,$D$8:$D$442,D27,$H$8:$H$442,"Serviço"),0))))
A28: =IF($H28="UNIDADE CONSTRUTIVA",OFFSET(A28,-1,0)+1,LARGE(A$3:A27,1)) | B28: =IF(H28="UNIDADE CONSTRUTIVA",0,IF(H28="CÉLULA CONSTRUTIVA",OFFSET(B28,-1,0)+1,OFFSET(B28,-1,0))) | C28: =IF(H28="CÉLULA CONSTRUTIVA",0,IF(H28="ETAPA",OFFSET(C28,-1,0)+1,OFFSET(C28,-1,0))) | D28: =IF(H28="ETAPA",0,IF(H28="SUBETAPA",OFFSET(D28,-1,0)+1,OFFSET(D28,-1,0))) | E28: =IF(H28="Subetapa",0,IF(H28="serviço",OFFSET(E28,-1,0)+1,OFFSET(E28,-1,0))) | H28: SERVIÇO | I28: =IF(H28="Unidade Construtiva",TEXT(A28,"00"),IF(H28="Célula Construtiva",TEXT(B28,"00"),IF(H28="Etapa",CONCATENATE(TEXT(B28,"00"),".",TEXT(C28,"000")),IF(H28="Subetapa",CONCATENATE(TEXT(B28,"00"),".",TEXT(C28,"000"),".",TEXT(D28,"000")),IF(H28="Serviço",CONCATENATE(TEXT(B28,"00"),".",TEXT(C28,"000"),".",TEXT(D28,"000"),".",TEXT(E28,"000")),""))))) | J28: Controle tecnológico do concreto | K28: =_xlfn.XLOOKUP($J28,BASES!$A$12:$A$392,BASES!$C$12:$C$392) | L28: =_xlfn.XLOOKUP($J28,BASES!$A$12:$A$392,BASES!$D$12:$D$392) | M28: ='Cont.Tecnol.'!F6+'Cont.Tecnol.'!F11+'Cont.Tecnol.'!F16+'Cont.Tecnol.'!F21+'Cont.Tecnol.'!F26 | N28: =IF(H28="Serviço",M28*L28,IF(H28="CÉLULA CONSTRUTIVA",SUMIFS($N$8:$N$442,$B$8:$B$442,B28,$H$8:$H$442,"Serviço"),IF(H28="ETAPA",SUMIFS($N$8:$N$442,$B$8:$B$442,B28,$C$8:$C$442,C28,$H$8:$H$442,"Serviço"),IF(H28="SUBETAPA",SUMIFS($N$8:$N$442,$B$8:$B$442,B28,$C$8:$C$442,C28,$D$8:$D$442,D28,$H$8:$H$442,"Serviço"),0)))) | O28: Estimado conrfome aba "Cont. Tecnol."
A29: =IF($H29="UNIDADE CONSTRUTIVA",OFFSET(A29,-1,0)+1,LARGE(A$3:A28,1)) | B29: =IF(H29="UNIDADE CONSTRUTIVA",0,IF(H29="CÉLULA CONSTRUTIVA",OFFSET(B29,-1,0)+1,OFFSET(B29,-1,0))) | C29: =IF(H29="CÉLULA CONSTRUTIVA",0,IF(H29="ETAPA",OFFSET(C29,-1,0)+1,OFFSET(C29,-1,0))) | D29: =IF(H29="ETAPA",0,IF(H29="SUBETAPA",OFFSET(D29,-1,0)+1,OFFSET(D29,-1,0))) | E29: =IF(H29="Subetapa",0,IF(H29="serviço",OFFSET(E29,-1,0)+1,OFFSET(E29,-1,0))) | H29: SERVIÇO | I29: =IF(H29="Unidade Construtiva",TEXT(A29,"00"),IF(H29="Célula Construtiva",TEXT(B29,"00"),IF(H29="Etapa",CONCATENATE(TEXT(B29,"00"),".",TEXT(C29,"000")),IF(H29="Subetapa",CONCATENATE(TEXT(B29,"00"),".",TEXT(C29,"000"),".",TEXT(D29,"000")),IF(H29="Serviço",CONCATENATE(TEXT(B29,"00"),".",TEXT(C29,"000"),".",TEXT(D29,"000"),".",TEXT(E29,"000")),""))))) | J29: Prova de carga | K29: =_xlfn.XLOOKUP($J29,BASES!$A$12:$A$392,BASES!$C$12:$C$392) | L29: =_xlfn.XLOOKUP($J29,BASES!$A$12:$A$392,BASES!$D$12:$D$392) | M29: =_xlfn.XLOOKUP($J29,BASES!$A$1:$A$2289,BASES!$E$1:$E$2289) | N29: =IF(H29="Serviço",M29*L29,IF(H29="CÉLULA CONSTRUTIVA",SUMIFS($N$8:$N$442,$B$8:$B$442,B29,$H$8:$H$442,"Serviço"),IF(H29="ETAPA",SUMIFS($N$8:$N$442,$B$8:$B$442,B29,$C$8:$C$442,C29,$H$8:$H$442,"Serviço"),IF(H29="SUBETAPA",SUMIFS($N$8:$N$442,$B$8:$B$442,B29,$C$8:$C$442,C29,$D$8:$D$442,D29,$H$8:$H$442,"Serviço"),0)))) | O29: =_xlfn.XLOOKUP($J29,BASES!$A$12:$A$392,BASES!$F$12:$F$392)
A30: =IF($H30="UNIDADE CONSTRUTIVA",OFFSET(A30,-1,0)+1,LARGE(A$3:A29,1)) | B30: =IF(H30="UNIDADE CONSTRUTIVA",0,IF(H30="CÉLULA CONSTRUTIVA",OFFSET(B30,-1,0)+1,OFFSET(B30,-1,0))) | C30: =IF(H30="CÉLULA CONSTRUTIVA",0,IF(H30="ETAPA",OFFSET(C30,-1,0)+1,OFFSET(C30,-1,0))) | D30: =IF(H30="ETAPA",0,IF(H30="SUBETAPA",OFFSET(D30,-1,0)+1,OFFSET(D30,-1,0))) | E30: =IF(H30="Subetapa",0,IF(H30="serviço",OFFSET(E30,-1,0)+1,OFFSET(E30,-1,0))) | H30: SERVIÇO | I30: =IF(H30="Unidade Construtiva",TEXT(A30,"00"),IF(H30="Célula Construtiva",TEXT(B30,"00"),IF(H30="Etapa",CONCATENATE(TEXT(B30,"00"),".",TEXT(C30,"000")),IF(H30="Subetapa",CONCATENATE(TEXT(B30,"00"),".",TEXT(C30,"000"),".",TEXT(D30,"000")),IF(H30="Serviço",CONCATENATE(TEXT(B30,"00"),".",TEXT(C30,"000"),".",TEXT(D30,"000"),".",TEXT(E30,"000")),""))))) | J30: Ensaio de arrancamento de reboco | K30: =_xlfn.XLOOKUP($J30,BASES!$A$12:$A$392,BASES!$C$12:$C$392) | L30: =_xlfn.XLOOKUP($J30,BASES!$A$12:$A$392,BASES!$D$12:$D$392) | M30: =_xlfn.XLOOKUP($J30,BASES!$A$1:$A$2289,BASES!$E$1:$E$2289) | N30: =IF(H30="Serviço",M30*L30,IF(H30="CÉLULA CONSTRUTIVA",SUMIFS($N$8:$N$442,$B$8:$B$442,B30,$H$8:$H$442,"Serviço"),IF(H30="ETAPA",SUMIFS($N$8:$N$442,$B$8:$B$442,B30,$C$8:$C$442,C30,$H$8:$H$442,"Serviço"),IF(H30="SUBETAPA",SUMIFS($N$8:$N$442,$B$8:$B$442,B30,$C$8:$C$442,C30,$D$8:$D$442,D30,$H$8:$H$442,"Serviço"),0)))) | O30: =_xlfn.XLOOKUP($J30,BASES!$A$12:$A$392,BASES!$F$12:$F$392)
A31: =IF($H31="UNIDADE CONSTRUTIVA",OFFSET(A31,-1,0)+1,LARGE(A$3:A30,1)) | B31: =IF(H31="UNIDADE CONSTRUTIVA",0,IF(H31="CÉLULA CONSTRUTIVA",OFFSET(B31,-1,0)+1,OFFSET(B31,-1,0))) | C31: =IF(H31="CÉLULA CONSTRUTIVA",0,IF(H31="ETAPA",OFFSET(C31,-1,0)+1,OFFSET(C31,-1,0))) | D31: =IF(H31="ETAPA",0,IF(H31="SUBETAPA",OFFSET(D31,-1,0)+1,OFFSET(D31,-1,0))) | E31: =IF(H31="Subetapa",0,IF(H31="serviço",OFFSET(E31,-1,0)+1,OFFSET(E31,-1,0))) | H31: SERVIÇO | I31: =IF(H31="Unidade Construtiva",TEXT(A31,"00"),IF(H31="Célula Construtiva",TEXT(B31,"00"),IF(H31="Etapa",CONCATENATE(TEXT(B31,"00"),".",TEXT(C31,"000")),IF(H31="Subetapa",CONCATENATE(TEXT(B31,"00"),".",TEXT(C31,"000"),".",TEXT(D31,"000")),IF(H31="Serviço",CONCATENATE(TEXT(B31,"00"),".",TEXT(C31,"000"),".",TEXT(D31,"000"),".",TEXT(E31,"000")),""))))) | J31: Laudo de Vizinhança | K31: =_xlfn.XLOOKUP($J31,BASES!$A$12:$A$392,BASES!$C$12:$C$392) | L31: =_xlfn.XLOOKUP($J31,BASES!$A$12:$A$392,BASES!$D$12:$D$392) | M31: =_xlfn.XLOOKUP($J31,BASES!$A$1:$A$2289,BASES!$E$1:$E$2289) | N31: =IF(H31="Serviço",M31*L31,IF(H31="CÉLULA CONSTRUTIVA",SUMIFS($N$8:$N$442,$B$8:$B$442,B31,$H$8:$H$442,"Serviço"),IF(H31="ETAPA",SUMIFS($N$8:$N$442,$B$8:$B$442,B31,$C$8:$C$442,C31,$H$8:$H$442,"Serviço"),IF(H31="SUBETAPA",SUMIFS($N$8:$N$442,$B$8:$B$442,B31,$C$8:$C$442,C31,$D$8:$D$442,D31,$H$8:$H$442,"Serviço"),0)))) | O31: =_xlfn.XLOOKUP($J31,BASES!$A$12:$A$392,BASES!$F$12:$F$392)
A32: =IF($H32="UNIDADE CONSTRUTIVA",OFFSET(A32,-1,0)+1,LARGE(A$3:A31,1)) | B32: =IF(H32="UNIDADE CONSTRUTIVA",0,IF(H32="CÉLULA CONSTRUTIVA",OFFSET(B32,-1,0)+1,OFFSET(B32,-1,0))) | C32: =IF(H32="CÉLULA CONSTRUTIVA",0,IF(H32="ETAPA",OFFSET(C32,-1,0)+1,OFFSET(C32,-1,0))) | D32: =IF(H32="ETAPA",0,IF(H32="SUBETAPA",OFFSET(D32,-1,0)+1,OFFSET(D32,-1,0))) | E32: =IF(H32="Subetapa",0,IF(H32="serviço",OFFSET(E32,-1,0)+1,OFFSET(E32,-1,0))) | H32: ETAPA | I32: =IF(H32="Unidade Construtiva",TEXT(A32,"00"),IF(H32="Célula Construtiva",TEXT(B32,"00"),IF(H32="Etapa",CONCATENATE(TEXT(B32,"00"),".",TEXT(C32,"000")),IF(H32="Subetapa",CONCATENATE(TEXT(B32,"00"),".",TEXT(C32,"000"),".",TEXT(D32,"000")),IF(H32="Serviço",CONCATENATE(TEXT(B32,"00"),".",TEXT(C32,"000"),".",TEXT(D32,"000"),".",TEXT(E32,"000")),""))))) | J32: CONSUMOS, TAXAS E DOCUMENTOS | N32: =IF(H32="Serviço",M32*L32,IF(H32="CÉLULA CONSTRUTIVA",SUMIFS($N$8:$N$442,$B$8:$B$442,B32,$H$8:$H$442,"Serviço"),IF(H32="ETAPA",SUMIFS($N$8:$N$442,$B$8:$B$442,B32,$C$8:$C$442,C32,$H$8:$H$442,"Serviço"),IF(H32="SUBETAPA",SUMIFS($N$8:$N$442,$B$8:$B$442,B32,$C$8:$C$442,C32,$D$8:$D$442,D32,$H$8:$H$442,"Serviço"),0))))
A33: =IF($H33="UNIDADE CONSTRUTIVA",OFFSET(A33,-1,0)+1,LARGE(A$3:A32,1)) | B33: =IF(H33="UNIDADE CONSTRUTIVA",0,IF(H33="CÉLULA CONSTRUTIVA",OFFSET(B33,-1,0)+1,OFFSET(B33,-1,0))) | C33: =IF(H33="CÉLULA CONSTRUTIVA",0,IF(H33="ETAPA",OFFSET(C33,-1,0)+1,OFFSET(C33,-1,0))) | D33: =IF(H33="ETAPA",0,IF(H33="SUBETAPA",OFFSET(D33,-1,0)+1,OFFSET(D33,-1,0))) | E33: =IF(H33="Subetapa",0,IF(H33="serviço",OFFSET(E33,-1,0)+1,OFFSET(E33,-1,0))) | H33: SUBETAPA | I33: =IF(H33="Unidade Construtiva",TEXT(A33,"00"),IF(H33="Célula Construtiva",TEXT(B33,"00"),IF(H33="Etapa",CONCATENATE(TEXT(B33,"00"),".",TEXT(C33,"000")),IF(H33="Subetapa",CONCATENATE(TEXT(B33,"00"),".",TEXT(C33,"000"),".",TEXT(D33,"000")),IF(H33="Serviço",CONCATENATE(TEXT(B33,"00"),".",TEXT(C33,"000"),".",TEXT(D33,"000"),".",TEXT(E33,"000")),""))))) | J33: Licenciamentos, Taxas, Impostos, Aprovações e Seguros | N33: =IF(H33="Serviço",M33*L33,IF(H33="CÉLULA CONSTRUTIVA",SUMIFS($N$8:$N$467,$B$8:$B$467,B33,$H$8:$H$467,"Serviço"),IF(H33="ETAPA",SUMIFS($N$8:$N$467,$B$8:$B$467,B33,$C$8:$C$467,C33,$H$8:$H$467,"Serviço"),IF(H33="SUBETAPA",SUMIFS($N$8:$N$467,$B$8:$B$467,B33,$C$8:$C$467,C33,$D$8:$D$467,D33,$H$8:$H$467,"Serviço"),0))))
A34: =IF($H34="UNIDADE CONSTRUTIVA",OFFSET(A34,-1,0)+1,LARGE(A$3:A33,1)) | B34: =IF(H34="UNIDADE CONSTRUTIVA",0,IF(H34="CÉLULA CONSTRUTIVA",OFFSET(B34,-1,0)+1,OFFSET(B34,-1,0))) | C34: =IF(H34="CÉLULA CONSTRUTIVA",0,IF(H34="ETAPA",OFFSET(C34,-1,0)+1,OFFSET(C34,-1,0))) | D34: =IF(H34="ETAPA",0,IF(H34="SUBETAPA",OFFSET(D34,-1,0)+1,OFFSET(D34,-1,0))) | E34: =IF(H34="Subetapa",0,IF(H34="serviço",OFFSET(E34,-1,0)+1,OFFSET(E34,-1,0))) | H34: SERVIÇO | I34: =IF(H34="Unidade Construtiva",TEXT(A34,"00"),IF(H34="Célula Construtiva",TEXT(B34,"00"),IF(H34="Etapa",CONCATENATE(TEXT(B34,"00"),".",TEXT(C34,"000")),IF(H34="Subetapa",CONCATENATE(TEXT(B34,"00"),".",TEXT(C34,"000"),".",TEXT(D34,"000")),IF(H34="Serviço",CONCATENATE(TEXT(B34,"00"),".",TEXT(C34,"000"),".",TEXT(D34,"000"),".",TEXT(E34,"000")),""))))) | J34: Despesas de Seguros | K34: =_xlfn.XLOOKUP($J34,BASES!$A$12:$A$392,BASES!$C$12:$C$392) | L34: =_xlfn.XLOOKUP($J34,BASES!$A$12:$A$392,BASES!$D$12:$D$392) | M34: =_xlfn.XLOOKUP($J34,BASES!$A$1:$A$2289,BASES!$E$1:$E$2289) | N34: =IF(H34="Serviço",M34*L34,IF(H34="CÉLULA CONSTRUTIVA",SUMIFS($N$8:$N$467,$B$8:$B$467,B34,$H$8:$H$467,"Serviço"),IF(H34="ETAPA",SUMIFS($N$8:$N$467,$B$8:$B$467,B34,$C$8:$C$467,C34,$H$8:$H$467,"Serviço"),IF(H34="SUBETAPA",SUMIFS($N$8:$N$467,$B$8:$B$467,B34,$C$8:$C$467,C34,$D$8:$D$467,D34,$H$8:$H$467,"Serviço"),0)))) | O34: =_xlfn.XLOOKUP($J34,BASES!$A$12:$A$392,BASES!$F$12:$F$392)
A35: =IF($H35="UNIDADE CONSTRUTIVA",OFFSET(A35,-1,0)+1,LARGE(A$3:A34,1)) | B35: =IF(H35="UNIDADE CONSTRUTIVA",0,IF(H35="CÉLULA CONSTRUTIVA",OFFSET(B35,-1,0)+1,OFFSET(B35,-1,0))) | C35: =IF(H35="CÉLULA CONSTRUTIVA",0,IF(H35="ETAPA",OFFSET(C35,-1,0)+1,OFFSET(C35,-1,0))) | D35: =IF(H35="ETAPA",0,IF(H35="SUBETAPA",OFFSET(D35,-1,0)+1,OFFSET(D35,-1,0))) | E35: =IF(H35="Subetapa",0,IF(H35="serviço",OFFSET(E35,-1,0)+1,OFFSET(E35,-1,0))) | H35: SERVIÇO | I35: =IF(H35="Unidade Construtiva",TEXT(A35,"00"),IF(H35="Célula Construtiva",TEXT(B35,"00"),IF(H35="Etapa",CONCATENATE(TEXT(B35,"00"),".",TEXT(C35,"000")),IF(H35="Subetapa",CONCATENATE(TEXT(B35,"00"),".",TEXT(C35,"000"),".",TEXT(D35,"000")),IF(H35="Serviço",CONCATENATE(TEXT(B35,"00"),".",TEXT(C35,"000"),".",TEXT(D35,"000"),".",TEXT(E35,"000")),""))))) | J35: Taxas de consulta de viabilidade | K35: =_xlfn.XLOOKUP($J35,BASES!$A$12:$A$392,BASES!$C$12:$C$392) | L35: =_xlfn.XLOOKUP($J35,BASES!$A$12:$A$392,BASES!$D$12:$D$392) | M35: =_xlfn.XLOOKUP($J35,BASES!$A$1:$A$2289,BASES!$E$1:$E$2289) | N35: =IF(H35="Serviço",M35*L35,IF(H35="CÉLULA CONSTRUTIVA",SUMIFS($N$8:$N$467,$B$8:$B$467,B35,$H$8:$H$467,"Serviço"),IF(H35="ETAPA",SUMIFS($N$8:$N$467,$B$8:$B$467,B35,$C$8:$C$467,C35,$H$8:$H$467,"Serviço"),IF(H35="SUBETAPA",SUMIFS($N$8:$N$467,$B$8:$B$467,B35,$C$8:$C$467,C35,$D$8:$D$467,D35,$H$8:$H$467,"Serviço"),0)))) | O35: =_xlfn.XLOOKUP($J35,BASES!$A$12:$A$392,BASES!$F$12:$F$392)
A36: =IF($H36="UNIDADE CONSTRUTIVA",OFFSET(A36,-1,0)+1,LARGE(A$3:A35,1)) | B36: =IF(H36="UNIDADE CONSTRUTIVA",0,IF(H36="CÉLULA CONSTRUTIVA",OFFSET(B36,-1,0)+1,OFFSET(B36,-1,0))) | C36: =IF(H36="CÉLULA CONSTRUTIVA",0,IF(H36="ETAPA",OFFSET(C36,-1,0)+1,OFFSET(C36,-1,0))) | D36: =IF(H36="ETAPA",0,IF(H36="SUBETAPA",OFFSET(D36,-1,0)+1,OFFSET(D36,-1,0))) | E36: =IF(H36="Subetapa",0,IF(H36="serviço",OFFSET(E36,-1,0)+1,OFFSET(E36,-1,0))) | H36: SERVIÇO | I36: =IF(H36="Unidade Construtiva",TEXT(A36,"00"),IF(H36="Célula Construtiva",TEXT(B36,"00"),IF(H36="Etapa",CONCATENATE(TEXT(B36,"00"),".",TEXT(C36,"000")),IF(H36="Subetapa",CONCATENATE(TEXT(B36,"00"),".",TEXT(C36,"000"),".",TEXT(D36,"000")),IF(H36="Serviço",CONCATENATE(TEXT(B36,"00"),".",TEXT(C36,"000"),".",TEXT(D36,"000"),".",TEXT(E36,"000")),""))))) | J36: Avaliação e Legalização ambiental | K36: =_xlfn.XLOOKUP($J36,BASES!$A$12:$A$392,BASES!$C$12:$C$392) | L36: =_xlfn.XLOOKUP($J36,BASES!$A$12:$A$392,BASES!$D$12:$D$392) | M36: =_xlfn.XLOOKUP($J36,BASES!$A$1:$A$2289,BASES!$E$1:$E$2289) | N36: =IF(H36="Serviço",M36*L36,IF(H36="CÉLULA CONSTRUTIVA",SUMIFS($N$8:$N$467,$B$8:$B$467,B36,$H$8:$H$467,"Serviço"),IF(H36="ETAPA",SUMIFS($N$8:$N$467,$B$8:$B$467,B36,$C$8:$C$467,C36,$H$8:$H$467,"Serviço"),IF(H36="SUBETAPA",SUMIFS($N$8:$N$467,$B$8:$B$467,B36,$C$8:$C$467,C36,$D$8:$D$467,D36,$H$8:$H$467,"Serviço"),0)))) | O36: =_xlfn.XLOOKUP($J36,BASES!$A$12:$A$392,BASES!$F$12:$F$392)
A37: =IF($H37="UNIDADE CONSTRUTIVA",OFFSET(A37,-1,0)+1,LARGE(A$3:A36,1)) | B37: =IF(H37="UNIDADE CONSTRUTIVA",0,IF(H37="CÉLULA CONSTRUTIVA",OFFSET(B37,-1,0)+1,OFFSET(B37,-1,0))) | C37: =IF(H37="CÉLULA CONSTRUTIVA",0,IF(H37="ETAPA",OFFSET(C37,-1,0)+1,OFFSET(C37,-1,0))) | D37: =IF(H37="ETAPA",0,IF(H37="SUBETAPA",OFFSET(D37,-1,0)+1,OFFSET(D37,-1,0))) | E37: =IF(H37="Subetapa",0,IF(H37="serviço",OFFSET(E37,-1,0)+1,OFFSET(E37,-1,0))) | H37: SERVIÇO | I37: =IF(H37="Unidade Construtiva",TEXT(A37,"00"),IF(H37="Célula Construtiva",TEXT(B37,"00"),IF(H37="Etapa",CONCATENATE(TEXT(B37,"00"),".",TEXT(C37,"000")),IF(H37="Subetapa",CONCATENATE(TEXT(B37,"00"),".",TEXT(C37,"000"),".",TEXT(D37,"000")),IF(H37="Serviço",CONCATENATE(TEXT(B37,"00"),".",TEXT(C37,"000"),".",TEXT(D37,"000"),".",TEXT(E37,"000")),""))))) | J37: Aprovação e legalização prefeitura | K37: =_xlfn.XLOOKUP($J37,BASES!$A$12:$A$392,BASES!$C$12:$C$392) | L37: =_xlfn.XLOOKUP($J37,BASES!$A$12:$A$392,BASES!$D$12:$D$392) | M37: =_xlfn.XLOOKUP($J37,BASES!$A$1:$A$2289,BASES!$E$1:$E$2289) | N37: =IF(H37="Serviço",M37*L37,IF(H37="CÉLULA CONSTRUTIVA",SUMIFS($N$8:$N$467,$B$8:$B$467,B37,$H$8:$H$467,"Serviço"),IF(H37="ETAPA",SUMIFS($N$8:$N$467,$B$8:$B$467,B37,$C$8:$C$467,C37,$H$8:$H$467,"Serviço"),IF(H37="SUBETAPA",SUMIFS($N$8:$N$467,$B$8:$B$467,B37,$C$8:$C$467,C37,$D$8:$D$467,D37,$H$8:$H$467,"Serviço"),0)))) | O37: =_xlfn.XLOOKUP($J37,BASES!$A$12:$A$392,BASES!$F$12:$F$392)
A38: =IF($H38="UNIDADE CONSTRUTIVA",OFFSET(A38,-1,0)+1,LARGE(A$3:A37,1)) | B38: =IF(H38="UNIDADE CONSTRUTIVA",0,IF(H38="CÉLULA CONSTRUTIVA",OFFSET(B38,-1,0)+1,OFFSET(B38,-1,0))) | C38: =IF(H38="CÉLULA CONSTRUTIVA",0,IF(H38="ETAPA",OFFSET(C38,-1,0)+1,OFFSET(C38,-1,0))) | D38: =IF(H38="ETAPA",0,IF(H38="SUBETAPA",OFFSET(D38,-1,0)+1,OFFSET(D38,-1,0))) | E38: =IF(H38="Subetapa",0,IF(H38="serviço",OFFSET(E38,-1,0)+1,OFFSET(E38,-1,0))) | H38: SERVIÇO | I38: =IF(H38="Unidade Construtiva",TEXT(A38,"00"),IF(H38="Célula Construtiva",TEXT(B38,"00"),IF(H38="Etapa",CONCATENATE(TEXT(B38,"00"),".",TEXT(C38,"000")),IF(H38="Subetapa",CONCATENATE(TEXT(B38,"00"),".",TEXT(C38,"000"),".",TEXT(D38,"000")),IF(H38="Serviço",CONCATENATE(TEXT(B38,"00"),".",TEXT(C38,"000"),".",TEXT(D38,"000"),".",TEXT(E38,"000")),""))))) | J38: Aprovação e legalização água e esgoto | K38: =_xlfn.XLOOKUP($J38,BASES!$A$12:$A$392,BASES!$C$12:$C$392) | L38: =_xlfn.XLOOKUP($J38,BASES!$A$12:$A$392,BASES!$D$12:$D$392) | M38: =_xlfn.XLOOKUP($J38,BASES!$A$1:$A$2289,BASES!$E$1:$E$2289) | N38: =IF(H38="Serviço",M38*L38,IF(H38="CÉLULA CONSTRUTIVA",SUMIFS($N$8:$N$467,$B$8:$B$467,B38,$H$8:$H$467,"Serviço"),IF(H38="ETAPA",SUMIFS($N$8:$N$467,$B$8:$B$467,B38,$C$8:$C$467,C38,$H$8:$H$467,"Serviço"),IF(H38="SUBETAPA",SUMIFS($N$8:$N$467,$B$8:$B$467,B38,$C$8:$C$467,C38,$D$8:$D$467,D38,$H$8:$H$467,"Serviço"),0)))) | O38: =_xlfn.XLOOKUP($J38,BASES!$A$12:$A$392,BASES!$F$12:$F$392)
A39: =IF($H39="UNIDADE CONSTRUTIVA",OFFSET(A39,-1,0)+1,LARGE(A$3:A38,1)) | B39: =IF(H39="UNIDADE CONSTRUTIVA",0,IF(H39="CÉLULA CONSTRUTIVA",OFFSET(B39,-1,0)+1,OFFSET(B39,-1,0))) | C39: =IF(H39="CÉLULA CONSTRUTIVA",0,IF(H39="ETAPA",OFFSET(C39,-1,0)+1,OFFSET(C39,-1,0))) | D39: =IF(H39="ETAPA",0,IF(H39="SUBETAPA",OFFSET(D39,-1,0)+1,OFFSET(D39,-1,0))) | E39: =IF(H39="Subetapa",0,IF(H39="serviço",OFFSET(E39,-1,0)+1,OFFSET(E39,-1,0))) | H39: SERVIÇO | I39: =IF(H39="Unidade Construtiva",TEXT(A39,"00"),IF(H39="Célula Construtiva",TEXT(B39,"00"),IF(H39="Etapa",CONCATENATE(TEXT(B39,"00"),".",TEXT(C39,"000")),IF(H39="Subetapa",CONCATENATE(TEXT(B39,"00"),".",TEXT(C39,"000"),".",TEXT(D39,"000")),IF(H39="Serviço",CONCATENATE(TEXT(B39,"00"),".",TEXT(C39,"000"),".",TEXT(D39,"000"),".",TEXT(E39,"000")),""))))) | J39: Aprovação e legalização elétrico | K39: =_xlfn.XLOOKUP($J39,BASES!$A$12:$A$392,BASES!$C$12:$C$392) | L39: =_xlfn.XLOOKUP($J39,BASES!$A$12:$A$392,BASES!$D$12:$D$392) | M39: =_xlfn.XLOOKUP($J39,BASES!$A$1:$A$2289,BASES!$E$1:$E$2289) | N39: =IF(H39="Serviço",M39*L39,IF(H39="CÉLULA CONSTRUTIVA",SUMIFS($N$8:$N$467,$B$8:$B$467,B39,$H$8:$H$467,"Serviço"),IF(H39="ETAPA",SUMIFS($N$8:$N$467,$B$8:$B$467,B39,$C$8:$C$467,C39,$H$8:$H$467,"Serviço"),IF(H39="SUBETAPA",SUMIFS($N$8:$N$467,$B$8:$B$467,B39,$C$8:$C$467,C39,$D$8:$D$467,D39,$H$8:$H$467,"Serviço"),0)))) | O39: =_xlfn.XLOOKUP($J39,BASES!$A$12:$A$392,BASES!$F$12:$F$392)
A40: =IF($H40="UNIDADE CONSTRUTIVA",OFFSET(A40,-1,0)+1,LARGE(A$3:A39,1)) | B40: =IF(H40="UNIDADE CONSTRUTIVA",0,IF(H40="CÉLULA CONSTRUTIVA",OFFSET(B40,-1,0)+1,OFFSET(B40,-1,0))) | C40: =IF(H40="CÉLULA CONSTRUTIVA",0,IF(H40="ETAPA",OFFSET(C40,-1,0)+1,OFFSET(C40,-1,0))) | D40: =IF(H40="ETAPA",0,IF(H40="SUBETAPA",OFFSET(D40,-1,0)+1,OFFSET(D40,-1,0))) | E40: =IF(H40="Subetapa",0,IF(H40="serviço",OFFSET(E40,-1,0)+1,OFFSET(E40,-1,0))) | H40: SERVIÇO | I40: =IF(H40="Unidade Construtiva",TEXT(A40,"00"),IF(H40="Célula Construtiva",TEXT(B40,"00"),IF(H40="Etapa",CONCATENATE(TEXT(B40,"00"),".",TEXT(C40,"000")),IF(H40="Subetapa",CONCATENATE(TEXT(B40,"00"),".",TEXT(C40,"000"),".",TEXT(D40,"000")),IF(H40="Serviço",CONCATENATE(TEXT(B40,"00"),".",TEXT(C40,"000"),".",TEXT(D40,"000"),".",TEXT(E40,"000")),""))))) | J40: Aprovação e legalização bombeiros | K40: =_xlfn.XLOOKUP($J40,BASES!$A$12:$A$392,BASES!$C$12:$C$392) | L40: =_xlfn.XLOOKUP($J40,BASES!$A$12:$A$392,BASES!$D$12:$D$392) | M40: =_xlfn.XLOOKUP($J40,BASES!$A$1:$A$2289,BASES!$E$1:$E$2289) | N40: =IF(H40="Serviço",M40*L40,IF(H40="CÉLULA CONSTRUTIVA",SUMIFS($N$8:$N$467,$B$8:$B$467,B40,$H$8:$H$467,"Serviço"),IF(H40="ETAPA",SUMIFS($N$8:$N$467,$B$8:$B$467,B40,$C$8:$C$467,C40,$H$8:$H$467,"Serviço"),IF(H40="SUBETAPA",SUMIFS($N$8:$N$467,$B$8:$B$467,B40,$C$8:$C$467,C40,$D$8:$D$467,D40,$H$8:$H$467,"Serviço"),0)))) | O40: =_xlfn.XLOOKUP($J40,BASES!$A$12:$A$392,BASES!$F$12:$F$392)
A41: =IF($H41="UNIDADE CONSTRUTIVA",OFFSET(A41,-1,0)+1,LARGE(A$3:A40,1)) | B41: =IF(H41="UNIDADE CONSTRUTIVA",0,IF(H41="CÉLULA CONSTRUTIVA",OFFSET(B41,-1,0)+1,OFFSET(B41,-1,0))) | C41: =IF(H41="CÉLULA CONSTRUTIVA",0,IF(H41="ETAPA",OFFSET(C41,-1,0)+1,OFFSET(C41,-1,0))) | D41: =IF(H41="ETAPA",0,IF(H41="SUBETAPA",OFFSET(D41,-1,0)+1,OFFSET(D41,-1,0))) | E41: =IF(H41="Subetapa",0,IF(H41="serviço",OFFSET(E41,-1,0)+1,OFFSET(E41,-1,0))) | H41: SERVIÇO | I41: =IF(H41="Unidade Construtiva",TEXT(A41,"00"),IF(H41="Célula Construtiva",TEXT(B41,"00"),IF(H41="Etapa",CONCATENATE(TEXT(B41,"00"),".",TEXT(C41,"000")),IF(H41="Subetapa",CONCATENATE(TEXT(B41,"00"),".",TEXT(C41,"000"),".",TEXT(D41,"000")),IF(H41="Serviço",CONCATENATE(TEXT(B41,"00"),".",TEXT(C41,"000"),".",TEXT(D41,"000"),".",TEXT(E41,"000")),""))))) | J41: Taxas ART | K41: =_xlfn.XLOOKUP($J41,BASES!$A$12:$A$392,BASES!$C$12:$C$392) | L41: =_xlfn.XLOOKUP($J41,BASES!$A$12:$A$392,BASES!$D$12:$D$392) | M41: =_xlfn.XLOOKUP($J41,BASES!$A$1:$A$2289,BASES!$E$1:$E$2289) | N41: =IF(H41="Serviço",M41*L41,IF(H41="CÉLULA CONSTRUTIVA",SUMIFS($N$8:$N$467,$B$8:$B$467,B41,$H$8:$H$467,"Serviço"),IF(H41="ETAPA",SUMIFS($N$8:$N$467,$B$8:$B$467,B41,$C$8:$C$467,C41,$H$8:$H$467,"Serviço"),IF(H41="SUBETAPA",SUMIFS($N$8:$N$467,$B$8:$B$467,B41,$C$8:$C$467,C41,$D$8:$D$467,D41,$H$8:$H$467,"Serviço"),0)))) | O41: =_xlfn.XLOOKUP($J41,BASES!$A$12:$A$392,BASES!$F$12:$F$392)
A42: =IF($H42="UNIDADE CONSTRUTIVA",OFFSET(A42,-1,0)+1,LARGE(A$3:A41,1)) | B42: =IF(H42="UNIDADE CONSTRUTIVA",0,IF(H42="CÉLULA CONSTRUTIVA",OFFSET(B42,-1,0)+1,OFFSET(B42,-1,0))) | C42: =IF(H42="CÉLULA CONSTRUTIVA",0,IF(H42="ETAPA",OFFSET(C42,-1,0)+1,OFFSET(C42,-1,0))) | D42: =IF(H42="ETAPA",0,IF(H42="SUBETAPA",OFFSET(D42,-1,0)+1,OFFSET(D42,-1,0))) | E42: =IF(H42="Subetapa",0,IF(H42="serviço",OFFSET(E42,-1,0)+1,OFFSET(E42,-1,0))) | H42: SERVIÇO | I42: =IF(H42="Unidade Construtiva",TEXT(A42,"00"),IF(H42="Célula Construtiva",TEXT(B42,"00"),IF(H42="Etapa",CONCATENATE(TEXT(B42,"00"),".",TEXT(C42,"000")),IF(H42="Subetapa",CONCATENATE(TEXT(B42,"00"),".",TEXT(C42,"000"),".",TEXT(D42,"000")),IF(H42="Serviço",CONCATENATE(TEXT(B42,"00"),".",TEXT(C42,"000"),".",TEXT(D42,"000"),".",TEXT(E42,"000")),""))))) | J42: Taxas alvará | K42: =_xlfn.XLOOKUP($J42,BASES!$A$12:$A$392,BASES!$C$12:$C$392) | L42: =_xlfn.XLOOKUP($J42,BASES!$A$12:$A$392,BASES!$D$12:$D$392) | M42: =_xlfn.XLOOKUP($J42,BASES!$A$1:$A$2289,BASES!$E$1:$E$2289) | N42: =IF(H42="Serviço",M42*L42,IF(H42="CÉLULA CONSTRUTIVA",SUMIFS($N$8:$N$467,$B$8:$B$467,B42,$H$8:$H$467,"Serviço"),IF(H42="ETAPA",SUMIFS($N$8:$N$467,$B$8:$B$467,B42,$C$8:$C$467,C42,$H$8:$H$467,"Serviço"),IF(H42="SUBETAPA",SUMIFS($N$8:$N$467,$B$8:$B$467,B42,$C$8:$C$467,C42,$D$8:$D$467,D42,$H$8:$H$467,"Serviço"),0)))) | O42: =_xlfn.XLOOKUP($J42,BASES!$A$12:$A$392,BASES!$F$12:$F$392)
A43: =IF($H43="UNIDADE CONSTRUTIVA",OFFSET(A43,-1,0)+1,LARGE(A$3:A42,1)) | B43: =IF(H43="UNIDADE CONSTRUTIVA",0,IF(H43="CÉLULA CONSTRUTIVA",OFFSET(B43,-1,0)+1,OFFSET(B43,-1,0))) | C43: =IF(H43="CÉLULA CONSTRUTIVA",0,IF(H43="ETAPA",OFFSET(C43,-1,0)+1,OFFSET(C43,-1,0))) | D43: =IF(H43="ETAPA",0,IF(H43="SUBETAPA",OFFSET(D43,-1,0)+1,OFFSET(D43,-1,0))) | E43: =IF(H43="Subetapa",0,IF(H43="serviço",OFFSET(E43,-1,0)+1,OFFSET(E43,-1,0))) | H43: SERVIÇO | I43: =IF(H43="Unidade Construtiva",TEXT(A43,"00"),IF(H43="Célula Construtiva",TEXT(B43,"00"),IF(H43="Etapa",CONCATENATE(TEXT(B43,"00"),".",TEXT(C43,"000")),IF(H43="Subetapa",CONCATENATE(TEXT(B43,"00"),".",TEXT(C43,"000"),".",TEXT(D43,"000")),IF(H43="Serviço",CONCATENATE(TEXT(B43,"00"),".",TEXT(C43,"000"),".",TEXT(D43,"000"),".",TEXT(E43,"000")),""))))) | J43: Taxa Renovação Alvará de Construção | K43: =_xlfn.XLOOKUP($J43,BASES!$A$12:$A$392,BASES!$C$12:$C$392) | L43: =_xlfn.XLOOKUP($J43,BASES!$A$12:$A$392,BASES!$D$12:$D$392) | M43: =_xlfn.XLOOKUP($J43,BASES!$A$1:$A$2289,BASES!$E$1:$E$2289) | N43: =IF(H43="Serviço",M43*L43,IF(H43="CÉLULA CONSTRUTIVA",SUMIFS($N$8:$N$467,$B$8:$B$467,B43,$H$8:$H$467,"Serviço"),IF(H43="ETAPA",SUMIFS($N$8:$N$467,$B$8:$B$467,B43,$C$8:$C$467,C43,$H$8:$H$467,"Serviço"),IF(H43="SUBETAPA",SUMIFS($N$8:$N$467,$B$8:$B$467,B43,$C$8:$C$467,C43,$D$8:$D$467,D43,$H$8:$H$467,"Serviço"),0)))) | O43: =_xlfn.XLOOKUP($J43,BASES!$A$12:$A$392,BASES!$F$12:$F$392)
A44: =IF($H44="UNIDADE CONSTRUTIVA",OFFSET(A44,-1,0)+1,LARGE(A$3:A43,1)) | B44: =IF(H44="UNIDADE CONSTRUTIVA",0,IF(H44="CÉLULA CONSTRUTIVA",OFFSET(B44,-1,0)+1,OFFSET(B44,-1,0))) | C44: =IF(H44="CÉLULA CONSTRUTIVA",0,IF(H44="ETAPA",OFFSET(C44,-1,0)+1,OFFSET(C44,-1,0))) | D44: =IF(H44="ETAPA",0,IF(H44="SUBETAPA",OFFSET(D44,-1,0)+1,OFFSET(D44,-1,0))) | E44: =IF(H44="Subetapa",0,IF(H44="serviço",OFFSET(E44,-1,0)+1,OFFSET(E44,-1,0))) | H44: SERVIÇO | I44: =IF(H44="Unidade Construtiva",TEXT(A44,"00"),IF(H44="Célula Construtiva",TEXT(B44,"00"),IF(H44="Etapa",CONCATENATE(TEXT(B44,"00"),".",TEXT(C44,"000")),IF(H44="Subetapa",CONCATENATE(TEXT(B44,"00"),".",TEXT(C44,"000"),".",TEXT(D44,"000")),IF(H44="Serviço",CONCATENATE(TEXT(B44,"00"),".",TEXT(C44,"000"),".",TEXT(D44,"000"),".",TEXT(E44,"000")),""))))) | J44: Taxas de Alvará de Demolição | K44: =_xlfn.XLOOKUP($J44,BASES!$A$12:$A$392,BASES!$C$12:$C$392) | L44: =_xlfn.XLOOKUP($J44,BASES!$A$12:$A$392,BASES!$D$12:$D$392) | M44: =_xlfn.XLOOKUP($J44,BASES!$A$1:$A$2289,BASES!$E$1:$E$2289) | N44: =IF(H44="Serviço",M44*L44,IF(H44="CÉLULA CONSTRUTIVA",SUMIFS($N$8:$N$467,$B$8:$B$467,B44,$H$8:$H$467,"Serviço"),IF(H44="ETAPA",SUMIFS($N$8:$N$467,$B$8:$B$467,B44,$C$8:$C$467,C44,$H$8:$H$467,"Serviço"),IF(H44="SUBETAPA",SUMIFS($N$8:$N$467,$B$8:$B$467,B44,$C$8:$C$467,C44,$D$8:$D$467,D44,$H$8:$H$467,"Serviço"),0)))) | O44: =_xlfn.XLOOKUP($J44,BASES!$A$12:$A$392,BASES!$F$12:$F$392)
A45: =IF($H45="UNIDADE CONSTRUTIVA",OFFSET(A45,-1,0)+1,LARGE(A$3:A44,1)) | B45: =IF(H45="UNIDADE CONSTRUTIVA",0,IF(H45="CÉLULA CONSTRUTIVA",OFFSET(B45,-1,0)+1,OFFSET(B45,-1,0))) | C45: =IF(H45="CÉLULA CONSTRUTIVA",0,IF(H45="ETAPA",OFFSET(C45,-1,0)+1,OFFSET(C45,-1,0))) | D45: =IF(H45="ETAPA",0,IF(H45="SUBETAPA",OFFSET(D45,-1,0)+1,OFFSET(D45,-1,0))) | E45: =IF(H45="Subetapa",0,IF(H45="serviço",OFFSET(E45,-1,0)+1,OFFSET(E45,-1,0))) | H45: SERVIÇO | I45: =IF(H45="Unidade Construtiva",TEXT(A45,"00"),IF(H45="Célula Construtiva",TEXT(B45,"00"),IF(H45="Etapa",CONCATENATE(TEXT(B45,"00"),".",TEXT(C45,"000")),IF(H45="Subetapa",CONCATENATE(TEXT(B45,"00"),".",TEXT(C45,"000"),".",TEXT(D45,"000")),IF(H45="Serviço",CONCATENATE(TEXT(B45,"00"),".",TEXT(C45,"000"),".",TEXT(D45,"000"),".",TEXT(E45,"000")),""))))) | J45: Despesas cartório, licenças, certidões e jurídicas | K45: =_xlfn.XLOOKUP($J45,BASES!$A$12:$A$392,BASES!$C$12:$C$392) | L45: =_xlfn.XLOOKUP($J45,BASES!$A$12:$A$392,BASES!$D$12:$D$392) | M45: =_xlfn.XLOOKUP($J45,BASES!$A$1:$A$2289,BASES!$E$1:$E$2289) | N45: =IF(H45="Serviço",M45*L45,IF(H45="CÉLULA CONSTRUTIVA",SUMIFS($N$8:$N$467,$B$8:$B$467,B45,$H$8:$H$467,"Serviço"),IF(H45="ETAPA",SUMIFS($N$8:$N$467,$B$8:$B$467,B45,$C$8:$C$467,C45,$H$8:$H$467,"Serviço"),IF(H45="SUBETAPA",SUMIFS($N$8:$N$467,$B$8:$B$467,B45,$C$8:$C$467,C45,$D$8:$D$467,D45,$H$8:$H$467,"Serviço"),0)))) | O45: =_xlfn.XLOOKUP($J45,BASES!$A$12:$A$392,BASES!$F$12:$F$392)
... A48: =IF($H48="UNIDADE CONSTRUTIVA",OFFSET(A48,-1,0)+1,LARGE(A$3:A47,1)) | B48: =IF(H48="UNIDADE CONSTRUTIVA",0,IF(H48="CÉLULA CONSTRUTIVA",OFFSET(B48,-1,0)+1,OFFSET(B48,-1,0))) | C48: =IF(H48="CÉLULA CONSTRUTIVA",0,IF(H48="ETAPA",OFFSET(C48,-1,0)+1,OFFSET(C48,-1,0))) | D48: =IF(H48="ETAPA",0,IF(H48="SUBETAPA",OFFSET(D48,-1,0)+1,OFFSET(D48,-1,0))) | E48: =IF(H48="Subetapa",0,IF(H48="serviço",OFFSET(E48,-1,0)+1,OFFSET(E48,-1,0))) | H48: SERVIÇO | I48: =IF(H48="Unidade Construtiva",TEXT(A48,"00"),IF(H48="Célula Construtiva",TEXT(B48,"00"),IF(H48="Etapa",CONCATENATE(TEXT(B48,"00"),".",TEXT(C48,"000")),IF(H48="Subetapa",CONCATENATE(TEXT(B48,"00"),".",TEXT(C48,"000"),".",TEXT(D48,"000")),IF(H48="Serviço",CONCATENATE(TEXT(B48,"00"),".",TEXT(C48,"000"),".",TEXT(D48,"000"),".",TEXT(E48,"000")),""))))) | J48: Taxa Habite-se | K48: =_xlfn.XLOOKUP($J48,BASES!$A$12:$A$392,BASES!$C$12:$C$392) | L48: =_xlfn.XLOOKUP($J48,BASES!$A$12:$A$392,BASES!$D$12:$D$392) | M48: =_xlfn.XLOOKUP($J48,BASES!$A$1:$A$2289,BASES!$E$1:$E$2289) | N48: =IF(H48="Serviço",M48*L48,IF(H48="CÉLULA CONSTRUTIVA",SUMIFS($N$8:$N$467,$B$8:$B$467,B48,$H$8:$H$467,"Serviço"),IF(H48="ETAPA",SUMIFS($N$8:$N$467,$B$8:$B$467,B48,$C$8:$C$467,C48,$H$8:$H$467,"Serviço"),IF(H48="SUBETAPA",SUMIFS($N$8:$N$467,$B$8:$B$467,B48,$C$8:$C$467,C48,$D$8:$D$467,D48,$H$8:$H$467,"Serviço"),0)))) | O48: =_xlfn.XLOOKUP($J48,BASES!$A$12:$A$392,BASES!$F$12:$F$392)
A49: =IF($H49="UNIDADE CONSTRUTIVA",OFFSET(A49,-1,0)+1,LARGE(A$3:A48,1)) | B49: =IF(H49="UNIDADE CONSTRUTIVA",0,IF(H49="CÉLULA CONSTRUTIVA",OFFSET(B49,-1,0)+1,OFFSET(B49,-1,0))) | C49: =IF(H49="CÉLULA CONSTRUTIVA",0,IF(H49="ETAPA",OFFSET(C49,-1,0)+1,OFFSET(C49,-1,0))) | D49: =IF(H49="ETAPA",0,IF(H49="SUBETAPA",OFFSET(D49,-1,0)+1,OFFSET(D49,-1,0))) | E49: =IF(H49="Subetapa",0,IF(H49="serviço",OFFSET(E49,-1,0)+1,OFFSET(E49,-1,0))) | H49: SUBETAPA | I49: =IF(H49="Unidade Construtiva",TEXT(A49,"00"),IF(H49="Célula Construtiva",TEXT(B49,"00"),IF(H49="Etapa",CONCATENATE(TEXT(B49,"00"),".",TEXT(C49,"000")),IF(H49="Subetapa",CONCATENATE(TEXT(B49,"00"),".",TEXT(C49,"000"),".",TEXT(D49,"000")),IF(H49="Serviço",CONCATENATE(TEXT(B49,"00"),".",TEXT(C49,"000"),".",TEXT(D49,"000"),".",TEXT(E49,"000")),""))))) | J49: Documentos | N49: =IF(H49="Serviço",M49*L49,IF(H49="CÉLULA CONSTRUTIVA",SUMIFS($N$8:$N$467,$B$8:$B$467,B49,$H$8:$H$467,"Serviço"),IF(H49="ETAPA",SUMIFS($N$8:$N$467,$B$8:$B$467,B49,$C$8:$C$467,C49,$H$8:$H$467,"Serviço"),IF(H49="SUBETAPA",SUMIFS($N$8:$N$467,$B$8:$B$467,B49,$C$8:$C$467,C49,$D$8:$D$467,D49,$H$8:$H$467,"Serviço"),0))))
A50: =IF($H50="UNIDADE CONSTRUTIVA",OFFSET(A50,-1,0)+1,LARGE(A$3:A49,1)) | B50: =IF(H50="UNIDADE CONSTRUTIVA",0,IF(H50="CÉLULA CONSTRUTIVA",OFFSET(B50,-1,0)+1,OFFSET(B50,-1,0))) | C50: =IF(H50="CÉLULA CONSTRUTIVA",0,IF(H50="ETAPA",OFFSET(C50,-1,0)+1,OFFSET(C50,-1,0))) | D50: =IF(H50="ETAPA",0,IF(H50="SUBETAPA",OFFSET(D50,-1,0)+1,OFFSET(D50,-1,0))) | E50: =IF(H50="Subetapa",0,IF(H50="serviço",OFFSET(E50,-1,0)+1,OFFSET(E50,-1,0))) | H50: SERVIÇO | I50: =IF(H50="Unidade Construtiva",TEXT(A50,"00"),IF(H50="Célula Construtiva",TEXT(B50,"00"),IF(H50="Etapa",CONCATENATE(TEXT(B50,"00"),".",TEXT(C50,"000")),IF(H50="Subetapa",CONCATENATE(TEXT(B50,"00"),".",TEXT(C50,"000"),".",TEXT(D50,"000")),IF(H50="Serviço",CONCATENATE(TEXT(B50,"00"),".",TEXT(C50,"000"),".",TEXT(D50,"000"),".",TEXT(E50,"000")),""))))) | J50: As Built | K50: =_xlfn.XLOOKUP($J50,BASES!$A$12:$A$392,BASES!$C$12:$C$392) | L50: =_xlfn.XLOOKUP($J50,BASES!$A$12:$A$392,BASES!$D$12:$D$392) | M50: =_xlfn.XLOOKUP($J50,BASES!$A$1:$A$2289,BASES!$E$1:$E$2289) | N50: =IF(H50="Serviço",M50*L50,IF(H50="CÉLULA CONSTRUTIVA",SUMIFS($N$8:$N$467,$B$8:$B$467,B50,$H$8:$H$467,"Serviço"),IF(H50="ETAPA",SUMIFS($N$8:$N$467,$B$8:$B$467,B50,$C$8:$C$467,C50,$H$8:$H$467,"Serviço"),IF(H50="SUBETAPA",SUMIFS($N$8:$N$467,$B$8:$B$467,B50,$C$8:$C$467,C50,$D$8:$D$467,D50,$H$8:$H$467,"Serviço"),0)))) | O50: =_xlfn.XLOOKUP($J50,BASES!$A$12:$A$392,BASES!$F$12:$F$392)
A51: =IF($H51="UNIDADE CONSTRUTIVA",OFFSET(A51,-1,0)+1,LARGE(A$3:A50,1)) | B51: =IF(H51="UNIDADE CONSTRUTIVA",0,IF(H51="CÉLULA CONSTRUTIVA",OFFSET(B51,-1,0)+1,OFFSET(B51,-1,0))) | C51: =IF(H51="CÉLULA CONSTRUTIVA",0,IF(H51="ETAPA",OFFSET(C51,-1,0)+1,OFFSET(C51,-1,0))) | D51: =IF(H51="ETAPA",0,IF(H51="SUBETAPA",OFFSET(D51,-1,0)+1,OFFSET(D51,-1,0))) | E51: =IF(H51="Subetapa",0,IF(H51="serviço",OFFSET(E51,-1,0)+1,OFFSET(E51,-1,0))) | H51: SERVIÇO | I51: =IF(H51="Unidade Construtiva",TEXT(A51,"00"),IF(H51="Célula Construtiva",TEXT(B51,"00"),IF(H51="Etapa",CONCATENATE(TEXT(B51,"00"),".",TEXT(C51,"000")),IF(H51="Subetapa",CONCATENATE(TEXT(B51,"00"),".",TEXT(C51,"000"),".",TEXT(D51,"000")),IF(H51="Serviço",CONCATENATE(TEXT(B51,"00"),".",TEXT(C51,"000"),".",TEXT(D51,"000"),".",TEXT(E51,"000")),""))))) | J51: Laudo técnico de vistoria de entrega | K51: =_xlfn.XLOOKUP($J51,BASES!$A$12:$A$392,BASES!$C$12:$C$392) | L51: =_xlfn.XLOOKUP($J51,BASES!$A$12:$A$392,BASES!$D$12:$D$392) | M51: =_xlfn.XLOOKUP($J51,BASES!$A$1:$A$2289,BASES!$E$1:$E$2289) | N51: =IF(H51="Serviço",M51*L51,IF(H51="CÉLULA CONSTRUTIVA",SUMIFS($N$8:$N$467,$B$8:$B$467,B51,$H$8:$H$467,"Serviço"),IF(H51="ETAPA",SUMIFS($N$8:$N$467,$B$8:$B$467,B51,$C$8:$C$467,C51,$H$8:$H$467,"Serviço"),IF(H51="SUBETAPA",SUMIFS($N$8:$N$467,$B$8:$B$467,B51,$C$8:$C$467,C51,$D$8:$D$467,D51,$H$8:$H$467,"Serviço"),0)))) | O51: =_xlfn.XLOOKUP($J51,BASES!$A$12:$A$392,BASES!$F$12:$F$392)
A52: =IF($H52="UNIDADE CONSTRUTIVA",OFFSET(A52,-1,0)+1,LARGE(A$3:A51,1)) | B52: =IF(H52="UNIDADE CONSTRUTIVA",0,IF(H52="CÉLULA CONSTRUTIVA",OFFSET(B52,-1,0)+1,OFFSET(B52,-1,0))) | C52: =IF(H52="CÉLULA CONSTRUTIVA",0,IF(H52="ETAPA",OFFSET(C52,-1,0)+1,OFFSET(C52,-1,0))) | D52: =IF(H52="ETAPA",0,IF(H52="SUBETAPA",OFFSET(D52,-1,0)+1,OFFSET(D52,-1,0))) | E52: =IF(H52="Subetapa",0,IF(H52="serviço",OFFSET(E52,-1,0)+1,OFFSET(E52,-1,0))) | H52: SERVIÇO | I52: =IF(H52="Unidade Construtiva",TEXT(A52,"00"),IF(H52="Célula Construtiva",TEXT(B52,"00"),IF(H52="Etapa",CONCATENATE(TEXT(B52,"00"),".",TEXT(C52,"000")),IF(H52="Subetapa",CONCATENATE(TEXT(B52,"00"),".",TEXT(C52,"000"),".",TEXT(D52,"000")),IF(H52="Serviço",CONCATENATE(TEXT(B52,"00"),".",TEXT(C52,"000"),".",TEXT(D52,"000"),".",TEXT(E52,"000")),""))))) | J52: Manuais técnicos condomínio/proprietários | K52: =_xlfn.XLOOKUP($J52,BASES!$A$12:$A$392,BASES!$C$12:$C$392) | L52: =_xlfn.XLOOKUP($J52,BASES!$A$12:$A$392,BASES!$D$12:$D$392) | M52: =_xlfn.XLOOKUP($J52,BASES!$A$1:$A$2289,BASES!$E$1:$E$2289) | N52: =IF(H52="Serviço",M52*L52,IF(H52="CÉLULA CONSTRUTIVA",SUMIFS($N$8:$N$467,$B$8:$B$467,B52,$H$8:$H$467,"Serviço"),IF(H52="ETAPA",SUMIFS($N$8:$N$467,$B$8:$B$467,B52,$C$8:$C$467,C52,$H$8:$H$467,"Serviço"),IF(H52="SUBETAPA",SUMIFS($N$8:$N$467,$B$8:$B$467,B52,$C$8:$C$467,C52,$D$8:$D$467,D52,$H$8:$H$467,"Serviço"),0)))) | O52: =_xlfn.XLOOKUP($J52,BASES!$A$12:$A$392,BASES!$F$12:$F$392)
A53: =IF($H53="UNIDADE CONSTRUTIVA",OFFSET(A53,-1,0)+1,LARGE(A$3:A52,1)) | B53: =IF(H53="UNIDADE CONSTRUTIVA",0,IF(H53="CÉLULA CONSTRUTIVA",OFFSET(B53,-1,0)+1,OFFSET(B53,-1,0))) | C53: =IF(H53="CÉLULA CONSTRUTIVA",0,IF(H53="ETAPA",OFFSET(C53,-1,0)+1,OFFSET(C53,-1,0))) | D53: =IF(H53="ETAPA",0,IF(H53="SUBETAPA",OFFSET(D53,-1,0)+1,OFFSET(D53,-1,0))) | E53: =IF(H53="Subetapa",0,IF(H53="serviço",OFFSET(E53,-1,0)+1,OFFSET(E53,-1,0))) | H53: SERVIÇO | I53: =IF(H53="Unidade Construtiva",TEXT(A53,"00"),IF(H53="Célula Construtiva",TEXT(B53,"00"),IF(H53="Etapa",CONCATENATE(TEXT(B53,"00"),".",TEXT(C53,"000")),IF(H53="Subetapa",CONCATENATE(TEXT(B53,"00"),".",TEXT(C53,"000"),".",TEXT(D53,"000")),IF(H53="Serviço",CONCATENATE(TEXT(B53,"00"),".",TEXT(C53,"000"),".",TEXT(D53,"000"),".",TEXT(E53,"000")),""))))) | J53: Certidão INSS | K53: =_xlfn.XLOOKUP($J53,BASES!$A$12:$A$392,BASES!$C$12:$C$392) | L53: =_xlfn.XLOOKUP($J53,BASES!$A$12:$A$392,BASES!$D$12:$D$392) | M53: =_xlfn.XLOOKUP($J53,BASES!$A$1:$A$2289,BASES!$E$1:$E$2289) | N53: =IF(H53="Serviço",M53*L53,IF(H53="CÉLULA CONSTRUTIVA",SUMIFS($N$8:$N$467,$B$8:$B$467,B53,$H$8:$H$467,"Serviço"),IF(H53="ETAPA",SUMIFS($N$8:$N$467,$B$8:$B$467,B53,$C$8:$C$467,C53,$H$8:$H$467,"Serviço"),IF(H53="SUBETAPA",SUMIFS($N$8:$N$467,$B$8:$B$467,B53,$C$8:$C$467,C53,$D$8:$D$467,D53,$H$8:$H$467,"Serviço"),0)))) | O53: =_xlfn.XLOOKUP($J53,BASES!$A$12:$A$392,BASES!$F$12:$F$392)
A54: =IF($H54="UNIDADE CONSTRUTIVA",OFFSET(A54,-1,0)+1,LARGE(A$3:A53,1)) | B54: =IF(H54="UNIDADE CONSTRUTIVA",0,IF(H54="CÉLULA CONSTRUTIVA",OFFSET(B54,-1,0)+1,OFFSET(B54,-1,0))) | C54: =IF(H54="CÉLULA CONSTRUTIVA",0,IF(H54="ETAPA",OFFSET(C54,-1,0)+1,OFFSET(C54,-1,0))) | D54: =IF(H54="ETAPA",0,IF(H54="SUBETAPA",OFFSET(D54,-1,0)+1,OFFSET(D54,-1,0))) | E54: =IF(H54="Subetapa",0,IF(H54="serviço",OFFSET(E54,-1,0)+1,OFFSET(E54,-1,0))) | H54: CÉLULA CONSTRUTIVA | I54: =IF(H54="Unidade Construtiva",TEXT(A54,"00"),IF(H54="Célula Construtiva",TEXT(B54,"00"),IF(H54="Etapa",CONCATENATE(TEXT(B54,"00"),".",TEXT(C54,"000")),IF(H54="Subetapa",CONCATENATE(TEXT(B54,"00"),".",TEXT(C54,"000"),".",TEXT(D54,"000")),IF(H54="Serviço",CONCATENATE(TEXT(B54,"00"),".",TEXT(C54,"000"),".",TEXT(D54,"000"),".",TEXT(E54,"000")),""))))) | J54: SERVIÇOS INICIAIS | N54: =IF(H54="Serviço",M54*L54,IF(H54="CÉLULA CONSTRUTIVA",SUMIFS($N$8:$N$442,$B$8:$B$442,B54,$H$8:$H$442,"Serviço"),IF(H54="ETAPA",SUMIFS($N$8:$N$442,$B$8:$B$442,B54,$C$8:$C$442,C54,$H$8:$H$442,"Serviço"),IF(H54="SUBETAPA",SUMIFS($N$8:$N$442,$B$8:$B$442,B54,$C$8:$C$442,C54,$D$8:$D$442,D54,$H$8:$H$442,"Serviço"),0))))
A55: =IF($H55="UNIDADE CONSTRUTIVA",OFFSET(A55,-1,0)+1,LARGE(A$3:A54,1)) | B55: =IF(H55="UNIDADE CONSTRUTIVA",0,IF(H55="CÉLULA CONSTRUTIVA",OFFSET(B55,-1,0)+1,OFFSET(B55,-1,0))) | C55: =IF(H55="CÉLULA CONSTRUTIVA",0,IF(H55="ETAPA",OFFSET(C55,-1,0)+1,OFFSET(C55,-1,0))) | D55: =IF(H55="ETAPA",0,IF(H55="SUBETAPA",OFFSET(D55,-1,0)+1,OFFSET(D55,-1,0))) | E55: =IF(H55="Subetapa",0,IF(H55="serviço",OFFSET(E55,-1,0)+1,OFFSET(E55,-1,0))) | H55: ETAPA | I55: =IF(H55="Unidade Construtiva",TEXT(A55,"00"),IF(H55="Célula Construtiva",TEXT(B55,"00"),IF(H55="Etapa",CONCATENATE(TEXT(B55,"00"),".",TEXT(C55,"000")),IF(H55="Subetapa",CONCATENATE(TEXT(B55,"00"),".",TEXT(C55,"000"),".",TEXT(D55,"000")),IF(H55="Serviço",CONCATENATE(TEXT(B55,"00"),".",TEXT(C55,"000"),".",TEXT(D55,"000"),".",TEXT(E55,"000")),""))))) | J55: SEGURANÇA, MEIO AMBIENTE E SAÚDE | N55: =IF(H55="Serviço",M55*L55,IF(H55="CÉLULA CONSTRUTIVA",SUMIFS($N$8:$N$442,$B$8:$B$442,B55,$H$8:$H$442,"Serviço"),IF(H55="ETAPA",SUMIFS($N$8:$N$442,$B$8:$B$442,B55,$C$8:$C$442,C55,$H$8:$H$442,"Serviço"),IF(H55="SUBETAPA",SUMIFS($N$8:$N$442,$B$8:$B$442,B55,$C$8:$C$442,C55,$D$8:$D$442,D55,$H$8:$H$442,"Serviço"),0))))
A56: =IF($H56="UNIDADE CONSTRUTIVA",OFFSET(A56,-1,0)+1,LARGE(A$3:A55,1)) | B56: =IF(H56="UNIDADE CONSTRUTIVA",0,IF(H56="CÉLULA CONSTRUTIVA",OFFSET(B56,-1,0)+1,OFFSET(B56,-1,0))) | C56: =IF(H56="CÉLULA CONSTRUTIVA",0,IF(H56="ETAPA",OFFSET(C56,-1,0)+1,OFFSET(C56,-1,0))) | D56: =IF(H56="ETAPA",0,IF(H56="SUBETAPA",OFFSET(D56,-1,0)+1,OFFSET(D56,-1,0))) | E56: =IF(H56="Subetapa",0,IF(H56="serviço",OFFSET(E56,-1,0)+1,OFFSET(E56,-1,0))) | H56: SUBETAPA | I56: =IF(H56="Unidade Construtiva",TEXT(A56,"00"),IF(H56="Célula Construtiva",TEXT(B56,"00"),IF(H56="Etapa",CONCATENATE(TEXT(B56,"00"),".",TEXT(C56,"000")),IF(H56="Subetapa",CONCATENATE(TEXT(B56,"00"),".",TEXT(C56,"000"),".",TEXT(D56,"000")),IF(H56="Serviço",CONCATENATE(TEXT(B56,"00"),".",TEXT(C56,"000"),".",TEXT(D56,"000"),".",TEXT(E56,"000")),""))))) | J56: Segurança do Trabalho | N56: =IF(H56="Serviço",M56*L56,IF(H56="CÉLULA CONSTRUTIVA",SUMIFS($N$8:$N$487,$B$8:$B$487,B56,$H$8:$H$487,"Serviço"),IF(H56="ETAPA",SUMIFS($N$8:$N$487,$B$8:$B$487,B56,$C$8:$C$487,C56,$H$8:$H$487,"Serviço"),IF(H56="SUBETAPA",SUMIFS($N$8:$N$487,$B$8:$B$487,B56,$C$8:$C$487,C56,$D$8:$D$487,D56,$H$8:$H$487,"Serviço"),0))))
A57: =IF($H57="UNIDADE CONSTRUTIVA",OFFSET(A57,-1,0)+1,LARGE(A$3:A56,1)) | B57: =IF(H57="UNIDADE CONSTRUTIVA",0,IF(H57="CÉLULA CONSTRUTIVA",OFFSET(B57,-1,0)+1,OFFSET(B57,-1,0))) | C57: =IF(H57="CÉLULA CONSTRUTIVA",0,IF(H57="ETAPA",OFFSET(C57,-1,0)+1,OFFSET(C57,-1,0))) | D57: =IF(H57="ETAPA",0,IF(H57="SUBETAPA",OFFSET(D57,-1,0)+1,OFFSET(D57,-1,0))) | E57: =IF(H57="Subetapa",0,IF(H57="serviço",OFFSET(E57,-1,0)+1,OFFSET(E57,-1,0))) | H57: SERVIÇO | I57: =IF(H57="Unidade Construtiva",TEXT(A57,"00"),IF(H57="Célula Construtiva",TEXT(B57,"00"),IF(H57="Etapa",CONCATENATE(TEXT(B57,"00"),".",TEXT(C57,"000")),IF(H57="Subetapa",CONCATENATE(TEXT(B57,"00"),".",TEXT(C57,"000"),".",TEXT(D57,"000")),IF(H57="Serviço",CONCATENATE(TEXT(B57,"00"),".",TEXT(C57,"000"),".",TEXT(D57,"000"),".",TEXT(E57,"000")),""))))) | J57: Serviço terceirizado de segurança do trabalho - Valor/mês (R$) | K57: =_xlfn.XLOOKUP($J57,BASES!$A$12:$A$392,BASES!$C$12:$C$392) | L57: =_xlfn.XLOOKUP($J57,BASES!$A$12:$A$392,BASES!$D$12:$D$392) | M57: =_xlfn.XLOOKUP($J57,BASES!$A$1:$A$2289,BASES!$E$1:$E$2289) | N57: =IF(H57="Serviço",M57*L57,IF(H57="CÉLULA CONSTRUTIVA",SUMIFS($N$8:$N$487,$B$8:$B$487,B57,$H$8:$H$487,"Serviço"),IF(H57="ETAPA",SUMIFS($N$8:$N$487,$B$8:$B$487,B57,$C$8:$C$487,C57,$H$8:$H$487,"Serviço"),IF(H57="SUBETAPA",SUMIFS($N$8:$N$487,$B$8:$B$487,B57,$C$8:$C$487,C57,$D$8:$D$487,D57,$H$8:$H$487,"Serviço"),0)))) | O57: =_xlfn.XLOOKUP($J57,BASES!$A$12:$A$392,BASES!$F$12:$F$392)
A58: =IF($H58="UNIDADE CONSTRUTIVA",OFFSET(A58,-1,0)+1,LARGE(A$3:A57,1)) | B58: =IF(H58="UNIDADE CONSTRUTIVA",0,IF(H58="CÉLULA CONSTRUTIVA",OFFSET(B58,-1,0)+1,OFFSET(B58,-1,0))) | C58: =IF(H58="CÉLULA CONSTRUTIVA",0,IF(H58="ETAPA",OFFSET(C58,-1,0)+1,OFFSET(C58,-1,0))) | D58: =IF(H58="ETAPA",0,IF(H58="SUBETAPA",OFFSET(D58,-1,0)+1,OFFSET(D58,-1,0))) | E58: =IF(H58="Subetapa",0,IF(H58="serviço",OFFSET(E58,-1,0)+1,OFFSET(E58,-1,0))) | H58: SERVIÇO | I58: =IF(H58="Unidade Construtiva",TEXT(A58,"00"),IF(H58="Célula Construtiva",TEXT(B58,"00"),IF(H58="Etapa",CONCATENATE(TEXT(B58,"00"),".",TEXT(C58,"000")),IF(H58="Subetapa",CONCATENATE(TEXT(B58,"00"),".",TEXT(C58,"000"),".",TEXT(D58,"000")),IF(H58="Serviço",CONCATENATE(TEXT(B58,"00"),".",TEXT(C58,"000"),".",TEXT(D58,"000"),".",TEXT(E58,"000")),""))))) | J58: Treinamento por funcionário (R$) | K58: =_xlfn.XLOOKUP($J58,BASES!$A$12:$A$392,BASES!$C$12:$C$392) | L58: =_xlfn.XLOOKUP($J58,BASES!$A$12:$A$392,BASES!$D$12:$D$392) | M58: =_xlfn.XLOOKUP($J58,BASES!$A$1:$A$2289,BASES!$E$1:$E$2289) | N58: =IF(H58="Serviço",M58*L58,IF(H58="CÉLULA CONSTRUTIVA",SUMIFS($N$8:$N$422,$B$8:$B$422,B58,$H$8:$H$422,"Serviço"),IF(H58="ETAPA",SUMIFS($N$8:$N$422,$B$8:$B$422,B58,$C$8:$C$422,C58,$H$8:$H$422,"Serviço"),IF(H58="SUBETAPA",SUMIFS($N$8:$N$422,$B$8:$B$422,B58,$C$8:$C$422,C58,$D$8:$D$422,D58,$H$8:$H$422,"Serviço"),0)))) | O58: =_xlfn.XLOOKUP($J58,BASES!$A$12:$A$392,BASES!$F$12:$F$392)
A59: =IF($H59="UNIDADE CONSTRUTIVA",OFFSET(A59,-1,0)+1,LARGE(A$3:A58,1)) | B59: =IF(H59="UNIDADE CONSTRUTIVA",0,IF(H59="CÉLULA CONSTRUTIVA",OFFSET(B59,-1,0)+1,OFFSET(B59,-1,0))) | C59: =IF(H59="CÉLULA CONSTRUTIVA",0,IF(H59="ETAPA",OFFSET(C59,-1,0)+1,OFFSET(C59,-1,0))) | D59: =IF(H59="ETAPA",0,IF(H59="SUBETAPA",OFFSET(D59,-1,0)+1,OFFSET(D59,-1,0))) | E59: =IF(H59="Subetapa",0,IF(H59="serviço",OFFSET(E59,-1,0)+1,OFFSET(E59,-1,0))) | H59: SERVIÇO | I59: =IF(H59="Unidade Construtiva",TEXT(A59,"00"),IF(H59="Célula Construtiva",TEXT(B59,"00"),IF(H59="Etapa",CONCATENATE(TEXT(B59,"00"),".",TEXT(C59,"000")),IF(H59="Subetapa",CONCATENATE(TEXT(B59,"00"),".",TEXT(C59,"000"),".",TEXT(D59,"000")),IF(H59="Serviço",CONCATENATE(TEXT(B59,"00"),".",TEXT(C59,"000"),".",TEXT(D59,"000"),".",TEXT(E59,"000")),""))))) | J59: Projetos de segurança do trabalho | K59: =_xlfn.XLOOKUP($J59,BASES!$A$12:$A$392,BASES!$C$12:$C$392) | L59: =_xlfn.XLOOKUP($J59,BASES!$A$12:$A$392,BASES!$D$12:$D$392) | M59: =_xlfn.XLOOKUP($J59,BASES!$A$1:$A$2289,BASES!$E$1:$E$2289) | N59: =IF(H59="Serviço",M59*L59,IF(H59="CÉLULA CONSTRUTIVA",SUMIFS($N$8:$N$422,$B$8:$B$422,B59,$H$8:$H$422,"Serviço"),IF(H59="ETAPA",SUMIFS($N$8:$N$422,$B$8:$B$422,B59,$C$8:$C$422,C59,$H$8:$H$422,"Serviço"),IF(H59="SUBETAPA",SUMIFS($N$8:$N$422,$B$8:$B$422,B59,$C$8:$C$422,C59,$D$8:$D$422,D59,$H$8:$H$422,"Serviço"),0)))) | O59: =_xlfn.XLOOKUP($J59,BASES!$A$12:$A$392,BASES!$F$12:$F$392)
A60: =IF($H60="UNIDADE CONSTRUTIVA",OFFSET(A60,-1,0)+1,LARGE(A$3:A59,1)) | B60: =IF(H60="UNIDADE CONSTRUTIVA",0,IF(H60="CÉLULA CONSTRUTIVA",OFFSET(B60,-1,0)+1,OFFSET(B60,-1,0))) | C60: =IF(H60="CÉLULA CONSTRUTIVA",0,IF(H60="ETAPA",OFFSET(C60,-1,0)+1,OFFSET(C60,-1,0))) | D60: =IF(H60="ETAPA",0,IF(H60="SUBETAPA",OFFSET(D60,-1,0)+1,OFFSET(D60,-1,0))) | E60: =IF(H60="Subetapa",0,IF(H60="serviço",OFFSET(E60,-1,0)+1,OFFSET(E60,-1,0))) | H60: SUBETAPA | I60: =IF(H60="Unidade Construtiva",TEXT(A60,"00"),IF(H60="Célula Construtiva",TEXT(B60,"00"),IF(H60="Etapa",CONCATENATE(TEXT(B60,"00"),".",TEXT(C60,"000")),IF(H60="Subetapa",CONCATENATE(TEXT(B60,"00"),".",TEXT(C60,"000"),".",TEXT(D60,"000")),IF(H60="Serviço",CONCATENATE(TEXT(B60,"00"),".",TEXT(C60,"000"),".",TEXT(D60,"000"),".",TEXT(E60,"000")),""))))) | J60: Equipamentos de proteção | N60: =IF(H60="Serviço",M60*L60,IF(H60="CÉLULA CONSTRUTIVA",SUMIFS($N$8:$N$442,$B$8:$B$442,B60,$H$8:$H$442,"Serviço"),IF(H60="ETAPA",SUMIFS($N$8:$N$442,$B$8:$B$442,B60,$C$8:$C$442,C60,$H$8:$H$442,"Serviço"),IF(H60="SUBETAPA",SUMIFS($N$8:$N$442,$B$8:$B$442,B60,$C$8:$C$442,C60,$D$8:$D$442,D60,$H$8:$H$442,"Serviço"),0))))
A61: =IF($H61="UNIDADE CONSTRUTIVA",OFFSET(A61,-1,0)+1,LARGE(A$3:A60,1)) | B61: =IF(H61="UNIDADE CONSTRUTIVA",0,IF(H61="CÉLULA CONSTRUTIVA",OFFSET(B61,-1,0)+1,OFFSET(B61,-1,0))) | C61: =IF(H61="CÉLULA CONSTRUTIVA",0,IF(H61="ETAPA",OFFSET(C61,-1,0)+1,OFFSET(C61,-1,0))) | D61: =IF(H61="ETAPA",0,IF(H61="SUBETAPA",OFFSET(D61,-1,0)+1,OFFSET(D61,-1,0))) | E61: =IF(H61="Subetapa",0,IF(H61="serviço",OFFSET(E61,-1,0)+1,OFFSET(E61,-1,0))) | H61: SERVIÇO | I61: =IF(H61="Unidade Construtiva",TEXT(A61,"00"),IF(H61="Célula Construtiva",TEXT(B61,"00"),IF(H61="Etapa",CONCATENATE(TEXT(B61,"00"),".",TEXT(C61,"000")),IF(H61="Subetapa",CONCATENATE(TEXT(B61,"00"),".",TEXT(C61,"000"),".",TEXT(D61,"000")),IF(H61="Serviço",CONCATENATE(TEXT(B61,"00"),".",TEXT(C61,"000"),".",TEXT(D61,"000"),".",TEXT(E61,"000")),""))))) | J61: Equipamentos de proteção individual - EPI | K61: =_xlfn.XLOOKUP($J61,BASES!$A$12:$A$392,BASES!$C$12:$C$392) | L61: =_xlfn.XLOOKUP($J61,BASES!$A$12:$A$392,BASES!$D$12:$D$392) | M61: =_xlfn.XLOOKUP($J61,BASES!$A$1:$A$2289,BASES!$E$1:$E$2289) | N61: =IF(H61="Serviço",M61*L61,IF(H61="CÉLULA CONSTRUTIVA",SUMIFS($N$8:$N$442,$B$8:$B$442,B61,$H$8:$H$442,"Serviço"),IF(H61="ETAPA",SUMIFS($N$8:$N$442,$B$8:$B$442,B61,$C$8:$C$442,C61,$H$8:$H$442,"Serviço"),IF(H61="SUBETAPA",SUMIFS($N$8:$N$442,$B$8:$B$442,B61,$C$8:$C$442,C61,$D$8:$D$442,D61,$H$8:$H$442,"Serviço"),0)))) | O61: =_xlfn.XLOOKUP($J61,BASES!$A$12:$A$392,BASES!$F$12:$F$392)
A62: =IF($H62="UNIDADE CONSTRUTIVA",OFFSET(A62,-1,0)+1,LARGE(A$3:A61,1)) | B62: =IF(H62="UNIDADE CONSTRUTIVA",0,IF(H62="CÉLULA CONSTRUTIVA",OFFSET(B62,-1,0)+1,OFFSET(B62,-1,0))) | C62: =IF(H62="CÉLULA CONSTRUTIVA",0,IF(H62="ETAPA",OFFSET(C62,-1,0)+1,OFFSET(C62,-1,0))) | D62: =IF(H62="ETAPA",0,IF(H62="SUBETAPA",OFFSET(D62,-1,0)+1,OFFSET(D62,-1,0))) | E62: =IF(H62="Subetapa",0,IF(H62="serviço",OFFSET(E62,-1,0)+1,OFFSET(E62,-1,0))) | H62: SERVIÇO | I62: =IF(H62="Unidade Construtiva",TEXT(A62,"00"),IF(H62="Célula Construtiva",TEXT(B62,"00"),IF(H62="Etapa",CONCATENATE(TEXT(B62,"00"),".",TEXT(C62,"000")),IF(H62="Subetapa",CONCATENATE(TEXT(B62,"00"),".",TEXT(C62,"000"),".",TEXT(D62,"000")),IF(H62="Serviço",CONCATENATE(TEXT(B62,"00"),".",TEXT(C62,"000"),".",TEXT(D62,"000"),".",TEXT(E62,"000")),""))))) | J62: Bandeja de proteção primária | K62: =_xlfn.XLOOKUP($J62,BASES!$A$12:$A$392,BASES!$C$12:$C$392) | L62: =EPCs!D11 | M62: =_xlfn.XLOOKUP($J62,[4]CPU!$D$1:$D$3132,[4]CPU!$H$1:$H$3132) | N62: =IF(H62="Serviço",M62*L62,IF(H62="CÉLULA CONSTRUTIVA",SUMIFS($N$8:$N$442,$B$8:$B$442,B62,$H$8:$H$442,"Serviço"),IF(H62="ETAPA",SUMIFS($N$8:$N$442,$B$8:$B$442,B62,$C$8:$C$442,C62,$H$8:$H$442,"Serviço"),IF(H62="SUBETAPA",SUMIFS($N$8:$N$442,$B$8:$B$442,B62,$C$8:$C$442,C62,$D$8:$D$442,D62,$H$8:$H$442,"Serviço"),0)))) | O62: EPC'S
A63: =IF($H63="UNIDADE CONSTRUTIVA",OFFSET(A63,-1,0)+1,LARGE(A$3:A62,1)) | B63: =IF(H63="UNIDADE CONSTRUTIVA",0,IF(H63="CÉLULA CONSTRUTIVA",OFFSET(B63,-1,0)+1,OFFSET(B63,-1,0))) | C63: =IF(H63="CÉLULA CONSTRUTIVA",0,IF(H63="ETAPA",OFFSET(C63,-1,0)+1,OFFSET(C63,-1,0))) | D63: =IF(H63="ETAPA",0,IF(H63="SUBETAPA",OFFSET(D63,-1,0)+1,OFFSET(D63,-1,0))) | E63: =IF(H63="Subetapa",0,IF(H63="serviço",OFFSET(E63,-1,0)+1,OFFSET(E63,-1,0))) | H63: SERVIÇO | I63: =IF(H63="Unidade Construtiva",TEXT(A63,"00"),IF(H63="Célula Construtiva",TEXT(B63,"00"),IF(H63="Etapa",CONCATENATE(TEXT(B63,"00"),".",TEXT(C63,"000")),IF(H63="Subetapa",CONCATENATE(TEXT(B63,"00"),".",TEXT(C63,"000"),".",TEXT(D63,"000")),IF(H63="Serviço",CONCATENATE(TEXT(B63,"00"),".",TEXT(C63,"000"),".",TEXT(D63,"000"),".",TEXT(E63,"000")),""))))) | J63: Guarda-corpo de vãos, fixado em fôrma de madeira, em trama de madeira com tela de polipropileno | K63: =_xlfn.XLOOKUP($J63,BASES!$A$12:$A$392,BASES!$C$12:$C$392) | L63: =EPCs!D18 | M63: =_xlfn.XLOOKUP($J63,[4]CPU!$D$1:$D$3132,[4]CPU!$H$1:$H$3132) | N63: =IF(H63="Serviço",M63*L63,IF(H63="CÉLULA CONSTRUTIVA",SUMIFS($N$8:$N$442,$B$8:$B$442,B63,$H$8:$H$442,"Serviço"),IF(H63="ETAPA",SUMIFS($N$8:$N$442,$B$8:$B$442,B63,$C$8:$C$442,C63,$H$8:$H$442,"Serviço"),IF(H63="SUBETAPA",SUMIFS($N$8:$N$442,$B$8:$B$442,B63,$C$8:$C$442,C63,$D$8:$D$442,D63,$H$8:$H$442,"Serviço"),0)))) | O63: EPC'S | P63: A ser defido em momento final
A64: =IF($H64="UNIDADE CONSTRUTIVA",OFFSET(A64,-1,0)+1,LARGE(A$3:A63,1)) | B64: =IF(H64="UNIDADE CONSTRUTIVA",0,IF(H64="CÉLULA CONSTRUTIVA",OFFSET(B64,-1,0)+1,OFFSET(B64,-1,0))) | C64: =IF(H64="CÉLULA CONSTRUTIVA",0,IF(H64="ETAPA",OFFSET(C64,-1,0)+1,OFFSET(C64,-1,0))) | D64: =IF(H64="ETAPA",0,IF(H64="SUBETAPA",OFFSET(D64,-1,0)+1,OFFSET(D64,-1,0))) | E64: =IF(H64="Subetapa",0,IF(H64="serviço",OFFSET(E64,-1,0)+1,OFFSET(E64,-1,0))) | H64: SERVIÇO | I64: =IF(H64="Unidade Construtiva",TEXT(A64,"00"),IF(H64="Célula Construtiva",TEXT(B64,"00"),IF(H64="Etapa",CONCATENATE(TEXT(B64,"00"),".",TEXT(C64,"000")),IF(H64="Subetapa",CONCATENATE(TEXT(B64,"00"),".",TEXT(C64,"000"),".",TEXT(D64,"000")),IF(H64="Serviço",CONCATENATE(TEXT(B64,"00"),".",TEXT(C64,"000"),".",TEXT(D64,"000"),".",TEXT(E64,"000")),""))))) | J64: Tela fachadeira | K64: =_xlfn.XLOOKUP($J64,BASES!$A$12:$A$392,BASES!$C$12:$C$392) | L64: =EPCs!D47 | M64: =_xlfn.XLOOKUP($J64,[4]CPU!$D$1:$D$3132,[4]CPU!$H$1:$H$3132) | N64: =IF(H64="Serviço",M64*L64,IF(H64="CÉLULA CONSTRUTIVA",SUMIFS($N$8:$N$442,$B$8:$B$442,B64,$H$8:$H$442,"Serviço"),IF(H64="ETAPA",SUMIFS($N$8:$N$442,$B$8:$B$442,B64,$C$8:$C$442,C64,$H$8:$H$442,"Serviço"),IF(H64="SUBETAPA",SUMIFS($N$8:$N$442,$B$8:$B$442,B64,$C$8:$C$442,C64,$D$8:$D$442,D64,$H$8:$H$442,"Serviço"),0)))) | O64: EPC'S
A65: =IF($H65="UNIDADE CONSTRUTIVA",OFFSET(A65,-1,0)+1,LARGE(A$3:A64,1)) | B65: =IF(H65="UNIDADE CONSTRUTIVA",0,IF(H65="CÉLULA CONSTRUTIVA",OFFSET(B65,-1,0)+1,OFFSET(B65,-1,0))) | C65: =IF(H65="CÉLULA CONSTRUTIVA",0,IF(H65="ETAPA",OFFSET(C65,-1,0)+1,OFFSET(C65,-1,0))) | D65: =IF(H65="ETAPA",0,IF(H65="SUBETAPA",OFFSET(D65,-1,0)+1,OFFSET(D65,-1,0))) | E65: =IF(H65="Subetapa",0,IF(H65="serviço",OFFSET(E65,-1,0)+1,OFFSET(E65,-1,0))) | H65: SERVIÇO | I65: =IF(H65="Unidade Construtiva",TEXT(A65,"00"),IF(H65="Célula Construtiva",TEXT(B65,"00"),IF(H65="Etapa",CONCATENATE(TEXT(B65,"00"),".",TEXT(C65,"000")),IF(H65="Subetapa",CONCATENATE(TEXT(B65,"00"),".",TEXT(C65,"000"),".",TEXT(D65,"000")),IF(H65="Serviço",CONCATENATE(TEXT(B65,"00"),".",TEXT(C65,"000"),".",TEXT(D65,"000"),".",TEXT(E65,"000")),""))))) | J65: Fechamento removível de vãos de porta de elevador em madeira | K65: =_xlfn.XLOOKUP($J65,BASES!$A$12:$A$392,BASES!$C$12:$C$392) | L65: =EPCs!D34 | M65: =_xlfn.XLOOKUP($J65,[4]CPU!$D$1:$D$3132,[4]CPU!$H$1:$H$3132) | N65: =IF(H65="Serviço",M65*L65,IF(H65="CÉLULA CONSTRUTIVA",SUMIFS($N$8:$N$442,$B$8:$B$442,B65,$H$8:$H$442,"Serviço"),IF(H65="ETAPA",SUMIFS($N$8:$N$442,$B$8:$B$442,B65,$C$8:$C$442,C65,$H$8:$H$442,"Serviço"),IF(H65="SUBETAPA",SUMIFS($N$8:$N$442,$B$8:$B$442,B65,$C$8:$C$442,C65,$D$8:$D$442,D65,$H$8:$H$442,"Serviço"),0)))) | O65: EPC'S
A66: =IF($H66="UNIDADE CONSTRUTIVA",OFFSET(A66,-1,0)+1,LARGE(A$3:A65,1)) | B66: =IF(H66="UNIDADE CONSTRUTIVA",0,IF(H66="CÉLULA CONSTRUTIVA",OFFSET(B66,-1,0)+1,OFFSET(B66,-1,0))) | C66: =IF(H66="CÉLULA CONSTRUTIVA",0,IF(H66="ETAPA",OFFSET(C66,-1,0)+1,OFFSET(C66,-1,0))) | D66: =IF(H66="ETAPA",0,IF(H66="SUBETAPA",OFFSET(D66,-1,0)+1,OFFSET(D66,-1,0))) | E66: =IF(H66="Subetapa",0,IF(H66="serviço",OFFSET(E66,-1,0)+1,OFFSET(E66,-1,0))) | H66: SERVIÇO | I66: =IF(H66="Unidade Construtiva",TEXT(A66,"00"),IF(H66="Célula Construtiva",TEXT(B66,"00"),IF(H66="Etapa",CONCATENATE(TEXT(B66,"00"),".",TEXT(C66,"000")),IF(H66="Subetapa",CONCATENATE(TEXT(B66,"00"),".",TEXT(C66,"000"),".",TEXT(D66,"000")),IF(H66="Serviço",CONCATENATE(TEXT(B66,"00"),".",TEXT(C66,"000"),".",TEXT(D66,"000"),".",TEXT(E66,"000")),""))))) | J66: Fechamento removível de vãos de porta de entrada dos aptos. em madeira | K66: =_xlfn.XLOOKUP($J66,BASES!$A$12:$A$392,BASES!$C$12:$C$392) | L66: =EPCs!D37 | M66: =_xlfn.XLOOKUP($J66,[4]CPU!$D$1:$D$3132,[4]CPU!$H$1:$H$3132) | N66: =IF(H66="Serviço",M66*L66,IF(H66="CÉLULA CONSTRUTIVA",SUMIFS($N$8:$N$442,$B$8:$B$442,B66,$H$8:$H$442,"Serviço"),IF(H66="ETAPA",SUMIFS($N$8:$N$442,$B$8:$B$442,B66,$C$8:$C$442,C66,$H$8:$H$442,"Serviço"),IF(H66="SUBETAPA",SUMIFS($N$8:$N$442,$B$8:$B$442,B66,$C$8:$C$442,C66,$D$8:$D$442,D66,$H$8:$H$442,"Serviço"),0)))) | O66: EPC'S
A67: =IF($H67="UNIDADE CONSTRUTIVA",OFFSET(A67,-1,0)+1,LARGE(A$3:A66,1)) | B67: =IF(H67="UNIDADE CONSTRUTIVA",0,IF(H67="CÉLULA CONSTRUTIVA",OFFSET(B67,-1,0)+1,OFFSET(B67,-1,0))) | C67: =IF(H67="CÉLULA CONSTRUTIVA",0,IF(H67="ETAPA",OFFSET(C67,-1,0)+1,OFFSET(C67,-1,0))) | D67: =IF(H67="ETAPA",0,IF(H67="SUBETAPA",OFFSET(D67,-1,0)+1,OFFSET(D67,-1,0))) | E67: =IF(H67="Subetapa",0,IF(H67="serviço",OFFSET(E67,-1,0)+1,OFFSET(E67,-1,0))) | H67: SERVIÇO | I67: =IF(H67="Unidade Construtiva",TEXT(A67,"00"),IF(H67="Célula Construtiva",TEXT(B67,"00"),IF(H67="Etapa",CONCATENATE(TEXT(B67,"00"),".",TEXT(C67,"000")),IF(H67="Subetapa",CONCATENATE(TEXT(B67,"00"),".",TEXT(C67,"000"),".",TEXT(D67,"000")),IF(H67="Serviço",CONCATENATE(TEXT(B67,"00"),".",TEXT(C67,"000"),".",TEXT(D67,"000"),".",TEXT(E67,"000")),""))))) | J67: Cobertura para Proteção de Pedestres | K67: =_xlfn.XLOOKUP($J67,BASES!$A$12:$A$392,BASES!$C$12:$C$392) | L67: =_xlfn.XLOOKUP($J67,BASES!$A$12:$A$392,BASES!$D$12:$D$392) | M67: 247.08 | N67: =IF(H67="Serviço",M67*L67,IF(H67="CÉLULA CONSTRUTIVA",SUMIFS($N$8:$N$442,$B$8:$B$442,B67,$H$8:$H$442,"Serviço"),IF(H67="ETAPA",SUMIFS($N$8:$N$442,$B$8:$B$442,B67,$C$8:$C$442,C67,$H$8:$H$442,"Serviço"),IF(H67="SUBETAPA",SUMIFS($N$8:$N$442,$B$8:$B$442,B67,$C$8:$C$442,C67,$D$8:$D$442,D67,$H$8:$H$442,"Serviço"),0)))) | O67: EPC'S
A68: =IF($H68="UNIDADE CONSTRUTIVA",OFFSET(A68,-1,0)+1,LARGE(A$3:A67,1)) | B68: =IF(H68="UNIDADE CONSTRUTIVA",0,IF(H68="CÉLULA CONSTRUTIVA",OFFSET(B68,-1,0)+1,OFFSET(B68,-1,0))) | C68: =IF(H68="CÉLULA CONSTRUTIVA",0,IF(H68="ETAPA",OFFSET(C68,-1,0)+1,OFFSET(C68,-1,0))) | D68: =IF(H68="ETAPA",0,IF(H68="SUBETAPA",OFFSET(D68,-1,0)+1,OFFSET(D68,-1,0))) | E68: =IF(H68="Subetapa",0,IF(H68="serviço",OFFSET(E68,-1,0)+1,OFFSET(E68,-1,0))) | H68: SERVIÇO | I68: =IF(H68="Unidade Construtiva",TEXT(A68,"00"),IF(H68="Célula Construtiva",TEXT(B68,"00"),IF(H68="Etapa",CONCATENATE(TEXT(B68,"00"),".",TEXT(C68,"000")),IF(H68="Subetapa",CONCATENATE(TEXT(B68,"00"),".",TEXT(C68,"000"),".",TEXT(D68,"000")),IF(H68="Serviço",CONCATENATE(TEXT(B68,"00"),".",TEXT(C68,"000"),".",TEXT(D68,"000"),".",TEXT(E68,"000")),""))))) | J68: Varal de segurança com cabo de aço (linha de vida) | K68: =_xlfn.XLOOKUP($J68,BASES!$A$12:$A$392,BASES!$C$12:$C$392) | L68: =EPCs!D67 | M68: =_xlfn.XLOOKUP($J68,[4]CPU!$D$1:$D$3132,[4]CPU!$H$1:$H$3132) | N68: =IF(H68="Serviço",M68*L68,IF(H68="CÉLULA CONSTRUTIVA",SUMIFS($N$8:$N$442,$B$8:$B$442,B68,$H$8:$H$442,"Serviço"),IF(H68="ETAPA",SUMIFS($N$8:$N$442,$B$8:$B$442,B68,$C$8:$C$442,C68,$H$8:$H$442,"Serviço"),IF(H68="SUBETAPA",SUMIFS($N$8:$N$442,$B$8:$B$442,B68,$C$8:$C$442,C68,$D$8:$D$442,D68,$H$8:$H$442,"Serviço"),0)))) | O68: EPC'S
A69: =IF($H69="UNIDADE CONSTRUTIVA",OFFSET(A69,-1,0)+1,LARGE(A$3:A68,1)) | B69: =IF(H69="UNIDADE CONSTRUTIVA",0,IF(H69="CÉLULA CONSTRUTIVA",OFFSET(B69,-1,0)+1,OFFSET(B69,-1,0))) | C69: =IF(H69="CÉLULA CONSTRUTIVA",0,IF(H69="ETAPA",OFFSET(C69,-1,0)+1,OFFSET(C69,-1,0))) | D69: =IF(H69="ETAPA",0,IF(H69="SUBETAPA",OFFSET(D69,-1,0)+1,OFFSET(D69,-1,0))) | E69: =IF(H69="Subetapa",0,IF(H69="serviço",OFFSET(E69,-1,0)+1,OFFSET(E69,-1,0))) | H69: SERVIÇO | I69: =IF(H69="Unidade Construtiva",TEXT(A69,"00"),IF(H69="Célula Construtiva",TEXT(B69,"00"),IF(H69="Etapa",CONCATENATE(TEXT(B69,"00"),".",TEXT(C69,"000")),IF(H69="Subetapa",CONCATENATE(TEXT(B69,"00"),".",TEXT(C69,"000"),".",TEXT(D69,"000")),IF(H69="Serviço",CONCATENATE(TEXT(B69,"00"),".",TEXT(C69,"000"),".",TEXT(D69,"000"),".",TEXT(E69,"000")),""))))) | J69: Tela SLQA | K69: =_xlfn.XLOOKUP($J69,BASES!$A$12:$A$392,BASES!$C$12:$C$392) | L69: =EPCs!D53 | M69: =_xlfn.XLOOKUP($J69,[4]CPU!$D$1:$D$3132,[4]CPU!$H$1:$H$3132) | N69: =IF(H69="Serviço",M69*L69,IF(H69="CÉLULA CONSTRUTIVA",SUMIFS($N$8:$N$442,$B$8:$B$442,B69,$H$8:$H$442,"Serviço"),IF(H69="ETAPA",SUMIFS($N$8:$N$442,$B$8:$B$442,B69,$C$8:$C$442,C69,$H$8:$H$442,"Serviço"),IF(H69="SUBETAPA",SUMIFS($N$8:$N$442,$B$8:$B$442,B69,$C$8:$C$442,C69,$D$8:$D$442,D69,$H$8:$H$442,"Serviço"),0)))) | O69: EPC'S
A70: =IF($H70="UNIDADE CONSTRUTIVA",OFFSET(A70,-1,0)+1,LARGE(A$3:A69,1)) | B70: =IF(H70="UNIDADE CONSTRUTIVA",0,IF(H70="CÉLULA CONSTRUTIVA",OFFSET(B70,-1,0)+1,OFFSET(B70,-1,0))) | C70: =IF(H70="CÉLULA CONSTRUTIVA",0,IF(H70="ETAPA",OFFSET(C70,-1,0)+1,OFFSET(C70,-1,0))) | D70: =IF(H70="ETAPA",0,IF(H70="SUBETAPA",OFFSET(D70,-1,0)+1,OFFSET(D70,-1,0))) | E70: =IF(H70="Subetapa",0,IF(H70="serviço",OFFSET(E70,-1,0)+1,OFFSET(E70,-1,0))) | H70: SUBETAPA | I70: =IF(H70="Unidade Construtiva",TEXT(A70,"00"),IF(H70="Célula Construtiva",TEXT(B70,"00"),IF(H70="Etapa",CONCATENATE(TEXT(B70,"00"),".",TEXT(C70,"000")),IF(H70="Subetapa",CONCATENATE(TEXT(B70,"00"),".",TEXT(C70,"000"),".",TEXT(D70,"000")),IF(H70="Serviço",CONCATENATE(TEXT(B70,"00"),".",TEXT(C70,"000"),".",TEXT(D70,"000"),".",TEXT(E70,"000")),""))))) | J70: Meio Ambiente | N70: =IF(H70="Serviço",M70*L70,IF(H70="CÉLULA CONSTRUTIVA",SUMIFS($N$8:$N$422,$B$8:$B$422,B70,$H$8:$H$422,"Serviço"),IF(H70="ETAPA",SUMIFS($N$8:$N$422,$B$8:$B$422,B70,$C$8:$C$422,C70,$H$8:$H$422,"Serviço"),IF(H70="SUBETAPA",SUMIFS($N$8:$N$422,$B$8:$B$422,B70,$C$8:$C$422,C70,$D$8:$D$422,D70,$H$8:$H$422,"Serviço"),0))))
A71: =IF($H71="UNIDADE CONSTRUTIVA",OFFSET(A71,-1,0)+1,LARGE(A$3:A70,1)) | B71: =IF(H71="UNIDADE CONSTRUTIVA",0,IF(H71="CÉLULA CONSTRUTIVA",OFFSET(B71,-1,0)+1,OFFSET(B71,-1,0))) | C71: =IF(H71="CÉLULA CONSTRUTIVA",0,IF(H71="ETAPA",OFFSET(C71,-1,0)+1,OFFSET(C71,-1,0))) | D71: =IF(H71="ETAPA",0,IF(H71="SUBETAPA",OFFSET(D71,-1,0)+1,OFFSET(D71,-1,0))) | E71: =IF(H71="Subetapa",0,IF(H71="serviço",OFFSET(E71,-1,0)+1,OFFSET(E71,-1,0))) | H71: SERVIÇO | I71: =IF(H71="Unidade Construtiva",TEXT(A71,"00"),IF(H71="Célula Construtiva",TEXT(B71,"00"),IF(H71="Etapa",CONCATENATE(TEXT(B71,"00"),".",TEXT(C71,"000")),IF(H71="Subetapa",CONCATENATE(TEXT(B71,"00"),".",TEXT(C71,"000"),".",TEXT(D71,"000")),IF(H71="Serviço",CONCATENATE(TEXT(B71,"00"),".",TEXT(C71,"000"),".",TEXT(D71,"000"),".",TEXT(E71,"000")),""))))) | J71: Elaboração do Programa de Controle Médico de Saúde Ocupacional (PCMSO) | K71: =_xlfn.XLOOKUP($J71,BASES!$A$12:$A$392,BASES!$C$12:$C$392) | L71: =_xlfn.XLOOKUP($J71,BASES!$A$12:$A$392,BASES!$D$12:$D$392) | M71: =_xlfn.XLOOKUP($J71,BASES!$A$1:$A$2289,BASES!$E$1:$E$2289) | N71: =IF(H71="Serviço",M71*L71,IF(H71="CÉLULA CONSTRUTIVA",SUMIFS($N$8:$N$422,$B$8:$B$422,B71,$H$8:$H$422,"Serviço"),IF(H71="ETAPA",SUMIFS($N$8:$N$422,$B$8:$B$422,B71,$C$8:$C$422,C71,$H$8:$H$422,"Serviço"),IF(H71="SUBETAPA",SUMIFS($N$8:$N$422,$B$8:$B$422,B71,$C$8:$C$422,C71,$D$8:$D$422,D71,$H$8:$H$422,"Serviço"),0)))) | O71: =_xlfn.XLOOKUP($J71,BASES!$A$12:$A$392,BASES!$F$12:$F$392)
A72: =IF($H72="UNIDADE CONSTRUTIVA",OFFSET(A72,-1,0)+1,LARGE(A$3:A71,1)) | B72: =IF(H72="UNIDADE CONSTRUTIVA",0,IF(H72="CÉLULA CONSTRUTIVA",OFFSET(B72,-1,0)+1,OFFSET(B72,-1,0))) | C72: =IF(H72="CÉLULA CONSTRUTIVA",0,IF(H72="ETAPA",OFFSET(C72,-1,0)+1,OFFSET(C72,-1,0))) | D72: =IF(H72="ETAPA",0,IF(H72="SUBETAPA",OFFSET(D72,-1,0)+1,OFFSET(D72,-1,0))) | E72: =IF(H72="Subetapa",0,IF(H72="serviço",OFFSET(E72,-1,0)+1,OFFSET(E72,-1,0))) | H72: SERVIÇO | I72: =IF(H72="Unidade Construtiva",TEXT(A72,"00"),IF(H72="Célula Construtiva",TEXT(B72,"00"),IF(H72="Etapa",CONCATENATE(TEXT(B72,"00"),".",TEXT(C72,"000")),IF(H72="Subetapa",CONCATENATE(TEXT(B72,"00"),".",TEXT(C72,"000"),".",TEXT(D72,"000")),IF(H72="Serviço",CONCATENATE(TEXT(B72,"00"),".",TEXT(C72,"000"),".",TEXT(D72,"000"),".",TEXT(E72,"000")),""))))) | J72: Elaboração do programa de gerenciamento de riscos (PGR) | K72: =_xlfn.XLOOKUP($J72,BASES!$A$12:$A$392,BASES!$C$12:$C$392) | L72: =_xlfn.XLOOKUP($J72,BASES!$A$12:$A$392,BASES!$D$12:$D$392) | M72: =_xlfn.XLOOKUP($J72,BASES!$A$1:$A$2289,BASES!$E$1:$E$2289) | N72: =IF(H72="Serviço",M72*L72,IF(H72="CÉLULA CONSTRUTIVA",SUMIFS($N$8:$N$422,$B$8:$B$422,B72,$H$8:$H$422,"Serviço"),IF(H72="ETAPA",SUMIFS($N$8:$N$422,$B$8:$B$422,B72,$C$8:$C$422,C72,$H$8:$H$422,"Serviço"),IF(H72="SUBETAPA",SUMIFS($N$8:$N$422,$B$8:$B$422,B72,$C$8:$C$422,C72,$D$8:$D$422,D72,$H$8:$H$422,"Serviço"),0)))) | O72: =_xlfn.XLOOKUP($J72,BASES!$A$12:$A$392,BASES!$F$12:$F$392)
A73: =IF($H73="UNIDADE CONSTRUTIVA",OFFSET(A73,-1,0)+1,LARGE(A$3:A72,1)) | B73: =IF(H73="UNIDADE CONSTRUTIVA",0,IF(H73="CÉLULA CONSTRUTIVA",OFFSET(B73,-1,0)+1,OFFSET(B73,-1,0))) | C73: =IF(H73="CÉLULA CONSTRUTIVA",0,IF(H73="ETAPA",OFFSET(C73,-1,0)+1,OFFSET(C73,-1,0))) | D73: =IF(H73="ETAPA",0,IF(H73="SUBETAPA",OFFSET(D73,-1,0)+1,OFFSET(D73,-1,0))) | E73: =IF(H73="Subetapa",0,IF(H73="serviço",OFFSET(E73,-1,0)+1,OFFSET(E73,-1,0))) | H73: SERVIÇO | I73: =IF(H73="Unidade Construtiva",TEXT(A73,"00"),IF(H73="Célula Construtiva",TEXT(B73,"00"),IF(H73="Etapa",CONCATENATE(TEXT(B73,"00"),".",TEXT(C73,"000")),IF(H73="Subetapa",CONCATENATE(TEXT(B73,"00"),".",TEXT(C73,"000"),".",TEXT(D73,"000")),IF(H73="Serviço",CONCATENATE(TEXT(B73,"00"),".",TEXT(C73,"000"),".",TEXT(D73,"000"),".",TEXT(E73,"000")),""))))) | J73: Remoção de entulhos e resíduos | K73: =_xlfn.XLOOKUP($J73,BASES!$A$12:$A$392,BASES!$C$12:$C$392) | L73: =_xlfn.XLOOKUP($J73,BASES!$A$12:$A$392,BASES!$D$12:$D$392) | M73: =_xlfn.XLOOKUP($J73,BASES!$A$1:$A$2289,BASES!$E$1:$E$2289) | N73: =IF(H73="Serviço",M73*L73,IF(H73="CÉLULA CONSTRUTIVA",SUMIFS($N$8:$N$422,$B$8:$B$422,B73,$H$8:$H$422,"Serviço"),IF(H73="ETAPA",SUMIFS($N$8:$N$422,$B$8:$B$422,B73,$C$8:$C$422,C73,$H$8:$H$422,"Serviço"),IF(H73="SUBETAPA",SUMIFS($N$8:$N$422,$B$8:$B$422,B73,$C$8:$C$422,C73,$D$8:$D$422,D73,$H$8:$H$422,"Serviço"),0)))) | O73: Considerado 4 caçambas de entulho ao mês
A74: =IF($H74="UNIDADE CONSTRUTIVA",OFFSET(A74,-1,0)+1,LARGE(A$3:A73,1)) | B74: =IF(H74="UNIDADE CONSTRUTIVA",0,IF(H74="CÉLULA CONSTRUTIVA",OFFSET(B74,-1,0)+1,OFFSET(B74,-1,0))) | C74: =IF(H74="CÉLULA CONSTRUTIVA",0,IF(H74="ETAPA",OFFSET(C74,-1,0)+1,OFFSET(C74,-1,0))) | D74: =IF(H74="ETAPA",0,IF(H74="SUBETAPA",OFFSET(D74,-1,0)+1,OFFSET(D74,-1,0))) | E74: =IF(H74="Subetapa",0,IF(H74="serviço",OFFSET(E74,-1,0)+1,OFFSET(E74,-1,0))) | H74: SUBETAPA | I74: =IF(H74="Unidade Construtiva",TEXT(A74,"00"),IF(H74="Célula Construtiva",TEXT(B74,"00"),IF(H74="Etapa",CONCATENATE(TEXT(B74,"00"),".",TEXT(C74,"000")),IF(H74="Subetapa",CONCATENATE(TEXT(B74,"00"),".",TEXT(C74,"000"),".",TEXT(D74,"000")),IF(H74="Serviço",CONCATENATE(TEXT(B74,"00"),".",TEXT(C74,"000"),".",TEXT(D74,"000"),".",TEXT(E74,"000")),""))))) | J74: Saúde Ocupacional | N74: =IF(H74="Serviço",M74*L74,IF(H74="CÉLULA CONSTRUTIVA",SUMIFS($N$8:$N$422,$B$8:$B$422,B74,$H$8:$H$422,"Serviço"),IF(H74="ETAPA",SUMIFS($N$8:$N$422,$B$8:$B$422,B74,$C$8:$C$422,C74,$H$8:$H$422,"Serviço"),IF(H74="SUBETAPA",SUMIFS($N$8:$N$422,$B$8:$B$422,B74,$C$8:$C$422,C74,$D$8:$D$422,D74,$H$8:$H$422,"Serviço"),0))))
A75: =IF($H75="UNIDADE CONSTRUTIVA",OFFSET(A75,-1,0)+1,LARGE(A$3:A74,1)) | B75: =IF(H75="UNIDADE CONSTRUTIVA",0,IF(H75="CÉLULA CONSTRUTIVA",OFFSET(B75,-1,0)+1,OFFSET(B75,-1,0))) | C75: =IF(H75="CÉLULA CONSTRUTIVA",0,IF(H75="ETAPA",OFFSET(C75,-1,0)+1,OFFSET(C75,-1,0))) | D75: =IF(H75="ETAPA",0,IF(H75="SUBETAPA",OFFSET(D75,-1,0)+1,OFFSET(D75,-1,0))) | E75: =IF(H75="Subetapa",0,IF(H75="serviço",OFFSET(E75,-1,0)+1,OFFSET(E75,-1,0))) | H75: SERVIÇO | I75: =IF(H75="Unidade Construtiva",TEXT(A75,"00"),IF(H75="Célula Construtiva",TEXT(B75,"00"),IF(H75="Etapa",CONCATENATE(TEXT(B75,"00"),".",TEXT(C75,"000")),IF(H75="Subetapa",CONCATENATE(TEXT(B75,"00"),".",TEXT(C75,"000"),".",TEXT(D75,"000")),IF(H75="Serviço",CONCATENATE(TEXT(B75,"00"),".",TEXT(C75,"000"),".",TEXT(D75,"000"),".",TEXT(E75,"000")),""))))) | J75: Medicamentos preventivos e de emergência | K75: =_xlfn.XLOOKUP($J75,BASES!$A$12:$A$392,BASES!$C$12:$C$392) | L75: =_xlfn.XLOOKUP($J75,BASES!$A$12:$A$392,BASES!$D$12:$D$392) | M75: =_xlfn.XLOOKUP($J75,BASES!$A$1:$A$2289,BASES!$E$1:$E$2289) | N75: =IF(H75="Serviço",M75*L75,IF(H75="CÉLULA CONSTRUTIVA",SUMIFS($N$8:$N$422,$B$8:$B$422,B75,$H$8:$H$422,"Serviço"),IF(H75="ETAPA",SUMIFS($N$8:$N$422,$B$8:$B$422,B75,$C$8:$C$422,C75,$H$8:$H$422,"Serviço"),IF(H75="SUBETAPA",SUMIFS($N$8:$N$422,$B$8:$B$422,B75,$C$8:$C$422,C75,$D$8:$D$422,D75,$H$8:$H$422,"Serviço"),0)))) | O75: =_xlfn.XLOOKUP($J75,BASES!$A$12:$A$392,BASES!$F$12:$F$392)
A76: =IF($H76="UNIDADE CONSTRUTIVA",OFFSET(A76,-1,0)+1,LARGE(A$3:A75,1)) | B76: =IF(H76="UNIDADE CONSTRUTIVA",0,IF(H76="CÉLULA CONSTRUTIVA",OFFSET(B76,-1,0)+1,OFFSET(B76,-1,0))) | C76: =IF(H76="CÉLULA CONSTRUTIVA",0,IF(H76="ETAPA",OFFSET(C76,-1,0)+1,OFFSET(C76,-1,0))) | D76: =IF(H76="ETAPA",0,IF(H76="SUBETAPA",OFFSET(D76,-1,0)+1,OFFSET(D76,-1,0))) | E76: =IF(H76="Subetapa",0,IF(H76="serviço",OFFSET(E76,-1,0)+1,OFFSET(E76,-1,0))) | H76: SERVIÇO | I76: =IF(H76="Unidade Construtiva",TEXT(A76,"00"),IF(H76="Célula Construtiva",TEXT(B76,"00"),IF(H76="Etapa",CONCATENATE(TEXT(B76,"00"),".",TEXT(C76,"000")),IF(H76="Subetapa",CONCATENATE(TEXT(B76,"00"),".",TEXT(C76,"000"),".",TEXT(D76,"000")),IF(H76="Serviço",CONCATENATE(TEXT(B76,"00"),".",TEXT(C76,"000"),".",TEXT(D76,"000"),".",TEXT(E76,"000")),""))))) | J76: Kit socorrista | K76: =_xlfn.XLOOKUP($J76,BASES!$A$12:$A$392,BASES!$C$12:$C$392) | L76: =_xlfn.XLOOKUP($J76,BASES!$A$12:$A$392,BASES!$D$12:$D$392) | M76: =_xlfn.XLOOKUP($J76,BASES!$A$1:$A$2289,BASES!$E$1:$E$2289) | N76: =IF(H76="Serviço",M76*L76,IF(H76="CÉLULA CONSTRUTIVA",SUMIFS($N$8:$N$422,$B$8:$B$422,B76,$H$8:$H$422,"Serviço"),IF(H76="ETAPA",SUMIFS($N$8:$N$422,$B$8:$B$422,B76,$C$8:$C$422,C76,$H$8:$H$422,"Serviço"),IF(H76="SUBETAPA",SUMIFS($N$8:$N$422,$B$8:$B$422,B76,$C$8:$C$422,C76,$D$8:$D$422,D76,$H$8:$H$422,"Serviço"),0)))) | O76: =_xlfn.XLOOKUP($J76,BASES!$A$12:$A$392,BASES!$F$12:$F$392)
A77: =IF($H77="UNIDADE CONSTRUTIVA",OFFSET(A77,-1,0)+1,LARGE(A$3:A76,1)) | B77: =IF(H77="UNIDADE CONSTRUTIVA",0,IF(H77="CÉLULA CONSTRUTIVA",OFFSET(B77,-1,0)+1,OFFSET(B77,-1,0))) | C77: =IF(H77="CÉLULA CONSTRUTIVA",0,IF(H77="ETAPA",OFFSET(C77,-1,0)+1,OFFSET(C77,-1,0))) | D77: =IF(H77="ETAPA",0,IF(H77="SUBETAPA",OFFSET(D77,-1,0)+1,OFFSET(D77,-1,0))) | E77: =IF(H77="Subetapa",0,IF(H77="serviço",OFFSET(E77,-1,0)+1,OFFSET(E77,-1,0))) | H77: SERVIÇO | I77: =IF(H77="Unidade Construtiva",TEXT(A77,"00"),IF(H77="Célula Construtiva",TEXT(B77,"00"),IF(H77="Etapa",CONCATENATE(TEXT(B77,"00"),".",TEXT(C77,"000")),IF(H77="Subetapa",CONCATENATE(TEXT(B77,"00"),".",TEXT(C77,"000"),".",TEXT(D77,"000")),IF(H77="Serviço",CONCATENATE(TEXT(B77,"00"),".",TEXT(C77,"000"),".",TEXT(D77,"000"),".",TEXT(E77,"000")),""))))) | J77: Dedetização, desratização e sanitização dos ambientes | K77: =_xlfn.XLOOKUP($J77,BASES!$A$12:$A$392,BASES!$C$12:$C$392) | L77: =_xlfn.XLOOKUP($J77,BASES!$A$12:$A$392,BASES!$D$12:$D$392) | M77: =_xlfn.XLOOKUP($J77,BASES!$A$1:$A$2289,BASES!$E$1:$E$2289) | N77: =IF(H77="Serviço",M77*L77,IF(H77="CÉLULA CONSTRUTIVA",SUMIFS($N$8:$N$422,$B$8:$B$422,B77,$H$8:$H$422,"Serviço"),IF(H77="ETAPA",SUMIFS($N$8:$N$422,$B$8:$B$422,B77,$C$8:$C$422,C77,$H$8:$H$422,"Serviço"),IF(H77="SUBETAPA",SUMIFS($N$8:$N$422,$B$8:$B$422,B77,$C$8:$C$422,C77,$D$8:$D$422,D77,$H$8:$H$422,"Serviço"),0)))) | O77: =_xlfn.XLOOKUP($J77,BASES!$A$12:$A$392,BASES!$F$12:$F$392)
A78: =IF($H78="UNIDADE CONSTRUTIVA",OFFSET(A78,-1,0)+1,LARGE(A$3:A77,1)) | B78: =IF(H78="UNIDADE CONSTRUTIVA",0,IF(H78="CÉLULA CONSTRUTIVA",OFFSET(B78,-1,0)+1,OFFSET(B78,-1,0))) | C78: =IF(H78="CÉLULA CONSTRUTIVA",0,IF(H78="ETAPA",OFFSET(C78,-1,0)+1,OFFSET(C78,-1,0))) | D78: =IF(H78="ETAPA",0,IF(H78="SUBETAPA",OFFSET(D78,-1,0)+1,OFFSET(D78,-1,0))) | E78: =IF(H78="Subetapa",0,IF(H78="serviço",OFFSET(E78,-1,0)+1,OFFSET(E78,-1,0))) | H78: ETAPA | I78: =IF(H78="Unidade Construtiva",TEXT(A78,"00"),IF(H78="Célula Construtiva",TEXT(B78,"00"),IF(H78="Etapa",CONCATENATE(TEXT(B78,"00"),".",TEXT(C78,"000")),IF(H78="Subetapa",CONCATENATE(TEXT(B78,"00"),".",TEXT(C78,"000"),".",TEXT(D78,"000")),IF(H78="Serviço",CONCATENATE(TEXT(B78,"00"),".",TEXT(C78,"000"),".",TEXT(D78,"000"),".",TEXT(E78,"000")),""))))) | J78: ADMINISTRAÇÃO E CANTEIRO DE OBRA | N78: =IF(H78="Serviço",M78*L78,IF(H78="CÉLULA CONSTRUTIVA",SUMIFS($N$8:$N$422,$B$8:$B$422,B78,$H$8:$H$422,"Serviço"),IF(H78="ETAPA",SUMIFS($N$8:$N$422,$B$8:$B$422,B78,$C$8:$C$422,C78,$H$8:$H$422,"Serviço"),IF(H78="SUBETAPA",SUMIFS($N$8:$N$422,$B$8:$B$422,B78,$C$8:$C$422,C78,$D$8:$D$422,D78,$H$8:$H$422,"Serviço"),0))))
A79: =IF($H79="UNIDADE CONSTRUTIVA",OFFSET(A79,-1,0)+1,LARGE(A$3:A78,1)) | B79: =IF(H79="UNIDADE CONSTRUTIVA",0,IF(H79="CÉLULA CONSTRUTIVA",OFFSET(B79,-1,0)+1,OFFSET(B79,-1,0))) | C79: =IF(H79="CÉLULA CONSTRUTIVA",0,IF(H79="ETAPA",OFFSET(C79,-1,0)+1,OFFSET(C79,-1,0))) | D79: =IF(H79="ETAPA",0,IF(H79="SUBETAPA",OFFSET(D79,-1,0)+1,OFFSET(D79,-1,0))) | E79: =IF(H79="Subetapa",0,IF(H79="serviço",OFFSET(E79,-1,0)+1,OFFSET(E79,-1,0))) | H79: SUBETAPA | I79: =IF(H79="Unidade Construtiva",TEXT(A79,"00"),IF(H79="Célula Construtiva",TEXT(B79,"00"),IF(H79="Etapa",CONCATENATE(TEXT(B79,"00"),".",TEXT(C79,"000")),IF(H79="Subetapa",CONCATENATE(TEXT(B79,"00"),".",TEXT(C79,"000"),".",TEXT(D79,"000")),IF(H79="Serviço",CONCATENATE(TEXT(B79,"00"),".",TEXT(C79,"000"),".",TEXT(D79,"000"),".",TEXT(E79,"000")),""))))) | J79: Equipe de Gestão e Apoio | N79: =IF(H79="Serviço",M79*L79,IF(H79="CÉLULA CONSTRUTIVA",SUMIFS($N$8:$N$422,$B$8:$B$422,B79,$H$8:$H$422,"Serviço"),IF(H79="ETAPA",SUMIFS($N$8:$N$422,$B$8:$B$422,B79,$C$8:$C$422,C79,$H$8:$H$422,"Serviço"),IF(H79="SUBETAPA",SUMIFS($N$8:$N$422,$B$8:$B$422,B79,$C$8:$C$422,C79,$D$8:$D$422,D79,$H$8:$H$422,"Serviço"),0))))
A80: =IF($H80="UNIDADE CONSTRUTIVA",OFFSET(A80,-1,0)+1,LARGE(A$3:A79,1)) | B80: =IF(H80="UNIDADE CONSTRUTIVA",0,IF(H80="CÉLULA CONSTRUTIVA",OFFSET(B80,-1,0)+1,OFFSET(B80,-1,0))) | C80: =IF(H80="CÉLULA CONSTRUTIVA",0,IF(H80="ETAPA",OFFSET(C80,-1,0)+1,OFFSET(C80,-1,0))) | D80: =IF(H80="ETAPA",0,IF(H80="SUBETAPA",OFFSET(D80,-1,0)+1,OFFSET(D80,-1,0))) | E80: =IF(H80="Subetapa",0,IF(H80="serviço",OFFSET(E80,-1,0)+1,OFFSET(E80,-1,0))) | H80: SERVIÇO | I80: =IF(H80="Unidade Construtiva",TEXT(A80,"00"),IF(H80="Célula Construtiva",TEXT(B80,"00"),IF(H80="Etapa",CONCATENATE(TEXT(B80,"00"),".",TEXT(C80,"000")),IF(H80="Subetapa",CONCATENATE(TEXT(B80,"00"),".",TEXT(C80,"000"),".",TEXT(D80,"000")),IF(H80="Serviço",CONCATENATE(TEXT(B80,"00"),".",TEXT(C80,"000"),".",TEXT(D80,"000"),".",TEXT(E80,"000")),""))))) | J80: Engenheiro Civil | K80: =_xlfn.XLOOKUP($J80,BASES!$A$12:$A$392,BASES!$C$12:$C$392) | L80: =_xlfn.XLOOKUP($J80,BASES!$A$12:$A$392,BASES!$D$12:$D$392) | M80: =_xlfn.XLOOKUP($J80,BASES!$A$1:$A$2289,BASES!$E$1:$E$2289) | N80: =IF(H80="Serviço",M80*L80,IF(H80="CÉLULA CONSTRUTIVA",SUMIFS($N$8:$N$422,$B$8:$B$422,B80,$H$8:$H$422,"Serviço"),IF(H80="ETAPA",SUMIFS($N$8:$N$422,$B$8:$B$422,B80,$C$8:$C$422,C80,$H$8:$H$422,"Serviço"),IF(H80="SUBETAPA",SUMIFS($N$8:$N$422,$B$8:$B$422,B80,$C$8:$C$422,C80,$D$8:$D$422,D80,$H$8:$H$422,"Serviço"),0)))) | O80: =_xlfn.XLOOKUP($J80,BASES!$A$12:$A$392,BASES!$F$12:$F$392)
A81: =IF($H81="UNIDADE CONSTRUTIVA",OFFSET(A81,-1,0)+1,LARGE(A$3:A80,1)) | B81: =IF(H81="UNIDADE CONSTRUTIVA",0,IF(H81="CÉLULA CONSTRUTIVA",OFFSET(B81,-1,0)+1,OFFSET(B81,-1,0))) | C81: =IF(H81="CÉLULA CONSTRUTIVA",0,IF(H81="ETAPA",OFFSET(C81,-1,0)+1,OFFSET(C81,-1,0))) | D81: =IF(H81="ETAPA",0,IF(H81="SUBETAPA",OFFSET(D81,-1,0)+1,OFFSET(D81,-1,0))) | E81: =IF(H81="Subetapa",0,IF(H81="serviço",OFFSET(E81,-1,0)+1,OFFSET(E81,-1,0))) | H81: SERVIÇO | I81: =IF(H81="Unidade Construtiva",TEXT(A81,"00"),IF(H81="Célula Construtiva",TEXT(B81,"00"),IF(H81="Etapa",CONCATENATE(TEXT(B81,"00"),".",TEXT(C81,"000")),IF(H81="Subetapa",CONCATENATE(TEXT(B81,"00"),".",TEXT(C81,"000"),".",TEXT(D81,"000")),IF(H81="Serviço",CONCATENATE(TEXT(B81,"00"),".",TEXT(C81,"000"),".",TEXT(D81,"000"),".",TEXT(E81,"000")),""))))) | J81: Mestre De Obras | K81: =_xlfn.XLOOKUP($J81,BASES!$A$12:$A$392,BASES!$C$12:$C$392) | L81: =_xlfn.XLOOKUP($J81,BASES!$A$12:$A$392,BASES!$D$12:$D$392) | M81: =_xlfn.XLOOKUP($J81,BASES!$A$1:$A$2289,BASES!$E$1:$E$2289) | N81: =IF(H81="Serviço",M81*L81,IF(H81="CÉLULA CONSTRUTIVA",SUMIFS($N$8:$N$422,$B$8:$B$422,B81,$H$8:$H$422,"Serviço"),IF(H81="ETAPA",SUMIFS($N$8:$N$422,$B$8:$B$422,B81,$C$8:$C$422,C81,$H$8:$H$422,"Serviço"),IF(H81="SUBETAPA",SUMIFS($N$8:$N$422,$B$8:$B$422,B81,$C$8:$C$422,C81,$D$8:$D$422,D81,$H$8:$H$422,"Serviço"),0)))) | O81: =_xlfn.XLOOKUP($J81,BASES!$A$12:$A$392,BASES!$F$12:$F$392)
A82: =IF($H82="UNIDADE CONSTRUTIVA",OFFSET(A82,-1,0)+1,LARGE(A$3:A81,1)) | B82: =IF(H82="UNIDADE CONSTRUTIVA",0,IF(H82="CÉLULA CONSTRUTIVA",OFFSET(B82,-1,0)+1,OFFSET(B82,-1,0))) | C82: =IF(H82="CÉLULA CONSTRUTIVA",0,IF(H82="ETAPA",OFFSET(C82,-1,0)+1,OFFSET(C82,-1,0))) | D82: =IF(H82="ETAPA",0,IF(H82="SUBETAPA",OFFSET(D82,-1,0)+1,OFFSET(D82,-1,0))) | E82: =IF(H82="Subetapa",0,IF(H82="serviço",OFFSET(E82,-1,0)+1,OFFSET(E82,-1,0))) | H82: SERVIÇO | I82: =IF(H82="Unidade Construtiva",TEXT(A82,"00"),IF(H82="Célula Construtiva",TEXT(B82,"00"),IF(H82="Etapa",CONCATENATE(TEXT(B82,"00"),".",TEXT(C82,"000")),IF(H82="Subetapa",CONCATENATE(TEXT(B82,"00"),".",TEXT(C82,"000"),".",TEXT(D82,"000")),IF(H82="Serviço",CONCATENATE(TEXT(B82,"00"),".",TEXT(C82,"000"),".",TEXT(D82,"000"),".",TEXT(E82,"000")),""))))) | J82: Auxiliar de engenharia | K82: =_xlfn.XLOOKUP($J82,BASES!$A$12:$A$392,BASES!$C$12:$C$392) | L82: =_xlfn.XLOOKUP($J82,BASES!$A$12:$A$392,BASES!$D$12:$D$392) | M82: =_xlfn.XLOOKUP($J82,BASES!$A$1:$A$2289,BASES!$E$1:$E$2289) | N82: =IF(H82="Serviço",M82*L82,IF(H82="CÉLULA CONSTRUTIVA",SUMIFS($N$8:$N$422,$B$8:$B$422,B82,$H$8:$H$422,"Serviço"),IF(H82="ETAPA",SUMIFS($N$8:$N$422,$B$8:$B$422,B82,$C$8:$C$422,C82,$H$8:$H$422,"Serviço"),IF(H82="SUBETAPA",SUMIFS($N$8:$N$422,$B$8:$B$422,B82,$C$8:$C$422,C82,$D$8:$D$422,D82,$H$8:$H$422,"Serviço"),0)))) | O82: =_xlfn.XLOOKUP($J82,BASES!$A$12:$A$392,BASES!$F$12:$F$392)
A83: =IF($H83="UNIDADE CONSTRUTIVA",OFFSET(A83,-1,0)+1,LARGE(A$3:A82,1)) | B83: =IF(H83="UNIDADE CONSTRUTIVA",0,IF(H83="CÉLULA CONSTRUTIVA",OFFSET(B83,-1,0)+1,OFFSET(B83,-1,0))) | C83: =IF(H83="CÉLULA CONSTRUTIVA",0,IF(H83="ETAPA",OFFSET(C83,-1,0)+1,OFFSET(C83,-1,0))) | D83: =IF(H83="ETAPA",0,IF(H83="SUBETAPA",OFFSET(D83,-1,0)+1,OFFSET(D83,-1,0))) | E83: =IF(H83="Subetapa",0,IF(H83="serviço",OFFSET(E83,-1,0)+1,OFFSET(E83,-1,0))) | H83: SERVIÇO | I83: =IF(H83="Unidade Construtiva",TEXT(A83,"00"),IF(H83="Célula Construtiva",TEXT(B83,"00"),IF(H83="Etapa",CONCATENATE(TEXT(B83,"00"),".",TEXT(C83,"000")),IF(H83="Subetapa",CONCATENATE(TEXT(B83,"00"),".",TEXT(C83,"000"),".",TEXT(D83,"000")),IF(H83="Serviço",CONCATENATE(TEXT(B83,"00"),".",TEXT(C83,"000"),".",TEXT(D83,"000"),".",TEXT(E83,"000")),""))))) | J83: Estagiário | K83: =_xlfn.XLOOKUP($J83,BASES!$A$12:$A$392,BASES!$C$12:$C$392) | L83: =_xlfn.XLOOKUP($J83,BASES!$A$12:$A$392,BASES!$D$12:$D$392) | M83: =_xlfn.XLOOKUP($J83,BASES!$A$1:$A$2289,BASES!$E$1:$E$2289) | N83: =IF(H83="Serviço",M83*L83,IF(H83="CÉLULA CONSTRUTIVA",SUMIFS($N$8:$N$422,$B$8:$B$422,B83,$H$8:$H$422,"Serviço"),IF(H83="ETAPA",SUMIFS($N$8:$N$422,$B$8:$B$422,B83,$C$8:$C$422,C83,$H$8:$H$422,"Serviço"),IF(H83="SUBETAPA",SUMIFS($N$8:$N$422,$B$8:$B$422,B83,$C$8:$C$422,C83,$D$8:$D$422,D83,$H$8:$H$422,"Serviço"),0)))) | O83: =_xlfn.XLOOKUP($J83,BASES!$A$12:$A$392,BASES!$F$12:$F$392)
A84: =IF($H84="UNIDADE CONSTRUTIVA",OFFSET(A84,-1,0)+1,LARGE(A$3:A83,1)) | B84: =IF(H84="UNIDADE CONSTRUTIVA",0,IF(H84="CÉLULA CONSTRUTIVA",OFFSET(B84,-1,0)+1,OFFSET(B84,-1,0))) | C84: =IF(H84="CÉLULA CONSTRUTIVA",0,IF(H84="ETAPA",OFFSET(C84,-1,0)+1,OFFSET(C84,-1,0))) | D84: =IF(H84="ETAPA",0,IF(H84="SUBETAPA",OFFSET(D84,-1,0)+1,OFFSET(D84,-1,0))) | E84: =IF(H84="Subetapa",0,IF(H84="serviço",OFFSET(E84,-1,0)+1,OFFSET(E84,-1,0))) | H84: SERVIÇO | I84: =IF(H84="Unidade Construtiva",TEXT(A84,"00"),IF(H84="Célula Construtiva",TEXT(B84,"00"),IF(H84="Etapa",CONCATENATE(TEXT(B84,"00"),".",TEXT(C84,"000")),IF(H84="Subetapa",CONCATENATE(TEXT(B84,"00"),".",TEXT(C84,"000"),".",TEXT(D84,"000")),IF(H84="Serviço",CONCATENATE(TEXT(B84,"00"),".",TEXT(C84,"000"),".",TEXT(D84,"000"),".",TEXT(E84,"000")),""))))) | J84: Guincheiro | K84: =_xlfn.XLOOKUP($J84,BASES!$A$12:$A$392,BASES!$C$12:$C$392) | L84: =_xlfn.XLOOKUP($J84,BASES!$A$12:$A$392,BASES!$D$12:$D$392) | M84: =_xlfn.XLOOKUP($J84,BASES!$A$1:$A$2289,BASES!$E$1:$E$2289) | N84: =IF(H84="Serviço",M84*L84,IF(H84="CÉLULA CONSTRUTIVA",SUMIFS($N$8:$N$422,$B$8:$B$422,B84,$H$8:$H$422,"Serviço"),IF(H84="ETAPA",SUMIFS($N$8:$N$422,$B$8:$B$422,B84,$C$8:$C$422,C84,$H$8:$H$422,"Serviço"),IF(H84="SUBETAPA",SUMIFS($N$8:$N$422,$B$8:$B$422,B84,$C$8:$C$422,C84,$D$8:$D$422,D84,$H$8:$H$422,"Serviço"),0)))) | O84: =_xlfn.XLOOKUP($J84,BASES!$A$12:$A$392,BASES!$F$12:$F$392)
A85: =IF($H85="UNIDADE CONSTRUTIVA",OFFSET(A85,-1,0)+1,LARGE(A$3:A84,1)) | B85: =IF(H85="UNIDADE CONSTRUTIVA",0,IF(H85="CÉLULA CONSTRUTIVA",OFFSET(B85,-1,0)+1,OFFSET(B85,-1,0))) | C85: =IF(H85="CÉLULA CONSTRUTIVA",0,IF(H85="ETAPA",OFFSET(C85,-1,0)+1,OFFSET(C85,-1,0))) | D85: =IF(H85="ETAPA",0,IF(H85="SUBETAPA",OFFSET(D85,-1,0)+1,OFFSET(D85,-1,0))) | E85: =IF(H85="Subetapa",0,IF(H85="serviço",OFFSET(E85,-1,0)+1,OFFSET(E85,-1,0))) | H85: SERVIÇO | I85: =IF(H85="Unidade Construtiva",TEXT(A85,"00"),IF(H85="Célula Construtiva",TEXT(B85,"00"),IF(H85="Etapa",CONCATENATE(TEXT(B85,"00"),".",TEXT(C85,"000")),IF(H85="Subetapa",CONCATENATE(TEXT(B85,"00"),".",TEXT(C85,"000"),".",TEXT(D85,"000")),IF(H85="Serviço",CONCATENATE(TEXT(B85,"00"),".",TEXT(C85,"000"),".",TEXT(D85,"000"),".",TEXT(E85,"000")),""))))) | J85: Equipe de apoio | K85: =_xlfn.XLOOKUP($J85,BASES!$A$12:$A$392,BASES!$C$12:$C$392) | L85: =_xlfn.XLOOKUP($J85,BASES!$A$12:$A$392,BASES!$D$12:$D$392) | M85: =_xlfn.XLOOKUP($J85,BASES!$A$1:$A$2289,BASES!$E$1:$E$2289) | N85: =IF(H85="Serviço",M85*L85,IF(H85="CÉLULA CONSTRUTIVA",SUMIFS($N$8:$N$422,$B$8:$B$422,B85,$H$8:$H$422,"Serviço"),IF(H85="ETAPA",SUMIFS($N$8:$N$422,$B$8:$B$422,B85,$C$8:$C$422,C85,$H$8:$H$422,"Serviço"),IF(H85="SUBETAPA",SUMIFS($N$8:$N$422,$B$8:$B$422,B85,$C$8:$C$422,C85,$D$8:$D$422,D85,$H$8:$H$422,"Serviço"),0)))) | O85: Estimado - Montagem e desmontagem de proteção coletiva 4 funcionários/carpinteiros.
A86: =IF($H86="UNIDADE CONSTRUTIVA",OFFSET(A86,-1,0)+1,LARGE(A$3:A85,1)) | B86: =IF(H86="UNIDADE CONSTRUTIVA",0,IF(H86="CÉLULA CONSTRUTIVA",OFFSET(B86,-1,0)+1,OFFSET(B86,-1,0))) | C86: =IF(H86="CÉLULA CONSTRUTIVA",0,IF(H86="ETAPA",OFFSET(C86,-1,0)+1,OFFSET(C86,-1,0))) | D86: =IF(H86="ETAPA",0,IF(H86="SUBETAPA",OFFSET(D86,-1,0)+1,OFFSET(D86,-1,0))) | E86: =IF(H86="Subetapa",0,IF(H86="serviço",OFFSET(E86,-1,0)+1,OFFSET(E86,-1,0))) | H86: SUBETAPA | I86: =IF(H86="Unidade Construtiva",TEXT(A86,"00"),IF(H86="Célula Construtiva",TEXT(B86,"00"),IF(H86="Etapa",CONCATENATE(TEXT(B86,"00"),".",TEXT(C86,"000")),IF(H86="Subetapa",CONCATENATE(TEXT(B86,"00"),".",TEXT(C86,"000"),".",TEXT(D86,"000")),IF(H86="Serviço",CONCATENATE(TEXT(B86,"00"),".",TEXT(C86,"000"),".",TEXT(D86,"000"),".",TEXT(E86,"000")),""))))) | J86: Despesas de Consumo e Manutenção | N86: =IF(H86="Serviço",M86*L86,IF(H86="CÉLULA CONSTRUTIVA",SUMIFS($N$8:$N$422,$B$8:$B$422,B86,$H$8:$H$422,"Serviço"),IF(H86="ETAPA",SUMIFS($N$8:$N$422,$B$8:$B$422,B86,$C$8:$C$422,C86,$H$8:$H$422,"Serviço"),IF(H86="SUBETAPA",SUMIFS($N$8:$N$422,$B$8:$B$422,B86,$C$8:$C$422,C86,$D$8:$D$422,D86,$H$8:$H$422,"Serviço"),0))))
A87: =IF($H87="UNIDADE CONSTRUTIVA",OFFSET(A87,-1,0)+1,LARGE(A$3:A86,1)) | B87: =IF(H87="UNIDADE CONSTRUTIVA",0,IF(H87="CÉLULA CONSTRUTIVA",OFFSET(B87,-1,0)+1,OFFSET(B87,-1,0))) | C87: =IF(H87="CÉLULA CONSTRUTIVA",0,IF(H87="ETAPA",OFFSET(C87,-1,0)+1,OFFSET(C87,-1,0))) | D87: =IF(H87="ETAPA",0,IF(H87="SUBETAPA",OFFSET(D87,-1,0)+1,OFFSET(D87,-1,0))) | E87: =IF(H87="Subetapa",0,IF(H87="serviço",OFFSET(E87,-1,0)+1,OFFSET(E87,-1,0))) | H87: SERVIÇO | I87: =IF(H87="Unidade Construtiva",TEXT(A87,"00"),IF(H87="Célula Construtiva",TEXT(B87,"00"),IF(H87="Etapa",CONCATENATE(TEXT(B87,"00"),".",TEXT(C87,"000")),IF(H87="Subetapa",CONCATENATE(TEXT(B87,"00"),".",TEXT(C87,"000"),".",TEXT(D87,"000")),IF(H87="Serviço",CONCATENATE(TEXT(B87,"00"),".",TEXT(C87,"000"),".",TEXT(D87,"000"),".",TEXT(E87,"000")),""))))) | J87: Consumos Mensais: Água e Esgoto | K87: =_xlfn.XLOOKUP($J87,BASES!$A$12:$A$392,BASES!$C$12:$C$392) | L87: =_xlfn.XLOOKUP($J87,BASES!$A$12:$A$392,BASES!$D$12:$D$392) | M87: =_xlfn.XLOOKUP($J87,BASES!$A$1:$A$2289,BASES!$E$1:$E$2289) | N87: =IF(H87="Serviço",M87*L87,IF(H87="CÉLULA CONSTRUTIVA",SUMIFS($N$8:$N$422,$B$8:$B$422,B87,$H$8:$H$422,"Serviço"),IF(H87="ETAPA",SUMIFS($N$8:$N$422,$B$8:$B$422,B87,$C$8:$C$422,C87,$H$8:$H$422,"Serviço"),IF(H87="SUBETAPA",SUMIFS($N$8:$N$422,$B$8:$B$422,B87,$C$8:$C$422,C87,$D$8:$D$422,D87,$H$8:$H$422,"Serviço"),0)))) | O87: =_xlfn.XLOOKUP($J87,BASES!$A$12:$A$392,BASES!$F$12:$F$392)
A88: =IF($H88="UNIDADE CONSTRUTIVA",OFFSET(A88,-1,0)+1,LARGE(A$3:A87,1)) | B88: =IF(H88="UNIDADE CONSTRUTIVA",0,IF(H88="CÉLULA CONSTRUTIVA",OFFSET(B88,-1,0)+1,OFFSET(B88,-1,0))) | C88: =IF(H88="CÉLULA CONSTRUTIVA",0,IF(H88="ETAPA",OFFSET(C88,-1,0)+1,OFFSET(C88,-1,0))) | D88: =IF(H88="ETAPA",0,IF(H88="SUBETAPA",OFFSET(D88,-1,0)+1,OFFSET(D88,-1,0))) | E88: =IF(H88="Subetapa",0,IF(H88="serviço",OFFSET(E88,-1,0)+1,OFFSET(E88,-1,0))) | H88: SERVIÇO | I88: =IF(H88="Unidade Construtiva",TEXT(A88,"00"),IF(H88="Célula Construtiva",TEXT(B88,"00"),IF(H88="Etapa",CONCATENATE(TEXT(B88,"00"),".",TEXT(C88,"000")),IF(H88="Subetapa",CONCATENATE(TEXT(B88,"00"),".",TEXT(C88,"000"),".",TEXT(D88,"000")),IF(H88="Serviço",CONCATENATE(TEXT(B88,"00"),".",TEXT(C88,"000"),".",TEXT(D88,"000"),".",TEXT(E88,"000")),""))))) | J88: Consumos Mensais: Luz/energia | K88: =_xlfn.XLOOKUP($J88,BASES!$A$12:$A$392,BASES!$C$12:$C$392) | L88: =_xlfn.XLOOKUP($J88,BASES!$A$12:$A$392,BASES!$D$12:$D$392) | M88: =_xlfn.XLOOKUP($J88,BASES!$A$1:$A$2289,BASES!$E$1:$E$2289) | N88: =IF(H88="Serviço",M88*L88,IF(H88="CÉLULA CONSTRUTIVA",SUMIFS($N$8:$N$422,$B$8:$B$422,B88,$H$8:$H$422,"Serviço"),IF(H88="ETAPA",SUMIFS($N$8:$N$422,$B$8:$B$422,B88,$C$8:$C$422,C88,$H$8:$H$422,"Serviço"),IF(H88="SUBETAPA",SUMIFS($N$8:$N$422,$B$8:$B$422,B88,$C$8:$C$422,C88,$D$8:$D$422,D88,$H$8:$H$422,"Serviço"),0)))) | O88: =_xlfn.XLOOKUP($J88,BASES!$A$12:$A$392,BASES!$F$12:$F$392)
A89: =IF($H89="UNIDADE CONSTRUTIVA",OFFSET(A89,-1,0)+1,LARGE(A$3:A88,1)) | B89: =IF(H89="UNIDADE CONSTRUTIVA",0,IF(H89="CÉLULA CONSTRUTIVA",OFFSET(B89,-1,0)+1,OFFSET(B89,-1,0))) | C89: =IF(H89="CÉLULA CONSTRUTIVA",0,IF(H89="ETAPA",OFFSET(C89,-1,0)+1,OFFSET(C89,-1,0))) | D89: =IF(H89="ETAPA",0,IF(H89="SUBETAPA",OFFSET(D89,-1,0)+1,OFFSET(D89,-1,0))) | E89: =IF(H89="Subetapa",0,IF(H89="serviço",OFFSET(E89,-1,0)+1,OFFSET(E89,-1,0))) | H89: SERVIÇO | I89: =IF(H89="Unidade Construtiva",TEXT(A89,"00"),IF(H89="Célula Construtiva",TEXT(B89,"00"),IF(H89="Etapa",CONCATENATE(TEXT(B89,"00"),".",TEXT(C89,"000")),IF(H89="Subetapa",CONCATENATE(TEXT(B89,"00"),".",TEXT(C89,"000"),".",TEXT(D89,"000")),IF(H89="Serviço",CONCATENATE(TEXT(B89,"00"),".",TEXT(C89,"000"),".",TEXT(D89,"000"),".",TEXT(E89,"000")),""))))) | J89: Consumos Mensais: Telefone | K89: =_xlfn.XLOOKUP($J89,BASES!$A$12:$A$392,BASES!$C$12:$C$392) | L89: =_xlfn.XLOOKUP($J89,BASES!$A$12:$A$392,BASES!$D$12:$D$392) | M89: =_xlfn.XLOOKUP($J89,BASES!$A$1:$A$2289,BASES!$E$1:$E$2289) | N89: =IF(H89="Serviço",M89*L89,IF(H89="CÉLULA CONSTRUTIVA",SUMIFS($N$8:$N$422,$B$8:$B$422,B89,$H$8:$H$422,"Serviço"),IF(H89="ETAPA",SUMIFS($N$8:$N$422,$B$8:$B$422,B89,$C$8:$C$422,C89,$H$8:$H$422,"Serviço"),IF(H89="SUBETAPA",SUMIFS($N$8:$N$422,$B$8:$B$422,B89,$C$8:$C$422,C89,$D$8:$D$422,D89,$H$8:$H$422,"Serviço"),0)))) | O89: =_xlfn.XLOOKUP($J89,BASES!$A$12:$A$392,BASES!$F$12:$F$392)
A90: =IF($H90="UNIDADE CONSTRUTIVA",OFFSET(A90,-1,0)+1,LARGE(A$3:A89,1)) | B90: =IF(H90="UNIDADE CONSTRUTIVA",0,IF(H90="CÉLULA CONSTRUTIVA",OFFSET(B90,-1,0)+1,OFFSET(B90,-1,0))) | C90: =IF(H90="CÉLULA CONSTRUTIVA",0,IF(H90="ETAPA",OFFSET(C90,-1,0)+1,OFFSET(C90,-1,0))) | D90: =IF(H90="ETAPA",0,IF(H90="SUBETAPA",OFFSET(D90,-1,0)+1,OFFSET(D90,-1,0))) | E90: =IF(H90="Subetapa",0,IF(H90="serviço",OFFSET(E90,-1,0)+1,OFFSET(E90,-1,0))) | H90: SERVIÇO | I90: =IF(H90="Unidade Construtiva",TEXT(A90,"00"),IF(H90="Célula Construtiva",TEXT(B90,"00"),IF(H90="Etapa",CONCATENATE(TEXT(B90,"00"),".",TEXT(C90,"000")),IF(H90="Subetapa",CONCATENATE(TEXT(B90,"00"),".",TEXT(C90,"000"),".",TEXT(D90,"000")),IF(H90="Serviço",CONCATENATE(TEXT(B90,"00"),".",TEXT(C90,"000"),".",TEXT(D90,"000"),".",TEXT(E90,"000")),""))))) | J90: Consumos Mensais: Coleta de Lixo | K90: =_xlfn.XLOOKUP($J90,BASES!$A$12:$A$392,BASES!$C$12:$C$392) | L90: =_xlfn.XLOOKUP($J90,BASES!$A$12:$A$392,BASES!$D$12:$D$392) | M90: =_xlfn.XLOOKUP($J90,BASES!$A$1:$A$2289,BASES!$E$1:$E$2289) | N90: =IF(H90="Serviço",M90*L90,IF(H90="CÉLULA CONSTRUTIVA",SUMIFS($N$8:$N$422,$B$8:$B$422,B90,$H$8:$H$422,"Serviço"),IF(H90="ETAPA",SUMIFS($N$8:$N$422,$B$8:$B$422,B90,$C$8:$C$422,C90,$H$8:$H$422,"Serviço"),IF(H90="SUBETAPA",SUMIFS($N$8:$N$422,$B$8:$B$422,B90,$C$8:$C$422,C90,$D$8:$D$422,D90,$H$8:$H$422,"Serviço"),0)))) | O90: =_xlfn.XLOOKUP($J90,BASES!$A$12:$A$392,BASES!$F$12:$F$392)
A91: =IF($H91="UNIDADE CONSTRUTIVA",OFFSET(A91,-1,0)+1,LARGE(A$3:A90,1)) | B91: =IF(H91="UNIDADE CONSTRUTIVA",0,IF(H91="CÉLULA CONSTRUTIVA",OFFSET(B91,-1,0)+1,OFFSET(B91,-1,0))) | C91: =IF(H91="CÉLULA CONSTRUTIVA",0,IF(H91="ETAPA",OFFSET(C91,-1,0)+1,OFFSET(C91,-1,0))) | D91: =IF(H91="ETAPA",0,IF(H91="SUBETAPA",OFFSET(D91,-1,0)+1,OFFSET(D91,-1,0))) | E91: =IF(H91="Subetapa",0,IF(H91="serviço",OFFSET(E91,-1,0)+1,OFFSET(E91,-1,0))) | H91: SERVIÇO | I91: =IF(H91="Unidade Construtiva",TEXT(A91,"00"),IF(H91="Célula Construtiva",TEXT(B91,"00"),IF(H91="Etapa",CONCATENATE(TEXT(B91,"00"),".",TEXT(C91,"000")),IF(H91="Subetapa",CONCATENATE(TEXT(B91,"00"),".",TEXT(C91,"000"),".",TEXT(D91,"000")),IF(H91="Serviço",CONCATENATE(TEXT(B91,"00"),".",TEXT(C91,"000"),".",TEXT(D91,"000"),".",TEXT(E91,"000")),""))))) | J91: Consumos Mensais: Alimentação | K91: =_xlfn.XLOOKUP($J91,BASES!$A$12:$A$392,BASES!$C$12:$C$392) | L91: =_xlfn.XLOOKUP($J91,BASES!$A$12:$A$392,BASES!$D$12:$D$392) | M91: =_xlfn.XLOOKUP($J91,BASES!$A$1:$A$2289,BASES!$E$1:$E$2289) | N91: =IF(H91="Serviço",M91*L91,IF(H91="CÉLULA CONSTRUTIVA",SUMIFS($N$8:$N$422,$B$8:$B$422,B91,$H$8:$H$422,"Serviço"),IF(H91="ETAPA",SUMIFS($N$8:$N$422,$B$8:$B$422,B91,$C$8:$C$422,C91,$H$8:$H$422,"Serviço"),IF(H91="SUBETAPA",SUMIFS($N$8:$N$422,$B$8:$B$422,B91,$C$8:$C$422,C91,$D$8:$D$422,D91,$H$8:$H$422,"Serviço"),0)))) | O91: =_xlfn.XLOOKUP($J91,BASES!$A$12:$A$392,BASES!$F$12:$F$392)
A92: =IF($H92="UNIDADE CONSTRUTIVA",OFFSET(A92,-1,0)+1,LARGE(A$3:A91,1)) | B92: =IF(H92="UNIDADE CONSTRUTIVA",0,IF(H92="CÉLULA CONSTRUTIVA",OFFSET(B92,-1,0)+1,OFFSET(B92,-1,0))) | C92: =IF(H92="CÉLULA CONSTRUTIVA",0,IF(H92="ETAPA",OFFSET(C92,-1,0)+1,OFFSET(C92,-1,0))) | D92: =IF(H92="ETAPA",0,IF(H92="SUBETAPA",OFFSET(D92,-1,0)+1,OFFSET(D92,-1,0))) | E92: =IF(H92="Subetapa",0,IF(H92="serviço",OFFSET(E92,-1,0)+1,OFFSET(E92,-1,0))) | H92: SERVIÇO | I92: =IF(H92="Unidade Construtiva",TEXT(A92,"00"),IF(H92="Célula Construtiva",TEXT(B92,"00"),IF(H92="Etapa",CONCATENATE(TEXT(B92,"00"),".",TEXT(C92,"000")),IF(H92="Subetapa",CONCATENATE(TEXT(B92,"00"),".",TEXT(C92,"000"),".",TEXT(D92,"000")),IF(H92="Serviço",CONCATENATE(TEXT(B92,"00"),".",TEXT(C92,"000"),".",TEXT(D92,"000"),".",TEXT(E92,"000")),""))))) | J92: Consumos Mensais: Mateirial de expediênte/escritório | K92: =_xlfn.XLOOKUP($J92,BASES!$A$12:$A$392,BASES!$C$12:$C$392) | L92: =_xlfn.XLOOKUP($J92,BASES!$A$12:$A$392,BASES!$D$12:$D$392) | M92: =_xlfn.XLOOKUP($J92,BASES!$A$1:$A$2289,BASES!$E$1:$E$2289) | N92: =IF(H92="Serviço",M92*L92,IF(H92="CÉLULA CONSTRUTIVA",SUMIFS($N$8:$N$422,$B$8:$B$422,B92,$H$8:$H$422,"Serviço"),IF(H92="ETAPA",SUMIFS($N$8:$N$422,$B$8:$B$422,B92,$C$8:$C$422,C92,$H$8:$H$422,"Serviço"),IF(H92="SUBETAPA",SUMIFS($N$8:$N$422,$B$8:$B$422,B92,$C$8:$C$422,C92,$D$8:$D$422,D92,$H$8:$H$422,"Serviço"),0)))) | O92: =_xlfn.XLOOKUP($J92,BASES!$A$12:$A$392,BASES!$F$12:$F$392)
A93: =IF($H93="UNIDADE CONSTRUTIVA",OFFSET(A93,-1,0)+1,LARGE(A$3:A92,1)) | B93: =IF(H93="UNIDADE CONSTRUTIVA",0,IF(H93="CÉLULA CONSTRUTIVA",OFFSET(B93,-1,0)+1,OFFSET(B93,-1,0))) | C93: =IF(H93="CÉLULA CONSTRUTIVA",0,IF(H93="ETAPA",OFFSET(C93,-1,0)+1,OFFSET(C93,-1,0))) | D93: =IF(H93="ETAPA",0,IF(H93="SUBETAPA",OFFSET(D93,-1,0)+1,OFFSET(D93,-1,0))) | E93: =IF(H93="Subetapa",0,IF(H93="serviço",OFFSET(E93,-1,0)+1,OFFSET(E93,-1,0))) | H93: SERVIÇO | I93: =IF(H93="Unidade Construtiva",TEXT(A93,"00"),IF(H93="Célula Construtiva",TEXT(B93,"00"),IF(H93="Etapa",CONCATENATE(TEXT(B93,"00"),".",TEXT(C93,"000")),IF(H93="Subetapa",CONCATENATE(TEXT(B93,"00"),".",TEXT(C93,"000"),".",TEXT(D93,"000")),IF(H93="Serviço",CONCATENATE(TEXT(B93,"00"),".",TEXT(C93,"000"),".",TEXT(D93,"000"),".",TEXT(E93,"000")),""))))) | J93: Consumos Mensais: Material de higiêne e limpeza | K93: =_xlfn.XLOOKUP($J93,BASES!$A$12:$A$392,BASES!$C$12:$C$392) | L93: =_xlfn.XLOOKUP($J93,BASES!$A$12:$A$392,BASES!$D$12:$D$392) | M93: =_xlfn.XLOOKUP($J93,BASES!$A$1:$A$2289,BASES!$E$1:$E$2289) | N93: =IF(H93="Serviço",M93*L93,IF(H93="CÉLULA CONSTRUTIVA",SUMIFS($N$8:$N$422,$B$8:$B$422,B93,$H$8:$H$422,"Serviço"),IF(H93="ETAPA",SUMIFS($N$8:$N$422,$B$8:$B$422,B93,$C$8:$C$422,C93,$H$8:$H$422,"Serviço"),IF(H93="SUBETAPA",SUMIFS($N$8:$N$422,$B$8:$B$422,B93,$C$8:$C$422,C93,$D$8:$D$422,D93,$H$8:$H$422,"Serviço"),0)))) | O93: =_xlfn.XLOOKUP($J93,BASES!$A$12:$A$392,BASES!$F$12:$F$392)
A94: =IF($H94="UNIDADE CONSTRUTIVA",OFFSET(A94,-1,0)+1,LARGE(A$3:A93,1)) | B94: =IF(H94="UNIDADE CONSTRUTIVA",0,IF(H94="CÉLULA CONSTRUTIVA",OFFSET(B94,-1,0)+1,OFFSET(B94,-1,0))) | C94: =IF(H94="CÉLULA CONSTRUTIVA",0,IF(H94="ETAPA",OFFSET(C94,-1,0)+1,OFFSET(C94,-1,0))) | D94: =IF(H94="ETAPA",0,IF(H94="SUBETAPA",OFFSET(D94,-1,0)+1,OFFSET(D94,-1,0))) | E94: =IF(H94="Subetapa",0,IF(H94="serviço",OFFSET(E94,-1,0)+1,OFFSET(E94,-1,0))) | H94: SERVIÇO | I94: =IF(H94="Unidade Construtiva",TEXT(A94,"00"),IF(H94="Célula Construtiva",TEXT(B94,"00"),IF(H94="Etapa",CONCATENATE(TEXT(B94,"00"),".",TEXT(C94,"000")),IF(H94="Subetapa",CONCATENATE(TEXT(B94,"00"),".",TEXT(C94,"000"),".",TEXT(D94,"000")),IF(H94="Serviço",CONCATENATE(TEXT(B94,"00"),".",TEXT(C94,"000"),".",TEXT(D94,"000"),".",TEXT(E94,"000")),""))))) | J94: Consumos gerais: Fretes | K94: =_xlfn.XLOOKUP($J94,BASES!$A$12:$A$392,BASES!$C$12:$C$392) | L94: =_xlfn.XLOOKUP($J94,BASES!$A$12:$A$392,BASES!$D$12:$D$392) | M94: =_xlfn.XLOOKUP($J94,BASES!$A$1:$A$2289,BASES!$E$1:$E$2289) | N94: =IF(H94="Serviço",M94*L94,IF(H94="CÉLULA CONSTRUTIVA",SUMIFS($N$8:$N$422,$B$8:$B$422,B94,$H$8:$H$422,"Serviço"),IF(H94="ETAPA",SUMIFS($N$8:$N$422,$B$8:$B$422,B94,$C$8:$C$422,C94,$H$8:$H$422,"Serviço"),IF(H94="SUBETAPA",SUMIFS($N$8:$N$422,$B$8:$B$422,B94,$C$8:$C$422,C94,$D$8:$D$422,D94,$H$8:$H$422,"Serviço"),0)))) | O94: =_xlfn.XLOOKUP($J94,BASES!$A$12:$A$392,BASES!$F$12:$F$392)
A95: =IF($H95="UNIDADE CONSTRUTIVA",OFFSET(A95,-1,0)+1,LARGE(A$3:A94,1)) | B95: =IF(H95="UNIDADE CONSTRUTIVA",0,IF(H95="CÉLULA CONSTRUTIVA",OFFSET(B95,-1,0)+1,OFFSET(B95,-1,0))) | C95: =IF(H95="CÉLULA CONSTRUTIVA",0,IF(H95="ETAPA",OFFSET(C95,-1,0)+1,OFFSET(C95,-1,0))) | D95: =IF(H95="ETAPA",0,IF(H95="SUBETAPA",OFFSET(D95,-1,0)+1,OFFSET(D95,-1,0))) | E95: =IF(H95="Subetapa",0,IF(H95="serviço",OFFSET(E95,-1,0)+1,OFFSET(E95,-1,0))) | H95: SERVIÇO | I95: =IF(H95="Unidade Construtiva",TEXT(A95,"00"),IF(H95="Célula Construtiva",TEXT(B95,"00"),IF(H95="Etapa",CONCATENATE(TEXT(B95,"00"),".",TEXT(C95,"000")),IF(H95="Subetapa",CONCATENATE(TEXT(B95,"00"),".",TEXT(C95,"000"),".",TEXT(D95,"000")),IF(H95="Serviço",CONCATENATE(TEXT(B95,"00"),".",TEXT(C95,"000"),".",TEXT(D95,"000"),".",TEXT(E95,"000")),""))))) | J95: Consumos gerais: Consumo de cópias | K95: =_xlfn.XLOOKUP($J95,BASES!$A$12:$A$392,BASES!$C$12:$C$392) | L95: =_xlfn.XLOOKUP($J95,BASES!$A$12:$A$392,BASES!$D$12:$D$392) | M95: =_xlfn.XLOOKUP($J95,BASES!$A$1:$A$2289,BASES!$E$1:$E$2289) | N95: =IF(H95="Serviço",M95*L95,IF(H95="CÉLULA CONSTRUTIVA",SUMIFS($N$8:$N$422,$B$8:$B$422,B95,$H$8:$H$422,"Serviço"),IF(H95="ETAPA",SUMIFS($N$8:$N$422,$B$8:$B$422,B95,$C$8:$C$422,C95,$H$8:$H$422,"Serviço"),IF(H95="SUBETAPA",SUMIFS($N$8:$N$422,$B$8:$B$422,B95,$C$8:$C$422,C95,$D$8:$D$422,D95,$H$8:$H$422,"Serviço"),0)))) | O95: =_xlfn.XLOOKUP($J95,BASES!$A$12:$A$392,BASES!$F$12:$F$392)
A96: =IF($H96="UNIDADE CONSTRUTIVA",OFFSET(A96,-1,0)+1,LARGE(A$3:A95,1)) | B96: =IF(H96="UNIDADE CONSTRUTIVA",0,IF(H96="CÉLULA CONSTRUTIVA",OFFSET(B96,-1,0)+1,OFFSET(B96,-1,0))) | C96: =IF(H96="CÉLULA CONSTRUTIVA",0,IF(H96="ETAPA",OFFSET(C96,-1,0)+1,OFFSET(C96,-1,0))) | D96: =IF(H96="ETAPA",0,IF(H96="SUBETAPA",OFFSET(D96,-1,0)+1,OFFSET(D96,-1,0))) | E96: =IF(H96="Subetapa",0,IF(H96="serviço",OFFSET(E96,-1,0)+1,OFFSET(E96,-1,0))) | H96: SERVIÇO | I96: =IF(H96="Unidade Construtiva",TEXT(A96,"00"),IF(H96="Célula Construtiva",TEXT(B96,"00"),IF(H96="Etapa",CONCATENATE(TEXT(B96,"00"),".",TEXT(C96,"000")),IF(H96="Subetapa",CONCATENATE(TEXT(B96,"00"),".",TEXT(C96,"000"),".",TEXT(D96,"000")),IF(H96="Serviço",CONCATENATE(TEXT(B96,"00"),".",TEXT(C96,"000"),".",TEXT(D96,"000"),".",TEXT(E96,"000")),""))))) | J96: Consumos gerais: Gerenciamento Eletrônico | K96: =_xlfn.XLOOKUP($J96,BASES!$A$12:$A$392,BASES!$C$12:$C$392) | L96: =_xlfn.XLOOKUP($J96,BASES!$A$12:$A$392,BASES!$D$12:$D$392) | M96: =_xlfn.XLOOKUP($J96,BASES!$A$1:$A$2289,BASES!$E$1:$E$2289) | N96: =IF(H96="Serviço",M96*L96,IF(H96="CÉLULA CONSTRUTIVA",SUMIFS($N$8:$N$422,$B$8:$B$422,B96,$H$8:$H$422,"Serviço"),IF(H96="ETAPA",SUMIFS($N$8:$N$422,$B$8:$B$422,B96,$C$8:$C$422,C96,$H$8:$H$422,"Serviço"),IF(H96="SUBETAPA",SUMIFS($N$8:$N$422,$B$8:$B$422,B96,$C$8:$C$422,C96,$D$8:$D$422,D96,$H$8:$H$422,"Serviço"),0)))) | O96: =_xlfn.XLOOKUP($J96,BASES!$A$12:$A$392,BASES!$F$12:$F$392)
A97: =IF($H97="UNIDADE CONSTRUTIVA",OFFSET(A97,-1,0)+1,LARGE(A$3:A96,1)) | B97: =IF(H97="UNIDADE CONSTRUTIVA",0,IF(H97="CÉLULA CONSTRUTIVA",OFFSET(B97,-1,0)+1,OFFSET(B97,-1,0))) | C97: =IF(H97="CÉLULA CONSTRUTIVA",0,IF(H97="ETAPA",OFFSET(C97,-1,0)+1,OFFSET(C97,-1,0))) | D97: =IF(H97="ETAPA",0,IF(H97="SUBETAPA",OFFSET(D97,-1,0)+1,OFFSET(D97,-1,0))) | E97: =IF(H97="Subetapa",0,IF(H97="serviço",OFFSET(E97,-1,0)+1,OFFSET(E97,-1,0))) | H97: SERVIÇO | I97: =IF(H97="Unidade Construtiva",TEXT(A97,"00"),IF(H97="Célula Construtiva",TEXT(B97,"00"),IF(H97="Etapa",CONCATENATE(TEXT(B97,"00"),".",TEXT(C97,"000")),IF(H97="Subetapa",CONCATENATE(TEXT(B97,"00"),".",TEXT(C97,"000"),".",TEXT(D97,"000")),IF(H97="Serviço",CONCATENATE(TEXT(B97,"00"),".",TEXT(C97,"000"),".",TEXT(D97,"000"),".",TEXT(E97,"000")),""))))) | J97: Consumos gerais: Despesas com vizinhos | K97: =_xlfn.XLOOKUP($J97,BASES!$A$12:$A$392,BASES!$C$12:$C$392) | L97: =_xlfn.XLOOKUP($J97,BASES!$A$12:$A$392,BASES!$D$12:$D$392) | M97: =_xlfn.XLOOKUP($J97,BASES!$A$1:$A$2289,BASES!$E$1:$E$2289) | N97: =IF(H97="Serviço",M97*L97,IF(H97="CÉLULA CONSTRUTIVA",SUMIFS($N$8:$N$422,$B$8:$B$422,B97,$H$8:$H$422,"Serviço"),IF(H97="ETAPA",SUMIFS($N$8:$N$422,$B$8:$B$422,B97,$C$8:$C$422,C97,$H$8:$H$422,"Serviço"),IF(H97="SUBETAPA",SUMIFS($N$8:$N$422,$B$8:$B$422,B97,$C$8:$C$422,C97,$D$8:$D$422,D97,$H$8:$H$422,"Serviço"),0)))) | O97: =_xlfn.XLOOKUP($J97,BASES!$A$12:$A$392,BASES!$F$12:$F$392)
A98: =IF($H98="UNIDADE CONSTRUTIVA",OFFSET(A98,-1,0)+1,LARGE(A$3:A97,1)) | B98: =IF(H98="UNIDADE CONSTRUTIVA",0,IF(H98="CÉLULA CONSTRUTIVA",OFFSET(B98,-1,0)+1,OFFSET(B98,-1,0))) | C98: =IF(H98="CÉLULA CONSTRUTIVA",0,IF(H98="ETAPA",OFFSET(C98,-1,0)+1,OFFSET(C98,-1,0))) | D98: =IF(H98="ETAPA",0,IF(H98="SUBETAPA",OFFSET(D98,-1,0)+1,OFFSET(D98,-1,0))) | E98: =IF(H98="Subetapa",0,IF(H98="serviço",OFFSET(E98,-1,0)+1,OFFSET(E98,-1,0))) | H98: SERVIÇO | I98: =IF(H98="Unidade Construtiva",TEXT(A98,"00"),IF(H98="Célula Construtiva",TEXT(B98,"00"),IF(H98="Etapa",CONCATENATE(TEXT(B98,"00"),".",TEXT(C98,"000")),IF(H98="Subetapa",CONCATENATE(TEXT(B98,"00"),".",TEXT(C98,"000"),".",TEXT(D98,"000")),IF(H98="Serviço",CONCATENATE(TEXT(B98,"00"),".",TEXT(C98,"000"),".",TEXT(D98,"000"),".",TEXT(E98,"000")),""))))) | J98: Consumos gerais: Esgotamento de sistema sanitário temporário | K98: =_xlfn.XLOOKUP($J98,BASES!$A$12:$A$392,BASES!$C$12:$C$392) | L98: =_xlfn.XLOOKUP($J98,BASES!$A$12:$A$392,BASES!$D$12:$D$392) | M98: =_xlfn.XLOOKUP($J98,BASES!$A$1:$A$2289,BASES!$E$1:$E$2289) | N98: =IF(H98="Serviço",M98*L98,IF(H98="CÉLULA CONSTRUTIVA",SUMIFS($N$8:$N$422,$B$8:$B$422,B98,$H$8:$H$422,"Serviço"),IF(H98="ETAPA",SUMIFS($N$8:$N$422,$B$8:$B$422,B98,$C$8:$C$422,C98,$H$8:$H$422,"Serviço"),IF(H98="SUBETAPA",SUMIFS($N$8:$N$422,$B$8:$B$422,B98,$C$8:$C$422,C98,$D$8:$D$422,D98,$H$8:$H$422,"Serviço"),0)))) | O98: =_xlfn.XLOOKUP($J98,BASES!$A$12:$A$392,BASES!$F$12:$F$392)
... A100: =IF($H100="UNIDADE CONSTRUTIVA",OFFSET(A100,-1,0)+1,LARGE(A$3:A99,1)) | B100: =IF(H100="UNIDADE CONSTRUTIVA",0,IF(H100="CÉLULA CONSTRUTIVA",OFFSET(B100,-1,0)+1,OFFSET(B100,-1,0))) | C100: =IF(H100="CÉLULA CONSTRUTIVA",0,IF(H100="ETAPA",OFFSET(C100,-1,0)+1,OFFSET(C100,-1,0))) | D100: =IF(H100="ETAPA",0,IF(H100="SUBETAPA",OFFSET(D100,-1,0)+1,OFFSET(D100,-1,0))) | E100: =IF(H100="Subetapa",0,IF(H100="serviço",OFFSET(E100,-1,0)+1,OFFSET(E100,-1,0))) | H100: SERVIÇO | I100: =IF(H100="Unidade Construtiva",TEXT(A100,"00"),IF(H100="Célula Construtiva",TEXT(B100,"00"),IF(H100="Etapa",CONCATENATE(TEXT(B100,"00"),".",TEXT(C100,"000")),IF(H100="Subetapa",CONCATENATE(TEXT(B100,"00"),".",TEXT(C100,"000"),".",TEXT(D100,"000")),IF(H100="Serviço",CONCATENATE(TEXT(B100,"00"),".",TEXT(C100,"000"),".",TEXT(D100,"000"),".",TEXT(E100,"000")),""))))) | J100: Equipamentos de escritorio | K100: =_xlfn.XLOOKUP($J100,BASES!$A$12:$A$392,BASES!$C$12:$C$392) | L100: =_xlfn.XLOOKUP($J100,BASES!$A$12:$A$392,BASES!$D$12:$D$392) | M100: =_xlfn.XLOOKUP($J100,BASES!$A$1:$A$2289,BASES!$E$1:$E$2289) | N100: =IF(H100="Serviço",M100*L100,IF(H100="CÉLULA CONSTRUTIVA",SUMIFS($N$8:$N$422,$B$8:$B$422,B100,$H$8:$H$422,"Serviço"),IF(H100="ETAPA",SUMIFS($N$8:$N$422,$B$8:$B$422,B100,$C$8:$C$422,C100,$H$8:$H$422,"Serviço"),IF(H100="SUBETAPA",SUMIFS($N$8:$N$422,$B$8:$B$422,B100,$C$8:$C$422,C100,$D$8:$D$422,D100,$H$8:$H$422,"Serviço"),0)))) | O100: =_xlfn.XLOOKUP($J100,BASES!$A$12:$A$392,BASES!$F$12:$F$392)
A101: =IF($H101="UNIDADE CONSTRUTIVA",OFFSET(A101,-1,0)+1,LARGE(A$3:A100,1)) | B101: =IF(H101="UNIDADE CONSTRUTIVA",0,IF(H101="CÉLULA CONSTRUTIVA",OFFSET(B101,-1,0)+1,OFFSET(B101,-1,0))) | C101: =IF(H101="CÉLULA CONSTRUTIVA",0,IF(H101="ETAPA",OFFSET(C101,-1,0)+1,OFFSET(C101,-1,0))) | D101: =IF(H101="ETAPA",0,IF(H101="SUBETAPA",OFFSET(D101,-1,0)+1,OFFSET(D101,-1,0))) | E101: =IF(H101="Subetapa",0,IF(H101="serviço",OFFSET(E101,-1,0)+1,OFFSET(E101,-1,0))) | H101: SERVIÇO | I101: =IF(H101="Unidade Construtiva",TEXT(A101,"00"),IF(H101="Célula Construtiva",TEXT(B101,"00"),IF(H101="Etapa",CONCATENATE(TEXT(B101,"00"),".",TEXT(C101,"000")),IF(H101="Subetapa",CONCATENATE(TEXT(B101,"00"),".",TEXT(C101,"000"),".",TEXT(D101,"000")),IF(H101="Serviço",CONCATENATE(TEXT(B101,"00"),".",TEXT(C101,"000"),".",TEXT(D101,"000"),".",TEXT(E101,"000")),""))))) | J101: Sinalizacao Plaqueiro | K101: =_xlfn.XLOOKUP($J101,BASES!$A$12:$A$392,BASES!$C$12:$C$392) | L101: =_xlfn.XLOOKUP($J101,BASES!$A$12:$A$392,BASES!$D$12:$D$392) | M101: =_xlfn.XLOOKUP($J101,BASES!$A$1:$A$2289,BASES!$E$1:$E$2289) | N101: =IF(H101="Serviço",M101*L101,IF(H101="CÉLULA CONSTRUTIVA",SUMIFS($N$8:$N$422,$B$8:$B$422,B101,$H$8:$H$422,"Serviço"),IF(H101="ETAPA",SUMIFS($N$8:$N$422,$B$8:$B$422,B101,$C$8:$C$422,C101,$H$8:$H$422,"Serviço"),IF(H101="SUBETAPA",SUMIFS($N$8:$N$422,$B$8:$B$422,B101,$C$8:$C$422,C101,$D$8:$D$422,D101,$H$8:$H$422,"Serviço"),0)))) | O101: Estimado - Placa indicativa fixada na estrutura por pregos + Sinalização com fita fixada em cone
A102: =IF($H102="UNIDADE CONSTRUTIVA",OFFSET(A102,-1,0)+1,LARGE(A$3:A101,1)) | B102: =IF(H102="UNIDADE CONSTRUTIVA",0,IF(H102="CÉLULA CONSTRUTIVA",OFFSET(B102,-1,0)+1,OFFSET(B102,-1,0))) | C102: =IF(H102="CÉLULA CONSTRUTIVA",0,IF(H102="ETAPA",OFFSET(C102,-1,0)+1,OFFSET(C102,-1,0))) | D102: =IF(H102="ETAPA",0,IF(H102="SUBETAPA",OFFSET(D102,-1,0)+1,OFFSET(D102,-1,0))) | E102: =IF(H102="Subetapa",0,IF(H102="serviço",OFFSET(E102,-1,0)+1,OFFSET(E102,-1,0))) | H102: SUBETAPA | I102: =IF(H102="Unidade Construtiva",TEXT(A102,"00"),IF(H102="Célula Construtiva",TEXT(B102,"00"),IF(H102="Etapa",CONCATENATE(TEXT(B102,"00"),".",TEXT(C102,"000")),IF(H102="Subetapa",CONCATENATE(TEXT(B102,"00"),".",TEXT(C102,"000"),".",TEXT(D102,"000")),IF(H102="Serviço",CONCATENATE(TEXT(B102,"00"),".",TEXT(C102,"000"),".",TEXT(D102,"000"),".",TEXT(E102,"000")),""))))) | J102: Manutenção de Canteiro de Obra | N102: =IF(H102="Serviço",M102*L102,IF(H102="CÉLULA CONSTRUTIVA",SUMIFS($N$8:$N$422,$B$8:$B$422,B102,$H$8:$H$422,"Serviço"),IF(H102="ETAPA",SUMIFS($N$8:$N$422,$B$8:$B$422,B102,$C$8:$C$422,C102,$H$8:$H$422,"Serviço"),IF(H102="SUBETAPA",SUMIFS($N$8:$N$422,$B$8:$B$422,B102,$C$8:$C$422,C102,$D$8:$D$422,D102,$H$8:$H$422,"Serviço"),0))))
A103: =IF($H103="UNIDADE CONSTRUTIVA",OFFSET(A103,-1,0)+1,LARGE(A$3:A102,1)) | B103: =IF(H103="UNIDADE CONSTRUTIVA",0,IF(H103="CÉLULA CONSTRUTIVA",OFFSET(B103,-1,0)+1,OFFSET(B103,-1,0))) | C103: =IF(H103="CÉLULA CONSTRUTIVA",0,IF(H103="ETAPA",OFFSET(C103,-1,0)+1,OFFSET(C103,-1,0))) | D103: =IF(H103="ETAPA",0,IF(H103="SUBETAPA",OFFSET(D103,-1,0)+1,OFFSET(D103,-1,0))) | E103: =IF(H103="Subetapa",0,IF(H103="serviço",OFFSET(E103,-1,0)+1,OFFSET(E103,-1,0))) | H103: SERVIÇO | I103: =IF(H103="Unidade Construtiva",TEXT(A103,"00"),IF(H103="Célula Construtiva",TEXT(B103,"00"),IF(H103="Etapa",CONCATENATE(TEXT(B103,"00"),".",TEXT(C103,"000")),IF(H103="Subetapa",CONCATENATE(TEXT(B103,"00"),".",TEXT(C103,"000"),".",TEXT(D103,"000")),IF(H103="Serviço",CONCATENATE(TEXT(B103,"00"),".",TEXT(C103,"000"),".",TEXT(D103,"000"),".",TEXT(E103,"000")),""))))) | J103: Despesas de manutenção: Manutenção provisória do canteiro | K103: =_xlfn.XLOOKUP($J103,BASES!$A$12:$A$392,BASES!$C$12:$C$392) | L103: =_xlfn.XLOOKUP($J103,BASES!$A$12:$A$392,BASES!$D$12:$D$392) | M103: =_xlfn.XLOOKUP($J103,BASES!$A$1:$A$2289,BASES!$E$1:$E$2289) | N103: =IF(H103="Serviço",M103*L103,IF(H103="CÉLULA CONSTRUTIVA",SUMIFS($N$8:$N$422,$B$8:$B$422,B103,$H$8:$H$422,"Serviço"),IF(H103="ETAPA",SUMIFS($N$8:$N$422,$B$8:$B$422,B103,$C$8:$C$422,C103,$H$8:$H$422,"Serviço"),IF(H103="SUBETAPA",SUMIFS($N$8:$N$422,$B$8:$B$422,B103,$C$8:$C$422,C103,$D$8:$D$422,D103,$H$8:$H$422,"Serviço"),0)))) | O103: =_xlfn.XLOOKUP($J103,BASES!$A$12:$A$392,BASES!$F$12:$F$392)
A104: =IF($H104="UNIDADE CONSTRUTIVA",OFFSET(A104,-1,0)+1,LARGE(A$3:A103,1)) | B104: =IF(H104="UNIDADE CONSTRUTIVA",0,IF(H104="CÉLULA CONSTRUTIVA",OFFSET(B104,-1,0)+1,OFFSET(B104,-1,0))) | C104: =IF(H104="CÉLULA CONSTRUTIVA",0,IF(H104="ETAPA",OFFSET(C104,-1,0)+1,OFFSET(C104,-1,0))) | D104: =IF(H104="ETAPA",0,IF(H104="SUBETAPA",OFFSET(D104,-1,0)+1,OFFSET(D104,-1,0))) | E104: =IF(H104="Subetapa",0,IF(H104="serviço",OFFSET(E104,-1,0)+1,OFFSET(E104,-1,0))) | H104: SERVIÇO | I104: =IF(H104="Unidade Construtiva",TEXT(A104,"00"),IF(H104="Célula Construtiva",TEXT(B104,"00"),IF(H104="Etapa",CONCATENATE(TEXT(B104,"00"),".",TEXT(C104,"000")),IF(H104="Subetapa",CONCATENATE(TEXT(B104,"00"),".",TEXT(C104,"000"),".",TEXT(D104,"000")),IF(H104="Serviço",CONCATENATE(TEXT(B104,"00"),".",TEXT(C104,"000"),".",TEXT(D104,"000"),".",TEXT(E104,"000")),""))))) | J104: Despesas de manutenção: Manutenção provisória elétrica | K104: =_xlfn.XLOOKUP($J104,BASES!$A$12:$A$392,BASES!$C$12:$C$392) | L104: =_xlfn.XLOOKUP($J104,BASES!$A$12:$A$392,BASES!$D$12:$D$392) | M104: =_xlfn.XLOOKUP($J104,BASES!$A$1:$A$2289,BASES!$E$1:$E$2289) | N104: =IF(H104="Serviço",M104*L104,IF(H104="CÉLULA CONSTRUTIVA",SUMIFS($N$8:$N$422,$B$8:$B$422,B104,$H$8:$H$422,"Serviço"),IF(H104="ETAPA",SUMIFS($N$8:$N$422,$B$8:$B$422,B104,$C$8:$C$422,C104,$H$8:$H$422,"Serviço"),IF(H104="SUBETAPA",SUMIFS($N$8:$N$422,$B$8:$B$422,B104,$C$8:$C$422,C104,$D$8:$D$422,D104,$H$8:$H$422,"Serviço"),0)))) | O104: =_xlfn.XLOOKUP($J104,BASES!$A$12:$A$392,BASES!$F$12:$F$392)
A105: =IF($H105="UNIDADE CONSTRUTIVA",OFFSET(A105,-1,0)+1,LARGE(A$3:A104,1)) | B105: =IF(H105="UNIDADE CONSTRUTIVA",0,IF(H105="CÉLULA CONSTRUTIVA",OFFSET(B105,-1,0)+1,OFFSET(B105,-1,0))) | C105: =IF(H105="CÉLULA CONSTRUTIVA",0,IF(H105="ETAPA",OFFSET(C105,-1,0)+1,OFFSET(C105,-1,0))) | D105: =IF(H105="ETAPA",0,IF(H105="SUBETAPA",OFFSET(D105,-1,0)+1,OFFSET(D105,-1,0))) | E105: =IF(H105="Subetapa",0,IF(H105="serviço",OFFSET(E105,-1,0)+1,OFFSET(E105,-1,0))) | H105: SERVIÇO | I105: =IF(H105="Unidade Construtiva",TEXT(A105,"00"),IF(H105="Célula Construtiva",TEXT(B105,"00"),IF(H105="Etapa",CONCATENATE(TEXT(B105,"00"),".",TEXT(C105,"000")),IF(H105="Subetapa",CONCATENATE(TEXT(B105,"00"),".",TEXT(C105,"000"),".",TEXT(D105,"000")),IF(H105="Serviço",CONCATENATE(TEXT(B105,"00"),".",TEXT(C105,"000"),".",TEXT(D105,"000"),".",TEXT(E105,"000")),""))))) | J105: Despesas de manutenção: Manutenção provisória hidrossanitária | K105: =_xlfn.XLOOKUP($J105,BASES!$A$12:$A$392,BASES!$C$12:$C$392) | L105: =_xlfn.XLOOKUP($J105,BASES!$A$12:$A$392,BASES!$D$12:$D$392) | M105: =_xlfn.XLOOKUP($J105,BASES!$A$1:$A$2289,BASES!$E$1:$E$2289) | N105: =IF(H105="Serviço",M105*L105,IF(H105="CÉLULA CONSTRUTIVA",SUMIFS($N$8:$N$422,$B$8:$B$422,B105,$H$8:$H$422,"Serviço"),IF(H105="ETAPA",SUMIFS($N$8:$N$422,$B$8:$B$422,B105,$C$8:$C$422,C105,$H$8:$H$422,"Serviço"),IF(H105="SUBETAPA",SUMIFS($N$8:$N$422,$B$8:$B$422,B105,$C$8:$C$422,C105,$D$8:$D$422,D105,$H$8:$H$422,"Serviço"),0)))) | O105: =_xlfn.XLOOKUP($J105,BASES!$A$12:$A$392,BASES!$F$12:$F$392)
A106: =IF($H106="UNIDADE CONSTRUTIVA",OFFSET(A106,-1,0)+1,LARGE(A$3:A105,1)) | B106: =IF(H106="UNIDADE CONSTRUTIVA",0,IF(H106="CÉLULA CONSTRUTIVA",OFFSET(B106,-1,0)+1,OFFSET(B106,-1,0))) | C106: =IF(H106="CÉLULA CONSTRUTIVA",0,IF(H106="ETAPA",OFFSET(C106,-1,0)+1,OFFSET(C106,-1,0))) | D106: =IF(H106="ETAPA",0,IF(H106="SUBETAPA",OFFSET(D106,-1,0)+1,OFFSET(D106,-1,0))) | E106: =IF(H106="Subetapa",0,IF(H106="serviço",OFFSET(E106,-1,0)+1,OFFSET(E106,-1,0))) | H106: SERVIÇO | I106: =IF(H106="Unidade Construtiva",TEXT(A106,"00"),IF(H106="Célula Construtiva",TEXT(B106,"00"),IF(H106="Etapa",CONCATENATE(TEXT(B106,"00"),".",TEXT(C106,"000")),IF(H106="Subetapa",CONCATENATE(TEXT(B106,"00"),".",TEXT(C106,"000"),".",TEXT(D106,"000")),IF(H106="Serviço",CONCATENATE(TEXT(B106,"00"),".",TEXT(C106,"000"),".",TEXT(D106,"000"),".",TEXT(E106,"000")),""))))) | J106: Despesas de manutenção: Manutenção provisória vigilância e acessos | K106: =_xlfn.XLOOKUP($J106,BASES!$A$12:$A$392,BASES!$C$12:$C$392) | L106: =_xlfn.XLOOKUP($J106,BASES!$A$12:$A$392,BASES!$D$12:$D$392) | M106: =_xlfn.XLOOKUP($J106,BASES!$A$1:$A$2289,BASES!$E$1:$E$2289) | N106: =IF(H106="Serviço",M106*L106,IF(H106="CÉLULA CONSTRUTIVA",SUMIFS($N$8:$N$422,$B$8:$B$422,B106,$H$8:$H$422,"Serviço"),IF(H106="ETAPA",SUMIFS($N$8:$N$422,$B$8:$B$422,B106,$C$8:$C$422,C106,$H$8:$H$422,"Serviço"),IF(H106="SUBETAPA",SUMIFS($N$8:$N$422,$B$8:$B$422,B106,$C$8:$C$422,C106,$D$8:$D$422,D106,$H$8:$H$422,"Serviço"),0)))) | O106: =_xlfn.XLOOKUP($J106,BASES!$A$12:$A$392,BASES!$F$12:$F$392)
...
