Workbook
Name \0: #REF!
Name \0: #REF!
Name \0: #REF!
Name \0: #REF!
Name \0: #REF!
Name \0: #REF!
Name \0: #REF!
Name \0: #REF!
Name \0: #REF!
Name \0: #REF!
Name \1: #REF!
Name \1: #REF!
Name \1: #REF!
Name \1: #REF!
Name \1: #REF!
Name \1: #REF!
Name \a: #REF!
Name \a: #REF!
Name \a: #REF!
Name \a: #REF!
Name \a: #REF!
Name \a: #REF!
Name \a: #REF!
Name \a: #REF!
Name \a: #REF!
Name \b: #REF!
Name \b: #REF!
Name \b: #REF!
Name \b: #REF!
Name \c: #REF!
Name \c: #REF!
Name \c: #REF!
Name \c: #REF!
Name \d: #REF!
Name \d: #REF!
Name \d: #REF!
Name \d: #REF!
Name \e: #REF!
Name \e: #REF!
Name \e: #REF!
Name \e: #REF!
Name \i: #REF!
Name \i: #REF!
Name \i: #REF!
Name \i: #REF!
Name \J: #REF!
Name \J: #REF!
Name \J: #REF!
Name \J: #REF!
Name \k: #REF!
Name \k: #REF!
Name \k: #REF!
Name \k: #REF!
Name \k: #REF!
Name \l: #N/A
Name \m: #REF!
Name \m: #REF!
Name \m: #REF!
Name \m: #REF!
Name \m: #REF!

Sheet Obra 
C1: Projeto | D1: Brisa da armação
C2: Empresa | D2: HACASA
C3: Revisão | D3: R00 - Letícia
A4: QUADRO DE ÁREAS
B6: Descrição | C6: Unidade | E6: Quantidade | G6: Imagens
B7: MESES DE OBRA | C7: MÊS | E7: 48
B8: ÁREA DO TERRENO | C8: M² | E8: 1410.3
B9: ÁREA CONSTRUÍDA | C9: M² | E9: =SUM($E$15:$E$25) -> 12828.33
B10: NÚMERO DE UNIDADES HABITACIONAIS | C10: UN | E10: 117
B11: NÚMERO DE UNIDADES COMERCIAIS | C11: UN | E11: 4
B12: ÁREA PRIVATIVA | C12: M² | E12: 7101.75
B13: NÚMERO DE PAVIMENTOS | C13: UN | E13: 20
B15: Térreo | C15: M² | E15: 918.44
B16: Garagem G1 | C16: M² | E16: 1045.47
B17: Garagem G2 | C17: M² | E17: 1045.47
B18: Garagem G3 | C18: M² | E18: 1045.47
B19: Garagem G4 | C19: M² | E19: 1051.41
B20: Tipo 01 (1x) | C20: M² | E20: 545.33
B21: Tipo 02 (11x) | C21: M² | E21: 5998.63
B22: Tipo 03 (01x) | C22: M² | E22: 557.79
... B25: Caixa D'água | C25: M² | E25: 40.32
B31: ETAPA | C31: VALOR ORÇADO | D31: % | E31: VALOR / m²
B32: GERENCIAMENTO TÉCNICO E ADMINISTRATIVO | C32: 4609930 | D32: =C32/C$53 -> 0.10902428 | E32: =C32/$E$9 -> 359.35543
B33: MOVIMENTAÇÃO DE TERRA | C33: 231016.84 | D33: =C33/C$53 -> 0.0054635201 | E33: =C33/$E$9 -> 18.008333
B34: INFRAESTRUTURA | C34: 2489515.3 | D34: =C34/C$53 -> 0.058876733 | E34: =C34/$E$9 -> 194.06386
B35: SUPRAESTRUTURA | C35: 8183443.8 | D35: =C35/C$53 -> 0.19353745 | E35: =C35/$E$9 -> 637.91965
B36: ALVENARIA | C36: 1838976.9 | D36: =C36/C$53 -> 0.04349158 | E36: =C36/$E$9 -> 143.35279
B37: INSTALAÇÕES ELÉTRICAS, HIDRÁULICAS, GLP E PREVENTIVAS | C37: 2423175.5 | D37: =C37/C$53 -> 0.057307806 | E37: =C37/$E$9 -> 188.89252
B38: CLIMATIZAÇÃO, EXAUSTÃO MECÂNICA E PRESSURIZAÇÃO | C38: 874867.45 | D38: =C38/C$53 -> 0.020690509 | E38: =C38/$E$9 -> 68.198078
B39: REVESTIMENTOS ARGAMASSADOS PISO E PAREDE | C39: 2123455.5 | D39: =C39/C$53 -> 0.050219464 | E39: =C39/$E$9 -> 165.5286
B40: REVESTIMENTOS ARGAMASSADOS TETO | C40: 767.25885 | D40: =C40/C$53 -> 1.8145579e-05 | E40: =C40/$E$9 -> 0.059809722
B41: IMPERMEABILIZAÇÃO | C41: 1217962.5 | D41: =C41/C$53 -> 0.028804666 | E41: =C41/$E$9 -> 94.943187
B42: ACABAMENTOS INTERNOS EM PAREDE | C42: 421316.73 | D42: =C42/C$53 -> 0.0099640894 | E42: =C42/$E$9 -> 32.842679
B43: ACABAMENTOS EM PISOS E PAVIMENTAÇÕES | C43: 1609363.8 | D43: =C43/C$53 -> 0.038061258 | E43: =C43/$E$9 -> 125.45388
... B52: IMPREVISTOS | C52: 738697.75 | D52: =C52/C$53 -> 0.017470112 | E52: =C52/$E$9 -> 57.583314
B53: TOTAL | C53: =SUM(C32:C52) -> 42283515 | D53: =SUM(D32:D52) -> 1 | E53: =SUM(E32:E52) -> 3296.1044
B54: CUB/SC | C54: 2863.73 | D54: 45597 | E54: =ROUNDUP(+E53/C54,2)&" CUB" -> 1,16 CUB

Sheet EPCs
A1: Obra | B1: ='Obra '!D1 -> Brisa da armação
A2: Empresa | B2: ='Obra '!D2 -> HACASA
A3: Revisão | B3: ='Obra '!D3 -> R00 - Letícia | K3: Guia pavimentos
A4: Equipamentos de proteção coletiva | K4: Pavimento | L4: Área | M4: Perímetro | N4: Pé Direito
A5: Bandejas de proteção
B7: Descrição | C7: Unidade | D7: Quantidade | F7: Imagem formulário
B8: Perímetro de projeção embasamento | C8: m
B9: Perímetro de projeção Primária tipo 1 | C9: m
B10: Perímetro de projeção torre tipo 1 | C10: m
B11: Bandeja de proteção primária | C11: m | D11: =D8+D9 -> 0
B12: Bandeja de proteção secundária | C12: m | D12: =D10 -> 0
B13: * Considerado as informações do Projeto de Segurança
A14: Guarda - corpo de vãos
B16: Descrição | C16: Unidade | D16: Quantidade | F16: Imagem formulário
B17: Perímetro de vãos | C17: m
B18: Guarda - corpo de vãos | C18: m | D18: =D17 -> 0
A20: Guarda - corpo de desforma
B22: Descrição | C22: Unidade | D22: Quantidade | F22: Imagem formulário
B23: Perímetro de projeção da torre | C23: m | D23: =M22 -> 0
B24: Repetições de pavimentos** | C24: un | D24: 4
B25: Proteção de periferia pós desforma torre | C25: m | D25: =(D23*D24) -> 0
A27: Fechamento removível de vãos em madeira
B29: Descrição | C29: Unidade | D29: Quantidade | F29: Imagem formulário
B30: Área das portas de elevadores | C30: m2
B31: Quantidade de elevadores | C31: un
B32: Quantidade de portas de elevadores | C32: un
B33: Fechamento removível de vãos em madeira | C33: m2 | D33: =D30*D32 -> 0
B34: Área das portas de aptos | C34: m2
B35: Quantidade de aptos | C35: un
B36: =A27 -> Fechamento removível de vãos em madeira | C36: m2 | D36: =D34*D35 -> 0
A38: Tela fachadeira
B40: Descrição | C40: Unidade | D40: Quantidade | F40: Imagem formulário
B41: Area da fachada | C41: m² | D41: =SUMPRODUCT($M$9:$M$22,$N$9:$N$22) -> 0
B42: =A38 -> Tela fachadeira | C42: m2 | D42: =D41 -> 0
A44: SLQA
B46: Descrição | C46: Unidade | D46: Quantidade | F46: Imagem formulário
B47: Perímetro de projeção da torre 1 | C47: m | D47: =$M$22 -> 0
B48: Altura de cobrimento da tela | C48: un | D48: 1
B49: =A44 -> SLQA | C49: m | D49: =D47*D48 -> 0
A52: Tapume
B54: Descrição | C54: Unidade | D54: Quantidade | F54: Imagem formulário
B55: Perímetro de encontro com pavimentação | C55: m
B56: Altura do tapume | C56: m | D56: 2.4
B57: =A52 -> Tapume | C57: m2 | D57: =D56*D55 -> 0
A59: Linha de Vida
B61: Descrição | C61: Unidade | D61: Quantidade | F61: Imagem formulário
B62: Perímetro de Pavimentos | C62: m | D62: =$D$25 -> 0
B63: =A59 -> Linha de Vida | C63: m | D63: =D62 -> 0
A65: Cobertura para Proteção de Pedestres
B67: Descrição | C67: Unidade | D67: Quantidade | F67: Imagem formulário
B68: Perímetro de projeção torre | C68: m
B69: Altura de cobrimento da tela | C69: m
B70: Cobertura para Proteção de Pedestres | C70: m2 | D70: =D68*D69 -> 0

Sheet CANTEIRO
A1: Obra | B1: ='Obra '!D1 -> Brisa da armação
A2: Empresa | B2: ='Obra '!D2 -> HACASA
A3: Revisão | B3: ='Obra '!D3 -> R00 - Letícia | O3: Número de funcionários | S3: Produtividade média (h/m2)
A4: Instalações de canteiro | O4: Área construída | P4: 6601.277 | S4: A.C/prazo | T4: =P4/P5 -> 235.75989
A5: Instalações de canteiro | O5: Prazo da obra | P5: 28 | Q5: meses | S5: Pm | T5: 49 | U5: h/m2
O6: NF | P6: =ROUNDUP((P4*T5)/P5/180,) -> 65 | Q6: funcionários
B7: Descrição | C7: Unidade | D7: Quantidade | O7: Pavimentos | P7: 10
B8: Produtividade média | C8: m2 / mês | D8: ='Obra '!$E$9/'Obra '!$E$7 -> 267.25688 | O8: Equipe administrativa | P8: 5 | Q8: funcionários
B9: Pm | C9: h/m2 | D9: 41
B10: Numero de funcionários | C10: un | D10: =ROUNDUP((D9*'Obra '!$E$9)/'Obra '!$E$7/180,) -> 61
B11: Equipe administrativa | C11: un | D11: 5 | O11: Barracão interno | P11: =450+(P4-13000)/1000*16 -> 347.62043
B12: Pontos de água e esgoto | C12: un | D12: =ROUNDUP($D$10/20,0) -> 4 | E12: 20 funcionários/ponto | O12: Externo | P12: =P11*0.4 -> 139.04817
B13: Bebedouro | C13: un | D13: =ROUNDUP('Obra '!$E$13/5,0) -> 4 | E13: 1 / 5 pav.
B14: Ferramentas | C14: R$ | D14: =800*D10 -> 48800 | E14: 800,00/func. | P14: =SUM(P11:P13) -> 486.6686
B15: EPI | C15: R$ | D15: =500*D10 -> 30500 | E15: 500,00/func.
B16: Banheiro | C16: un | D16: =ROUNDUP($D$10/20,0) -> 4 | E16: 1/20 func | O16: Área refeitório | P16: 1 | Q16: m²/funcionários
P17: =P16*P6 -> 65 | Q17: m²
A18: Mobiliário de canteiro
O19: Área de vestiário | P19: 1.5 | Q19: m²/funcionários
B20: Descrição | C20: Unidade | D20: Quantidade | E20: Custo unitário | F20: Custo total | P20: =P19*P6 -> 97.5 | Q20: m²
B21: Cadeira | C21: un | D21: =ROUNDUP(D11*1.5,) -> 8 | E21: 200 | F21: =D21*E21 -> 1600
B22: Mesa | C22: un | D22: 1 | E22: 1000 | F22: =E22*D22 -> 1000
B23: Ar condicionado | C23: un | D23: 2 | E23: 5000 | F23: =E23*D23 -> 10000
B24: Armário | C24: m | D24: 4 | E24: 900 | F24: =E24*D24 -> 3600
B25: Escrivaninha | C25: un | D25: =D11 -> 5 | E25: 800 | F25: =E25*D25 -> 4000
B26: TOTAL | F26: =F23+F24+F25+F22+F21 -> 20200
B27: Descrição | C27: Unidade | D27: Quantidade | E27: Custo unitário | F27: Custo total
B28: Computador pessoal | C28: un | D28: =D11 -> 5 | E28: 6500 | F28: =D28*E28 -> 32500
B29: Impressora | C29: un | D29: 1 | E29: 2000 | F29: =E29*D29 -> 2000
B30: Roteador | C30: un | D30: 2 | E30: 500 | F30: =E30*D30 -> 1000
B31: TOTAL | F31: =+F28+F29+F30 -> 35500 | O31: Área sanitários | P31: =1*ROUNDUP(P6/20,) -> 4 | Q31: m²
A33: Instalações Provisórias (central de aço, formas, argamassa, almoxarifado geral, construções temporárias) | O33: área lavatório | P33: =0.6*ROUNDUP(P6/20,) -> 2.4 | Q33: m²
O34: Área de chuveiros | P34: =0.8*ROUNDUP(P6/10,) -> 5.6 | Q34: m²
B35: Descrição | C35: Unidade | D35: Será utilizado | E35: Quantidade | F35: Custo unitário | G35: Custo total
B36: Central de aço | C36: m2 | D36: Sim | E36: =IF(D36="Sim",15,0) -> 15 | F36: 115.4849 | G36: =IF(D36="sim",E36*F36,0) -> 1732.2735
B37: Central de fôrmas | C37: m2 | D37: Sim | E37: =IF(D37="Sim",15,0) -> 15 | F37: 115.4849 | G37: =IF(D37="sim",E37*F37,0) -> 1732.2735
B38: Central de Argamassa | C38: m2 | D38: Sim | E38: =IF(D38="Sim",15,0) -> 15 | F38: 115.4849 | G38: =IF(D38="sim",E38*F38,0) -> 1732.2735
B39: Armazenamento de cerâmicas* | C39: m2 | D39: Sim | E39: =IF(D39="não",0,ROUNDUP(3*'Obra '!$E$10/COUNTIFS($D$39:$D$47,"Sim"),)) -> 51 | F39: 201.22489 | G39: =IF(D39="sim",E39*F39,0) -> 10262.469
B40: Armazenamento de placas degesso* | C40: m2 | D40: Não | E40: =IF(D40="não",0,ROUNDUP(3*'Obra '!$E$10/COUNTIFS($D$39:$D$47,"Sim"),)) -> 0 | F40: 201.22489 | G40: =IF(D40="sim",E40*F40,0) -> 0
B41: Armazenamento de blocos* | C41: m2 | D41: Sim | E41: =IF(D41="não",0,ROUNDUP(3*'Obra '!$E$10/COUNTIFS($D$39:$D$47,"Sim"),)) -> 51 | F41: 201.22489 | G41: =IF(D41="sim",E41*F41,0) -> 10262.469
B42: Armazenamento de contramarcos* | C42: m2 | D42: Sim | E42: =IF(D42="não",0,ROUNDUP(3*'Obra '!$E$10/COUNTIFS($D$39:$D$47,"Sim"),)) -> 51 | F42: 201.22489 | G42: =IF(D42="sim",E42*F42,0) -> 10262.469
B43: Armazenamento de portas e rodapés* | C43: m2 | D43: Sim | E43: =IF(D43="não",0,ROUNDUP(3*'Obra '!$E$10/COUNTIFS($D$39:$D$47,"Sim"),)) -> 51 | F43: 201.22489 | G43: =IF(D43="sim",E43*F43,0) -> 10262.469
B44: Armazenamento de esquadrias* | C44: m2 | D44: Não | E44: =IF(D44="não",0,ROUNDUP(3*'Obra '!$E$10/COUNTIFS($D$39:$D$47,"Sim"),)) -> 0 | F44: 201.22489 | G44: =IF(D44="sim",E44*F44,0) -> 0
B45: Armazenamento de instalações complementares* | C45: m2 | D45: Sim | E45: =IF(D45="não",0,ROUNDUP(3*'Obra '!$E$10/COUNTIFS($D$39:$D$47,"Sim"),)) -> 51 | F45: 201.22489 | G45: =IF(D45="sim",E45*F45,0) -> 10262.469
B46: Armazenamento para estoque geral* | C46: m2 | D46: Sim | E46: =IF(D46="não",0,ROUNDUP(3*'Obra '!$E$10/COUNTIFS($D$39:$D$47,"Sim"),)) -> 51 | F46: 201.22489 | G46: =IF(D46="sim",E46*F46,0) -> 10262.469
B47: Construções temporárias | C47: m2 | D47: Sim | E47: =IF(D47="não",0,ROUNDUP(3*'Obra '!$E$10/COUNTIFS($D$39:$D$47,"Sim"),)) -> 51 | F47: 272.8753 | G47: =IF(D47="sim",E47*F47,0) -> 13916.64
B48: Almoxarifado geral | C48: m2 | D48: Sim | E48: =IF(D48="Sim",10*15,0) -> 150 | F48: 272.8753 | G48: =IF(D48="sim",E48*F48,0) -> 40931.295
B49: Guarita | C49: m2 | D49: Não | E49: =IF(D49="Sim",ROUNDUP(25,),0) -> 0 | F49: 0 | G49: =IF(D49="sim",E49*F49,0) -> 0
B50: Lava Rodas | C50: m2 | D50: Sim | E50: =IF(D50="Sim",ROUNDUP(25,),0) -> 25 | F50: 0 | G50: =IF(D50="sim",E50*F50,0) -> 0
B51: TOTAL | G51: =SUM(G36:G50) -> 121619.57
O52: área lavatório | P52: =0.6*ROUNDUP(P21/20,) -> 0 | Q52: m²
B53: * Central de armazenamento entre pavimentos
O54: Área de chuveiros | P54: =0.8*ROUNDUP(P21/10,) -> 0 | Q54: m²
A55: Sinalização
B57: Descrição | C57: Unidade | D57: Será utilizado | E57: Quantidade | F57: Custo unitário | G57: Custo total
B58: Placa indicativa fixada na estrutura por pregos | C58: VB | D58: Sim | E58: 1 | F58: 7891.02 | G58: =IF(D58="sim",E58*F58,0) -> 7891.02 | O58: Escritório | P58: 8 | Q58: m²/pessoa
B59: Placa indicativa fixada em totem | C59: m2 | D59: Não | G59: =IF(D59="sim",E59*F59,0) -> 0 | P59: =P58*P8 -> 40 | Q59: m²
B60: Instalação de sinalizador noturno | C60: m2 | D60: Não | G60: =IF(D60="sim",E60*F60,0) -> 0
B61: Sinalização com fita fixada em cone | C61: m2 | D61: Não | G61: =IF(D61="sim",E61*F61,0) -> 0 | O61: Almoxarifado | P61: =IF(P4<20000,100,100+((P4-20000)/1000)*5) -> 100 | Q61: m2
B62: Sinalização com fita fixada na estrutura amarrada | C62: m2 | D62: Não | G62: =IF(D62="sim",E62*F62,0) -> 0
B63: #REF! | C63: VB | D63: Sim | G63: =IF(D63="sim",E63*F63,0) -> 0
B64: TOTAL | G64: =SUM(G58:G63) -> 7891.02 | O64: Ferramentas | P64: =P6*800 -> 52000 | Q64: 800 por funcionário
O66: EPI | P66: =P6*500 -> 32500 | Q66: 500,00 por funcionário | R66: Considerando entrega de 2 uniformes, capacete, bota, óculos e cinto
O69: Banheiro | P69: 1 | Q69: para cada | R69: 20 | S69: pessoas
P70: =ROUNDUP(P6/R69,) -> 4

Sheet Ensaios 
C1: Projeto | D1: ='Obra '!D1 -> Brisa da armação
C2: Empresa | D2: ='Obra '!D2 -> HACASA
C3: Revisão | D3: ='Obra '!D3 -> R00 - Letícia
A4: ENSAIOS
A5: Item | B5: Descrição/Especificação | C5: Unid. | D5: V. Unit. (R$) | E5: Qtde. | F5: V. Total (R$) | G5: Observações
B6: CONTROLE TECNOLÓGICO - CONCRETO | F6: =SUM(F7:F12) -> 261480
A7: 1 | B7: Laudo e ART | C7: vb | D7: 1450 | E7: 1 | F7: =$D7*E7 -> 1450
A8: =A7+1 -> 2 | B8: Controle Tecnologico Infraestrutura - Coleta materiais da obra | C8: unid. | D8: 20 | E8: =ROUNDUP(([4]Resumo!L181+[4]Resumo!L182+[4]Resumo!L218)/8,0)*4 -> 1444 | F8: =$D8*E8 -> 28880 | G8: 4 CPs por caminhão betoneira de 8m³
A9: =A8+1 -> 3 | B9: Controle Tecnologico Contenção - Coleta materiais da obra | C9: unid. | D9: 20 | E9: =ROUNDUP(([4]Resumo!L200+[4]Resumo!L201)/8,0)*4 -> 452 | F9: =$D9*E9 -> 9040 | G9: 4 CPs por caminhão betoneira de 8m³
A10: =A9+1 -> 4 | B10: Controle Tecnologico Supraestrutura - Coleta materiais da obra | C10: unid. | D10: 20 | E10: =ROUNDUP(([4]Resumo!L242+[4]Resumo!L243+[4]Resumo!L271+[4]Resumo!L272+[4]Resumo!L294+[4]Resumo!L295)/8,0)*4 -> 5972 | F10: =$D10*E10 -> 119440 | G10: 4 CPs por caminhão betoneira de 8m³
A11: =A8+1 -> 3 | B11: Controle Tecnológico - Ensaio de concreto endurecido/grouth - compressão simples / Detalhe: Concreto | C11: cps | D11: 12.5 | E11: =E8+E9+E10 -> 7868 | F11: =$D11*E11 -> 98350
A12: =A11+1 -> 4 | B12: Determinação do módulo de deformação tangente inicial (Eci) (módulo de elasticidade), Incluindo Avaliação Estática dos Resultados (NBR 8522 e NBR 12655) | C12: ensaio | D12: 480 | E12: =[4]Obra!E56/5 -> 9 | F12: =$D12*E12 -> 4320 | G12: A cada 5 pav. (e quando houver troca de fornecedor)
B13: ACUSTICA - ENSAIO DE RUIDOS ( PISO + FACHADA) | F13: =SUM(F14:F15) -> 9000
A14: 1 | B14: Ensaio de Desempenho Acustico para piso Ensaio de ruído aéreo e ruído de impacto em Laje de dorm. | C14: ensaios | D14: 7500 | E14: 1 | F14: =$D14*E14 -> 7500 | G14: 1 ensaio
A15: =A14+1 -> 2 | B15: Ensaio de Desempenho Acustico para vedação externa Ensaio de isolamento a ruído aéreo em Fachada de dorm. | C15: ensaios | D15: 1500 | E15: 1 | F15: =$D15*E15 -> 1500 | G15: 1 ensaio
B16: ENSAIO PARA CAIXILHOS | F16: =SUM(F17:F19) -> 9968
A17: 1 | B17: Permeabilidade ao ar Estanqueidade a agua Resistencias a cargas uniformes distribuidas | C17: ensaios | D17: 3174 | E17: 1 | F17: =$D17*E17 -> 3174 | G17: 1 ensaio por tipo de caixilho (dormitório, sala, área de serviço e banheiro e terraço, se houver)
A18: =A17+1 -> 2 | B18: Resistencia as operações de manuseio com manutenção SEM persiana integrada | C18: ensaios | D18: 2774 | E18: 1 | F18: =$D18*E18 -> 2774 | G18: 1 ensaio por tipo de caixilho (dormitório, sala, área de serviço e banheiro e terraço, se houver)
A19: =A18+1 -> 3 | B19: Resistencia as operações de manuseio com manutenção COM persiana integrada | C19: ensaios | D19: 4020 | E19: 1 | F19: =$D19*E19 -> 4020 | G19: 1 ensaio por tipo de caixilho (dormitório, sala, área de serviço e banheiro e terraço, se houver)
B20: ENSAIO PARA GUARDA-CORPO | F20: =F21 -> 4210
A21: 1 | B21: Ensaio de guarda-corpo Determinação do esforço horizontal, esforço vertical e Resistencia a impactos | C21: ensaios | D21: 4210 | E21: 1 | F21: =$D21*E21 -> 4210 | G21: 1 prototipo por projeto
B22: ENSAIOS PARA ARGAMASSA DE REVESTIMENTO (FACHADA) | F22: =F23 -> 1260
A23: 1 | B23: Ensaio de arrancamento de argamassa de revestimento Determinação da aderencia a tração | C23: ensaios | D23: 1260 | E23: 1 | F23: =$D23*E23 -> 1260 | G23: 1 ensaio por torre
B24: ENSAIO PARA REVESTIMENTOS CERÂMICOS | F24: =F25 -> 664.44444
A25: 1 | B25: Aderência em Revestimento Cerâmico Determinação da aderência a tração (NBR 13754) | C25: ensaios | D25: 664.44444 | E25: 1 | F25: =$D25*E25 -> 664.44444 | G25: Torre Alta: 1 ensaio por torre, por referência de produto
B26: ENSAIO PARA ANCORAGEM (GANHOS DA COBERTURA) | F26: =SUM(F27:F28) -> 3165
A27: 1 | B27: Arrancamento de ganchos da cobertura Ensaio de Arrancamento | C27: ensaios | D27: 1680 | E27: 1 | F27: =$D27*E27 -> 1680 | G27: 1 ensaio por torre
A28: =A27+1 -> 2 | B28: Arrancamento de ganchos da cobertura Emissão de Relatorio e Laudos, incluindo Mobilização/ Desmobilização | C28: ensaios | D28: 1485 | E28: 1 | F28: =$D28*E28 -> 1485 | G28: 1 por tipo de torre
B29: ENSAIOS PARA ALVENARIA ESTRUTURAL | F29: =SUM(F30:F35) -> 81801
A30: 1 | B30: Controle Tecnológico - Ensaio de concreto endurecido/grouth - compressão simples / Detalhe: Groute | C30: unid. | D30: 8.5 | F30: 2805 | G30: ≥ 12Mpa: 6 CP's x núm pav x núm torres + ANEXOS (CONSIDERAR +6 CPs PARA CADA PAVIMENTO DE ANEXOS - INCLUINDO EMBASAMENTO E PLATIBANDA - SE HOUVER) Torre alta: 6CPs por pavimento
A31: =A30+1 -> 2 | B31: Ensaio de Argamassa - Determinação da resistência a compressão - no cubo (NBR 15961-2/2011) | C31: unid. | D31: 18 | F31: 11556 | G31: ≥ 12Mpa: 6 CP's x núm pav x núm torres + ANEXOS (CONSIDERAR +6 CPs PARA CADA PAVIMENTO DE ANEXOS - INCLUINDO EMBASAMENTO E PLATIBANDA - SE HOUVER) Torre alta: 6CPs por pavimento P/ pavimento > 600m²: 12 CPs
A32: =A31+1 -> 3 | B32: Ensaio Prisma - Determinação da resistência a compressão - Oco (NBR 15961-2/2011) | C32: unid. | D32: 50 | F32: 27600 | G32: 12 CP's x núm pav x núm torres Torre alta: 12CPs por pavimento P/ pavimento > 600m²: 12 CPs
A33: =A32+1 -> 4 | B33: Ensaio Prisma - Determinação da resistência a compressão - Cheio (NBR 15961-2/2011) | C33: unid. | D33: 65 | F33: 35880 | G33: 12 CP's x núm pav x núm torres Torre alta: 12CPs por pavimento P/ pavimento > 600m²: 12 CPs
A34: =A33+1 -> 5 | B34: Ensaio de Bloco - Determinação da resistência a compressão com dimensionamento (NBR 12118) | C34: cps | D34: 40 | F34: 2640 | G34: 6 cps x núm classes de resistencia
A35: =A34+1 -> 6 | B35: Ensaio de Bloco - Determinação da absorção e área liquida (NBR 12118) | C35: unid | D35: 40 | F35: 1320 | G35: 3 cps x núm classe de resistencia
C36: SUBTOTAL: | F36: =F29+F26+F24+F22+F20+F16+F13+F6 -> 371548.44

Sheet BASES
A1: Estimativas Custos Indiretos
A2: Empresa | B2: ='Obra '!$D$1 -> Brisa da armação | H2: CN empreendimentos | J2: CN empreendimentos | L2: Amalfi Construções e Incorporações | N2: Amalfi Construções e Incorporações | P2: Amalfi Construções e Incorporações | R2: Amalfi Construções e Incorporações | T2: AS Ramos | V2: Mabrem Maiochi Empreendimentos | X2: All Empreendimentos | Z2: All Empreendimentos | AB2: ASPEN TOWERS | AD2: Barra 4 | AF2: Atlantia | AH2: Modelo
A3: Obra | B3: ='Obra '!$D$2 -> HACASA | H3: Brava Ocean | J3: BRAVA VALLEY | L3: Tramonti | N3: MARINE | P3: MAIORI | R3: Ravello | T3: PAESAGGIO | V3: LIBERATO | X3: Acacias JK | Z3: Lago di Garda Residenciale | AB3: JTA EMPREENDIMENTOS E URBANISMO | AD3: Viva 4 | AF3: H empreendimentos | AH3: Modelo
A4: Prazo de Obra | B4: ='Obra '!$E$7 -> 48 | AB4: 56 | AD4: 33 | AF4: 65 | AH4: Modelo
A5: Cidade/Estado | H5: Itajaí - SC | J5: Itajaí - SC | L5: Itajaí - SC | N5: Navegantes - SC | P5: Itajaí - SC | R5: Itajaí - SC | T5: Balneáreo Camboriú - SC | V5: Itajaí - SC | X5: Florianópolis – SC | Z5: Porto Belo - SC | AB5: Porto Belo - SC | AD5: Florianópolis - SC | AF5: Porto Belo - SC | AH5: Modelo
A6: R$/m² | B6: =$E$11/$B$8 -> 294.52801 | H6: 360.73572 | J6: 219.31773 | L6: 380.09457 | N6: 419.37 | P6: 396.69 | R6: 353.33 | T6: 263.26 | V6: 200.45074 | X6: 374.84 | Z6: 583.04 | AB6: 437.74041 | AD6: 311.85511 | AF6: 291.75097
A7: Área de Terreno | B7: ='Obra '!$E$8 -> 1410.3 | H7: 6060 | J7: 2713.9 | L7: 1224.03 | N7: 600 | P7: 914.4 | R7: 1412.41 | T7: 1734.23 | V7: 1634.37 | X7: 460.03 | Z7: 675 | AB7: 1473.45 | AD7: 3794.1 | AF7: 1410.3 | AH7: Modelo
A8: Área Construída | B8: ='Obra '!$E$9 -> 12828.33 | H8: 61763.96 | J8: 23497.71 | L8: 15602.89 | N8: 4498.68 | P8: 8366.5 | R8: 13434.29 | T8: 19144.43 | V8: 10520.39 | X8: 1943.23 | Z8: 7055.73 | AB8: 22087.95 | AD8: 13223.26 | AF8: 12828.33 | AH8: Modelo
A9: N° pavimentos | B9: ='Obra '!$E$13 -> 20 | H9: 31 | J9: 46 | L9: 28 | N9: 12 | P9: 20 | R9: 21 | T9: 35 | V9: 18 | X9: 8 | Z9: 19 | AB9: 34 | AD9: 6 | AF9: 20 | AH9: Modelo
A10: Cub | B10: 2863.73 | H10: 2662.47 | J10: 2470.83 | L10: 2863.73 | N10: 2750.52 | P10: 2747.9 | R10: 2753.62 | T10: 2680.84 | V10: 2754.98 | X10: 2758.46 | Z10: 2846.12 | AB10: 2846.12 | AD10: 2863.73 | AF10: 2863.73 | AJ10: =SUM(AJ13:AJ338) -> 3778302.5
A11: Data Cub | B11: 45616 | D11: Total | E11: =SUMPRODUCT($D$12:$D$341,$E$12:$E$341) -> 3778302.5 | H11: 44958 | J11: 44682 | L11: 45536 | N11: 45139 | P11: 45108 | R11: 45323 | T11: 45017 | V11: 45231 | X11: 45413 | Z11: 45566 | AB11: 45586 | AD11: 45616 | AF11: 45616 | AJ11: =SUM(AJ14:AJ339) -> 3778302.5
A12: Descrição | C12: Unidade | D12: Quantidade | E12: Valor (R$) | F12: Status do Custo | G12: Indice Médio | H12: Valor | I12: Referência | J12: Valor | K12: Referência | L12: Valor | M12: Referência | N12: Valor | O12: Referência | P12: Valor | Q12: Referência | R12: Valor | S12: Referência | T12: Valor | U12: Referência | V12: Valor | W12: Referência | X12: Valor | Y12: Referência | Z12: Valor | AA12: Referência | AB12: Valor | AC12: Referência | AD12: Valor | AE12: Referência | AF12: Valor | AG12: Referência | AH12: Valor | AI12: Referência | AJ12: =SUM(AJ15:AJ340) -> 3778302.5
A13: TEC 01 – ESTUDOS, PROJETOS, CONSULTORIAS, ENSAIOS E LAUDOS
A14: ESTUDOS | E14: =SUMPRODUCT(D15:D23,E15:E23) -> 47208.254
A15: Memorial descritivo | C15: vb | D15: 1 | E15: =$B$8*0.49 -> 6285.8817 | F15: Estimado | G15: =IFERROR(AVERAGEIFS($H15:$AI15,H$12:AI$12,"Referência"),"") -> 0.39071743 | H15: 17220 | I15: =IF(H15=0,"",($B$10/H$10)*H15/H$8) -> 0.29987852 | J15: 1532.0642 | K15: =IF(J15=0,"",($B$10/J$10)*J15/J$8) -> 0.075568469 | L15: 0 | M15: =IF(L15=0,"",($B$10/L$10)*L15/L$8) | N15: 2138.0766 | O15: =IF(N15=0,"",($B$10/N$10)*N15/N$8) -> 0.49482932 | P15: 0 | Q15: =IF(P15=0,"",($B$10/P$10)*P15/P$8) | R15: 0 | S15: =IF(R15=0,"",($B$10/R$10)*R15/R$8) | T15: 0 | U15: =IF(T15=0,"",($B$10/T$10)*T15/T$8) | V15: 5000 | W15: =IF(V15=0,"",($B$10/V$10)*V15/V$8) -> 0.49402825 | X15: 0 | Y15: =IF(X15=0,"",($B$10/X$10)*X15/X$8) | Z15: 0 | AA15: =IF(Z15=0,"",($B$10/Z$10)*Z15/Z$8) | AB15: 0 | AC15: =IF(AB15=0,"",($B$10/AB$10)*AB15/AB$8) | AD15: 6479.3974 | AE15: =IF(AD15=0,"",($B$10/AD$10)*AD15/AD$8) -> 0.49 | AF15: 6285.8817 | AG15: =IF(AF15=0,"",($B$10/AF$10)*AF15/AF$8) -> 0.49 | AI15: =IF(AH15=0,"",($B$10/AH$10)*AH15/AH$8) | AJ15: =E15*D15 -> 6285.8817 | AK15: 1
A16: Levantamento topográfico | C16: vb | D16: 1 | E16: =$B$8*0.46 -> 5901.0318 | F16: Estimado | G16: =IFERROR(AVERAGEIFS($H16:$AI16,H$12:AI$12,"Referência"),"") -> 0.99743036 | H16: 14207 | I16: =IF(H16=0,"",($B$10/H$10)*H16/H$8) -> 0.24740849 | J16: 0 | K16: =IF(J16=0,"",($B$10/J$10)*J16/J$8) | L16: 6709.2427 | M16: =IF(L16=0,"",($B$10/L$10)*L16/L$8) -> 0.43 | N16: 0 | O16: =IF(N16=0,"",($B$10/N$10)*N16/N$8) | P16: 3500 | Q16: =IF(P16=0,"",($B$10/P$10)*P16/P$8) -> 0.43596876 | R16: 0 | S16: =IF(R16=0,"",($B$10/R$10)*R16/R$8) | T16: 0 | U16: =IF(T16=0,"",($B$10/T$10)*T16/T$8) | V16: 4750 | W16: =IF(V16=0,"",($B$10/V$10)*V16/V$8) -> 0.46932684 | X16: 10000 | Y16: =IF(X16=0,"",($B$10/X$10)*X16/X$8) -> 5.3424587 | Z16: 5000 | AA16: =IF(Z16=0,"",($B$10/Z$10)*Z16/Z$8) -> 0.71302854 | AB16: 9630 | AC16: =IF(AB16=0,"",($B$10/AB$10)*AB16/AB$8) -> 0.43868192 | AD16: 5818.2344 | AE16: =IF(AD16=0,"",($B$10/AD$10)*AD16/AD$8) -> 0.44 | AF16: 5901.0318 | AG16: =IF(AF16=0,"",($B$10/AF$10)*AF16/AF$8) -> 0.46 | AI16: =IF(AH16=0,"",($B$10/AH$10)*AH16/AH$8) | AJ16: =E16*D16 -> 5901.0318 | AK16: 1
A17: Estudo geológico | C17: vb | F17: Não Solicitado | G17: =IFERROR(AVERAGEIFS($H17:$AI17,H$12:AI$12,"Referência"),"") -> 0.36998069 | H17: 12048 | I17: =IF(H17=0,"",($B$10/H$10)*H17/H$8) -> 0.20981048 | J17: 0 | K17: =IF(J17=0,"",($B$10/J$10)*J17/J$8) | L17: 0 | M17: =IF(L17=0,"",($B$10/L$10)*L17/L$8) | N17: 0 | O17: =IF(N17=0,"",($B$10/N$10)*N17/N$8) | P17: 0 | Q17: =IF(P17=0,"",($B$10/P$10)*P17/P$8) | R17: 0 | S17: =IF(R17=0,"",($B$10/R$10)*R17/R$8) | T17: 8067.1619 | U17: =IF(T17=0,"",($B$10/T$10)*T17/T$8) -> 0.45013161 | V17: 0 | W17: =IF(V17=0,"",($B$10/V$10)*V17/V$8) | X17: 0 | Y17: =IF(X17=0,"",($B$10/X$10)*X17/X$8) | Z17: 0 | AA17: =IF(Z17=0,"",($B$10/Z$10)*Z17/Z$8) | AB17: 0 | AC17: =IF(AB17=0,"",($B$10/AB$10)*AB17/AB$8) | AD17: 5950.467 | AE17: =IF(AD17=0,"",($B$10/AD$10)*AD17/AD$8) -> 0.45 | AF17: 0 | AG17: =IF(AF17=0,"",($B$10/AF$10)*AF17/AF$8) | AI17: =IF(AH17=0,"",($B$10/AH$10)*AH17/AH$8) | AJ17: =E17*D17 -> 0 | AK17: 0
A18: Estudo ambiental | C18: vb | D18: 1 | E18: =$B$8*1.24 -> 15907.129 | F18: Estimado | G18: =IFERROR(AVERAGEIFS($H18:$AI18,H$12:AI$12,"Referência"),"") -> 1.6056752 | H18: 16064 | I18: =IF(H18=0,"",($B$10/H$10)*H18/H$8) -> 0.2797473 | J18: 0 | K18: =IF(J18=0,"",($B$10/J$10)*J18/J$8) | L18: 15000 | M18: =IF(L18=0,"",($B$10/L$10)*L18/L$8) -> 0.96136036 | N18: 0 | O18: =IF(N18=0,"",($B$10/N$10)*N18/N$8) | P18: 11964.095 | Q18: =IF(P18=0,"",($B$10/P$10)*P18/P$8) -> 1.4902776 | R18: 0 | S18: =IF(R18=0,"",($B$10/R$10)*R18/R$8) | T18: 27426.591 | U18: =IF(T18=0,"",($B$10/T$10)*T18/T$8) -> 1.5303493 | V18: 49892.2 | W18: =IF(V18=0,"",($B$10/V$10)*V18/V$8) -> 4.9296312 | X18: 0 | Y18: =IF(X18=0,"",($B$10/X$10)*X18/X$8) | Z18: 4000 | AA18: =IF(Z18=0,"",($B$10/Z$10)*Z18/Z$8) -> 0.57042283 | AB18: 26765.958 | AC18: =IF(AB18=0,"",($B$10/AB$10)*AB18/AB$8) -> 1.2192879 | AD18: 29487.87 | AE18: =IF(AD18=0,"",($B$10/AD$10)*AD18/AD$8) -> 2.23 | AF18: 15907.129 | AG18: =IF(AF18=0,"",($B$10/AF$10)*AF18/AF$8) -> 1.24 | AI18: =IF(AH18=0,"",($B$10/AH$10)*AH18/AH$8) | AJ18: =E18*D18 -> 15907.129 | AK18: 1
A19: Sondagem do terreno | C19: vb | D19: 1 | E19: =$B$8*1.1 -> 14111.163 | F19: Estimado | G19: =IFERROR(AVERAGEIFS($H19:$AI19,H$12:AI$12,"Referência"),"") -> 0.93154156 | H19: 48270 | I19: =IF(H19=0,"",($B$10/H$10)*H19/H$8) -> 0.84060024 | J19: 0 | K19: =IF(J19=0,"",($B$10/J$10)*J19/J$8) | L19: 14364 | M19: =IF(L19=0,"",($B$10/L$10)*L19/L$8) -> 0.92059868 | N19: 0 | O19: =IF(N19=0,"",($B$10/N$10)*N19/N$8) | P19: 5500 | Q19: =IF(P19=0,"",($B$10/P$10)*P19/P$8) -> 0.68509377 | R19: 0 | S19: =IF(R19=0,"",($B$10/R$10)*R19/R$8) | T19: 0 | U19: =IF(T19=0,"",($B$10/T$10)*T19/T$8) | V19: 8830 | W19: =IF(V19=0,"",($B$10/V$10)*V19/V$8) -> 0.87245389 | X19: 0 | Y19: =IF(X19=0,"",($B$10/X$10)*X19/X$8) | Z19: 4800 | AA19: =IF(Z19=0,"",($B$10/Z$10)*Z19/Z$8) -> 0.6845074 | AB19: 33347 | AC19: =IF(AB19=0,"",($B$10/AB$10)*AB19/AB$8) -> 1.5190785 | AD19: 10975.306 | AE19: =IF(AD19=0,"",($B$10/AD$10)*AD19/AD$8) -> 0.83 | AF19: 14111.163 | AG19: =IF(AF19=0,"",($B$10/AF$10)*AF19/AF$8) -> 1.1 | AI19: =IF(AH19=0,"",($B$10/AH$10)*AH19/AH$8) | AJ19: =E19*D19 -> 14111.163 | AK19: 1
A20: Projeto de canteiro | C20: vb | D20: 1 | E20: =$B$8*0.39 -> 5003.0487 | F20: Estimado | G20: =IFERROR(AVERAGEIFS($H20:$AI20,H$12:AI$12,"Referência"),"") -> 0.38632166 | H20: 14056 | I20: =IF(H20=0,"",($B$10/H$10)*H20/H$8) -> 0.24477889 | J20: 3778.8344 | K20: =IF(J20=0,"",($B$10/J$10)*J20/J$8) -> 0.18638953 | L20: 0 | M20: =IF(L20=0,"",($B$10/L$10)*L20/L$8) | N20: 0 | O20: =IF(N20=0,"",($B$10/N$10)*N20/N$8) | P20: 0 | Q20: =IF(P20=0,"",($B$10/P$10)*P20/P$8) | R20: 0 | S20: =IF(R20=0,"",($B$10/R$10)*R20/R$8) | T20: 0 | U20: =IF(T20=0,"",($B$10/T$10)*T20/T$8) | V20: 3950 | W20: =IF(V20=0,"",($B$10/V$10)*V20/V$8) -> 0.39028232 | X20: 0 | Y20: =IF(X20=0,"",($B$10/X$10)*X20/X$8) | Z20: 5000 | AA20: =IF(Z20=0,"",($B$10/Z$10)*Z20/Z$8) -> 0.71302854 | AB20: 8556.3309 | AC20: =IF(AB20=0,"",($B$10/AB$10)*AB20/AB$8) -> 0.38977235 | AD20: 5157.0714 | AE20: =IF(AD20=0,"",($B$10/AD$10)*AD20/AD$8) -> 0.39 | AF20: 5003.0487 | AG20: =IF(AF20=0,"",($B$10/AF$10)*AF20/AF$8) -> 0.39 | AI20: =IF(AH20=0,"",($B$10/AH$10)*AH20/AH$8) | AJ20: =E20*D20 -> 5003.0487 | AK20: 1
A21: Estudo de Análise Técnica de Projeto | C21: vb | F21: Não Solicitado | G21: =IFERROR(AVERAGEIFS($H21:$AI21,H$12:AI$12,"Referência"),"") -> 2.6909045 | H21: 0 | I21: =IF(H21=0,"",($B$10/H$10)*H21/H$8) | J21: 0 | K21: =IF(J21=0,"",($B$10/J$10)*J21/J$8) | L21: 42000 | M21: =IF(L21=0,"",($B$10/L$10)*L21/L$8) -> 2.691809 | N21: 0 | O21: =IF(N21=0,"",($B$10/N$10)*N21/N$8) | P21: 0 | Q21: =IF(P21=0,"",($B$10/P$10)*P21/P$8) | R21: 0 | S21: =IF(R21=0,"",($B$10/R$10)*R21/R$8) | T21: 0 | U21: =IF(T21=0,"",($B$10/T$10)*T21/T$8) | V21: 0 | W21: =IF(V21=0,"",($B$10/V$10)*V21/V$8) | X21: 0 | Y21: =IF(X21=0,"",($B$10/X$10)*X21/X$8) | Z21: 0 | AA21: =IF(Z21=0,"",($B$10/Z$10)*Z21/Z$8) | AB21: 0 | AC21: =IF(AB21=0,"",($B$10/AB$10)*AB21/AB$8) | AD21: 35570.569 | AE21: =IF(AD21=0,"",($B$10/AD$10)*AD21/AD$8) -> 2.69 | AF21: 0 | AG21: =IF(AF21=0,"",($B$10/AF$10)*AF21/AF$8) | AI21: =IF(AH21=0,"",($B$10/AH$10)*AH21/AH$8) | AJ21: =E21*D21 -> 0 | AK21: 0
A22: Estudo Rebaixamento de Lençol Freático | C22: vb | F22: Não Solicitado | G22: =IFERROR(AVERAGEIFS($H22:$AI22,H$12:AI$12,"Referência"),"") -> 0.64090691 | H22: 0 | I22: =IF(H22=0,"",($B$10/H$10)*H22/H$8) | J22: 0 | K22: =IF(J22=0,"",($B$10/J$10)*J22/J$8) | L22: 10000 | M22: =IF(L22=0,"",($B$10/L$10)*L22/L$8) -> 0.64090691 | N22: 0 | O22: =IF(N22=0,"",($B$10/N$10)*N22/N$8) | P22: 0 | Q22: =IF(P22=0,"",($B$10/P$10)*P22/P$8) | R22: 0 | S22: =IF(R22=0,"",($B$10/R$10)*R22/R$8) | T22: 0 | U22: =IF(T22=0,"",($B$10/T$10)*T22/T$8) | V22: 0 | W22: =IF(V22=0,"",($B$10/V$10)*V22/V$8) | X22: 0 | Y22: =IF(X22=0,"",($B$10/X$10)*X22/X$8) | Z22: 0 | AA22: =IF(Z22=0,"",($B$10/Z$10)*Z22/Z$8) | AB22: 0 | AC22: =IF(AB22=0,"",($B$10/AB$10)*AB22/AB$8) | AD22: 0 | AE22: =IF(AD22=0,"",($B$10/AD$10)*AD22/AD$8) | AF22: 0 | AG22: =IF(AF22=0,"",($B$10/AF$10)*AF22/AF$8) | AI22: =IF(AH22=0,"",($B$10/AH$10)*AH22/AH$8) | AJ22: =E22*D22 -> 0 | AK22: 0
A23: Informações complementares de Estudos | C23: vb | F23: Não Solicitado | G23: =IFERROR(AVERAGEIFS($H23:$AI23,H$12:AI$12,"Referência"),"") | H23: 0 | I23: =IF(H23=0,"",($B$10/H$10)*H23/H$8) | J23: 0 | K23: =IF(J23=0,"",($B$10/J$10)*J23/J$8) | L23: 0 | M23: =IF(L23=0,"",($B$10/L$10)*L23/L$8) | N23: 0 | O23: =IF(N23=0,"",($B$10/N$10)*N23/N$8) | P23: 0 | Q23: =IF(P23=0,"",($B$10/P$10)*P23/P$8) | R23: 0 | S23: =IF(R23=0,"",($B$10/R$10)*R23/R$8) | T23: 0 | U23: =IF(T23=0,"",($B$10/T$10)*T23/T$8) | V23: 0 | W23: =IF(V23=0,"",($B$10/V$10)*V23/V$8) | X23: 0 | Y23: =IF(X23=0,"",($B$10/X$10)*X23/X$8) | Z23: 0 | AA23: =IF(Z23=0,"",($B$10/Z$10)*Z23/Z$8) | AB23: 0 | AC23: =IF(AB23=0,"",($B$10/AB$10)*AB23/AB$8) | AD23: 0 | AE23: =IF(AD23=0,"",($B$10/AD$10)*AD23/AD$8) | AF23: 0 | AG23: =IF(AF23=0,"",($B$10/AF$10)*AF23/AF$8) | AI23: =IF(AH23=0,"",($B$10/AH$10)*AH23/AH$8) | AJ23: =E23*D23 -> 0 | AK23: 0
A24: Projetos - Arquitetonico | E24: =SUMPRODUCT(D25:D31,E25:E31) -> 174465.29 | I24: =IF(H24=0,"",($B$10/H$10)*H24/H$8) | K24: =IF(J24=0,"",($B$10/J$10)*J24/J$8) | M24: =IF(L24=0,"",($B$10/L$10)*L24/L$8) | O24: =IF(N24=0,"",($B$10/N$10)*N24/N$8) | Q24: =IF(P24=0,"",($B$10/P$10)*P24/P$8) | S24: =IF(R24=0,"",($B$10/R$10)*R24/R$8) | U24: =IF(T24=0,"",($B$10/T$10)*T24/T$8) | W24: =IF(V24=0,"",($B$10/V$10)*V24/V$8) | Y24: =IF(X24=0,"",($B$10/X$10)*X24/X$8) | AA24: =IF(Z24=0,"",($B$10/Z$10)*Z24/Z$8) | AC24: =IF(AB24=0,"",($B$10/AB$10)*AB24/AB$8) | AE24: =IF(AD24=0,"",($B$10/AD$10)*AD24/AD$8) | AG24: =IF(AF24=0,"",($B$10/AF$10)*AF24/AF$8) | AI24: =IF(AH24=0,"",($B$10/AH$10)*AH24/AH$8) | AK24: 0
A25: Legalização de incorporação | C25: vb | D25: 1 | E25: =$B$8*1.62 -> 20781.895 | F25: Estimado | G25: =IFERROR(AVERAGEIFS($H25:$AI25,H$12:AI$12,"Referência"),"") -> 1.547038 | H25: 48190 | I25: =IF(H25=0,"",($B$10/H$10)*H25/H$8) -> 0.83920708 | J25: 0 | K25: =IF(J25=0,"",($B$10/J$10)*J25/J$8) | L25: 28553.289 | M25: =IF(L25=0,"",($B$10/L$10)*L25/L$8) -> 1.83 | N25: 0 | O25: =IF(N25=0,"",($B$10/N$10)*N25/N$8) | P25: 0 | Q25: =IF(P25=0,"",($B$10/P$10)*P25/P$8) | R25: 24583.635 | S25: =IF(R25=0,"",($B$10/R$10)*R25/R$8) -> 1.9030905 | T25: 35080.523 | U25: =IF(T25=0,"",($B$10/T$10)*T25/T$8) -> 1.9574235 | V25: 0 | W25: =IF(V25=0,"",($B$10/V$10)*V25/V$8) | X25: 0 | Y25: =IF(X25=0,"",($B$10/X$10)*X25/X$8) | Z25: 0 | AA25: =IF(Z25=0,"",($B$10/Z$10)*Z25/Z$8) | AB25: 17112.662 | AC25: =IF(AB25=0,"",($B$10/AB$10)*AB25/AB$8) -> 0.77954469 | AD25: 25124.194 | AE25: =IF(AD25=0,"",($B$10/AD$10)*AD25/AD$8) -> 1.9 | AF25: 20781.895 | AG25: =IF(AF25=0,"",($B$10/AF$10)*AF25/AF$8) -> 1.62 | AI25: =IF(AH25=0,"",($B$10/AH$10)*AH25/AH$8) | AJ25: =E25*D25 -> 20781.895 | AK25: 1
A26: Projeto Arquitetônico | C26: vb | F26: Não Solicitado | G26: =IFERROR(AVERAGEIFS($H26:$AI26,H$12:AI$12,"Referência"),"") -> 7.203173 | H26: 0 | I26: =IF(H26=0,"",($B$10/H$10)*H26/H$8) | J26: 0 | K26: =IF(J26=0,"",($B$10/J$10)*J26/J$8) | L26: 0 | M26: =IF(L26=0,"",($B$10/L$10)*L26/L$8) | N26: 0 | O26: =IF(N26=0,"",($B$10/N$10)*N26/N$8) | P26: 74000 | Q26: =IF(P26=0,"",($B$10/P$10)*P26/P$8) -> 9.2176253 | R26: 0 | S26: =IF(R26=0,"",($B$10/R$10)*R26/R$8) | T26: 0 | U26: =IF(T26=0,"",($B$10/T$10)*T26/T$8) | V26: 82118 | W26: =IF(V26=0,"",($B$10/V$10)*V26/V$8) -> 8.1137224 | X26: 0 | Y26: =IF(X26=0,"",($B$10/X$10)*X26/X$8) | Z26: 30000 | AA26: =IF(Z26=0,"",($B$10/Z$10)*Z26/Z$8) -> 4.2781712 | AB26: 0 | AC26: =IF(AB26=0,"",($B$10/AB$10)*AB26/AB$8) | AD26: 0 | AE26: =IF(AD26=0,"",($B$10/AD$10)*AD26/AD$8) | AF26: 0 | AG26: =IF(AF26=0,"",($B$10/AF$10)*AF26/AF$8) | AI26: =IF(AH26=0,"",($B$10/AH$10)*AH26/AH$8) | AJ26: =E26*D26 -> 0 | AK26: 0
A27: Projeto Arquitetônico Legal | C27: vb | D27: 1 | E27: =$B$8*6.98 -> 89541.743 | F27: Estimado | G27: =IFERROR(AVERAGEIFS($H27:$AI27,H$12:AI$12,"Referência"),"") -> 9.3722888 | H27: 0 | I27: =IF(H27=0,"",($B$10/H$10)*H27/H$8) | J27: 0 | K27: =IF(J27=0,"",($B$10/J$10)*J27/J$8) | L27: 140000 | M27: =IF(L27=0,"",($B$10/L$10)*L27/L$8) -> 8.9726967 | N27: 0 | O27: =IF(N27=0,"",($B$10/N$10)*N27/N$8) | P27: 0 | Q27: =IF(P27=0,"",($B$10/P$10)*P27/P$8) | R27: 0 | S27: =IF(R27=0,"",($B$10/R$10)*R27/R$8) | T27: 0 | U27: =IF(T27=0,"",($B$10/T$10)*T27/T$8) | V27: 0 | W27: =IF(V27=0,"",($B$10/V$10)*V27/V$8) | X27: 40816 | Y27: =IF(X27=0,"",($B$10/X$10)*X27/X$8) -> 21.805779 | Z27: 31725 | AA27: =IF(Z27=0,"",($B$10/Z$10)*Z27/Z$8) -> 4.5241661 | AB27: 109345.52 | AC27: =IF(AB27=0,"",($B$10/AB$10)*AB27/AB$8) -> 4.9810907 | AD27: 118612.64 | AE27: =IF(AD27=0,"",($B$10/AD$10)*AD27/AD$8) -> 8.97 | AF27: 89541.743 | AG27: =IF(AF27=0,"",($B$10/AF$10)*AF27/AF$8) -> 6.98 | AI27: =IF(AH27=0,"",($B$10/AH$10)*AH27/AH$8) | AJ27: =E27*D27 -> 89541.743 | AK27: 1
A28: Projeto Arquitetônico Executivo | C28: vb | F28: Não Solicitado | G28: =IFERROR(AVERAGEIFS($H28:$AI28,H$12:AI$12,"Referência"),"") -> 5.9981799 | H28: 305000 | I28: =IF(H28=0,"",($B$10/H$10)*H28/H$8) -> 5.3114372 | J28: 0 | K28: =IF(J28=0,"",($B$10/J$10)*J28/J$8) | L28: 0 | M28: =IF(L28=0,"",($B$10/L$10)*L28/L$8) | N28: 0 | O28: =IF(N28=0,"",($B$10/N$10)*N28/N$8) | P28: 0 | Q28: =IF(P28=0,"",($B$10/P$10)*P28/P$8) | R28: 0 | S28: =IF(R28=0,"",($B$10/R$10)*R28/R$8) | T28: 0 | U28: =IF(T28=0,"",($B$10/T$10)*T28/T$8) | V28: 0 | W28: =IF(V28=0,"",($B$10/V$10)*V28/V$8) | X28: 0 | Y28: =IF(X28=0,"",($B$10/X$10)*X28/X$8) | Z28: 31725 | AA28: =IF(Z28=0,"",($B$10/Z$10)*Z28/Z$8) -> 4.5241661 | AB28: 108380.19 | AC28: =IF(AB28=0,"",($B$10/AB$10)*AB28/AB$8) -> 4.9371164 | AD28: 121918.46 | AE28: =IF(AD28=0,"",($B$10/AD$10)*AD28/AD$8) -> 9.22 | AF28: 0 | AG28: =IF(AF28=0,"",($B$10/AF$10)*AF28/AF$8) | AI28: =IF(AH28=0,"",($B$10/AH$10)*AH28/AH$8) | AJ28: =E28*D28 -> 0 | AK28: 0
A29: Projeto Arquitetônico interiores | C29: vb | D29: 1 | E29: =$B$8*5 -> 64141.65 | F29: Estimado | G29: =IFERROR(AVERAGEIFS($H29:$AI29,H$12:AI$12,"Referência"),"") -> 6.5208551 | H29: 660000 | I29: =IF(H29=0,"",($B$10/H$10)*H29/H$8) -> 11.493602 | J29: 0 | K29: =IF(J29=0,"",($B$10/J$10)*J29/J$8) | L29: 77500 | M29: =IF(L29=0,"",($B$10/L$10)*L29/L$8) -> 4.9670285 | N29: 0 | O29: =IF(N29=0,"",($B$10/N$10)*N29/N$8) | P29: 0 | Q29: =IF(P29=0,"",($B$10/P$10)*P29/P$8) | R29: 0 | S29: =IF(R29=0,"",($B$10/R$10)*R29/R$8) | T29: 0 | U29: =IF(T29=0,"",($B$10/T$10)*T29/T$8) | V29: 0 | W29: =IF(V29=0,"",($B$10/V$10)*V29/V$8) | X29: 0 | Y29: =IF(X29=0,"",($B$10/X$10)*X29/X$8) | Z29: 14100 | AA29: =IF(Z29=0,"",($B$10/Z$10)*Z29/Z$8) -> 2.0107405 | AB29: 234531.22 | AC29: =IF(AB29=0,"",($B$10/AB$10)*AB29/AB$8) -> 10.68376 | AD29: 65719.602 | AE29: =IF(AD29=0,"",($B$10/AD$10)*AD29/AD$8) -> 4.97 | AF29: 64141.65 | AG29: =IF(AF29=0,"",($B$10/AF$10)*AF29/AF$8) -> 5 | AI29: =IF(AH29=0,"",($B$10/AH$10)*AH29/AH$8) | AJ29: =E29*D29 -> 64141.65 | AK29: 1
A30: Projeto arquitetônico de fachada | C30: vb | F30: Não Solicitado | G30: =IFERROR(AVERAGEIFS($H30:$AI30,H$12:AI$12,"Referência"),"") -> 1.1427206 | H30: 0 | I30: =IF(H30=0,"",($B$10/H$10)*H30/H$8) | J30: 11513.878 | K30: =IF(J30=0,"",($B$10/J$10)*J30/J$8) -> 0.56791754 | L30: 0 | M30: =IF(L30=0,"",($B$10/L$10)*L30/L$8) | N30: 0 | O30: =IF(N30=0,"",($B$10/N$10)*N30/N$8) | P30: 0 | Q30: =IF(P30=0,"",($B$10/P$10)*P30/P$8) | R30: 0 | S30: =IF(R30=0,"",($B$10/R$10)*R30/R$8) | T30: 0 | U30: =IF(T30=0,"",($B$10/T$10)*T30/T$8) | V30: 0 | W30: =IF(V30=0,"",($B$10/V$10)*V30/V$8) | X30: 0 | Y30: =IF(X30=0,"",($B$10/X$10)*X30/X$8) | Z30: 14100 | AA30: =IF(Z30=0,"",($B$10/Z$10)*Z30/Z$8) -> 2.0107405 | AB30: 18648.414 | AC30: =IF(AB30=0,"",($B$10/AB$10)*AB30/AB$8) -> 0.84950383 | AD30: 0 | AE30: =IF(AD30=0,"",($B$10/AD$10)*AD30/AD$8) | AF30: 0 | AG30: =IF(AF30=0,"",($B$10/AF$10)*AF30/AF$8) | AI30: =IF(AH30=0,"",($B$10/AH$10)*AH30/AH$8) | AJ30: =E30*D30 -> 0 | AK30: 0
A31: Projeto técnico de fachada | C31: vb | F31: Não Solicitado | G31: =IFERROR(AVERAGEIFS($H31:$AI31,H$12:AI$12,"Referência"),"") -> 0.80753011 | H31: 0 | I31: =IF(H31=0,"",($B$10/H$10)*H31/H$8) | J31: 4500 | K31: =IF(J31=0,"",($B$10/J$10)*J31/J$8) -> 0.22196075 | L31: 0 | M31: =IF(L31=0,"",($B$10/L$10)*L31/L$8) | N31: 0 | O31: =IF(N31=0,"",($B$10/N$10)*N31/N$8) | P31: 0 | Q31: =IF(P31=0,"",($B$10/P$10)*P31/P$8) | R31: 0 | S31: =IF(R31=0,"",($B$10/R$10)*R31/R$8) | T31: 0 | U31: =IF(T31=0,"",($B$10/T$10)*T31/T$8) | V31: 0 | W31: =IF(V31=0,"",($B$10/V$10)*V31/V$8) | X31: 0 | Y31: =IF(X31=0,"",($B$10/X$10)*X31/X$8) | Z31: 14100 | AA31: =IF(Z31=0,"",($B$10/Z$10)*Z31/Z$8) -> 2.0107405 | AB31: 4168.4689 | AC31: =IF(AB31=0,"",($B$10/AB$10)*AB31/AB$8) -> 0.18988909 | AD31: 0 | AE31: =IF(AD31=0,"",($B$10/AD$10)*AD31/AD$8) | AF31: 0 | AG31: =IF(AF31=0,"",($B$10/AF$10)*AF31/AF$8) | AI31: =IF(AH31=0,"",($B$10/AH$10)*AH31/AH$8) | AJ31: =E31*D31 -> 0 | AK31: 0
A32: Projetos - Estrutural | E32: =SUMPRODUCT(D33:D37,E33:E37) -> 104294.32 | I32: =IF(H32=0,"",($B$10/H$10)*H32/H$8) | K32: =IF(J32=0,"",($B$10/J$10)*J32/J$8) | M32: =IF(L32=0,"",($B$10/L$10)*L32/L$8) | O32: =IF(N32=0,"",($B$10/N$10)*N32/N$8) | Q32: =IF(P32=0,"",($B$10/P$10)*P32/P$8) | S32: =IF(R32=0,"",($B$10/R$10)*R32/R$8) | U32: =IF(T32=0,"",($B$10/T$10)*T32/T$8) | W32: =IF(V32=0,"",($B$10/V$10)*V32/V$8) | Y32: =IF(X32=0,"",($B$10/X$10)*X32/X$8) | AA32: =IF(Z32=0,"",($B$10/Z$10)*Z32/Z$8) | AC32: =IF(AB32=0,"",($B$10/AB$10)*AB32/AB$8) | AE32: =IF(AD32=0,"",($B$10/AD$10)*AD32/AD$8) | AG32: =IF(AF32=0,"",($B$10/AF$10)*AF32/AF$8) | AI32: =IF(AH32=0,"",($B$10/AH$10)*AH32/AH$8) | AK32: 0
A33: Projeto de terraplanagem | C33: vb | F33: Não Solicitado | G33: =IFERROR(AVERAGEIFS($H33:$AI33,H$12:AI$12,"Referência"),"") -> 0.16602333 | H33: 0 | I33: =IF(H33=0,"",($B$10/H$10)*H33/H$8) | J33: 1532.0642 | K33: =IF(J33=0,"",($B$10/J$10)*J33/J$8) -> 0.075568469 | L33: 0 | M33: =IF(L33=0,"",($B$10/L$10)*L33/L$8) | N33: 984.25197 | O33: =IF(N33=0,"",($B$10/N$10)*N33/N$8) -> 0.22779199 | P33: 1500 | Q33: =IF(P33=0,"",($B$10/P$10)*P33/P$8) -> 0.18684376 | R33: 0 | S33: =IF(R33=0,"",($B$10/R$10)*R33/R$8) | T33: 0 | U33: =IF(T33=0,"",($B$10/T$10)*T33/T$8) | V33: 0 | W33: =IF(V33=0,"",($B$10/V$10)*V33/V$8) | X33: 0 | Y33: =IF(X33=0,"",($B$10/X$10)*X33/X$8) | Z33: 0 | AA33: =IF(Z33=0,"",($B$10/Z$10)*Z33/Z$8) | AB33: 3290.8965 | AC33: =IF(AB33=0,"",($B$10/AB$10)*AB33/AB$8) -> 0.14991244 | AD33: 2512.4194 | AE33: =IF(AD33=0,"",($B$10/AD$10)*AD33/AD$8) -> 0.19 | AF33: 0 | AG33: =IF(AF33=0,"",($B$10/AF$10)*AF33/AF$8) | AI33: =IF(AH33=0,"",($B$10/AH$10)*AH33/AH$8) | AJ33: =E33*D33 -> 0 | AK33: 0
A34: Projeto de Fundação | C34: vb | D34: 1 | E34: =$B$8*1.9 -> 24373.827 | F34: Estimado | G34: =IFERROR(AVERAGEIFS($H34:$AI34,H$12:AI$12,"Referência"),"") -> 1.8759971 | H34: 61396 | I34: =IF(H34=0,"",($B$10/H$10)*H34/H$8) -> 1.0691836 | J34: 46064.489 | K34: =IF(J34=0,"",($B$10/J$10)*J34/J$8) -> 2.272113 | L34: 44600 | M34: =IF(L34=0,"",($B$10/L$10)*L34/L$8) -> 2.8584448 | N34: 0 | O34: =IF(N34=0,"",($B$10/N$10)*N34/N$8) | P34: 0 | Q34: =IF(P34=0,"",($B$10/P$10)*P34/P$8) | R34: 0 | S34: =IF(R34=0,"",($B$10/R$10)*R34/R$8) | T34: 0 | U34: =IF(T34=0,"",($B$10/T$10)*T34/T$8) | V34: 9600 | W34: =IF(V34=0,"",($B$10/V$10)*V34/V$8) -> 0.94853424 | X34: 0 | Y34: =IF(X34=0,"",($B$10/X$10)*X34/X$8) | Z34: 8000 | AA34: =IF(Z34=0,"",($B$10/Z$10)*Z34/Z$8) -> 1.1408457 | AB34: 43001.048 | AC34: =IF(AB34=0,"",($B$10/AB$10)*AB34/AB$8) -> 1.9588559 | AD34: 37818.524 | AE34: =IF(AD34=0,"",($B$10/AD$10)*AD34/AD$8) -> 2.86 | AF34: 24373.827 | AG34: =IF(AF34=0,"",($B$10/AF$10)*AF34/AF$8) -> 1.9 | AI34: =IF(AH34=0,"",($B$10/AH$10)*AH34/AH$8) | AJ34: =E34*D34 -> 24373.827 | AK34: 1
A35: Projeto estrutural | C35: vb | D35: 1 | E35: =$B$8*6.23 -> 79920.496 | F35: Estimado | G35: =IFERROR(AVERAGEIFS($H35:$AI35,H$12:AI$12,"Referência"),"") -> 6.8526819 | H35: 230000 | I35: =IF(H35=0,"",($B$10/H$10)*H35/H$8) -> 4.0053461 | J35: 0 | K35: =IF(J35=0,"",($B$10/J$10)*J35/J$8) | L35: 109543.5 | M35: =IF(L35=0,"",($B$10/L$10)*L35/L$8) -> 7.0207186 | N35: 0 | O35: =IF(N35=0,"",($B$10/N$10)*N35/N$8) | P35: 41100 | Q35: =IF(P35=0,"",($B$10/P$10)*P35/P$8) -> 5.1195189 | R35: 0 | S35: =IF(R35=0,"",($B$10/R$10)*R35/R$8) | T35: 287022.46 | U35: =IF(T35=0,"",($B$10/T$10)*T35/T$8) -> 16.015283 | V35: 55000 | W35: =IF(V35=0,"",($B$10/V$10)*V35/V$8) -> 5.4343107 | X35: 0 | Y35: =IF(X35=0,"",($B$10/X$10)*X35/X$8) | Z35: 58000 | AA35: =IF(Z35=0,"",($B$10/Z$10)*Z35/Z$8) -> 8.2711311 | AB35: 81614.233 | AC35: =IF(AB35=0,"",($B$10/AB$10)*AB35/AB$8) -> 3.7178285 | AD35: 77488.304 | AE35: =IF(AD35=0,"",($B$10/AD$10)*AD35/AD$8) -> 5.86 | AF35: 79920.496 | AG35: =IF(AF35=0,"",($B$10/AF$10)*AF35/AF$8) -> 6.23 | AI35: =IF(AH35=0,"",($B$10/AH$10)*AH35/AH$8) | AJ35: =E35*D35 -> 79920.496 | AK35: 1
A36: Projeto de estrutura metálica | C36: vb | F36: Não Solicitado | G36: =IFERROR(AVERAGEIFS($H36:$AI36,H$12:AI$12,"Referência"),"") | H36: 0 | I36: =IF(H36=0,"",($B$10/H$10)*H36/H$8) | J36: 0 | K36: =IF(J36=0,"",($B$10/J$10)*J36/J$8) | L36: 0 | M36: =IF(L36=0,"",($B$10/L$10)*L36/L$8) | N36: 0 | O36: =IF(N36=0,"",($B$10/N$10)*N36/N$8) | P36: 0 | Q36: =IF(P36=0,"",($B$10/P$10)*P36/P$8) | R36: 0 | S36: =IF(R36=0,"",($B$10/R$10)*R36/R$8) | T36: 0 | U36: =IF(T36=0,"",($B$10/T$10)*T36/T$8) | V36: 0 | W36: =IF(V36=0,"",($B$10/V$10)*V36/V$8) | X36: 0 | Y36: =IF(X36=0,"",($B$10/X$10)*X36/X$8) | Z36: 0 | AA36: =IF(Z36=0,"",($B$10/Z$10)*Z36/Z$8) | AB36: 0 | AC36: =IF(AB36=0,"",($B$10/AB$10)*AB36/AB$8) | AD36: 0 | AE36: =IF(AD36=0,"",($B$10/AD$10)*AD36/AD$8) | AF36: 0 | AG36: =IF(AF36=0,"",($B$10/AF$10)*AF36/AF$8) | AI36: =IF(AH36=0,"",($B$10/AH$10)*AH36/AH$8) | AJ36: =E36*D36 -> 0 | AK36: 0
A37: Projeto de alvenaria estrutural | C37: vb | F37: Não Solicitado | G37: =IFERROR(AVERAGEIFS($H37:$AI37,H$12:AI$12,"Referência"),"") | H37: 0 | I37: =IF(H37=0,"",($B$10/H$10)*H37/H$8) | J37: 0 | K37: =IF(J37=0,"",($B$10/J$10)*J37/J$8) | L37: 0 | M37: =IF(L37=0,"",($B$10/L$10)*L37/L$8) | N37: 0 | O37: =IF(N37=0,"",($B$10/N$10)*N37/N$8) | P37: 0 | Q37: =IF(P37=0,"",($B$10/P$10)*P37/P$8) | R37: 0 | S37: =IF(R37=0,"",($B$10/R$10)*R37/R$8) | T37: 0 | U37: =IF(T37=0,"",($B$10/T$10)*T37/T$8) | V37: 0 | W37: =IF(V37=0,"",($B$10/V$10)*V37/V$8) | X37: 0 | Y37: =IF(X37=0,"",($B$10/X$10)*X37/X$8) | Z37: 0 | AA37: =IF(Z37=0,"",($B$10/Z$10)*Z37/Z$8) | AB37: 0 | AC37: =IF(AB37=0,"",($B$10/AB$10)*AB37/AB$8) | AD37: 0 | AE37: =IF(AD37=0,"",($B$10/AD$10)*AD37/AD$8) | AF37: 0 | AG37: =IF(AF37=0,"",($B$10/AF$10)*AF37/AF$8) | AI37: =IF(AH37=0,"",($B$10/AH$10)*AH37/AH$8) | AJ37: =E37*D37 -> 0 | AK37: 0
A38: Projetos - Complementares | E38: =SUMPRODUCT(D39:D58,E39:E58) -> 85244.253 | I38: =IF(H38=0,"",($B$10/H$10)*H38/H$8) | K38: =IF(J38=0,"",($B$10/J$10)*J38/J$8) | M38: =IF(L38=0,"",($B$10/L$10)*L38/L$8) | O38: =IF(N38=0,"",($B$10/N$10)*N38/N$8) | Q38: =IF(P38=0,"",($B$10/P$10)*P38/P$8) | S38: =IF(R38=0,"",($B$10/R$10)*R38/R$8) | U38: =IF(T38=0,"",($B$10/T$10)*T38/T$8) | W38: =IF(V38=0,"",($B$10/V$10)*V38/V$8) | Y38: =IF(X38=0,"",($B$10/X$10)*X38/X$8) | AA38: =IF(Z38=0,"",($B$10/Z$10)*Z38/Z$8) | AC38: =IF(AB38=0,"",($B$10/AB$10)*AB38/AB$8) | AE38: =IF(AD38=0,"",($B$10/AD$10)*AD38/AD$8) | AG38: =IF(AF38=0,"",($B$10/AF$10)*AF38/AF$8) | AI38: =IF(AH38=0,"",($B$10/AH$10)*AH38/AH$8) | AK38: 0
A39: Projeto elétrico/comunicação/telefonia/luminotécnico | C39: vb | F39: Não Solicitado | G39: =IFERROR(AVERAGEIFS($H39:$AI39,H$12:AI$12,"Referência"),"") -> 5.339256 | H39: 440000 | I39: =IF(H39=0,"",($B$10/H$10)*H39/H$8) -> 7.6624012 | J39: 0 | K39: =IF(J39=0,"",($B$10/J$10)*J39/J$8) | L39: 0 | M39: =IF(L39=0,"",($B$10/L$10)*L39/L$8) | N39: 0 | O39: =IF(N39=0,"",($B$10/N$10)*N39/N$8) | P39: 0 | Q39: =IF(P39=0,"",($B$10/P$10)*P39/P$8) | R39: 0 | S39: =IF(R39=0,"",($B$10/R$10)*R39/R$8) | T39: 0 | U39: =IF(T39=0,"",($B$10/T$10)*T39/T$8) | V39: 0 | W39: =IF(V39=0,"",($B$10/V$10)*V39/V$8) | X39: 0 | Y39: =IF(X39=0,"",($B$10/X$10)*X39/X$8) | Z39: 21150 | AA39: =IF(Z39=0,"",($B$10/Z$10)*Z39/Z$8) -> 3.0161107 | AB39: 0 | AC39: =IF(AB39=0,"",($B$10/AB$10)*AB39/AB$8) | AD39: 0 | AE39: =IF(AD39=0,"",($B$10/AD$10)*AD39/AD$8) | AF39: 0 | AG39: =IF(AF39=0,"",($B$10/AF$10)*AF39/AF$8) | AI39: =IF(AH39=0,"",($B$10/AH$10)*AH39/AH$8) | AJ39: =E39*D39 -> 0 | AK39: 0
A40: Projeto elétrico/comunicação/telefonia | C40: vb | D40: 1 | E40: =$B$8*2.49 -> 31942.542 | F40: Estimado | G40: =IFERROR(AVERAGEIFS($H40:$AI40,H$12:AI$12,"Referência"),"") -> 3.630328 | H40: 440000 | I40: =IF(H40=0,"",($B$10/H$10)*H40/H$8) -> 7.6624012 | J40: 0 | K40: =IF(J40=0,"",($B$10/J$10)*J40/J$8) | L40: 38900 | M40: =IF(L40=0,"",($B$10/L$10)*L40/L$8) -> 2.4931279 | N40: 0 | O40: =IF(N40=0,"",($B$10/N$10)*N40/N$8) | P40: 0 | Q40: =IF(P40=0,"",($B$10/P$10)*P40/P$8) | R40: 0 | S40: =IF(R40=0,"",($B$10/R$10)*R40/R$8) | T40: 0 | U40: =IF(T40=0,"",($B$10/T$10)*T40/T$8) | V40: 0 | W40: =IF(V40=0,"",($B$10/V$10)*V40/V$8) | X40: 0 | Y40: =IF(X40=0,"",($B$10/X$10)*X40/X$8) | Z40: 21150 | AA40: =IF(Z40=0,"",($B$10/Z$10)*Z40/Z$8) -> 3.0161107 | AB40: 0 | AC40: =IF(AB40=0,"",($B$10/AB$10)*AB40/AB$8) | AD40: 32925.917 | AE40: =IF(AD40=0,"",($B$10/AD$10)*AD40/AD$8) -> 2.49 | AF40: 31942.542 | AG40: =IF(AF40=0,"",($B$10/AF$10)*AF40/AF$8) -> 2.49 | AI40: =IF(AH40=0,"",($B$10/AH$10)*AH40/AH$8) | AJ40: =E40*D40 -> 31942.542 | AK40: 1
A41: Projeto elétrico | C41: vb | F41: Não Solicitado | G41: =IFERROR(AVERAGEIFS($H41:$AI41,H$12:AI$12,"Referência"),"") -> 3.0260379 | H41: 0 | I41: =IF(H41=0,"",($B$10/H$10)*H41/H$8) | J41: 0 | K41: =IF(J41=0,"",($B$10/J$10)*J41/J$8) | L41: 0 | M41: =IF(L41=0,"",($B$10/L$10)*L41/L$8) | N41: 0 | O41: =IF(N41=0,"",($B$10/N$10)*N41/N$8) | P41: 0 | Q41: =IF(P41=0,"",($B$10/P$10)*P41/P$8) | R41: 0 | S41: =IF(R41=0,"",($B$10/R$10)*R41/R$8) | T41: 42096.628 | U41: =IF(T41=0,"",($B$10/T$10)*T41/T$8) -> 2.3489082 | V41: 0 | W41: =IF(V41=0,"",($B$10/V$10)*V41/V$8) | X41: 5936 | Y41: =IF(X41=0,"",($B$10/X$10)*X41/X$8) -> 3.1712835 | Z41: 0 | AA41: =IF(Z41=0,"",($B$10/Z$10)*Z41/Z$8) | AB41: 78103.944 | AC41: =IF(AB41=0,"",($B$10/AB$10)*AB41/AB$8) -> 3.5579219 | AD41: 0 | AE41: =IF(AD41=0,"",($B$10/AD$10)*AD41/AD$8) | AF41: 0 | AG41: =IF(AF41=0,"",($B$10/AF$10)*AF41/AF$8) | AI41: =IF(AH41=0,"",($B$10/AH$10)*AH41/AH$8) | AJ41: =E41*D41 -> 0 | AK41: 0
A42: Projeto comunicação e dados | C42: vb | F42: Não Solicitado | G42: =IFERROR(AVERAGEIFS($H42:$AI42,H$12:AI$12,"Referência"),"") -> 1.6820342 | H42: 0 | I42: =IF(H42=0,"",($B$10/H$10)*H42/H$8) | J42: 0 | K42: =IF(J42=0,"",($B$10/J$10)*J42/J$8) | L42: 0 | M42: =IF(L42=0,"",($B$10/L$10)*L42/L$8) | N42: 0 | O42: =IF(N42=0,"",($B$10/N$10)*N42/N$8) | P42: 0 | Q42: =IF(P42=0,"",($B$10/P$10)*P42/P$8) | R42: 0 | S42: =IF(R42=0,"",($B$10/R$10)*R42/R$8) | T42: 0 | U42: =IF(T42=0,"",($B$10/T$10)*T42/T$8) | V42: 0 | W42: =IF(V42=0,"",($B$10/V$10)*V42/V$8) | X42: 2967 | Y42: =IF(X42=0,"",($B$10/X$10)*X42/X$8) -> 1.5851075 | Z42: 0 | AA42: =IF(Z42=0,"",($B$10/Z$10)*Z42/Z$8) | AB42: 39051.972 | AC42: =IF(AB42=0,"",($B$10/AB$10)*AB42/AB$8) -> 1.778961 | AD42: 0 | AE42: =IF(AD42=0,"",($B$10/AD$10)*AD42/AD$8) | AF42: 0 | AG42: =IF(AF42=0,"",($B$10/AF$10)*AF42/AF$8) | AI42: =IF(AH42=0,"",($B$10/AH$10)*AH42/AH$8) | AJ42: =E42*D42 -> 0 | AK42: 0
A43: Projeto de telefonia | C43: vb | F43: Não Solicitado | G43: =IFERROR(AVERAGEIFS($H43:$AI43,H$12:AI$12,"Referência"),"") -> 0.59596954 | H43: 0 | I43: =IF(H43=0,"",($B$10/H$10)*H43/H$8) | J43: 0 | K43: =IF(J43=0,"",($B$10/J$10)*J43/J$8) | L43: 0 | M43: =IF(L43=0,"",($B$10/L$10)*L43/L$8) | N43: 0 | O43: =IF(N43=0,"",($B$10/N$10)*N43/N$8) | P43: 1000 | Q43: =IF(P43=0,"",($B$10/P$10)*P43/P$8) -> 0.1245625 | R43: 0 | S43: =IF(R43=0,"",($B$10/R$10)*R43/R$8) | T43: 0 | U43: =IF(T43=0,"",($B$10/T$10)*T43/T$8) | V43: 0 | W43: =IF(V43=0,"",($B$10/V$10)*V43/V$8) | X43: 0 | Y43: =IF(X43=0,"",($B$10/X$10)*X43/X$8) | Z43: 0 | AA43: =IF(Z43=0,"",($B$10/Z$10)*Z43/Z$8) | AB43: 23431.183 | AC43: =IF(AB43=0,"",($B$10/AB$10)*AB43/AB$8) -> 1.0673766 | AD43: 0 | AE43: =IF(AD43=0,"",($B$10/AD$10)*AD43/AD$8) | AF43: 0 | AG43: =IF(AF43=0,"",($B$10/AF$10)*AF43/AF$8) | AI43: =IF(AH43=0,"",($B$10/AH$10)*AH43/AH$8) | AJ43: =E43*D43 -> 0 | AK43: 0
A44: Projeto luminotécnico | C44: vb | D44: 1 | E44: =$B$8*2.49/2 -> 15971.271 | F44: Estimado | G44: =IFERROR(AVERAGEIFS($H44:$AI44,H$12:AI$12,"Referência"),"") -> 0.55028672 | H44: 0 | I44: =IF(H44=0,"",($B$10/H$10)*H44/H$8) | J44: 0 | K44: =IF(J44=0,"",($B$10/J$10)*J44/J$8) | L44: 0 | M44: =IF(L44=0,"",($B$10/L$10)*L44/L$8) | N44: 0 | O44: =IF(N44=0,"",($B$10/N$10)*N44/N$8) | P44: 1000 | Q44: =IF(P44=0,"",($B$10/P$10)*P44/P$8) -> 0.1245625 | R44: 0 | S44: =IF(R44=0,"",($B$10/R$10)*R44/R$8) | T44: 0 | U44: =IF(T44=0,"",($B$10/T$10)*T44/T$8) | V44: 0 | W44: =IF(V44=0,"",($B$10/V$10)*V44/V$8) | X44: 0 | Y44: =IF(X44=0,"",($B$10/X$10)*X44/X$8) | Z44: 0 | AA44: =IF(Z44=0,"",($B$10/Z$10)*Z44/Z$8) | AB44: 15620.789 | AC44: =IF(AB44=0,"",($B$10/AB$10)*AB44/AB$8) -> 0.71158439 | AD44: 1586.7912 | AE44: =IF(AD44=0,"",($B$10/AD$10)*AD44/AD$8) -> 0.12 | AF44: 15971.271 | AG44: =IF(AF44=0,"",($B$10/AF$10)*AF44/AF$8) -> 1.245 | AI44: =IF(AH44=0,"",($B$10/AH$10)*AH44/AH$8) | AJ44: =E44*D44 -> 15971.271 | AK44: 1
A45: Projeto de automação | C45: vb | F45: Não Solicitado | G45: =IFERROR(AVERAGEIFS($H45:$AI45,H$12:AI$12,"Referência"),"") -> 0.32252455 | H45: 19250 | I45: =IF(H45=0,"",($B$10/H$10)*H45/H$8) -> 0.33523005 | J45: 0 | K45: =IF(J45=0,"",($B$10/J$10)*J45/J$8) | L45: 0 | M45: =IF(L45=0,"",($B$10/L$10)*L45/L$8) | N45: 0 | O45: =IF(N45=0,"",($B$10/N$10)*N45/N$8) | P45: 0 | Q45: =IF(P45=0,"",($B$10/P$10)*P45/P$8) | R45: 0 | S45: =IF(R45=0,"",($B$10/R$10)*R45/R$8) | T45: 0 | U45: =IF(T45=0,"",($B$10/T$10)*T45/T$8) | V45: 0 | W45: =IF(V45=0,"",($B$10/V$10)*V45/V$8) | X45: 0 | Y45: =IF(X45=0,"",($B$10/X$10)*X45/X$8) | Z45: 0 | AA45: =IF(Z45=0,"",($B$10/Z$10)*Z45/Z$8) | AB45: 6801.1861 | AC45: =IF(AB45=0,"",($B$10/AB$10)*AB45/AB$8) -> 0.30981904 | AD45: 0 | AE45: =IF(AD45=0,"",($B$10/AD$10)*AD45/AD$8) | AF45: 0 | AG45: =IF(AF45=0,"",($B$10/AF$10)*AF45/AF$8) | AI45: =IF(AH45=0,"",($B$10/AH$10)*AH45/AH$8) | AJ45: =E45*D45 -> 0 | AK45: 0
A46: Projeto hidrossanitário | C46: vb | D46: 1 | E46: =$B$8*1.63 -> 20910.178 | F46: Estimado | G46: =IFERROR(AVERAGEIFS($H46:$AI46,H$12:AI$12,"Referência"),"") -> 2.0449756 | H46: 0 | I46: =IF(H46=0,"",($B$10/H$10)*H46/H$8) | J46: 0 | K46: =IF(J46=0,"",($B$10/J$10)*J46/J$8) | L46: 0 | M46: =IF(L46=0,"",($B$10/L$10)*L46/L$8) | N46: 0 | O46: =IF(N46=0,"",($B$10/N$10)*N46/N$8) | P46: 10000 | Q46: =IF(P46=0,"",($B$10/P$10)*P46/P$8) -> 1.245625 | R46: 0 | S46: =IF(R46=0,"",($B$10/R$10)*R46/R$8) | T46: 0 | U46: =IF(T46=0,"",($B$10/T$10)*T46/T$8) | V46: 16500 | W46: =IF(V46=0,"",($B$10/V$10)*V46/V$8) -> 1.6302932 | X46: 9500 | Y46: =IF(X46=0,"",($B$10/X$10)*X46/X$8) -> 5.0753357 | Z46: 0 | AA46: =IF(Z46=0,"",($B$10/Z$10)*Z46/Z$8) | AB46: 14128.916 | AC46: =IF(AB46=0,"",($B$10/AB$10)*AB46/AB$8) -> 0.64362408 | AD46: 0 | AE46: =IF(AD46=0,"",($B$10/AD$10)*AD46/AD$8) | AF46: 20910.178 | AG46: =IF(AF46=0,"",($B$10/AF$10)*AF46/AF$8) -> 1.63 | AI46: =IF(AH46=0,"",($B$10/AH$10)*AH46/AH$8) | AJ46: =E46*D46 -> 20910.178 | AK46: 1
A47: Projeto hidrossanitário/drenagem/pluvial | C47: vb | F47: Não Solicitado | G47: =IFERROR(AVERAGEIFS($H47:$AI47,H$12:AI$12,"Referência"),"") -> 2.7132461 | H47: 0 | I47: =IF(H47=0,"",($B$10/H$10)*H47/H$8) | J47: 0 | K47: =IF(J47=0,"",($B$10/J$10)*J47/J$8) | L47: 40000 | M47: =IF(L47=0,"",($B$10/L$10)*L47/L$8) -> 2.5636276 | N47: 0 | O47: =IF(N47=0,"",($B$10/N$10)*N47/N$8) | P47: 0 | Q47: =IF(P47=0,"",($B$10/P$10)*P47/P$8) | R47: 0 | S47: =IF(R47=0,"",($B$10/R$10)*R47/R$8) | T47: 0 | U47: =IF(T47=0,"",($B$10/T$10)*T47/T$8) | V47: 0 | W47: =IF(V47=0,"",($B$10/V$10)*V47/V$8) | X47: 0 | Y47: =IF(X47=0,"",($B$10/X$10)*X47/X$8) | Z47: 21150 | AA47: =IF(Z47=0,"",($B$10/Z$10)*Z47/Z$8) -> 3.0161107 | AB47: 0 | AC47: =IF(AB47=0,"",($B$10/AB$10)*AB47/AB$8) | AD47: 33851.546 | AE47: =IF(AD47=0,"",($B$10/AD$10)*AD47/AD$8) -> 2.56 | AF47: 0 | AG47: =IF(AF47=0,"",($B$10/AF$10)*AF47/AF$8) | AI47: =IF(AH47=0,"",($B$10/AH$10)*AH47/AH$8) | AJ47: =E47*D47 -> 0 | AK47: 0
A48: Projeto de drenagem | C48: vb | F48: Não Solicitado | G48: =IFERROR(AVERAGEIFS($H48:$AI48,H$12:AI$12,"Referência"),"") -> 0.18389259 | H48: 0 | I48: =IF(H48=0,"",($B$10/H$10)*H48/H$8) | J48: 0 | K48: =IF(J48=0,"",($B$10/J$10)*J48/J$8) | L48: 0 | M48: =IF(L48=0,"",($B$10/L$10)*L48/L$8) | N48: 0 | O48: =IF(N48=0,"",($B$10/N$10)*N48/N$8) | P48: 0 | Q48: =IF(P48=0,"",($B$10/P$10)*P48/P$8) | R48: 0 | S48: =IF(R48=0,"",($B$10/R$10)*R48/R$8) | T48: 0 | U48: =IF(T48=0,"",($B$10/T$10)*T48/T$8) | V48: 0 | W48: =IF(V48=0,"",($B$10/V$10)*V48/V$8) | X48: 0 | Y48: =IF(X48=0,"",($B$10/X$10)*X48/X$8) | Z48: 0 | AA48: =IF(Z48=0,"",($B$10/Z$10)*Z48/Z$8) | AB48: 4036.833 | AC48: =IF(AB48=0,"",($B$10/AB$10)*AB48/AB$8) -> 0.18389259 | AD48: 0 | AE48: =IF(AD48=0,"",($B$10/AD$10)*AD48/AD$8) | AF48: 0 | AG48: =IF(AF48=0,"",($B$10/AF$10)*AF48/AF$8) | AI48: =IF(AH48=0,"",($B$10/AH$10)*AH48/AH$8) | AJ48: =E48*D48 -> 0 | AK48: 0
A49: Projeto pluvial | C49: vb | F49: Não Solicitado | G49: =IFERROR(AVERAGEIFS($H49:$AI49,H$12:AI$12,"Referência"),"") -> 0.091946297 | H49: 0 | I49: =IF(H49=0,"",($B$10/H$10)*H49/H$8) | J49: 0 | K49: =IF(J49=0,"",($B$10/J$10)*J49/J$8) | L49: 0 | M49: =IF(L49=0,"",($B$10/L$10)*L49/L$8) | N49: 0 | O49: =IF(N49=0,"",($B$10/N$10)*N49/N$8) | P49: 0 | Q49: =IF(P49=0,"",($B$10/P$10)*P49/P$8) | R49: 0 | S49: =IF(R49=0,"",($B$10/R$10)*R49/R$8) | T49: 0 | U49: =IF(T49=0,"",($B$10/T$10)*T49/T$8) | V49: 0 | W49: =IF(V49=0,"",($B$10/V$10)*V49/V$8) | X49: 0 | Y49: =IF(X49=0,"",($B$10/X$10)*X49/X$8) | Z49: 0 | AA49: =IF(Z49=0,"",($B$10/Z$10)*Z49/Z$8) | AB49: 2018.4165 | AC49: =IF(AB49=0,"",($B$10/AB$10)*AB49/AB$8) -> 0.091946297 | AD49: 0 | AE49: =IF(AD49=0,"",($B$10/AD$10)*AD49/AD$8) | AF49: 0 | AG49: =IF(AF49=0,"",($B$10/AF$10)*AF49/AF$8) | AI49: =IF(AH49=0,"",($B$10/AH$10)*AH49/AH$8) | AJ49: =E49*D49 -> 0 | AK49: 0
A50: Projeto de irrigação | C50: vb | F50: Não Solicitado | G50: =IFERROR(AVERAGEIFS($H50:$AI50,H$12:AI$12,"Referência"),"") | H50: 0 | I50: =IF(H50=0,"",($B$10/H$10)*H50/H$8) | J50: 0 | K50: =IF(J50=0,"",($B$10/J$10)*J50/J$8) | L50: 0 | M50: =IF(L50=0,"",($B$10/L$10)*L50/L$8) | N50: 0 | O50: =IF(N50=0,"",($B$10/N$10)*N50/N$8) | P50: 0 | Q50: =IF(P50=0,"",($B$10/P$10)*P50/P$8) | R50: 0 | S50: =IF(R50=0,"",($B$10/R$10)*R50/R$8) | T50: 0 | U50: =IF(T50=0,"",($B$10/T$10)*T50/T$8) | V50: 0 | W50: =IF(V50=0,"",($B$10/V$10)*V50/V$8) | X50: 0 | Y50: =IF(X50=0,"",($B$10/X$10)*X50/X$8) | Z50: 0 | AA50: =IF(Z50=0,"",($B$10/Z$10)*Z50/Z$8) | AB50: 0 | AC50: =IF(AB50=0,"",($B$10/AB$10)*AB50/AB$8) | AD50: 0 | AE50: =IF(AD50=0,"",($B$10/AD$10)*AD50/AD$8) | AF50: 0 | AG50: =IF(AF50=0,"",($B$10/AF$10)*AF50/AF$8) | AI50: =IF(AH50=0,"",($B$10/AH$10)*AH50/AH$8) | AJ50: =E50*D50 -> 0 | AK50: 0
A51: Projeto preventivo (PPCI - Plano de Prevenção e Proteção Contra Incêndios) e Gás | C51: vb | D51: 1 | E51: =$B$8*2.56/2 -> 16420.262 | F51: Estimado | G51: =IFERROR(AVERAGEIFS($H51:$AI51,H$12:AI$12,"Referência"),"") -> 2.3549346 | H51: 0 | I51: =IF(H51=0,"",($B$10/H$10)*H51/H$8) | J51: 0 | K51: =IF(J51=0,"",($B$10/J$10)*J51/J$8) | L51: 40000 | M51: =IF(L51=0,"",($B$10/L$10)*L51/L$8) -> 2.5636276 | N51: 0 | O51: =IF(N51=0,"",($B$10/N$10)*N51/N$8) | P51: 0 | Q51: =IF(P51=0,"",($B$10/P$10)*P51/P$8) | R51: 0 | S51: =IF(R51=0,"",($B$10/R$10)*R51/R$8) | T51: 0 | U51: =IF(T51=0,"",($B$10/T$10)*T51/T$8) | V51: 0 | W51: =IF(V51=0,"",($B$10/V$10)*V51/V$8) | X51: 0 | Y51: =IF(X51=0,"",($B$10/X$10)*X51/X$8) | Z51: 21150 | AA51: =IF(Z51=0,"",($B$10/Z$10)*Z51/Z$8) -> 3.0161107 | AB51: 0 | AC51: =IF(AB51=0,"",($B$10/AB$10)*AB51/AB$8) | AD51: 33851.546 | AE51: =IF(AD51=0,"",($B$10/AD$10)*AD51/AD$8) -> 2.56 | AF51: 16420.262 | AG51: =IF(AF51=0,"",($B$10/AF$10)*AF51/AF$8) -> 1.28 | AI51: =IF(AH51=0,"",($B$10/AH$10)*AH51/AH$8) | AJ51: =E51*D51 -> 16420.262 | AK51: 1
A52: Projeto preventivo (PPCI) | C52: vb | F52: Não Solicitado | G52: =IFERROR(AVERAGEIFS($H52:$AI52,H$12:AI$12,"Referência"),"") -> 0.72957388 | H52: 0 | I52: =IF(H52=0,"",($B$10/H$10)*H52/H$8) | J52: 0 | K52: =IF(J52=0,"",($B$10/J$10)*J52/J$8) | L52: 0 | M52: =IF(L52=0,"",($B$10/L$10)*L52/L$8) | N52: 0 | O52: =IF(N52=0,"",($B$10/N$10)*N52/N$8) | P52: 0 | Q52: =IF(P52=0,"",($B$10/P$10)*P52/P$8) | R52: 0 | S52: =IF(R52=0,"",($B$10/R$10)*R52/R$8) | T52: 0 | U52: =IF(T52=0,"",($B$10/T$10)*T52/T$8) | V52: 0 | W52: =IF(V52=0,"",($B$10/V$10)*V52/V$8) | X52: 0 | Y52: =IF(X52=0,"",($B$10/X$10)*X52/X$8) | Z52: 0 | AA52: =IF(Z52=0,"",($B$10/Z$10)*Z52/Z$8) | AB52: 16015.696 | AC52: =IF(AB52=0,"",($B$10/AB$10)*AB52/AB$8) -> 0.72957388 | AD52: 0 | AE52: =IF(AD52=0,"",($B$10/AD$10)*AD52/AD$8) | AF52: 0 | AG52: =IF(AF52=0,"",($B$10/AF$10)*AF52/AF$8) | AI52: =IF(AH52=0,"",($B$10/AH$10)*AH52/AH$8) | AJ52: =E52*D52 -> 0 | AK52: 0
A53: Projeto de climatização/exaustão | C53: vb | F53: Não Solicitado | G53: =IFERROR(AVERAGEIFS($H53:$AI53,H$12:AI$12,"Referência"),"") -> 1.15 | H53: 0 | I53: =IF(H53=0,"",($B$10/H$10)*H53/H$8) | J53: 0 | K53: =IF(J53=0,"",($B$10/J$10)*J53/J$8) | L53: 0 | M53: =IF(L53=0,"",($B$10/L$10)*L53/L$8) | N53: 0 | O53: =IF(N53=0,"",($B$10/N$10)*N53/N$8) | P53: 0 | Q53: =IF(P53=0,"",($B$10/P$10)*P53/P$8) | R53: 0 | S53: =IF(R53=0,"",($B$10/R$10)*R53/R$8) | T53: 0 | U53: =IF(T53=0,"",($B$10/T$10)*T53/T$8) | V53: 0 | W53: =IF(V53=0,"",($B$10/V$10)*V53/V$8) | X53: 0 | Y53: =IF(X53=0,"",($B$10/X$10)*X53/X$8) | Z53: 0 | AA53: =IF(Z53=0,"",($B$10/Z$10)*Z53/Z$8) | AB53: 0 | AC53: =IF(AB53=0,"",($B$10/AB$10)*AB53/AB$8) | AD53: 15206.749 | AE53: =IF(AD53=0,"",($B$10/AD$10)*AD53/AD$8) -> 1.15 | AF53: 0 | AG53: =IF(AF53=0,"",($B$10/AF$10)*AF53/AF$8) | AI53: =IF(AH53=0,"",($B$10/AH$10)*AH53/AH$8) | AJ53: =E53*D53 -> 0 | AK53: 0
A54: Projeto de climatização | C54: vb | F54: Não Solicitado | G54: =IFERROR(AVERAGEIFS($H54:$AI54,H$12:AI$12,"Referência"),"") -> 0.69262314 | H54: 0 | I54: =IF(H54=0,"",($B$10/H$10)*H54/H$8) | J54: 0 | K54: =IF(J54=0,"",($B$10/J$10)*J54/J$8) | L54: 0 | M54: =IF(L54=0,"",($B$10/L$10)*L54/L$8) | N54: 0 | O54: =IF(N54=0,"",($B$10/N$10)*N54/N$8) | P54: 1000 | Q54: =IF(P54=0,"",($B$10/P$10)*P54/P$8) -> 0.1245625 | R54: 0 | S54: =IF(R54=0,"",($B$10/R$10)*R54/R$8) | T54: 16103.971 | U54: =IF(T54=0,"",($B$10/T$10)*T54/T$8) -> 0.89856958 | V54: 0 | W54: =IF(V54=0,"",($B$10/V$10)*V54/V$8) | X54: 1400 | Y54: =IF(X54=0,"",($B$10/X$10)*X54/X$8) -> 0.74794422 | Z54: 0 | AA54: =IF(Z54=0,"",($B$10/Z$10)*Z54/Z$8) | AB54: 21939.31 | AC54: =IF(AB54=0,"",($B$10/AB$10)*AB54/AB$8) -> 0.99941627 | AD54: 0 | AE54: =IF(AD54=0,"",($B$10/AD$10)*AD54/AD$8) | AF54: 0 | AG54: =IF(AF54=0,"",($B$10/AF$10)*AF54/AF$8) | AI54: =IF(AH54=0,"",($B$10/AH$10)*AH54/AH$8) | AJ54: =E54*D54 -> 0 | AK54: 0
A55: Projeto de exautão | C55: vb | F55: Não Solicitado | G55: =IFERROR(AVERAGEIFS($H55:$AI55,H$12:AI$12,"Referência"),"") -> 0.19988325 | H55: 0 | I55: =IF(H55=0,"",($B$10/H$10)*H55/H$8) | J55: 0 | K55: =IF(J55=0,"",($B$10/J$10)*J55/J$8) | L55: 0 | M55: =IF(L55=0,"",($B$10/L$10)*L55/L$8) | N55: 0 | O55: =IF(N55=0,"",($B$10/N$10)*N55/N$8) | P55: 0 | Q55: =IF(P55=0,"",($B$10/P$10)*P55/P$8) | R55: 0 | S55: =IF(R55=0,"",($B$10/R$10)*R55/R$8) | T55: 0 | U55: =IF(T55=0,"",($B$10/T$10)*T55/T$8) | V55: 0 | W55: =IF(V55=0,"",($B$10/V$10)*V55/V$8) | X55: 0 | Y55: =IF(X55=0,"",($B$10/X$10)*X55/X$8) | Z55: 0 | AA55: =IF(Z55=0,"",($B$10/Z$10)*Z55/Z$8) | AB55: 4387.862 | AC55: =IF(AB55=0,"",($B$10/AB$10)*AB55/AB$8) -> 0.19988325 | AD55: 0 | AE55: =IF(AD55=0,"",($B$10/AD$10)*AD55/AD$8) | AF55: 0 | AG55: =IF(AF55=0,"",($B$10/AF$10)*AF55/AF$8) | AI55: =IF(AH55=0,"",($B$10/AH$10)*AH55/AH$8) | AJ55: =E55*D55 -> 0 | AK55: 0
A56: Projeto de gás | C56: vb | F56: Não Solicitado | G56: =IFERROR(AVERAGEIFS($H56:$AI56,H$12:AI$12,"Referência"),"") -> 0.43974316 | H56: 0 | I56: =IF(H56=0,"",($B$10/H$10)*H56/H$8) | J56: 0 | K56: =IF(J56=0,"",($B$10/J$10)*J56/J$8) | L56: 0 | M56: =IF(L56=0,"",($B$10/L$10)*L56/L$8) | N56: 0 | O56: =IF(N56=0,"",($B$10/N$10)*N56/N$8) | P56: 0 | Q56: =IF(P56=0,"",($B$10/P$10)*P56/P$8) | R56: 0 | S56: =IF(R56=0,"",($B$10/R$10)*R56/R$8) | T56: 0 | U56: =IF(T56=0,"",($B$10/T$10)*T56/T$8) | V56: 0 | W56: =IF(V56=0,"",($B$10/V$10)*V56/V$8) | X56: 0 | Y56: =IF(X56=0,"",($B$10/X$10)*X56/X$8) | Z56: 0 | AA56: =IF(Z56=0,"",($B$10/Z$10)*Z56/Z$8) | AB56: 9653.2964 | AC56: =IF(AB56=0,"",($B$10/AB$10)*AB56/AB$8) -> 0.43974316 | AD56: 0 | AE56: =IF(AD56=0,"",($B$10/AD$10)*AD56/AD$8) | AF56: 0 | AG56: =IF(AF56=0,"",($B$10/AF$10)*AF56/AF$8) | AI56: =IF(AH56=0,"",($B$10/AH$10)*AH56/AH$8) | AJ56: =E56*D56 -> 0 | AK56: 0
A57: Projeto de Segurança | C57: vb | F57: Não Solicitado | G57: =IFERROR(AVERAGEIFS($H57:$AI57,H$12:AI$12,"Referência"),"") -> 0.61415409 | H57: 0 | I57: =IF(H57=0,"",($B$10/H$10)*H57/H$8) | J57: 0 | K57: =IF(J57=0,"",($B$10/J$10)*J57/J$8) | L57: 0 | M57: =IF(L57=0,"",($B$10/L$10)*L57/L$8) | N57: 0 | O57: =IF(N57=0,"",($B$10/N$10)*N57/N$8) | P57: 5000 | Q57: =IF(P57=0,"",($B$10/P$10)*P57/P$8) -> 0.62281252 | R57: 0 | S57: =IF(R57=0,"",($B$10/R$10)*R57/R$8) | T57: 0 | U57: =IF(T57=0,"",($B$10/T$10)*T57/T$8) | V57: 0 | W57: =IF(V57=0,"",($B$10/V$10)*V57/V$8) | X57: 0 | Y57: =IF(X57=0,"",($B$10/X$10)*X57/X$8) | Z57: 0 | AA57: =IF(Z57=0,"",($B$10/Z$10)*Z57/Z$8) | AB57: 13163.586 | AC57: =IF(AB57=0,"",($B$10/AB$10)*AB57/AB$8) -> 0.59964976 | AD57: 8198.4212 | AE57: =IF(AD57=0,"",($B$10/AD$10)*AD57/AD$8) -> 0.62 | AF57: 0 | AG57: =IF(AF57=0,"",($B$10/AF$10)*AF57/AF$8) | AI57: =IF(AH57=0,"",($B$10/AH$10)*AH57/AH$8) | AJ57: =E57*D57 -> 0 | AK57: 0
A58: Projeto pressurização | C58: vb | F58: Não Solicitado | G58: =IFERROR(AVERAGEIFS($H58:$AI58,H$12:AI$12,"Referência"),"") | H58: 0 | I58: =IF(H58=0,"",($B$10/H$10)*H58/H$8) | J58: 0 | K58: =IF(J58=0,"",($B$10/J$10)*J58/J$8) | L58: 0 | M58: =IF(L58=0,"",($B$10/L$10)*L58/L$8) | N58: 0 | O58: =IF(N58=0,"",($B$10/N$10)*N58/N$8) | P58: 0 | Q58: =IF(P58=0,"",($B$10/P$10)*P58/P$8) | R58: 0 | S58: =IF(R58=0,"",($B$10/R$10)*R58/R$8) | T58: 0 | U58: =IF(T58=0,"",($B$10/T$10)*T58/T$8) | V58: 0 | W58: =IF(V58=0,"",($B$10/V$10)*V58/V$8) | X58: 0 | Y58: =IF(X58=0,"",($B$10/X$10)*X58/X$8) | Z58: 0 | AA58: =IF(Z58=0,"",($B$10/Z$10)*Z58/Z$8) | AB58: 0 | AC58: =IF(AB58=0,"",($B$10/AB$10)*AB58/AB$8) | AD58: 0 | AE58: =IF(AD58=0,"",($B$10/AD$10)*AD58/AD$8) | AF58: 0 | AG58: =IF(AF58=0,"",($B$10/AF$10)*AF58/AF$8) | AI58: =IF(AH58=0,"",($B$10/AH$10)*AH58/AH$8) | AJ58: =E58*D58 -> 0 | AK58: 0
A59: Projetos - Complementares | E59: =SUMPRODUCT(D60:D68,E60:E68) -> 14239.446 | I59: =IF(H59=0,"",($B$10/H$10)*H59/H$8) | K59: =IF(J59=0,"",($B$10/J$10)*J59/J$8) | M59: =IF(L59=0,"",($B$10/L$10)*L59/L$8) | O59: =IF(N59=0,"",($B$10/N$10)*N59/N$8) | Q59: =IF(P59=0,"",($B$10/P$10)*P59/P$8) | S59: =IF(R59=0,"",($B$10/R$10)*R59/R$8) | U59: =IF(T59=0,"",($B$10/T$10)*T59/T$8) | W59: =IF(V59=0,"",($B$10/V$10)*V59/V$8) | Y59: =IF(X59=0,"",($B$10/X$10)*X59/X$8) | AA59: =IF(Z59=0,"",($B$10/Z$10)*Z59/Z$8) | AC59: =IF(AB59=0,"",($B$10/AB$10)*AB59/AB$8) | AE59: =IF(AD59=0,"",($B$10/AD$10)*AD59/AD$8) | AG59: =IF(AF59=0,"",($B$10/AF$10)*AF59/AF$8) | AI59: =IF(AH59=0,"",($B$10/AH$10)*AH59/AH$8) | AK59: 0
A60: Projeto de Impremeabilização | C60: vb | F60: Não Solicitado | G60: =IFERROR(AVERAGEIFS($H60:$AI60,H$12:AI$12,"Referência"),"") -> 1.1246935 | H60: 0 | I60: =IF(H60=0,"",($B$10/H$10)*H60/H$8) | J60: 0 | K60: =IF(J60=0,"",($B$10/J$10)*J60/J$8) | L60: 0 | M60: =IF(L60=0,"",($B$10/L$10)*L60/L$8) | N60: 0 | O60: =IF(N60=0,"",($B$10/N$10)*N60/N$8) | P60: 0 | Q60: =IF(P60=0,"",($B$10/P$10)*P60/P$8) | R60: 0 | S60: =IF(R60=0,"",($B$10/R$10)*R60/R$8) | T60: 0 | U60: =IF(T60=0,"",($B$10/T$10)*T60/T$8) | V60: 0 | W60: =IF(V60=0,"",($B$10/V$10)*V60/V$8) | X60: 0 | Y60: =IF(X60=0,"",($B$10/X$10)*X60/X$8) | Z60: 0 | AA60: =IF(Z60=0,"",($B$10/Z$10)*Z60/Z$8) | AB60: 23036.276 | AC60: =IF(AB60=0,"",($B$10/AB$10)*AB60/AB$8) -> 1.0493871 | AD60: 15867.912 | AE60: =IF(AD60=0,"",($B$10/AD$10)*AD60/AD$8) -> 1.2 | AF60: 0 | AG60: =IF(AF60=0,"",($B$10/AF$10)*AF60/AF$8) | AI60: =IF(AH60=0,"",($B$10/AH$10)*AH60/AH$8) | AJ60: =E60*D60 -> 0 | AK60: 0
A61: Projeto de esquadrias | C61: vb | F61: Não Solicitado | G61: =IFERROR(AVERAGEIFS($H61:$AI61,H$12:AI$12,"Referência"),"") -> 2.7347139 | H61: 0 | I61: =IF(H61=0,"",($B$10/H$10)*H61/H$8) | J61: 0 | K61: =IF(J61=0,"",($B$10/J$10)*J61/J$8) | L61: 0 | M61: =IF(L61=0,"",($B$10/L$10)*L61/L$8) | N61: 14272.375 | O61: =IF(N61=0,"",($B$10/N$10)*N61/N$8) -> 3.3031507 | P61: 26543.302 | Q61: =IF(P61=0,"",($B$10/P$10)*P61/P$8) -> 3.3063001 | R61: 0 | S61: =IF(R61=0,"",($B$10/R$10)*R61/R$8) | T61: 0 | U61: =IF(T61=0,"",($B$10/T$10)*T61/T$8) | V61: 0 | W61: =IF(V61=0,"",($B$10/V$10)*V61/V$8) | X61: 0 | Y61: =IF(X61=0,"",($B$10/X$10)*X61/X$8) | Z61: 0 | AA61: =IF(Z61=0,"",($B$10/Z$10)*Z61/Z$8) | AB61: 22378.096 | AC61: =IF(AB61=0,"",($B$10/AB$10)*AB61/AB$8) -> 1.0194046 | AD61: 43768.991 | AE61: =IF(AD61=0,"",($B$10/AD$10)*AD61/AD$8) -> 3.31 | AF61: 0 | AG61: =IF(AF61=0,"",($B$10/AF$10)*AF61/AF$8) | AI61: =IF(AH61=0,"",($B$10/AH$10)*AH61/AH$8) | AJ61: =E61*D61 -> 0 | AK61: 0
A62: Projeto de forro | C62: vb | F62: Não Solicitado | G62: =IFERROR(AVERAGEIFS($H62:$AI62,H$12:AI$12,"Referência"),"") -> 1.0094104 | H62: 0 | I62: =IF(H62=0,"",($B$10/H$10)*H62/H$8) | J62: 0 | K62: =IF(J62=0,"",($B$10/J$10)*J62/J$8) | L62: 0 | M62: =IF(L62=0,"",($B$10/L$10)*L62/L$8) | N62: 0 | O62: =IF(N62=0,"",($B$10/N$10)*N62/N$8) | P62: 0 | Q62: =IF(P62=0,"",($B$10/P$10)*P62/P$8) | R62: 0 | S62: =IF(R62=0,"",($B$10/R$10)*R62/R$8) | T62: 0 | U62: =IF(T62=0,"",($B$10/T$10)*T62/T$8) | V62: 0 | W62: =IF(V62=0,"",($B$10/V$10)*V62/V$8) | X62: 0 | Y62: =IF(X62=0,"",($B$10/X$10)*X62/X$8) | Z62: 0 | AA62: =IF(Z62=0,"",($B$10/Z$10)*Z62/Z$8) | AB62: 22158.703 | AC62: =IF(AB62=0,"",($B$10/AB$10)*AB62/AB$8) -> 1.0094104 | AD62: 0 | AE62: =IF(AD62=0,"",($B$10/AD$10)*AD62/AD$8) | AF62: 0 | AG62: =IF(AF62=0,"",($B$10/AF$10)*AF62/AF$8) | AI62: =IF(AH62=0,"",($B$10/AH$10)*AH62/AH$8) | AJ62: =E62*D62 -> 0 | AK62: 0
A63: Projeto acústico | C63: vb | F63: Não Solicitado | G63: =IFERROR(AVERAGEIFS($H63:$AI63,H$12:AI$12,"Referência"),"") -> 0.99941627 | H63: 0 | I63: =IF(H63=0,"",($B$10/H$10)*H63/H$8) | J63: 0 | K63: =IF(J63=0,"",($B$10/J$10)*J63/J$8) | L63: 0 | M63: =IF(L63=0,"",($B$10/L$10)*L63/L$8) | N63: 0 | O63: =IF(N63=0,"",($B$10/N$10)*N63/N$8) | P63: 0 | Q63: =IF(P63=0,"",($B$10/P$10)*P63/P$8) | R63: 0 | S63: =IF(R63=0,"",($B$10/R$10)*R63/R$8) | T63: 0 | U63: =IF(T63=0,"",($B$10/T$10)*T63/T$8) | V63: 0 | W63: =IF(V63=0,"",($B$10/V$10)*V63/V$8) | X63: 0 | Y63: =IF(X63=0,"",($B$10/X$10)*X63/X$8) | Z63: 0 | AA63: =IF(Z63=0,"",($B$10/Z$10)*Z63/Z$8) | AB63: 21939.31 | AC63: =IF(AB63=0,"",($B$10/AB$10)*AB63/AB$8) -> 0.99941627 | AD63: 0 | AE63: =IF(AD63=0,"",($B$10/AD$10)*AD63/AD$8) | AF63: 0 | AG63: =IF(AF63=0,"",($B$10/AF$10)*AF63/AF$8) | AI63: =IF(AH63=0,"",($B$10/AH$10)*AH63/AH$8) | AJ63: =E63*D63 -> 0 | AK63: 0
A64: Protjeto de Sonorização | C64: vb | F64: Não Solicitado | G64: =IFERROR(AVERAGEIFS($H64:$AI64,H$12:AI$12,"Referência"),"") -> 0.49970814 | H64: 0 | I64: =IF(H64=0,"",($B$10/H$10)*H64/H$8) | J64: 0 | K64: =IF(J64=0,"",($B$10/J$10)*J64/J$8) | L64: 0 | M64: =IF(L64=0,"",($B$10/L$10)*L64/L$8) | N64: 0 | O64: =IF(N64=0,"",($B$10/N$10)*N64/N$8) | P64: 0 | Q64: =IF(P64=0,"",($B$10/P$10)*P64/P$8) | R64: 0 | S64: =IF(R64=0,"",($B$10/R$10)*R64/R$8) | T64: 0 | U64: =IF(T64=0,"",($B$10/T$10)*T64/T$8) | V64: 0 | W64: =IF(V64=0,"",($B$10/V$10)*V64/V$8) | X64: 0 | Y64: =IF(X64=0,"",($B$10/X$10)*X64/X$8) | Z64: 0 | AA64: =IF(Z64=0,"",($B$10/Z$10)*Z64/Z$8) | AB64: 10969.655 | AC64: =IF(AB64=0,"",($B$10/AB$10)*AB64/AB$8) -> 0.49970814 | AD64: 0 | AE64: =IF(AD64=0,"",($B$10/AD$10)*AD64/AD$8) | AF64: 0 | AG64: =IF(AF64=0,"",($B$10/AF$10)*AF64/AF$8) | AI64: =IF(AH64=0,"",($B$10/AH$10)*AH64/AH$8) | AJ64: =E64*D64 -> 0 | AK64: 0
A65: Projeto de Piscina | C65: vb | F65: Não Solicitado | G65: =IFERROR(AVERAGEIFS($H65:$AI65,H$12:AI$12,"Referência"),"") -> 0.54370346 | H65: 0 | I65: =IF(H65=0,"",($B$10/H$10)*H65/H$8) | J65: 0 | K65: =IF(J65=0,"",($B$10/J$10)*J65/J$8) | L65: 0 | M65: =IF(L65=0,"",($B$10/L$10)*L65/L$8) | N65: 0 | O65: =IF(N65=0,"",($B$10/N$10)*N65/N$8) | P65: 4370.2006 | Q65: =IF(P65=0,"",($B$10/P$10)*P65/P$8) -> 0.54436313 | R65: 0 | S65: =IF(R65=0,"",($B$10/R$10)*R65/R$8) | T65: 10049.717 | U65: =IF(T65=0,"",($B$10/T$10)*T65/T$8) -> 0.56075424 | V65: 0 | W65: =IF(V65=0,"",($B$10/V$10)*V65/V$8) | X65: 0 | Y65: =IF(X65=0,"",($B$10/X$10)*X65/X$8) | Z65: 0 | AA65: =IF(Z65=0,"",($B$10/Z$10)*Z65/Z$8) | AB65: 11408.441 | AC65: =IF(AB65=0,"",($B$10/AB$10)*AB65/AB$8) -> 0.51969646 | AD65: 7272.793 | AE65: =IF(AD65=0,"",($B$10/AD$10)*AD65/AD$8) -> 0.55 | AF65: 0 | AG65: =IF(AF65=0,"",($B$10/AF$10)*AF65/AF$8) | AI65: =IF(AH65=0,"",($B$10/AH$10)*AH65/AH$8) | AJ65: =E65*D65 -> 0 | AK65: 0
A66: Projeto de comunicação visual | C66: vb | F66: Não Solicitado | G66: =IFERROR(AVERAGEIFS($H66:$AI66,H$12:AI$12,"Referência"),"") -> 1.0393992 | H66: 0 | I66: =IF(H66=0,"",($B$10/H$10)*H66/H$8) | J66: 0 | K66: =IF(J66=0,"",($B$10/J$10)*J66/J$8) | L66: 0 | M66: =IF(L66=0,"",($B$10/L$10)*L66/L$8) | N66: 0 | O66: =IF(N66=0,"",($B$10/N$10)*N66/N$8) | P66: 8500 | Q66: =IF(P66=0,"",($B$10/P$10)*P66/P$8) -> 1.0587813 | R66: 0 | S66: =IF(R66=0,"",($B$10/R$10)*R66/R$8) | T66: 0 | U66: =IF(T66=0,"",($B$10/T$10)*T66/T$8) | V66: 0 | W66: =IF(V66=0,"",($B$10/V$10)*V66/V$8) | X66: 0 | Y66: =IF(X66=0,"",($B$10/X$10)*X66/X$8) | Z66: 0 | AA66: =IF(Z66=0,"",($B$10/Z$10)*Z66/Z$8) | AB66: 21939.31 | AC66: =IF(AB66=0,"",($B$10/AB$10)*AB66/AB$8) -> 0.99941627 | AD66: 14016.656 | AE66: =IF(AD66=0,"",($B$10/AD$10)*AD66/AD$8) -> 1.06 | AF66: 0 | AG66: =IF(AF66=0,"",($B$10/AF$10)*AF66/AF$8) | AI66: =IF(AH66=0,"",($B$10/AH$10)*AH66/AH$8) | AJ66: =E66*D66 -> 0 | AK66: 0
A67: Projeto de Paisagismo | C67: vb | D67: 1 | E67: =$B$8*1.11 -> 14239.446 | F67: Estimado | G67: =IFERROR(AVERAGEIFS($H67:$AI67,H$12:AI$12,"Referência"),"") -> 1.2307453 | H67: 40500 | I67: =IF(H67=0,"",($B$10/H$10)*H67/H$8) -> 0.7052892 | J67: 0 | K67: =IF(J67=0,"",($B$10/J$10)*J67/J$8) | L67: 0 | M67: =IF(L67=0,"",($B$10/L$10)*L67/L$8) | N67: 0 | O67: =IF(N67=0,"",($B$10/N$10)*N67/N$8) | P67: 13800 | Q67: =IF(P67=0,"",($B$10/P$10)*P67/P$8) -> 1.7189626 | R67: 0 | S67: =IF(R67=0,"",($B$10/R$10)*R67/R$8) | T67: 0 | U67: =IF(T67=0,"",($B$10/T$10)*T67/T$8) | V67: 0 | W67: =IF(V67=0,"",($B$10/V$10)*V67/V$8) | X67: 0 | Y67: =IF(X67=0,"",($B$10/X$10)*X67/X$8) | Z67: 0 | AA67: =IF(Z67=0,"",($B$10/Z$10)*Z67/Z$8) | AB67: 19745.379 | AC67: =IF(AB67=0,"",($B$10/AB$10)*AB67/AB$8) -> 0.89947464 | AD67: 22744.007 | AE67: =IF(AD67=0,"",($B$10/AD$10)*AD67/AD$8) -> 1.72 | AF67: 14239.446 | AG67: =IF(AF67=0,"",($B$10/AF$10)*AF67/AF$8) -> 1.11 | AI67: =IF(AH67=0,"",($B$10/AH$10)*AH67/AH$8) | AJ67: =E67*D67 -> 14239.446 | AK67: 1
A68: Projeto de pavimentação | C68: vb | F68: Não Solicitado | G68: =IFERROR(AVERAGEIFS($H68:$AI68,H$12:AI$12,"Referência"),"") | H68: 0 | I68: =IF(H68=0,"",($B$10/H$10)*H68/H$8) | J68: 0 | K68: =IF(J68=0,"",($B$10/J$10)*J68/J$8) | L68: 0 | M68: =IF(L68=0,"",($B$10/L$10)*L68/L$8) | N68: 0 | O68: =IF(N68=0,"",($B$10/N$10)*N68/N$8) | P68: 0 | Q68: =IF(P68=0,"",($B$10/P$10)*P68/P$8) | R68: 0 | S68: =IF(R68=0,"",($B$10/R$10)*R68/R$8) | T68: 0 | U68: =IF(T68=0,"",($B$10/T$10)*T68/T$8) | V68: 0 | W68: =IF(V68=0,"",($B$10/V$10)*V68/V$8) | X68: 0 | Y68: =IF(X68=0,"",($B$10/X$10)*X68/X$8) | Z68: 0 | AA68: =IF(Z68=0,"",($B$10/Z$10)*Z68/Z$8) | AB68: 0 | AC68: =IF(AB68=0,"",($B$10/AB$10)*AB68/AB$8) | AD68: 0 | AE68: =IF(AD68=0,"",($B$10/AD$10)*AD68/AD$8) | AF68: 0 | AG68: =IF(AF68=0,"",($B$10/AF$10)*AF68/AF$8) | AI68: =IF(AH68=0,"",($B$10/AH$10)*AH68/AH$8) | AJ68: =E68*D68 -> 0 | AK68: 0
A69: Projetos - BIM | E69: =SUMPRODUCT(D70:D73,E70:E73) -> 0 | I69: =IF(H69=0,"",($B$10/H$10)*H69/H$8) | K69: =IF(J69=0,"",($B$10/J$10)*J69/J$8) | M69: =IF(L69=0,"",($B$10/L$10)*L69/L$8) | O69: =IF(N69=0,"",($B$10/N$10)*N69/N$8) | Q69: =IF(P69=0,"",($B$10/P$10)*P69/P$8) | S69: =IF(R69=0,"",($B$10/R$10)*R69/R$8) | U69: =IF(T69=0,"",($B$10/T$10)*T69/T$8) | W69: =IF(V69=0,"",($B$10/V$10)*V69/V$8) | Y69: =IF(X69=0,"",($B$10/X$10)*X69/X$8) | AA69: =IF(Z69=0,"",($B$10/Z$10)*Z69/Z$8) | AB69: 24352.634 | AC69: =IF(AB69=0,"",($B$10/AB$10)*AB69/AB$8) -> 1.1093521 | AE69: =IF(AD69=0,"",($B$10/AD$10)*AD69/AD$8) | AG69: =IF(AF69=0,"",($B$10/AF$10)*AF69/AF$8) | AI69: =IF(AH69=0,"",($B$10/AH$10)*AH69/AH$8) | AK69: 0
A70: Modelagem BIM arquitetônica | C70: vb | F70: Não Solicitado | G70: =IFERROR(AVERAGEIFS($H70:$AI70,H$12:AI$12,"Referência"),"") -> 1.49 | H70: 0 | I70: =IF(H70=0,"",($B$10/H$10)*H70/H$8) | J70: 0 | K70: =IF(J70=0,"",($B$10/J$10)*J70/J$8) | L70: 0 | M70: =IF(L70=0,"",($B$10/L$10)*L70/L$8) | N70: 0 | O70: =IF(N70=0,"",($B$10/N$10)*N70/N$8) | P70: 0 | Q70: =IF(P70=0,"",($B$10/P$10)*P70/P$8) | R70: 0 | S70: =IF(R70=0,"",($B$10/R$10)*R70/R$8) | T70: 0 | U70: =IF(T70=0,"",($B$10/T$10)*T70/T$8) | V70: 0 | W70: =IF(V70=0,"",($B$10/V$10)*V70/V$8) | X70: 0 | Y70: =IF(X70=0,"",($B$10/X$10)*X70/X$8) | Z70: 0 | AA70: =IF(Z70=0,"",($B$10/Z$10)*Z70/Z$8) | AC70: =IF(AB70=0,"",($B$10/AB$10)*AB70/AB$8) | AD70: 19702.657 | AE70: =IF(AD70=0,"",($B$10/AD$10)*AD70/AD$8) -> 1.49 | AF70: 0 | AG70: =IF(AF70=0,"",($B$10/AF$10)*AF70/AF$8) | AI70: =IF(AH70=0,"",($B$10/AH$10)*AH70/AH$8) | AJ70: =E70*D70 -> 0 | AK70: 0
A71: Modelagem BIM Complementares | C71: vb | F71: Não Solicitado | G71: =IFERROR(AVERAGEIFS($H71:$AI71,H$12:AI$12,"Referência"),"") -> 2.4900424 | H71: 0 | I71: =IF(H71=0,"",($B$10/H$10)*H71/H$8) | J71: 0 | K71: =IF(J71=0,"",($B$10/J$10)*J71/J$8) | L71: 0 | M71: =IF(L71=0,"",($B$10/L$10)*L71/L$8) | N71: 10754.031 | O71: =IF(N71=0,"",($B$10/N$10)*N71/N$8) -> 2.488877 | P71: 20000 | Q71: =IF(P71=0,"",($B$10/P$10)*P71/P$8) -> 2.4912501 | R71: 0 | S71: =IF(R71=0,"",($B$10/R$10)*R71/R$8) | T71: 0 | U71: =IF(T71=0,"",($B$10/T$10)*T71/T$8) | V71: 0 | W71: =IF(V71=0,"",($B$10/V$10)*V71/V$8) | X71: 0 | Y71: =IF(X71=0,"",($B$10/X$10)*X71/X$8) | Z71: 0 | AA71: =IF(Z71=0,"",($B$10/Z$10)*Z71/Z$8) | AB71: 0 | AC71: =IF(AB71=0,"",($B$10/AB$10)*AB71/AB$8) | AD71: 32925.917 | AE71: =IF(AD71=0,"",($B$10/AD$10)*AD71/AD$8) -> 2.49 | AF71: 0 | AG71: =IF(AF71=0,"",($B$10/AF$10)*AF71/AF$8) | AI71: =IF(AH71=0,"",($B$10/AH$10)*AH71/AH$8) | AJ71: =E71*D71 -> 0 | AK71: 0
A72: Compatibilização de Projetos BIM | C72: vb | F72: Não Solicitado | G72: =IFERROR(AVERAGEIFS($H72:$AI72,H$12:AI$12,"Referência"),"") -> 1.3665695 | H72: 0 | I72: =IF(H72=0,"",($B$10/H$10)*H72/H$8) | J72: 0 | K72: =IF(J72=0,"",($B$10/J$10)*J72/J$8) | L72: 0 | M72: =IF(L72=0,"",($B$10/L$10)*L72/L$8) | N72: 5901.0915 | O72: =IF(N72=0,"",($B$10/N$10)*N72/N$8) -> 1.3657289 | P72: 10974.66 | Q72: =IF(P72=0,"",($B$10/P$10)*P72/P$8) -> 1.3670311 | R72: 0 | S72: =IF(R72=0,"",($B$10/R$10)*R72/R$8) | T72: 0 | U72: =IF(T72=0,"",($B$10/T$10)*T72/T$8) | V72: 13800 | W72: =IF(V72=0,"",($B$10/V$10)*V72/V$8) -> 1.363518 | X72: 0 | Y72: =IF(X72=0,"",($B$10/X$10)*X72/X$8) | Z72: 0 | AA72: =IF(Z72=0,"",($B$10/Z$10)*Z72/Z$8) | AB72: 0 | AC72: =IF(AB72=0,"",($B$10/AB$10)*AB72/AB$8) | AD72: 18115.866 | AE72: =IF(AD72=0,"",($B$10/AD$10)*AD72/AD$8) -> 1.37 | AF72: 0 | AG72: =IF(AF72=0,"",($B$10/AF$10)*AF72/AF$8) | AI72: =IF(AH72=0,"",($B$10/AH$10)*AH72/AH$8) | AJ72: =E72*D72 -> 0 | AK72: 0
A73: Informações complementares de projetos | C73: vb | F73: Não Solicitado | G73: =IFERROR(AVERAGEIFS($H73:$AI73,H$12:AI$12,"Referência"),"") | H73: 0 | I73: =IF(H73=0,"",($B$10/H$10)*H73/H$8) | J73: 0 | K73: =IF(J73=0,"",($B$10/J$10)*J73/J$8) | L73: 0 | M73: =IF(L73=0,"",($B$10/L$10)*L73/L$8) | N73: 0 | O73: =IF(N73=0,"",($B$10/N$10)*N73/N$8) | P73: 0 | Q73: =IF(P73=0,"",($B$10/P$10)*P73/P$8) | R73: 0 | S73: =IF(R73=0,"",($B$10/R$10)*R73/R$8) | T73: 0 | U73: =IF(T73=0,"",($B$10/T$10)*T73/T$8) | V73: 0 | W73: =IF(V73=0,"",($B$10/V$10)*V73/V$8) | X73: 0 | Y73: =IF(X73=0,"",($B$10/X$10)*X73/X$8) | Z73: 0 | AA73: =IF(Z73=0,"",($B$10/Z$10)*Z73/Z$8) | AB73: 0 | AC73: =IF(AB73=0,"",($B$10/AB$10)*AB73/AB$8) | AE73: =IF(AD73=0,"",($B$10/AD$10)*AD73/AD$8) | AF73: 0 | AG73: =IF(AF73=0,"",($B$10/AF$10)*AF73/AF$8) | AI73: =IF(AH73=0,"",($B$10/AH$10)*AH73/AH$8) | AJ73: =E73*D73 -> 0 | AK73: 0
A74: CONSULTORIAS | E74: =SUMPRODUCT(D75:D81,E75:E81) -> 96000 | I74: =IF(H74=0,"",($B$10/H$10)*H74/H$8) | K74: =IF(J74=0,"",($B$10/J$10)*J74/J$8) | M74: =IF(L74=0,"",($B$10/L$10)*L74/L$8) | O74: =IF(N74=0,"",($B$10/N$10)*N74/N$8) | Q74: =IF(P74=0,"",($B$10/P$10)*P74/P$8) | S74: =IF(R74=0,"",($B$10/R$10)*R74/R$8) | U74: =IF(T74=0,"",($B$10/T$10)*T74/T$8) | W74: =IF(V74=0,"",($B$10/V$10)*V74/V$8) | Y74: =IF(X74=0,"",($B$10/X$10)*X74/X$8) | AA74: =IF(Z74=0,"",($B$10/Z$10)*Z74/Z$8) | AB74: 0 | AC74: =IF(AB74=0,"",($B$10/AB$10)*AB74/AB$8) | AE74: =IF(AD74=0,"",($B$10/AD$10)*AD74/AD$8) | AG74: =IF(AF74=0,"",($B$10/AF$10)*AF74/AF$8) | AI74: =IF(AH74=0,"",($B$10/AH$10)*AH74/AH$8) | AK74: 1
A75: Consultorias Técnicas de esquadrias | C75: vb | F75: Não Solicitado | G75: =IFERROR(AVERAGEIFS($H75:$AI75,H$12:AI$12,"Referência"),"") | H75: 0 | I75: =IF(H75=0,"",($B$10/H$10)*H75/H$8) | J75: 0 | K75: =IF(J75=0,"",($B$10/J$10)*J75/J$8) | L75: 0 | M75: =IF(L75=0,"",($B$10/L$10)*L75/L$8) | N75: 0 | O75: =IF(N75=0,"",($B$10/N$10)*N75/N$8) | P75: 0 | Q75: =IF(P75=0,"",($B$10/P$10)*P75/P$8) | R75: 0 | S75: =IF(R75=0,"",($B$10/R$10)*R75/R$8) | T75: 0 | U75: =IF(T75=0,"",($B$10/T$10)*T75/T$8) | V75: 0 | W75: =IF(V75=0,"",($B$10/V$10)*V75/V$8) | X75: 0 | Y75: =IF(X75=0,"",($B$10/X$10)*X75/X$8) | Z75: 0 | AA75: =IF(Z75=0,"",($B$10/Z$10)*Z75/Z$8) | AC75: =IF(AB75=0,"",($B$10/AB$10)*AB75/AB$8) | AE75: =IF(AD75=0,"",($B$10/AD$10)*AD75/AD$8) | AF75: 0 | AG75: =IF(AF75=0,"",($B$10/AF$10)*AF75/AF$8) | AI75: =IF(AH75=0,"",($B$10/AH$10)*AH75/AH$8) | AJ75: =E75*D75 -> 0 | AK75: 0
A76: Consultoria técnica de fachada | C76: vb | F76: Não Solicitado | G76: =IFERROR(AVERAGEIFS($H76:$AI76,H$12:AI$12,"Referência"),"") | H76: 0 | I76: =IF(H76=0,"",($B$10/H$10)*H76/H$8) | J76: 0 | K76: =IF(J76=0,"",($B$10/J$10)*J76/J$8) | L76: 0 | M76: =IF(L76=0,"",($B$10/L$10)*L76/L$8) | N76: 0 | O76: =IF(N76=0,"",($B$10/N$10)*N76/N$8) | P76: 0 | Q76: =IF(P76=0,"",($B$10/P$10)*P76/P$8) | R76: 0 | S76: =IF(R76=0,"",($B$10/R$10)*R76/R$8) | T76: 0 | U76: =IF(T76=0,"",($B$10/T$10)*T76/T$8) | V76: 0 | W76: =IF(V76=0,"",($B$10/V$10)*V76/V$8) | X76: 0 | Y76: =IF(X76=0,"",($B$10/X$10)*X76/X$8) | Z76: 0 | AA76: =IF(Z76=0,"",($B$10/Z$10)*Z76/Z$8) | AB76: 0 | AC76: =IF(AB76=0,"",($B$10/AB$10)*AB76/AB$8) | AE76: =IF(AD76=0,"",($B$10/AD$10)*AD76/AD$8) | AF76: 0 | AG76: =IF(AF76=0,"",($B$10/AF$10)*AF76/AF$8) | AI76: =IF(AH76=0,"",($B$10/AH$10)*AH76/AH$8) | AJ76: =E76*D76 -> 0 | AK76: 0
A77: consultoria técnica de legalização | C77: vb | D77: 1 | E77: 51000 | F77: Recebido | G77: =IFERROR(AVERAGEIFS($H77:$AI77,H$12:AI$12,"Referência"),"") -> 3.9755759 | H77: 0 | I77: =IF(H77=0,"",($B$10/H$10)*H77/H$8) | J77: 0 | K77: =IF(J77=0,"",($B$10/J$10)*J77/J$8) | L77: 0 | M77: =IF(L77=0,"",($B$10/L$10)*L77/L$8) | N77: 0 | O77: =IF(N77=0,"",($B$10/N$10)*N77/N$8) | P77: 0 | Q77: =IF(P77=0,"",($B$10/P$10)*P77/P$8) | R77: 0 | S77: =IF(R77=0,"",($B$10/R$10)*R77/R$8) | T77: 0 | U77: =IF(T77=0,"",($B$10/T$10)*T77/T$8) | V77: 0 | W77: =IF(V77=0,"",($B$10/V$10)*V77/V$8) | X77: 0 | Y77: =IF(X77=0,"",($B$10/X$10)*X77/X$8) | Z77: 0 | AA77: =IF(Z77=0,"",($B$10/Z$10)*Z77/Z$8) | AB77: 0 | AC77: =IF(AB77=0,"",($B$10/AB$10)*AB77/AB$8) | AE77: =IF(AD77=0,"",($B$10/AD$10)*AD77/AD$8) | AF77: 51000 | AG77: =IF(AF77=0,"",($B$10/AF$10)*AF77/AF$8) -> 3.9755759 | AI77: =IF(AH77=0,"",($B$10/AH$10)*AH77/AH$8) | AJ77: =E77*D77 -> 51000 | AK77: 1
A78: Orçamento e planejamento | C78: vb | D78: 1 | E78: 45000 | F78: Recebido | G78: =IFERROR(AVERAGEIFS($H78:$AI78,H$12:AI$12,"Referência"),"") -> 5.9365245 | H78: 56000 | I78: =IF(H78=0,"",($B$10/H$10)*H78/H$8) -> 0.9752147 | J78: 0 | K78: =IF(J78=0,"",($B$10/J$10)*J78/J$8) | L78: 147828.63 | M78: =IF(L78=0,"",($B$10/L$10)*L78/L$8) -> 9.474439 | N78: 0 | O78: =IF(N78=0,"",($B$10/N$10)*N78/N$8) | P78: 0 | Q78: =IF(P78=0,"",($B$10/P$10)*P78/P$8) | R78: 0 | S78: =IF(R78=0,"",($B$10/R$10)*R78/R$8) | T78: 84512.169 | U78: =IF(T78=0,"",($B$10/T$10)*T78/T$8) -> 4.7156111 | V78: 0 | W78: =IF(V78=0,"",($B$10/V$10)*V78/V$8) | X78: 21000 | Y78: =IF(X78=0,"",($B$10/X$10)*X78/X$8) -> 11.219163 | Z78: 32000 | AA78: =IF(Z78=0,"",($B$10/Z$10)*Z78/Z$8) -> 4.5633827 | AB78: 0 | AC78: =IF(AB78=0,"",($B$10/AB$10)*AB78/AB$8) | AD78: 93885.146 | AE78: =IF(AD78=0,"",($B$10/AD$10)*AD78/AD$8) -> 7.1 | AF78: 45000 | AG78: =IF(AF78=0,"",($B$10/AF$10)*AF78/AF$8) -> 3.5078611 | AI78: =IF(AH78=0,"",($B$10/AH$10)*AH78/AH$8) | AJ78: =E78*D78 -> 45000 | AK78: 1
A79: Consultoria técnica de qualidade | C79: vb | F79: Não Solicitado | G79: =IFERROR(AVERAGEIFS($H79:$AI79,H$12:AI$12,"Referência"),"") -> 1.960503 | H79: 0 | I79: =IF(H79=0,"",($B$10/H$10)*H79/H$8) | J79: 0 | K79: =IF(J79=0,"",($B$10/J$10)*J79/J$8) | L79: 0 | M79: =IF(L79=0,"",($B$10/L$10)*L79/L$8) | N79: 0 | O79: =IF(N79=0,"",($B$10/N$10)*N79/N$8) | P79: 0 | Q79: =IF(P79=0,"",($B$10/P$10)*P79/P$8) | R79: 0 | S79: =IF(R79=0,"",($B$10/R$10)*R79/R$8) | T79: 0 | U79: =IF(T79=0,"",($B$10/T$10)*T79/T$8) | V79: 0 | W79: =IF(V79=0,"",($B$10/V$10)*V79/V$8) | X79: 0 | Y79: =IF(X79=0,"",($B$10/X$10)*X79/X$8) | Z79: 0 | AA79: =IF(Z79=0,"",($B$10/Z$10)*Z79/Z$8) | AB79: 56000 | AC79: =IF(AB79=0,"",($B$10/AB$10)*AB79/AB$8) -> 2.551006 | AD79: 18115.866 | AE79: =IF(AD79=0,"",($B$10/AD$10)*AD79/AD$8) -> 1.37 | AF79: 0 | AG79: =IF(AF79=0,"",($B$10/AF$10)*AF79/AF$8) | AI79: =IF(AH79=0,"",($B$10/AH$10)*AH79/AH$8) | AJ79: =E79*D79 -> 0 | AK79: 0
A80: Auditoria de qualidade | C80: vb | F80: Não Solicitado | G80: =IFERROR(AVERAGEIFS($H80:$AI80,H$12:AI$12,"Referência"),"") -> 0.75706453 | H80: 4305 | I80: =IF(H80=0,"",($B$10/H$10)*H80/H$8) -> 0.07496963 | J80: 0 | K80: =IF(J80=0,"",($B$10/J$10)*J80/J$8) | L80: 0 | M80: =IF(L80=0,"",($B$10/L$10)*L80/L$8) | N80: 0 | O80: =IF(N80=0,"",($B$10/N$10)*N80/N$8) | P80: 0 | Q80: =IF(P80=0,"",($B$10/P$10)*P80/P$8) | R80: 0 | S80: =IF(R80=0,"",($B$10/R$10)*R80/R$8) | T80: 0 | U80: =IF(T80=0,"",($B$10/T$10)*T80/T$8) | V80: 0 | W80: =IF(V80=0,"",($B$10/V$10)*V80/V$8) | X80: 0 | Y80: =IF(X80=0,"",($B$10/X$10)*X80/X$8) | Z80: 0 | AA80: =IF(Z80=0,"",($B$10/Z$10)*Z80/Z$8) | AB80: 31592.606 | AC80: =IF(AB80=0,"",($B$10/AB$10)*AB80/AB$8) -> 1.4391594 | AE80: =IF(AD80=0,"",($B$10/AD$10)*AD80/AD$8) | AF80: 0 | AG80: =IF(AF80=0,"",($B$10/AF$10)*AF80/AF$8) | AI80: =IF(AH80=0,"",($B$10/AH$10)*AH80/AH$8) | AJ80: =E80*D80 -> 0 | AK80: 0
A81: Prevision | C81: vb | F81: Não Solicitado | G81: =IFERROR(AVERAGEIFS($H81:$AI81,H$12:AI$12,"Referência"),"") -> 2.0765384 | H81: 0 | I81: =IF(H81=0,"",($B$10/H$10)*H81/H$8) | J81: 0 | K81: =IF(J81=0,"",($B$10/J$10)*J81/J$8) | L81: 32400 | M81: =IF(L81=0,"",($B$10/L$10)*L81/L$8) -> 2.0765384 | N81: 0 | O81: =IF(N81=0,"",($B$10/N$10)*N81/N$8) | P81: 0 | Q81: =IF(P81=0,"",($B$10/P$10)*P81/P$8) | R81: 0 | S81: =IF(R81=0,"",($B$10/R$10)*R81/R$8) | T81: 0 | U81: =IF(T81=0,"",($B$10/T$10)*T81/T$8) | V81: 0 | W81: =IF(V81=0,"",($B$10/V$10)*V81/V$8) | X81: 0 | Y81: =IF(X81=0,"",($B$10/X$10)*X81/X$8) | Z81: 0 | AA81: =IF(Z81=0,"",($B$10/Z$10)*Z81/Z$8) | AB81: 0 | AC81: =IF(AB81=0,"",($B$10/AB$10)*AB81/AB$8) | AE81: =IF(AD81=0,"",($B$10/AD$10)*AD81/AD$8) | AF81: 0 | AG81: =IF(AF81=0,"",($B$10/AF$10)*AF81/AF$8) | AI81: =IF(AH81=0,"",($B$10/AH$10)*AH81/AH$8) | AJ81: =E81*D81 -> 0 | AK81: 0
A82: SERVIÇOS TÉCNICOS | E82: =SUMPRODUCT(D83:D111,E83:E111) -> 31924.826 | I82: =IF(H82=0,"",($B$10/H$10)*H82/H$8) | K82: =IF(J82=0,"",($B$10/J$10)*J82/J$8) | M82: =IF(L82=0,"",($B$10/L$10)*L82/L$8) | O82: =IF(N82=0,"",($B$10/N$10)*N82/N$8) | Q82: =IF(P82=0,"",($B$10/P$10)*P82/P$8) | S82: =IF(R82=0,"",($B$10/R$10)*R82/R$8) | U82: =IF(T82=0,"",($B$10/T$10)*T82/T$8) | W82: =IF(V82=0,"",($B$10/V$10)*V82/V$8) | Y82: =IF(X82=0,"",($B$10/X$10)*X82/X$8) | AA82: =IF(Z82=0,"",($B$10/Z$10)*Z82/Z$8) | AB82: 0 | AC82: =IF(AB82=0,"",($B$10/AB$10)*AB82/AB$8) | AE82: =IF(AD82=0,"",($B$10/AD$10)*AD82/AD$8) | AG82: =IF(AF82=0,"",($B$10/AF$10)*AF82/AF$8) | AI82: =IF(AH82=0,"",($B$10/AH$10)*AH82/AH$8) | AK82: 1
A83: Controle tecnológico do concreto | C83: Un | D83: =5107.97215808545/8*4 -> 2553.9861 | E83: 12.5 | F83: Não Solicitado | G83: =IFERROR(AVERAGEIFS($H83:$AI83,H$12:AI$12,"Referência"),"") -> 3.023141 | H83: 0 | I83: =IF(H83=0,"",($B$10/H$10)*H83/H$8) | J83: 0 | K83: =IF(J83=0,"",($B$10/J$10)*J83/J$8) | L83: 12.5 | M83: =IF(L83=0,"",($B$10/L$10)*L83/L$8) -> 0.00080113364 | N83: 0 | O83: =IF(N83=0,"",($B$10/N$10)*N83/N$8) | P83: 0 | Q83: =IF(P83=0,"",($B$10/P$10)*P83/P$8) | R83: 0 | S83: =IF(R83=0,"",($B$10/R$10)*R83/R$8) | T83: 0 | U83: =IF(T83=0,"",($B$10/T$10)*T83/T$8) | V83: 0 | W83: =IF(V83=0,"",($B$10/V$10)*V83/V$8) | X83: 0 | Y83: =IF(X83=0,"",($B$10/X$10)*X83/X$8) | Z83: 53314 | AA83: =IF(Z83=0,"",($B$10/Z$10)*Z83/Z$8) -> 7.6028807 | AC83: =IF(AB83=0,"",($B$10/AB$10)*AB83/AB$8) | AD83: 26450 | AE83: =IF(AD83=0,"",($B$10/AD$10)*AD83/AD$8) -> 2.0002632 | AF83: 31924.826 | AG83: =IF(AF83=0,"",($B$10/AF$10)*AF83/AF$8) -> 2.488619 | AI83: =IF(AH83=0,"",($B$10/AH$10)*AH83/AH$8) | AJ83: =E83*D83 -> 31924.826 | AK83: 1
A84: Ensaio de graute | C84: vb | F84: Não Solicitado | G84: =IFERROR(AVERAGEIFS($H84:$AI84,H$12:AI$12,"Referência"),"") -> 5.0888601 | H84: 0 | I84: =IF(H84=0,"",($B$10/H$10)*H84/H$8) | J84: 0 | K84: =IF(J84=0,"",($B$10/J$10)*J84/J$8) | L84: 26314.5 | M84: =IF(L84=0,"",($B$10/L$10)*L84/L$8) -> 1.6865145 | N84: 0 | O84: =IF(N84=0,"",($B$10/N$10)*N84/N$8) | P84: 0 | Q84: =IF(P84=0,"",($B$10/P$10)*P84/P$8) | R84: 0 | S84: =IF(R84=0,"",($B$10/R$10)*R84/R$8) | T84: 0 | U84: =IF(T84=0,"",($B$10/T$10)*T84/T$8) | V84: 0 | W84: =IF(V84=0,"",($B$10/V$10)*V84/V$8) | X84: 0 | Y84: =IF(X84=0,"",($B$10/X$10)*X84/X$8) | Z84: 0 | AA84: =IF(Z84=0,"",($B$10/Z$10)*Z84/Z$8) | AB84: 186400 | AC84: =IF(AB84=0,"",($B$10/AB$10)*AB84/AB$8) -> 8.4912057 | AE84: =IF(AD84=0,"",($B$10/AD$10)*AD84/AD$8) | AF84: 0 | AG84: =IF(AF84=0,"",($B$10/AF$10)*AF84/AF$8) | AI84: =IF(AH84=0,"",($B$10/AH$10)*AH84/AH$8) | AJ84: =E84*D84 -> 0 | AK84: 0
A85: Ensaio de argamassa | C85: vb | F85: Não Solicitado | G85: =IFERROR(AVERAGEIFS($H85:$AI85,H$12:AI$12,"Referência"),"") -> 1.4054287 | H85: 0 | I85: =IF(H85=0,"",($B$10/H$10)*H85/H$8) | J85: 0 | K85: =IF(J85=0,"",($B$10/J$10)*J85/J$8) | L85: 21928.75 | M85: =IF(L85=0,"",($B$10/L$10)*L85/L$8) -> 1.4054287 | N85: 0 | O85: =IF(N85=0,"",($B$10/N$10)*N85/N$8) | P85: 0 | Q85: =IF(P85=0,"",($B$10/P$10)*P85/P$8) | R85: 0 | S85: =IF(R85=0,"",($B$10/R$10)*R85/R$8) | T85: 0 | U85: =IF(T85=0,"",($B$10/T$10)*T85/T$8) | V85: 0 | W85: =IF(V85=0,"",($B$10/V$10)*V85/V$8) | X85: 0 | Y85: =IF(X85=0,"",($B$10/X$10)*X85/X$8) | Z85: 0 | AA85: =IF(Z85=0,"",($B$10/Z$10)*Z85/Z$8) | AB85: 0 | AC85: =IF(AB85=0,"",($B$10/AB$10)*AB85/AB$8) | AE85: =IF(AD85=0,"",($B$10/AD$10)*AD85/AD$8) | AF85: 0 | AG85: =IF(AF85=0,"",($B$10/AF$10)*AF85/AF$8) | AI85: =IF(AH85=0,"",($B$10/AH$10)*AH85/AH$8) | AJ85: =E85*D85 -> 0 | AK85: 0
A86: Prova de carga | C86: vb | F86: Não Solicitado | G86: =IFERROR(AVERAGEIFS($H86:$AI86,H$12:AI$12,"Referência"),"") -> 2.0501622 | H86: 0 | I86: =IF(H86=0,"",($B$10/H$10)*H86/H$8) | J86: 0 | K86: =IF(J86=0,"",($B$10/J$10)*J86/J$8) | L86: 30893.722 | M86: =IF(L86=0,"",($B$10/L$10)*L86/L$8) -> 1.98 | N86: 0 | O86: =IF(N86=0,"",($B$10/N$10)*N86/N$8) | P86: 0 | Q86: =IF(P86=0,"",($B$10/P$10)*P86/P$8) | R86: 0 | S86: =IF(R86=0,"",($B$10/R$10)*R86/R$8) | T86: 38000 | U86: =IF(T86=0,"",($B$10/T$10)*T86/T$8) -> 2.1203245 | V86: 0 | W86: =IF(V86=0,"",($B$10/V$10)*V86/V$8) | X86: 0 | Y86: =IF(X86=0,"",($B$10/X$10)*X86/X$8) | Z86: 0 | AA86: =IF(Z86=0,"",($B$10/Z$10)*Z86/Z$8) | AB86: 0 | AC86: =IF(AB86=0,"",($B$10/AB$10)*AB86/AB$8) | AE86: =IF(AD86=0,"",($B$10/AD$10)*AD86/AD$8) | AF86: 0 | AG86: =IF(AF86=0,"",($B$10/AF$10)*AF86/AF$8) | AI86: =IF(AH86=0,"",($B$10/AH$10)*AH86/AH$8) | AJ86: =E86*D86 -> 0 | AK86: 0
A87: Tese de Esquadrias | C87: vb | F87: Não Solicitado | G87: =IFERROR(AVERAGEIFS($H87:$AI87,H$12:AI$12,"Referência"),"") -> 2.264057 | H87: 0 | I87: =IF(H87=0,"",($B$10/H$10)*H87/H$8) | J87: 0 | K87: =IF(J87=0,"",($B$10/J$10)*J87/J$8) | L87: 35325.832 | M87: =IF(L87=0,"",($B$10/L$10)*L87/L$8) -> 2.264057 | N87: 0 | O87: =IF(N87=0,"",($B$10/N$10)*N87/N$8) | P87: 0 | Q87: =IF(P87=0,"",($B$10/P$10)*P87/P$8) | R87: 0 | S87: =IF(R87=0,"",($B$10/R$10)*R87/R$8) | T87: 0 | U87: =IF(T87=0,"",($B$10/T$10)*T87/T$8) | V87: 0 | W87: =IF(V87=0,"",($B$10/V$10)*V87/V$8) | X87: 0 | Y87: =IF(X87=0,"",($B$10/X$10)*X87/X$8) | Z87: 0 | AA87: =IF(Z87=0,"",($B$10/Z$10)*Z87/Z$8) | AB87: 0 | AC87: =IF(AB87=0,"",($B$10/AB$10)*AB87/AB$8) | AE87: =IF(AD87=0,"",($B$10/AD$10)*AD87/AD$8) | AF87: 0 | AG87: =IF(AF87=0,"",($B$10/AF$10)*AF87/AF$8) | AI87: =IF(AH87=0,"",($B$10/AH$10)*AH87/AH$8) | AJ87: =E87*D87 -> 0 | AK87: 0
A88: Ensiao de caixilho | C88: vb | F88: Não Solicitado | G88: =IFERROR(AVERAGEIFS($H88:$AI88,H$12:AI$12,"Referência"),"") -> 1.1320285 | H88: 0 | I88: =IF(H88=0,"",($B$10/H$10)*H88/H$8) | J88: 0 | K88: =IF(J88=0,"",($B$10/J$10)*J88/J$8) | L88: 17662.916 | M88: =IF(L88=0,"",($B$10/L$10)*L88/L$8) -> 1.1320285 | N88: 0 | O88: =IF(N88=0,"",($B$10/N$10)*N88/N$8) | P88: 0 | Q88: =IF(P88=0,"",($B$10/P$10)*P88/P$8) | R88: 0 | S88: =IF(R88=0,"",($B$10/R$10)*R88/R$8) | T88: 0 | U88: =IF(T88=0,"",($B$10/T$10)*T88/T$8) | V88: 0 | W88: =IF(V88=0,"",($B$10/V$10)*V88/V$8) | X88: 0 | Y88: =IF(X88=0,"",($B$10/X$10)*X88/X$8) | Z88: 0 | AA88: =IF(Z88=0,"",($B$10/Z$10)*Z88/Z$8) | AB88: 0 | AC88: =IF(AB88=0,"",($B$10/AB$10)*AB88/AB$8) | AE88: =IF(AD88=0,"",($B$10/AD$10)*AD88/AD$8) | AF88: 0 | AG88: =IF(AF88=0,"",($B$10/AF$10)*AF88/AF$8) | AI88: =IF(AH88=0,"",($B$10/AH$10)*AH88/AH$8) | AJ88: =E88*D88 -> 0 | AK88: 0
A89: Ensaio de guarda-corpo | C89: vb | F89: Não Solicitado | G89: =IFERROR(AVERAGEIFS($H89:$AI89,H$12:AI$12,"Referência"),"") -> 0.75468565 | H89: 0 | I89: =IF(H89=0,"",($B$10/H$10)*H89/H$8) | J89: 0 | K89: =IF(J89=0,"",($B$10/J$10)*J89/J$8) | L89: 11775.277 | M89: =IF(L89=0,"",($B$10/L$10)*L89/L$8) -> 0.75468565 | N89: 0 | O89: =IF(N89=0,"",($B$10/N$10)*N89/N$8) | P89: 0 | Q89: =IF(P89=0,"",($B$10/P$10)*P89/P$8) | R89: 0 | S89: =IF(R89=0,"",($B$10/R$10)*R89/R$8) | T89: 0 | U89: =IF(T89=0,"",($B$10/T$10)*T89/T$8) | V89: 0 | W89: =IF(V89=0,"",($B$10/V$10)*V89/V$8) | X89: 0 | Y89: =IF(X89=0,"",($B$10/X$10)*X89/X$8) | Z89: 0 | AA89: =IF(Z89=0,"",($B$10/Z$10)*Z89/Z$8) | AB89: 0 | AC89: =IF(AB89=0,"",($B$10/AB$10)*AB89/AB$8) | AE89: =IF(AD89=0,"",($B$10/AD$10)*AD89/AD$8) | AF89: 0 | AG89: =IF(AF89=0,"",($B$10/AF$10)*AF89/AF$8) | AI89: =IF(AH89=0,"",($B$10/AH$10)*AH89/AH$8) | AJ89: =E89*D89 -> 0 | AK89: 0
A90: Ensaio de arrancamento de reboco | C90: vb | F90: Não Solicitado | G90: =IFERROR(AVERAGEIFS($H90:$AI90,H$12:AI$12,"Referência"),"") -> 0.60374852 | H90: 0 | I90: =IF(H90=0,"",($B$10/H$10)*H90/H$8) | J90: 0 | K90: =IF(J90=0,"",($B$10/J$10)*J90/J$8) | L90: 9420.2218 | M90: =IF(L90=0,"",($B$10/L$10)*L90/L$8) -> 0.60374852 | N90: 0 | O90: =IF(N90=0,"",($B$10/N$10)*N90/N$8) | P90: 0 | Q90: =IF(P90=0,"",($B$10/P$10)*P90/P$8) | R90: 0 | S90: =IF(R90=0,"",($B$10/R$10)*R90/R$8) | T90: 0 | U90: =IF(T90=0,"",($B$10/T$10)*T90/T$8) | V90: 0 | W90: =IF(V90=0,"",($B$10/V$10)*V90/V$8) | X90: 0 | Y90: =IF(X90=0,"",($B$10/X$10)*X90/X$8) | Z90: 0 | AA90: =IF(Z90=0,"",($B$10/Z$10)*Z90/Z$8) | AB90: 0 | AC90: =IF(AB90=0,"",($B$10/AB$10)*AB90/AB$8) | AE90: =IF(AD90=0,"",($B$10/AD$10)*AD90/AD$8) | AF90: 0 | AG90: =IF(AF90=0,"",($B$10/AF$10)*AF90/AF$8) | AI90: =IF(AH90=0,"",($B$10/AH$10)*AH90/AH$8) | AJ90: =E90*D90 -> 0 | AK90: 0
A91: Ensaio de arrancamento revestimento cerâmico | C91: vb | F91: Não Solicitado | G91: =IFERROR(AVERAGEIFS($H91:$AI91,H$12:AI$12,"Referência"),"") -> 0.67921709 | H91: 0 | I91: =IF(H91=0,"",($B$10/H$10)*H91/H$8) | J91: 0 | K91: =IF(J91=0,"",($B$10/J$10)*J91/J$8) | L91: 10597.75 | M91: =IF(L91=0,"",($B$10/L$10)*L91/L$8) -> 0.67921709 | N91: 0 | O91: =IF(N91=0,"",($B$10/N$10)*N91/N$8) | P91: 0 | Q91: =IF(P91=0,"",($B$10/P$10)*P91/P$8) | R91: 0 | S91: =IF(R91=0,"",($B$10/R$10)*R91/R$8) | T91: 0 | U91: =IF(T91=0,"",($B$10/T$10)*T91/T$8) | V91: 0 | W91: =IF(V91=0,"",($B$10/V$10)*V91/V$8) | X91: 0 | Y91: =IF(X91=0,"",($B$10/X$10)*X91/X$8) | Z91: 0 | AA91: =IF(Z91=0,"",($B$10/Z$10)*Z91/Z$8) | AB91: 0 | AC91: =IF(AB91=0,"",($B$10/AB$10)*AB91/AB$8) | AE91: =IF(AD91=0,"",($B$10/AD$10)*AD91/AD$8) | AF91: 0 | AG91: =IF(AF91=0,"",($B$10/AF$10)*AF91/AF$8) | AI91: =IF(AH91=0,"",($B$10/AH$10)*AH91/AH$8) | AJ91: =E91*D91 -> 0 | AK91: 0
A92: Ensaio de arrancamento fachada | C92: vb | F92: Não Solicitado | G92: =IFERROR(AVERAGEIFS($H92:$AI92,H$12:AI$12,"Referência"),"") -> 0.79241994 | H92: 0 | I92: =IF(H92=0,"",($B$10/H$10)*H92/H$8) | J92: 0 | K92: =IF(J92=0,"",($B$10/J$10)*J92/J$8) | L92: 12364.041 | M92: =IF(L92=0,"",($B$10/L$10)*L92/L$8) -> 0.79241994 | N92: 0 | O92: =IF(N92=0,"",($B$10/N$10)*N92/N$8) | P92: 0 | Q92: =IF(P92=0,"",($B$10/P$10)*P92/P$8) | R92: 0 | S92: =IF(R92=0,"",($B$10/R$10)*R92/R$8) | T92: 0 | U92: =IF(T92=0,"",($B$10/T$10)*T92/T$8) | V92: 0 | W92: =IF(V92=0,"",($B$10/V$10)*V92/V$8) | X92: 0 | Y92: =IF(X92=0,"",($B$10/X$10)*X92/X$8) | Z92: 0 | AA92: =IF(Z92=0,"",($B$10/Z$10)*Z92/Z$8) | AB92: 0 | AC92: =IF(AB92=0,"",($B$10/AB$10)*AB92/AB$8) | AE92: =IF(AD92=0,"",($B$10/AD$10)*AD92/AD$8) | AF92: 0 | AG92: =IF(AF92=0,"",($B$10/AF$10)*AF92/AF$8) | AI92: =IF(AH92=0,"",($B$10/AH$10)*AH92/AH$8) | AJ92: =E92*D92 -> 0 | AK92: 0
A93: Ensaio de arrancamento de gancho da cobertura | C93: vb | F93: Não Solicitado | G93: =IFERROR(AVERAGEIFS($H93:$AI93,H$12:AI$12,"Referência"),"") -> 0.37734283 | H93: 0 | I93: =IF(H93=0,"",($B$10/H$10)*H93/H$8) | J93: 0 | K93: =IF(J93=0,"",($B$10/J$10)*J93/J$8) | L93: 5887.6386 | M93: =IF(L93=0,"",($B$10/L$10)*L93/L$8) -> 0.37734283 | N93: 0 | O93: =IF(N93=0,"",($B$10/N$10)*N93/N$8) | P93: 0 | Q93: =IF(P93=0,"",($B$10/P$10)*P93/P$8) | R93: 0 | S93: =IF(R93=0,"",($B$10/R$10)*R93/R$8) | T93: 0 | U93: =IF(T93=0,"",($B$10/T$10)*T93/T$8) | V93: 0 | W93: =IF(V93=0,"",($B$10/V$10)*V93/V$8) | X93: 0 | Y93: =IF(X93=0,"",($B$10/X$10)*X93/X$8) | Z93: 0 | AA93: =IF(Z93=0,"",($B$10/Z$10)*Z93/Z$8) | AB93: 0 | AC93: =IF(AB93=0,"",($B$10/AB$10)*AB93/AB$8) | AE93: =IF(AD93=0,"",($B$10/AD$10)*AD93/AD$8) | AF93: 0 | AG93: =IF(AF93=0,"",($B$10/AF$10)*AF93/AF$8) | AI93: =IF(AH93=0,"",($B$10/AH$10)*AH93/AH$8) | AJ93: =E93*D93 -> 0 | AK93: 0
A94: Ensaio de prisma (oco e cheio) | C94: vb | F94: Não Solicitado | G94: =IFERROR(AVERAGEIFS($H94:$AI94,H$12:AI$12,"Referência"),"") -> 0.83015422 | H94: 0 | I94: =IF(H94=0,"",($B$10/H$10)*H94/H$8) | J94: 0 | K94: =IF(J94=0,"",($B$10/J$10)*J94/J$8) | L94: 12952.805 | M94: =IF(L94=0,"",($B$10/L$10)*L94/L$8) -> 0.83015422 | N94: 0 | O94: =IF(N94=0,"",($B$10/N$10)*N94/N$8) | P94: 0 | Q94: =IF(P94=0,"",($B$10/P$10)*P94/P$8) | R94: 0 | S94: =IF(R94=0,"",($B$10/R$10)*R94/R$8) | T94: 0 | U94: =IF(T94=0,"",($B$10/T$10)*T94/T$8) | V94: 0 | W94: =IF(V94=0,"",($B$10/V$10)*V94/V$8) | X94: 0 | Y94: =IF(X94=0,"",($B$10/X$10)*X94/X$8) | Z94: 0 | AA94: =IF(Z94=0,"",($B$10/Z$10)*Z94/Z$8) | AB94: 0 | AC94: =IF(AB94=0,"",($B$10/AB$10)*AB94/AB$8) | AE94: =IF(AD94=0,"",($B$10/AD$10)*AD94/AD$8) | AF94: 0 | AG94: =IF(AF94=0,"",($B$10/AF$10)*AF94/AF$8) | AI94: =IF(AH94=0,"",($B$10/AH$10)*AH94/AH$8) | AJ94: =E94*D94 -> 0 | AK94: 0
A95: Ensaio de bloco estrutual | C95: vb | F95: Não Solicitado | G95: =IFERROR(AVERAGEIFS($H95:$AI95,H$12:AI$12,"Referência"),"") -> 0.81506051 | H95: 0 | I95: =IF(H95=0,"",($B$10/H$10)*H95/H$8) | J95: 0 | K95: =IF(J95=0,"",($B$10/J$10)*J95/J$8) | L95: 12717.299 | M95: =IF(L95=0,"",($B$10/L$10)*L95/L$8) -> 0.81506051 | N95: 0 | O95: =IF(N95=0,"",($B$10/N$10)*N95/N$8) | P95: 0 | Q95: =IF(P95=0,"",($B$10/P$10)*P95/P$8) | R95: 0 | S95: =IF(R95=0,"",($B$10/R$10)*R95/R$8) | T95: 0 | U95: =IF(T95=0,"",($B$10/T$10)*T95/T$8) | V95: 0 | W95: =IF(V95=0,"",($B$10/V$10)*V95/V$8) | X95: 0 | Y95: =IF(X95=0,"",($B$10/X$10)*X95/X$8) | Z95: 0 | AA95: =IF(Z95=0,"",($B$10/Z$10)*Z95/Z$8) | AB95: 0 | AC95: =IF(AB95=0,"",($B$10/AB$10)*AB95/AB$8) | AE95: =IF(AD95=0,"",($B$10/AD$10)*AD95/AD$8) | AF95: 0 | AG95: =IF(AF95=0,"",($B$10/AF$10)*AF95/AF$8) | AI95: =IF(AH95=0,"",($B$10/AH$10)*AH95/AH$8) | AJ95: =E95*D95 -> 0 | AK95: 0
... A111: Teste de Acoragem | C111: vb | F111: Não Solicitado | G111: =IFERROR(AVERAGEIFS($H111:$AI111,H$12:AI$12,"Referência"),"") | H111: 0 | I111: =IF(H111=0,"",($B$10/H$10)*H111/H$8) | J111: 0 | K111: =IF(J111=0,"",($B$10/J$10)*J111/J$8) | L111: 0 | M111: =IF(L111=0,"",($B$10/L$10)*L111/L$8) | N111: 0 | O111: =IF(N111=0,"",($B$10/N$10)*N111/N$8) | P111: 0 | Q111: =IF(P111=0,"",($B$10/P$10)*P111/P$8) | R111: 0 | S111: =IF(R111=0,"",($B$10/R$10)*R111/R$8) | T111: 0 | U111: =IF(T111=0,"",($B$10/T$10)*T111/T$8) | V111: 0 | W111: =IF(V111=0,"",($B$10/V$10)*V111/V$8) | X111: 0 | Y111: =IF(X111=0,"",($B$10/X$10)*X111/X$8) | Z111: 0 | AA111: =IF(Z111=0,"",($B$10/Z$10)*Z111/Z$8) | AB111: 0 | AC111: =IF(AB111=0,"",($B$10/AB$10)*AB111/AB$8) | AE111: =IF(AD111=0,"",($B$10/AD$10)*AD111/AD$8) | AF111: 0 | AG111: =IF(AF111=0,"",($B$10/AF$10)*AF111/AF$8) | AI111: =IF(AH111=0,"",($B$10/AH$10)*AH111/AH$8) | AJ111: =E111*D111 -> 0 | AK111: 0
A112: TEC 02 – TAXAS, DOCUMENTOS | I112: =IF(H112=0,"",($B$10/H$10)*H112/H$8) | K112: =IF(J112=0,"",($B$10/J$10)*J112/J$8) | M112: =IF(L112=0,"",($B$10/L$10)*L112/L$8) | O112: =IF(N112=0,"",($B$10/N$10)*N112/N$8) | Q112: =IF(P112=0,"",($B$10/P$10)*P112/P$8) | S112: =IF(R112=0,"",($B$10/R$10)*R112/R$8) | U112: =IF(T112=0,"",($B$10/T$10)*T112/T$8) | W112: =IF(V112=0,"",($B$10/V$10)*V112/V$8) | Y112: =IF(X112=0,"",($B$10/X$10)*X112/X$8) | AA112: =IF(Z112=0,"",($B$10/Z$10)*Z112/Z$8) | AB112: 0 | AC112: =IF(AB112=0,"",($B$10/AB$10)*AB112/AB$8) | AE112: =IF(AD112=0,"",($B$10/AD$10)*AD112/AD$8) | AG112: =IF(AF112=0,"",($B$10/AF$10)*AF112/AF$8) | AI112: =IF(AH112=0,"",($B$10/AH$10)*AH112/AH$8) | AK112: 0
A113: TAXAS E DOCUMENTOS | E113: =SUMPRODUCT(D114,E114) -> 25000 | I113: =IF(H113=0,"",($B$10/H$10)*H113/H$8) | K113: =IF(J113=0,"",($B$10/J$10)*J113/J$8) | M113: =IF(L113=0,"",($B$10/L$10)*L113/L$8) | O113: =IF(N113=0,"",($B$10/N$10)*N113/N$8) | Q113: =IF(P113=0,"",($B$10/P$10)*P113/P$8) | S113: =IF(R113=0,"",($B$10/R$10)*R113/R$8) | U113: =IF(T113=0,"",($B$10/T$10)*T113/T$8) | W113: =IF(V113=0,"",($B$10/V$10)*V113/V$8) | Y113: =IF(X113=0,"",($B$10/X$10)*X113/X$8) | AA113: =IF(Z113=0,"",($B$10/Z$10)*Z113/Z$8) | AC113: =IF(AB113=0,"",($B$10/AB$10)*AB113/AB$8) | AE113: =IF(AD113=0,"",($B$10/AD$10)*AD113/AD$8) | AG113: =IF(AF113=0,"",($B$10/AF$10)*AF113/AF$8) | AI113: =IF(AH113=0,"",($B$10/AH$10)*AH113/AH$8) | AK113: 0
A114: Despesas de Seguros | C114: vb | D114: 1 | E114: 25000 | F114: Recebido | G114: =IFERROR(AVERAGEIFS($H114:$AI114,H$12:AI$12,"Referência"),"") -> 3.0531661 | H114: 401578 | I114: =IF(H114=0,"",($B$10/H$10)*H114/H$8) -> 6.9932995 | J114: 117488.55 | K114: =IF(J114=0,"",($B$10/J$10)*J114/J$8) -> 5.795077 | L114: 33546.213 | M114: =IF(L114=0,"",($B$10/L$10)*L114/L$8) -> 2.15 | N114: 0 | O114: =IF(N114=0,"",($B$10/N$10)*N114/N$8) | P114: 18000 | Q114: =IF(P114=0,"",($B$10/P$10)*P114/P$8) -> 2.2421251 | R114: 0 | S114: =IF(R114=0,"",($B$10/R$10)*R114/R$8) | T114: 47151.412 | U114: =IF(T114=0,"",($B$10/T$10)*T114/T$8) -> 2.6309551 | V114: 18093.474 | W114: =IF(V114=0,"",($B$10/V$10)*V114/V$8) -> 1.7877374 | X114: 0 | Y114: =IF(X114=0,"",($B$10/X$10)*X114/X$8) | Z114: 12134.785 | AA114: =IF(Z114=0,"",($B$10/Z$10)*Z114/Z$8) -> 1.7304895 | AC114: =IF(AB114=0,"",($B$10/AB$10)*AB114/AB$8) | AD114: 29091.172 | AE114: =IF(AD114=0,"",($B$10/AD$10)*AD114/AD$8) -> 2.2 | AF114: 25000 | AG114: =IF(AF114=0,"",($B$10/AF$10)*AF114/AF$8) -> 1.9488117 | AI114: =IF(AH114=0,"",($B$10/AH$10)*AH114/AH$8) | AJ114: =E114*D114 -> 25000 | AK114: 1
A115: Aprovação e legalização | E115: =SUMPRODUCT(D116:D120,E116:E120) -> 61600 | I115: =IF(H115=0,"",($B$10/H$10)*H115/H$8) | K115: =IF(J115=0,"",($B$10/J$10)*J115/J$8) | M115: =IF(L115=0,"",($B$10/L$10)*L115/L$8) | O115: =IF(N115=0,"",($B$10/N$10)*N115/N$8) | Q115: =IF(P115=0,"",($B$10/P$10)*P115/P$8) | S115: =IF(R115=0,"",($B$10/R$10)*R115/R$8) | U115: =IF(T115=0,"",($B$10/T$10)*T115/T$8) | W115: =IF(V115=0,"",($B$10/V$10)*V115/V$8) | Y115: =IF(X115=0,"",($B$10/X$10)*X115/X$8) | AA115: =IF(Z115=0,"",($B$10/Z$10)*Z115/Z$8) | AB115: 96752.357 | AC115: =IF(AB115=0,"",($B$10/AB$10)*AB115/AB$8) -> 4.4074258 | AE115: =IF(AD115=0,"",($B$10/AD$10)*AD115/AD$8) | AG115: =IF(AF115=0,"",($B$10/AF$10)*AF115/AF$8) | AI115: =IF(AH115=0,"",($B$10/AH$10)*AH115/AH$8) | AK115: 0
...

Sheet ESQUADRIAS
A1: Obra | B1: ='Obra '!D1 -> Brisa da armação
A2: Empresa | B2: ='Obra '!D2 -> HACASA
A3: Revisão | B3: ='Obra '!D3 -> R00 - Letícia
A4: LEVANTAMENTO ESQUADRIAS
A5: Aplicação | B5: Descrição do Material | C5: Largura (Cm) | D5: Altura (Cm) | E5: Total m2/m | F5: Total un | H5: Pavimentos | R5: Visus | V5: Fornecedor 1 | Y5: Fornecedor 2
H6: Térreo | I6: Garagem G1 | J6: Garagem G2 | K6: Garagem G3 | L6: Garagem G4 | M6: Tipo 01 (1x) | N6: Tipo 02 (11x) | O6: Tipo 03 (01x) | P6: Rooftop | R6: Largura (Cm) | S6: Altura (Cm) | T6: Total m2/m | V6: Custo Unitário | W6: Cuto Total | Y6: Custo Unitário | Z6: Cuto Total
H7: 1 | I7: 1 | J7: 1 | K7: 1 | L7: 1 | M7: 1 | N7: 11 | O7: 1 | P7: 1
A8: Porta Madeira | B8: P1 - PORTA DE ABRIR, 1 FOLHA, MADEIRA MACICA, 90 x 210 cm | C8: 0.9 | D8: 2.1 | E8: =IF(D8=0,SUMPRODUCT($H$7:$P$7,$H8:$P8)*(C8),SUMPRODUCT($H$7:$P$7,$H8:$P8)*(C8*D8)) -> 0 | F8: =SUMPRODUCT($H$7:$P$7,$H8:$P8) -> 0 | T8: 0 | W8: =V8*F8 -> 0 | Z8: =Y8*I8 -> 0
A9: Porta Madeira | B9: P2 - PORTA DE ABRIR, 1 FOLHA, MADEIRA SEMI-OCA, 80 x 210 cm | C9: 0.8 | D9: 2.1 | E9: =IF(D9=0,SUMPRODUCT($H$7:$P$7,$H9:$P9)*(C9),SUMPRODUCT($H$7:$P$7,$H9:$P9)*(C9*D9)) -> 0 | F9: =SUMPRODUCT($H$7:$P$7,$H9:$P9) -> 0 | T9: 0 | W9: =V9*F9 -> 0 | Z9: =Y9*I9 -> 0
A10: Porta Madeira | B10: P3 - PORTA DE ABRIR, 1 FOLHA, MADEIRA SEMI-OCA, 70 x 210 cm | C10: 0.7 | D10: 2.1 | E10: =IF(D10=0,SUMPRODUCT($H$7:$P$7,$H10:$P10)*(C10),SUMPRODUCT($H$7:$P$7,$H10:$P10)*(C10*D10)) -> 0 | F10: =SUMPRODUCT($H$7:$P$7,$H10:$P10) -> 0 | T10: 0 | W10: =V10*F10 -> 0 | Z10: =Y10*I10 -> 0
A11: Porta Madeira | B11: PORTA DE CORRER, 1 FOLHA, MADEIRA, 80 x 210 cm | C11: 0.8 | D11: 2.1 | E11: =IF(D11=0,SUMPRODUCT($H$7:$P$7,$H11:$P11)*(C11),SUMPRODUCT($H$7:$P$7,$H11:$P11)*(C11*D11)) -> 0 | F11: =SUMPRODUCT($H$7:$P$7,$H11:$P11) -> 0 | T11: 0 | W11: =V11*F11 -> 0 | Z11: =Y11*I11 -> 0
A12: Porta Madeira | E12: =IF(D12=0,SUMPRODUCT($H$7:$P$7,$H12:$P12)*(C12),SUMPRODUCT($H$7:$P$7,$H12:$P12)*(C12*D12)) -> 0 | F12: =SUMPRODUCT($H$7:$P$7,$H12:$P12) -> 0 | T12: 0 | W12: =V12*F12 -> 0 | Z12: =Y12*I12 -> 0
A13: Porta Madeira | E13: =IF(D13=0,SUMPRODUCT($H$7:$P$7,$H13:$P13)*(C13),SUMPRODUCT($H$7:$P$7,$H13:$P13)*(C13*D13)) -> 0 | F13: =SUMPRODUCT($H$7:$P$7,$H13:$P13) -> 0 | T13: 0 | W13: =V13*F13 -> 0 | Z13: =Y13*I13 -> 0
A14: Corrimão Madeira (m) | B14: CORRIMÃO ESCADA_PAREDE - MADEIRA | E14: =IF(D14=0,SUMPRODUCT($H$7:$P$7,$H14:$P14)*(C14),SUMPRODUCT($H$7:$P$7,$H14:$P14)*(C14*D14)) -> 0 | F14: =SUMPRODUCT($H$7:$P$7,$H14:$P14) -> 0 | T14: 0 | W14: =V14*F14 -> 0 | Z14: =Y14*I14 -> 0
A15: Corrimão Madeira (m) | E15: =IF(D15=0,SUMPRODUCT($H$7:$P$7,$H15:$P15)*(C15),SUMPRODUCT($H$7:$P$7,$H15:$P15)*(C15*D15)) -> 0 | F15: =SUMPRODUCT($H$7:$P$7,$H15:$P15) -> 0 | T15: 0 | W15: =V15*F15 -> 0 | Z15: =Y15*I15 -> 0
A16: Corrimão Madeira (m) | E16: =IF(D16=0,SUMPRODUCT($H$7:$P$7,$H16:$P16)*(C16),SUMPRODUCT($H$7:$P$7,$H16:$P16)*(C16*D16)) -> 0 | F16: =SUMPRODUCT($H$7:$P$7,$H16:$P16) -> 0 | T16: 0 | W16: =V16*F16 -> 0 | Z16: =Y16*I16 -> 0
A17: Corrimão Madeira (m) | E17: =IF(D17=0,SUMPRODUCT($H$7:$P$7,$H17:$P17)*(C17),SUMPRODUCT($H$7:$P$7,$H17:$P17)*(C17*D17)) -> 0 | F17: =SUMPRODUCT($H$7:$P$7,$H17:$P17) -> 0 | T17: 0 | W17: =V17*F17 -> 0 | Z17: =Y17*I17 -> 0
A18: Corrimão Madeira (m) | E18: =IF(D18=0,SUMPRODUCT($H$7:$P$7,$H18:$P18)*(C18),SUMPRODUCT($H$7:$P$7,$H18:$P18)*(C18*D18)) -> 0 | F18: =SUMPRODUCT($H$7:$P$7,$H18:$P18) -> 0 | T18: 0 | W18: =V18*F18 -> 0 | Z18: =Y18*I18 -> 0
A19: Corrimão Madeira (m) | E19: =IF(D19=0,SUMPRODUCT($H$7:$P$7,$H19:$P19)*(C19),SUMPRODUCT($H$7:$P$7,$H19:$P19)*(C19*D19)) -> 0 | F19: =SUMPRODUCT($H$7:$P$7,$H19:$P19) -> 0 | T19: 0 | W19: =V19*F19 -> 0 | Z19: =Y19*I19 -> 0
A20: Corrimão Madeira (m) | E20: =IF(D20=0,SUMPRODUCT($H$7:$P$7,$H20:$P20)*(C20),SUMPRODUCT($H$7:$P$7,$H20:$P20)*(C20*D20)) -> 0 | F20: =SUMPRODUCT($H$7:$P$7,$H20:$P20) -> 0 | T20: 0 | W20: =V20*F20 -> 0 | Z20: =Y20*I20 -> 0
A21: Brise de Madeira (m) | B21: BRISE DE MADEIRA VERTICAL - 140 cm | C21: 1.4 | E21: =IF(D21=0,SUMPRODUCT($H$7:$P$7,$H21:$P21)*(C21),SUMPRODUCT($H$7:$P$7,$H21:$P21)*(C21*D21)) -> 0 | F21: =SUMPRODUCT($H$7:$P$7,$H21:$P21) -> 0 | W21: =V21*E21 -> 0 | Z21: =Y21*I21 -> 0
A22: Brise de Madeira (m) | B22: BRISE DE MADEIRA VERTICAL - 156 cm | C22: 1.56 | E22: =IF(D22=0,SUMPRODUCT($H$7:$P$7,$H22:$P22)*(C22),SUMPRODUCT($H$7:$P$7,$H22:$P22)*(C22*D22)) -> 0 | F22: =SUMPRODUCT($H$7:$P$7,$H22:$P22) -> 0 | W22: =V22*E22 -> 0 | Z22: =Y22*I22 -> 0
A23: Brise de Madeira (m) | B23: BRISE DE MADEIRA VERTICAL - 282 cm | C23: 2.82 | E23: =IF(D23=0,SUMPRODUCT($H$7:$P$7,$H23:$P23)*(C23),SUMPRODUCT($H$7:$P$7,$H23:$P23)*(C23*D23)) -> 0 | F23: =SUMPRODUCT($H$7:$P$7,$H23:$P23) -> 0 | W23: =V23*E23 -> 0 | Z23: =Y23*I23 -> 0
A24: Brise de Madeira (m) | B24: BRISE DE MADEIRA VERTICAL - 291 cm | C24: 2.91 | E24: =IF(D24=0,SUMPRODUCT($H$7:$P$7,$H24:$P24)*(C24),SUMPRODUCT($H$7:$P$7,$H24:$P24)*(C24*D24)) -> 0 | F24: =SUMPRODUCT($H$7:$P$7,$H24:$P24) -> 0 | W24: =V24*E24 -> 0 | Z24: =Y24*I24 -> 0
A25: Brise de Madeira (m) | B25: BRISE DE MADEIRA VERTICAL - 396 cm | C25: 3.96 | E25: =IF(D25=0,SUMPRODUCT($H$7:$P$7,$H25:$P25)*(C25),SUMPRODUCT($H$7:$P$7,$H25:$P25)*(C25*D25)) -> 0 | F25: =SUMPRODUCT($H$7:$P$7,$H25:$P25) -> 0 | W25: =V25*E25 -> 0 | Z25: =Y25*I25 -> 0
A26: Brise de Madeira (m) | B26: BRISE DE MADEIRA VERTICAL - 406 cm | C26: 4.06 | E26: =IF(D26=0,SUMPRODUCT($H$7:$P$7,$H26:$P26)*(C26),SUMPRODUCT($H$7:$P$7,$H26:$P26)*(C26*D26)) -> 0 | F26: =SUMPRODUCT($H$7:$P$7,$H26:$P26) -> 0 | W26: =V26*E26 -> 0 | Z26: =Y26*I26 -> 0
A27: Brise de Madeira (m) | B27: BRISE DE MADEIRA VERTICAL - 71 cm | C27: 71 | E27: =IF(D27=0,SUMPRODUCT($H$7:$P$7,$H27:$P27)*(C27),SUMPRODUCT($H$7:$P$7,$H27:$P27)*(C27*D27)) -> 0 | F27: =SUMPRODUCT($H$7:$P$7,$H27:$P27) -> 0 | W27: =V27*E27 -> 0 | Z27: =Y27*I27 -> 0
A28: Brise de Madeira (m) | B28: BRISE DE MADEIRA VERTICAL - 96 cm | C28: 0.96 | E28: =IF(D28=0,SUMPRODUCT($H$7:$P$7,$H28:$P28)*(C28),SUMPRODUCT($H$7:$P$7,$H28:$P28)*(C28*D28)) -> 0 | F28: =SUMPRODUCT($H$7:$P$7,$H28:$P28) -> 0 | W28: =V28*E28 -> 0 | Z28: =Y28*I28 -> 0
A29: Brise de Madeira (m) | E29: =IF(D29=0,SUMPRODUCT($H$7:$P$7,$H29:$P29)*(C29),SUMPRODUCT($H$7:$P$7,$H29:$P29)*(C29*D29)) -> 0 | F29: =SUMPRODUCT($H$7:$P$7,$H29:$P29) -> 0 | W29: =V29*E29 -> 0 | Z29: =Y29*I29 -> 0
A30: ContraMarco | B30: CONTRAMARCO | E30: =IF(D30=0,SUMPRODUCT($H$7:$P$7,$H30:$P30)*(C30),SUMPRODUCT($H$7:$P$7,$H30:$P30)*(C30*D30)) -> 0 | F30: =SUMPRODUCT($H$7:$P$7,$H30:$P30) -> 0 | W30: =V30*F30 -> 0 | Z30: =Y30*I30 -> 0
A31: ContraMarco | E31: =IF(D31=0,SUMPRODUCT($H$7:$P$7,$H31:$P31)*(C31),SUMPRODUCT($H$7:$P$7,$H31:$P31)*(C31*D31)) -> 0 | F31: =SUMPRODUCT($H$7:$P$7,$H31:$P31) -> 0 | W31: =V31*F31 -> 0 | Z31: =Y31*I31 -> 0
A32: ContraMarco | E32: =IF(D32=0,SUMPRODUCT($H$7:$P$7,$H32:$P32)*(C32),SUMPRODUCT($H$7:$P$7,$H32:$P32)*(C32*D32)) -> 0 | F32: =SUMPRODUCT($H$7:$P$7,$H32:$P32) -> 0 | W32: =V32*F32 -> 0 | Z32: =Y32*I32 -> 0
A33: ContraMarco | E33: =IF(D33=0,SUMPRODUCT($H$7:$P$7,$H33:$P33)*(C33),SUMPRODUCT($H$7:$P$7,$H33:$P33)*(C33*D33)) -> 0 | F33: =SUMPRODUCT($H$7:$P$7,$H33:$P33) -> 0 | W33: =V33*F33 -> 0 | Z33: =Y33*I33 -> 0
A34: ContraMarco | E34: =IF(D34=0,SUMPRODUCT($H$7:$P$7,$H34:$P34)*(C34),SUMPRODUCT($H$7:$P$7,$H34:$P34)*(C34*D34)) -> 0 | F34: =SUMPRODUCT($H$7:$P$7,$H34:$P34) -> 0 | W34: =V34*F34 -> 0 | Z34: =Y34*I34 -> 0
A35: Portões Alumínio | E35: =IF(D35=0,SUMPRODUCT($H$7:$P$7,$H35:$P35)*(C35),SUMPRODUCT($H$7:$P$7,$H35:$P35)*(C35*D35)) -> 0 | F35: =SUMPRODUCT($H$7:$P$7,$H35:$P35) -> 0 | W35: =V35*F35 -> 0 | Z35: =Y35*F35 -> 0
A36: Portões Alumínio | E36: =IF(D36=0,SUMPRODUCT($H$7:$P$7,$H36:$P36)*(C36),SUMPRODUCT($H$7:$P$7,$H36:$P36)*(C36*D36)) -> 0 | F36: =SUMPRODUCT($H$7:$P$7,$H36:$P36) -> 0 | W36: =V36*F36 -> 0 | Z36: =Y36*F36 -> 0
A37: Portões Alumínio | E37: =IF(D37=0,SUMPRODUCT($H$7:$P$7,$H37:$P37)*(C37),SUMPRODUCT($H$7:$P$7,$H37:$P37)*(C37*D37)) -> 0 | F37: =SUMPRODUCT($H$7:$P$7,$H37:$P37) -> 0 | W37: =V37*F37 -> 0 | Z37: =Y37*F37 -> 0
A38: Portões Alumínio | E38: =IF(D38=0,SUMPRODUCT($H$7:$P$7,$H38:$P38)*(C38),SUMPRODUCT($H$7:$P$7,$H38:$P38)*(C38*D38)) -> 0 | F38: =SUMPRODUCT($H$7:$P$7,$H38:$P38) -> 0 | W38: =V38*F38 -> 0 | Z38: =Y38*F38 -> 0
A39: Portas Alumínio | B39: P5 - PORTA DE ABRIR, 1 FOLHA, VIDRO E ALUMINIO, 80 x 210 cm | C39: 0.8 | D39: 2.1 | E39: =IF(D39=0,SUMPRODUCT($H$7:$P$7,$H39:$P39)*(C39),SUMPRODUCT($H$7:$P$7,$H39:$P39)*(C39*D39)) -> 0 | F39: =SUMPRODUCT($H$7:$P$7,$H39:$P39) -> 0 | W39: =V39*F39 -> 0 | Z39: =Y39*F39 -> 0
A40: Portas Alumínio | B40: P6 - PORTA DE ABRIR, 1 FOLHA, ALUMINIO VENEZIANA, 60 x 210 cm | C40: 0.6 | D40: 2.1 | E40: =IF(D40=0,SUMPRODUCT($H$7:$P$7,$H40:$P40)*(C40),SUMPRODUCT($H$7:$P$7,$H40:$P40)*(C40*D40)) -> 0 | F40: =SUMPRODUCT($H$7:$P$7,$H40:$P40) -> 0 | W40: =V40*F40 -> 0 | Z40: =Y40*F40 -> 0
A41: Portas Alumínio | B41: P7 - PORTAO BASCULANTE, 1 FOLHA, ALUMÍNIO, 400 x 230 cm | C41: 4 | D41: 2.3 | E41: =IF(D41=0,SUMPRODUCT($H$7:$P$7,$H41:$P41)*(C41),SUMPRODUCT($H$7:$P$7,$H41:$P41)*(C41*D41)) -> 0 | F41: =SUMPRODUCT($H$7:$P$7,$H41:$P41) -> 0 | W41: =V41*F41 -> 0 | Z41: =Y41*F41 -> 0
A42: Portas Alumínio | B42: P8 - PORTA DE ABRIR, 2 FOLHAS, ALUMINIO VENEZIANA, 140 x 115 cm | C42: 1.4 | D42: 1.15 | E42: =IF(D42=0,SUMPRODUCT($H$7:$P$7,$H42:$P42)*(C42),SUMPRODUCT($H$7:$P$7,$H42:$P42)*(C42*D42)) -> 0 | F42: =SUMPRODUCT($H$7:$P$7,$H42:$P42) -> 0 | W42: =V42*F42 -> 0 | Z42: =Y42*F42 -> 0
A43: Portas Alumínio | B43: PE - PORTA DE ABRIR, 1 FOLHA, VIDRO E ALUMINIO, 100 x 230 cm | C43: 1 | D43: 2.3 | E43: =IF(D43=0,SUMPRODUCT($H$7:$P$7,$H43:$P43)*(C43),SUMPRODUCT($H$7:$P$7,$H43:$P43)*(C43*D43)) -> 0 | F43: =SUMPRODUCT($H$7:$P$7,$H43:$P43) -> 0 | W43: =V43*F43 -> 0 | Z43: =Y43*F43 -> 0
A44: Portas Alumínio | B44: PJ1 - PORTA DE CORRER, 4 FOLHAS, VIDRO E ALUMÍNIO, 200 x 230 cm | C44: 2 | D44: 2.3 | E44: =IF(D44=0,SUMPRODUCT($H$7:$P$7,$H44:$P44)*(C44),SUMPRODUCT($H$7:$P$7,$H44:$P44)*(C44*D44)) -> 0 | F44: =SUMPRODUCT($H$7:$P$7,$H44:$P44) -> 0 | W44: =V44*F44 -> 0 | Z44: =Y44*F44 -> 0
A45: Portas Alumínio | B45: PJ2 - PORTA DE CORRER, 4 FOLHAS, VIDRO E ALUMINIO, 260 x 230 cm | C45: 2.6 | D45: 2.3 | E45: =IF(D45=0,SUMPRODUCT($H$7:$P$7,$H45:$P45)*(C45),SUMPRODUCT($H$7:$P$7,$H45:$P45)*(C45*D45)) -> 0 | F45: =SUMPRODUCT($H$7:$P$7,$H45:$P45) -> 0 | W45: =V45*F45 -> 0 | Z45: =Y45*F45 -> 0
A46: Portas Alumínio | B46: PJ3 - PORTA DE CORRER, 4 FOLHAS, VIDRO E ALUMÍNIO, 360 x 230 cm | C46: 3.6 | D46: 2.3 | E46: =IF(D46=0,SUMPRODUCT($H$7:$P$7,$H46:$P46)*(C46),SUMPRODUCT($H$7:$P$7,$H46:$P46)*(C46*D46)) -> 0 | F46: =SUMPRODUCT($H$7:$P$7,$H46:$P46) -> 0 | W46: =V46*F46 -> 0 | Z46: =Y46*F46 -> 0
A47: Portas Alumínio | B47: PJ4 - PORTA DE ABRIR, 2 FOLHAS, ALUMÍNIO VENEZIANA, 150 x 210 cm | C47: 1.5 | D47: 2.1 | E47: =IF(D47=0,SUMPRODUCT($H$7:$P$7,$H47:$P47)*(C47),SUMPRODUCT($H$7:$P$7,$H47:$P47)*(C47*D47)) -> 0 | F47: =SUMPRODUCT($H$7:$P$7,$H47:$P47) -> 0 | W47: =V47*F47 -> 0 | Z47: =Y47*F47 -> 0
A48: Portas Alumínio | B48: PORTA DE ABRIR, 1 FOLHA + 2 LUZES LATERAIS, ALUMINIO E VIDRO, 526 x 316 cm | C48: 5.26 | D48: 3.16 | E48: =IF(D48=0,SUMPRODUCT($H$7:$P$7,$H48:$P48)*(C48),SUMPRODUCT($H$7:$P$7,$H48:$P48)*(C48*D48)) -> 0 | F48: =SUMPRODUCT($H$7:$P$7,$H48:$P48) -> 0 | W48: =V48*F48 -> 0 | Z48: =Y48*F48 -> 0
A49: Portas Alumínio | B49: PORTA DE ABRIR, 1 FOLHA + 2 LUZES LATERAIS, ALUMINIO E VIDRO, 580 x 316 cm | C49: 5.8 | D49: 3.16 | E49: =IF(D49=0,SUMPRODUCT($H$7:$P$7,$H49:$P49)*(C49),SUMPRODUCT($H$7:$P$7,$H49:$P49)*(C49*D49)) -> 0 | F49: =SUMPRODUCT($H$7:$P$7,$H49:$P49) -> 0 | W49: =V49*F49 -> 0 | Z49: =Y49*F49 -> 0
A50: Portas Alumínio | B50: PORTA DE ABRIR, 1 FOLHA + 2 LUZES LATERAIS, ALUMINIO E VIDRO, 647 x 316 cm | C50: 6.47 | D50: 3.16 | E50: =IF(D50=0,SUMPRODUCT($H$7:$P$7,$H50:$P50)*(C50),SUMPRODUCT($H$7:$P$7,$H50:$P50)*(C50*D50)) -> 0 | F50: =SUMPRODUCT($H$7:$P$7,$H50:$P50) -> 0 | W50: =V50*F50 -> 0 | Z50: =Y50*F50 -> 0
... A52: Portas Alumínio | B52: PORTA DE ABRIR, 1 FOLHA + 2 LUZES LATERAIS, ALUMINIO E VIDRO, 830 x 316 cm | C52: 8.3 | D52: 3.16 | E52: =IF(D52=0,SUMPRODUCT($H$7:$P$7,$H52:$P52)*(C52),SUMPRODUCT($H$7:$P$7,$H52:$P52)*(C52*D52)) -> 0 | F52: =SUMPRODUCT($H$7:$P$7,$H52:$P52) -> 0 | W52: =V52*F52 -> 0 | Z52: =Y52*F52 -> 0
A53: Portas Alumínio | E53: =IF(D53=0,SUMPRODUCT($H$7:$P$7,$H53:$P53)*(C53),SUMPRODUCT($H$7:$P$7,$H53:$P53)*(C53*D53)) -> 0 | F53: =SUMPRODUCT($H$7:$P$7,$H53:$P53) -> 0 | W53: =V53*F53 -> 0 | Z53: =Y53*F53 -> 0
A54: Portas Alumínio | E54: =IF(D54=0,SUMPRODUCT($H$7:$P$7,$H54:$P54)*(C54),SUMPRODUCT($H$7:$P$7,$H54:$P54)*(C54*D54)) -> 0 | F54: =SUMPRODUCT($H$7:$P$7,$H54:$P54) -> 0 | W54: =V54*F54 -> 0 | Z54: =Y54*F54 -> 0
A55: Portas Alumínio | E55: =IF(D55=0,SUMPRODUCT($H$7:$P$7,$H55:$P55)*(C55),SUMPRODUCT($H$7:$P$7,$H55:$P55)*(C55*D55)) -> 0 | F55: =SUMPRODUCT($H$7:$P$7,$H55:$P55) -> 0 | W55: =V55*F55 -> 0 | Z55: =Y55*F55 -> 0
A56: Janela/Maxim-ar Alumínio (un) | B56: J10 - JANELA DE CORRER, 4 FOLHAS, ALUMÍNIO E VIDRO, 300 x 120 cm | C56: 3 | D56: 1.2 | E56: =IF(D56=0,SUMPRODUCT($H$7:$P$7,$H56:$P56)*(C56),SUMPRODUCT($H$7:$P$7,$H56:$P56)*(C56*D56)) -> 0 | F56: =SUMPRODUCT($H$7:$P$7,$H56:$P56) -> 0 | W56: =V56*F56 -> 0 | Z56: =Y56*F56 -> 0
A57: Janela/Maxim-ar Alumínio (un) | B57: J11 - JANELA FIXA, 1 FOLHA, ALUMÍNIO E VIDRO, 60 x 213 cm | C57: 0.6 | D57: 2.13 | E57: =IF(D57=0,SUMPRODUCT($H$7:$P$7,$H57:$P57)*(C57),SUMPRODUCT($H$7:$P$7,$H57:$P57)*(C57*D57)) -> 0 | F57: =SUMPRODUCT($H$7:$P$7,$H57:$P57) -> 0 | W57: =V57*F57 -> 0 | Z57: =Y57*F57 -> 0
A58: Janela/Maxim-ar Alumínio (un) | B58: J12 - JANELA FIXA, 1 FOLHA, ALUMINIO VENEZIANA, 60 x 30 cm | C58: 0.6 | D58: 0.3 | E58: =IF(D58=0,SUMPRODUCT($H$7:$P$7,$H58:$P58)*(C58),SUMPRODUCT($H$7:$P$7,$H58:$P58)*(C58*D58)) -> 0 | F58: =SUMPRODUCT($H$7:$P$7,$H58:$P58) -> 0 | W58: =V58*F58 -> 0 | Z58: =Y58*F58 -> 0
A59: Janela/Maxim-ar Alumínio (un) | B59: J13 - JANELA FIXA, 1 FOLHA, ALUMÍNIO VENEZIANA, 60 x 120 cm | C59: 0.6 | D59: 1.2 | E59: =IF(D59=0,SUMPRODUCT($H$7:$P$7,$H59:$P59)*(C59),SUMPRODUCT($H$7:$P$7,$H59:$P59)*(C59*D59)) -> 0 | F59: =SUMPRODUCT($H$7:$P$7,$H59:$P59) -> 0 | W59: =V59*F59 -> 0 | Z59: =Y59*F59 -> 0
A60: Janela/Maxim-ar Alumínio (un) | B60: J1 - JANELA MAXIM-AIR, 1 FOLHA, ALUMINIO E VIDRO, 60 x 70 cm | C60: 0.6 | D60: 0.7 | E60: =IF(D60=0,SUMPRODUCT($H$7:$P$7,$H60:$P60)*(C60),SUMPRODUCT($H$7:$P$7,$H60:$P60)*(C60*D60)) -> 0 | F60: =SUMPRODUCT($H$7:$P$7,$H60:$P60) -> 0 | W60: =V60*F60 -> 0 | Z60: =Y60*F60 -> 0
A61: Janela/Maxim-ar Alumínio (un) | B61: J2 - JANELA MAXIM-AIR, 1 FOLHA, ALUMÍNIO E VIDRO, 80 x 70 cm | C61: 0.8 | D61: 0.7 | E61: =IF(D61=0,SUMPRODUCT($H$7:$P$7,$H61:$P61)*(C61),SUMPRODUCT($H$7:$P$7,$H61:$P61)*(C61*D61)) -> 0 | F61: =SUMPRODUCT($H$7:$P$7,$H61:$P61) -> 0 | W61: =V61*F61 -> 0 | Z61: =Y61*F61 -> 0
A62: Janela/Maxim-ar Alumínio (un) | B62: J3 - JANELA DE CORRER, 2 FOLHAS + PEITORIL FIXO, ALUMÍNIO E VIDRO, 150 x 120 cm | C62: 1.5 | D62: 1.2 | E62: =IF(D62=0,SUMPRODUCT($H$7:$P$7,$H62:$P62)*(C62),SUMPRODUCT($H$7:$P$7,$H62:$P62)*(C62*D62)) -> 0 | F62: =SUMPRODUCT($H$7:$P$7,$H62:$P62) -> 0 | W62: =V62*F62 -> 0 | Z62: =Y62*F62 -> 0
A63: Janela/Maxim-ar Alumínio (un) | B63: J4 - JANELA FIXA, 1 FOLHA, ALUMÍNIO E VIDRO, 80 x 80 cm | C63: 0.8 | D63: 0.8 | E63: =IF(D63=0,SUMPRODUCT($H$7:$P$7,$H63:$P63)*(C63),SUMPRODUCT($H$7:$P$7,$H63:$P63)*(C63*D63)) -> 0 | F63: =SUMPRODUCT($H$7:$P$7,$H63:$P63) -> 0 | W63: =V63*F63 -> 0 | Z63: =Y63*F63 -> 0
A64: Janela/Maxim-ar Alumínio (un) | B64: J5 - JANELA FIXA, 1 FOLHA, ALUMINIO VENEZIANA, 180 x 95 cm | C64: 1.8 | D64: 0.95 | E64: =IF(D64=0,SUMPRODUCT($H$7:$P$7,$H64:$P64)*(C64),SUMPRODUCT($H$7:$P$7,$H64:$P64)*(C64*D64)) -> 0 | F64: =SUMPRODUCT($H$7:$P$7,$H64:$P64) -> 0 | W64: =V64*F64 -> 0 | Z64: =Y64*F64 -> 0
A65: Janela/Maxim-ar Alumínio (un) | B65: J6 - JANELA FIXA, 1 FOLHA, ALUMINIO VENEZIANA, 150 x 100 cm | C65: 1.5 | D65: 1 | E65: =IF(D65=0,SUMPRODUCT($H$7:$P$7,$H65:$P65)*(C65),SUMPRODUCT($H$7:$P$7,$H65:$P65)*(C65*D65)) -> 0 | F65: =SUMPRODUCT($H$7:$P$7,$H65:$P65) -> 0 | W65: =V65*F65 -> 0 | Z65: =Y65*F65 -> 0
A66: Janela/Maxim-ar Alumínio (un) | B66: J7 - JANELA FIXA, 1 FOLHA, ALUMÍNIO VENEZIANA, 90 x 185 cm | C66: 0.9 | D66: 1.85 | E66: =IF(D66=0,SUMPRODUCT($H$7:$P$7,$H66:$P66)*(C66),SUMPRODUCT($H$7:$P$7,$H66:$P66)*(C66*D66)) -> 0 | F66: =SUMPRODUCT($H$7:$P$7,$H66:$P66) -> 0 | W66: =V66*F66 -> 0 | Z66: =Y66*F66 -> 0
A67: Janela/Maxim-ar Alumínio (un) | B67: J8 - JANELA DE CORRER, 2 FOLHAS + PEITORIL FIXO, ALUMÍNIO E VIDRO, 200 x 120 cm | C67: 2 | D67: 1.2 | E67: =IF(D67=0,SUMPRODUCT($H$7:$P$7,$H67:$P67)*(C67),SUMPRODUCT($H$7:$P$7,$H67:$P67)*(C67*D67)) -> 0 | F67: =SUMPRODUCT($H$7:$P$7,$H67:$P67) -> 0 | W67: =V67*F67 -> 0 | Z67: =Y67*F67 -> 0
... A72: Janela/Maxim-ar Alumínio (un) | B72: ABERTURA PARA CHURRASQUEIRA, ALUMÍNIO, 60 x 60 cm | C72: 0.6 | D72: 0.6 | E72: =IF(D72=0,SUMPRODUCT($H$7:$P$7,$H72:$P72)*(C72),SUMPRODUCT($H$7:$P$7,$H72:$P72)*(C72*D72)) -> 0 | F72: =SUMPRODUCT($H$7:$P$7,$H72:$P72) -> 0 | W72: =V72*F72 -> 0 | Z72: =Y72*F72 -> 0
A73: Janela/Maxim-ar Alumínio (un) | E73: =IF(D73=0,SUMPRODUCT($H$7:$P$7,$H73:$P73)*(C73),SUMPRODUCT($H$7:$P$7,$H73:$P73)*(C73*D73)) -> 0 | F73: =SUMPRODUCT($H$7:$P$7,$H73:$P73) -> 0 | W73: =V73*F73 -> 0 | Z73: =Y73*F73 -> 0
A74: Brise de Alumínio (m2) | B74: Moldura de Alumínio em Fachadas | C74: 61.01 | D74: 12.6 | E74: =IF(D74=0,SUMPRODUCT($H$7:$P$7,$H74:$P74)*(C74),SUMPRODUCT($H$7:$P$7,$H74:$P74)*(C74*D74)) -> 0 | F74: =SUMPRODUCT($H$7:$P$7,$H74:$P74) -> 0 | W74: =V74*F74 -> 0 | Z74: =Y74*E74 -> 0
A75: Brise de Alumínio (m2) | B75: Moldura de Alumínio em Fachadas | C75: 41.4019 | D75: 12.6 | E75: =IF(D75=0,SUMPRODUCT($H$7:$P$7,$H75:$P75)*(C75),SUMPRODUCT($H$7:$P$7,$H75:$P75)*(C75*D75)) -> 0 | F75: =SUMPRODUCT($H$7:$P$7,$H75:$P75) -> 0 | W75: =V75*F75 -> 0 | Z75: =Y75*E75 -> 0
A76: Brise de Alumínio (m2) | E76: =IF(D76=0,SUMPRODUCT($H$7:$P$7,$H76:$P76)*(C76),SUMPRODUCT($H$7:$P$7,$H76:$P76)*(C76*D76)) -> 0 | F76: =SUMPRODUCT($H$7:$P$7,$H76:$P76) -> 0 | W76: =V76*F76 -> 0 | Z76: =Y76*E76 -> 0
A77: Brise de Alumínio (m2) | E77: =IF(D77=0,SUMPRODUCT($H$7:$P$7,$H77:$P77)*(C77),SUMPRODUCT($H$7:$P$7,$H77:$P77)*(C77*D77)) -> 0 | F77: =SUMPRODUCT($H$7:$P$7,$H77:$P77) -> 0 | W77: =V77*F77 -> 0 | Z77: =Y77*E77 -> 0
A78: Guarda Corpo Alumínio(m) | B78: GUARDA CORPO DE ALUMÍNIO, H=110 cm | C78: 16.34 | E78: =IF(D78=0,SUMPRODUCT($H$7:$P$7,$H78:$P78)*(C78),SUMPRODUCT($H$7:$P$7,$H78:$P78)*(C78*D78)) -> 0 | F78: =SUMPRODUCT($H$7:$P$7,$H78:$P78) -> 0 | W78: =V78*E78 -> 0 | Z78: =Y78*E78 -> 0
A79: Guarda Corpo Alumínio(m) | B79: GUARDA-CORPO, VIDRO, 110 cm | C79: 250.29 | E79: =IF(D79=0,SUMPRODUCT($H$7:$P$7,$H79:$P79)*(C79),SUMPRODUCT($H$7:$P$7,$H79:$P79)*(C79*D79)) -> 0 | F79: =SUMPRODUCT($H$7:$P$7,$H79:$P79) -> 0 | W79: =V79*E79 -> 0 | Z79: =Y79*E79 -> 0
A80: Guarda Corpo Alumínio(m) | B80: GUARDA-CORPO, VIDRO, 120cm | C80: 16.05 | E80: =IF(D80=0,SUMPRODUCT($H$7:$P$7,$H80:$P80)*(C80),SUMPRODUCT($H$7:$P$7,$H80:$P80)*(C80*D80)) -> 0 | F80: =SUMPRODUCT($H$7:$P$7,$H80:$P80) -> 0 | W80: =V80*E80 -> 0 | Z80: =Y80*E80 -> 0
A81: Guarda Corpo Alumínio(m) | B81: GUARDA-CORPO, VIDRO, 240cm | C81: 36.75 | E81: =IF(D81=0,SUMPRODUCT($H$7:$P$7,$H81:$P81)*(C81),SUMPRODUCT($H$7:$P$7,$H81:$P81)*(C81*D81)) -> 0 | F81: =SUMPRODUCT($H$7:$P$7,$H81:$P81) -> 0 | W81: =V81*E81 -> 0 | Z81: =Y81*E81 -> 0
A82: Guarda Corpo Alumínio(m) | B82: GUARDA-CORPO, VIDRO, altura a definir | C82: 6.89 | E82: =IF(D82=0,SUMPRODUCT($H$7:$P$7,$H82:$P82)*(C82),SUMPRODUCT($H$7:$P$7,$H82:$P82)*(C82*D82)) -> 0 | F82: =SUMPRODUCT($H$7:$P$7,$H82:$P82) -> 0 | W82: =V82*E82 -> 0 | Z82: =Y82*E82 -> 0
A83: Guarda Corpo Alumínio(m) | E83: =IF(D83=0,SUMPRODUCT($H$7:$P$7,$H83:$P83)*(C83),SUMPRODUCT($H$7:$P$7,$H83:$P83)*(C83*D83)) -> 0 | F83: =SUMPRODUCT($H$7:$P$7,$H83:$P83) -> 0 | W83: =V83*E83 -> 0 | Z83: =Y83*E83 -> 0
A84: Esquadria de Vidro | B84: PELE DE VIDRO, 116.75 x 316 cm | C84: 1.1675 | D84: 3.16 | E84: =IF(D84=0,SUMPRODUCT($H$7:$P$7,$H84:$P84)*(C84),SUMPRODUCT($H$7:$P$7,$H84:$P84)*(C84*D84)) -> 0 | F84: =SUMPRODUCT($H$7:$P$7,$H84:$P84) -> 0 | W84: =V84*E84 -> 0 | Z84: =Y84*E84 -> 0
A85: Esquadria de Vidro | B85: PELE DE VIDRO, 122 x 280 cm | C85: 122 | D85: 2.8 | E85: =IF(D85=0,SUMPRODUCT($H$7:$P$7,$H85:$P85)*(C85),SUMPRODUCT($H$7:$P$7,$H85:$P85)*(C85*D85)) -> 0 | F85: =SUMPRODUCT($H$7:$P$7,$H85:$P85) -> 0 | W85: =V85*E85 -> 0 | Z85: =Y85*E85 -> 0
A86: Esquadria de Vidro | B86: PELE DE VIDRO, 150 x 206 cm | C86: 1.5 | D86: 2.06 | E86: =IF(D86=0,SUMPRODUCT($H$7:$P$7,$H86:$P86)*(C86),SUMPRODUCT($H$7:$P$7,$H86:$P86)*(C86*D86)) -> 0 | F86: =SUMPRODUCT($H$7:$P$7,$H86:$P86) -> 0 | W86: =V86*E86 -> 0 | Z86: =Y86*E86 -> 0
A87: Esquadria de Vidro | B87: PELE DE VIDRO, 158.5 x 280 cm | C87: 1.585 | D87: 2.8 | E87: =IF(D87=0,SUMPRODUCT($H$7:$P$7,$H87:$P87)*(C87),SUMPRODUCT($H$7:$P$7,$H87:$P87)*(C87*D87)) -> 0 | F87: =SUMPRODUCT($H$7:$P$7,$H87:$P87) -> 0 | W87: =V87*E87 -> 0 | Z87: =Y87*E87 -> 0
A88: Esquadria de Vidro | B88: PELE DE VIDRO, 246.5 x 316 cm | C88: 2.465 | D88: 3.16 | E88: =IF(D88=0,SUMPRODUCT($H$7:$P$7,$H88:$P88)*(C88),SUMPRODUCT($H$7:$P$7,$H88:$P88)*(C88*D88)) -> 0 | F88: =SUMPRODUCT($H$7:$P$7,$H88:$P88) -> 0 | W88: =V88*E88 -> 0 | Z88: =Y88*E88 -> 0
A89: Esquadria de Vidro | B89: PELE DE VIDRO, 315 x 280 cm | C89: 3.15 | D89: 2.8 | E89: =IF(D89=0,SUMPRODUCT($H$7:$P$7,$H89:$P89)*(C89),SUMPRODUCT($H$7:$P$7,$H89:$P89)*(C89*D89)) -> 0 | F89: =SUMPRODUCT($H$7:$P$7,$H89:$P89) -> 0 | W89: =V89*E89 -> 0 | Z89: =Y89*E89 -> 0
A90: Esquadria de Vidro | B90: PELE DE VIDRO, 593.05 x 280 cm | C90: 5.935 | D90: 2.8 | E90: =IF(D90=0,SUMPRODUCT($H$7:$P$7,$H90:$P90)*(C90),SUMPRODUCT($H$7:$P$7,$H90:$P90)*(C90*D90)) -> 0 | F90: =SUMPRODUCT($H$7:$P$7,$H90:$P90) -> 0 | W90: =V90*E90 -> 0 | Z90: =Y90*E90 -> 0
A91: Esquadria de Vidro | B91: PELE DE VIDRO, 66 x 316 cm | C91: 0.66 | D91: 3.16 | E91: =IF(D91=0,SUMPRODUCT($H$7:$P$7,$H91:$P91)*(C91),SUMPRODUCT($H$7:$P$7,$H91:$P91)*(C91*D91)) -> 0 | F91: =SUMPRODUCT($H$7:$P$7,$H91:$P91) -> 0 | W91: =V91*E91 -> 0 | Z91: =Y91*E91 -> 0
A92: Esquadria de Vidro | B92: Fachada em esquadria de vidro fixo | E92: =IF(D92=0,SUMPRODUCT($H$7:$P$7,$H92:$P92)*(C92),SUMPRODUCT($H$7:$P$7,$H92:$P92)*(C92*D92)) -> 0 | F92: =SUMPRODUCT($H$7:$P$7,$H92:$P92) -> 0 | W92: =V92*E92 -> 0 | Z92: =Y92*E92 -> 0
A93: Esquadria de Vidro | E93: =IF(D93=0,SUMPRODUCT($H$7:$P$7,$H93:$P93)*(C93),SUMPRODUCT($H$7:$P$7,$H93:$P93)*(C93*D93)) -> 0 | F93: =SUMPRODUCT($H$7:$P$7,$H93:$P93) -> 0 | W93: =V93*E93 -> 0 | Z93: =Y93*E93 -> 0
A94: Esquadria de Vidro | E94: =IF(D94=0,SUMPRODUCT($H$7:$P$7,$H94:$P94)*(C94),SUMPRODUCT($H$7:$P$7,$H94:$P94)*(C94*D94)) -> 0 | F94: =SUMPRODUCT($H$7:$P$7,$H94:$P94) -> 0 | W94: =V94*E94 -> 0 | Z94: =Y94*E94 -> 0
A95: Portas/Portões Ferro | B95: PCF-1 - PORTA DE ABRIR, 1 FOLHA, CORTA FOGO, 80 x 210 cm | C95: 0.8 | D95: 210 | E95: =IF(D95=0,SUMPRODUCT($H$7:$P$7,$H95:$P95)*(C95),SUMPRODUCT($H$7:$P$7,$H95:$P95)*(C95*D95)) -> 0 | F95: =SUMPRODUCT($H$7:$P$7,$H95:$P95) -> 0 | W95: =V95*F95 -> 0 | Z95: =Y95*I95 -> 0 | AA95: =(ESQUADRIAS!D95*2+ESQUADRIAS!C95)*ESQUADRIAS!F95/100 -> 0
A96: Portas/Portões Ferro | B96: PCF-2 - PORTA DE ABRIR, 1 FOLHA, CORTA FOGO, 90 x 210 cm | C96: 0.9 | D96: 210 | E96: =IF(D96=0,SUMPRODUCT($H$7:$P$7,$H96:$P96)*(C96),SUMPRODUCT($H$7:$P$7,$H96:$P96)*(C96*D96)) -> 0 | F96: =SUMPRODUCT($H$7:$P$7,$H96:$P96) -> 0 | W96: =V96*F96 -> 0 | Z96: =Y96*I96 -> 0 | AA96: =(ESQUADRIAS!D96*2+ESQUADRIAS!C96)*ESQUADRIAS!F96/100 -> 0
A97: Portas/Portões Ferro | B97: PCF-3 - PORTA DE ABRIR, 1 FOLHA, CORTA FOGO, 100 x 210 cm | C97: 1 | D97: 210 | E97: =IF(D97=0,SUMPRODUCT($H$7:$P$7,$H97:$P97)*(C97),SUMPRODUCT($H$7:$P$7,$H97:$P97)*(C97*D97)) -> 0 | F97: =SUMPRODUCT($H$7:$P$7,$H97:$P97) -> 0 | W97: =V97*F97 -> 0 | Z97: =Y97*I97 -> 0 | AA97: =(ESQUADRIAS!D97*2+ESQUADRIAS!C97)*ESQUADRIAS!F97/100 -> 0
A98: Portas/Portões Ferro | E98: =IF(D98=0,SUMPRODUCT($H$7:$P$7,$H98:$P98)*(C98),SUMPRODUCT($H$7:$P$7,$H98:$P98)*(C98*D98)) -> 0 | F98: =SUMPRODUCT($H$7:$P$7,$H98:$P98) -> 0 | W98: =V98*F98 -> 0 | Z98: =Y98*I98 -> 0
A99: Janela / Basculhante / Veneziana Ferro (un) | E99: =IF(D99=0,SUMPRODUCT($H$7:$P$7,$H99:$P99)*(C99),SUMPRODUCT($H$7:$P$7,$H99:$P99)*(C99*D99)) -> 0 | F99: =SUMPRODUCT($H$7:$P$7,$H99:$P99) -> 0 | W99: =V99*F99 -> 0 | Z99: =Y99*I99 -> 0
A100: Janela / Basculhante / Veneziana Ferro (un) | E100: =IF(D100=0,SUMPRODUCT($H$7:$P$7,$H100:$P100)*(C100),SUMPRODUCT($H$7:$P$7,$H100:$P100)*(C100*D100)) -> 0 | F100: =SUMPRODUCT($H$7:$P$7,$H100:$P100) -> 0 | W100: =V100*F100 -> 0 | Z100: =Y100*I100 -> 0
A101: Janela / Basculhante / Veneziana Ferro (un) | E101: =IF(D101=0,SUMPRODUCT($H$7:$P$7,$H101:$P101)*(C101),SUMPRODUCT($H$7:$P$7,$H101:$P101)*(C101*D101)) -> 0 | F101: =SUMPRODUCT($H$7:$P$7,$H101:$P101) -> 0 | W101: =V101*F101 -> 0 | Z101: =Y101*I101 -> 0
A102: Janela / Basculhante / Veneziana Ferro (un) | E102: =IF(D102=0,SUMPRODUCT($H$7:$P$7,$H102:$P102)*(C102),SUMPRODUCT($H$7:$P$7,$H102:$P102)*(C102*D102)) -> 0 | F102: =SUMPRODUCT($H$7:$P$7,$H102:$P102) -> 0 | W102: =V102*F102 -> 0 | Z102: =Y102*I102 -> 0
A103: Gradil/Guarda Corpo Ferro (m2) | E103: =IF(D103=0,SUMPRODUCT($H$7:$P$7,$H103:$P103)*(C103),SUMPRODUCT($H$7:$P$7,$H103:$P103)*(C103*D103)) -> 0 | F103: =SUMPRODUCT($H$7:$P$7,$H103:$P103) -> 0 | W103: =V103*F103 -> 0 | Z103: =Y103*I103 -> 0
A104: Gradil/Guarda Corpo Ferro (m2) | E104: =IF(D104=0,SUMPRODUCT($H$7:$P$7,$H104:$P104)*(C104),SUMPRODUCT($H$7:$P$7,$H104:$P104)*(C104*D104)) -> 0 | F104: =SUMPRODUCT($H$7:$P$7,$H104:$P104) -> 0 | W104: =V104*F104 -> 0 | Z104: =Y104*I104 -> 0
A105: Gradil/Guarda Corpo Ferro (m2) | E105: =IF(D105=0,SUMPRODUCT($H$7:$P$7,$H105:$P105)*(C105),SUMPRODUCT($H$7:$P$7,$H105:$P105)*(C105*D105)) -> 0 | F105: =SUMPRODUCT($H$7:$P$7,$H105:$P105) -> 0 | W105: =V105*F105 -> 0 | Z105: =Y105*I105 -> 0
...

Sheet MOBILIÁRIO
B1: Obra | C1: ='Obra '!D1 -> Brisa da armação
B2: Empresa | C2: ='Obra '!D2 -> HACASA
B3: Revisão | C3: ='Obra '!D3 -> R00 - Letícia
B4: LEVANTAMENTO MOBILIÁRIOS E EQUIPAMENTOS DE LAZER
B6: TOTAL PAVIMENTOS: | C6: =SUMPRODUCT($E$12:$E$163,$F$12:$F$163) -> 1669247.2
B7: ÁREA TOTAL: | C7: =SUMIFS($E$11:$E$163,$D$11:$D$163,"Área: ") -> 956.51
B8: CUSTO ACABAMENTOS ESPECIAIS: | C8: =SUMIFS($G$11:$G$163,$D$11:$D$163,"Acabamentos Especiais") -> 419472
B9: CUSTO/ M2 | C9: =C6/C7 -> 1745.1434
B11: Pavimento | C11: Ambiente | D11: Descrição | E11: Quantidade (un) | F11: Preço Unitário | G11: Preço Total | H11: Observações
B12: TERREO | G12: =SUM(G13:G18)/2 -> 56703
B13: =B12 -> TERREO | C13: Hall Principal | D13: Área: | E13: 30.5 | G13: =SUM(G14:G18) -> 56703
B14: =B13 -> TERREO | C14: =C13 -> Hall Principal | D14: Acabamentos Especiais | E14: =E13 -> 30.5 | F14: 450 | G14: =E14*F14 -> 13725
B15: =B14 -> TERREO | C15: =C14 -> Hall Principal | D15: Poltrona Corda Estofada Algodão Estrutura em Madeira Amêndoa | E15: 6 | F15: 2033 | G15: =E15*F15 -> 12198
B16: =B15 -> TERREO | C16: =C15 -> Hall Principal | D16: Espelhos | E16: 1 | F16: 4800 | G16: =E16*F16 -> 4800
B17: =B16 -> TERREO | C17: =C16 -> Hall Principal | D17: Pendente Luminaria de trilho para teto | E17: 1 | F17: 980 | G17: =E17*F17 -> 980
B18: =B17 -> TERREO | C18: =C17 -> Hall Principal | D18: Marcenaria | E18: 1 | F18: 25000 | G18: =E18*F18 -> 25000
B19: =B18 -> TERREO | C19: Bike Share | D19: Área: | E19: 19.48 | G19: =SUM(G20:G23) -> 18450
B20: =B19 -> TERREO | C20: =C19 -> Bike Share | D20: Suporte de parede para bicicletas, gancho vertical, resistente suporta até 30 kg | E20: 7 | F20: 150 | G20: =E20*F20 -> 1050
B21: =B20 -> TERREO | C21: =C20 -> Bike Share | D21: Estação de Carregamento de Bike Elétrica, Carregador EV | E21: 1 | F21: 7500 | G21: =E21*F21 -> 7500
B22: =B21 -> TERREO | C22: =C21 -> Bike Share | D22: Divisória Aramada decoração | E22: 4 | F22: 1250 | G22: =E22*F22 -> 5000
B23: =B22 -> TERREO | C23: =C22 -> Bike Share | D23: Pendente Luminaria de trilho para teto | E23: 5 | F23: 980 | G23: =E23*F23 -> 4900
B24: =B23 -> TERREO | C24: Pranchário | D24: Área: | E24: 4.87 | G24: =SUM(G25:G25) -> 7890
B25: =B24 -> TERREO | C25: =C24 -> Pranchário | D25: Suporte de para Pranchas | E25: 1 | F25: 7890 | G25: =E25*F25 -> 7890
B26: =B25 -> TERREO | C26: Academia | D26: Área: | E26: 43.41 | G26: =SUM(G27:G41) -> 178255.5
B27: =B26 -> TERREO | C27: =C26 -> Academia | D27: Acabamentos Especiais | E27: =E26 -> 43.41 | F27: 450 | G27: =E27*F27 -> 19534.5
B28: =B27 -> TERREO | C28: =C27 -> Academia | D28: ESTEIRA ERGOMÉTRICA ATHLETIC NEW EXTREME 18 KM/H | E28: 3 | F28: 9000 | G28: =E28*F28 -> 27000
B29: =B28 -> TERREO | C29: =C28 -> Academia | D29: SPINNING ATHLETIC ADVANCED 2200BS | E29: 2 | F29: 3245 | G29: =E29*F29 -> 6490
B30: =B29 -> TERREO | C30: =C29 -> Academia | D30: ESTAÇÃO DE MUSCULAÇÃO ATHLETIC POWER PLUS | E30: 1 | F30: 62000 | G30: =E30*F30 -> 62000
B31: =B30 -> TERREO | C31: =C30 -> Academia | D31: Kit Banco Supino Reto Inclinado + 2x Barras 40cm + Barra 1,50m + 80kg anilhas em PVC | E31: 1 | F31: 3250 | G31: =E31*F31 -> 3250
B32: =B31 -> TERREO | C32: =C31 -> Academia | D32: Estação de Musculação e Banco Supino Gallant GBS1H03A-PT | E32: 1 | F32: 859 | G32: =E32*F32 -> 859
B33: =B32 -> TERREO | C33: =C32 -> Academia | D33: Kit Ketleball + suporte | E33: 1 | F33: 2650 | G33: =E33*F33 -> 2650
B34: =B33 -> TERREO | C34: =C33 -> Academia | D34: Tapete de yoga Asana - 4.5mm PVC ecológico - Ameixa | E34: 6 | F34: 150 | G34: =E34*F34 -> 900
B35: =B34 -> TERREO | C35: =C34 -> Academia | D35: Espelho | E35: 1 | F35: 3500 | G35: =E35*F35 -> 3500
B36: =B35 -> TERREO | C36: =C35 -> Academia | D36: Marcenaria | E36: 1 | F36: 35500 | G36: =E36*F36 -> 35500
B37: =B36 -> TERREO | C37: =C36 -> Academia | D37: Purificador Electrolux Água Gelada, Fria e Natural com Painel Easy Touch Cinza (PE11X) - Bivolt | E37: 1 | F37: 1250 | G37: =E37*F37 -> 1250
B38: =B37 -> TERREO | C38: =C37 -> Academia | D38: Kit Fitness 20kg + 2 Barras 40cm Rosca + 1 Barra 120cm Presilhas | E38: 2 | F38: 1200 | G38: =E38*F38 -> 2400
B39: =B38 -> TERREO | C39: =C38 -> Academia | D39: Kit Halteres Ajustáveis Com Rosca 20kg - Top! | E39: 10 | F39: 450 | G39: =E39*F39 -> 4500
... B41: =B40 -> TERREO | C41: =C40 -> Academia | D41: SUPORTE TORRE EXPOSITOR PARA 20 HALTERES DE 01KG A 10KG | E41: 1 | F41: 1562 | G41: =E41*F41 -> 1562
B42: =B41 -> TERREO | C42: Lavanderia | D42: Área: | E42: 14.42 | G42: =SUM(G43:G48) -> 105846.03
B43: =B42 -> TERREO | C43: =C42 -> Lavanderia | D43: Acabamentos Especiais | E43: =E42 -> 14.42 | F43: 450 | G43: =E43*F43 -> 6489
B44: =B43 -> TERREO | C44: =C43 -> Lavanderia | D44: Acessórios de decoração | E44: 1 | F44: 3000 | G44: =E44*F44 -> 3000
B45: =B44 -> TERREO | C45: =C44 -> Lavanderia | D45: Marcenaria | E45: 1 | F45: 15500 | G45: =E45*F45 -> 15500
B46: =B45 -> TERREO | C46: =C45 -> Lavanderia | D46: WashTower™ AI DD™ Máquina que Lava e Seca 17kg, 220V - Aço Escovado | E46: 3 | F46: 22999.01 | G46: =E46*F46 -> 68997.03
B47: =B46 -> TERREO | C47: =C46 -> Lavanderia | D47: Fliperama Multijogos | E47: 1 | F47: 5000 | G47: =E47*F47 -> 5000
B48: =B47 -> TERREO | C48: =C47 -> Lavanderia | D48: Pendente Luminaria de trilho para teto | E48: 7 | F48: 980 | G48: =E48*F48 -> 6860
B49: =B48 -> TERREO | C49: Smart Market | D49: Área: | E49: 43.41 | G49: =SUM(G50:G53) -> 96454.5
B50: =B49 -> TERREO | C50: =C49 -> Smart Market | D50: Acabamentos Especiais | E50: =E49 -> 43.41 | F50: 450 | G50: =E50*F50 -> 19534.5
B51: =B50 -> TERREO | C51: =C50 -> Smart Market | D51: Geladeira Expositora mercadorias | E51: 3 | F51: 12500 | G51: =E51*F51 -> 37500
B52: =B51 -> TERREO | C52: =C51 -> Smart Market | D52: Marcenaria | E52: 1 | F52: 35500 | G52: =E52*F52 -> 35500
B53: =B52 -> TERREO | C53: =C52 -> Smart Market | D53: Pendente Luminaria de trilho para teto | E53: 4 | F53: 980 | G53: =E53*F53 -> 3920
B54: =B53 -> TERREO | C54: Delivery | D54: Área: | E54: 43.41 | G54: =SUM(G55:G58) -> 96454.5
B55: =B54 -> TERREO | C55: =C54 -> Delivery | D55: Acabamentos Especiais | E55: =E54 -> 43.41 | F55: 450 | G55: =E55*F55 -> 19534.5
B56: =B55 -> TERREO | C56: =C55 -> Delivery | D56: Geladeira Expositora mercadorias | E56: 3 | F56: 12500 | G56: =E56*F56 -> 37500
B57: =B56 -> TERREO | C57: =C56 -> Delivery | D57: Marcenaria | E57: 1 | F57: 35500 | G57: =E57*F57 -> 35500
B58: =B57 -> TERREO | C58: =C57 -> Delivery | D58: Pendente Luminaria de trilho para teto | E58: 4 | F58: 980 | G58: =E58*F58 -> 3920
B59: =B58 -> TERREO | C59: Coworking | D59: Área: | E59: 28.02 | G59: =SUM(G60:G70) -> 44070.9
B60: =B59 -> TERREO | C60: =C59 -> Coworking | D60: Acabamentos Especiais | E60: =E59 -> 28.02 | F60: 450 | G60: =E60*F60 -> 12609
B61: =B60 -> TERREO | C61: =C60 -> Coworking | D61: Acessórios de decoração | E61: 1 | F61: 3000 | G61: =E61*F61 -> 3000
B62: =B61 -> TERREO | C62: =C61 -> Coworking | D62: Sofá Ilha Com Encosto | E62: 1 | F62: 7649.9 | G62: =E62*F62 -> 7649.9
B63: =B62 -> TERREO | C63: =C62 -> Coworking | D63: Mesa Dupla P/ 4 Pessoas. E Divisória | E63: 1 | F63: 3905 | G63: =E63*F63 -> 3905
B64: =B63 -> TERREO | C64: =C63 -> Coworking | D64: Mesa para escritório 3 pessoas | E64: 1 | F64: 1850 | G64: =E64*F64 -> 1850
B65: =B64 -> TERREO | C65: =C64 -> Coworking | D65: Sofá 2 Ligares | E65: 1 | F65: 2490 | G65: =E65*F65 -> 2490
B66: =B65 -> TERREO | C66: =C65 -> Coworking | D66: Poltrona Corda Estofada Algodão Estrutura em Madeira Amêndoa | E66: 2 | F66: 2033 | G66: =E66*F66 -> 4066
B67: =B66 -> TERREO | C67: =C66 -> Coworking | D67: Mesa individual para Notbook | E67: 2 | F67: 495.5 | G67: =E67*F67 -> 991
B68: =B67 -> TERREO | C68: =C67 -> Coworking | D68: Balanço de teto 1 Lugar | E68: 1 | F68: 2550 | G68: =E68*F68 -> 2550
B69: =B68 -> TERREO | C69: =C68 -> Coworking | D69: Estrutura de Ferro para decoração paisagistica | E69: 1 | F69: 3000 | G69: =E69*F69 -> 3000
B70: =B69 -> TERREO | C70: =C69 -> Coworking | D70: Pendente Luminaria de trilho para teto | E70: 2 | F70: 980 | G70: =E70*F70 -> 1960
B71: Rooftop | G71: =SUM(G72:G159)/2 -> 855365.72
B72: =B71 -> Rooftop | C72: Pub | D72: Área: | E72: 41.51 | G72: =SUM(G73:G84) -> 139967
B73: =B72 -> Rooftop | C73: =C72 -> Pub | D73: Acabamentos Especiais | E73: =E72 -> 41.51 | F73: 450 | G73: =E73*F73 -> 18679.5
B74: =B73 -> Rooftop | C74: =C73 -> Pub | D74: Mesa de Bilhar Versátil 2P Vintage | E74: 1 | F74: 24000 | G74: =E74*F74 -> 24000
B75: =B74 -> Rooftop | C75: =C74 -> Pub | D75: Marcenaria | E75: 1 | F75: 49500 | G75: =E75*F75 -> 49500
B76: =B75 -> Rooftop | C76: =C75 -> Pub | D76: 5 Tacos De Bilhar | E76: 1 | F76: 1000 | G76: =E76*F76 -> 1000
B77: =B76 -> Rooftop | C77: =C76 -> Pub | D77: Jogo de Bolas Numeradas 54mm para Sinuca + Bolão Branco | E77: 1 | F77: 400 | G77: =E77*F77 -> 400
B78: =B77 -> Rooftop | C78: =C77 -> Pub | D78: Cortina | E78: 6 | F78: 2900 | G78: =E78*F78 -> 17400
B79: =B77 -> Rooftop | C79: =C77 -> Pub | D79: Pendente Luminaria De Teto Em Madeira Ø38cm | E79: 3 | F79: 980 | G79: =E79*F79 -> 2940
B80: =B78 -> Rooftop | C80: =C78 -> Pub | D80: Pendente Luminaria de trilho para teto | E80: 1 | F80: 980 | G80: =E80*F80 -> 980
B81: =B80 -> Rooftop | C81: =C80 -> Pub | D81: Decoração | E81: 1 | F81: 15000 | G81: =E81*F81 -> 15000
B82: =B81 -> Rooftop | C82: =C81 -> Pub | D82: Plantas | E82: 1 | F82: 1000 | G82: =E82*F82 -> 1000
B83: =B82 -> Rooftop | C83: =C82 -> Pub | D83: Banqueta Samantha Encosto Anatômico Design Contemporâneo | E83: 5 | F83: 1561.7 | G83: =E83*F83 -> 7808.5
B84: =B83 -> Rooftop | C84: =C83 -> Pub | D84: mesa de Centro | E84: 1 | F84: 1259 | G84: =E84*F84 -> 1259
B85: =B84 -> Rooftop | C85: Salão de Festas | D85: Área: | E85: 77.63 | G85: =SUM(G86:G102) -> 191779.31
B86: =B85 -> Rooftop | C86: =C85 -> Salão de Festas | D86: Acabamentos Especiais | E86: =E85 -> 77.63 | F86: 450 | G86: =E86*F86 -> 34933.5
B87: =B86 -> Rooftop | C87: =C86 -> Salão de Festas | D87: Poltrona Corda Estofada Algodão Estrutura em Madeira Amêndoa | E87: 2 | F87: 2033 | G87: =E87*F87 -> 4066
B88: =B87 -> Rooftop | C88: =C86 -> Salão de Festas | D88: Banqueta Samantha Encosto Anatômico Design Contemporâneo | E88: 6 | F88: 1561.7 | G88: =E88*F88 -> 9370.2
B89: =B88 -> Rooftop | C89: =C87 -> Salão de Festas | D89: Composição De Parede Decoração Artesanatos Cestas De Palha | E89: 1 | F89: 980 | G89: =E89*F89 -> 980
B90: =B89 -> Rooftop | C90: =C89 -> Salão de Festas | D90: Marcenaria | E90: 1 | F90: 62000 | G90: =E90*F90 -> 62000
B91: =B90 -> Rooftop | C91: =C90 -> Salão de Festas | D91: Mesa de Jantar Ingrid Redonda Design Atemporal | E91: 4 | F91: 2507.5 | G91: =E91*F91 -> 10030
B92: =B91 -> Rooftop | C92: =C91 -> Salão de Festas | D92: Cadeira Oliveira Fixa | E92: =E91*4 -> 16 | F92: 1569.37 | G92: =E92*F92 -> 25109.92
B93: =B92 -> Rooftop | C93: =C92 -> Salão de Festas | D93: Cooktop Fischer Platinium 5 Bocas Vidro e Alumínio 19784-23299 Bivolt Preto | E93: 1 | F93: 1500 | G93: =E93*F93 -> 1500
B94: =B93 -> Rooftop | C94: =C93 -> Salão de Festas | D94: Geladeira Electrolux Multidoor Efficient Com Autosense E Inverter 590 L Inox Look Im8s 127v 02623fba130 | E94: 1 | F94: 9270 | G94: =E94*F94 -> 9270
B95: =B94 -> Rooftop | C95: =C94 -> Salão de Festas | D95: Conjunto/Jogo de Panelas 5 Peças, Frigideira, Caçarola em Alumínio | E95: 1 | F95: 1012.99 | G95: =E95*F95 -> 1012.99
B96: =B95 -> Rooftop | C96: =C95 -> Salão de Festas | D96: Estojo e Faqueiro C/ 101 Pçs Lace Inox St James | E96: 1 | F96: 1672.28 | G96: =E96*F96 -> 1672.28
B97: =B96 -> Rooftop | C97: =C96 -> Salão de Festas | D97: Linha Completa Sommelier (18 Taças + 12 Copos) | E97: 3 | F97: 830.42 | G97: =E97*F97 -> 2491.26
B98: =B97 -> Rooftop | C98: =C97 -> Salão de Festas | D98: Cortina | E98: 6 | F98: 2900 | G98: =E98*F98 -> 17400
B99: =B98 -> Rooftop | C99: =C98 -> Salão de Festas | D99: Jogo churrasqueira | E99: 1 | F99: 980 | G99: =E99*F99 -> 980
B100: =B99 -> Rooftop | C100: =C99 -> Salão de Festas | D100: Linha Taças em Cristal Sommelier para Água, Vinho e Espumante (18 Taças) | E100: 4 | F100: 950 | G100: =E100*F100 -> 3800
B101: =B100 -> Rooftop | C101: =C100 -> Salão de Festas | D101: Suporte Para Vaso Em Madeira + Vaso Redondo Sala Escritório | E101: 6 | F101: 650 | G101: =E101*F101 -> 3900
B102: =B101 -> Rooftop | C102: =C101 -> Salão de Festas | D102: Sofá De Canto Boreal Base De Ferro Esquerdo | E102: 1 | F102: 3263.16 | G102: =E102*F102 -> 3263.16
B103: =B102 -> Rooftop | C103: Brinquedoteca | D103: Área: | E103: 24.43 | G103: =SUM(G104:G112) -> 92743.5
...

Sheet Ger_Tec e Adm
G4: PROJETO: | I4: ='Obra '!D1 -> Brisa da armação | O4: REVISÃO: | P4: DATA
G5: EMPRESA: | I5: ='Obra '!D2 -> HACASA | O5: ='Obra '!D3 -> R00 - Letícia | P5: 45728
A6: Unidade Construtiva | B6: Célula Construtiva | C6: Etapa | D6: Subetapa | E6: Serviço | G6: GERENCIAMENTO EXECUTIVO
A7: 0 | B7: 0 | C7: 0 | D7: 0 | E7: 0 | G7: Atalho | H7: NIVEL | I7: Item | J7: Descrição | K7: Unidade | L7: Quant. | M7: Preço un | N7: Total | O7: Considerações | P7: Situação
A8: =IF($H8="UNIDADE CONSTRUTIVA",OFFSET(A8,-1,0)+1,LARGE(A$3:A7,1)) -> 0 | B8: =IF(H8="UNIDADE CONSTRUTIVA",0,IF(H8="CÉLULA CONSTRUTIVA",OFFSET(B8,-1,0)+1,OFFSET(B8,-1,0))) -> 1 | C8: =IF(H8="CÉLULA CONSTRUTIVA",0,IF(H8="ETAPA",OFFSET(C8,-1,0)+1,OFFSET(C8,-1,0))) -> 0 | D8: =IF(H8="ETAPA",0,IF(H8="SUBETAPA",OFFSET(D8,-1,0)+1,OFFSET(D8,-1,0))) -> 0 | E8: =IF(H8="Subetapa",0,IF(H8="serviço",OFFSET(E8,-1,0)+1,OFFSET(E8,-1,0))) -> 0 | H8: CÉLULA CONSTRUTIVA | I8: =IF(H8="Unidade Construtiva",TEXT(A8,"00"),IF(H8="Célula Construtiva",TEXT(B8,"00"),IF(H8="Etapa",CONCATENATE(TEXT(B8,"00"),".",TEXT(C8,"000")),IF(H8="Subetapa",CONCATENATE(TEXT(B8,"00"),".",TEXT(C8,"000"),".",TEXT(D8,"000")),IF(H8="Serviço",CONCATENATE(TEXT(B8,"00"),".",TEXT(C8,"000"),".",TEXT(D8,"000"),".",TEXT(E8,"000")),""))))) -> 01 | J8: SERVIÇOS TÉCNICOS | N8: =IF(H8="Serviço",M8*L8,IF(H8="CÉLULA CONSTRUTIVA",SUMIFS($N$8:$N$417,$B$8:$B$417,B8,$H$8:$H$417,"Serviço"),IF(H8="ETAPA",SUMIFS($N$8:$N$417,$B$8:$B$417,B8,$C$8:$C$417,C8,$H$8:$H$417,"Serviço"),IF(H8="SUBETAPA",SUMIFS($N$8:$N$417,$B$8:$B$417,B8,$C$8:$C$417,C8,$D$8:$D$417,D8,$H$8:$H$417,"Serviço"),0)))) -> 586319.4 | P8: -
A9: =IF($H9="UNIDADE CONSTRUTIVA",OFFSET(A9,-1,0)+1,LARGE(A$3:A8,1)) -> 0 | B9: =IF(H9="UNIDADE CONSTRUTIVA",0,IF(H9="CÉLULA CONSTRUTIVA",OFFSET(B9,-1,0)+1,OFFSET(B9,-1,0))) -> 1 | C9: =IF(H9="CÉLULA CONSTRUTIVA",0,IF(H9="ETAPA",OFFSET(C9,-1,0)+1,OFFSET(C9,-1,0))) -> 1 | D9: =IF(H9="ETAPA",0,IF(H9="SUBETAPA",OFFSET(D9,-1,0)+1,OFFSET(D9,-1,0))) -> 0 | E9: =IF(H9="Subetapa",0,IF(H9="serviço",OFFSET(E9,-1,0)+1,OFFSET(E9,-1,0))) -> 0 | H9: ETAPA | I9: =IF(H9="Unidade Construtiva",TEXT(A9,"00"),IF(H9="Célula Construtiva",TEXT(B9,"00"),IF(H9="Etapa",CONCATENATE(TEXT(B9,"00"),".",TEXT(C9,"000")),IF(H9="Subetapa",CONCATENATE(TEXT(B9,"00"),".",TEXT(C9,"000"),".",TEXT(D9,"000")),IF(H9="Serviço",CONCATENATE(TEXT(B9,"00"),".",TEXT(C9,"000"),".",TEXT(D9,"000"),".",TEXT(E9,"000")),""))))) -> 01.001 | J9: ESTUDOS, PROJETOS, CONSULTORIA E ENSAIOS | N9: =IF(H9="Serviço",M9*L9,IF(H9="CÉLULA CONSTRUTIVA",SUMIFS($N$8:$N$417,$B$8:$B$417,B9,$H$8:$H$417,"Serviço"),IF(H9="ETAPA",SUMIFS($N$8:$N$417,$B$8:$B$417,B9,$C$8:$C$417,C9,$H$8:$H$417,"Serviço"),IF(H9="SUBETAPA",SUMIFS($N$8:$N$417,$B$8:$B$417,B9,$C$8:$C$417,C9,$D$8:$D$417,D9,$H$8:$H$417,"Serviço"),0)))) -> 434557.45 | P9: -
A10: =IF($H10="UNIDADE CONSTRUTIVA",OFFSET(A10,-1,0)+1,LARGE(A$3:A9,1)) -> 0 | B10: =IF(H10="UNIDADE CONSTRUTIVA",0,IF(H10="CÉLULA CONSTRUTIVA",OFFSET(B10,-1,0)+1,OFFSET(B10,-1,0))) -> 1 | C10: =IF(H10="CÉLULA CONSTRUTIVA",0,IF(H10="ETAPA",OFFSET(C10,-1,0)+1,OFFSET(C10,-1,0))) -> 1 | D10: =IF(H10="ETAPA",0,IF(H10="SUBETAPA",OFFSET(D10,-1,0)+1,OFFSET(D10,-1,0))) -> 1 | E10: =IF(H10="Subetapa",0,IF(H10="serviço",OFFSET(E10,-1,0)+1,OFFSET(E10,-1,0))) -> 0 | H10: SUBETAPA | I10: =IF(H10="Unidade Construtiva",TEXT(A10,"00"),IF(H10="Célula Construtiva",TEXT(B10,"00"),IF(H10="Etapa",CONCATENATE(TEXT(B10,"00"),".",TEXT(C10,"000")),IF(H10="Subetapa",CONCATENATE(TEXT(B10,"00"),".",TEXT(C10,"000"),".",TEXT(D10,"000")),IF(H10="Serviço",CONCATENATE(TEXT(B10,"00"),".",TEXT(C10,"000"),".",TEXT(D10,"000"),".",TEXT(E10,"000")),""))))) -> 01.001.001 | J10: Estudos | N10: =IF(H10="Serviço",M10*L10,IF(H10="CÉLULA CONSTRUTIVA",SUMIFS($N$8:$N$417,$B$8:$B$417,B10,$H$8:$H$417,"Serviço"),IF(H10="ETAPA",SUMIFS($N$8:$N$417,$B$8:$B$417,B10,$C$8:$C$417,C10,$H$8:$H$417,"Serviço"),IF(H10="SUBETAPA",SUMIFS($N$8:$N$417,$B$8:$B$417,B10,$C$8:$C$417,C10,$D$8:$D$417,D10,$H$8:$H$417,"Serviço"),0)))) -> 30575.83
A11: =IF($H11="UNIDADE CONSTRUTIVA",OFFSET(A11,-1,0)+1,LARGE(A$3:A10,1)) -> 0 | B11: =IF(H11="UNIDADE CONSTRUTIVA",0,IF(H11="CÉLULA CONSTRUTIVA",OFFSET(B11,-1,0)+1,OFFSET(B11,-1,0))) -> 1 | C11: =IF(H11="CÉLULA CONSTRUTIVA",0,IF(H11="ETAPA",OFFSET(C11,-1,0)+1,OFFSET(C11,-1,0))) -> 1 | D11: =IF(H11="ETAPA",0,IF(H11="SUBETAPA",OFFSET(D11,-1,0)+1,OFFSET(D11,-1,0))) -> 1 | E11: =IF(H11="Subetapa",0,IF(H11="serviço",OFFSET(E11,-1,0)+1,OFFSET(E11,-1,0))) -> 1 | H11: SERVIÇO | I11: =IF(H11="Unidade Construtiva",TEXT(A11,"00"),IF(H11="Célula Construtiva",TEXT(B11,"00"),IF(H11="Etapa",CONCATENATE(TEXT(B11,"00"),".",TEXT(C11,"000")),IF(H11="Subetapa",CONCATENATE(TEXT(B11,"00"),".",TEXT(C11,"000"),".",TEXT(D11,"000")),IF(H11="Serviço",CONCATENATE(TEXT(B11,"00"),".",TEXT(C11,"000"),".",TEXT(D11,"000"),".",TEXT(E11,"000")),""))))) -> 01.001.001.001 | J11: Memorial descritivo | K11: vb | L11: 1 | M11: 6867.96 | N11: =IF(H11="Serviço",M11*L11,IF(H11="CÉLULA CONSTRUTIVA",SUMIFS($N$8:$N$417,$B$8:$B$417,B11,$H$8:$H$417,"Serviço"),IF(H11="ETAPA",SUMIFS($N$8:$N$417,$B$8:$B$417,B11,$C$8:$C$417,C11,$H$8:$H$417,"Serviço"),IF(H11="SUBETAPA",SUMIFS($N$8:$N$417,$B$8:$B$417,B11,$C$8:$C$417,C11,$D$8:$D$417,D11,$H$8:$H$417,"Serviço"),0)))) -> 6867.96 | O11: Estimado com base em índices históricos | P11: Lançado ERP
A12: =IF($H12="UNIDADE CONSTRUTIVA",OFFSET(A12,-1,0)+1,LARGE(A$3:A11,1)) -> 0 | B12: =IF(H12="UNIDADE CONSTRUTIVA",0,IF(H12="CÉLULA CONSTRUTIVA",OFFSET(B12,-1,0)+1,OFFSET(B12,-1,0))) -> 1 | C12: =IF(H12="CÉLULA CONSTRUTIVA",0,IF(H12="ETAPA",OFFSET(C12,-1,0)+1,OFFSET(C12,-1,0))) -> 1 | D12: =IF(H12="ETAPA",0,IF(H12="SUBETAPA",OFFSET(D12,-1,0)+1,OFFSET(D12,-1,0))) -> 1 | E12: =IF(H12="Subetapa",0,IF(H12="serviço",OFFSET(E12,-1,0)+1,OFFSET(E12,-1,0))) -> 2 | H12: SERVIÇO | I12: =IF(H12="Unidade Construtiva",TEXT(A12,"00"),IF(H12="Célula Construtiva",TEXT(B12,"00"),IF(H12="Etapa",CONCATENATE(TEXT(B12,"00"),".",TEXT(C12,"000")),IF(H12="Subetapa",CONCATENATE(TEXT(B12,"00"),".",TEXT(C12,"000"),".",TEXT(D12,"000")),IF(H12="Serviço",CONCATENATE(TEXT(B12,"00"),".",TEXT(C12,"000"),".",TEXT(D12,"000"),".",TEXT(E12,"000")),""))))) -> 01.001.001.002 | J12: Levantamento Topográfico | K12: vb | L12: 1 | M12: 900 | N12: =IF(H12="Serviço",M12*L12,IF(H12="CÉLULA CONSTRUTIVA",SUMIFS($N$8:$N$417,$B$8:$B$417,B12,$H$8:$H$417,"Serviço"),IF(H12="ETAPA",SUMIFS($N$8:$N$417,$B$8:$B$417,B12,$C$8:$C$417,C12,$H$8:$H$417,"Serviço"),IF(H12="SUBETAPA",SUMIFS($N$8:$N$417,$B$8:$B$417,B12,$C$8:$C$417,C12,$D$8:$D$417,D12,$H$8:$H$417,"Serviço"),0)))) -> 900 | O12: Valor informado em formulário | P12: Lançado ERP
A13: =IF($H13="UNIDADE CONSTRUTIVA",OFFSET(A13,-1,0)+1,LARGE(A$3:A12,1)) -> 0 | B13: =IF(H13="UNIDADE CONSTRUTIVA",0,IF(H13="CÉLULA CONSTRUTIVA",OFFSET(B13,-1,0)+1,OFFSET(B13,-1,0))) -> 1 | C13: =IF(H13="CÉLULA CONSTRUTIVA",0,IF(H13="ETAPA",OFFSET(C13,-1,0)+1,OFFSET(C13,-1,0))) -> 1 | D13: =IF(H13="ETAPA",0,IF(H13="SUBETAPA",OFFSET(D13,-1,0)+1,OFFSET(D13,-1,0))) -> 1 | E13: =IF(H13="Subetapa",0,IF(H13="serviço",OFFSET(E13,-1,0)+1,OFFSET(E13,-1,0))) -> 3 | H13: SERVIÇO | I13: =IF(H13="Unidade Construtiva",TEXT(A13,"00"),IF(H13="Célula Construtiva",TEXT(B13,"00"),IF(H13="Etapa",CONCATENATE(TEXT(B13,"00"),".",TEXT(C13,"000")),IF(H13="Subetapa",CONCATENATE(TEXT(B13,"00"),".",TEXT(C13,"000"),".",TEXT(D13,"000")),IF(H13="Serviço",CONCATENATE(TEXT(B13,"00"),".",TEXT(C13,"000"),".",TEXT(D13,"000"),".",TEXT(E13,"000")),""))))) -> 01.001.001.003 | J13: Estudo geológico | K13: vb | L13: 1 | M13: 5459.91 | N13: =IF(H13="Serviço",M13*L13,IF(H13="CÉLULA CONSTRUTIVA",SUMIFS($N$8:$N$417,$B$8:$B$417,B13,$H$8:$H$417,"Serviço"),IF(H13="ETAPA",SUMIFS($N$8:$N$417,$B$8:$B$417,B13,$C$8:$C$417,C13,$H$8:$H$417,"Serviço"),IF(H13="SUBETAPA",SUMIFS($N$8:$N$417,$B$8:$B$417,B13,$C$8:$C$417,C13,$D$8:$D$417,D13,$H$8:$H$417,"Serviço"),0)))) -> 5459.91 | O13: Estimado com base em índices históricos | P13: Lançado ERP
A14: =IF($H14="UNIDADE CONSTRUTIVA",OFFSET(A14,-1,0)+1,LARGE(A$3:A13,1)) -> 0 | B14: =IF(H14="UNIDADE CONSTRUTIVA",0,IF(H14="CÉLULA CONSTRUTIVA",OFFSET(B14,-1,0)+1,OFFSET(B14,-1,0))) -> 1 | C14: =IF(H14="CÉLULA CONSTRUTIVA",0,IF(H14="ETAPA",OFFSET(C14,-1,0)+1,OFFSET(C14,-1,0))) -> 1 | D14: =IF(H14="ETAPA",0,IF(H14="SUBETAPA",OFFSET(D14,-1,0)+1,OFFSET(D14,-1,0))) -> 1 | E14: =IF(H14="Subetapa",0,IF(H14="serviço",OFFSET(E14,-1,0)+1,OFFSET(E14,-1,0))) -> 4 | H14: SERVIÇO | I14: =IF(H14="Unidade Construtiva",TEXT(A14,"00"),IF(H14="Célula Construtiva",TEXT(B14,"00"),IF(H14="Etapa",CONCATENATE(TEXT(B14,"00"),".",TEXT(C14,"000")),IF(H14="Subetapa",CONCATENATE(TEXT(B14,"00"),".",TEXT(C14,"000"),".",TEXT(D14,"000")),IF(H14="Serviço",CONCATENATE(TEXT(B14,"00"),".",TEXT(C14,"000"),".",TEXT(D14,"000"),".",TEXT(E14,"000")),""))))) -> 01.001.001.004 | J14: Estudo ambiental | K14: vb | L14: 1 | M14: 3866.34 | N14: =IF(H14="Serviço",M14*L14,IF(H14="CÉLULA CONSTRUTIVA",SUMIFS($N$8:$N$417,$B$8:$B$417,B14,$H$8:$H$417,"Serviço"),IF(H14="ETAPA",SUMIFS($N$8:$N$417,$B$8:$B$417,B14,$C$8:$C$417,C14,$H$8:$H$417,"Serviço"),IF(H14="SUBETAPA",SUMIFS($N$8:$N$417,$B$8:$B$417,B14,$C$8:$C$417,C14,$D$8:$D$417,D14,$H$8:$H$417,"Serviço"),0)))) -> 3866.34 | O14: Valor informado em formulário | P14: Lançado ERP
A15: =IF($H15="UNIDADE CONSTRUTIVA",OFFSET(A15,-1,0)+1,LARGE(A$3:A14,1)) -> 0 | B15: =IF(H15="UNIDADE CONSTRUTIVA",0,IF(H15="CÉLULA CONSTRUTIVA",OFFSET(B15,-1,0)+1,OFFSET(B15,-1,0))) -> 1 | C15: =IF(H15="CÉLULA CONSTRUTIVA",0,IF(H15="ETAPA",OFFSET(C15,-1,0)+1,OFFSET(C15,-1,0))) -> 1 | D15: =IF(H15="ETAPA",0,IF(H15="SUBETAPA",OFFSET(D15,-1,0)+1,OFFSET(D15,-1,0))) -> 1 | E15: =IF(H15="Subetapa",0,IF(H15="serviço",OFFSET(E15,-1,0)+1,OFFSET(E15,-1,0))) -> 5 | H15: SERVIÇO | I15: =IF(H15="Unidade Construtiva",TEXT(A15,"00"),IF(H15="Célula Construtiva",TEXT(B15,"00"),IF(H15="Etapa",CONCATENATE(TEXT(B15,"00"),".",TEXT(C15,"000")),IF(H15="Subetapa",CONCATENATE(TEXT(B15,"00"),".",TEXT(C15,"000"),".",TEXT(D15,"000")),IF(H15="Serviço",CONCATENATE(TEXT(B15,"00"),".",TEXT(C15,"000"),".",TEXT(D15,"000"),".",TEXT(E15,"000")),""))))) -> 01.001.001.005 | J15: Sondagem do terreno | K15: vb | L15: 1 | M15: 6586 | N15: =IF(H15="Serviço",M15*L15,IF(H15="CÉLULA CONSTRUTIVA",SUMIFS($N$8:$N$417,$B$8:$B$417,B15,$H$8:$H$417,"Serviço"),IF(H15="ETAPA",SUMIFS($N$8:$N$417,$B$8:$B$417,B15,$C$8:$C$417,C15,$H$8:$H$417,"Serviço"),IF(H15="SUBETAPA",SUMIFS($N$8:$N$417,$B$8:$B$417,B15,$C$8:$C$417,C15,$D$8:$D$417,D15,$H$8:$H$417,"Serviço"),0)))) -> 6586 | O15: Valor informado em formulário | P15: Lançado ERP
A16: =IF($H16="UNIDADE CONSTRUTIVA",OFFSET(A16,-1,0)+1,LARGE(A$3:A15,1)) -> 0 | B16: =IF(H16="UNIDADE CONSTRUTIVA",0,IF(H16="CÉLULA CONSTRUTIVA",OFFSET(B16,-1,0)+1,OFFSET(B16,-1,0))) -> 1 | C16: =IF(H16="CÉLULA CONSTRUTIVA",0,IF(H16="ETAPA",OFFSET(C16,-1,0)+1,OFFSET(C16,-1,0))) -> 1 | D16: =IF(H16="ETAPA",0,IF(H16="SUBETAPA",OFFSET(D16,-1,0)+1,OFFSET(D16,-1,0))) -> 1 | E16: =IF(H16="Subetapa",0,IF(H16="serviço",OFFSET(E16,-1,0)+1,OFFSET(E16,-1,0))) -> 6 | H16: SERVIÇO | I16: =IF(H16="Unidade Construtiva",TEXT(A16,"00"),IF(H16="Célula Construtiva",TEXT(B16,"00"),IF(H16="Etapa",CONCATENATE(TEXT(B16,"00"),".",TEXT(C16,"000")),IF(H16="Subetapa",CONCATENATE(TEXT(B16,"00"),".",TEXT(C16,"000"),".",TEXT(D16,"000")),IF(H16="Serviço",CONCATENATE(TEXT(B16,"00"),".",TEXT(C16,"000"),".",TEXT(D16,"000"),".",TEXT(E16,"000")),""))))) -> 01.001.001.006 | J16: Projeto de canteiro | K16: vb | L16: 1 | M16: 6895.62 | N16: =IF(H16="Serviço",M16*L16,IF(H16="CÉLULA CONSTRUTIVA",SUMIFS($N$8:$N$417,$B$8:$B$417,B16,$H$8:$H$417,"Serviço"),IF(H16="ETAPA",SUMIFS($N$8:$N$417,$B$8:$B$417,B16,$C$8:$C$417,C16,$H$8:$H$417,"Serviço"),IF(H16="SUBETAPA",SUMIFS($N$8:$N$417,$B$8:$B$417,B16,$C$8:$C$417,C16,$D$8:$D$417,D16,$H$8:$H$417,"Serviço"),0)))) -> 6895.62 | O16: Estimado com base em índices históricos para elaboração interna | P16: Lançado ERP
A17: =IF($H17="UNIDADE CONSTRUTIVA",OFFSET(A17,-1,0)+1,LARGE(A$3:A16,1)) -> 0 | B17: =IF(H17="UNIDADE CONSTRUTIVA",0,IF(H17="CÉLULA CONSTRUTIVA",OFFSET(B17,-1,0)+1,OFFSET(B17,-1,0))) -> 1 | C17: =IF(H17="CÉLULA CONSTRUTIVA",0,IF(H17="ETAPA",OFFSET(C17,-1,0)+1,OFFSET(C17,-1,0))) -> 1 | D17: =IF(H17="ETAPA",0,IF(H17="SUBETAPA",OFFSET(D17,-1,0)+1,OFFSET(D17,-1,0))) -> 2 | E17: =IF(H17="Subetapa",0,IF(H17="serviço",OFFSET(E17,-1,0)+1,OFFSET(E17,-1,0))) -> 0 | H17: SUBETAPA | I17: =IF(H17="Unidade Construtiva",TEXT(A17,"00"),IF(H17="Célula Construtiva",TEXT(B17,"00"),IF(H17="Etapa",CONCATENATE(TEXT(B17,"00"),".",TEXT(C17,"000")),IF(H17="Subetapa",CONCATENATE(TEXT(B17,"00"),".",TEXT(C17,"000"),".",TEXT(D17,"000")),IF(H17="Serviço",CONCATENATE(TEXT(B17,"00"),".",TEXT(C17,"000"),".",TEXT(D17,"000"),".",TEXT(E17,"000")),""))))) -> 01.001.002 | J17: Projetos | N17: =IF(H17="Serviço",M17*L17,IF(H17="CÉLULA CONSTRUTIVA",SUMIFS($N$8:$N$417,$B$8:$B$417,B17,$H$8:$H$417,"Serviço"),IF(H17="ETAPA",SUMIFS($N$8:$N$417,$B$8:$B$417,B17,$C$8:$C$417,C17,$H$8:$H$417,"Serviço"),IF(H17="SUBETAPA",SUMIFS($N$8:$N$417,$B$8:$B$417,B17,$C$8:$C$417,C17,$D$8:$D$417,D17,$H$8:$H$417,"Serviço"),0)))) -> 265788.02
A18: =IF($H18="UNIDADE CONSTRUTIVA",OFFSET(A18,-1,0)+1,LARGE(A$3:A17,1)) -> 0 | B18: =IF(H18="UNIDADE CONSTRUTIVA",0,IF(H18="CÉLULA CONSTRUTIVA",OFFSET(B18,-1,0)+1,OFFSET(B18,-1,0))) -> 1 | C18: =IF(H18="CÉLULA CONSTRUTIVA",0,IF(H18="ETAPA",OFFSET(C18,-1,0)+1,OFFSET(C18,-1,0))) -> 1 | D18: =IF(H18="ETAPA",0,IF(H18="SUBETAPA",OFFSET(D18,-1,0)+1,OFFSET(D18,-1,0))) -> 2 | E18: =IF(H18="Subetapa",0,IF(H18="serviço",OFFSET(E18,-1,0)+1,OFFSET(E18,-1,0))) -> 1 | H18: SERVIÇO | I18: =IF(H18="Unidade Construtiva",TEXT(A18,"00"),IF(H18="Célula Construtiva",TEXT(B18,"00"),IF(H18="Etapa",CONCATENATE(TEXT(B18,"00"),".",TEXT(C18,"000")),IF(H18="Subetapa",CONCATENATE(TEXT(B18,"00"),".",TEXT(C18,"000"),".",TEXT(D18,"000")),IF(H18="Serviço",CONCATENATE(TEXT(B18,"00"),".",TEXT(C18,"000"),".",TEXT(D18,"000"),".",TEXT(E18,"000")),""))))) -> 01.001.002.001 | J18: Legalização de incorporação | K18: vb | L18: 1 | M18: 14611.4 | N18: =IF(H18="Serviço",M18*L18,IF(H18="CÉLULA CONSTRUTIVA",SUMIFS($N$8:$N$417,$B$8:$B$417,B18,$H$8:$H$417,"Serviço"),IF(H18="ETAPA",SUMIFS($N$8:$N$417,$B$8:$B$417,B18,$C$8:$C$417,C18,$H$8:$H$417,"Serviço"),IF(H18="SUBETAPA",SUMIFS($N$8:$N$417,$B$8:$B$417,B18,$C$8:$C$417,C18,$D$8:$D$417,D18,$H$8:$H$417,"Serviço"),0)))) -> 14611.4 | O18: Valor informado em formulário | P18: Lançado ERP
A19: =IF($H19="UNIDADE CONSTRUTIVA",OFFSET(A19,-1,0)+1,LARGE(A$3:A18,1)) -> 0 | B19: =IF(H19="UNIDADE CONSTRUTIVA",0,IF(H19="CÉLULA CONSTRUTIVA",OFFSET(B19,-1,0)+1,OFFSET(B19,-1,0))) -> 1 | C19: =IF(H19="CÉLULA CONSTRUTIVA",0,IF(H19="ETAPA",OFFSET(C19,-1,0)+1,OFFSET(C19,-1,0))) -> 1 | D19: =IF(H19="ETAPA",0,IF(H19="SUBETAPA",OFFSET(D19,-1,0)+1,OFFSET(D19,-1,0))) -> 2 | E19: =IF(H19="Subetapa",0,IF(H19="serviço",OFFSET(E19,-1,0)+1,OFFSET(E19,-1,0))) -> 2 | H19: SERVIÇO | I19: =IF(H19="Unidade Construtiva",TEXT(A19,"00"),IF(H19="Célula Construtiva",TEXT(B19,"00"),IF(H19="Etapa",CONCATENATE(TEXT(B19,"00"),".",TEXT(C19,"000")),IF(H19="Subetapa",CONCATENATE(TEXT(B19,"00"),".",TEXT(C19,"000"),".",TEXT(D19,"000")),IF(H19="Serviço",CONCATENATE(TEXT(B19,"00"),".",TEXT(C19,"000"),".",TEXT(D19,"000"),".",TEXT(E19,"000")),""))))) -> 01.001.002.002 | J19: Projeto Arquitetônico legal - incluindo: executivo + elétrico + comunicação e dados + telefonia + luminotécnico + hidrosanitário + drenagem + pluvial + gás | K19: vb | L19: 1 | M19: 80000 | N19: =IF(H19="Serviço",M19*L19,IF(H19="CÉLULA CONSTRUTIVA",SUMIFS($N$8:$N$417,$B$8:$B$417,B19,$H$8:$H$417,"Serviço"),IF(H19="ETAPA",SUMIFS($N$8:$N$417,$B$8:$B$417,B19,$C$8:$C$417,C19,$H$8:$H$417,"Serviço"),IF(H19="SUBETAPA",SUMIFS($N$8:$N$417,$B$8:$B$417,B19,$C$8:$C$417,C19,$D$8:$D$417,D19,$H$8:$H$417,"Serviço"),0)))) -> 80000 | O19: Valor informado em formulário | P19: Lançado ERP
A20: =IF($H20="UNIDADE CONSTRUTIVA",OFFSET(A20,-1,0)+1,LARGE(A$3:A19,1)) -> 0 | B20: =IF(H20="UNIDADE CONSTRUTIVA",0,IF(H20="CÉLULA CONSTRUTIVA",OFFSET(B20,-1,0)+1,OFFSET(B20,-1,0))) -> 1 | C20: =IF(H20="CÉLULA CONSTRUTIVA",0,IF(H20="ETAPA",OFFSET(C20,-1,0)+1,OFFSET(C20,-1,0))) -> 1 | D20: =IF(H20="ETAPA",0,IF(H20="SUBETAPA",OFFSET(D20,-1,0)+1,OFFSET(D20,-1,0))) -> 2 | E20: =IF(H20="Subetapa",0,IF(H20="serviço",OFFSET(E20,-1,0)+1,OFFSET(E20,-1,0))) -> 3 | H20: SERVIÇO | I20: =IF(H20="Unidade Construtiva",TEXT(A20,"00"),IF(H20="Célula Construtiva",TEXT(B20,"00"),IF(H20="Etapa",CONCATENATE(TEXT(B20,"00"),".",TEXT(C20,"000")),IF(H20="Subetapa",CONCATENATE(TEXT(B20,"00"),".",TEXT(C20,"000"),".",TEXT(D20,"000")),IF(H20="Serviço",CONCATENATE(TEXT(B20,"00"),".",TEXT(C20,"000"),".",TEXT(D20,"000"),".",TEXT(E20,"000")),""))))) -> 01.001.002.003 | J20: Projeto arquitetônico interiores/ambientação | K20: vb | L20: 1 | M20: 68955.14 | N20: =IF(H20="Serviço",M20*L20,IF(H20="CÉLULA CONSTRUTIVA",SUMIFS($N$8:$N$417,$B$8:$B$417,B20,$H$8:$H$417,"Serviço"),IF(H20="ETAPA",SUMIFS($N$8:$N$417,$B$8:$B$417,B20,$C$8:$C$417,C20,$H$8:$H$417,"Serviço"),IF(H20="SUBETAPA",SUMIFS($N$8:$N$417,$B$8:$B$417,B20,$C$8:$C$417,C20,$D$8:$D$417,D20,$H$8:$H$417,"Serviço"),0)))) -> 68955.14 | O20: Estimado com base em índices históricos | P20: Lançado ERP
A21: =IF($H21="UNIDADE CONSTRUTIVA",OFFSET(A21,-1,0)+1,LARGE(A$3:A20,1)) -> 0 | B21: =IF(H21="UNIDADE CONSTRUTIVA",0,IF(H21="CÉLULA CONSTRUTIVA",OFFSET(B21,-1,0)+1,OFFSET(B21,-1,0))) -> 1 | C21: =IF(H21="CÉLULA CONSTRUTIVA",0,IF(H21="ETAPA",OFFSET(C21,-1,0)+1,OFFSET(C21,-1,0))) -> 1 | D21: =IF(H21="ETAPA",0,IF(H21="SUBETAPA",OFFSET(D21,-1,0)+1,OFFSET(D21,-1,0))) -> 2 | E21: =IF(H21="Subetapa",0,IF(H21="serviço",OFFSET(E21,-1,0)+1,OFFSET(E21,-1,0))) -> 4 | H21: SERVIÇO | I21: =IF(H21="Unidade Construtiva",TEXT(A21,"00"),IF(H21="Célula Construtiva",TEXT(B21,"00"),IF(H21="Etapa",CONCATENATE(TEXT(B21,"00"),".",TEXT(C21,"000")),IF(H21="Subetapa",CONCATENATE(TEXT(B21,"00"),".",TEXT(C21,"000"),".",TEXT(D21,"000")),IF(H21="Serviço",CONCATENATE(TEXT(B21,"00"),".",TEXT(C21,"000"),".",TEXT(D21,"000"),".",TEXT(E21,"000")),""))))) -> 01.001.002.004 | J21: Projeto arquitetônico de fachada | K21: vb | L21: 1 | M21: 2721.48 | N21: =IF(H21="Serviço",M21*L21,IF(H21="CÉLULA CONSTRUTIVA",SUMIFS($N$8:$N$417,$B$8:$B$417,B21,$H$8:$H$417,"Serviço"),IF(H21="ETAPA",SUMIFS($N$8:$N$417,$B$8:$B$417,B21,$C$8:$C$417,C21,$H$8:$H$417,"Serviço"),IF(H21="SUBETAPA",SUMIFS($N$8:$N$417,$B$8:$B$417,B21,$C$8:$C$417,C21,$D$8:$D$417,D21,$H$8:$H$417,"Serviço"),0)))) -> 2721.48 | O21: Estimado com base em índices históricos | P21: Lançado ERP
A22: =IF($H22="UNIDADE CONSTRUTIVA",OFFSET(A22,-1,0)+1,LARGE(A$3:A21,1)) -> 0 | B22: =IF(H22="UNIDADE CONSTRUTIVA",0,IF(H22="CÉLULA CONSTRUTIVA",OFFSET(B22,-1,0)+1,OFFSET(B22,-1,0))) -> 1 | C22: =IF(H22="CÉLULA CONSTRUTIVA",0,IF(H22="ETAPA",OFFSET(C22,-1,0)+1,OFFSET(C22,-1,0))) -> 1 | D22: =IF(H22="ETAPA",0,IF(H22="SUBETAPA",OFFSET(D22,-1,0)+1,OFFSET(D22,-1,0))) -> 2 | E22: =IF(H22="Subetapa",0,IF(H22="serviço",OFFSET(E22,-1,0)+1,OFFSET(E22,-1,0))) -> 5 | H22: SERVIÇO | I22: =IF(H22="Unidade Construtiva",TEXT(A22,"00"),IF(H22="Célula Construtiva",TEXT(B22,"00"),IF(H22="Etapa",CONCATENATE(TEXT(B22,"00"),".",TEXT(C22,"000")),IF(H22="Subetapa",CONCATENATE(TEXT(B22,"00"),".",TEXT(C22,"000"),".",TEXT(D22,"000")),IF(H22="Serviço",CONCATENATE(TEXT(B22,"00"),".",TEXT(C22,"000"),".",TEXT(D22,"000"),".",TEXT(E22,"000")),""))))) -> 01.001.002.005 | J22: Projeto Estrutura | K22: vb | L22: 1 | M22: 65000 | N22: =IF(H22="Serviço",M22*L22,IF(H22="CÉLULA CONSTRUTIVA",SUMIFS($N$8:$N$417,$B$8:$B$417,B22,$H$8:$H$417,"Serviço"),IF(H22="ETAPA",SUMIFS($N$8:$N$417,$B$8:$B$417,B22,$C$8:$C$417,C22,$H$8:$H$417,"Serviço"),IF(H22="SUBETAPA",SUMIFS($N$8:$N$417,$B$8:$B$417,B22,$C$8:$C$417,C22,$D$8:$D$417,D22,$H$8:$H$417,"Serviço"),0)))) -> 65000 | O22: Valor informado em formulário | P22: Lançado ERP
A23: =IF($H23="UNIDADE CONSTRUTIVA",OFFSET(A23,-1,0)+1,LARGE(A$3:A22,1)) -> 0 | B23: =IF(H23="UNIDADE CONSTRUTIVA",0,IF(H23="CÉLULA CONSTRUTIVA",OFFSET(B23,-1,0)+1,OFFSET(B23,-1,0))) -> 1 | C23: =IF(H23="CÉLULA CONSTRUTIVA",0,IF(H23="ETAPA",OFFSET(C23,-1,0)+1,OFFSET(C23,-1,0))) -> 1 | D23: =IF(H23="ETAPA",0,IF(H23="SUBETAPA",OFFSET(D23,-1,0)+1,OFFSET(D23,-1,0))) -> 2 | E23: =IF(H23="Subetapa",0,IF(H23="serviço",OFFSET(E23,-1,0)+1,OFFSET(E23,-1,0))) -> 6 | H23: SERVIÇO | I23: =IF(H23="Unidade Construtiva",TEXT(A23,"00"),IF(H23="Célula Construtiva",TEXT(B23,"00"),IF(H23="Etapa",CONCATENATE(TEXT(B23,"00"),".",TEXT(C23,"000")),IF(H23="Subetapa",CONCATENATE(TEXT(B23,"00"),".",TEXT(C23,"000"),".",TEXT(D23,"000")),IF(H23="Serviço",CONCATENATE(TEXT(B23,"00"),".",TEXT(C23,"000"),".",TEXT(D23,"000"),".",TEXT(E23,"000")),""))))) -> 01.001.002.006 | J23: Projeto de terraplanagem | K23: vb | L23: 1 | M23: 8000 | N23: =IF(H23="Serviço",M23*L23,IF(H23="CÉLULA CONSTRUTIVA",SUMIFS($N$8:$N$417,$B$8:$B$417,B23,$H$8:$H$417,"Serviço"),IF(H23="ETAPA",SUMIFS($N$8:$N$417,$B$8:$B$417,B23,$C$8:$C$417,C23,$H$8:$H$417,"Serviço"),IF(H23="SUBETAPA",SUMIFS($N$8:$N$417,$B$8:$B$417,B23,$C$8:$C$417,C23,$D$8:$D$417,D23,$H$8:$H$417,"Serviço"),0)))) -> 8000 | O23: Valor informado em formulário COM EXECUÇÃO - projeto estimado com base em índices históricos | P23: Lançado ERP
A24: =IF($H24="UNIDADE CONSTRUTIVA",OFFSET(A24,-1,0)+1,LARGE(A$3:A23,1)) -> 0 | B24: =IF(H24="UNIDADE CONSTRUTIVA",0,IF(H24="CÉLULA CONSTRUTIVA",OFFSET(B24,-1,0)+1,OFFSET(B24,-1,0))) -> 1 | C24: =IF(H24="CÉLULA CONSTRUTIVA",0,IF(H24="ETAPA",OFFSET(C24,-1,0)+1,OFFSET(C24,-1,0))) -> 1 | D24: =IF(H24="ETAPA",0,IF(H24="SUBETAPA",OFFSET(D24,-1,0)+1,OFFSET(D24,-1,0))) -> 2 | E24: =IF(H24="Subetapa",0,IF(H24="serviço",OFFSET(E24,-1,0)+1,OFFSET(E24,-1,0))) -> 7 | H24: SERVIÇO | I24: =IF(H24="Unidade Construtiva",TEXT(A24,"00"),IF(H24="Célula Construtiva",TEXT(B24,"00"),IF(H24="Etapa",CONCATENATE(TEXT(B24,"00"),".",TEXT(C24,"000")),IF(H24="Subetapa",CONCATENATE(TEXT(B24,"00"),".",TEXT(C24,"000"),".",TEXT(D24,"000")),IF(H24="Serviço",CONCATENATE(TEXT(B24,"00"),".",TEXT(C24,"000"),".",TEXT(D24,"000"),".",TEXT(E24,"000")),""))))) -> 01.001.002.007 | J24: Projeto Fundações | K24: vb | L24: 1 | M24: 15000 | N24: =IF(H24="Serviço",M24*L24,IF(H24="CÉLULA CONSTRUTIVA",SUMIFS($N$8:$N$417,$B$8:$B$417,B24,$H$8:$H$417,"Serviço"),IF(H24="ETAPA",SUMIFS($N$8:$N$417,$B$8:$B$417,B24,$C$8:$C$417,C24,$H$8:$H$417,"Serviço"),IF(H24="SUBETAPA",SUMIFS($N$8:$N$417,$B$8:$B$417,B24,$C$8:$C$417,C24,$D$8:$D$417,D24,$H$8:$H$417,"Serviço"),0)))) -> 15000 | O24: Valor informado em formulário COM EXECUÇÃO - projeto estimado com base em índices históricos | P24: Lançado ERP
A25: =IF($H25="UNIDADE CONSTRUTIVA",OFFSET(A25,-1,0)+1,LARGE(A$3:A24,1)) -> 0 | B25: =IF(H25="UNIDADE CONSTRUTIVA",0,IF(H25="CÉLULA CONSTRUTIVA",OFFSET(B25,-1,0)+1,OFFSET(B25,-1,0))) -> 1 | C25: =IF(H25="CÉLULA CONSTRUTIVA",0,IF(H25="ETAPA",OFFSET(C25,-1,0)+1,OFFSET(C25,-1,0))) -> 1 | D25: =IF(H25="ETAPA",0,IF(H25="SUBETAPA",OFFSET(D25,-1,0)+1,OFFSET(D25,-1,0))) -> 2 | E25: =IF(H25="Subetapa",0,IF(H25="serviço",OFFSET(E25,-1,0)+1,OFFSET(E25,-1,0))) -> 8 | H25: SERVIÇO | I25: =IF(H25="Unidade Construtiva",TEXT(A25,"00"),IF(H25="Célula Construtiva",TEXT(B25,"00"),IF(H25="Etapa",CONCATENATE(TEXT(B25,"00"),".",TEXT(C25,"000")),IF(H25="Subetapa",CONCATENATE(TEXT(B25,"00"),".",TEXT(C25,"000"),".",TEXT(D25,"000")),IF(H25="Serviço",CONCATENATE(TEXT(B25,"00"),".",TEXT(C25,"000"),".",TEXT(D25,"000"),".",TEXT(E25,"000")),""))))) -> 01.001.002.008 | J25: Projeto preventivo (PPCI - Plano de Prevenção e Proteção Contra Incêndios) | K25: vb | L25: 1 | M25: 8500 | N25: =IF(H25="Serviço",M25*L25,IF(H25="CÉLULA CONSTRUTIVA",SUMIFS($N$8:$N$417,$B$8:$B$417,B25,$H$8:$H$417,"Serviço"),IF(H25="ETAPA",SUMIFS($N$8:$N$417,$B$8:$B$417,B25,$C$8:$C$417,C25,$H$8:$H$417,"Serviço"),IF(H25="SUBETAPA",SUMIFS($N$8:$N$417,$B$8:$B$417,B25,$C$8:$C$417,C25,$D$8:$D$417,D25,$H$8:$H$417,"Serviço"),0)))) -> 8500 | O25: Valor informado em formulário COM EXECUÇÃO - projeto estimado com base em índices históricos | P25: Lançado ERP
A26: =IF($H26="UNIDADE CONSTRUTIVA",OFFSET(A26,-1,0)+1,LARGE(A$3:A25,1)) -> 0 | B26: =IF(H26="UNIDADE CONSTRUTIVA",0,IF(H26="CÉLULA CONSTRUTIVA",OFFSET(B26,-1,0)+1,OFFSET(B26,-1,0))) -> 1 | C26: =IF(H26="CÉLULA CONSTRUTIVA",0,IF(H26="ETAPA",OFFSET(C26,-1,0)+1,OFFSET(C26,-1,0))) -> 1 | D26: =IF(H26="ETAPA",0,IF(H26="SUBETAPA",OFFSET(D26,-1,0)+1,OFFSET(D26,-1,0))) -> 2 | E26: =IF(H26="Subetapa",0,IF(H26="serviço",OFFSET(E26,-1,0)+1,OFFSET(E26,-1,0))) -> 9 | H26: SERVIÇO | I26: =IF(H26="Unidade Construtiva",TEXT(A26,"00"),IF(H26="Célula Construtiva",TEXT(B26,"00"),IF(H26="Etapa",CONCATENATE(TEXT(B26,"00"),".",TEXT(C26,"000")),IF(H26="Subetapa",CONCATENATE(TEXT(B26,"00"),".",TEXT(C26,"000"),".",TEXT(D26,"000")),IF(H26="Serviço",CONCATENATE(TEXT(B26,"00"),".",TEXT(C26,"000"),".",TEXT(D26,"000"),".",TEXT(E26,"000")),""))))) -> 01.001.002.009 | J26: Projeto de segurança | K26: vb | L26: 1 | M26: 3000 | N26: =IF(H26="Serviço",M26*L26,IF(H26="CÉLULA CONSTRUTIVA",SUMIFS($N$8:$N$417,$B$8:$B$417,B26,$H$8:$H$417,"Serviço"),IF(H26="ETAPA",SUMIFS($N$8:$N$417,$B$8:$B$417,B26,$C$8:$C$417,C26,$H$8:$H$417,"Serviço"),IF(H26="SUBETAPA",SUMIFS($N$8:$N$417,$B$8:$B$417,B26,$C$8:$C$417,C26,$D$8:$D$417,D26,$H$8:$H$417,"Serviço"),0)))) -> 3000 | O26: Valor informado em formulário | P26: Lançado ERP
A27: =IF($H27="UNIDADE CONSTRUTIVA",OFFSET(A27,-1,0)+1,LARGE(A$3:A26,1)) -> 0 | B27: =IF(H27="UNIDADE CONSTRUTIVA",0,IF(H27="CÉLULA CONSTRUTIVA",OFFSET(B27,-1,0)+1,OFFSET(B27,-1,0))) -> 1 | C27: =IF(H27="CÉLULA CONSTRUTIVA",0,IF(H27="ETAPA",OFFSET(C27,-1,0)+1,OFFSET(C27,-1,0))) -> 1 | D27: =IF(H27="ETAPA",0,IF(H27="SUBETAPA",OFFSET(D27,-1,0)+1,OFFSET(D27,-1,0))) -> 3 | E27: =IF(H27="Subetapa",0,IF(H27="serviço",OFFSET(E27,-1,0)+1,OFFSET(E27,-1,0))) -> 0 | H27: SUBETAPA | I27: =IF(H27="Unidade Construtiva",TEXT(A27,"00"),IF(H27="Célula Construtiva",TEXT(B27,"00"),IF(H27="Etapa",CONCATENATE(TEXT(B27,"00"),".",TEXT(C27,"000")),IF(H27="Subetapa",CONCATENATE(TEXT(B27,"00"),".",TEXT(C27,"000"),".",TEXT(D27,"000")),IF(H27="Serviço",CONCATENATE(TEXT(B27,"00"),".",TEXT(C27,"000"),".",TEXT(D27,"000"),".",TEXT(E27,"000")),""))))) -> 01.001.003 | J27: Consultorias | N27: =IF(H27="Serviço",M27*L27,IF(H27="CÉLULA CONSTRUTIVA",SUMIFS($N$8:$N$417,$B$8:$B$417,B27,$H$8:$H$417,"Serviço"),IF(H27="ETAPA",SUMIFS($N$8:$N$417,$B$8:$B$417,B27,$C$8:$C$417,C27,$H$8:$H$417,"Serviço"),IF(H27="SUBETAPA",SUMIFS($N$8:$N$417,$B$8:$B$417,B27,$C$8:$C$417,C27,$D$8:$D$417,D27,$H$8:$H$417,"Serviço"),0)))) -> 101073.6
A28: =IF($H28="UNIDADE CONSTRUTIVA",OFFSET(A28,-1,0)+1,LARGE(A$3:A27,1)) -> 0 | B28: =IF(H28="UNIDADE CONSTRUTIVA",0,IF(H28="CÉLULA CONSTRUTIVA",OFFSET(B28,-1,0)+1,OFFSET(B28,-1,0))) -> 1 | C28: =IF(H28="CÉLULA CONSTRUTIVA",0,IF(H28="ETAPA",OFFSET(C28,-1,0)+1,OFFSET(C28,-1,0))) -> 1 | D28: =IF(H28="ETAPA",0,IF(H28="SUBETAPA",OFFSET(D28,-1,0)+1,OFFSET(D28,-1,0))) -> 3 | E28: =IF(H28="Subetapa",0,IF(H28="serviço",OFFSET(E28,-1,0)+1,OFFSET(E28,-1,0))) -> 1 | H28: SERVIÇO | I28: =IF(H28="Unidade Construtiva",TEXT(A28,"00"),IF(H28="Célula Construtiva",TEXT(B28,"00"),IF(H28="Etapa",CONCATENATE(TEXT(B28,"00"),".",TEXT(C28,"000")),IF(H28="Subetapa",CONCATENATE(TEXT(B28,"00"),".",TEXT(C28,"000"),".",TEXT(D28,"000")),IF(H28="Serviço",CONCATENATE(TEXT(B28,"00"),".",TEXT(C28,"000"),".",TEXT(D28,"000"),".",TEXT(E28,"000")),""))))) -> 01.001.003.001 | J28: Consultoria técnica de legalização | K28: vb | L28: 1 | M28: 37872.56 | N28: =IF(H28="Serviço",M28*L28,IF(H28="CÉLULA CONSTRUTIVA",SUMIFS($N$8:$N$417,$B$8:$B$417,B28,$H$8:$H$417,"Serviço"),IF(H28="ETAPA",SUMIFS($N$8:$N$417,$B$8:$B$417,B28,$C$8:$C$417,C28,$H$8:$H$417,"Serviço"),IF(H28="SUBETAPA",SUMIFS($N$8:$N$417,$B$8:$B$417,B28,$C$8:$C$417,C28,$D$8:$D$417,D28,$H$8:$H$417,"Serviço"),0)))) -> 37872.56 | O28: Estimado com base em índices históricos | P28: Lançado ERP
A29: =IF($H29="UNIDADE CONSTRUTIVA",OFFSET(A29,-1,0)+1,LARGE(A$3:A28,1)) -> 0 | B29: =IF(H29="UNIDADE CONSTRUTIVA",0,IF(H29="CÉLULA CONSTRUTIVA",OFFSET(B29,-1,0)+1,OFFSET(B29,-1,0))) -> 1 | C29: =IF(H29="CÉLULA CONSTRUTIVA",0,IF(H29="ETAPA",OFFSET(C29,-1,0)+1,OFFSET(C29,-1,0))) -> 1 | D29: =IF(H29="ETAPA",0,IF(H29="SUBETAPA",OFFSET(D29,-1,0)+1,OFFSET(D29,-1,0))) -> 3 | E29: =IF(H29="Subetapa",0,IF(H29="serviço",OFFSET(E29,-1,0)+1,OFFSET(E29,-1,0))) -> 2 | H29: SERVIÇO | I29: =IF(H29="Unidade Construtiva",TEXT(A29,"00"),IF(H29="Célula Construtiva",TEXT(B29,"00"),IF(H29="Etapa",CONCATENATE(TEXT(B29,"00"),".",TEXT(C29,"000")),IF(H29="Subetapa",CONCATENATE(TEXT(B29,"00"),".",TEXT(C29,"000"),".",TEXT(D29,"000")),IF(H29="Serviço",CONCATENATE(TEXT(B29,"00"),".",TEXT(C29,"000"),".",TEXT(D29,"000"),".",TEXT(E29,"000")),""))))) -> 01.001.003.002 | J29: Orçamento e planejamento | K29: vb | L29: 1 | M29: =24500+11900 -> 36400 | N29: =IF(H29="Serviço",M29*L29,IF(H29="CÉLULA CONSTRUTIVA",SUMIFS($N$8:$N$417,$B$8:$B$417,B29,$H$8:$H$417,"Serviço"),IF(H29="ETAPA",SUMIFS($N$8:$N$417,$B$8:$B$417,B29,$C$8:$C$417,C29,$H$8:$H$417,"Serviço"),IF(H29="SUBETAPA",SUMIFS($N$8:$N$417,$B$8:$B$417,B29,$C$8:$C$417,C29,$D$8:$D$417,D29,$H$8:$H$417,"Serviço"),0)))) -> 36400 | O29: Custo de contratação Cartesian | P29: Lançado ERP
A30: =IF($H30="UNIDADE CONSTRUTIVA",OFFSET(A30,-1,0)+1,LARGE(A$3:A29,1)) -> 0 | B30: =IF(H30="UNIDADE CONSTRUTIVA",0,IF(H30="CÉLULA CONSTRUTIVA",OFFSET(B30,-1,0)+1,OFFSET(B30,-1,0))) -> 1 | C30: =IF(H30="CÉLULA CONSTRUTIVA",0,IF(H30="ETAPA",OFFSET(C30,-1,0)+1,OFFSET(C30,-1,0))) -> 1 | D30: =IF(H30="ETAPA",0,IF(H30="SUBETAPA",OFFSET(D30,-1,0)+1,OFFSET(D30,-1,0))) -> 3 | E30: =IF(H30="Subetapa",0,IF(H30="serviço",OFFSET(E30,-1,0)+1,OFFSET(E30,-1,0))) -> 3 | H30: SERVIÇO | I30: =IF(H30="Unidade Construtiva",TEXT(A30,"00"),IF(H30="Célula Construtiva",TEXT(B30,"00"),IF(H30="Etapa",CONCATENATE(TEXT(B30,"00"),".",TEXT(C30,"000")),IF(H30="Subetapa",CONCATENATE(TEXT(B30,"00"),".",TEXT(C30,"000"),".",TEXT(D30,"000")),IF(H30="Serviço",CONCATENATE(TEXT(B30,"00"),".",TEXT(C30,"000"),".",TEXT(D30,"000"),".",TEXT(E30,"000")),""))))) -> 01.001.003.003 | J30: Consultoria técnicas diversas | K30: vb | L30: 1 | M30: 16492.95 | N30: =IF(H30="Serviço",M30*L30,IF(H30="CÉLULA CONSTRUTIVA",SUMIFS($N$8:$N$417,$B$8:$B$417,B30,$H$8:$H$417,"Serviço"),IF(H30="ETAPA",SUMIFS($N$8:$N$417,$B$8:$B$417,B30,$C$8:$C$417,C30,$H$8:$H$417,"Serviço"),IF(H30="SUBETAPA",SUMIFS($N$8:$N$417,$B$8:$B$417,B30,$C$8:$C$417,C30,$D$8:$D$417,D30,$H$8:$H$417,"Serviço"),0)))) -> 16492.95 | O30: Estimado com base em índices históricos | P30: Lançado ERP
A31: =IF($H31="UNIDADE CONSTRUTIVA",OFFSET(A31,-1,0)+1,LARGE(A$3:A30,1)) -> 0 | B31: =IF(H31="UNIDADE CONSTRUTIVA",0,IF(H31="CÉLULA CONSTRUTIVA",OFFSET(B31,-1,0)+1,OFFSET(B31,-1,0))) -> 1 | C31: =IF(H31="CÉLULA CONSTRUTIVA",0,IF(H31="ETAPA",OFFSET(C31,-1,0)+1,OFFSET(C31,-1,0))) -> 1 | D31: =IF(H31="ETAPA",0,IF(H31="SUBETAPA",OFFSET(D31,-1,0)+1,OFFSET(D31,-1,0))) -> 3 | E31: =IF(H31="Subetapa",0,IF(H31="serviço",OFFSET(E31,-1,0)+1,OFFSET(E31,-1,0))) -> 4 | H31: SERVIÇO | I31: =IF(H31="Unidade Construtiva",TEXT(A31,"00"),IF(H31="Célula Construtiva",TEXT(B31,"00"),IF(H31="Etapa",CONCATENATE(TEXT(B31,"00"),".",TEXT(C31,"000")),IF(H31="Subetapa",CONCATENATE(TEXT(B31,"00"),".",TEXT(C31,"000"),".",TEXT(D31,"000")),IF(H31="Serviço",CONCATENATE(TEXT(B31,"00"),".",TEXT(C31,"000"),".",TEXT(D31,"000"),".",TEXT(E31,"000")),""))))) -> 01.001.003.004 | J31: Auditoria de qualidade | K31: vb | L31: 1 | M31: 10308.09 | N31: =IF(H31="Serviço",M31*L31,IF(H31="CÉLULA CONSTRUTIVA",SUMIFS($N$8:$N$417,$B$8:$B$417,B31,$H$8:$H$417,"Serviço"),IF(H31="ETAPA",SUMIFS($N$8:$N$417,$B$8:$B$417,B31,$C$8:$C$417,C31,$H$8:$H$417,"Serviço"),IF(H31="SUBETAPA",SUMIFS($N$8:$N$417,$B$8:$B$417,B31,$C$8:$C$417,C31,$D$8:$D$417,D31,$H$8:$H$417,"Serviço"),0)))) -> 10308.09 | O31: Estimado com base em índices históricos | P31: Lançado ERP
A32: =IF($H32="UNIDADE CONSTRUTIVA",OFFSET(A32,-1,0)+1,LARGE(A$3:A31,1)) -> 0 | B32: =IF(H32="UNIDADE CONSTRUTIVA",0,IF(H32="CÉLULA CONSTRUTIVA",OFFSET(B32,-1,0)+1,OFFSET(B32,-1,0))) -> 1 | C32: =IF(H32="CÉLULA CONSTRUTIVA",0,IF(H32="ETAPA",OFFSET(C32,-1,0)+1,OFFSET(C32,-1,0))) -> 1 | D32: =IF(H32="ETAPA",0,IF(H32="SUBETAPA",OFFSET(D32,-1,0)+1,OFFSET(D32,-1,0))) -> 4 | E32: =IF(H32="Subetapa",0,IF(H32="serviço",OFFSET(E32,-1,0)+1,OFFSET(E32,-1,0))) -> 0 | H32: SUBETAPA | I32: =IF(H32="Unidade Construtiva",TEXT(A32,"00"),IF(H32="Célula Construtiva",TEXT(B32,"00"),IF(H32="Etapa",CONCATENATE(TEXT(B32,"00"),".",TEXT(C32,"000")),IF(H32="Subetapa",CONCATENATE(TEXT(B32,"00"),".",TEXT(C32,"000"),".",TEXT(D32,"000")),IF(H32="Serviço",CONCATENATE(TEXT(B32,"00"),".",TEXT(C32,"000"),".",TEXT(D32,"000"),".",TEXT(E32,"000")),""))))) -> 01.001.004 | J32: Ensaios | N32: =IF(H32="Serviço",M32*L32,IF(H32="CÉLULA CONSTRUTIVA",SUMIFS($N$8:$N$417,$B$8:$B$417,B32,$H$8:$H$417,"Serviço"),IF(H32="ETAPA",SUMIFS($N$8:$N$417,$B$8:$B$417,B32,$C$8:$C$417,C32,$H$8:$H$417,"Serviço"),IF(H32="SUBETAPA",SUMIFS($N$8:$N$417,$B$8:$B$417,B32,$C$8:$C$417,C32,$D$8:$D$417,D32,$H$8:$H$417,"Serviço"),0)))) -> 37120
A33: =IF($H33="UNIDADE CONSTRUTIVA",OFFSET(A33,-1,0)+1,LARGE(A$3:A32,1)) -> 0 | B33: =IF(H33="UNIDADE CONSTRUTIVA",0,IF(H33="CÉLULA CONSTRUTIVA",OFFSET(B33,-1,0)+1,OFFSET(B33,-1,0))) -> 1 | C33: =IF(H33="CÉLULA CONSTRUTIVA",0,IF(H33="ETAPA",OFFSET(C33,-1,0)+1,OFFSET(C33,-1,0))) -> 1 | D33: =IF(H33="ETAPA",0,IF(H33="SUBETAPA",OFFSET(D33,-1,0)+1,OFFSET(D33,-1,0))) -> 4 | E33: =IF(H33="Subetapa",0,IF(H33="serviço",OFFSET(E33,-1,0)+1,OFFSET(E33,-1,0))) -> 1 | H33: SERVIÇO | I33: =IF(H33="Unidade Construtiva",TEXT(A33,"00"),IF(H33="Célula Construtiva",TEXT(B33,"00"),IF(H33="Etapa",CONCATENATE(TEXT(B33,"00"),".",TEXT(C33,"000")),IF(H33="Subetapa",CONCATENATE(TEXT(B33,"00"),".",TEXT(C33,"000"),".",TEXT(D33,"000")),IF(H33="Serviço",CONCATENATE(TEXT(B33,"00"),".",TEXT(C33,"000"),".",TEXT(D33,"000"),".",TEXT(E33,"000")),""))))) -> 01.001.004.001 | J33: Controle Tecnologico de Concreto | K33: vb | L33: 1 | M33: ='Controle Tecnologico'!F12 -> 37120 | N33: =IF(H33="Serviço",M33*L33,IF(H33="CÉLULA CONSTRUTIVA",SUMIFS($N$8:$N$417,$B$8:$B$417,B33,$H$8:$H$417,"Serviço"),IF(H33="ETAPA",SUMIFS($N$8:$N$417,$B$8:$B$417,B33,$C$8:$C$417,C33,$H$8:$H$417,"Serviço"),IF(H33="SUBETAPA",SUMIFS($N$8:$N$417,$B$8:$B$417,B33,$C$8:$C$417,C33,$D$8:$D$417,D33,$H$8:$H$417,"Serviço"),0)))) -> 37120 | P33: Pendente
A34: =IF($H34="UNIDADE CONSTRUTIVA",OFFSET(A34,-1,0)+1,LARGE(A$3:A33,1)) -> 0 | B34: =IF(H34="UNIDADE CONSTRUTIVA",0,IF(H34="CÉLULA CONSTRUTIVA",OFFSET(B34,-1,0)+1,OFFSET(B34,-1,0))) -> 1 | C34: =IF(H34="CÉLULA CONSTRUTIVA",0,IF(H34="ETAPA",OFFSET(C34,-1,0)+1,OFFSET(C34,-1,0))) -> 2 | D34: =IF(H34="ETAPA",0,IF(H34="SUBETAPA",OFFSET(D34,-1,0)+1,OFFSET(D34,-1,0))) -> 0 | E34: =IF(H34="Subetapa",0,IF(H34="serviço",OFFSET(E34,-1,0)+1,OFFSET(E34,-1,0))) -> 1 | H34: ETAPA | I34: =IF(H34="Unidade Construtiva",TEXT(A34,"00"),IF(H34="Célula Construtiva",TEXT(B34,"00"),IF(H34="Etapa",CONCATENATE(TEXT(B34,"00"),".",TEXT(C34,"000")),IF(H34="Subetapa",CONCATENATE(TEXT(B34,"00"),".",TEXT(C34,"000"),".",TEXT(D34,"000")),IF(H34="Serviço",CONCATENATE(TEXT(B34,"00"),".",TEXT(C34,"000"),".",TEXT(D34,"000"),".",TEXT(E34,"000")),""))))) -> 01.002 | J34: CONSUMOS, TAXAS E DOCUMENTOS | N34: =IF(H34="Serviço",M34*L34,IF(H34="CÉLULA CONSTRUTIVA",SUMIFS($N$8:$N$417,$B$8:$B$417,B34,$H$8:$H$417,"Serviço"),IF(H34="ETAPA",SUMIFS($N$8:$N$417,$B$8:$B$417,B34,$C$8:$C$417,C34,$H$8:$H$417,"Serviço"),IF(H34="SUBETAPA",SUMIFS($N$8:$N$417,$B$8:$B$417,B34,$C$8:$C$417,C34,$D$8:$D$417,D34,$H$8:$H$417,"Serviço"),0)))) -> 151761.95 | P34: -
A35: =IF($H35="UNIDADE CONSTRUTIVA",OFFSET(A35,-1,0)+1,LARGE(A$3:A34,1)) -> 0 | B35: =IF(H35="UNIDADE CONSTRUTIVA",0,IF(H35="CÉLULA CONSTRUTIVA",OFFSET(B35,-1,0)+1,OFFSET(B35,-1,0))) -> 1 | C35: =IF(H35="CÉLULA CONSTRUTIVA",0,IF(H35="ETAPA",OFFSET(C35,-1,0)+1,OFFSET(C35,-1,0))) -> 2 | D35: =IF(H35="ETAPA",0,IF(H35="SUBETAPA",OFFSET(D35,-1,0)+1,OFFSET(D35,-1,0))) -> 1 | E35: =IF(H35="Subetapa",0,IF(H35="serviço",OFFSET(E35,-1,0)+1,OFFSET(E35,-1,0))) -> 0 | H35: SUBETAPA | I35: =IF(H35="Unidade Construtiva",TEXT(A35,"00"),IF(H35="Célula Construtiva",TEXT(B35,"00"),IF(H35="Etapa",CONCATENATE(TEXT(B35,"00"),".",TEXT(C35,"000")),IF(H35="Subetapa",CONCATENATE(TEXT(B35,"00"),".",TEXT(C35,"000"),".",TEXT(D35,"000")),IF(H35="Serviço",CONCATENATE(TEXT(B35,"00"),".",TEXT(C35,"000"),".",TEXT(D35,"000"),".",TEXT(E35,"000")),""))))) -> 01.002.001 | J35: Licenciamentos, Taxas, Impostos, Aprovações e Seguros | N35: =IF(H35="Serviço",M35*L35,IF(H35="CÉLULA CONSTRUTIVA",SUMIFS($N$8:$N$417,$B$8:$B$417,B35,$H$8:$H$417,"Serviço"),IF(H35="ETAPA",SUMIFS($N$8:$N$417,$B$8:$B$417,B35,$C$8:$C$417,C35,$H$8:$H$417,"Serviço"),IF(H35="SUBETAPA",SUMIFS($N$8:$N$417,$B$8:$B$417,B35,$C$8:$C$417,C35,$D$8:$D$417,D35,$H$8:$H$417,"Serviço"),0)))) -> 97239.61
A36: =IF($H36="UNIDADE CONSTRUTIVA",OFFSET(A36,-1,0)+1,LARGE(A$3:A35,1)) -> 0 | B36: =IF(H36="UNIDADE CONSTRUTIVA",0,IF(H36="CÉLULA CONSTRUTIVA",OFFSET(B36,-1,0)+1,OFFSET(B36,-1,0))) -> 1 | C36: =IF(H36="CÉLULA CONSTRUTIVA",0,IF(H36="ETAPA",OFFSET(C36,-1,0)+1,OFFSET(C36,-1,0))) -> 2 | D36: =IF(H36="ETAPA",0,IF(H36="SUBETAPA",OFFSET(D36,-1,0)+1,OFFSET(D36,-1,0))) -> 1 | E36: =IF(H36="Subetapa",0,IF(H36="serviço",OFFSET(E36,-1,0)+1,OFFSET(E36,-1,0))) -> 1 | H36: SERVIÇO | I36: =IF(H36="Unidade Construtiva",TEXT(A36,"00"),IF(H36="Célula Construtiva",TEXT(B36,"00"),IF(H36="Etapa",CONCATENATE(TEXT(B36,"00"),".",TEXT(C36,"000")),IF(H36="Subetapa",CONCATENATE(TEXT(B36,"00"),".",TEXT(C36,"000"),".",TEXT(D36,"000")),IF(H36="Serviço",CONCATENATE(TEXT(B36,"00"),".",TEXT(C36,"000"),".",TEXT(D36,"000"),".",TEXT(E36,"000")),""))))) -> 01.002.001.001 | J36: Despesas de Seguros | K36: vb | L36: 1 | M36: 11316.52 | N36: =IF(H36="Serviço",M36*L36,IF(H36="CÉLULA CONSTRUTIVA",SUMIFS($N$8:$N$417,$B$8:$B$417,B36,$H$8:$H$417,"Serviço"),IF(H36="ETAPA",SUMIFS($N$8:$N$417,$B$8:$B$417,B36,$C$8:$C$417,C36,$H$8:$H$417,"Serviço"),IF(H36="SUBETAPA",SUMIFS($N$8:$N$417,$B$8:$B$417,B36,$C$8:$C$417,C36,$D$8:$D$417,D36,$H$8:$H$417,"Serviço"),0)))) -> 11316.52 | O36: Valor informado em formulário | P36: Lançado ERP
A37: =IF($H37="UNIDADE CONSTRUTIVA",OFFSET(A37,-1,0)+1,LARGE(A$3:A36,1)) -> 0 | B37: =IF(H37="UNIDADE CONSTRUTIVA",0,IF(H37="CÉLULA CONSTRUTIVA",OFFSET(B37,-1,0)+1,OFFSET(B37,-1,0))) -> 1 | C37: =IF(H37="CÉLULA CONSTRUTIVA",0,IF(H37="ETAPA",OFFSET(C37,-1,0)+1,OFFSET(C37,-1,0))) -> 2 | D37: =IF(H37="ETAPA",0,IF(H37="SUBETAPA",OFFSET(D37,-1,0)+1,OFFSET(D37,-1,0))) -> 1 | E37: =IF(H37="Subetapa",0,IF(H37="serviço",OFFSET(E37,-1,0)+1,OFFSET(E37,-1,0))) -> 2 | H37: SERVIÇO | I37: =IF(H37="Unidade Construtiva",TEXT(A37,"00"),IF(H37="Célula Construtiva",TEXT(B37,"00"),IF(H37="Etapa",CONCATENATE(TEXT(B37,"00"),".",TEXT(C37,"000")),IF(H37="Subetapa",CONCATENATE(TEXT(B37,"00"),".",TEXT(C37,"000"),".",TEXT(D37,"000")),IF(H37="Serviço",CONCATENATE(TEXT(B37,"00"),".",TEXT(C37,"000"),".",TEXT(D37,"000"),".",TEXT(E37,"000")),""))))) -> 01.002.001.002 | J37: Aprovação e legalização ambiental | K37: vb | L37: 1 | M37: 5683.51 | N37: =IF(H37="Serviço",M37*L37,IF(H37="CÉLULA CONSTRUTIVA",SUMIFS($N$8:$N$417,$B$8:$B$417,B37,$H$8:$H$417,"Serviço"),IF(H37="ETAPA",SUMIFS($N$8:$N$417,$B$8:$B$417,B37,$C$8:$C$417,C37,$H$8:$H$417,"Serviço"),IF(H37="SUBETAPA",SUMIFS($N$8:$N$417,$B$8:$B$417,B37,$C$8:$C$417,C37,$D$8:$D$417,D37,$H$8:$H$417,"Serviço"),0)))) -> 5683.51 | O37: Valor informado em formulário | P37: Lançado ERP
A38: =IF($H38="UNIDADE CONSTRUTIVA",OFFSET(A38,-1,0)+1,LARGE(A$3:A37,1)) -> 0 | B38: =IF(H38="UNIDADE CONSTRUTIVA",0,IF(H38="CÉLULA CONSTRUTIVA",OFFSET(B38,-1,0)+1,OFFSET(B38,-1,0))) -> 1 | C38: =IF(H38="CÉLULA CONSTRUTIVA",0,IF(H38="ETAPA",OFFSET(C38,-1,0)+1,OFFSET(C38,-1,0))) -> 2 | D38: =IF(H38="ETAPA",0,IF(H38="SUBETAPA",OFFSET(D38,-1,0)+1,OFFSET(D38,-1,0))) -> 1 | E38: =IF(H38="Subetapa",0,IF(H38="serviço",OFFSET(E38,-1,0)+1,OFFSET(E38,-1,0))) -> 3 | H38: SERVIÇO | I38: =IF(H38="Unidade Construtiva",TEXT(A38,"00"),IF(H38="Célula Construtiva",TEXT(B38,"00"),IF(H38="Etapa",CONCATENATE(TEXT(B38,"00"),".",TEXT(C38,"000")),IF(H38="Subetapa",CONCATENATE(TEXT(B38,"00"),".",TEXT(C38,"000"),".",TEXT(D38,"000")),IF(H38="Serviço",CONCATENATE(TEXT(B38,"00"),".",TEXT(C38,"000"),".",TEXT(D38,"000"),".",TEXT(E38,"000")),""))))) -> 01.002.001.003 | J38: Aprovação e legalização prefeitura | K38: vb | L38: 1 | M38: 23251.17 | N38: =IF(H38="Serviço",M38*L38,IF(H38="CÉLULA CONSTRUTIVA",SUMIFS($N$8:$N$417,$B$8:$B$417,B38,$H$8:$H$417,"Serviço"),IF(H38="ETAPA",SUMIFS($N$8:$N$417,$B$8:$B$417,B38,$C$8:$C$417,C38,$H$8:$H$417,"Serviço"),IF(H38="SUBETAPA",SUMIFS($N$8:$N$417,$B$8:$B$417,B38,$C$8:$C$417,C38,$D$8:$D$417,D38,$H$8:$H$417,"Serviço"),0)))) -> 23251.17 | O38: Estimado com base em índices históricos | P38: Lançado ERP
A39: =IF($H39="UNIDADE CONSTRUTIVA",OFFSET(A39,-1,0)+1,LARGE(A$3:A38,1)) -> 0 | B39: =IF(H39="UNIDADE CONSTRUTIVA",0,IF(H39="CÉLULA CONSTRUTIVA",OFFSET(B39,-1,0)+1,OFFSET(B39,-1,0))) -> 1 | C39: =IF(H39="CÉLULA CONSTRUTIVA",0,IF(H39="ETAPA",OFFSET(C39,-1,0)+1,OFFSET(C39,-1,0))) -> 2 | D39: =IF(H39="ETAPA",0,IF(H39="SUBETAPA",OFFSET(D39,-1,0)+1,OFFSET(D39,-1,0))) -> 1 | E39: =IF(H39="Subetapa",0,IF(H39="serviço",OFFSET(E39,-1,0)+1,OFFSET(E39,-1,0))) -> 4 | H39: SERVIÇO | I39: =IF(H39="Unidade Construtiva",TEXT(A39,"00"),IF(H39="Célula Construtiva",TEXT(B39,"00"),IF(H39="Etapa",CONCATENATE(TEXT(B39,"00"),".",TEXT(C39,"000")),IF(H39="Subetapa",CONCATENATE(TEXT(B39,"00"),".",TEXT(C39,"000"),".",TEXT(D39,"000")),IF(H39="Serviço",CONCATENATE(TEXT(B39,"00"),".",TEXT(C39,"000"),".",TEXT(D39,"000"),".",TEXT(E39,"000")),""))))) -> 01.002.001.004 | J39: Aprovação e legalização água e esgoto | K39: vb | L39: 1 | M39: 5503.94 | N39: =IF(H39="Serviço",M39*L39,IF(H39="CÉLULA CONSTRUTIVA",SUMIFS($N$8:$N$417,$B$8:$B$417,B39,$H$8:$H$417,"Serviço"),IF(H39="ETAPA",SUMIFS($N$8:$N$417,$B$8:$B$417,B39,$C$8:$C$417,C39,$H$8:$H$417,"Serviço"),IF(H39="SUBETAPA",SUMIFS($N$8:$N$417,$B$8:$B$417,B39,$C$8:$C$417,C39,$D$8:$D$417,D39,$H$8:$H$417,"Serviço"),0)))) -> 5503.94 | O39: Estimado com base em índices históricos | P39: Lançado ERP
A40: =IF($H40="UNIDADE CONSTRUTIVA",OFFSET(A40,-1,0)+1,LARGE(A$3:A39,1)) -> 0 | B40: =IF(H40="UNIDADE CONSTRUTIVA",0,IF(H40="CÉLULA CONSTRUTIVA",OFFSET(B40,-1,0)+1,OFFSET(B40,-1,0))) -> 1 | C40: =IF(H40="CÉLULA CONSTRUTIVA",0,IF(H40="ETAPA",OFFSET(C40,-1,0)+1,OFFSET(C40,-1,0))) -> 2 | D40: =IF(H40="ETAPA",0,IF(H40="SUBETAPA",OFFSET(D40,-1,0)+1,OFFSET(D40,-1,0))) -> 1 | E40: =IF(H40="Subetapa",0,IF(H40="serviço",OFFSET(E40,-1,0)+1,OFFSET(E40,-1,0))) -> 5 | H40: SERVIÇO | I40: =IF(H40="Unidade Construtiva",TEXT(A40,"00"),IF(H40="Célula Construtiva",TEXT(B40,"00"),IF(H40="Etapa",CONCATENATE(TEXT(B40,"00"),".",TEXT(C40,"000")),IF(H40="Subetapa",CONCATENATE(TEXT(B40,"00"),".",TEXT(C40,"000"),".",TEXT(D40,"000")),IF(H40="Serviço",CONCATENATE(TEXT(B40,"00"),".",TEXT(C40,"000"),".",TEXT(D40,"000"),".",TEXT(E40,"000")),""))))) -> 01.002.001.005 | J40: Aprovação e legalização elétrico | K40: vb | L40: 1 | M40: 4488.9 | N40: =IF(H40="Serviço",M40*L40,IF(H40="CÉLULA CONSTRUTIVA",SUMIFS($N$8:$N$417,$B$8:$B$417,B40,$H$8:$H$417,"Serviço"),IF(H40="ETAPA",SUMIFS($N$8:$N$417,$B$8:$B$417,B40,$C$8:$C$417,C40,$H$8:$H$417,"Serviço"),IF(H40="SUBETAPA",SUMIFS($N$8:$N$417,$B$8:$B$417,B40,$C$8:$C$417,C40,$D$8:$D$417,D40,$H$8:$H$417,"Serviço"),0)))) -> 4488.9 | O40: Estimado com base em índices históricos | P40: Lançado ERP
A41: =IF($H41="UNIDADE CONSTRUTIVA",OFFSET(A41,-1,0)+1,LARGE(A$3:A40,1)) -> 0 | B41: =IF(H41="UNIDADE CONSTRUTIVA",0,IF(H41="CÉLULA CONSTRUTIVA",OFFSET(B41,-1,0)+1,OFFSET(B41,-1,0))) -> 1 | C41: =IF(H41="CÉLULA CONSTRUTIVA",0,IF(H41="ETAPA",OFFSET(C41,-1,0)+1,OFFSET(C41,-1,0))) -> 2 | D41: =IF(H41="ETAPA",0,IF(H41="SUBETAPA",OFFSET(D41,-1,0)+1,OFFSET(D41,-1,0))) -> 1 | E41: =IF(H41="Subetapa",0,IF(H41="serviço",OFFSET(E41,-1,0)+1,OFFSET(E41,-1,0))) -> 6 | H41: SERVIÇO | I41: =IF(H41="Unidade Construtiva",TEXT(A41,"00"),IF(H41="Célula Construtiva",TEXT(B41,"00"),IF(H41="Etapa",CONCATENATE(TEXT(B41,"00"),".",TEXT(C41,"000")),IF(H41="Subetapa",CONCATENATE(TEXT(B41,"00"),".",TEXT(C41,"000"),".",TEXT(D41,"000")),IF(H41="Serviço",CONCATENATE(TEXT(B41,"00"),".",TEXT(C41,"000"),".",TEXT(D41,"000"),".",TEXT(E41,"000")),""))))) -> 01.002.001.006 | J41: Aprovação e legalização bombeiros | K41: vb | L41: 1 | M41: 4881.64 | N41: =IF(H41="Serviço",M41*L41,IF(H41="CÉLULA CONSTRUTIVA",SUMIFS($N$8:$N$417,$B$8:$B$417,B41,$H$8:$H$417,"Serviço"),IF(H41="ETAPA",SUMIFS($N$8:$N$417,$B$8:$B$417,B41,$C$8:$C$417,C41,$H$8:$H$417,"Serviço"),IF(H41="SUBETAPA",SUMIFS($N$8:$N$417,$B$8:$B$417,B41,$C$8:$C$417,C41,$D$8:$D$417,D41,$H$8:$H$417,"Serviço"),0)))) -> 4881.64 | O41: Estimado com base em índices históricos | P41: Lançado ERP
A42: =IF($H42="UNIDADE CONSTRUTIVA",OFFSET(A42,-1,0)+1,LARGE(A$3:A41,1)) -> 0 | B42: =IF(H42="UNIDADE CONSTRUTIVA",0,IF(H42="CÉLULA CONSTRUTIVA",OFFSET(B42,-1,0)+1,OFFSET(B42,-1,0))) -> 1 | C42: =IF(H42="CÉLULA CONSTRUTIVA",0,IF(H42="ETAPA",OFFSET(C42,-1,0)+1,OFFSET(C42,-1,0))) -> 2 | D42: =IF(H42="ETAPA",0,IF(H42="SUBETAPA",OFFSET(D42,-1,0)+1,OFFSET(D42,-1,0))) -> 1 | E42: =IF(H42="Subetapa",0,IF(H42="serviço",OFFSET(E42,-1,0)+1,OFFSET(E42,-1,0))) -> 7 | H42: SERVIÇO | I42: =IF(H42="Unidade Construtiva",TEXT(A42,"00"),IF(H42="Célula Construtiva",TEXT(B42,"00"),IF(H42="Etapa",CONCATENATE(TEXT(B42,"00"),".",TEXT(C42,"000")),IF(H42="Subetapa",CONCATENATE(TEXT(B42,"00"),".",TEXT(C42,"000"),".",TEXT(D42,"000")),IF(H42="Serviço",CONCATENATE(TEXT(B42,"00"),".",TEXT(C42,"000"),".",TEXT(D42,"000"),".",TEXT(E42,"000")),""))))) -> 01.002.001.007 | J42: Taxas de ART | K42: vb | L42: 1 | M42: 600 | N42: =IF(H42="Serviço",M42*L42,IF(H42="CÉLULA CONSTRUTIVA",SUMIFS($N$8:$N$417,$B$8:$B$417,B42,$H$8:$H$417,"Serviço"),IF(H42="ETAPA",SUMIFS($N$8:$N$417,$B$8:$B$417,B42,$C$8:$C$417,C42,$H$8:$H$417,"Serviço"),IF(H42="SUBETAPA",SUMIFS($N$8:$N$417,$B$8:$B$417,B42,$C$8:$C$417,C42,$D$8:$D$417,D42,$H$8:$H$417,"Serviço"),0)))) -> 600 | O42: Valor informado em formulário | P42: Lançado ERP
A43: =IF($H43="UNIDADE CONSTRUTIVA",OFFSET(A43,-1,0)+1,LARGE(A$3:A42,1)) -> 0 | B43: =IF(H43="UNIDADE CONSTRUTIVA",0,IF(H43="CÉLULA CONSTRUTIVA",OFFSET(B43,-1,0)+1,OFFSET(B43,-1,0))) -> 1 | C43: =IF(H43="CÉLULA CONSTRUTIVA",0,IF(H43="ETAPA",OFFSET(C43,-1,0)+1,OFFSET(C43,-1,0))) -> 2 | D43: =IF(H43="ETAPA",0,IF(H43="SUBETAPA",OFFSET(D43,-1,0)+1,OFFSET(D43,-1,0))) -> 1 | E43: =IF(H43="Subetapa",0,IF(H43="serviço",OFFSET(E43,-1,0)+1,OFFSET(E43,-1,0))) -> 8 | H43: SERVIÇO | I43: =IF(H43="Unidade Construtiva",TEXT(A43,"00"),IF(H43="Célula Construtiva",TEXT(B43,"00"),IF(H43="Etapa",CONCATENATE(TEXT(B43,"00"),".",TEXT(C43,"000")),IF(H43="Subetapa",CONCATENATE(TEXT(B43,"00"),".",TEXT(C43,"000"),".",TEXT(D43,"000")),IF(H43="Serviço",CONCATENATE(TEXT(B43,"00"),".",TEXT(C43,"000"),".",TEXT(D43,"000"),".",TEXT(E43,"000")),""))))) -> 01.002.001.008 | J43: Alvará Construção | K43: vb | L43: 1 | M43: 11758.71 | N43: =IF(H43="Serviço",M43*L43,IF(H43="CÉLULA CONSTRUTIVA",SUMIFS($N$8:$N$417,$B$8:$B$417,B43,$H$8:$H$417,"Serviço"),IF(H43="ETAPA",SUMIFS($N$8:$N$417,$B$8:$B$417,B43,$C$8:$C$417,C43,$H$8:$H$417,"Serviço"),IF(H43="SUBETAPA",SUMIFS($N$8:$N$417,$B$8:$B$417,B43,$C$8:$C$417,C43,$D$8:$D$417,D43,$H$8:$H$417,"Serviço"),0)))) -> 11758.71 | O43: Valor informado em formulário | P43: Lançado ERP
A44: =IF($H44="UNIDADE CONSTRUTIVA",OFFSET(A44,-1,0)+1,LARGE(A$3:A43,1)) -> 0 | B44: =IF(H44="UNIDADE CONSTRUTIVA",0,IF(H44="CÉLULA CONSTRUTIVA",OFFSET(B44,-1,0)+1,OFFSET(B44,-1,0))) -> 1 | C44: =IF(H44="CÉLULA CONSTRUTIVA",0,IF(H44="ETAPA",OFFSET(C44,-1,0)+1,OFFSET(C44,-1,0))) -> 2 | D44: =IF(H44="ETAPA",0,IF(H44="SUBETAPA",OFFSET(D44,-1,0)+1,OFFSET(D44,-1,0))) -> 1 | E44: =IF(H44="Subetapa",0,IF(H44="serviço",OFFSET(E44,-1,0)+1,OFFSET(E44,-1,0))) -> 9 | H44: SERVIÇO | I44: =IF(H44="Unidade Construtiva",TEXT(A44,"00"),IF(H44="Célula Construtiva",TEXT(B44,"00"),IF(H44="Etapa",CONCATENATE(TEXT(B44,"00"),".",TEXT(C44,"000")),IF(H44="Subetapa",CONCATENATE(TEXT(B44,"00"),".",TEXT(C44,"000"),".",TEXT(D44,"000")),IF(H44="Serviço",CONCATENATE(TEXT(B44,"00"),".",TEXT(C44,"000"),".",TEXT(D44,"000"),".",TEXT(E44,"000")),""))))) -> 01.002.001.009 | J44: Despesas cartório, licenças, certidões e jurídicas | K44: vb | L44: 1 | M44: 12489.88 | N44: =IF(H44="Serviço",M44*L44,IF(H44="CÉLULA CONSTRUTIVA",SUMIFS($N$8:$N$417,$B$8:$B$417,B44,$H$8:$H$417,"Serviço"),IF(H44="ETAPA",SUMIFS($N$8:$N$417,$B$8:$B$417,B44,$C$8:$C$417,C44,$H$8:$H$417,"Serviço"),IF(H44="SUBETAPA",SUMIFS($N$8:$N$417,$B$8:$B$417,B44,$C$8:$C$417,C44,$D$8:$D$417,D44,$H$8:$H$417,"Serviço"),0)))) -> 12489.88 | O44: Estimado com base em índices históricos | P44: Lançado ERP
A45: =IF($H45="UNIDADE CONSTRUTIVA",OFFSET(A45,-1,0)+1,LARGE(A$3:A44,1)) -> 0 | B45: =IF(H45="UNIDADE CONSTRUTIVA",0,IF(H45="CÉLULA CONSTRUTIVA",OFFSET(B45,-1,0)+1,OFFSET(B45,-1,0))) -> 1 | C45: =IF(H45="CÉLULA CONSTRUTIVA",0,IF(H45="ETAPA",OFFSET(C45,-1,0)+1,OFFSET(C45,-1,0))) -> 2 | D45: =IF(H45="ETAPA",0,IF(H45="SUBETAPA",OFFSET(D45,-1,0)+1,OFFSET(D45,-1,0))) -> 1 | E45: =IF(H45="Subetapa",0,IF(H45="serviço",OFFSET(E45,-1,0)+1,OFFSET(E45,-1,0))) -> 10 | H45: SERVIÇO | I45: =IF(H45="Unidade Construtiva",TEXT(A45,"00"),IF(H45="Célula Construtiva",TEXT(B45,"00"),IF(H45="Etapa",CONCATENATE(TEXT(B45,"00"),".",TEXT(C45,"000")),IF(H45="Subetapa",CONCATENATE(TEXT(B45,"00"),".",TEXT(C45,"000"),".",TEXT(D45,"000")),IF(H45="Serviço",CONCATENATE(TEXT(B45,"00"),".",TEXT(C45,"000"),".",TEXT(D45,"000"),".",TEXT(E45,"000")),""))))) -> 01.002.001.010 | J45: Incorporação | K45: vb | L45: 1 | M45: 6611.4 | N45: =IF(H45="Serviço",M45*L45,IF(H45="CÉLULA CONSTRUTIVA",SUMIFS($N$8:$N$417,$B$8:$B$417,B45,$H$8:$H$417,"Serviço"),IF(H45="ETAPA",SUMIFS($N$8:$N$417,$B$8:$B$417,B45,$C$8:$C$417,C45,$H$8:$H$417,"Serviço"),IF(H45="SUBETAPA",SUMIFS($N$8:$N$417,$B$8:$B$417,B45,$C$8:$C$417,C45,$D$8:$D$417,D45,$H$8:$H$417,"Serviço"),0)))) -> 6611.4 | O45: Valor informado em formulário | P45: Lançado ERP
A46: =IF($H46="UNIDADE CONSTRUTIVA",OFFSET(A46,-1,0)+1,LARGE(A$3:A45,1)) -> 0 | B46: =IF(H46="UNIDADE CONSTRUTIVA",0,IF(H46="CÉLULA CONSTRUTIVA",OFFSET(B46,-1,0)+1,OFFSET(B46,-1,0))) -> 1 | C46: =IF(H46="CÉLULA CONSTRUTIVA",0,IF(H46="ETAPA",OFFSET(C46,-1,0)+1,OFFSET(C46,-1,0))) -> 2 | D46: =IF(H46="ETAPA",0,IF(H46="SUBETAPA",OFFSET(D46,-1,0)+1,OFFSET(D46,-1,0))) -> 1 | E46: =IF(H46="Subetapa",0,IF(H46="serviço",OFFSET(E46,-1,0)+1,OFFSET(E46,-1,0))) -> 11 | H46: SERVIÇO | I46: =IF(H46="Unidade Construtiva",TEXT(A46,"00"),IF(H46="Célula Construtiva",TEXT(B46,"00"),IF(H46="Etapa",CONCATENATE(TEXT(B46,"00"),".",TEXT(C46,"000")),IF(H46="Subetapa",CONCATENATE(TEXT(B46,"00"),".",TEXT(C46,"000"),".",TEXT(D46,"000")),IF(H46="Serviço",CONCATENATE(TEXT(B46,"00"),".",TEXT(C46,"000"),".",TEXT(D46,"000"),".",TEXT(E46,"000")),""))))) -> 01.002.001.011 | J46: Iptu | K46: vb | L46: 1 | M46: 3047.18 | N46: =IF(H46="Serviço",M46*L46,IF(H46="CÉLULA CONSTRUTIVA",SUMIFS($N$8:$N$417,$B$8:$B$417,B46,$H$8:$H$417,"Serviço"),IF(H46="ETAPA",SUMIFS($N$8:$N$417,$B$8:$B$417,B46,$C$8:$C$417,C46,$H$8:$H$417,"Serviço"),IF(H46="SUBETAPA",SUMIFS($N$8:$N$417,$B$8:$B$417,B46,$C$8:$C$417,C46,$D$8:$D$417,D46,$H$8:$H$417,"Serviço"),0)))) -> 3047.18 | O46: Valor informado em formulário | P46: Lançado ERP
A47: =IF($H47="UNIDADE CONSTRUTIVA",OFFSET(A47,-1,0)+1,LARGE(A$3:A46,1)) -> 0 | B47: =IF(H47="UNIDADE CONSTRUTIVA",0,IF(H47="CÉLULA CONSTRUTIVA",OFFSET(B47,-1,0)+1,OFFSET(B47,-1,0))) -> 1 | C47: =IF(H47="CÉLULA CONSTRUTIVA",0,IF(H47="ETAPA",OFFSET(C47,-1,0)+1,OFFSET(C47,-1,0))) -> 2 | D47: =IF(H47="ETAPA",0,IF(H47="SUBETAPA",OFFSET(D47,-1,0)+1,OFFSET(D47,-1,0))) -> 1 | E47: =IF(H47="Subetapa",0,IF(H47="serviço",OFFSET(E47,-1,0)+1,OFFSET(E47,-1,0))) -> 12 | H47: SERVIÇO | I47: =IF(H47="Unidade Construtiva",TEXT(A47,"00"),IF(H47="Célula Construtiva",TEXT(B47,"00"),IF(H47="Etapa",CONCATENATE(TEXT(B47,"00"),".",TEXT(C47,"000")),IF(H47="Subetapa",CONCATENATE(TEXT(B47,"00"),".",TEXT(C47,"000"),".",TEXT(D47,"000")),IF(H47="Serviço",CONCATENATE(TEXT(B47,"00"),".",TEXT(C47,"000"),".",TEXT(D47,"000"),".",TEXT(E47,"000")),""))))) -> 01.002.001.012 | J47: Alvará Habite-se | K47: vb | L47: 1 | M47: 7606.76 | N47: =IF(H47="Serviço",M47*L47,IF(H47="CÉLULA CONSTRUTIVA",SUMIFS($N$8:$N$417,$B$8:$B$417,B47,$H$8:$H$417,"Serviço"),IF(H47="ETAPA",SUMIFS($N$8:$N$417,$B$8:$B$417,B47,$C$8:$C$417,C47,$H$8:$H$417,"Serviço"),IF(H47="SUBETAPA",SUMIFS($N$8:$N$417,$B$8:$B$417,B47,$C$8:$C$417,C47,$D$8:$D$417,D47,$H$8:$H$417,"Serviço"),0)))) -> 7606.76 | O47: Estimado com base em índices históricos | P47: Lançado ERP
A48: =IF($H48="UNIDADE CONSTRUTIVA",OFFSET(A48,-1,0)+1,LARGE(A$3:A47,1)) -> 0 | B48: =IF(H48="UNIDADE CONSTRUTIVA",0,IF(H48="CÉLULA CONSTRUTIVA",OFFSET(B48,-1,0)+1,OFFSET(B48,-1,0))) -> 1 | C48: =IF(H48="CÉLULA CONSTRUTIVA",0,IF(H48="ETAPA",OFFSET(C48,-1,0)+1,OFFSET(C48,-1,0))) -> 2 | D48: =IF(H48="ETAPA",0,IF(H48="SUBETAPA",OFFSET(D48,-1,0)+1,OFFSET(D48,-1,0))) -> 2 | E48: =IF(H48="Subetapa",0,IF(H48="serviço",OFFSET(E48,-1,0)+1,OFFSET(E48,-1,0))) -> 0 | H48: SUBETAPA | I48: =IF(H48="Unidade Construtiva",TEXT(A48,"00"),IF(H48="Célula Construtiva",TEXT(B48,"00"),IF(H48="Etapa",CONCATENATE(TEXT(B48,"00"),".",TEXT(C48,"000")),IF(H48="Subetapa",CONCATENATE(TEXT(B48,"00"),".",TEXT(C48,"000"),".",TEXT(D48,"000")),IF(H48="Serviço",CONCATENATE(TEXT(B48,"00"),".",TEXT(C48,"000"),".",TEXT(D48,"000"),".",TEXT(E48,"000")),""))))) -> 01.002.002 | J48: Documentos | N48: =IF(H48="Serviço",M48*L48,IF(H48="CÉLULA CONSTRUTIVA",SUMIFS($N$8:$N$417,$B$8:$B$417,B48,$H$8:$H$417,"Serviço"),IF(H48="ETAPA",SUMIFS($N$8:$N$417,$B$8:$B$417,B48,$C$8:$C$417,C48,$H$8:$H$417,"Serviço"),IF(H48="SUBETAPA",SUMIFS($N$8:$N$417,$B$8:$B$417,B48,$C$8:$C$417,C48,$D$8:$D$417,D48,$H$8:$H$417,"Serviço"),0)))) -> 54522.34
A49: =IF($H49="UNIDADE CONSTRUTIVA",OFFSET(A49,-1,0)+1,LARGE(A$3:A48,1)) -> 0 | B49: =IF(H49="UNIDADE CONSTRUTIVA",0,IF(H49="CÉLULA CONSTRUTIVA",OFFSET(B49,-1,0)+1,OFFSET(B49,-1,0))) -> 1 | C49: =IF(H49="CÉLULA CONSTRUTIVA",0,IF(H49="ETAPA",OFFSET(C49,-1,0)+1,OFFSET(C49,-1,0))) -> 2 | D49: =IF(H49="ETAPA",0,IF(H49="SUBETAPA",OFFSET(D49,-1,0)+1,OFFSET(D49,-1,0))) -> 2 | E49: =IF(H49="Subetapa",0,IF(H49="serviço",OFFSET(E49,-1,0)+1,OFFSET(E49,-1,0))) -> 1 | H49: SERVIÇO | I49: =IF(H49="Unidade Construtiva",TEXT(A49,"00"),IF(H49="Célula Construtiva",TEXT(B49,"00"),IF(H49="Etapa",CONCATENATE(TEXT(B49,"00"),".",TEXT(C49,"000")),IF(H49="Subetapa",CONCATENATE(TEXT(B49,"00"),".",TEXT(C49,"000"),".",TEXT(D49,"000")),IF(H49="Serviço",CONCATENATE(TEXT(B49,"00"),".",TEXT(C49,"000"),".",TEXT(D49,"000"),".",TEXT(E49,"000")),""))))) -> 01.002.002.001 | J49: As Built | K49: vb | L49: 1 | M49: 8302.01 | N49: =IF(H49="Serviço",M49*L49,IF(H49="CÉLULA CONSTRUTIVA",SUMIFS($N$8:$N$417,$B$8:$B$417,B49,$H$8:$H$417,"Serviço"),IF(H49="ETAPA",SUMIFS($N$8:$N$417,$B$8:$B$417,B49,$C$8:$C$417,C49,$H$8:$H$417,"Serviço"),IF(H49="SUBETAPA",SUMIFS($N$8:$N$417,$B$8:$B$417,B49,$C$8:$C$417,C49,$D$8:$D$417,D49,$H$8:$H$417,"Serviço"),0)))) -> 8302.01 | O49: Estimado com base em índices históricos | P49: Lançado ERP
A50: =IF($H50="UNIDADE CONSTRUTIVA",OFFSET(A50,-1,0)+1,LARGE(A$3:A49,1)) -> 0 | B50: =IF(H50="UNIDADE CONSTRUTIVA",0,IF(H50="CÉLULA CONSTRUTIVA",OFFSET(B50,-1,0)+1,OFFSET(B50,-1,0))) -> 1 | C50: =IF(H50="CÉLULA CONSTRUTIVA",0,IF(H50="ETAPA",OFFSET(C50,-1,0)+1,OFFSET(C50,-1,0))) -> 2 | D50: =IF(H50="ETAPA",0,IF(H50="SUBETAPA",OFFSET(D50,-1,0)+1,OFFSET(D50,-1,0))) -> 2 | E50: =IF(H50="Subetapa",0,IF(H50="serviço",OFFSET(E50,-1,0)+1,OFFSET(E50,-1,0))) -> 2 | H50: SERVIÇO | I50: =IF(H50="Unidade Construtiva",TEXT(A50,"00"),IF(H50="Célula Construtiva",TEXT(B50,"00"),IF(H50="Etapa",CONCATENATE(TEXT(B50,"00"),".",TEXT(C50,"000")),IF(H50="Subetapa",CONCATENATE(TEXT(B50,"00"),".",TEXT(C50,"000"),".",TEXT(D50,"000")),IF(H50="Serviço",CONCATENATE(TEXT(B50,"00"),".",TEXT(C50,"000"),".",TEXT(D50,"000"),".",TEXT(E50,"000")),""))))) -> 01.002.002.002 | J50: Laudo técnico de vistoria de entrega | K50: vb | L50: 1 | M50: 11335.44 | N50: =IF(H50="Serviço",M50*L50,IF(H50="CÉLULA CONSTRUTIVA",SUMIFS($N$8:$N$417,$B$8:$B$417,B50,$H$8:$H$417,"Serviço"),IF(H50="ETAPA",SUMIFS($N$8:$N$417,$B$8:$B$417,B50,$C$8:$C$417,C50,$H$8:$H$417,"Serviço"),IF(H50="SUBETAPA",SUMIFS($N$8:$N$417,$B$8:$B$417,B50,$C$8:$C$417,C50,$D$8:$D$417,D50,$H$8:$H$417,"Serviço"),0)))) -> 11335.44 | O50: Estimado com base em índices históricos | P50: Lançado ERP
A51: =IF($H51="UNIDADE CONSTRUTIVA",OFFSET(A51,-1,0)+1,LARGE(A$3:A50,1)) -> 0 | B51: =IF(H51="UNIDADE CONSTRUTIVA",0,IF(H51="CÉLULA CONSTRUTIVA",OFFSET(B51,-1,0)+1,OFFSET(B51,-1,0))) -> 1 | C51: =IF(H51="CÉLULA CONSTRUTIVA",0,IF(H51="ETAPA",OFFSET(C51,-1,0)+1,OFFSET(C51,-1,0))) -> 2 | D51: =IF(H51="ETAPA",0,IF(H51="SUBETAPA",OFFSET(D51,-1,0)+1,OFFSET(D51,-1,0))) -> 2 | E51: =IF(H51="Subetapa",0,IF(H51="serviço",OFFSET(E51,-1,0)+1,OFFSET(E51,-1,0))) -> 3 | H51: SERVIÇO | I51: =IF(H51="Unidade Construtiva",TEXT(A51,"00"),IF(H51="Célula Construtiva",TEXT(B51,"00"),IF(H51="Etapa",CONCATENATE(TEXT(B51,"00"),".",TEXT(C51,"000")),IF(H51="Subetapa",CONCATENATE(TEXT(B51,"00"),".",TEXT(C51,"000"),".",TEXT(D51,"000")),IF(H51="Serviço",CONCATENATE(TEXT(B51,"00"),".",TEXT(C51,"000"),".",TEXT(D51,"000"),".",TEXT(E51,"000")),""))))) -> 01.002.002.003 | J51: Manuais técnicos condomínio/proprietários | K51: vb | L51: 1 | M51: 6500 | N51: =IF(H51="Serviço",M51*L51,IF(H51="CÉLULA CONSTRUTIVA",SUMIFS($N$8:$N$417,$B$8:$B$417,B51,$H$8:$H$417,"Serviço"),IF(H51="ETAPA",SUMIFS($N$8:$N$417,$B$8:$B$417,B51,$C$8:$C$417,C51,$H$8:$H$417,"Serviço"),IF(H51="SUBETAPA",SUMIFS($N$8:$N$417,$B$8:$B$417,B51,$C$8:$C$417,C51,$D$8:$D$417,D51,$H$8:$H$417,"Serviço"),0)))) -> 6500 | O51: Estimado com base em índices históricos | P51: Lançado ERP
A52: =IF($H52="UNIDADE CONSTRUTIVA",OFFSET(A52,-1,0)+1,LARGE(A$3:A51,1)) -> 0 | B52: =IF(H52="UNIDADE CONSTRUTIVA",0,IF(H52="CÉLULA CONSTRUTIVA",OFFSET(B52,-1,0)+1,OFFSET(B52,-1,0))) -> 1 | C52: =IF(H52="CÉLULA CONSTRUTIVA",0,IF(H52="ETAPA",OFFSET(C52,-1,0)+1,OFFSET(C52,-1,0))) -> 2 | D52: =IF(H52="ETAPA",0,IF(H52="SUBETAPA",OFFSET(D52,-1,0)+1,OFFSET(D52,-1,0))) -> 2 | E52: =IF(H52="Subetapa",0,IF(H52="serviço",OFFSET(E52,-1,0)+1,OFFSET(E52,-1,0))) -> 4 | H52: SERVIÇO | I52: =IF(H52="Unidade Construtiva",TEXT(A52,"00"),IF(H52="Célula Construtiva",TEXT(B52,"00"),IF(H52="Etapa",CONCATENATE(TEXT(B52,"00"),".",TEXT(C52,"000")),IF(H52="Subetapa",CONCATENATE(TEXT(B52,"00"),".",TEXT(C52,"000"),".",TEXT(D52,"000")),IF(H52="Serviço",CONCATENATE(TEXT(B52,"00"),".",TEXT(C52,"000"),".",TEXT(D52,"000"),".",TEXT(E52,"000")),""))))) -> 01.002.002.004 | J52: Certidão INSS | K52: vb | L52: 1 | M52: 28384.89 | N52: =IF(H52="Serviço",M52*L52,IF(H52="CÉLULA CONSTRUTIVA",SUMIFS($N$8:$N$417,$B$8:$B$417,B52,$H$8:$H$417,"Serviço"),IF(H52="ETAPA",SUMIFS($N$8:$N$417,$B$8:$B$417,B52,$C$8:$C$417,C52,$H$8:$H$417,"Serviço"),IF(H52="SUBETAPA",SUMIFS($N$8:$N$417,$B$8:$B$417,B52,$C$8:$C$417,C52,$D$8:$D$417,D52,$H$8:$H$417,"Serviço"),0)))) -> 28384.89 | O52: Estimado com base em índices históricos | P52: Lançado ERP
