Workbook
Name _: #REF!
Name _: #REF!
Name _: #REF!
Name _: #REF!
Name _: #REF!
Name __: #REF!
Name __: #REF!
Name __: #REF!
Name ______ACR10: #REF!
Name ______ACR10: #REF!
Name ______ACR10: #REF!
Name ______ACR10: #REF!
Name ______ACR10: #REF!
Name ______ACR15: #REF!
Name ______ACR15: #REF!
Name ______ACR15: #REF!
Name ______ACR15: #REF!
Name ______ACR15: #REF!
Name ______acr20: #REF!
Name ______acr20: #REF!
Name ______acr20: #REF!
Name ______acr20: #REF!
Name ______acr20: #REF!
Name ______acr5: #REF!
Name ______acr5: #REF!
Name ______acr5: #REF!
Name ______acr5: #REF!
Name ______acr5: #REF!
Name ______ARQ1: #REF!
Name ______ARQ1: #REF!
Name ______ARQ1: #REF!
Name ______ARQ1: #REF!
Name ______ARQ1: #REF!
Name ______QT100: #REF!
Name ______QT100: #REF!
Name ______QT100: #REF!
Name ______QT100: #REF!
Name ______QT100: #REF!
Name ______QT2: #REF!
Name ______QT2: #REF!
Name ______QT2: #REF!
Name ______QT2: #REF!
Name ______QT2: #REF!
Name ______QT3: #REF!
Name ______QT3: #REF!
Name ______QT3: #REF!
Name ______QT3: #REF!
Name ______QT3: #REF!
Name ______QT4: #REF!
Name ______QT4: #REF!
Name ______QT4: #REF!
Name ______QT4: #REF!
Name ______QT4: #REF!
Name ______QT50: #REF!
Name ______QT50: #REF!
Name ______QT50: #REF!
Name ______QT50: #REF!
Name ______QT50: #REF!
Name ______QT75: #REF!
Name ______QT75: #REF!

Sheet Obra 
C1: Projeto | D1: Mosaico
C2: Empresa | D2: Grupo DUO
C3: Revisão | D3: R00
A4: QUADRO DE ÁREAS
B6: Descrição | C6: Unidade | E6: Quantidade | G6: Imagens
B7: MESES DE OBRA | C7: MÊS | E7: 42
B8: ÁREA DO TERRENO | C8: M² | E8: 1140
B9: ÁREA CONSTRUÍDA | C9: M² | E9: 7672.04
B10: NÚMERO DE UNIDADES HABITACIONAIS | C10: UN | E10: 81
B11: NÚMERO DE UNIDADES COMERCIAIS | C11: UN | E11: 2
B12: ÁREA PRIVATIVA | C12: M² | E12: 4782.91
B13: NÚMERO DE PAVIMENTOS | C13: UN | E13: 16
B15: 1º Pavimento | C15: M² | E15: 787.31
B16: 2º Pavimento | C16: M² | E16: 785.88
B17: 3º Pavimento | C17: M² | E17: 808.07
B18: 4º Pavimento | C18: M² | E18: 506.35
B19: 5º Pavimento | C19: M² | E19: 506.35
... B30: Reservatórios | C30: M² | E30: 27.75
B34: ETAPA | C34: VALOR ORÇADO | D34: % | E34: VALOR / m²
B35: GERENCIAMENTO TÉCNICO E ADMINISTRATIVO | C35: ='Ger_Tec e Adm'!N121 -> 5188435.6 | D35: =C35/C$53 -> 0.1677078 | E35: =C35/$E$9 -> 676.27849
B36: MOVIMENTAÇÃO DE TERRA | C36: =Ger_Executivo!N8 -> 96602.73 | D36: =C36/C$53 -> 0.0031225272 | E36: =C36/$E$9 -> 12.591531
B37: INFRAESTRUTURA | C37: =Ger_Executivo!N18 -> 1590820.8 | D37: =C37/C$53 -> 0.051420712 | E37: =C37/$E$9 -> 207.35304
B38: SUPRAESTRUTURA | C38: =Ger_Executivo!N51 -> 5123650 | D38: =C38/C$53 -> 0.16561371 | E38: =C38/$E$9 -> 667.83411
B39: ALVENARIA | C39: =Ger_Executivo!N76 -> 1312845.6 | D39: =C39/C$53 -> 0.042435612 | E39: =C39/$E$9 -> 171.12079
B40: IMPERMEABILIZAÇÃO E TRATAMENTOS | C40: =Ger_Executivo!N92 -> 674300.8 | D40: =C40/C$53 -> 0.021795684 | E40: =C40/$E$9 -> 87.890679
B41: INSTALAÇÕES ELÉTRICAS, HIDRÁULICAS, GLP E PREVENTIVAS | C41: =Ger_Executivo!N116+Ger_Executivo!N128+Ger_Executivo!N144+Ger_Executivo!N156 -> 2428838.7 | D41: =C41/C$53 -> 0.078508289 | E41: =C41/$E$9 -> 316.58317
B42: EQUIPAMENTOS E SISTEMAS ESPECIAIS | C42: =Ger_Executivo!N162+Ger_Executivo!N169 -> 865640.05 | D42: =C42/C$53 -> 0.027980417 | E42: =C42/$E$9 -> 112.83049
B43: CLIMATIZAÇÃO, EXAUSTÃO MECÂNICA E PRESSURIZAÇÃO | C43: =Ger_Executivo!N176 -> 229561 | D43: =C43/C$53 -> 0.0074201885 | E43: =C43/$E$9 -> 29.921768
B44: REVESTIMENTOS INTERNOS DE PAREDE | C44: =Ger_Executivo!N184 -> 1510715.5 | D44: =C44/C$53 -> 0.048831437 | E44: =C44/$E$9 -> 196.91183
B45: REVESTIMENTOS INTERNOS DE TETO | C45: =Ger_Executivo!N204 -> 557998.01 | D45: =C45/C$53 -> 0.018036384 | E45: =C45/$E$9 -> 72.731373
B46: PISOS E PAVIMENTAÇÕES | C46: =Ger_Executivo!N212 -> 2160927.4 | D46: =C46/C$53 -> 0.069848488 | E46: =C46/$E$9 -> 281.66269
B47: SISTEMAS DE PINTURA INTERNA | C47: =Ger_Executivo!N237 -> 1247040.6 | D47: =C47/C$53 -> 0.040308573 | E47: =C47/$E$9 -> 162.54355
B48: ESQUADRIAS, VIDROS E FERRAGENS | C48: =Ger_Executivo!N259 -> 3562144.1 | D48: =C48/C$53 -> 0.11514055 | E48: =C48/$E$9 -> 464.30208
B49: LOUÇAS E METAIS | C49: =Ger_Executivo!N296 -> 251275.31 | D49: =C49/C$53 -> 0.0081220685 | E49: =C49/$E$9 -> 32.752085
B50: REVESTIMENTOS E ACABAMENTOS EM FACHADA | C50: =Ger_Executivo!N306 -> 2820993 | D50: =C50/C$53 -> 0.091184043 | E50: =C50/$E$9 -> 367.6979
B51: SERVIÇOS COMPLEMENTARES E FINAIS | C51: =Ger_Executivo!N326 -> 935038.96 | D51: =C51/C$53 -> 0.030223624 | E51: =C51/$E$9 -> 121.87618
B52: IMPREVISTOS | C52: =Ger_Executivo!N344 -> 380525.89 | D52: =C52/C$53 -> 0.012299885 | E52: =C52/$E$9 -> 49.599049
B53: TOTAL | C53: =SUM(C35:C52) -> 30937354 | D53: =SUM(D35:D52) -> 1 | E53: =SUM(E35:E52) -> 4032.4808
B54: CUB/SC | C54: 2999.38 | D54: 45931 | E54: =ROUND(+E53/C54,2)&" CUB" -> 1,34 CUB
B63: MOVIMENTAÇÃO DE TERRA
B64: INFRAESTRUTURA
B65: SUPRAESTRUTURA
B66: ALVENARIAS E VEDAÇÕES
B67: IMPERMEABILIZAÇÃO E TRATAMENTOS
B68: SISTEMAS E INSTALAÇÕES HIDROSSANITÁRIAS E DRENAGEM
B69: SISTEMAS E INSTALAÇÕES ELÉTRICAS
B70: INSTALAÇÕES PREVENTIVAS
B71: INSTALAÇÕES DE GÁS
B72: INSTALAÇÕES DE COMUNICAÇÕES
B73: EQUIPAMENTOS E SISTEMAS ESPECIAIS
B74: CLIMATIZAÇÃO, EXAUSTÃO MECÂNICA E PRESSURIZAÇÃO
... B84: IMPREVISTOS E CONTINGÊNCIAS

Sheet EPCs
A1: Obra | B1: ='Obra '!D1 -> Mosaico
A2: Empresa | B2: ='Obra '!D2 -> Grupo DUO
A3: Revisão | B3: ='Obra '!D3 -> R00 | K3: Guia pavimentos
A4: Equipamentos de proteção coletiva | K4: Pavimento | L4: Área | M4: Perímetro | N4: Pé Direito
A5: Bandejas de proteção
K6: ='Obra '!B15 -> 1º Pavimento | L6: ='Obra '!E15 -> 787.31 | M6: 135.43 | N6: 3.24
B7: Descrição | C7: Unidade | D7: Quantidade | F7: Imagem formulário | K7: ='Obra '!B16 -> 2º Pavimento | L7: ='Obra '!E16 -> 785.88 | M7: 120.85 | N7: 3.96 | O7: 15.95
B8: Perímetro de projeção embasamento - primária | C8: m | D8: 135.43 | K8: ='Obra '!B17 -> 3º Pavimento | L8: ='Obra '!E17 -> 808.07 | M8: 125.95 | N8: 3.24 | O8: 15.95
B9: Perímetro de projeção embasamento - secundária | C9: m | D9: 290.49 | K9: ='Obra '!B18 -> 4º Pavimento | L9: ='Obra '!E18 -> 506.35 | M9: 96.83 | N9: 3.24 | O9: 15.95
K10: ='Obra '!B19 -> 5º Pavimento | L10: ='Obra '!E19 -> 506.35 | M10: 96.83 | N10: 3.24 | O10: 15.95
K11: ='Obra '!B20 -> 6º Pavimento | L11: ='Obra '!E20 -> 506.35 | M11: 96.83 | N11: 3.24 | O11: 15.95
B12: Bandeja de proteção primária | C12: m | D12: =D8+D10 -> 135.43 | K12: ='Obra '!B21 -> 7º Pavimento | L12: ='Obra '!E21 -> 506.35 | M12: 96.83 | N12: 3.24 | O12: 37.075
B13: Bandeja de proteção secundária | C13: m | D13: =D9+D11 -> 290.49 | K13: ='Obra '!B22 -> 8º Pavimento | L13: ='Obra '!E22 -> 506.35 | M13: 96.83 | N13: 3.24 | O13: =29.4*24 -> 705.6
K14: ='Obra '!B23 -> 9º Pavimento | L14: ='Obra '!E23 -> 506.35 | M14: 96.83 | N14: 3.24
A15: Guarda - corpo de vãos | K15: ='Obra '!B24 -> 10º Pavimento | L15: ='Obra '!E24 -> 506.35 | M15: 96.83 | N15: 3.24
K16: ='Obra '!B25 -> 11º Pavimento | L16: ='Obra '!E25 -> 506.35 | M16: 96.83 | N16: 3.24 | O16: =SUM(O6:O15) -> 822.425
B17: Descrição | C17: Unidade | D17: Quantidade | F17: Imagem formulário | K17: ='Obra '!B26 -> 12º Pavimento | L17: ='Obra '!E26 -> 506.35 | M17: 96.83 | N17: 2.88
B18: Perímetro de vãos | C18: m | D18: 530.19 | K18: ='Obra '!B27 -> Mezanino | L18: ='Obra '!E27 -> 194.44 | M18: 96.83 | N18: 2.88
B19: Guarda - corpo de vãos | C19: m | D19: =D18 -> 530.19 | K19: ='Obra '!B28 -> Cobertura | L19: ='Obra '!E28 -> 483.01 | M19: 89.08 | N19: 4.32
K20: ='Obra '!B29 -> Barrilete | L20: ='Obra '!E29 -> 27.75 | M20: 60.35 | N20: 3
A21: Guarda - corpo de desforma | K21: ='Obra '!B30 -> Reservatórios | L21: ='Obra '!E30 -> 27.75 | M21: 27.92 | N21: 3.32
K22: ='Obra '!B31 -> 0 | M22: =SUM(M6:M21) -> 1527.88
B23: Descrição | C23: Unidade | D23: Quantidade | F23: Imagem formulário
B24: Perímetro de projeção da torre | C24: m | D24: 96.83
B25: Repetições de pavimentos** | C25: un | D25: 4
B26: Proteção de periferia pós desforma torre | C26: m | D26: =(D24*D25) -> 387.32
A28: Fechamento removível de vãos em madeira
B30: Descrição | C30: Unidade | D30: Quantidade | F30: Imagem formulário
B31: Área das portas de elevadores | C31: m2 | D31: =0.9*2.1 -> 1.89
B32: Quantidade de elevadores | C32: un | D32: 2
B33: Quantidade de portas de elevadores | C33: un | D33: 28
B34: Fechamento removível de vãos em madeira | C34: m2 | D34: =D31*D33 -> 52.92
A36: Fechamento removível de vãos de portas de entrada de apto em madeira
B38: Descrição | C38: Unidade | D38: Quantidade | F38: Imagem formulário
B39: Área das portas de entrada | C39: m2 | D39: =0.9*2.1 -> 1.89
B40: Quantidade de portas de entrada | C40: un | D40: 81
B41: Fechamento removível de vãos em madeira | C41: m2 | D41: =D39*D40 -> 153.09
A43: Tela fachadeira
B45: Descrição | C45: Unidade | D45: Quantidade | F45: Imagem formulário
B46: Area da fachada | C46: m² | D46: =SUMPRODUCT($M$7:$M$21,$N$7:$N$21) -> 4612.7884
B47: =A43 -> Tela fachadeira | C47: m2 | D47: =D46 -> 4612.7884
A49: Tapume
B51: Descrição | C51: Unidade | D51: Quantidade | F51: Imagem formulário
B52: Perímetro de encontro com pavimentação | C52: m | D52: 37.81
B53: Altura do tapume | C53: m | D53: 2.4
B54: =A49 -> Tapume | C54: m2 | D54: =D53*D52 -> 90.744
A56: Linha de Vida
B58: Descrição | C58: Unidade | D58: Quantidade | F58: Imagem formulário
B59: Perímetro de Pavimentos | C59: m | D59: =$D$26 -> 387.32
B60: =A56 -> Linha de Vida | C60: m | D60: =D59 -> 387.32
A62: Cobertura para Proteção de Pedestres
B64: Descrição | C64: Unidade | D64: Quantidade | F64: Imagem formulário
B65: Perímetro de projeção torre | C65: m
B66: Altura de cobrimento da tela | C66: m
B67: Cobertura para Proteção de Pedestres | C67: m2 | D67: =D65*D66 -> 0

Sheet CANTEIRO
A1: Obra | B1: ='Obra '!D1 -> Mosaico
A2: Empresa | B2: ='Obra '!D2 -> Grupo DUO
A3: Revisão | B3: ='Obra '!D3 -> R00
A4: Instalações de canteiro
A5: Instalações de canteiro
B7: Descrição | C7: Unidade | D7: Quantidade
B8: Produtividade média | C8: m2 / mês | D8: ='Obra '!$E$9/'Obra '!$E$7 -> 182.66762
B9: Pm | C9: h/m2 | D9: 49
B10: Numero de funcionários | C10: un | D10: =ROUNDUP((D9*'Obra '!$E$9)/'Obra '!$E$7/180,) -> 50
B11: Equipe administrativa | C11: un | D11: 2
B12: Pontos de água e esgoto | C12: un | D12: =ROUNDUP($D$10/20,0) -> 3 | E12: 20 funcionários/ponto
B13: Bebedouro | C13: un | D13: =ROUNDUP('Obra '!$E$13/5,0) -> 4 | E13: 1 / 5 pav.
B14: Ferramentas | C14: R$ | D14: =800*D10 -> 40000 | E14: 800,00/func.
B15: EPI | C15: R$ | D15: =500*(D10+D11) -> 26000 | E15: 500,00/func.
B16: Banheiro | C16: un | D16: =ROUNDUP($D$10/20,0) -> 3 | E16: 1/20 func
A18: Mobiliário de canteiro
B20: Descrição | C20: Unidade | D20: Quantidade | E20: Custo unitário | F20: Custo total
B21: Cadeira | C21: un | D21: =ROUNDUP(D11*1.5,) -> 3 | E21: 200 | F21: =D21*E21 -> 600
B22: Mesa | C22: un | D22: 1 | E22: 1000 | F22: =E22*D22 -> 1000
B23: Ar condicionado | C23: un | D23: 1 | E23: 5000 | F23: =E23*D23 -> 5000
B24: Armário | C24: m | D24: 4 | E24: 900 | F24: =E24*D24 -> 3600
B25: Escrivaninha | C25: un | D25: 5 | E25: 800 | F25: =E25*D25 -> 4000
B26: TOTAL | F26: =F23+F24+F25+F22+F21 -> 14200
B27: Descrição | C27: Unidade | D27: Quantidade | E27: Custo unitário | F27: Custo total
B28: Computador pessoal | C28: un | D28: 5 | E28: 6500 | F28: =D28*E28 -> 32500
B29: Impressora | C29: un | D29: 1 | E29: 2000 | F29: =E29*D29 -> 2000
B30: Roteador | C30: un | D30: 2 | E30: 500 | F30: =E30*D30 -> 1000
B31: TOTAL | F31: =+F28+F29+F30 -> 35500
A33: Instalações Provisórias (central de aço, formas, argamassa, almoxarifado geral, construções temporárias)
B35: Descrição | C35: Unidade | D35: Será utilizado | E35: Quantidade | F35: Custo unitário | G35: Custo total
B36: Central de aço | C36: m2 | D36: Sim | E36: =IF(D36="Sim",15,0) -> 15 | F36: 115.4849 | G36: =IF(D36="sim",E36*F36,0) -> 1732.2735
B37: Central de fôrmas | C37: m2 | D37: Sim | E37: =IF(D37="Sim",15,0) -> 15 | F37: 115.4849 | G37: =IF(D37="sim",E37*F37,0) -> 1732.2735
B38: Central de Argamassa | C38: m2 | D38: Sim | E38: =IF(D38="Sim",15,0) -> 15 | F38: 115.4849 | G38: =IF(D38="sim",E38*F38,0) -> 1732.2735
B39: Armazenamento de cerâmicas* | C39: m2 | D39: Sim | E39: =IF(D39="não",0,ROUNDUP(3*'Obra '!$E$10/COUNTIFS($D$39:$D$47,"Sim"),)) -> 35 | F39: 201.22489 | G39: =IF(D39="sim",E39*F39,0) -> 7042.8712
B40: Armazenamento de placas degesso* | C40: m2 | D40: Não | E40: =IF(D40="não",0,ROUNDUP(3*'Obra '!$E$10/COUNTIFS($D$39:$D$47,"Sim"),)) -> 0 | F40: 201.22489 | G40: =IF(D40="sim",E40*F40,0) -> 0
B41: Armazenamento de blocos* | C41: m2 | D41: Sim | E41: =IF(D41="não",0,ROUNDUP(3*'Obra '!$E$10/COUNTIFS($D$39:$D$47,"Sim"),)) -> 35 | F41: 201.22489 | G41: =IF(D41="sim",E41*F41,0) -> 7042.8712
B42: Armazenamento de contramarcos* | C42: m2 | D42: Sim | E42: =IF(D42="não",0,ROUNDUP(3*'Obra '!$E$10/COUNTIFS($D$39:$D$47,"Sim"),)) -> 35 | F42: 201.22489 | G42: =IF(D42="sim",E42*F42,0) -> 7042.8712
B43: Armazenamento de portas e rodapés* | C43: m2 | D43: Sim | E43: =IF(D43="não",0,ROUNDUP(3*'Obra '!$E$10/COUNTIFS($D$39:$D$47,"Sim"),)) -> 35 | F43: 201.22489 | G43: =IF(D43="sim",E43*F43,0) -> 7042.8712
B44: Armazenamento de esquadrias* | C44: m2 | D44: Não | E44: =IF(D44="não",0,ROUNDUP(3*'Obra '!$E$10/COUNTIFS($D$39:$D$47,"Sim"),)) -> 0 | F44: 201.22489 | G44: =IF(D44="sim",E44*F44,0) -> 0
B45: Armazenamento de instalações complementares* | C45: m2 | D45: Sim | E45: =IF(D45="não",0,ROUNDUP(3*'Obra '!$E$10/COUNTIFS($D$39:$D$47,"Sim"),)) -> 35 | F45: 201.22489 | G45: =IF(D45="sim",E45*F45,0) -> 7042.8712
B46: Armazenamento para estoque geral* | C46: m2 | D46: Sim | E46: =IF(D46="não",0,ROUNDUP(3*'Obra '!$E$10/COUNTIFS($D$39:$D$47,"Sim"),)) -> 35 | F46: 201.22489 | G46: =IF(D46="sim",E46*F46,0) -> 7042.8712
B47: Construções temporárias | C47: m2 | D47: Sim | E47: =IF(D47="não",0,ROUNDUP(3*'Obra '!$E$10/COUNTIFS($D$39:$D$47,"Sim"),)) -> 35 | F47: 272.8753 | G47: =IF(D47="sim",E47*F47,0) -> 9550.6355
B48: Almoxarifado geral | C48: m2 | D48: Sim | E48: =IF(D48="Sim",10*15,0) -> 150 | F48: 272.8753 | G48: =IF(D48="sim",E48*F48,0) -> 40931.295
B49: Guarita | C49: m2 | D49: Não | E49: =IF(D49="Sim",ROUNDUP(25,),0) -> 0 | F49: 0 | G49: =IF(D49="sim",E49*F49,0) -> 0
B50: Lava Rodas | C50: m2 | D50: Sim | E50: =IF(D50="Sim",ROUNDUP(25,),0) -> 25 | F50: 0 | G50: =IF(D50="sim",E50*F50,0) -> 0
B51: TOTAL | G51: =SUM(G36:G50) -> 97935.978
B53: * Central de armazenamento entre pavimentos
A55: Sinalização
B57: Descrição | C57: Unidade | D57: Será utilizado | E57: Quantidade | F57: Custo unitário | G57: Custo total
B58: Placa indicativa fixada na estrutura por pregos | C58: VB | D58: Sim | E58: 1 | F58: 7891.02 | G58: =IF(D58="sim",E58*F58,0) -> 7891.02
B59: Placa indicativa fixada em totem | C59: VB | D59: Sim | E59: 1 | F59: =F58*0.2 -> 1578.204 | G59: =IF(D59="sim",E59*F59,0) -> 1578.204
B60: Instalação de sinalizador noturno | C60: m2 | D60: Não | G60: =IF(D60="sim",E60*F60,0) -> 0
B61: Sinalização com fita fixada em cone | C61: m2 | D61: Não | G61: =IF(D61="sim",E61*F61,0) -> 0
B62: Sinalização com fita fixada na estrutura amarrada | C62: m2 | D62: Não | G62: =IF(D62="sim",E62*F62,0) -> 0
B63: TOTAL | G63: =SUM(G58:G62) -> 9469.224

Sheet Ensaios 
C1: Projeto | D1: ='Obra '!D1 -> Mosaico
C2: Empresa | D2: ='Obra '!D2 -> Grupo DUO
C3: Revisão | D3: ='Obra '!D3 -> R00
A4: ENSAIOS
A5: Item | B5: Descrição/Especificação | C5: Unid. | D5: V. Unit. (R$) | E5: Qtde. | F5: V. Total (R$) | G5: Observações
B6: CONTROLE TECNOLÓGICO - CONCRETO | F6: =SUM(F7:F12) -> 39640
A7: 1 | B7: Laudo e ART | C7: vb | D7: 1450 | E7: 1 | F7: =$D7*E7 -> 1450
A8: =A7+1 -> 2 | B8: Controle Tecnologico Infraestrutura - Coleta materiais da obra | C8: unid. | D8: 20 | E8: =ROUNDUP((Aço_Infraestrutura!P23)/8,0)*4 -> 188 | F8: =$D8*E8 -> 3760 | G8: 4 CPs por caminhão betoneira de 8m³
A9: =A8+1 -> 3 | B9: Controle Tecnologico Contenção - Coleta materiais da obra | C9: unid. | D9: 20 | E9: =ROUNDUP((Estacas!K13)/8,0)*4 -> 64 | F9: =$D9*E9 -> 1280 | G9: 4 CPs por caminhão betoneira de 8m³
A10: =A9+1 -> 4 | B10: Controle Tecnologico Supraestrutura - Coleta materiais da obra | C10: unid. | D10: 20 | E10: =ROUNDUP((Supraestrutura!P97)/8,0)*4 -> 864 | F10: =$D10*E10 -> 17280 | G10: 4 CPs por caminhão betoneira de 8m³
A11: =A8+1 -> 3 | B11: Controle Tecnológico - Ensaio de concreto endurecido/grouth - compressão simples / Detalhe: Concreto | C11: cps | D11: 12.5 | E11: =E8+E9+E10 -> 1116 | F11: =$D11*E11 -> 13950
A12: =A11+1 -> 4 | B12: Determinação do módulo de deformação tangente inicial (Eci) (módulo de elasticidade), Incluindo Avaliação Estática dos Resultados (NBR 8522 e NBR 12655) | C12: ensaio | D12: 480 | E12: =ROUNDUP('Obra '!E13/5,0) -> 4 | F12: =$D12*E12 -> 1920 | G12: A cada 5 pav. (e quando houver troca de fornecedor)
B13: ACUSTICA - ENSAIO DE RUIDOS ( PISO + FACHADA) | F13: =SUM(F14:F15) -> 0
A14: 1 | B14: Ensaio de Desempenho Acustico para piso Ensaio de ruído aéreo e ruído de impacto em Laje de dorm. | C14: ensaios | D14: 7500 | F14: =$D14*E14 -> 0 | G14: 1 ensaio
A15: =A14+1 -> 2 | B15: Ensaio de Desempenho Acustico para vedação externa Ensaio de isolamento a ruído aéreo em Fachada de dorm. | C15: ensaios | D15: 1500 | F15: =$D15*E15 -> 0 | G15: 1 ensaio
B16: ENSAIO PARA CAIXILHOS | F16: =SUM(F17:F19) -> 0
A17: 1 | B17: Permeabilidade ao ar Estanqueidade a agua Resistencias a cargas uniformes distribuidas | C17: ensaios | D17: 3174 | F17: =$D17*E17 -> 0 | G17: 1 ensaio por tipo de caixilho (dormitório, sala, área de serviço e banheiro e terraço, se houver)
A18: =A17+1 -> 2 | B18: Resistencia as operações de manuseio com manutenção SEM persiana integrada | C18: ensaios | D18: 2774 | F18: =$D18*E18 -> 0 | G18: 1 ensaio por tipo de caixilho (dormitório, sala, área de serviço e banheiro e terraço, se houver)
A19: =A18+1 -> 3 | B19: Resistencia as operações de manuseio com manutenção COM persiana integrada | C19: ensaios | D19: 4020 | F19: =$D19*E19 -> 0 | G19: 1 ensaio por tipo de caixilho (dormitório, sala, área de serviço e banheiro e terraço, se houver)
B20: ENSAIO PARA GUARDA-CORPO | F20: =F21 -> 4210
A21: 1 | B21: Ensaio de guarda-corpo Determinação do esforço horizontal, esforço vertical e Resistencia a impactos | C21: ensaios | D21: 4210 | E21: 1 | F21: =$D21*E21 -> 4210 | G21: 1 prototipo por projeto
B22: ENSAIOS PARA ARGAMASSA DE REVESTIMENTO (FACHADA) | F22: =F23 -> 1260
A23: 1 | B23: Ensaio de arrancamento de argamassa de revestimento Determinação da aderencia a tração | C23: ensaios | D23: 1260 | E23: 1 | F23: =$D23*E23 -> 1260 | G23: 1 ensaio por torre
B24: ENSAIO ARRANCAMENTO DE REBOCO | F24: =F25 -> 1260
A25: 1 | B25: Ensaio de arrancamento de argamassa de reboco Determinação da aderencia a tração | C25: ensaios | D25: 1260 | E25: 1 | F25: =$D25*E25 -> 1260 | G25: 1 ensaio por torre
B26: ENSAIO PARA REVESTIMENTOS CERÂMICOS | F26: =F27 -> 664.44444
A27: 1 | B27: Aderência em Revestimento Cerâmico Determinação da aderência a tração (NBR 13754) | C27: ensaios | D27: 664.44444 | E27: 1 | F27: =$D27*E27 -> 664.44444 | G27: Torre Alta: 1 ensaio por torre, por referência de produto
B28: ENSAIO PARA ANCORAGEM (GANHOS DA COBERTURA) | F28: =SUM(F29) -> 1680
A29: 1 | B29: Arrancamento de ganchos da cobertura Ensaio de Arrancamento | C29: ensaios | D29: 1680 | E29: 1 | F29: =$D29*E29 -> 1680 | G29: 1 ensaio por torre
B30: ENSAIOS PARA ALVENARIA ESTRUTURAL | F30: =SUM(F31:F36) -> 1728
A31: 1 | B31: Controle Tecnológico - Ensaio de concreto endurecido/grouth - compressão simples / Detalhe: Groute | C31: unid. | D31: 8.5 | G31: ≥ 12Mpa: 6 CP's x núm pav x núm torres + ANEXOS (CONSIDERAR +6 CPs PARA CADA PAVIMENTO DE ANEXOS - INCLUINDO EMBASAMENTO E PLATIBANDA - SE HOUVER) Torre alta: 6CPs por pavimento
A32: =A31+1 -> 2 | B32: Ensaio de Argamassa - Determinação da resistência a compressão - no cubo (NBR 15961-2/2011) | C32: unid. | D32: 18 | E32: =6*'Obra '!E13 -> 96 | F32: =E32*D32 -> 1728 | G32: ≥ 12Mpa: 6 CP's x núm pav x núm torres + ANEXOS (CONSIDERAR +6 CPs PARA CADA PAVIMENTO DE ANEXOS - INCLUINDO EMBASAMENTO E PLATIBANDA - SE HOUVER) Torre alta: 6CPs por pavimento P/ pavimento > 600m²: 12 CPs
A33: =A32+1 -> 3 | B33: Ensaio Prisma - Determinação da resistência a compressão - Oco (NBR 15961-2/2011) | C33: unid. | D33: 50 | G33: 12 CP's x núm pav x núm torres Torre alta: 12CPs por pavimento P/ pavimento > 600m²: 12 CPs
A34: =A33+1 -> 4 | B34: Ensaio Prisma - Determinação da resistência a compressão - Cheio (NBR 15961-2/2011) | C34: unid. | D34: 65 | G34: 12 CP's x núm pav x núm torres Torre alta: 12CPs por pavimento P/ pavimento > 600m²: 12 CPs
A35: =A34+1 -> 5 | B35: Ensaio de Bloco - Determinação da resistência a compressão com dimensionamento (NBR 12118) | C35: cps | D35: 40 | G35: 6 cps x núm classes de resistencia
A36: =A35+1 -> 6 | B36: Ensaio de Bloco - Determinação da absorção e área liquida (NBR 12118) | C36: unid | D36: 40 | G36: 3 cps x núm classe de resistencia
C37: SUBTOTAL: | F37: =F30+F28+F26+F22+F20+F16+F13+F6 -> 49182.444

Sheet Ger_Tec e Adm
G4: PROJETO: | I4: ='Obra '!D1 -> Mosaico | O4: REVISÃO: | P4: DATA
G5: EMPRESA: | I5: ='Obra '!D2 -> Grupo DUO | O5: ='Obra '!D3 -> R00 | P5: 45877
A6: Unidade Construtiva | B6: Célula Construtiva | C6: Etapa | D6: Subetapa | E6: Serviço | G6: GERENCIAMENTO EXECUTIVO
A7: 0 | B7: 0 | C7: 0 | D7: 0 | E7: 0 | G7: Atalho | H7: NIVEL | I7: Item | J7: Descrição | K7: Unidade | L7: Quant. | M7: Preço un | N7: Total | O7: Considerações | P7: Situação
A8: =IF($H8="UNIDADE CONSTRUTIVA",OFFSET(A8,-1,0)+1,LARGE(A$3:A7,1)) -> 0 | B8: =IF(H8="UNIDADE CONSTRUTIVA",0,IF(H8="CÉLULA CONSTRUTIVA",OFFSET(B8,-1,0)+1,OFFSET(B8,-1,0))) -> 1 | C8: =IF(H8="CÉLULA CONSTRUTIVA",0,IF(H8="ETAPA",OFFSET(C8,-1,0)+1,OFFSET(C8,-1,0))) -> 0 | D8: =IF(H8="ETAPA",0,IF(H8="SUBETAPA",OFFSET(D8,-1,0)+1,OFFSET(D8,-1,0))) -> 0 | E8: =IF(H8="Subetapa",0,IF(H8="serviço",OFFSET(E8,-1,0)+1,OFFSET(E8,-1,0))) -> 0 | H8: CÉLULA CONSTRUTIVA | I8: =IF(H8="Unidade Construtiva",TEXT(A8,"00"),IF(H8="Célula Construtiva",TEXT(B8,"00"),IF(H8="Etapa",CONCATENATE(TEXT(B8,"00"),".",TEXT(C8,"000")),IF(H8="Subetapa",CONCATENATE(TEXT(B8,"00"),".",TEXT(C8,"000"),".",TEXT(D8,"000")),IF(H8="Serviço",CONCATENATE(TEXT(B8,"00"),".",TEXT(C8,"000"),".",TEXT(D8,"000"),".",TEXT(E8,"000")),""))))) -> 01 | J8: SERVIÇOS TÉCNICOS | N8: =IF(H8="Serviço",M8*L8,IF(H8="CÉLULA CONSTRUTIVA",SUMIFS($N$8:$N$418,$B$8:$B$418,B8,$H$8:$H$418,"Serviço"),IF(H8="ETAPA",SUMIFS($N$8:$N$418,$B$8:$B$418,B8,$C$8:$C$418,C8,$H$8:$H$418,"Serviço"),IF(H8="SUBETAPA",SUMIFS($N$8:$N$418,$B$8:$B$418,B8,$C$8:$C$418,C8,$D$8:$D$418,D8,$H$8:$H$418,"Serviço"),0)))) -> 2526660.3
A9: =IF($H9="UNIDADE CONSTRUTIVA",OFFSET(A9,-1,0)+1,LARGE(A$3:A8,1)) -> 0 | B9: =IF(H9="UNIDADE CONSTRUTIVA",0,IF(H9="CÉLULA CONSTRUTIVA",OFFSET(B9,-1,0)+1,OFFSET(B9,-1,0))) -> 1 | C9: =IF(H9="CÉLULA CONSTRUTIVA",0,IF(H9="ETAPA",OFFSET(C9,-1,0)+1,OFFSET(C9,-1,0))) -> 1 | D9: =IF(H9="ETAPA",0,IF(H9="SUBETAPA",OFFSET(D9,-1,0)+1,OFFSET(D9,-1,0))) -> 0 | E9: =IF(H9="Subetapa",0,IF(H9="serviço",OFFSET(E9,-1,0)+1,OFFSET(E9,-1,0))) -> 0 | H9: ETAPA | I9: =IF(H9="Unidade Construtiva",TEXT(A9,"00"),IF(H9="Célula Construtiva",TEXT(B9,"00"),IF(H9="Etapa",CONCATENATE(TEXT(B9,"00"),".",TEXT(C9,"000")),IF(H9="Subetapa",CONCATENATE(TEXT(B9,"00"),".",TEXT(C9,"000"),".",TEXT(D9,"000")),IF(H9="Serviço",CONCATENATE(TEXT(B9,"00"),".",TEXT(C9,"000"),".",TEXT(D9,"000"),".",TEXT(E9,"000")),""))))) -> 01.001 | J9: ESTUDOS, PROJETOS, CONSULTORIA E ENSAIOS | N9: =IF(H9="Serviço",M9*L9,IF(H9="CÉLULA CONSTRUTIVA",SUMIFS($N$8:$N$418,$B$8:$B$418,B9,$H$8:$H$418,"Serviço"),IF(H9="ETAPA",SUMIFS($N$8:$N$418,$B$8:$B$418,B9,$C$8:$C$418,C9,$H$8:$H$418,"Serviço"),IF(H9="SUBETAPA",SUMIFS($N$8:$N$418,$B$8:$B$418,B9,$C$8:$C$418,C9,$D$8:$D$418,D9,$H$8:$H$418,"Serviço"),0)))) -> 852669.77
A10: =IF($H10="UNIDADE CONSTRUTIVA",OFFSET(A10,-1,0)+1,LARGE(A$3:A9,1)) -> 0 | B10: =IF(H10="UNIDADE CONSTRUTIVA",0,IF(H10="CÉLULA CONSTRUTIVA",OFFSET(B10,-1,0)+1,OFFSET(B10,-1,0))) -> 1 | C10: =IF(H10="CÉLULA CONSTRUTIVA",0,IF(H10="ETAPA",OFFSET(C10,-1,0)+1,OFFSET(C10,-1,0))) -> 1 | D10: =IF(H10="ETAPA",0,IF(H10="SUBETAPA",OFFSET(D10,-1,0)+1,OFFSET(D10,-1,0))) -> 1 | E10: =IF(H10="Subetapa",0,IF(H10="serviço",OFFSET(E10,-1,0)+1,OFFSET(E10,-1,0))) -> 0 | H10: SUBETAPA | I10: =IF(H10="Unidade Construtiva",TEXT(A10,"00"),IF(H10="Célula Construtiva",TEXT(B10,"00"),IF(H10="Etapa",CONCATENATE(TEXT(B10,"00"),".",TEXT(C10,"000")),IF(H10="Subetapa",CONCATENATE(TEXT(B10,"00"),".",TEXT(C10,"000"),".",TEXT(D10,"000")),IF(H10="Serviço",CONCATENATE(TEXT(B10,"00"),".",TEXT(C10,"000"),".",TEXT(D10,"000"),".",TEXT(E10,"000")),""))))) -> 01.001.001 | J10: Estudos | N10: =IF(H10="Serviço",M10*L10,IF(H10="CÉLULA CONSTRUTIVA",SUMIFS($N$8:$N$418,$B$8:$B$418,B10,$H$8:$H$418,"Serviço"),IF(H10="ETAPA",SUMIFS($N$8:$N$418,$B$8:$B$418,B10,$C$8:$C$418,C10,$H$8:$H$418,"Serviço"),IF(H10="SUBETAPA",SUMIFS($N$8:$N$418,$B$8:$B$418,B10,$C$8:$C$418,C10,$D$8:$D$418,D10,$H$8:$H$418,"Serviço"),0)))) -> 45800
A11: =IF($H11="UNIDADE CONSTRUTIVA",OFFSET(A11,-1,0)+1,LARGE(A$3:A10,1)) -> 0 | B11: =IF(H11="UNIDADE CONSTRUTIVA",0,IF(H11="CÉLULA CONSTRUTIVA",OFFSET(B11,-1,0)+1,OFFSET(B11,-1,0))) -> 1 | C11: =IF(H11="CÉLULA CONSTRUTIVA",0,IF(H11="ETAPA",OFFSET(C11,-1,0)+1,OFFSET(C11,-1,0))) -> 1 | D11: =IF(H11="ETAPA",0,IF(H11="SUBETAPA",OFFSET(D11,-1,0)+1,OFFSET(D11,-1,0))) -> 1 | E11: =IF(H11="Subetapa",0,IF(H11="serviço",OFFSET(E11,-1,0)+1,OFFSET(E11,-1,0))) -> 1 | H11: SERVIÇO | I11: =IF(H11="Unidade Construtiva",TEXT(A11,"00"),IF(H11="Célula Construtiva",TEXT(B11,"00"),IF(H11="Etapa",CONCATENATE(TEXT(B11,"00"),".",TEXT(C11,"000")),IF(H11="Subetapa",CONCATENATE(TEXT(B11,"00"),".",TEXT(C11,"000"),".",TEXT(D11,"000")),IF(H11="Serviço",CONCATENATE(TEXT(B11,"00"),".",TEXT(C11,"000"),".",TEXT(D11,"000"),".",TEXT(E11,"000")),""))))) -> 01.001.001.001 | J11: Levantamento topográfico | K11: vb | L11: 1 | M11: 1800 | N11: =IF(H11="Serviço",M11*L11,IF(H11="CÉLULA CONSTRUTIVA",SUMIFS($N$8:$N$418,$B$8:$B$418,B11,$H$8:$H$418,"Serviço"),IF(H11="ETAPA",SUMIFS($N$8:$N$418,$B$8:$B$418,B11,$C$8:$C$418,C11,$H$8:$H$418,"Serviço"),IF(H11="SUBETAPA",SUMIFS($N$8:$N$418,$B$8:$B$418,B11,$C$8:$C$418,C11,$D$8:$D$418,D11,$H$8:$H$418,"Serviço"),0)))) -> 1800 | O11: Valor informado em formulário | P11: Lançado ERP
A12: =IF($H12="UNIDADE CONSTRUTIVA",OFFSET(A12,-1,0)+1,LARGE(A$3:A11,1)) -> 0 | B12: =IF(H12="UNIDADE CONSTRUTIVA",0,IF(H12="CÉLULA CONSTRUTIVA",OFFSET(B12,-1,0)+1,OFFSET(B12,-1,0))) -> 1 | C12: =IF(H12="CÉLULA CONSTRUTIVA",0,IF(H12="ETAPA",OFFSET(C12,-1,0)+1,OFFSET(C12,-1,0))) -> 1 | D12: =IF(H12="ETAPA",0,IF(H12="SUBETAPA",OFFSET(D12,-1,0)+1,OFFSET(D12,-1,0))) -> 1 | E12: =IF(H12="Subetapa",0,IF(H12="serviço",OFFSET(E12,-1,0)+1,OFFSET(E12,-1,0))) -> 2 | H12: SERVIÇO | I12: =IF(H12="Unidade Construtiva",TEXT(A12,"00"),IF(H12="Célula Construtiva",TEXT(B12,"00"),IF(H12="Etapa",CONCATENATE(TEXT(B12,"00"),".",TEXT(C12,"000")),IF(H12="Subetapa",CONCATENATE(TEXT(B12,"00"),".",TEXT(C12,"000"),".",TEXT(D12,"000")),IF(H12="Serviço",CONCATENATE(TEXT(B12,"00"),".",TEXT(C12,"000"),".",TEXT(D12,"000"),".",TEXT(E12,"000")),""))))) -> 01.001.001.002 | J12: Sondagem do terreno | K12: vb | L12: 1 | M12: 44000 | N12: =IF(H12="Serviço",M12*L12,IF(H12="CÉLULA CONSTRUTIVA",SUMIFS($N$8:$N$418,$B$8:$B$418,B12,$H$8:$H$418,"Serviço"),IF(H12="ETAPA",SUMIFS($N$8:$N$418,$B$8:$B$418,B12,$C$8:$C$418,C12,$H$8:$H$418,"Serviço"),IF(H12="SUBETAPA",SUMIFS($N$8:$N$418,$B$8:$B$418,B12,$C$8:$C$418,C12,$D$8:$D$418,D12,$H$8:$H$418,"Serviço"),0)))) -> 44000 | O12: Valor informado em formulário | P12: Lançado ERP
A13: =IF($H13="UNIDADE CONSTRUTIVA",OFFSET(A13,-1,0)+1,LARGE(A$3:A12,1)) -> 0 | B13: =IF(H13="UNIDADE CONSTRUTIVA",0,IF(H13="CÉLULA CONSTRUTIVA",OFFSET(B13,-1,0)+1,OFFSET(B13,-1,0))) -> 1 | C13: =IF(H13="CÉLULA CONSTRUTIVA",0,IF(H13="ETAPA",OFFSET(C13,-1,0)+1,OFFSET(C13,-1,0))) -> 1 | D13: =IF(H13="ETAPA",0,IF(H13="SUBETAPA",OFFSET(D13,-1,0)+1,OFFSET(D13,-1,0))) -> 2 | E13: =IF(H13="Subetapa",0,IF(H13="serviço",OFFSET(E13,-1,0)+1,OFFSET(E13,-1,0))) -> 0 | H13: SUBETAPA | I13: =IF(H13="Unidade Construtiva",TEXT(A13,"00"),IF(H13="Célula Construtiva",TEXT(B13,"00"),IF(H13="Etapa",CONCATENATE(TEXT(B13,"00"),".",TEXT(C13,"000")),IF(H13="Subetapa",CONCATENATE(TEXT(B13,"00"),".",TEXT(C13,"000"),".",TEXT(D13,"000")),IF(H13="Serviço",CONCATENATE(TEXT(B13,"00"),".",TEXT(C13,"000"),".",TEXT(D13,"000"),".",TEXT(E13,"000")),""))))) -> 01.001.002 | J13: Projetos | N13: =IF(H13="Serviço",M13*L13,IF(H13="CÉLULA CONSTRUTIVA",SUMIFS($N$8:$N$418,$B$8:$B$418,B13,$H$8:$H$418,"Serviço"),IF(H13="ETAPA",SUMIFS($N$8:$N$418,$B$8:$B$418,B13,$C$8:$C$418,C13,$H$8:$H$418,"Serviço"),IF(H13="SUBETAPA",SUMIFS($N$8:$N$418,$B$8:$B$418,B13,$C$8:$C$418,C13,$D$8:$D$418,D13,$H$8:$H$418,"Serviço"),0)))) -> 614822.41
A14: =IF($H14="UNIDADE CONSTRUTIVA",OFFSET(A14,-1,0)+1,LARGE(A$3:A13,1)) -> 0 | B14: =IF(H14="UNIDADE CONSTRUTIVA",0,IF(H14="CÉLULA CONSTRUTIVA",OFFSET(B14,-1,0)+1,OFFSET(B14,-1,0))) -> 1 | C14: =IF(H14="CÉLULA CONSTRUTIVA",0,IF(H14="ETAPA",OFFSET(C14,-1,0)+1,OFFSET(C14,-1,0))) -> 1 | D14: =IF(H14="ETAPA",0,IF(H14="SUBETAPA",OFFSET(D14,-1,0)+1,OFFSET(D14,-1,0))) -> 2 | E14: =IF(H14="Subetapa",0,IF(H14="serviço",OFFSET(E14,-1,0)+1,OFFSET(E14,-1,0))) -> 1 | H14: SERVIÇO | I14: =IF(H14="Unidade Construtiva",TEXT(A14,"00"),IF(H14="Célula Construtiva",TEXT(B14,"00"),IF(H14="Etapa",CONCATENATE(TEXT(B14,"00"),".",TEXT(C14,"000")),IF(H14="Subetapa",CONCATENATE(TEXT(B14,"00"),".",TEXT(C14,"000"),".",TEXT(D14,"000")),IF(H14="Serviço",CONCATENATE(TEXT(B14,"00"),".",TEXT(C14,"000"),".",TEXT(D14,"000"),".",TEXT(E14,"000")),""))))) -> 01.001.002.001 | J14: Projeto Arquitetônico legal - incluindo: executivo + interiores + fachada | K14: vb | L14: 1 | M14: 320000 | N14: =IF(H14="Serviço",M14*L14,IF(H14="CÉLULA CONSTRUTIVA",SUMIFS($N$8:$N$418,$B$8:$B$418,B14,$H$8:$H$418,"Serviço"),IF(H14="ETAPA",SUMIFS($N$8:$N$418,$B$8:$B$418,B14,$C$8:$C$418,C14,$H$8:$H$418,"Serviço"),IF(H14="SUBETAPA",SUMIFS($N$8:$N$418,$B$8:$B$418,B14,$C$8:$C$418,C14,$D$8:$D$418,D14,$H$8:$H$418,"Serviço"),0)))) -> 320000 | O14: Valor informado em formulário | P14: Lançado ERP
A15: =IF($H15="UNIDADE CONSTRUTIVA",OFFSET(A15,-1,0)+1,LARGE(A$3:A14,1)) -> 0 | B15: =IF(H15="UNIDADE CONSTRUTIVA",0,IF(H15="CÉLULA CONSTRUTIVA",OFFSET(B15,-1,0)+1,OFFSET(B15,-1,0))) -> 1 | C15: =IF(H15="CÉLULA CONSTRUTIVA",0,IF(H15="ETAPA",OFFSET(C15,-1,0)+1,OFFSET(C15,-1,0))) -> 1 | D15: =IF(H15="ETAPA",0,IF(H15="SUBETAPA",OFFSET(D15,-1,0)+1,OFFSET(D15,-1,0))) -> 2 | E15: =IF(H15="Subetapa",0,IF(H15="serviço",OFFSET(E15,-1,0)+1,OFFSET(E15,-1,0))) -> 2 | H15: SERVIÇO | I15: =IF(H15="Unidade Construtiva",TEXT(A15,"00"),IF(H15="Célula Construtiva",TEXT(B15,"00"),IF(H15="Etapa",CONCATENATE(TEXT(B15,"00"),".",TEXT(C15,"000")),IF(H15="Subetapa",CONCATENATE(TEXT(B15,"00"),".",TEXT(C15,"000"),".",TEXT(D15,"000")),IF(H15="Serviço",CONCATENATE(TEXT(B15,"00"),".",TEXT(C15,"000"),".",TEXT(D15,"000"),".",TEXT(E15,"000")),""))))) -> 01.001.002.002 | J15: Projeto técnico de fachada | K15: vb | L15: 1 | M15: 9933.5054 | N15: =IF(H15="Serviço",M15*L15,IF(H15="CÉLULA CONSTRUTIVA",SUMIFS($N$8:$N$418,$B$8:$B$418,B15,$H$8:$H$418,"Serviço"),IF(H15="ETAPA",SUMIFS($N$8:$N$418,$B$8:$B$418,B15,$C$8:$C$418,C15,$H$8:$H$418,"Serviço"),IF(H15="SUBETAPA",SUMIFS($N$8:$N$418,$B$8:$B$418,B15,$C$8:$C$418,C15,$D$8:$D$418,D15,$H$8:$H$418,"Serviço"),0)))) -> 9933.5054 | O15: Estimado com base em índices históricos | P15: Lançado ERP
A16: =IF($H16="UNIDADE CONSTRUTIVA",OFFSET(A16,-1,0)+1,LARGE(A$3:A15,1)) -> 0 | B16: =IF(H16="UNIDADE CONSTRUTIVA",0,IF(H16="CÉLULA CONSTRUTIVA",OFFSET(B16,-1,0)+1,OFFSET(B16,-1,0))) -> 1 | C16: =IF(H16="CÉLULA CONSTRUTIVA",0,IF(H16="ETAPA",OFFSET(C16,-1,0)+1,OFFSET(C16,-1,0))) -> 1 | D16: =IF(H16="ETAPA",0,IF(H16="SUBETAPA",OFFSET(D16,-1,0)+1,OFFSET(D16,-1,0))) -> 2 | E16: =IF(H16="Subetapa",0,IF(H16="serviço",OFFSET(E16,-1,0)+1,OFFSET(E16,-1,0))) -> 3 | H16: SERVIÇO | I16: =IF(H16="Unidade Construtiva",TEXT(A16,"00"),IF(H16="Célula Construtiva",TEXT(B16,"00"),IF(H16="Etapa",CONCATENATE(TEXT(B16,"00"),".",TEXT(C16,"000")),IF(H16="Subetapa",CONCATENATE(TEXT(B16,"00"),".",TEXT(C16,"000"),".",TEXT(D16,"000")),IF(H16="Serviço",CONCATENATE(TEXT(B16,"00"),".",TEXT(C16,"000"),".",TEXT(D16,"000"),".",TEXT(E16,"000")),""))))) -> 01.001.002.003 | J16: Projeto de Estrutural/Fundações/ Elétrico/Hidro/PPCI/Gás | K16: vb | L16: 1 | M16: 170000 | N16: =IF(H16="Serviço",M16*L16,IF(H16="CÉLULA CONSTRUTIVA",SUMIFS($N$8:$N$418,$B$8:$B$418,B16,$H$8:$H$418,"Serviço"),IF(H16="ETAPA",SUMIFS($N$8:$N$418,$B$8:$B$418,B16,$C$8:$C$418,C16,$H$8:$H$418,"Serviço"),IF(H16="SUBETAPA",SUMIFS($N$8:$N$418,$B$8:$B$418,B16,$C$8:$C$418,C16,$D$8:$D$418,D16,$H$8:$H$418,"Serviço"),0)))) -> 170000 | O16: Valor informado em formulário | P16: Lançado ERP
A17: =IF($H17="UNIDADE CONSTRUTIVA",OFFSET(A17,-1,0)+1,LARGE(A$3:A16,1)) -> 0 | B17: =IF(H17="UNIDADE CONSTRUTIVA",0,IF(H17="CÉLULA CONSTRUTIVA",OFFSET(B17,-1,0)+1,OFFSET(B17,-1,0))) -> 1 | C17: =IF(H17="CÉLULA CONSTRUTIVA",0,IF(H17="ETAPA",OFFSET(C17,-1,0)+1,OFFSET(C17,-1,0))) -> 1 | D17: =IF(H17="ETAPA",0,IF(H17="SUBETAPA",OFFSET(D17,-1,0)+1,OFFSET(D17,-1,0))) -> 2 | E17: =IF(H17="Subetapa",0,IF(H17="serviço",OFFSET(E17,-1,0)+1,OFFSET(E17,-1,0))) -> 4 | H17: SERVIÇO | I17: =IF(H17="Unidade Construtiva",TEXT(A17,"00"),IF(H17="Célula Construtiva",TEXT(B17,"00"),IF(H17="Etapa",CONCATENATE(TEXT(B17,"00"),".",TEXT(C17,"000")),IF(H17="Subetapa",CONCATENATE(TEXT(B17,"00"),".",TEXT(C17,"000"),".",TEXT(D17,"000")),IF(H17="Serviço",CONCATENATE(TEXT(B17,"00"),".",TEXT(C17,"000"),".",TEXT(D17,"000"),".",TEXT(E17,"000")),""))))) -> 01.001.002.004 | J17: Projeto de Impermeabilização | K17: vb | L17: 1 | M17: 17221.491 | N17: =IF(H17="Serviço",M17*L17,IF(H17="CÉLULA CONSTRUTIVA",SUMIFS($N$8:$N$418,$B$8:$B$418,B17,$H$8:$H$418,"Serviço"),IF(H17="ETAPA",SUMIFS($N$8:$N$418,$B$8:$B$418,B17,$C$8:$C$418,C17,$H$8:$H$418,"Serviço"),IF(H17="SUBETAPA",SUMIFS($N$8:$N$418,$B$8:$B$418,B17,$C$8:$C$418,C17,$D$8:$D$418,D17,$H$8:$H$418,"Serviço"),0)))) -> 17221.491 | O17: Estimado com base em índices históricos | P17: Lançado ERP
A18: =IF($H18="UNIDADE CONSTRUTIVA",OFFSET(A18,-1,0)+1,LARGE(A$3:A17,1)) -> 0 | B18: =IF(H18="UNIDADE CONSTRUTIVA",0,IF(H18="CÉLULA CONSTRUTIVA",OFFSET(B18,-1,0)+1,OFFSET(B18,-1,0))) -> 1 | C18: =IF(H18="CÉLULA CONSTRUTIVA",0,IF(H18="ETAPA",OFFSET(C18,-1,0)+1,OFFSET(C18,-1,0))) -> 1 | D18: =IF(H18="ETAPA",0,IF(H18="SUBETAPA",OFFSET(D18,-1,0)+1,OFFSET(D18,-1,0))) -> 2 | E18: =IF(H18="Subetapa",0,IF(H18="serviço",OFFSET(E18,-1,0)+1,OFFSET(E18,-1,0))) -> 5 | H18: SERVIÇO | I18: =IF(H18="Unidade Construtiva",TEXT(A18,"00"),IF(H18="Célula Construtiva",TEXT(B18,"00"),IF(H18="Etapa",CONCATENATE(TEXT(B18,"00"),".",TEXT(C18,"000")),IF(H18="Subetapa",CONCATENATE(TEXT(B18,"00"),".",TEXT(C18,"000"),".",TEXT(D18,"000")),IF(H18="Serviço",CONCATENATE(TEXT(B18,"00"),".",TEXT(C18,"000"),".",TEXT(D18,"000"),".",TEXT(E18,"000")),""))))) -> 01.001.002.005 | J18: Projeto de segurança | K18: vb | L18: 1 | M18: 4998.6149 | N18: =IF(H18="Serviço",M18*L18,IF(H18="CÉLULA CONSTRUTIVA",SUMIFS($N$8:$N$418,$B$8:$B$418,B18,$H$8:$H$418,"Serviço"),IF(H18="ETAPA",SUMIFS($N$8:$N$418,$B$8:$B$418,B18,$C$8:$C$418,C18,$H$8:$H$418,"Serviço"),IF(H18="SUBETAPA",SUMIFS($N$8:$N$418,$B$8:$B$418,B18,$C$8:$C$418,C18,$D$8:$D$418,D18,$H$8:$H$418,"Serviço"),0)))) -> 4998.6149 | O18: Estimado com base em índices históricos | P18: Lançado ERP
A19: =IF($H19="UNIDADE CONSTRUTIVA",OFFSET(A19,-1,0)+1,LARGE(A$3:A18,1)) -> 0 | B19: =IF(H19="UNIDADE CONSTRUTIVA",0,IF(H19="CÉLULA CONSTRUTIVA",OFFSET(B19,-1,0)+1,OFFSET(B19,-1,0))) -> 1 | C19: =IF(H19="CÉLULA CONSTRUTIVA",0,IF(H19="ETAPA",OFFSET(C19,-1,0)+1,OFFSET(C19,-1,0))) -> 1 | D19: =IF(H19="ETAPA",0,IF(H19="SUBETAPA",OFFSET(D19,-1,0)+1,OFFSET(D19,-1,0))) -> 2 | E19: =IF(H19="Subetapa",0,IF(H19="serviço",OFFSET(E19,-1,0)+1,OFFSET(E19,-1,0))) -> 6 | H19: SERVIÇO | I19: =IF(H19="Unidade Construtiva",TEXT(A19,"00"),IF(H19="Célula Construtiva",TEXT(B19,"00"),IF(H19="Etapa",CONCATENATE(TEXT(B19,"00"),".",TEXT(C19,"000")),IF(H19="Subetapa",CONCATENATE(TEXT(B19,"00"),".",TEXT(C19,"000"),".",TEXT(D19,"000")),IF(H19="Serviço",CONCATENATE(TEXT(B19,"00"),".",TEXT(C19,"000"),".",TEXT(D19,"000"),".",TEXT(E19,"000")),""))))) -> 01.001.002.006 | J19: Projeto de climatização/exaustão | K19: vb | L19: 1 | M19: 29000 | N19: =IF(H19="Serviço",M19*L19,IF(H19="CÉLULA CONSTRUTIVA",SUMIFS($N$8:$N$418,$B$8:$B$418,B19,$H$8:$H$418,"Serviço"),IF(H19="ETAPA",SUMIFS($N$8:$N$418,$B$8:$B$418,B19,$C$8:$C$418,C19,$H$8:$H$418,"Serviço"),IF(H19="SUBETAPA",SUMIFS($N$8:$N$418,$B$8:$B$418,B19,$C$8:$C$418,C19,$D$8:$D$418,D19,$H$8:$H$418,"Serviço"),0)))) -> 29000 | O19: Valor informado em formulário | P19: Lançado ERP
A20: =IF($H20="UNIDADE CONSTRUTIVA",OFFSET(A20,-1,0)+1,LARGE(A$3:A19,1)) -> 0 | B20: =IF(H20="UNIDADE CONSTRUTIVA",0,IF(H20="CÉLULA CONSTRUTIVA",OFFSET(B20,-1,0)+1,OFFSET(B20,-1,0))) -> 1 | C20: =IF(H20="CÉLULA CONSTRUTIVA",0,IF(H20="ETAPA",OFFSET(C20,-1,0)+1,OFFSET(C20,-1,0))) -> 1 | D20: =IF(H20="ETAPA",0,IF(H20="SUBETAPA",OFFSET(D20,-1,0)+1,OFFSET(D20,-1,0))) -> 2 | E20: =IF(H20="Subetapa",0,IF(H20="serviço",OFFSET(E20,-1,0)+1,OFFSET(E20,-1,0))) -> 7 | H20: SERVIÇO | I20: =IF(H20="Unidade Construtiva",TEXT(A20,"00"),IF(H20="Célula Construtiva",TEXT(B20,"00"),IF(H20="Etapa",CONCATENATE(TEXT(B20,"00"),".",TEXT(C20,"000")),IF(H20="Subetapa",CONCATENATE(TEXT(B20,"00"),".",TEXT(C20,"000"),".",TEXT(D20,"000")),IF(H20="Serviço",CONCATENATE(TEXT(B20,"00"),".",TEXT(C20,"000"),".",TEXT(D20,"000"),".",TEXT(E20,"000")),""))))) -> 01.001.002.007 | J20: Projeto de irrigação | K20: vb | L20: 1 | M20: 5447.1484 | N20: =IF(H20="Serviço",M20*L20,IF(H20="CÉLULA CONSTRUTIVA",SUMIFS($N$8:$N$418,$B$8:$B$418,B20,$H$8:$H$418,"Serviço"),IF(H20="ETAPA",SUMIFS($N$8:$N$418,$B$8:$B$418,B20,$C$8:$C$418,C20,$H$8:$H$418,"Serviço"),IF(H20="SUBETAPA",SUMIFS($N$8:$N$418,$B$8:$B$418,B20,$C$8:$C$418,C20,$D$8:$D$418,D20,$H$8:$H$418,"Serviço"),0)))) -> 5447.1484 | O20: Estimado com base em índices históricos | P20: Lançado ERP
A21: =IF($H21="UNIDADE CONSTRUTIVA",OFFSET(A21,-1,0)+1,LARGE(A$3:A20,1)) -> 0 | B21: =IF(H21="UNIDADE CONSTRUTIVA",0,IF(H21="CÉLULA CONSTRUTIVA",OFFSET(B21,-1,0)+1,OFFSET(B21,-1,0))) -> 1 | C21: =IF(H21="CÉLULA CONSTRUTIVA",0,IF(H21="ETAPA",OFFSET(C21,-1,0)+1,OFFSET(C21,-1,0))) -> 1 | D21: =IF(H21="ETAPA",0,IF(H21="SUBETAPA",OFFSET(D21,-1,0)+1,OFFSET(D21,-1,0))) -> 2 | E21: =IF(H21="Subetapa",0,IF(H21="serviço",OFFSET(E21,-1,0)+1,OFFSET(E21,-1,0))) -> 8 | H21: SERVIÇO | I21: =IF(H21="Unidade Construtiva",TEXT(A21,"00"),IF(H21="Célula Construtiva",TEXT(B21,"00"),IF(H21="Etapa",CONCATENATE(TEXT(B21,"00"),".",TEXT(C21,"000")),IF(H21="Subetapa",CONCATENATE(TEXT(B21,"00"),".",TEXT(C21,"000"),".",TEXT(D21,"000")),IF(H21="Serviço",CONCATENATE(TEXT(B21,"00"),".",TEXT(C21,"000"),".",TEXT(D21,"000"),".",TEXT(E21,"000")),""))))) -> 01.001.002.008 | J21: Projeto de furações | K21: vb | L21: 1 | M21: 34500 | N21: =IF(H21="Serviço",M21*L21,IF(H21="CÉLULA CONSTRUTIVA",SUMIFS($N$8:$N$418,$B$8:$B$418,B21,$H$8:$H$418,"Serviço"),IF(H21="ETAPA",SUMIFS($N$8:$N$418,$B$8:$B$418,B21,$C$8:$C$418,C21,$H$8:$H$418,"Serviço"),IF(H21="SUBETAPA",SUMIFS($N$8:$N$418,$B$8:$B$418,B21,$C$8:$C$418,C21,$D$8:$D$418,D21,$H$8:$H$418,"Serviço"),0)))) -> 34500 | O21: Valor informado em formulário | P21: Lançado ERP
A22: =IF($H22="UNIDADE CONSTRUTIVA",OFFSET(A22,-1,0)+1,LARGE(A$3:A21,1)) -> 0 | B22: =IF(H22="UNIDADE CONSTRUTIVA",0,IF(H22="CÉLULA CONSTRUTIVA",OFFSET(B22,-1,0)+1,OFFSET(B22,-1,0))) -> 1 | C22: =IF(H22="CÉLULA CONSTRUTIVA",0,IF(H22="ETAPA",OFFSET(C22,-1,0)+1,OFFSET(C22,-1,0))) -> 1 | D22: =IF(H22="ETAPA",0,IF(H22="SUBETAPA",OFFSET(D22,-1,0)+1,OFFSET(D22,-1,0))) -> 2 | E22: =IF(H22="Subetapa",0,IF(H22="serviço",OFFSET(E22,-1,0)+1,OFFSET(E22,-1,0))) -> 9 | H22: SERVIÇO | I22: =IF(H22="Unidade Construtiva",TEXT(A22,"00"),IF(H22="Célula Construtiva",TEXT(B22,"00"),IF(H22="Etapa",CONCATENATE(TEXT(B22,"00"),".",TEXT(C22,"000")),IF(H22="Subetapa",CONCATENATE(TEXT(B22,"00"),".",TEXT(C22,"000"),".",TEXT(D22,"000")),IF(H22="Serviço",CONCATENATE(TEXT(B22,"00"),".",TEXT(C22,"000"),".",TEXT(D22,"000"),".",TEXT(E22,"000")),""))))) -> 01.001.002.009 | J22: Projeto de Piscina | K22: vb | L22: 1 | M22: 5703.7202 | N22: =IF(H22="Serviço",M22*L22,IF(H22="CÉLULA CONSTRUTIVA",SUMIFS($N$8:$N$418,$B$8:$B$418,B22,$H$8:$H$418,"Serviço"),IF(H22="ETAPA",SUMIFS($N$8:$N$418,$B$8:$B$418,B22,$C$8:$C$418,C22,$H$8:$H$418,"Serviço"),IF(H22="SUBETAPA",SUMIFS($N$8:$N$418,$B$8:$B$418,B22,$C$8:$C$418,C22,$D$8:$D$418,D22,$H$8:$H$418,"Serviço"),0)))) -> 5703.7202 | O22: Estimado com base em índices históricos | P22: Lançado ERP
A23: =IF($H23="UNIDADE CONSTRUTIVA",OFFSET(A23,-1,0)+1,LARGE(A$3:A22,1)) -> 0 | B23: =IF(H23="UNIDADE CONSTRUTIVA",0,IF(H23="CÉLULA CONSTRUTIVA",OFFSET(B23,-1,0)+1,OFFSET(B23,-1,0))) -> 1 | C23: =IF(H23="CÉLULA CONSTRUTIVA",0,IF(H23="ETAPA",OFFSET(C23,-1,0)+1,OFFSET(C23,-1,0))) -> 1 | D23: =IF(H23="ETAPA",0,IF(H23="SUBETAPA",OFFSET(D23,-1,0)+1,OFFSET(D23,-1,0))) -> 2 | E23: =IF(H23="Subetapa",0,IF(H23="serviço",OFFSET(E23,-1,0)+1,OFFSET(E23,-1,0))) -> 10 | H23: SERVIÇO | I23: =IF(H23="Unidade Construtiva",TEXT(A23,"00"),IF(H23="Célula Construtiva",TEXT(B23,"00"),IF(H23="Etapa",CONCATENATE(TEXT(B23,"00"),".",TEXT(C23,"000")),IF(H23="Subetapa",CONCATENATE(TEXT(B23,"00"),".",TEXT(C23,"000"),".",TEXT(D23,"000")),IF(H23="Serviço",CONCATENATE(TEXT(B23,"00"),".",TEXT(C23,"000"),".",TEXT(D23,"000"),".",TEXT(E23,"000")),""))))) -> 01.001.002.010 | J23: Projeto de Paisagismo | K23: vb | L23: 1 | M23: 18017.931 | N23: =IF(H23="Serviço",M23*L23,IF(H23="CÉLULA CONSTRUTIVA",SUMIFS($N$8:$N$418,$B$8:$B$418,B23,$H$8:$H$418,"Serviço"),IF(H23="ETAPA",SUMIFS($N$8:$N$418,$B$8:$B$418,B23,$C$8:$C$418,C23,$H$8:$H$418,"Serviço"),IF(H23="SUBETAPA",SUMIFS($N$8:$N$418,$B$8:$B$418,B23,$C$8:$C$418,C23,$D$8:$D$418,D23,$H$8:$H$418,"Serviço"),0)))) -> 18017.931 | O23: Estimado com base em índices históricos | P23: Lançado ERP
A24: =IF($H24="UNIDADE CONSTRUTIVA",OFFSET(A24,-1,0)+1,LARGE(A$3:A23,1)) -> 0 | B24: =IF(H24="UNIDADE CONSTRUTIVA",0,IF(H24="CÉLULA CONSTRUTIVA",OFFSET(B24,-1,0)+1,OFFSET(B24,-1,0))) -> 1 | C24: =IF(H24="CÉLULA CONSTRUTIVA",0,IF(H24="ETAPA",OFFSET(C24,-1,0)+1,OFFSET(C24,-1,0))) -> 1 | D24: =IF(H24="ETAPA",0,IF(H24="SUBETAPA",OFFSET(D24,-1,0)+1,OFFSET(D24,-1,0))) -> 3 | E24: =IF(H24="Subetapa",0,IF(H24="serviço",OFFSET(E24,-1,0)+1,OFFSET(E24,-1,0))) -> 0 | H24: SUBETAPA | I24: =IF(H24="Unidade Construtiva",TEXT(A24,"00"),IF(H24="Célula Construtiva",TEXT(B24,"00"),IF(H24="Etapa",CONCATENATE(TEXT(B24,"00"),".",TEXT(C24,"000")),IF(H24="Subetapa",CONCATENATE(TEXT(B24,"00"),".",TEXT(C24,"000"),".",TEXT(D24,"000")),IF(H24="Serviço",CONCATENATE(TEXT(B24,"00"),".",TEXT(C24,"000"),".",TEXT(D24,"000"),".",TEXT(E24,"000")),""))))) -> 01.001.003 | J24: Consultorias | N24: =IF(H24="Serviço",M24*L24,IF(H24="CÉLULA CONSTRUTIVA",SUMIFS($N$8:$N$418,$B$8:$B$418,B24,$H$8:$H$418,"Serviço"),IF(H24="ETAPA",SUMIFS($N$8:$N$418,$B$8:$B$418,B24,$C$8:$C$418,C24,$H$8:$H$418,"Serviço"),IF(H24="SUBETAPA",SUMIFS($N$8:$N$418,$B$8:$B$418,B24,$C$8:$C$418,C24,$D$8:$D$418,D24,$H$8:$H$418,"Serviço"),0)))) -> 141604.91
A25: =IF($H25="UNIDADE CONSTRUTIVA",OFFSET(A25,-1,0)+1,LARGE(A$3:A24,1)) -> 0 | B25: =IF(H25="UNIDADE CONSTRUTIVA",0,IF(H25="CÉLULA CONSTRUTIVA",OFFSET(B25,-1,0)+1,OFFSET(B25,-1,0))) -> 1 | C25: =IF(H25="CÉLULA CONSTRUTIVA",0,IF(H25="ETAPA",OFFSET(C25,-1,0)+1,OFFSET(C25,-1,0))) -> 1 | D25: =IF(H25="ETAPA",0,IF(H25="SUBETAPA",OFFSET(D25,-1,0)+1,OFFSET(D25,-1,0))) -> 3 | E25: =IF(H25="Subetapa",0,IF(H25="serviço",OFFSET(E25,-1,0)+1,OFFSET(E25,-1,0))) -> 1 | H25: SERVIÇO | I25: =IF(H25="Unidade Construtiva",TEXT(A25,"00"),IF(H25="Célula Construtiva",TEXT(B25,"00"),IF(H25="Etapa",CONCATENATE(TEXT(B25,"00"),".",TEXT(C25,"000")),IF(H25="Subetapa",CONCATENATE(TEXT(B25,"00"),".",TEXT(C25,"000"),".",TEXT(D25,"000")),IF(H25="Serviço",CONCATENATE(TEXT(B25,"00"),".",TEXT(C25,"000"),".",TEXT(D25,"000"),".",TEXT(E25,"000")),""))))) -> 01.001.003.001 | J25: Compatibilização de Projetos BIM | K25: vb | L25: 1 | M25: 68700 | N25: =IF(H25="Serviço",M25*L25,IF(H25="CÉLULA CONSTRUTIVA",SUMIFS($N$8:$N$418,$B$8:$B$418,B25,$H$8:$H$418,"Serviço"),IF(H25="ETAPA",SUMIFS($N$8:$N$418,$B$8:$B$418,B25,$C$8:$C$418,C25,$H$8:$H$418,"Serviço"),IF(H25="SUBETAPA",SUMIFS($N$8:$N$418,$B$8:$B$418,B25,$C$8:$C$418,C25,$D$8:$D$418,D25,$H$8:$H$418,"Serviço"),0)))) -> 68700 | O25: Valor informado em formulário | P25: Lançado ERP
A26: =IF($H26="UNIDADE CONSTRUTIVA",OFFSET(A26,-1,0)+1,LARGE(A$3:A25,1)) -> 0 | B26: =IF(H26="UNIDADE CONSTRUTIVA",0,IF(H26="CÉLULA CONSTRUTIVA",OFFSET(B26,-1,0)+1,OFFSET(B26,-1,0))) -> 1 | C26: =IF(H26="CÉLULA CONSTRUTIVA",0,IF(H26="ETAPA",OFFSET(C26,-1,0)+1,OFFSET(C26,-1,0))) -> 1 | D26: =IF(H26="ETAPA",0,IF(H26="SUBETAPA",OFFSET(D26,-1,0)+1,OFFSET(D26,-1,0))) -> 3 | E26: =IF(H26="Subetapa",0,IF(H26="serviço",OFFSET(E26,-1,0)+1,OFFSET(E26,-1,0))) -> 2 | H26: SERVIÇO | I26: =IF(H26="Unidade Construtiva",TEXT(A26,"00"),IF(H26="Célula Construtiva",TEXT(B26,"00"),IF(H26="Etapa",CONCATENATE(TEXT(B26,"00"),".",TEXT(C26,"000")),IF(H26="Subetapa",CONCATENATE(TEXT(B26,"00"),".",TEXT(C26,"000"),".",TEXT(D26,"000")),IF(H26="Serviço",CONCATENATE(TEXT(B26,"00"),".",TEXT(C26,"000"),".",TEXT(D26,"000"),".",TEXT(E26,"000")),""))))) -> 01.001.003.002 | J26: Orçamento e planejamento | K26: vb | L26: 1 | M26: 43209.164 | N26: =IF(H26="Serviço",M26*L26,IF(H26="CÉLULA CONSTRUTIVA",SUMIFS($N$8:$N$418,$B$8:$B$418,B26,$H$8:$H$418,"Serviço"),IF(H26="ETAPA",SUMIFS($N$8:$N$418,$B$8:$B$418,B26,$C$8:$C$418,C26,$H$8:$H$418,"Serviço"),IF(H26="SUBETAPA",SUMIFS($N$8:$N$418,$B$8:$B$418,B26,$C$8:$C$418,C26,$D$8:$D$418,D26,$H$8:$H$418,"Serviço"),0)))) -> 43209.164 | O26: Valor informado em formulário | P26: Lançado ERP
A27: =IF($H27="UNIDADE CONSTRUTIVA",OFFSET(A27,-1,0)+1,LARGE(A$3:A26,1)) -> 0 | B27: =IF(H27="UNIDADE CONSTRUTIVA",0,IF(H27="CÉLULA CONSTRUTIVA",OFFSET(B27,-1,0)+1,OFFSET(B27,-1,0))) -> 1 | C27: =IF(H27="CÉLULA CONSTRUTIVA",0,IF(H27="ETAPA",OFFSET(C27,-1,0)+1,OFFSET(C27,-1,0))) -> 1 | D27: =IF(H27="ETAPA",0,IF(H27="SUBETAPA",OFFSET(D27,-1,0)+1,OFFSET(D27,-1,0))) -> 3 | E27: =IF(H27="Subetapa",0,IF(H27="serviço",OFFSET(E27,-1,0)+1,OFFSET(E27,-1,0))) -> 3 | H27: SERVIÇO | I27: =IF(H27="Unidade Construtiva",TEXT(A27,"00"),IF(H27="Célula Construtiva",TEXT(B27,"00"),IF(H27="Etapa",CONCATENATE(TEXT(B27,"00"),".",TEXT(C27,"000")),IF(H27="Subetapa",CONCATENATE(TEXT(B27,"00"),".",TEXT(C27,"000"),".",TEXT(D27,"000")),IF(H27="Serviço",CONCATENATE(TEXT(B27,"00"),".",TEXT(C27,"000"),".",TEXT(D27,"000"),".",TEXT(E27,"000")),""))))) -> 01.001.003.003 | J27: Consultoria técnica de fachada | K27: vb | L27: 1 | M27: 29695.746 | N27: =IF(H27="Serviço",M27*L27,IF(H27="CÉLULA CONSTRUTIVA",SUMIFS($N$8:$N$418,$B$8:$B$418,B27,$H$8:$H$418,"Serviço"),IF(H27="ETAPA",SUMIFS($N$8:$N$418,$B$8:$B$418,B27,$C$8:$C$418,C27,$H$8:$H$418,"Serviço"),IF(H27="SUBETAPA",SUMIFS($N$8:$N$418,$B$8:$B$418,B27,$C$8:$C$418,C27,$D$8:$D$418,D27,$H$8:$H$418,"Serviço"),0)))) -> 29695.746 | O27: Estimado com base em índices históricos | P27: Lançado ERP
A28: =IF($H28="UNIDADE CONSTRUTIVA",OFFSET(A28,-1,0)+1,LARGE(A$3:A27,1)) -> 0 | B28: =IF(H28="UNIDADE CONSTRUTIVA",0,IF(H28="CÉLULA CONSTRUTIVA",OFFSET(B28,-1,0)+1,OFFSET(B28,-1,0))) -> 1 | C28: =IF(H28="CÉLULA CONSTRUTIVA",0,IF(H28="ETAPA",OFFSET(C28,-1,0)+1,OFFSET(C28,-1,0))) -> 1 | D28: =IF(H28="ETAPA",0,IF(H28="SUBETAPA",OFFSET(D28,-1,0)+1,OFFSET(D28,-1,0))) -> 4 | E28: =IF(H28="Subetapa",0,IF(H28="serviço",OFFSET(E28,-1,0)+1,OFFSET(E28,-1,0))) -> 0 | H28: SUBETAPA | I28: =IF(H28="Unidade Construtiva",TEXT(A28,"00"),IF(H28="Célula Construtiva",TEXT(B28,"00"),IF(H28="Etapa",CONCATENATE(TEXT(B28,"00"),".",TEXT(C28,"000")),IF(H28="Subetapa",CONCATENATE(TEXT(B28,"00"),".",TEXT(C28,"000"),".",TEXT(D28,"000")),IF(H28="Serviço",CONCATENATE(TEXT(B28,"00"),".",TEXT(C28,"000"),".",TEXT(D28,"000"),".",TEXT(E28,"000")),""))))) -> 01.001.004 | J28: Ensaios | N28: =IF(H28="Serviço",M28*L28,IF(H28="CÉLULA CONSTRUTIVA",SUMIFS($N$8:$N$418,$B$8:$B$418,B28,$H$8:$H$418,"Serviço"),IF(H28="ETAPA",SUMIFS($N$8:$N$418,$B$8:$B$418,B28,$C$8:$C$418,C28,$H$8:$H$418,"Serviço"),IF(H28="SUBETAPA",SUMIFS($N$8:$N$418,$B$8:$B$418,B28,$C$8:$C$418,C28,$D$8:$D$418,D28,$H$8:$H$418,"Serviço"),0)))) -> 50442.444
A29: =IF($H29="UNIDADE CONSTRUTIVA",OFFSET(A29,-1,0)+1,LARGE(A$3:A28,1)) -> 0 | B29: =IF(H29="UNIDADE CONSTRUTIVA",0,IF(H29="CÉLULA CONSTRUTIVA",OFFSET(B29,-1,0)+1,OFFSET(B29,-1,0))) -> 1 | C29: =IF(H29="CÉLULA CONSTRUTIVA",0,IF(H29="ETAPA",OFFSET(C29,-1,0)+1,OFFSET(C29,-1,0))) -> 1 | D29: =IF(H29="ETAPA",0,IF(H29="SUBETAPA",OFFSET(D29,-1,0)+1,OFFSET(D29,-1,0))) -> 4 | E29: =IF(H29="Subetapa",0,IF(H29="serviço",OFFSET(E29,-1,0)+1,OFFSET(E29,-1,0))) -> 1 | H29: SERVIÇO | I29: =IF(H29="Unidade Construtiva",TEXT(A29,"00"),IF(H29="Célula Construtiva",TEXT(B29,"00"),IF(H29="Etapa",CONCATENATE(TEXT(B29,"00"),".",TEXT(C29,"000")),IF(H29="Subetapa",CONCATENATE(TEXT(B29,"00"),".",TEXT(C29,"000"),".",TEXT(D29,"000")),IF(H29="Serviço",CONCATENATE(TEXT(B29,"00"),".",TEXT(C29,"000"),".",TEXT(D29,"000"),".",TEXT(E29,"000")),""))))) -> 01.001.004.001 | J29: Controle Tecnologico de Concreto | K29: vb | L29: 1 | M29: ='Ensaios '!F6 -> 39640 | N29: =IF(H29="Serviço",M29*L29,IF(H29="CÉLULA CONSTRUTIVA",SUMIFS($N$8:$N$418,$B$8:$B$418,B29,$H$8:$H$418,"Serviço"),IF(H29="ETAPA",SUMIFS($N$8:$N$418,$B$8:$B$418,B29,$C$8:$C$418,C29,$H$8:$H$418,"Serviço"),IF(H29="SUBETAPA",SUMIFS($N$8:$N$418,$B$8:$B$418,B29,$C$8:$C$418,C29,$D$8:$D$418,D29,$H$8:$H$418,"Serviço"),0)))) -> 39640 | O29: Estimado com base em índices históricos | P29: Lançado ERP
A30: =IF($H30="UNIDADE CONSTRUTIVA",OFFSET(A30,-1,0)+1,LARGE(A$3:A29,1)) -> 0 | B30: =IF(H30="UNIDADE CONSTRUTIVA",0,IF(H30="CÉLULA CONSTRUTIVA",OFFSET(B30,-1,0)+1,OFFSET(B30,-1,0))) -> 1 | C30: =IF(H30="CÉLULA CONSTRUTIVA",0,IF(H30="ETAPA",OFFSET(C30,-1,0)+1,OFFSET(C30,-1,0))) -> 1 | D30: =IF(H30="ETAPA",0,IF(H30="SUBETAPA",OFFSET(D30,-1,0)+1,OFFSET(D30,-1,0))) -> 4 | E30: =IF(H30="Subetapa",0,IF(H30="serviço",OFFSET(E30,-1,0)+1,OFFSET(E30,-1,0))) -> 2 | H30: SERVIÇO | I30: =IF(H30="Unidade Construtiva",TEXT(A30,"00"),IF(H30="Célula Construtiva",TEXT(B30,"00"),IF(H30="Etapa",CONCATENATE(TEXT(B30,"00"),".",TEXT(C30,"000")),IF(H30="Subetapa",CONCATENATE(TEXT(B30,"00"),".",TEXT(C30,"000"),".",TEXT(D30,"000")),IF(H30="Serviço",CONCATENATE(TEXT(B30,"00"),".",TEXT(C30,"000"),".",TEXT(D30,"000"),".",TEXT(E30,"000")),""))))) -> 01.001.004.002 | J30: Ensaio de argamassa | K30: vb | L30: 1 | M30: 1728 | N30: =IF(H30="Serviço",M30*L30,IF(H30="CÉLULA CONSTRUTIVA",SUMIFS($N$8:$N$418,$B$8:$B$418,B30,$H$8:$H$418,"Serviço"),IF(H30="ETAPA",SUMIFS($N$8:$N$418,$B$8:$B$418,B30,$C$8:$C$418,C30,$H$8:$H$418,"Serviço"),IF(H30="SUBETAPA",SUMIFS($N$8:$N$418,$B$8:$B$418,B30,$C$8:$C$418,C30,$D$8:$D$418,D30,$H$8:$H$418,"Serviço"),0)))) -> 1728 | O30: Estimado com base em índices históricos | P30: Lançado ERP
A31: =IF($H31="UNIDADE CONSTRUTIVA",OFFSET(A31,-1,0)+1,LARGE(A$3:A30,1)) -> 0 | B31: =IF(H31="UNIDADE CONSTRUTIVA",0,IF(H31="CÉLULA CONSTRUTIVA",OFFSET(B31,-1,0)+1,OFFSET(B31,-1,0))) -> 1 | C31: =IF(H31="CÉLULA CONSTRUTIVA",0,IF(H31="ETAPA",OFFSET(C31,-1,0)+1,OFFSET(C31,-1,0))) -> 1 | D31: =IF(H31="ETAPA",0,IF(H31="SUBETAPA",OFFSET(D31,-1,0)+1,OFFSET(D31,-1,0))) -> 4 | E31: =IF(H31="Subetapa",0,IF(H31="serviço",OFFSET(E31,-1,0)+1,OFFSET(E31,-1,0))) -> 3 | H31: SERVIÇO | I31: =IF(H31="Unidade Construtiva",TEXT(A31,"00"),IF(H31="Célula Construtiva",TEXT(B31,"00"),IF(H31="Etapa",CONCATENATE(TEXT(B31,"00"),".",TEXT(C31,"000")),IF(H31="Subetapa",CONCATENATE(TEXT(B31,"00"),".",TEXT(C31,"000"),".",TEXT(D31,"000")),IF(H31="Serviço",CONCATENATE(TEXT(B31,"00"),".",TEXT(C31,"000"),".",TEXT(D31,"000"),".",TEXT(E31,"000")),""))))) -> 01.001.004.003 | J31: Ensaio de guarda-corpo | K31: vb | L31: 1 | M31: 4210 | N31: =IF(H31="Serviço",M31*L31,IF(H31="CÉLULA CONSTRUTIVA",SUMIFS($N$8:$N$418,$B$8:$B$418,B31,$H$8:$H$418,"Serviço"),IF(H31="ETAPA",SUMIFS($N$8:$N$418,$B$8:$B$418,B31,$C$8:$C$418,C31,$H$8:$H$418,"Serviço"),IF(H31="SUBETAPA",SUMIFS($N$8:$N$418,$B$8:$B$418,B31,$C$8:$C$418,C31,$D$8:$D$418,D31,$H$8:$H$418,"Serviço"),0)))) -> 4210 | O31: Estimado com base em índices históricos | P31: Lançado ERP
A32: =IF($H32="UNIDADE CONSTRUTIVA",OFFSET(A32,-1,0)+1,LARGE(A$3:A31,1)) -> 0 | B32: =IF(H32="UNIDADE CONSTRUTIVA",0,IF(H32="CÉLULA CONSTRUTIVA",OFFSET(B32,-1,0)+1,OFFSET(B32,-1,0))) -> 1 | C32: =IF(H32="CÉLULA CONSTRUTIVA",0,IF(H32="ETAPA",OFFSET(C32,-1,0)+1,OFFSET(C32,-1,0))) -> 1 | D32: =IF(H32="ETAPA",0,IF(H32="SUBETAPA",OFFSET(D32,-1,0)+1,OFFSET(D32,-1,0))) -> 4 | E32: =IF(H32="Subetapa",0,IF(H32="serviço",OFFSET(E32,-1,0)+1,OFFSET(E32,-1,0))) -> 4 | H32: SERVIÇO | I32: =IF(H32="Unidade Construtiva",TEXT(A32,"00"),IF(H32="Célula Construtiva",TEXT(B32,"00"),IF(H32="Etapa",CONCATENATE(TEXT(B32,"00"),".",TEXT(C32,"000")),IF(H32="Subetapa",CONCATENATE(TEXT(B32,"00"),".",TEXT(C32,"000"),".",TEXT(D32,"000")),IF(H32="Serviço",CONCATENATE(TEXT(B32,"00"),".",TEXT(C32,"000"),".",TEXT(D32,"000"),".",TEXT(E32,"000")),""))))) -> 01.001.004.004 | J32: Ensaio de arrancamento de reboco | K32: vb | L32: 1 | M32: 1260 | N32: =IF(H32="Serviço",M32*L32,IF(H32="CÉLULA CONSTRUTIVA",SUMIFS($N$8:$N$418,$B$8:$B$418,B32,$H$8:$H$418,"Serviço"),IF(H32="ETAPA",SUMIFS($N$8:$N$418,$B$8:$B$418,B32,$C$8:$C$418,C32,$H$8:$H$418,"Serviço"),IF(H32="SUBETAPA",SUMIFS($N$8:$N$418,$B$8:$B$418,B32,$C$8:$C$418,C32,$D$8:$D$418,D32,$H$8:$H$418,"Serviço"),0)))) -> 1260 | O32: Estimado com base em índices históricos | P32: Lançado ERP
A33: =IF($H33="UNIDADE CONSTRUTIVA",OFFSET(A33,-1,0)+1,LARGE(A$3:A32,1)) -> 0 | B33: =IF(H33="UNIDADE CONSTRUTIVA",0,IF(H33="CÉLULA CONSTRUTIVA",OFFSET(B33,-1,0)+1,OFFSET(B33,-1,0))) -> 1 | C33: =IF(H33="CÉLULA CONSTRUTIVA",0,IF(H33="ETAPA",OFFSET(C33,-1,0)+1,OFFSET(C33,-1,0))) -> 1 | D33: =IF(H33="ETAPA",0,IF(H33="SUBETAPA",OFFSET(D33,-1,0)+1,OFFSET(D33,-1,0))) -> 4 | E33: =IF(H33="Subetapa",0,IF(H33="serviço",OFFSET(E33,-1,0)+1,OFFSET(E33,-1,0))) -> 5 | H33: SERVIÇO | I33: =IF(H33="Unidade Construtiva",TEXT(A33,"00"),IF(H33="Célula Construtiva",TEXT(B33,"00"),IF(H33="Etapa",CONCATENATE(TEXT(B33,"00"),".",TEXT(C33,"000")),IF(H33="Subetapa",CONCATENATE(TEXT(B33,"00"),".",TEXT(C33,"000"),".",TEXT(D33,"000")),IF(H33="Serviço",CONCATENATE(TEXT(B33,"00"),".",TEXT(C33,"000"),".",TEXT(D33,"000"),".",TEXT(E33,"000")),""))))) -> 01.001.004.005 | J33: Ensaio de arrancamento revestimento cerâmico | K33: vb | L33: 1 | M33: 664.44444 | N33: =IF(H33="Serviço",M33*L33,IF(H33="CÉLULA CONSTRUTIVA",SUMIFS($N$8:$N$418,$B$8:$B$418,B33,$H$8:$H$418,"Serviço"),IF(H33="ETAPA",SUMIFS($N$8:$N$418,$B$8:$B$418,B33,$C$8:$C$418,C33,$H$8:$H$418,"Serviço"),IF(H33="SUBETAPA",SUMIFS($N$8:$N$418,$B$8:$B$418,B33,$C$8:$C$418,C33,$D$8:$D$418,D33,$H$8:$H$418,"Serviço"),0)))) -> 664.44444 | O33: Estimado com base em índices históricos | P33: Lançado ERP
A34: =IF($H34="UNIDADE CONSTRUTIVA",OFFSET(A34,-1,0)+1,LARGE(A$3:A33,1)) -> 0 | B34: =IF(H34="UNIDADE CONSTRUTIVA",0,IF(H34="CÉLULA CONSTRUTIVA",OFFSET(B34,-1,0)+1,OFFSET(B34,-1,0))) -> 1 | C34: =IF(H34="CÉLULA CONSTRUTIVA",0,IF(H34="ETAPA",OFFSET(C34,-1,0)+1,OFFSET(C34,-1,0))) -> 1 | D34: =IF(H34="ETAPA",0,IF(H34="SUBETAPA",OFFSET(D34,-1,0)+1,OFFSET(D34,-1,0))) -> 4 | E34: =IF(H34="Subetapa",0,IF(H34="serviço",OFFSET(E34,-1,0)+1,OFFSET(E34,-1,0))) -> 6 | H34: SERVIÇO | I34: =IF(H34="Unidade Construtiva",TEXT(A34,"00"),IF(H34="Célula Construtiva",TEXT(B34,"00"),IF(H34="Etapa",CONCATENATE(TEXT(B34,"00"),".",TEXT(C34,"000")),IF(H34="Subetapa",CONCATENATE(TEXT(B34,"00"),".",TEXT(C34,"000"),".",TEXT(D34,"000")),IF(H34="Serviço",CONCATENATE(TEXT(B34,"00"),".",TEXT(C34,"000"),".",TEXT(D34,"000"),".",TEXT(E34,"000")),""))))) -> 01.001.004.006 | J34: Ensaio de arrancamento fachada | K34: vb | L34: 1 | M34: 1260 | N34: =IF(H34="Serviço",M34*L34,IF(H34="CÉLULA CONSTRUTIVA",SUMIFS($N$8:$N$418,$B$8:$B$418,B34,$H$8:$H$418,"Serviço"),IF(H34="ETAPA",SUMIFS($N$8:$N$418,$B$8:$B$418,B34,$C$8:$C$418,C34,$H$8:$H$418,"Serviço"),IF(H34="SUBETAPA",SUMIFS($N$8:$N$418,$B$8:$B$418,B34,$C$8:$C$418,C34,$D$8:$D$418,D34,$H$8:$H$418,"Serviço"),0)))) -> 1260 | O34: Estimado com base em índices históricos | P34: Lançado ERP
A35: =IF($H35="UNIDADE CONSTRUTIVA",OFFSET(A35,-1,0)+1,LARGE(A$3:A34,1)) -> 0 | B35: =IF(H35="UNIDADE CONSTRUTIVA",0,IF(H35="CÉLULA CONSTRUTIVA",OFFSET(B35,-1,0)+1,OFFSET(B35,-1,0))) -> 1 | C35: =IF(H35="CÉLULA CONSTRUTIVA",0,IF(H35="ETAPA",OFFSET(C35,-1,0)+1,OFFSET(C35,-1,0))) -> 1 | D35: =IF(H35="ETAPA",0,IF(H35="SUBETAPA",OFFSET(D35,-1,0)+1,OFFSET(D35,-1,0))) -> 4 | E35: =IF(H35="Subetapa",0,IF(H35="serviço",OFFSET(E35,-1,0)+1,OFFSET(E35,-1,0))) -> 7 | H35: SERVIÇO | I35: =IF(H35="Unidade Construtiva",TEXT(A35,"00"),IF(H35="Célula Construtiva",TEXT(B35,"00"),IF(H35="Etapa",CONCATENATE(TEXT(B35,"00"),".",TEXT(C35,"000")),IF(H35="Subetapa",CONCATENATE(TEXT(B35,"00"),".",TEXT(C35,"000"),".",TEXT(D35,"000")),IF(H35="Serviço",CONCATENATE(TEXT(B35,"00"),".",TEXT(C35,"000"),".",TEXT(D35,"000"),".",TEXT(E35,"000")),""))))) -> 01.001.004.007 | J35: Ensaio de arrancamento de gancho da cobertura | K35: vb | L35: 1 | M35: 1680 | N35: =IF(H35="Serviço",M35*L35,IF(H35="CÉLULA CONSTRUTIVA",SUMIFS($N$8:$N$418,$B$8:$B$418,B35,$H$8:$H$418,"Serviço"),IF(H35="ETAPA",SUMIFS($N$8:$N$418,$B$8:$B$418,B35,$C$8:$C$418,C35,$H$8:$H$418,"Serviço"),IF(H35="SUBETAPA",SUMIFS($N$8:$N$418,$B$8:$B$418,B35,$C$8:$C$418,C35,$D$8:$D$418,D35,$H$8:$H$418,"Serviço"),0)))) -> 1680 | O35: Estimado com base em índices históricos | P35: Lançado ERP
A36: =IF($H36="UNIDADE CONSTRUTIVA",OFFSET(A36,-1,0)+1,LARGE(A$3:A35,1)) -> 0 | B36: =IF(H36="UNIDADE CONSTRUTIVA",0,IF(H36="CÉLULA CONSTRUTIVA",OFFSET(B36,-1,0)+1,OFFSET(B36,-1,0))) -> 1 | C36: =IF(H36="CÉLULA CONSTRUTIVA",0,IF(H36="ETAPA",OFFSET(C36,-1,0)+1,OFFSET(C36,-1,0))) -> 2 | D36: =IF(H36="ETAPA",0,IF(H36="SUBETAPA",OFFSET(D36,-1,0)+1,OFFSET(D36,-1,0))) -> 0 | E36: =IF(H36="Subetapa",0,IF(H36="serviço",OFFSET(E36,-1,0)+1,OFFSET(E36,-1,0))) -> 7 | H36: ETAPA | I36: =IF(H36="Unidade Construtiva",TEXT(A36,"00"),IF(H36="Célula Construtiva",TEXT(B36,"00"),IF(H36="Etapa",CONCATENATE(TEXT(B36,"00"),".",TEXT(C36,"000")),IF(H36="Subetapa",CONCATENATE(TEXT(B36,"00"),".",TEXT(C36,"000"),".",TEXT(D36,"000")),IF(H36="Serviço",CONCATENATE(TEXT(B36,"00"),".",TEXT(C36,"000"),".",TEXT(D36,"000"),".",TEXT(E36,"000")),""))))) -> 01.002 | J36: CONSUMOS, TAXAS E DOCUMENTOS | N36: =IF(H36="Serviço",M36*L36,IF(H36="CÉLULA CONSTRUTIVA",SUMIFS($N$8:$N$418,$B$8:$B$418,B36,$H$8:$H$418,"Serviço"),IF(H36="ETAPA",SUMIFS($N$8:$N$418,$B$8:$B$418,B36,$C$8:$C$418,C36,$H$8:$H$418,"Serviço"),IF(H36="SUBETAPA",SUMIFS($N$8:$N$418,$B$8:$B$418,B36,$C$8:$C$418,C36,$D$8:$D$418,D36,$H$8:$H$418,"Serviço"),0)))) -> 1673990.5 | P36: -
A37: =IF($H37="UNIDADE CONSTRUTIVA",OFFSET(A37,-1,0)+1,LARGE(A$3:A36,1)) -> 0 | B37: =IF(H37="UNIDADE CONSTRUTIVA",0,IF(H37="CÉLULA CONSTRUTIVA",OFFSET(B37,-1,0)+1,OFFSET(B37,-1,0))) -> 1 | C37: =IF(H37="CÉLULA CONSTRUTIVA",0,IF(H37="ETAPA",OFFSET(C37,-1,0)+1,OFFSET(C37,-1,0))) -> 2 | D37: =IF(H37="ETAPA",0,IF(H37="SUBETAPA",OFFSET(D37,-1,0)+1,OFFSET(D37,-1,0))) -> 1 | E37: =IF(H37="Subetapa",0,IF(H37="serviço",OFFSET(E37,-1,0)+1,OFFSET(E37,-1,0))) -> 0 | H37: SUBETAPA | I37: =IF(H37="Unidade Construtiva",TEXT(A37,"00"),IF(H37="Célula Construtiva",TEXT(B37,"00"),IF(H37="Etapa",CONCATENATE(TEXT(B37,"00"),".",TEXT(C37,"000")),IF(H37="Subetapa",CONCATENATE(TEXT(B37,"00"),".",TEXT(C37,"000"),".",TEXT(D37,"000")),IF(H37="Serviço",CONCATENATE(TEXT(B37,"00"),".",TEXT(C37,"000"),".",TEXT(D37,"000"),".",TEXT(E37,"000")),""))))) -> 01.002.001 | J37: Licenciamentos, Taxas, Impostos, Aprovações e Seguros | N37: =IF(H37="Serviço",M37*L37,IF(H37="CÉLULA CONSTRUTIVA",SUMIFS($N$8:$N$418,$B$8:$B$418,B37,$H$8:$H$418,"Serviço"),IF(H37="ETAPA",SUMIFS($N$8:$N$418,$B$8:$B$418,B37,$C$8:$C$418,C37,$H$8:$H$418,"Serviço"),IF(H37="SUBETAPA",SUMIFS($N$8:$N$418,$B$8:$B$418,B37,$C$8:$C$418,C37,$D$8:$D$418,D37,$H$8:$H$418,"Serviço"),0)))) -> 1645252.2
A38: =IF($H38="UNIDADE CONSTRUTIVA",OFFSET(A38,-1,0)+1,LARGE(A$3:A37,1)) -> 0 | B38: =IF(H38="UNIDADE CONSTRUTIVA",0,IF(H38="CÉLULA CONSTRUTIVA",OFFSET(B38,-1,0)+1,OFFSET(B38,-1,0))) -> 1 | C38: =IF(H38="CÉLULA CONSTRUTIVA",0,IF(H38="ETAPA",OFFSET(C38,-1,0)+1,OFFSET(C38,-1,0))) -> 2 | D38: =IF(H38="ETAPA",0,IF(H38="SUBETAPA",OFFSET(D38,-1,0)+1,OFFSET(D38,-1,0))) -> 1 | E38: =IF(H38="Subetapa",0,IF(H38="serviço",OFFSET(E38,-1,0)+1,OFFSET(E38,-1,0))) -> 1 | H38: SERVIÇO | I38: =IF(H38="Unidade Construtiva",TEXT(A38,"00"),IF(H38="Célula Construtiva",TEXT(B38,"00"),IF(H38="Etapa",CONCATENATE(TEXT(B38,"00"),".",TEXT(C38,"000")),IF(H38="Subetapa",CONCATENATE(TEXT(B38,"00"),".",TEXT(C38,"000"),".",TEXT(D38,"000")),IF(H38="Serviço",CONCATENATE(TEXT(B38,"00"),".",TEXT(C38,"000"),".",TEXT(D38,"000"),".",TEXT(E38,"000")),""))))) -> 01.002.001.001 | J38: Despesas de Seguros | K38: vb | L38: 1 | M38: 23000 | N38: =IF(H38="Serviço",M38*L38,IF(H38="CÉLULA CONSTRUTIVA",SUMIFS($N$8:$N$418,$B$8:$B$418,B38,$H$8:$H$418,"Serviço"),IF(H38="ETAPA",SUMIFS($N$8:$N$418,$B$8:$B$418,B38,$C$8:$C$418,C38,$H$8:$H$418,"Serviço"),IF(H38="SUBETAPA",SUMIFS($N$8:$N$418,$B$8:$B$418,B38,$C$8:$C$418,C38,$D$8:$D$418,D38,$H$8:$H$418,"Serviço"),0)))) -> 23000 | O38: Valor informado em formulário | P38: Lançado ERP
A39: =IF($H39="UNIDADE CONSTRUTIVA",OFFSET(A39,-1,0)+1,LARGE(A$3:A38,1)) -> 0 | B39: =IF(H39="UNIDADE CONSTRUTIVA",0,IF(H39="CÉLULA CONSTRUTIVA",OFFSET(B39,-1,0)+1,OFFSET(B39,-1,0))) -> 1 | C39: =IF(H39="CÉLULA CONSTRUTIVA",0,IF(H39="ETAPA",OFFSET(C39,-1,0)+1,OFFSET(C39,-1,0))) -> 2 | D39: =IF(H39="ETAPA",0,IF(H39="SUBETAPA",OFFSET(D39,-1,0)+1,OFFSET(D39,-1,0))) -> 1 | E39: =IF(H39="Subetapa",0,IF(H39="serviço",OFFSET(E39,-1,0)+1,OFFSET(E39,-1,0))) -> 2 | H39: SERVIÇO | I39: =IF(H39="Unidade Construtiva",TEXT(A39,"00"),IF(H39="Célula Construtiva",TEXT(B39,"00"),IF(H39="Etapa",CONCATENATE(TEXT(B39,"00"),".",TEXT(C39,"000")),IF(H39="Subetapa",CONCATENATE(TEXT(B39,"00"),".",TEXT(C39,"000"),".",TEXT(D39,"000")),IF(H39="Serviço",CONCATENATE(TEXT(B39,"00"),".",TEXT(C39,"000"),".",TEXT(D39,"000"),".",TEXT(E39,"000")),""))))) -> 01.002.001.002 | J39: Outorga, aprovação e demais taxas | K39: vb | L39: 1 | M39: 1500000 | N39: =IF(H39="Serviço",M39*L39,IF(H39="CÉLULA CONSTRUTIVA",SUMIFS($N$8:$N$418,$B$8:$B$418,B39,$H$8:$H$418,"Serviço"),IF(H39="ETAPA",SUMIFS($N$8:$N$418,$B$8:$B$418,B39,$C$8:$C$418,C39,$H$8:$H$418,"Serviço"),IF(H39="SUBETAPA",SUMIFS($N$8:$N$418,$B$8:$B$418,B39,$C$8:$C$418,C39,$D$8:$D$418,D39,$H$8:$H$418,"Serviço"),0)))) -> 1500000 | O39: Valor informado em formulário | P39: Lançado ERP
A40: =IF($H40="UNIDADE CONSTRUTIVA",OFFSET(A40,-1,0)+1,LARGE(A$3:A39,1)) -> 0 | B40: =IF(H40="UNIDADE CONSTRUTIVA",0,IF(H40="CÉLULA CONSTRUTIVA",OFFSET(B40,-1,0)+1,OFFSET(B40,-1,0))) -> 1 | C40: =IF(H40="CÉLULA CONSTRUTIVA",0,IF(H40="ETAPA",OFFSET(C40,-1,0)+1,OFFSET(C40,-1,0))) -> 2 | D40: =IF(H40="ETAPA",0,IF(H40="SUBETAPA",OFFSET(D40,-1,0)+1,OFFSET(D40,-1,0))) -> 1 | E40: =IF(H40="Subetapa",0,IF(H40="serviço",OFFSET(E40,-1,0)+1,OFFSET(E40,-1,0))) -> 3 | H40: SERVIÇO | I40: =IF(H40="Unidade Construtiva",TEXT(A40,"00"),IF(H40="Célula Construtiva",TEXT(B40,"00"),IF(H40="Etapa",CONCATENATE(TEXT(B40,"00"),".",TEXT(C40,"000")),IF(H40="Subetapa",CONCATENATE(TEXT(B40,"00"),".",TEXT(C40,"000"),".",TEXT(D40,"000")),IF(H40="Serviço",CONCATENATE(TEXT(B40,"00"),".",TEXT(C40,"000"),".",TEXT(D40,"000"),".",TEXT(E40,"000")),""))))) -> 01.002.001.003 | J40: Aprovação e legalização prefeitura | K40: vb | L40: 1 | M40: 20084.108 | N40: =IF(H40="Serviço",M40*L40,IF(H40="CÉLULA CONSTRUTIVA",SUMIFS($N$8:$N$418,$B$8:$B$418,B40,$H$8:$H$418,"Serviço"),IF(H40="ETAPA",SUMIFS($N$8:$N$418,$B$8:$B$418,B40,$C$8:$C$418,C40,$H$8:$H$418,"Serviço"),IF(H40="SUBETAPA",SUMIFS($N$8:$N$418,$B$8:$B$418,B40,$C$8:$C$418,C40,$D$8:$D$418,D40,$H$8:$H$418,"Serviço"),0)))) -> 20084.108 | O40: Estimado com base em índices históricos | P40: Lançado ERP
A41: =IF($H41="UNIDADE CONSTRUTIVA",OFFSET(A41,-1,0)+1,LARGE(A$3:A40,1)) -> 0 | B41: =IF(H41="UNIDADE CONSTRUTIVA",0,IF(H41="CÉLULA CONSTRUTIVA",OFFSET(B41,-1,0)+1,OFFSET(B41,-1,0))) -> 1 | C41: =IF(H41="CÉLULA CONSTRUTIVA",0,IF(H41="ETAPA",OFFSET(C41,-1,0)+1,OFFSET(C41,-1,0))) -> 2 | D41: =IF(H41="ETAPA",0,IF(H41="SUBETAPA",OFFSET(D41,-1,0)+1,OFFSET(D41,-1,0))) -> 1 | E41: =IF(H41="Subetapa",0,IF(H41="serviço",OFFSET(E41,-1,0)+1,OFFSET(E41,-1,0))) -> 4 | H41: SERVIÇO | I41: =IF(H41="Unidade Construtiva",TEXT(A41,"00"),IF(H41="Célula Construtiva",TEXT(B41,"00"),IF(H41="Etapa",CONCATENATE(TEXT(B41,"00"),".",TEXT(C41,"000")),IF(H41="Subetapa",CONCATENATE(TEXT(B41,"00"),".",TEXT(C41,"000"),".",TEXT(D41,"000")),IF(H41="Serviço",CONCATENATE(TEXT(B41,"00"),".",TEXT(C41,"000"),".",TEXT(D41,"000"),".",TEXT(E41,"000")),""))))) -> 01.002.001.004 | J41: Aprovação e legalização água e esgoto | K41: vb | L41: 1 | M41: 5080.9483 | N41: =IF(H41="Serviço",M41*L41,IF(H41="CÉLULA CONSTRUTIVA",SUMIFS($N$8:$N$418,$B$8:$B$418,B41,$H$8:$H$418,"Serviço"),IF(H41="ETAPA",SUMIFS($N$8:$N$418,$B$8:$B$418,B41,$C$8:$C$418,C41,$H$8:$H$418,"Serviço"),IF(H41="SUBETAPA",SUMIFS($N$8:$N$418,$B$8:$B$418,B41,$C$8:$C$418,C41,$D$8:$D$418,D41,$H$8:$H$418,"Serviço"),0)))) -> 5080.9483 | O41: Estimado com base em índices históricos | P41: Lançado ERP
A42: =IF($H42="UNIDADE CONSTRUTIVA",OFFSET(A42,-1,0)+1,LARGE(A$3:A41,1)) -> 0 | B42: =IF(H42="UNIDADE CONSTRUTIVA",0,IF(H42="CÉLULA CONSTRUTIVA",OFFSET(B42,-1,0)+1,OFFSET(B42,-1,0))) -> 1 | C42: =IF(H42="CÉLULA CONSTRUTIVA",0,IF(H42="ETAPA",OFFSET(C42,-1,0)+1,OFFSET(C42,-1,0))) -> 2 | D42: =IF(H42="ETAPA",0,IF(H42="SUBETAPA",OFFSET(D42,-1,0)+1,OFFSET(D42,-1,0))) -> 1 | E42: =IF(H42="Subetapa",0,IF(H42="serviço",OFFSET(E42,-1,0)+1,OFFSET(E42,-1,0))) -> 5 | H42: SERVIÇO | I42: =IF(H42="Unidade Construtiva",TEXT(A42,"00"),IF(H42="Célula Construtiva",TEXT(B42,"00"),IF(H42="Etapa",CONCATENATE(TEXT(B42,"00"),".",TEXT(C42,"000")),IF(H42="Subetapa",CONCATENATE(TEXT(B42,"00"),".",TEXT(C42,"000"),".",TEXT(D42,"000")),IF(H42="Serviço",CONCATENATE(TEXT(B42,"00"),".",TEXT(C42,"000"),".",TEXT(D42,"000"),".",TEXT(E42,"000")),""))))) -> 01.002.001.005 | J42: Aprovação e legalização elétrico | K42: vb | L42: 1 | M42: 8678.6051 | N42: =IF(H42="Serviço",M42*L42,IF(H42="CÉLULA CONSTRUTIVA",SUMIFS($N$8:$N$418,$B$8:$B$418,B42,$H$8:$H$418,"Serviço"),IF(H42="ETAPA",SUMIFS($N$8:$N$418,$B$8:$B$418,B42,$C$8:$C$418,C42,$H$8:$H$418,"Serviço"),IF(H42="SUBETAPA",SUMIFS($N$8:$N$418,$B$8:$B$418,B42,$C$8:$C$418,C42,$D$8:$D$418,D42,$H$8:$H$418,"Serviço"),0)))) -> 8678.6051 | O42: Estimado com base em índices históricos | P42: Lançado ERP
A43: =IF($H43="UNIDADE CONSTRUTIVA",OFFSET(A43,-1,0)+1,LARGE(A$3:A42,1)) -> 0 | B43: =IF(H43="UNIDADE CONSTRUTIVA",0,IF(H43="CÉLULA CONSTRUTIVA",OFFSET(B43,-1,0)+1,OFFSET(B43,-1,0))) -> 1 | C43: =IF(H43="CÉLULA CONSTRUTIVA",0,IF(H43="ETAPA",OFFSET(C43,-1,0)+1,OFFSET(C43,-1,0))) -> 2 | D43: =IF(H43="ETAPA",0,IF(H43="SUBETAPA",OFFSET(D43,-1,0)+1,OFFSET(D43,-1,0))) -> 1 | E43: =IF(H43="Subetapa",0,IF(H43="serviço",OFFSET(E43,-1,0)+1,OFFSET(E43,-1,0))) -> 6 | H43: SERVIÇO | I43: =IF(H43="Unidade Construtiva",TEXT(A43,"00"),IF(H43="Célula Construtiva",TEXT(B43,"00"),IF(H43="Etapa",CONCATENATE(TEXT(B43,"00"),".",TEXT(C43,"000")),IF(H43="Subetapa",CONCATENATE(TEXT(B43,"00"),".",TEXT(C43,"000"),".",TEXT(D43,"000")),IF(H43="Serviço",CONCATENATE(TEXT(B43,"00"),".",TEXT(C43,"000"),".",TEXT(D43,"000"),".",TEXT(E43,"000")),""))))) -> 01.002.001.006 | J43: Aprovação e legalização bombeiros | K43: vb | L43: 1 | M43: 7085.7896 | N43: =IF(H43="Serviço",M43*L43,IF(H43="CÉLULA CONSTRUTIVA",SUMIFS($N$8:$N$418,$B$8:$B$418,B43,$H$8:$H$418,"Serviço"),IF(H43="ETAPA",SUMIFS($N$8:$N$418,$B$8:$B$418,B43,$C$8:$C$418,C43,$H$8:$H$418,"Serviço"),IF(H43="SUBETAPA",SUMIFS($N$8:$N$418,$B$8:$B$418,B43,$C$8:$C$418,C43,$D$8:$D$418,D43,$H$8:$H$418,"Serviço"),0)))) -> 7085.7896 | O43: Estimado com base em índices históricos | P43: Lançado ERP
A44: =IF($H44="UNIDADE CONSTRUTIVA",OFFSET(A44,-1,0)+1,LARGE(A$3:A43,1)) -> 0 | B44: =IF(H44="UNIDADE CONSTRUTIVA",0,IF(H44="CÉLULA CONSTRUTIVA",OFFSET(B44,-1,0)+1,OFFSET(B44,-1,0))) -> 1 | C44: =IF(H44="CÉLULA CONSTRUTIVA",0,IF(H44="ETAPA",OFFSET(C44,-1,0)+1,OFFSET(C44,-1,0))) -> 2 | D44: =IF(H44="ETAPA",0,IF(H44="SUBETAPA",OFFSET(D44,-1,0)+1,OFFSET(D44,-1,0))) -> 1 | E44: =IF(H44="Subetapa",0,IF(H44="serviço",OFFSET(E44,-1,0)+1,OFFSET(E44,-1,0))) -> 7 | H44: SERVIÇO | I44: =IF(H44="Unidade Construtiva",TEXT(A44,"00"),IF(H44="Célula Construtiva",TEXT(B44,"00"),IF(H44="Etapa",CONCATENATE(TEXT(B44,"00"),".",TEXT(C44,"000")),IF(H44="Subetapa",CONCATENATE(TEXT(B44,"00"),".",TEXT(C44,"000"),".",TEXT(D44,"000")),IF(H44="Serviço",CONCATENATE(TEXT(B44,"00"),".",TEXT(C44,"000"),".",TEXT(D44,"000"),".",TEXT(E44,"000")),""))))) -> 01.002.001.007 | J44: Taxas de ART | K44: vb | L44: 1 | M44: 2568.1078 | N44: =IF(H44="Serviço",M44*L44,IF(H44="CÉLULA CONSTRUTIVA",SUMIFS($N$8:$N$418,$B$8:$B$418,B44,$H$8:$H$418,"Serviço"),IF(H44="ETAPA",SUMIFS($N$8:$N$418,$B$8:$B$418,B44,$C$8:$C$418,C44,$H$8:$H$418,"Serviço"),IF(H44="SUBETAPA",SUMIFS($N$8:$N$418,$B$8:$B$418,B44,$C$8:$C$418,C44,$D$8:$D$418,D44,$H$8:$H$418,"Serviço"),0)))) -> 2568.1078 | O44: Estimado com base em índices históricos | P44: Lançado ERP
A45: =IF($H45="UNIDADE CONSTRUTIVA",OFFSET(A45,-1,0)+1,LARGE(A$3:A44,1)) -> 0 | B45: =IF(H45="UNIDADE CONSTRUTIVA",0,IF(H45="CÉLULA CONSTRUTIVA",OFFSET(B45,-1,0)+1,OFFSET(B45,-1,0))) -> 1 | C45: =IF(H45="CÉLULA CONSTRUTIVA",0,IF(H45="ETAPA",OFFSET(C45,-1,0)+1,OFFSET(C45,-1,0))) -> 2 | D45: =IF(H45="ETAPA",0,IF(H45="SUBETAPA",OFFSET(D45,-1,0)+1,OFFSET(D45,-1,0))) -> 1 | E45: =IF(H45="Subetapa",0,IF(H45="serviço",OFFSET(E45,-1,0)+1,OFFSET(E45,-1,0))) -> 8 | H45: SERVIÇO | I45: =IF(H45="Unidade Construtiva",TEXT(A45,"00"),IF(H45="Célula Construtiva",TEXT(B45,"00"),IF(H45="Etapa",CONCATENATE(TEXT(B45,"00"),".",TEXT(C45,"000")),IF(H45="Subetapa",CONCATENATE(TEXT(B45,"00"),".",TEXT(C45,"000"),".",TEXT(D45,"000")),IF(H45="Serviço",CONCATENATE(TEXT(B45,"00"),".",TEXT(C45,"000"),".",TEXT(D45,"000"),".",TEXT(E45,"000")),""))))) -> 01.002.001.008 | J45: Alvará Construção | K45: vb | L45: 1 | M45: 41388.431 | N45: =IF(H45="Serviço",M45*L45,IF(H45="CÉLULA CONSTRUTIVA",SUMIFS($N$8:$N$418,$B$8:$B$418,B45,$H$8:$H$418,"Serviço"),IF(H45="ETAPA",SUMIFS($N$8:$N$418,$B$8:$B$418,B45,$C$8:$C$418,C45,$H$8:$H$418,"Serviço"),IF(H45="SUBETAPA",SUMIFS($N$8:$N$418,$B$8:$B$418,B45,$C$8:$C$418,C45,$D$8:$D$418,D45,$H$8:$H$418,"Serviço"),0)))) -> 41388.431 | O45: Estimado com base em índices históricos | P45: Lançado ERP
A46: =IF($H46="UNIDADE CONSTRUTIVA",OFFSET(A46,-1,0)+1,LARGE(A$3:A45,1)) -> 0 | B46: =IF(H46="UNIDADE CONSTRUTIVA",0,IF(H46="CÉLULA CONSTRUTIVA",OFFSET(B46,-1,0)+1,OFFSET(B46,-1,0))) -> 1 | C46: =IF(H46="CÉLULA CONSTRUTIVA",0,IF(H46="ETAPA",OFFSET(C46,-1,0)+1,OFFSET(C46,-1,0))) -> 2 | D46: =IF(H46="ETAPA",0,IF(H46="SUBETAPA",OFFSET(D46,-1,0)+1,OFFSET(D46,-1,0))) -> 1 | E46: =IF(H46="Subetapa",0,IF(H46="serviço",OFFSET(E46,-1,0)+1,OFFSET(E46,-1,0))) -> 9 | H46: SERVIÇO | I46: =IF(H46="Unidade Construtiva",TEXT(A46,"00"),IF(H46="Célula Construtiva",TEXT(B46,"00"),IF(H46="Etapa",CONCATENATE(TEXT(B46,"00"),".",TEXT(C46,"000")),IF(H46="Subetapa",CONCATENATE(TEXT(B46,"00"),".",TEXT(C46,"000"),".",TEXT(D46,"000")),IF(H46="Serviço",CONCATENATE(TEXT(B46,"00"),".",TEXT(C46,"000"),".",TEXT(D46,"000"),".",TEXT(E46,"000")),""))))) -> 01.002.001.009 | J46: Iptu | K46: vb | L46: 1 | M46: 18717.19 | N46: =IF(H46="Serviço",M46*L46,IF(H46="CÉLULA CONSTRUTIVA",SUMIFS($N$8:$N$418,$B$8:$B$418,B46,$H$8:$H$418,"Serviço"),IF(H46="ETAPA",SUMIFS($N$8:$N$418,$B$8:$B$418,B46,$C$8:$C$418,C46,$H$8:$H$418,"Serviço"),IF(H46="SUBETAPA",SUMIFS($N$8:$N$418,$B$8:$B$418,B46,$C$8:$C$418,C46,$D$8:$D$418,D46,$H$8:$H$418,"Serviço"),0)))) -> 18717.19 | O46: Estimado com base em índices históricos | P46: Lançado ERP
A47: =IF($H47="UNIDADE CONSTRUTIVA",OFFSET(A47,-1,0)+1,LARGE(A$3:A46,1)) -> 0 | B47: =IF(H47="UNIDADE CONSTRUTIVA",0,IF(H47="CÉLULA CONSTRUTIVA",OFFSET(B47,-1,0)+1,OFFSET(B47,-1,0))) -> 1 | C47: =IF(H47="CÉLULA CONSTRUTIVA",0,IF(H47="ETAPA",OFFSET(C47,-1,0)+1,OFFSET(C47,-1,0))) -> 2 | D47: =IF(H47="ETAPA",0,IF(H47="SUBETAPA",OFFSET(D47,-1,0)+1,OFFSET(D47,-1,0))) -> 1 | E47: =IF(H47="Subetapa",0,IF(H47="serviço",OFFSET(E47,-1,0)+1,OFFSET(E47,-1,0))) -> 10 | H47: SERVIÇO | I47: =IF(H47="Unidade Construtiva",TEXT(A47,"00"),IF(H47="Célula Construtiva",TEXT(B47,"00"),IF(H47="Etapa",CONCATENATE(TEXT(B47,"00"),".",TEXT(C47,"000")),IF(H47="Subetapa",CONCATENATE(TEXT(B47,"00"),".",TEXT(C47,"000"),".",TEXT(D47,"000")),IF(H47="Serviço",CONCATENATE(TEXT(B47,"00"),".",TEXT(C47,"000"),".",TEXT(D47,"000"),".",TEXT(E47,"000")),""))))) -> 01.002.001.010 | J47: Alvará Habite-se | K47: vb | L47: 1 | M47: 9624.1543 | N47: =IF(H47="Serviço",M47*L47,IF(H47="CÉLULA CONSTRUTIVA",SUMIFS($N$8:$N$418,$B$8:$B$418,B47,$H$8:$H$418,"Serviço"),IF(H47="ETAPA",SUMIFS($N$8:$N$418,$B$8:$B$418,B47,$C$8:$C$418,C47,$H$8:$H$418,"Serviço"),IF(H47="SUBETAPA",SUMIFS($N$8:$N$418,$B$8:$B$418,B47,$C$8:$C$418,C47,$D$8:$D$418,D47,$H$8:$H$418,"Serviço"),0)))) -> 9624.1543 | O47: Estimado com base em índices históricos | P47: Lançado ERP
A48: =IF($H48="UNIDADE CONSTRUTIVA",OFFSET(A48,-1,0)+1,LARGE(A$3:A47,1)) -> 0 | B48: =IF(H48="UNIDADE CONSTRUTIVA",0,IF(H48="CÉLULA CONSTRUTIVA",OFFSET(B48,-1,0)+1,OFFSET(B48,-1,0))) -> 1 | C48: =IF(H48="CÉLULA CONSTRUTIVA",0,IF(H48="ETAPA",OFFSET(C48,-1,0)+1,OFFSET(C48,-1,0))) -> 2 | D48: =IF(H48="ETAPA",0,IF(H48="SUBETAPA",OFFSET(D48,-1,0)+1,OFFSET(D48,-1,0))) -> 1 | E48: =IF(H48="Subetapa",0,IF(H48="serviço",OFFSET(E48,-1,0)+1,OFFSET(E48,-1,0))) -> 11 | H48: SERVIÇO | I48: =IF(H48="Unidade Construtiva",TEXT(A48,"00"),IF(H48="Célula Construtiva",TEXT(B48,"00"),IF(H48="Etapa",CONCATENATE(TEXT(B48,"00"),".",TEXT(C48,"000")),IF(H48="Subetapa",CONCATENATE(TEXT(B48,"00"),".",TEXT(C48,"000"),".",TEXT(D48,"000")),IF(H48="Serviço",CONCATENATE(TEXT(B48,"00"),".",TEXT(C48,"000"),".",TEXT(D48,"000"),".",TEXT(E48,"000")),""))))) -> 01.002.001.011 | J48: Certidão INSS | K48: vb | L48: 1 | M48: 9024.8263 | N48: =IF(H48="Serviço",M48*L48,IF(H48="CÉLULA CONSTRUTIVA",SUMIFS($N$8:$N$418,$B$8:$B$418,B48,$H$8:$H$418,"Serviço"),IF(H48="ETAPA",SUMIFS($N$8:$N$418,$B$8:$B$418,B48,$C$8:$C$418,C48,$H$8:$H$418,"Serviço"),IF(H48="SUBETAPA",SUMIFS($N$8:$N$418,$B$8:$B$418,B48,$C$8:$C$418,C48,$D$8:$D$418,D48,$H$8:$H$418,"Serviço"),0)))) -> 9024.8263 | O48: Estimado com base em índices históricos | P48: Lançado ERP
A49: =IF($H49="UNIDADE CONSTRUTIVA",OFFSET(A49,-1,0)+1,LARGE(A$3:A48,1)) -> 0 | B49: =IF(H49="UNIDADE CONSTRUTIVA",0,IF(H49="CÉLULA CONSTRUTIVA",OFFSET(B49,-1,0)+1,OFFSET(B49,-1,0))) -> 1 | C49: =IF(H49="CÉLULA CONSTRUTIVA",0,IF(H49="ETAPA",OFFSET(C49,-1,0)+1,OFFSET(C49,-1,0))) -> 2 | D49: =IF(H49="ETAPA",0,IF(H49="SUBETAPA",OFFSET(D49,-1,0)+1,OFFSET(D49,-1,0))) -> 2 | E49: =IF(H49="Subetapa",0,IF(H49="serviço",OFFSET(E49,-1,0)+1,OFFSET(E49,-1,0))) -> 0 | H49: SUBETAPA | I49: =IF(H49="Unidade Construtiva",TEXT(A49,"00"),IF(H49="Célula Construtiva",TEXT(B49,"00"),IF(H49="Etapa",CONCATENATE(TEXT(B49,"00"),".",TEXT(C49,"000")),IF(H49="Subetapa",CONCATENATE(TEXT(B49,"00"),".",TEXT(C49,"000"),".",TEXT(D49,"000")),IF(H49="Serviço",CONCATENATE(TEXT(B49,"00"),".",TEXT(C49,"000"),".",TEXT(D49,"000"),".",TEXT(E49,"000")),""))))) -> 01.002.002 | J49: Documentos | N49: =IF(H49="Serviço",M49*L49,IF(H49="CÉLULA CONSTRUTIVA",SUMIFS($N$8:$N$418,$B$8:$B$418,B49,$H$8:$H$418,"Serviço"),IF(H49="ETAPA",SUMIFS($N$8:$N$418,$B$8:$B$418,B49,$C$8:$C$418,C49,$H$8:$H$418,"Serviço"),IF(H49="SUBETAPA",SUMIFS($N$8:$N$418,$B$8:$B$418,B49,$C$8:$C$418,C49,$D$8:$D$418,D49,$H$8:$H$418,"Serviço"),0)))) -> 28738.346
A50: =IF($H50="UNIDADE CONSTRUTIVA",OFFSET(A50,-1,0)+1,LARGE(A$3:A49,1)) -> 0 | B50: =IF(H50="UNIDADE CONSTRUTIVA",0,IF(H50="CÉLULA CONSTRUTIVA",OFFSET(B50,-1,0)+1,OFFSET(B50,-1,0))) -> 1 | C50: =IF(H50="CÉLULA CONSTRUTIVA",0,IF(H50="ETAPA",OFFSET(C50,-1,0)+1,OFFSET(C50,-1,0))) -> 2 | D50: =IF(H50="ETAPA",0,IF(H50="SUBETAPA",OFFSET(D50,-1,0)+1,OFFSET(D50,-1,0))) -> 2 | E50: =IF(H50="Subetapa",0,IF(H50="serviço",OFFSET(E50,-1,0)+1,OFFSET(E50,-1,0))) -> 1 | H50: SERVIÇO | I50: =IF(H50="Unidade Construtiva",TEXT(A50,"00"),IF(H50="Célula Construtiva",TEXT(B50,"00"),IF(H50="Etapa",CONCATENATE(TEXT(B50,"00"),".",TEXT(C50,"000")),IF(H50="Subetapa",CONCATENATE(TEXT(B50,"00"),".",TEXT(C50,"000"),".",TEXT(D50,"000")),IF(H50="Serviço",CONCATENATE(TEXT(B50,"00"),".",TEXT(C50,"000"),".",TEXT(D50,"000"),".",TEXT(E50,"000")),""))))) -> 01.002.002.001 | J50: As Built | K50: vb | L50: 1 | M50: 9548.9813 | N50: =IF(H50="Serviço",M50*L50,IF(H50="CÉLULA CONSTRUTIVA",SUMIFS($N$8:$N$418,$B$8:$B$418,B50,$H$8:$H$418,"Serviço"),IF(H50="ETAPA",SUMIFS($N$8:$N$418,$B$8:$B$418,B50,$C$8:$C$418,C50,$H$8:$H$418,"Serviço"),IF(H50="SUBETAPA",SUMIFS($N$8:$N$418,$B$8:$B$418,B50,$C$8:$C$418,C50,$D$8:$D$418,D50,$H$8:$H$418,"Serviço"),0)))) -> 9548.9813 | O50: Estimado com base em índices históricos | P50: Lançado ERP
A51: =IF($H51="UNIDADE CONSTRUTIVA",OFFSET(A51,-1,0)+1,LARGE(A$3:A50,1)) -> 0 | B51: =IF(H51="UNIDADE CONSTRUTIVA",0,IF(H51="CÉLULA CONSTRUTIVA",OFFSET(B51,-1,0)+1,OFFSET(B51,-1,0))) -> 1 | C51: =IF(H51="CÉLULA CONSTRUTIVA",0,IF(H51="ETAPA",OFFSET(C51,-1,0)+1,OFFSET(C51,-1,0))) -> 2 | D51: =IF(H51="ETAPA",0,IF(H51="SUBETAPA",OFFSET(D51,-1,0)+1,OFFSET(D51,-1,0))) -> 2 | E51: =IF(H51="Subetapa",0,IF(H51="serviço",OFFSET(E51,-1,0)+1,OFFSET(E51,-1,0))) -> 2 | H51: SERVIÇO | I51: =IF(H51="Unidade Construtiva",TEXT(A51,"00"),IF(H51="Célula Construtiva",TEXT(B51,"00"),IF(H51="Etapa",CONCATENATE(TEXT(B51,"00"),".",TEXT(C51,"000")),IF(H51="Subetapa",CONCATENATE(TEXT(B51,"00"),".",TEXT(C51,"000"),".",TEXT(D51,"000")),IF(H51="Serviço",CONCATENATE(TEXT(B51,"00"),".",TEXT(C51,"000"),".",TEXT(D51,"000"),".",TEXT(E51,"000")),""))))) -> 01.002.002.002 | J51: Laudo de Vizinhança | K51: vb | L51: 1 | M51: 7900 | N51: =IF(H51="Serviço",M51*L51,IF(H51="CÉLULA CONSTRUTIVA",SUMIFS($N$8:$N$418,$B$8:$B$418,B51,$H$8:$H$418,"Serviço"),IF(H51="ETAPA",SUMIFS($N$8:$N$418,$B$8:$B$418,B51,$C$8:$C$418,C51,$H$8:$H$418,"Serviço"),IF(H51="SUBETAPA",SUMIFS($N$8:$N$418,$B$8:$B$418,B51,$C$8:$C$418,C51,$D$8:$D$418,D51,$H$8:$H$418,"Serviço"),0)))) -> 7900 | O51: Valor informado em formulário | P51: Lançado ERP
A52: =IF($H52="UNIDADE CONSTRUTIVA",OFFSET(A52,-1,0)+1,LARGE(A$3:A51,1)) -> 0 | B52: =IF(H52="UNIDADE CONSTRUTIVA",0,IF(H52="CÉLULA CONSTRUTIVA",OFFSET(B52,-1,0)+1,OFFSET(B52,-1,0))) -> 1 | C52: =IF(H52="CÉLULA CONSTRUTIVA",0,IF(H52="ETAPA",OFFSET(C52,-1,0)+1,OFFSET(C52,-1,0))) -> 2 | D52: =IF(H52="ETAPA",0,IF(H52="SUBETAPA",OFFSET(D52,-1,0)+1,OFFSET(D52,-1,0))) -> 2 | E52: =IF(H52="Subetapa",0,IF(H52="serviço",OFFSET(E52,-1,0)+1,OFFSET(E52,-1,0))) -> 3 | H52: SERVIÇO | I52: =IF(H52="Unidade Construtiva",TEXT(A52,"00"),IF(H52="Célula Construtiva",TEXT(B52,"00"),IF(H52="Etapa",CONCATENATE(TEXT(B52,"00"),".",TEXT(C52,"000")),IF(H52="Subetapa",CONCATENATE(TEXT(B52,"00"),".",TEXT(C52,"000"),".",TEXT(D52,"000")),IF(H52="Serviço",CONCATENATE(TEXT(B52,"00"),".",TEXT(C52,"000"),".",TEXT(D52,"000"),".",TEXT(E52,"000")),""))))) -> 01.002.002.003 | J52: Manuais técnicos condomínio/proprietários | K52: vb | L52: 1 | M52: 11289.364 | N52: =IF(H52="Serviço",M52*L52,IF(H52="CÉLULA CONSTRUTIVA",SUMIFS($N$8:$N$418,$B$8:$B$418,B52,$H$8:$H$418,"Serviço"),IF(H52="ETAPA",SUMIFS($N$8:$N$418,$B$8:$B$418,B52,$C$8:$C$418,C52,$H$8:$H$418,"Serviço"),IF(H52="SUBETAPA",SUMIFS($N$8:$N$418,$B$8:$B$418,B52,$C$8:$C$418,C52,$D$8:$D$418,D52,$H$8:$H$418,"Serviço"),0)))) -> 11289.364 | O52: Estimado com base em índices históricos | P52: Lançado ERP
A53: =IF($H53="UNIDADE CONSTRUTIVA",OFFSET(A53,-1,0)+1,LARGE(A$3:A52,1)) -> 0 | B53: =IF(H53="UNIDADE CONSTRUTIVA",0,IF(H53="CÉLULA CONSTRUTIVA",OFFSET(B53,-1,0)+1,OFFSET(B53,-1,0))) -> 2 | C53: =IF(H53="CÉLULA CONSTRUTIVA",0,IF(H53="ETAPA",OFFSET(C53,-1,0)+1,OFFSET(C53,-1,0))) -> 0 | D53: =IF(H53="ETAPA",0,IF(H53="SUBETAPA",OFFSET(D53,-1,0)+1,OFFSET(D53,-1,0))) -> 2 | E53: =IF(H53="Subetapa",0,IF(H53="serviço",OFFSET(E53,-1,0)+1,OFFSET(E53,-1,0))) -> 3 | H53: CÉLULA CONSTRUTIVA | I53: =IF(H53="Unidade Construtiva",TEXT(A53,"00"),IF(H53="Célula Construtiva",TEXT(B53,"00"),IF(H53="Etapa",CONCATENATE(TEXT(B53,"00"),".",TEXT(C53,"000")),IF(H53="Subetapa",CONCATENATE(TEXT(B53,"00"),".",TEXT(C53,"000"),".",TEXT(D53,"000")),IF(H53="Serviço",CONCATENATE(TEXT(B53,"00"),".",TEXT(C53,"000"),".",TEXT(D53,"000"),".",TEXT(E53,"000")),""))))) -> 02 | J53: SERVIÇOS INICIAIS | N53: =IF(H53="Serviço",M53*L53,IF(H53="CÉLULA CONSTRUTIVA",SUMIFS($N$8:$N$418,$B$8:$B$418,B53,$H$8:$H$418,"Serviço"),IF(H53="ETAPA",SUMIFS($N$8:$N$418,$B$8:$B$418,B53,$C$8:$C$418,C53,$H$8:$H$418,"Serviço"),IF(H53="SUBETAPA",SUMIFS($N$8:$N$418,$B$8:$B$418,B53,$C$8:$C$418,C53,$D$8:$D$418,D53,$H$8:$H$418,"Serviço"),0)))) -> 2182515.3
A54: =IF($H54="UNIDADE CONSTRUTIVA",OFFSET(A54,-1,0)+1,LARGE(A$3:A53,1)) -> 0 | B54: =IF(H54="UNIDADE CONSTRUTIVA",0,IF(H54="CÉLULA CONSTRUTIVA",OFFSET(B54,-1,0)+1,OFFSET(B54,-1,0))) -> 2 | C54: =IF(H54="CÉLULA CONSTRUTIVA",0,IF(H54="ETAPA",OFFSET(C54,-1,0)+1,OFFSET(C54,-1,0))) -> 1 | D54: =IF(H54="ETAPA",0,IF(H54="SUBETAPA",OFFSET(D54,-1,0)+1,OFFSET(D54,-1,0))) -> 0 | E54: =IF(H54="Subetapa",0,IF(H54="serviço",OFFSET(E54,-1,0)+1,OFFSET(E54,-1,0))) -> 3 | H54: ETAPA | I54: =IF(H54="Unidade Construtiva",TEXT(A54,"00"),IF(H54="Célula Construtiva",TEXT(B54,"00"),IF(H54="Etapa",CONCATENATE(TEXT(B54,"00"),".",TEXT(C54,"000")),IF(H54="Subetapa",CONCATENATE(TEXT(B54,"00"),".",TEXT(C54,"000"),".",TEXT(D54,"000")),IF(H54="Serviço",CONCATENATE(TEXT(B54,"00"),".",TEXT(C54,"000"),".",TEXT(D54,"000"),".",TEXT(E54,"000")),""))))) -> 02.001 | J54: SEGURANÇA, MEIO AMBIENTE E SAÚDE | N54: =IF(H54="Serviço",M54*L54,IF(H54="CÉLULA CONSTRUTIVA",SUMIFS($N$8:$N$418,$B$8:$B$418,B54,$H$8:$H$418,"Serviço"),IF(H54="ETAPA",SUMIFS($N$8:$N$418,$B$8:$B$418,B54,$C$8:$C$418,C54,$H$8:$H$418,"Serviço"),IF(H54="SUBETAPA",SUMIFS($N$8:$N$418,$B$8:$B$418,B54,$C$8:$C$418,C54,$D$8:$D$418,D54,$H$8:$H$418,"Serviço"),0)))) -> 754993.32
A55: =IF($H55="UNIDADE CONSTRUTIVA",OFFSET(A55,-1,0)+1,LARGE(A$3:A54,1)) -> 0 | B55: =IF(H55="UNIDADE CONSTRUTIVA",0,IF(H55="CÉLULA CONSTRUTIVA",OFFSET(B55,-1,0)+1,OFFSET(B55,-1,0))) -> 2 | C55: =IF(H55="CÉLULA CONSTRUTIVA",0,IF(H55="ETAPA",OFFSET(C55,-1,0)+1,OFFSET(C55,-1,0))) -> 1 | D55: =IF(H55="ETAPA",0,IF(H55="SUBETAPA",OFFSET(D55,-1,0)+1,OFFSET(D55,-1,0))) -> 1 | E55: =IF(H55="Subetapa",0,IF(H55="serviço",OFFSET(E55,-1,0)+1,OFFSET(E55,-1,0))) -> 0 | H55: SUBETAPA | I55: =IF(H55="Unidade Construtiva",TEXT(A55,"00"),IF(H55="Célula Construtiva",TEXT(B55,"00"),IF(H55="Etapa",CONCATENATE(TEXT(B55,"00"),".",TEXT(C55,"000")),IF(H55="Subetapa",CONCATENATE(TEXT(B55,"00"),".",TEXT(C55,"000"),".",TEXT(D55,"000")),IF(H55="Serviço",CONCATENATE(TEXT(B55,"00"),".",TEXT(C55,"000"),".",TEXT(D55,"000"),".",TEXT(E55,"000")),""))))) -> 02.001.001 | J55: Segurança do Trabalho | N55: =IF(H55="Serviço",M55*L55,IF(H55="CÉLULA CONSTRUTIVA",SUMIFS($N$8:$N$418,$B$8:$B$418,B55,$H$8:$H$418,"Serviço"),IF(H55="ETAPA",SUMIFS($N$8:$N$418,$B$8:$B$418,B55,$C$8:$C$418,C55,$H$8:$H$418,"Serviço"),IF(H55="SUBETAPA",SUMIFS($N$8:$N$418,$B$8:$B$418,B55,$C$8:$C$418,C55,$D$8:$D$418,D55,$H$8:$H$418,"Serviço"),0)))) -> 211000
A56: =IF($H56="UNIDADE CONSTRUTIVA",OFFSET(A56,-1,0)+1,LARGE(A$3:A55,1)) -> 0 | B56: =IF(H56="UNIDADE CONSTRUTIVA",0,IF(H56="CÉLULA CONSTRUTIVA",OFFSET(B56,-1,0)+1,OFFSET(B56,-1,0))) -> 2 | C56: =IF(H56="CÉLULA CONSTRUTIVA",0,IF(H56="ETAPA",OFFSET(C56,-1,0)+1,OFFSET(C56,-1,0))) -> 1 | D56: =IF(H56="ETAPA",0,IF(H56="SUBETAPA",OFFSET(D56,-1,0)+1,OFFSET(D56,-1,0))) -> 1 | E56: =IF(H56="Subetapa",0,IF(H56="serviço",OFFSET(E56,-1,0)+1,OFFSET(E56,-1,0))) -> 1 | H56: SERVIÇO | I56: =IF(H56="Unidade Construtiva",TEXT(A56,"00"),IF(H56="Célula Construtiva",TEXT(B56,"00"),IF(H56="Etapa",CONCATENATE(TEXT(B56,"00"),".",TEXT(C56,"000")),IF(H56="Subetapa",CONCATENATE(TEXT(B56,"00"),".",TEXT(C56,"000"),".",TEXT(D56,"000")),IF(H56="Serviço",CONCATENATE(TEXT(B56,"00"),".",TEXT(C56,"000"),".",TEXT(D56,"000"),".",TEXT(E56,"000")),""))))) -> 02.001.001.001 | J56: Técnico de segurança do trabalho | K56: mes | L56: 42 | M56: 5000 | N56: =IF(H56="Serviço",M56*L56,IF(H56="CÉLULA CONSTRUTIVA",SUMIFS($N$8:$N$418,$B$8:$B$418,B56,$H$8:$H$418,"Serviço"),IF(H56="ETAPA",SUMIFS($N$8:$N$418,$B$8:$B$418,B56,$C$8:$C$418,C56,$H$8:$H$418,"Serviço"),IF(H56="SUBETAPA",SUMIFS($N$8:$N$418,$B$8:$B$418,B56,$C$8:$C$418,C56,$D$8:$D$418,D56,$H$8:$H$418,"Serviço"),0)))) -> 210000 | O56: Valor informado em formulário | P56: Lançado ERP
A57: =IF($H57="UNIDADE CONSTRUTIVA",OFFSET(A57,-1,0)+1,LARGE(A$3:A56,1)) -> 0 | B57: =IF(H57="UNIDADE CONSTRUTIVA",0,IF(H57="CÉLULA CONSTRUTIVA",OFFSET(B57,-1,0)+1,OFFSET(B57,-1,0))) -> 2 | C57: =IF(H57="CÉLULA CONSTRUTIVA",0,IF(H57="ETAPA",OFFSET(C57,-1,0)+1,OFFSET(C57,-1,0))) -> 1 | D57: =IF(H57="ETAPA",0,IF(H57="SUBETAPA",OFFSET(D57,-1,0)+1,OFFSET(D57,-1,0))) -> 1 | E57: =IF(H57="Subetapa",0,IF(H57="serviço",OFFSET(E57,-1,0)+1,OFFSET(E57,-1,0))) -> 2 | H57: SERVIÇO | I57: =IF(H57="Unidade Construtiva",TEXT(A57,"00"),IF(H57="Célula Construtiva",TEXT(B57,"00"),IF(H57="Etapa",CONCATENATE(TEXT(B57,"00"),".",TEXT(C57,"000")),IF(H57="Subetapa",CONCATENATE(TEXT(B57,"00"),".",TEXT(C57,"000"),".",TEXT(D57,"000")),IF(H57="Serviço",CONCATENATE(TEXT(B57,"00"),".",TEXT(C57,"000"),".",TEXT(D57,"000"),".",TEXT(E57,"000")),""))))) -> 02.001.001.002 | J57: Equipamentos de proteção individual - EPI | K57: vb | L57: 1 | M57: 1000 | N57: =IF(H57="Serviço",M57*L57,IF(H57="CÉLULA CONSTRUTIVA",SUMIFS($N$8:$N$418,$B$8:$B$418,B57,$H$8:$H$418,"Serviço"),IF(H57="ETAPA",SUMIFS($N$8:$N$418,$B$8:$B$418,B57,$C$8:$C$418,C57,$H$8:$H$418,"Serviço"),IF(H57="SUBETAPA",SUMIFS($N$8:$N$418,$B$8:$B$418,B57,$C$8:$C$418,C57,$D$8:$D$418,D57,$H$8:$H$418,"Serviço"),0)))) -> 1000 | O57: Estimado com base em índices históricos | P57: Lançado ERP
A58: =IF($H58="UNIDADE CONSTRUTIVA",OFFSET(A58,-1,0)+1,LARGE(A$3:A57,1)) -> 0 | B58: =IF(H58="UNIDADE CONSTRUTIVA",0,IF(H58="CÉLULA CONSTRUTIVA",OFFSET(B58,-1,0)+1,OFFSET(B58,-1,0))) -> 2 | C58: =IF(H58="CÉLULA CONSTRUTIVA",0,IF(H58="ETAPA",OFFSET(C58,-1,0)+1,OFFSET(C58,-1,0))) -> 1 | D58: =IF(H58="ETAPA",0,IF(H58="SUBETAPA",OFFSET(D58,-1,0)+1,OFFSET(D58,-1,0))) -> 2 | E58: =IF(H58="Subetapa",0,IF(H58="serviço",OFFSET(E58,-1,0)+1,OFFSET(E58,-1,0))) -> 0 | H58: SUBETAPA | I58: =IF(H58="Unidade Construtiva",TEXT(A58,"00"),IF(H58="Célula Construtiva",TEXT(B58,"00"),IF(H58="Etapa",CONCATENATE(TEXT(B58,"00"),".",TEXT(C58,"000")),IF(H58="Subetapa",CONCATENATE(TEXT(B58,"00"),".",TEXT(C58,"000"),".",TEXT(D58,"000")),IF(H58="Serviço",CONCATENATE(TEXT(B58,"00"),".",TEXT(C58,"000"),".",TEXT(D58,"000"),".",TEXT(E58,"000")),""))))) -> 02.001.002 | J58: Equipamentos de proteção de canteiro | N58: =IF(H58="Serviço",M58*L58,IF(H58="CÉLULA CONSTRUTIVA",SUMIFS($N$8:$N$418,$B$8:$B$418,B58,$H$8:$H$418,"Serviço"),IF(H58="ETAPA",SUMIFS($N$8:$N$418,$B$8:$B$418,B58,$C$8:$C$418,C58,$H$8:$H$418,"Serviço"),IF(H58="SUBETAPA",SUMIFS($N$8:$N$418,$B$8:$B$418,B58,$C$8:$C$418,C58,$D$8:$D$418,D58,$H$8:$H$418,"Serviço"),0)))) -> 532788.09
A59: =IF($H59="UNIDADE CONSTRUTIVA",OFFSET(A59,-1,0)+1,LARGE(A$3:A58,1)) -> 0 | B59: =IF(H59="UNIDADE CONSTRUTIVA",0,IF(H59="CÉLULA CONSTRUTIVA",OFFSET(B59,-1,0)+1,OFFSET(B59,-1,0))) -> 2 | C59: =IF(H59="CÉLULA CONSTRUTIVA",0,IF(H59="ETAPA",OFFSET(C59,-1,0)+1,OFFSET(C59,-1,0))) -> 1 | D59: =IF(H59="ETAPA",0,IF(H59="SUBETAPA",OFFSET(D59,-1,0)+1,OFFSET(D59,-1,0))) -> 2 | E59: =IF(H59="Subetapa",0,IF(H59="serviço",OFFSET(E59,-1,0)+1,OFFSET(E59,-1,0))) -> 1 | H59: SERVIÇO | I59: =IF(H59="Unidade Construtiva",TEXT(A59,"00"),IF(H59="Célula Construtiva",TEXT(B59,"00"),IF(H59="Etapa",CONCATENATE(TEXT(B59,"00"),".",TEXT(C59,"000")),IF(H59="Subetapa",CONCATENATE(TEXT(B59,"00"),".",TEXT(C59,"000"),".",TEXT(D59,"000")),IF(H59="Serviço",CONCATENATE(TEXT(B59,"00"),".",TEXT(C59,"000"),".",TEXT(D59,"000"),".",TEXT(E59,"000")),""))))) -> 02.001.002.001 | J59: Bandeja de Proteção Primária com estrutura metálica e trama de madeira | K59: m | L59: =EPCs!D12 -> 135.43 | M59: 284.7986 | N59: =IF(H59="Serviço",M59*L59,IF(H59="CÉLULA CONSTRUTIVA",SUMIFS($N$8:$N$418,$B$8:$B$418,B59,$H$8:$H$418,"Serviço"),IF(H59="ETAPA",SUMIFS($N$8:$N$418,$B$8:$B$418,B59,$C$8:$C$418,C59,$H$8:$H$418,"Serviço"),IF(H59="SUBETAPA",SUMIFS($N$8:$N$418,$B$8:$B$418,B59,$C$8:$C$418,C59,$D$8:$D$418,D59,$H$8:$H$418,"Serviço"),0)))) -> 38570.274 | O59: Previsto confomre NR18 | P59: Lançado ERP
A60: =IF($H60="UNIDADE CONSTRUTIVA",OFFSET(A60,-1,0)+1,LARGE(A$3:A59,1)) -> 0 | B60: =IF(H60="UNIDADE CONSTRUTIVA",0,IF(H60="CÉLULA CONSTRUTIVA",OFFSET(B60,-1,0)+1,OFFSET(B60,-1,0))) -> 2 | C60: =IF(H60="CÉLULA CONSTRUTIVA",0,IF(H60="ETAPA",OFFSET(C60,-1,0)+1,OFFSET(C60,-1,0))) -> 1 | D60: =IF(H60="ETAPA",0,IF(H60="SUBETAPA",OFFSET(D60,-1,0)+1,OFFSET(D60,-1,0))) -> 2 | E60: =IF(H60="Subetapa",0,IF(H60="serviço",OFFSET(E60,-1,0)+1,OFFSET(E60,-1,0))) -> 2 | H60: SERVIÇO | I60: =IF(H60="Unidade Construtiva",TEXT(A60,"00"),IF(H60="Célula Construtiva",TEXT(B60,"00"),IF(H60="Etapa",CONCATENATE(TEXT(B60,"00"),".",TEXT(C60,"000")),IF(H60="Subetapa",CONCATENATE(TEXT(B60,"00"),".",TEXT(C60,"000"),".",TEXT(D60,"000")),IF(H60="Serviço",CONCATENATE(TEXT(B60,"00"),".",TEXT(C60,"000"),".",TEXT(D60,"000"),".",TEXT(E60,"000")),""))))) -> 02.001.002.002 | J60: Bandeja de Proteção Secundária com estrutura metálica e trama de madeira | K60: m | L60: =EPCs!D13 -> 290.49 | M60: 270.9386 | N60: =IF(H60="Serviço",M60*L60,IF(H60="CÉLULA CONSTRUTIVA",SUMIFS($N$8:$N$418,$B$8:$B$418,B60,$H$8:$H$418,"Serviço"),IF(H60="ETAPA",SUMIFS($N$8:$N$418,$B$8:$B$418,B60,$C$8:$C$418,C60,$H$8:$H$418,"Serviço"),IF(H60="SUBETAPA",SUMIFS($N$8:$N$418,$B$8:$B$418,B60,$C$8:$C$418,C60,$D$8:$D$418,D60,$H$8:$H$418,"Serviço"),0)))) -> 78704.954 | O60: Previsto confomre NR18 | P60: Lançado ERP
A61: =IF($H61="UNIDADE CONSTRUTIVA",OFFSET(A61,-1,0)+1,LARGE(A$3:A60,1)) -> 0 | B61: =IF(H61="UNIDADE CONSTRUTIVA",0,IF(H61="CÉLULA CONSTRUTIVA",OFFSET(B61,-1,0)+1,OFFSET(B61,-1,0))) -> 2 | C61: =IF(H61="CÉLULA CONSTRUTIVA",0,IF(H61="ETAPA",OFFSET(C61,-1,0)+1,OFFSET(C61,-1,0))) -> 1 | D61: =IF(H61="ETAPA",0,IF(H61="SUBETAPA",OFFSET(D61,-1,0)+1,OFFSET(D61,-1,0))) -> 2 | E61: =IF(H61="Subetapa",0,IF(H61="serviço",OFFSET(E61,-1,0)+1,OFFSET(E61,-1,0))) -> 3 | H61: SERVIÇO | I61: =IF(H61="Unidade Construtiva",TEXT(A61,"00"),IF(H61="Célula Construtiva",TEXT(B61,"00"),IF(H61="Etapa",CONCATENATE(TEXT(B61,"00"),".",TEXT(C61,"000")),IF(H61="Subetapa",CONCATENATE(TEXT(B61,"00"),".",TEXT(C61,"000"),".",TEXT(D61,"000")),IF(H61="Serviço",CONCATENATE(TEXT(B61,"00"),".",TEXT(C61,"000"),".",TEXT(D61,"000"),".",TEXT(E61,"000")),""))))) -> 02.001.002.003 | J61: Guarda-corpo de vãos, fixado em fôrma de madeira, em trama de madeira com tela de polipropileno | K61: m2 | L61: =EPCs!D19 -> 530.19 | M61: 38.653767 | N61: =IF(H61="Serviço",M61*L61,IF(H61="CÉLULA CONSTRUTIVA",SUMIFS($N$8:$N$418,$B$8:$B$418,B61,$H$8:$H$418,"Serviço"),IF(H61="ETAPA",SUMIFS($N$8:$N$418,$B$8:$B$418,B61,$C$8:$C$418,C61,$H$8:$H$418,"Serviço"),IF(H61="SUBETAPA",SUMIFS($N$8:$N$418,$B$8:$B$418,B61,$C$8:$C$418,C61,$D$8:$D$418,D61,$H$8:$H$418,"Serviço"),0)))) -> 20493.841 | O61: Previsto confomre NR18 | P61: Lançado ERP
A62: =IF($H62="UNIDADE CONSTRUTIVA",OFFSET(A62,-1,0)+1,LARGE(A$3:A61,1)) -> 0 | B62: =IF(H62="UNIDADE CONSTRUTIVA",0,IF(H62="CÉLULA CONSTRUTIVA",OFFSET(B62,-1,0)+1,OFFSET(B62,-1,0))) -> 2 | C62: =IF(H62="CÉLULA CONSTRUTIVA",0,IF(H62="ETAPA",OFFSET(C62,-1,0)+1,OFFSET(C62,-1,0))) -> 1 | D62: =IF(H62="ETAPA",0,IF(H62="SUBETAPA",OFFSET(D62,-1,0)+1,OFFSET(D62,-1,0))) -> 2 | E62: =IF(H62="Subetapa",0,IF(H62="serviço",OFFSET(E62,-1,0)+1,OFFSET(E62,-1,0))) -> 4 | H62: SERVIÇO | I62: =IF(H62="Unidade Construtiva",TEXT(A62,"00"),IF(H62="Célula Construtiva",TEXT(B62,"00"),IF(H62="Etapa",CONCATENATE(TEXT(B62,"00"),".",TEXT(C62,"000")),IF(H62="Subetapa",CONCATENATE(TEXT(B62,"00"),".",TEXT(C62,"000"),".",TEXT(D62,"000")),IF(H62="Serviço",CONCATENATE(TEXT(B62,"00"),".",TEXT(C62,"000"),".",TEXT(D62,"000"),".",TEXT(E62,"000")),""))))) -> 02.001.002.004 | J62: Guarda corpo de laje após desforma de pontalete de madeira, travessões e tela | K62: m | L62: =EPCs!D26 -> 387.32 | M62: 41.037177 | N62: =IF(H62="Serviço",M62*L62,IF(H62="CÉLULA CONSTRUTIVA",SUMIFS($N$8:$N$418,$B$8:$B$418,B62,$H$8:$H$418,"Serviço"),IF(H62="ETAPA",SUMIFS($N$8:$N$418,$B$8:$B$418,B62,$C$8:$C$418,C62,$H$8:$H$418,"Serviço"),IF(H62="SUBETAPA",SUMIFS($N$8:$N$418,$B$8:$B$418,B62,$C$8:$C$418,C62,$D$8:$D$418,D62,$H$8:$H$418,"Serviço"),0)))) -> 15894.519 | O62: Previsto confomre NR18 | P62: Lançado ERP
A63: =IF($H63="UNIDADE CONSTRUTIVA",OFFSET(A63,-1,0)+1,LARGE(A$3:A62,1)) -> 0 | B63: =IF(H63="UNIDADE CONSTRUTIVA",0,IF(H63="CÉLULA CONSTRUTIVA",OFFSET(B63,-1,0)+1,OFFSET(B63,-1,0))) -> 2 | C63: =IF(H63="CÉLULA CONSTRUTIVA",0,IF(H63="ETAPA",OFFSET(C63,-1,0)+1,OFFSET(C63,-1,0))) -> 1 | D63: =IF(H63="ETAPA",0,IF(H63="SUBETAPA",OFFSET(D63,-1,0)+1,OFFSET(D63,-1,0))) -> 2 | E63: =IF(H63="Subetapa",0,IF(H63="serviço",OFFSET(E63,-1,0)+1,OFFSET(E63,-1,0))) -> 5 | H63: SERVIÇO | I63: =IF(H63="Unidade Construtiva",TEXT(A63,"00"),IF(H63="Célula Construtiva",TEXT(B63,"00"),IF(H63="Etapa",CONCATENATE(TEXT(B63,"00"),".",TEXT(C63,"000")),IF(H63="Subetapa",CONCATENATE(TEXT(B63,"00"),".",TEXT(C63,"000"),".",TEXT(D63,"000")),IF(H63="Serviço",CONCATENATE(TEXT(B63,"00"),".",TEXT(C63,"000"),".",TEXT(D63,"000"),".",TEXT(E63,"000")),""))))) -> 02.001.002.005 | J63: Fechamento removível de vãos de porta de elevador em madeira | K63: m2 | L63: =EPCs!D34 -> 52.92 | M63: 47.353011 | N63: =IF(H63="Serviço",M63*L63,IF(H63="CÉLULA CONSTRUTIVA",SUMIFS($N$8:$N$418,$B$8:$B$418,B63,$H$8:$H$418,"Serviço"),IF(H63="ETAPA",SUMIFS($N$8:$N$418,$B$8:$B$418,B63,$C$8:$C$418,C63,$H$8:$H$418,"Serviço"),IF(H63="SUBETAPA",SUMIFS($N$8:$N$418,$B$8:$B$418,B63,$C$8:$C$418,C63,$D$8:$D$418,D63,$H$8:$H$418,"Serviço"),0)))) -> 2505.9213 | O63: Previsto confomre NR18 | P63: Lançado ERP
A64: =IF($H64="UNIDADE CONSTRUTIVA",OFFSET(A64,-1,0)+1,LARGE(A$3:A63,1)) -> 0 | B64: =IF(H64="UNIDADE CONSTRUTIVA",0,IF(H64="CÉLULA CONSTRUTIVA",OFFSET(B64,-1,0)+1,OFFSET(B64,-1,0))) -> 2 | C64: =IF(H64="CÉLULA CONSTRUTIVA",0,IF(H64="ETAPA",OFFSET(C64,-1,0)+1,OFFSET(C64,-1,0))) -> 1 | D64: =IF(H64="ETAPA",0,IF(H64="SUBETAPA",OFFSET(D64,-1,0)+1,OFFSET(D64,-1,0))) -> 2 | E64: =IF(H64="Subetapa",0,IF(H64="serviço",OFFSET(E64,-1,0)+1,OFFSET(E64,-1,0))) -> 6 | H64: SERVIÇO | I64: =IF(H64="Unidade Construtiva",TEXT(A64,"00"),IF(H64="Célula Construtiva",TEXT(B64,"00"),IF(H64="Etapa",CONCATENATE(TEXT(B64,"00"),".",TEXT(C64,"000")),IF(H64="Subetapa",CONCATENATE(TEXT(B64,"00"),".",TEXT(C64,"000"),".",TEXT(D64,"000")),IF(H64="Serviço",CONCATENATE(TEXT(B64,"00"),".",TEXT(C64,"000"),".",TEXT(D64,"000"),".",TEXT(E64,"000")),""))))) -> 02.001.002.006 | J64: Fechamento removível de vãos de porta de entrada dos aptos. em madeira | K64: m2 | L64: =EPCs!D41 -> 153.09 | M64: 47.353011 | N64: =IF(H64="Serviço",M64*L64,IF(H64="CÉLULA CONSTRUTIVA",SUMIFS($N$8:$N$418,$B$8:$B$418,B64,$H$8:$H$418,"Serviço"),IF(H64="ETAPA",SUMIFS($N$8:$N$418,$B$8:$B$418,B64,$C$8:$C$418,C64,$H$8:$H$418,"Serviço"),IF(H64="SUBETAPA",SUMIFS($N$8:$N$418,$B$8:$B$418,B64,$C$8:$C$418,C64,$D$8:$D$418,D64,$H$8:$H$418,"Serviço"),0)))) -> 7249.2725 | O64: Previsto confomre NR18 | P64: Lançado ERP
A65: =IF($H65="UNIDADE CONSTRUTIVA",OFFSET(A65,-1,0)+1,LARGE(A$3:A64,1)) -> 0 | B65: =IF(H65="UNIDADE CONSTRUTIVA",0,IF(H65="CÉLULA CONSTRUTIVA",OFFSET(B65,-1,0)+1,OFFSET(B65,-1,0))) -> 2 | C65: =IF(H65="CÉLULA CONSTRUTIVA",0,IF(H65="ETAPA",OFFSET(C65,-1,0)+1,OFFSET(C65,-1,0))) -> 1 | D65: =IF(H65="ETAPA",0,IF(H65="SUBETAPA",OFFSET(D65,-1,0)+1,OFFSET(D65,-1,0))) -> 2 | E65: =IF(H65="Subetapa",0,IF(H65="serviço",OFFSET(E65,-1,0)+1,OFFSET(E65,-1,0))) -> 7 | H65: SERVIÇO | I65: =IF(H65="Unidade Construtiva",TEXT(A65,"00"),IF(H65="Célula Construtiva",TEXT(B65,"00"),IF(H65="Etapa",CONCATENATE(TEXT(B65,"00"),".",TEXT(C65,"000")),IF(H65="Subetapa",CONCATENATE(TEXT(B65,"00"),".",TEXT(C65,"000"),".",TEXT(D65,"000")),IF(H65="Serviço",CONCATENATE(TEXT(B65,"00"),".",TEXT(C65,"000"),".",TEXT(D65,"000"),".",TEXT(E65,"000")),""))))) -> 02.001.002.007 | J65: Rede de proteção, SLQA, leve | K65: m | L65: 697.18 | M65: 417.439 | N65: =IF(H65="Serviço",M65*L65,IF(H65="CÉLULA CONSTRUTIVA",SUMIFS($N$8:$N$418,$B$8:$B$418,B65,$H$8:$H$418,"Serviço"),IF(H65="ETAPA",SUMIFS($N$8:$N$418,$B$8:$B$418,B65,$C$8:$C$418,C65,$H$8:$H$418,"Serviço"),IF(H65="SUBETAPA",SUMIFS($N$8:$N$418,$B$8:$B$418,B65,$C$8:$C$418,C65,$D$8:$D$418,D65,$H$8:$H$418,"Serviço"),0)))) -> 291030.12 | O65: Previsto confomre NR18 | P65: Lançado ERP
A66: =IF($H66="UNIDADE CONSTRUTIVA",OFFSET(A66,-1,0)+1,LARGE(A$3:A65,1)) -> 0 | B66: =IF(H66="UNIDADE CONSTRUTIVA",0,IF(H66="CÉLULA CONSTRUTIVA",OFFSET(B66,-1,0)+1,OFFSET(B66,-1,0))) -> 2 | C66: =IF(H66="CÉLULA CONSTRUTIVA",0,IF(H66="ETAPA",OFFSET(C66,-1,0)+1,OFFSET(C66,-1,0))) -> 1 | D66: =IF(H66="ETAPA",0,IF(H66="SUBETAPA",OFFSET(D66,-1,0)+1,OFFSET(D66,-1,0))) -> 2 | E66: =IF(H66="Subetapa",0,IF(H66="serviço",OFFSET(E66,-1,0)+1,OFFSET(E66,-1,0))) -> 8 | H66: SERVIÇO | I66: =IF(H66="Unidade Construtiva",TEXT(A66,"00"),IF(H66="Célula Construtiva",TEXT(B66,"00"),IF(H66="Etapa",CONCATENATE(TEXT(B66,"00"),".",TEXT(C66,"000")),IF(H66="Subetapa",CONCATENATE(TEXT(B66,"00"),".",TEXT(C66,"000"),".",TEXT(D66,"000")),IF(H66="Serviço",CONCATENATE(TEXT(B66,"00"),".",TEXT(C66,"000"),".",TEXT(D66,"000"),".",TEXT(E66,"000")),""))))) -> 02.001.002.008 | J66: Tela fachadeira mosqueteiro reforçada simples | K66: m2 | L66: =EPCs!D47 -> 4612.7884 | M66: 7.9493 | N66: =IF(H66="Serviço",M66*L66,IF(H66="CÉLULA CONSTRUTIVA",SUMIFS($N$8:$N$418,$B$8:$B$418,B66,$H$8:$H$418,"Serviço"),IF(H66="ETAPA",SUMIFS($N$8:$N$418,$B$8:$B$418,B66,$C$8:$C$418,C66,$H$8:$H$418,"Serviço"),IF(H66="SUBETAPA",SUMIFS($N$8:$N$418,$B$8:$B$418,B66,$C$8:$C$418,C66,$D$8:$D$418,D66,$H$8:$H$418,"Serviço"),0)))) -> 36668.439 | O66: Previsto confomre NR18 | P66: Lançado ERP
A67: =IF($H67="UNIDADE CONSTRUTIVA",OFFSET(A67,-1,0)+1,LARGE(A$3:A66,1)) -> 0 | B67: =IF(H67="UNIDADE CONSTRUTIVA",0,IF(H67="CÉLULA CONSTRUTIVA",OFFSET(B67,-1,0)+1,OFFSET(B67,-1,0))) -> 2 | C67: =IF(H67="CÉLULA CONSTRUTIVA",0,IF(H67="ETAPA",OFFSET(C67,-1,0)+1,OFFSET(C67,-1,0))) -> 1 | D67: =IF(H67="ETAPA",0,IF(H67="SUBETAPA",OFFSET(D67,-1,0)+1,OFFSET(D67,-1,0))) -> 2 | E67: =IF(H67="Subetapa",0,IF(H67="serviço",OFFSET(E67,-1,0)+1,OFFSET(E67,-1,0))) -> 9 | H67: SERVIÇO | I67: =IF(H67="Unidade Construtiva",TEXT(A67,"00"),IF(H67="Célula Construtiva",TEXT(B67,"00"),IF(H67="Etapa",CONCATENATE(TEXT(B67,"00"),".",TEXT(C67,"000")),IF(H67="Subetapa",CONCATENATE(TEXT(B67,"00"),".",TEXT(C67,"000"),".",TEXT(D67,"000")),IF(H67="Serviço",CONCATENATE(TEXT(B67,"00"),".",TEXT(C67,"000"),".",TEXT(D67,"000"),".",TEXT(E67,"000")),""))))) -> 02.001.002.009 | J67: Sinalização de obra | K67: vb | L67: 1 | M67: 7891.02 | N67: =IF(H67="Serviço",M67*L67,IF(H67="CÉLULA CONSTRUTIVA",SUMIFS($N$8:$N$418,$B$8:$B$418,B67,$H$8:$H$418,"Serviço"),IF(H67="ETAPA",SUMIFS($N$8:$N$418,$B$8:$B$418,B67,$C$8:$C$418,C67,$H$8:$H$418,"Serviço"),IF(H67="SUBETAPA",SUMIFS($N$8:$N$418,$B$8:$B$418,B67,$C$8:$C$418,C67,$D$8:$D$418,D67,$H$8:$H$418,"Serviço"),0)))) -> 7891.02 | O67: Previsto confomre NR18 | P67: Lançado ERP
A68: =IF($H68="UNIDADE CONSTRUTIVA",OFFSET(A68,-1,0)+1,LARGE(A$3:A67,1)) -> 0 | B68: =IF(H68="UNIDADE CONSTRUTIVA",0,IF(H68="CÉLULA CONSTRUTIVA",OFFSET(B68,-1,0)+1,OFFSET(B68,-1,0))) -> 2 | C68: =IF(H68="CÉLULA CONSTRUTIVA",0,IF(H68="ETAPA",OFFSET(C68,-1,0)+1,OFFSET(C68,-1,0))) -> 1 | D68: =IF(H68="ETAPA",0,IF(H68="SUBETAPA",OFFSET(D68,-1,0)+1,OFFSET(D68,-1,0))) -> 2 | E68: =IF(H68="Subetapa",0,IF(H68="serviço",OFFSET(E68,-1,0)+1,OFFSET(E68,-1,0))) -> 10 | H68: SERVIÇO | I68: =IF(H68="Unidade Construtiva",TEXT(A68,"00"),IF(H68="Célula Construtiva",TEXT(B68,"00"),IF(H68="Etapa",CONCATENATE(TEXT(B68,"00"),".",TEXT(C68,"000")),IF(H68="Subetapa",CONCATENATE(TEXT(B68,"00"),".",TEXT(C68,"000"),".",TEXT(D68,"000")),IF(H68="Serviço",CONCATENATE(TEXT(B68,"00"),".",TEXT(C68,"000"),".",TEXT(D68,"000"),".",TEXT(E68,"000")),""))))) -> 02.001.002.010 | J68: Linha de vida | K68: m | L68: =EPCs!D60 -> 387.32 | M68: 87.214 | N68: =IF(H68="Serviço",M68*L68,IF(H68="CÉLULA CONSTRUTIVA",SUMIFS($N$8:$N$418,$B$8:$B$418,B68,$H$8:$H$418,"Serviço"),IF(H68="ETAPA",SUMIFS($N$8:$N$418,$B$8:$B$418,B68,$C$8:$C$418,C68,$H$8:$H$418,"Serviço"),IF(H68="SUBETAPA",SUMIFS($N$8:$N$418,$B$8:$B$418,B68,$C$8:$C$418,C68,$D$8:$D$418,D68,$H$8:$H$418,"Serviço"),0)))) -> 33779.726 | O68: Previsto confomre NR18 | P68: Lançado ERP
A69: =IF($H69="UNIDADE CONSTRUTIVA",OFFSET(A69,-1,0)+1,LARGE(A$3:A68,1)) -> 0 | B69: =IF(H69="UNIDADE CONSTRUTIVA",0,IF(H69="CÉLULA CONSTRUTIVA",OFFSET(B69,-1,0)+1,OFFSET(B69,-1,0))) -> 2 | C69: =IF(H69="CÉLULA CONSTRUTIVA",0,IF(H69="ETAPA",OFFSET(C69,-1,0)+1,OFFSET(C69,-1,0))) -> 1 | D69: =IF(H69="ETAPA",0,IF(H69="SUBETAPA",OFFSET(D69,-1,0)+1,OFFSET(D69,-1,0))) -> 3 | E69: =IF(H69="Subetapa",0,IF(H69="serviço",OFFSET(E69,-1,0)+1,OFFSET(E69,-1,0))) -> 0 | H69: SUBETAPA | I69: =IF(H69="Unidade Construtiva",TEXT(A69,"00"),IF(H69="Célula Construtiva",TEXT(B69,"00"),IF(H69="Etapa",CONCATENATE(TEXT(B69,"00"),".",TEXT(C69,"000")),IF(H69="Subetapa",CONCATENATE(TEXT(B69,"00"),".",TEXT(C69,"000"),".",TEXT(D69,"000")),IF(H69="Serviço",CONCATENATE(TEXT(B69,"00"),".",TEXT(C69,"000"),".",TEXT(D69,"000"),".",TEXT(E69,"000")),""))))) -> 02.001.003 | J69: Meio Ambiente | N69: =IF(H69="Serviço",M69*L69,IF(H69="CÉLULA CONSTRUTIVA",SUMIFS($N$8:$N$418,$B$8:$B$418,B69,$H$8:$H$418,"Serviço"),IF(H69="ETAPA",SUMIFS($N$8:$N$418,$B$8:$B$418,B69,$C$8:$C$418,C69,$H$8:$H$418,"Serviço"),IF(H69="SUBETAPA",SUMIFS($N$8:$N$418,$B$8:$B$418,B69,$C$8:$C$418,C69,$D$8:$D$418,D69,$H$8:$H$418,"Serviço"),0)))) -> 8413.9296
A70: =IF($H70="UNIDADE CONSTRUTIVA",OFFSET(A70,-1,0)+1,LARGE(A$3:A69,1)) -> 0 | B70: =IF(H70="UNIDADE CONSTRUTIVA",0,IF(H70="CÉLULA CONSTRUTIVA",OFFSET(B70,-1,0)+1,OFFSET(B70,-1,0))) -> 2 | C70: =IF(H70="CÉLULA CONSTRUTIVA",0,IF(H70="ETAPA",OFFSET(C70,-1,0)+1,OFFSET(C70,-1,0))) -> 1 | D70: =IF(H70="ETAPA",0,IF(H70="SUBETAPA",OFFSET(D70,-1,0)+1,OFFSET(D70,-1,0))) -> 3 | E70: =IF(H70="Subetapa",0,IF(H70="serviço",OFFSET(E70,-1,0)+1,OFFSET(E70,-1,0))) -> 1 | H70: SERVIÇO | I70: =IF(H70="Unidade Construtiva",TEXT(A70,"00"),IF(H70="Célula Construtiva",TEXT(B70,"00"),IF(H70="Etapa",CONCATENATE(TEXT(B70,"00"),".",TEXT(C70,"000")),IF(H70="Subetapa",CONCATENATE(TEXT(B70,"00"),".",TEXT(C70,"000"),".",TEXT(D70,"000")),IF(H70="Serviço",CONCATENATE(TEXT(B70,"00"),".",TEXT(C70,"000"),".",TEXT(D70,"000"),".",TEXT(E70,"000")),""))))) -> 02.001.003.001 | J70: Projetos de Segurança do Trabalho | K70: vb | L70: 1 | M70: 4611.8417 | N70: =IF(H70="Serviço",M70*L70,IF(H70="CÉLULA CONSTRUTIVA",SUMIFS($N$8:$N$418,$B$8:$B$418,B70,$H$8:$H$418,"Serviço"),IF(H70="ETAPA",SUMIFS($N$8:$N$418,$B$8:$B$418,B70,$C$8:$C$418,C70,$H$8:$H$418,"Serviço"),IF(H70="SUBETAPA",SUMIFS($N$8:$N$418,$B$8:$B$418,B70,$C$8:$C$418,C70,$D$8:$D$418,D70,$H$8:$H$418,"Serviço"),0)))) -> 4611.8417 | O70: Estimado com base em índices históricos | P70: Lançado ERP
A71: =IF($H71="UNIDADE CONSTRUTIVA",OFFSET(A71,-1,0)+1,LARGE(A$3:A70,1)) -> 0 | B71: =IF(H71="UNIDADE CONSTRUTIVA",0,IF(H71="CÉLULA CONSTRUTIVA",OFFSET(B71,-1,0)+1,OFFSET(B71,-1,0))) -> 2 | C71: =IF(H71="CÉLULA CONSTRUTIVA",0,IF(H71="ETAPA",OFFSET(C71,-1,0)+1,OFFSET(C71,-1,0))) -> 1 | D71: =IF(H71="ETAPA",0,IF(H71="SUBETAPA",OFFSET(D71,-1,0)+1,OFFSET(D71,-1,0))) -> 3 | E71: =IF(H71="Subetapa",0,IF(H71="serviço",OFFSET(E71,-1,0)+1,OFFSET(E71,-1,0))) -> 2 | H71: SERVIÇO | I71: =IF(H71="Unidade Construtiva",TEXT(A71,"00"),IF(H71="Célula Construtiva",TEXT(B71,"00"),IF(H71="Etapa",CONCATENATE(TEXT(B71,"00"),".",TEXT(C71,"000")),IF(H71="Subetapa",CONCATENATE(TEXT(B71,"00"),".",TEXT(C71,"000"),".",TEXT(D71,"000")),IF(H71="Serviço",CONCATENATE(TEXT(B71,"00"),".",TEXT(C71,"000"),".",TEXT(D71,"000"),".",TEXT(E71,"000")),""))))) -> 02.001.003.002 | J71: Elaboração do programa de gerenciamento de riscos (PGR) | K71: vb | L71: 1 | M71: 3452.418 | N71: =IF(H71="Serviço",M71*L71,IF(H71="CÉLULA CONSTRUTIVA",SUMIFS($N$8:$N$418,$B$8:$B$418,B71,$H$8:$H$418,"Serviço"),IF(H71="ETAPA",SUMIFS($N$8:$N$418,$B$8:$B$418,B71,$C$8:$C$418,C71,$H$8:$H$418,"Serviço"),IF(H71="SUBETAPA",SUMIFS($N$8:$N$418,$B$8:$B$418,B71,$C$8:$C$418,C71,$D$8:$D$418,D71,$H$8:$H$418,"Serviço"),0)))) -> 3452.418 | O71: Estimado com base em índices históricos | P71: Lançado ERP
A72: =IF($H72="UNIDADE CONSTRUTIVA",OFFSET(A72,-1,0)+1,LARGE(A$3:A71,1)) -> 0 | B72: =IF(H72="UNIDADE CONSTRUTIVA",0,IF(H72="CÉLULA CONSTRUTIVA",OFFSET(B72,-1,0)+1,OFFSET(B72,-1,0))) -> 2 | C72: =IF(H72="CÉLULA CONSTRUTIVA",0,IF(H72="ETAPA",OFFSET(C72,-1,0)+1,OFFSET(C72,-1,0))) -> 1 | D72: =IF(H72="ETAPA",0,IF(H72="SUBETAPA",OFFSET(D72,-1,0)+1,OFFSET(D72,-1,0))) -> 3 | E72: =IF(H72="Subetapa",0,IF(H72="serviço",OFFSET(E72,-1,0)+1,OFFSET(E72,-1,0))) -> 3 | H72: SERVIÇO | I72: =IF(H72="Unidade Construtiva",TEXT(A72,"00"),IF(H72="Célula Construtiva",TEXT(B72,"00"),IF(H72="Etapa",CONCATENATE(TEXT(B72,"00"),".",TEXT(C72,"000")),IF(H72="Subetapa",CONCATENATE(TEXT(B72,"00"),".",TEXT(C72,"000"),".",TEXT(D72,"000")),IF(H72="Serviço",CONCATENATE(TEXT(B72,"00"),".",TEXT(C72,"000"),".",TEXT(D72,"000"),".",TEXT(E72,"000")),""))))) -> 02.001.003.003 | J72: Remoção de entulhos e resíduos | K72: vb | L72: 1 | M72: 349.6699 | N72: =IF(H72="Serviço",M72*L72,IF(H72="CÉLULA CONSTRUTIVA",SUMIFS($N$8:$N$418,$B$8:$B$418,B72,$H$8:$H$418,"Serviço"),IF(H72="ETAPA",SUMIFS($N$8:$N$418,$B$8:$B$418,B72,$C$8:$C$418,C72,$H$8:$H$418,"Serviço"),IF(H72="SUBETAPA",SUMIFS($N$8:$N$418,$B$8:$B$418,B72,$C$8:$C$418,C72,$D$8:$D$418,D72,$H$8:$H$418,"Serviço"),0)))) -> 349.6699 | P72: Lançado ERP
A73: =IF($H73="UNIDADE CONSTRUTIVA",OFFSET(A73,-1,0)+1,LARGE(A$3:A72,1)) -> 0 | B73: =IF(H73="UNIDADE CONSTRUTIVA",0,IF(H73="CÉLULA CONSTRUTIVA",OFFSET(B73,-1,0)+1,OFFSET(B73,-1,0))) -> 2 | C73: =IF(H73="CÉLULA CONSTRUTIVA",0,IF(H73="ETAPA",OFFSET(C73,-1,0)+1,OFFSET(C73,-1,0))) -> 1 | D73: =IF(H73="ETAPA",0,IF(H73="SUBETAPA",OFFSET(D73,-1,0)+1,OFFSET(D73,-1,0))) -> 4 | E73: =IF(H73="Subetapa",0,IF(H73="serviço",OFFSET(E73,-1,0)+1,OFFSET(E73,-1,0))) -> 0 | H73: SUBETAPA | I73: =IF(H73="Unidade Construtiva",TEXT(A73,"00"),IF(H73="Célula Construtiva",TEXT(B73,"00"),IF(H73="Etapa",CONCATENATE(TEXT(B73,"00"),".",TEXT(C73,"000")),IF(H73="Subetapa",CONCATENATE(TEXT(B73,"00"),".",TEXT(C73,"000"),".",TEXT(D73,"000")),IF(H73="Serviço",CONCATENATE(TEXT(B73,"00"),".",TEXT(C73,"000"),".",TEXT(D73,"000"),".",TEXT(E73,"000")),""))))) -> 02.001.004 | J73: Saúde Ocupacional | N73: =IF(H73="Serviço",M73*L73,IF(H73="CÉLULA CONSTRUTIVA",SUMIFS($N$8:$N$418,$B$8:$B$418,B73,$H$8:$H$418,"Serviço"),IF(H73="ETAPA",SUMIFS($N$8:$N$418,$B$8:$B$418,B73,$C$8:$C$418,C73,$H$8:$H$418,"Serviço"),IF(H73="SUBETAPA",SUMIFS($N$8:$N$418,$B$8:$B$418,B73,$C$8:$C$418,C73,$D$8:$D$418,D73,$H$8:$H$418,"Serviço"),0)))) -> 2791.3038
A74: =IF($H74="UNIDADE CONSTRUTIVA",OFFSET(A74,-1,0)+1,LARGE(A$3:A73,1)) -> 0 | B74: =IF(H74="UNIDADE CONSTRUTIVA",0,IF(H74="CÉLULA CONSTRUTIVA",OFFSET(B74,-1,0)+1,OFFSET(B74,-1,0))) -> 2 | C74: =IF(H74="CÉLULA CONSTRUTIVA",0,IF(H74="ETAPA",OFFSET(C74,-1,0)+1,OFFSET(C74,-1,0))) -> 1 | D74: =IF(H74="ETAPA",0,IF(H74="SUBETAPA",OFFSET(D74,-1,0)+1,OFFSET(D74,-1,0))) -> 4 | E74: =IF(H74="Subetapa",0,IF(H74="serviço",OFFSET(E74,-1,0)+1,OFFSET(E74,-1,0))) -> 1 | H74: SERVIÇO | I74: =IF(H74="Unidade Construtiva",TEXT(A74,"00"),IF(H74="Célula Construtiva",TEXT(B74,"00"),IF(H74="Etapa",CONCATENATE(TEXT(B74,"00"),".",TEXT(C74,"000")),IF(H74="Subetapa",CONCATENATE(TEXT(B74,"00"),".",TEXT(C74,"000"),".",TEXT(D74,"000")),IF(H74="Serviço",CONCATENATE(TEXT(B74,"00"),".",TEXT(C74,"000"),".",TEXT(D74,"000"),".",TEXT(E74,"000")),""))))) -> 02.001.004.001 | J74: Dedetização, desratização e sanitização dos ambientes | K74: mes | L74: 42 | M74: 66.459614 | N74: =IF(H74="Serviço",M74*L74,IF(H74="CÉLULA CONSTRUTIVA",SUMIFS($N$8:$N$418,$B$8:$B$418,B74,$H$8:$H$418,"Serviço"),IF(H74="ETAPA",SUMIFS($N$8:$N$418,$B$8:$B$418,B74,$C$8:$C$418,C74,$H$8:$H$418,"Serviço"),IF(H74="SUBETAPA",SUMIFS($N$8:$N$418,$B$8:$B$418,B74,$C$8:$C$418,C74,$D$8:$D$418,D74,$H$8:$H$418,"Serviço"),0)))) -> 2791.3038 | O74: Estimado com base em índices históricos | P74: Lançado ERP
A75: =IF($H75="UNIDADE CONSTRUTIVA",OFFSET(A75,-1,0)+1,LARGE(A$3:A74,1)) -> 0 | B75: =IF(H75="UNIDADE CONSTRUTIVA",0,IF(H75="CÉLULA CONSTRUTIVA",OFFSET(B75,-1,0)+1,OFFSET(B75,-1,0))) -> 2 | C75: =IF(H75="CÉLULA CONSTRUTIVA",0,IF(H75="ETAPA",OFFSET(C75,-1,0)+1,OFFSET(C75,-1,0))) -> 2 | D75: =IF(H75="ETAPA",0,IF(H75="SUBETAPA",OFFSET(D75,-1,0)+1,OFFSET(D75,-1,0))) -> 0 | E75: =IF(H75="Subetapa",0,IF(H75="serviço",OFFSET(E75,-1,0)+1,OFFSET(E75,-1,0))) -> 1 | H75: ETAPA | I75: =IF(H75="Unidade Construtiva",TEXT(A75,"00"),IF(H75="Célula Construtiva",TEXT(B75,"00"),IF(H75="Etapa",CONCATENATE(TEXT(B75,"00"),".",TEXT(C75,"000")),IF(H75="Subetapa",CONCATENATE(TEXT(B75,"00"),".",TEXT(C75,"000"),".",TEXT(D75,"000")),IF(H75="Serviço",CONCATENATE(TEXT(B75,"00"),".",TEXT(C75,"000"),".",TEXT(D75,"000"),".",TEXT(E75,"000")),""))))) -> 02.002 | J75: ADMINISTRAÇÃO E CANTEIRO DE OBRA | N75: =IF(H75="Serviço",M75*L75,IF(H75="CÉLULA CONSTRUTIVA",SUMIFS($N$8:$N$418,$B$8:$B$418,B75,$H$8:$H$418,"Serviço"),IF(H75="ETAPA",SUMIFS($N$8:$N$418,$B$8:$B$418,B75,$C$8:$C$418,C75,$H$8:$H$418,"Serviço"),IF(H75="SUBETAPA",SUMIFS($N$8:$N$418,$B$8:$B$418,B75,$C$8:$C$418,C75,$D$8:$D$418,D75,$H$8:$H$418,"Serviço"),0)))) -> 1427522
A76: =IF($H76="UNIDADE CONSTRUTIVA",OFFSET(A76,-1,0)+1,LARGE(A$3:A75,1)) -> 0 | B76: =IF(H76="UNIDADE CONSTRUTIVA",0,IF(H76="CÉLULA CONSTRUTIVA",OFFSET(B76,-1,0)+1,OFFSET(B76,-1,0))) -> 2 | C76: =IF(H76="CÉLULA CONSTRUTIVA",0,IF(H76="ETAPA",OFFSET(C76,-1,0)+1,OFFSET(C76,-1,0))) -> 2 | D76: =IF(H76="ETAPA",0,IF(H76="SUBETAPA",OFFSET(D76,-1,0)+1,OFFSET(D76,-1,0))) -> 1 | E76: =IF(H76="Subetapa",0,IF(H76="serviço",OFFSET(E76,-1,0)+1,OFFSET(E76,-1,0))) -> 0 | H76: SUBETAPA | I76: =IF(H76="Unidade Construtiva",TEXT(A76,"00"),IF(H76="Célula Construtiva",TEXT(B76,"00"),IF(H76="Etapa",CONCATENATE(TEXT(B76,"00"),".",TEXT(C76,"000")),IF(H76="Subetapa",CONCATENATE(TEXT(B76,"00"),".",TEXT(C76,"000"),".",TEXT(D76,"000")),IF(H76="Serviço",CONCATENATE(TEXT(B76,"00"),".",TEXT(C76,"000"),".",TEXT(D76,"000"),".",TEXT(E76,"000")),""))))) -> 02.002.001 | J76: Equipe de Gestão e Apoio | N76: =IF(H76="Serviço",M76*L76,IF(H76="CÉLULA CONSTRUTIVA",SUMIFS($N$8:$N$418,$B$8:$B$418,B76,$H$8:$H$418,"Serviço"),IF(H76="ETAPA",SUMIFS($N$8:$N$418,$B$8:$B$418,B76,$C$8:$C$418,C76,$H$8:$H$418,"Serviço"),IF(H76="SUBETAPA",SUMIFS($N$8:$N$418,$B$8:$B$418,B76,$C$8:$C$418,C76,$D$8:$D$418,D76,$H$8:$H$418,"Serviço"),0)))) -> 908029.37
A77: =IF($H77="UNIDADE CONSTRUTIVA",OFFSET(A77,-1,0)+1,LARGE(A$3:A76,1)) -> 0 | B77: =IF(H77="UNIDADE CONSTRUTIVA",0,IF(H77="CÉLULA CONSTRUTIVA",OFFSET(B77,-1,0)+1,OFFSET(B77,-1,0))) -> 2 | C77: =IF(H77="CÉLULA CONSTRUTIVA",0,IF(H77="ETAPA",OFFSET(C77,-1,0)+1,OFFSET(C77,-1,0))) -> 2 | D77: =IF(H77="ETAPA",0,IF(H77="SUBETAPA",OFFSET(D77,-1,0)+1,OFFSET(D77,-1,0))) -> 1 | E77: =IF(H77="Subetapa",0,IF(H77="serviço",OFFSET(E77,-1,0)+1,OFFSET(E77,-1,0))) -> 1 | H77: SERVIÇO | I77: =IF(H77="Unidade Construtiva",TEXT(A77,"00"),IF(H77="Célula Construtiva",TEXT(B77,"00"),IF(H77="Etapa",CONCATENATE(TEXT(B77,"00"),".",TEXT(C77,"000")),IF(H77="Subetapa",CONCATENATE(TEXT(B77,"00"),".",TEXT(C77,"000"),".",TEXT(D77,"000")),IF(H77="Serviço",CONCATENATE(TEXT(B77,"00"),".",TEXT(C77,"000"),".",TEXT(D77,"000"),".",TEXT(E77,"000")),""))))) -> 02.002.001.001 | J77: Engenheiro Civil | K77: mês | L77: ='Obra '!$E$7 -> 42 | M77: 10000 | N77: =IF(H77="Serviço",M77*L77,IF(H77="CÉLULA CONSTRUTIVA",SUMIFS($N$8:$N$418,$B$8:$B$418,B77,$H$8:$H$418,"Serviço"),IF(H77="ETAPA",SUMIFS($N$8:$N$418,$B$8:$B$418,B77,$C$8:$C$418,C77,$H$8:$H$418,"Serviço"),IF(H77="SUBETAPA",SUMIFS($N$8:$N$418,$B$8:$B$418,B77,$C$8:$C$418,C77,$D$8:$D$418,D77,$H$8:$H$418,"Serviço"),0)))) -> 420000 | O77: Valor informado em formulário | P77: Lançado ERP
A78: =IF($H78="UNIDADE CONSTRUTIVA",OFFSET(A78,-1,0)+1,LARGE(A$3:A77,1)) -> 0 | B78: =IF(H78="UNIDADE CONSTRUTIVA",0,IF(H78="CÉLULA CONSTRUTIVA",OFFSET(B78,-1,0)+1,OFFSET(B78,-1,0))) -> 2 | C78: =IF(H78="CÉLULA CONSTRUTIVA",0,IF(H78="ETAPA",OFFSET(C78,-1,0)+1,OFFSET(C78,-1,0))) -> 2 | D78: =IF(H78="ETAPA",0,IF(H78="SUBETAPA",OFFSET(D78,-1,0)+1,OFFSET(D78,-1,0))) -> 1 | E78: =IF(H78="Subetapa",0,IF(H78="serviço",OFFSET(E78,-1,0)+1,OFFSET(E78,-1,0))) -> 2 | H78: SERVIÇO | I78: =IF(H78="Unidade Construtiva",TEXT(A78,"00"),IF(H78="Célula Construtiva",TEXT(B78,"00"),IF(H78="Etapa",CONCATENATE(TEXT(B78,"00"),".",TEXT(C78,"000")),IF(H78="Subetapa",CONCATENATE(TEXT(B78,"00"),".",TEXT(C78,"000"),".",TEXT(D78,"000")),IF(H78="Serviço",CONCATENATE(TEXT(B78,"00"),".",TEXT(C78,"000"),".",TEXT(D78,"000"),".",TEXT(E78,"000")),""))))) -> 02.002.001.002 | J78: Equipe de apoio | K78: mês | L78: ='Obra '!E7 -> 42 | M78: 11619.747 | N78: =IF(H78="Serviço",M78*L78,IF(H78="CÉLULA CONSTRUTIVA",SUMIFS($N$8:$N$418,$B$8:$B$418,B78,$H$8:$H$418,"Serviço"),IF(H78="ETAPA",SUMIFS($N$8:$N$418,$B$8:$B$418,B78,$C$8:$C$418,C78,$H$8:$H$418,"Serviço"),IF(H78="SUBETAPA",SUMIFS($N$8:$N$418,$B$8:$B$418,B78,$C$8:$C$418,C78,$D$8:$D$418,D78,$H$8:$H$418,"Serviço"),0)))) -> 488029.37 | O78: Estimado com base em índices históricos | P78: Lançado ERP
A79: =IF($H79="UNIDADE CONSTRUTIVA",OFFSET(A79,-1,0)+1,LARGE(A$3:A78,1)) -> 0 | B79: =IF(H79="UNIDADE CONSTRUTIVA",0,IF(H79="CÉLULA CONSTRUTIVA",OFFSET(B79,-1,0)+1,OFFSET(B79,-1,0))) -> 2 | C79: =IF(H79="CÉLULA CONSTRUTIVA",0,IF(H79="ETAPA",OFFSET(C79,-1,0)+1,OFFSET(C79,-1,0))) -> 2 | D79: =IF(H79="ETAPA",0,IF(H79="SUBETAPA",OFFSET(D79,-1,0)+1,OFFSET(D79,-1,0))) -> 2 | E79: =IF(H79="Subetapa",0,IF(H79="serviço",OFFSET(E79,-1,0)+1,OFFSET(E79,-1,0))) -> 0 | H79: SUBETAPA | I79: =IF(H79="Unidade Construtiva",TEXT(A79,"00"),IF(H79="Célula Construtiva",TEXT(B79,"00"),IF(H79="Etapa",CONCATENATE(TEXT(B79,"00"),".",TEXT(C79,"000")),IF(H79="Subetapa",CONCATENATE(TEXT(B79,"00"),".",TEXT(C79,"000"),".",TEXT(D79,"000")),IF(H79="Serviço",CONCATENATE(TEXT(B79,"00"),".",TEXT(C79,"000"),".",TEXT(D79,"000"),".",TEXT(E79,"000")),""))))) -> 02.002.002 | J79: Despesas de Consumo e Manutenção | N79: =IF(H79="Serviço",M79*L79,IF(H79="CÉLULA CONSTRUTIVA",SUMIFS($N$8:$N$418,$B$8:$B$418,B79,$H$8:$H$418,"Serviço"),IF(H79="ETAPA",SUMIFS($N$8:$N$418,$B$8:$B$418,B79,$C$8:$C$418,C79,$H$8:$H$418,"Serviço"),IF(H79="SUBETAPA",SUMIFS($N$8:$N$418,$B$8:$B$418,B79,$C$8:$C$418,C79,$D$8:$D$418,D79,$H$8:$H$418,"Serviço"),0)))) -> 35719.107
A80: =IF($H80="UNIDADE CONSTRUTIVA",OFFSET(A80,-1,0)+1,LARGE(A$3:A79,1)) -> 0 | B80: =IF(H80="UNIDADE CONSTRUTIVA",0,IF(H80="CÉLULA CONSTRUTIVA",OFFSET(B80,-1,0)+1,OFFSET(B80,-1,0))) -> 2 | C80: =IF(H80="CÉLULA CONSTRUTIVA",0,IF(H80="ETAPA",OFFSET(C80,-1,0)+1,OFFSET(C80,-1,0))) -> 2 | D80: =IF(H80="ETAPA",0,IF(H80="SUBETAPA",OFFSET(D80,-1,0)+1,OFFSET(D80,-1,0))) -> 2 | E80: =IF(H80="Subetapa",0,IF(H80="serviço",OFFSET(E80,-1,0)+1,OFFSET(E80,-1,0))) -> 1 | H80: SERVIÇO | I80: =IF(H80="Unidade Construtiva",TEXT(A80,"00"),IF(H80="Célula Construtiva",TEXT(B80,"00"),IF(H80="Etapa",CONCATENATE(TEXT(B80,"00"),".",TEXT(C80,"000")),IF(H80="Subetapa",CONCATENATE(TEXT(B80,"00"),".",TEXT(C80,"000"),".",TEXT(D80,"000")),IF(H80="Serviço",CONCATENATE(TEXT(B80,"00"),".",TEXT(C80,"000"),".",TEXT(D80,"000"),".",TEXT(E80,"000")),""))))) -> 02.002.002.001 | J80: Demolições | K80: vb | L80: 1 | M80: 33849.507 | N80: =IF(H80="Serviço",M80*L80,IF(H80="CÉLULA CONSTRUTIVA",SUMIFS($N$8:$N$418,$B$8:$B$418,B80,$H$8:$H$418,"Serviço"),IF(H80="ETAPA",SUMIFS($N$8:$N$418,$B$8:$B$418,B80,$C$8:$C$418,C80,$H$8:$H$418,"Serviço"),IF(H80="SUBETAPA",SUMIFS($N$8:$N$418,$B$8:$B$418,B80,$C$8:$C$418,C80,$D$8:$D$418,D80,$H$8:$H$418,"Serviço"),0)))) -> 33849.507 | O80: Estimado com base em índices históricos | P80: Lançado ERP
A81: =IF($H81="UNIDADE CONSTRUTIVA",OFFSET(A81,-1,0)+1,LARGE(A$3:A80,1)) -> 0 | B81: =IF(H81="UNIDADE CONSTRUTIVA",0,IF(H81="CÉLULA CONSTRUTIVA",OFFSET(B81,-1,0)+1,OFFSET(B81,-1,0))) -> 2 | C81: =IF(H81="CÉLULA CONSTRUTIVA",0,IF(H81="ETAPA",OFFSET(C81,-1,0)+1,OFFSET(C81,-1,0))) -> 2 | D81: =IF(H81="ETAPA",0,IF(H81="SUBETAPA",OFFSET(D81,-1,0)+1,OFFSET(D81,-1,0))) -> 2 | E81: =IF(H81="Subetapa",0,IF(H81="serviço",OFFSET(E81,-1,0)+1,OFFSET(E81,-1,0))) -> 2 | H81: SERVIÇO | I81: =IF(H81="Unidade Construtiva",TEXT(A81,"00"),IF(H81="Célula Construtiva",TEXT(B81,"00"),IF(H81="Etapa",CONCATENATE(TEXT(B81,"00"),".",TEXT(C81,"000")),IF(H81="Subetapa",CONCATENATE(TEXT(B81,"00"),".",TEXT(C81,"000"),".",TEXT(D81,"000")),IF(H81="Serviço",CONCATENATE(TEXT(B81,"00"),".",TEXT(C81,"000"),".",TEXT(D81,"000"),".",TEXT(E81,"000")),""))))) -> 02.002.002.002 | J81: Limpeza mecânica da camada vegetal | K81: m2 | L81: ='Obra '!E8 -> 1140 | M81: 1.64 | N81: =IF(H81="Serviço",M81*L81,IF(H81="CÉLULA CONSTRUTIVA",SUMIFS($N$8:$N$418,$B$8:$B$418,B81,$H$8:$H$418,"Serviço"),IF(H81="ETAPA",SUMIFS($N$8:$N$418,$B$8:$B$418,B81,$C$8:$C$418,C81,$H$8:$H$418,"Serviço"),IF(H81="SUBETAPA",SUMIFS($N$8:$N$418,$B$8:$B$418,B81,$C$8:$C$418,C81,$D$8:$D$418,D81,$H$8:$H$418,"Serviço"),0)))) -> 1869.6 | O81: Estimado com base em índices históricos | P81: Lançado ERP
A82: =IF($H82="UNIDADE CONSTRUTIVA",OFFSET(A82,-1,0)+1,LARGE(A$3:A81,1)) -> 0 | B82: =IF(H82="UNIDADE CONSTRUTIVA",0,IF(H82="CÉLULA CONSTRUTIVA",OFFSET(B82,-1,0)+1,OFFSET(B82,-1,0))) -> 2 | C82: =IF(H82="CÉLULA CONSTRUTIVA",0,IF(H82="ETAPA",OFFSET(C82,-1,0)+1,OFFSET(C82,-1,0))) -> 2 | D82: =IF(H82="ETAPA",0,IF(H82="SUBETAPA",OFFSET(D82,-1,0)+1,OFFSET(D82,-1,0))) -> 3 | E82: =IF(H82="Subetapa",0,IF(H82="serviço",OFFSET(E82,-1,0)+1,OFFSET(E82,-1,0))) -> 0 | H82: SUBETAPA | I82: =IF(H82="Unidade Construtiva",TEXT(A82,"00"),IF(H82="Célula Construtiva",TEXT(B82,"00"),IF(H82="Etapa",CONCATENATE(TEXT(B82,"00"),".",TEXT(C82,"000")),IF(H82="Subetapa",CONCATENATE(TEXT(B82,"00"),".",TEXT(C82,"000"),".",TEXT(D82,"000")),IF(H82="Serviço",CONCATENATE(TEXT(B82,"00"),".",TEXT(C82,"000"),".",TEXT(D82,"000"),".",TEXT(E82,"000")),""))))) -> 02.002.003 | J82: Despesas de Consumo e Manutenção | N82: =IF(H82="Serviço",M82*L82,IF(H82="CÉLULA CONSTRUTIVA",SUMIFS($N$8:$N$418,$B$8:$B$418,B82,$H$8:$H$418,"Serviço"),IF(H82="ETAPA",SUMIFS($N$8:$N$418,$B$8:$B$418,B82,$C$8:$C$418,C82,$H$8:$H$418,"Serviço"),IF(H82="SUBETAPA",SUMIFS($N$8:$N$418,$B$8:$B$418,B82,$C$8:$C$418,C82,$D$8:$D$418,D82,$H$8:$H$418,"Serviço"),0)))) -> 355613.88
A83: =IF($H83="UNIDADE CONSTRUTIVA",OFFSET(A83,-1,0)+1,LARGE(A$3:A82,1)) -> 0 | B83: =IF(H83="UNIDADE CONSTRUTIVA",0,IF(H83="CÉLULA CONSTRUTIVA",OFFSET(B83,-1,0)+1,OFFSET(B83,-1,0))) -> 2 | C83: =IF(H83="CÉLULA CONSTRUTIVA",0,IF(H83="ETAPA",OFFSET(C83,-1,0)+1,OFFSET(C83,-1,0))) -> 2 | D83: =IF(H83="ETAPA",0,IF(H83="SUBETAPA",OFFSET(D83,-1,0)+1,OFFSET(D83,-1,0))) -> 3 | E83: =IF(H83="Subetapa",0,IF(H83="serviço",OFFSET(E83,-1,0)+1,OFFSET(E83,-1,0))) -> 1 | H83: SERVIÇO | I83: =IF(H83="Unidade Construtiva",TEXT(A83,"00"),IF(H83="Célula Construtiva",TEXT(B83,"00"),IF(H83="Etapa",CONCATENATE(TEXT(B83,"00"),".",TEXT(C83,"000")),IF(H83="Subetapa",CONCATENATE(TEXT(B83,"00"),".",TEXT(C83,"000"),".",TEXT(D83,"000")),IF(H83="Serviço",CONCATENATE(TEXT(B83,"00"),".",TEXT(C83,"000"),".",TEXT(D83,"000"),".",TEXT(E83,"000")),""))))) -> 02.002.003.001 | J83: Consumo de água e esgoto | K83: mês | L83: ='Obra '!$E$7 -> 42 | M83: 500 | N83: =IF(H83="Serviço",M83*L83,IF(H83="CÉLULA CONSTRUTIVA",SUMIFS($N$8:$N$418,$B$8:$B$418,B83,$H$8:$H$418,"Serviço"),IF(H83="ETAPA",SUMIFS($N$8:$N$418,$B$8:$B$418,B83,$C$8:$C$418,C83,$H$8:$H$418,"Serviço"),IF(H83="SUBETAPA",SUMIFS($N$8:$N$418,$B$8:$B$418,B83,$C$8:$C$418,C83,$D$8:$D$418,D83,$H$8:$H$418,"Serviço"),0)))) -> 21000 | O83: Estimado com base em índices históricos | P83: Lançado ERP
A84: =IF($H84="UNIDADE CONSTRUTIVA",OFFSET(A84,-1,0)+1,LARGE(A$3:A83,1)) -> 0 | B84: =IF(H84="UNIDADE CONSTRUTIVA",0,IF(H84="CÉLULA CONSTRUTIVA",OFFSET(B84,-1,0)+1,OFFSET(B84,-1,0))) -> 2 | C84: =IF(H84="CÉLULA CONSTRUTIVA",0,IF(H84="ETAPA",OFFSET(C84,-1,0)+1,OFFSET(C84,-1,0))) -> 2 | D84: =IF(H84="ETAPA",0,IF(H84="SUBETAPA",OFFSET(D84,-1,0)+1,OFFSET(D84,-1,0))) -> 3 | E84: =IF(H84="Subetapa",0,IF(H84="serviço",OFFSET(E84,-1,0)+1,OFFSET(E84,-1,0))) -> 2 | H84: SERVIÇO | I84: =IF(H84="Unidade Construtiva",TEXT(A84,"00"),IF(H84="Célula Construtiva",TEXT(B84,"00"),IF(H84="Etapa",CONCATENATE(TEXT(B84,"00"),".",TEXT(C84,"000")),IF(H84="Subetapa",CONCATENATE(TEXT(B84,"00"),".",TEXT(C84,"000"),".",TEXT(D84,"000")),IF(H84="Serviço",CONCATENATE(TEXT(B84,"00"),".",TEXT(C84,"000"),".",TEXT(D84,"000"),".",TEXT(E84,"000")),""))))) -> 02.002.003.002 | J84: Consumo de luz/energia | K84: mês | L84: ='Obra '!$E$7 -> 42 | M84: 500 | N84: =IF(H84="Serviço",M84*L84,IF(H84="CÉLULA CONSTRUTIVA",SUMIFS($N$8:$N$418,$B$8:$B$418,B84,$H$8:$H$418,"Serviço"),IF(H84="ETAPA",SUMIFS($N$8:$N$418,$B$8:$B$418,B84,$C$8:$C$418,C84,$H$8:$H$418,"Serviço"),IF(H84="SUBETAPA",SUMIFS($N$8:$N$418,$B$8:$B$418,B84,$C$8:$C$418,C84,$D$8:$D$418,D84,$H$8:$H$418,"Serviço"),0)))) -> 21000 | O84: Estimado com base em índices históricos | P84: Lançado ERP
A85: =IF($H85="UNIDADE CONSTRUTIVA",OFFSET(A85,-1,0)+1,LARGE(A$3:A84,1)) -> 0 | B85: =IF(H85="UNIDADE CONSTRUTIVA",0,IF(H85="CÉLULA CONSTRUTIVA",OFFSET(B85,-1,0)+1,OFFSET(B85,-1,0))) -> 2 | C85: =IF(H85="CÉLULA CONSTRUTIVA",0,IF(H85="ETAPA",OFFSET(C85,-1,0)+1,OFFSET(C85,-1,0))) -> 2 | D85: =IF(H85="ETAPA",0,IF(H85="SUBETAPA",OFFSET(D85,-1,0)+1,OFFSET(D85,-1,0))) -> 3 | E85: =IF(H85="Subetapa",0,IF(H85="serviço",OFFSET(E85,-1,0)+1,OFFSET(E85,-1,0))) -> 3 | H85: SERVIÇO | I85: =IF(H85="Unidade Construtiva",TEXT(A85,"00"),IF(H85="Célula Construtiva",TEXT(B85,"00"),IF(H85="Etapa",CONCATENATE(TEXT(B85,"00"),".",TEXT(C85,"000")),IF(H85="Subetapa",CONCATENATE(TEXT(B85,"00"),".",TEXT(C85,"000"),".",TEXT(D85,"000")),IF(H85="Serviço",CONCATENATE(TEXT(B85,"00"),".",TEXT(C85,"000"),".",TEXT(D85,"000"),".",TEXT(E85,"000")),""))))) -> 02.002.003.003 | J85: Consumo internet | K85: mês | L85: ='Obra '!$E$7 -> 42 | M85: 76.7204 | N85: =IF(H85="Serviço",M85*L85,IF(H85="CÉLULA CONSTRUTIVA",SUMIFS($N$8:$N$418,$B$8:$B$418,B85,$H$8:$H$418,"Serviço"),IF(H85="ETAPA",SUMIFS($N$8:$N$418,$B$8:$B$418,B85,$C$8:$C$418,C85,$H$8:$H$418,"Serviço"),IF(H85="SUBETAPA",SUMIFS($N$8:$N$418,$B$8:$B$418,B85,$C$8:$C$418,C85,$D$8:$D$418,D85,$H$8:$H$418,"Serviço"),0)))) -> 3222.2568 | O85: Estimado com base em índices históricos | P85: Lançado ERP
A86: =IF($H86="UNIDADE CONSTRUTIVA",OFFSET(A86,-1,0)+1,LARGE(A$3:A85,1)) -> 0 | B86: =IF(H86="UNIDADE CONSTRUTIVA",0,IF(H86="CÉLULA CONSTRUTIVA",OFFSET(B86,-1,0)+1,OFFSET(B86,-1,0))) -> 2 | C86: =IF(H86="CÉLULA CONSTRUTIVA",0,IF(H86="ETAPA",OFFSET(C86,-1,0)+1,OFFSET(C86,-1,0))) -> 2 | D86: =IF(H86="ETAPA",0,IF(H86="SUBETAPA",OFFSET(D86,-1,0)+1,OFFSET(D86,-1,0))) -> 3 | E86: =IF(H86="Subetapa",0,IF(H86="serviço",OFFSET(E86,-1,0)+1,OFFSET(E86,-1,0))) -> 4 | H86: SERVIÇO | I86: =IF(H86="Unidade Construtiva",TEXT(A86,"00"),IF(H86="Célula Construtiva",TEXT(B86,"00"),IF(H86="Etapa",CONCATENATE(TEXT(B86,"00"),".",TEXT(C86,"000")),IF(H86="Subetapa",CONCATENATE(TEXT(B86,"00"),".",TEXT(C86,"000"),".",TEXT(D86,"000")),IF(H86="Serviço",CONCATENATE(TEXT(B86,"00"),".",TEXT(C86,"000"),".",TEXT(D86,"000"),".",TEXT(E86,"000")),""))))) -> 02.002.003.004 | J86: Coleta de lixo | K86: mês | L86: ='Obra '!$E$7 -> 42 | M86: 38.3602 | N86: =IF(H86="Serviço",M86*L86,IF(H86="CÉLULA CONSTRUTIVA",SUMIFS($N$8:$N$418,$B$8:$B$418,B86,$H$8:$H$418,"Serviço"),IF(H86="ETAPA",SUMIFS($N$8:$N$418,$B$8:$B$418,B86,$C$8:$C$418,C86,$H$8:$H$418,"Serviço"),IF(H86="SUBETAPA",SUMIFS($N$8:$N$418,$B$8:$B$418,B86,$C$8:$C$418,C86,$D$8:$D$418,D86,$H$8:$H$418,"Serviço"),0)))) -> 1611.1284 | O86: Estimado com base em índices históricos | P86: Lançado ERP
A87: =IF($H87="UNIDADE CONSTRUTIVA",OFFSET(A87,-1,0)+1,LARGE(A$3:A86,1)) -> 0 | B87: =IF(H87="UNIDADE CONSTRUTIVA",0,IF(H87="CÉLULA CONSTRUTIVA",OFFSET(B87,-1,0)+1,OFFSET(B87,-1,0))) -> 2 | C87: =IF(H87="CÉLULA CONSTRUTIVA",0,IF(H87="ETAPA",OFFSET(C87,-1,0)+1,OFFSET(C87,-1,0))) -> 2 | D87: =IF(H87="ETAPA",0,IF(H87="SUBETAPA",OFFSET(D87,-1,0)+1,OFFSET(D87,-1,0))) -> 3 | E87: =IF(H87="Subetapa",0,IF(H87="serviço",OFFSET(E87,-1,0)+1,OFFSET(E87,-1,0))) -> 5 | H87: SERVIÇO | I87: =IF(H87="Unidade Construtiva",TEXT(A87,"00"),IF(H87="Célula Construtiva",TEXT(B87,"00"),IF(H87="Etapa",CONCATENATE(TEXT(B87,"00"),".",TEXT(C87,"000")),IF(H87="Subetapa",CONCATENATE(TEXT(B87,"00"),".",TEXT(C87,"000"),".",TEXT(D87,"000")),IF(H87="Serviço",CONCATENATE(TEXT(B87,"00"),".",TEXT(C87,"000"),".",TEXT(D87,"000"),".",TEXT(E87,"000")),""))))) -> 02.002.003.005 | J87: Consumo de material de expediente/escritório | K87: mês | L87: ='Obra '!$E$7 -> 42 | M87: 200 | N87: =IF(H87="Serviço",M87*L87,IF(H87="CÉLULA CONSTRUTIVA",SUMIFS($N$8:$N$418,$B$8:$B$418,B87,$H$8:$H$418,"Serviço"),IF(H87="ETAPA",SUMIFS($N$8:$N$418,$B$8:$B$418,B87,$C$8:$C$418,C87,$H$8:$H$418,"Serviço"),IF(H87="SUBETAPA",SUMIFS($N$8:$N$418,$B$8:$B$418,B87,$C$8:$C$418,C87,$D$8:$D$418,D87,$H$8:$H$418,"Serviço"),0)))) -> 8400 | O87: Estimado com base em índices históricos | P87: Lançado ERP
A88: =IF($H88="UNIDADE CONSTRUTIVA",OFFSET(A88,-1,0)+1,LARGE(A$3:A87,1)) -> 0 | B88: =IF(H88="UNIDADE CONSTRUTIVA",0,IF(H88="CÉLULA CONSTRUTIVA",OFFSET(B88,-1,0)+1,OFFSET(B88,-1,0))) -> 2 | C88: =IF(H88="CÉLULA CONSTRUTIVA",0,IF(H88="ETAPA",OFFSET(C88,-1,0)+1,OFFSET(C88,-1,0))) -> 2 | D88: =IF(H88="ETAPA",0,IF(H88="SUBETAPA",OFFSET(D88,-1,0)+1,OFFSET(D88,-1,0))) -> 3 | E88: =IF(H88="Subetapa",0,IF(H88="serviço",OFFSET(E88,-1,0)+1,OFFSET(E88,-1,0))) -> 6 | H88: SERVIÇO | I88: =IF(H88="Unidade Construtiva",TEXT(A88,"00"),IF(H88="Célula Construtiva",TEXT(B88,"00"),IF(H88="Etapa",CONCATENATE(TEXT(B88,"00"),".",TEXT(C88,"000")),IF(H88="Subetapa",CONCATENATE(TEXT(B88,"00"),".",TEXT(C88,"000"),".",TEXT(D88,"000")),IF(H88="Serviço",CONCATENATE(TEXT(B88,"00"),".",TEXT(C88,"000"),".",TEXT(D88,"000"),".",TEXT(E88,"000")),""))))) -> 02.002.003.006 | J88: Consumo de material de higiene e limpeza | K88: mês | L88: ='Obra '!$E$7 -> 42 | M88: 500 | N88: =IF(H88="Serviço",M88*L88,IF(H88="CÉLULA CONSTRUTIVA",SUMIFS($N$8:$N$418,$B$8:$B$418,B88,$H$8:$H$418,"Serviço"),IF(H88="ETAPA",SUMIFS($N$8:$N$418,$B$8:$B$418,B88,$C$8:$C$418,C88,$H$8:$H$418,"Serviço"),IF(H88="SUBETAPA",SUMIFS($N$8:$N$418,$B$8:$B$418,B88,$C$8:$C$418,C88,$D$8:$D$418,D88,$H$8:$H$418,"Serviço"),0)))) -> 21000 | O88: Estimado com base em índices históricos | P88: Lançado ERP
A89: =IF($H89="UNIDADE CONSTRUTIVA",OFFSET(A89,-1,0)+1,LARGE(A$3:A88,1)) -> 0 | B89: =IF(H89="UNIDADE CONSTRUTIVA",0,IF(H89="CÉLULA CONSTRUTIVA",OFFSET(B89,-1,0)+1,OFFSET(B89,-1,0))) -> 2 | C89: =IF(H89="CÉLULA CONSTRUTIVA",0,IF(H89="ETAPA",OFFSET(C89,-1,0)+1,OFFSET(C89,-1,0))) -> 2 | D89: =IF(H89="ETAPA",0,IF(H89="SUBETAPA",OFFSET(D89,-1,0)+1,OFFSET(D89,-1,0))) -> 3 | E89: =IF(H89="Subetapa",0,IF(H89="serviço",OFFSET(E89,-1,0)+1,OFFSET(E89,-1,0))) -> 7 | H89: SERVIÇO | I89: =IF(H89="Unidade Construtiva",TEXT(A89,"00"),IF(H89="Célula Construtiva",TEXT(B89,"00"),IF(H89="Etapa",CONCATENATE(TEXT(B89,"00"),".",TEXT(C89,"000")),IF(H89="Subetapa",CONCATENATE(TEXT(B89,"00"),".",TEXT(C89,"000"),".",TEXT(D89,"000")),IF(H89="Serviço",CONCATENATE(TEXT(B89,"00"),".",TEXT(C89,"000"),".",TEXT(D89,"000"),".",TEXT(E89,"000")),""))))) -> 02.002.003.007 | J89: Consumo de cópias | K89: mês | L89: ='Obra '!$E$7 -> 42 | M89: 73.2534 | N89: =IF(H89="Serviço",M89*L89,IF(H89="CÉLULA CONSTRUTIVA",SUMIFS($N$8:$N$418,$B$8:$B$418,B89,$H$8:$H$418,"Serviço"),IF(H89="ETAPA",SUMIFS($N$8:$N$418,$B$8:$B$418,B89,$C$8:$C$418,C89,$H$8:$H$418,"Serviço"),IF(H89="SUBETAPA",SUMIFS($N$8:$N$418,$B$8:$B$418,B89,$C$8:$C$418,C89,$D$8:$D$418,D89,$H$8:$H$418,"Serviço"),0)))) -> 3076.6428 | O89: Estimado com base em índices históricos | P89: Lançado ERP
A90: =IF($H90="UNIDADE CONSTRUTIVA",OFFSET(A90,-1,0)+1,LARGE(A$3:A89,1)) -> 0 | B90: =IF(H90="UNIDADE CONSTRUTIVA",0,IF(H90="CÉLULA CONSTRUTIVA",OFFSET(B90,-1,0)+1,OFFSET(B90,-1,0))) -> 2 | C90: =IF(H90="CÉLULA CONSTRUTIVA",0,IF(H90="ETAPA",OFFSET(C90,-1,0)+1,OFFSET(C90,-1,0))) -> 2 | D90: =IF(H90="ETAPA",0,IF(H90="SUBETAPA",OFFSET(D90,-1,0)+1,OFFSET(D90,-1,0))) -> 3 | E90: =IF(H90="Subetapa",0,IF(H90="serviço",OFFSET(E90,-1,0)+1,OFFSET(E90,-1,0))) -> 8 | H90: SERVIÇO | I90: =IF(H90="Unidade Construtiva",TEXT(A90,"00"),IF(H90="Célula Construtiva",TEXT(B90,"00"),IF(H90="Etapa",CONCATENATE(TEXT(B90,"00"),".",TEXT(C90,"000")),IF(H90="Subetapa",CONCATENATE(TEXT(B90,"00"),".",TEXT(C90,"000"),".",TEXT(D90,"000")),IF(H90="Serviço",CONCATENATE(TEXT(B90,"00"),".",TEXT(C90,"000"),".",TEXT(D90,"000"),".",TEXT(E90,"000")),""))))) -> 02.002.003.008 | J90: Despesas com vizinhos | K90: vb | L90: 1 | M90: 16787.254 | N90: =IF(H90="Serviço",M90*L90,IF(H90="CÉLULA CONSTRUTIVA",SUMIFS($N$8:$N$418,$B$8:$B$418,B90,$H$8:$H$418,"Serviço"),IF(H90="ETAPA",SUMIFS($N$8:$N$418,$B$8:$B$418,B90,$C$8:$C$418,C90,$H$8:$H$418,"Serviço"),IF(H90="SUBETAPA",SUMIFS($N$8:$N$418,$B$8:$B$418,B90,$C$8:$C$418,C90,$D$8:$D$418,D90,$H$8:$H$418,"Serviço"),0)))) -> 16787.254 | O90: Estimado com base em índices históricos | P90: Lançado ERP
A91: =IF($H91="UNIDADE CONSTRUTIVA",OFFSET(A91,-1,0)+1,LARGE(A$3:A90,1)) -> 0 | B91: =IF(H91="UNIDADE CONSTRUTIVA",0,IF(H91="CÉLULA CONSTRUTIVA",OFFSET(B91,-1,0)+1,OFFSET(B91,-1,0))) -> 2 | C91: =IF(H91="CÉLULA CONSTRUTIVA",0,IF(H91="ETAPA",OFFSET(C91,-1,0)+1,OFFSET(C91,-1,0))) -> 2 | D91: =IF(H91="ETAPA",0,IF(H91="SUBETAPA",OFFSET(D91,-1,0)+1,OFFSET(D91,-1,0))) -> 3 | E91: =IF(H91="Subetapa",0,IF(H91="serviço",OFFSET(E91,-1,0)+1,OFFSET(E91,-1,0))) -> 9 | H91: SERVIÇO | I91: =IF(H91="Unidade Construtiva",TEXT(A91,"00"),IF(H91="Célula Construtiva",TEXT(B91,"00"),IF(H91="Etapa",CONCATENATE(TEXT(B91,"00"),".",TEXT(C91,"000")),IF(H91="Subetapa",CONCATENATE(TEXT(B91,"00"),".",TEXT(C91,"000"),".",TEXT(D91,"000")),IF(H91="Serviço",CONCATENATE(TEXT(B91,"00"),".",TEXT(C91,"000"),".",TEXT(D91,"000"),".",TEXT(E91,"000")),""))))) -> 02.002.003.009 | J91: Manutenção provisória do canteiro | K91: mês | L91: ='Obra '!$E$7 -> 42 | M91: 5199.4629 | N91: =IF(H91="Serviço",M91*L91,IF(H91="CÉLULA CONSTRUTIVA",SUMIFS($N$8:$N$418,$B$8:$B$418,B91,$H$8:$H$418,"Serviço"),IF(H91="ETAPA",SUMIFS($N$8:$N$418,$B$8:$B$418,B91,$C$8:$C$418,C91,$H$8:$H$418,"Serviço"),IF(H91="SUBETAPA",SUMIFS($N$8:$N$418,$B$8:$B$418,B91,$C$8:$C$418,C91,$D$8:$D$418,D91,$H$8:$H$418,"Serviço"),0)))) -> 218377.44 | O91: Estimado com base em índices históricos | P91: Lançado ERP
A92: =IF($H92="UNIDADE CONSTRUTIVA",OFFSET(A92,-1,0)+1,LARGE(A$3:A91,1)) -> 0 | B92: =IF(H92="UNIDADE CONSTRUTIVA",0,IF(H92="CÉLULA CONSTRUTIVA",OFFSET(B92,-1,0)+1,OFFSET(B92,-1,0))) -> 2 | C92: =IF(H92="CÉLULA CONSTRUTIVA",0,IF(H92="ETAPA",OFFSET(C92,-1,0)+1,OFFSET(C92,-1,0))) -> 2 | D92: =IF(H92="ETAPA",0,IF(H92="SUBETAPA",OFFSET(D92,-1,0)+1,OFFSET(D92,-1,0))) -> 3 | E92: =IF(H92="Subetapa",0,IF(H92="serviço",OFFSET(E92,-1,0)+1,OFFSET(E92,-1,0))) -> 10 | H92: SERVIÇO | I92: =IF(H92="Unidade Construtiva",TEXT(A92,"00"),IF(H92="Célula Construtiva",TEXT(B92,"00"),IF(H92="Etapa",CONCATENATE(TEXT(B92,"00"),".",TEXT(C92,"000")),IF(H92="Subetapa",CONCATENATE(TEXT(B92,"00"),".",TEXT(C92,"000"),".",TEXT(D92,"000")),IF(H92="Serviço",CONCATENATE(TEXT(B92,"00"),".",TEXT(C92,"000"),".",TEXT(D92,"000"),".",TEXT(E92,"000")),""))))) -> 02.002.003.010 | J92: Manutenção provisória elétrica | K92: mês | L92: ='Obra '!$E$7 -> 42 | M92: 453.16771 | N92: =IF(H92="Serviço",M92*L92,IF(H92="CÉLULA CONSTRUTIVA",SUMIFS($N$8:$N$418,$B$8:$B$418,B92,$H$8:$H$418,"Serviço"),IF(H92="ETAPA",SUMIFS($N$8:$N$418,$B$8:$B$418,B92,$C$8:$C$418,C92,$H$8:$H$418,"Serviço"),IF(H92="SUBETAPA",SUMIFS($N$8:$N$418,$B$8:$B$418,B92,$C$8:$C$418,C92,$D$8:$D$418,D92,$H$8:$H$418,"Serviço"),0)))) -> 19033.044 | O92: Estimado com base em índices históricos | P92: Lançado ERP
A93: =IF($H93="UNIDADE CONSTRUTIVA",OFFSET(A93,-1,0)+1,LARGE(A$3:A92,1)) -> 0 | B93: =IF(H93="UNIDADE CONSTRUTIVA",0,IF(H93="CÉLULA CONSTRUTIVA",OFFSET(B93,-1,0)+1,OFFSET(B93,-1,0))) -> 2 | C93: =IF(H93="CÉLULA CONSTRUTIVA",0,IF(H93="ETAPA",OFFSET(C93,-1,0)+1,OFFSET(C93,-1,0))) -> 2 | D93: =IF(H93="ETAPA",0,IF(H93="SUBETAPA",OFFSET(D93,-1,0)+1,OFFSET(D93,-1,0))) -> 3 | E93: =IF(H93="Subetapa",0,IF(H93="serviço",OFFSET(E93,-1,0)+1,OFFSET(E93,-1,0))) -> 11 | H93: SERVIÇO | I93: =IF(H93="Unidade Construtiva",TEXT(A93,"00"),IF(H93="Célula Construtiva",TEXT(B93,"00"),IF(H93="Etapa",CONCATENATE(TEXT(B93,"00"),".",TEXT(C93,"000")),IF(H93="Subetapa",CONCATENATE(TEXT(B93,"00"),".",TEXT(C93,"000"),".",TEXT(D93,"000")),IF(H93="Serviço",CONCATENATE(TEXT(B93,"00"),".",TEXT(C93,"000"),".",TEXT(D93,"000"),".",TEXT(E93,"000")),""))))) -> 02.002.003.011 | J93: Manutenção provisória hidrossanitária | K93: mês | L93: ='Obra '!$E$7 -> 42 | M93: 317.2174 | N93: =IF(H93="Serviço",M93*L93,IF(H93="CÉLULA CONSTRUTIVA",SUMIFS($N$8:$N$418,$B$8:$B$418,B93,$H$8:$H$418,"Serviço"),IF(H93="ETAPA",SUMIFS($N$8:$N$418,$B$8:$B$418,B93,$C$8:$C$418,C93,$H$8:$H$418,"Serviço"),IF(H93="SUBETAPA",SUMIFS($N$8:$N$418,$B$8:$B$418,B93,$C$8:$C$418,C93,$D$8:$D$418,D93,$H$8:$H$418,"Serviço"),0)))) -> 13323.131 | O93: Estimado com base em índices históricos | P93: Lançado ERP
A94: =IF($H94="UNIDADE CONSTRUTIVA",OFFSET(A94,-1,0)+1,LARGE(A$3:A93,1)) -> 0 | B94: =IF(H94="UNIDADE CONSTRUTIVA",0,IF(H94="CÉLULA CONSTRUTIVA",OFFSET(B94,-1,0)+1,OFFSET(B94,-1,0))) -> 2 | C94: =IF(H94="CÉLULA CONSTRUTIVA",0,IF(H94="ETAPA",OFFSET(C94,-1,0)+1,OFFSET(C94,-1,0))) -> 2 | D94: =IF(H94="ETAPA",0,IF(H94="SUBETAPA",OFFSET(D94,-1,0)+1,OFFSET(D94,-1,0))) -> 3 | E94: =IF(H94="Subetapa",0,IF(H94="serviço",OFFSET(E94,-1,0)+1,OFFSET(E94,-1,0))) -> 12 | H94: SERVIÇO | I94: =IF(H94="Unidade Construtiva",TEXT(A94,"00"),IF(H94="Célula Construtiva",TEXT(B94,"00"),IF(H94="Etapa",CONCATENATE(TEXT(B94,"00"),".",TEXT(C94,"000")),IF(H94="Subetapa",CONCATENATE(TEXT(B94,"00"),".",TEXT(C94,"000"),".",TEXT(D94,"000")),IF(H94="Serviço",CONCATENATE(TEXT(B94,"00"),".",TEXT(C94,"000"),".",TEXT(D94,"000"),".",TEXT(E94,"000")),""))))) -> 02.002.003.012 | J94: Manutenção provisória vigilância e acessos | K94: mês | L94: ='Obra '!$E$7 -> 42 | M94: 209.11875 | N94: =IF(H94="Serviço",M94*L94,IF(H94="CÉLULA CONSTRUTIVA",SUMIFS($N$8:$N$418,$B$8:$B$418,B94,$H$8:$H$418,"Serviço"),IF(H94="ETAPA",SUMIFS($N$8:$N$418,$B$8:$B$418,B94,$C$8:$C$418,C94,$H$8:$H$418,"Serviço"),IF(H94="SUBETAPA",SUMIFS($N$8:$N$418,$B$8:$B$418,B94,$C$8:$C$418,C94,$D$8:$D$418,D94,$H$8:$H$418,"Serviço"),0)))) -> 8782.9874 | O94: Estimado com base em índices históricos | P94: Lançado ERP
A95: =IF($H95="UNIDADE CONSTRUTIVA",OFFSET(A95,-1,0)+1,LARGE(A$3:A94,1)) -> 0 | B95: =IF(H95="UNIDADE CONSTRUTIVA",0,IF(H95="CÉLULA CONSTRUTIVA",OFFSET(B95,-1,0)+1,OFFSET(B95,-1,0))) -> 2 | C95: =IF(H95="CÉLULA CONSTRUTIVA",0,IF(H95="ETAPA",OFFSET(C95,-1,0)+1,OFFSET(C95,-1,0))) -> 2 | D95: =IF(H95="ETAPA",0,IF(H95="SUBETAPA",OFFSET(D95,-1,0)+1,OFFSET(D95,-1,0))) -> 4 | E95: =IF(H95="Subetapa",0,IF(H95="serviço",OFFSET(E95,-1,0)+1,OFFSET(E95,-1,0))) -> 0 | H95: SUBETAPA | I95: =IF(H95="Unidade Construtiva",TEXT(A95,"00"),IF(H95="Célula Construtiva",TEXT(B95,"00"),IF(H95="Etapa",CONCATENATE(TEXT(B95,"00"),".",TEXT(C95,"000")),IF(H95="Subetapa",CONCATENATE(TEXT(B95,"00"),".",TEXT(C95,"000"),".",TEXT(D95,"000")),IF(H95="Serviço",CONCATENATE(TEXT(B95,"00"),".",TEXT(C95,"000"),".",TEXT(D95,"000"),".",TEXT(E95,"000")),""))))) -> 02.002.004 | J95: Instalações Provisórias de Canteiro de Obra | N95: =IF(H95="Serviço",M95*L95,IF(H95="CÉLULA CONSTRUTIVA",SUMIFS($N$8:$N$418,$B$8:$B$418,B95,$H$8:$H$418,"Serviço"),IF(H95="ETAPA",SUMIFS($N$8:$N$418,$B$8:$B$418,B95,$C$8:$C$418,C95,$H$8:$H$418,"Serviço"),IF(H95="SUBETAPA",SUMIFS($N$8:$N$418,$B$8:$B$418,B95,$C$8:$C$418,C95,$D$8:$D$418,D95,$H$8:$H$418,"Serviço"),0)))) -> 112824.94
A96: =IF($H96="UNIDADE CONSTRUTIVA",OFFSET(A96,-1,0)+1,LARGE(A$3:A95,1)) -> 0 | B96: =IF(H96="UNIDADE CONSTRUTIVA",0,IF(H96="CÉLULA CONSTRUTIVA",OFFSET(B96,-1,0)+1,OFFSET(B96,-1,0))) -> 2 | C96: =IF(H96="CÉLULA CONSTRUTIVA",0,IF(H96="ETAPA",OFFSET(C96,-1,0)+1,OFFSET(C96,-1,0))) -> 2 | D96: =IF(H96="ETAPA",0,IF(H96="SUBETAPA",OFFSET(D96,-1,0)+1,OFFSET(D96,-1,0))) -> 4 | E96: =IF(H96="Subetapa",0,IF(H96="serviço",OFFSET(E96,-1,0)+1,OFFSET(E96,-1,0))) -> 1 | H96: SERVIÇO | I96: =IF(H96="Unidade Construtiva",TEXT(A96,"00"),IF(H96="Célula Construtiva",TEXT(B96,"00"),IF(H96="Etapa",CONCATENATE(TEXT(B96,"00"),".",TEXT(C96,"000")),IF(H96="Subetapa",CONCATENATE(TEXT(B96,"00"),".",TEXT(C96,"000"),".",TEXT(D96,"000")),IF(H96="Serviço",CONCATENATE(TEXT(B96,"00"),".",TEXT(C96,"000"),".",TEXT(D96,"000"),".",TEXT(E96,"000")),""))))) -> 02.002.004.001 | J96: Instalações Provisórias (central de aço, formas, argamassa, almoxarifado geral, construções temporárias) | K96: vb | L96: 1 | M96: 97935.978 | N96: =IF(H96="Serviço",M96*L96,IF(H96="CÉLULA CONSTRUTIVA",SUMIFS($N$8:$N$418,$B$8:$B$418,B96,$H$8:$H$418,"Serviço"),IF(H96="ETAPA",SUMIFS($N$8:$N$418,$B$8:$B$418,B96,$C$8:$C$418,C96,$H$8:$H$418,"Serviço"),IF(H96="SUBETAPA",SUMIFS($N$8:$N$418,$B$8:$B$418,B96,$C$8:$C$418,C96,$D$8:$D$418,D96,$H$8:$H$418,"Serviço"),0)))) -> 97935.978 | O96: Estimado com base em índices históricos | P96: Lançado ERP
A97: =IF($H97="UNIDADE CONSTRUTIVA",OFFSET(A97,-1,0)+1,LARGE(A$3:A96,1)) -> 0 | B97: =IF(H97="UNIDADE CONSTRUTIVA",0,IF(H97="CÉLULA CONSTRUTIVA",OFFSET(B97,-1,0)+1,OFFSET(B97,-1,0))) -> 2 | C97: =IF(H97="CÉLULA CONSTRUTIVA",0,IF(H97="ETAPA",OFFSET(C97,-1,0)+1,OFFSET(C97,-1,0))) -> 2 | D97: =IF(H97="ETAPA",0,IF(H97="SUBETAPA",OFFSET(D97,-1,0)+1,OFFSET(D97,-1,0))) -> 4 | E97: =IF(H97="Subetapa",0,IF(H97="serviço",OFFSET(E97,-1,0)+1,OFFSET(E97,-1,0))) -> 2 | H97: SERVIÇO | I97: =IF(H97="Unidade Construtiva",TEXT(A97,"00"),IF(H97="Célula Construtiva",TEXT(B97,"00"),IF(H97="Etapa",CONCATENATE(TEXT(B97,"00"),".",TEXT(C97,"000")),IF(H97="Subetapa",CONCATENATE(TEXT(B97,"00"),".",TEXT(C97,"000"),".",TEXT(D97,"000")),IF(H97="Serviço",CONCATENATE(TEXT(B97,"00"),".",TEXT(C97,"000"),".",TEXT(D97,"000"),".",TEXT(E97,"000")),""))))) -> 02.002.004.002 | J97: Tapume de telha metálica trapezoidal | K97: m2 | L97: =EPCs!D54 -> 90.744 | M97: 164.0766 | N97: =IF(H97="Serviço",M97*L97,IF(H97="CÉLULA CONSTRUTIVA",SUMIFS($N$8:$N$418,$B$8:$B$418,B97,$H$8:$H$418,"Serviço"),IF(H97="ETAPA",SUMIFS($N$8:$N$418,$B$8:$B$418,B97,$C$8:$C$418,C97,$H$8:$H$418,"Serviço"),IF(H97="SUBETAPA",SUMIFS($N$8:$N$418,$B$8:$B$418,B97,$C$8:$C$418,C97,$D$8:$D$418,D97,$H$8:$H$418,"Serviço"),0)))) -> 14888.967 | O97: Estimado com base em índices históricos | P97: Lançado ERP
A98: =IF($H98="UNIDADE CONSTRUTIVA",OFFSET(A98,-1,0)+1,LARGE(A$3:A97,1)) -> 0 | B98: =IF(H98="UNIDADE CONSTRUTIVA",0,IF(H98="CÉLULA CONSTRUTIVA",OFFSET(B98,-1,0)+1,OFFSET(B98,-1,0))) -> 2 | C98: =IF(H98="CÉLULA CONSTRUTIVA",0,IF(H98="ETAPA",OFFSET(C98,-1,0)+1,OFFSET(C98,-1,0))) -> 2 | D98: =IF(H98="ETAPA",0,IF(H98="SUBETAPA",OFFSET(D98,-1,0)+1,OFFSET(D98,-1,0))) -> 5 | E98: =IF(H98="Subetapa",0,IF(H98="serviço",OFFSET(E98,-1,0)+1,OFFSET(E98,-1,0))) -> 0 | H98: SUBETAPA | I98: =IF(H98="Unidade Construtiva",TEXT(A98,"00"),IF(H98="Célula Construtiva",TEXT(B98,"00"),IF(H98="Etapa",CONCATENATE(TEXT(B98,"00"),".",TEXT(C98,"000")),IF(H98="Subetapa",CONCATENATE(TEXT(B98,"00"),".",TEXT(C98,"000"),".",TEXT(D98,"000")),IF(H98="Serviço",CONCATENATE(TEXT(B98,"00"),".",TEXT(C98,"000"),".",TEXT(D98,"000"),".",TEXT(E98,"000")),""))))) -> 02.002.005 | J98: Ligações Provisórias | N98: =IF(H98="Serviço",M98*L98,IF(H98="CÉLULA CONSTRUTIVA",SUMIFS($N$8:$N$418,$B$8:$B$418,B98,$H$8:$H$418,"Serviço"),IF(H98="ETAPA",SUMIFS($N$8:$N$418,$B$8:$B$418,B98,$C$8:$C$418,C98,$H$8:$H$418,"Serviço"),IF(H98="SUBETAPA",SUMIFS($N$8:$N$418,$B$8:$B$418,B98,$C$8:$C$418,C98,$D$8:$D$418,D98,$H$8:$H$418,"Serviço"),0)))) -> 15334.695
A99: =IF($H99="UNIDADE CONSTRUTIVA",OFFSET(A99,-1,0)+1,LARGE(A$3:A98,1)) -> 0 | B99: =IF(H99="UNIDADE CONSTRUTIVA",0,IF(H99="CÉLULA CONSTRUTIVA",OFFSET(B99,-1,0)+1,OFFSET(B99,-1,0))) -> 2 | C99: =IF(H99="CÉLULA CONSTRUTIVA",0,IF(H99="ETAPA",OFFSET(C99,-1,0)+1,OFFSET(C99,-1,0))) -> 2 | D99: =IF(H99="ETAPA",0,IF(H99="SUBETAPA",OFFSET(D99,-1,0)+1,OFFSET(D99,-1,0))) -> 5 | E99: =IF(H99="Subetapa",0,IF(H99="serviço",OFFSET(E99,-1,0)+1,OFFSET(E99,-1,0))) -> 1 | H99: SERVIÇO | I99: =IF(H99="Unidade Construtiva",TEXT(A99,"00"),IF(H99="Célula Construtiva",TEXT(B99,"00"),IF(H99="Etapa",CONCATENATE(TEXT(B99,"00"),".",TEXT(C99,"000")),IF(H99="Subetapa",CONCATENATE(TEXT(B99,"00"),".",TEXT(C99,"000"),".",TEXT(D99,"000")),IF(H99="Serviço",CONCATENATE(TEXT(B99,"00"),".",TEXT(C99,"000"),".",TEXT(D99,"000"),".",TEXT(E99,"000")),""))))) -> 02.002.005.001 | J99: Redes Provisórias: Rede de água fria, esgoto e drenagem | K99: vb | L99: 1 | M99: 8130.061 | N99: =IF(H99="Serviço",M99*L99,IF(H99="CÉLULA CONSTRUTIVA",SUMIFS($N$8:$N$418,$B$8:$B$418,B99,$H$8:$H$418,"Serviço"),IF(H99="ETAPA",SUMIFS($N$8:$N$418,$B$8:$B$418,B99,$C$8:$C$418,C99,$H$8:$H$418,"Serviço"),IF(H99="SUBETAPA",SUMIFS($N$8:$N$418,$B$8:$B$418,B99,$C$8:$C$418,C99,$D$8:$D$418,D99,$H$8:$H$418,"Serviço"),0)))) -> 8130.061 | O99: Estimado com base em índices históricos | P99: Lançado ERP
A100: =IF($H100="UNIDADE CONSTRUTIVA",OFFSET(A100,-1,0)+1,LARGE(A$3:A99,1)) -> 0 | B100: =IF(H100="UNIDADE CONSTRUTIVA",0,IF(H100="CÉLULA CONSTRUTIVA",OFFSET(B100,-1,0)+1,OFFSET(B100,-1,0))) -> 2 | C100: =IF(H100="CÉLULA CONSTRUTIVA",0,IF(H100="ETAPA",OFFSET(C100,-1,0)+1,OFFSET(C100,-1,0))) -> 2 | D100: =IF(H100="ETAPA",0,IF(H100="SUBETAPA",OFFSET(D100,-1,0)+1,OFFSET(D100,-1,0))) -> 5 | E100: =IF(H100="Subetapa",0,IF(H100="serviço",OFFSET(E100,-1,0)+1,OFFSET(E100,-1,0))) -> 2 | H100: SERVIÇO | I100: =IF(H100="Unidade Construtiva",TEXT(A100,"00"),IF(H100="Célula Construtiva",TEXT(B100,"00"),IF(H100="Etapa",CONCATENATE(TEXT(B100,"00"),".",TEXT(C100,"000")),IF(H100="Subetapa",CONCATENATE(TEXT(B100,"00"),".",TEXT(C100,"000"),".",TEXT(D100,"000")),IF(H100="Serviço",CONCATENATE(TEXT(B100,"00"),".",TEXT(C100,"000"),".",TEXT(D100,"000"),".",TEXT(E100,"000")),""))))) -> 02.002.005.002 | J100: Redes Provisórias: Redes elétricas, comunicação e dados | K100: vb | L100: 1 | M100: 7204.6344 | N100: =IF(H100="Serviço",M100*L100,IF(H100="CÉLULA CONSTRUTIVA",SUMIFS($N$8:$N$418,$B$8:$B$418,B100,$H$8:$H$418,"Serviço"),IF(H100="ETAPA",SUMIFS($N$8:$N$418,$B$8:$B$418,B100,$C$8:$C$418,C100,$H$8:$H$418,"Serviço"),IF(H100="SUBETAPA",SUMIFS($N$8:$N$418,$B$8:$B$418,B100,$C$8:$C$418,C100,$D$8:$D$418,D100,$H$8:$H$418,"Serviço"),0)))) -> 7204.6344 | O100: Estimado com base em índices históricos | P100: Lançado ERP
A101: =IF($H101="UNIDADE CONSTRUTIVA",OFFSET(A101,-1,0)+1,LARGE(A$3:A100,1)) -> 0 | B101: =IF(H101="UNIDADE CONSTRUTIVA",0,IF(H101="CÉLULA CONSTRUTIVA",OFFSET(B101,-1,0)+1,OFFSET(B101,-1,0))) -> 3 | C101: =IF(H101="CÉLULA CONSTRUTIVA",0,IF(H101="ETAPA",OFFSET(C101,-1,0)+1,OFFSET(C101,-1,0))) -> 0 | D101: =IF(H101="ETAPA",0,IF(H101="SUBETAPA",OFFSET(D101,-1,0)+1,OFFSET(D101,-1,0))) -> 5 | E101: =IF(H101="Subetapa",0,IF(H101="serviço",OFFSET(E101,-1,0)+1,OFFSET(E101,-1,0))) -> 2 | H101: CÉLULA CONSTRUTIVA | I101: =IF(H101="Unidade Construtiva",TEXT(A101,"00"),IF(H101="Célula Construtiva",TEXT(B101,"00"),IF(H101="Etapa",CONCATENATE(TEXT(B101,"00"),".",TEXT(C101,"000")),IF(H101="Subetapa",CONCATENATE(TEXT(B101,"00"),".",TEXT(C101,"000"),".",TEXT(D101,"000")),IF(H101="Serviço",CONCATENATE(TEXT(B101,"00"),".",TEXT(C101,"000"),".",TEXT(D101,"000"),".",TEXT(E101,"000")),""))))) -> 03 | J101: EQUIPAMENTOS | N101: =IF(H101="Serviço",M101*L101,IF(H101="CÉLULA CONSTRUTIVA",SUMIFS($N$8:$N$418,$B$8:$B$418,B101,$H$8:$H$418,"Serviço"),IF(H101="ETAPA",SUMIFS($N$8:$N$418,$B$8:$B$418,B101,$C$8:$C$418,C101,$H$8:$H$418,"Serviço"),IF(H101="SUBETAPA",SUMIFS($N$8:$N$418,$B$8:$B$418,B101,$C$8:$C$418,C101,$D$8:$D$418,D101,$H$8:$H$418,"Serviço"),0)))) -> 479260
A102: =IF($H102="UNIDADE CONSTRUTIVA",OFFSET(A102,-1,0)+1,LARGE(A$3:A101,1)) -> 0 | B102: =IF(H102="UNIDADE CONSTRUTIVA",0,IF(H102="CÉLULA CONSTRUTIVA",OFFSET(B102,-1,0)+1,OFFSET(B102,-1,0))) -> 3 | C102: =IF(H102="CÉLULA CONSTRUTIVA",0,IF(H102="ETAPA",OFFSET(C102,-1,0)+1,OFFSET(C102,-1,0))) -> 1 | D102: =IF(H102="ETAPA",0,IF(H102="SUBETAPA",OFFSET(D102,-1,0)+1,OFFSET(D102,-1,0))) -> 0 | E102: =IF(H102="Subetapa",0,IF(H102="serviço",OFFSET(E102,-1,0)+1,OFFSET(E102,-1,0))) -> 2 | H102: ETAPA | I102: =IF(H102="Unidade Construtiva",TEXT(A102,"00"),IF(H102="Célula Construtiva",TEXT(B102,"00"),IF(H102="Etapa",CONCATENATE(TEXT(B102,"00"),".",TEXT(C102,"000")),IF(H102="Subetapa",CONCATENATE(TEXT(B102,"00"),".",TEXT(C102,"000"),".",TEXT(D102,"000")),IF(H102="Serviço",CONCATENATE(TEXT(B102,"00"),".",TEXT(C102,"000"),".",TEXT(D102,"000"),".",TEXT(E102,"000")),""))))) -> 03.001 | J102: EQUIPAMENTOS | N102: =IF(H102="Serviço",M102*L102,IF(H102="CÉLULA CONSTRUTIVA",SUMIFS($N$8:$N$418,$B$8:$B$418,B102,$H$8:$H$418,"Serviço"),IF(H102="ETAPA",SUMIFS($N$8:$N$418,$B$8:$B$418,B102,$C$8:$C$418,C102,$H$8:$H$418,"Serviço"),IF(H102="SUBETAPA",SUMIFS($N$8:$N$418,$B$8:$B$418,B102,$C$8:$C$418,C102,$D$8:$D$418,D102,$H$8:$H$418,"Serviço"),0)))) -> 479260
A103: =IF($H103="UNIDADE CONSTRUTIVA",OFFSET(A103,-1,0)+1,LARGE(A$3:A102,1)) -> 0 | B103: =IF(H103="UNIDADE CONSTRUTIVA",0,IF(H103="CÉLULA CONSTRUTIVA",OFFSET(B103,-1,0)+1,OFFSET(B103,-1,0))) -> 3 | C103: =IF(H103="CÉLULA CONSTRUTIVA",0,IF(H103="ETAPA",OFFSET(C103,-1,0)+1,OFFSET(C103,-1,0))) -> 1 | D103: =IF(H103="ETAPA",0,IF(H103="SUBETAPA",OFFSET(D103,-1,0)+1,OFFSET(D103,-1,0))) -> 1 | E103: =IF(H103="Subetapa",0,IF(H103="serviço",OFFSET(E103,-1,0)+1,OFFSET(E103,-1,0))) -> 0 | H103: SUBETAPA | I103: =IF(H103="Unidade Construtiva",TEXT(A103,"00"),IF(H103="Célula Construtiva",TEXT(B103,"00"),IF(H103="Etapa",CONCATENATE(TEXT(B103,"00"),".",TEXT(C103,"000")),IF(H103="Subetapa",CONCATENATE(TEXT(B103,"00"),".",TEXT(C103,"000"),".",TEXT(D103,"000")),IF(H103="Serviço",CONCATENATE(TEXT(B103,"00"),".",TEXT(C103,"000"),".",TEXT(D103,"000"),".",TEXT(E103,"000")),""))))) -> 03.001.001 | J103: Equipamentos de Obra | N103: =IF(H103="Serviço",M103*L103,IF(H103="CÉLULA CONSTRUTIVA",SUMIFS($N$8:$N$418,$B$8:$B$418,B103,$H$8:$H$418,"Serviço"),IF(H103="ETAPA",SUMIFS($N$8:$N$418,$B$8:$B$418,B103,$C$8:$C$418,C103,$H$8:$H$418,"Serviço"),IF(H103="SUBETAPA",SUMIFS($N$8:$N$418,$B$8:$B$418,B103,$C$8:$C$418,C103,$D$8:$D$418,D103,$H$8:$H$418,"Serviço"),0)))) -> 393100
...

Sheet Ger_Executivo
G4: PROJETO: | I4: ='Ger_Tec e Adm'!I4 -> Mosaico | O4: REVISÃO: | P4: DATA
G5: EMPRESA: | I5: ='Ger_Tec e Adm'!I5 -> Grupo DUO | O5: R00
A6: Unidade Construtiva | B6: Célula Construtiva | C6: Etapa | D6: Subetapa | E6: Serviço | G6: GERENCIAMENTO EXECUTIVO
A7: 0 | B7: 0 | C7: 0 | D7: 0 | E7: 0 | G7: Atalho | H7: NIVEL | I7: Item | J7: Descrição | K7: Unidade | L7: Quant. | M7: Preço un | N7: Total | O7: Considerações | P7: Situação
A8: =IF($H8="UNIDADE CONSTRUTIVA",OFFSET(A8,-1,0)+1,LARGE(A$3:A7,1)) -> 0 | B8: =IF(H8="UNIDADE CONSTRUTIVA",0,IF(H8="CÉLULA CONSTRUTIVA",OFFSET(B8,-1,0)+1,OFFSET(B8,-1,0))) -> 1 | C8: =IF(H8="CÉLULA CONSTRUTIVA",0,IF(H8="ETAPA",OFFSET(C8,-1,0)+1,OFFSET(C8,-1,0))) -> 0 | D8: =IF(H8="ETAPA",0,IF(H8="SUBETAPA",OFFSET(D8,-1,0)+1,OFFSET(D8,-1,0))) -> 0 | E8: =IF(H8="Subetapa",0,IF(H8="serviço",OFFSET(E8,-1,0)+1,OFFSET(E8,-1,0))) -> 0 | H8: CÉLULA CONSTRUTIVA | I8: =IF(H8="Unidade Construtiva",TEXT(A8,"00"),IF(H8="Célula Construtiva",TEXT(B8,"00"),IF(H8="Etapa",CONCATENATE(TEXT(B8,"00"),".",TEXT(C8,"000")),IF(H8="Subetapa",CONCATENATE(TEXT(B8,"00"),".",TEXT(C8,"000"),".",TEXT(D8,"000")),IF(H8="Serviço",CONCATENATE(TEXT(B8,"00"),".",TEXT(C8,"000"),".",TEXT(D8,"000"),".",TEXT(E8,"000")),""))))) -> 01 | J8: MOVIMENTAÇÃO DE TERRA | N8: =IF(H8="Serviço",M8*L8,IF(H8="CÉLULA CONSTRUTIVA",SUMIFS($N$8:$N$352,$B$8:$B$352,B8,$H$8:$H$352,"Serviço"),IF(H8="ETAPA",SUMIFS($N$8:$N$352,$B$8:$B$352,B8,$C$8:$C$352,C8,$H$8:$H$352,"Serviço"),IF(H8="SUBETAPA",SUMIFS($N$8:$N$352,$B$8:$B$352,B8,$C$8:$C$352,C8,$D$8:$D$352,D8,$H$8:$H$352,"Serviço"),0)))) -> 96602.73 | Q8: =N8/'Obra '!$C$53 -> 0.0031225272
A9: =IF($H9="UNIDADE CONSTRUTIVA",OFFSET(A9,-1,0)+1,LARGE(A$3:A8,1)) -> 0 | B9: =IF(H9="UNIDADE CONSTRUTIVA",0,IF(H9="CÉLULA CONSTRUTIVA",OFFSET(B9,-1,0)+1,OFFSET(B9,-1,0))) -> 1 | C9: =IF(H9="CÉLULA CONSTRUTIVA",0,IF(H9="ETAPA",OFFSET(C9,-1,0)+1,OFFSET(C9,-1,0))) -> 1 | D9: =IF(H9="ETAPA",0,IF(H9="SUBETAPA",OFFSET(D9,-1,0)+1,OFFSET(D9,-1,0))) -> 0 | E9: =IF(H9="Subetapa",0,IF(H9="serviço",OFFSET(E9,-1,0)+1,OFFSET(E9,-1,0))) -> 0 | H9: ETAPA | I9: =IF(H9="Unidade Construtiva",TEXT(A9,"00"),IF(H9="Célula Construtiva",TEXT(B9,"00"),IF(H9="Etapa",CONCATENATE(TEXT(B9,"00"),".",TEXT(C9,"000")),IF(H9="Subetapa",CONCATENATE(TEXT(B9,"00"),".",TEXT(C9,"000"),".",TEXT(D9,"000")),IF(H9="Serviço",CONCATENATE(TEXT(B9,"00"),".",TEXT(C9,"000"),".",TEXT(D9,"000"),".",TEXT(E9,"000")),""))))) -> 01.001 | J9: MOVIMENTAÇÃO DE TERRA | N9: =IF(H9="Serviço",M9*L9,IF(H9="CÉLULA CONSTRUTIVA",SUMIFS($N$8:$N$352,$B$8:$B$352,B9,$H$8:$H$352,"Serviço"),IF(H9="ETAPA",SUMIFS($N$8:$N$352,$B$8:$B$352,B9,$C$8:$C$352,C9,$H$8:$H$352,"Serviço"),IF(H9="SUBETAPA",SUMIFS($N$8:$N$352,$B$8:$B$352,B9,$C$8:$C$352,C9,$D$8:$D$352,D9,$H$8:$H$352,"Serviço"),0)))) -> 96602.73
A10: =IF($H10="UNIDADE CONSTRUTIVA",OFFSET(A10,-1,0)+1,LARGE(A$3:A9,1)) -> 0 | B10: =IF(H10="UNIDADE CONSTRUTIVA",0,IF(H10="CÉLULA CONSTRUTIVA",OFFSET(B10,-1,0)+1,OFFSET(B10,-1,0))) -> 1 | C10: =IF(H10="CÉLULA CONSTRUTIVA",0,IF(H10="ETAPA",OFFSET(C10,-1,0)+1,OFFSET(C10,-1,0))) -> 1 | D10: =IF(H10="ETAPA",0,IF(H10="SUBETAPA",OFFSET(D10,-1,0)+1,OFFSET(D10,-1,0))) -> 1 | E10: =IF(H10="Subetapa",0,IF(H10="serviço",OFFSET(E10,-1,0)+1,OFFSET(E10,-1,0))) -> 0 | H10: SUBETAPA | I10: =IF(H10="Unidade Construtiva",TEXT(A10,"00"),IF(H10="Célula Construtiva",TEXT(B10,"00"),IF(H10="Etapa",CONCATENATE(TEXT(B10,"00"),".",TEXT(C10,"000")),IF(H10="Subetapa",CONCATENATE(TEXT(B10,"00"),".",TEXT(C10,"000"),".",TEXT(D10,"000")),IF(H10="Serviço",CONCATENATE(TEXT(B10,"00"),".",TEXT(C10,"000"),".",TEXT(D10,"000"),".",TEXT(E10,"000")),""))))) -> 01.001.001 | J10: Escavação e Reaterro de Valas | N10: =IF(H10="Serviço",M10*L10,IF(H10="CÉLULA CONSTRUTIVA",SUMIFS($N$8:$N$352,$B$8:$B$352,B10,$H$8:$H$352,"Serviço"),IF(H10="ETAPA",SUMIFS($N$8:$N$352,$B$8:$B$352,B10,$C$8:$C$352,C10,$H$8:$H$352,"Serviço"),IF(H10="SUBETAPA",SUMIFS($N$8:$N$352,$B$8:$B$352,B10,$C$8:$C$352,C10,$D$8:$D$352,D10,$H$8:$H$352,"Serviço"),0)))) -> 52651.439
A11: =IF($H11="UNIDADE CONSTRUTIVA",OFFSET(A11,-1,0)+1,LARGE(A$3:A10,1)) -> 0 | B11: =IF(H11="UNIDADE CONSTRUTIVA",0,IF(H11="CÉLULA CONSTRUTIVA",OFFSET(B11,-1,0)+1,OFFSET(B11,-1,0))) -> 1 | C11: =IF(H11="CÉLULA CONSTRUTIVA",0,IF(H11="ETAPA",OFFSET(C11,-1,0)+1,OFFSET(C11,-1,0))) -> 1 | D11: =IF(H11="ETAPA",0,IF(H11="SUBETAPA",OFFSET(D11,-1,0)+1,OFFSET(D11,-1,0))) -> 1 | E11: =IF(H11="Subetapa",0,IF(H11="serviço",OFFSET(E11,-1,0)+1,OFFSET(E11,-1,0))) -> 1 | H11: SERVIÇO | I11: =IF(H11="Unidade Construtiva",TEXT(A11,"00"),IF(H11="Célula Construtiva",TEXT(B11,"00"),IF(H11="Etapa",CONCATENATE(TEXT(B11,"00"),".",TEXT(C11,"000")),IF(H11="Subetapa",CONCATENATE(TEXT(B11,"00"),".",TEXT(C11,"000"),".",TEXT(D11,"000")),IF(H11="Serviço",CONCATENATE(TEXT(B11,"00"),".",TEXT(C11,"000"),".",TEXT(D11,"000"),".",TEXT(E11,"000")),""))))) -> 01.001.001.001 | J11: Escavação mecanizada para blocos de fundação, vigas de fundação, dutos e cisternas, com retroescavadeira | K11: m3 | L11: ='Fundação Rasa'!G7+'Fundação Rasa'!G8 -> 1165.053 | M11: =IFERROR(VLOOKUP(J11,CPU!$D$2:$H$327,5,FALSE),0) -> 36.36 | N11: =IF(H11="Serviço",M11*L11,IF(H11="CÉLULA CONSTRUTIVA",SUMIFS($N$8:$N$352,$B$8:$B$352,B11,$H$8:$H$352,"Serviço"),IF(H11="ETAPA",SUMIFS($N$8:$N$352,$B$8:$B$352,B11,$C$8:$C$352,C11,$H$8:$H$352,"Serviço"),IF(H11="SUBETAPA",SUMIFS($N$8:$N$352,$B$8:$B$352,B11,$C$8:$C$352,C11,$D$8:$D$352,D11,$H$8:$H$352,"Serviço"),0)))) -> 42361.328 | P11: Finalizado
A12: =IF($H12="UNIDADE CONSTRUTIVA",OFFSET(A12,-1,0)+1,LARGE(A$3:A11,1)) -> 0 | B12: =IF(H12="UNIDADE CONSTRUTIVA",0,IF(H12="CÉLULA CONSTRUTIVA",OFFSET(B12,-1,0)+1,OFFSET(B12,-1,0))) -> 1 | C12: =IF(H12="CÉLULA CONSTRUTIVA",0,IF(H12="ETAPA",OFFSET(C12,-1,0)+1,OFFSET(C12,-1,0))) -> 1 | D12: =IF(H12="ETAPA",0,IF(H12="SUBETAPA",OFFSET(D12,-1,0)+1,OFFSET(D12,-1,0))) -> 1 | E12: =IF(H12="Subetapa",0,IF(H12="serviço",OFFSET(E12,-1,0)+1,OFFSET(E12,-1,0))) -> 2 | H12: SERVIÇO | I12: =IF(H12="Unidade Construtiva",TEXT(A12,"00"),IF(H12="Célula Construtiva",TEXT(B12,"00"),IF(H12="Etapa",CONCATENATE(TEXT(B12,"00"),".",TEXT(C12,"000")),IF(H12="Subetapa",CONCATENATE(TEXT(B12,"00"),".",TEXT(C12,"000"),".",TEXT(D12,"000")),IF(H12="Serviço",CONCATENATE(TEXT(B12,"00"),".",TEXT(C12,"000"),".",TEXT(D12,"000"),".",TEXT(E12,"000")),""))))) -> 01.001.001.002 | J12: Reaterro mecanizado de valas para blocos e vigas de fundação, com retroescavadeira | K12: m3 | L12: ='Fundação Rasa'!I7 -> 707.22413 | M12: =IFERROR(VLOOKUP(J12,CPU!$D$2:$H$327,5,FALSE),0) -> 14.55 | N12: =IF(H12="Serviço",M12*L12,IF(H12="CÉLULA CONSTRUTIVA",SUMIFS($N$8:$N$352,$B$8:$B$352,B12,$H$8:$H$352,"Serviço"),IF(H12="ETAPA",SUMIFS($N$8:$N$352,$B$8:$B$352,B12,$C$8:$C$352,C12,$H$8:$H$352,"Serviço"),IF(H12="SUBETAPA",SUMIFS($N$8:$N$352,$B$8:$B$352,B12,$C$8:$C$352,C12,$D$8:$D$352,D12,$H$8:$H$352,"Serviço"),0)))) -> 10290.111 | P12: Finalizado
A13: =IF($H13="UNIDADE CONSTRUTIVA",OFFSET(A13,-1,0)+1,LARGE(A$3:A12,1)) -> 0 | B13: =IF(H13="UNIDADE CONSTRUTIVA",0,IF(H13="CÉLULA CONSTRUTIVA",OFFSET(B13,-1,0)+1,OFFSET(B13,-1,0))) -> 1 | C13: =IF(H13="CÉLULA CONSTRUTIVA",0,IF(H13="ETAPA",OFFSET(C13,-1,0)+1,OFFSET(C13,-1,0))) -> 1 | D13: =IF(H13="ETAPA",0,IF(H13="SUBETAPA",OFFSET(D13,-1,0)+1,OFFSET(D13,-1,0))) -> 2 | E13: =IF(H13="Subetapa",0,IF(H13="serviço",OFFSET(E13,-1,0)+1,OFFSET(E13,-1,0))) -> 0 | H13: SUBETAPA | I13: =IF(H13="Unidade Construtiva",TEXT(A13,"00"),IF(H13="Célula Construtiva",TEXT(B13,"00"),IF(H13="Etapa",CONCATENATE(TEXT(B13,"00"),".",TEXT(C13,"000")),IF(H13="Subetapa",CONCATENATE(TEXT(B13,"00"),".",TEXT(C13,"000"),".",TEXT(D13,"000")),IF(H13="Serviço",CONCATENATE(TEXT(B13,"00"),".",TEXT(C13,"000"),".",TEXT(D13,"000"),".",TEXT(E13,"000")),""))))) -> 01.001.002 | J13: Lastro de brita | N13: =IF(H13="Serviço",M13*L13,IF(H13="CÉLULA CONSTRUTIVA",SUMIFS($N$8:$N$352,$B$8:$B$352,B13,$H$8:$H$352,"Serviço"),IF(H13="ETAPA",SUMIFS($N$8:$N$352,$B$8:$B$352,B13,$C$8:$C$352,C13,$H$8:$H$352,"Serviço"),IF(H13="SUBETAPA",SUMIFS($N$8:$N$352,$B$8:$B$352,B13,$C$8:$C$352,C13,$D$8:$D$352,D13,$H$8:$H$352,"Serviço"),0)))) -> 5890.2441
A14: =IF($H14="UNIDADE CONSTRUTIVA",OFFSET(A14,-1,0)+1,LARGE(A$3:A13,1)) -> 0 | B14: =IF(H14="UNIDADE CONSTRUTIVA",0,IF(H14="CÉLULA CONSTRUTIVA",OFFSET(B14,-1,0)+1,OFFSET(B14,-1,0))) -> 1 | C14: =IF(H14="CÉLULA CONSTRUTIVA",0,IF(H14="ETAPA",OFFSET(C14,-1,0)+1,OFFSET(C14,-1,0))) -> 1 | D14: =IF(H14="ETAPA",0,IF(H14="SUBETAPA",OFFSET(D14,-1,0)+1,OFFSET(D14,-1,0))) -> 2 | E14: =IF(H14="Subetapa",0,IF(H14="serviço",OFFSET(E14,-1,0)+1,OFFSET(E14,-1,0))) -> 1 | H14: SERVIÇO | I14: =IF(H14="Unidade Construtiva",TEXT(A14,"00"),IF(H14="Célula Construtiva",TEXT(B14,"00"),IF(H14="Etapa",CONCATENATE(TEXT(B14,"00"),".",TEXT(C14,"000")),IF(H14="Subetapa",CONCATENATE(TEXT(B14,"00"),".",TEXT(C14,"000"),".",TEXT(D14,"000")),IF(H14="Serviço",CONCATENATE(TEXT(B14,"00"),".",TEXT(C14,"000"),".",TEXT(D14,"000"),".",TEXT(E14,"000")),""))))) -> 01.001.002.001 | J14: Lastro de Concreto Magro, Aplicado em Blocos de Fundação, e=10cm | K14: m3 | L14: ='Fundação Rasa'!L7+'Fundação Rasa'!L8 -> 14.284227 | M14: =IFERROR(VLOOKUP(J14,CPU!$D$2:$H$327,5,FALSE),0) -> 412.36 | N14: =IF(H14="Serviço",M14*L14,IF(H14="CÉLULA CONSTRUTIVA",SUMIFS($N$8:$N$352,$B$8:$B$352,B14,$H$8:$H$352,"Serviço"),IF(H14="ETAPA",SUMIFS($N$8:$N$352,$B$8:$B$352,B14,$C$8:$C$352,C14,$H$8:$H$352,"Serviço"),IF(H14="SUBETAPA",SUMIFS($N$8:$N$352,$B$8:$B$352,B14,$C$8:$C$352,C14,$D$8:$D$352,D14,$H$8:$H$352,"Serviço"),0)))) -> 5890.2441 | P14: Finalizado
A15: =IF($H15="UNIDADE CONSTRUTIVA",OFFSET(A15,-1,0)+1,LARGE(A$3:A14,1)) -> 0 | B15: =IF(H15="UNIDADE CONSTRUTIVA",0,IF(H15="CÉLULA CONSTRUTIVA",OFFSET(B15,-1,0)+1,OFFSET(B15,-1,0))) -> 1 | C15: =IF(H15="CÉLULA CONSTRUTIVA",0,IF(H15="ETAPA",OFFSET(C15,-1,0)+1,OFFSET(C15,-1,0))) -> 1 | D15: =IF(H15="ETAPA",0,IF(H15="SUBETAPA",OFFSET(D15,-1,0)+1,OFFSET(D15,-1,0))) -> 3 | E15: =IF(H15="Subetapa",0,IF(H15="serviço",OFFSET(E15,-1,0)+1,OFFSET(E15,-1,0))) -> 0 | H15: SUBETAPA | I15: =IF(H15="Unidade Construtiva",TEXT(A15,"00"),IF(H15="Célula Construtiva",TEXT(B15,"00"),IF(H15="Etapa",CONCATENATE(TEXT(B15,"00"),".",TEXT(C15,"000")),IF(H15="Subetapa",CONCATENATE(TEXT(B15,"00"),".",TEXT(C15,"000"),".",TEXT(D15,"000")),IF(H15="Serviço",CONCATENATE(TEXT(B15,"00"),".",TEXT(C15,"000"),".",TEXT(D15,"000"),".",TEXT(E15,"000")),""))))) -> 01.001.003 | J15: Movimentação de bota - fora | N15: =IF(H15="Serviço",M15*L15,IF(H15="CÉLULA CONSTRUTIVA",SUMIFS($N$8:$N$352,$B$8:$B$352,B15,$H$8:$H$352,"Serviço"),IF(H15="ETAPA",SUMIFS($N$8:$N$352,$B$8:$B$352,B15,$C$8:$C$352,C15,$H$8:$H$352,"Serviço"),IF(H15="SUBETAPA",SUMIFS($N$8:$N$352,$B$8:$B$352,B15,$C$8:$C$352,C15,$D$8:$D$352,D15,$H$8:$H$352,"Serviço"),0)))) -> 38061.046
A16: =IF($H16="UNIDADE CONSTRUTIVA",OFFSET(A16,-1,0)+1,LARGE(A$3:A15,1)) -> 0 | B16: =IF(H16="UNIDADE CONSTRUTIVA",0,IF(H16="CÉLULA CONSTRUTIVA",OFFSET(B16,-1,0)+1,OFFSET(B16,-1,0))) -> 1 | C16: =IF(H16="CÉLULA CONSTRUTIVA",0,IF(H16="ETAPA",OFFSET(C16,-1,0)+1,OFFSET(C16,-1,0))) -> 1 | D16: =IF(H16="ETAPA",0,IF(H16="SUBETAPA",OFFSET(D16,-1,0)+1,OFFSET(D16,-1,0))) -> 3 | E16: =IF(H16="Subetapa",0,IF(H16="serviço",OFFSET(E16,-1,0)+1,OFFSET(E16,-1,0))) -> 1 | H16: SERVIÇO | I16: =IF(H16="Unidade Construtiva",TEXT(A16,"00"),IF(H16="Célula Construtiva",TEXT(B16,"00"),IF(H16="Etapa",CONCATENATE(TEXT(B16,"00"),".",TEXT(C16,"000")),IF(H16="Subetapa",CONCATENATE(TEXT(B16,"00"),".",TEXT(C16,"000"),".",TEXT(D16,"000")),IF(H16="Serviço",CONCATENATE(TEXT(B16,"00"),".",TEXT(C16,"000"),".",TEXT(D16,"000"),".",TEXT(E16,"000")),""))))) -> 01.001.003.001 | J16: Movimentação de terra para bota-fora - valas de fundação | K16: m3 | L16: ='Fundação Rasa'!J7+'Fundação Rasa'!J8 -> 595.17757 | M16: =IFERROR(VLOOKUP(J16,CPU!$D$2:$H$327,5,FALSE),0) -> 45.45 | N16: =IF(H16="Serviço",M16*L16,IF(H16="CÉLULA CONSTRUTIVA",SUMIFS($N$8:$N$352,$B$8:$B$352,B16,$H$8:$H$352,"Serviço"),IF(H16="ETAPA",SUMIFS($N$8:$N$352,$B$8:$B$352,B16,$C$8:$C$352,C16,$H$8:$H$352,"Serviço"),IF(H16="SUBETAPA",SUMIFS($N$8:$N$352,$B$8:$B$352,B16,$C$8:$C$352,C16,$D$8:$D$352,D16,$H$8:$H$352,"Serviço"),0)))) -> 27050.821 | O16: Considerado empolamento 30% da escavação | P16: Finalizado
A17: =IF($H17="UNIDADE CONSTRUTIVA",OFFSET(A17,-1,0)+1,LARGE(A$3:A16,1)) -> 0 | B17: =IF(H17="UNIDADE CONSTRUTIVA",0,IF(H17="CÉLULA CONSTRUTIVA",OFFSET(B17,-1,0)+1,OFFSET(B17,-1,0))) -> 1 | C17: =IF(H17="CÉLULA CONSTRUTIVA",0,IF(H17="ETAPA",OFFSET(C17,-1,0)+1,OFFSET(C17,-1,0))) -> 1 | D17: =IF(H17="ETAPA",0,IF(H17="SUBETAPA",OFFSET(D17,-1,0)+1,OFFSET(D17,-1,0))) -> 3 | E17: =IF(H17="Subetapa",0,IF(H17="serviço",OFFSET(E17,-1,0)+1,OFFSET(E17,-1,0))) -> 2 | H17: SERVIÇO | I17: =IF(H17="Unidade Construtiva",TEXT(A17,"00"),IF(H17="Célula Construtiva",TEXT(B17,"00"),IF(H17="Etapa",CONCATENATE(TEXT(B17,"00"),".",TEXT(C17,"000")),IF(H17="Subetapa",CONCATENATE(TEXT(B17,"00"),".",TEXT(C17,"000"),".",TEXT(D17,"000")),IF(H17="Serviço",CONCATENATE(TEXT(B17,"00"),".",TEXT(C17,"000"),".",TEXT(D17,"000"),".",TEXT(E17,"000")),""))))) -> 01.001.003.002 | J17: Movimentação de terra para bota-fora - Estacas | K17: m3 | L17: =Estacas!J13 -> 161.48762 | M17: =IFERROR(VLOOKUP(J17,CPU!$D$2:$H$327,5,FALSE),0) -> 68.18 | N17: =IF(H17="Serviço",M17*L17,IF(H17="CÉLULA CONSTRUTIVA",SUMIFS($N$8:$N$352,$B$8:$B$352,B17,$H$8:$H$352,"Serviço"),IF(H17="ETAPA",SUMIFS($N$8:$N$352,$B$8:$B$352,B17,$C$8:$C$352,C17,$H$8:$H$352,"Serviço"),IF(H17="SUBETAPA",SUMIFS($N$8:$N$352,$B$8:$B$352,B17,$C$8:$C$352,C17,$D$8:$D$352,D17,$H$8:$H$352,"Serviço"),0)))) -> 11010.226 | O17: Considerado empolamento 30% da escavação | P17: Finalizado
A18: =IF($H18="UNIDADE CONSTRUTIVA",OFFSET(A18,-1,0)+1,LARGE(A$3:A17,1)) -> 0 | B18: =IF(H18="UNIDADE CONSTRUTIVA",0,IF(H18="CÉLULA CONSTRUTIVA",OFFSET(B18,-1,0)+1,OFFSET(B18,-1,0))) -> 2 | C18: =IF(H18="CÉLULA CONSTRUTIVA",0,IF(H18="ETAPA",OFFSET(C18,-1,0)+1,OFFSET(C18,-1,0))) -> 0 | D18: =IF(H18="ETAPA",0,IF(H18="SUBETAPA",OFFSET(D18,-1,0)+1,OFFSET(D18,-1,0))) -> 3 | E18: =IF(H18="Subetapa",0,IF(H18="serviço",OFFSET(E18,-1,0)+1,OFFSET(E18,-1,0))) -> 2 | H18: CÉLULA CONSTRUTIVA | I18: =IF(H18="Unidade Construtiva",TEXT(A18,"00"),IF(H18="Célula Construtiva",TEXT(B18,"00"),IF(H18="Etapa",CONCATENATE(TEXT(B18,"00"),".",TEXT(C18,"000")),IF(H18="Subetapa",CONCATENATE(TEXT(B18,"00"),".",TEXT(C18,"000"),".",TEXT(D18,"000")),IF(H18="Serviço",CONCATENATE(TEXT(B18,"00"),".",TEXT(C18,"000"),".",TEXT(D18,"000"),".",TEXT(E18,"000")),""))))) -> 02 | J18: INFRAESTRUTURA | N18: =IF(H18="Serviço",M18*L18,IF(H18="CÉLULA CONSTRUTIVA",SUMIFS($N$8:$N$352,$B$8:$B$352,B18,$H$8:$H$352,"Serviço"),IF(H18="ETAPA",SUMIFS($N$8:$N$352,$B$8:$B$352,B18,$C$8:$C$352,C18,$H$8:$H$352,"Serviço"),IF(H18="SUBETAPA",SUMIFS($N$8:$N$352,$B$8:$B$352,B18,$C$8:$C$352,C18,$D$8:$D$352,D18,$H$8:$H$352,"Serviço"),0)))) -> 1590820.8
A19: =IF($H19="UNIDADE CONSTRUTIVA",OFFSET(A19,-1,0)+1,LARGE(A$3:A18,1)) -> 0 | B19: =IF(H19="UNIDADE CONSTRUTIVA",0,IF(H19="CÉLULA CONSTRUTIVA",OFFSET(B19,-1,0)+1,OFFSET(B19,-1,0))) -> 2 | C19: =IF(H19="CÉLULA CONSTRUTIVA",0,IF(H19="ETAPA",OFFSET(C19,-1,0)+1,OFFSET(C19,-1,0))) -> 1 | D19: =IF(H19="ETAPA",0,IF(H19="SUBETAPA",OFFSET(D19,-1,0)+1,OFFSET(D19,-1,0))) -> 0 | E19: =IF(H19="Subetapa",0,IF(H19="serviço",OFFSET(E19,-1,0)+1,OFFSET(E19,-1,0))) -> 2 | H19: ETAPA | I19: =IF(H19="Unidade Construtiva",TEXT(A19,"00"),IF(H19="Célula Construtiva",TEXT(B19,"00"),IF(H19="Etapa",CONCATENATE(TEXT(B19,"00"),".",TEXT(C19,"000")),IF(H19="Subetapa",CONCATENATE(TEXT(B19,"00"),".",TEXT(C19,"000"),".",TEXT(D19,"000")),IF(H19="Serviço",CONCATENATE(TEXT(B19,"00"),".",TEXT(C19,"000"),".",TEXT(D19,"000"),".",TEXT(E19,"000")),""))))) -> 02.001 | J19: FUNDAÇÃO PROFUNDA | N19: =IF(H19="Serviço",M19*L19,IF(H19="CÉLULA CONSTRUTIVA",SUMIFS($N$8:$N$352,$B$8:$B$352,B19,$H$8:$H$352,"Serviço"),IF(H19="ETAPA",SUMIFS($N$8:$N$352,$B$8:$B$352,B19,$C$8:$C$352,C19,$H$8:$H$352,"Serviço"),IF(H19="SUBETAPA",SUMIFS($N$8:$N$352,$B$8:$B$352,B19,$C$8:$C$352,C19,$D$8:$D$352,D19,$H$8:$H$352,"Serviço"),0)))) -> 761346.71
A20: =IF($H20="UNIDADE CONSTRUTIVA",OFFSET(A20,-1,0)+1,LARGE(A$3:A19,1)) -> 0 | B20: =IF(H20="UNIDADE CONSTRUTIVA",0,IF(H20="CÉLULA CONSTRUTIVA",OFFSET(B20,-1,0)+1,OFFSET(B20,-1,0))) -> 2 | C20: =IF(H20="CÉLULA CONSTRUTIVA",0,IF(H20="ETAPA",OFFSET(C20,-1,0)+1,OFFSET(C20,-1,0))) -> 1 | D20: =IF(H20="ETAPA",0,IF(H20="SUBETAPA",OFFSET(D20,-1,0)+1,OFFSET(D20,-1,0))) -> 1 | E20: =IF(H20="Subetapa",0,IF(H20="serviço",OFFSET(E20,-1,0)+1,OFFSET(E20,-1,0))) -> 0 | H20: SUBETAPA | I20: =IF(H20="Unidade Construtiva",TEXT(A20,"00"),IF(H20="Célula Construtiva",TEXT(B20,"00"),IF(H20="Etapa",CONCATENATE(TEXT(B20,"00"),".",TEXT(C20,"000")),IF(H20="Subetapa",CONCATENATE(TEXT(B20,"00"),".",TEXT(C20,"000"),".",TEXT(D20,"000")),IF(H20="Serviço",CONCATENATE(TEXT(B20,"00"),".",TEXT(C20,"000"),".",TEXT(D20,"000"),".",TEXT(E20,"000")),""))))) -> 02.001.001 | J20: Perfuração | N20: =IF(H20="Serviço",M20*L20,IF(H20="CÉLULA CONSTRUTIVA",SUMIFS($N$8:$N$352,$B$8:$B$352,B20,$H$8:$H$352,"Serviço"),IF(H20="ETAPA",SUMIFS($N$8:$N$352,$B$8:$B$352,B20,$C$8:$C$352,C20,$H$8:$H$352,"Serviço"),IF(H20="SUBETAPA",SUMIFS($N$8:$N$352,$B$8:$B$352,B20,$C$8:$C$352,C20,$D$8:$D$352,D20,$H$8:$H$352,"Serviço"),0)))) -> 475369
A21: =IF($H21="UNIDADE CONSTRUTIVA",OFFSET(A21,-1,0)+1,LARGE(A$3:A20,1)) -> 0 | B21: =IF(H21="UNIDADE CONSTRUTIVA",0,IF(H21="CÉLULA CONSTRUTIVA",OFFSET(B21,-1,0)+1,OFFSET(B21,-1,0))) -> 2 | C21: =IF(H21="CÉLULA CONSTRUTIVA",0,IF(H21="ETAPA",OFFSET(C21,-1,0)+1,OFFSET(C21,-1,0))) -> 1 | D21: =IF(H21="ETAPA",0,IF(H21="SUBETAPA",OFFSET(D21,-1,0)+1,OFFSET(D21,-1,0))) -> 1 | E21: =IF(H21="Subetapa",0,IF(H21="serviço",OFFSET(E21,-1,0)+1,OFFSET(E21,-1,0))) -> 1 | H21: SERVIÇO | I21: =IF(H21="Unidade Construtiva",TEXT(A21,"00"),IF(H21="Célula Construtiva",TEXT(B21,"00"),IF(H21="Etapa",CONCATENATE(TEXT(B21,"00"),".",TEXT(C21,"000")),IF(H21="Subetapa",CONCATENATE(TEXT(B21,"00"),".",TEXT(C21,"000"),".",TEXT(D21,"000")),IF(H21="Serviço",CONCATENATE(TEXT(B21,"00"),".",TEXT(C21,"000"),".",TEXT(D21,"000"),".",TEXT(E21,"000")),""))))) -> 02.001.001.001 | J21: Execucao Estaca Raiz 20Cm | K21: m | L21: =Estacas!H12 -> 75 | M21: =IFERROR(VLOOKUP(J21,CPU!$D$2:$H$327,5,FALSE),0) -> 145 | N21: =IF(H21="Serviço",M21*L21,IF(H21="CÉLULA CONSTRUTIVA",SUMIFS($N$8:$N$352,$B$8:$B$352,B21,$H$8:$H$352,"Serviço"),IF(H21="ETAPA",SUMIFS($N$8:$N$352,$B$8:$B$352,B21,$C$8:$C$352,C21,$H$8:$H$352,"Serviço"),IF(H21="SUBETAPA",SUMIFS($N$8:$N$352,$B$8:$B$352,B21,$C$8:$C$352,C21,$D$8:$D$352,D21,$H$8:$H$352,"Serviço"),0)))) -> 10875 | O21: Quantitade de Projetos | P21: Finalizado
A22: =IF($H22="UNIDADE CONSTRUTIVA",OFFSET(A22,-1,0)+1,LARGE(A$3:A21,1)) -> 0 | B22: =IF(H22="UNIDADE CONSTRUTIVA",0,IF(H22="CÉLULA CONSTRUTIVA",OFFSET(B22,-1,0)+1,OFFSET(B22,-1,0))) -> 2 | C22: =IF(H22="CÉLULA CONSTRUTIVA",0,IF(H22="ETAPA",OFFSET(C22,-1,0)+1,OFFSET(C22,-1,0))) -> 1 | D22: =IF(H22="ETAPA",0,IF(H22="SUBETAPA",OFFSET(D22,-1,0)+1,OFFSET(D22,-1,0))) -> 1 | E22: =IF(H22="Subetapa",0,IF(H22="serviço",OFFSET(E22,-1,0)+1,OFFSET(E22,-1,0))) -> 2 | H22: SERVIÇO | I22: =IF(H22="Unidade Construtiva",TEXT(A22,"00"),IF(H22="Célula Construtiva",TEXT(B22,"00"),IF(H22="Etapa",CONCATENATE(TEXT(B22,"00"),".",TEXT(C22,"000")),IF(H22="Subetapa",CONCATENATE(TEXT(B22,"00"),".",TEXT(C22,"000"),".",TEXT(D22,"000")),IF(H22="Serviço",CONCATENATE(TEXT(B22,"00"),".",TEXT(C22,"000"),".",TEXT(D22,"000"),".",TEXT(E22,"000")),""))))) -> 02.001.001.002 | J22: Execucao Estaca Raiz 25Cm | K22: m | L22: =Estacas!H11 -> 445.5 | M22: =IFERROR(VLOOKUP(J22,CPU!$D$2:$H$327,5,FALSE),0) -> 180 | N22: =IF(H22="Serviço",M22*L22,IF(H22="CÉLULA CONSTRUTIVA",SUMIFS($N$8:$N$352,$B$8:$B$352,B22,$H$8:$H$352,"Serviço"),IF(H22="ETAPA",SUMIFS($N$8:$N$352,$B$8:$B$352,B22,$C$8:$C$352,C22,$H$8:$H$352,"Serviço"),IF(H22="SUBETAPA",SUMIFS($N$8:$N$352,$B$8:$B$352,B22,$C$8:$C$352,C22,$D$8:$D$352,D22,$H$8:$H$352,"Serviço"),0)))) -> 80190 | O22: Quantitade de Projetos | P22: Finalizado
A23: =IF($H23="UNIDADE CONSTRUTIVA",OFFSET(A23,-1,0)+1,LARGE(A$3:A22,1)) -> 0 | B23: =IF(H23="UNIDADE CONSTRUTIVA",0,IF(H23="CÉLULA CONSTRUTIVA",OFFSET(B23,-1,0)+1,OFFSET(B23,-1,0))) -> 2 | C23: =IF(H23="CÉLULA CONSTRUTIVA",0,IF(H23="ETAPA",OFFSET(C23,-1,0)+1,OFFSET(C23,-1,0))) -> 1 | D23: =IF(H23="ETAPA",0,IF(H23="SUBETAPA",OFFSET(D23,-1,0)+1,OFFSET(D23,-1,0))) -> 1 | E23: =IF(H23="Subetapa",0,IF(H23="serviço",OFFSET(E23,-1,0)+1,OFFSET(E23,-1,0))) -> 3 | H23: SERVIÇO | I23: =IF(H23="Unidade Construtiva",TEXT(A23,"00"),IF(H23="Célula Construtiva",TEXT(B23,"00"),IF(H23="Etapa",CONCATENATE(TEXT(B23,"00"),".",TEXT(C23,"000")),IF(H23="Subetapa",CONCATENATE(TEXT(B23,"00"),".",TEXT(C23,"000"),".",TEXT(D23,"000")),IF(H23="Serviço",CONCATENATE(TEXT(B23,"00"),".",TEXT(C23,"000"),".",TEXT(D23,"000"),".",TEXT(E23,"000")),""))))) -> 02.001.001.003 | J23: Execucao Estaca Raiz 31Cm | K23: m | L23: =Estacas!H10 -> 745 | M23: =IFERROR(VLOOKUP(J23,CPU!$D$2:$H$327,5,FALSE),0) -> 220 | N23: =IF(H23="Serviço",M23*L23,IF(H23="CÉLULA CONSTRUTIVA",SUMIFS($N$8:$N$352,$B$8:$B$352,B23,$H$8:$H$352,"Serviço"),IF(H23="ETAPA",SUMIFS($N$8:$N$352,$B$8:$B$352,B23,$C$8:$C$352,C23,$H$8:$H$352,"Serviço"),IF(H23="SUBETAPA",SUMIFS($N$8:$N$352,$B$8:$B$352,B23,$C$8:$C$352,C23,$D$8:$D$352,D23,$H$8:$H$352,"Serviço"),0)))) -> 163900 | O23: Quantitade de Projetos | P23: Finalizado
A24: =IF($H24="UNIDADE CONSTRUTIVA",OFFSET(A24,-1,0)+1,LARGE(A$3:A23,1)) -> 0 | B24: =IF(H24="UNIDADE CONSTRUTIVA",0,IF(H24="CÉLULA CONSTRUTIVA",OFFSET(B24,-1,0)+1,OFFSET(B24,-1,0))) -> 2 | C24: =IF(H24="CÉLULA CONSTRUTIVA",0,IF(H24="ETAPA",OFFSET(C24,-1,0)+1,OFFSET(C24,-1,0))) -> 1 | D24: =IF(H24="ETAPA",0,IF(H24="SUBETAPA",OFFSET(D24,-1,0)+1,OFFSET(D24,-1,0))) -> 1 | E24: =IF(H24="Subetapa",0,IF(H24="serviço",OFFSET(E24,-1,0)+1,OFFSET(E24,-1,0))) -> 4 | H24: SERVIÇO | I24: =IF(H24="Unidade Construtiva",TEXT(A24,"00"),IF(H24="Célula Construtiva",TEXT(B24,"00"),IF(H24="Etapa",CONCATENATE(TEXT(B24,"00"),".",TEXT(C24,"000")),IF(H24="Subetapa",CONCATENATE(TEXT(B24,"00"),".",TEXT(C24,"000"),".",TEXT(D24,"000")),IF(H24="Serviço",CONCATENATE(TEXT(B24,"00"),".",TEXT(C24,"000"),".",TEXT(D24,"000"),".",TEXT(E24,"000")),""))))) -> 02.001.001.004 | J24: Execucao Estaca Raiz 41Cm | K24: m | L24: =Estacas!H9 -> 331.5 | M24: =IFERROR(VLOOKUP(J24,CPU!$D$2:$H$327,5,FALSE),0) -> 356 | N24: =IF(H24="Serviço",M24*L24,IF(H24="CÉLULA CONSTRUTIVA",SUMIFS($N$8:$N$352,$B$8:$B$352,B24,$H$8:$H$352,"Serviço"),IF(H24="ETAPA",SUMIFS($N$8:$N$352,$B$8:$B$352,B24,$C$8:$C$352,C24,$H$8:$H$352,"Serviço"),IF(H24="SUBETAPA",SUMIFS($N$8:$N$352,$B$8:$B$352,B24,$C$8:$C$352,C24,$D$8:$D$352,D24,$H$8:$H$352,"Serviço"),0)))) -> 118014 | O24: Quantitade de Projetos | P24: Finalizado
A25: =IF($H25="UNIDADE CONSTRUTIVA",OFFSET(A25,-1,0)+1,LARGE(A$3:A24,1)) -> 0 | B25: =IF(H25="UNIDADE CONSTRUTIVA",0,IF(H25="CÉLULA CONSTRUTIVA",OFFSET(B25,-1,0)+1,OFFSET(B25,-1,0))) -> 2 | C25: =IF(H25="CÉLULA CONSTRUTIVA",0,IF(H25="ETAPA",OFFSET(C25,-1,0)+1,OFFSET(C25,-1,0))) -> 1 | D25: =IF(H25="ETAPA",0,IF(H25="SUBETAPA",OFFSET(D25,-1,0)+1,OFFSET(D25,-1,0))) -> 1 | E25: =IF(H25="Subetapa",0,IF(H25="serviço",OFFSET(E25,-1,0)+1,OFFSET(E25,-1,0))) -> 5 | H25: SERVIÇO | I25: =IF(H25="Unidade Construtiva",TEXT(A25,"00"),IF(H25="Célula Construtiva",TEXT(B25,"00"),IF(H25="Etapa",CONCATENATE(TEXT(B25,"00"),".",TEXT(C25,"000")),IF(H25="Subetapa",CONCATENATE(TEXT(B25,"00"),".",TEXT(C25,"000"),".",TEXT(D25,"000")),IF(H25="Serviço",CONCATENATE(TEXT(B25,"00"),".",TEXT(C25,"000"),".",TEXT(D25,"000"),".",TEXT(E25,"000")),""))))) -> 02.001.001.005 | J25: Mobilização e desmobilização de equipamentos - Para execução de estaca raiz | K25: vb | L25: 1 | M25: 15600 | N25: =IF(H25="Serviço",M25*L25,IF(H25="CÉLULA CONSTRUTIVA",SUMIFS($N$8:$N$352,$B$8:$B$352,B25,$H$8:$H$352,"Serviço"),IF(H25="ETAPA",SUMIFS($N$8:$N$352,$B$8:$B$352,B25,$C$8:$C$352,C25,$H$8:$H$352,"Serviço"),IF(H25="SUBETAPA",SUMIFS($N$8:$N$352,$B$8:$B$352,B25,$C$8:$C$352,C25,$D$8:$D$352,D25,$H$8:$H$352,"Serviço"),0)))) -> 15600 | P25: Finalizado
A26: =IF($H26="UNIDADE CONSTRUTIVA",OFFSET(A26,-1,0)+1,LARGE(A$3:A25,1)) -> 0 | B26: =IF(H26="UNIDADE CONSTRUTIVA",0,IF(H26="CÉLULA CONSTRUTIVA",OFFSET(B26,-1,0)+1,OFFSET(B26,-1,0))) -> 2 | C26: =IF(H26="CÉLULA CONSTRUTIVA",0,IF(H26="ETAPA",OFFSET(C26,-1,0)+1,OFFSET(C26,-1,0))) -> 1 | D26: =IF(H26="ETAPA",0,IF(H26="SUBETAPA",OFFSET(D26,-1,0)+1,OFFSET(D26,-1,0))) -> 1 | E26: =IF(H26="Subetapa",0,IF(H26="serviço",OFFSET(E26,-1,0)+1,OFFSET(E26,-1,0))) -> 6 | H26: SERVIÇO | I26: =IF(H26="Unidade Construtiva",TEXT(A26,"00"),IF(H26="Célula Construtiva",TEXT(B26,"00"),IF(H26="Etapa",CONCATENATE(TEXT(B26,"00"),".",TEXT(C26,"000")),IF(H26="Subetapa",CONCATENATE(TEXT(B26,"00"),".",TEXT(C26,"000"),".",TEXT(D26,"000")),IF(H26="Serviço",CONCATENATE(TEXT(B26,"00"),".",TEXT(C26,"000"),".",TEXT(D26,"000"),".",TEXT(E26,"000")),""))))) -> 02.001.001.006 | J26: Corte e Preparo de Cabeça de Estaca | K26: un | L26: =Estacas!C13 -> 263 | M26: 330 | N26: =IF(H26="Serviço",M26*L26,IF(H26="CÉLULA CONSTRUTIVA",SUMIFS($N$8:$N$352,$B$8:$B$352,B26,$H$8:$H$352,"Serviço"),IF(H26="ETAPA",SUMIFS($N$8:$N$352,$B$8:$B$352,B26,$C$8:$C$352,C26,$H$8:$H$352,"Serviço"),IF(H26="SUBETAPA",SUMIFS($N$8:$N$352,$B$8:$B$352,B26,$C$8:$C$352,C26,$D$8:$D$352,D26,$H$8:$H$352,"Serviço"),0)))) -> 86790 | O26: Quantitade de Projetos | P26: Finalizado
A27: =IF($H27="UNIDADE CONSTRUTIVA",OFFSET(A27,-1,0)+1,LARGE(A$3:A26,1)) -> 0 | B27: =IF(H27="UNIDADE CONSTRUTIVA",0,IF(H27="CÉLULA CONSTRUTIVA",OFFSET(B27,-1,0)+1,OFFSET(B27,-1,0))) -> 2 | C27: =IF(H27="CÉLULA CONSTRUTIVA",0,IF(H27="ETAPA",OFFSET(C27,-1,0)+1,OFFSET(C27,-1,0))) -> 1 | D27: =IF(H27="ETAPA",0,IF(H27="SUBETAPA",OFFSET(D27,-1,0)+1,OFFSET(D27,-1,0))) -> 2 | E27: =IF(H27="Subetapa",0,IF(H27="serviço",OFFSET(E27,-1,0)+1,OFFSET(E27,-1,0))) -> 0 | H27: SUBETAPA | I27: =IF(H27="Unidade Construtiva",TEXT(A27,"00"),IF(H27="Célula Construtiva",TEXT(B27,"00"),IF(H27="Etapa",CONCATENATE(TEXT(B27,"00"),".",TEXT(C27,"000")),IF(H27="Subetapa",CONCATENATE(TEXT(B27,"00"),".",TEXT(C27,"000"),".",TEXT(D27,"000")),IF(H27="Serviço",CONCATENATE(TEXT(B27,"00"),".",TEXT(C27,"000"),".",TEXT(D27,"000"),".",TEXT(E27,"000")),""))))) -> 02.001.002 | J27: Armadura | N27: =IF(H27="Serviço",M27*L27,IF(H27="CÉLULA CONSTRUTIVA",SUMIFS($N$8:$N$352,$B$8:$B$352,B27,$H$8:$H$352,"Serviço"),IF(H27="ETAPA",SUMIFS($N$8:$N$352,$B$8:$B$352,B27,$C$8:$C$352,C27,$H$8:$H$352,"Serviço"),IF(H27="SUBETAPA",SUMIFS($N$8:$N$352,$B$8:$B$352,B27,$C$8:$C$352,C27,$D$8:$D$352,D27,$H$8:$H$352,"Serviço"),0)))) -> 156629.95
A28: =IF($H28="UNIDADE CONSTRUTIVA",OFFSET(A28,-1,0)+1,LARGE(A$3:A27,1)) -> 0 | B28: =IF(H28="UNIDADE CONSTRUTIVA",0,IF(H28="CÉLULA CONSTRUTIVA",OFFSET(B28,-1,0)+1,OFFSET(B28,-1,0))) -> 2 | C28: =IF(H28="CÉLULA CONSTRUTIVA",0,IF(H28="ETAPA",OFFSET(C28,-1,0)+1,OFFSET(C28,-1,0))) -> 1 | D28: =IF(H28="ETAPA",0,IF(H28="SUBETAPA",OFFSET(D28,-1,0)+1,OFFSET(D28,-1,0))) -> 2 | E28: =IF(H28="Subetapa",0,IF(H28="serviço",OFFSET(E28,-1,0)+1,OFFSET(E28,-1,0))) -> 1 | H28: SERVIÇO | I28: =IF(H28="Unidade Construtiva",TEXT(A28,"00"),IF(H28="Célula Construtiva",TEXT(B28,"00"),IF(H28="Etapa",CONCATENATE(TEXT(B28,"00"),".",TEXT(C28,"000")),IF(H28="Subetapa",CONCATENATE(TEXT(B28,"00"),".",TEXT(C28,"000"),".",TEXT(D28,"000")),IF(H28="Serviço",CONCATENATE(TEXT(B28,"00"),".",TEXT(C28,"000"),".",TEXT(D28,"000"),".",TEXT(E28,"000")),""))))) -> 02.001.002.001 | J28: Armação aço CA-50 ø 6,3mm para estaca (corte e dobra em obra) | K28: kg | L28: =Estacas!M13 -> 295 | M28: =IFERROR(VLOOKUP(J28,CPU!$D$2:$H$327,5,FALSE),0) -> 7.3284519 | N28: =IF(H28="Serviço",M28*L28,IF(H28="CÉLULA CONSTRUTIVA",SUMIFS($N$8:$N$352,$B$8:$B$352,B28,$H$8:$H$352,"Serviço"),IF(H28="ETAPA",SUMIFS($N$8:$N$352,$B$8:$B$352,B28,$C$8:$C$352,C28,$H$8:$H$352,"Serviço"),IF(H28="SUBETAPA",SUMIFS($N$8:$N$352,$B$8:$B$352,B28,$C$8:$C$352,C28,$D$8:$D$352,D28,$H$8:$H$352,"Serviço"),0)))) -> 2161.8933 | O28: Quantitade de Projetos - 10% de perda | P28: Finalizado
A29: =IF($H29="UNIDADE CONSTRUTIVA",OFFSET(A29,-1,0)+1,LARGE(A$3:A28,1)) -> 0 | B29: =IF(H29="UNIDADE CONSTRUTIVA",0,IF(H29="CÉLULA CONSTRUTIVA",OFFSET(B29,-1,0)+1,OFFSET(B29,-1,0))) -> 2 | C29: =IF(H29="CÉLULA CONSTRUTIVA",0,IF(H29="ETAPA",OFFSET(C29,-1,0)+1,OFFSET(C29,-1,0))) -> 1 | D29: =IF(H29="ETAPA",0,IF(H29="SUBETAPA",OFFSET(D29,-1,0)+1,OFFSET(D29,-1,0))) -> 2 | E29: =IF(H29="Subetapa",0,IF(H29="serviço",OFFSET(E29,-1,0)+1,OFFSET(E29,-1,0))) -> 2 | H29: SERVIÇO | I29: =IF(H29="Unidade Construtiva",TEXT(A29,"00"),IF(H29="Célula Construtiva",TEXT(B29,"00"),IF(H29="Etapa",CONCATENATE(TEXT(B29,"00"),".",TEXT(C29,"000")),IF(H29="Subetapa",CONCATENATE(TEXT(B29,"00"),".",TEXT(C29,"000"),".",TEXT(D29,"000")),IF(H29="Serviço",CONCATENATE(TEXT(B29,"00"),".",TEXT(C29,"000"),".",TEXT(D29,"000"),".",TEXT(E29,"000")),""))))) -> 02.001.002.002 | J29: Armação aço CA-50 ø 8,0mm para estaca (corte e dobra em obra) | K29: kg | L29: =Estacas!N13 -> 1453 | M29: =IFERROR(VLOOKUP(J29,CPU!$D$2:$H$327,5,FALSE),0) -> 7.065275 | N29: =IF(H29="Serviço",M29*L29,IF(H29="CÉLULA CONSTRUTIVA",SUMIFS($N$8:$N$352,$B$8:$B$352,B29,$H$8:$H$352,"Serviço"),IF(H29="ETAPA",SUMIFS($N$8:$N$352,$B$8:$B$352,B29,$C$8:$C$352,C29,$H$8:$H$352,"Serviço"),IF(H29="SUBETAPA",SUMIFS($N$8:$N$352,$B$8:$B$352,B29,$C$8:$C$352,C29,$D$8:$D$352,D29,$H$8:$H$352,"Serviço"),0)))) -> 10265.845 | O29: Quantitade de Projetos - 10% de perda | P29: Finalizado
A30: =IF($H30="UNIDADE CONSTRUTIVA",OFFSET(A30,-1,0)+1,LARGE(A$3:A29,1)) -> 0 | B30: =IF(H30="UNIDADE CONSTRUTIVA",0,IF(H30="CÉLULA CONSTRUTIVA",OFFSET(B30,-1,0)+1,OFFSET(B30,-1,0))) -> 2 | C30: =IF(H30="CÉLULA CONSTRUTIVA",0,IF(H30="ETAPA",OFFSET(C30,-1,0)+1,OFFSET(C30,-1,0))) -> 1 | D30: =IF(H30="ETAPA",0,IF(H30="SUBETAPA",OFFSET(D30,-1,0)+1,OFFSET(D30,-1,0))) -> 2 | E30: =IF(H30="Subetapa",0,IF(H30="serviço",OFFSET(E30,-1,0)+1,OFFSET(E30,-1,0))) -> 3 | H30: SERVIÇO | I30: =IF(H30="Unidade Construtiva",TEXT(A30,"00"),IF(H30="Célula Construtiva",TEXT(B30,"00"),IF(H30="Etapa",CONCATENATE(TEXT(B30,"00"),".",TEXT(C30,"000")),IF(H30="Subetapa",CONCATENATE(TEXT(B30,"00"),".",TEXT(C30,"000"),".",TEXT(D30,"000")),IF(H30="Serviço",CONCATENATE(TEXT(B30,"00"),".",TEXT(C30,"000"),".",TEXT(D30,"000"),".",TEXT(E30,"000")),""))))) -> 02.001.002.003 | J30: Armação aço CA-50 ø 16,0mm para estaca (corte e dobra em obra) | K30: kg | L30: =Estacas!O13 -> 4810 | M30: =IFERROR(VLOOKUP(J30,CPU!$D$2:$H$327,5,FALSE),0) -> 6.6893452 | N30: =IF(H30="Serviço",M30*L30,IF(H30="CÉLULA CONSTRUTIVA",SUMIFS($N$8:$N$352,$B$8:$B$352,B30,$H$8:$H$352,"Serviço"),IF(H30="ETAPA",SUMIFS($N$8:$N$352,$B$8:$B$352,B30,$C$8:$C$352,C30,$H$8:$H$352,"Serviço"),IF(H30="SUBETAPA",SUMIFS($N$8:$N$352,$B$8:$B$352,B30,$C$8:$C$352,C30,$D$8:$D$352,D30,$H$8:$H$352,"Serviço"),0)))) -> 32175.75 | O30: Quantitade de Projetos - 10% de perda | P30: Finalizado
A31: =IF($H31="UNIDADE CONSTRUTIVA",OFFSET(A31,-1,0)+1,LARGE(A$3:A30,1)) -> 0 | B31: =IF(H31="UNIDADE CONSTRUTIVA",0,IF(H31="CÉLULA CONSTRUTIVA",OFFSET(B31,-1,0)+1,OFFSET(B31,-1,0))) -> 2 | C31: =IF(H31="CÉLULA CONSTRUTIVA",0,IF(H31="ETAPA",OFFSET(C31,-1,0)+1,OFFSET(C31,-1,0))) -> 1 | D31: =IF(H31="ETAPA",0,IF(H31="SUBETAPA",OFFSET(D31,-1,0)+1,OFFSET(D31,-1,0))) -> 2 | E31: =IF(H31="Subetapa",0,IF(H31="serviço",OFFSET(E31,-1,0)+1,OFFSET(E31,-1,0))) -> 4 | H31: SERVIÇO | I31: =IF(H31="Unidade Construtiva",TEXT(A31,"00"),IF(H31="Célula Construtiva",TEXT(B31,"00"),IF(H31="Etapa",CONCATENATE(TEXT(B31,"00"),".",TEXT(C31,"000")),IF(H31="Subetapa",CONCATENATE(TEXT(B31,"00"),".",TEXT(C31,"000"),".",TEXT(D31,"000")),IF(H31="Serviço",CONCATENATE(TEXT(B31,"00"),".",TEXT(C31,"000"),".",TEXT(D31,"000"),".",TEXT(E31,"000")),""))))) -> 02.001.002.004 | J31: Armação aço CA-50 ø 20,0mm para estaca (corte e dobra em obra) | K31: kg | L31: =Estacas!P13 -> 16747 | M31: =IFERROR(VLOOKUP(J31,CPU!$D$2:$H$327,5,FALSE),0) -> 6.6893452 | N31: =IF(H31="Serviço",M31*L31,IF(H31="CÉLULA CONSTRUTIVA",SUMIFS($N$8:$N$352,$B$8:$B$352,B31,$H$8:$H$352,"Serviço"),IF(H31="ETAPA",SUMIFS($N$8:$N$352,$B$8:$B$352,B31,$C$8:$C$352,C31,$H$8:$H$352,"Serviço"),IF(H31="SUBETAPA",SUMIFS($N$8:$N$352,$B$8:$B$352,B31,$C$8:$C$352,C31,$D$8:$D$352,D31,$H$8:$H$352,"Serviço"),0)))) -> 112026.46 | O31: Quantitade de Projetos - 10% de perda | P31: Finalizado
A32: =IF($H32="UNIDADE CONSTRUTIVA",OFFSET(A32,-1,0)+1,LARGE(A$3:A31,1)) -> 0 | B32: =IF(H32="UNIDADE CONSTRUTIVA",0,IF(H32="CÉLULA CONSTRUTIVA",OFFSET(B32,-1,0)+1,OFFSET(B32,-1,0))) -> 2 | C32: =IF(H32="CÉLULA CONSTRUTIVA",0,IF(H32="ETAPA",OFFSET(C32,-1,0)+1,OFFSET(C32,-1,0))) -> 1 | D32: =IF(H32="ETAPA",0,IF(H32="SUBETAPA",OFFSET(D32,-1,0)+1,OFFSET(D32,-1,0))) -> 3 | E32: =IF(H32="Subetapa",0,IF(H32="serviço",OFFSET(E32,-1,0)+1,OFFSET(E32,-1,0))) -> 0 | H32: SUBETAPA | I32: =IF(H32="Unidade Construtiva",TEXT(A32,"00"),IF(H32="Célula Construtiva",TEXT(B32,"00"),IF(H32="Etapa",CONCATENATE(TEXT(B32,"00"),".",TEXT(C32,"000")),IF(H32="Subetapa",CONCATENATE(TEXT(B32,"00"),".",TEXT(C32,"000"),".",TEXT(D32,"000")),IF(H32="Serviço",CONCATENATE(TEXT(B32,"00"),".",TEXT(C32,"000"),".",TEXT(D32,"000"),".",TEXT(E32,"000")),""))))) -> 02.001.003 | J32: Lançamento de Concreto para Estacas | N32: =IF(H32="Serviço",M32*L32,IF(H32="CÉLULA CONSTRUTIVA",SUMIFS($N$8:$N$352,$B$8:$B$352,B32,$H$8:$H$352,"Serviço"),IF(H32="ETAPA",SUMIFS($N$8:$N$352,$B$8:$B$352,B32,$C$8:$C$352,C32,$H$8:$H$352,"Serviço"),IF(H32="SUBETAPA",SUMIFS($N$8:$N$352,$B$8:$B$352,B32,$C$8:$C$352,C32,$D$8:$D$352,D32,$H$8:$H$352,"Serviço"),0)))) -> 129347.76
A33: =IF($H33="UNIDADE CONSTRUTIVA",OFFSET(A33,-1,0)+1,LARGE(A$3:A32,1)) -> 0 | B33: =IF(H33="UNIDADE CONSTRUTIVA",0,IF(H33="CÉLULA CONSTRUTIVA",OFFSET(B33,-1,0)+1,OFFSET(B33,-1,0))) -> 2 | C33: =IF(H33="CÉLULA CONSTRUTIVA",0,IF(H33="ETAPA",OFFSET(C33,-1,0)+1,OFFSET(C33,-1,0))) -> 1 | D33: =IF(H33="ETAPA",0,IF(H33="SUBETAPA",OFFSET(D33,-1,0)+1,OFFSET(D33,-1,0))) -> 3 | E33: =IF(H33="Subetapa",0,IF(H33="serviço",OFFSET(E33,-1,0)+1,OFFSET(E33,-1,0))) -> 1 | H33: SERVIÇO | I33: =IF(H33="Unidade Construtiva",TEXT(A33,"00"),IF(H33="Célula Construtiva",TEXT(B33,"00"),IF(H33="Etapa",CONCATENATE(TEXT(B33,"00"),".",TEXT(C33,"000")),IF(H33="Subetapa",CONCATENATE(TEXT(B33,"00"),".",TEXT(C33,"000"),".",TEXT(D33,"000")),IF(H33="Serviço",CONCATENATE(TEXT(B33,"00"),".",TEXT(C33,"000"),".",TEXT(D33,"000"),".",TEXT(E33,"000")),""))))) -> 02.001.003.001 | J33: Argamassa bombeável 25MPa para estaca raiz | K33: m3 | L33: =Estacas!K13 -> 124.22124 | M33: =IFERROR(VLOOKUP(J33,CPU!$D$2:$H$327,5,FALSE),0) -> 1041.2692 | N33: =IF(H33="Serviço",M33*L33,IF(H33="CÉLULA CONSTRUTIVA",SUMIFS($N$8:$N$352,$B$8:$B$352,B33,$H$8:$H$352,"Serviço"),IF(H33="ETAPA",SUMIFS($N$8:$N$352,$B$8:$B$352,B33,$C$8:$C$352,C33,$H$8:$H$352,"Serviço"),IF(H33="SUBETAPA",SUMIFS($N$8:$N$352,$B$8:$B$352,B33,$C$8:$C$352,C33,$D$8:$D$352,D33,$H$8:$H$352,"Serviço"),0)))) -> 129347.76 | O33: Quantitade de Projetos - 30% de perda | P33: Finalizado
A34: =IF($H34="UNIDADE CONSTRUTIVA",OFFSET(A34,-1,0)+1,LARGE(A$3:A33,1)) -> 0 | B34: =IF(H34="UNIDADE CONSTRUTIVA",0,IF(H34="CÉLULA CONSTRUTIVA",OFFSET(B34,-1,0)+1,OFFSET(B34,-1,0))) -> 2 | C34: =IF(H34="CÉLULA CONSTRUTIVA",0,IF(H34="ETAPA",OFFSET(C34,-1,0)+1,OFFSET(C34,-1,0))) -> 2 | D34: =IF(H34="ETAPA",0,IF(H34="SUBETAPA",OFFSET(D34,-1,0)+1,OFFSET(D34,-1,0))) -> 0 | E34: =IF(H34="Subetapa",0,IF(H34="serviço",OFFSET(E34,-1,0)+1,OFFSET(E34,-1,0))) -> 1 | H34: ETAPA | I34: =IF(H34="Unidade Construtiva",TEXT(A34,"00"),IF(H34="Célula Construtiva",TEXT(B34,"00"),IF(H34="Etapa",CONCATENATE(TEXT(B34,"00"),".",TEXT(C34,"000")),IF(H34="Subetapa",CONCATENATE(TEXT(B34,"00"),".",TEXT(C34,"000"),".",TEXT(D34,"000")),IF(H34="Serviço",CONCATENATE(TEXT(B34,"00"),".",TEXT(C34,"000"),".",TEXT(D34,"000"),".",TEXT(E34,"000")),""))))) -> 02.002 | J34: FUNDAÇÃO RASA | N34: =IF(H34="Serviço",M34*L34,IF(H34="CÉLULA CONSTRUTIVA",SUMIFS($N$8:$N$352,$B$8:$B$352,B34,$H$8:$H$352,"Serviço"),IF(H34="ETAPA",SUMIFS($N$8:$N$352,$B$8:$B$352,B34,$C$8:$C$352,C34,$H$8:$H$352,"Serviço"),IF(H34="SUBETAPA",SUMIFS($N$8:$N$352,$B$8:$B$352,B34,$C$8:$C$352,C34,$D$8:$D$352,D34,$H$8:$H$352,"Serviço"),0)))) -> 829474.08
A35: =IF($H35="UNIDADE CONSTRUTIVA",OFFSET(A35,-1,0)+1,LARGE(A$3:A34,1)) -> 0 | B35: =IF(H35="UNIDADE CONSTRUTIVA",0,IF(H35="CÉLULA CONSTRUTIVA",OFFSET(B35,-1,0)+1,OFFSET(B35,-1,0))) -> 2 | C35: =IF(H35="CÉLULA CONSTRUTIVA",0,IF(H35="ETAPA",OFFSET(C35,-1,0)+1,OFFSET(C35,-1,0))) -> 2 | D35: =IF(H35="ETAPA",0,IF(H35="SUBETAPA",OFFSET(D35,-1,0)+1,OFFSET(D35,-1,0))) -> 1 | E35: =IF(H35="Subetapa",0,IF(H35="serviço",OFFSET(E35,-1,0)+1,OFFSET(E35,-1,0))) -> 0 | H35: SUBETAPA | I35: =IF(H35="Unidade Construtiva",TEXT(A35,"00"),IF(H35="Célula Construtiva",TEXT(B35,"00"),IF(H35="Etapa",CONCATENATE(TEXT(B35,"00"),".",TEXT(C35,"000")),IF(H35="Subetapa",CONCATENATE(TEXT(B35,"00"),".",TEXT(C35,"000"),".",TEXT(D35,"000")),IF(H35="Serviço",CONCATENATE(TEXT(B35,"00"),".",TEXT(C35,"000"),".",TEXT(D35,"000"),".",TEXT(E35,"000")),""))))) -> 02.002.001 | J35: Forma | N35: =IF(H35="Serviço",M35*L35,IF(H35="CÉLULA CONSTRUTIVA",SUMIFS($N$8:$N$352,$B$8:$B$352,B35,$H$8:$H$352,"Serviço"),IF(H35="ETAPA",SUMIFS($N$8:$N$352,$B$8:$B$352,B35,$C$8:$C$352,C35,$H$8:$H$352,"Serviço"),IF(H35="SUBETAPA",SUMIFS($N$8:$N$352,$B$8:$B$352,B35,$C$8:$C$352,C35,$D$8:$D$352,D35,$H$8:$H$352,"Serviço"),0)))) -> 79725.4 | O35: Considerado blocos, vigas de fundação, lajes,pilares de arranque, dutos e cisternas
A36: =IF($H36="UNIDADE CONSTRUTIVA",OFFSET(A36,-1,0)+1,LARGE(A$3:A35,1)) -> 0 | B36: =IF(H36="UNIDADE CONSTRUTIVA",0,IF(H36="CÉLULA CONSTRUTIVA",OFFSET(B36,-1,0)+1,OFFSET(B36,-1,0))) -> 2 | C36: =IF(H36="CÉLULA CONSTRUTIVA",0,IF(H36="ETAPA",OFFSET(C36,-1,0)+1,OFFSET(C36,-1,0))) -> 2 | D36: =IF(H36="ETAPA",0,IF(H36="SUBETAPA",OFFSET(D36,-1,0)+1,OFFSET(D36,-1,0))) -> 1 | E36: =IF(H36="Subetapa",0,IF(H36="serviço",OFFSET(E36,-1,0)+1,OFFSET(E36,-1,0))) -> 1 | H36: SERVIÇO | I36: =IF(H36="Unidade Construtiva",TEXT(A36,"00"),IF(H36="Célula Construtiva",TEXT(B36,"00"),IF(H36="Etapa",CONCATENATE(TEXT(B36,"00"),".",TEXT(C36,"000")),IF(H36="Subetapa",CONCATENATE(TEXT(B36,"00"),".",TEXT(C36,"000"),".",TEXT(D36,"000")),IF(H36="Serviço",CONCATENATE(TEXT(B36,"00"),".",TEXT(C36,"000"),".",TEXT(D36,"000"),".",TEXT(E36,"000")),""))))) -> 02.002.001.001 | J36: Forma para infraestrutura em Tábuas de Madeira Serrada, reaproveitamento 2X | K36: m2 | L36: =Aço_Infraestrutura!O23 -> 2134.51 | M36: =IFERROR(VLOOKUP(J36,CPU!$D$2:$H$327,5,FALSE),0) -> 37.35068 | N36: =IF(H36="Serviço",M36*L36,IF(H36="CÉLULA CONSTRUTIVA",SUMIFS($N$8:$N$352,$B$8:$B$352,B36,$H$8:$H$352,"Serviço"),IF(H36="ETAPA",SUMIFS($N$8:$N$352,$B$8:$B$352,B36,$C$8:$C$352,C36,$H$8:$H$352,"Serviço"),IF(H36="SUBETAPA",SUMIFS($N$8:$N$352,$B$8:$B$352,B36,$C$8:$C$352,C36,$D$8:$D$352,D36,$H$8:$H$352,"Serviço"),0)))) -> 79725.4 | P36: Finalizado
A37: =IF($H37="UNIDADE CONSTRUTIVA",OFFSET(A37,-1,0)+1,LARGE(A$3:A36,1)) -> 0 | B37: =IF(H37="UNIDADE CONSTRUTIVA",0,IF(H37="CÉLULA CONSTRUTIVA",OFFSET(B37,-1,0)+1,OFFSET(B37,-1,0))) -> 2 | C37: =IF(H37="CÉLULA CONSTRUTIVA",0,IF(H37="ETAPA",OFFSET(C37,-1,0)+1,OFFSET(C37,-1,0))) -> 2 | D37: =IF(H37="ETAPA",0,IF(H37="SUBETAPA",OFFSET(D37,-1,0)+1,OFFSET(D37,-1,0))) -> 2 | E37: =IF(H37="Subetapa",0,IF(H37="serviço",OFFSET(E37,-1,0)+1,OFFSET(E37,-1,0))) -> 0 | H37: SUBETAPA | I37: =IF(H37="Unidade Construtiva",TEXT(A37,"00"),IF(H37="Célula Construtiva",TEXT(B37,"00"),IF(H37="Etapa",CONCATENATE(TEXT(B37,"00"),".",TEXT(C37,"000")),IF(H37="Subetapa",CONCATENATE(TEXT(B37,"00"),".",TEXT(C37,"000"),".",TEXT(D37,"000")),IF(H37="Serviço",CONCATENATE(TEXT(B37,"00"),".",TEXT(C37,"000"),".",TEXT(D37,"000"),".",TEXT(E37,"000")),""))))) -> 02.002.002 | J37: Armadura | N37: =IF(H37="Serviço",M37*L37,IF(H37="CÉLULA CONSTRUTIVA",SUMIFS($N$8:$N$352,$B$8:$B$352,B37,$H$8:$H$352,"Serviço"),IF(H37="ETAPA",SUMIFS($N$8:$N$352,$B$8:$B$352,B37,$C$8:$C$352,C37,$H$8:$H$352,"Serviço"),IF(H37="SUBETAPA",SUMIFS($N$8:$N$352,$B$8:$B$352,B37,$C$8:$C$352,C37,$D$8:$D$352,D37,$H$8:$H$352,"Serviço"),0)))) -> 181024.64
A38: =IF($H38="UNIDADE CONSTRUTIVA",OFFSET(A38,-1,0)+1,LARGE(A$3:A37,1)) -> 0 | B38: =IF(H38="UNIDADE CONSTRUTIVA",0,IF(H38="CÉLULA CONSTRUTIVA",OFFSET(B38,-1,0)+1,OFFSET(B38,-1,0))) -> 2 | C38: =IF(H38="CÉLULA CONSTRUTIVA",0,IF(H38="ETAPA",OFFSET(C38,-1,0)+1,OFFSET(C38,-1,0))) -> 2 | D38: =IF(H38="ETAPA",0,IF(H38="SUBETAPA",OFFSET(D38,-1,0)+1,OFFSET(D38,-1,0))) -> 2 | E38: =IF(H38="Subetapa",0,IF(H38="serviço",OFFSET(E38,-1,0)+1,OFFSET(E38,-1,0))) -> 1 | H38: SERVIÇO | I38: =IF(H38="Unidade Construtiva",TEXT(A38,"00"),IF(H38="Célula Construtiva",TEXT(B38,"00"),IF(H38="Etapa",CONCATENATE(TEXT(B38,"00"),".",TEXT(C38,"000")),IF(H38="Subetapa",CONCATENATE(TEXT(B38,"00"),".",TEXT(C38,"000"),".",TEXT(D38,"000")),IF(H38="Serviço",CONCATENATE(TEXT(B38,"00"),".",TEXT(C38,"000"),".",TEXT(D38,"000"),".",TEXT(E38,"000")),""))))) -> 02.002.002.001 | J38: Armação aço CA-50 ø 6,3mm para infraestrutura (corte e dobra em industria) | K38: kg | L38: =Aço_Infraestrutura!D23 -> 4784.5 | M38: =IFERROR(VLOOKUP(J38,CPU!$D$2:$H$327,5,FALSE),0) -> 7.456275 | N38: =IF(H38="Serviço",M38*L38,IF(H38="CÉLULA CONSTRUTIVA",SUMIFS($N$8:$N$352,$B$8:$B$352,B38,$H$8:$H$352,"Serviço"),IF(H38="ETAPA",SUMIFS($N$8:$N$352,$B$8:$B$352,B38,$C$8:$C$352,C38,$H$8:$H$352,"Serviço"),IF(H38="SUBETAPA",SUMIFS($N$8:$N$352,$B$8:$B$352,B38,$C$8:$C$352,C38,$D$8:$D$352,D38,$H$8:$H$352,"Serviço"),0)))) -> 35674.548 | P38: Finalizado
A39: =IF($H39="UNIDADE CONSTRUTIVA",OFFSET(A39,-1,0)+1,LARGE(A$3:A38,1)) -> 0 | B39: =IF(H39="UNIDADE CONSTRUTIVA",0,IF(H39="CÉLULA CONSTRUTIVA",OFFSET(B39,-1,0)+1,OFFSET(B39,-1,0))) -> 2 | C39: =IF(H39="CÉLULA CONSTRUTIVA",0,IF(H39="ETAPA",OFFSET(C39,-1,0)+1,OFFSET(C39,-1,0))) -> 2 | D39: =IF(H39="ETAPA",0,IF(H39="SUBETAPA",OFFSET(D39,-1,0)+1,OFFSET(D39,-1,0))) -> 2 | E39: =IF(H39="Subetapa",0,IF(H39="serviço",OFFSET(E39,-1,0)+1,OFFSET(E39,-1,0))) -> 2 | H39: SERVIÇO | I39: =IF(H39="Unidade Construtiva",TEXT(A39,"00"),IF(H39="Célula Construtiva",TEXT(B39,"00"),IF(H39="Etapa",CONCATENATE(TEXT(B39,"00"),".",TEXT(C39,"000")),IF(H39="Subetapa",CONCATENATE(TEXT(B39,"00"),".",TEXT(C39,"000"),".",TEXT(D39,"000")),IF(H39="Serviço",CONCATENATE(TEXT(B39,"00"),".",TEXT(C39,"000"),".",TEXT(D39,"000"),".",TEXT(E39,"000")),""))))) -> 02.002.002.002 | J39: Armação aço CA-50 ø 8,0mm para infraestrutura (corte e dobra em industria) | K39: kg | L39: =Aço_Infraestrutura!E23 -> 3069.6 | M39: =IFERROR(VLOOKUP(J39,CPU!$D$2:$H$327,5,FALSE),0) -> 7.456275 | N39: =IF(H39="Serviço",M39*L39,IF(H39="CÉLULA CONSTRUTIVA",SUMIFS($N$8:$N$352,$B$8:$B$352,B39,$H$8:$H$352,"Serviço"),IF(H39="ETAPA",SUMIFS($N$8:$N$352,$B$8:$B$352,B39,$C$8:$C$352,C39,$H$8:$H$352,"Serviço"),IF(H39="SUBETAPA",SUMIFS($N$8:$N$352,$B$8:$B$352,B39,$C$8:$C$352,C39,$D$8:$D$352,D39,$H$8:$H$352,"Serviço"),0)))) -> 22887.782 | P39: Finalizado
A40: =IF($H40="UNIDADE CONSTRUTIVA",OFFSET(A40,-1,0)+1,LARGE(A$3:A39,1)) -> 0 | B40: =IF(H40="UNIDADE CONSTRUTIVA",0,IF(H40="CÉLULA CONSTRUTIVA",OFFSET(B40,-1,0)+1,OFFSET(B40,-1,0))) -> 2 | C40: =IF(H40="CÉLULA CONSTRUTIVA",0,IF(H40="ETAPA",OFFSET(C40,-1,0)+1,OFFSET(C40,-1,0))) -> 2 | D40: =IF(H40="ETAPA",0,IF(H40="SUBETAPA",OFFSET(D40,-1,0)+1,OFFSET(D40,-1,0))) -> 2 | E40: =IF(H40="Subetapa",0,IF(H40="serviço",OFFSET(E40,-1,0)+1,OFFSET(E40,-1,0))) -> 3 | H40: SERVIÇO | I40: =IF(H40="Unidade Construtiva",TEXT(A40,"00"),IF(H40="Célula Construtiva",TEXT(B40,"00"),IF(H40="Etapa",CONCATENATE(TEXT(B40,"00"),".",TEXT(C40,"000")),IF(H40="Subetapa",CONCATENATE(TEXT(B40,"00"),".",TEXT(C40,"000"),".",TEXT(D40,"000")),IF(H40="Serviço",CONCATENATE(TEXT(B40,"00"),".",TEXT(C40,"000"),".",TEXT(D40,"000"),".",TEXT(E40,"000")),""))))) -> 02.002.002.003 | J40: Armação aço CA-50 ø 10,0mm para infraestrutura (corte e dobra em industria) | K40: kg | L40: =Aço_Infraestrutura!F23 -> 5992.3 | M40: =IFERROR(VLOOKUP(J40,CPU!$D$2:$H$327,5,FALSE),0) -> 7.166275 | N40: =IF(H40="Serviço",M40*L40,IF(H40="CÉLULA CONSTRUTIVA",SUMIFS($N$8:$N$352,$B$8:$B$352,B40,$H$8:$H$352,"Serviço"),IF(H40="ETAPA",SUMIFS($N$8:$N$352,$B$8:$B$352,B40,$C$8:$C$352,C40,$H$8:$H$352,"Serviço"),IF(H40="SUBETAPA",SUMIFS($N$8:$N$352,$B$8:$B$352,B40,$C$8:$C$352,C40,$D$8:$D$352,D40,$H$8:$H$352,"Serviço"),0)))) -> 42942.47 | P40: Finalizado
A41: =IF($H41="UNIDADE CONSTRUTIVA",OFFSET(A41,-1,0)+1,LARGE(A$3:A40,1)) -> 0 | B41: =IF(H41="UNIDADE CONSTRUTIVA",0,IF(H41="CÉLULA CONSTRUTIVA",OFFSET(B41,-1,0)+1,OFFSET(B41,-1,0))) -> 2 | C41: =IF(H41="CÉLULA CONSTRUTIVA",0,IF(H41="ETAPA",OFFSET(C41,-1,0)+1,OFFSET(C41,-1,0))) -> 2 | D41: =IF(H41="ETAPA",0,IF(H41="SUBETAPA",OFFSET(D41,-1,0)+1,OFFSET(D41,-1,0))) -> 2 | E41: =IF(H41="Subetapa",0,IF(H41="serviço",OFFSET(E41,-1,0)+1,OFFSET(E41,-1,0))) -> 4 | H41: SERVIÇO | I41: =IF(H41="Unidade Construtiva",TEXT(A41,"00"),IF(H41="Célula Construtiva",TEXT(B41,"00"),IF(H41="Etapa",CONCATENATE(TEXT(B41,"00"),".",TEXT(C41,"000")),IF(H41="Subetapa",CONCATENATE(TEXT(B41,"00"),".",TEXT(C41,"000"),".",TEXT(D41,"000")),IF(H41="Serviço",CONCATENATE(TEXT(B41,"00"),".",TEXT(C41,"000"),".",TEXT(D41,"000"),".",TEXT(E41,"000")),""))))) -> 02.002.002.004 | J41: Armação aço CA-50 ø 12,5mm para infraestrutura (corte e dobra em industria) | K41: kg | L41: =Aço_Infraestrutura!G23 -> 3487.6 | M41: =IFERROR(VLOOKUP(J41,CPU!$D$2:$H$327,5,FALSE),0) -> 6.996275 | N41: =IF(H41="Serviço",M41*L41,IF(H41="CÉLULA CONSTRUTIVA",SUMIFS($N$8:$N$352,$B$8:$B$352,B41,$H$8:$H$352,"Serviço"),IF(H41="ETAPA",SUMIFS($N$8:$N$352,$B$8:$B$352,B41,$C$8:$C$352,C41,$H$8:$H$352,"Serviço"),IF(H41="SUBETAPA",SUMIFS($N$8:$N$352,$B$8:$B$352,B41,$C$8:$C$352,C41,$D$8:$D$352,D41,$H$8:$H$352,"Serviço"),0)))) -> 24400.209 | P41: Finalizado
A42: =IF($H42="UNIDADE CONSTRUTIVA",OFFSET(A42,-1,0)+1,LARGE(A$3:A41,1)) -> 0 | B42: =IF(H42="UNIDADE CONSTRUTIVA",0,IF(H42="CÉLULA CONSTRUTIVA",OFFSET(B42,-1,0)+1,OFFSET(B42,-1,0))) -> 2 | C42: =IF(H42="CÉLULA CONSTRUTIVA",0,IF(H42="ETAPA",OFFSET(C42,-1,0)+1,OFFSET(C42,-1,0))) -> 2 | D42: =IF(H42="ETAPA",0,IF(H42="SUBETAPA",OFFSET(D42,-1,0)+1,OFFSET(D42,-1,0))) -> 2 | E42: =IF(H42="Subetapa",0,IF(H42="serviço",OFFSET(E42,-1,0)+1,OFFSET(E42,-1,0))) -> 5 | H42: SERVIÇO | I42: =IF(H42="Unidade Construtiva",TEXT(A42,"00"),IF(H42="Célula Construtiva",TEXT(B42,"00"),IF(H42="Etapa",CONCATENATE(TEXT(B42,"00"),".",TEXT(C42,"000")),IF(H42="Subetapa",CONCATENATE(TEXT(B42,"00"),".",TEXT(C42,"000"),".",TEXT(D42,"000")),IF(H42="Serviço",CONCATENATE(TEXT(B42,"00"),".",TEXT(C42,"000"),".",TEXT(D42,"000"),".",TEXT(E42,"000")),""))))) -> 02.002.002.005 | J42: Armação aço CA-50 ø 16,0mm para infraestrutura (corte e dobra em industria) | K42: kg | L42: =Aço_Infraestrutura!H23 -> 2557.9 | M42: =IFERROR(VLOOKUP(J42,CPU!$D$2:$H$327,5,FALSE),0) -> 7.316775 | N42: =IF(H42="Serviço",M42*L42,IF(H42="CÉLULA CONSTRUTIVA",SUMIFS($N$8:$N$352,$B$8:$B$352,B42,$H$8:$H$352,"Serviço"),IF(H42="ETAPA",SUMIFS($N$8:$N$352,$B$8:$B$352,B42,$C$8:$C$352,C42,$H$8:$H$352,"Serviço"),IF(H42="SUBETAPA",SUMIFS($N$8:$N$352,$B$8:$B$352,B42,$C$8:$C$352,C42,$D$8:$D$352,D42,$H$8:$H$352,"Serviço"),0)))) -> 18715.579 | P42: Finalizado
A43: =IF($H43="UNIDADE CONSTRUTIVA",OFFSET(A43,-1,0)+1,LARGE(A$3:A42,1)) -> 0 | B43: =IF(H43="UNIDADE CONSTRUTIVA",0,IF(H43="CÉLULA CONSTRUTIVA",OFFSET(B43,-1,0)+1,OFFSET(B43,-1,0))) -> 2 | C43: =IF(H43="CÉLULA CONSTRUTIVA",0,IF(H43="ETAPA",OFFSET(C43,-1,0)+1,OFFSET(C43,-1,0))) -> 2 | D43: =IF(H43="ETAPA",0,IF(H43="SUBETAPA",OFFSET(D43,-1,0)+1,OFFSET(D43,-1,0))) -> 2 | E43: =IF(H43="Subetapa",0,IF(H43="serviço",OFFSET(E43,-1,0)+1,OFFSET(E43,-1,0))) -> 6 | H43: SERVIÇO | I43: =IF(H43="Unidade Construtiva",TEXT(A43,"00"),IF(H43="Célula Construtiva",TEXT(B43,"00"),IF(H43="Etapa",CONCATENATE(TEXT(B43,"00"),".",TEXT(C43,"000")),IF(H43="Subetapa",CONCATENATE(TEXT(B43,"00"),".",TEXT(C43,"000"),".",TEXT(D43,"000")),IF(H43="Serviço",CONCATENATE(TEXT(B43,"00"),".",TEXT(C43,"000"),".",TEXT(D43,"000"),".",TEXT(E43,"000")),""))))) -> 02.002.002.006 | J43: Armação aço CA-50 ø 20,0mm para infraestrutura (corte e dobra em industria) | K43: kg | L43: =Aço_Infraestrutura!I23 -> 3999 | M43: =IFERROR(VLOOKUP(J43,CPU!$D$2:$H$327,5,FALSE),0) -> 7.316775 | N43: =IF(H43="Serviço",M43*L43,IF(H43="CÉLULA CONSTRUTIVA",SUMIFS($N$8:$N$352,$B$8:$B$352,B43,$H$8:$H$352,"Serviço"),IF(H43="ETAPA",SUMIFS($N$8:$N$352,$B$8:$B$352,B43,$C$8:$C$352,C43,$H$8:$H$352,"Serviço"),IF(H43="SUBETAPA",SUMIFS($N$8:$N$352,$B$8:$B$352,B43,$C$8:$C$352,C43,$D$8:$D$352,D43,$H$8:$H$352,"Serviço"),0)))) -> 29259.783 | P43: Finalizado
A44: =IF($H44="UNIDADE CONSTRUTIVA",OFFSET(A44,-1,0)+1,LARGE(A$3:A43,1)) -> 0 | B44: =IF(H44="UNIDADE CONSTRUTIVA",0,IF(H44="CÉLULA CONSTRUTIVA",OFFSET(B44,-1,0)+1,OFFSET(B44,-1,0))) -> 2 | C44: =IF(H44="CÉLULA CONSTRUTIVA",0,IF(H44="ETAPA",OFFSET(C44,-1,0)+1,OFFSET(C44,-1,0))) -> 2 | D44: =IF(H44="ETAPA",0,IF(H44="SUBETAPA",OFFSET(D44,-1,0)+1,OFFSET(D44,-1,0))) -> 2 | E44: =IF(H44="Subetapa",0,IF(H44="serviço",OFFSET(E44,-1,0)+1,OFFSET(E44,-1,0))) -> 7 | H44: SERVIÇO | I44: =IF(H44="Unidade Construtiva",TEXT(A44,"00"),IF(H44="Célula Construtiva",TEXT(B44,"00"),IF(H44="Etapa",CONCATENATE(TEXT(B44,"00"),".",TEXT(C44,"000")),IF(H44="Subetapa",CONCATENATE(TEXT(B44,"00"),".",TEXT(C44,"000"),".",TEXT(D44,"000")),IF(H44="Serviço",CONCATENATE(TEXT(B44,"00"),".",TEXT(C44,"000"),".",TEXT(D44,"000"),".",TEXT(E44,"000")),""))))) -> 02.002.002.007 | J44: Armação aço CA-50 ø 25,0mm para infraestrutura (corte e dobra em industria) | K44: kg | L44: =Aço_Infraestrutura!J23 -> 382 | M44: =IFERROR(VLOOKUP(J44,CPU!$D$2:$H$327,5,FALSE),0) -> 7.316775 | N44: =IF(H44="Serviço",M44*L44,IF(H44="CÉLULA CONSTRUTIVA",SUMIFS($N$8:$N$352,$B$8:$B$352,B44,$H$8:$H$352,"Serviço"),IF(H44="ETAPA",SUMIFS($N$8:$N$352,$B$8:$B$352,B44,$C$8:$C$352,C44,$H$8:$H$352,"Serviço"),IF(H44="SUBETAPA",SUMIFS($N$8:$N$352,$B$8:$B$352,B44,$C$8:$C$352,C44,$D$8:$D$352,D44,$H$8:$H$352,"Serviço"),0)))) -> 2795.008 | P44: Finalizado
A45: =IF($H45="UNIDADE CONSTRUTIVA",OFFSET(A45,-1,0)+1,LARGE(A$3:A44,1)) -> 0 | B45: =IF(H45="UNIDADE CONSTRUTIVA",0,IF(H45="CÉLULA CONSTRUTIVA",OFFSET(B45,-1,0)+1,OFFSET(B45,-1,0))) -> 2 | C45: =IF(H45="CÉLULA CONSTRUTIVA",0,IF(H45="ETAPA",OFFSET(C45,-1,0)+1,OFFSET(C45,-1,0))) -> 2 | D45: =IF(H45="ETAPA",0,IF(H45="SUBETAPA",OFFSET(D45,-1,0)+1,OFFSET(D45,-1,0))) -> 2 | E45: =IF(H45="Subetapa",0,IF(H45="serviço",OFFSET(E45,-1,0)+1,OFFSET(E45,-1,0))) -> 8 | H45: SERVIÇO | I45: =IF(H45="Unidade Construtiva",TEXT(A45,"00"),IF(H45="Célula Construtiva",TEXT(B45,"00"),IF(H45="Etapa",CONCATENATE(TEXT(B45,"00"),".",TEXT(C45,"000")),IF(H45="Subetapa",CONCATENATE(TEXT(B45,"00"),".",TEXT(C45,"000"),".",TEXT(D45,"000")),IF(H45="Serviço",CONCATENATE(TEXT(B45,"00"),".",TEXT(C45,"000"),".",TEXT(D45,"000"),".",TEXT(E45,"000")),""))))) -> 02.002.002.008 | J45: Armação aço CA-50 ø 32,0mm para infraestrutura (corte e dobra em industria) | K45: kg | L45: =Aço_Infraestrutura!K23 -> 611.3 | M45: 7 | N45: =IF(H45="Serviço",M45*L45,IF(H45="CÉLULA CONSTRUTIVA",SUMIFS($N$8:$N$352,$B$8:$B$352,B45,$H$8:$H$352,"Serviço"),IF(H45="ETAPA",SUMIFS($N$8:$N$352,$B$8:$B$352,B45,$C$8:$C$352,C45,$H$8:$H$352,"Serviço"),IF(H45="SUBETAPA",SUMIFS($N$8:$N$352,$B$8:$B$352,B45,$C$8:$C$352,C45,$D$8:$D$352,D45,$H$8:$H$352,"Serviço"),0)))) -> 4279.1 | P45: Finalizado
A46: =IF($H46="UNIDADE CONSTRUTIVA",OFFSET(A46,-1,0)+1,LARGE(A$3:A45,1)) -> 0 | B46: =IF(H46="UNIDADE CONSTRUTIVA",0,IF(H46="CÉLULA CONSTRUTIVA",OFFSET(B46,-1,0)+1,OFFSET(B46,-1,0))) -> 2 | C46: =IF(H46="CÉLULA CONSTRUTIVA",0,IF(H46="ETAPA",OFFSET(C46,-1,0)+1,OFFSET(C46,-1,0))) -> 2 | D46: =IF(H46="ETAPA",0,IF(H46="SUBETAPA",OFFSET(D46,-1,0)+1,OFFSET(D46,-1,0))) -> 2 | E46: =IF(H46="Subetapa",0,IF(H46="serviço",OFFSET(E46,-1,0)+1,OFFSET(E46,-1,0))) -> 9 | H46: SERVIÇO | I46: =IF(H46="Unidade Construtiva",TEXT(A46,"00"),IF(H46="Célula Construtiva",TEXT(B46,"00"),IF(H46="Etapa",CONCATENATE(TEXT(B46,"00"),".",TEXT(C46,"000")),IF(H46="Subetapa",CONCATENATE(TEXT(B46,"00"),".",TEXT(C46,"000"),".",TEXT(D46,"000")),IF(H46="Serviço",CONCATENATE(TEXT(B46,"00"),".",TEXT(C46,"000"),".",TEXT(D46,"000"),".",TEXT(E46,"000")),""))))) -> 02.002.002.009 | J46: Armação aço CA-60 ø 5,00mm para infraestrutura (corte e dobra em industria) | K46: kg | L46: =Aço_Infraestrutura!L23 -> 9 | M46: =IFERROR(VLOOKUP(J46,CPU!$D$2:$H$327,5,FALSE),0) -> 7.796275 | N46: =IF(H46="Serviço",M46*L46,IF(H46="CÉLULA CONSTRUTIVA",SUMIFS($N$8:$N$352,$B$8:$B$352,B46,$H$8:$H$352,"Serviço"),IF(H46="ETAPA",SUMIFS($N$8:$N$352,$B$8:$B$352,B46,$C$8:$C$352,C46,$H$8:$H$352,"Serviço"),IF(H46="SUBETAPA",SUMIFS($N$8:$N$352,$B$8:$B$352,B46,$C$8:$C$352,C46,$D$8:$D$352,D46,$H$8:$H$352,"Serviço"),0)))) -> 70.166475 | P46: Finalizado
A47: =IF($H47="UNIDADE CONSTRUTIVA",OFFSET(A47,-1,0)+1,LARGE(A$3:A46,1)) -> 0 | B47: =IF(H47="UNIDADE CONSTRUTIVA",0,IF(H47="CÉLULA CONSTRUTIVA",OFFSET(B47,-1,0)+1,OFFSET(B47,-1,0))) -> 2 | C47: =IF(H47="CÉLULA CONSTRUTIVA",0,IF(H47="ETAPA",OFFSET(C47,-1,0)+1,OFFSET(C47,-1,0))) -> 2 | D47: =IF(H47="ETAPA",0,IF(H47="SUBETAPA",OFFSET(D47,-1,0)+1,OFFSET(D47,-1,0))) -> 3 | E47: =IF(H47="Subetapa",0,IF(H47="serviço",OFFSET(E47,-1,0)+1,OFFSET(E47,-1,0))) -> 0 | H47: SUBETAPA | I47: =IF(H47="Unidade Construtiva",TEXT(A47,"00"),IF(H47="Célula Construtiva",TEXT(B47,"00"),IF(H47="Etapa",CONCATENATE(TEXT(B47,"00"),".",TEXT(C47,"000")),IF(H47="Subetapa",CONCATENATE(TEXT(B47,"00"),".",TEXT(C47,"000"),".",TEXT(D47,"000")),IF(H47="Serviço",CONCATENATE(TEXT(B47,"00"),".",TEXT(C47,"000"),".",TEXT(D47,"000"),".",TEXT(E47,"000")),""))))) -> 02.002.003 | J47: Concreto | N47: =IF(H47="Serviço",M47*L47,IF(H47="CÉLULA CONSTRUTIVA",SUMIFS($N$8:$N$352,$B$8:$B$352,B47,$H$8:$H$352,"Serviço"),IF(H47="ETAPA",SUMIFS($N$8:$N$352,$B$8:$B$352,B47,$C$8:$C$352,C47,$H$8:$H$352,"Serviço"),IF(H47="SUBETAPA",SUMIFS($N$8:$N$352,$B$8:$B$352,B47,$C$8:$C$352,C47,$D$8:$D$352,D47,$H$8:$H$352,"Serviço"),0)))) -> 226244.19
