Workbook
Name \0: #REF!
Name \0: #REF!
Name \0: #REF!
Name \0: #REF!
Name \0: #REF!
Name \0: #REF!
Name \0: #REF!
Name \0: #REF!
Name \0: #REF!
Name \0: #REF!
Name \0: #REF!
Name \0: #REF!
Name \1: #REF!
Name \1: #REF!
Name \1: #REF!
Name \1: #REF!
Name \1: #REF!
Name \1: #REF!
Name \1: #REF!
Name \1: #REF!
Name \1: #REF!
Name \a: #REF!
Name \a: #REF!
Name \a: #REF!
Name \a: #REF!
Name \a: #REF!
Name \a: #REF!
Name \a: #REF!
Name \a: #REF!
Name \a: #REF!
Name \a: #REF!
Name \a: #REF!
Name \b: #REF!
Name \b: #REF!
Name \b: #REF!
Name \b: #REF!
Name \b: #REF!
Name \b: #REF!
Name \b: #REF!
Name \b: #REF!
Name \c: #REF!
Name \c: #REF!
Name \c: #REF!
Name \c: #REF!
Name \c: #REF!
Name \c: #REF!
Name \c: #REF!
Name \c: #REF!
Name \d: #REF!
Name \d: #REF!
Name \d: #REF!
Name \d: #REF!
Name \d: #REF!
Name \d: #REF!
Name \d: #REF!
Name \d: #REF!
Name \e: #REF!
Name \e: #REF!
Name \e: #REF!
Name \e: #REF!

Sheet OBRA
A1: Obra | B1: Sense106
A2: Empresa | B2: HOLZE Empreendimentos
A3: Revisão | B3: R00
A4: DADOS OBRA
A6: ARQUITETURA
B8: Descrição | C8: Unidade | D8: Quantidade
B9: ÁREA DO TERRENO | C9: M2 | D9: 720.16
B10: ÁREA CONSTRUÍDA | C10: M2 | D10: 8700
B11: NÚMERO DE UNIDADES HABITACIONAIS | C11: UN | D11: =20*3 -> 60
B12: MESES DE OBRA | C12: MÊS | D12: 48
B13: NÚMERO DE PAVIMENTOS | C13: UN | D13: 27

Sheet EPC's
A1: Obra | B1: =OBRA!B1 -> Sense106
A2: Empresa | B2: =OBRA!B2 -> HOLZE Empreendimentos
A3: Revisão | B3: =OBRA!B3 -> R00
A4: LEVANTAMENTO QUANTITATIVO
A6: Equipamentos de proteção coletiva
A8: Bandejas de proteção
B10: Descrição | C10: Unidade | D10: Quantidade
B11: Perímetro de projeção embasamento | C11: m | D11: 102.22
B12: Número de montagens de bandeja primária | C12: un | D12: 1
B13: Perímetro de projeção torre | C13: m | D13: 69.49
B14: Número de montagens de bandeja primária | C14: un | D14: 1
B15: Bandeja de proteção primária | C15: m | D15: =D11*D12+D13*D14 -> 171.71
B16: Perímetro de projeção torre | C16: m | D16: =D13 -> 69.49
B17: Número de montagens de bandeja secundária | C17: un | D17: 5
B18: Bandeja de proteção secundária | C18: m | D18: =D16*D17 -> 347.45
A20: Guarda - corpo de desforma
B22: Descrição | C22: Unidade | D22: Quantidade
B23: Perímetro de projeção da torre | C23: m | D23: =D16 -> 69.49
B24: Repetições de pavimentos** | C24: un | D24: 4
B25: Proteção de periferia pós desforma torre | C25: m | D25: =(D23*D24) -> 277.96
A27: Tela fachadeira
B29: Descrição | C29: Unidade | D29: Quantidade
B30: Area da fachada coberta | C30: m² | D30: =1998.89+2*2016.93 -> 6032.75
B31: Tela fachadeira | C31: m2 | D31: =D30 -> 6032.75
A33: Fechamento removível de vãos em madeira
B35: Descrição | C35: Unidade | D35: Quantidade
B36: Área das portas de elevadores | C36: m2 | D36: =0.9*2.4 -> 2.16
B37: Quantidade de elevadores | C37: un | D37: 2
B38: Quantidade de portas de elevadores | C38: un | D38: =D37*25 -> 50
B39: Fechamento removível de vãos em madeira | C39: m2 | D39: =D36*D38 -> 108
A41: Guarda - corpo de vãos
B43: Descrição | C43: Unidade | D43: Quantidade
B44: Perímetro de vãos | C44: m | D44: =9.8+14.5+12.2+23.56+12.8*20 -> 316.06
B45: Guarda - corpo de vãos | C45: m | D45: =D44 -> 316.06
A47: Tapume
B49: Descrição | C49: Unidade | D49: Quantidade
B50: Perímetro de encontro com pavimentação | C50: m | D50: 25.72
B51: Altura do tapume | C51: m | D51: 2.4
B52: Área de tapume | C52: m2 | D52: =D51*D50 -> 61.728
A54: Linha de vida
B56: Descrição | C56: Unidade | D56: Quantidade
B57: Perímetro da torre | C57: m | D57: =D25 -> 277.96
B58: Linha de vida | C58: m | D58: =D57 -> 277.96
A60: SLQA
B62: Descrição | C62: Unidade | D62: Quantidade
B63: Perímetro de projeção torre | C63: m | D63: =D16 -> 69.49
B64: Altura de cobrimento da tela | C64: m | D64: =3.24*2 -> 6.48
B65: Tela SQLA | C65: m2 | D65: =D63*D64 -> 450.2952
A67: Fechamento de fossos
B69: Descrição | C69: Unidade | D69: Quantidade
B70: Area de fossos | C70: m2 | D70: 12.14
B71: Numero de pavimentos | C71: un | D71: =OBRA!D13 -> 27
B72: Área de fechamento de fossos | C72: m2 | D72: =D71*D70 -> 327.78
A74: Cobertura para proteção de pedestres
B76: Descrição | C76: Unidade | D76: Quantidade
B77: Perímetro de encontro com pavimentação | C77: m | D77: =D50 -> 25.72
B78: Repetição | C78: un | D78: 1
B79: Cobertura para proteção de pedestres | C79: m | D79: =D78*D77 -> 25.72

Sheet CANTEIRO
A1: Obra | B1: =OBRA!B1 -> Sense106
A2: Empresa | B2: =OBRA!B2 -> HOLZE Empreendimentos
A3: Revisão | B3: =OBRA!B3 -> R00
A4: LEVANTAMENTO QUANTITATIVO
A6: Instalações de canteiro
A8: Instalações de canteiro
B10: Descrição | C10: Unidade | D10: Quantidade
B11: Produtividade média | C11: ac/prazo | D11: =OBRA!D10/OBRA!D12 -> 181.25
B12: Pm | C12: h/m2 | D12: 49
B13: Numero de funcionários | C13: un | D13: =ROUNDUP((D12*OBRA!D10)/OBRA!D12/180,) -> 50
B14: Equipe administrativa | C14: un | D14: 5
B15: Pontos de água e esgoto | C15: un | D15: =ROUNDUP(($D$13+D14)/20,0) -> 3 | E15: 20 funcionários/ponto
B16: Bebedouro | C16: un | D16: =ROUNDUP(OBRA!$D$13/5,0) -> 6 | E16: 1 / 5 pav.
B17: Ferramentas | C17: R$ | D17: =800*(D13+D14) -> 44000 | E17: 800,00/func.
B18: EPI | C18: R$ | D18: =500*(D13+D14) -> 27500 | E18: 500,00/func.
B19: Banheiro | C19: un | D19: =ROUNDUP(($D$13+D14)/20,0) -> 3 | E19: 1/20 func
A21: Mobiliário de canteiro
B23: Descrição | C23: Unidade | D23: Quantidade | E23: Custo unitário | F23: Custo total
B24: Cadeira | C24: un | D24: =ROUNDUP(D28*1.5,0) -> 8 | E24: 200 | F24: =D24*E24 -> 1600
B25: Mesa | C25: un | D25: 1 | E25: 1000 | F25: =E25*D25 -> 1000
B26: Ar condicionado | C26: un | D26: 1 | E26: 5000 | F26: =E26*D26 -> 5000
B27: Armário | C27: m | D27: 6 | E27: 900 | F27: =E27*D27 -> 5400
B28: Escrivaninha | C28: un | D28: =D14 -> 5 | E28: 800 | F28: =E28*D28 -> 4000
B29: TOTAL | F29: =F26+F27+F28+F25+F24 -> 17000
B30: Descrição | C30: Unidade | D30: Quantidade | E30: Custo unitário | F30: Custo total
B31: Computador pessoal | C31: un | D31: =D14 -> 5 | E31: 6000 | F31: =D31*E31 -> 30000
B32: Impressora | C32: un | D32: 1 | E32: 2000 | F32: =E32*D32 -> 2000
B33: Roteador | C33: un | D33: 2 | E33: 500 | F33: =E33*D33 -> 1000
B34: TOTAL | F34: =+F31+F32+F33 -> 33000

Sheet CONTROLE_TEC
E5: COND.01
A6: Item | B6: Descrição/Especificação | C6: Unid. | D6: V. Unit. (R$) | E6: Qtde. | F6: V. Total (R$) | G6: Observações
B7: CONTROLE TECNOLÓGICO - CONCRETO
A8: 1 | B8: Laudo e ART | C8: vb | D8: 1450 | E8: 1 | F8: =$D8*E8 -> 1450
A9: =A8+1 -> 2 | B9: Controle Tecnologico - Coleta materiais da obra | C9: unid. | D9: 20 | E9: =ROUNDUP((ORÇAMENTO!L226+ORÇAMENTO!L235+ORÇAMENTO!L251+SUPRA!K53)/8,0)*4 -> 1780 | F9: =$D9*E9 -> 35600 | G9: 4 CPs por caminhão betoneira de 8m³
A10: =A9+1 -> 3 | B10: Controle Tecnológico - Ensaio de concreto endurecido/grouth - compressão simples / Detalhe: Concreto | C10: cps | D10: 12.5 | E10: =E9 -> 1780 | F10: =$D10*E10 -> 22250 | G10: 4 CPs por caminhão betoneira de 8m³
A11: =A10+1 -> 4 | B11: Determinação do módulo de deformação tangente inicial (Eci) (módulo de elasticidade), Incluindo Avaliação Estática dos Resultados (NBR 8522 e NBR 12655) | C11: ensaio | D11: 480 | E11: 5 | F11: =$D11*E11 -> 2400 | G11: A cada 5 pav. (e quando houver troca de fornecedor)
C12: SUBTOTAL: | F12: =SUM(F8:F11) -> 61700
B14: ENSAIOS PARA ARGAMASSA DE REVESTIMENTO (FACHADA)
A15: 1 | B15: Ensaio de arrancamento de argamassa de revestimento Determinação da aderencia a tração | C15: ensaios | D15: 2760 | E15: 1 | F15: =$D15*E15 -> 2760 | G15: 1 ensaio por torre
C16: SUBTOTAL: | F16: =F15 -> 2760
C18: VALOR TOTAL: | F18: =F16+F12 -> 64460

Sheet ORÇAMENTO
G4: PROJETO: | I4: SENSE106 | O4: REVISÃO: | P4: DATA
G5: EMPRESA: | I5: HOLZE EMPREENDIMENTOS | O5: R01 - Edileni Silva | P5: 45608
A6: Unidade Construtiva | B6: Célula Construtiva | C6: Etapa | D6: Subetapa | E6: Serviço | G6: GERENCIAMENTO EXECUTIVO
A7: 0 | B7: 0 | C7: 0 | D7: 0 | E7: 0 | G7: Atalho | H7: NIVEL | I7: Item | J7: Descrição | K7: Unidade | L7: Quant. | M7: Preço un | N7: Total | O7: Considerações | P7: Situação
A8: =IF($H8="UNIDADE CONSTRUTIVA",OFFSET(A8,-1,0)+1,LARGE(A$3:A5,1)) -> 1 | B8: =IF(H8="UNIDADE CONSTRUTIVA",0,IF(H8="CÉLULA CONSTRUTIVA",OFFSET(B8,-1,0)+1,OFFSET(B8,-1,0))) -> 0 | C8: =IF(H8="CÉLULA CONSTRUTIVA",0,IF(H8="ETAPA",OFFSET(C8,-1,0)+1,OFFSET(C8,-1,0))) -> 0 | D8: =IF(H8="ETAPA",0,IF(H8="SUBETAPA",OFFSET(D8,-1,0)+1,OFFSET(D8,-1,0))) -> 0 | E8: =IF(H8="Subetapa",0,IF(H8="serviço",OFFSET(E8,-1,0)+1,OFFSET(E8,-1,0))) -> 0 | H8: UNIDADE CONSTRUTIVA | I8: =IF(H8="Unidade Construtiva",TEXT(A8,"00"),IF(H8="Célula Construtiva",TEXT(B8,"00"),IF(H8="Etapa",CONCATENATE(TEXT(B8,"00"),".",TEXT(C8,"000")),IF(H8="Subetapa",CONCATENATE(TEXT(B8,"00"),".",TEXT(C8,"000"),".",TEXT(D8,"000")),IF(H8="Serviço",CONCATENATE(TEXT(B8,"00"),".",TEXT(C8,"000"),".",TEXT(D8,"000"),".",TEXT(E8,"000")),""))))) -> 01 | J8: CUSTOS INDIRETOS | N8: =SUM(N9,N13,N47,N78,N111,N175) -> 5309214
H9: CÉLULA CONSTRUTIVA | I9: 01 | J9: AQUISIÇÃO DO TERRENO | N9: =N10 -> 450000
H10: ETAPA | I10: 01 | J10: AQUISIÇÃO DO TERRENO | N10: =N11 -> 450000
H11: SUBETAPA | I11: 01.000.001 | J11: Aquisição do terreno | N11: =N12 -> 450000
H12: SERVIÇO | I12: 01.000.001.001 | J12: Aquisição do terreno | K12: vb | L12: 1 | M12: 450000 | N12: =M12*L12 -> 450000 | O12: Custo atualizado conforme solicitação do dia 27/10/2024 | P12: Lançado ERP
H13: CÉLULA CONSTRUTIVA | I13: 02 | J13: ESTUDOS, PROJETOS E CONSULTORIAS | N13: =SUM(N14,N25,N35,N42) -> 598398.03
H14: ETAPA | I14: 02.001 | J14: ESTUDOS, PROJETOS E CONSULTORIAS | N14: =SUM(N15,N17,N19,N21,N23) -> 23178.03
H15: SUBETAPA | I15: 02.001.001 | J15: Memorial descritivo | N15: =SUM(N16) -> 4134.83
H16: SERVIÇO | I16: 02.001.001.001 | J16: Memorial descritivo | K16: vb | L16: 1 | M16: =VLOOKUP(J16,Preços!$C$7:$F$498,4,FALSE) -> 4134.83 | N16: =M16*L16 -> 4134.83 | O16: Custo conforme respostas informadas no formulário de custos indiretos. | P16: Lançado ERP
H17: SUBETAPA | I17: 02.001.002 | J17: Levantamento Topográfico | N17: =SUM(N18) -> 1224.76
H18: SERVIÇO | I18: 02.001.002.001 | J18: Levantamento Topográfico | K18: vb | L18: 1 | M18: =VLOOKUP(J18,Preços!$C$7:$F$498,4,FALSE) -> 1224.76 | N18: =M18*L18 -> 1224.76 | O18: Custo conforme respostas informadas no formulário de custos indiretos. | P18: Lançado ERP
H19: SUBETAPA | I19: 02.001.003 | J19: Estudo ambiental | N19: =SUM(N20) -> 4318.44
H20: SERVIÇO | I20: 02.001.003.001 | J20: Estudo ambiental | K20: vb | L20: 1 | M20: =VLOOKUP(J20,Preços!$C$7:$F$498,4,FALSE) -> 4318.44 | N20: =M20*L20 -> 4318.44 | O20: Custo conforme respostas informadas no formulário de custos indiretos. | P20: Lançado ERP
H21: SUBETAPA | I21: 02.001.004 | J21: Sondagem do terreno | N21: =SUM(N22) -> 9500
H22: SERVIÇO | I22: 02.001.004.001 | J22: Sondagem do terreno | K22: vb | L22: 1 | M22: =VLOOKUP(J22,Preços!$C$7:$F$498,4,FALSE) -> 9500 | N22: =M22*L22 -> 9500 | O22: Custo conforme respostas informadas no formulário de custos indiretos. | P22: Lançado ERP
H23: SUBETAPA | I23: 02.001.005 | J23: Projeto de canteiro | N23: =SUM(N24) -> 4000
H24: SERVIÇO | I24: 02.001.005.001 | J24: Projeto de canteiro | K24: vb | L24: 1 | M24: =VLOOKUP(J24,Preços!$C$7:$F$498,4,FALSE) -> 4000 | N24: =M24*L24 -> 4000 | O24: Custo conforme respostas informadas no formulário de custos indiretos. | P24: Lançado ERP
H25: ETAPA | I25: 02.002 | J25: PROJETOS | N25: =SUM(N26,N28,N30,N32) -> 348000
H26: SUBETAPA | I26: 02.002.001 | J26: Legalização de incorporação | N26: =SUM(N27) -> 33000
H27: SERVIÇO | I27: 02.002.000.001 | J27: Legalização de incorporação | K27: vb | L27: 1 | M27: =VLOOKUP(J27,Preços!$C$7:$F$498,4,FALSE) -> 33000 | N27: =M27*L27 -> 33000 | O27: Custo conforme respostas informadas no formulário de custos indiretos. | P27: Lançado ERP
H28: SUBETAPA | I28: 02.002.001 | J28: Projetos Integrados | N28: =SUM(N29) -> 230000
H29: SERVIÇO | I29: 02.002.001.001 | J29: Projeto Arquitetônico legal | K29: vb | L29: 1 | M29: 230000 | N29: =M29*L29 -> 230000 | O29: Custo atualizado conforme solicitação do dia 27/10/2024 | P29: Lançado ERP
H30: SUBETAPA | I30: 02.002.002 | J30: Projeto de interiores | N30: =SUM(N31) -> 25000
H31: SERVIÇO | I31: 02.002.002.001 | J31: Projeto de interiores | K31: vb | L31: 1 | M31: =VLOOKUP(J31,Preços!$C$7:$F$498,4,FALSE) -> 25000 | N31: =M31*L31 -> 25000 | O31: Custo conforme respostas informadas no formulário de custos indiretos. | P31: Lançado ERP
H32: SUBETAPA | I32: 02.002.003 | J32: Projetos Estrutural e Fundações | N32: =SUM(N33:N34) -> 60000
H33: SERVIÇO | I33: 02.002.003.001 | J33: Projeto Fundações | K33: vb | L33: 1 | M33: =VLOOKUP(J33,Preços!$C$7:$F$498,4,FALSE) -> 8000 | N33: =M33*L33 -> 8000 | O33: Custo conforme respostas informadas no formulário de custos indiretos. | P33: Lançado ERP
H34: SERVIÇO | I34: 02.002.003.002 | J34: Projeto Estrutural | K34: vb | L34: 1 | M34: =VLOOKUP(J34,Preços!$C$7:$F$498,4,FALSE) -> 52000 | N34: =M34*L34 -> 52000 | O34: Custo conforme respostas informadas no formulário de custos indiretos. | P34: Lançado ERP
H35: ETAPA | I35: 02.003 | J35: CONSULTORIAS | N35: =SUM(N36,N38) -> 160000
H36: SUBETAPA | I36: 02.003.001 | J36: Orçamento e planejamento | N36: =SUM(N37) -> 40000
H37: SERVIÇO | I37: 02.003.001.001 | J37: Orçamento e planejamento | K37: vb | L37: 1 | M37: =VLOOKUP(J37,Preços!$C$7:$F$498,4,FALSE) -> 40000 | N37: =M37*L37 -> 40000 | O37: Custo conforme respostas informadas no formulário de custos indiretos. | P37: Lançado ERP
H38: SUBETAPA | I38: 02.003.002 | J38: Softwares | N38: =SUM(N39:N41) -> 120000
H39: SERVIÇO | I39: 02.003.002.001 | J39: Assinatura Ampli | K39: vb | L39: 1 | M39: 33887.04 | N39: =M39*L39 -> 33887.04 | O39: Custo atualizado conforme solicitação do dia 27/10/2024 | P39: Lançado ERP
H40: SERVIÇO | I40: 02.003.002.002 | J40: Assinatura Prevision | K40: vb | L40: 1 | M40: 71760.8 | N40: =M40*L40 -> 71760.8 | O40: Custo atualizado conforme solicitação do dia 27/10/2024 | P40: Lançado ERP
H41: SERVIÇO | I41: 02.003.002.003 | J41: Assinatura Nuvem de Dados | K41: vb | L41: 1 | M41: 14352.16 | N41: =M41*L41 -> 14352.16 | O41: Custo atualizado conforme solicitação do dia 27/10/2024 | P41: Lançado ERP
H42: ETAPA | I42: 02.004 | J42: ENSAIOS E LAUDOS | N42: =SUM(N43,N45) -> 67220
H43: SUBETAPA | I43: 02.004.001 | J43: Controle Tecnologico de Concreto | N43: =SUM(N44) -> 64460
H44: SERVIÇO | I44: 02.004.001.001 | J44: Controle Tecnologico de Concreto | K44: vb | L44: 1 | M44: =CONTROLE_TEC!F18 -> 64460 | N44: =M44*L44 -> 64460 | O44: Custo atualizado conforme solicitação do dia 27/10/2024 / Alteração na profundidade das estacas. | P44: Lançado ERP
H45: SUBETAPA | I45: 02.004.002 | J45: Arrancamento de argamassa | N45: =SUM(N46) -> 2760
H46: SERVIÇO | I46: 02.004.002.001 | J46: Ensaio de arrancamento de argamassa de revestimento | K46: vb | L46: 1 | M46: =VLOOKUP(J46,Preços!$C$7:$F$498,4,FALSE) -> 2760 | N46: =M46*L46 -> 2760 | O46: Custo conforme respostas informadas no formulário de custos indiretos. | P46: Lançado ERP
H47: CÉLULA CONSTRUTIVA | I47: 03 | J47: TAXAS, DOCUMENTOS | N47: =N48 -> 1106677
H48: ETAPA | I48: 03.001 | J48: TAXAS, DOCUMENTOS | N48: =SUM(N49,N51,N57,N60,N62,N64,N66,N68,N70,N72,N74,N76) -> 1106677
H49: SUBETAPA | I49: 03.001.001 | J49: Despesas de Seguros | N49: =SUM(N50) -> 17000
H50: SERVIÇO | I50: 03.001.001.001 | J50: Despesas de Seguros | K50: vb | L50: 1 | M50: 17000 | N50: =M50*L50 -> 17000 | O50: Custo atualizado conforme solicitação do dia 27/10/2024 | P50: Lançado ERP
H51: SUBETAPA | I51: 03.001.002 | J51: Aprovações e legalização | N51: =SUM(N52:N56) -> 80000
H52: SERVIÇO | I52: 03.001.002.001 | J52: Aprovação e legalização ambiental | K52: vb | L52: 1 | M52: 11428.57 | N52: =M52*L52 -> 11428.57 | O52: Custo atualizado conforme solicitação do dia 27/10/2024 | P52: Lançado ERP
H53: SERVIÇO | I53: 03.001.002.002 | J53: Aprovação e legalização prefeitura | K53: vb | L53: 1 | M53: 36571.43 | N53: =M53*L53 -> 36571.43 | O53: Custo atualizado conforme solicitação do dia 27/10/2024 | P53: Lançado ERP
H54: SERVIÇO | I54: 03.001.002.003 | J54: Aprovação e legalização água e esgoto | K54: vb | L54: 1 | M54: 11428.57 | N54: =M54*L54 -> 11428.57 | O54: Custo atualizado conforme solicitação do dia 27/10/2024 | P54: Lançado ERP
H55: SERVIÇO | I55: 03.001.002.004 | J55: Aprovação e legalização elétrico | K55: vb | L55: 1 | M55: 11428.57 | N55: =M55*L55 -> 11428.57 | O55: Custo atualizado conforme solicitação do dia 27/10/2024 | P55: Lançado ERP
H56: SERVIÇO | I56: 03.001.002.005 | J56: Aprovação e legalização Bombeiros | K56: vb | L56: 1 | M56: 9142.86 | N56: =M56*L56 -> 9142.86 | O56: Custo atualizado conforme solicitação do dia 27/10/2024 | P56: Lançado ERP
H57: SUBETAPA | I57: 03.001.003 | J57: Taxas de ART, cartório, licenças, certidões e jurídicas | N57: =SUM(N58:N59) -> 40000
H58: SERVIÇO | I58: 03.001.003.001 | J58: Taxas de ART | K58: vb | L58: 1 | M58: =VLOOKUP(J58,Preços!$C$7:$F$498,4,FALSE) -> 5000 | N58: =M58*L58 -> 5000 | O58: Custo conforme respostas informadas no formulário de custos indiretos. | P58: Lançado ERP
H59: SERVIÇO | I59: 03.001.003.002 | J59: Despesas de cartório / taxas gerais | K59: vb | L59: 1 | M59: =VLOOKUP(J59,Preços!$C$7:$F$498,4,FALSE) -> 35000 | N59: =M59*L59 -> 35000 | O59: Custo conforme respostas informadas no formulário de custos indiretos. | P59: Lançado ERP
H60: SUBETAPA | I60: 03.001.004 | J60: Taxas de Alvará | N60: =SUM(N61) -> 88000
H61: SERVIÇO | I61: 03.001.004.001 | J61: Taxas de Alvará | K61: vb | L61: 1 | M61: =VLOOKUP(J61,Preços!$C$7:$F$498,4,FALSE) -> 88000 | N61: =M61*L61 -> 88000 | O61: Custo conforme respostas informadas no formulário de custos indiretos. | P61: Lançado ERP
H62: SUBETAPA | I62: 03.001.005 | J62: Outorga | N62: =SUM(N63) -> 800905.22
H63: SERVIÇO | I63: 03.001.005.001 | J63: Outorga | K63: vb | L63: 1 | M63: =VLOOKUP(J63,Preços!$C$7:$F$498,4,FALSE) -> 800905.22 | N63: =M63*L63 -> 800905.22 | O63: Custo conforme respostas informadas no formulário de custos indiretos. | P63: Lançado ERP
H64: SUBETAPA | I64: 03.001.006 | J64: Incorporação | N64: =SUM(N65) -> 10000
H65: SERVIÇO | I65: 03.001.006.001 | J65: Incorporação | K65: vb | L65: 1 | M65: =VLOOKUP(J65,Preços!$C$7:$F$498,4,FALSE) -> 10000 | N65: =M65*L65 -> 10000 | O65: Custo conforme respostas informadas no formulário de custos indiretos. | P65: Lançado ERP
H66: SUBETAPA | I66: 03.001.007 | J66: IPTU | N66: =SUM(N67) -> 15000
H67: SERVIÇO | I67: 03.001.007.001 | J67: Iptu | K67: vb | L67: 1 | M67: =VLOOKUP(J67,Preços!$C$7:$F$498,4,FALSE) -> 15000 | N67: =M67*L67 -> 15000 | O67: Custo conforme respostas informadas no formulário de custos indiretos. | P67: Lançado ERP
H68: SUBETAPA | I68: 03.001.008 | J68: Taxa Habite-se | N68: =SUM(N69) -> 11319.43
H69: SERVIÇO | I69: 03.001.008.001 | J69: Alvará Habite-se | K69: vb | L69: 1 | M69: =VLOOKUP(J69,Preços!$C$7:$F$498,4,FALSE) -> 11319.43 | N69: =M69*L69 -> 11319.43 | O69: Custo conforme respostas informadas no formulário de custos indiretos. | P69: Lançado ERP
H70: SUBETAPA | I70: 03.001.009 | J70: As built | N70: =SUM(N71) -> 10000
H71: SERVIÇO | I71: 03.001.009.001 | J71: As built | K71: vb | L71: 1 | M71: =VLOOKUP(J71,Preços!$C$7:$F$498,4,FALSE) -> 10000 | N71: =M71*L71 -> 10000 | O71: Custo conforme respostas informadas no formulário de custos indiretos. | P71: Lançado ERP
H72: SUBETAPA | I72: 03.001.010 | J72: Laudo técnico de vistoria de entrega | N72: =SUM(N73) -> 10000
H73: SERVIÇO | I73: 03.001.010.001 | J73: Laudo técnico de vistoria de entrega | K73: vb | L73: 1 | M73: =VLOOKUP(J73,Preços!$C$7:$F$498,4,FALSE) -> 10000 | N73: =M73*L73 -> 10000 | O73: Custo conforme respostas informadas no formulário de custos indiretos. | P73: Lançado ERP
H74: SUBETAPA | I74: 03.001.011 | J74: Manuais de condomínio/proprietários | N74: =SUM(N75) -> 15000
H75: SERVIÇO | I75: 03.001.011.001 | J75: Manuais de condomínio/proprietários | K75: vb | L75: 1 | M75: =VLOOKUP(J75,Preços!$C$7:$F$498,4,FALSE) -> 15000 | N75: =M75*L75 -> 15000 | O75: Custo conforme respostas informadas no formulário de custos indiretos. | P75: Lançado ERP
H76: SUBETAPA | I76: 03.001.012 | J76: Certidão INSS | N76: =SUM(N77) -> 9452.34
H77: SERVIÇO | I77: 03.001.012.001 | J77: Certidão INSS | K77: vb | L77: 1 | M77: =VLOOKUP(J77,Preços!$C$7:$F$498,4,FALSE) -> 9452.34 | N77: =M77*L77 -> 9452.34 | O77: Custo conforme respostas informadas no formulário de custos indiretos. | P77: Lançado ERP
H78: CÉLULA CONSTRUTIVA | I78: 04 | J78: SEGURANÇA, MEIO AMBIENTE E SAÚDE | N78: =SUM(N79,N82) -> 479062.28
H79: ETAPA | I79: 04.001 | J79: SEGURANÇA, MEIO AMBIENTE E SAÚDE | N79: =N80 -> 35000
H80: SUBETAPA | I80: 04.001.001 | J80: Serviço terceirizado de segurança e técnico | N80: =SUM(N81) -> 35000
H81: SERVIÇO | I81: 04.001.001.001 | J81: Serviço terceirizado de segurança do trabalho | K81: vb | L81: 1 | M81: 35000 | N81: =M81*L81 -> 35000 | O81: Custo atualizado conforme solicitação do dia 27/10/2024 | P81: Lançado ERP
H82: ETAPA | I82: 04.002 | J82: EQUIPAMENTOS DE PROTEÇÃO | N82: =SUM(N83,N85,N88,N94,N97,N99,N104,N106,N109) -> 444062.28
H83: SUBETAPA | I83: 04.002.001 | J83: EPI | N83: =SUM(N84) -> 27500
H84: SERVIÇO | I84: 04.002.001.001 | J84: Equipamento de proteção individual - EPI | K84: vb | L84: 1 | M84: =VLOOKUP(J84,Preços!$C$7:$F$498,4,FALSE) -> 27500 | N84: =M84*L84 -> 27500 | O84: Custo conforme respostas informadas no formulário de custos indiretos. | P84: Lançado ERP
H85: SUBETAPA | I85: 04.002.002 | J85: Bandejas de proteção | N85: =SUM(N86:N87) -> 85000
H86: SERVIÇO | I86: 04.002.002.001 | J86: Bandejas Primarias | K86: vb | L86: 1 | M86: 68095.67 | N86: =M86*L86 -> 68095.67 | O86: Custo atualizado conforme solicitação do dia 27/10/2024 | P86: Lançado ERP
H87: SERVIÇO | I87: 04.002.002.002 | J87: Bandejas Secundarias | K87: vb | L87: 1 | M87: 16904.33 | N87: =M87*L87 -> 16904.33 | O87: Custo atualizado conforme solicitação do dia 27/10/2024 | P87: Lançado ERP
H88: SUBETAPA | I88: 04.002.003 | J88: Guarda-corpos, fechamentos removíveis e proteções | N88: =SUM(N89:N93) -> 54182.74
H89: SERVIÇO | I89: 04.002.003.001 | J89: Guarda-corpo de vãos, fixado em forma de madeira, em trama de madeira com tela de polipropileno | K89: m | L89: 316.06 | M89: =VLOOKUP(J89,Preços!$C$7:$F$498,4,FALSE) -> 18.6728 | N89: =M89*L89 -> 5901.7252 | O89: Custo conforme respostas informadas no formulário de custos indiretos. | P89: Lançado ERP
H90: SERVIÇO | I90: 04.002.003.002 | J90: Fechamento removível de vãos de porta de elevador em madeira | K90: m2 | L90: 108 | M90: =VLOOKUP(J90,Preços!$C$7:$F$498,4,FALSE) -> 99.339 | N90: =M90*L90 -> 10728.612 | O90: Custo conforme respostas informadas no formulário de custos indiretos. | P90: Lançado ERP
H91: SERVIÇO | I91: 04.002.003.003 | J91: Guarda corpo de laje apos desforma | K91: m | L91: 277.96 | M91: =VLOOKUP(J91,Preços!$C$7:$F$498,4,FALSE) -> 11.7464 | N91: =M91*L91 -> 3265.0293 | O91: Custo conforme respostas informadas no formulário de custos indiretos. | P91: Lançado ERP
H92: SERVIÇO | I92: 04.002.003.004 | J92: Fechamento de fossos | K92: m2 | L92: 327.78 | M92: =VLOOKUP(J92,Preços!$C$7:$F$498,4,FALSE) -> 93.7232 | N92: =M92*L92 -> 30720.59 | O92: Custo conforme respostas informadas no formulário de custos indiretos. | P92: Lançado ERP
H93: SERVIÇO | I93: 04.002.003.005 | J93: Cobertura para proteção de pedestres | K93: m | L93: 25.72 | M93: =VLOOKUP(J93,Preços!$C$7:$F$498,4,FALSE) -> 138.6774 | N93: =M93*L93 -> 3566.7827 | O93: Custo conforme respostas informadas no formulário de custos indiretos. | P93: Lançado ERP
H94: SUBETAPA | I94: 04.002.004 | J94: Tela fachadeira e SLQA | N94: =SUM(N95:N96) -> 123871.33
H95: SERVIÇO | I95: 04.002.004.001 | J95: Tela em polietileno para fachada | K95: m2 | L95: 6032.75 | M95: =VLOOKUP(J95,Preços!$C$7:$F$498,4,FALSE) -> 9.9461 | N95: =M95*L95 -> 60002.335 | O95: Custo conforme respostas informadas no formulário de custos indiretos. | P95: Lançado ERP
H96: SERVIÇO | I96: 04.002.004.002 | J96: Tela SLQA | K96: vb | L96: 1 | M96: =VLOOKUP(J96,Preços!$C$7:$F$498,4,FALSE) -> 63869 | N96: =M96*L96 -> 63869 | O96: Custo conforme respostas informadas no formulário de custos indiretos. | P96: Lançado ERP
H97: SUBETAPA | I97: 04.002.005 | J97: Linha de vida | N97: =SUM(N98) -> 43508.523
H98: SERVIÇO | I98: 04.002.005.001 | J98: Linha de vida | K98: m | L98: 277.96 | M98: =VLOOKUP(J98,Preços!$C$7:$F$498,4,FALSE) -> 156.528 | N98: =M98*L98 -> 43508.523 | O98: Custo conforme respostas informadas no formulário de custos indiretos. | P98: Lançado ERP
H99: SUBETAPA | I99: 04.002.006 | J99: PPRA / PCMSO / PCMAT / Projetos de segurança do trabalho | N99: =SUM(N100:N103) -> 20500
H100: SERVIÇO | I100: 04.002.006.001 | J100: Elaboração do Programa de Prevenção dos Riscos Ambientais (PPRA) | K100: vb | L100: 1 | M100: =VLOOKUP(J100,Preços!$C$7:$F$498,4,FALSE) -> 5000 | N100: =M100*L100 -> 5000 | O100: Custo conforme respostas informadas no formulário de custos indiretos. | P100: Lançado ERP
H101: SERVIÇO | I101: 04.002.006.002 | J101: Elaboração do Programa de Controle Médico de Saúde Ocupacional (PCMSO) | K101: vb | L101: 1 | M101: =VLOOKUP(J101,Preços!$C$7:$F$498,4,FALSE) -> 5500 | N101: =M101*L101 -> 5500 | O101: Custo conforme respostas informadas no formulário de custos indiretos. | P101: Lançado ERP
H102: SERVIÇO | I102: 04.002.006.003 | J102: Elaboração do Programa de Condições e meio Ambiente de Trabalho na Indústria de Construção (PCMAT) | K102: vb | L102: 1 | M102: =VLOOKUP(J102,Preços!$C$7:$F$498,4,FALSE) -> 5000 | N102: =M102*L102 -> 5000 | O102: Custo conforme respostas informadas no formulário de custos indiretos. | P102: Lançado ERP
H103: SERVIÇO | I103: 04.002.006.004 | J103: Projetos de Segurança do Trabalho | K103: vb | L103: 1 | M103: =VLOOKUP(J103,Preços!$C$7:$F$498,4,FALSE) -> 5000 | N103: =M103*L103 -> 5000 | O103: Custo conforme respostas informadas no formulário de custos indiretos. | P103: Lançado ERP
...

Sheet MO Infra
L6: =(92273.31+12957.46+45908+7494) -> 158632.77 | M6: =L6/(259.53*2+288.02) -> 196.55148

Sheet Composições
B1: Projeto | C1: =ORÇAMENTO!I4 -> SENSE106
B2: Empresa | C2: =ORÇAMENTO!I5 -> HOLZE EMPREENDIMENTOS
B3: Revisão | C3: =ORÇAMENTO!O5 -> R01 - Edileni Silva
A4: COMPOSIÇÕES
A6: PILARES
A7: Montagem | E7: Fabricação | G7: =13/2 -> 6.5 | H7: 1x | I7: 6x | J7: 10x
A8: Arame | B8: kg | C8: 0.0357 | E8: Prego 17x21 | F8: kg | G8: 0.215 | H8: =G8/$G$7 -> 0.033076923 | I8: =H8*6 -> 0.19846154 | J8: =H8*10 -> 0.33076923
A9: Desmoldante | B9: l | C9: 0.017 | E9: Pontalete | F9: m3 | G9: 0.0338 | H9: =G9/$G$7 -> 0.0052 | I9: =H9*6 -> 0.0312 | J9: =H9*10 -> 0.052
A10: Prego 17x21 | B10: kg | C10: 0.027 | E10: Compensado | F10: um | G10: 0.552 | H10: =G10/$G$7 -> 0.084923077 | I10: =H10*6 -> 0.50953846 | J10: =H10*10 -> 0.84923077
E11: Sarrafo | F11: m3 | G11: 0.017 | H11: =G11/$G$7 -> 0.0026153846 | I11: =H11*6 -> 0.015692308 | J11: =H11*10 -> 0.026153846
A13: Fabricação+montagem
A14: Arame | B14: kg | C14: =C8 -> 0.0357 | D14: 12.05
A15: Desmoldante | B15: l | C15: =C9 -> 0.017 | D15: 7.7
A16: Prego 17x21 | B16: kg | C16: =C10+J8 -> 0.35776923 | D16: 17.19
A17: Pontalete | B17: m | C17: =J9/(0.025*0.1) -> 20.8 | D17: =1100*(0.1*0.025) -> 2.75
A18: Compensado | B18: um | C18: =J10 -> 0.84923077 | D18: 102.89
A19: Sarrafo | B19: m | C19: =J11/(0.07*0.07) -> 5.3375196 | D19: =1100*(0.07*0.07) -> 5.39
D20: =SUMPRODUCT(C14:C19,D14:D19) -> 180.05772
A23: VIGAS
A24: Montagem | E24: Fabricação | G24: =13/2 -> 6.5 | H24: 1x | I24: 6x | J24: 10x
A25: Arame | B25: kg | C25: 0.0357 | E25: Prego 17x21 | F25: kg | G25: 0.159 | H25: =G25/$G$7 -> 0.024461538 | I25: =H25*6 -> 0.14676923 | J25: =H25*10 -> 0.24461538
A26: Desmoldante | B26: l | C26: 0.017 | E26: Pontalete | F26: m3 | G26: 0.0009 | H26: =G26/$G$7 -> 0.00013846154 | I26: =H26*6 -> 0.00083076923 | J26: =H26*10 -> 0.0013846154
A27: Prego 17x21 | B27: kg | C27: 0.049 | E27: Compensado | F27: um | G27: 0.4736 | H27: =G27/$G$7 -> 0.072861538 | I27: =H27*6 -> 0.43716923 | J27: =H27*10 -> 0.72861538
A28: Pontalete | B28: m3 | C28: 0.00164 | E28: Sarrafo | F28: m3 | G28: 0.0145 | H28: =G28/$G$7 -> 0.0022307692 | I28: =H28*6 -> 0.013384615 | J28: =H28*10 -> 0.022307692
A30: Fabricação+montagem
A31: Arame | B31: kg | C31: =C25 -> 0.0357 | D31: 12.05
A32: Desmoldante | B32: l | C32: =C26 -> 0.017 | D32: 7.7
A33: Prego 17x21 | B33: kg | C33: =C27+J25 -> 0.29361538 | D33: 17.19
A34: Pontalete | B34: m | C34: =(J26+C28)/(0.025*0.1) -> 1.2098462 | D34: =1100*(0.1*0.025) -> 2.75
A35: Compensado | B35: um | C35: =J27 -> 0.72861538 | D35: 102.89
A36: Sarrafo | B36: m | C36: =J28/(0.07*0.07) -> 4.5525903 | D36: =1100*(0.07*0.07) -> 5.39
D37: =SUMPRODUCT(C31:C36,D31:D36) -> 108.44111
A40: RAMPAS
A41: Montagem
A42: Arame | B42: kg | C42: 0.0357
A43: Desmoldante | B43: l | C43: 0.017
A44: Prego 17x21 | B44: kg | C44: 0.049
A45: Pontalete | B45: m3 | C45: 0.00164
A47: Fabricação+montagem | D47: 1x | E47: 10x
A48: Arame | B48: kg | C48: =C42 -> 0.0357 | D48: =C48 -> 0.0357 | E48: =D48 -> 0.0357 | F48: 12.05
A49: Desmoldante | B49: l | C49: 0.004 | D49: =C49 -> 0.004 | E49: =D49 -> 0.004 | F49: 7.7
A50: Prego 17x21 | B50: kg | C50: 0.172 | D50: =C50/6 -> 0.028666667 | E50: =D50*10 -> 0.28666667 | F50: 17.19
A51: Pontalete | B51: m | C51: 7.188 | D51: =C51/6 -> 1.198 | E51: =D51*10 -> 11.98 | F51: =1100*(0.1*0.025) -> 2.75
A52: Compensado | B52: um | C52: 0.495 | D52: =C52/6 -> 0.0825 | E52: =D52*10 -> 0.825 | F52: 102.89
A53: Sarrafo | B53: m | C53: 0.925 | D53: =C53/6 -> 0.15416667 | E53: =D53*10 -> 1.5416667 | F53: =1100*(0.07*0.07) -> 5.39
F54: =SUMPRODUCT(E48:E53,F48:F53) -> 131.52762
A56: LAJES
A57: Montagem | E57: Fabricação | G57: =13/2 -> 6.5 | H57: 1x | I57: 6x | J57: 10x
A58: Arame | B58: kg | C58: 0.0357 | E58: Compensado | F58: um | G58: 0.4736 | H58: =G58/$G$7 -> 0.072861538 | I58: =H58*6 -> 0.43716923 | J58: =H58*10 -> 0.72861538
A59: Desmoldante | B59: l | C59: 0.017
A61: Fabricação+montagem
A62: Arame | B62: kg | C62: =C58 -> 0.0357 | D62: 12.05
A63: Desmoldante | B63: l | C63: =C59 -> 0.017 | D63: 7.7
A64: Compensado | B64: um | C64: =J58 -> 0.72861538 | D64: 102.89
D65: =SUMPRODUCT(C62:C64,D62:D64) -> 75.528322
A68: BLOCOS DE FUNDAÇÃO E VIGAS BALDRAME
A69: Fabricação+montagem
A70: Desmoldante | B70: l | C70: 0.0167
A71: Sarrafo | B71: m | C71: 3.426
A72: Pontalete | B72: m2 | C72: 2.504 | D72: =C72*0.075*0.075 -> 0.014085
A73: Prego | B73: kg | C73: =0.042+0.029 -> 0.071
A74: Tábua | B74: m2 | C74: 4.284 | D74: =C74*0.025*0.3 -> 0.03213

Sheet Preços
B1: Projeto | C1: =ORÇAMENTO!I4 -> SENSE106
B2: Empresa | C2: =ORÇAMENTO!I5 -> HOLZE EMPREENDIMENTOS
B3: Revisão | C3: =ORÇAMENTO!O5 -> R01 - Edileni Silva
A4: SERVIÇOS
B6: Código | C6: Descrição | E6: Unidade | F6: Total
B7: 2149 | C7: Levantamento Topográfico | E7: vb | F7: 1224.76
B8: 2155 | C8: Projeto Arquitetônico legal | E8: vb | F8: 230000
B9: 2158 | C9: Projeto Estrutural | E9: vb | F9: 52000
B10: 2164 | C10: Projeto Fundações | E10: vb | F10: 8000
B11: 2168 | C11: Comunicação Visual | E11: vb | F11: 86965.7
B12: 2384 | C12: Escavação Mecânica Vala Exceto Rocha até 1.5m | E12: m3 | F12: 37.44
B13: 2413 | C13: Contrapiso comum, aderido, espessura de 6cm, com argamassa usinada | E13: m2 | F13: 26.73
B14: 2414 | C14: Contrapiso comum, aderido, espessura de 8cm, com argamassa usinada | E14: m2 | F14: 35.64
B15: 2417 | C15: Contrapiso comum, aderido, espessura de 5cm, com argamassa usinada | E15: m2 | F15: 22.275
B16: 2523 | C16: Forma Compensado Plástica 17mm Reaproveitamento 7x | E16: m2 | F16: 195031.93
B17: 2558 | C17: Armação aço CA-50 ø 6,3mm para supraestrutura (corte e dobra em indústria) | E17: kg | F17: 7.5498
B18: 2559 | C18: Armação aço CA-50 ø 8mm para supraestrutura (corte e dobra em indústria) | E18: kg | F18: 7.2105
... B443: 80138 | C443: Aquisição do terreno | E443: vb | F443: 450000
M467: =VLOOKUP(J467,Preços!$C$6:$E$1205,4,FALSE) -> #N/A

Sheet Projeção torre
B1: Projeto | C1: =ORÇAMENTO!I4 -> SENSE106
B2: Empresa | C2: =ORÇAMENTO!I5 -> HOLZE EMPREENDIMENTOS
B3: Revisão | C3: =ORÇAMENTO!O5 -> R01 - Edileni Silva
A4: PROJEÇÃO DA TORRE
E41: Área: | F41: 720.16 | G41: m²
E42: Perímetro | F42: =28*2+25.72*2 -> 107.44 | G42: m
E45: TÉRREO | F45: 622.81
E46: GARAGEM G2 | F46: 653.05
E47: GARAGEM G3 | F47: 653.05
E48: GARAGEM G4 | F48: 653.05
E49: LAZER | F49: 653.05
E50: TIPOS | F50: =269.69*20 -> 5393.8
E51: COBERTURA | F51: 269.69
E52: RES. SUPERIOR | F52: 67.76
E55: ÁREA CONSTRUÍDA | F55: =F45+F46+F47+F48+F49+F50+F52 -> 8696.57

Sheet Cotações
B1: Projeto | C1: =ORÇAMENTO!I4 -> SENSE106
B2: Empresa | C2: =ORÇAMENTO!I5 -> HOLZE EMPREENDIMENTOS
B3: Revisão | C3: R00 - Michelle Furlan - 06/02/24
A4: CONTROLE DE COTAÇÕES
A5: INFORMAÇÕES IMPORTANTES: CNPJ XXXX / XXXXX / Endereço da obra: XXXX
A6: Item | B6: Data | C6: Site | D6: Status | E6: E-mail

Sheet Estacas
B1: Projeto | C1: =ORÇAMENTO!I4 -> SENSE106
B2: Empresa | C2: =ORÇAMENTO!I5 -> HOLZE EMPREENDIMENTOS
B3: Revisão | C3: R00 - Michelle Furlan -
A4: ESTACAS
A5: ITEM | B5: TIPO | C5: QUANT | D5: DIMENSÕES UNITÁRIAS | H5: TOTAL | I5: ESCAV | J5: BOTA-FORA | K5: CONCRETO | M5: TAXA AÇO
D6: C. Topo | E6: C. Apoio | F6: Ø peça | G6: H | M6: KG/M3
D7: m | E7: m | F7: m | G7: m | H7: m | I7: m3 | J7: m3 | K7: m3 | L7: TIPO
A8: 1091 - LOCAÇÃO DAS ESTACAS - R0.pdf // 1092 - LOCAÇÃO DAS ESTACAS - R0.pdf // 1093 - LOCAÇÃO DAS ESTACAS - R0.pdf // 1094 - LOCAÇÃO DAS ESTACAS - R0.pdf // 1095 - LOCAÇÃO DAS ESTACAS - R0.pdf // 1096 - LOCAÇÃO DAS ESTACAS - R0.pdf // 1097 - LOCAÇÃO DAS ESTACAS - R0.pdf // 1098 - LOCAÇÃO DAS ESTACAS - R0.pdf // 1099 - LOCAÇÃO DAS ESTACAS - R0.pdf // 1100 - LOCAÇÃO DAS ESTACAS - R0.pdf // 1101 - LOCAÇÃO DAS ESTACAS - R0.pdf // 1102 - LOCAÇÃO DAS ESTACAS - R0.pdf // 1103 - LOCAÇÃO DAS ESTACAS - R0.pdf // 1104 - LOCAÇÃO DAS ESTACAS - R0.pdf // 1105 - LOCAÇÃO DAS ESTACAS - R0.pdf // 1106 - LOCAÇÃO DAS ESTACAS - R0.pdf // 1107 - LOCAÇÃO DAS ESTACAS - R0.pdf // 1108 - LOCAÇÃO DAS ESTACAS - R0.pdf // 1109 - LOCAÇÃO DAS ESTACAS - R0.pdf // 1110 - LOCAÇÃO DAS ESTACAS - R0.pdf // 1111 - LOCAÇÃO DAS ESTACAS - R0.pdf // 1112 - LOCAÇÃO DAS ESTACAS - R0.pdf // 1113 - LOCAÇÃO DAS ESTACAS - R0.pdf // 1114 - LOCAÇÃO DAS ESTACAS - R0.pdf // 1115 - LOCAÇÃO DAS ESTACAS - R0.pdf // 1116 - LOCAÇÃO DAS ESTACAS - R0.pdf // 1117 - LOCAÇÃO DAS ESTACAS - R0.pdf // 1118 - LOCAÇÃO DAS ESTACAS - R0.pdf // 1119 - LOCAÇÃO DAS ESTACAS - R0.pdf // 1120 - LOCAÇÃO DAS ESTACAS - R0.pdf // 1121 - LOCAÇÃO DAS ESTACAS - R0.pdf // 1122 - LOCAÇÃO DAS ESTACAS - R0.pdf
A9: F1 | B9: Hélice diam 50 cm | C9: 1 | E9: 35 | F9: 0.5 | G9: =IF(C9="","",ROUNDUP((E9-D9),1)) -> 35 | H9: =IF(C9="","",C9*G9) -> 35 | I9: =IF(C9="","",PI()*((F9/2)^2)*H9) -> 6.8722339 | J9: =IF(C9="","",I9*1.3) -> 8.9339041 | K9: =IF(C9="","",I9) -> 6.8722339 | L9: 40 MPa | M9: =IF(C9="","",K9*$M$7) -> 0
A10: F2 | B10: Hélice diam 50 cm | C10: 1 | E10: 35 | F10: 0.5 | G10: =IF(C10="","",ROUNDUP((E10-D10),1)) -> 35 | H10: =IF(C10="","",C10*G10) -> 35 | I10: =IF(C10="","",PI()*((F10/2)^2)*H10) -> 6.8722339 | J10: =IF(C10="","",I10*1.3) -> 8.9339041 | K10: =IF(C10="","",I10) -> 6.8722339 | L10: 40 MPa | M10: =IF(C10="","",K10*$M$7) -> 0
A11: F3 | B11: Hélice diam 50 cm | C11: 1 | E11: 35 | F11: 0.5 | G11: =IF(C11="","",ROUNDUP((E11-D11),1)) -> 35 | H11: =IF(C11="","",C11*G11) -> 35 | I11: =IF(C11="","",PI()*((F11/2)^2)*H11) -> 6.8722339 | J11: =IF(C11="","",I11*1.3) -> 8.9339041 | K11: =IF(C11="","",I11) -> 6.8722339 | L11: 40 MPa | M11: =IF(C11="","",K11*$M$7) -> 0
A12: F4 | B12: Hélice diam 50 cm | C12: 1 | E12: 35 | F12: 0.5 | G12: =IF(C12="","",ROUNDUP((E12-D12),1)) -> 35 | H12: =IF(C12="","",C12*G12) -> 35 | I12: =IF(C12="","",PI()*((F12/2)^2)*H12) -> 6.8722339 | J12: =IF(C12="","",I12*1.3) -> 8.9339041 | K12: =IF(C12="","",I12) -> 6.8722339 | L12: 40 MPa | M12: =IF(C12="","",K12*$M$7) -> 0
A13: F5 | B13: Hélice diam 50 cm | C13: 1 | E13: 35 | F13: 0.5 | G13: =IF(C13="","",ROUNDUP((E13-D13),1)) -> 35 | H13: =IF(C13="","",C13*G13) -> 35 | I13: =IF(C13="","",PI()*((F13/2)^2)*H13) -> 6.8722339 | J13: =IF(C13="","",I13*1.3) -> 8.9339041 | K13: =IF(C13="","",I13) -> 6.8722339 | L13: 40 MPa | M13: =IF(C13="","",K13*$M$7) -> 0
A14: F6 | B14: Hélice diam 50 cm | C14: 1 | E14: 35 | F14: 0.5 | G14: =IF(C14="","",ROUNDUP((E14-D14),1)) -> 35 | H14: =IF(C14="","",C14*G14) -> 35 | I14: =IF(C14="","",PI()*((F14/2)^2)*H14) -> 6.8722339 | J14: =IF(C14="","",I14*1.3) -> 8.9339041 | K14: =IF(C14="","",I14) -> 6.8722339 | L14: 40 MPa | M14: =IF(C14="","",K14*$M$7) -> 0
A15: F7 | B15: Hélice diam 50 cm | C15: 1 | E15: 35 | F15: 0.5 | G15: =IF(C15="","",ROUNDUP((E15-D15),1)) -> 35 | H15: =IF(C15="","",C15*G15) -> 35 | I15: =IF(C15="","",PI()*((F15/2)^2)*H15) -> 6.8722339 | J15: =IF(C15="","",I15*1.3) -> 8.9339041 | K15: =IF(C15="","",I15) -> 6.8722339 | L15: 40 MPa | M15: =IF(C15="","",K15*$M$7) -> 0
A16: F8 | B16: Hélice diam 50 cm | C16: 1 | E16: 35 | F16: 0.5 | G16: =IF(C16="","",ROUNDUP((E16-D16),1)) -> 35 | H16: =IF(C16="","",C16*G16) -> 35 | I16: =IF(C16="","",PI()*((F16/2)^2)*H16) -> 6.8722339 | J16: =IF(C16="","",I16*1.3) -> 8.9339041 | K16: =IF(C16="","",I16) -> 6.8722339 | L16: 40 MPa | M16: =IF(C16="","",K16*$M$7) -> 0
A17: F9 | B17: Hélice diam 50 cm | C17: 1 | E17: 35 | F17: 0.5 | G17: =IF(C17="","",ROUNDUP((E17-D17),1)) -> 35 | H17: =IF(C17="","",C17*G17) -> 35 | I17: =IF(C17="","",PI()*((F17/2)^2)*H17) -> 6.8722339 | J17: =IF(C17="","",I17*1.3) -> 8.9339041 | K17: =IF(C17="","",I17) -> 6.8722339 | L17: 40 MPa | M17: =IF(C17="","",K17*$M$7) -> 0
A18: F10 | B18: Hélice diam 50 cm | C18: 1 | E18: 35 | F18: 0.5 | G18: =IF(C18="","",ROUNDUP((E18-D18),1)) -> 35 | H18: =IF(C18="","",C18*G18) -> 35 | I18: =IF(C18="","",PI()*((F18/2)^2)*H18) -> 6.8722339 | J18: =IF(C18="","",I18*1.3) -> 8.9339041 | K18: =IF(C18="","",I18) -> 6.8722339 | L18: 40 MPa | M18: =IF(C18="","",K18*$M$7) -> 0
A19: F11 | B19: Hélice diam 50 cm | C19: 1 | E19: 35 | F19: 0.5 | G19: =IF(C19="","",ROUNDUP((E19-D19),1)) -> 35 | H19: =IF(C19="","",C19*G19) -> 35 | I19: =IF(C19="","",PI()*((F19/2)^2)*H19) -> 6.8722339 | J19: =IF(C19="","",I19*1.3) -> 8.9339041 | K19: =IF(C19="","",I19) -> 6.8722339 | L19: 40 MPa | M19: =IF(C19="","",K19*$M$7) -> 0
A20: F12 | B20: Hélice diam 60 cm | C20: 1 | E20: 35 | F20: 0.6 | G20: =IF(C20="","",ROUNDUP((E20-D20),1)) -> 35 | H20: =IF(C20="","",C20*G20) -> 35 | I20: =IF(C20="","",PI()*((F20/2)^2)*H20) -> 9.8960169 | J20: =IF(C20="","",I20*1.3) -> 12.864822 | K20: =IF(C20="","",I20) -> 9.8960169 | L20: 40 MPa | M20: =IF(C20="","",K20*$M$7) -> 0
... A40: P26+P31 | B40: Hélice diam 60 cm | C40: 8 | E40: 35 | F40: 0.6 | G40: =IF(C40="","",ROUNDUP((E40-D40),1)) -> 35 | H40: =IF(C40="","",C40*G40) -> 280 | I40: =IF(C40="","",PI()*((F40/2)^2)*H40) -> 79.168135 | J40: =IF(C40="","",I40*1.3) -> 102.91858 | K40: =IF(C40="","",I40) -> 79.168135 | L40: 40 MPa | M40: =IF(C40="","",K40*$M$7) -> 0
G41: =IF(C41="","",ROUNDUP((E41-D41),1)) | H41: =IF(C41="","",C41*G41) | I41: =IF(C41="","",PI()*((F41/2)^2)*H41) | J41: =IF(C41="","",I41*1.3) | K41: =IF(C41="","",I41) | M41: =IF(C41="","",K41*$M$7)
A42: Prova de carga | F42: =IF(B42="","",VLOOKUP(B42,$F$44:$G$52,2,0)) | G42: =IF(C42="","",ROUNDUP((E42-D42),1)) | H42: =IF(C42="","",C42*G42) | I42: =IF(C42="","",PI()*((F42/2)^2)*H42) | J42: =IF(C42="","",I42*1.3) | K42: =IF(C42="","",I42) | M42: =IF(C42="","",K42*$M$7)
A43: TOTAL GERAL | B43: Arrasamento | C43: =SUM(C8:C42) -> 92 | H43: =SUM(H8:H42) -> 3220 | I43: =SUM(I$8:I42) -> 840.88654 | J43: =SUM(J$8:J42) -> 1093.1525 | K43: =SUM(K$8:K42) -> 840.88654 | M43: =SUM(M$8:M42) -> 0
A44: OBSERVAÇÕES: | F44: Hélice diam 35 cm | G44: 0.35 | H44: =SUMIF($B$8:$B$42,$F44,$H$8:$H$42) -> 0 | K44: =SUMIF($L$8:$L$42,$L44,$K$8:$K$42) -> 0 | L44: 20 MPa
F45: Hélice diam 40 cm | G45: 0.4 | H45: =SUMIF($B$8:$B$42,$F45,$H$8:$H$42) -> 0 | K45: =SUMIF($L$8:$L$42,$L45,$K$8:$K$42) -> 0 | L45: 25 MPa
F46: Hélice diam 50 cm | G46: 0.5 | H46: =SUMIF($B$8:$B$42,$F46,$H$8:$H$42) -> 805 | K46: =SUMIF($L$8:$L$42,$L46,$K$8:$K$42) -> 0 | L46: 30 MPa
F47: Hélice diam 60 cm | G47: 0.6 | H47: =SUMIF($B$8:$B$42,$F47,$H$8:$H$42) -> 2415 | K47: =SUMIF($L$8:$L$42,$L47,$K$8:$K$42) -> 0 | L47: 35 MPa
F48: Hélice diam 70 cm | G48: 0.7 | H48: =SUMIF($B$8:$B$42,$F48,$H$8:$H$42) -> 0 | K48: =SUMIF($L$8:$L$42,$L48,$K$8:$K$42) -> 840.88654 | L48: 40 MPa
F49: Hélice diam 80 cm | G49: 0.8 | H49: =SUMIF($B$8:$B$42,$F49,$H$8:$H$42) -> 0 | K49: =SUMIF($L$8:$L$42,$L49,$K$8:$K$42) -> 0 | L49: .... MPa
F50: Hélice diam 90 cm | G50: 0.9 | H50: =SUMIF($B$8:$B$42,$F50,$H$8:$H$42) -> 0 | K50: =SUMIF($L$8:$L$42,$L50,$K$8:$K$42) -> 0 | L50: .... MPa
F51: E.P. Hélice diam 70 cm | G51: 0.7 | H51: =SUMIF($B$8:$B$42,$F51,$H$8:$H$42) -> 0 | K51: =SUMIF($L$8:$L$42,$L51,$K$8:$K$42) -> 0 | L51: .... MPa
F52: - | H52: =SUMIF($B$8:$B$42,$F52,$H$8:$H$42) -> 0 | K52: =SUMIF($L$8:$L$42,$L52,$K$8:$K$42) -> 0 | L52: .... MPa
A134: CUSTO
A135: *proposta salva no drive

Sheet Arm. Estacas
B1: Projeto | C1: =ORÇAMENTO!I4 -> SENSE106
B2: Empresa | C2: =ORÇAMENTO!I5 -> HOLZE EMPREENDIMENTOS
B3: Revisão | C3: R00 - Michelle Furlan - 15/05
A4: ARMAÇÃO ESTACAS
A5: ITEM | C5: QUANT | D5: QUANTIDADE POR ITEM CA-50 - m | K5: CA-60 - m
D6: 6.3 | E6: 8 | F6: 10 | G6: 12.5 | H6: 16 | I6: 20 | J6: 25 | K6: 5 | L6: 0 | M6: 0 | N6: 0 | O6: 0
A7: =Estacas!$A$8 -> 1091 - LOCAÇÃO DAS ESTACAS - R0.pdf // 1092 - LOCAÇÃO DAS ESTACAS - R0.pdf // 1093 - LOCAÇÃO DAS ESTACAS - R0.pdf // 1094 - LOCAÇÃO DAS ESTACAS - R0.pdf // 1095 - LOCAÇÃO DAS ESTACAS - R0.pdf // 1096 - LOCAÇÃO DAS ESTACAS - R0.pdf // 1097 - LOCAÇÃO DAS ESTACAS - R0.pdf // 1098 - LOCAÇÃO DAS ESTACAS - R0.pdf // 1099 - LOCAÇÃO DAS ESTACAS - R0.pdf // 1100 - LOCAÇÃO DAS ESTACAS - R0.pdf // 1101 - LOCAÇÃO DAS ESTACAS - R0.pdf // 1102 - LOCAÇÃO DAS ESTACAS - R0.pdf // 1103 - LOCAÇÃO DAS ESTACAS - R0.pdf // 1104 - LOCAÇÃO DAS ESTACAS - R0.pdf // 1105 - LOCAÇÃO DAS ESTACAS - R0.pdf // 1106 - LOCAÇÃO DAS ESTACAS - R0.pdf // 1107 - LOCAÇÃO DAS ESTACAS - R0.pdf // 1108 - LOCAÇÃO DAS ESTACAS - R0.pdf // 1109 - LOCAÇÃO DAS ESTACAS - R0.pdf // 1110 - LOCAÇÃO DAS ESTACAS - R0.pdf // 1111 - LOCAÇÃO DAS ESTACAS - R0.pdf // 1112 - LOCAÇÃO DAS ESTACAS - R0.pdf // 1113 - LOCAÇÃO DAS ESTACAS - R0.pdf // 1114 - LOCAÇÃO DAS ESTACAS - R0.pdf // 1115 - LOCAÇÃO DAS ESTACAS - R0.pdf // 1116 - LOCAÇÃO DAS ESTACAS - R0.pdf // 1117 - LOCAÇÃO DAS ESTACAS - R0.pdf // 1118 - LOCAÇÃO DAS ESTACAS - R0.pdf // 1119 - LOCAÇÃO DAS ESTACAS - R0.pdf // 1120 - LOCAÇÃO DAS ESTACAS - R0.pdf // 1121 - LOCAÇÃO DAS ESTACAS - R0.pdf // 1122 - LOCAÇÃO DAS ESTACAS - R0.pdf
A8: F1 | C8: 1 | D8: 8.575 | H8: 47.31
A9: F2 | C9: 1 | D9: 8.575 | H9: 47.31
A10: F3 | C10: 1 | D10: 8.575 | H10: 47.31
A11: F4 | C11: 1 | D11: 8.575 | H11: 47.31
A12: F5 | C12: 1 | D12: 8.575 | H12: 47.31
A13: F6 | C13: 1 | D13: 8.575 | H13: 47.31
A14: F7 | C14: 1 | D14: 8.575 | H14: 47.31
A15: F8 | C15: 1 | D15: 8.575 | H15: 47.31
A16: F9 | C16: 1 | D16: 8.575 | H16: 47.31
A17: F10 | C17: 1 | D17: 8.575 | H17: 47.31
A18: F11 | C18: 1 | D18: 10.78 | H18: 75.696
A19: F12 | C19: 1 | D19: 8.575 | H19: 47.31
... A39: P26+P31 | C39: 8 | D39: 10.78 | H39: 75.696
A40: PROJETO | D40: 1052 | H40: 6905.49
B41: TOTAL - M | C41: =SUM(D41:O41) -> 7922.695 | D41: =SUMPRODUCT(D7:D40,$C7:$C40) -> 1031.205 | E41: =SUMPRODUCT(E7:E40,$C7:$C40) -> 0 | F41: =SUMPRODUCT(F7:F40,$C7:$C40) -> 0 | G41: =SUMPRODUCT(G7:G40,$C7:$C40) -> 0 | H41: =SUMPRODUCT(H7:H40,$C7:$C40) -> 6891.49 | I41: =SUMPRODUCT(I7:I40,$C7:$C40) -> 0 | J41: =SUMPRODUCT(J7:J40,$C7:$C40) -> 0 | K41: =SUMPRODUCT(K7:K40,$C7:$C40) -> 0 | ... O41: =SUMPRODUCT(O7:O40,$C7:$C40) -> 0
B42: PESO kg/m | D42: 1 | E42: 1 | F42: 1 | G42: 1 | H42: 1 | I42: 1 | J42: 1 | K42: 1 | L42: 1 | M42: 1 | N42: 1 | O42: 1
B43: TOTAL - kg | C43: =SUM(D43:O43) -> 7922.695 | D43: =D42*D41 -> 1031.205 | E43: =E42*E41 -> 0 | F43: =F42*F41 -> 0 | G43: =G42*G41 -> 0 | H43: =H42*H41 -> 6891.49 | I43: =I42*I41 -> 0 | J43: =J42*J41 -> 0 | K43: =K42*K41 -> 0 | ... O43: =O42*O41 -> 0
A44: OBSERVAÇÕES: | D44: =1-D41/D40 -> 0.01976711 | E44: =IF(D44<10%,"Usar valor de projeto","Confirmar com cliente") -> Usar valor de projeto | H44: =1-H41/H40 -> 0.0020273724 | I44: =IF(H44<10%,"Usar valor de projeto","Confirmar com cliente") -> Usar valor de projeto
A46: TABELA DE AÇO
A47: CA-50 | D47: CA-60
A48: Ø - mm | B48: kg/m | C48: pol | D48: Ø - mm | E48: kg/m
A49: 6.3 | B49: 0.245 | C49: 1/4" | D49: 3.4 | E49: 0.079
A50: 8 | B50: 0.395 | C50: 5/16" | D50: 4.2 | E50: 0.109
A51: 10 | B51: 0.617 | C51: 3/8" | D51: 5 | E51: 0.154
A52: 12.5 | B52: 0.963 | C52: 1/2" | D52: 6 | E52: 0.222
A53: 16 | B53: 1.578 | C53: 5/8" | D53: 7 | E53: 0.302
A54: 20 | B54: 2.466 | C54: 3/4" | D54: 8 | E54: 0.395
A55: 25 | B55: 3.853 | C55: 1" | D55: 9.5 | E55: 0.558
A56: 32 | B56: 6.313 | C56: 1 1/4" | D56: 0
A57: 40 | B57: 9.865 | C57: 1 5/8" | D57: 0

Sheet Duto&Cisterna
D1: Projeto | E1: =ORÇAMENTO!I4 -> SENSE106
D2: Empresa | E2: =ORÇAMENTO!I5 -> HOLZE EMPREENDIMENTOS
D3: Revisão | E3: R00 - Michelle Furlan -
A4: DUTO E CISTERNA
A5: PROJETO:
A6: CÓDIGO DO RESERVATÓRIO | B6: NÚMERO DE REPETIÇÕES | C6: COMPRIMENTO DO RESERVATÓRIO | D6: LARGURA DO RESERVATÓRIO | E6: ESPESSURA DE CONCRETO | F6: ALTURA DO RESERVATÓRIO | G6: ALTURA INTERNA DO RESERVATÓRIO | H6: COMPRIMENTO INTERNO DO RESERVATÓRIO | I6: LARGURA INTERNA DO RESERVATÓRIO | J6: ESPESSURA DE LASTRO PARA O RESERVATÓRIO | K6: ESPAÇAMENTO LATERAL PARA ESCAVAÇÃO | L6: FORMA DO RESERVATÓRIO | M6: VOLUME DE CONCRETO | N6: VOLUME DE ESCAVAÇÃO | O6: VOLUME DE REATERRO | P6: VOLUME DE BOTA-FORA | Q6: APILOAMENTO DE VALA | R6: VOLUME DE LASTRO
A7: COD. | B7: R | C7: L | D7: B | E7: e.C. | F7: H | G7: h | H7: l | I7: b | J7: e.L. | K7: K | L7: F | M7: C | N7: VE | O7: VA | P7: VB | Q7: AP | R7: VM
B8: UD | C8: m | D8: m | E8: m | F8: m | G8: m | H8: m | I8: m | J8: m | K8: m | L8: m2 | M8: m3 | N8: m3 | O8: m3 | P8: m3 | Q8: m2 | R8: m3
A9: CISTERNA | B9: 1 | C9: 5.1 | D9: 3.2 | E9: 0.2 | F9: 3 | G9: =F9-E9 -> 2.8 | H9: =C9-E9*2 -> 4.7 | I9: =D9-E9*2 -> 2.8 | J9: 0.05 | K9: =G9 -> 2.8 | L9: =(C9*F9*2+D9*F9*2+I9*G9*2+H9*G9*2)*B9 -> 91.8 | M9: =C9*D9*F9-G9*H9*I9 -> 12.112 | N9: =(C9+K9)*(D9+K9)*(F9+J9)*B9 -> 144.57 | O9: =N9-C9*D9*F9*B9 -> 95.61 | P9: =N9-O9 -> 48.96 | Q9: =C9*D9*B9 -> 16.32 | R9: =J9*Q9 -> 0.816
A10: TAMPA CISTERNA | B10: 1 | C10: 5.1 | D10: 3.2 | E10: 0.2 | F10: 0.2 | G10: =F10-E10 -> 0 | H10: =C10-E10*2 -> 4.7 | I10: =D10-E10*2 -> 2.8 | K10: =G10 -> 0 | L10: =(2*E10*D10+2*E10*C10+H10*I10)*B10 -> 16.48 | M10: =C10*D10*F10-G10*H10*I10 -> 3.264
A11: DUTO DE AR - TRECHO 1 | B11: 1 | C11: 23.35 | D11: 2.35 | E11: 0.15 | F11: 2.2 | G11: =F11-E11 -> 2.05 | H11: =C11-E11*2 -> 23.05 | I11: =D11-E11*2 -> 2.05 | J11: 0.05 | K11: =G11 -> 2.05 | L11: =G11*(7.55)+F11+(8.13)+0.35*(2.35+2.05) -> 27.3475 | M11: 40 | N11: =(C11+K11)*(D11+K11)*(F11+J11)*B11 -> 251.46 | O11: =N11-C11*D11*G11*B11 -> 138.97138 | P11: =N11-O11 -> 112.48863 | Q11: =C11*D11*B11 -> 54.8725 | R11: =J11*Q11 -> 2.743625
A12: DUTO DE AR - TRECHO 2 | B12: 1 | C12: 2.9 | D12: 2.35 | E12: 0.15 | F12: 1.85 | G12: =F12-E12 -> 1.7 | H12: =C12-E12*2 -> 2.6 | I12: =D12-E12*2 -> 2.05 | J12: 0.05 | K12: =G12 -> 1.7 | L12: =F12*(46.247)+G12*(46.397) -> 164.43185 | N12: =(C12+K12)*(D12+K12)*(F12+J12)*B12 -> 35.397 | O12: =N12-C12*D12*G12*B12 -> 23.8115 | P12: =N12-O12 -> 11.5855 | Q12: =C12*D12*B12 -> 6.815 | R12: =J12*Q12 -> 0.34075
A13: DUTO DE AR - TRECHO 1.1 | B13: 1 | C13: 3.25 | D13: 1.3 | E13: 0.15 | F13: 2.2 | G13: =F13-E13 -> 2.05 | H13: =C13-E13*2 -> 2.95 | I13: =D13-E13*2 -> 1 | K13: =G13 -> 2.05 | L13: =F13*(7.8)+G13+(7.05) -> 26.26 | N13: =(C13+K13)*(D13+K13)*(F13+J13)*B13 -> 39.061 | O13: =N13-C13*D13*G13*B13 -> 30.39975 | P13: =N13-O13 -> 8.66125 | Q13: =I13*E13 -> 0.15 | R13: =J13*Q13 -> 0
A14: DUTO DE AR - TETO | L14: 57.63
A15: TOTAL | L15: =SUM(L9:L14) -> 383.94935 | M15: =SUM(M9:M14) -> 55.376 | N15: =SUM(N9:N14) -> 470.488 | O15: =SUM(O9:O14) -> 288.79263 | P15: =SUM(P9:P14) -> 181.69538 | Q15: =SUM(Q9:Q14) -> 78.1575 | R15: =SUM(R9:R14) -> 3.900375

Sheet Blocos
D1: Projeto | E1: =ORÇAMENTO!I4 -> SENSE106
D2: Empresa | E2: =ORÇAMENTO!I5 -> HOLZE EMPREENDIMENTOS
D3: Revisão | E3: R00 - Michelle Furlan -
A4: BLOCOS RETANGULARES
A5: ITEM | F5: QUANT | G5: DIMENSÕES UNITÁRIAS - m | J5: ADIÇÃO | K5: ADIÇÃO | L5: ESCAV | M5: APILOA | N5: REATER | O5: BOTA FORA | P5: LASTRO | Q5: FORMA | R5: FORMA (PROJETISTA) | S5: CONCRETO | T5: CONCRETO (PROJETISTA) | U5: TIPO | W5: RESUMO - CONCRETO
G6: LARGURA | H6: COMPR | I6: ALTURA | J6: LARGURA | K6: ALTURA | P6: Concreto (m3)
G7: A | H7: C | I7: B | J7: m | K7: m | L7: m3 | M7: m2 | N7: m3 | O7: m3 | P7: 0.05 | Q7: m2 | R7: m2 | S7: m3 | T7: m3 | W7: m3 | X7: TIPO
A8: Sense - Blocos de Fundação.dwg | W8: =SUMIF($U$8:$U$33,$X8,$S$8:$S$33)+SUMIF($U$51:$U$57,$X8,$S$51:$S$57) -> 0 | X8: 25 MPa
A9: BF1 | F9: 1 | G9: 0.9 | H9: 0.9 | I9: 0.8 | J9: =IF(I9<=1,0.6,I9) -> 0.6 | L9: =(G9+J9)*(I9+K9+$P$7)*(H9+J9)*F9 -> 1.9125 | M9: =(G9)*(H9)*F9 -> 0.81 | N9: =+L9-S9 -> 1.2645 | O9: =(L9-N9)*1.3 -> 0.8424 | P9: =M9*$P$7 -> 0.0405 | Q9: =(2*G9+H9*2)*I9*F9 -> 2.88 | R9: 2.88 | S9: =G9*I9*H9*F9 -> 0.648 | T9: 0.65 | U9: 40 MPa | W9: =SUMIF($U$8:$U$33,$X9,$S$8:$S$33)+SUMIF($U$51:$U$57,$X9,$S$51:$S$57) -> 0 | X9: 30 MPa
A10: BF2 | F10: 1 | G10: 0.9 | H10: 0.9 | I10: 0.8 | J10: =IF(I10<=1,0.6,I10) -> 0.6 | L10: =(G10+J10)*(I10+K10+$P$7)*(H10+J10)*F10 -> 1.9125 | M10: =(G10)*(H10)*F10 -> 0.81 | N10: =+L10-S10 -> 1.2645 | O10: =(L10-N10)*1.3 -> 0.8424 | P10: =M10*$P$7 -> 0.0405 | Q10: =(2*G10+H10*2)*I10*F10 -> 2.88 | R10: 2.88 | S10: =G10*I10*H10*F10 -> 0.648 | T10: 0.65 | U10: 40 MPa | W10: =SUMIF($U$8:$U$33,$X10,$S$8:$S$33)+SUMIF($U$51:$U$57,$X10,$S$51:$S$57) -> 0 | X10: 35 MPa
A11: BF3 | F11: 1 | G11: 0.9 | H11: 0.9 | I11: 0.8 | J11: =IF(I11<=1,0.6,I11) -> 0.6 | L11: =(G11+J11)*(I11+K11+$P$7)*(H11+J11)*F11 -> 1.9125 | M11: =(G11)*(H11)*F11 -> 0.81 | N11: =+L11-S11 -> 1.2645 | O11: =(L11-N11)*1.3 -> 0.8424 | P11: =M11*$P$7 -> 0.0405 | Q11: =(2*G11+H11*2)*I11*F11 -> 2.88 | R11: 2.88 | S11: =G11*I11*H11*F11 -> 0.648 | T11: 0.65 | U11: 40 MPa | W11: =SUMIF($U$8:$U$33,$X11,$S$8:$S$33)+SUMIF($U$51:$U$57,$X11,$S$51:$S$57) -> 230.13784 | X11: 40 MPa
A12: BF4 | F12: 1 | G12: 0.9 | H12: 0.9 | I12: 0.8 | J12: =IF(I12<=1,0.6,I12) -> 0.6 | L12: =(G12+J12)*(I12+K12+$P$7)*(H12+J12)*F12 -> 1.9125 | M12: =(G12)*(H12)*F12 -> 0.81 | N12: =+L12-S12 -> 1.2645 | O12: =(L12-N12)*1.3 -> 0.8424 | P12: =M12*$P$7 -> 0.0405 | Q12: =(2*G12+H12*2)*I12*F12 -> 2.88 | R12: 2.88 | S12: =G12*I12*H12*F12 -> 0.648 | T12: 0.65 | U12: 40 MPa | W12: =SUMIF($U$8:$U$33,$X12,$S$8:$S$33)+SUMIF($U$51:$U$57,$X12,$S$51:$S$57) -> 0
A13: BF5 | F13: 1 | G13: 0.9 | H13: 0.9 | I13: 0.8 | J13: =IF(I13<=1,0.6,I13) -> 0.6 | L13: =(G13+J13)*(I13+K13+$P$7)*(H13+J13)*F13 -> 1.9125 | M13: =(G13)*(H13)*F13 -> 0.81 | N13: =+L13-S13 -> 1.2645 | O13: =(L13-N13)*1.3 -> 0.8424 | P13: =M13*$P$7 -> 0.0405 | Q13: =(2*G13+H13*2)*I13*F13 -> 2.88 | R13: 2.88 | S13: =G13*I13*H13*F13 -> 0.648 | T13: 0.65 | U13: 40 MPa | W13: =SUMIF($U$8:$U$33,$X13,$S$8:$S$33)+SUMIF($U$51:$U$57,$X13,$S$51:$S$57) -> 0
A14: BF6 | F14: 1 | G14: 0.9 | H14: 0.9 | I14: 0.8 | J14: =IF(I14<=1,0.6,I14) -> 0.6 | L14: =(G14+J14)*(I14+K14+$P$7)*(H14+J14)*F14 -> 1.9125 | M14: =(G14)*(H14)*F14 -> 0.81 | N14: =+L14-S14 -> 1.2645 | O14: =(L14-N14)*1.3 -> 0.8424 | P14: =M14*$P$7 -> 0.0405 | Q14: =(2*G14+H14*2)*I14*F14 -> 2.88 | R14: 2.88 | S14: =G14*I14*H14*F14 -> 0.648 | T14: 0.65 | U14: 40 MPa | W14: =SUMIF($U$8:$U$33,$X14,$S$8:$S$33)+SUMIF($U$51:$U$57,$X14,$S$51:$S$57) -> 0
A15: BF7 | F15: 1 | G15: 0.9 | H15: 0.9 | I15: 0.8 | J15: =IF(I15<=1,0.6,I15) -> 0.6 | L15: =(G15+J15)*(I15+K15+$P$7)*(H15+J15)*F15 -> 1.9125 | M15: =(G15)*(H15)*F15 -> 0.81 | N15: =+L15-S15 -> 1.2645 | O15: =(L15-N15)*1.3 -> 0.8424 | P15: =M15*$P$7 -> 0.0405 | Q15: =(2*G15+H15*2)*I15*F15 -> 2.88 | R15: 2.88 | S15: =G15*I15*H15*F15 -> 0.648 | T15: 0.65 | U15: 40 MPa | W15: =SUM(W8:W14) -> 230.13784 | X15: =IF(S34=W15,"OK","Conferir") -> Conferir
A16: BF8 | F16: 1 | G16: 0.9 | H16: 0.9 | I16: 0.8 | J16: =IF(I16<=1,0.6,I16) -> 0.6 | L16: =(G16+J16)*(I16+K16+$P$7)*(H16+J16)*F16 -> 1.9125 | M16: =(G16)*(H16)*F16 -> 0.81 | N16: =+L16-S16 -> 1.2645 | O16: =(L16-N16)*1.3 -> 0.8424 | P16: =M16*$P$7 -> 0.0405 | Q16: =(2*G16+H16*2)*I16*F16 -> 2.88 | R16: 2.88 | S16: =G16*I16*H16*F16 -> 0.648 | T16: 0.65 | U16: 40 MPa
A17: BF9 | F17: 1 | G17: 0.9 | H17: 0.9 | I17: 0.8 | J17: =IF(I17<=1,0.6,I17) -> 0.6 | L17: =(G17+J17)*(I17+K17+$P$7)*(H17+J17)*F17 -> 1.9125 | M17: =(G17)*(H17)*F17 -> 0.81 | N17: =+L17-S17 -> 1.2645 | O17: =(L17-N17)*1.3 -> 0.8424 | P17: =M17*$P$7 -> 0.0405 | Q17: =(2*G17+H17*2)*I17*F17 -> 2.88 | R17: 2.88 | S17: =G17*I17*H17*F17 -> 0.648 | T17: 0.65 | U17: 40 MPa
A18: BF10 | F18: 1 | G18: 0.9 | H18: 0.9 | I18: 0.8 | J18: =IF(I18<=1,0.6,I18) -> 0.6 | L18: =(G18+J18)*(I18+K18+$P$7)*(H18+J18)*F18 -> 1.9125 | M18: =(G18)*(H18)*F18 -> 0.81 | N18: =+L18-S18 -> 1.2645 | O18: =(L18-N18)*1.3 -> 0.8424 | P18: =M18*$P$7 -> 0.0405 | Q18: =(2*G18+H18*2)*I18*F18 -> 2.88 | R18: 2.88 | S18: =G18*I18*H18*F18 -> 0.648 | T18: 0.65 | U18: 40 MPa
A19: BF11 | F19: 1 | G19: 1 | H19: 1 | I19: 1 | J19: =IF(I19<=1,0.6,I19) -> 0.6 | L19: =(G19+J19)*(I19+K19+$P$7)*(H19+J19)*F19 -> 2.688 | M19: =(G19)*(H19)*F19 -> 1 | N19: =+L19-S19 -> 1.688 | O19: =(L19-N19)*1.3 -> 1.3 | P19: =M19*$P$7 -> 0.05 | Q19: =(2*G19+H19*2)*I19*F19 -> 4 | R19: 4 | S19: =G19*I19*H19*F19 -> 1 | T19: 1 | U19: 40 MPa
A20: BF12 | F20: 1 | G20: 0.9 | H20: 0.9 | I20: 0.8 | J20: =IF(I20<=1,0.6,I20) -> 0.6 | L20: =(G20+J20)*(I20+K20+$P$7)*(H20+J20)*F20 -> 1.9125 | M20: =(G20)*(H20)*F20 -> 0.81 | N20: =+L20-S20 -> 1.2645 | O20: =(L20-N20)*1.3 -> 0.8424 | P20: =M20*$P$7 -> 0.0405 | Q20: =(2*G20+H20*2)*I20*F20 -> 2.88 | R20: 2.88 | S20: =G20*I20*H20*F20 -> 0.648 | T20: 0.65 | U20: 40 MPa
A21: BF13 | F21: 1 | G21: 0.9 | H21: 0.9 | I21: 0.8 | J21: =IF(I21<=1,0.6,I21) -> 0.6 | L21: =(G21+J21)*(I21+K21+$P$7)*(H21+J21)*F21 -> 1.9125 | M21: =(G21)*(H21)*F21 -> 0.81 | N21: =+L21-S21 -> 1.2645 | O21: =(L21-N21)*1.3 -> 0.8424 | P21: =M21*$P$7 -> 0.0405 | Q21: =(2*G21+H21*2)*I21*F21 -> 2.88 | R21: 2.88 | S21: =G21*I21*H21*F21 -> 0.648 | T21: 0.65 | U21: 40 MPa
A22: BF14 | F22: 1 | G22: 0.9 | H22: 0.9 | I22: 0.8 | J22: =IF(I22<=1,0.6,I22) -> 0.6 | L22: =(G22+J22)*(I22+K22+$P$7)*(H22+J22)*F22 -> 1.9125 | M22: =(G22)*(H22)*F22 -> 0.81 | N22: =+L22-S22 -> 1.2645 | O22: =(L22-N22)*1.3 -> 0.8424 | P22: =M22*$P$7 -> 0.0405 | Q22: =(2*G22+H22*2)*I22*F22 -> 2.88 | R22: 2.88 | S22: =G22*I22*H22*F22 -> 0.648 | T22: 0.65 | U22: 40 MPa
A23: BF15 | F23: 1 | G23: 0.9 | H23: 0.9 | I23: 0.8 | J23: =IF(I23<=1,0.6,I23) -> 0.6 | L23: =(G23+J23)*(I23+K23+$P$7)*(H23+J23)*F23 -> 1.9125 | M23: =(G23)*(H23)*F23 -> 0.81 | N23: =+L23-S23 -> 1.2645 | O23: =(L23-N23)*1.3 -> 0.8424 | P23: =M23*$P$7 -> 0.0405 | Q23: =(2*G23+H23*2)*I23*F23 -> 2.88 | R23: 2.88 | S23: =G23*I23*H23*F23 -> 0.648 | T23: 0.65 | U23: 40 MPa
A24: BF16 | F24: 1 | G24: 0.9 | H24: 0.9 | I24: 0.8 | J24: =IF(I24<=1,0.6,I24) -> 0.6 | L24: =(G24+J24)*(I24+K24+$P$7)*(H24+J24)*F24 -> 1.9125 | M24: =(G24)*(H24)*F24 -> 0.81 | N24: =+L24-S24 -> 1.2645 | O24: =(L24-N24)*1.3 -> 0.8424 | P24: =M24*$P$7 -> 0.0405 | Q24: =(2*G24+H24*2)*I24*F24 -> 2.88 | R24: 2.88 | S24: =G24*I24*H24*F24 -> 0.648 | T24: 0.65 | U24: 40 MPa
A25: B8 | F25: 1 | G25: 2.65 | H25: 1 | I25: 1 | J25: =IF(I25<=1,0.6,I25) -> 0.6 | L25: =(G25+J25)*(I25+K25+$P$7)*(H25+J25)*F25 -> 5.46 | M25: =(G25)*(H25)*F25 -> 2.65 | N25: =+L25-S25 -> 2.81 | O25: =(L25-N25)*1.3 -> 3.445 | P25: =M25*$P$7 -> 0.1325 | Q25: =(2*G25+H25*2)*I25*F25 -> 7.3 | R25: 20.82 | S25: =G25*I25*H25*F25 -> 2.65 | T25: 12.97 | U25: 40 MPa
A26: B9 | F26: 1 | G26: 3.66 | H26: 2.095 | I26: 1.35 | J26: =IF(I26<=1,0.6,I26) -> 1.35 | L26: =(G26+J26)*(I26+K26+$P$7)*(H26+J26)*F26 -> 24.16323 | M26: =(G26)*(H26)*F26 -> 7.6677 | N26: =+L26-S26 -> 13.811835 | O26: =(L26-N26)*1.3 -> 13.456814 | P26: =M26*$P$7 -> 0.383385 | Q26: =(2*G26+H26*2)*I26*F26 -> 15.5385 | S26: =G26*I26*H26*F26 -> 10.351395 | U26: 40 MPa
A27: B10 | F27: 1 | G27: 4.118 | H27: 4.6 | I27: 1.8 | J27: =IF(I27<=1,0.6,I27) -> 1.8 | L27: =(G27+J27)*(I27+K27+$P$7)*(H27+J27)*F27 -> 70.06912 | M27: =(G27)*(H27)*F27 -> 18.9428 | N27: =+L27-S27 -> 35.97208 | O27: =(L27-N27)*1.3 -> 44.326152 | P27: =M27*$P$7 -> 0.94714 | Q27: =(2*G27+H27*2)*I27*F27 -> 31.3848 | R27: 57.06 | S27: =G27*I27*H27*F27 -> 34.09704 | T27: 67.8 | U27: 40 MPa
A28: B11 | F28: 1 | G28: 4.118 | H28: 4.6 | I28: 1.8 | J28: =IF(I28<=1,0.6,I28) -> 1.8 | L28: =(G28+J28)*(I28+K28+$P$7)*(H28+J28)*F28 -> 70.06912 | M28: =(G28)*(H28)*F28 -> 18.9428 | N28: =+L28-S28 -> 35.97208 | O28: =(L28-N28)*1.3 -> 44.326152 | P28: =M28*$P$7 -> 0.94714 | Q28: =(2*G28+H28*2)*I28*F28 -> 31.3848 | S28: =G28*I28*H28*F28 -> 34.09704 | U28: 40 MPa
A29: B17 | F29: 1 | G29: 2.65 | H29: 2.65 | I29: 1.2 | J29: =IF(I29<=1,0.6,I29) -> 1.2 | L29: =(G29+J29)*(I29+K29+$P$7)*(H29+J29)*F29 -> 18.528125 | M29: =(G29)*(H29)*F29 -> 7.0225 | N29: =+L29-S29 -> 10.101125 | O29: =(L29-N29)*1.3 -> 10.9551 | P29: =M29*$P$7 -> 0.351125 | Q29: =(2*G29+H29*2)*I29*F29 -> 12.72 | R29: 12.72 | S29: =G29*I29*H29*F29 -> 8.427 | T29: 8.26 | U29: 40 MPa
A30: B18 | F30: 1 | G30: 4.3 | H30: 4.3 | I30: 1.8 | J30: =IF(I30<=1,0.6,I30) -> 1.8 | L30: =(G30+J30)*(I30+K30+$P$7)*(H30+J30)*F30 -> 68.8385 | M30: =(G30)*(H30)*F30 -> 18.49 | N30: =+L30-S30 -> 35.5565 | O30: =(L30-N30)*1.3 -> 43.2666 | P30: =M30*$P$7 -> 0.9245 | Q30: =(2*G30+H30*2)*I30*F30 -> 30.96 | R30: 43 | S30: =G30*I30*H30*F30 -> 33.282 | T30: 33.4 | U30: 40 MPa
A31: B19 | F31: 1 | G31: 2.649 | H31: 3.859 | I31: 1.5 | J31: =IF(I31<=1,0.6,I31) -> 1.5 | L31: =(G31+J31)*(I31+K31+$P$7)*(H31+J31)*F31 -> 34.463461 | M31: =(G31)*(H31)*F31 -> 10.222491 | N31: =+L31-S31 -> 19.129725 | O31: =(L31-N31)*1.3 -> 19.933857 | P31: =M31*$P$7 -> 0.51112455 | Q31: =(2*G31+H31*2)*I31*F31 -> 19.524 | R31: 20 | S31: =G31*I31*H31*F31 -> 15.333737 | T31: 15.34 | U31: 40 MPa
A32: B(P25+P30) | F32: 1 | G32: 5.95 | H32: 2.65 | I32: 1.5 | J32: =IF(I32<=1,0.6,I32) -> 1.5 | L32: =(G32+J32)*(I32+K32+$P$7)*(H32+J32)*F32 -> 47.922125 | M32: =(G32)*(H32)*F32 -> 15.7675 | N32: =+L32-S32 -> 24.270875 | O32: =(L32-N32)*1.3 -> 30.746625 | P32: =M32*$P$7 -> 0.788375 | Q32: =(2*G32+H32*2)*I32*F32 -> 25.8 | R32: =31.8/2 -> 15.9 | S32: =G32*I32*H32*F32 -> 23.65125 | T32: =47.2/2 -> 23.6 | U32: 40 MPa
A33: B(P26+P31) | F33: 1 | G33: 5.95 | H33: 2.65 | I33: 1.5 | J33: =IF(I33<=1,0.6,I33) -> 1.5 | L33: =(G33+J33)*(I33+K33+$P$7)*(H33+J33)*F33 -> 47.922125 | M33: =(G33)*(H33)*F33 -> 15.7675 | N33: =+L33-S33 -> 24.270875 | O33: =(L33-N33)*1.3 -> 30.746625 | P33: =M33*$P$7 -> 0.788375 | Q33: =(2*G33+H33*2)*I33*F33 -> 25.8 | R33: =31.8/2 -> 15.9 | S33: =G33*I33*H33*F33 -> 23.65125 | T33: =47.2/2 -> 23.6 | U33: 40 MPa
A34: TOTAL | L34: =SUM(L7:L33) -> 418.81131 | M34: =SUM(M7:M33) -> 128.62329 | N34: =SUM(N7:N33) -> 222.55059 | O34: =SUM(O7:O33) -> 255.13892 | P34: =SUM(P7:P33) -> 6.4811646 | Q34: =SUM(Q7:Q33) -> 247.6121 | R34: =SUM(R9:R33) -> 232.6 | S34: =SUM(S8:S33) -> 196.26071 | T34: =SUM(T9:T33) -> 195.72
A35: QUANTITATIVOS PROJETISTA | Q35: 0 | S35: 0
R36: =1-Q34/R34 -> -0.064540413 | T36: =1-S34/T34 -> -0.0027626788
H37: DETALHE TÍPICO | R37: =IF(R36<10%,"Usar valor de projeto","Confirmar com cliente") -> Usar valor de projeto | T37: =IF(T36<10%,"Usar valor de projeto","Confirmar com cliente") -> Usar valor de projeto
A46: BLOCOS TRIANGULARES
A47: ITEM | B47: QUANT | C47: LADO 1 DO BLOCO | D47: LADO 2 DO BLOCO | E47: LADO 3 DO BLOCO | F47: LADO 4 DO BLOCO | G47: LADO 5 DO BLOCO | H47: ALTURA DO BLOCO | I47: ESPESSURA DO LASTRO DE CONCRETO | J47: ADICIONAL LARGURA | K47: ADICIONAL ALTURA | L47: ESCAV | M47: APILOA | N47: REATERRO | O47: BOTA-FORA | P47: LASTRO | Q47: FORMA | R47: FORMA (PROJETISTA) | S47: CONCRETO | T47: CONCRETO (PROJETISTA) | U47: TIPO
B48: R | C48: h1 + h2 | D48: h2 | E48: B | F48: b2 | G48: b1 | H48: Hb | I48: e.L. | J48: K | K48: K | L48: VE | M48: AP | N48: VA | O48: VB | P48: VM | Q48: F | R48: F | S48: C | T48: C
B49: UD | C49: m | D49: m | E49: m | F49: m | G49: m | H49: m | I49: m | J49: m | K49: m | L49: m3 | M49: m2 | N49: m3 | O49: m3 | P49: m3 | Q49: m2 | R49: m2 | S49: m3 | T49: m3
A50: Sense - Blocos de Fundação.dwg
A51: B15 | B51: 1 | C51: 2.429 | D51: 0.5 | E51: 2.805 | F51: 2.227 | G51: 0.577 | H51: 1.2 | I51: 0.05 | J51: =IF(H51<=1,0.6,H51) -> 1.2 | L51: =(C51+J51)*(E51+J51)*(H51+I51+K51)*B51 -> 18.167681 | M51: =(((E51+F51)*D51/2)+((E51+G51)*(C51-D51))/2)*B51 -> 4.519939 | N51: =L51-S51 -> 12.743754 | O51: =(L51-N51)*1.3 -> 7.0511048 | P51: =M51*I51 -> 0.22599695 | Q51: =(F51*H51+G51*H51+(((C51-D51)^2+((E51-G51)/2)^2)^(1/2))*H51*2+(((D51^2)+((E51-F51)/2)^2)^(1/2))*H51*2)*B51 -> 10.096982 | R51: =20.19/2 -> 10.095 | S51: =(((E51+F51)*D51/2)+((E51+G51)*(C51-D51))/2)*H51*B51 -> 5.4239268 | T51: =10.59/2 -> 5.295 | U51: 40 MPa
A52: B16 | B52: 1 | C52: 2.429 | D52: 0.5 | E52: 2.81 | F52: 2.227 | G52: 0.577 | H52: 1.2 | I52: 0.05 | J52: =IF(H52<=1,0.6,H52) -> 1.2 | L52: =(C52+J52)*(E52+J52)*(H52+I52+K52)*B52 -> 18.190362 | M52: =(((E52+F52)*D52/2)+((E52+G52)*(C52-D52))/2)*B52 -> 4.5260115 | N52: =L52-S52 -> 12.759149 | O52: =(L52-N52)*1.3 -> 7.0605779 | P52: =M52*I52 -> 0.22630058 | Q52: =(F52*H52+G52*H52+(((C52-D52)^2+((E52-G52)/2)^2)^(1/2))*H52*2+(((D52^2)+((E52-F52)/2)^2)^(1/2))*H52*2)*B52 -> 10.102997 | R52: =20.19/2 -> 10.095 | S52: =(((E52+F52)*D52/2)+((E52+G52)*(C52-D52))/2)*H52*B52 -> 5.4312138 | T52: =10.59/2 -> 5.295 | U52: 40 MPa
A53: B22 | B53: 1 | C53: 2.095 | D53: 0.45 | E53: 2.419 | F53: 1.9 | G53: 0.52 | H53: 1 | I53: 0.05 | J53: =IF(H53<=1,0.6,H53) -> 0.6 | L53: =(C53+J53)*(E53+J53)*(H53+I53+K53)*B53 -> 8.5430153 | M53: =(((E53+F53)*D53/2)+((E53+G53)*(C53-D53))/2)*B53 -> 3.3891025 | N53: =L53-S53 -> 5.1539128 | O53: =(L53-N53)*1.3 -> 4.4058332 | P53: =M53*I53 -> 0.16945513 | Q53: =(F53*H53+G53*H53+(((C53-D53)^2+((E53-G53)/2)^2)^(1/2))*H53*2+(((D53^2)+((E53-F53)/2)^2)^(1/2))*H53*2)*B53 -> 7.2576466 | R53: 7.26 | S53: =(((E53+F53)*D53/2)+((E53+G53)*(C53-D53))/2)*H53*B53 -> 3.3891025 | T53: 3.3 | U53: 40 MPa
A54: B24 | B54: 1 | C54: 2.299 | D54: 0.5 | E54: 2.655 | F54: 2.077 | G54: 0.577 | H54: 1.2 | I54: 0.05 | J54: =IF(H54<=1,0.6,H54) -> 1.2 | L54: =(C54+J54)*(E54+J54)*(H54+I54+K54)*B54 -> 16.860806 | M54: =(((E54+F54)*D54/2)+((E54+G54)*(C54-D54))/2)*B54 -> 4.090184 | N54: =L54-S54 -> 11.952585 | O54: =(L54-N54)*1.3 -> 6.380687 | P54: =M54*I54 -> 0.2045092 | Q54: =(F54*H54+G54*H54+(((C54-D54)^2+((E54-G54)/2)^2)^(1/2))*H54*2+(((D54^2)+((E54-F54)/2)^2)^(1/2))*H54*2)*B54 -> 9.556782 | R54: =38.23/4 -> 9.5575 | S54: =(((E54+F54)*D54/2)+((E54+G54)*(C54-D54))/2)*H54*B54 -> 4.9082208 | T54: =18.64/4 -> 4.66 | U54: 40 MPa
A55: B27 | B55: 1 | C55: 2.299 | D55: 0.5 | E55: 2.655 | F55: 2.077 | G55: 0.577 | H55: 1.2 | I55: 0.05 | J55: =IF(H55<=1,0.6,H55) -> 1.2 | L55: =(C55+J55)*(E55+J55)*(H55+I55+K55)*B55 -> 16.860806 | M55: =(((E55+F55)*D55/2)+((E55+G55)*(C55-D55))/2)*B55 -> 4.090184 | N55: =L55-S55 -> 11.952585 | O55: =(L55-N55)*1.3 -> 6.380687 | P55: =M55*I55 -> 0.2045092 | Q55: =(F55*H55+G55*H55+(((C55-D55)^2+((E55-G55)/2)^2)^(1/2))*H55*2+(((D55^2)+((E55-F55)/2)^2)^(1/2))*H55*2)*B55 -> 9.556782 | R55: =38.23/4 -> 9.5575 | S55: =(((E55+F55)*D55/2)+((E55+G55)*(C55-D55))/2)*H55*B55 -> 4.9082208 | T55: =18.64/4 -> 4.66 | U55: 40 MPa
A56: B29 | B56: 1 | C56: 2.299 | D56: 0.5 | E56: 2.655 | F56: 2.077 | G56: 0.577 | H56: 1.2 | I56: 0.05 | J56: =IF(H56<=1,0.6,H56) -> 1.2 | L56: =(C56+J56)*(E56+J56)*(H56+I56+K56)*B56 -> 16.860806 | M56: =(((E56+F56)*D56/2)+((E56+G56)*(C56-D56))/2)*B56 -> 4.090184 | N56: =L56-S56 -> 11.952585 | O56: =(L56-N56)*1.3 -> 6.380687 | P56: =M56*I56 -> 0.2045092 | Q56: =(F56*H56+G56*H56+(((C56-D56)^2+((E56-G56)/2)^2)^(1/2))*H56*2+(((D56^2)+((E56-F56)/2)^2)^(1/2))*H56*2)*B56 -> 9.556782 | R56: =38.23/4 -> 9.5575 | S56: =(((E56+F56)*D56/2)+((E56+G56)*(C56-D56))/2)*H56*B56 -> 4.9082208 | T56: =18.64/4 -> 4.66 | U56: 40 MPa
A57: B32 | B57: 1 | C57: 2.299 | D57: 0.5 | E57: 2.655 | F57: 2.077 | G57: 0.577 | H57: 1.2 | I57: 0.05 | J57: =IF(H57<=1,0.6,H57) -> 1.2 | L57: =(C57+J57)*(E57+J57)*(H57+I57+K57)*B57 -> 16.860806 | M57: =(((E57+F57)*D57/2)+((E57+G57)*(C57-D57))/2)*B57 -> 4.090184 | N57: =L57-S57 -> 11.952585 | O57: =(L57-N57)*1.3 -> 6.380687 | P57: =M57*I57 -> 0.2045092 | Q57: =(F57*H57+G57*H57+(((C57-D57)^2+((E57-G57)/2)^2)^(1/2))*H57*2+(((D57^2)+((E57-F57)/2)^2)^(1/2))*H57*2)*B57 -> 9.556782 | R57: =38.23/4 -> 9.5575 | S57: =(((E57+F57)*D57/2)+((E57+G57)*(C57-D57))/2)*H57*B57 -> 4.9082208 | T57: =18.64/4 -> 4.66 | U57: 40 MPa
A58: TOTAL | B58: =SUM(B51:B57) -> 7 | L58: =SUM(L51:L57) -> 112.34428 | M58: =SUM(M51:M57) -> 28.795789 | N58: =SUM(N51:N57) -> 78.467158 | O58: =SUM(O51:O57) -> 44.040264 | P58: =SUM(P51:P57) -> 1.4397894 | Q58: =SUM(Q51:Q57) -> 65.684754 | R58: =SUM(R51:R57) -> 65.68 | S58: =SUM(S51:S57) -> 33.877126 | T58: =SUM(T51:T57) -> 32.53
R59: =1-Q58/R58 -> -7.237639e-05 | T59: =1-S58/T58 -> -0.041411814
R60: =IF(R59<10%,"Usar valor de projeto","Confirmar com cliente") -> Usar valor de projeto | T60: =IF(T59<10%,"Usar valor de projeto","Confirmar com cliente") -> Usar valor de projeto
H62: DETALHE TÍPICO
A84: TOTAL GERAL | F84: =B58+F34 -> 7 | L84: =L58+L34 -> 531.15559 | M84: =M58+M34 -> 157.41908 | N84: =N58+N34 -> 301.01775 | O84: =O58+O34 -> 299.17919 | P84: =P58+P34 -> 7.920954 | Q84: =Q58+Q34 -> 313.29685 | R84: =R58+R34 -> 298.28 | S84: =S58+S34 -> 230.13784 | T84: =T58+T34 -> 228.25

Sheet Arm. Cortina
B1: Projeto | C1: =ORÇAMENTO!I4 -> SENSE106
B2: Empresa | C2: =ORÇAMENTO!I5 -> HOLZE EMPREENDIMENTOS
B3: Revisão | C3: R00 - Michelle Furlan
A4: ARMAÇÃO CORTINA
A5: ITEM | C5: QUANT | D5: QUANTIDADE POR ITEM CA-50 - m | K5: CA-60 - m
D6: 6.3 | E6: 8 | F6: 10 | G6: 12.5 | H6: 16 | I6: 20 | J6: 25 | K6: 5 | L6: 0 | M6: 0 | N6: 0 | O6: 0
A7: PROJETO:
C8: 1
A9: PROJETO:
C10: 1
A11: PROJETO:
C12: 1
A13: PROJETO:
C14: 1
A15: PROJETO:
C16: 1
B17: TOTAL - M | C17: =SUM(D17:O17) -> 0 | D17: =SUMPRODUCT(D7:D16,$C7:$C16) -> 0 | E17: =SUMPRODUCT(E7:E16,$C7:$C16) -> 0 | F17: =SUMPRODUCT(F7:F16,$C7:$C16) -> 0 | G17: =SUMPRODUCT(G7:G16,$C7:$C16) -> 0 | H17: =SUMPRODUCT(H7:H16,$C7:$C16) -> 0 | I17: =SUMPRODUCT(I7:I16,$C7:$C16) -> 0 | J17: =SUMPRODUCT(J7:J16,$C7:$C16) -> 0 | K17: =SUMPRODUCT(K7:K16,$C7:$C16) -> 0 | ... O17: =SUMPRODUCT(O7:O16,$C7:$C16) -> 0
B18: PESO kg/m | D18: 1 | E18: 1 | F18: 1 | G18: 1 | H18: 1 | I18: 1 | J18: 1 | K18: 1 | L18: 1 | M18: 1 | N18: 1 | O18: 1
B19: TOTAL - kg | C19: =SUM(D19:O19) -> 0 | D19: =D18*D17 -> 0 | E19: =E18*E17 -> 0 | F19: =F18*F17 -> 0 | G19: =G18*G17 -> 0 | H19: =H18*H17 -> 0 | I19: =I18*I17 -> 0 | J19: =J18*J17 -> 0 | K19: =K18*K17 -> 0 | ... O19: =O18*O17 -> 0

Sheet Tabela de Aço
A1: TABELA DE AÇO
A2: CA-50 | D2: CA-60
A3: Ø - mm | B3: kg/m | C3: pol | D3: Ø - mm | E3: kg/m
A4: 6.3 | B4: 0.245 | C4: 1/4" | D4: 3.4 | E4: 0.079
A5: 8 | B5: 0.395 | C5: 5/16" | D5: 4.2 | E5: 0.109
A6: 10 | B6: 0.617 | C6: 3/8" | D6: 5 | E6: 0.154
A7: 12.5 | B7: 0.963 | C7: 1/2" | D7: 6 | E7: 0.222
A8: 16 | B8: 1.578 | C8: 5/8" | D8: 7 | E8: 0.302
A9: 20 | B9: 2.466 | C9: 3/4" | D9: 8 | E9: 0.395
A10: 25 | B10: 3.853 | C10: 1" | D10: 9.5 | E10: 0.558
A11: 32 | B11: 6.313 | C11: 1 1/4" | D11: 0
A12: 40 | B12: 9.865 | C12: 1 5/8" | D12: 0

Sheet Vigas Fundação
B1: Projeto | C1: =ORÇAMENTO!I4 -> SENSE106
B2: Empresa | C2: =ORÇAMENTO!I5 -> HOLZE EMPREENDIMENTOS
B3: Revisão | C3: R00 - Michelle Furlan
A4: VIGAS FUNDAÇÃO
A5: ITEM | B5: DIMENSÕES UNITÁRIAS - m | E5: Adição | H5: ESCAV | I5: APILOA | J5: REATER | K5: BOTA FORA | L5: LASTRO | M5: FORMA | O5: FORMA (PROJETISTA) | P5: CONCRETO | Q5: CONCRETO (PROJETISTA) | S5: TAXA AÇO (KG/M3) | T5: IMPERM | V5: RESUMO - CONCRETO
B6: LARG | C6: COMP | D6: ALT | E6: LARG | F6: ALT | G6: QUANT | L6: m3 | V6: m3 | W6: TIPO
B7: A | C7: C | D7: B | E7: m | F7: m | H7: m3 | I7: m2 | J7: m3 | K7: m3 | L7: 0.05 | M7: lados | N7: m2 | P7: m3 | R7: TIPO | T7: m2
A8: PROJETO: PRÉ-FORMA-R03 | V8: =SUMIF($R$8:$R$68,$W8,$P$8:$P$68) -> 0 | W8: 20 MPa
A9: V1 | B9: 0.2 | C9: 5.14 | D9: 0.6 | E9: =IF(D9<=1,0.6,1.2) -> 0.6 | G9: 1 | H9: =((B9+E9)*(D9+F9)*C9)*G9 -> 2.4672 | I9: =(B9)*(C9)*G9 -> 1.028 | J9: =H9-P9 -> 1.8504 | K9: =(H9-J9)*1.3 -> 0.80184 | L9: =I9*$L$7 -> 0.0514 | M9: 2 | N9: =((C9*D9*M9))*G9 -> 6.168 | O9: 39.05 | P9: =B9*D9*C9*G9 -> 0.6168 | Q9: 3.59 | R9: 40 MPa | S9: =P9*$S$7 -> 0 | T9: =C9*B9+2*C9*D9 -> 7.196 | V9: =SUMIF($R$8:$R$68,$W9,$P$8:$P$68) -> 0 | W9: 25 MPa
A10: V2 | B10: 0.2 | C10: 9.52 | D10: 0.6 | E10: =IF(D10<=1,0.6,1.2) -> 0.6 | G10: 1 | H10: =((B10+E10)*(D10+F10)*C10)*G10 -> 4.5696 | I10: =(B10)*(C10)*G10 -> 1.904 | J10: =H10-P10 -> 3.4272 | K10: =(H10-J10)*1.3 -> 1.48512 | L10: =I10*$L$7 -> 0.0952 | M10: 2 | N10: =((C10*D10*M10))*G10 -> 11.424 | P10: =B10*D10*C10*G10 -> 1.1424 | R10: 40 MPa | S10: =P10*$S$7 -> 0 | T10: =C10*B10+2*C10*D10 -> 13.328 | V10: =SUMIF($R$8:$R$68,$W10,$P$8:$P$68) -> 0 | W10: 30 MPa
A11: V3 | B11: 0.2 | C11: 12 | D11: 0.6 | E11: =IF(D11<=1,0.6,1.2) -> 0.6 | G11: 1 | H11: =((B11+E11)*(D11+F11)*C11)*G11 -> 5.76 | I11: =(B11)*(C11)*G11 -> 2.4 | J11: =H11-P11 -> 4.32 | K11: =(H11-J11)*1.3 -> 1.872 | L11: =I11*$L$7 -> 0.12 | M11: 2 | N11: =((C11*D11*M11))*G11 -> 14.4 | P11: =B11*D11*C11*G11 -> 1.44 | R11: 40 MPa | S11: =P11*$S$7 -> 0 | T11: =C11*B11+2*C11*D11 -> 16.8 | V11: =SUMIF($R$8:$R$68,$W11,$P$8:$P$68) -> 0 | W11: 35 MPa
A12: V4 | B12: 0.15 | C12: 3.5 | D12: 0.6 | E12: =IF(D12<=1,0.6,1.2) -> 0.6 | G12: 1 | H12: =((B12+E12)*(D12+F12)*C12)*G12 -> 1.575 | I12: =(B12)*(C12)*G12 -> 0.525 | J12: =H12-P12 -> 1.26 | K12: =(H12-J12)*1.3 -> 0.4095 | L12: =I12*$L$7 -> 0.02625 | M12: 2 | N12: =((C12*D12*M12))*G12 -> 4.2 | P12: =B12*D12*C12*G12 -> 0.315 | R12: 40 MPa | S12: =P12*$S$7 -> 0 | T12: =C12*B12+2*C12*D12 -> 4.725 | V12: =SUMIF($R$8:$R$68,$W12,$P$8:$P$68) -> 54.5681 | W12: 40 MPa
A13: V5 | B13: 0.15 | C13: 4.16 | D13: 0.6 | E13: =IF(D13<=1,0.6,1.2) -> 0.6 | G13: 1 | H13: =((B13+E13)*(D13+F13)*C13)*G13 -> 1.872 | I13: =(B13)*(C13)*G13 -> 0.624 | J13: =H13-P13 -> 1.4976 | K13: =(H13-J13)*1.3 -> 0.48672 | L13: =I13*$L$7 -> 0.0312 | M13: 2 | N13: =((C13*D13*M13))*G13 -> 4.992 | P13: =B13*D13*C13*G13 -> 0.3744 | R13: 40 MPa | S13: =P13*$S$7 -> 0 | T13: =C13*B13+2*C13*D13 -> 5.616
A14: V6 | B14: 0.15 | C14: 4.4 | D14: 0.6 | E14: =IF(D14<=1,0.6,1.2) -> 0.6 | G14: 1 | H14: =((B14+E14)*(D14+F14)*C14)*G14 -> 1.98 | I14: =(B14)*(C14)*G14 -> 0.66 | J14: =H14-P14 -> 1.584 | K14: =(H14-J14)*1.3 -> 0.5148 | L14: =I14*$L$7 -> 0.033 | M14: 2 | N14: =((C14*D14*M14))*G14 -> 5.28 | O14: 19.01 | P14: =B14*D14*C14*G14 -> 0.396 | Q14: 2.72 | R14: 40 MPa | S14: =P14*$S$7 -> 0 | T14: =C14*B14+2*C14*D14 -> 5.94
A15: V7 | B15: 0.5 | C15: 4.54 | D15: 0.6 | E15: =IF(D15<=1,0.6,1.2) -> 0.6 | G15: 1 | H15: =((B15+E15)*(D15+F15)*C15)*G15 -> 2.9964 | I15: =(B15)*(C15)*G15 -> 2.27 | J15: =H15-P15 -> 1.6344 | K15: =(H15-J15)*1.3 -> 1.7706 | L15: =I15*$L$7 -> 0.1135 | M15: 2 | N15: =((C15*D15*M15))*G15 -> 5.448 | P15: =B15*D15*C15*G15 -> 1.362 | R15: 40 MPa | S15: =P15*$S$7 -> 0 | T15: =C15*B15+2*C15*D15 -> 7.718
A16: V8 | B16: 0.3 | C16: 5.56 | D16: 0.6 | E16: =IF(D16<=1,0.6,1.2) -> 0.6 | G16: 1 | H16: =((B16+E16)*(D16+F16)*C16)*G16 -> 3.0024 | I16: =(B16)*(C16)*G16 -> 1.668 | J16: =H16-P16 -> 2.0016 | K16: =(H16-J16)*1.3 -> 1.30104 | L16: =I16*$L$7 -> 0.0834 | M16: 2 | N16: =((C16*D16*M16))*G16 -> 6.672 | P16: =B16*D16*C16*G16 -> 1.0008 | R16: 40 MPa | S16: =P16*$S$7 -> 0 | T16: =C16*B16+2*C16*D16 -> 8.34
A17: V9 | B17: 0.2 | C17: 4.2 | D17: 0.6 | E17: =IF(D17<=1,0.6,1.2) -> 0.6 | G17: 1 | H17: =((B17+E17)*(D17+F17)*C17)*G17 -> 2.016 | I17: =(B17)*(C17)*G17 -> 0.84 | J17: =H17-P17 -> 1.512 | K17: =(H17-J17)*1.3 -> 0.6552 | L17: =I17*$L$7 -> 0.042 | M17: 2 | N17: =((C17*D17*M17))*G17 -> 5.04 | P17: =B17*D17*C17*G17 -> 0.504 | R17: 40 MPa | S17: =P17*$S$7 -> 0 | T17: =C17*B17+2*C17*D17 -> 5.88
A18: V10 | B18: 0.5 | C18: 6.15 | D18: 0.6 | E18: =IF(D18<=1,0.6,1.2) -> 0.6 | G18: 1 | H18: =((B18+E18)*(D18+F18)*C18)*G18 -> 4.059 | I18: =(B18)*(C18)*G18 -> 3.075 | J18: =H18-P18 -> 2.214 | K18: =(H18-J18)*1.3 -> 2.3985 | L18: =I18*$L$7 -> 0.15375 | M18: 2 | N18: =((C18*D18*M18))*G18 -> 7.38 | O18: 21.81 | P18: =B18*D18*C18*G18 -> 1.845 | Q18: 3.78 | R18: 40 MPa | S18: =P18*$S$7 -> 0 | T18: =C18*B18+2*C18*D18 -> 10.455
A19: V11 | B19: 0.14 | C19: 6.1 | D19: 0.5 | E19: =IF(D19<=1,0.6,1.2) -> 0.6 | G19: 1 | H19: =((B19+E19)*(D19+F19)*C19)*G19 -> 2.257 | I19: =(B19)*(C19)*G19 -> 0.854 | J19: =H19-P19 -> 1.83 | K19: =(H19-J19)*1.3 -> 0.5551 | L19: =I19*$L$7 -> 0.0427 | M19: 2 | N19: =((C19*D19*M19))*G19 -> 6.1 | P19: =B19*D19*C19*G19 -> 0.427 | R19: 40 MPa | S19: =P19*$S$7 -> 0 | T19: =C19*B19+2*C19*D19 -> 6.954
A20: V12 | B20: 0.5 | C20: 6.15 | D20: 0.6 | E20: =IF(D20<=1,0.6,1.2) -> 0.6 | G20: 1 | H20: =((B20+E20)*(D20+F20)*C20)*G20 -> 4.059 | I20: =(B20)*(C20)*G20 -> 3.075 | J20: =H20-P20 -> 2.214 | K20: =(H20-J20)*1.3 -> 2.3985 | L20: =I20*$L$7 -> 0.15375 | M20: 2 | N20: =((C20*D20*M20))*G20 -> 7.38 | P20: =B20*D20*C20*G20 -> 1.845 | R20: 40 MPa | S20: =P20*$S$7 -> 0 | T20: =C20*B20+2*C20*D20 -> 10.455
A21: V13 | B21: 0.5 | C21: 4.54 | D21: 0.6 | E21: =IF(D21<=1,0.6,1.2) -> 0.6 | G21: 1 | H21: =((B21+E21)*(D21+F21)*C21)*G21 -> 2.9964 | I21: =(B21)*(C21)*G21 -> 2.27 | J21: =H21-P21 -> 1.6344 | K21: =(H21-J21)*1.3 -> 1.7706 | L21: =I21*$L$7 -> 0.1135 | M21: 2 | N21: =((C21*D21*M21))*G21 -> 5.448 | O21: 24.83 | P21: =B21*D21*C21*G21 -> 1.362 | Q21: 2.38 | R21: 40 MPa | S21: =P21*$S$7 -> 0 | T21: =C21*B21+2*C21*D21 -> 7.718
A22: V14 | B22: 0.14 | C22: 2.25 | D22: 1.9 | E22: =IF(D22<=1,0.6,1.2) -> 1.2 | G22: 1 | H22: =((B22+E22)*(D22+F22)*C22)*G22 -> 5.7285 | I22: =(B22)*(C22)*G22 -> 0.315 | J22: =H22-P22 -> 5.13 | K22: =(H22-J22)*1.3 -> 0.77805 | L22: =I22*$L$7 -> 0.01575 | M22: 2 | N22: =((C22*D22*M22))*G22 -> 8.55 | P22: =B22*D22*C22*G22 -> 0.5985 | R22: 40 MPa | S22: =P22*$S$7 -> 0 | T22: =C22*B22+2*C22*D22 -> 8.865
A23: V15 | B23: 0.14 | C23: 2.34 | D23: 0.5 | E23: =IF(D23<=1,0.6,1.2) -> 0.6 | G23: 1 | H23: =((B23+E23)*(D23+F23)*C23)*G23 -> 0.8658 | I23: =(B23)*(C23)*G23 -> 0.3276 | J23: =H23-P23 -> 0.702 | K23: =(H23-J23)*1.3 -> 0.21294 | L23: =I23*$L$7 -> 0.01638 | M23: 2 | N23: =((C23*D23*M23))*G23 -> 2.34 | P23: =B23*D23*C23*G23 -> 0.1638 | R23: 40 MPa | S23: =P23*$S$7 -> 0 | T23: =C23*B23+2*C23*D23 -> 2.6676
A24: V16 | B24: 0.14 | C24: 4 | D24: 0.5 | E24: =IF(D24<=1,0.6,1.2) -> 0.6 | G24: 1 | H24: =((B24+E24)*(D24+F24)*C24)*G24 -> 1.48 | I24: =(B24)*(C24)*G24 -> 0.56 | J24: =H24-P24 -> 1.2 | K24: =(H24-J24)*1.3 -> 0.364 | L24: =I24*$L$7 -> 0.028 | M24: 2 | N24: =((C24*D24*M24))*G24 -> 4 | P24: =B24*D24*C24*G24 -> 0.28 | R24: 40 MPa | S24: =P24*$S$7 -> 0 | T24: =C24*B24+2*C24*D24 -> 4.56
A25: V17 | B25: 0.14 | C25: 2.25 | D25: 1.9 | E25: =IF(D25<=1,0.6,1.2) -> 1.2 | G25: 1 | H25: =((B25+E25)*(D25+F25)*C25)*G25 -> 5.7285 | I25: =(B25)*(C25)*G25 -> 0.315 | J25: =H25-P25 -> 5.13 | K25: =(H25-J25)*1.3 -> 0.77805 | L25: =I25*$L$7 -> 0.01575 | M25: 2 | N25: =((C25*D25*M25))*G25 -> 8.55 | P25: =B25*D25*C25*G25 -> 0.5985 | R25: 40 MPa | S25: =P25*$S$7 -> 0 | T25: =C25*B25+2*C25*D25 -> 8.865
A26: V18 | B26: 0.15 | C26: 3.71 | D26: 0.6 | E26: =IF(D26<=1,0.6,1.2) -> 0.6 | G26: 1 | H26: =((B26+E26)*(D26+F26)*C26)*G26 -> 1.6695 | I26: =(B26)*(C26)*G26 -> 0.5565 | J26: =H26-P26 -> 1.3356 | K26: =(H26-J26)*1.3 -> 0.43407 | L26: =I26*$L$7 -> 0.027825 | M26: 2 | N26: =((C26*D26*M26))*G26 -> 4.452 | O26: 17.44 | P26: =B26*D26*C26*G26 -> 0.3339 | Q26: 3.11 | R26: 40 MPa | S26: =P26*$S$7 -> 0 | T26: =C26*B26+2*C26*D26 -> 5.0085
A27: V19 | B27: 0.5 | C27: 6.5 | D27: 0.6 | E27: =IF(D27<=1,0.6,1.2) -> 0.6 | G27: 1 | H27: =((B27+E27)*(D27+F27)*C27)*G27 -> 4.29 | I27: =(B27)*(C27)*G27 -> 3.25 | J27: =H27-P27 -> 2.34 | K27: =(H27-J27)*1.3 -> 2.535 | L27: =I27*$L$7 -> 0.1625 | M27: 2 | N27: =((C27*D27*M27))*G27 -> 7.8 | P27: =B27*D27*C27*G27 -> 1.95 | R27: 40 MPa | S27: =P27*$S$7 -> 0 | T27: =C27*B27+2*C27*D27 -> 11.05
A28: V20 | B28: 0.5 | C28: 4.54 | D28: 0.6 | E28: =IF(D28<=1,0.6,1.2) -> 0.6 | G28: 1 | H28: =((B28+E28)*(D28+F28)*C28)*G28 -> 2.9964 | I28: =(B28)*(C28)*G28 -> 2.27 | J28: =H28-P28 -> 1.6344 | K28: =(H28-J28)*1.3 -> 1.7706 | L28: =I28*$L$7 -> 0.1135 | M28: 2 | N28: =((C28*D28*M28))*G28 -> 5.448 | P28: =B28*D28*C28*G28 -> 1.362 | R28: 40 MPa | S28: =P28*$S$7 -> 0 | T28: =C28*B28+2*C28*D28 -> 7.718
A29: V21 | B29: 0.5 | C29: 5.135 | D29: 0.6 | E29: =IF(D29<=1,0.6,1.2) -> 0.6 | G29: 1 | H29: =((B29+E29)*(D29+F29)*C29)*G29 -> 3.3891 | I29: =(B29)*(C29)*G29 -> 2.5675 | J29: =H29-P29 -> 1.8486 | K29: =(H29-J29)*1.3 -> 2.00265 | L29: =I29*$L$7 -> 0.128375 | M29: 2 | N29: =((C29*D29*M29))*G29 -> 6.162 | O29: 27.62 | P29: =B29*D29*C29*G29 -> 1.5405 | Q29: 4.28 | R29: 40 MPa | S29: =P29*$S$7 -> 0 | T29: =C29*B29+2*C29*D29 -> 8.7295
A30: V22 | B30: 0.2 | C30: 15.725 | D30: 0.5 | E30: =IF(D30<=1,0.6,1.2) -> 0.6 | G30: 1 | H30: =((B30+E30)*(D30+F30)*C30)*G30 -> 6.29 | I30: =(B30)*(C30)*G30 -> 3.145 | J30: =H30-P30 -> 4.7175 | K30: =(H30-J30)*1.3 -> 2.04425 | L30: =I30*$L$7 -> 0.15725 | M30: 2 | N30: =((C30*D30*M30))*G30 -> 15.725 | P30: =B30*D30*C30*G30 -> 1.5725 | R30: 40 MPa | S30: =P30*$S$7 -> 0 | T30: =C30*B30+2*C30*D30 -> 18.87
A31: V23 | B31: 0.5 | C31: 5.4 | D31: 0.6 | E31: =IF(D31<=1,0.6,1.2) -> 0.6 | G31: 1 | H31: =((B31+E31)*(D31+F31)*C31)*G31 -> 3.564 | I31: =(B31)*(C31)*G31 -> 2.7 | J31: =H31-P31 -> 1.944 | K31: =(H31-J31)*1.3 -> 2.106 | L31: =I31*$L$7 -> 0.135 | M31: 2 | N31: =((C31*D31*M31))*G31 -> 6.48 | P31: =B31*D31*C31*G31 -> 1.62 | R31: 40 MPa | S31: =P31*$S$7 -> 0 | T31: =C31*B31+2*C31*D31 -> 9.18
A32: V24 | B32: 0.5 | C32: 5.135 | D32: 0.6 | E32: =IF(D32<=1,0.6,1.2) -> 0.6 | G32: 1 | H32: =((B32+E32)*(D32+F32)*C32)*G32 -> 3.3891 | I32: =(B32)*(C32)*G32 -> 2.5675 | J32: =H32-P32 -> 1.8486 | K32: =(H32-J32)*1.3 -> 2.00265 | L32: =I32*$L$7 -> 0.128375 | M32: 2 | N32: =((C32*D32*M32))*G32 -> 6.162 | O32: 30.18 | P32: =B32*D32*C32*G32 -> 1.5405 | Q32: 4.28 | R32: 40 MPa | S32: =P32*$S$7 -> 0 | T32: =C32*B32+2*C32*D32 -> 8.7295
A33: V25 | B33: 0.2 | C33: 15.725 | D33: 0.5 | E33: =IF(D33<=1,0.6,1.2) -> 0.6 | G33: 1 | H33: =((B33+E33)*(D33+F33)*C33)*G33 -> 6.29 | I33: =(B33)*(C33)*G33 -> 3.145 | J33: =H33-P33 -> 4.7175 | K33: =(H33-J33)*1.3 -> 2.04425 | L33: =I33*$L$7 -> 0.15725 | M33: 2 | N33: =((C33*D33*M33))*G33 -> 15.725 | P33: =B33*D33*C33*G33 -> 1.5725 | R33: 40 MPa | S33: =P33*$S$7 -> 0 | T33: =C33*B33+2*C33*D33 -> 18.87
A34: V26 | B34: 0.5 | C34: 5.4 | D34: 0.6 | E34: =IF(D34<=1,0.6,1.2) -> 0.6 | G34: 1 | H34: =((B34+E34)*(D34+F34)*C34)*G34 -> 3.564 | I34: =(B34)*(C34)*G34 -> 2.7 | J34: =H34-P34 -> 1.944 | K34: =(H34-J34)*1.3 -> 2.106 | L34: =I34*$L$7 -> 0.135 | M34: 2 | N34: =((C34*D34*M34))*G34 -> 6.48 | P34: =B34*D34*C34*G34 -> 1.62 | R34: 40 MPa | S34: =P34*$S$7 -> 0 | T34: =C34*B34+2*C34*D34 -> 9.18
A35: V27 | B35: 0.2 | C35: 3.6 | D35: 0.6 | E35: =IF(D35<=1,0.6,1.2) -> 0.6 | G35: 1 | H35: =((B35+E35)*(D35+F35)*C35)*G35 -> 1.728 | I35: =(B35)*(C35)*G35 -> 0.72 | J35: =H35-P35 -> 1.296 | K35: =(H35-J35)*1.3 -> 0.5616 | L35: =I35*$L$7 -> 0.036 | M35: 2 | N35: =((C35*D35*M35))*G35 -> 4.32 | O35: 44.87 | P35: =B35*D35*C35*G35 -> 0.432 | Q35: 3.89 | R35: 40 MPa | S35: =P35*$S$7 -> 0 | T35: =C35*B35+2*C35*D35 -> 5.04
A36: V28 | B36: 0.2 | C36: 10.95 | D36: 0.6 | E36: =IF(D36<=1,0.6,1.2) -> 0.6 | G36: 1 | H36: =((B36+E36)*(D36+F36)*C36)*G36 -> 5.256 | I36: =(B36)*(C36)*G36 -> 2.19 | J36: =H36-P36 -> 3.942 | K36: =(H36-J36)*1.3 -> 1.7082 | L36: =I36*$L$7 -> 0.1095 | M36: 2 | N36: =((C36*D36*M36))*G36 -> 13.14 | P36: =B36*D36*C36*G36 -> 1.314 | R36: 40 MPa | S36: =P36*$S$7 -> 0 | T36: =C36*B36+2*C36*D36 -> 15.33
A37: V29 | B37: 0.2 | C37: 10.4 | D37: 0.6 | E37: =IF(D37<=1,0.6,1.2) -> 0.6 | G37: 1 | H37: =((B37+E37)*(D37+F37)*C37)*G37 -> 4.992 | I37: =(B37)*(C37)*G37 -> 2.08 | J37: =H37-P37 -> 3.744 | K37: =(H37-J37)*1.3 -> 1.6224 | L37: =I37*$L$7 -> 0.104 | M37: 2 | N37: =((C37*D37*M37))*G37 -> 12.48 | P37: =B37*D37*C37*G37 -> 1.248 | R37: 40 MPa | S37: =P37*$S$7 -> 0 | T37: =C37*B37+2*C37*D37 -> 14.56
A38: V30 | B38: 0.15 | C38: 3.6 | D38: 0.6 | E38: =IF(D38<=1,0.6,1.2) -> 0.6 | G38: 1 | H38: =((B38+E38)*(D38+F38)*C38)*G38 -> 1.62 | I38: =(B38)*(C38)*G38 -> 0.54 | J38: =H38-P38 -> 1.296 | K38: =(H38-J38)*1.3 -> 0.4212 | L38: =I38*$L$7 -> 0.027 | M38: 2 | N38: =((C38*D38*M38))*G38 -> 4.32 | P38: =B38*D38*C38*G38 -> 0.324 | R38: 40 MPa | S38: =P38*$S$7 -> 0 | T38: =C38*B38+2*C38*D38 -> 4.86
A39: V31 | B39: 0.15 | C39: 10.5 | D39: 0.6 | E39: =IF(D39<=1,0.6,1.2) -> 0.6 | G39: 1 | H39: =((B39+E39)*(D39+F39)*C39)*G39 -> 4.725 | I39: =(B39)*(C39)*G39 -> 1.575 | J39: =H39-P39 -> 3.78 | K39: =(H39-J39)*1.3 -> 1.2285 | L39: =I39*$L$7 -> 0.07875 | M39: 2 | N39: =((C39*D39*M39))*G39 -> 12.6 | P39: =B39*D39*C39*G39 -> 0.945 | R39: 40 MPa | S39: =P39*$S$7 -> 0 | T39: =C39*B39+2*C39*D39 -> 14.175
A40: V32 | B40: 0.5 | C40: 5.5 | D40: 0.6 | E40: =IF(D40<=1,0.6,1.2) -> 0.6 | G40: 1 | H40: =((B40+E40)*(D40+F40)*C40)*G40 -> 3.63 | I40: =(B40)*(C40)*G40 -> 2.75 | J40: =H40-P40 -> 1.98 | K40: =(H40-J40)*1.3 -> 2.145 | L40: =I40*$L$7 -> 0.1375 | M40: 2 | N40: =((C40*D40*M40))*G40 -> 6.6 | O40: 24.2 | P40: =B40*D40*C40*G40 -> 1.65 | Q40: 3.38 | R40: 40 MPa | S40: =P40*$S$7 -> 0 | T40: =C40*B40+2*C40*D40 -> 9.35
A41: V33 | B41: 0.2 | C41: 2.4 | D41: 0.6 | E41: =IF(D41<=1,0.6,1.2) -> 0.6 | G41: 1 | H41: =((B41+E41)*(D41+F41)*C41)*G41 -> 1.152 | I41: =(B41)*(C41)*G41 -> 0.48 | J41: =H41-P41 -> 0.864 | K41: =(H41-J41)*1.3 -> 0.3744 | L41: =I41*$L$7 -> 0.024 | M41: 2 | N41: =((C41*D41*M41))*G41 -> 2.88 | P41: =B41*D41*C41*G41 -> 0.288 | R41: 40 MPa | S41: =P41*$S$7 -> 0 | T41: =C41*B41+2*C41*D41 -> 3.36
A42: V34 | B42: 0.2 | C42: 10.85 | D42: 0.6 | E42: =IF(D42<=1,0.6,1.2) -> 0.6 | G42: 1 | H42: =((B42+E42)*(D42+F42)*C42)*G42 -> 5.208 | I42: =(B42)*(C42)*G42 -> 2.17 | J42: =H42-P42 -> 3.906 | K42: =(H42-J42)*1.3 -> 1.6926 | L42: =I42*$L$7 -> 0.1085 | M42: 2 | N42: =((C42*D42*M42))*G42 -> 13.02 | P42: =B42*D42*C42*G42 -> 1.302 | R42: 40 MPa | S42: =P42*$S$7 -> 0 | T42: =C42*B42+2*C42*D42 -> 15.19
A43: V35 | B43: 0.2 | C43: 5.4 | D43: 0.6 | E43: =IF(D43<=1,0.6,1.2) -> 0.6 | G43: 1 | H43: =((B43+E43)*(D43+F43)*C43)*G43 -> 2.592 | I43: =(B43)*(C43)*G43 -> 1.08 | J43: =H43-P43 -> 1.944 | K43: =(H43-J43)*1.3 -> 0.8424 | L43: =I43*$L$7 -> 0.054 | M43: 2 | N43: =((C43*D43*M43))*G43 -> 6.48 | P43: =B43*D43*C43*G43 -> 0.648 | R43: 40 MPa | S43: =P43*$S$7 -> 0 | T43: =C43*B43+2*C43*D43 -> 7.56
A44: V36 | B44: 0.5 | C44: 5.3 | D44: 0.6 | E44: =IF(D44<=1,0.6,1.2) -> 0.6 | G44: 1 | H44: =((B44+E44)*(D44+F44)*C44)*G44 -> 3.498 | I44: =(B44)*(C44)*G44 -> 2.65 | J44: =H44-P44 -> 1.908 | K44: =(H44-J44)*1.3 -> 2.067 | L44: =I44*$L$7 -> 0.1325 | M44: 2 | N44: =((C44*D44*M44))*G44 -> 6.36 | O44: 18.94 | P44: =B44*D44*C44*G44 -> 1.59 | Q44: 2.4 | R44: 40 MPa | S44: =P44*$S$7 -> 0 | T44: =C44*B44+2*C44*D44 -> 9.01
A45: V37 | B45: 0.15 | C45: 2.4 | D45: 0.6 | E45: =IF(D45<=1,0.6,1.2) -> 0.6 | G45: 1 | H45: =((B45+E45)*(D45+F45)*C45)*G45 -> 1.08 | I45: =(B45)*(C45)*G45 -> 0.36 | J45: =H45-P45 -> 0.864 | K45: =(H45-J45)*1.3 -> 0.2808 | L45: =I45*$L$7 -> 0.018 | M45: 2 | N45: =((C45*D45*M45))*G45 -> 2.88 | P45: =B45*D45*C45*G45 -> 0.216 | R45: 40 MPa | S45: =P45*$S$7 -> 0 | T45: =C45*B45+2*C45*D45 -> 3.24
A46: V38 | B46: 0.15 | C46: 6.55 | D46: 0.5 | E46: =IF(D46<=1,0.6,1.2) -> 0.6 | G46: 1 | H46: =((B46+E46)*(D46+F46)*C46)*G46 -> 2.45625 | I46: =(B46)*(C46)*G46 -> 0.9825 | J46: =H46-P46 -> 1.965 | K46: =(H46-J46)*1.3 -> 0.638625 | L46: =I46*$L$7 -> 0.049125 | M46: 2 | N46: =((C46*D46*M46))*G46 -> 6.55 | P46: =B46*D46*C46*G46 -> 0.49125 | R46: 40 MPa | S46: =P46*$S$7 -> 0 | T46: =C46*B46+2*C46*D46 -> 7.5325
A47: V39 | B47: 0.15 | C47: 3.3 | D47: 0.6 | E47: =IF(D47<=1,0.6,1.2) -> 0.6 | G47: 1 | H47: =((B47+E47)*(D47+F47)*C47)*G47 -> 1.485 | I47: =(B47)*(C47)*G47 -> 0.495 | J47: =H47-P47 -> 1.188 | K47: =(H47-J47)*1.3 -> 0.3861 | L47: =I47*$L$7 -> 0.02475 | M47: 2 | N47: =((C47*D47*M47))*G47 -> 3.96 | P47: =B47*D47*C47*G47 -> 0.297 | R47: 40 MPa | S47: =P47*$S$7 -> 0 | T47: =C47*B47+2*C47*D47 -> 4.455
A48: V40 | B48: 0.15 | C48: 4.1 | D48: 0.6 | E48: =IF(D48<=1,0.6,1.2) -> 0.6 | G48: 1 | H48: =((B48+E48)*(D48+F48)*C48)*G48 -> 1.845 | I48: =(B48)*(C48)*G48 -> 0.615 | J48: =H48-P48 -> 1.476 | K48: =(H48-J48)*1.3 -> 0.4797 | L48: =I48*$L$7 -> 0.03075 | M48: 2 | N48: =((C48*D48*M48))*G48 -> 4.92 | P48: =B48*D48*C48*G48 -> 0.369 | R48: 40 MPa | S48: =P48*$S$7 -> 0 | T48: =C48*B48+2*C48*D48 -> 5.535
A49: V41 | B49: 0.5 | C49: 7.1 | D49: 0.6 | E49: =IF(D49<=1,0.6,1.2) -> 0.6 | G49: 1 | H49: =((B49+E49)*(D49+F49)*C49)*G49 -> 4.686 | I49: =(B49)*(C49)*G49 -> 3.55 | J49: =H49-P49 -> 2.556 | K49: =(H49-J49)*1.3 -> 2.769 | L49: =I49*$L$7 -> 0.1775 | M49: 2 | N49: =((C49*D49*M49))*G49 -> 8.52 | O49: 19.58 | P49: =B49*D49*C49*G49 -> 2.13 | Q49: 3.75 | R49: 40 MPa | S49: =P49*$S$7 -> 0 | T49: =C49*B49+2*C49*D49 -> 12.07
A50: V42 | B50: 0.25 | C50: 3 | D50: 0.5 | E50: =IF(D50<=1,0.6,1.2) -> 0.6 | G50: 1 | H50: =((B50+E50)*(D50+F50)*C50)*G50 -> 1.275 | I50: =(B50)*(C50)*G50 -> 0.75 | J50: =H50-P50 -> 0.9 | K50: =(H50-J50)*1.3 -> 0.4875 | L50: =I50*$L$7 -> 0.0375 | M50: 2 | N50: =((C50*D50*M50))*G50 -> 3 | P50: =B50*D50*C50*G50 -> 0.375 | R50: 40 MPa | S50: =P50*$S$7 -> 0 | T50: =C50*B50+2*C50*D50 -> 3.75
A51: V43 | B51: 0.5 | C51: 6.15 | D51: 0.6 | E51: =IF(D51<=1,0.6,1.2) -> 0.6 | G51: 1 | H51: =((B51+E51)*(D51+F51)*C51)*G51 -> 4.059 | I51: =(B51)*(C51)*G51 -> 3.075 | J51: =H51-P51 -> 2.214 | K51: =(H51-J51)*1.3 -> 2.3985 | L51: =I51*$L$7 -> 0.15375 | M51: 2 | N51: =((C51*D51*M51))*G51 -> 7.38 | P51: =B51*D51*C51*G51 -> 1.845 | R51: 40 MPa | S51: =P51*$S$7 -> 0 | T51: =C51*B51+2*C51*D51 -> 10.455
A52: V44 | B52: 0.15 | C52: 2.4 | D52: 0.6 | E52: =IF(D52<=1,0.6,1.2) -> 0.6 | G52: 1 | H52: =((B52+E52)*(D52+F52)*C52)*G52 -> 1.08 | I52: =(B52)*(C52)*G52 -> 0.36 | J52: =H52-P52 -> 0.864 | K52: =(H52-J52)*1.3 -> 0.2808 | L52: =I52*$L$7 -> 0.018 | M52: 2 | N52: =((C52*D52*M52))*G52 -> 2.88 | P52: =B52*D52*C52*G52 -> 0.216 | R52: 40 MPa | S52: =P52*$S$7 -> 0 | T52: =C52*B52+2*C52*D52 -> 3.24
A53: V45 | B53: 0.14 | C53: 1.69 | D53: 0.5 | E53: =IF(D53<=1,0.6,1.2) -> 0.6 | G53: 1 | H53: =((B53+E53)*(D53+F53)*C53)*G53 -> 0.6253 | I53: =(B53)*(C53)*G53 -> 0.2366 | J53: =H53-P53 -> 0.507 | K53: =(H53-J53)*1.3 -> 0.15379 | L53: =I53*$L$7 -> 0.01183 | M53: 2 | N53: =((C53*D53*M53))*G53 -> 1.69 | O53: 29.89 | P53: =B53*D53*C53*G53 -> 0.1183 | Q53: 2.49 | R53: 40 MPa | S53: =P53*$S$7 -> 0 | T53: =C53*B53+2*C53*D53 -> 1.9266
A54: V46 | B54: 0.15 | C54: 6.6 | D54: 0.5 | E54: =IF(D54<=1,0.6,1.2) -> 0.6 | G54: 1 | H54: =((B54+E54)*(D54+F54)*C54)*G54 -> 2.475 | I54: =(B54)*(C54)*G54 -> 0.99 | J54: =H54-P54 -> 1.98 | K54: =(H54-J54)*1.3 -> 0.6435 | L54: =I54*$L$7 -> 0.0495 | M54: 2 | N54: =((C54*D54*M54))*G54 -> 6.6 | P54: =B54*D54*C54*G54 -> 0.495 | R54: 40 MPa | S54: =P54*$S$7 -> 0 | T54: =C54*B54+2*C54*D54 -> 7.59
A55: V47 | B55: 0.14 | C55: 4.2 | D55: 1.9 | E55: =IF(D55<=1,0.6,1.2) -> 1.2 | G55: 1 | H55: =((B55+E55)*(D55+F55)*C55)*G55 -> 10.6932 | I55: =(B55)*(C55)*G55 -> 0.588 | J55: =H55-P55 -> 9.576 | K55: =(H55-J55)*1.3 -> 1.45236 | L55: =I55*$L$7 -> 0.0294 | M55: 2 | N55: =((C55*D55*M55))*G55 -> 15.96 | P55: =B55*D55*C55*G55 -> 1.1172 | R55: 40 MPa | S55: =P55*$S$7 -> 0 | T55: =C55*B55+2*C55*D55 -> 16.548
A56: V48 | B56: 0.25 | C56: 2.95 | D56: 1.9 | E56: =IF(D56<=1,0.6,1.2) -> 1.2 | G56: 1 | H56: =((B56+E56)*(D56+F56)*C56)*G56 -> 8.12725 | I56: =(B56)*(C56)*G56 -> 0.7375 | J56: =H56-P56 -> 6.726 | K56: =(H56-J56)*1.3 -> 1.821625 | L56: =I56*$L$7 -> 0.036875 | M56: 2 | N56: =((C56*D56*M56))*G56 -> 11.21 | P56: =B56*D56*C56*G56 -> 1.40125 | R56: 40 MPa | S56: =P56*$S$7 -> 0 | T56: =C56*B56+2*C56*D56 -> 11.9475
A57: V48 | B57: 0.25 | C57: 1.85 | D57: 0.6 | E57: =IF(D57<=1,0.6,1.2) -> 0.6 | G57: 1 | H57: =((B57+E57)*(D57+F57)*C57)*G57 -> 0.9435 | I57: =(B57)*(C57)*G57 -> 0.4625 | J57: =H57-P57 -> 0.666 | K57: =(H57-J57)*1.3 -> 0.36075 | L57: =I57*$L$7 -> 0.023125 | M57: 2 | N57: =((C57*D57*M57))*G57 -> 2.22 | P57: =B57*D57*C57*G57 -> 0.2775 | R57: 40 MPa | S57: =P57*$S$7 -> 0 | T57: =C57*B57+2*C57*D57 -> 2.6825
A58: V49 | B58: 0.5 | C58: 6.1 | D58: 0.6 | E58: =IF(D58<=1,0.6,1.2) -> 0.6 | G58: 1 | H58: =((B58+E58)*(D58+F58)*C58)*G58 -> 4.026 | I58: =(B58)*(C58)*G58 -> 3.05 | J58: =H58-P58 -> 2.196 | K58: =(H58-J58)*1.3 -> 2.379 | L58: =I58*$L$7 -> 0.1525 | M58: 2 | N58: =((C58*D58*M58))*G58 -> 7.32 | O58: 20.85 | P58: =B58*D58*C58*G58 -> 1.83 | Q58: 3.81 | R58: 40 MPa | S58: =P58*$S$7 -> 0 | T58: =C58*B58+2*C58*D58 -> 10.37
A59: V50 | B59: 0.15 | C59: 2.4 | D59: 0.6 | E59: =IF(D59<=1,0.6,1.2) -> 0.6 | G59: 1 | H59: =((B59+E59)*(D59+F59)*C59)*G59 -> 1.08 | I59: =(B59)*(C59)*G59 -> 0.36 | J59: =H59-P59 -> 0.864 | K59: =(H59-J59)*1.3 -> 0.2808 | L59: =I59*$L$7 -> 0.018 | M59: 2 | N59: =((C59*D59*M59))*G59 -> 2.88 | P59: =B59*D59*C59*G59 -> 0.216 | R59: 40 MPa | S59: =P59*$S$7 -> 0 | T59: =C59*B59+2*C59*D59 -> 3.24
A60: V51 | B60: 0.5 | C60: 6.4 | D60: 0.6 | E60: =IF(D60<=1,0.6,1.2) -> 0.6 | G60: 1 | H60: =((B60+E60)*(D60+F60)*C60)*G60 -> 4.224 | I60: =(B60)*(C60)*G60 -> 3.2 | J60: =H60-P60 -> 2.304 | K60: =(H60-J60)*1.3 -> 2.496 | L60: =I60*$L$7 -> 0.16 | M60: 2 | N60: =((C60*D60*M60))*G60 -> 7.68 | P60: =B60*D60*C60*G60 -> 1.92 | R60: 40 MPa | S60: =P60*$S$7 -> 0 | T60: =C60*B60+2*C60*D60 -> 10.88
A61: V52 | B61: 0.15 | C61: 3.6 | D61: 0.6 | E61: =IF(D61<=1,0.6,1.2) -> 0.6 | G61: 1 | H61: =((B61+E61)*(D61+F61)*C61)*G61 -> 1.62 | I61: =(B61)*(C61)*G61 -> 0.54 | J61: =H61-P61 -> 1.296 | K61: =(H61-J61)*1.3 -> 0.4212 | L61: =I61*$L$7 -> 0.027 | M61: 2 | N61: =((C61*D61*M61))*G61 -> 4.32 | P61: =B61*D61*C61*G61 -> 0.324 | R61: 40 MPa | S61: =P61*$S$7 -> 0 | T61: =C61*B61+2*C61*D61 -> 4.86
A62: V53 | B62: 0.15 | C62: 8.35 | D62: 0.6 | E62: =IF(D62<=1,0.6,1.2) -> 0.6 | G62: 1 | H62: =((B62+E62)*(D62+F62)*C62)*G62 -> 3.7575 | I62: =(B62)*(C62)*G62 -> 1.2525 | J62: =H62-P62 -> 3.006 | K62: =(H62-J62)*1.3 -> 0.97695 | L62: =I62*$L$7 -> 0.062625 | M62: 2 | N62: =((C62*D62*M62))*G62 -> 10.02 | O62: 39.83 | P62: =B62*D62*C62*G62 -> 0.7515 | Q62: 3.53 | R62: 40 MPa | S62: =P62*$S$7 -> 0 | T62: =C62*B62+2*C62*D62 -> 11.2725
A63: V54 | B63: 0.2 | C63: 3.6 | D63: 0.6 | E63: =IF(D63<=1,0.6,1.2) -> 0.6 | G63: 1 | H63: =((B63+E63)*(D63+F63)*C63)*G63 -> 1.728 | I63: =(B63)*(C63)*G63 -> 0.72 | J63: =H63-P63 -> 1.296 | K63: =(H63-J63)*1.3 -> 0.5616 | L63: =I63*$L$7 -> 0.036 | M63: 2 | N63: =((C63*D63*M63))*G63 -> 4.32 | P63: =B63*D63*C63*G63 -> 0.432 | R63: 40 MPa | S63: =P63*$S$7 -> 0 | T63: =C63*B63+2*C63*D63 -> 5.04
A64: V55 | B64: 0.2 | C64: 7.1 | D64: 0.6 | E64: =IF(D64<=1,0.6,1.2) -> 0.6 | G64: 1 | H64: =((B64+E64)*(D64+F64)*C64)*G64 -> 3.408 | I64: =(B64)*(C64)*G64 -> 1.42 | J64: =H64-P64 -> 2.556 | K64: =(H64-J64)*1.3 -> 1.1076 | L64: =I64*$L$7 -> 0.071 | M64: 2 | N64: =((C64*D64*M64))*G64 -> 8.52 | P64: =B64*D64*C64*G64 -> 0.852 | R64: 40 MPa | S64: =P64*$S$7 -> 0 | T64: =C64*B64+2*C64*D64 -> 9.94
A65: V56 | B65: 0.2 | C65: 6.4 | D65: 0.6 | E65: =IF(D65<=1,0.6,1.2) -> 0.6 | G65: 1 | H65: =((B65+E65)*(D65+F65)*C65)*G65 -> 3.072 | I65: =(B65)*(C65)*G65 -> 1.28 | J65: =H65-P65 -> 2.304 | K65: =(H65-J65)*1.3 -> 0.9984 | L65: =I65*$L$7 -> 0.064 | M65: 2 | N65: =((C65*D65*M65))*G65 -> 7.68 | P65: =B65*D65*C65*G65 -> 0.768 | R65: 40 MPa | S65: =P65*$S$7 -> 0 | T65: =C65*B65+2*C65*D65 -> 8.96
A66: V57 | B66: 0.2 | C66: 8.35 | D66: 0.6 | E66: =IF(D66<=1,0.6,1.2) -> 0.6 | G66: 1 | H66: =((B66+E66)*(D66+F66)*C66)*G66 -> 4.008 | I66: =(B66)*(C66)*G66 -> 1.67 | J66: =H66-P66 -> 3.006 | K66: =(H66-J66)*1.3 -> 1.3026 | L66: =I66*$L$7 -> 0.0835 | M66: 2 | N66: =((C66*D66*M66))*G66 -> 10.02 | P66: =B66*D66*C66*G66 -> 1.002 | R66: 40 MPa | S66: =P66*$S$7 -> 0 | T66: =C66*B66+2*C66*D66 -> 11.69
B68: TOTAL GERAL | C68: =SUM(C8:C66) -> 327.16 | H68: =SUM(H8:H67) -> 191.0099 | I68: =SUM(I8:I67) -> 88.5417 | J68: =H68-Q68 -> 143.6199 | K68: =(H68-J68)*1.3 -> 61.607 | L68: =SUM(L8:L67) -> 4.427085 | N68: =SUM(N8:N67) -> 410.536 | O68: =SUM(O8:O67) -> 378.1 | P68: =SUM(P8:P67) -> 54.5681 | Q68: =SUM(Q8:Q67) -> 47.39 | S68: =SUM(S8:S67) -> 0 | T68: =SUM(T8:T67) -> 499.0777 | U68: Considerada a impermeabilização do lado e da parte de cima, PREVALECE quantidades do modelo.
O69: =1-N68/O68 -> -0.085786829 | Q69: =1-P68/Q68 -> -0.15146866
O70: =IF(ABS(O69)<10%,"Usar valor de projeto","Confirmar com cliente") -> Usar valor de projeto | Q70: =IF(ABS(Q69)<10%,"Usar valor de projeto","Confirmar com cliente") -> Confirmar com cliente
A71: IMPERMEABILIZAÇÃO DO BALDRAME | K71: DETALHE TÍPICO
A72: Total | B72: =N68 -> 410.536

Sheet Lajes Fundação
D1: Projeto | E1: =ORÇAMENTO!I4 -> SENSE106
D2: Empresa | E2: =ORÇAMENTO!I5 -> HOLZE EMPREENDIMENTOS
D3: Revisão | E3: R00 - Michelle Furlan -
A4: POÇOS DE ELEVADORES
A5: PROJETO:
A6: COMPRIMENTO DO POÇO | B6: LARGURA DO POÇO | C6: ESPESSURA DE CONCRETO | D6: ALTURA DO POÇO | E6: ALTURA INTERNA DO RESERVATÓRIO | F6: COMPRIMENTO INTERNO DO RESERVATÓRIO | G6: LARGURA INTERNA DO RESERVATÓRIO | H6: NÚMERO DE ELEVADORES | I6: ESPESSURA DE LASTRO PARA O POÇO | J6: ESPAÇAMENTO LATERAL PARA ESCAVAÇÃO | K6: VOLUME DE ESCAVAÇÃO | L6: VOLUME DE REATERRO | M6: VOLUME DE BOTA-FORA | N6: APILOAMENTO DE VALA | O6: VOLUME DE LASTRO
A7: L | B7: B | C7: e.C. | D7: H | E7: h | F7: l | G7: b | H7: n | I7: e.L. | J7: K | K7: VE | L7: VA | M7: VB | N7: AP | O7: VM
A8: m | B8: m | C8: m | D8: m | E8: m | F8: m | G8: m | H8: UD | I8: m | J8: m | K8: m3 | L8: m3 | M8: m3 | N8: m2 | O8: m3
A9: 4.2 | B9: 2.25 | C9: 0.14 | D9: 1.75 | E9: =D9-C9 -> 1.61 | F9: =A9-C9*2 -> 3.92 | G9: =B9-C9*2 -> 1.97 | H9: 2 | I9: 0.05 | J9: =IF(D9<=1,0.6,D9) -> 1.75 | K9: =(A9+J9)*(B9+J9)*(D9+I9)*H9 -> 85.68 | L9: =K9-H9*A9*B9*D9 -> 52.605 | M9: =K9-L9 -> 33.075 | N9: =(A9*B9)*H9 -> 18.9 | O9: =I9*N9 -> 0.945
E10: =D10-C10 -> 0 | F10: =A10-C10*2 -> 0 | G10: =B10-C10*2 -> 0 | J10: =IF(D10<=1,0.6,D10) -> 0.6 | K10: =(A10+J10)*(B10+J10)*(D10+I10)*H10 -> 0 | L10: =K10-H10*A10*B10*D10 -> 0 | M10: =K10-L10 -> 0 | N10: =(A10*B10)*H10 -> 0 | O10: =I10*N10 -> 0
A11: TOTAL | K11: =SUM(K9:K10) -> 85.68 | L11: =SUM(L9:L10) -> 52.605 | M11: =SUM(M9:M10) -> 33.075 | N11: =SUM(N9:N10) -> 18.9 | O11: =SUM(O9:O10) -> 0.945
F13: CÓDIGO DA LAJE MACIÇA | G13: LADO 1 DA LAJE | H13: LADO 2 DA LAJE | I13: AREA DE LAJE | J13: ESPESSURA DA LAJE | K13: FORMAS DE COMPENSADO | L13: VOLUME DE CONCRETO
F14: Cód. | G14: L1 | H14: L2 | I14: A | J14: e | K14: F | L14: C
G15: m | H15: m | I15: m2 | J15: m | K15: m2 | L15: m3
F16: LE1 | G16: 1.86 | H16: 1.81 | I16: =G16*H16 -> 3.3666 | J16: 0.15 | K16: =2*G16+2*H16 -> 7.34 | L16: =I16*J16 -> 0.50499
F17: LE2 | G17: 1.86 | H17: 1.81 | I17: =G17*H17 -> 3.3666 | J17: 0.15 | K17: =G17+H17 -> 3.67 | L17: =I17*J17 -> 0.50499
I18: =F18*G18 -> 0 | K18: =I18 -> 0 | L18: =I18*J18 -> 0
F19: TOTAL | I19: =SUM(I16:I18) -> 6.7332 | K19: =SUM(K16:K18) -> 11.01 | L19: =SUM(L16:L18) -> 1.00998
F21: Comtempla escavação do poço e a concretagem do fundo
A23: PROJETO | B23: PEÇA | C23: DIMENSÕES UNITÁRIAS | G23: FORMA | J23: CONCRETO | M23: LAJE / MOLDE | N23: IMAGENS LEVANTAMENTO
C24: ÁREA m² | D24: PERÍMETRO m | E24: ALT m | F24: QUANT | G24: COEF | H24: UNIT m² | I24: TOTAL m² | J24: UNIT m³ | K24: TOTAL m³ | L24: RESISTÊNCIA | M24: TIPO
A25: TÉRREO
A26: Radier | G26: 1 | H26: =IF(C26="","",IF(F26<0,-C26+(D26*(E26+0.02)),C26+(D26*(E26+0.02)))) | I26: =IF(C26="","",IF(F26>0,F26*H26,F26*-H26)) | J26: =IF(C26="","",IF(F26<0,-C26*E26,C26*E26)) | K26: 84 | L26: 40MPa -Térreo | M26: MOLDADA IN LOCO
I27: =SUM(I26) -> 0 | K27: =SUM(K25:K26) -> 84

Sheet Pilares enterrados
D1: Projeto | E1: =ORÇAMENTO!I4 -> SENSE106
D2: Empresa | E2: =ORÇAMENTO!I5 -> HOLZE EMPREENDIMENTOS
D3: Revisão | E3: R00 - Michelle Furlan -
A4: POÇOS DE ELEVADORES
A5: PROJETO:
A6: PAVIMENTO | B6: CÓDIGO DO PILAR | C6: REPETIÇÕES | D6: LADO 1 DO PILAR | E6: LADO 2 DO PILAR | F6: ALTURA DO PILAR | G6: FORMAS DE COMPENSADO | H6: VOLUME DE CONCRETO | I6: ESPAÇAMENTO LATERAL PARA ESCAVAÇÃO | J6: VOLUME DE ESCAVAÇÃO | K6: VOLUME DE REATERRO | L6: VOLUME DE BOTA-FORA
B7: Cód. | C7: R | D7: L1 | E7: L2 | F7: H | G7: F | H7: C | I7: K | J7: VE | K7: VA | L7: VB
C8: UD | D8: m | E8: m | F8: m | G8: m2 | H8: m3 | I8: m | J8: m3 | K8: m3 | L8: m3
A9: TÉRREO | B9: F1 | C9: 1 | D9: 0.25 | E9: 0.5 | F9: 2.35 | G9: 19.8 | H9: 1.85 | I9: =IF(F9<=1,0.6,F9) -> 2.35 | J9: =(D9+I9)*(E9+I9)*(F9)*C9 -> 17.4135 | K9: =J9-D9*E9*F9*C9 -> 17.11975 | L9: =(J9-K9)*1.3 -> 0.381875
A10: TÉRREO | B10: F2 | C10: 1 | D10: 0.25 | E10: 0.5 | F10: 2.35 | I10: =IF(F10<=1,0.6,F10) -> 2.35 | J10: =(D10+I10)*(E10+I10)*(F10)*C10 -> 17.4135 | K10: =J10-D10*E10*F10*C10 -> 17.11975 | L10: =(J10-K10)*1.3 -> 0.381875
A11: TÉRREO | B11: F3 | C11: 1 | D11: 0.25 | E11: 0.5 | F11: 2.35 | I11: =IF(F11<=1,0.6,F11) -> 2.35 | J11: =(D11+I11)*(E11+I11)*(F11)*C11 -> 17.4135 | K11: =J11-D11*E11*F11*C11 -> 17.11975 | L11: =(J11-K11)*1.3 -> 0.381875
A12: TÉRREO | B12: F4 | C12: 1 | D12: 0.25 | E12: 0.5 | F12: 2.35 | I12: =IF(F12<=1,0.6,F12) -> 2.35 | J12: =(D12+I12)*(E12+I12)*(F12)*C12 -> 17.4135 | K12: =J12-D12*E12*F12*C12 -> 17.11975 | L12: =(J12-K12)*1.3 -> 0.381875
A13: TÉRREO | B13: F5 | C13: 1 | D13: 0.25 | E13: 0.5 | F13: 2.35 | I13: =IF(F13<=1,0.6,F13) -> 2.35 | J13: =(D13+I13)*(E13+I13)*(F13)*C13 -> 17.4135 | K13: =J13-D13*E13*F13*C13 -> 17.11975 | L13: =(J13-K13)*1.3 -> 0.381875
A14: TÉRREO | B14: F6 | C14: 1 | D14: 0.25 | E14: 0.5 | F14: 2.35 | I14: =IF(F14<=1,0.6,F14) -> 2.35 | J14: =(D14+I14)*(E14+I14)*(F14)*C14 -> 17.4135 | K14: =J14-D14*E14*F14*C14 -> 17.11975 | L14: =(J14-K14)*1.3 -> 0.381875
A15: TÉRREO | B15: F7 | C15: 1 | D15: 0.25 | E15: 0.5 | F15: 2.35 | I15: =IF(F15<=1,0.6,F15) -> 2.35 | J15: =(D15+I15)*(E15+I15)*(F15)*C15 -> 17.4135 | K15: =J15-D15*E15*F15*C15 -> 17.11975 | L15: =(J15-K15)*1.3 -> 0.381875
A16: TÉRREO | B16: F8 | C16: 1 | D16: 0.25 | E16: 0.5 | F16: 2.35 | I16: =IF(F16<=1,0.6,F16) -> 2.35 | J16: =(D16+I16)*(E16+I16)*(F16)*C16 -> 17.4135 | K16: =J16-D16*E16*F16*C16 -> 17.11975 | L16: =(J16-K16)*1.3 -> 0.381875
A17: TÉRREO | B17: F9 | C17: 1 | D17: 0.25 | E17: 0.5 | F17: 2.35 | I17: =IF(F17<=1,0.6,F17) -> 2.35 | J17: =(D17+I17)*(E17+I17)*(F17)*C17 -> 17.4135 | K17: =J17-D17*E17*F17*C17 -> 17.11975 | L17: =(J17-K17)*1.3 -> 0.381875
A18: TÉRREO | B18: F10 | C18: 1 | D18: 0.25 | E18: 0.5 | F18: 2.35 | I18: =IF(F18<=1,0.6,F18) -> 2.35 | J18: =(D18+I18)*(E18+I18)*(F18)*C18 -> 17.4135 | K18: =J18-D18*E18*F18*C18 -> 17.11975 | L18: =(J18-K18)*1.3 -> 0.381875
A19: TÉRREO | B19: F11 | C19: 1 | D19: 0.25 | E19: 0.5 | F19: 2.35 | I19: =IF(F19<=1,0.6,F19) -> 2.35 | J19: =(D19+I19)*(E19+I19)*(F19)*C19 -> 17.4135 | K19: =J19-D19*E19*F19*C19 -> 17.11975 | L19: =(J19-K19)*1.3 -> 0.381875
A20: TÉRREO | B20: F12 | C20: 1 | D20: 0.25 | E20: 0.5 | F20: 2.35 | I20: =IF(F20<=1,0.6,F20) -> 2.35 | J20: =(D20+I20)*(E20+I20)*(F20)*C20 -> 17.4135 | K20: =J20-D20*E20*F20*C20 -> 17.11975 | L20: =(J20-K20)*1.3 -> 0.381875
A21: TÉRREO | B21: F13 | C21: 1 | D21: 0.25 | E21: 0.5 | F21: 2.35 | I21: =IF(F21<=1,0.6,F21) -> 2.35 | J21: =(D21+I21)*(E21+I21)*(F21)*C21 -> 17.4135 | K21: =J21-D21*E21*F21*C21 -> 17.11975 | L21: =(J21-K21)*1.3 -> 0.381875
... A27: TÉRREO | B27: P22 | C27: 1 | D27: 0.3 | E27: 1.2 | F27: 2.35 | I27: =IF(F27<=1,0.6,F27) -> 2.35 | J27: =(D27+I27)*(E27+I27)*(F27)*C27 -> 22.107625 | K27: =J27-D27*E27*F27*C27 -> 21.261625 | L27: =(J27-K27)*1.3 -> 1.0998
A28: TÉRREO | B28: P10 | C28: 1 | D28: 0.25 | E28: 4.2 | F28: 2.35 | G28: 32.97 | H28: 3.9 | I28: =IF(F28<=1,0.6,F28) -> 2.35 | J28: =(D28+I28)*(E28+I28)*(F28)*C28 -> 40.0205 | K28: =J28-D28*E28*F28*C28 -> 37.553 | L28: =(J28-K28)*1.3 -> 3.20775
A29: TÉRREO | B29: P11 | C29: 1 | D29: 0.25 | E29: 4.2 | F29: 2.35 | I29: =IF(F29<=1,0.6,F29) -> 2.35 | J29: =(D29+I29)*(E29+I29)*(F29)*C29 -> 40.0205 | K29: =J29-D29*E29*F29*C29 -> 37.553 | L29: =(J29-K29)*1.3 -> 3.20775
A30: TÉRREO | B30: P15 | C30: 1 | D30: 0.3 | E30: 1.2 | F30: 2.35 | I30: =IF(F30<=1,0.6,F30) -> 2.35 | J30: =(D30+I30)*(E30+I30)*(F30)*C30 -> 22.107625 | K30: =J30-D30*E30*F30*C30 -> 21.261625 | L30: =(J30-K30)*1.3 -> 1.0998
A31: TÉRREO | B31: P16 | C31: 1 | D31: 0.3 | E31: 1.2 | F31: 2.35 | I31: =IF(F31<=1,0.6,F31) -> 2.35 | J31: =(D31+I31)*(E31+I31)*(F31)*C31 -> 22.107625 | K31: =J31-D31*E31*F31*C31 -> 21.261625 | L31: =(J31-K31)*1.3 -> 1.0998
A32: TÉRREO | B32: P17 | C32: 1 | D32: 0.25 | E32: 2.05 | F32: 3.55 | G32: 24.6 | H32: 3.03 | I32: =IF(F32<=1,0.6,F32) -> 3.55 | J32: =(D32+I32)*(E32+I32)*(F32)*C32 -> 75.544 | K32: =J32-D32*E32*F32*C32 -> 73.724625 | L32: =(J32-K32)*1.3 -> 2.3651875
A33: TÉRREO | B33: P18 | C33: 1 | D33: 0.25 | E33: 4.25 | F33: 3.55 | I33: =IF(F33<=1,0.6,F33) -> 3.55 | J33: =(D33+I33)*(E33+I33)*(F33)*C33 -> 105.222 | K33: =J33-D33*E33*F33*C33 -> 101.45012 | L33: =(J33-K33)*1.3 -> 4.9034375
A34: TÉRREO | B34: P19 | C34: 1 | D34: 0.3 | E34: 1.5 | F34: 2.35 | I34: =IF(F34<=1,0.6,F34) -> 2.35 | J34: =(D34+I34)*(E34+I34)*(F34)*C34 -> 23.975875 | K34: =J34-D34*E34*F34*C34 -> 22.918375 | L34: =(J34-K34)*1.3 -> 1.37475
A35: TÉRREO | B35: P24 | C35: 1 | D35: 0.3 | E35: 1.2 | F35: 2.35 | G35: 14.4 | H35: 1.73 | I35: =IF(F35<=1,0.6,F35) -> 2.35 | J35: =(D35+I35)*(E35+I35)*(F35)*C35 -> 22.107625 | K35: =J35-D35*E35*F35*C35 -> 21.261625 | L35: =(J35-K35)*1.3 -> 1.0998
A36: TÉRREO | B36: P25 | C36: 1 | D36: 0.3 | E36: 1.2 | F36: 2.35 | I36: =IF(F36<=1,0.6,F36) -> 2.35 | J36: =(D36+I36)*(E36+I36)*(F36)*C36 -> 22.107625 | K36: =J36-D36*E36*F36*C36 -> 21.261625 | L36: =(J36-K36)*1.3 -> 1.0998
A37: TÉRREO | B37: P26 | C37: 1 | D37: 0.3 | E37: 1.2 | F37: 2.35 | I37: =IF(F37<=1,0.6,F37) -> 2.35 | J37: =(D37+I37)*(E37+I37)*(F37)*C37 -> 22.107625 | K37: =J37-D37*E37*F37*C37 -> 21.261625 | L37: =(J37-K37)*1.3 -> 1.0998
A38: TÉRREO | B38: P27 | C38: 1 | D38: 0.3 | E38: 1.2 | F38: 2.35 | I38: =IF(F38<=1,0.6,F38) -> 2.35 | J38: =(D38+I38)*(E38+I38)*(F38)*C38 -> 22.107625 | K38: =J38-D38*E38*F38*C38 -> 21.261625 | L38: =(J38-K38)*1.3 -> 1.0998
A39: TÉRREO | B39: P29 | C39: 1 | D39: 0.3 | E39: 1.2 | F39: 2.35 | I39: =IF(F39<=1,0.6,F39) -> 2.35 | J39: =(D39+I39)*(E39+I39)*(F39)*C39 -> 22.107625 | K39: =J39-D39*E39*F39*C39 -> 21.261625 | L39: =(J39-K39)*1.3 -> 1.0998
A40: TÉRREO | B40: P30 | C40: 1 | D40: 0.3 | E40: 1.2 | F40: 2.35 | I40: =IF(F40<=1,0.6,F40) -> 2.35 | J40: =(D40+I40)*(E40+I40)*(F40)*C40 -> 22.107625 | K40: =J40-D40*E40*F40*C40 -> 21.261625 | L40: =(J40-K40)*1.3 -> 1.0998
A41: TÉRREO | B41: P31 | C41: 1 | D41: 0.3 | E41: 1.2 | F41: 2.35 | I41: =IF(F41<=1,0.6,F41) -> 2.35 | J41: =(D41+I41)*(E41+I41)*(F41)*C41 -> 22.107625 | K41: =J41-D41*E41*F41*C41 -> 21.261625 | L41: =(J41-K41)*1.3 -> 1.0998
A42: TOTAL | G42: =SUM(G9:G41) -> 91.77 | H42: =SUM(H9:H41) -> 10.51 | J42: =SUM(J9:J41) -> 828.69037 | K42: =SUM(K9:K41) -> 802.25462 | L42: =SUM(L9:L41) -> 34.366475

Sheet Arm. Fund. Dir
B1: Projeto | C1: =ORÇAMENTO!I4 -> SENSE106
B2: Empresa | C2: =ORÇAMENTO!I5 -> HOLZE EMPREENDIMENTOS
B3: Revisão | C3: R00 - Michelle Furlan - 29/06
A4: ARMAÇÃO FUNDAÇÃO DIRETA
A5: ITEM | C5: QUANT | D5: QUANTIDADE POR ITEM CA-50 - m | K5: CA-60 - m
D6: 6.3 | E6: 8 | F6: 10 | G6: 12.5 | H6: 16 | I6: 20 | J6: 25 | K6: 5 | L6: 0 | M6: 0 | N6: 0 | O6: 0
A7: =Blocos!A8 -> Sense - Blocos de Fundação.dwg
A8: BLOCOS | C8: 1 | F8: 245 | G8: 1780 | H8: 5045 | I8: 14115
A10: PILARES ENTERRADOS | C10: 1 | D10: 285 | E10: 195 | F10: 540 | G10: 0 | H10: 385 | I10: 5295
A12: VIGAS BALDRAME | C12: 1 | D12: 400 | E12: 865 | F12: 740 | G12: 45 | H12: 2920 | I12: 3000
A14: DUTO E CISTERNA | C14: 1 | E14: 2140 | F14: 600 | G14: 570
A16: POÇO DO ELEVADOR | C16: 1 | E16: 72.7
A18: LAJE RADIER | C18: 1 | E18: 3087.3
B19: TOTAL - M | C19: =SUM(D19:O19) -> 42325 | D19: =SUMPRODUCT(D7:D18,$C7:$C18) -> 685 | E19: =SUMPRODUCT(E7:E18,$C7:$C18) -> 6360 | F19: =SUMPRODUCT(F7:F18,$C7:$C18) -> 2125 | G19: =SUMPRODUCT(G7:G18,$C7:$C18) -> 2395 | H19: =SUMPRODUCT(H7:H18,$C7:$C18) -> 8350 | I19: =SUMPRODUCT(I7:I18,$C7:$C18) -> 22410 | J19: =SUMPRODUCT(J7:J16,$C7:$C16) -> 0 | K19: =SUMPRODUCT(K7:K16,$C7:$C16) -> 0 | L19: =SUMPRODUCT(L7:L16,$C7:$C16) -> 0 | M19: =SUMPRODUCT(M7:M16,$C7:$C16) -> 0 | N19: =SUMPRODUCT(N7:N16,$C7:$C16) -> 0 | O19: =SUMPRODUCT(O7:O16,$C7:$C16) -> 0
B20: PESO kg/m | D20: 1 | E20: 1 | F20: 1 | G20: 1 | H20: 1 | I20: 1 | J20: 1 | K20: 1 | L20: 1 | M20: 1 | N20: 1 | O20: 1
B21: TOTAL - kg | C21: =SUM(D21:O21) -> 42325 | D21: =D20*D19 -> 685 | E21: =E20*E19 -> 6360 | F21: =F20*F19 -> 2125 | G21: =G20*G19 -> 2395 | H21: =H20*H19 -> 8350 | I21: =I20*I19 -> 22410 | J21: =J20*J19 -> 0 | K21: =K20*K19 -> 0 | ... O21: =O20*O19 -> 0

Sheet Vigas
A2: EMPREENDIMENTO: | B2: =ORÇAMENTO!I4 -> SENSE106 | I2: REVISÃO: | L2: DATA:
A3: =ORÇAMENTO!G5 -> EMPRESA: | B3: =ORÇAMENTO!I5 -> HOLZE EMPREENDIMENTOS | I3: =ORÇAMENTO!O5 -> R01 - Edileni Silva | L3: =ORÇAMENTO!P5 -> 45608
A4: PEÇA | B4: DIMENSÕES UNITÁRIAS | E4: QUANT | F4: FORMA | J4: CONCRETO | N4: RESUMO - CONCRETO | Q4: RESUMO - FORMAS
B5: LARG | C5: ALT | D5: COMP | F5: FUNDO S/N | G5: Lados | H5: UNIT | I5: TOTAL | J5: UNIT | K5: TOTAL | L5: RESISTÊNCIA | N5: m3 | O5: RESISTÊNCIA | Q5: m2 | R5: PAVIMENTOS
A6: PROJETO: | N6: =IF(O6="","",SUMIF($L$6:$L$103,O6,$K$6:$K$103)) -> 30.77 | O6: 40 MPa - G2 | Q6: =IF(R6="","",SUMIF($L$6:$L$103,R6,$I$6:$I$103)) -> 214.27 | R6: 40 MPa - G2
F7: S | G7: 2 | H7: =IF(F7="s",(B7+(C7*G7))*D7+C7*B7*2,C7*G7*D7+B7*C7*2) -> 0 | I7: =H7*E7 -> 0 | J7: =B7*C7*D7 -> 0 | K7: =J7*E7 -> 0 | L7: 40MPa | N7: =IF(O7="","",SUMIF($L$6:$L$103,O7,$K$6:$K$103)) -> 29.56 | O7: 40 MPa - G3 | Q7: =IF(R7="","",SUMIF($L$6:$L$103,R7,$I$6:$I$103)) -> 204.11 | R7: 40 MPa - G3
F8: S | G8: 2 | H8: =IF(F8="s",(B8+(C8*G8))*D8+C8*B8*2,C8*G8*D8+B8*C8*2) -> 0 | I8: =H8*E8 -> 0 | J8: =B8*C8*D8 -> 0 | K8: =J8*E8 -> 0 | L8: 40MPa | N8: =IF(O8="","",SUMIF($L$6:$L$103,O8,$K$6:$K$103)) -> 29.56 | O8: 40 MPa - G4 | Q8: =IF(R8="","",SUMIF($L$6:$L$103,R8,$I$6:$I$103)) -> 204.11 | R8: 40 MPa - G4
F9: S | G9: 2 | H9: =IF(F9="s",(B9+(C9*G9))*D9+C9*B9*2,C9*G9*D9+B9*C9*2) -> 0 | I9: =H9*E9 -> 0 | J9: =B9*C9*D9 -> 0 | K9: =J9*E9 -> 0 | L9: 40MPa | N9: =IF(O9="","",SUMIF($L$6:$L$103,O9,$K$6:$K$103)) -> 154.39 | O9: 35MPa - Lazer | Q9: =IF(R9="","",SUMIF($L$6:$L$103,R9,$I$6:$I$103)) -> 594.61 | R9: 35MPa - Lazer
F10: S | G10: 2 | H10: =IF(F10="s",(B10+(C10*G10))*D10+C10*B10*2,C10*G10*D10+B10*C10*2) -> 0 | I10: =H10*E10 -> 0 | J10: =B10*C10*D10 -> 0 | K10: =J10*E10 -> 0 | L10: 40MPa | N10: =IF(O10="","",SUMIF($L$6:$L$103,O10,$K$6:$K$103)) -> 244.14 | O10: 35MPa - Tipos | Q10: =IF(R10="","",SUMIF($L$6:$L$103,R10,$I$6:$I$103)) -> 2288.37 | R10: 35MPa - Tipos
H11: =IF(F11="s",(B11+(C11*G11))*D11+C11*B11*2,C11*G11*D11+B11*C11*2) -> 0 | I11: =H11*E11 -> 0 | J11: =B11*C11*D11 -> 0 | K11: =J11*E11 -> 0 | L11: 40MPa | N11: =IF(O11="","",SUMIF($L$6:$L$103,O11,$K$6:$K$103)) -> 12.26 | O11: 35MPa - Cobertura | Q11: =IF(R11="","",SUMIF($L$6:$L$103,R11,$I$6:$I$103)) -> 115.59 | R11: 35MPa - Cobertura
A12: GARAGEM G2 / Sense - Vigas do G02 ao G04 (3x).dwg | N12: =IF(O12="","",SUMIF($L$6:$L$103,O12,$K$6:$K$103)) -> 12.46 | O12: 35MPa - Pav. Técnicos | Q12: =IF(R12="","",SUMIF($L$6:$L$103,R12,$I$6:$I$103)) -> 111.54 | R12: 35MPa - Pav. Técnicos
A13: V1, V2, V3 e V04 | F13: S | G13: 2 | H13: =IF(F13="s",(B13+(C13*G13))*D13+C13*B13*2,C13*G13*D13+B13*C13*2) -> 0 | I13: 23.17 | J13: =B13*C13*D13 -> 0 | K13: 2.55 | L13: 40 MPa - G2 | N13: =SUM(N6:N12) -> 513.14 | O13: =IF(K104=N13,"OK","Conferir") -> OK | Q13: =SUM(Q6:Q12) -> 3732.6 | R13: =IF(I104=Q13,"OK","Conferir") -> OK
A14: V5, V6, V7, V8 e V9 | F14: S | G14: 2 | H14: =IF(F14="s",(B14+(C14*G14))*D14+C14*B14*2,C14*G14*D14+B14*C14*2) -> 0 | I14: 13.87 | J14: =B14*C14*D14 -> 0 | K14: 1.48 | L14: 40 MPa - G2
A15: V10 ~ V15 | F15: S | G15: 2 | H15: =IF(F15="s",(B15+(C15*G15))*D15+C15*B15*2,C15*G15*D15+B15*C15*2) -> 0 | I15: 14.12 | J15: =B15*C15*D15 -> 0 | K15: 1.53 | L15: 40 MPa - G2
A16: V16 ~ V19 | F16: S | G16: 2 | H16: =IF(F16="s",(B16+(C16*G16))*D16+C16*B16*2,C16*G16*D16+B16*C16*2) -> 0 | I16: 16.81 | J16: =B16*C16*D16 -> 0 | K16: 4.2 | L16: 40 MPa - G2
A17: V20 ~ V22 | F17: S | G17: 2 | H17: =IF(F17="s",(B17+(C17*G17))*D17+C17*B17*2,C17*G17*D17+B17*C17*2) -> 0 | I17: 26.19 | J17: =B17*C17*D17 -> 0 | K17: 4.34 | L17: 40 MPa - G2
A18: V23 ~ V26 | F18: S | G18: 2 | H18: =IF(F18="s",(B18+(C18*G18))*D18+C18*B18*2,C18*G18*D18+B18*C18*2) -> 0 | I18: 23.51 | J18: =B18*C18*D18 -> 0 | K18: 2.75 | L18: 40 MPa - G2
A19: V17 ~ V31 | F19: S | G19: 2 | H19: =IF(F19="s",(B19+(C19*G19))*D19+C19*B19*2,C19*G19*D19+B19*C19*2) -> 0 | I19: 15.99 | J19: =B19*C19*D19 -> 0 | K19: 3.71 | L19: 40 MPa - G2
A20: V32 ~ V37 | F20: S | G20: 2 | H20: =IF(F20="s",(B20+(C20*G20))*D20+C20*B20*2,C20*G20*D20+B20*C20*2) -> 0 | I20: 11.62 | J20: =B20*C20*D20 -> 0 | K20: 2.27 | L20: 40 MPa - G2
A21: V38 ~ V42 | F21: S | G21: 2 | H21: =IF(F21="s",(B21+(C21*G21))*D21+C21*B21*2,C21*G21*D21+B21*C21*2) -> 0 | I21: 15.41 | J21: =B21*C21*D21 -> 0 | K21: 2.1 | L21: 40 MPa - G2
A22: V43 ~ V41 | F22: S | G22: 2 | H22: =IF(F22="s",(B22+(C22*G22))*D22+C22*B22*2,C22*G22*D22+B22*C22*2) -> 0 | I22: 18.4 | J22: =B22*C22*D22 -> 0 | K22: 1.87 | L22: 40 MPa - G2
A23: Vigas rampa // Sense - Det.Rampa 01.dwg | F23: S | G23: 2 | H23: =IF(F23="s",(B23+(C23*G23))*D23+C23*B23*2,C23*G23*D23+B23*C23*2) -> 0 | I23: =18.93+16.25 -> 35.18 | J23: =B23*C23*D23 -> 0 | K23: =2.14+1.83 -> 3.97 | L23: 40 MPa - G2
A24: GARAGEM G3 / Sense - Vigas do G02 ao G04 (3x).dwg
A25: V1, V2, V3 e V04 | F25: S | G25: 2 | H25: =IF(F25="s",(B25+(C25*G25))*D25+C25*B25*2,C25*G25*D25+B25*C25*2) -> 0 | I25: 23.17 | J25: =B25*C25*D25 -> 0 | K25: 2.55 | L25: 40 MPa - G3
A26: V5, V6, V7, V8 e V9 | F26: S | G26: 2 | H26: =IF(F26="s",(B26+(C26*G26))*D26+C26*B26*2,C26*G26*D26+B26*C26*2) -> 0 | I26: 13.87 | J26: =B26*C26*D26 -> 0 | K26: 1.48 | L26: 40 MPa - G3
A27: V10 ~ V15 | F27: S | G27: 2 | H27: =IF(F27="s",(B27+(C27*G27))*D27+C27*B27*2,C27*G27*D27+B27*C27*2) -> 0 | I27: 14.12 | J27: =B27*C27*D27 -> 0 | K27: 1.53 | L27: 40 MPa - G3
A28: V16 ~ V19 | F28: S | G28: 2 | H28: =IF(F28="s",(B28+(C28*G28))*D28+C28*B28*2,C28*G28*D28+B28*C28*2) -> 0 | I28: 16.81 | J28: =B28*C28*D28 -> 0 | K28: 4.2 | L28: 40 MPa - G3
A29: V20 ~ V22 | F29: S | G29: 2 | H29: =IF(F29="s",(B29+(C29*G29))*D29+C29*B29*2,C29*G29*D29+B29*C29*2) -> 0 | I29: 26.19 | J29: =B29*C29*D29 -> 0 | K29: 4.34 | L29: 40 MPa - G3
A30: V23 ~ V26 | F30: S | G30: 2 | H30: =IF(F30="s",(B30+(C30*G30))*D30+C30*B30*2,C30*G30*D30+B30*C30*2) -> 0 | I30: 23.51 | J30: =B30*C30*D30 -> 0 | K30: 2.75 | L30: 40 MPa - G3
A31: V17 ~ V31 | F31: S | G31: 2 | H31: =IF(F31="s",(B31+(C31*G31))*D31+C31*B31*2,C31*G31*D31+B31*C31*2) -> 0 | I31: 15.99 | J31: =B31*C31*D31 -> 0 | K31: 3.71 | L31: 40 MPa - G3
A32: V32 ~ V37 | F32: S | G32: 2 | H32: =IF(F32="s",(B32+(C32*G32))*D32+C32*B32*2,C32*G32*D32+B32*C32*2) -> 0 | I32: 11.62 | J32: =B32*C32*D32 -> 0 | K32: 2.27 | L32: 40 MPa - G3
A33: V38 ~ V42 | F33: S | G33: 2 | H33: =IF(F33="s",(B33+(C33*G33))*D33+C33*B33*2,C33*G33*D33+B33*C33*2) -> 0 | I33: 15.41 | J33: =B33*C33*D33 -> 0 | K33: 2.1 | L33: 40 MPa - G3
A34: V43 ~ V41 | F34: S | G34: 2 | H34: =IF(F34="s",(B34+(C34*G34))*D34+C34*B34*2,C34*G34*D34+B34*C34*2) -> 0 | I34: 18.4 | J34: =B34*C34*D34 -> 0 | K34: 1.87 | L34: 40 MPa - G3
A35: Vigas rampa // Sense - Det.Rampa 02(x2).dwg | F35: S | G35: 2 | H35: =IF(F35="s",(B35+(C35*G35))*D35+C35*B35*2,C35*G35*D35+B35*C35*2) -> 0 | I35: 25.02 | J35: =B35*C35*D35 -> 0 | K35: 2.76 | L35: 40 MPa - G3
A36: GARAGEM G4 / Sense - Vigas do G02 ao G04 (3x).dwg
A37: V1, V2, V3 e V04 | F37: S | G37: 2 | H37: =IF(F37="s",(B37+(C37*G37))*D37+C37*B37*2,C37*G37*D37+B37*C37*2) -> 0 | I37: 23.17 | J37: =B37*C37*D37 -> 0 | K37: 2.55 | L37: 40 MPa - G4
A38: V5, V6, V7, V8 e V9 | F38: S | G38: 2 | H38: =IF(F38="s",(B38+(C38*G38))*D38+C38*B38*2,C38*G38*D38+B38*C38*2) -> 0 | I38: 13.87 | J38: =B38*C38*D38 -> 0 | K38: 1.48 | L38: 40 MPa - G4
A39: V10 ~ V15 | F39: S | G39: 2 | H39: =IF(F39="s",(B39+(C39*G39))*D39+C39*B39*2,C39*G39*D39+B39*C39*2) -> 0 | I39: 14.12 | J39: =B39*C39*D39 -> 0 | K39: 1.53 | L39: 40 MPa - G4
A40: V16 ~ V19 | F40: S | G40: 2 | H40: =IF(F40="s",(B40+(C40*G40))*D40+C40*B40*2,C40*G40*D40+B40*C40*2) -> 0 | I40: 16.81 | J40: =B40*C40*D40 -> 0 | K40: 4.2 | L40: 40 MPa - G4
A41: V20 ~ V22 | F41: S | G41: 2 | H41: =IF(F41="s",(B41+(C41*G41))*D41+C41*B41*2,C41*G41*D41+B41*C41*2) -> 0 | I41: 26.19 | J41: =B41*C41*D41 -> 0 | K41: 4.34 | L41: 40 MPa - G4
A42: V23 ~ V26 | F42: S | G42: 2 | H42: =IF(F42="s",(B42+(C42*G42))*D42+C42*B42*2,C42*G42*D42+B42*C42*2) -> 0 | I42: 23.51 | J42: =B42*C42*D42 -> 0 | K42: 2.75 | L42: 40 MPa - G4
A43: V17 ~ V31 | F43: S | G43: 2 | H43: =IF(F43="s",(B43+(C43*G43))*D43+C43*B43*2,C43*G43*D43+B43*C43*2) -> 0 | I43: 15.99 | J43: =B43*C43*D43 -> 0 | K43: 3.71 | L43: 40 MPa - G4
A44: V32 ~ V37 | F44: S | G44: 2 | H44: =IF(F44="s",(B44+(C44*G44))*D44+C44*B44*2,C44*G44*D44+B44*C44*2) -> 0 | I44: 11.62 | J44: =B44*C44*D44 -> 0 | K44: 2.27 | L44: 40 MPa - G4
A45: V38 ~ V42 | F45: S | G45: 2 | H45: =IF(F45="s",(B45+(C45*G45))*D45+C45*B45*2,C45*G45*D45+B45*C45*2) -> 0 | I45: 15.41 | J45: =B45*C45*D45 -> 0 | K45: 2.1 | L45: 40 MPa - G4
A46: V43 ~ V41 | F46: S | G46: 2 | H46: =IF(F46="s",(B46+(C46*G46))*D46+C46*B46*2,C46*G46*D46+B46*C46*2) -> 0 | I46: 18.4 | J46: =B46*C46*D46 -> 0 | K46: 1.87 | L46: 40 MPa - G4
A47: Vigas rampa // Sense - Det.Rampa 02(x2).dwg | F47: S | G47: 2 | H47: =IF(F47="s",(B47+(C47*G47))*D47+C47*B47*2,C47*G47*D47+B47*C47*2) -> 0 | I47: 25.02 | J47: =B47*C47*D47 -> 0 | K47: 2.76 | L47: 40 MPa - G4
A49: LAZER
A50: Sense - Vigas do Lazer - Folha 1 | F50: S | G50: 2 | H50: =IF(F50="s",(B50+(C50*G50))*D50+C50*B50*2,C50*G50*D50+B50*C50*2) -> 0 | I50: 22.66 | J50: =B50*C50*D50 -> 0 | K50: 2.27 | L50: 35MPa - Lazer
A51: Sense - Vigas do Lazer - Folha 2 | F51: S | G51: 2 | H51: =IF(F51="s",(B51+(C51*G51))*D51+C51*B51*2,C51*G51*D51+B51*C51*2) -> 0 | I51: 31.46 | J51: =B51*C51*D51 -> 0 | K51: 11.94 | L51: 35MPa - Lazer
A52: Sense - Vigas do Lazer - Folha 3 | F52: S | G52: 2 | H52: =IF(F52="s",(B52+(C52*G52))*D52+C52*B52*2,C52*G52*D52+B52*C52*2) -> 0 | I52: 16.55 | J52: =B52*C52*D52 -> 0 | K52: 1.56 | L52: 35MPa - Lazer
A53: Sense - Vigas do Lazer - Folha 4 | F53: S | G53: 2 | H53: =IF(F53="s",(B53+(C53*G53))*D53+C53*B53*2,C53*G53*D53+B53*C53*2) -> 0 | I53: 31.31 | J53: =B53*C53*D53 -> 0 | K53: 11.74 | L53: 35MPa - Lazer
A54: Sense - Vigas do Lazer - Folha 5 | F54: S | G54: 2 | H54: =IF(F54="s",(B54+(C54*G54))*D54+C54*B54*2,C54*G54*D54+B54*C54*2) -> 0 | I54: 27.37 | J54: =B54*C54*D54 -> 0 | K54: 2.96 | L54: 35MPa - Lazer
A55: Sense - Vigas do Lazer - Folha 6 | F55: S | G55: 2 | H55: =IF(F55="s",(B55+(C55*G55))*D55+C55*B55*2,C55*G55*D55+B55*C55*2) -> 0 | I55: 43.96 | J55: =B55*C55*D55 -> 0 | K55: 17.42 | L55: 35MPa - Lazer
A56: Sense - Vigas do Lazer - Folha 7 | F56: S | G56: 2 | H56: =IF(F56="s",(B56+(C56*G56))*D56+C56*B56*2,C56*G56*D56+B56*C56*2) -> 0 | I56: 17.86 | J56: =B56*C56*D56 -> 0 | K56: 2.11 | L56: 35MPa - Lazer
A57: Sense - Vigas do Lazer - Folha 8 | F57: S | G57: 2 | H57: =IF(F57="s",(B57+(C57*G57))*D57+C57*B57*2,C57*G57*D57+B57*C57*2) -> 0 | I57: 64.53 | J57: =B57*C57*D57 -> 0 | K57: 34.14 | L57: 35MPa - Lazer
A58: Sense - Vigas do Lazer - Folha 9 | F58: S | G58: 2 | H58: =IF(F58="s",(B58+(C58*G58))*D58+C58*B58*2,C58*G58*D58+B58*C58*2) -> 0 | I58: 63.51 | J58: =B58*C58*D58 -> 0 | K58: 29.19 | L58: 35MPa - Lazer
A59: Sense - Vigas do Lazer - Folha 10 | F59: S | G59: 2 | H59: =IF(F59="s",(B59+(C59*G59))*D59+C59*B59*2,C59*G59*D59+B59*C59*2) -> 0 | I59: 27.81 | J59: =B59*C59*D59 -> 0 | K59: 3.21 | L59: 35MPa - Lazer
A60: Sense - Vigas do Lazer - Folha 11 | F60: S | G60: 2 | H60: =IF(F60="s",(B60+(C60*G60))*D60+C60*B60*2,C60*G60*D60+B60*C60*2) -> 0 | I60: 23.06 | J60: =B60*C60*D60 -> 0 | K60: 2.49 | L60: 35MPa - Lazer
A61: Sense - Vigas do Lazer - Folha 12 | F61: S | G61: 2 | H61: =IF(F61="s",(B61+(C61*G61))*D61+C61*B61*2,C61*G61*D61+B61*C61*2) -> 0 | I61: 34.92 | J61: =B61*C61*D61 -> 0 | K61: 14.56 | L61: 35MPa - Lazer
... A66: Sense - Vigas do Lazer - Folha 17 | F66: S | G66: 2 | H66: =IF(F66="s",(B66+(C66*G66))*D66+C66*B66*2,C66*G66*D66+B66*C66*2) -> 0 | I66: 50.73 | J66: =B66*C66*D66 -> 0 | K66: 5.11 | L66: 35MPa - Lazer
A68: TIPOS
A69: Sense - Vigas do Tipo 01 - Folha 1 | F69: S | G69: 2 | H69: =IF(F69="s",(B69+(C69*G69))*D69+C69*B69*2,C69*G69*D69+B69*C69*2) -> 0 | I69: 22.88 | J69: =B69*C69*D69 -> 0 | K69: 1.91 | L69: 35MPa - Tipos
A70: Sense - Vigas do Tipo 01 - Folha 2 | F70: S | G70: 2 | H70: =IF(F70="s",(B70+(C70*G70))*D70+C70*B70*2,C70*G70*D70+B70*C70*2) -> 0 | I70: 15.74 | J70: =B70*C70*D70 -> 0 | K70: 1.39 | L70: 35MPa - Tipos
A71: Sense - Vigas do Tipo 01 - Folha 3 | F71: S | G71: 2 | H71: =IF(F71="s",(B71+(C71*G71))*D71+C71*B71*2,C71*G71*D71+B71*C71*2) -> 0 | I71: 11.13 | J71: =B71*C71*D71 -> 0 | K71: 2.78 | L71: 35MPa - Tipos
A72: Sense - Vigas do Tipo 01 - Folha 4 | F72: S | G72: 2 | H72: =IF(F72="s",(B72+(C72*G72))*D72+C72*B72*2,C72*G72*D72+B72*C72*2) -> 0 | I72: 30.34 | J72: =B72*C72*D72 -> 0 | K72: 2.47 | L72: 35MPa - Tipos
A73: Sense - Vigas do Tipo 01 - Folha 5 | F73: S | G73: 2 | H73: =IF(F73="s",(B73+(C73*G73))*D73+C73*B73*2,C73*G73*D73+B73*C73*2) -> 0 | I73: 7.95 | J73: =B73*C73*D73 -> 0 | K73: 1.51 | L73: 35MPa - Tipos
A74: Sense - Vigas do Tipo 01 - Folha 6 | F74: S | G74: 2 | H74: =IF(F74="s",(B74+(C74*G74))*D74+C74*B74*2,C74*G74*D74+B74*C74*2) -> 0 | I74: 20.46 | J74: =B74*C74*D74 -> 0 | K74: 1.71 | L74: 35MPa - Tipos
A76: Sense - Vigas do Tipo 02 ao Tipo 12 (11x) - Folha 1 | E76: 11 | F76: S | G76: 2 | H76: 22.88 | I76: =H76*E76 -> 251.68 | J76: 1.91 | K76: =J76*E76 -> 21.01 | L76: 35MPa - Tipos
A77: Sense - Vigas do Tipo 02 ao Tipo 12 (11x) - Folha 2 | E77: 11 | F77: S | G77: 2 | H77: 17.75 | I77: =H77*E77 -> 195.25 | J77: 1.57 | K77: =J77*E77 -> 17.27 | L77: 35MPa - Tipos
A78: Sense - Vigas do Tipo 02 ao Tipo 12 (11x) - Folha 3 | E78: 11 | F78: S | G78: 2 | H78: 15.35 | I78: =H78*E78 -> 168.85 | J78: 3.06 | K78: =J78*E78 -> 33.66 | L78: 35MPa - Tipos
A79: Sense - Vigas do Tipo 02 ao Tipo 12 (11x) - Folha 4 | E79: 11 | F79: S | G79: 2 | H79: 30.34 | I79: =H79*E79 -> 333.74 | J79: 2.47 | K79: =J79*E79 -> 27.17 | L79: 35MPa - Tipos
A80: Sense - Vigas do Tipo 02 ao Tipo 12 (11x) - Folha 5 | E80: 11 | F80: S | G80: 2 | H80: 7.95 | I80: =H80*E80 -> 87.45 | J80: 1.51 | K80: =J80*E80 -> 16.61 | L80: 35MPa - Tipos
A81: Sense - Vigas do Tipo 02 ao Tipo 12 (11x) - Folha 6 | E81: 11 | F81: S | G81: 2 | H81: 20.46 | I81: =H81*E81 -> 225.06 | J81: 1.71 | K81: =J81*E81 -> 18.81 | L81: 35MPa - Tipos
A83: Sense - Vigas do Tipo 13 ao Tipo 20 (8x) - Folha 1 | E83: 8 | F83: S | G83: 2 | H83: 22.88 | I83: =H83*E83 -> 183.04 | J83: 1.91 | K83: =J83*E83 -> 15.28 | L83: 35MPa - Tipos
A84: Sense - Vigas do Tipo 13 ao Tipo 20 (8x) - Folha 2 | E84: 8 | F84: S | G84: 2 | H84: 17.75 | I84: =H84*E84 -> 142 | J84: 1.57 | K84: =J84*E84 -> 12.56 | L84: 35MPa - Tipos
A85: Sense - Vigas do Tipo 13 ao Tipo 20 (8x) - Folha 3 | E85: 8 | F85: S | G85: 2 | H85: 15.35 | I85: =H85*E85 -> 122.8 | J85: 3.06 | K85: =J85*E85 -> 24.48 | L85: 35MPa - Tipos
A86: Sense - Vigas do Tipo 13 ao Tipo 20 (8x) - Folha 4 | E86: 8 | F86: S | G86: 2 | H86: 30.34 | I86: =H86*E86 -> 242.72 | J86: 2.47 | K86: =J86*E86 -> 19.76 | L86: 35MPa - Tipos
A87: Sense - Vigas do Tipo 13 ao Tipo 20 (8x) - Folha 5 | E87: 8 | F87: S | G87: 2 | H87: 7.95 | I87: =H87*E87 -> 63.6 | J87: 1.51 | K87: =J87*E87 -> 12.08 | L87: 35MPa - Tipos
A88: Sense - Vigas do Tipo 13 ao Tipo 20 (8x) - Folha 6 | E88: 8 | F88: S | G88: 2 | H88: 20.46 | I88: =H88*E88 -> 163.68 | J88: 1.71 | K88: =J88*E88 -> 13.68 | L88: 35MPa - Tipos
A90: COBERTURA // Sense - Vigas da Cobertura
A91: Sense - Vigas da Cobertura - Folha 1 | F91: S | G91: 2 | H91: =IF(F91="s",(B91+(C91*G91))*D91+C91*B91*2,C91*G91*D91+B91*C91*2) -> 0 | I91: 28.29 | J91: =B91*C91*D91 -> 0 | K91: 2.26 | L91: 35MPa - Cobertura
A92: Sense - Vigas da Cobertura - Folha 2 | F92: S | G92: 2 | H92: =IF(F92="s",(B92+(C92*G92))*D92+C92*B92*2,C92*G92*D92+B92*C92*2) -> 0 | I92: 13.2 | J92: =B92*C92*D92 -> 0 | K92: 1.25 | L92: 35MPa - Cobertura
A93: Sense - Vigas da Cobertura - Folha 3 | F93: S | G93: 2 | H93: =IF(F93="s",(B93+(C93*G93))*D93+C93*B93*2,C93*G93*D93+B93*C93*2) -> 0 | I93: 15.35 | J93: =B93*C93*D93 -> 0 | K93: 3.06 | L93: 35MPa - Cobertura
A94: Sense - Vigas da Cobertura - Folha 4 | F94: S | G94: 2 | H94: =IF(F94="s",(B94+(C94*G94))*D94+C94*B94*2,C94*G94*D94+B94*C94*2) -> 0 | I94: 30.34 | J94: =B94*C94*D94 -> 0 | K94: 2.47 | L94: 35MPa - Cobertura
A95: Sense - Vigas da Cobertura - Folha 5 | F95: S | G95: 2 | H95: =IF(F95="s",(B95+(C95*G95))*D95+C95*B95*2,C95*G95*D95+B95*C95*2) -> 0 | I95: 6.99 | J95: =B95*C95*D95 -> 0 | K95: 1.44 | L95: 35MPa - Cobertura
A96: Sense - Vigas da Cobertura - Folha 6 | F96: S | G96: 2 | H96: =IF(F96="s",(B96+(C96*G96))*D96+C96*B96*2,C96*G96*D96+B96*C96*2) -> 0 | I96: 21.42 | J96: =B96*C96*D96 -> 0 | K96: 1.78 | L96: 35MPa - Cobertura
A98: PAV. TÉC // Sense - Vigas dos Pav.Tecnicos
A99: Sense - Vigas dos Pav.Tecnicos - Folha 1 | F99: S | G99: 2 | H99: =IF(F99="s",(B99+(C99*G99))*D99+C99*B99*2,C99*G99*D99+B99*C99*2) -> 0 | I99: 2.84 | J99: =B99*C99*D99 -> 0 | K99: 0.29 | L99: 35MPa - Pav. Técnicos
A100: Sense - Vigas dos Pav.Tecnicos - Folha 2 | F100: S | G100: 2 | H100: =IF(F100="s",(B100+(C100*G100))*D100+C100*B100*2,C100*G100*D100+B100*C100*2) -> 0 | I100: 49.46 | J100: =B100*C100*D100 -> 0 | K100: 5.31 | L100: 35MPa - Pav. Técnicos
A101: Sense - Vigas dos Pav.Tecnicos - Folha 3 | F101: S | G101: 2 | H101: =IF(F101="s",(B101+(C101*G101))*D101+C101*B101*2,C101*G101*D101+B101*C101*2) -> 0 | I101: 31.69 | J101: =B101*C101*D101 -> 0 | K101: 3.94 | L101: 35MPa - Pav. Técnicos
A102: Sense - Vigas dos Pav.Tecnicos - Folha 4 | F102: S | G102: 2 | H102: =IF(F102="s",(B102+(C102*G102))*D102+C102*B102*2,C102*G102*D102+B102*C102*2) -> 0 | I102: 27.55 | J102: =B102*C102*D102 -> 0 | K102: 2.92 | L102: 35MPa - Pav. Técnicos
A104: TOTAL | I104: =SUM(I6:I103) -> 3732.6 | K104: =SUM(K6:K103) -> 513.14

Sheet Pilares
A2: EMPREENDIMENTO: | B2: =ORÇAMENTO!I4 -> SENSE106 | H2: REVISÃO: | K2: DATA:
A3: =ORÇAMENTO!G5 -> EMPRESA: | B3: =ORÇAMENTO!I5 -> HOLZE EMPREENDIMENTOS | H3: =ORÇAMENTO!O5 -> R01 - Edileni Silva | K3: =ORÇAMENTO!P5 -> 45608
A4: PEÇA | B4: DIMENSÕES UNITÁRIAS - METROS | E4: QUANT | F4: FORMA | I4: CONCRETO | M4: RESUMO - CONCRETO | P4: RESUMO - FORMAS
B5: SEÇÃO 1 | C5: SEÇÃO 2 | D5: ALTURA | F5: LADOS | G5: UNIT | H5: TOTAL | I5: UNIT | J5: TOTAL | K5: RESISTÊNCIA | M5: m3 | N5: RESISTÊNCIA | P5: m2 | Q5: PAVIMENTOS
A6: TÉRREO | M6: =IF(N6="","",SUMIF($K$6:$K$61,N6,$J$6:$J$61)) -> 0 | N6: 40MPa - Térreo | P6: =IF(Q6="","",SUMIF($K$6:$K$61,Q6,$H$6:$H$61)) -> 0 | Q6: 40MPa - Térreo
F7: 0 | M7: =IF(N7="","",SUMIF($K$6:$K$61,N7,$J$6:$J$61)) -> 41.61 | N7: 40MPa - G2 | P7: =IF(Q7="","",SUMIF($K$6:$K$61,Q7,$H$6:$H$61)) -> 381.74 | Q7: 40MPa - G2
A8: GARAGEM G2 | M8: =IF(N8="","",SUMIF($K$6:$K$61,N8,$J$6:$J$61)) -> 30.26 | N8: 40MPa - G3 | P8: =IF(Q8="","",SUMIF($K$6:$K$61,Q8,$H$6:$H$61)) -> 272.63 | Q8: 40MPa - G3
A9: Sense - Pilares do G02 - Folha 1.pdf | F9: 4 | G9: =IF(F9=2,C9*2*D9,IF(F9=4,(B9+C9)*2*D9,0)) -> 0 | H9: 142.56 | I9: =B9*D9*C9 -> 0 | J9: 13.07 | K9: 40MPa - G2 | M9: =IF(N9="","",SUMIF($K$6:$K$61,N9,$J$6:$J$61)) -> 30.26 | N9: 40MPa - G4 | P9: =IF(Q9="","",SUMIF($K$6:$K$61,Q9,$H$6:$H$61)) -> 272.63 | Q9: 40MPa - G4
A10: Sense - Pilares do G02 - Folha 2.pdf | F10: 4 | G10: =IF(F10=2,C10*2*D10,IF(F10=4,(B10+C10)*2*D10,0)) -> 0 | H10: 88.7 | I10: =B10*D10*C10 -> 0 | J10: 10.35 | K10: 40MPa - G2 | M10: =IF(N10="","",SUMIF($K$6:$K$61,N10,$J$6:$J$61)) -> 37.7 | N10: 40MPa - Lazer | P10: =IF(Q10="","",SUMIF($K$6:$K$61,Q10,$H$6:$H$61)) -> 345.99 | Q10: 40MPa - Lazer
A11: Sense - Pilares do G02 - Folha 3.pdf | F11: 4 | G11: =IF(F11=2,C11*2*D11,IF(F11=4,(B11+C11)*2*D11,0)) -> 0 | H11: 150.48 | I11: =B11*D11*C11 -> 0 | J11: 18.19 | K11: 40MPa - G2 | M11: =IF(N11="","",SUMIF($K$6:$K$61,N11,$J$6:$J$61)) -> 504.28 | N11: 35MPa - Tipos | P11: =IF(Q11="","",SUMIF($K$6:$K$61,Q11,$H$6:$H$61)) -> 4413.15 | Q11: 35MPa - Tipos
M12: =IF(N12="","",SUMIF($K$6:$K$61,N12,$J$6:$J$61)) -> 25.11 | N12: 35MPa - Cobertura | P12: =IF(Q12="","",SUMIF($K$6:$K$61,Q12,$H$6:$H$61)) -> 220.01 | Q12: 35MPa - Cobertura
A13: GARAGEM G3 | M13: =IF(N13="","",SUMIF($K$6:$K$61,N13,$J$6:$J$61)) -> 24.97 | N13: 35MPa - Pav. Tec. | P13: =IF(Q13="","",SUMIF($K$6:$K$61,Q13,$H$6:$H$61)) -> 215.22 | Q13: 35MPa - Pav. Tec.
A14: Sense - Pilares do G03 - Folha 1.pdf | F14: 4 | G14: =IF(F14=2,C14*2*D14,IF(F14=4,(B14+C14)*2*D14,0)) -> 0 | H14: 133.34 | I14: =B14*D14*C14 -> 0 | J14: 12.82 | K14: 40MPa - G3 | M14: =SUM(M6:M13) -> 694.19 | N14: =IF(J61=M14,"OK","Conferir") -> OK | P14: =SUM(P6:P13) -> 6121.37 | Q14: =IF(H61=P14,"OK","Conferir") -> OK
A15: Sense - Pilares do G03 - Folha 2.pdf | F15: 4 | G15: =IF(F15=2,C15*2*D15,IF(F15=4,(B15+C15)*2*D15,0)) -> 0 | H15: 33.88 | I15: =B15*D15*C15 -> 0 | J15: 4.5 | K15: 40MPa - G3
A16: Sense - Pilares do G03 - Folha 3.pdf | F16: 4 | G16: =IF(F16=2,C16*2*D16,IF(F16=4,(B16+C16)*2*D16,0)) -> 0 | H16: 105.41 | I16: =B16*D16*C16 -> 0 | J16: 12.94 | K16: 40MPa - G3
A18: GARAGEM G4
A19: Sense - Pilares do G04 - Folha 1.pdf | F19: 4 | G19: =IF(F19=2,C19*2*D19,IF(F19=4,(B19+C19)*2*D19,0)) -> 0 | H19: 133.34 | I19: =B19*D19*C19 -> 0 | J19: 12.82 | K19: 40MPa - G4
A20: Sense - Pilares do G04 - Folha 2.pdf | F20: 4 | G20: =IF(F20=2,C20*2*D20,IF(F20=4,(B20+C20)*2*D20,0)) -> 0 | H20: 33.88 | I20: =B20*D20*C20 -> 0 | J20: 4.5 | K20: 40MPa - G4
A21: Sense - Pilares do G04 - Folha 3.pdf | F21: 4 | G21: =IF(F21=2,C21*2*D21,IF(F21=4,(B21+C21)*2*D21,0)) -> 0 | H21: 105.41 | I21: =B21*D21*C21 -> 0 | J21: 12.94 | K21: 40MPa - G4
A23: LAZER
A24: Sense - Pilares do Lazer - Folha 1.pdf | F24: 4 | G24: =IF(F24=2,C24*2*D24,IF(F24=4,(B24+C24)*2*D24,0)) -> 0 | H24: 166.23 | I24: =B24*D24*C24 -> 0 | J24: 15.97 | K24: 40MPa - Lazer
A25: Sense - Pilares do Lazer - Folha 2.pdf | F25: 4 | G25: =IF(F25=2,C25*2*D25,IF(F25=4,(B25+C25)*2*D25,0)) -> 0 | H25: 48.6 | I25: =B25*D25*C25 -> 0 | J25: 5.63 | K25: 40MPa - Lazer
A26: Sense - Pilares do Lazer - Folha 3.pdf | F26: 4 | G26: =IF(F26=2,C26*2*D26,IF(F26=4,(B26+C26)*2*D26,0)) -> 0 | H26: 87.96 | I26: =B26*D26*C26 -> 0 | J26: 10.92 | K26: 40MPa - Lazer
A27: Sense - Pilares do Lazer - Folha 4.pdf | F27: 4 | G27: =IF(F27=2,C27*2*D27,IF(F27=4,(B27+C27)*2*D27,0)) -> 0 | H27: 43.2 | I27: =B27*D27*C27 -> 0 | J27: 5.18 | K27: 40MPa - Lazer
A28: TIPOS
A29: Sense - Pilares do Tipo 01 - Folha 1 | E29: 1 | F29: 4 | G29: 72.58 | H29: =E29*G29 -> 72.58 | I29: 8.46 | J29: =I29*E29 -> 8.46 | K29: 35MPa - Tipos
A30: Sense - Pilares do Tipo 01 - Folha 2 | E30: 1 | F30: 4 | G30: 98.17 | H30: =E30*G30 -> 98.17 | I30: 10.98 | J30: =I30*E30 -> 10.98 | K30: 35MPa - Tipos
A31: Sense - Pilares do Tipo 01 - Folha 3 | E31: 1 | F31: 4 | G31: 62.21 | H31: =E31*G31 -> 62.21 | I31: 7.14 | J31: =I31*E31 -> 7.14 | K31: 35MPa - Tipos
A33: Sense - Pilares do Tipo 02 - Folha 1 | E33: 1 | F33: 4 | G33: 68.54 | H33: =E33*G33 -> 68.54 | I33: 7.99 | J33: =I33*E33 -> 7.99 | K33: 35MPa - Tipos
A34: Sense - Pilares do Tipo 02 - Folha 2 | E34: 1 | F34: 4 | G34: 92.72 | H34: =E34*G34 -> 92.72 | I34: 10.98 | J34: =I34*E34 -> 10.98 | K34: 35MPa - Tipos
A35: Sense - Pilares do Tipo 02 - Folha 3 | E35: 1 | F35: 4 | G35: 58.75 | H35: =E35*G35 -> 58.75 | I35: 6.75 | J35: =I35*E35 -> 6.75 | K35: 35MPa - Tipos
A37: Sense - Pilares do Tipo 03 - Folha 1 | E37: 1 | F37: 4 | G37: 68.54 | H37: =E37*G37 -> 68.54 | I37: 7.99 | J37: =I37*E37 -> 7.99 | K37: 35MPa - Tipos
A38: Sense - Pilares do Tipo 03 - Folha 2 | E38: 1 | F38: 4 | G38: 92.72 | H38: =E38*G38 -> 92.72 | I38: 10.37 | J38: =I38*E38 -> 10.37 | K38: 35MPa - Tipos
A39: Sense - Pilares do Tipo 03 - Folha 3 | E39: 1 | F39: 4 | G39: 58.75 | H39: =E39*G39 -> 58.75 | I39: 6.75 | J39: =I39*E39 -> 6.75 | K39: 35MPa - Tipos
A41: Sense - Pilares do Tipo 04 - Folha 1 | E41: 1 | F41: 4 | G41: 68.54 | H41: =E41*G41 -> 68.54 | I41: 7.99 | J41: =I41*E41 -> 7.99 | K41: 35MPa - Tipos
A42: Sense - Pilares do Tipo 04 - Folha 2 | E42: 1 | F42: 4 | G42: 92.72 | H42: =E42*G42 -> 92.72 | I42: 10.37 | J42: =I42*E42 -> 10.37 | K42: 35MPa - Tipos
A43: Sense - Pilares do Tipo 04 - Folha 3 | E43: 1 | F43: 4 | G43: 58.75 | H43: =E43*G43 -> 58.75 | I43: 6.75 | J43: =I43*E43 -> 6.75 | K43: 35MPa - Tipos
... A47: Sense - Pilares do Tipo 05 - Folha 3 | E47: 16 | F47: 4 | G47: 58.75 | H47: =E47*G47 -> 940 | I47: 6.75 | J47: =I47*E47 -> 108 | K47: 35MPa - Tipos
A49: COBERTURA
A50: Sense - Pilares da Cobertura - Folha 1 | F50: 4 | G50: =IF(F50=2,C50*2*D50,IF(F50=4,(B50+C50)*2*D50,0)) -> 0 | H50: 68.54 | I50: =B50*D50*C50 -> 0 | J50: 7.99 | K50: 35MPa - Cobertura
A51: Sense - Pilares da Cobertura - Folha 2 | F51: 4 | G51: =IF(F51=2,C51*2*D51,IF(F51=4,(B51+C51)*2*D51,0)) -> 0 | H51: 77.42 | I51: =B51*D51*C51 -> 0 | J51: 8.84 | K51: 35MPa - Cobertura
A52: Sense - Pilares da Cobertura - Folha 3 | F52: 4 | G52: =IF(F52=2,C52*2*D52,IF(F52=4,(B52+C52)*2*D52,0)) -> 0 | H52: 74.05 | I52: =B52*D52*C52 -> 0 | J52: 8.28 | K52: 35MPa - Cobertura
A54: PAV. TÉC
A55: Sense - Pilares dos Pav.Tecnicos - Folha 1 | F55: 4 | G55: =IF(F55=2,C55*2*D55,IF(F55=4,(B55+C55)*2*D55,0)) -> 0 | H55: 22.64 | I55: =B55*D55*C55 -> 0 | J55: 2.46 | K55: 35MPa - Pav. Tec.
A56: Sense - Pilares dos Pav.Tecnicos - Folha 2 | F56: 4 | G56: =IF(F56=2,C56*2*D56,IF(F56=4,(B56+C56)*2*D56,0)) -> 0 | H56: 90.72 | I56: =B56*D56*C56 -> 0 | J56: 10.58 | K56: 35MPa - Pav. Tec.
A57: Sense - Pilares dos Pav.Tecnicos - Folha 3 | F57: 4 | G57: =IF(F57=2,C57*2*D57,IF(F57=4,(B57+C57)*2*D57,0)) -> 0 | H57: 45.92 | I57: =B57*D57*C57 -> 0 | J57: 5.36 | K57: 35MPa - Pav. Tec.
A58: Sense - Pilares dos Pav.Tecnicos - Folha 4 | F58: 4 | G58: =IF(F58=2,C58*2*D58,IF(F58=4,(B58+C58)*2*D58,0)) -> 0 | H58: 19.8 | I58: =B58*D58*C58 -> 0 | J58: 2.56 | K58: 35MPa - Pav. Tec.
A59: Sense - Pilares dos Pav.Tecnicos - Folha 5 | F59: 4 | G59: =IF(F59=2,C59*2*D59,IF(F59=4,(B59+C59)*2*D59,0)) -> 0 | H59: 36.14 | I59: =B59*D59*C59 -> 0 | J59: 4.01 | K59: 35MPa - Pav. Tec.
A61: TOTAL GERAL | H61: =SUM(H6:H60) -> 6121.37 | I61: m² | J61: =SUM(J6:J60) -> 694.19 | K61: m³

Sheet Lajes
A2: EMPREENDIMENTO: | B2: =ORÇAMENTO!I4 -> SENSE106 | L2: REVISÃO: | N2: DATA:
A3: =ORÇAMENTO!G5 -> EMPRESA: | B3: =ORÇAMENTO!I5 -> HOLZE EMPREENDIMENTOS | L3: =ORÇAMENTO!O5 -> R01 - Edileni Silva | N3: =ORÇAMENTO!P5 -> 45608
A4: PROJETO | B4: PEÇA | C4: DIMENSÕES UNITÁRIAS | G4: FORMA | J4: CONCRETO | M4: LAJE / MOLDE | N4: IMAGENS LEVANTAMENTO | P4: RESUMO - CONCRETO | S4: RESUMO - FORMAS
C5: ÁREA m² | D5: PERÍMETRO m | E5: ALT m | F5: QUANT | G5: COEF | H5: UNIT m² | I5: TOTAL m² | J5: UNIT m³ | K5: TOTAL m³ | L5: RESISTÊNCIA | M5: TIPO | P5: m3 | Q5: RESISTÊNCIA | S5: m2 | T5: PAVIMENTOS
A6: GARAGEM G2 // Sense - Lajes do G02 ao G03 (2x).dwg | H6: =IF(C6="","",IF(F6<0,-C6+(D6*(E6+0.02)),C6+(D6*(E6+0.02)))) | I6: =IF(C6="","",IF(F6>0,F6*H6,F6*-H6)) | J6: =IF(C6="","",IF(F6<0,-C6*E6,C6*E6)) | K6: =IF(C6="","",IF(F6>0,J6*F6,-J6*F6)) | P6: =IF(Q6="","",SUMIF($L$6:$L$21,Q6,$K$6:$K$21)) -> 0 | Q6: 40MPa -Térreo | S6: =IF(T6="","",SUMIF($L$6:$L$21,T6,$I$6:$I$21)) -> 0 | T6: 40MPa -Térreo
A7: Laje | G7: 1 | H7: =IF(C7="","",IF(F7<0,-C7+(D7*(E7+0.02)),C7+(D7*(E7+0.02)))) | I7: =I9 -> 376.7 | J7: =IF(C7="","",IF(F7<0,-C7*E7,C7*E7)) | K7: 58 | L7: 40 MPa - G2 | M7: MOLDADA IN LOCO | P7: =IF(Q7="","",SUMIF($L$6:$L$21,Q7,$K$6:$K$21)) -> 58 | Q7: 40 MPa - G2 | S7: =IF(T7="","",SUMIF($L$6:$L$21,T7,$I$6:$I$21)) -> 376.7 | T7: 40 MPa - G2
A8: GARAGEM G3 // Sense - Lajes do G02 ao G03 (2x).dwg | H8: =IF(C8="","",IF(F8<0,-C8+(D8*(E8+0.02)),C8+(D8*(E8+0.02)))) | I8: =IF(C8="","",IF(F8>0,F8*H8,F8*-H8)) | J8: =IF(C8="","",IF(F8<0,-C8*E8,C8*E8)) | K8: =IF(C8="","",IF(F8>0,J8*F8,-J8*F8)) | P8: =IF(Q8="","",SUMIF($L$6:$L$21,Q8,$K$6:$K$21)) -> 58 | Q8: 40 MPa - G3 | S8: =IF(T8="","",SUMIF($L$6:$L$21,T8,$I$6:$I$21)) -> 376.7 | T8: 40 MPa - G3
A9: Laje | G9: 1 | H9: =IF(C9="","",IF(F9<0,-C9+(D9*(E9+0.02)),C9+(D9*(E9+0.02)))) | I9: =I11 -> 376.7 | J9: =IF(C9="","",IF(F9<0,-C9*E9,C9*E9)) | K9: 58 | L9: 40 MPa - G3 | M9: MOLDADA IN LOCO | P9: =IF(Q9="","",SUMIF($L$6:$L$21,Q9,$K$6:$K$21)) -> 62.8 | Q9: 40 MPa - G4 | S9: =IF(T9="","",SUMIF($L$6:$L$21,T9,$I$6:$I$21)) -> 376.7 | T9: 40 MPa - G4
A10: GARAGEM G4 // Sense - Lajes do G04 | H10: =IF(C10="","",IF(F10<0,-C10+(D10*(E10+0.02)),C10+(D10*(E10+0.02)))) | I10: =IF(C10="","",IF(F10>0,F10*H10,F10*-H10)) | J10: =IF(C10="","",IF(F10<0,-C10*E10,C10*E10)) | K10: =IF(C10="","",IF(F10>0,J10*F10,-J10*F10)) | P10: =IF(Q10="","",SUMIF($L$6:$L$21,Q10,$K$6:$K$21)) -> 90 | Q10: 35MPa - Lazer | S10: =IF(T10="","",SUMIF($L$6:$L$21,T10,$I$6:$I$21)) -> 376.7 | T10: 35MPa - Lazer
A11: Laje | G11: 1 | H11: =IF(C11="","",IF(F11<0,-C11+(D11*(E11+0.02)),C11+(D11*(E11+0.02)))) | I11: =I13 -> 376.7 | J11: =IF(C11="","",IF(F11<0,-C11*E11,C11*E11)) | K11: 62.8 | L11: 40 MPa - G4 | M11: MOLDADA IN LOCO | P11: =IF(Q11="","",SUMIF($L$6:$L$21,Q11,$K$6:$K$21)) -> 616 | Q11: 35MPa - Tipos | S11: =IF(T11="","",SUMIF($L$6:$L$21,T11,$I$6:$I$21)) -> 822.8 | T11: 35MPa - Tipos
A12: LAZER // Sense - Lajes do Lazer.dwg | H12: =IF(C12="","",IF(F12<0,-C12+(D12*(E12+0.02)),C12+(D12*(E12+0.02)))) | I12: =IF(C12="","",IF(F12>0,F12*H12,F12*-H12)) | J12: =IF(C12="","",IF(F12<0,-C12*E12,C12*E12)) | K12: =IF(C12="","",IF(F12>0,J12*F12,-J12*F12)) | P12: =IF(Q12="","",SUMIF($L$6:$L$21,Q12,$K$6:$K$21)) -> 30.4 | Q12: 35MPa - Cobertura | S12: =IF(T12="","",SUMIF($L$6:$L$21,T12,$I$6:$I$21)) -> 41.14 | T12: 35MPa - Cobertura
A13: Laje | C13: 376.7 | F13: 1 | G13: 1 | H13: =IF(C13="","",IF(F13<0,-C13+(D13*(E13+0.02)),C13+(D13*(E13+0.02)))) -> 376.7 | I13: =IF(C13="","",IF(F13>0,F13*H13,F13*-H13)) -> 376.7 | J13: =IF(C13="","",IF(F13<0,-C13*E13,C13*E13)) -> 0 | K13: 90 | L13: 35MPa - Lazer | M13: MOLDADA IN LOCO | P13: =IF(Q13="","",SUMIF($L$6:$L$21,Q13,$K$6:$K$21)) -> 17.3 | Q13: 35MPa - Pav. Técnicos | S13: =IF(T13="","",SUMIF($L$6:$L$21,T13,$I$6:$I$21)) -> 101.58 | T13: 35MPa - Pav. Técnicos
A14: TIPO // Sense - Lajes do Tipo (20x) | H14: =IF(C14="","",IF(F14<0,-C14+(D14*(E14+0.02)),C14+(D14*(E14+0.02)))) | I14: =IF(C14="","",IF(F14>0,F14*H14,F14*-H14)) | J14: =IF(C14="","",IF(F14<0,-C14*E14,C14*E14)) | K14: =IF(C14="","",IF(F14>0,J14*F14,-J14*F14)) | P14: =SUM(P6:P13) -> 932.5 | Q14: =IF(K22=P14,"OK","Conferir") -> OK | S14: =SUM(S6:S13) -> 2472.32 | T14: =IF(I22=S14,"OK","Conferir") -> OK
A15: Laje | C15: 41.14 | F15: 20 | G15: 1 | H15: 41.14 | I15: =IF(C15="","",IF(F15>0,F15*H15,F15*-H15)) -> 822.8 | J15: 30.8 | K15: =J15*F15 -> 616 | L15: 35MPa - Tipos | M15: MOLDADA IN LOCO
A16: COBERTURA // Sense - Lajes da Cobertura.dwg | H16: =IF(C16="","",IF(F16<0,-C16+(D16*(E16+0.02)),C16+(D16*(E16+0.02)))) | I16: =IF(C16="","",IF(F16>0,F16*H16,F16*-H16)) | J16: =IF(C16="","",IF(F16<0,-C16*E16,C16*E16)) | K16: =IF(C16="","",IF(F16>0,J16*F16,-J16*F16))
A17: Laje | G17: 1 | H17: =IF(C17="","",IF(F17<0,-C17+(D17*(E17+0.02)),C17+(D17*(E17+0.02)))) | I17: 41.14 | J17: =IF(C17="","",IF(F17<0,-C17*E17,C17*E17)) | K17: 30.4 | L17: 35MPa - Cobertura | M17: MOLDADA IN LOCO
A18: PAV. TÉCNICOS // Sense - Lajes dos Pav.Tecnicos.dwg | H18: =IF(C18="","",IF(F18<0,-C18+(D18*(E18+0.02)),C18+(D18*(E18+0.02)))) | I18: =IF(C18="","",IF(F18>0,F18*H18,F18*-H18)) | J18: =IF(C18="","",IF(F18<0,-C18*E18,C18*E18)) | K18: =IF(C18="","",IF(F18>0,J18*F18,-J18*F18))
A19: Laje | G19: 1 | H19: =IF(C19="","",IF(F19<0,-C19+(D19*(E19+0.02)),C19+(D19*(E19+0.02)))) | I19: 56.86 | K19: 8.36 | L19: 35MPa - Pav. Técnicos | M19: MOLDADA IN LOCO
A20: Laje | G20: 1 | H20: =IF(C20="","",IF(F20<0,-C20+(D20*(E20+0.02)),C20+(D20*(E20+0.02)))) | I20: 39.62 | J20: =IF(C20="","",IF(F20<0,-C20*E20,C20*E20)) | K20: 7.92 | L20: 35MPa - Pav. Técnicos | M20: MOLDADA IN LOCO
A21: Laje | G21: 1 | H21: =IF(C21="","",IF(F21<0,-C21+(D21*(E21+0.02)),C21+(D21*(E21+0.02)))) | I21: 5.1 | J21: =IF(C21="","",IF(F21<0,-C21*E21,C21*E21)) | K21: 1.02 | L21: 35MPa - Pav. Técnicos | M21: MOLDADA IN LOCO
I22: =SUM(I6:I21) -> 2472.32 | K22: =SUM(K6:K21) -> 932.5
A25: PAVIMENTO | B25: CUBETA
A26: CUBETAS | B26: Cubeta inteira | C26: Meia cubeta | D26: TIPO
A27: TÉRREO | H27: Qtd | I27: Custo diário | J27: Custo mensal
A28: GARAGEM G2 | B28: 483 | C28: 83 | D28: 20x80x80 | G28: 2x GARAGEM | H28: =SUM(B28)*2 -> 966 | I28: =H28*0.45 -> 434.7 | J28: =I28*30 -> 13041
A29: GARAGEM G3 | B29: 483 | C29: 83 | D29: 20x80x80 | G29: 3X TIPO | H29: =SUM(B32)/20*3 -> 666 | I29: =H29*0.45 -> 299.7 | J29: =I29*30 -> 8991
A30: GARAGEM G4 | B30: 483 | C30: 83 | D30: 20x80x80
A31: LAZER | B31: 161 | C31: 23 | D31: 20x80x80
A32: TIPOS | B32: =20*222 -> 4440 | C32: =20*40 -> 800 | D32: 20x80x80
A33: COBERTURA | B33: 222 | C33: 40 | D33: 20x80x80
A34: PAV. TÉCNICOS
C36: =SUM(B28:C31)*2 -> 3764 | D36: =C36*0.45*30 -> 50814 | E36: custo mensal

Sheet Rampas
A2: EMPREENDIMENTO: | B2: =ORÇAMENTO!I4 -> SENSE106 | L2: REVISÃO: | N2: DATA:
A3: =ORÇAMENTO!G5 -> EMPRESA: | B3: =ORÇAMENTO!I5 -> HOLZE EMPREENDIMENTOS | L3: =ORÇAMENTO!O5 -> R01 - Edileni Silva | N3: =ORÇAMENTO!P5 -> 45608
A4: PROJETO | B4: PEÇA | C4: DIMENSÕES UNITÁRIAS | G4: FORMA | J4: CONCRETO | M4: LAJE / MOLDE | N4: IMAGENS LEVANTAMENTO | P4: RESUMO - CONCRETO | S4: RESUMO - FORMAS
C5: ÁREA m² | D5: PERÍMETRO m | E5: ALT m | F5: QUANT | G5: COEF | H5: UNIT m² | I5: TOTAL m² | J5: UNIT m³ | K5: TOTAL m³ | L5: RESISTÊNCIA | M5: TIPO | P5: m3 | Q5: RESISTÊNCIA | S5: m2 | T5: PAVIMENTOS
A6: GARAGEM G2 // Sense - Lajes do G02 ao G03 (2x).dwg | H6: =IF(C6="","",IF(F6<0,-C6+(D6*(E6+0.02)),C6+(D6*(E6+0.02)))) | I6: =IF(C6="","",IF(F6>0,F6*H6,F6*-H6)) | J6: =IF(C6="","",IF(F6<0,-C6*E6,C6*E6)) | K6: =IF(C6="","",IF(F6>0,J6*F6,-J6*F6)) | P6: =IF(Q6="","",SUMIF($L$6:$L$11,Q6,$K$6:$K$11)) -> 0 | Q6: 40MPa -Térreo | S6: =IF(T6="","",SUMIF($L$6:$L$11,T6,$I$6:$I$11)) -> 0 | T6: 40MPa -Térreo
A7: Rampa | G7: 1 | H7: =IF(C7="","",IF(F7<0,-C7+(D7*(E7+0.02)),C7+(D7*(E7+0.02)))) | I7: 138.05 | J7: =IF(C7="","",IF(F7<0,-C7*E7,C7*E7)) | K7: 28 | L7: 40 MPa - G2 | M7: MOLDADA IN LOCO | P7: =IF(Q7="","",SUMIF($L$6:$L$11,Q7,$K$6:$K$11)) -> 28 | Q7: 40 MPa - G2 | S7: =IF(T7="","",SUMIF($L$6:$L$11,T7,$I$6:$I$11)) -> 138.05 | T7: 40 MPa - G2
A8: GARAGEM G3 // Sense - Lajes do G02 ao G03 (2x).dwg | H8: =IF(C8="","",IF(F8<0,-C8+(D8*(E8+0.02)),C8+(D8*(E8+0.02)))) | I8: =IF(C8="","",IF(F8>0,F8*H8,F8*-H8)) | J8: =IF(C8="","",IF(F8<0,-C8*E8,C8*E8)) | K8: =IF(C8="","",IF(F8>0,J8*F8,-J8*F8)) | P8: =IF(Q8="","",SUMIF($L$6:$L$11,Q8,$K$6:$K$11)) -> 26.8 | Q8: 40 MPa - G3 | S8: =IF(T8="","",SUMIF($L$6:$L$11,T8,$I$6:$I$11)) -> 138.05 | T8: 40 MPa - G3
A9: Rampa | G9: 1 | H9: =IF(C9="","",IF(F9<0,-C9+(D9*(E9+0.02)),C9+(D9*(E9+0.02)))) | I9: 138.05 | J9: =IF(C9="","",IF(F9<0,-C9*E9,C9*E9)) | K9: 26.8 | L9: 40 MPa - G3 | M9: MOLDADA IN LOCO | P9: =IF(Q9="","",SUMIF($L$6:$L$11,Q9,$K$6:$K$11)) -> 26.8 | Q9: 40 MPa - G4 | S9: =IF(T9="","",SUMIF($L$6:$L$11,T9,$I$6:$I$11)) -> 138.05 | T9: 40 MPa - G4
A10: GARAGEM G4 // Sense - Lajes do G04 | H10: =IF(C10="","",IF(F10<0,-C10+(D10*(E10+0.02)),C10+(D10*(E10+0.02)))) | I10: =IF(C10="","",IF(F10>0,F10*H10,F10*-H10)) | J10: =IF(C10="","",IF(F10<0,-C10*E10,C10*E10)) | K10: =IF(C10="","",IF(F10>0,J10*F10,-J10*F10)) | P10: =SUM(P7:P9) -> 81.6 | Q10: =IF(K12=P10,"OK","Conferir") -> OK | S10: =SUM(S7:S9) -> 414.15 | T10: =IF(I12=S10,"OK","Conferir") -> OK
A11: Rampa | G11: 1 | H11: =IF(C11="","",IF(F11<0,-C11+(D11*(E11+0.02)),C11+(D11*(E11+0.02)))) | I11: 138.05 | J11: =IF(C11="","",IF(F11<0,-C11*E11,C11*E11)) | K11: 26.8 | L11: 40 MPa - G4 | M11: MOLDADA IN LOCO
B12: TOTAL | C12: =SUMPRODUCT(C6:C11,F6:F11) -> 0 | I12: =SUM(I6:I11) -> 414.15 | K12: =SUM(K6:K11) -> 81.6

Sheet Escadas
A2: EMPREENDIMENTO: | P2: REVISÃO: | R2: DATA:
A3: =ORÇAMENTO!G5 -> EMPRESA: | P3: R00 -
A4: PROJETO | B4: PEÇA | C4: LAJE PISO | G4: DEGRAUS / ESPELHO | K4: QUANT | L4: FORMA | O4: CONCRETO | T4: RESUMO - CONCRETO | W4: RESUMO - FORMAS
C5: LARG | D5: COMPR | E5: ESPESS | F5: QUANT | G5: LARG | H5: ALT | I5: BASE | J5: QUANT | L5: LAJE PISO | M5: DEGRAUS | N5: TOTAL | O5: LAJE PISO | P5: DEGRAUS | Q5: TOTAL | R5: RESISTÊNCIA
C6: A | D6: B | E6: C | F6: D | G6: E | H6: F | I6: G | J6: H | L6: m2 | M6: m2 | N6: m2 | O6: m3 | P6: m3 | Q6: m3 | T6: m3 | U6: RESISTÊNCIA | W6: m2 | X6: PAVIMENTOS
A7: TÉRREO >> GARAGEM G2 // Sense - Escada 01.pdf | T7: =IF(U7="","",SUMIF($R$7:$R$55,U7,$Q$7:$Q$55)) -> 2.93419 | U7: 40 MPa - G2 | W7: =IF(X7="","",SUMIF($R$7:$R$55,X7,$N$7:$N$55)) -> 27.3789 | X7: 40 MPa - G2
B8: 1º lance | C8: 1.255 | D8: 3.99 | E8: 0.14 | F8: 1 | G8: 0.28 | H8: 0.18 | I8: =SQRT((G8^2)+(H8^2)) -> 0.33286634 | J8: 12 | K8: 1 | L8: =(((C8*D8)+(((C8+D8)*2)*E8))*F8)*K8 -> 6.47605 | M8: =(((H8*C8)+(((G8*H8)/2)*2))*J8)*K8 -> 3.3156 | N8: =SUM(L8:M8) -> 9.79165 | O8: =(((C8*D8)*E8)*F8)*K8 -> 0.701043 | P8: =((((G8*H8)/2)*C8)*J8)*K8 -> 0.379512 | Q8: =SUM(O8:P8) -> 1.080555 | R8: 40 MPa - G2 | T8: =IF(U8="","",SUMIF($R$7:$R$55,U8,$Q$7:$Q$55)) -> 2.6873315 | U8: 40 MPa - G3 | W8: =IF(X8="","",SUMIF($R$7:$R$55,X8,$N$7:$N$55)) -> 25.223625 | X8: 40 MPa - G3
B9: Patamar | C9: 2.51 | D9: 1.3 | E9: 0.14 | F9: 1 | I9: =SQRT((G9^2)+(H9^2)) -> 0 | K9: 1 | L9: =(((C9*D9)+(((C9+D9)*2)*E9))*F9)*K9 -> 4.3298 | M9: =(((H9*C9)+(((G9*H9)/2)*2))*J9)*K9 -> 0 | N9: =SUM(L9:M9) -> 4.3298 | O9: =(((C9*D9)*E9)*F9)*K9 -> 0.45682 | P9: =((((G9*H9)/2)*C9)*J9)*K9 -> 0 | Q9: =SUM(O9:P9) -> 0.45682 | R9: 40 MPa - G2 | T9: =IF(U9="","",SUMIF($R$7:$R$55,U9,$Q$7:$Q$55)) -> 2.6873315 | U9: 40 MPa - G4 | W9: =IF(X9="","",SUMIF($R$7:$R$55,X9,$N$7:$N$55)) -> 25.223625 | X9: 40 MPa - G4
B10: 2º lance | C10: 1.255 | D10: 3.33 | E10: 0.14 | F10: 1 | G10: 0.28 | H10: 0.18 | I10: =SQRT((G10^2)+(H10^2)) -> 0.33286634 | J10: 10 | K10: 1 | L10: =(((C10*D10)+(((C10+D10)*2)*E10))*F10)*K10 -> 5.46295 | M10: =(((H10*C10)+(((G10*H10)/2)*2))*J10)*K10 -> 2.763 | N10: =SUM(L10:M10) -> 8.22595 | O10: =(((C10*D10)*E10)*F10)*K10 -> 0.585081 | P10: =((((G10*H10)/2)*C10)*J10)*K10 -> 0.31626 | Q10: =SUM(O10:P10) -> 0.901341 | R10: 40 MPa - G2 | T10: =IF(U10="","",SUMIF($R$7:$R$55,U10,$Q$7:$Q$55)) -> 2.853368 | U10: 40MPa - Lazer | W10: =IF(X10="","",SUMIF($R$7:$R$55,X10,$N$7:$N$55)) -> 26.6728 | X10: 40MPa - Lazer
B11: Patamar antes | C11: =2.51/2 -> 1.255 | D11: 1.315 | E11: 0.14 | F11: 1 | I11: =SQRT((G11^2)+(H11^2)) -> 0 | K11: 1 | L11: =(((C11*D11)+(((C11+D11)*2)*E11))*F11)*K11 -> 2.369925 | M11: =(((H11*C11)+(((G11*H11)/2)*2))*J11)*K11 -> 0 | N11: =SUM(L11:M11) -> 2.369925 | O11: =(((C11*D11)*E11)*F11)*K11 -> 0.2310455 | P11: =((((G11*H11)/2)*C11)*J11)*K11 -> 0 | Q11: =SUM(O11:P11) -> 0.2310455 | R11: 40 MPa - G2 | T11: =IF(U11="","",SUMIF($R$7:$R$55,U11,$Q$7:$Q$55)) -> 54.648849 | U11: 35MPa - Tipos | W11: =IF(X11="","",SUMIF($R$7:$R$55,X11,$N$7:$N$55)) -> 512.32673 | X11: 35MPa - Tipos
B12: Patamar depois | C12: =2.51/2 -> 1.255 | D12: 1.505 | E12: 0.14 | F12: 1 | I12: =SQRT((G12^2)+(H12^2)) -> 0 | K12: 1 | L12: =(((C12*D12)+(((C12+D12)*2)*E12))*F12)*K12 -> 2.661575 | M12: =(((H12*C12)+(((G12*H12)/2)*2))*J12)*K12 -> 0 | N12: =SUM(L12:M12) -> 2.661575 | O12: =(((C12*D12)*E12)*F12)*K12 -> 0.2644285 | P12: =((((G12*H12)/2)*C12)*J12)*K12 -> 0 | Q12: =SUM(O12:P12) -> 0.2644285 | R12: 40 MPa - G2 | T12: =IF(U12="","",SUMIF($R$7:$R$55,U12,$Q$7:$Q$55)) -> 2.730378 | U12: 35MPa - Cobertura | W12: =IF(X12="","",SUMIF($R$7:$R$55,X12,$N$7:$N$55)) -> 25.5983 | X12: 35MPa - Cobertura
B13: PROJETISTA | Q13: 3 | T13: =IF(U13="","",SUMIF($R$7:$R$55,U13,$Q$7:$Q$55)) -> 0 | U13: 35MPa - Pav. Técnicos | W13: =IF(X13="","",SUMIF($R$7:$R$55,X13,$N$7:$N$55)) -> 0 | X13: 35MPa - Pav. Técnicos
A14: GARAGEM G2 >> GARAGEM G3 // Sense - Escada 02.pdf | T14: =SUM(T7:T13) -> 68.541449 | U14: =IF(Q56=T14,"OK","Conferir") -> OK | W14: =SUM(W7:W13) -> 642.42398 | X14: =IF(N56=W14,"OK","Conferir") -> OK
B15: 1º lance | C15: 1.255 | D15: 3.33 | E15: 0.14 | F15: 1 | G15: 0.28 | H15: 0.18 | I15: =SQRT((G15^2)+(H15^2)) -> 0.33286634 | J15: 10 | K15: 1 | L15: =(((C15*D15)+(((C15+D15)*2)*E15))*F15)*K15 -> 5.46295 | M15: =(((H15*C15)+(((G15*H15)/2)*2))*J15)*K15 -> 2.763 | N15: =SUM(L15:M15) -> 8.22595 | O15: =(((C15*D15)*E15)*F15)*K15 -> 0.585081 | P15: =((((G15*H15)/2)*C15)*J15)*K15 -> 0.31626 | Q15: =SUM(O15:P15) -> 0.901341 | R15: 40 MPa - G3
B16: Patamar | C16: 2.51 | D16: 1.295 | E16: 0.14 | F16: 1 | I16: =SQRT((G16^2)+(H16^2)) -> 0 | K16: 1 | L16: =(((C16*D16)+(((C16+D16)*2)*E16))*F16)*K16 -> 4.31585 | M16: =(((H16*C16)+(((G16*H16)/2)*2))*J16)*K16 -> 0 | N16: =SUM(L16:M16) -> 4.31585 | O16: =(((C16*D16)*E16)*F16)*K16 -> 0.455063 | P16: =((((G16*H16)/2)*C16)*J16)*K16 -> 0 | Q16: =SUM(O16:P16) -> 0.455063 | R16: 40 MPa - G3
B17: 2º lance | C17: 1.255 | D17: 1.995 | E17: 0.14 | F17: 1 | G17: 0.28 | H17: 0.18 | I17: =SQRT((G17^2)+(H17^2)) -> 0.33286634 | J17: 6 | K17: 1 | L17: =(((C17*D17)+(((C17+D17)*2)*E17))*F17)*K17 -> 3.413725 | M17: =(((H17*C17)+(((G17*H17)/2)*2))*J17)*K17 -> 1.6578 | N17: =SUM(L17:M17) -> 5.071525 | O17: =(((C17*D17)*E17)*F17)*K17 -> 0.3505215 | P17: =((((G17*H17)/2)*C17)*J17)*K17 -> 0.189756 | Q17: =SUM(O17:P17) -> 0.5402775 | R17: 40 MPa - G3
B18: Patamar depois | C18: =2.51/2 -> 1.255 | D18: =1.8+0.825 -> 2.625 | E18: 0.14 | F18: 1 | I18: =SQRT((G18^2)+(H18^2)) -> 0 | K18: 1 | L18: =(((C18*D18)+(((C18+D18)*2)*E18))*F18)*K18 -> 4.380775 | M18: =(((H18*C18)+(((G18*H18)/2)*2))*J18)*K18 -> 0 | N18: =SUM(L18:M18) -> 4.380775 | O18: =(((C18*D18)*E18)*F18)*K18 -> 0.4612125 | P18: =((((G18*H18)/2)*C18)*J18)*K18 -> 0 | Q18: =SUM(O18:P18) -> 0.4612125 | R18: 40 MPa - G3
B19: Patamar antes | C19: =2.51/2 -> 1.255 | D19: 1.875 | E19: 0.14 | F19: 1 | I19: =SQRT((G19^2)+(H19^2)) -> 0 | K19: 1 | L19: =(((C19*D19)+(((C19+D19)*2)*E19))*F19)*K19 -> 3.229525 | M19: =(((H19*C19)+(((G19*H19)/2)*2))*J19)*K19 -> 0 | N19: =SUM(L19:M19) -> 3.229525 | O19: =(((C19*D19)*E19)*F19)*K19 -> 0.3294375 | P19: =((((G19*H19)/2)*C19)*J19)*K19 -> 0 | Q19: =SUM(O19:P19) -> 0.3294375 | R19: 40 MPa - G3
B20: PROJETISTA | Q20: 2.6
A21: GARAGEM G3 >> GARAGEM G4 // Sense - Escada 02.pdf
B22: 1º lance | C22: 1.255 | D22: 3.33 | E22: 0.14 | F22: 1 | G22: 0.28 | H22: 0.18 | I22: =SQRT((G22^2)+(H22^2)) -> 0.33286634 | J22: 10 | K22: 1 | L22: =(((C22*D22)+(((C22+D22)*2)*E22))*F22)*K22 -> 5.46295 | M22: =(((H22*C22)+(((G22*H22)/2)*2))*J22)*K22 -> 2.763 | N22: =SUM(L22:M22) -> 8.22595 | O22: =(((C22*D22)*E22)*F22)*K22 -> 0.585081 | P22: =((((G22*H22)/2)*C22)*J22)*K22 -> 0.31626 | Q22: =SUM(O22:P22) -> 0.901341 | R22: 40 MPa - G4
B23: Patamar | C23: 2.51 | D23: 1.295 | E23: 0.14 | F23: 1 | I23: =SQRT((G23^2)+(H23^2)) -> 0 | K23: 1 | L23: =(((C23*D23)+(((C23+D23)*2)*E23))*F23)*K23 -> 4.31585 | M23: =(((H23*C23)+(((G23*H23)/2)*2))*J23)*K23 -> 0 | N23: =SUM(L23:M23) -> 4.31585 | O23: =(((C23*D23)*E23)*F23)*K23 -> 0.455063 | P23: =((((G23*H23)/2)*C23)*J23)*K23 -> 0 | Q23: =SUM(O23:P23) -> 0.455063 | R23: 40 MPa - G4
B24: 2º lance | C24: 1.255 | D24: 1.995 | E24: 0.14 | F24: 1 | G24: 0.28 | H24: 0.18 | I24: =SQRT((G24^2)+(H24^2)) -> 0.33286634 | J24: 6 | K24: 1 | L24: =(((C24*D24)+(((C24+D24)*2)*E24))*F24)*K24 -> 3.413725 | M24: =(((H24*C24)+(((G24*H24)/2)*2))*J24)*K24 -> 1.6578 | N24: =SUM(L24:M24) -> 5.071525 | O24: =(((C24*D24)*E24)*F24)*K24 -> 0.3505215 | P24: =((((G24*H24)/2)*C24)*J24)*K24 -> 0.189756 | Q24: =SUM(O24:P24) -> 0.5402775 | R24: 40 MPa - G4
B25: Patamar depois | C25: =2.51/2 -> 1.255 | D25: =1.8+0.825 -> 2.625 | E25: 0.14 | F25: 1 | I25: =SQRT((G25^2)+(H25^2)) -> 0 | K25: 1 | L25: =(((C25*D25)+(((C25+D25)*2)*E25))*F25)*K25 -> 4.380775 | M25: =(((H25*C25)+(((G25*H25)/2)*2))*J25)*K25 -> 0 | N25: =SUM(L25:M25) -> 4.380775 | O25: =(((C25*D25)*E25)*F25)*K25 -> 0.4612125 | P25: =((((G25*H25)/2)*C25)*J25)*K25 -> 0 | Q25: =SUM(O25:P25) -> 0.4612125 | R25: 40 MPa - G4
B26: Patamar antes | C26: =2.51/2 -> 1.255 | D26: 1.875 | E26: 0.14 | F26: 1 | I26: =SQRT((G26^2)+(H26^2)) -> 0 | K26: 1 | L26: =(((C26*D26)+(((C26+D26)*2)*E26))*F26)*K26 -> 3.229525 | M26: =(((H26*C26)+(((G26*H26)/2)*2))*J26)*K26 -> 0 | N26: =SUM(L26:M26) -> 3.229525 | O26: =(((C26*D26)*E26)*F26)*K26 -> 0.3294375 | P26: =((((G26*H26)/2)*C26)*J26)*K26 -> 0 | Q26: =SUM(O26:P26) -> 0.3294375 | R26: 40 MPa - G4
B27: PROJETISTA | Q27: 2.6
A28: GARAGEM G4 >> LAZER // Sense - Escada 03.pdf
B29: 1º lance | C29: 1.255 | D29: 3.33 | E29: 0.14 | F29: 1 | G29: 0.28 | H29: 0.18 | I29: =SQRT((G29^2)+(H29^2)) -> 0.33286634 | J29: 10 | K29: 1 | L29: =(((C29*D29)+(((C29+D29)*2)*E29))*F29)*K29 -> 5.46295 | M29: =(((H29*C29)+(((G29*H29)/2)*2))*J29)*K29 -> 2.763 | N29: =SUM(L29:M29) -> 8.22595 | O29: =(((C29*D29)*E29)*F29)*K29 -> 0.585081 | P29: =((((G29*H29)/2)*C29)*J29)*K29 -> 0.31626 | Q29: =SUM(O29:P29) -> 0.901341 | R29: 40MPa - Lazer
B30: Patamar | C30: 2.51 | D30: 1.3 | E30: 0.14 | F30: 1 | I30: =SQRT((G30^2)+(H30^2)) -> 0 | K30: 1 | L30: =(((C30*D30)+(((C30+D30)*2)*E30))*F30)*K30 -> 4.3298 | M30: =(((H30*C30)+(((G30*H30)/2)*2))*J30)*K30 -> 0 | N30: =SUM(L30:M30) -> 4.3298 | O30: =(((C30*D30)*E30)*F30)*K30 -> 0.45682 | P30: =((((G30*H30)/2)*C30)*J30)*K30 -> 0 | Q30: =SUM(O30:P30) -> 0.45682 | R30: 40MPa - Lazer
B31: 2º lance | C31: 1.255 | D31: 3.33 | E31: 0.14 | F31: 1 | G31: 0.28 | H31: 0.18 | I31: =SQRT((G31^2)+(H31^2)) -> 0.33286634 | J31: 10 | K31: 1 | L31: =(((C31*D31)+(((C31+D31)*2)*E31))*F31)*K31 -> 5.46295 | M31: =(((H31*C31)+(((G31*H31)/2)*2))*J31)*K31 -> 2.763 | N31: =SUM(L31:M31) -> 8.22595 | O31: =(((C31*D31)*E31)*F31)*K31 -> 0.585081 | P31: =((((G31*H31)/2)*C31)*J31)*K31 -> 0.31626 | Q31: =SUM(O31:P31) -> 0.901341 | R31: 40MPa - Lazer
B32: Patamar depois | C32: =2.51/2 -> 1.255 | D32: 1.505 | E32: 0.14 | F32: 1 | I32: =SQRT((G32^2)+(H32^2)) -> 0 | K32: 1 | L32: =(((C32*D32)+(((C32+D32)*2)*E32))*F32)*K32 -> 2.661575 | M32: =(((H32*C32)+(((G32*H32)/2)*2))*J32)*K32 -> 0 | N32: =SUM(L32:M32) -> 2.661575 | O32: =(((C32*D32)*E32)*F32)*K32 -> 0.2644285 | P32: =((((G32*H32)/2)*C32)*J32)*K32 -> 0 | Q32: =SUM(O32:P32) -> 0.2644285 | R32: 40MPa - Lazer
B33: Patamar antes | C33: =2.51/2 -> 1.255 | D33: 1.875 | E33: 0.14 | F33: 1 | I33: =SQRT((G33^2)+(H33^2)) -> 0 | K33: 1 | L33: =(((C33*D33)+(((C33+D33)*2)*E33))*F33)*K33 -> 3.229525 | M33: =(((H33*C33)+(((G33*H33)/2)*2))*J33)*K33 -> 0 | N33: =SUM(L33:M33) -> 3.229525 | O33: =(((C33*D33)*E33)*F33)*K33 -> 0.3294375 | P33: =((((G33*H33)/2)*C33)*J33)*K33 -> 0 | Q33: =SUM(O33:P33) -> 0.3294375 | R33: 40MPa - Lazer
B34: PROJETISTA | Q34: 3
A35: TIPOS // Sense - Escada 04.pdf
A36: LAZER >> TIPO 1 | B36: 1º lance | C36: 1.255 | D36: 3.33 | E36: 0.14 | F36: 1 | G36: 0.28 | H36: 0.18 | I36: =SQRT((G36^2)+(H36^2)) -> 0.33286634 | J36: 10 | K36: 1 | L36: =(((C36*D36)+(((C36+D36)*2)*E36))*F36)*K36 -> 5.46295 | M36: =(((H36*C36)+(((G36*H36)/2)*2))*J36)*K36 -> 2.763 | N36: =SUM(L36:M36) -> 8.22595 | O36: =(((C36*D36)*E36)*F36)*K36 -> 0.585081 | P36: =((((G36*H36)/2)*C36)*J36)*K36 -> 0.31626 | Q36: =SUM(O36:P36) -> 0.901341 | R36: 35MPa - Tipos
B37: Patamar | C37: 2.51 | D37: 1.3 | E37: 0.14 | F37: 1 | I37: =SQRT((G37^2)+(H37^2)) -> 0 | K37: 1 | L37: =(((C37*D37)+(((C37+D37)*2)*E37))*F37)*K37 -> 4.3298 | M37: =(((H37*C37)+(((G37*H37)/2)*2))*J37)*K37 -> 0 | N37: =SUM(L37:M37) -> 4.3298 | O37: =(((C37*D37)*E37)*F37)*K37 -> 0.45682 | P37: =((((G37*H37)/2)*C37)*J37)*K37 -> 0 | Q37: =SUM(O37:P37) -> 0.45682 | R37: 35MPa - Tipos
B38: 2º lance | C38: 1.255 | D38: 2.665 | E38: 0.14 | F38: 1 | G38: 0.28 | H38: 0.18 | I38: =SQRT((G38^2)+(H38^2)) -> 0.33286634 | J38: 8 | K38: 1 | L38: =(((C38*D38)+(((C38+D38)*2)*E38))*F38)*K38 -> 4.442175 | M38: =(((H38*C38)+(((G38*H38)/2)*2))*J38)*K38 -> 2.2104 | N38: =SUM(L38:M38) -> 6.652575 | O38: =(((C38*D38)*E38)*F38)*K38 -> 0.4682405 | P38: =((((G38*H38)/2)*C38)*J38)*K38 -> 0.253008 | Q38: =SUM(O38:P38) -> 0.7212485 | R38: 35MPa - Tipos
B39: Patamar antes | C39: =2.51/2 -> 1.255 | D39: 1.875 | E39: 0.14 | F39: 1 | I39: =SQRT((G39^2)+(H39^2)) -> 0 | K39: 1 | L39: =(((C39*D39)+(((C39+D39)*2)*E39))*F39)*K39 -> 3.229525 | M39: =(((H39*C39)+(((G39*H39)/2)*2))*J39)*K39 -> 0 | N39: =SUM(L39:M39) -> 3.229525 | O39: =(((C39*D39)*E39)*F39)*K39 -> 0.3294375 | P39: =((((G39*H39)/2)*C39)*J39)*K39 -> 0 | Q39: =SUM(O39:P39) -> 0.3294375 | R39: 35MPa - Tipos
B40: Patamar depois | C40: =2.51/2 -> 1.255 | D40: =1.8+0.265 -> 2.065 | E40: 0.14 | F40: 1 | I40: =SQRT((G40^2)+(H40^2)) -> 0 | K40: 1 | L40: =(((C40*D40)+(((C40+D40)*2)*E40))*F40)*K40 -> 3.521175 | M40: =(((H40*C40)+(((G40*H40)/2)*2))*J40)*K40 -> 0 | N40: =SUM(L40:M40) -> 3.521175 | O40: =(((C40*D40)*E40)*F40)*K40 -> 0.3628205 | P40: =((((G40*H40)/2)*C40)*J40)*K40 -> 0 | Q40: =SUM(O40:P40) -> 0.3628205 | R40: 35MPa - Tipos
A42: TIPO 1 >> TIPO 20 | B42: 1º lance | C42: 1.255 | D42: 3.33 | E42: 0.14 | F42: 1 | G42: 0.28 | H42: 0.18 | I42: =SQRT((G42^2)+(H42^2)) -> 0.33286634 | J42: 10 | K42: 19 | L42: =(((C42*D42)+(((C42+D42)*2)*E42))*F42)*K42 -> 103.79605 | M42: =(((H42*C42)+(((G42*H42)/2)*2))*J42)*K42 -> 52.497 | N42: =SUM(L42:M42) -> 156.29305 | O42: =(((C42*D42)*E42)*F42)*K42 -> 11.116539 | P42: =((((G42*H42)/2)*C42)*J42)*K42 -> 6.00894 | Q42: =SUM(O42:P42) -> 17.125479 | R42: 35MPa - Tipos
B43: Patamar | C43: 2.51 | D43: 1.3 | E43: 0.14 | F43: 1 | I43: =SQRT((G43^2)+(H43^2)) -> 0 | K43: 19 | L43: =(((C43*D43)+(((C43+D43)*2)*E43))*F43)*K43 -> 82.2662 | M43: =(((H43*C43)+(((G43*H43)/2)*2))*J43)*K43 -> 0 | N43: =SUM(L43:M43) -> 82.2662 | O43: =(((C43*D43)*E43)*F43)*K43 -> 8.67958 | P43: =((((G43*H43)/2)*C43)*J43)*K43 -> 0 | Q43: =SUM(O43:P43) -> 8.67958 | R43: 35MPa - Tipos
B44: 2º lance | C44: 1.255 | D44: 2.33 | E44: 0.14 | F44: 1 | G44: 0.28 | H44: 0.18 | I44: =SQRT((G44^2)+(H44^2)) -> 0.33286634 | J44: 7 | K44: 19 | L44: =(((C44*D44)+(((C44+D44)*2)*E44))*F44)*K44 -> 74.63105 | M44: =(((H44*C44)+(((G44*H44)/2)*2))*J44)*K44 -> 36.7479 | N44: =SUM(L44:M44) -> 111.37895 | O44: =(((C44*D44)*E44)*F44)*K44 -> 7.778239 | P44: =((((G44*H44)/2)*C44)*J44)*K44 -> 4.206258 | Q44: =SUM(O44:P44) -> 11.984497 | R44: 35MPa - Tipos
B45: Patamar antes | C45: =2.51/2 -> 1.255 | D45: 1.875 | E45: 0.14 | F45: 1 | I45: =SQRT((G45^2)+(H45^2)) -> 0 | K45: 19 | L45: =(((C45*D45)+(((C45+D45)*2)*E45))*F45)*K45 -> 61.360975 | M45: =(((H45*C45)+(((G45*H45)/2)*2))*J45)*K45 -> 0 | N45: =SUM(L45:M45) -> 61.360975 | O45: =(((C45*D45)*E45)*F45)*K45 -> 6.2593125 | P45: =((((G45*H45)/2)*C45)*J45)*K45 -> 0 | Q45: =SUM(O45:P45) -> 6.2593125 | R45: 35MPa - Tipos
B46: Patamar depois | C46: =2.51/2 -> 1.255 | D46: =1.8+0.545 -> 2.345 | E46: 0.14 | F46: 1 | I46: =SQRT((G46^2)+(H46^2)) -> 0 | K46: 19 | L46: =(((C46*D46)+(((C46+D46)*2)*E46))*F46)*K46 -> 75.068525 | M46: =(((H46*C46)+(((G46*H46)/2)*2))*J46)*K46 -> 0 | N46: =SUM(L46:M46) -> 75.068525 | O46: =(((C46*D46)*E46)*F46)*K46 -> 7.8283135 | P46: =((((G46*H46)/2)*C46)*J46)*K46 -> 0 | Q46: =SUM(O46:P46) -> 7.8283135 | R46: 35MPa - Tipos
B48: PROJETISTA | Q48: =2.8*20 -> 56
A49: COBERTURA
A50: TIPO 20 >> COBERRTURA | B50: 1º lance | C50: 1.255 | D50: 3.33 | E50: 0.14 | F50: 1 | G50: 0.28 | H50: 0.18 | I50: =SQRT((G50^2)+(H50^2)) -> 0.33286634 | J50: 10 | K50: 1 | L50: =(((C50*D50)+(((C50+D50)*2)*E50))*F50)*K50 -> 5.46295 | M50: =(((H50*C50)+(((G50*H50)/2)*2))*J50)*K50 -> 2.763 | N50: =SUM(L50:M50) -> 8.22595 | O50: =(((C50*D50)*E50)*F50)*K50 -> 0.585081 | P50: =((((G50*H50)/2)*C50)*J50)*K50 -> 0.31626 | Q50: =SUM(O50:P50) -> 0.901341 | R50: 35MPa - Cobertura
B51: Patamar | C51: 2.51 | D51: 1.3 | E51: 0.14 | F51: 1 | I51: =SQRT((G51^2)+(H51^2)) -> 0 | K51: 1 | L51: =(((C51*D51)+(((C51+D51)*2)*E51))*F51)*K51 -> 4.3298 | M51: =(((H51*C51)+(((G51*H51)/2)*2))*J51)*K51 -> 0 | N51: =SUM(L51:M51) -> 4.3298 | O51: =(((C51*D51)*E51)*F51)*K51 -> 0.45682 | P51: =((((G51*H51)/2)*C51)*J51)*K51 -> 0 | Q51: =SUM(O51:P51) -> 0.45682 | R51: 35MPa - Cobertura
B52: 2º lance | C52: 1.255 | D52: 2.33 | E52: 0.14 | F52: 1 | G52: 0.28 | H52: 0.18 | I52: =SQRT((G52^2)+(H52^2)) -> 0.33286634 | J52: 7 | K52: 1 | L52: =(((C52*D52)+(((C52+D52)*2)*E52))*F52)*K52 -> 3.92795 | M52: =(((H52*C52)+(((G52*H52)/2)*2))*J52)*K52 -> 1.9341 | N52: =SUM(L52:M52) -> 5.86205 | O52: =(((C52*D52)*E52)*F52)*K52 -> 0.409381 | P52: =((((G52*H52)/2)*C52)*J52)*K52 -> 0.221382 | Q52: =SUM(O52:P52) -> 0.630763 | R52: 35MPa - Cobertura
B53: Patamar antes | C53: =2.51/2 -> 1.255 | D53: 1.875 | E53: 0.14 | F53: 1 | I53: =SQRT((G53^2)+(H53^2)) -> 0 | K53: 1 | L53: =(((C53*D53)+(((C53+D53)*2)*E53))*F53)*K53 -> 3.229525 | M53: =(((H53*C53)+(((G53*H53)/2)*2))*J53)*K53 -> 0 | N53: =SUM(L53:M53) -> 3.229525 | O53: =(((C53*D53)*E53)*F53)*K53 -> 0.3294375 | P53: =((((G53*H53)/2)*C53)*J53)*K53 -> 0 | Q53: =SUM(O53:P53) -> 0.3294375 | R53: 35MPa - Cobertura
B54: Patamar depois | C54: =2.51/2 -> 1.255 | D54: =1.8+0.545 -> 2.345 | E54: 0.14 | F54: 1 | I54: =SQRT((G54^2)+(H54^2)) -> 0 | K54: 1 | L54: =(((C54*D54)+(((C54+D54)*2)*E54))*F54)*K54 -> 3.950975 | M54: =(((H54*C54)+(((G54*H54)/2)*2))*J54)*K54 -> 0 | N54: =SUM(L54:M54) -> 3.950975 | O54: =(((C54*D54)*E54)*F54)*K54 -> 0.4120165 | P54: =((((G54*H54)/2)*C54)*J54)*K54 -> 0 | Q54: =SUM(O54:P54) -> 0.4120165 | R54: 35MPa - Cobertura
B55: PROJETISTA | Q55: 2.8
B56: TOTAL | N56: =SUM(N7:N55) -> 642.42397 | Q56: =SUM(Q8:Q12,Q15:Q19,Q22:Q26,Q29:Q33,Q36:Q46,Q50:Q54) -> 68.541449
B57: QUANTITATIVO PROJETISTA
B61: DETALHE DA ESCADA MEDIDAS A SEREM FORNECIDAS
E64: E | H64: C
C69: F
F72: B

Sheet SUPRA
B1: Projeto | C1: =ORÇAMENTO!I4 -> SENSE106
B2: Empresa | C2: =ORÇAMENTO!I5 -> HOLZE EMPREENDIMENTOS
B3: Revisão | C3: =ORÇAMENTO!O5 -> R01 - Edileni Silva
A4: ARMAÇÃO SUPRAESTRUTURA
A5: ITEM | C5: QUANT | D5: QUANTIDADE POR ITEM CA-50 - kg | K5: CONCRETO | L5: FORMA | M5: TELA Q61
D6: 6.3 | E6: 8 | F6: 10 | G6: 12.5 | H6: 16 | I6: 20 | J6: 25 | K6: m³ | L6: m² | M6: QTD | N6: 0
A7: PROJETO: Sense 106 - Resumo de Materiais.xls
A8: TÉRREO
A9: PILARES | B9: =SUM(D9:I13) -> 0 | C9: 1
A10: VIGAS | C10: 1
A11: LAJES | B11: Radier térreo | C11: 1
A12: ESCADAS | C12: 1
A13: RAMPA | C13: 1
A14: GARAGEM G2
A15: PILARES | B15: =SUM(D15:I19) -> 19445 | C15: 1 | D15: 435 | E15: 325 | F15: 745 | H15: 980 | I15: 6480 | K15: =Pilares!M7 -> 41.61 | L15: =Pilares!P7 -> 381.74
A16: VIGAS | C16: 1 | D16: 670 | E16: 255 | F16: 90 | G16: 15 | H16: 3510 | I16: 180 | K16: =Vigas!N6 -> 30.77 | L16: =Vigas!Q6 -> 214.27
A17: LAJES | C17: 1 | E17: 1675 | F17: 1835 | G17: 335 | H17: 90 | K17: =Lajes!P7 -> 58 | L17: =Lajes!S7 -> 376.7 | M17: 28 | N17: =M17*(2.45*6) -> 411.6
A18: ESCADAS | C18: 1 | D18: 15 | E18: 25 | F18: 105 | K18: =Escadas!Q13 -> 3 | L18: =Escadas!W7 -> 27.3789
A19: RAMPA | C19: 1 | D19: 55 | F19: 750 | G19: 505 | H19: 370 | K19: =Rampas!P7 -> 28 | L19: =Rampas!S7 -> 138.05
A20: GARAGEM G3 | K20: =SUM(K15:K19) -> 161.38
A21: PILARES | B21: =SUM(D21:I25) -> 16540 | C21: 1 | D21: 290 | E21: 245 | F21: 455 | H21: 695 | I21: 4600 | K21: =Pilares!M8 -> 30.26 | L21: =Pilares!P8 -> 272.63
A22: VIGAS | C22: 1 | D22: 670 | E22: 255 | F22: 90 | G22: 15 | H22: 3510 | I22: 180 | K22: =Vigas!N7 -> 29.56 | L22: =Vigas!Q7 -> 204.11
A23: LAJES | C23: 1 | E23: 1675 | F23: 1835 | G23: 335 | H23: 90 | K23: =Lajes!P8 -> 58 | L23: =Lajes!S8 -> 376.7 | M23: 28 | N23: =M23*(2.45*6) -> 411.6
A24: ESCADAS | C24: 1 | D24: 15 | E24: 25 | F24: 105 | K24: =Escadas!Q20 -> 2.6 | L24: =Escadas!W8 -> 25.223625
A25: RAMPA | C25: 1 | D25: 35 | F25: 635 | G25: 515 | H25: 270 | K25: =Rampas!P8 -> 26.8 | L25: =Rampas!S8 -> 138.05
A26: GARAGEM G4 | K26: =SUM(K21:K25) -> 147.22
A27: PILARES | B27: =SUM(D27:I31) -> 16910 | C27: 1 | D27: 290 | E27: 245 | F27: 455 | H27: 695 | I27: 4600 | K27: =Pilares!M9 -> 30.26 | L27: =Pilares!P9 -> 272.63
A28: VIGAS | C28: 1 | D28: 670 | E28: 255 | F28: 90 | G28: 15 | H28: 3510 | I28: 180 | K28: =Vigas!N8 -> 29.56 | L28: =Vigas!Q8 -> 204.11
A29: LAJES | C29: 1 | E29: 1675 | F29: 2055 | G29: 485 | H29: 90 | K29: =Lajes!P9 -> 62.8 | L29: =Lajes!S9 -> 376.7 | M29: 28 | N29: =M29*(2.45*6) -> 411.6
A30: ESCADAS | C30: 1 | D30: 15 | E30: 25 | F30: 105 | K30: =Escadas!Q27 -> 2.6 | L30: =Escadas!W9 -> 25.223625
A31: RAMPA | C31: 1 | D31: 35 | F31: 635 | G31: 515 | H31: 270 | K31: =Rampas!P9 -> 26.8 | L31: =Rampas!S9 -> 138.05
A32: LAZER | K32: =SUM(K27:K31) -> 152.02
A33: PILARES | B33: =SUM(D33:I36) -> 36025 | C33: 1 | D33: 340 | E33: 280 | F33: 615 | H33: 745 | I33: 5370 | K33: =Pilares!M10 -> 37.7 | L33: =Pilares!P10 -> 345.99
A34: VIGAS | C34: 1 | D34: 190 | E34: 745 | F34: 1410 | G34: 2425 | H34: 7765 | I34: 11710 | K34: =Vigas!N9 -> 154.39 | L34: =Vigas!Q9 -> 594.61
A35: LAJES | C35: 1 | E35: 1255 | F35: 2100 | G35: 930 | K35: =Lajes!P10 -> 90 | L35: =Lajes!S10 -> 376.7 | M35: 10 | N35: =M35*(2.45*6) -> 147
A36: ESCADAS | C36: 1 | D36: 15 | E36: 25 | F36: 105 | K36: =Escadas!Q34 -> 3
A37: TIPOS | K37: =SUM(K33:K36) -> 285.09
A38: PILARES | B38: =SUM(D38:I41) -> 131200 | C38: 1 | D38: 6950 | E38: 4195 | F38: 875 | G38: 0 | H38: 32020 | I38: 4625 | K38: =Pilares!M11 -> 504.28 | L38: =Pilares!P11 -> 4413.15
A39: VIGAS | C39: 1 | D39: 2485 | E39: 7970 | F39: 1960 | G39: 3700 | H39: 28860 | I39: 7960 | K39: =Vigas!N10 -> 244.14 | L39: =Vigas!Q10 -> 2288.37
A40: LAJES | C40: 1 | D40: 800 | E40: 15200 | F40: 9600 | G40: 1100 | K40: =Lajes!P11 -> 616 | L40: =Lajes!S11 -> 822.8 | M40: 280 | N40: =M40*(2.45*6) -> 4116
A41: ESCADAS | C41: 1 | D41: 300 | E41: 500 | F41: 2100 | K41: =Escadas!Q48 -> 56 | L41: =Escadas!W11 -> 512.32673
A42: COBERTURA | K42: =SUM(K38:K41) -> 1420.42
A43: PILARES | B43: =SUM(D43:I46) -> 5130 | C43: 1 | D43: 365 | E43: 170 | H43: 1390 | K43: =Pilares!M12 -> 25.11 | L43: =Pilares!P12 -> 220.01
A44: VIGAS | C44: 1 | D44: 215 | E44: 250 | F44: 75 | G44: 495 | H44: 715 | K44: =Vigas!N11 -> 12.26 | L44: =Vigas!Q11 -> 115.59
A45: LAJES | C45: 1 | D45: 30 | E45: 745 | F45: 480 | G45: 55 | K45: =Lajes!P12 -> 30.4 | L45: =Lajes!S12 -> 41.14 | M45: 14 | N45: =M45*(2.45*6) -> 205.8
A46: ESCADAS | C46: 1 | D46: 15 | E46: 25 | F46: 105 | K46: =Escadas!Q55 -> 2.8 | L46: =Escadas!W12 -> 25.5983
A47: PAVIMENTOS TÉCNICOS | K47: =SUM(K43:K46) -> 70.57
A48: PILARES | B48: =SUM(D48:I50) -> 4555 | C48: 1 | D48: 275 | E48: 340 | G48: 45 | H48: 1315 | K48: =Pilares!M13 -> 24.97 | L48: =Pilares!P13 -> 215.22
A49: VIGAS | C49: 1 | D49: 35 | E49: 425 | F49: 335 | G49: 75 | H49: 740 | K49: =Vigas!N12 -> 12.46 | L49: =Vigas!Q12 -> 111.54
A50: LAJES | C50: 1 | E50: 395 | F50: 575 | K50: =Lajes!P13 -> 17.3 | L50: =Lajes!S13 -> 101.58
K51: =SUM(K48:K50) -> 54.73
B53: TOTAL - M | C53: =SUM(D53:J53) -> 229805 | D53: =SUMPRODUCT(D7:D52,$C7:$C52) -> 15210 | E53: =SUMPRODUCT(E7:E52,$C7:$C52) -> 39200 | F53: =SUMPRODUCT(F7:F52,$C7:$C52) -> 30320 | G53: =SUMPRODUCT(G7:G52,$C7:$C52) -> 11560 | H53: =SUMPRODUCT(H7:H52,$C7:$C52) -> 87630 | I53: =SUMPRODUCT(I7:I52,$C7:$C52) -> 45885 | J53: =SUMPRODUCT(J7:J52,$C7:$C52) -> 0 | K53: =K51+K47+K42+K32+K26+K20+K37 -> 2291.43 | M53: =SUMPRODUCT(M7:M52,$C7:$C52) -> 388 | N53: =SUMPRODUCT(N7:N52,$C7:$C52) -> 5703.6
B54: PESO kg/m | D54: 1 | E54: 1 | F54: 1 | G54: 1 | H54: 1 | I54: 1 | J54: 1 | M54: 1 | N54: 1
B55: TOTAL - kg | C55: =SUM(D55:J55) -> 229805 | D55: =D54*D53 -> 15210 | E55: =E54*E53 -> 39200 | F55: =F54*F53 -> 30320 | G55: =G54*G53 -> 11560 | H55: =H54*H53 -> 87630 | I55: =I54*I53 -> 45885 | J55: =J54*J53 -> 0 | M55: =M54*M53 -> 388 | N55: =N54*N53 -> 5703.6

Sheet ARQ.
A2: Descrição | B2: Unid. | C2: Quantidade
A4: 01_TÉRREO
A5: Alvenaria de vedação com blocos cerâmicos
A6: BLOCO CERAMICO, 11,5 cm | B6: m² | C6: 185.56
A7: BLOCO CERAMICO, 14 cm | B7: m² | C7: 331.42
A8: Alvenaria de vedação com bocos acf
A9: BLOCO ANTI-CHAMAS, 12,5 cm | B9: m² | C9: 177.81
A10: Serviços complementares para alvenaria
A11: ENCUNHAMENTO | B11: m | C11: 224.76
A12: TELA SOLDADA | B12: m² | C12: 348
A13: Verga e contraverga | B13: m | C13: 43.44
A14: Regularização e proteção mecânica
A15: REGULARIZAÇAO | B15: m² | C15: 23.42
A16: PROTEÇAO MECANICA | B16: m² | C16: 17.98
A17: Impermeabilizaçao e tratamentos
A18: IMPERMEABILIZAÇAO EM AREAS TECNICAS | B18: m² | C18: 34.94
A19: IMPERMEABILIZAÇAO EM AREAS TECNICAS // | B19: m² | C19: 5.39
A20: IMPERMEABILIZAÇAO EM BANHEIRO | B20: m² | C20: 23.48
A21: IMPERMEABILIZAÇAO EM BANHEIRO // | B21: m² | C21: 10.92
A22: IMPERMEABILIZAÇAO EM CENTRAL DE GAS/LIXEIRA | B22: m² | C22: 58.79
A23: IMPERMEABILIZAÇAO EM CENTRAL DE GAS/LIXEIRA // | B23: m² | C23: 9.91
A24: IMPERMEABILIZAÇAO EM FLOREIRAS | B24: m² | C24: 8.9
A25: IMPERMEABILIZAÇAO EM FOSSO ELEVADOR | B25: m² | C25: 93.82
A26: IMPERMEABILIZAÇAO EM FOSSO ELEVADOR // | B26: m² | C26: 7.11
A27: IMPERMEABILIZAÇAO EM TERRAÇOS // | B27: m² | C27: 8.06
A28: IMPERMEABILIZAÇAO EM VIGAS BALDRAME | B28: m² | C28: 353.36
A29: Contrapiso
A30: REVESTIMENTO - CONTRA PISO, 4 cm // | B30: m² | C30: 5.8
A31: REVESTIMENTO - CONTRA PISO, 5 cm // | B31: m² | C31: 14.4
A32: REVESTIMENTO - CONTRA PISO, 6 cm // | B32: m² | C32: 202.01
A33: REVESTIMENTO - CONTRA PISO, 8 cm // | B33: m² | C33: 8.6
A34: REVESTIMENTO - CONTRA PISO, REGULARIZAÇÃO 2 cm | B34: m² | C34: 10.66
A35: REVESTIMENTO - PINTURA RESINA, ESCADA/ANTECAMERA // REVESTIMENTO - CONTRA PISO, REGULARIZAÇÃO 2 cm | B35: m² | C35: 2.72
A36: Regularização
A37: REVESTIMENTO - REGULARIZAÇAO, 3 cm // | B37: m² | C37: 158.23
A38: REVESTIMENTO - REGULARIZAÇAO, 5 cm // | B38: m² | C38: 90.45
A39: Acabamentos cimentados
A40: REVESTIMENTO - PISO CONCRETO ESTAMPADO // | B40: m² | C40: 90.53
A41: REVESTIMENTO - POLIMENTO DE PISO // | B41: m² | C41: 245.5 | D41: 10.3661 | E41: =C41-D41 -> 235.1339 | F41: Considerar esse valor
A42: Chapisco Interno | D42: Camada extra de polimento de piso adicionada erroneamente no modelo
A43: .CHAPISCO ARGAMASSADO INTERNO | B43: m² | C43: 918.95
A44: .CHAPISCO ARGAMASSADO PARA ESTRUTURA INTERNO | B44: m² | C44: 238.42
A45: Reboco Interno
A46: .REBOCO ARGAMASSADO INTERNO | B46: m² | C46: 1157.37
A47: Estucamento
A48: .ESTUCAMENTO | B48: m² | C48: 120.08
A49: Revestimento interno argamassado em teto
A50: ESTUCAMENTO EM TETO COM PINTURA | B50: m² | C50: 434.07
A51: Acabamento de gesso em teto
A52: FORRO DE GESSO MINERAL | B52: m² | C52: 181.51
A53: Acabamentos cerâmicos em piso
A54: REVESTIMENTO - CERAMICA, A. COMUM INTERNA // | B54: m² | C54: 8.39
A55: REVESTIMENTO - CERAMICA, LIXEIRA/GN // | B55: m² | C55: 14.03
A56: REVESTIMENTO - LADRILHO HIDRAULICO // | B56: m² | C56: 143.9
A57: REVESTIMENTO - PORCELANATO, AREA COMUM INTERNA // | B57: m² | C57: 143.7
A58: REVESTIMENTO - PORCELANATO, HALL EXTERNO // | B58: m² | C58: 6.58
A59: REVESTIMENTO - PORCELANATO, HALL INTERNO // | B59: m² | C59: 35.11
A60: Rodapes
A61: RODAPE EM CERAMICA, 10 cm | B61: m | C61: 27.73
A62: RODAPE EM PEDRA NATURAL, 10 cm | B62: m | C62: 8.52
A63: RODAPE EM PEDRA NATURAL, 5 cm | B63: m | C63: 29.86
A64: RODAPE EM POLIESTIRENO, 10 cm | B64: m | C64: 100.56
A65: RODAPE EM POLIESTIRENO, 15 cm | B65: m | C65: 27.32
A66: Soleira
A67: REVESTIMENTO - SOLEIRA, PEDRA NATURAL // | B67: m² | C67: 1.86
A68: Acabamentos cerâmicos
A69: REVESTIMENTO INTERNO, PAREDE - CERAMICA, LIXEIRA/G.N | B69: m² | C69: 62.23
A70: Sistema de pintura em piso
A71: REVESTIMENTO - PINTURA EPOXI, DEMARCAÇAO DE VAGAS // | B71: m² | C71: 9.96
A72: REVESTIMENTO - PINTURA EPOXI, GARAGEM // | B72: m² | C72: 235.13
A73: REVESTIMENTO - PINTURA RESINA, A. TECNICA // | B73: m² | C73: 14.4
A74: REVESTIMENTO - PINTURA RESINA, ESCADA/ANTECAMERA | B74: m² | C74: 10.66
A75: REVESTIMENTO - PINTURA RESINA, ESCADA/ANTECAMERA // | B75: m² | C75: 31.35
A76: Sistemas de pintura em parede
A77: REVESTIMENTO INTERNO, PAREDE - PINTURA, A. COMUM | B77: m² | C77: 405.33
A78: REVESTIMENTO INTERNO, PAREDE - PINTURA, A. TECNICA | B78: m² | C78: 79.78
A79: REVESTIMENTO INTERNO, PAREDE - PINTURA, ESCADA/ANTECAMERA | B79: m² | C79: 105.04
A80: REVESTIMENTO INTERNO, PAREDE - PINTURA, FAIXA DE GARAGEM | B80: m² | C80: 30.31
A81: REVESTIMENTO INTERNO, PAREDE - PINTURA, GARAGEM | B81: m² | C81: 452.96
A82: REVESTIMENTO INTERNO, PAREDE - PINTURA, HALL | B82: m² | C82: 113.25
A83: Sistemas de pintura em teto
A84: PINTURA EM TETO | B84: m² | C84: 615.58
A85: Contramarco
A86: Contramarco | B86: m | C86: 116.78
A87: Esquadrias de alumínio
A88: DEA01 - JANELA FIXA, 1 FOLHA, TELA GALVANIZADA, 125 x 80 cm | B88: m² | C88: 1.04
A89: DEF02 - JANELA FIXA, 1 FOLHA, TELA GALVANIZADA, 125 x 80 cm | B89: m² | C89: 1.04
A90: P10 - PORTA DE ABRIR, 1 FOLHA, ALUMÍNIO VENEZIANA, 90 x 210 cm | B90: m² | C90: 1.89
A91: P11 - PORTA DE ABRIR, 1 FOLHA, ALUMÍNIO VENEZIANA, 90 x 210 cm | B91: m² | C91: 1.89
A92: P14 - PORTA DE CORRER, 1 FOLHA, ALUMINIO, 90 x 210 cm | B92: m² | C92: 2.21
A93: P15 - PORTA DE ABRIR, 2 FOLHAS, ALUMÍNIO VENEZIANA, 140 x 210 cm | B93: m² | C93: 2.94
A94: P16 - PORTA DE ABRIR, 2 FOLHAS, ALUMÍNIO VENEZIANA, 200 x 210 cm | B94: m² | C94: 4.2
A95: P17 - PORTA DE CORRER, 4 FOLHAS, ALUMÍNIO VENEZIANA, 400 x 210 cm | B95: m² | C95: 8.38
A96: P24 - PORTAO BASCULANTE, 1 FOLHA, ALUMÍNIO, 400 x 250 cm | B96: m² | C96: 3.29
A97: P25 - PORTA DE ABRIR, 1 FOLHA, VIDRO E ALUMÍNIO, 90 x 210 cm | B97: m² | C97: 1.89
A98: PB01 - PORTA DE ABRIR, 1 FOLHA + BANDEIRA, ALUMINIO E VIDRO, 260 x 296 cm | B98: m² | C98: 7.78
A99: PB02 - PORTA DE ABRIR, 1 FOLHA + BANDEIRA, ALUMINIO E VIDRO, 480 x 291 cm | B99: m² | C99: 14.08
A100: PB03 - PORTA DE ABRIR, 1 FOLHA + BANDEIRA, ALUMINIO E VIDRO, 490 x 291 cm | B100: m² | C100: 14.38
A101: Esquadrias de madeira
A102: CORRIMÃO ESCADA_PAREDE - MADEIRA | B102: m | C102: 17.92
...

Sheet IMPERM.
B1: Obra | C1: =ORÇAMENTO!I4 -> SENSE106
B2: Empresa | C2: =ORÇAMENTO!I5 -> HOLZE EMPREENDIMENTOS
B3: Data | C3: =ORÇAMENTO!P5 -> 45608
B4: Revisão | C4: =ORÇAMENTO!O5 -> R01 - Edileni Silva
A5: IMPERMEABILIZAÇÃO
B7: Descrição | C7: Impermeabilização | D7: Quantidade | F7: RESUMO POR ÁREA
F8: IMPERMEABILIZAÇAO EM AREAS TECNICAS | G8: =SUMIF($B$9:$D$89,F8,$D$9:$D$89) -> 300.07 | H8: m²
B9: FUNDAÇÕES | F9: IMPERMEABILIZAÇAO EM BANHEIRO | G9: =SUMIF($B$9:$D$89,F9,$D$9:$D$89) -> 1152.32 | H9: m²
B10: IMPERMEABILIZAÇAO RESERVATÓRIO ENTERRADO | C10: Impermeabilização cisterna | D10: =2.8*4.7*2-0.6*0.6+2.3*2.8*2+2.3*4.7*2 -> 60.46 | F10: IMPERMEABILIZAÇAO EM CENTRAL DE GAS/LIXEIRA | G10: =SUMIF($B$9:$D$89,F10,$D$9:$D$89) -> 68.7 | H10: m²
B11: IMPERMEABILIZAÇAO DUTO | C11: Impermeabilização duto | D11: =51.7827*2+53.4477*1.7+5.6375*2+7.55*2.05+2.05*0.35 -> 221.89649 | F11: IMPERMEABILIZAÇAO EM FLOREIRAS | G11: =SUMIF($B$9:$D$89,F11,$D$9:$D$89) -> 120.04 | H11: m²
B12: IMPERMEABILIZAÇAO EM ETE | C12: Impermeabilização com resina epóxi alcatrão | D12: =E93+E94+E95+E96 -> 70.685835 | F12: IMPERMEABILIZAÇAO EM FOSSO ELEVADOR | G12: =SUMIF($B$9:$D$89,F12,$D$9:$D$89) -> 100.93 | H12: m²
B13: IMPERMEABILIZAÇÃO TANQUE DE LODO | C13: Impermeabilização com resina epóxi alcatrão | D13: =E97 -> 31.573006 | F13: IMPERMEABILIZAÇAO EM TERRAÇOS | G13: =SUMIF($B$9:$D$89,F13,$D$9:$D$89) -> 582.05 | H13: m²
B14: IMPERMEABILIZAÇÃO CAPTAÇÃO DE ÁGUA DA CHUVA | C14: Impermeabilização de reservatório de água da chuva | D14: =E99 -> 14.137167 | F14: IMPERMEABILIZAÇAO EM VIGAS BALDRAME | G14: =SUMIF($B$9:$D$89,F14,$D$9:$D$89) -> 353.36 | H14: m²
B15: 01_TÉRREO | F15: IMPERMEABILIZAÇAO EM ESQUADRIAS | G15: =SUMIF($B$9:$D$89,F15,$D$9:$D$89) -> 250.3 | H15: m²
B16: Regularização e proteção mecânica | F16: IMPERMEABILIZAÇAO EM PISCINA | G16: =SUMIF($B$9:$D$89,F16,$D$9:$D$89) -> 131.51 | H16: m²
B17: REGULARIZAÇAO | D17: 23.42 | F17: IMPERMEABILIZAÇAO EM AREA DE SERVIÇO | G17: =SUMIF($B$9:$D$89,F17,$D$9:$D$89) -> 381.6 | H17: m²
B18: PROTEÇAO MECANICA | D18: 17.98 | F18: IMPERMEABILIZAÇAO EM BOX DE BANHEIRO | G18: =SUMIF($B$9:$D$89,F18,$D$9:$D$89) -> 568 | H18: m²
B19: Impermeabilizaçao e tratamentos | F19: IMPERMEABILIZAÇAO EM COZINHA | G19: =SUMIF($B$9:$D$89,F19,$D$9:$D$89) -> 351 | H19: m²
B20: IMPERMEABILIZAÇAO EM AREAS TECNICAS | C20: Impermeabilização flexível com manta - uma camada | D20: 34.94 | F20: IMPERMEABILIZAÇAO EM RESERVATORIOS | G20: =SUMIF($B$9:$D$89,F20,$D$9:$D$89) -> 107.97 | H20: m²
B21: IMPERMEABILIZAÇAO EM AREAS TECNICAS | C21: Impermeabilização flexível com manta - uma camada | D21: 5.39 | F21: IMPERMEABILIZAÇAO EM TAMPA DE RESERVATÓRIOS | G21: =SUMIF($B$9:$D$89,F21,$D$9:$D$89) -> 64.43 | H21: m²
B22: IMPERMEABILIZAÇAO EM BANHEIRO | C22: Impermeabilização com argamassa polimérica | D22: 23.48 | F22: IMPERMEABILIZAÇÃO EM PAREDE DIVISA VIZINHO | G22: =SUMIF($B$9:$D$89,F22,$D$9:$D$89) -> 398.3 | H22: m²
B23: IMPERMEABILIZAÇAO EM BANHEIRO | C23: Impermeabilização com argamassa polimérica | D23: 10.92 | F23: IMPERMEABILIZAÇAO RESERVATÓRIO ENTERRADO | G23: =SUMIF($B$9:$D$89,F23,$D$9:$D$89) -> 60.46 | H23: m²
B24: IMPERMEABILIZAÇAO EM CENTRAL DE GAS/LIXEIRA | C24: Impermeabilização com argamassa polimérica | D24: 58.79 | F24: IMPERMEABILIZAÇAO DUTO | G24: =SUMIF($B$9:$D$89,F24,$D$9:$D$89) -> 221.89649 | H24: m²
B25: IMPERMEABILIZAÇAO EM CENTRAL DE GAS/LIXEIRA | C25: Impermeabilização com argamassa polimérica | D25: 9.91 | F25: IMPERMEABILIZAÇAO EM ETE | G25: =SUMIF($B$9:$D$89,F25,$D$9:$D$89) -> 70.685835 | H25: m²
B26: IMPERMEABILIZAÇAO EM FLOREIRAS | C26: Impermeabilização flexível com manta - duas camadas | D26: 8.9 | F26: IMPERMEABILIZAÇÃO TANQUE DE LODO | G26: =SUMIF($B$9:$D$89,F26,$D$9:$D$89) -> 31.573006 | H26: m²
B27: IMPERMEABILIZAÇAO EM FOSSO ELEVADOR | C27: Impermeabilização com argamassa polimérica | D27: 93.82 | F27: IMPERMEABILIZAÇÃO CAPTAÇÃO DE ÁGUA DA CHUVA | G27: =SUMIF($B$9:$D$89,F27,$D$9:$D$89) -> 14.137167 | H27: m²
B28: IMPERMEABILIZAÇAO EM FOSSO ELEVADOR | C28: Impermeabilização com argamassa polimérica | D28: 7.11 | G28: =SUM(G8:G27) -> 5329.3325
B29: IMPERMEABILIZAÇAO EM TERRAÇOS | C29: Impermeabilização flexível com manta com asfalto derretido - uma camada | D29: 8.06
B30: IMPERMEABILIZAÇAO EM VIGAS BALDRAME | C30: Impermeabilização com tinta asfáltica em baldrames | D30: 353.36
B31: IMPERMEABILIZAÇÃO EM PAREDE DIVISA VIZINHO | C31: Pintura impermeaável para fachadas | D31: 102.9 | E31: 18kg/150m² | F31: DESCRIÇÃO
B32: 02_GARAGEM 02 | E32: =18/150 -> 0.12 | F32: Impermeabilização flexível com manta - uma camada | G32: =SUMIF($C$9:$D$89,F32,$D$9:$D$89) -> 364.5 | H32: m²
B33: IMPERMEABILIZAÇÃO EM PAREDE DIVISA VIZINHO | C33: Pintura impermeaável para fachadas | D33: 74.6 | E33: 18.3 | F33: Impermeabilização flexível com manta - duas camadas | G33: =SUMIF($C$9:$D$89,F33,$D$9:$D$89) -> 359.52 | H33: m²
B34: 03_GARAGEM 03 | F34: Impermeabilização flexível com manta com asfalto derretido - uma camada | G34: =SUMIF($C$9:$D$89,F34,$D$9:$D$89) -> 582.05 | H34: m²
B35: IMPERMEABILIZAÇÃO EM PAREDE DIVISA VIZINHO | C35: Pintura impermeaável para fachadas | D35: 74.6 | F35: Impermeabilização com argamassa polimérica em peitoris | G35: =SUMIF($C$9:$D$89,F35,$D$9:$D$89) -> 250.3 | H35: m²
B36: 04_GARAGEM 04 | F36: Impermeabilização com argamassa polimérica | G36: =SUMIF($C$9:$D$89,F36,$D$9:$D$89) -> 2622.55 | H36: m²
B37: IMPERMEABILIZAÇÃO EM PAREDE DIVISA VIZINHO | C37: Pintura impermeaável para fachadas | D37: 93.25 | F37: Pintura impermeaável para fachadas | G37: =SUMIF($C$9:$D$89,F37,$D$9:$D$89) -> 398.3 | H37: m²
B38: 05_LAZER | F38: Impermeabilização cisterna | G38: =SUMIF($C$9:$D$89,F38,$D$9:$D$89) -> 60.46 | H38: m²
B39: Regularização e proteção mecânica | F39: Impermeabilização duto | G39: =SUMIF($C$9:$D$89,F39,$D$9:$D$89) -> 221.89649 | H39: m²
B40: REGULARIZAÇAO | D40: 6.74 | F40: Impermeabilização com resina epóxi alcatrão | G40: =SUMIF($C$9:$D$89,F40,$D$9:$D$89) -> 102.25884 | H40: m²
B41: PROTEÇAO MECANICA | D41: 370.32 | F41: Impermeabilização de reservatório de água da chuva | G41: =SUMIF($C$9:$D$89,F41,$D$9:$D$89) -> 14.137167 | H41: m²
B42: Impermeabilizaçao e tratamentos | F42: Impermeabilização com tinta asfáltica em baldrames | G42: =SUMIF($C$9:$D$89,F42,$D$9:$D$89) -> 353.36 | H42: m²
B43: IMPERMEABILIZAÇAO EM BANHEIRO | C43: Impermeabilização com argamassa polimérica | D43: 15.58 | G43: =SUM(G32:G42) -> 5329.3325
B44: IMPERMEABILIZAÇAO EM BANHEIRO | C44: Impermeabilização com argamassa polimérica | D44: 6.74
B45: IMPERMEABILIZAÇAO EM ESQUADRIAS | C45: Impermeabilização com argamassa polimérica em peitoris | D45: 0.2
B46: IMPERMEABILIZAÇAO EM ESQUADRIAS | C46: Impermeabilização com argamassa polimérica em peitoris | D46: 0.1
B47: IMPERMEABILIZAÇAO EM FLOREIRAS | C47: Impermeabilização flexível com manta - duas camadas | D47: 60.49
B48: IMPERMEABILIZAÇAO EM FLOREIRAS | C48: Impermeabilização flexível com manta - duas camadas | D48: 50.65
B49: IMPERMEABILIZAÇAO EM PISCINA | C49: Impermeabilização flexível com manta - duas camadas | D49: 54.01
B50: IMPERMEABILIZAÇAO EM PISCINA | C50: Impermeabilização flexível com manta - duas camadas | D50: 77.5
B51: IMPERMEABILIZAÇAO EM TERRAÇOS | C51: Impermeabilização flexível com manta com asfalto derretido - uma camada | D51: 65.01
B52: IMPERMEABILIZAÇAO EM TERRAÇOS | C52: Impermeabilização flexível com manta com asfalto derretido - uma camada | D52: 242.16
B53: IMPERMEABILIZAÇÃO EM PAREDE DIVISA VIZINHO | C53: Pintura impermeaável para fachadas | D53: 52.95
B54: 06-25_TIPOS
B55: Regularização e proteção mecânica
B56: REGULARIZAÇAO | D56: 875.2
B57: Impermeabilizaçao e tratamentos
B58: IMPERMEABILIZAÇAO EM AREA DE SERVIÇO | C58: Impermeabilização com argamassa polimérica | D58: 242
B59: IMPERMEABILIZAÇAO EM AREA DE SERVIÇO | C59: Impermeabilização com argamassa polimérica | D59: 139.6
B60: IMPERMEABILIZAÇAO EM AREAS TECNICAS | C60: Impermeabilização flexível com manta - uma camada | D60: 66.2
B61: IMPERMEABILIZAÇAO EM AREAS TECNICAS | C61: Impermeabilização flexível com manta - uma camada | D61: 128.8
B62: IMPERMEABILIZAÇAO EM BANHEIRO | C62: Impermeabilização com argamassa polimérica | D62: 736.6
B63: IMPERMEABILIZAÇAO EM BANHEIRO | C63: Impermeabilização com argamassa polimérica | D63: 359
B64: IMPERMEABILIZAÇAO EM BOX DE BANHEIRO | C64: Impermeabilização com argamassa polimérica | D64: 459.4
B65: IMPERMEABILIZAÇAO EM BOX DE BANHEIRO | C65: Impermeabilização com argamassa polimérica | D65: 108.6
B66: IMPERMEABILIZAÇAO EM COZINHA | C66: Impermeabilização com argamassa polimérica | D66: 212
B67: IMPERMEABILIZAÇAO EM COZINHA | C67: Impermeabilização com argamassa polimérica | D67: 139
B68: IMPERMEABILIZAÇAO EM ESQUADRIAS | C68: Impermeabilização com argamassa polimérica em peitoris | D68: 190.2
B69: IMPERMEABILIZAÇAO EM ESQUADRIAS | C69: Impermeabilização com argamassa polimérica em peitoris | D69: 59.8
B70: 26_TELHADO
B71: Regularização e proteção mecânica
B72: REGULARIZAÇAO | D72: 6.53
B73: PROTEÇAO MECANICA | D73: 184.71
B74: Impermeabilizaçao e tratamentos
B75: IMPERMEABILIZAÇAO EM AREAS TECNICAS | C75: Impermeabilização flexível com manta - uma camada | D75: 58.21
B76: IMPERMEABILIZAÇAO EM AREAS TECNICAS | C76: Impermeabilização flexível com manta - uma camada | D76: 6.53
B77: IMPERMEABILIZAÇAO EM TERRAÇOS | C77: Impermeabilização flexível com manta com asfalto derretido - uma camada | D77: 82.11
B78: IMPERMEABILIZAÇAO EM TERRAÇOS | C78: Impermeabilização flexível com manta com asfalto derretido - uma camada | D78: 184.71
B79: 27_RESERV. SUPERIOR
B80: Regularização e proteção mecânica
B81: REGULARIZAÇAO | D81: 38.8
B82: Impermeabilizaçao e tratamentos
B83: IMPERMEABILIZAÇAO EM RESERVATORIOS | C83: Impermeabilização flexível com manta - duas camadas | D83: 69.17
B84: IMPERMEABILIZAÇAO EM RESERVATORIOS | C84: Impermeabilização flexível com manta - duas camadas | D84: 38.8
B85: 28_TAMPA RESERV. SUP
B86: Regularização e proteção mecânica
B87: PROTEÇAO MECANICA | D87: 64.43
B88: Impermeabilizaçao e tratamentos
B89: IMPERMEABILIZAÇAO EM TAMPA DE RESERVATÓRIOS | C89: Impermeabilização flexível com manta - uma camada | D89: 64.43
C92: Diâmetro | D92: Altura útil | E92: Área impermeabilização
B93: DECANTADOR PRIMARIO | C93: 2 | D93: 1.15 | E93: =2*PI()*(C93/2)*(C93/2+D93) -> 13.508848
B94: REATOR | C94: 3 | D94: 2.2 | E94: =2*PI()*(C94/2)*(C94/2+D94) -> 34.871678
B95: DECANTADOR SECUNDÁRIO | C95: 2 | D95: 1.65 | E95: =2*PI()*(C95/2)*(C95/2+D95) -> 16.650441
B96: DESINFCÇÃO | C96: 1 | D96: 1.3 | E96: =2*PI()*(C96/2)*(C96/2+D96) -> 5.6548668
B97: TANQUE DE DESCARTE DE LODO | C97: 3 | D97: 1.85 | E97: =2*PI()*(C97/2)*(C97/2+D97) -> 31.573006
B99: CAP. ÁGUA CHUVA | C99: 2 | D99: 1.25 | E99: =2*PI()*(C99/2)*(C99/2+D99) -> 14.137167
C102: Impermeabilização flexível com manta | D102: =G32+G33 -> 724.02 | E102: m²
C103: Impermeabilização flexível com manta com asfalto derretido - uma camada | D103: =G34 -> 582.05 | E103: m²
C104: Impermeabilização com argamassa polimérica | D104: =G35+G36 -> 2872.85 | E104: m²
C105: Impermeabilização com resina epóxi alcatrão | D105: =G40 -> 102.25884 | E105: m²

Sheet FACHADA
A2: Descrição | B2: Unid. | C2: Quantidade
A4: Sistema de pintura em piso
A5: REVESTIMENTO EXTERNO - PINTURA PARA FACHADA, COR ELEFANTE // | B5: m² | C5: 28.01
A6: Chapisco externo
A7: FACHADA FRONTAL - .CHAPISCO ARGAMASSADO EXTERNO | B7: m² | C7: 880.51
A8: FACHADA LATERAL DIREITA - .CHAPISCO ARGAMASSADO EXTERNO | B8: m² | C8: 583.44
A9: FACHADA LATERAL ESQUERDA - .CHAPISCO ARGAMASSADO EXTERNO | B9: m² | C9: 974.98
A10: FACHADA POSTERIOR - .CHAPISCO ARGAMASSADO EXTERNO | B10: m² | C10: 850.1
A11: FACHADA FRONTAL - .CHAPISCO ARGAMASSADO PARA ESTRUTURA EXTERNO | B11: m² | C11: 225.24
A12: FACHADA LATERAL DIREITA - .CHAPISCO ARGAMASSADO PARA ESTRUTURA EXTERNO | B12: m² | C12: 682.58
A13: FACHADA LATERAL ESQUERDA - .CHAPISCO ARGAMASSADO PARA ESTRUTURA EXTERNO | B13: m² | C13: 632.77
A14: FACHADA POSTERIOR - .CHAPISCO ARGAMASSADO PARA ESTRUTURA EXTERNO | B14: m² | C14: 494.17
A15: Reboco externo
A16: FACHADA FRONTAL - .REBOCO ARGAMASSADO EXTERNO | B16: m² | C16: 1105.74
A17: FACHADA LATERAL DIREITA - .REBOCO ARGAMASSADO EXTERNO | B17: m² | C17: 1266.02
A18: FACHADA LATERAL ESQUERDA - .REBOCO ARGAMASSADO EXTERNO | B18: m² | C18: 1607.75
A19: FACHADA POSTERIOR - .REBOCO ARGAMASSADO EXTERNO | B19: m² | C19: 1344.27
A20: Pintura e textura em fachada
A21: FACHADA FRONTAL - REVESTIMENTO EXTERNO - PINTURA PARA FACHADA, ELEFANTE | B21: m² | C21: 129.02
A22: FACHADA FRONTAL - REVESTIMENTO EXTERNO - PINTURA PARA FACHADA, PATATIVA | B22: m² | C22: 70.59
A23: FACHADA FRONTAL - REVESTIMENTO EXTERNO - TEXTURA GRAFIATO PARA FACHADA, ELEFANTE | B23: m² | C23: 162.12
A24: FACHADA FRONTAL - REVESTIMENTO EXTERNO - TEXTURA GRAFIATO PARA FACHADA, NANQUIM | B24: m² | C24: 142.89
A25: FACHADA FRONTAL - REVESTIMENTO EXTERNO - TEXTURA GRAFIATO PARA FACHADA,PATATIVA | B25: m² | C25: 41.03
A26: FACHADA FRONTAL - REVESTIMENTO EXTERNO - TEXTURA GRAFITO PARA FACHADA, ELEFANTE | B26: m² | C26: 354.09
A27: FACHADA LATERAL DIREITA - REVESTIMENTO EXTERNO - TEXTURA GRAFIATO PARA FACHADA, ELEFANTE | B27: m² | C27: 662.39
A28: FACHADA LATERAL DIREITA - REVESTIMENTO EXTERNO - TEXTURA GRAFIATO PARA FACHADA,PATATIVA | B28: m² | C28: 20.19
A29: FACHADA LATERAL DIREITA - REVESTIMENTO EXTERNO - TEXTURA GRAFITO PARA FACHADA, ELEFANTE | B29: m² | C29: 539.16
A30: FACHADA LATERAL DIREITA - REVESTIMENTO EXTERNO - TEXTURA PARA FACHADA, LAZER EXTERNO | B30: m² | C30: 44.27
A31: FACHADA LATERAL ESQUERDA - REVESTIMENTO EXTERNO - PINTURA PARA FACHADA, DIVISA VIZINHO | B31: m² | C31: 389.48
A32: FACHADA LATERAL ESQUERDA - REVESTIMENTO EXTERNO - TEXTURA GRAFIATO PARA FACHADA, ELEFANTE | B32: m² | C32: 522.17
... A40: FACHADA POSTERIOR - REVESTIMENTO EXTERNO - TEXTURA PARA FACHADA, LAZER EXTERNO | B40: m² | C40: 62.13
A41: Acabamentos especiais em fachada
A42: FACHADA FRONTAL - 0303_CERAMICA MADEIRA ALVENARIA FACHADA - REVESTIMENTO EXTERNO - CERAMICA PARA FACHADA | B42: m² | C42: 59.9
A43: FACHADA LATERAL ESQUERDA - 0303_CERAMICA MADEIRA ALVENARIA FACHADA - REVESTIMENTO EXTERNO - CERAMICA PARA FACHADA | B43: m² | C43: 5.14
A44: FACHADA FRONTAL - 0304_CERAMICA MADEIRA ESTRUTURA FACHADA - REVESTIMENTO EXTERNO - CERAMICA PARA FACHADA | B44: m² | C44: 20.58
A45: FACHADA FRONTAL - 0305_CERAMICA VERTICAL ALVENARIA FACHADA - REVESTIMENTO EXTERNO - CERAMICA PARA FACHADA | B45: m² | C45: 104
A46: FACHADA FRONTAL - 0306_CERAMICA VERTICAL ESTRUTURA FACHADA - REVESTIMENTO EXTERNO - CERAMICA PARA FACHADA | B46: m² | C46: 21.52
A47: FACHADA LATERAL ESQUERDA - 0307_CERAMICA MADEIRA ALVENARIA FACHADA, DIVISA VIZINHO - REVESTIMENTO EXTERNO - CERAMICA PARA FACHADA | B47: m² | C47: 5.29
A48: FACHADA LATERAL ESQUERDA - 0308_CERAMICA MADEIRA ESTRUTURA FACHADA - DIVISA VIZINHO - REVESTIMENTO EXTERNO - CERAMICA PARA FACHADA | B48: m² | C48: 0.51
A51: FRONTAL
A52: FACHADA FRONTAL - .CHAPISCO ARGAMASSADO PARA ESTRUTURA EXTERNO | B52: =SUMIF($A$4:$C$48,A52,$C$4:$C$48) -> 225.24
A53: FACHADA FRONTAL - .CHAPISCO ARGAMASSADO EXTERNO | B53: =SUMIF($A$4:$C$48,A53,$C$4:$C$48) -> 880.51
A54: FACHADA FRONTAL - .REBOCO ARGAMASSADO EXTERNO | B54: =SUMIF($A$4:$C$48,A54,$C$4:$C$48) -> 1105.74
A55: FACHADA FRONTAL - REVESTIMENTO EXTERNO - PINTURA PARA FACHADA, ELEFANTE | B55: =SUMIF($A$4:$C$48,A55,$C$4:$C$48) -> 129.02
A56: FACHADA FRONTAL - REVESTIMENTO EXTERNO - PINTURA PARA FACHADA, PATATIVA | B56: =SUMIF($A$4:$C$48,A56,$C$4:$C$48) -> 70.59
A57: FACHADA FRONTAL - REVESTIMENTO EXTERNO - TEXTURA GRAFIATO PARA FACHADA, ELEFANTE | B57: =SUMIF($A$4:$C$48,A57,$C$4:$C$48) -> 162.12
A58: FACHADA FRONTAL - REVESTIMENTO EXTERNO - TEXTURA GRAFIATO PARA FACHADA, NANQUIM | B58: =SUMIF($A$4:$C$48,A58,$C$4:$C$48) -> 142.89
A59: FACHADA FRONTAL - REVESTIMENTO EXTERNO - TEXTURA GRAFIATO PARA FACHADA,PATATIVA | B59: =SUMIF($A$4:$C$48,A59,$C$4:$C$48) -> 41.03
A60: FACHADA FRONTAL - REVESTIMENTO EXTERNO - TEXTURA GRAFITO PARA FACHADA, ELEFANTE | B60: =SUMIF($A$4:$C$48,A60,$C$4:$C$48) -> 354.09
A61: FACHADA FRONTAL - 0303_CERAMICA MADEIRA ALVENARIA FACHADA - REVESTIMENTO EXTERNO - CERAMICA PARA FACHADA | B61: =SUMIF($A$4:$C$48,A61,$C$4:$C$48) -> 59.9
A62: FACHADA FRONTAL - 0304_CERAMICA MADEIRA ESTRUTURA FACHADA - REVESTIMENTO EXTERNO - CERAMICA PARA FACHADA | B62: =SUMIF($A$4:$C$48,A62,$C$4:$C$48) -> 20.58
A63: FACHADA FRONTAL - 0305_CERAMICA VERTICAL ALVENARIA FACHADA - REVESTIMENTO EXTERNO - CERAMICA PARA FACHADA | B63: =SUMIF($A$4:$C$48,A63,$C$4:$C$48) -> 104
A64: FACHADA FRONTAL - 0306_CERAMICA VERTICAL ESTRUTURA FACHADA - REVESTIMENTO EXTERNO - CERAMICA PARA FACHADA | B64: =SUMIF($A$4:$C$48,A64,$C$4:$C$48) -> 21.52
A65: REVESTIMENTO EXTERNO - PINTURA PARA FACHADA, COR ELEFANTE // | B65: =SUMIF($A$4:$C$48,A65,$C$4:$C$48) -> 28.01 | C65: =SUM(B52:B65) -> 3345.24
A67: LATERAL DIREITA
A68: FACHADA LATERAL DIREITA - .CHAPISCO ARGAMASSADO PARA ESTRUTURA EXTERNO | B68: =SUMIF($A$4:$C$48,A68,$C$4:$C$48) -> 682.58
A69: FACHADA LATERAL DIREITA - .CHAPISCO ARGAMASSADO EXTERNO | B69: =SUMIF($A$4:$C$48,A69,$C$4:$C$48) -> 583.44
A70: FACHADA LATERAL DIREITA - .REBOCO ARGAMASSADO EXTERNO | B70: =SUMIF($A$4:$C$48,A70,$C$4:$C$48) -> 1266.02
A71: FACHADA LATERAL DIREITA - REVESTIMENTO EXTERNO - TEXTURA GRAFIATO PARA FACHADA, ELEFANTE | B71: =SUMIF($A$4:$C$48,A71,$C$4:$C$48) -> 662.39
A72: FACHADA LATERAL DIREITA - REVESTIMENTO EXTERNO - TEXTURA GRAFIATO PARA FACHADA,PATATIVA | B72: =SUMIF($A$4:$C$48,A72,$C$4:$C$48) -> 20.19
A73: FACHADA LATERAL DIREITA - REVESTIMENTO EXTERNO - TEXTURA GRAFITO PARA FACHADA, ELEFANTE | B73: =SUMIF($A$4:$C$48,A73,$C$4:$C$48) -> 539.16
A74: FACHADA LATERAL DIREITA - REVESTIMENTO EXTERNO - TEXTURA PARA FACHADA, LAZER EXTERNO | B74: =SUMIF($A$4:$C$48,A74,$C$4:$C$48) -> 44.27 | C74: =SUM(B68:B74) -> 3798.05
A76: LATERAL ESQUERDA
A77: FACHADA LATERAL ESQUERDA - .CHAPISCO ARGAMASSADO PARA ESTRUTURA EXTERNO | B77: =SUMIF($A$4:$C$48,A77,$C$4:$C$48) -> 632.77
A78: FACHADA LATERAL ESQUERDA - .CHAPISCO ARGAMASSADO EXTERNO | B78: =SUMIF($A$4:$C$48,A78,$C$4:$C$48) -> 974.98
A79: FACHADA LATERAL ESQUERDA - .REBOCO ARGAMASSADO EXTERNO | B79: =SUMIF($A$4:$C$48,A79,$C$4:$C$48) -> 1607.75
A80: FACHADA LATERAL ESQUERDA - REVESTIMENTO EXTERNO - PINTURA PARA FACHADA, DIVISA VIZINHO | B80: =SUMIF($A$4:$C$48,A80,$C$4:$C$48) -> 389.48
A81: FACHADA LATERAL ESQUERDA - REVESTIMENTO EXTERNO - TEXTURA GRAFIATO PARA FACHADA, ELEFANTE | B81: =SUMIF($A$4:$C$48,A81,$C$4:$C$48) -> 522.17
A82: FACHADA LATERAL ESQUERDA - REVESTIMENTO EXTERNO - TEXTURA GRAFIATO PARA FACHADA,PATATIVA | B82: =SUMIF($A$4:$C$48,A82,$C$4:$C$48) -> 31.2
A83: FACHADA LATERAL ESQUERDA - REVESTIMENTO EXTERNO - TEXTURA GRAFITO PARA FACHADA, ELEFANTE | B83: =SUMIF($A$4:$C$48,A83,$C$4:$C$48) -> 582.39
A84: FACHADA LATERAL ESQUERDA - REVESTIMENTO EXTERNO - TEXTURA PARA FACHADA, LAZER EXTERNO | B84: =SUMIF($A$4:$C$48,A84,$C$4:$C$48) -> 71.57
A85: FACHADA LATERAL ESQUERDA - 0303_CERAMICA MADEIRA ALVENARIA FACHADA - REVESTIMENTO EXTERNO - CERAMICA PARA FACHADA | B85: =SUMIF($A$4:$C$48,A85,$C$4:$C$48) -> 5.14
A86: FACHADA LATERAL ESQUERDA - 0307_CERAMICA MADEIRA ALVENARIA FACHADA, DIVISA VIZINHO - REVESTIMENTO EXTERNO - CERAMICA PARA FACHADA | B86: =SUMIF($A$4:$C$48,A86,$C$4:$C$48) -> 5.29
A87: FACHADA LATERAL ESQUERDA - 0308_CERAMICA MADEIRA ESTRUTURA FACHADA - DIVISA VIZINHO - REVESTIMENTO EXTERNO - CERAMICA PARA FACHADA | B87: =SUMIF($A$4:$C$48,A87,$C$4:$C$48) -> 0.51 | C87: =SUM(B77:B87) -> 4823.25
A89: POSTERIOR
A90: FACHADA POSTERIOR - .CHAPISCO ARGAMASSADO PARA ESTRUTURA EXTERNO | B90: =SUMIF($A$4:$C$48,A90,$C$4:$C$48) -> 494.17
A91: FACHADA POSTERIOR - .CHAPISCO ARGAMASSADO EXTERNO | B91: =SUMIF($A$4:$C$48,A91,$C$4:$C$48) -> 850.1
A92: FACHADA POSTERIOR - .REBOCO ARGAMASSADO EXTERNO | B92: =SUMIF($A$4:$C$48,A92,$C$4:$C$48) -> 1344.27
A93: FACHADA POSTERIOR - REVESTIMENTO EXTERNO - PINTURA PARA FACHADA, DIVISA VIZINHO | B93: =SUMIF($A$4:$C$48,A93,$C$4:$C$48) -> 394.63
A94: FACHADA POSTERIOR - REVESTIMENTO EXTERNO - TEXTURA GRAFIATO PARA FACHADA, ELEFANTE | B94: =SUMIF($A$4:$C$48,A94,$C$4:$C$48) -> 392.61
A95: FACHADA POSTERIOR - REVESTIMENTO EXTERNO - TEXTURA GRAFIATO PARA FACHADA,PATATIVA | B95: =SUMIF($A$4:$C$48,A95,$C$4:$C$48) -> 15.68
A96: FACHADA POSTERIOR - REVESTIMENTO EXTERNO - TEXTURA GRAFITO PARA FACHADA, ELEFANTE | B96: =SUMIF($A$4:$C$48,A96,$C$4:$C$48) -> 479.21
A97: FACHADA POSTERIOR - REVESTIMENTO EXTERNO - TEXTURA PARA FACHADA, LAZER EXTERNO | B97: =SUMIF($A$4:$C$48,A97,$C$4:$C$48) -> 62.13 | C97: =SUM(B90:B97) -> 4032.8

Sheet ESQ. ALUM.
B1: Obra | C1: =ORÇAMENTO!I4 -> SENSE106
B2: Empresa | C2: =ORÇAMENTO!I5 -> HOLZE EMPREENDIMENTOS
B3: Data | C3: =ORÇAMENTO!P5 -> 45608
B4: Revisão | C4: =ORÇAMENTO!O5 -> R01 - Edileni Silva
A5: ESQUADRIAS DE ALUMÍNIO
A6: Pavimento | B6: Tipo | C6: Identificador | D6: Descrição | E6: Quantidade (un) | F6: Largura (m) | G6: Altura (m) | H6: Repetição | I6: Area (m²) | J6: Pingadeira | K6: Verga | L6: Contra-verga | M6: Observações
A7: TERREO | J7: =J8+J11 -> 30 | K7: =K8+K11 -> 34.5 | L7: =L8+L11 -> 43.5
A8: =A7 -> TERREO | B8: JANELA | J8: =SUM(J9:J10) -> 2.5 | K8: =SUM(K9:K10) -> 3.1 | L8: =SUM(L9:L10) -> 4.3
A9: =A7 -> TERREO | B9: =B8 -> JANELA | D9: DEA01 - JANELA FIXA, 1 FOLHA, TELA GALVANIZADA, 125 x 80 cm | E9: 1 | F9: 1.25 | G9: 0.8 | H9: 1 | I9: =H9*G9*F9*E9 -> 1 | J9: =F9*H9*E9 -> 1.25 | K9: =IF(F9<1.5,(F9+0.15*2),(F9+0.2*2))*H9*E9 -> 1.55 | L9: =IF(F9<1.5,(F9+0.45*2),(F9+0.6*2))*H9*E9 -> 2.15
A10: =A8 -> TERREO | B10: =B9 -> JANELA | D10: DEF02 - JANELA FIXA, 1 FOLHA, TELA GALVANIZADA, 125 x 80 cm | E10: 1 | F10: 1.25 | G10: 0.8 | H10: 1 | I10: =H10*G10*F10*E10 -> 1 | J10: =F10*H10*E10 -> 1.25 | K10: =IF(F10<1.5,(F10+0.15*2),(F10+0.2*2))*H10*E10 -> 1.55 | L10: =IF(F10<1.5,(F10+0.45*2),(F10+0.6*2))*H10*E10 -> 2.15
A11: =A8 -> TERREO | B11: PORTA | J11: =SUM(J12:J22) -> 27.5 | K11: =SUM(K12:K22) -> 31.4 | L11: =SUM(L12:L22) -> 39.2
A12: =A9 -> TERREO | B12: =B11 -> PORTA | D12: P10 - PORTA DE ABRIR, 1 FOLHA, ALUMÍNIO VENEZIANA, 90 x 210 cm | E12: 1 | F12: 0.9 | G12: 2.1 | H12: 1 | I12: =H12*G12*F12*E12 -> 1.89 | J12: =F12*H12*E12 -> 0.9 | K12: =IF(F12<1.5,(F12+0.15*2),(F12+0.2*2))*H12*E12 -> 1.2 | L12: =IF(F12<1.5,(F12+0.45*2),(F12+0.6*2))*H12*E12 -> 1.8
A13: =A11 -> TERREO | B13: =B12 -> PORTA | D13: P11 - PORTA DE ABRIR, 1 FOLHA, ALUMÍNIO VENEZIANA, 110 x 210 cm | E13: 1 | F13: 1.1 | G13: 2.1 | H13: 1 | I13: =H13*G13*F13*E13 -> 2.31 | J13: =F13*H13*E13 -> 1.1 | K13: =IF(F13<1.5,(F13+0.15*2),(F13+0.2*2))*H13*E13 -> 1.4 | L13: =IF(F13<1.5,(F13+0.45*2),(F13+0.6*2))*H13*E13 -> 2
A14: =A12 -> TERREO | B14: =B13 -> PORTA | D14: P14 - PORTA DE CORRER, 1 FOLHA, ALUMINIO, 90 x 210 cm | E14: 1 | F14: 0.9 | G14: 2.1 | H14: 1 | I14: =H14*G14*F14*E14 -> 1.89 | J14: =F14*H14*E14 -> 0.9 | K14: =IF(F14<1.5,(F14+0.15*2),(F14+0.2*2))*H14*E14 -> 1.2 | L14: =IF(F14<1.5,(F14+0.45*2),(F14+0.6*2))*H14*E14 -> 1.8
A15: =A13 -> TERREO | B15: =B14 -> PORTA | D15: P15 - PORTA DE ABRIR, 2 FOLHAS, ALUMÍNIO VENEZIANA, 140 x 210 cm | E15: 1 | F15: 1.4 | G15: 2.1 | H15: 1 | I15: =H15*G15*F15*E15 -> 2.94 | J15: =F15*H15*E15 -> 1.4 | K15: =IF(F15<1.5,(F15+0.15*2),(F15+0.2*2))*H15*E15 -> 1.7 | L15: =IF(F15<1.5,(F15+0.45*2),(F15+0.6*2))*H15*E15 -> 2.3
A16: =A14 -> TERREO | B16: =B15 -> PORTA | D16: P16 - PORTA DE ABRIR, 2 FOLHAS, ALUMÍNIO VENEZIANA, 200 x 210 cm | E16: 1 | F16: 2 | G16: 2.1 | H16: 1 | I16: =H16*G16*F16*E16 -> 4.2 | J16: =F16*H16*E16 -> 2 | K16: =IF(F16<1.5,(F16+0.15*2),(F16+0.2*2))*H16*E16 -> 2.4 | L16: =IF(F16<1.5,(F16+0.45*2),(F16+0.6*2))*H16*E16 -> 3.2
A17: =A15 -> TERREO | B17: =B16 -> PORTA | D17: P17 - PORTA DE CORRER, 4 FOLHAS, ALUMÍNIO VENEZIANA, 400 x 210 cm | E17: 1 | F17: 4 | G17: 2.1 | H17: 1 | I17: =H17*G17*F17*E17 -> 8.4 | J17: =F17*H17*E17 -> 4 | K17: =IF(F17<1.5,(F17+0.15*2),(F17+0.2*2))*H17*E17 -> 4.4 | L17: =IF(F17<1.5,(F17+0.45*2),(F17+0.6*2))*H17*E17 -> 5.2
A18: =A16 -> TERREO | B18: =B17 -> PORTA | D18: P24 - PORTAO BASCULANTE, 1 FOLHA, ALUMÍNIO, 400 x 250 cm | E18: 1 | F18: 4 | G18: 2.5 | H18: 1 | I18: =H18*G18*F18*E18 -> 10 | J18: =F18*H18*E18 -> 4 | K18: =IF(F18<1.5,(F18+0.15*2),(F18+0.2*2))*H18*E18 -> 4.4 | L18: =IF(F18<1.5,(F18+0.45*2),(F18+0.6*2))*H18*E18 -> 5.2
A19: =A17 -> TERREO | B19: =B18 -> PORTA | D19: P25 - PORTA DE ABRIR, 1 FOLHA, VIDRO E ALUMÍNIO, 90 x 210 cm | E19: 1 | F19: 0.9 | G19: 2.1 | H19: 1 | I19: =H19*G19*F19*E19 -> 1.89 | J19: =F19*H19*E19 -> 0.9 | K19: =IF(F19<1.5,(F19+0.15*2),(F19+0.2*2))*H19*E19 -> 1.2 | L19: =IF(F19<1.5,(F19+0.45*2),(F19+0.6*2))*H19*E19 -> 1.8
A20: =A18 -> TERREO | B20: =B19 -> PORTA | D20: PB01 - PORTA DE ABRIR, 1 FOLHA + BANDEIRA, ALUMINIO E VIDRO, 260 x 296 cm | E20: 1 | F20: 2.6 | G20: 2.96 | H20: 1 | I20: =H20*G20*F20*E20 -> 7.696 | J20: =F20*H20*E20 -> 2.6 | K20: =IF(F20<1.5,(F20+0.15*2),(F20+0.2*2))*H20*E20 -> 3 | L20: =IF(F20<1.5,(F20+0.45*2),(F20+0.6*2))*H20*E20 -> 3.8
A21: =A19 -> TERREO | B21: =B20 -> PORTA | D21: PB02 - PORTA DE ABRIR, 1 FOLHA + BANDEIRA, ALUMINIO E VIDRO, 480 x 291 cm | E21: 1 | F21: 4.8 | G21: 2.91 | H21: 1 | I21: =H21*G21*F21*E21 -> 13.968 | J21: =F21*H21*E21 -> 4.8 | K21: =IF(F21<1.5,(F21+0.15*2),(F21+0.2*2))*H21*E21 -> 5.2 | L21: =IF(F21<1.5,(F21+0.45*2),(F21+0.6*2))*H21*E21 -> 6
A22: =A20 -> TERREO | B22: =B21 -> PORTA | D22: PB03 - PORTA DE ABRIR, 1 FOLHA + BANDEIRA, ALUMINIO E VIDRO, 490 x 291 cm | E22: 1 | F22: 4.9 | G22: 2.91 | H22: 1 | I22: =H22*G22*F22*E22 -> 14.259 | J22: =F22*H22*E22 -> 4.9 | K22: =IF(F22<1.5,(F22+0.15*2),(F22+0.2*2))*H22*E22 -> 5.3 | L22: =IF(F22<1.5,(F22+0.45*2),(F22+0.6*2))*H22*E22 -> 6.1
A23: GARAGEM 2 | J23: =J24+J29 -> 24.55 | L23: =L24+L29 -> 48.85
A24: =A23 -> GARAGEM 2 | B24: JANELA | J24: =SUM(J25:J28) -> 12.55 | K24: =SUM(K25:K28) -> 14.65 | L24: =SUM(L25:L28) -> 18.85
A25: =A24 -> GARAGEM 2 | B25: =B24 -> JANELA | D25: DEA01 - JANELA FIXA, 1 FOLHA, TELA GALVANIZADA, 125 x 80 cm | E25: 1 | F25: 1.25 | G25: 0.8 | H25: 1 | I25: =H25*G25*F25*E25 -> 1 | J25: =F25*H25*E25 -> 1.25 | K25: =IF(F25<1.5,(F25+0.15*2),(F25+0.2*2))*H25*E25 -> 1.55 | L25: =IF(F25<1.5,(F25+0.45*2),(F25+0.6*2))*H25*E25 -> 2.15
A26: =A25 -> GARAGEM 2 | B26: =B10 -> JANELA | D26: DEF02 - JANELA FIXA, 1 FOLHA, TELA GALVANIZADA, 125 x 80 cm | E26: 2 | F26: 1.25 | G26: 0.8 | H26: 1 | I26: =H26*G26*F26*E26 -> 2 | J26: =F26*H26*E26 -> 2.5 | K26: =IF(F26<1.5,(F26+0.15*2),(F26+0.2*2))*H26*E26 -> 3.1 | L26: =IF(F26<1.5,(F26+0.45*2),(F26+0.6*2))*H26*E26 -> 4.3
A27: =A26 -> GARAGEM 2 | B27: =B26 -> JANELA | D27: J5 - JANELA FIXA, ALUMINIO 200 x 238 cm | E27: 2 | F27: 2 | G27: 2.38 | H27: 1 | I27: =H27*G27*F27*E27 -> 9.52 | J27: =F27*H27*E27 -> 4 | K27: =IF(F27<1.5,(F27+0.15*2),(F27+0.2*2))*H27*E27 -> 4.8 | L27: =IF(F27<1.5,(F27+0.45*2),(F27+0.6*2))*H27*E27 -> 6.4
A28: =A27 -> GARAGEM 2 | B28: =B27 -> JANELA | D28: J6 - JANELA FIXA, ALUMINIO 480 x 238 cm | E28: 1 | F28: 4.8 | G28: 2.38 | H28: 1 | I28: =H28*G28*F28*E28 -> 11.424 | J28: =F28*H28*E28 -> 4.8 | K28: =IF(F28<1.5,(F28+0.15*2),(F28+0.2*2))*H28*E28 -> 5.2 | L28: =IF(F28<1.5,(F28+0.45*2),(F28+0.6*2))*H28*E28 -> 6
A29: =A28 -> GARAGEM 2 | B29: PORTA | J29: =SUM(J30) -> 12 | K29: =SUM(K30) -> 18 | L29: =SUM(L30) -> 30
A30: =A29 -> GARAGEM 2 | B30: =B22 -> PORTA | D30: P8 - PORTA DE ABRIR, 1 FOLHA, ALUMÍNIO VENEZIANA, 60 x 100 cm | E30: 20 | F30: 0.6 | G30: 1 | H30: 1 | I30: =H30*G30*F30*E30 -> 12 | J30: =F30*H30*E30 -> 12 | K30: =IF(F30<1.5,(F30+0.15*2),(F30+0.2*2))*H30*E30 -> 18 | L30: =IF(F30<1.5,(F30+0.45*2),(F30+0.6*2))*H30*E30 -> 30
A31: GARAGEM 3 | J31: =J32+J38 -> 28 | L31: =L32+L38 -> 51.4
A32: =A31 -> GARAGEM 3 | B32: JANELA | J32: =SUM(J33:J37) -> 16 | K32: =SUM(K33:K37) -> 17.8 | L32: =SUM(L33:L37) -> 21.4
A33: =A32 -> GARAGEM 3 | B33: =B32 -> JANELA | D33: DEA01 - JANELA FIXA, 1 FOLHA, TELA GALVANIZADA, 125 x 80 cm | E33: 1 | F33: 1.25 | G33: 0.8 | H33: 1 | I33: =H33*G33*F33*E33 -> 1 | J33: =F33*H33*E33 -> 1.25 | K33: =IF(F33<1.5,(F33+0.15*2),(F33+0.2*2))*H33*E33 -> 1.55 | L33: =IF(F33<1.5,(F33+0.45*2),(F33+0.6*2))*H33*E33 -> 2.15
A34: =A33 -> GARAGEM 3 | B34: =B18 -> PORTA | D34: DEF02 - JANELA FIXA, 1 FOLHA, TELA GALVANIZADA, 125 x 80 cm | E34: 1 | F34: 1.25 | G34: 0.8 | H34: 1 | I34: =H34*G34*F34*E34 -> 1 | J34: =F34*H34*E34 -> 1.25 | K34: =IF(F34<1.5,(F34+0.15*2),(F34+0.2*2))*H34*E34 -> 1.55 | L34: =IF(F34<1.5,(F34+0.45*2),(F34+0.6*2))*H34*E34 -> 2.15
A35: =A34 -> GARAGEM 3 | B35: =B34 -> PORTA | D35: J7 - JANELA FIXA, ALUMINIO 460 x 238 cm | E35: 1 | F35: 4.6 | G35: 2.38 | H35: 1 | I35: =H35*G35*F35*E35 -> 10.948 | J35: =F35*H35*E35 -> 4.6 | K35: =IF(F35<1.5,(F35+0.15*2),(F35+0.2*2))*H35*E35 -> 5 | L35: =IF(F35<1.5,(F35+0.45*2),(F35+0.6*2))*H35*E35 -> 5.8
A36: =A34 -> GARAGEM 3 | B36: =B34 -> PORTA | D36: J8 - JANELA FIXA, ALUMINIO 380 x 238 cm | E36: 1 | F36: 3.8 | G36: 2.38 | H36: 1 | I36: =H36*G36*F36*E36 -> 9.044 | J36: =F36*H36*E36 -> 3.8 | K36: =IF(F36<1.5,(F36+0.15*2),(F36+0.2*2))*H36*E36 -> 4.2 | L36: =IF(F36<1.5,(F36+0.45*2),(F36+0.6*2))*H36*E36 -> 5
A37: =A36 -> GARAGEM 3 | B37: =B36 -> PORTA | D37: J9 - JANELA FIXA, ALUMINIO 510 x 238 cm | E37: 1 | F37: 5.1 | G37: 2.38 | H37: 1 | I37: =H37*G37*F37*E37 -> 12.138 | J37: =F37*H37*E37 -> 5.1 | K37: =IF(F37<1.5,(F37+0.15*2),(F37+0.2*2))*H37*E37 -> 5.5 | L37: =IF(F37<1.5,(F37+0.45*2),(F37+0.6*2))*H37*E37 -> 6.3
A38: =A37 -> GARAGEM 3 | B38: PORTA | J38: =SUM(J39) -> 12 | K38: =SUM(K39) -> 18 | L38: =SUM(L39) -> 30
A39: =A38 -> GARAGEM 3 | B39: =B30 -> PORTA | D39: P8 - PORTA DE ABRIR, 1 FOLHA, ALUMÍNIO VENEZIANA, 60 x 100 cm | E39: 20 | F39: 0.6 | G39: 1 | H39: 1 | I39: =H39*G39*F39*E39 -> 12 | J39: =F39*H39*E39 -> 12 | K39: =IF(F39<1.5,(F39+0.15*2),(F39+0.2*2))*H39*E39 -> 18 | L39: =IF(F39<1.5,(F39+0.45*2),(F39+0.6*2))*H39*E39 -> 30
A40: GARAGEM 4 | J40: =J41+J46 -> 24.45 | L40: =L41+L46 -> 46.95
A41: =A40 -> GARAGEM 4 | B41: JANELA | J41: =SUM(J42:J45) -> 12.45 | K41: =SUM(K42:K45) -> 13.95 | L41: =SUM(L42:L45) -> 16.95
A42: =A41 -> GARAGEM 4 | B42: =B41 -> JANELA | D42: DEA01 - JANELA FIXA, 1 FOLHA, TELA GALVANIZADA, 125 x 80 cm | E42: 1 | F42: 1.25 | G42: 0.8 | H42: 1 | I42: =H42*G42*F42*E42 -> 1 | J42: =F42*H42*E42 -> 1.25 | K42: =IF(F42<1.5,(F42+0.15*2),(F42+0.2*2))*H42*E42 -> 1.55 | L42: =IF(F42<1.5,(F42+0.45*2),(F42+0.6*2))*H42*E42 -> 2.15
A43: =A42 -> GARAGEM 4 | B43: =B26 -> JANELA | D43: J10 - JANELA FIXA, ALUMINIO 340 x 310 cm | E43: 1 | F43: 3.4 | G43: 3.1 | H43: 1 | I43: =H43*G43*F43*E43 -> 10.54 | J43: =F43*H43*E43 -> 3.4 | K43: =IF(F43<1.5,(F43+0.15*2),(F43+0.2*2))*H43*E43 -> 3.8 | L43: =IF(F43<1.5,(F43+0.45*2),(F43+0.6*2))*H43*E43 -> 4.6
A44: =A43 -> GARAGEM 4 | B44: =B43 -> JANELA | D44: J11 - JANELA FIXA, ALUMINIO 200 x 310 cm | E44: 1 | F44: 2 | G44: 3.1 | H44: 1 | I44: =H44*G44*F44*E44 -> 6.2 | J44: =F44*H44*E44 -> 2 | K44: =IF(F44<1.5,(F44+0.15*2),(F44+0.2*2))*H44*E44 -> 2.4 | L44: =IF(F44<1.5,(F44+0.45*2),(F44+0.6*2))*H44*E44 -> 3.2
A45: =A44 -> GARAGEM 4 | B45: =B44 -> JANELA | D45: J12 - JANELA FIXA, ALUMINIO 580 x 310 cm | E45: 1 | F45: 5.8 | G45: 3.1 | H45: 1 | I45: =H45*G45*F45*E45 -> 17.98 | J45: =F45*H45*E45 -> 5.8 | K45: =IF(F45<1.5,(F45+0.15*2),(F45+0.2*2))*H45*E45 -> 6.2 | L45: =IF(F45<1.5,(F45+0.45*2),(F45+0.6*2))*H45*E45 -> 7
