Workbook
Name \0: #REF!
Name \0: #REF!
Name \0: #REF!
Name \0: #REF!
Name \0: #REF!
Name \0: #REF!
Name \0: #REF!
Name \0: #REF!
Name \0: #REF!
Name \0: #REF!
Name \1: #REF!
Name \1: #REF!
Name \1: #REF!
Name \1: #REF!
Name \a: #REF!
Name \a: #REF!
Name \a: #REF!
Name \a: #REF!
Name \a: #REF!
Name \a: #REF!
Name \a: #REF!
Name \b: #REF!
Name \b: #REF!
Name \c: #REF!
Name \c: #REF!
Name \d: #REF!
Name \d: #REF!
Name \e: #REF!
Name \e: #REF!
Name \i: #REF!
Name \i: #REF!
Name \J: #REF!
Name \J: #REF!
Name \k: #REF!
Name \k: #REF!
Name \k: #REF!
Name \l: #N/A
Name \m: #REF!
Name \m: #REF!
Name \m: #REF!
Name \m: #REF!
Name \m: #REF!
Name \m: #REF!
Name \m: #REF!
Name \m: #REF!
Name \o: #REF!
Name \o: #REF!
Name \p: #REF!
Name \p: #REF!
Name \r: #REF!
Name \r: #REF!
Name \T: #REF!
Name \T: #REF!
Name \z: #REF!
Name \z: #REF!
Name \z: #REF!
Name \z: #REF!
Name _\0: #REF!
Name _\1: #REF!
Name _\a: #REF!

Sheet Versões
A1: ETAPA | B1: 365 - PRELIMINAR R00 | D1: 365 - PARAMETRICO | F1: 365 PARAMETRICO- INDEXADO | H1: DIFERENÇA
B2: VALOR | C2: VALOR / m² | D2: VALOR | E2: VALOR / m² | F2: VALOR | G2: VALOR / m² | H2: VALOR | I2: VALOR / m²
A3: =[1]ORÇAMENTO_EXECUTIVO!A2 -> GERENCIAMENTO TÉCNICO E ADMINISTRATIVO | B3: =[1]ORÇAMENTO_EXECUTIVO!B2 -> 3894011.7 | C3: =[1]ORÇAMENTO_EXECUTIVO!D2 -> 222.44428 | D3: 3504714.1 | E3: 200.57793 | F3: =D3*$D$80 -> 3651768 | G3: =E3*$D$80 -> 208.99395 | H3: =B3-F3 -> 242243.73 | I3: =C3-G3 -> 13.450333
A4: =[1]ORÇAMENTO_EXECUTIVO!A3 -> MOVIMENTAÇÃO DE TERRA | B4: =[1]ORÇAMENTO_EXECUTIVO!B3 -> 1400464.9 | C4: =[1]ORÇAMENTO_EXECUTIVO!D3 -> 80.001146 | D4: 1364651.1 | E4: 78.100205 | F4: =D4*$D$80 -> 1421910.4 | G4: =E4*$D$80 -> 81.377201 | H4: =B4-F4 -> -21445.489 | I4: =C4-G4 -> -1.3760554
A5: INFRAESTRUTURA E CONTENÇÃO | B5: =[1]ORÇAMENTO_EXECUTIVO!B4+[1]ORÇAMENTO_EXECUTIVO!B5 -> 5478291.1 | C5: =[1]ORÇAMENTO_EXECUTIVO!D4+[1]ORÇAMENTO_EXECUTIVO!D5 -> 312.94578 | D5: 6317421.7 | E5: 361.55169 | F5: =D5*$D$80 -> 6582493.6 | G5: =E5*$D$80 -> 376.722 | H5: =B5-F5 -> -1104202.4 | I5: =C5-G5 -> -63.776216
A6: =[1]ORÇAMENTO_EXECUTIVO!A6 -> SUPRAESTRUTURA | B6: =[1]ORÇAMENTO_EXECUTIVO!B6 -> 11888495 | C6: =[1]ORÇAMENTO_EXECUTIVO!D6 -> 679.12682 | D6: 10402968 | E6: 595.37115 | F6: =D6*$D$80 -> 10839465 | G6: =E6*$D$80 -> 620.35225 | H6: =B6-F6 -> 1049030.7 | I6: =C6-G6 -> 58.774565
A7: =[1]ORÇAMENTO_EXECUTIVO!A7 -> ALVENARIA | B7: =[1]ORÇAMENTO_EXECUTIVO!B7 -> 2669932.4 | C7: =[1]ORÇAMENTO_EXECUTIVO!D7 -> 152.51911 | D7: 2649104.4 | E7: 151.61062 | F7: =D7*$D$80 -> 2760257.9 | G7: =E7*$D$80 -> 157.97203 | H7: =B7-F7 -> -90325.464 | I7: =C7-G7 -> -5.4529187
A8: =[1]ORÇAMENTO_EXECUTIVO!A8 -> INSTALAÇÕES ELÉTRICAS, HIDRÁULICAS, GLP E PREVENTIVAS | B8: =[1]ORÇAMENTO_EXECUTIVO!B8 -> 6824216.5 | C8: =[1]ORÇAMENTO_EXECUTIVO!D8 -> 389.83137 | D8: 6444580.4 | E8: 368.8291 | F8: =D8*$D$80 -> 6714987.8 | G8: =E8*$D$80 -> 384.30476 | H8: =B8-F8 -> 109228.67 | I8: =C8-G8 -> 5.5266125
A9: =[1]ORÇAMENTO_EXECUTIVO!A9 -> EQUIPAMENTOS E SISTEMAS ESPECIAIS | B9: =[1]ORÇAMENTO_EXECUTIVO!B9 -> 3389279.9 | C9: =[1]ORÇAMENTO_EXECUTIVO!D9 -> 193.61162 | D9: 3372799 | E9: 193.0283 | F9: =D9*$D$80 -> 3514317.9 | G9: =E9*$D$80 -> 201.12756 | H9: =B9-F9 -> -125038 | I9: =C9-G9 -> -7.5159334
A10: =[1]ORÇAMENTO_EXECUTIVO!A10 -> IMPERMEABILIZAÇÃO | B10: =[1]ORÇAMENTO_EXECUTIVO!B10 -> 963633.78 | C10: =[1]ORÇAMENTO_EXECUTIVO!D10 -> 55.047298 | D10: 646680 | E10: 37.010075 | F10: =D10*$D$80 -> 673813.96 | G10: =E10*$D$80 -> 38.562976 | H10: =B10-F10 -> 289819.82 | I10: =C10-G10 -> 16.484322
A11: =[1]ORÇAMENTO_EXECUTIVO!A11 -> REVESTIMENTOS INTERNOS EM PISO E PAREDE | B11: =[1]ORÇAMENTO_EXECUTIVO!B11 -> 3955585.1 | C11: =[1]ORÇAMENTO_EXECUTIVO!D11 -> 225.96164 | D11: 3911886.4 | E11: 223.88076 | F11: =D11*$D$80 -> 4076024.7 | G11: =E11*$D$80 -> 233.27454 | H11: =B11-F11 -> -120439.66 | I11: =C11-G11 -> -7.3129004
A12: =[1]ORÇAMENTO_EXECUTIVO!A12 -> REVESTIMENTOS E ACABAMENTOS INTERNOS EM TETO | B12: =[1]ORÇAMENTO_EXECUTIVO!B12 -> 1140245.1 | C12: =[1]ORÇAMENTO_EXECUTIVO!D12 -> 65.136166 | D12: 1954740.9 | E12: 111.87157 | F12: =D12*$D$80 -> 2036759.7 | G12: =E12*$D$80 -> 116.56558 | H12: =B12-F12 -> -896514.6 | I12: =C12-G12 -> -51.429412
A13: =[1]ORÇAMENTO_EXECUTIVO!A13 -> ACABAMENTOS EM PISO E PAREDE | B13: =[1]ORÇAMENTO_EXECUTIVO!B13 -> 4304402.1 | C13: =[1]ORÇAMENTO_EXECUTIVO!D13 -> 245.88771 | D13: 3486357.6 | E13: 199.52736 | F13: =D13*$D$80 -> 3632641.3 | G13: =E13*$D$80 -> 207.89931 | H13: =B13-F13 -> 671760.81 | I13: =C13-G13 -> 37.988401
A14: =[1]ORÇAMENTO_EXECUTIVO!A14 -> PINTURA INTERNA | B14: =[1]ORÇAMENTO_EXECUTIVO!B14 -> 2594671 | C14: =[1]ORÇAMENTO_EXECUTIVO!D14 -> 148.21983 | D14: 2122696.8 | E14: 121.48383 | F14: =D14*$D$80 -> 2211762.7 | G14: =E14*$D$80 -> 126.58116 | H14: =B14-F14 -> 382908.32 | I14: =C14-G14 -> 21.638666
A15: =[1]ORÇAMENTO_EXECUTIVO!A15 -> ESQUADRIAS, VIDROS E FERRAGENS | B15: =[1]ORÇAMENTO_EXECUTIVO!B15 -> 5911420.4 | C15: =[1]ORÇAMENTO_EXECUTIVO!D15 -> 337.68816 | D15: 5968623.2 | E15: 341.58964 | F15: =D15*$D$80 -> 6219059.9 | G15: =E15*$D$80 -> 355.92236 | H15: =B15-F15 -> -307639.55 | I15: =C15-G15 -> -18.234201
A16: COBERTURA | D16: 389789.63 | E16: 22.308009 | F16: =D16*$D$80 -> 406144.76 | G16: =E16*$D$80 -> 23.244028 | H16: =B16-F16 -> -406144.76 | I16: =C16-G16 -> -23.244028
A17: =[1]ORÇAMENTO_EXECUTIVO!A16 -> REVESTIMENTOS E ACABAMENTOS DE FACHADA | B17: =[1]ORÇAMENTO_EXECUTIVO!B16 -> 2143436.7 | C17: =[1]ORÇAMENTO_EXECUTIVO!D16 -> 122.4432 | D17: 1910131.1 | E17: 109.31851 | F17: =D17*$D$80 -> 1990278 | G17: =E17*$D$80 -> 113.90539 | H17: =B17-F17 -> 153158.7 | I17: =C17-G17 -> 8.5378045
A18: =[1]ORÇAMENTO_EXECUTIVO!A17 -> SERVIÇOS COMPLEMENTARES | B18: =[1]ORÇAMENTO_EXECUTIVO!B17 -> 2620073.8 | C18: =[1]ORÇAMENTO_EXECUTIVO!D17 -> 149.67095 | D18: 2243441.3 | E18: 128.39415 | F18: =D18*$D$80 -> 2337573.6 | G18: =E18*$D$80 -> 133.78143 | H18: =B18-F18 -> 282500.24 | I18: =C18-G18 -> 15.889524
A19: =[1]ORÇAMENTO_EXECUTIVO!A18 -> IMPREVISTOS E CONTINGENCIAS | B19: =[1]ORÇAMENTO_EXECUTIVO!B18 -> 1810898.4 | C19: =[1]ORÇAMENTO_EXECUTIVO!D18 -> 103.44704 | D19: 2139091.8 | E19: 122.42214 | F19: =D19*$D$80 -> 2228845.7 | G19: =E19*$D$80 -> 127.55883 | H19: =B19-F19 -> -417947.22 | I19: =C19-G19 -> -24.111787
A20: TOTAL | B20: =SUM(B3:B19) -> 60989058 | C20: =SUM(C3:C19) -> 3483.9821 | D20: =SUM(D3:D19) -> 58829677 | E20: =SUM(E3:E19) -> 3366.875 | F20: =SUM(F3:F19) -> 61298104 | G20: =SUM(G3:G19) -> 3508.1453 | H20: =SUM(H3:H19) -> -309046.19 | I20: =SUM(I3:I19) -> -24.163223
A21: CUB/SC | B21: 2965.54 | C21: =C20/B21 -> 1.1748222 | D21: 2846.12 | E21: =E20/D21 -> 1.1829702 | G21: =G20/B21 -> 1.1829702 | I21: =H20/B20 -> -0.00506724
B22: 45839 | D22: 45566
D23: 45566
D24: 2846.12
B25: 2007.57 | D25: =[1]ORÇAMENTO_EXECUTIVO!C20 -> 45839 | F25: 2007.57 | H25: 2007.57
B26: 2461.35 | D26: 2007.57 | F26: 2461.35 | H26: 2461.35
B27: =B26/B25 -> 1.2260345 | D27: 2461.35 | F27: =F26/F25 -> 1.2260345 | H27: =H26/H25 -> 1.2260345
D28: =D27/D26 -> 1.2260345
C30: 1.1023 | E30: 1.1023 | G30: 1.1023 | I30: 1.1023
A32: 900,00 - 1100 | B32: 900 | F32: 900 | H32: 900
A33: 25,00 - 30,00 | B33: 25 | D33: 900 | F33: 25 | H33: 25
A34: 15,00 - 22,00 | B34: 15 | D34: 25 | F34: 15 | H34: 15
A35: 150,00 - 200,00 | B35: 150 | D35: 15 | F35: 150 | H35: 150
A36: 440,00 - 510,00 | B36: 440 | D36: 150 | F36: 440 | H36: 440
A37: - | D37: 440
A38: 55,00 - 70,00 | B38: 55 | F38: 55 | H38: 55
A39: 170,00 - 200,00 | B39: 170 | D39: 55 | F39: 170 | H39: 170
A40: 165,00 - 230,00 | B40: 165 | D40: 170 | F40: 165 | H40: 165
A41: 40,00 - 70,00 | B41: 40 | D41: 165 | F41: 40 | H41: 40
A42: 55,00 - 77,00 | B42: 55 | D42: 40 | F42: 55 | H42: 55
A43: 35,00 - 50,00 | B43: 35 | D43: 55 | F43: 35 | H43: 35
A44: 130,00 - 175,00 | B44: 130 | D44: 35 | F44: 130 | H44: 130
A45: 35,00 - 65,00 | B45: 35 | D45: 130 | F45: 35 | H45: 35
A46: 35,00 - 55,00 | B46: 35 | D46: 35 | F46: 35 | H46: 35
A47: 430,00 - 550,00 | B47: 430 | D47: 35 | F47: 430 | H47: 430
A48: 35,00 - 50,00 | B48: 35 | D48: 430 | F48: 35 | H48: 35
A49: 150,00 - 220,00 | B49: 150 | D49: 35 | F49: 150 | H49: 150
D50: 150
D79: =[1]ORÇAMENTO_EXECUTIVO!B20 -> 2965.54
D80: =D79/D24 -> 1.0419589

Sheet Obra 
C1: Projeto | D1: 365
C2: Empresa | D2: COTA
C3: Revisão | D3: R00
A4: QUADRO DE ÁREAS
B6: Descrição | C6: Unidade | E6: Quantidade | G6: Imagens
B7: MESES DE OBRA | C7: MÊS | E7: 43
B8: ÁREA DO TERRENO | C8: M² | E8: 2133.78
B9: ÁREA CONSTRUÍDA | C9: M² | E9: 17505.56
B10: NÚMERO DE UNIDADES HABITACIONAIS | C10: UN | E10: 176
B11: NÚMERO DE UNIDADES COMERCIAIS | C11: UN | E11: 0
B12: ÁREA PRIVATIVA | C12: M² | E12: 9509.28
B13: NÚMERO DE PAVIMENTOS | C13: UN | E13: 15
B15: Subsolo - Garagem 2 | C15: M² | E15: 1641.67
B16: Subsolo - Garagem 1 | C16: M² | E16: 1592.5
B17: Térreo | C17: M² | E17: 1559.6
B18: Mezanino | C18: M² | E18: 1588.25
B19: 2º pavimento | C19: M² | E19: 1155.62
... B22: Área Técnica | C22: M² | E22: 157.49
B32: ETAPA | C32: VALOR ORÇADO | D32: % | E32: VALOR / m²
B33: GERENCIAMENTO TÉCNICO E ADMINISTRATIVO | C33: ='Ger_Tec e Adm'!N101 -> 3667981.1 | D33: =C33/C$53 -> 0.060141626 | E33: =C33/$E$9 -> 209.53235
B34: MOVIMENTAÇÃO DE TERRA | C34: =Ger_Executivo!N8 -> 1400464.9 | D34: =C34/C$53 -> 0.022962559 | E34: =C34/$E$9 -> 80.001146
B35: INFRAESTRUTURA | C35: =Ger_Executivo!N23 -> 2627275.7 | D35: =C35/C$53 -> 0.04307782 | E35: =C35/$E$9 -> 150.08235
B36: CONTENÇÃO | C36: =Ger_Executivo!N47 -> 1381816.6 | D36: =C36/C$53 -> 0.022656795 | E36: =C36/$E$9 -> 78.935869
B37: SUPRAESTRUTURA | C37: =Ger_Executivo!N55 -> 6463760.8 | D37: =C37/C$53 -> 0.1059823 | E37: =C37/$E$9 -> 369.24045
B38: ALVENARIA | C38: =Ger_Executivo!N78 -> 1539779.4 | D38: =C38/C$53 -> 0.025246814 | E38: =C38/$E$9 -> 87.959448
B39: INSTALAÇÕES ELÉTRICAS, HIDRÁULICAS, GLP E PREVENTIVAS | C39: =Ger_Executivo!N105+Ger_Executivo!N114+Ger_Executivo!N128+Ger_Executivo!N133 -> 3600893.7 | D39: =C39/C$53 -> 0.059041635 | E39: =C39/$E$9 -> 205.7
B40: CLIMATIZAÇÃO, EXAUSTÃO MECÂNICA E PRESSURIZAÇÃO | C40: =Ger_Executivo!N156 -> 1083704.9 | D40: =C40/C$53 -> 0.017768841 | E40: =C40/$E$9 -> 61.906324
B41: REVESTIMENTOS E ACABAMENTOS EM PAREDE | C41: =Ger_Executivo!N164 -> 1426224.3 | D41: =C41/C$53 -> 0.023384922 | E41: =C41/$E$9 -> 81.472649
B42: REVESTIMENTOS ARGAMASSADOS TETO | C42: =Ger_Executivo!N177 -> 349137.96 | D42: =C42/C$53 -> 0.0057245999 | E42: =C42/$E$9 -> 19.944404
B43: IMPERMEABILIZAÇÃO | C43: =Ger_Executivo!N90 -> 511572.58 | D43: =C43/C$53 -> 0.0083879404 | E43: =C43/$E$9 -> 29.223434
B44: PISOS E PAVIMENTAÇÕES | C44: =Ger_Executivo!N187 -> 2539181.4 | D44: =C44/C$53 -> 0.041633393 | E44: =C44/$E$9 -> 145.05
B45: PINTURA INTERNA | C45: =Ger_Executivo!N206 -> 786426.24 | D45: =C45/C$53 -> 0.012894546 | E45: =C45/$E$9 -> 44.924369
B46: REVESTIMENTOS E ACABAMENTOS DE FACHADA | C46: =Ger_Executivo!N258 -> 561222.52 | D46: =C46/C$53 -> 0.0092020199 | E46: =C46/$E$9 -> 32.059673
B47: ESQUADRIAS, VIDROS E FERRAGENS | C47: =Ger_Executivo!N216 -> 5007297.9 | D47: =C47/C$53 -> 0.082101579 | E47: =C47/$E$9 -> 286.04043
B48: LOUÇAS E METAIS | C48: =Ger_Executivo!N250 -> 510955.57 | D48: =C48/C$53 -> 0.0083778236 | E48: =C48/$E$9 -> 29.188188
B49: EQUIPAMENTOS E SISTEMAS ESPECIAIS | C49: =Ger_Executivo!N145+Ger_Executivo!N137 -> 2305575 | D49: =C49/C$53 -> 0.037803093 | E49: =C49/$E$9 -> 131.7053
B50: SERVIÇOS COMPLEMENTARES | C50: =Ger_Executivo!N272 -> 1941982 | D50: =C50/C$53 -> 0.031841482 | E50: =C50/$E$9 -> 110.93515
B51: MÃO DE OBRA | C51: =Ger_Executivo!N291 -> 22603060 | D51: =C51/C$53 -> 0.37060845 | E51: =C51/$E$9 -> 1291.1932
B52: IMPREVISTOS | C52: =Ger_Executivo!N327 -> 680745.43 | D52: =C52/C$53 -> 0.011161763 | E52: =C52/$E$9 -> 38.887384
B53: TOTAL | C53: =SUM(C33:C52) -> 60989058 | D53: =SUM(D33:D52) -> 1 | E53: =SUM(E33:E52) -> 3483.9821
B54: CUB/SC | C54: 2965.54 | D54: 45839 | E54: =ROUND(+E53/C54,2)&" CUB" -> 1,17 CUB

Sheet Ger_Tec e Adm
G4: PROJETO: | I4: ='Obra '!D1 -> 365 | O4: REVISÃO: | P4: DATA
G5: EMPRESA: | I5: ='Obra '!D2 -> COTA | O5: ='Obra '!D3 -> R00 | P5: 45551
A6: Unidade Construtiva | B6: Célula Construtiva | C6: Etapa | D6: Subetapa | E6: Serviço | G6: GERENCIAMENTO EXECUTIVO
A7: 0 | B7: 0 | C7: 0 | D7: 0 | E7: 0 | G7: Atalho | H7: NIVEL | I7: Item | J7: Descrição | K7: Unidade | L7: Quant. | M7: Preço un | N7: Total | O7: Considerações | P7: Situação
A8: =IF($H8="UNIDADE CONSTRUTIVA",OFFSET(A8,-1,0)+1,LARGE(A$3:A7,1)) -> 0 | B8: =IF(H8="UNIDADE CONSTRUTIVA",0,IF(H8="CÉLULA CONSTRUTIVA",OFFSET(B8,-1,0)+1,OFFSET(B8,-1,0))) -> 1 | C8: =IF(H8="CÉLULA CONSTRUTIVA",0,IF(H8="ETAPA",OFFSET(C8,-1,0)+1,OFFSET(C8,-1,0))) -> 0 | D8: =IF(H8="ETAPA",0,IF(H8="SUBETAPA",OFFSET(D8,-1,0)+1,OFFSET(D8,-1,0))) -> 0 | E8: =IF(H8="Subetapa",0,IF(H8="serviço",OFFSET(E8,-1,0)+1,OFFSET(E8,-1,0))) -> 0 | H8: CÉLULA CONSTRUTIVA | I8: =IF(H8="Unidade Construtiva",TEXT(A8,"00"),IF(H8="Célula Construtiva",TEXT(B8,"00"),IF(H8="Etapa",CONCATENATE(TEXT(B8,"00"),".",TEXT(C8,"000")),IF(H8="Subetapa",CONCATENATE(TEXT(B8,"00"),".",TEXT(C8,"000"),".",TEXT(D8,"000")),IF(H8="Serviço",CONCATENATE(TEXT(B8,"00"),".",TEXT(C8,"000"),".",TEXT(D8,"000"),".",TEXT(E8,"000")),""))))) -> 01 | J8: SERVIÇOS TÉCNICOS | N8: =IF(H8="Serviço",M8*L8,IF(H8="CÉLULA CONSTRUTIVA",SUMIFS($N$8:$N$397,$B$8:$B$397,B8,$H$8:$H$397,"Serviço"),IF(H8="ETAPA",SUMIFS($N$8:$N$397,$B$8:$B$397,B8,$C$8:$C$397,C8,$H$8:$H$397,"Serviço"),IF(H8="SUBETAPA",SUMIFS($N$8:$N$397,$B$8:$B$397,B8,$C$8:$C$397,C8,$D$8:$D$397,D8,$H$8:$H$397,"Serviço"),0)))) -> 1783946.5 | P8: -
A9: =IF($H9="UNIDADE CONSTRUTIVA",OFFSET(A9,-1,0)+1,LARGE(A$3:A8,1)) -> 0 | B9: =IF(H9="UNIDADE CONSTRUTIVA",0,IF(H9="CÉLULA CONSTRUTIVA",OFFSET(B9,-1,0)+1,OFFSET(B9,-1,0))) -> 1 | C9: =IF(H9="CÉLULA CONSTRUTIVA",0,IF(H9="ETAPA",OFFSET(C9,-1,0)+1,OFFSET(C9,-1,0))) -> 1 | D9: =IF(H9="ETAPA",0,IF(H9="SUBETAPA",OFFSET(D9,-1,0)+1,OFFSET(D9,-1,0))) -> 0 | E9: =IF(H9="Subetapa",0,IF(H9="serviço",OFFSET(E9,-1,0)+1,OFFSET(E9,-1,0))) -> 0 | H9: ETAPA | I9: =IF(H9="Unidade Construtiva",TEXT(A9,"00"),IF(H9="Célula Construtiva",TEXT(B9,"00"),IF(H9="Etapa",CONCATENATE(TEXT(B9,"00"),".",TEXT(C9,"000")),IF(H9="Subetapa",CONCATENATE(TEXT(B9,"00"),".",TEXT(C9,"000"),".",TEXT(D9,"000")),IF(H9="Serviço",CONCATENATE(TEXT(B9,"00"),".",TEXT(C9,"000"),".",TEXT(D9,"000"),".",TEXT(E9,"000")),""))))) -> 01.001 | J9: ESTUDOS, PROJETOS, CONSULTORIA E ENSAIOS | N9: =IF(H9="Serviço",M9*L9,IF(H9="CÉLULA CONSTRUTIVA",SUMIFS($N$8:$N$397,$B$8:$B$397,B9,$H$8:$H$397,"Serviço"),IF(H9="ETAPA",SUMIFS($N$8:$N$397,$B$8:$B$397,B9,$C$8:$C$397,C9,$H$8:$H$397,"Serviço"),IF(H9="SUBETAPA",SUMIFS($N$8:$N$397,$B$8:$B$397,B9,$C$8:$C$397,C9,$D$8:$D$397,D9,$H$8:$H$397,"Serviço"),0)))) -> 1380455.6 | P9: -
A10: =IF($H10="UNIDADE CONSTRUTIVA",OFFSET(A10,-1,0)+1,LARGE(A$3:A9,1)) -> 0 | B10: =IF(H10="UNIDADE CONSTRUTIVA",0,IF(H10="CÉLULA CONSTRUTIVA",OFFSET(B10,-1,0)+1,OFFSET(B10,-1,0))) -> 1 | C10: =IF(H10="CÉLULA CONSTRUTIVA",0,IF(H10="ETAPA",OFFSET(C10,-1,0)+1,OFFSET(C10,-1,0))) -> 1 | D10: =IF(H10="ETAPA",0,IF(H10="SUBETAPA",OFFSET(D10,-1,0)+1,OFFSET(D10,-1,0))) -> 1 | E10: =IF(H10="Subetapa",0,IF(H10="serviço",OFFSET(E10,-1,0)+1,OFFSET(E10,-1,0))) -> 0 | H10: SUBETAPA | I10: =IF(H10="Unidade Construtiva",TEXT(A10,"00"),IF(H10="Célula Construtiva",TEXT(B10,"00"),IF(H10="Etapa",CONCATENATE(TEXT(B10,"00"),".",TEXT(C10,"000")),IF(H10="Subetapa",CONCATENATE(TEXT(B10,"00"),".",TEXT(C10,"000"),".",TEXT(D10,"000")),IF(H10="Serviço",CONCATENATE(TEXT(B10,"00"),".",TEXT(C10,"000"),".",TEXT(D10,"000"),".",TEXT(E10,"000")),""))))) -> 01.001.001 | J10: Estudos | N10: =IF(H10="Serviço",M10*L10,IF(H10="CÉLULA CONSTRUTIVA",SUMIFS($N$8:$N$397,$B$8:$B$397,B10,$H$8:$H$397,"Serviço"),IF(H10="ETAPA",SUMIFS($N$8:$N$397,$B$8:$B$397,B10,$C$8:$C$397,C10,$H$8:$H$397,"Serviço"),IF(H10="SUBETAPA",SUMIFS($N$8:$N$397,$B$8:$B$397,B10,$C$8:$C$397,C10,$D$8:$D$397,D10,$H$8:$H$397,"Serviço"),0)))) -> 53255.71
A11: =IF($H11="UNIDADE CONSTRUTIVA",OFFSET(A11,-1,0)+1,LARGE(A$3:A10,1)) -> 0 | B11: =IF(H11="UNIDADE CONSTRUTIVA",0,IF(H11="CÉLULA CONSTRUTIVA",OFFSET(B11,-1,0)+1,OFFSET(B11,-1,0))) -> 1 | C11: =IF(H11="CÉLULA CONSTRUTIVA",0,IF(H11="ETAPA",OFFSET(C11,-1,0)+1,OFFSET(C11,-1,0))) -> 1 | D11: =IF(H11="ETAPA",0,IF(H11="SUBETAPA",OFFSET(D11,-1,0)+1,OFFSET(D11,-1,0))) -> 1 | E11: =IF(H11="Subetapa",0,IF(H11="serviço",OFFSET(E11,-1,0)+1,OFFSET(E11,-1,0))) -> 1 | G11: 2149 | H11: SERVIÇO | I11: =IF(H11="Unidade Construtiva",TEXT(A11,"00"),IF(H11="Célula Construtiva",TEXT(B11,"00"),IF(H11="Etapa",CONCATENATE(TEXT(B11,"00"),".",TEXT(C11,"000")),IF(H11="Subetapa",CONCATENATE(TEXT(B11,"00"),".",TEXT(C11,"000"),".",TEXT(D11,"000")),IF(H11="Serviço",CONCATENATE(TEXT(B11,"00"),".",TEXT(C11,"000"),".",TEXT(D11,"000"),".",TEXT(E11,"000")),""))))) -> 01.001.001.001 | J11: Levantamento Topográfico | K11: vb | L11: 1 | M11: 9350.6735 | N11: =IF(H11="Serviço",M11*L11,IF(H11="CÉLULA CONSTRUTIVA",SUMIFS($N$8:$N$397,$B$8:$B$397,B11,$H$8:$H$397,"Serviço"),IF(H11="ETAPA",SUMIFS($N$8:$N$397,$B$8:$B$397,B11,$C$8:$C$397,C11,$H$8:$H$397,"Serviço"),IF(H11="SUBETAPA",SUMIFS($N$8:$N$397,$B$8:$B$397,B11,$C$8:$C$397,C11,$D$8:$D$397,D11,$H$8:$H$397,"Serviço"),0)))) -> 9350.6735 | P11: Lançado ERP
A12: =IF($H12="UNIDADE CONSTRUTIVA",OFFSET(A12,-1,0)+1,LARGE(A$3:A11,1)) -> 0 | B12: =IF(H12="UNIDADE CONSTRUTIVA",0,IF(H12="CÉLULA CONSTRUTIVA",OFFSET(B12,-1,0)+1,OFFSET(B12,-1,0))) -> 1 | C12: =IF(H12="CÉLULA CONSTRUTIVA",0,IF(H12="ETAPA",OFFSET(C12,-1,0)+1,OFFSET(C12,-1,0))) -> 1 | D12: =IF(H12="ETAPA",0,IF(H12="SUBETAPA",OFFSET(D12,-1,0)+1,OFFSET(D12,-1,0))) -> 1 | E12: =IF(H12="Subetapa",0,IF(H12="serviço",OFFSET(E12,-1,0)+1,OFFSET(E12,-1,0))) -> 2 | G12: 4666 | H12: SERVIÇO | I12: =IF(H12="Unidade Construtiva",TEXT(A12,"00"),IF(H12="Célula Construtiva",TEXT(B12,"00"),IF(H12="Etapa",CONCATENATE(TEXT(B12,"00"),".",TEXT(C12,"000")),IF(H12="Subetapa",CONCATENATE(TEXT(B12,"00"),".",TEXT(C12,"000"),".",TEXT(D12,"000")),IF(H12="Serviço",CONCATENATE(TEXT(B12,"00"),".",TEXT(C12,"000"),".",TEXT(D12,"000"),".",TEXT(E12,"000")),""))))) -> 01.001.001.002 | J12: Estudo ambiental | K12: vb | L12: 1 | M12: 25248.338 | N12: =IF(H12="Serviço",M12*L12,IF(H12="CÉLULA CONSTRUTIVA",SUMIFS($N$8:$N$397,$B$8:$B$397,B12,$H$8:$H$397,"Serviço"),IF(H12="ETAPA",SUMIFS($N$8:$N$397,$B$8:$B$397,B12,$C$8:$C$397,C12,$H$8:$H$397,"Serviço"),IF(H12="SUBETAPA",SUMIFS($N$8:$N$397,$B$8:$B$397,B12,$C$8:$C$397,C12,$D$8:$D$397,D12,$H$8:$H$397,"Serviço"),0)))) -> 25248.338 | P12: Lançado ERP
A13: =IF($H13="UNIDADE CONSTRUTIVA",OFFSET(A13,-1,0)+1,LARGE(A$3:A12,1)) -> 0 | B13: =IF(H13="UNIDADE CONSTRUTIVA",0,IF(H13="CÉLULA CONSTRUTIVA",OFFSET(B13,-1,0)+1,OFFSET(B13,-1,0))) -> 1 | C13: =IF(H13="CÉLULA CONSTRUTIVA",0,IF(H13="ETAPA",OFFSET(C13,-1,0)+1,OFFSET(C13,-1,0))) -> 1 | D13: =IF(H13="ETAPA",0,IF(H13="SUBETAPA",OFFSET(D13,-1,0)+1,OFFSET(D13,-1,0))) -> 1 | E13: =IF(H13="Subetapa",0,IF(H13="serviço",OFFSET(E13,-1,0)+1,OFFSET(E13,-1,0))) -> 3 | G13: 2153 | H13: SERVIÇO | I13: =IF(H13="Unidade Construtiva",TEXT(A13,"00"),IF(H13="Célula Construtiva",TEXT(B13,"00"),IF(H13="Etapa",CONCATENATE(TEXT(B13,"00"),".",TEXT(C13,"000")),IF(H13="Subetapa",CONCATENATE(TEXT(B13,"00"),".",TEXT(C13,"000"),".",TEXT(D13,"000")),IF(H13="Serviço",CONCATENATE(TEXT(B13,"00"),".",TEXT(C13,"000"),".",TEXT(D13,"000"),".",TEXT(E13,"000")),""))))) -> 01.001.001.003 | J13: Sondagem do terreno | K13: vb | L13: 1 | M13: 18656.699 | N13: =IF(H13="Serviço",M13*L13,IF(H13="CÉLULA CONSTRUTIVA",SUMIFS($N$8:$N$397,$B$8:$B$397,B13,$H$8:$H$397,"Serviço"),IF(H13="ETAPA",SUMIFS($N$8:$N$397,$B$8:$B$397,B13,$C$8:$C$397,C13,$H$8:$H$397,"Serviço"),IF(H13="SUBETAPA",SUMIFS($N$8:$N$397,$B$8:$B$397,B13,$C$8:$C$397,C13,$D$8:$D$397,D13,$H$8:$H$397,"Serviço"),0)))) -> 18656.699 | P13: Lançado ERP
A14: =IF($H14="UNIDADE CONSTRUTIVA",OFFSET(A14,-1,0)+1,LARGE(A$3:A13,1)) -> 0 | B14: =IF(H14="UNIDADE CONSTRUTIVA",0,IF(H14="CÉLULA CONSTRUTIVA",OFFSET(B14,-1,0)+1,OFFSET(B14,-1,0))) -> 1 | C14: =IF(H14="CÉLULA CONSTRUTIVA",0,IF(H14="ETAPA",OFFSET(C14,-1,0)+1,OFFSET(C14,-1,0))) -> 1 | D14: =IF(H14="ETAPA",0,IF(H14="SUBETAPA",OFFSET(D14,-1,0)+1,OFFSET(D14,-1,0))) -> 2 | E14: =IF(H14="Subetapa",0,IF(H14="serviço",OFFSET(E14,-1,0)+1,OFFSET(E14,-1,0))) -> 0 | H14: SUBETAPA | I14: =IF(H14="Unidade Construtiva",TEXT(A14,"00"),IF(H14="Célula Construtiva",TEXT(B14,"00"),IF(H14="Etapa",CONCATENATE(TEXT(B14,"00"),".",TEXT(C14,"000")),IF(H14="Subetapa",CONCATENATE(TEXT(B14,"00"),".",TEXT(C14,"000"),".",TEXT(D14,"000")),IF(H14="Serviço",CONCATENATE(TEXT(B14,"00"),".",TEXT(C14,"000"),".",TEXT(D14,"000"),".",TEXT(E14,"000")),""))))) -> 01.001.002 | J14: Projetos | N14: =IF(H14="Serviço",M14*L14,IF(H14="CÉLULA CONSTRUTIVA",SUMIFS($N$8:$N$397,$B$8:$B$397,B14,$H$8:$H$397,"Serviço"),IF(H14="ETAPA",SUMIFS($N$8:$N$397,$B$8:$B$397,B14,$C$8:$C$397,C14,$H$8:$H$397,"Serviço"),IF(H14="SUBETAPA",SUMIFS($N$8:$N$397,$B$8:$B$397,B14,$C$8:$C$397,C14,$D$8:$D$397,D14,$H$8:$H$397,"Serviço"),0)))) -> 1138195.7
A15: =IF($H15="UNIDADE CONSTRUTIVA",OFFSET(A15,-1,0)+1,LARGE(A$3:A14,1)) -> 0 | B15: =IF(H15="UNIDADE CONSTRUTIVA",0,IF(H15="CÉLULA CONSTRUTIVA",OFFSET(B15,-1,0)+1,OFFSET(B15,-1,0))) -> 1 | C15: =IF(H15="CÉLULA CONSTRUTIVA",0,IF(H15="ETAPA",OFFSET(C15,-1,0)+1,OFFSET(C15,-1,0))) -> 1 | D15: =IF(H15="ETAPA",0,IF(H15="SUBETAPA",OFFSET(D15,-1,0)+1,OFFSET(D15,-1,0))) -> 2 | E15: =IF(H15="Subetapa",0,IF(H15="serviço",OFFSET(E15,-1,0)+1,OFFSET(E15,-1,0))) -> 1 | G15: 4706 | H15: SERVIÇO | I15: =IF(H15="Unidade Construtiva",TEXT(A15,"00"),IF(H15="Célula Construtiva",TEXT(B15,"00"),IF(H15="Etapa",CONCATENATE(TEXT(B15,"00"),".",TEXT(C15,"000")),IF(H15="Subetapa",CONCATENATE(TEXT(B15,"00"),".",TEXT(C15,"000"),".",TEXT(D15,"000")),IF(H15="Serviço",CONCATENATE(TEXT(B15,"00"),".",TEXT(C15,"000"),".",TEXT(D15,"000"),".",TEXT(E15,"000")),""))))) -> 01.001.002.001 | J15: Legalização de incorporação | K15: vb | L15: 1 | M15: 133121.85 | N15: =IF(H15="Serviço",M15*L15,IF(H15="CÉLULA CONSTRUTIVA",SUMIFS($N$8:$N$397,$B$8:$B$397,B15,$H$8:$H$397,"Serviço"),IF(H15="ETAPA",SUMIFS($N$8:$N$397,$B$8:$B$397,B15,$C$8:$C$397,C15,$H$8:$H$397,"Serviço"),IF(H15="SUBETAPA",SUMIFS($N$8:$N$397,$B$8:$B$397,B15,$C$8:$C$397,C15,$D$8:$D$397,D15,$H$8:$H$397,"Serviço"),0)))) -> 133121.85 | P15: Lançado ERP
A16: =IF($H16="UNIDADE CONSTRUTIVA",OFFSET(A16,-1,0)+1,LARGE(A$3:A15,1)) -> 0 | B16: =IF(H16="UNIDADE CONSTRUTIVA",0,IF(H16="CÉLULA CONSTRUTIVA",OFFSET(B16,-1,0)+1,OFFSET(B16,-1,0))) -> 1 | C16: =IF(H16="CÉLULA CONSTRUTIVA",0,IF(H16="ETAPA",OFFSET(C16,-1,0)+1,OFFSET(C16,-1,0))) -> 1 | D16: =IF(H16="ETAPA",0,IF(H16="SUBETAPA",OFFSET(D16,-1,0)+1,OFFSET(D16,-1,0))) -> 2 | E16: =IF(H16="Subetapa",0,IF(H16="serviço",OFFSET(E16,-1,0)+1,OFFSET(E16,-1,0))) -> 2 | H16: SERVIÇO | I16: =IF(H16="Unidade Construtiva",TEXT(A16,"00"),IF(H16="Célula Construtiva",TEXT(B16,"00"),IF(H16="Etapa",CONCATENATE(TEXT(B16,"00"),".",TEXT(C16,"000")),IF(H16="Subetapa",CONCATENATE(TEXT(B16,"00"),".",TEXT(C16,"000"),".",TEXT(D16,"000")),IF(H16="Serviço",CONCATENATE(TEXT(B16,"00"),".",TEXT(C16,"000"),".",TEXT(D16,"000"),".",TEXT(E16,"000")),""))))) -> 01.001.002.002 | J16: Projeto arquitetônico legal | K16: vb | L16: 1 | M16: 163931.27 | N16: =IF(H16="Serviço",M16*L16,IF(H16="CÉLULA CONSTRUTIVA",SUMIFS($N$8:$N$397,$B$8:$B$397,B16,$H$8:$H$397,"Serviço"),IF(H16="ETAPA",SUMIFS($N$8:$N$397,$B$8:$B$397,B16,$C$8:$C$397,C16,$H$8:$H$397,"Serviço"),IF(H16="SUBETAPA",SUMIFS($N$8:$N$397,$B$8:$B$397,B16,$C$8:$C$397,C16,$D$8:$D$397,D16,$H$8:$H$397,"Serviço"),0)))) -> 163931.27 | P16: Lançado ERP
A17: =IF($H17="UNIDADE CONSTRUTIVA",OFFSET(A17,-1,0)+1,LARGE(A$3:A16,1)) -> 0 | B17: =IF(H17="UNIDADE CONSTRUTIVA",0,IF(H17="CÉLULA CONSTRUTIVA",OFFSET(B17,-1,0)+1,OFFSET(B17,-1,0))) -> 1 | C17: =IF(H17="CÉLULA CONSTRUTIVA",0,IF(H17="ETAPA",OFFSET(C17,-1,0)+1,OFFSET(C17,-1,0))) -> 1 | D17: =IF(H17="ETAPA",0,IF(H17="SUBETAPA",OFFSET(D17,-1,0)+1,OFFSET(D17,-1,0))) -> 2 | E17: =IF(H17="Subetapa",0,IF(H17="serviço",OFFSET(E17,-1,0)+1,OFFSET(E17,-1,0))) -> 3 | H17: SERVIÇO | I17: =IF(H17="Unidade Construtiva",TEXT(A17,"00"),IF(H17="Célula Construtiva",TEXT(B17,"00"),IF(H17="Etapa",CONCATENATE(TEXT(B17,"00"),".",TEXT(C17,"000")),IF(H17="Subetapa",CONCATENATE(TEXT(B17,"00"),".",TEXT(C17,"000"),".",TEXT(D17,"000")),IF(H17="Serviço",CONCATENATE(TEXT(B17,"00"),".",TEXT(C17,"000"),".",TEXT(D17,"000"),".",TEXT(E17,"000")),""))))) -> 01.001.002.003 | J17: Projeto arquitetônico executivo | K17: vb | L17: 1 | M17: 87917.954 | N17: =IF(H17="Serviço",M17*L17,IF(H17="CÉLULA CONSTRUTIVA",SUMIFS($N$8:$N$397,$B$8:$B$397,B17,$H$8:$H$397,"Serviço"),IF(H17="ETAPA",SUMIFS($N$8:$N$397,$B$8:$B$397,B17,$C$8:$C$397,C17,$H$8:$H$397,"Serviço"),IF(H17="SUBETAPA",SUMIFS($N$8:$N$397,$B$8:$B$397,B17,$C$8:$C$397,C17,$D$8:$D$397,D17,$H$8:$H$397,"Serviço"),0)))) -> 87917.954 | P17: Lançado ERP
A18: =IF($H18="UNIDADE CONSTRUTIVA",OFFSET(A18,-1,0)+1,LARGE(A$3:A16,1)) -> 0 | B18: =IF(H18="UNIDADE CONSTRUTIVA",0,IF(H18="CÉLULA CONSTRUTIVA",OFFSET(B18,-1,0)+1,OFFSET(B18,-1,0))) -> 1 | C18: =IF(H18="CÉLULA CONSTRUTIVA",0,IF(H18="ETAPA",OFFSET(C18,-1,0)+1,OFFSET(C18,-1,0))) -> 1 | D18: =IF(H18="ETAPA",0,IF(H18="SUBETAPA",OFFSET(D18,-1,0)+1,OFFSET(D18,-1,0))) -> 2 | E18: =IF(H18="Subetapa",0,IF(H18="serviço",OFFSET(E18,-1,0)+1,OFFSET(E18,-1,0))) -> 4 | H18: SERVIÇO | I18: =IF(H18="Unidade Construtiva",TEXT(A18,"00"),IF(H18="Célula Construtiva",TEXT(B18,"00"),IF(H18="Etapa",CONCATENATE(TEXT(B18,"00"),".",TEXT(C18,"000")),IF(H18="Subetapa",CONCATENATE(TEXT(B18,"00"),".",TEXT(C18,"000"),".",TEXT(D18,"000")),IF(H18="Serviço",CONCATENATE(TEXT(B18,"00"),".",TEXT(C18,"000"),".",TEXT(D18,"000"),".",TEXT(E18,"000")),""))))) -> 01.001.002.004 | J18: Projeto arquitetônico interiores/ambientação | K18: vb | L18: 1 | M18: 81457.198 | N18: =IF(H18="Serviço",M18*L18,IF(H18="CÉLULA CONSTRUTIVA",SUMIFS($N$8:$N$397,$B$8:$B$397,B18,$H$8:$H$397,"Serviço"),IF(H18="ETAPA",SUMIFS($N$8:$N$397,$B$8:$B$397,B18,$C$8:$C$397,C18,$H$8:$H$397,"Serviço"),IF(H18="SUBETAPA",SUMIFS($N$8:$N$397,$B$8:$B$397,B18,$C$8:$C$397,C18,$D$8:$D$397,D18,$H$8:$H$397,"Serviço"),0)))) -> 81457.198 | P18: Lançado ERP
A19: =IF($H19="UNIDADE CONSTRUTIVA",OFFSET(A19,-1,0)+1,LARGE(A$3:A17,1)) -> 0 | B19: =IF(H19="UNIDADE CONSTRUTIVA",0,IF(H19="CÉLULA CONSTRUTIVA",OFFSET(B19,-1,0)+1,OFFSET(B19,-1,0))) -> 1 | C19: =IF(H19="CÉLULA CONSTRUTIVA",0,IF(H19="ETAPA",OFFSET(C19,-1,0)+1,OFFSET(C19,-1,0))) -> 1 | D19: =IF(H19="ETAPA",0,IF(H19="SUBETAPA",OFFSET(D19,-1,0)+1,OFFSET(D19,-1,0))) -> 2 | E19: =IF(H19="Subetapa",0,IF(H19="serviço",OFFSET(E19,-1,0)+1,OFFSET(E19,-1,0))) -> 5 | H19: SERVIÇO | I19: =IF(H19="Unidade Construtiva",TEXT(A19,"00"),IF(H19="Célula Construtiva",TEXT(B19,"00"),IF(H19="Etapa",CONCATENATE(TEXT(B19,"00"),".",TEXT(C19,"000")),IF(H19="Subetapa",CONCATENATE(TEXT(B19,"00"),".",TEXT(C19,"000"),".",TEXT(D19,"000")),IF(H19="Serviço",CONCATENATE(TEXT(B19,"00"),".",TEXT(C19,"000"),".",TEXT(D19,"000"),".",TEXT(E19,"000")),""))))) -> 01.001.002.005 | J19: Projeto técnico de fachada | K19: vb | L19: 1 | M19: 16003.599 | N19: =IF(H19="Serviço",M19*L19,IF(H19="CÉLULA CONSTRUTIVA",SUMIFS($N$8:$N$397,$B$8:$B$397,B19,$H$8:$H$397,"Serviço"),IF(H19="ETAPA",SUMIFS($N$8:$N$397,$B$8:$B$397,B19,$C$8:$C$397,C19,$H$8:$H$397,"Serviço"),IF(H19="SUBETAPA",SUMIFS($N$8:$N$397,$B$8:$B$397,B19,$C$8:$C$397,C19,$D$8:$D$397,D19,$H$8:$H$397,"Serviço"),0)))) -> 16003.599 | P19: Lançado ERP
A20: =IF($H20="UNIDADE CONSTRUTIVA",OFFSET(A20,-1,0)+1,LARGE(A$3:A16,1)) -> 0 | B20: =IF(H20="UNIDADE CONSTRUTIVA",0,IF(H20="CÉLULA CONSTRUTIVA",OFFSET(B20,-1,0)+1,OFFSET(B20,-1,0))) -> 1 | C20: =IF(H20="CÉLULA CONSTRUTIVA",0,IF(H20="ETAPA",OFFSET(C20,-1,0)+1,OFFSET(C20,-1,0))) -> 1 | D20: =IF(H20="ETAPA",0,IF(H20="SUBETAPA",OFFSET(D20,-1,0)+1,OFFSET(D20,-1,0))) -> 2 | E20: =IF(H20="Subetapa",0,IF(H20="serviço",OFFSET(E20,-1,0)+1,OFFSET(E20,-1,0))) -> 6 | H20: SERVIÇO | I20: =IF(H20="Unidade Construtiva",TEXT(A20,"00"),IF(H20="Célula Construtiva",TEXT(B20,"00"),IF(H20="Etapa",CONCATENATE(TEXT(B20,"00"),".",TEXT(C20,"000")),IF(H20="Subetapa",CONCATENATE(TEXT(B20,"00"),".",TEXT(C20,"000"),".",TEXT(D20,"000")),IF(H20="Serviço",CONCATENATE(TEXT(B20,"00"),".",TEXT(C20,"000"),".",TEXT(D20,"000"),".",TEXT(E20,"000")),""))))) -> 01.001.002.006 | J20: Projeto de Fundação | K20: vb | L20: 1 | M20: 34231.753 | N20: =IF(H20="Serviço",M20*L20,IF(H20="CÉLULA CONSTRUTIVA",SUMIFS($N$8:$N$397,$B$8:$B$397,B20,$H$8:$H$397,"Serviço"),IF(H20="ETAPA",SUMIFS($N$8:$N$397,$B$8:$B$397,B20,$C$8:$C$397,C20,$H$8:$H$397,"Serviço"),IF(H20="SUBETAPA",SUMIFS($N$8:$N$397,$B$8:$B$397,B20,$C$8:$C$397,C20,$D$8:$D$397,D20,$H$8:$H$397,"Serviço"),0)))) -> 34231.753 | P20: Lançado ERP
A21: =IF($H21="UNIDADE CONSTRUTIVA",OFFSET(A21,-1,0)+1,LARGE(A$3:A18,1)) -> 0 | B21: =IF(H21="UNIDADE CONSTRUTIVA",0,IF(H21="CÉLULA CONSTRUTIVA",OFFSET(B21,-1,0)+1,OFFSET(B21,-1,0))) -> 1 | C21: =IF(H21="CÉLULA CONSTRUTIVA",0,IF(H21="ETAPA",OFFSET(C21,-1,0)+1,OFFSET(C21,-1,0))) -> 1 | D21: =IF(H21="ETAPA",0,IF(H21="SUBETAPA",OFFSET(D21,-1,0)+1,OFFSET(D21,-1,0))) -> 2 | E21: =IF(H21="Subetapa",0,IF(H21="serviço",OFFSET(E21,-1,0)+1,OFFSET(E21,-1,0))) -> 7 | H21: SERVIÇO | I21: =IF(H21="Unidade Construtiva",TEXT(A21,"00"),IF(H21="Célula Construtiva",TEXT(B21,"00"),IF(H21="Etapa",CONCATENATE(TEXT(B21,"00"),".",TEXT(C21,"000")),IF(H21="Subetapa",CONCATENATE(TEXT(B21,"00"),".",TEXT(C21,"000"),".",TEXT(D21,"000")),IF(H21="Serviço",CONCATENATE(TEXT(B21,"00"),".",TEXT(C21,"000"),".",TEXT(D21,"000"),".",TEXT(E21,"000")),""))))) -> 01.001.002.007 | J21: Projeto Estrutura | K21: vb | L21: 1 | M21: 109121.83 | N21: =IF(H21="Serviço",M21*L21,IF(H21="CÉLULA CONSTRUTIVA",SUMIFS($N$8:$N$397,$B$8:$B$397,B21,$H$8:$H$397,"Serviço"),IF(H21="ETAPA",SUMIFS($N$8:$N$397,$B$8:$B$397,B21,$C$8:$C$397,C21,$H$8:$H$397,"Serviço"),IF(H21="SUBETAPA",SUMIFS($N$8:$N$397,$B$8:$B$397,B21,$C$8:$C$397,C21,$D$8:$D$397,D21,$H$8:$H$397,"Serviço"),0)))) -> 109121.83 | P21: Lançado ERP
A22: =IF($H22="UNIDADE CONSTRUTIVA",OFFSET(A22,-1,0)+1,LARGE(A$3:A21,1)) -> 0 | B22: =IF(H22="UNIDADE CONSTRUTIVA",0,IF(H22="CÉLULA CONSTRUTIVA",OFFSET(B22,-1,0)+1,OFFSET(B22,-1,0))) -> 1 | C22: =IF(H22="CÉLULA CONSTRUTIVA",0,IF(H22="ETAPA",OFFSET(C22,-1,0)+1,OFFSET(C22,-1,0))) -> 1 | D22: =IF(H22="ETAPA",0,IF(H22="SUBETAPA",OFFSET(D22,-1,0)+1,OFFSET(D22,-1,0))) -> 2 | E22: =IF(H22="Subetapa",0,IF(H22="serviço",OFFSET(E22,-1,0)+1,OFFSET(E22,-1,0))) -> 8 | H22: SERVIÇO | I22: =IF(H22="Unidade Construtiva",TEXT(A22,"00"),IF(H22="Célula Construtiva",TEXT(B22,"00"),IF(H22="Etapa",CONCATENATE(TEXT(B22,"00"),".",TEXT(C22,"000")),IF(H22="Subetapa",CONCATENATE(TEXT(B22,"00"),".",TEXT(C22,"000"),".",TEXT(D22,"000")),IF(H22="Serviço",CONCATENATE(TEXT(B22,"00"),".",TEXT(C22,"000"),".",TEXT(D22,"000"),".",TEXT(E22,"000")),""))))) -> 01.001.002.008 | J22: Projeto elétrico/comunicação/telefonia/luminotécnico | K22: vb | L22: 1 | M22: 225325.76 | N22: =IF(H22="Serviço",M22*L22,IF(H22="CÉLULA CONSTRUTIVA",SUMIFS($N$8:$N$397,$B$8:$B$397,B22,$H$8:$H$397,"Serviço"),IF(H22="ETAPA",SUMIFS($N$8:$N$397,$B$8:$B$397,B22,$C$8:$C$397,C22,$H$8:$H$397,"Serviço"),IF(H22="SUBETAPA",SUMIFS($N$8:$N$397,$B$8:$B$397,B22,$C$8:$C$397,C22,$D$8:$D$397,D22,$H$8:$H$397,"Serviço"),0)))) -> 225325.76 | P22: Lançado ERP
A23: =IF($H23="UNIDADE CONSTRUTIVA",OFFSET(A23,-1,0)+1,LARGE(A$3:A22,1)) -> 0 | B23: =IF(H23="UNIDADE CONSTRUTIVA",0,IF(H23="CÉLULA CONSTRUTIVA",OFFSET(B23,-1,0)+1,OFFSET(B23,-1,0))) -> 1 | C23: =IF(H23="CÉLULA CONSTRUTIVA",0,IF(H23="ETAPA",OFFSET(C23,-1,0)+1,OFFSET(C23,-1,0))) -> 1 | D23: =IF(H23="ETAPA",0,IF(H23="SUBETAPA",OFFSET(D23,-1,0)+1,OFFSET(D23,-1,0))) -> 2 | E23: =IF(H23="Subetapa",0,IF(H23="serviço",OFFSET(E23,-1,0)+1,OFFSET(E23,-1,0))) -> 9 | H23: SERVIÇO | I23: =IF(H23="Unidade Construtiva",TEXT(A23,"00"),IF(H23="Célula Construtiva",TEXT(B23,"00"),IF(H23="Etapa",CONCATENATE(TEXT(B23,"00"),".",TEXT(C23,"000")),IF(H23="Subetapa",CONCATENATE(TEXT(B23,"00"),".",TEXT(C23,"000"),".",TEXT(D23,"000")),IF(H23="Serviço",CONCATENATE(TEXT(B23,"00"),".",TEXT(C23,"000"),".",TEXT(D23,"000"),".",TEXT(E23,"000")),""))))) -> 01.001.002.009 | J23: Projeto hidrossanitário/drenagem/pluvial | K23: vb | L23: 1 | M23: 60933.617 | N23: =IF(H23="Serviço",M23*L23,IF(H23="CÉLULA CONSTRUTIVA",SUMIFS($N$8:$N$397,$B$8:$B$397,B23,$H$8:$H$397,"Serviço"),IF(H23="ETAPA",SUMIFS($N$8:$N$397,$B$8:$B$397,B23,$C$8:$C$397,C23,$H$8:$H$397,"Serviço"),IF(H23="SUBETAPA",SUMIFS($N$8:$N$397,$B$8:$B$397,B23,$C$8:$C$397,C23,$D$8:$D$397,D23,$H$8:$H$397,"Serviço"),0)))) -> 60933.617 | P23: Lançado ERP
A24: =IF($H24="UNIDADE CONSTRUTIVA",OFFSET(A24,-1,0)+1,LARGE(A$3:A23,1)) -> 0 | B24: =IF(H24="UNIDADE CONSTRUTIVA",0,IF(H24="CÉLULA CONSTRUTIVA",OFFSET(B24,-1,0)+1,OFFSET(B24,-1,0))) -> 1 | C24: =IF(H24="CÉLULA CONSTRUTIVA",0,IF(H24="ETAPA",OFFSET(C24,-1,0)+1,OFFSET(C24,-1,0))) -> 1 | D24: =IF(H24="ETAPA",0,IF(H24="SUBETAPA",OFFSET(D24,-1,0)+1,OFFSET(D24,-1,0))) -> 2 | E24: =IF(H24="Subetapa",0,IF(H24="serviço",OFFSET(E24,-1,0)+1,OFFSET(E24,-1,0))) -> 10 | H24: SERVIÇO | I24: =IF(H24="Unidade Construtiva",TEXT(A24,"00"),IF(H24="Célula Construtiva",TEXT(B24,"00"),IF(H24="Etapa",CONCATENATE(TEXT(B24,"00"),".",TEXT(C24,"000")),IF(H24="Subetapa",CONCATENATE(TEXT(B24,"00"),".",TEXT(C24,"000"),".",TEXT(D24,"000")),IF(H24="Serviço",CONCATENATE(TEXT(B24,"00"),".",TEXT(C24,"000"),".",TEXT(D24,"000"),".",TEXT(E24,"000")),""))))) -> 01.001.002.010 | J24: Projeto preventivo (PPCI - Plano de Prevenção e Proteção Contra Incêndios) e Gás | K24: vb | L24: 1 | M24: 22961.088 | N24: =IF(H24="Serviço",M24*L24,IF(H24="CÉLULA CONSTRUTIVA",SUMIFS($N$8:$N$397,$B$8:$B$397,B24,$H$8:$H$397,"Serviço"),IF(H24="ETAPA",SUMIFS($N$8:$N$397,$B$8:$B$397,B24,$C$8:$C$397,C24,$H$8:$H$397,"Serviço"),IF(H24="SUBETAPA",SUMIFS($N$8:$N$397,$B$8:$B$397,B24,$C$8:$C$397,C24,$D$8:$D$397,D24,$H$8:$H$397,"Serviço"),0)))) -> 22961.088 | P24: Lançado ERP
A25: =IF($H25="UNIDADE CONSTRUTIVA",OFFSET(A25,-1,0)+1,LARGE(A$3:A23,1)) -> 0 | B25: =IF(H25="UNIDADE CONSTRUTIVA",0,IF(H25="CÉLULA CONSTRUTIVA",OFFSET(B25,-1,0)+1,OFFSET(B25,-1,0))) -> 1 | C25: =IF(H25="CÉLULA CONSTRUTIVA",0,IF(H25="ETAPA",OFFSET(C25,-1,0)+1,OFFSET(C25,-1,0))) -> 1 | D25: =IF(H25="ETAPA",0,IF(H25="SUBETAPA",OFFSET(D25,-1,0)+1,OFFSET(D25,-1,0))) -> 2 | E25: =IF(H25="Subetapa",0,IF(H25="serviço",OFFSET(E25,-1,0)+1,OFFSET(E25,-1,0))) -> 11 | G25: 4704 | H25: SERVIÇO | I25: =IF(H25="Unidade Construtiva",TEXT(A25,"00"),IF(H25="Célula Construtiva",TEXT(B25,"00"),IF(H25="Etapa",CONCATENATE(TEXT(B25,"00"),".",TEXT(C25,"000")),IF(H25="Subetapa",CONCATENATE(TEXT(B25,"00"),".",TEXT(C25,"000"),".",TEXT(D25,"000")),IF(H25="Serviço",CONCATENATE(TEXT(B25,"00"),".",TEXT(C25,"000"),".",TEXT(D25,"000"),".",TEXT(E25,"000")),""))))) -> 01.001.002.011 | J25: Projeto de Climatização | K25: vb | L25: 1 | M25: 22550.526 | N25: =IF(H25="Serviço",M25*L25,IF(H25="CÉLULA CONSTRUTIVA",SUMIFS($N$8:$N$397,$B$8:$B$397,B25,$H$8:$H$397,"Serviço"),IF(H25="ETAPA",SUMIFS($N$8:$N$397,$B$8:$B$397,B25,$C$8:$C$397,C25,$H$8:$H$397,"Serviço"),IF(H25="SUBETAPA",SUMIFS($N$8:$N$397,$B$8:$B$397,B25,$C$8:$C$397,C25,$D$8:$D$397,D25,$H$8:$H$397,"Serviço"),0)))) -> 22550.526 | P25: Lançado ERP
A26: =IF($H26="UNIDADE CONSTRUTIVA",OFFSET(A26,-1,0)+1,LARGE(A$3:A24,1)) -> 0 | B26: =IF(H26="UNIDADE CONSTRUTIVA",0,IF(H26="CÉLULA CONSTRUTIVA",OFFSET(B26,-1,0)+1,OFFSET(B26,-1,0))) -> 1 | C26: =IF(H26="CÉLULA CONSTRUTIVA",0,IF(H26="ETAPA",OFFSET(C26,-1,0)+1,OFFSET(C26,-1,0))) -> 1 | D26: =IF(H26="ETAPA",0,IF(H26="SUBETAPA",OFFSET(D26,-1,0)+1,OFFSET(D26,-1,0))) -> 2 | E26: =IF(H26="Subetapa",0,IF(H26="serviço",OFFSET(E26,-1,0)+1,OFFSET(E26,-1,0))) -> 12 | H26: SERVIÇO | I26: =IF(H26="Unidade Construtiva",TEXT(A26,"00"),IF(H26="Célula Construtiva",TEXT(B26,"00"),IF(H26="Etapa",CONCATENATE(TEXT(B26,"00"),".",TEXT(C26,"000")),IF(H26="Subetapa",CONCATENATE(TEXT(B26,"00"),".",TEXT(C26,"000"),".",TEXT(D26,"000")),IF(H26="Serviço",CONCATENATE(TEXT(B26,"00"),".",TEXT(C26,"000"),".",TEXT(D26,"000"),".",TEXT(E26,"000")),""))))) -> 01.001.002.012 | J26: Projeto de Paisagismo | K26: vb | L26: 1 | M26: 21765.216 | N26: =IF(H26="Serviço",M26*L26,IF(H26="CÉLULA CONSTRUTIVA",SUMIFS($N$8:$N$397,$B$8:$B$397,B26,$H$8:$H$397,"Serviço"),IF(H26="ETAPA",SUMIFS($N$8:$N$397,$B$8:$B$397,B26,$C$8:$C$397,C26,$H$8:$H$397,"Serviço"),IF(H26="SUBETAPA",SUMIFS($N$8:$N$397,$B$8:$B$397,B26,$C$8:$C$397,C26,$D$8:$D$397,D26,$H$8:$H$397,"Serviço"),0)))) -> 21765.216 | P26: Lançado ERP
A27: =IF($H27="UNIDADE CONSTRUTIVA",OFFSET(A27,-1,0)+1,LARGE(A$3:A25,1)) -> 0 | B27: =IF(H27="UNIDADE CONSTRUTIVA",0,IF(H27="CÉLULA CONSTRUTIVA",OFFSET(B27,-1,0)+1,OFFSET(B27,-1,0))) -> 1 | C27: =IF(H27="CÉLULA CONSTRUTIVA",0,IF(H27="ETAPA",OFFSET(C27,-1,0)+1,OFFSET(C27,-1,0))) -> 1 | D27: =IF(H27="ETAPA",0,IF(H27="SUBETAPA",OFFSET(D27,-1,0)+1,OFFSET(D27,-1,0))) -> 2 | E27: =IF(H27="Subetapa",0,IF(H27="serviço",OFFSET(E27,-1,0)+1,OFFSET(E27,-1,0))) -> 13 | G27: 4678 | H27: SERVIÇO | I27: =IF(H27="Unidade Construtiva",TEXT(A27,"00"),IF(H27="Célula Construtiva",TEXT(B27,"00"),IF(H27="Etapa",CONCATENATE(TEXT(B27,"00"),".",TEXT(C27,"000")),IF(H27="Subetapa",CONCATENATE(TEXT(B27,"00"),".",TEXT(C27,"000"),".",TEXT(D27,"000")),IF(H27="Serviço",CONCATENATE(TEXT(B27,"00"),".",TEXT(C27,"000"),".",TEXT(D27,"000"),".",TEXT(E27,"000")),""))))) -> 01.001.002.013 | J27: Projeto acústico | K27: vb | L27: 1 | M27: 17458.472 | N27: =IF(H27="Serviço",M27*L27,IF(H27="CÉLULA CONSTRUTIVA",SUMIFS($N$8:$N$397,$B$8:$B$397,B27,$H$8:$H$397,"Serviço"),IF(H27="ETAPA",SUMIFS($N$8:$N$397,$B$8:$B$397,B27,$C$8:$C$397,C27,$H$8:$H$397,"Serviço"),IF(H27="SUBETAPA",SUMIFS($N$8:$N$397,$B$8:$B$397,B27,$C$8:$C$397,C27,$D$8:$D$397,D27,$H$8:$H$397,"Serviço"),0)))) -> 17458.472 | P27: Lançado ERP
A28: =IF($H28="UNIDADE CONSTRUTIVA",OFFSET(A28,-1,0)+1,LARGE(A$3:A26,1)) -> 0 | B28: =IF(H28="UNIDADE CONSTRUTIVA",0,IF(H28="CÉLULA CONSTRUTIVA",OFFSET(B28,-1,0)+1,OFFSET(B28,-1,0))) -> 1 | C28: =IF(H28="CÉLULA CONSTRUTIVA",0,IF(H28="ETAPA",OFFSET(C28,-1,0)+1,OFFSET(C28,-1,0))) -> 1 | D28: =IF(H28="ETAPA",0,IF(H28="SUBETAPA",OFFSET(D28,-1,0)+1,OFFSET(D28,-1,0))) -> 2 | E28: =IF(H28="Subetapa",0,IF(H28="serviço",OFFSET(E28,-1,0)+1,OFFSET(E28,-1,0))) -> 14 | G28: 4680 | H28: SERVIÇO | I28: =IF(H28="Unidade Construtiva",TEXT(A28,"00"),IF(H28="Célula Construtiva",TEXT(B28,"00"),IF(H28="Etapa",CONCATENATE(TEXT(B28,"00"),".",TEXT(C28,"000")),IF(H28="Subetapa",CONCATENATE(TEXT(B28,"00"),".",TEXT(C28,"000"),".",TEXT(D28,"000")),IF(H28="Serviço",CONCATENATE(TEXT(B28,"00"),".",TEXT(C28,"000"),".",TEXT(D28,"000"),".",TEXT(E28,"000")),""))))) -> 01.001.002.014 | J28: Projeto piscina/fonte | K28: vb | L28: 1 | M28: 9829.0552 | N28: =IF(H28="Serviço",M28*L28,IF(H28="CÉLULA CONSTRUTIVA",SUMIFS($N$8:$N$397,$B$8:$B$397,B28,$H$8:$H$397,"Serviço"),IF(H28="ETAPA",SUMIFS($N$8:$N$397,$B$8:$B$397,B28,$C$8:$C$397,C28,$H$8:$H$397,"Serviço"),IF(H28="SUBETAPA",SUMIFS($N$8:$N$397,$B$8:$B$397,B28,$C$8:$C$397,C28,$D$8:$D$397,D28,$H$8:$H$397,"Serviço"),0)))) -> 9829.0552 | P28: Lançado ERP
A29: =IF($H29="UNIDADE CONSTRUTIVA",OFFSET(A29,-1,0)+1,LARGE(A$3:A26,1)) -> 0 | B29: =IF(H29="UNIDADE CONSTRUTIVA",0,IF(H29="CÉLULA CONSTRUTIVA",OFFSET(B29,-1,0)+1,OFFSET(B29,-1,0))) -> 1 | C29: =IF(H29="CÉLULA CONSTRUTIVA",0,IF(H29="ETAPA",OFFSET(C29,-1,0)+1,OFFSET(C29,-1,0))) -> 1 | D29: =IF(H29="ETAPA",0,IF(H29="SUBETAPA",OFFSET(D29,-1,0)+1,OFFSET(D29,-1,0))) -> 2 | E29: =IF(H29="Subetapa",0,IF(H29="serviço",OFFSET(E29,-1,0)+1,OFFSET(E29,-1,0))) -> 15 | G29: 4681 | H29: SERVIÇO | I29: =IF(H29="Unidade Construtiva",TEXT(A29,"00"),IF(H29="Célula Construtiva",TEXT(B29,"00"),IF(H29="Etapa",CONCATENATE(TEXT(B29,"00"),".",TEXT(C29,"000")),IF(H29="Subetapa",CONCATENATE(TEXT(B29,"00"),".",TEXT(C29,"000"),".",TEXT(D29,"000")),IF(H29="Serviço",CONCATENATE(TEXT(B29,"00"),".",TEXT(C29,"000"),".",TEXT(D29,"000"),".",TEXT(E29,"000")),""))))) -> 01.001.002.015 | J29: Projetos de Segurança do Trabalho | K29: vb | L29: 1 | M29: 5990.5769 | N29: =IF(H29="Serviço",M29*L29,IF(H29="CÉLULA CONSTRUTIVA",SUMIFS($N$8:$N$397,$B$8:$B$397,B29,$H$8:$H$397,"Serviço"),IF(H29="ETAPA",SUMIFS($N$8:$N$397,$B$8:$B$397,B29,$C$8:$C$397,C29,$H$8:$H$397,"Serviço"),IF(H29="SUBETAPA",SUMIFS($N$8:$N$397,$B$8:$B$397,B29,$C$8:$C$397,C29,$D$8:$D$397,D29,$H$8:$H$397,"Serviço"),0)))) -> 5990.5769 | P29: Lançado ERP
A30: =IF($H30="UNIDADE CONSTRUTIVA",OFFSET(A30,-1,0)+1,LARGE(A$3:A27,1)) -> 0 | B30: =IF(H30="UNIDADE CONSTRUTIVA",0,IF(H30="CÉLULA CONSTRUTIVA",OFFSET(B30,-1,0)+1,OFFSET(B30,-1,0))) -> 1 | C30: =IF(H30="CÉLULA CONSTRUTIVA",0,IF(H30="ETAPA",OFFSET(C30,-1,0)+1,OFFSET(C30,-1,0))) -> 1 | D30: =IF(H30="ETAPA",0,IF(H30="SUBETAPA",OFFSET(D30,-1,0)+1,OFFSET(D30,-1,0))) -> 2 | E30: =IF(H30="Subetapa",0,IF(H30="serviço",OFFSET(E30,-1,0)+1,OFFSET(E30,-1,0))) -> 16 | G30: 4684 | H30: SERVIÇO | I30: =IF(H30="Unidade Construtiva",TEXT(A30,"00"),IF(H30="Célula Construtiva",TEXT(B30,"00"),IF(H30="Etapa",CONCATENATE(TEXT(B30,"00"),".",TEXT(C30,"000")),IF(H30="Subetapa",CONCATENATE(TEXT(B30,"00"),".",TEXT(C30,"000"),".",TEXT(D30,"000")),IF(H30="Serviço",CONCATENATE(TEXT(B30,"00"),".",TEXT(C30,"000"),".",TEXT(D30,"000"),".",TEXT(E30,"000")),""))))) -> 01.001.002.016 | J30: Projeto de canteiro | K30: vb | L30: 1 | M30: 5878.053 | N30: =IF(H30="Serviço",M30*L30,IF(H30="CÉLULA CONSTRUTIVA",SUMIFS($N$8:$N$397,$B$8:$B$397,B30,$H$8:$H$397,"Serviço"),IF(H30="ETAPA",SUMIFS($N$8:$N$397,$B$8:$B$397,B30,$C$8:$C$397,C30,$H$8:$H$397,"Serviço"),IF(H30="SUBETAPA",SUMIFS($N$8:$N$397,$B$8:$B$397,B30,$C$8:$C$397,C30,$D$8:$D$397,D30,$H$8:$H$397,"Serviço"),0)))) -> 5878.053 | P30: Lançado ERP
A31: =IF($H31="UNIDADE CONSTRUTIVA",OFFSET(A31,-1,0)+1,LARGE(A$3:A26,1)) -> 0 | B31: =IF(H31="UNIDADE CONSTRUTIVA",0,IF(H31="CÉLULA CONSTRUTIVA",OFFSET(B31,-1,0)+1,OFFSET(B31,-1,0))) -> 1 | C31: =IF(H31="CÉLULA CONSTRUTIVA",0,IF(H31="ETAPA",OFFSET(C31,-1,0)+1,OFFSET(C31,-1,0))) -> 1 | D31: =IF(H31="ETAPA",0,IF(H31="SUBETAPA",OFFSET(D31,-1,0)+1,OFFSET(D31,-1,0))) -> 2 | E31: =IF(H31="Subetapa",0,IF(H31="serviço",OFFSET(E31,-1,0)+1,OFFSET(E31,-1,0))) -> 17 | G31: 4686 | H31: SERVIÇO | I31: =IF(H31="Unidade Construtiva",TEXT(A31,"00"),IF(H31="Célula Construtiva",TEXT(B31,"00"),IF(H31="Etapa",CONCATENATE(TEXT(B31,"00"),".",TEXT(C31,"000")),IF(H31="Subetapa",CONCATENATE(TEXT(B31,"00"),".",TEXT(C31,"000"),".",TEXT(D31,"000")),IF(H31="Serviço",CONCATENATE(TEXT(B31,"00"),".",TEXT(C31,"000"),".",TEXT(D31,"000"),".",TEXT(E31,"000")),""))))) -> 01.001.002.017 | J31: Compatibilização de Projetos BIM | K31: vb | L31: 1 | M31: 119717.83 | N31: =IF(H31="Serviço",M31*L31,IF(H31="CÉLULA CONSTRUTIVA",SUMIFS($N$8:$N$397,$B$8:$B$397,B31,$H$8:$H$397,"Serviço"),IF(H31="ETAPA",SUMIFS($N$8:$N$397,$B$8:$B$397,B31,$C$8:$C$397,C31,$H$8:$H$397,"Serviço"),IF(H31="SUBETAPA",SUMIFS($N$8:$N$397,$B$8:$B$397,B31,$C$8:$C$397,C31,$D$8:$D$397,D31,$H$8:$H$397,"Serviço"),0)))) -> 119717.83 | P31: Lançado ERP
A32: =IF($H32="UNIDADE CONSTRUTIVA",OFFSET(A32,-1,0)+1,LARGE(A$3:A23,1)) -> 0 | B32: =IF(H32="UNIDADE CONSTRUTIVA",0,IF(H32="CÉLULA CONSTRUTIVA",OFFSET(B32,-1,0)+1,OFFSET(B32,-1,0))) -> 1 | C32: =IF(H32="CÉLULA CONSTRUTIVA",0,IF(H32="ETAPA",OFFSET(C32,-1,0)+1,OFFSET(C32,-1,0))) -> 1 | D32: =IF(H32="ETAPA",0,IF(H32="SUBETAPA",OFFSET(D32,-1,0)+1,OFFSET(D32,-1,0))) -> 3 | E32: =IF(H32="Subetapa",0,IF(H32="serviço",OFFSET(E32,-1,0)+1,OFFSET(E32,-1,0))) -> 0 | H32: SUBETAPA | I32: =IF(H32="Unidade Construtiva",TEXT(A32,"00"),IF(H32="Célula Construtiva",TEXT(B32,"00"),IF(H32="Etapa",CONCATENATE(TEXT(B32,"00"),".",TEXT(C32,"000")),IF(H32="Subetapa",CONCATENATE(TEXT(B32,"00"),".",TEXT(C32,"000"),".",TEXT(D32,"000")),IF(H32="Serviço",CONCATENATE(TEXT(B32,"00"),".",TEXT(C32,"000"),".",TEXT(D32,"000"),".",TEXT(E32,"000")),""))))) -> 01.001.003 | J32: Consultorias | N32: =IF(H32="Serviço",M32*L32,IF(H32="CÉLULA CONSTRUTIVA",SUMIFS($N$8:$N$397,$B$8:$B$397,B32,$H$8:$H$397,"Serviço"),IF(H32="ETAPA",SUMIFS($N$8:$N$397,$B$8:$B$397,B32,$C$8:$C$397,C32,$H$8:$H$397,"Serviço"),IF(H32="SUBETAPA",SUMIFS($N$8:$N$397,$B$8:$B$397,B32,$C$8:$C$397,C32,$D$8:$D$397,D32,$H$8:$H$397,"Serviço"),0)))) -> 89661.773
A33: =IF($H33="UNIDADE CONSTRUTIVA",OFFSET(A33,-1,0)+1,LARGE(A$3:A32,1)) -> 0 | B33: =IF(H33="UNIDADE CONSTRUTIVA",0,IF(H33="CÉLULA CONSTRUTIVA",OFFSET(B33,-1,0)+1,OFFSET(B33,-1,0))) -> 1 | C33: =IF(H33="CÉLULA CONSTRUTIVA",0,IF(H33="ETAPA",OFFSET(C33,-1,0)+1,OFFSET(C33,-1,0))) -> 1 | D33: =IF(H33="ETAPA",0,IF(H33="SUBETAPA",OFFSET(D33,-1,0)+1,OFFSET(D33,-1,0))) -> 3 | E33: =IF(H33="Subetapa",0,IF(H33="serviço",OFFSET(E33,-1,0)+1,OFFSET(E33,-1,0))) -> 1 | G33: 4688 | H33: SERVIÇO | I33: =IF(H33="Unidade Construtiva",TEXT(A33,"00"),IF(H33="Célula Construtiva",TEXT(B33,"00"),IF(H33="Etapa",CONCATENATE(TEXT(B33,"00"),".",TEXT(C33,"000")),IF(H33="Subetapa",CONCATENATE(TEXT(B33,"00"),".",TEXT(C33,"000"),".",TEXT(D33,"000")),IF(H33="Serviço",CONCATENATE(TEXT(B33,"00"),".",TEXT(C33,"000"),".",TEXT(D33,"000"),".",TEXT(E33,"000")),""))))) -> 01.001.003.001 | J33: Auditoria de qualidade | K33: vb | L33: 1 | M33: 29097.453 | N33: =IF(H33="Serviço",M33*L33,IF(H33="CÉLULA CONSTRUTIVA",SUMIFS($N$8:$N$397,$B$8:$B$397,B33,$H$8:$H$397,"Serviço"),IF(H33="ETAPA",SUMIFS($N$8:$N$397,$B$8:$B$397,B33,$C$8:$C$397,C33,$H$8:$H$397,"Serviço"),IF(H33="SUBETAPA",SUMIFS($N$8:$N$397,$B$8:$B$397,B33,$C$8:$C$397,C33,$D$8:$D$397,D33,$H$8:$H$397,"Serviço"),0)))) -> 29097.453 | P33: Lançado ERP
A34: =IF($H34="UNIDADE CONSTRUTIVA",OFFSET(A34,-1,0)+1,LARGE(A$3:A33,1)) -> 0 | B34: =IF(H34="UNIDADE CONSTRUTIVA",0,IF(H34="CÉLULA CONSTRUTIVA",OFFSET(B34,-1,0)+1,OFFSET(B34,-1,0))) -> 1 | C34: =IF(H34="CÉLULA CONSTRUTIVA",0,IF(H34="ETAPA",OFFSET(C34,-1,0)+1,OFFSET(C34,-1,0))) -> 1 | D34: =IF(H34="ETAPA",0,IF(H34="SUBETAPA",OFFSET(D34,-1,0)+1,OFFSET(D34,-1,0))) -> 3 | E34: =IF(H34="Subetapa",0,IF(H34="serviço",OFFSET(E34,-1,0)+1,OFFSET(E34,-1,0))) -> 2 | H34: SERVIÇO | I34: =IF(H34="Unidade Construtiva",TEXT(A34,"00"),IF(H34="Célula Construtiva",TEXT(B34,"00"),IF(H34="Etapa",CONCATENATE(TEXT(B34,"00"),".",TEXT(C34,"000")),IF(H34="Subetapa",CONCATENATE(TEXT(B34,"00"),".",TEXT(C34,"000"),".",TEXT(D34,"000")),IF(H34="Serviço",CONCATENATE(TEXT(B34,"00"),".",TEXT(C34,"000"),".",TEXT(D34,"000"),".",TEXT(E34,"000")),""))))) -> 01.001.003.002 | J34: Orçamento e planejamento | K34: vb | L34: 1 | M34: 60564.32 | N34: =IF(H34="Serviço",M34*L34,IF(H34="CÉLULA CONSTRUTIVA",SUMIFS($N$8:$N$397,$B$8:$B$397,B34,$H$8:$H$397,"Serviço"),IF(H34="ETAPA",SUMIFS($N$8:$N$397,$B$8:$B$397,B34,$C$8:$C$397,C34,$H$8:$H$397,"Serviço"),IF(H34="SUBETAPA",SUMIFS($N$8:$N$397,$B$8:$B$397,B34,$C$8:$C$397,C34,$D$8:$D$397,D34,$H$8:$H$397,"Serviço"),0)))) -> 60564.32 | P34: Lançado ERP
A35: =IF($H35="UNIDADE CONSTRUTIVA",OFFSET(A35,-1,0)+1,LARGE(A$3:A34,1)) -> 0 | B35: =IF(H35="UNIDADE CONSTRUTIVA",0,IF(H35="CÉLULA CONSTRUTIVA",OFFSET(B35,-1,0)+1,OFFSET(B35,-1,0))) -> 1 | C35: =IF(H35="CÉLULA CONSTRUTIVA",0,IF(H35="ETAPA",OFFSET(C35,-1,0)+1,OFFSET(C35,-1,0))) -> 1 | D35: =IF(H35="ETAPA",0,IF(H35="SUBETAPA",OFFSET(D35,-1,0)+1,OFFSET(D35,-1,0))) -> 4 | E35: =IF(H35="Subetapa",0,IF(H35="serviço",OFFSET(E35,-1,0)+1,OFFSET(E35,-1,0))) -> 0 | H35: SUBETAPA | I35: =IF(H35="Unidade Construtiva",TEXT(A35,"00"),IF(H35="Célula Construtiva",TEXT(B35,"00"),IF(H35="Etapa",CONCATENATE(TEXT(B35,"00"),".",TEXT(C35,"000")),IF(H35="Subetapa",CONCATENATE(TEXT(B35,"00"),".",TEXT(C35,"000"),".",TEXT(D35,"000")),IF(H35="Serviço",CONCATENATE(TEXT(B35,"00"),".",TEXT(C35,"000"),".",TEXT(D35,"000"),".",TEXT(E35,"000")),""))))) -> 01.001.004 | J35: Ensaios | N35: =IF(H35="Serviço",M35*L35,IF(H35="CÉLULA CONSTRUTIVA",SUMIFS($N$8:$N$397,$B$8:$B$397,B35,$H$8:$H$397,"Serviço"),IF(H35="ETAPA",SUMIFS($N$8:$N$397,$B$8:$B$397,B35,$C$8:$C$397,C35,$H$8:$H$397,"Serviço"),IF(H35="SUBETAPA",SUMIFS($N$8:$N$397,$B$8:$B$397,B35,$C$8:$C$397,C35,$D$8:$D$397,D35,$H$8:$H$397,"Serviço"),0)))) -> 99342.435
A36: =IF($H36="UNIDADE CONSTRUTIVA",OFFSET(A36,-1,0)+1,LARGE(A$3:A35,1)) -> 0 | B36: =IF(H36="UNIDADE CONSTRUTIVA",0,IF(H36="CÉLULA CONSTRUTIVA",OFFSET(B36,-1,0)+1,OFFSET(B36,-1,0))) -> 1 | C36: =IF(H36="CÉLULA CONSTRUTIVA",0,IF(H36="ETAPA",OFFSET(C36,-1,0)+1,OFFSET(C36,-1,0))) -> 1 | D36: =IF(H36="ETAPA",0,IF(H36="SUBETAPA",OFFSET(D36,-1,0)+1,OFFSET(D36,-1,0))) -> 4 | E36: =IF(H36="Subetapa",0,IF(H36="serviço",OFFSET(E36,-1,0)+1,OFFSET(E36,-1,0))) -> 1 | G36: 2621 | H36: SERVIÇO | I36: =IF(H36="Unidade Construtiva",TEXT(A36,"00"),IF(H36="Célula Construtiva",TEXT(B36,"00"),IF(H36="Etapa",CONCATENATE(TEXT(B36,"00"),".",TEXT(C36,"000")),IF(H36="Subetapa",CONCATENATE(TEXT(B36,"00"),".",TEXT(C36,"000"),".",TEXT(D36,"000")),IF(H36="Serviço",CONCATENATE(TEXT(B36,"00"),".",TEXT(C36,"000"),".",TEXT(D36,"000"),".",TEXT(E36,"000")),""))))) -> 01.001.004.001 | J36: Controle Tecnologico de Concreto | K36: vb | L36: 1 | M36: 99342.435 | N36: =IF(H36="Serviço",M36*L36,IF(H36="CÉLULA CONSTRUTIVA",SUMIFS($N$8:$N$397,$B$8:$B$397,B36,$H$8:$H$397,"Serviço"),IF(H36="ETAPA",SUMIFS($N$8:$N$397,$B$8:$B$397,B36,$C$8:$C$397,C36,$H$8:$H$397,"Serviço"),IF(H36="SUBETAPA",SUMIFS($N$8:$N$397,$B$8:$B$397,B36,$C$8:$C$397,C36,$D$8:$D$397,D36,$H$8:$H$397,"Serviço"),0)))) -> 99342.435 | P36: Lançado ERP
A37: =IF($H37="UNIDADE CONSTRUTIVA",OFFSET(A37,-1,0)+1,LARGE(A$3:A36,1)) -> 0 | B37: =IF(H37="UNIDADE CONSTRUTIVA",0,IF(H37="CÉLULA CONSTRUTIVA",OFFSET(B37,-1,0)+1,OFFSET(B37,-1,0))) -> 1 | C37: =IF(H37="CÉLULA CONSTRUTIVA",0,IF(H37="ETAPA",OFFSET(C37,-1,0)+1,OFFSET(C37,-1,0))) -> 2 | D37: =IF(H37="ETAPA",0,IF(H37="SUBETAPA",OFFSET(D37,-1,0)+1,OFFSET(D37,-1,0))) -> 0 | E37: =IF(H37="Subetapa",0,IF(H37="serviço",OFFSET(E37,-1,0)+1,OFFSET(E37,-1,0))) -> 1 | H37: ETAPA | I37: =IF(H37="Unidade Construtiva",TEXT(A37,"00"),IF(H37="Célula Construtiva",TEXT(B37,"00"),IF(H37="Etapa",CONCATENATE(TEXT(B37,"00"),".",TEXT(C37,"000")),IF(H37="Subetapa",CONCATENATE(TEXT(B37,"00"),".",TEXT(C37,"000"),".",TEXT(D37,"000")),IF(H37="Serviço",CONCATENATE(TEXT(B37,"00"),".",TEXT(C37,"000"),".",TEXT(D37,"000"),".",TEXT(E37,"000")),""))))) -> 01.002 | J37: CONSUMOS, TAXAS E DOCUMENTOS | N37: =IF(H37="Serviço",M37*L37,IF(H37="CÉLULA CONSTRUTIVA",SUMIFS($N$8:$N$397,$B$8:$B$397,B37,$H$8:$H$397,"Serviço"),IF(H37="ETAPA",SUMIFS($N$8:$N$397,$B$8:$B$397,B37,$C$8:$C$397,C37,$H$8:$H$397,"Serviço"),IF(H37="SUBETAPA",SUMIFS($N$8:$N$397,$B$8:$B$397,B37,$C$8:$C$397,C37,$D$8:$D$397,D37,$H$8:$H$397,"Serviço"),0)))) -> 403490.89 | P37: -
A38: =IF($H38="UNIDADE CONSTRUTIVA",OFFSET(A38,-1,0)+1,LARGE(A$3:A37,1)) -> 0 | B38: =IF(H38="UNIDADE CONSTRUTIVA",0,IF(H38="CÉLULA CONSTRUTIVA",OFFSET(B38,-1,0)+1,OFFSET(B38,-1,0))) -> 1 | C38: =IF(H38="CÉLULA CONSTRUTIVA",0,IF(H38="ETAPA",OFFSET(C38,-1,0)+1,OFFSET(C38,-1,0))) -> 2 | D38: =IF(H38="ETAPA",0,IF(H38="SUBETAPA",OFFSET(D38,-1,0)+1,OFFSET(D38,-1,0))) -> 1 | E38: =IF(H38="Subetapa",0,IF(H38="serviço",OFFSET(E38,-1,0)+1,OFFSET(E38,-1,0))) -> 0 | H38: SUBETAPA | I38: =IF(H38="Unidade Construtiva",TEXT(A38,"00"),IF(H38="Célula Construtiva",TEXT(B38,"00"),IF(H38="Etapa",CONCATENATE(TEXT(B38,"00"),".",TEXT(C38,"000")),IF(H38="Subetapa",CONCATENATE(TEXT(B38,"00"),".",TEXT(C38,"000"),".",TEXT(D38,"000")),IF(H38="Serviço",CONCATENATE(TEXT(B38,"00"),".",TEXT(C38,"000"),".",TEXT(D38,"000"),".",TEXT(E38,"000")),""))))) -> 01.002.001 | J38: Licenciamentos, Taxas, Impostos, Aprovações e Seguros | N38: =IF(H38="Serviço",M38*L38,IF(H38="CÉLULA CONSTRUTIVA",SUMIFS($N$8:$N$397,$B$8:$B$397,B38,$H$8:$H$397,"Serviço"),IF(H38="ETAPA",SUMIFS($N$8:$N$397,$B$8:$B$397,B38,$C$8:$C$397,C38,$H$8:$H$397,"Serviço"),IF(H38="SUBETAPA",SUMIFS($N$8:$N$397,$B$8:$B$397,B38,$C$8:$C$397,C38,$D$8:$D$397,D38,$H$8:$H$397,"Serviço"),0)))) -> 314060.8
A39: =IF($H39="UNIDADE CONSTRUTIVA",OFFSET(A39,-1,0)+1,LARGE(A$3:A38,1)) -> 0 | B39: =IF(H39="UNIDADE CONSTRUTIVA",0,IF(H39="CÉLULA CONSTRUTIVA",OFFSET(B39,-1,0)+1,OFFSET(B39,-1,0))) -> 1 | C39: =IF(H39="CÉLULA CONSTRUTIVA",0,IF(H39="ETAPA",OFFSET(C39,-1,0)+1,OFFSET(C39,-1,0))) -> 2 | D39: =IF(H39="ETAPA",0,IF(H39="SUBETAPA",OFFSET(D39,-1,0)+1,OFFSET(D39,-1,0))) -> 1 | E39: =IF(H39="Subetapa",0,IF(H39="serviço",OFFSET(E39,-1,0)+1,OFFSET(E39,-1,0))) -> 1 | H39: SERVIÇO | I39: =IF(H39="Unidade Construtiva",TEXT(A39,"00"),IF(H39="Célula Construtiva",TEXT(B39,"00"),IF(H39="Etapa",CONCATENATE(TEXT(B39,"00"),".",TEXT(C39,"000")),IF(H39="Subetapa",CONCATENATE(TEXT(B39,"00"),".",TEXT(C39,"000"),".",TEXT(D39,"000")),IF(H39="Serviço",CONCATENATE(TEXT(B39,"00"),".",TEXT(C39,"000"),".",TEXT(D39,"000"),".",TEXT(E39,"000")),""))))) -> 01.002.001.001 | J39: Despesas de Seguros | K39: vb | L39: 1 | M39: 34982.491 | N39: =IF(H39="Serviço",M39*L39,IF(H39="CÉLULA CONSTRUTIVA",SUMIFS($N$8:$N$397,$B$8:$B$397,B39,$H$8:$H$397,"Serviço"),IF(H39="ETAPA",SUMIFS($N$8:$N$397,$B$8:$B$397,B39,$C$8:$C$397,C39,$H$8:$H$397,"Serviço"),IF(H39="SUBETAPA",SUMIFS($N$8:$N$397,$B$8:$B$397,B39,$C$8:$C$397,C39,$D$8:$D$397,D39,$H$8:$H$397,"Serviço"),0)))) -> 34982.491 | P39: Lançado ERP
A40: =IF($H40="UNIDADE CONSTRUTIVA",OFFSET(A40,-1,0)+1,LARGE(A$3:A39,1)) -> 0 | B40: =IF(H40="UNIDADE CONSTRUTIVA",0,IF(H40="CÉLULA CONSTRUTIVA",OFFSET(B40,-1,0)+1,OFFSET(B40,-1,0))) -> 1 | C40: =IF(H40="CÉLULA CONSTRUTIVA",0,IF(H40="ETAPA",OFFSET(C40,-1,0)+1,OFFSET(C40,-1,0))) -> 2 | D40: =IF(H40="ETAPA",0,IF(H40="SUBETAPA",OFFSET(D40,-1,0)+1,OFFSET(D40,-1,0))) -> 1 | E40: =IF(H40="Subetapa",0,IF(H40="serviço",OFFSET(E40,-1,0)+1,OFFSET(E40,-1,0))) -> 2 | H40: SERVIÇO | I40: =IF(H40="Unidade Construtiva",TEXT(A40,"00"),IF(H40="Célula Construtiva",TEXT(B40,"00"),IF(H40="Etapa",CONCATENATE(TEXT(B40,"00"),".",TEXT(C40,"000")),IF(H40="Subetapa",CONCATENATE(TEXT(B40,"00"),".",TEXT(C40,"000"),".",TEXT(D40,"000")),IF(H40="Serviço",CONCATENATE(TEXT(B40,"00"),".",TEXT(C40,"000"),".",TEXT(D40,"000"),".",TEXT(E40,"000")),""))))) -> 01.002.001.002 | J40: Aprovação e legalização ambiental | K40: vb | L40: 1 | M40: 117024.3 | N40: =IF(H40="Serviço",M40*L40,IF(H40="CÉLULA CONSTRUTIVA",SUMIFS($N$8:$N$397,$B$8:$B$397,B40,$H$8:$H$397,"Serviço"),IF(H40="ETAPA",SUMIFS($N$8:$N$397,$B$8:$B$397,B40,$C$8:$C$397,C40,$H$8:$H$397,"Serviço"),IF(H40="SUBETAPA",SUMIFS($N$8:$N$397,$B$8:$B$397,B40,$C$8:$C$397,C40,$D$8:$D$397,D40,$H$8:$H$397,"Serviço"),0)))) -> 117024.3 | P40: Lançado ERP
A41: =IF($H41="UNIDADE CONSTRUTIVA",OFFSET(A41,-1,0)+1,LARGE(A$3:A40,1)) -> 0 | B41: =IF(H41="UNIDADE CONSTRUTIVA",0,IF(H41="CÉLULA CONSTRUTIVA",OFFSET(B41,-1,0)+1,OFFSET(B41,-1,0))) -> 1 | C41: =IF(H41="CÉLULA CONSTRUTIVA",0,IF(H41="ETAPA",OFFSET(C41,-1,0)+1,OFFSET(C41,-1,0))) -> 2 | D41: =IF(H41="ETAPA",0,IF(H41="SUBETAPA",OFFSET(D41,-1,0)+1,OFFSET(D41,-1,0))) -> 1 | E41: =IF(H41="Subetapa",0,IF(H41="serviço",OFFSET(E41,-1,0)+1,OFFSET(E41,-1,0))) -> 3 | G41: 4692 | H41: SERVIÇO | I41: =IF(H41="Unidade Construtiva",TEXT(A41,"00"),IF(H41="Célula Construtiva",TEXT(B41,"00"),IF(H41="Etapa",CONCATENATE(TEXT(B41,"00"),".",TEXT(C41,"000")),IF(H41="Subetapa",CONCATENATE(TEXT(B41,"00"),".",TEXT(C41,"000"),".",TEXT(D41,"000")),IF(H41="Serviço",CONCATENATE(TEXT(B41,"00"),".",TEXT(C41,"000"),".",TEXT(D41,"000"),".",TEXT(E41,"000")),""))))) -> 01.002.001.003 | J41: Aprovação e legalização prefeitura | K41: vb | L41: 1 | M41: 35080.372 | N41: =IF(H41="Serviço",M41*L41,IF(H41="CÉLULA CONSTRUTIVA",SUMIFS($N$8:$N$397,$B$8:$B$397,B41,$H$8:$H$397,"Serviço"),IF(H41="ETAPA",SUMIFS($N$8:$N$397,$B$8:$B$397,B41,$C$8:$C$397,C41,$H$8:$H$397,"Serviço"),IF(H41="SUBETAPA",SUMIFS($N$8:$N$397,$B$8:$B$397,B41,$C$8:$C$397,C41,$D$8:$D$397,D41,$H$8:$H$397,"Serviço"),0)))) -> 35080.372 | P41: Lançado ERP
A42: =IF($H42="UNIDADE CONSTRUTIVA",OFFSET(A42,-1,0)+1,LARGE(A$3:A41,1)) -> 0 | B42: =IF(H42="UNIDADE CONSTRUTIVA",0,IF(H42="CÉLULA CONSTRUTIVA",OFFSET(B42,-1,0)+1,OFFSET(B42,-1,0))) -> 1 | C42: =IF(H42="CÉLULA CONSTRUTIVA",0,IF(H42="ETAPA",OFFSET(C42,-1,0)+1,OFFSET(C42,-1,0))) -> 2 | D42: =IF(H42="ETAPA",0,IF(H42="SUBETAPA",OFFSET(D42,-1,0)+1,OFFSET(D42,-1,0))) -> 1 | E42: =IF(H42="Subetapa",0,IF(H42="serviço",OFFSET(E42,-1,0)+1,OFFSET(E42,-1,0))) -> 4 | G42: 4694 | H42: SERVIÇO | I42: =IF(H42="Unidade Construtiva",TEXT(A42,"00"),IF(H42="Célula Construtiva",TEXT(B42,"00"),IF(H42="Etapa",CONCATENATE(TEXT(B42,"00"),".",TEXT(C42,"000")),IF(H42="Subetapa",CONCATENATE(TEXT(B42,"00"),".",TEXT(C42,"000"),".",TEXT(D42,"000")),IF(H42="Serviço",CONCATENATE(TEXT(B42,"00"),".",TEXT(C42,"000"),".",TEXT(D42,"000"),".",TEXT(E42,"000")),""))))) -> 01.002.001.004 | J42: Aprovação e legalização bombeiros | K42: vb | L42: 1 | M42: 16641.102 | N42: =IF(H42="Serviço",M42*L42,IF(H42="CÉLULA CONSTRUTIVA",SUMIFS($N$8:$N$397,$B$8:$B$397,B42,$H$8:$H$397,"Serviço"),IF(H42="ETAPA",SUMIFS($N$8:$N$397,$B$8:$B$397,B42,$C$8:$C$397,C42,$H$8:$H$397,"Serviço"),IF(H42="SUBETAPA",SUMIFS($N$8:$N$397,$B$8:$B$397,B42,$C$8:$C$397,C42,$D$8:$D$397,D42,$H$8:$H$397,"Serviço"),0)))) -> 16641.102 | P42: Lançado ERP
A43: =IF($H43="UNIDADE CONSTRUTIVA",OFFSET(A43,-1,0)+1,LARGE(A$3:A42,1)) -> 0 | B43: =IF(H43="UNIDADE CONSTRUTIVA",0,IF(H43="CÉLULA CONSTRUTIVA",OFFSET(B43,-1,0)+1,OFFSET(B43,-1,0))) -> 1 | C43: =IF(H43="CÉLULA CONSTRUTIVA",0,IF(H43="ETAPA",OFFSET(C43,-1,0)+1,OFFSET(C43,-1,0))) -> 2 | D43: =IF(H43="ETAPA",0,IF(H43="SUBETAPA",OFFSET(D43,-1,0)+1,OFFSET(D43,-1,0))) -> 1 | E43: =IF(H43="Subetapa",0,IF(H43="serviço",OFFSET(E43,-1,0)+1,OFFSET(E43,-1,0))) -> 5 | G43: 4696 | H43: SERVIÇO | I43: =IF(H43="Unidade Construtiva",TEXT(A43,"00"),IF(H43="Célula Construtiva",TEXT(B43,"00"),IF(H43="Etapa",CONCATENATE(TEXT(B43,"00"),".",TEXT(C43,"000")),IF(H43="Subetapa",CONCATENATE(TEXT(B43,"00"),".",TEXT(C43,"000"),".",TEXT(D43,"000")),IF(H43="Serviço",CONCATENATE(TEXT(B43,"00"),".",TEXT(C43,"000"),".",TEXT(D43,"000"),".",TEXT(E43,"000")),""))))) -> 01.002.001.005 | J43: Taxas de ART | K43: vb | L43: 1 | M43: 4476.4481 | N43: =IF(H43="Serviço",M43*L43,IF(H43="CÉLULA CONSTRUTIVA",SUMIFS($N$8:$N$397,$B$8:$B$397,B43,$H$8:$H$397,"Serviço"),IF(H43="ETAPA",SUMIFS($N$8:$N$397,$B$8:$B$397,B43,$C$8:$C$397,C43,$H$8:$H$397,"Serviço"),IF(H43="SUBETAPA",SUMIFS($N$8:$N$397,$B$8:$B$397,B43,$C$8:$C$397,C43,$D$8:$D$397,D43,$H$8:$H$397,"Serviço"),0)))) -> 4476.4481 | P43: Lançado ERP
A44: =IF($H44="UNIDADE CONSTRUTIVA",OFFSET(A44,-1,0)+1,LARGE(A$3:A43,1)) -> 0 | B44: =IF(H44="UNIDADE CONSTRUTIVA",0,IF(H44="CÉLULA CONSTRUTIVA",OFFSET(B44,-1,0)+1,OFFSET(B44,-1,0))) -> 1 | C44: =IF(H44="CÉLULA CONSTRUTIVA",0,IF(H44="ETAPA",OFFSET(C44,-1,0)+1,OFFSET(C44,-1,0))) -> 2 | D44: =IF(H44="ETAPA",0,IF(H44="SUBETAPA",OFFSET(D44,-1,0)+1,OFFSET(D44,-1,0))) -> 1 | E44: =IF(H44="Subetapa",0,IF(H44="serviço",OFFSET(E44,-1,0)+1,OFFSET(E44,-1,0))) -> 6 | H44: SERVIÇO | I44: =IF(H44="Unidade Construtiva",TEXT(A44,"00"),IF(H44="Célula Construtiva",TEXT(B44,"00"),IF(H44="Etapa",CONCATENATE(TEXT(B44,"00"),".",TEXT(C44,"000")),IF(H44="Subetapa",CONCATENATE(TEXT(B44,"00"),".",TEXT(C44,"000"),".",TEXT(D44,"000")),IF(H44="Serviço",CONCATENATE(TEXT(B44,"00"),".",TEXT(C44,"000"),".",TEXT(D44,"000"),".",TEXT(E44,"000")),""))))) -> 01.002.001.006 | J44: Alvará Construção | K44: vb | L44: 1 | M44: 58758.826 | N44: =IF(H44="Serviço",M44*L44,IF(H44="CÉLULA CONSTRUTIVA",SUMIFS($N$8:$N$397,$B$8:$B$397,B44,$H$8:$H$397,"Serviço"),IF(H44="ETAPA",SUMIFS($N$8:$N$397,$B$8:$B$397,B44,$C$8:$C$397,C44,$H$8:$H$397,"Serviço"),IF(H44="SUBETAPA",SUMIFS($N$8:$N$397,$B$8:$B$397,B44,$C$8:$C$397,C44,$D$8:$D$397,D44,$H$8:$H$397,"Serviço"),0)))) -> 58758.826 | P44: Lançado ERP
A45: =IF($H45="UNIDADE CONSTRUTIVA",OFFSET(A45,-1,0)+1,LARGE(A$3:A44,1)) -> 0 | B45: =IF(H45="UNIDADE CONSTRUTIVA",0,IF(H45="CÉLULA CONSTRUTIVA",OFFSET(B45,-1,0)+1,OFFSET(B45,-1,0))) -> 1 | C45: =IF(H45="CÉLULA CONSTRUTIVA",0,IF(H45="ETAPA",OFFSET(C45,-1,0)+1,OFFSET(C45,-1,0))) -> 2 | D45: =IF(H45="ETAPA",0,IF(H45="SUBETAPA",OFFSET(D45,-1,0)+1,OFFSET(D45,-1,0))) -> 1 | E45: =IF(H45="Subetapa",0,IF(H45="serviço",OFFSET(E45,-1,0)+1,OFFSET(E45,-1,0))) -> 7 | H45: SERVIÇO | I45: =IF(H45="Unidade Construtiva",TEXT(A45,"00"),IF(H45="Célula Construtiva",TEXT(B45,"00"),IF(H45="Etapa",CONCATENATE(TEXT(B45,"00"),".",TEXT(C45,"000")),IF(H45="Subetapa",CONCATENATE(TEXT(B45,"00"),".",TEXT(C45,"000"),".",TEXT(D45,"000")),IF(H45="Serviço",CONCATENATE(TEXT(B45,"00"),".",TEXT(C45,"000"),".",TEXT(D45,"000"),".",TEXT(E45,"000")),""))))) -> 01.002.001.007 | J45: Alvará Habite-se | K45: vb | L45: 1 | M45: 47097.258 | N45: =IF(H45="Serviço",M45*L45,IF(H45="CÉLULA CONSTRUTIVA",SUMIFS($N$8:$N$397,$B$8:$B$397,B45,$H$8:$H$397,"Serviço"),IF(H45="ETAPA",SUMIFS($N$8:$N$397,$B$8:$B$397,B45,$C$8:$C$397,C45,$H$8:$H$397,"Serviço"),IF(H45="SUBETAPA",SUMIFS($N$8:$N$397,$B$8:$B$397,B45,$C$8:$C$397,C45,$D$8:$D$397,D45,$H$8:$H$397,"Serviço"),0)))) -> 47097.258 | P45: Lançado ERP
A46: =IF($H46="UNIDADE CONSTRUTIVA",OFFSET(A46,-1,0)+1,LARGE(A$3:A45,1)) -> 0 | B46: =IF(H46="UNIDADE CONSTRUTIVA",0,IF(H46="CÉLULA CONSTRUTIVA",OFFSET(B46,-1,0)+1,OFFSET(B46,-1,0))) -> 1 | C46: =IF(H46="CÉLULA CONSTRUTIVA",0,IF(H46="ETAPA",OFFSET(C46,-1,0)+1,OFFSET(C46,-1,0))) -> 2 | D46: =IF(H46="ETAPA",0,IF(H46="SUBETAPA",OFFSET(D46,-1,0)+1,OFFSET(D46,-1,0))) -> 2 | E46: =IF(H46="Subetapa",0,IF(H46="serviço",OFFSET(E46,-1,0)+1,OFFSET(E46,-1,0))) -> 0 | H46: SUBETAPA | I46: =IF(H46="Unidade Construtiva",TEXT(A46,"00"),IF(H46="Célula Construtiva",TEXT(B46,"00"),IF(H46="Etapa",CONCATENATE(TEXT(B46,"00"),".",TEXT(C46,"000")),IF(H46="Subetapa",CONCATENATE(TEXT(B46,"00"),".",TEXT(C46,"000"),".",TEXT(D46,"000")),IF(H46="Serviço",CONCATENATE(TEXT(B46,"00"),".",TEXT(C46,"000"),".",TEXT(D46,"000"),".",TEXT(E46,"000")),""))))) -> 01.002.002 | J46: Documentos | N46: =IF(H46="Serviço",M46*L46,IF(H46="CÉLULA CONSTRUTIVA",SUMIFS($N$8:$N$397,$B$8:$B$397,B46,$H$8:$H$397,"Serviço"),IF(H46="ETAPA",SUMIFS($N$8:$N$397,$B$8:$B$397,B46,$C$8:$C$397,C46,$H$8:$H$397,"Serviço"),IF(H46="SUBETAPA",SUMIFS($N$8:$N$397,$B$8:$B$397,B46,$C$8:$C$397,C46,$D$8:$D$397,D46,$H$8:$H$397,"Serviço"),0)))) -> 89430.093
A47: =IF($H47="UNIDADE CONSTRUTIVA",OFFSET(A47,-1,0)+1,LARGE(A$3:A45,1)) -> 0 | B47: =IF(H47="UNIDADE CONSTRUTIVA",0,IF(H47="CÉLULA CONSTRUTIVA",OFFSET(B47,-1,0)+1,OFFSET(B47,-1,0))) -> 1 | C47: =IF(H47="CÉLULA CONSTRUTIVA",0,IF(H47="ETAPA",OFFSET(C47,-1,0)+1,OFFSET(C47,-1,0))) -> 2 | D47: =IF(H47="ETAPA",0,IF(H47="SUBETAPA",OFFSET(D47,-1,0)+1,OFFSET(D47,-1,0))) -> 2 | E47: =IF(H47="Subetapa",0,IF(H47="serviço",OFFSET(E47,-1,0)+1,OFFSET(E47,-1,0))) -> 1 | G47: 4698 | H47: SERVIÇO | I47: =IF(H47="Unidade Construtiva",TEXT(A47,"00"),IF(H47="Célula Construtiva",TEXT(B47,"00"),IF(H47="Etapa",CONCATENATE(TEXT(B47,"00"),".",TEXT(C47,"000")),IF(H47="Subetapa",CONCATENATE(TEXT(B47,"00"),".",TEXT(C47,"000"),".",TEXT(D47,"000")),IF(H47="Serviço",CONCATENATE(TEXT(B47,"00"),".",TEXT(C47,"000"),".",TEXT(D47,"000"),".",TEXT(E47,"000")),""))))) -> 01.002.002.001 | J47: As Built | K47: vb | L47: 1 | M47: 17395.468 | N47: =IF(H47="Serviço",M47*L47,IF(H47="CÉLULA CONSTRUTIVA",SUMIFS($N$8:$N$397,$B$8:$B$397,B47,$H$8:$H$397,"Serviço"),IF(H47="ETAPA",SUMIFS($N$8:$N$397,$B$8:$B$397,B47,$C$8:$C$397,C47,$H$8:$H$397,"Serviço"),IF(H47="SUBETAPA",SUMIFS($N$8:$N$397,$B$8:$B$397,B47,$C$8:$C$397,C47,$D$8:$D$397,D47,$H$8:$H$397,"Serviço"),0)))) -> 17395.468 | P47: Lançado ERP
A48: =IF($H48="UNIDADE CONSTRUTIVA",OFFSET(A48,-1,0)+1,LARGE(A$3:A46,1)) -> 0 | B48: =IF(H48="UNIDADE CONSTRUTIVA",0,IF(H48="CÉLULA CONSTRUTIVA",OFFSET(B48,-1,0)+1,OFFSET(B48,-1,0))) -> 1 | C48: =IF(H48="CÉLULA CONSTRUTIVA",0,IF(H48="ETAPA",OFFSET(C48,-1,0)+1,OFFSET(C48,-1,0))) -> 2 | D48: =IF(H48="ETAPA",0,IF(H48="SUBETAPA",OFFSET(D48,-1,0)+1,OFFSET(D48,-1,0))) -> 2 | E48: =IF(H48="Subetapa",0,IF(H48="serviço",OFFSET(E48,-1,0)+1,OFFSET(E48,-1,0))) -> 2 | G48: 4700 | H48: SERVIÇO | I48: =IF(H48="Unidade Construtiva",TEXT(A48,"00"),IF(H48="Célula Construtiva",TEXT(B48,"00"),IF(H48="Etapa",CONCATENATE(TEXT(B48,"00"),".",TEXT(C48,"000")),IF(H48="Subetapa",CONCATENATE(TEXT(B48,"00"),".",TEXT(C48,"000"),".",TEXT(D48,"000")),IF(H48="Serviço",CONCATENATE(TEXT(B48,"00"),".",TEXT(C48,"000"),".",TEXT(D48,"000"),".",TEXT(E48,"000")),""))))) -> 01.002.002.002 | J48: Manuais técnicos condomínio/proprietários | K48: vb | L48: 1 | M48: 52365.637 | N48: =IF(H48="Serviço",M48*L48,IF(H48="CÉLULA CONSTRUTIVA",SUMIFS($N$8:$N$397,$B$8:$B$397,B48,$H$8:$H$397,"Serviço"),IF(H48="ETAPA",SUMIFS($N$8:$N$397,$B$8:$B$397,B48,$C$8:$C$397,C48,$H$8:$H$397,"Serviço"),IF(H48="SUBETAPA",SUMIFS($N$8:$N$397,$B$8:$B$397,B48,$C$8:$C$397,C48,$D$8:$D$397,D48,$H$8:$H$397,"Serviço"),0)))) -> 52365.637 | P48: Lançado ERP
A49: =IF($H49="UNIDADE CONSTRUTIVA",OFFSET(A49,-1,0)+1,LARGE(A$3:A48,1)) -> 0 | B49: =IF(H49="UNIDADE CONSTRUTIVA",0,IF(H49="CÉLULA CONSTRUTIVA",OFFSET(B49,-1,0)+1,OFFSET(B49,-1,0))) -> 1 | C49: =IF(H49="CÉLULA CONSTRUTIVA",0,IF(H49="ETAPA",OFFSET(C49,-1,0)+1,OFFSET(C49,-1,0))) -> 2 | D49: =IF(H49="ETAPA",0,IF(H49="SUBETAPA",OFFSET(D49,-1,0)+1,OFFSET(D49,-1,0))) -> 2 | E49: =IF(H49="Subetapa",0,IF(H49="serviço",OFFSET(E49,-1,0)+1,OFFSET(E49,-1,0))) -> 3 | G49: 4702 | H49: SERVIÇO | I49: =IF(H49="Unidade Construtiva",TEXT(A49,"00"),IF(H49="Célula Construtiva",TEXT(B49,"00"),IF(H49="Etapa",CONCATENATE(TEXT(B49,"00"),".",TEXT(C49,"000")),IF(H49="Subetapa",CONCATENATE(TEXT(B49,"00"),".",TEXT(C49,"000"),".",TEXT(D49,"000")),IF(H49="Serviço",CONCATENATE(TEXT(B49,"00"),".",TEXT(C49,"000"),".",TEXT(D49,"000"),".",TEXT(E49,"000")),""))))) -> 01.002.002.003 | J49: Certidão INSS | K49: vb | L49: 1 | M49: 19668.987 | N49: =IF(H49="Serviço",M49*L49,IF(H49="CÉLULA CONSTRUTIVA",SUMIFS($N$8:$N$397,$B$8:$B$397,B49,$H$8:$H$397,"Serviço"),IF(H49="ETAPA",SUMIFS($N$8:$N$397,$B$8:$B$397,B49,$C$8:$C$397,C49,$H$8:$H$397,"Serviço"),IF(H49="SUBETAPA",SUMIFS($N$8:$N$397,$B$8:$B$397,B49,$C$8:$C$397,C49,$D$8:$D$397,D49,$H$8:$H$397,"Serviço"),0)))) -> 19668.987 | P49: Lançado ERP
A50: =IF($H50="UNIDADE CONSTRUTIVA",OFFSET(A50,-1,0)+1,LARGE(A$3:A49,1)) -> 0 | B50: =IF(H50="UNIDADE CONSTRUTIVA",0,IF(H50="CÉLULA CONSTRUTIVA",OFFSET(B50,-1,0)+1,OFFSET(B50,-1,0))) -> 2 | C50: =IF(H50="CÉLULA CONSTRUTIVA",0,IF(H50="ETAPA",OFFSET(C50,-1,0)+1,OFFSET(C50,-1,0))) -> 0 | D50: =IF(H50="ETAPA",0,IF(H50="SUBETAPA",OFFSET(D50,-1,0)+1,OFFSET(D50,-1,0))) -> 2 | E50: =IF(H50="Subetapa",0,IF(H50="serviço",OFFSET(E50,-1,0)+1,OFFSET(E50,-1,0))) -> 3 | H50: CÉLULA CONSTRUTIVA | I50: =IF(H50="Unidade Construtiva",TEXT(A50,"00"),IF(H50="Célula Construtiva",TEXT(B50,"00"),IF(H50="Etapa",CONCATENATE(TEXT(B50,"00"),".",TEXT(C50,"000")),IF(H50="Subetapa",CONCATENATE(TEXT(B50,"00"),".",TEXT(C50,"000"),".",TEXT(D50,"000")),IF(H50="Serviço",CONCATENATE(TEXT(B50,"00"),".",TEXT(C50,"000"),".",TEXT(D50,"000"),".",TEXT(E50,"000")),""))))) -> 02 | J50: GERENCIAMENTO ADMINISTRATIVO | N50: =IF(H50="Serviço",M50*L50,IF(H50="CÉLULA CONSTRUTIVA",SUMIFS($N$8:$N$397,$B$8:$B$397,B50,$H$8:$H$397,"Serviço"),IF(H50="ETAPA",SUMIFS($N$8:$N$397,$B$8:$B$397,B50,$C$8:$C$397,C50,$H$8:$H$397,"Serviço"),IF(H50="SUBETAPA",SUMIFS($N$8:$N$397,$B$8:$B$397,B50,$C$8:$C$397,C50,$D$8:$D$397,D50,$H$8:$H$397,"Serviço"),0)))) -> 1791735.4
A51: =IF($H51="UNIDADE CONSTRUTIVA",OFFSET(A51,-1,0)+1,LARGE(A$3:A50,1)) -> 0 | B51: =IF(H51="UNIDADE CONSTRUTIVA",0,IF(H51="CÉLULA CONSTRUTIVA",OFFSET(B51,-1,0)+1,OFFSET(B51,-1,0))) -> 2 | C51: =IF(H51="CÉLULA CONSTRUTIVA",0,IF(H51="ETAPA",OFFSET(C51,-1,0)+1,OFFSET(C51,-1,0))) -> 1 | D51: =IF(H51="ETAPA",0,IF(H51="SUBETAPA",OFFSET(D51,-1,0)+1,OFFSET(D51,-1,0))) -> 0 | E51: =IF(H51="Subetapa",0,IF(H51="serviço",OFFSET(E51,-1,0)+1,OFFSET(E51,-1,0))) -> 3 | H51: ETAPA | I51: =IF(H51="Unidade Construtiva",TEXT(A51,"00"),IF(H51="Célula Construtiva",TEXT(B51,"00"),IF(H51="Etapa",CONCATENATE(TEXT(B51,"00"),".",TEXT(C51,"000")),IF(H51="Subetapa",CONCATENATE(TEXT(B51,"00"),".",TEXT(C51,"000"),".",TEXT(D51,"000")),IF(H51="Serviço",CONCATENATE(TEXT(B51,"00"),".",TEXT(C51,"000"),".",TEXT(D51,"000"),".",TEXT(E51,"000")),""))))) -> 02.001 | J51: SEGURANÇA, MEIO AMBIENTE E SAÚDE | N51: =IF(H51="Serviço",M51*L51,IF(H51="CÉLULA CONSTRUTIVA",SUMIFS($N$8:$N$397,$B$8:$B$397,B51,$H$8:$H$397,"Serviço"),IF(H51="ETAPA",SUMIFS($N$8:$N$397,$B$8:$B$397,B51,$C$8:$C$397,C51,$H$8:$H$397,"Serviço"),IF(H51="SUBETAPA",SUMIFS($N$8:$N$397,$B$8:$B$397,B51,$C$8:$C$397,C51,$D$8:$D$397,D51,$H$8:$H$397,"Serviço"),0)))) -> 292055.02
A52: =IF($H52="UNIDADE CONSTRUTIVA",OFFSET(A52,-1,0)+1,LARGE(A$3:A51,1)) -> 0 | B52: =IF(H52="UNIDADE CONSTRUTIVA",0,IF(H52="CÉLULA CONSTRUTIVA",OFFSET(B52,-1,0)+1,OFFSET(B52,-1,0))) -> 2 | C52: =IF(H52="CÉLULA CONSTRUTIVA",0,IF(H52="ETAPA",OFFSET(C52,-1,0)+1,OFFSET(C52,-1,0))) -> 1 | D52: =IF(H52="ETAPA",0,IF(H52="SUBETAPA",OFFSET(D52,-1,0)+1,OFFSET(D52,-1,0))) -> 1 | E52: =IF(H52="Subetapa",0,IF(H52="serviço",OFFSET(E52,-1,0)+1,OFFSET(E52,-1,0))) -> 0 | H52: SUBETAPA | I52: =IF(H52="Unidade Construtiva",TEXT(A52,"00"),IF(H52="Célula Construtiva",TEXT(B52,"00"),IF(H52="Etapa",CONCATENATE(TEXT(B52,"00"),".",TEXT(C52,"000")),IF(H52="Subetapa",CONCATENATE(TEXT(B52,"00"),".",TEXT(C52,"000"),".",TEXT(D52,"000")),IF(H52="Serviço",CONCATENATE(TEXT(B52,"00"),".",TEXT(C52,"000"),".",TEXT(D52,"000"),".",TEXT(E52,"000")),""))))) -> 02.001.001 | J52: Equipamentos de proteção de canteiro | N52: =IF(H52="Serviço",M52*L52,IF(H52="CÉLULA CONSTRUTIVA",SUMIFS($N$8:$N$397,$B$8:$B$397,B52,$H$8:$H$397,"Serviço"),IF(H52="ETAPA",SUMIFS($N$8:$N$397,$B$8:$B$397,B52,$C$8:$C$397,C52,$H$8:$H$397,"Serviço"),IF(H52="SUBETAPA",SUMIFS($N$8:$N$397,$B$8:$B$397,B52,$C$8:$C$397,C52,$D$8:$D$397,D52,$H$8:$H$397,"Serviço"),0)))) -> 209181.24
A53: =IF($H53="UNIDADE CONSTRUTIVA",OFFSET(A53,-1,0)+1,LARGE(A$3:A52,1)) -> 0 | B53: =IF(H53="UNIDADE CONSTRUTIVA",0,IF(H53="CÉLULA CONSTRUTIVA",OFFSET(B53,-1,0)+1,OFFSET(B53,-1,0))) -> 2 | C53: =IF(H53="CÉLULA CONSTRUTIVA",0,IF(H53="ETAPA",OFFSET(C53,-1,0)+1,OFFSET(C53,-1,0))) -> 1 | D53: =IF(H53="ETAPA",0,IF(H53="SUBETAPA",OFFSET(D53,-1,0)+1,OFFSET(D53,-1,0))) -> 1 | E53: =IF(H53="Subetapa",0,IF(H53="serviço",OFFSET(E53,-1,0)+1,OFFSET(E53,-1,0))) -> 1 | H53: SERVIÇO | I53: =IF(H53="Unidade Construtiva",TEXT(A53,"00"),IF(H53="Célula Construtiva",TEXT(B53,"00"),IF(H53="Etapa",CONCATENATE(TEXT(B53,"00"),".",TEXT(C53,"000")),IF(H53="Subetapa",CONCATENATE(TEXT(B53,"00"),".",TEXT(C53,"000"),".",TEXT(D53,"000")),IF(H53="Serviço",CONCATENATE(TEXT(B53,"00"),".",TEXT(C53,"000"),".",TEXT(D53,"000"),".",TEXT(E53,"000")),""))))) -> 02.001.001.001 | J53: Bandeja de Proteção Primária com estrutura metálica e trama de madeira | K53: m | L53: 164.035 | M53: 284.8 | N53: =IF(H53="Serviço",M53*L53,IF(H53="CÉLULA CONSTRUTIVA",SUMIFS($N$8:$N$397,$B$8:$B$397,B53,$H$8:$H$397,"Serviço"),IF(H53="ETAPA",SUMIFS($N$8:$N$397,$B$8:$B$397,B53,$C$8:$C$397,C53,$H$8:$H$397,"Serviço"),IF(H53="SUBETAPA",SUMIFS($N$8:$N$397,$B$8:$B$397,B53,$C$8:$C$397,C53,$D$8:$D$397,D53,$H$8:$H$397,"Serviço"),0)))) -> 46717.168 | O53: Previsto confomre NR18 | P53: Lançado ERP
A54: =IF($H54="UNIDADE CONSTRUTIVA",OFFSET(A54,-1,0)+1,LARGE(A$3:A53,1)) -> 0 | B54: =IF(H54="UNIDADE CONSTRUTIVA",0,IF(H54="CÉLULA CONSTRUTIVA",OFFSET(B54,-1,0)+1,OFFSET(B54,-1,0))) -> 2 | C54: =IF(H54="CÉLULA CONSTRUTIVA",0,IF(H54="ETAPA",OFFSET(C54,-1,0)+1,OFFSET(C54,-1,0))) -> 1 | D54: =IF(H54="ETAPA",0,IF(H54="SUBETAPA",OFFSET(D54,-1,0)+1,OFFSET(D54,-1,0))) -> 1 | E54: =IF(H54="Subetapa",0,IF(H54="serviço",OFFSET(E54,-1,0)+1,OFFSET(E54,-1,0))) -> 2 | H54: SERVIÇO | I54: =IF(H54="Unidade Construtiva",TEXT(A54,"00"),IF(H54="Célula Construtiva",TEXT(B54,"00"),IF(H54="Etapa",CONCATENATE(TEXT(B54,"00"),".",TEXT(C54,"000")),IF(H54="Subetapa",CONCATENATE(TEXT(B54,"00"),".",TEXT(C54,"000"),".",TEXT(D54,"000")),IF(H54="Serviço",CONCATENATE(TEXT(B54,"00"),".",TEXT(C54,"000"),".",TEXT(D54,"000"),".",TEXT(E54,"000")),""))))) -> 02.001.001.002 | J54: Bandeja de Proteção Seundária com estrutura metálica e trama de madeira | K54: m | L54: 118.595 | M54: 270.94 | N54: =IF(H54="Serviço",M54*L54,IF(H54="CÉLULA CONSTRUTIVA",SUMIFS($N$8:$N$397,$B$8:$B$397,B54,$H$8:$H$397,"Serviço"),IF(H54="ETAPA",SUMIFS($N$8:$N$397,$B$8:$B$397,B54,$C$8:$C$397,C54,$H$8:$H$397,"Serviço"),IF(H54="SUBETAPA",SUMIFS($N$8:$N$397,$B$8:$B$397,B54,$C$8:$C$397,C54,$D$8:$D$397,D54,$H$8:$H$397,"Serviço"),0)))) -> 32132.129 | O54: Previsto confomre NR18 | P54: Lançado ERP
A55: =IF($H55="UNIDADE CONSTRUTIVA",OFFSET(A55,-1,0)+1,LARGE(A$3:A54,1)) -> 0 | B55: =IF(H55="UNIDADE CONSTRUTIVA",0,IF(H55="CÉLULA CONSTRUTIVA",OFFSET(B55,-1,0)+1,OFFSET(B55,-1,0))) -> 2 | C55: =IF(H55="CÉLULA CONSTRUTIVA",0,IF(H55="ETAPA",OFFSET(C55,-1,0)+1,OFFSET(C55,-1,0))) -> 1 | D55: =IF(H55="ETAPA",0,IF(H55="SUBETAPA",OFFSET(D55,-1,0)+1,OFFSET(D55,-1,0))) -> 1 | E55: =IF(H55="Subetapa",0,IF(H55="serviço",OFFSET(E55,-1,0)+1,OFFSET(E55,-1,0))) -> 3 | H55: SERVIÇO | I55: =IF(H55="Unidade Construtiva",TEXT(A55,"00"),IF(H55="Célula Construtiva",TEXT(B55,"00"),IF(H55="Etapa",CONCATENATE(TEXT(B55,"00"),".",TEXT(C55,"000")),IF(H55="Subetapa",CONCATENATE(TEXT(B55,"00"),".",TEXT(C55,"000"),".",TEXT(D55,"000")),IF(H55="Serviço",CONCATENATE(TEXT(B55,"00"),".",TEXT(C55,"000"),".",TEXT(D55,"000"),".",TEXT(E55,"000")),""))))) -> 02.001.001.003 | J55: Guarda-corpo de vãos, fixado em fôrma de madeira, em trama de madeira com tela de polipropileno | K55: m | L55: 350.23818 | M55: 15.3754 | N55: =IF(H55="Serviço",M55*L55,IF(H55="CÉLULA CONSTRUTIVA",SUMIFS($N$8:$N$397,$B$8:$B$397,B55,$H$8:$H$397,"Serviço"),IF(H55="ETAPA",SUMIFS($N$8:$N$397,$B$8:$B$397,B55,$C$8:$C$397,C55,$H$8:$H$397,"Serviço"),IF(H55="SUBETAPA",SUMIFS($N$8:$N$397,$B$8:$B$397,B55,$C$8:$C$397,C55,$D$8:$D$397,D55,$H$8:$H$397,"Serviço"),0)))) -> 5385.0521 | O55: Previsto confomre NR18 | P55: Lançado ERP
A56: =IF($H56="UNIDADE CONSTRUTIVA",OFFSET(A56,-1,0)+1,LARGE(A$3:A55,1)) -> 0 | B56: =IF(H56="UNIDADE CONSTRUTIVA",0,IF(H56="CÉLULA CONSTRUTIVA",OFFSET(B56,-1,0)+1,OFFSET(B56,-1,0))) -> 2 | C56: =IF(H56="CÉLULA CONSTRUTIVA",0,IF(H56="ETAPA",OFFSET(C56,-1,0)+1,OFFSET(C56,-1,0))) -> 1 | D56: =IF(H56="ETAPA",0,IF(H56="SUBETAPA",OFFSET(D56,-1,0)+1,OFFSET(D56,-1,0))) -> 1 | E56: =IF(H56="Subetapa",0,IF(H56="serviço",OFFSET(E56,-1,0)+1,OFFSET(E56,-1,0))) -> 4 | H56: SERVIÇO | I56: =IF(H56="Unidade Construtiva",TEXT(A56,"00"),IF(H56="Célula Construtiva",TEXT(B56,"00"),IF(H56="Etapa",CONCATENATE(TEXT(B56,"00"),".",TEXT(C56,"000")),IF(H56="Subetapa",CONCATENATE(TEXT(B56,"00"),".",TEXT(C56,"000"),".",TEXT(D56,"000")),IF(H56="Serviço",CONCATENATE(TEXT(B56,"00"),".",TEXT(C56,"000"),".",TEXT(D56,"000"),".",TEXT(E56,"000")),""))))) -> 02.001.001.004 | J56: Guarda corpo de laje após desforma de pontalete de madeira, travessões e tela | K56: m | L56: 474.38 | M56: 17.8887 | N56: =IF(H56="Serviço",M56*L56,IF(H56="CÉLULA CONSTRUTIVA",SUMIFS($N$8:$N$397,$B$8:$B$397,B56,$H$8:$H$397,"Serviço"),IF(H56="ETAPA",SUMIFS($N$8:$N$397,$B$8:$B$397,B56,$C$8:$C$397,C56,$H$8:$H$397,"Serviço"),IF(H56="SUBETAPA",SUMIFS($N$8:$N$397,$B$8:$B$397,B56,$C$8:$C$397,C56,$D$8:$D$397,D56,$H$8:$H$397,"Serviço"),0)))) -> 8486.0415 | O56: Previsto confomre NR18 | P56: Lançado ERP
A57: =IF($H57="UNIDADE CONSTRUTIVA",OFFSET(A57,-1,0)+1,LARGE(A$3:A56,1)) -> 0 | B57: =IF(H57="UNIDADE CONSTRUTIVA",0,IF(H57="CÉLULA CONSTRUTIVA",OFFSET(B57,-1,0)+1,OFFSET(B57,-1,0))) -> 2 | C57: =IF(H57="CÉLULA CONSTRUTIVA",0,IF(H57="ETAPA",OFFSET(C57,-1,0)+1,OFFSET(C57,-1,0))) -> 1 | D57: =IF(H57="ETAPA",0,IF(H57="SUBETAPA",OFFSET(D57,-1,0)+1,OFFSET(D57,-1,0))) -> 1 | E57: =IF(H57="Subetapa",0,IF(H57="serviço",OFFSET(E57,-1,0)+1,OFFSET(E57,-1,0))) -> 5 | H57: SERVIÇO | I57: =IF(H57="Unidade Construtiva",TEXT(A57,"00"),IF(H57="Célula Construtiva",TEXT(B57,"00"),IF(H57="Etapa",CONCATENATE(TEXT(B57,"00"),".",TEXT(C57,"000")),IF(H57="Subetapa",CONCATENATE(TEXT(B57,"00"),".",TEXT(C57,"000"),".",TEXT(D57,"000")),IF(H57="Serviço",CONCATENATE(TEXT(B57,"00"),".",TEXT(C57,"000"),".",TEXT(D57,"000"),".",TEXT(E57,"000")),""))))) -> 02.001.001.005 | J57: Fechamento removível de vãos de porta de elevador em madeira | K57: m2 | L57: 184.11 | M57: 47.35 | N57: =IF(H57="Serviço",M57*L57,IF(H57="CÉLULA CONSTRUTIVA",SUMIFS($N$8:$N$397,$B$8:$B$397,B57,$H$8:$H$397,"Serviço"),IF(H57="ETAPA",SUMIFS($N$8:$N$397,$B$8:$B$397,B57,$C$8:$C$397,C57,$H$8:$H$397,"Serviço"),IF(H57="SUBETAPA",SUMIFS($N$8:$N$397,$B$8:$B$397,B57,$C$8:$C$397,C57,$D$8:$D$397,D57,$H$8:$H$397,"Serviço"),0)))) -> 8717.6085 | O57: Previsto confomre NR18 | P57: Lançado ERP
A58: =IF($H58="UNIDADE CONSTRUTIVA",OFFSET(A58,-1,0)+1,LARGE(A$3:A57,1)) -> 0 | B58: =IF(H58="UNIDADE CONSTRUTIVA",0,IF(H58="CÉLULA CONSTRUTIVA",OFFSET(B58,-1,0)+1,OFFSET(B58,-1,0))) -> 2 | C58: =IF(H58="CÉLULA CONSTRUTIVA",0,IF(H58="ETAPA",OFFSET(C58,-1,0)+1,OFFSET(C58,-1,0))) -> 1 | D58: =IF(H58="ETAPA",0,IF(H58="SUBETAPA",OFFSET(D58,-1,0)+1,OFFSET(D58,-1,0))) -> 1 | E58: =IF(H58="Subetapa",0,IF(H58="serviço",OFFSET(E58,-1,0)+1,OFFSET(E58,-1,0))) -> 6 | H58: SERVIÇO | I58: =IF(H58="Unidade Construtiva",TEXT(A58,"00"),IF(H58="Célula Construtiva",TEXT(B58,"00"),IF(H58="Etapa",CONCATENATE(TEXT(B58,"00"),".",TEXT(C58,"000")),IF(H58="Subetapa",CONCATENATE(TEXT(B58,"00"),".",TEXT(C58,"000"),".",TEXT(D58,"000")),IF(H58="Serviço",CONCATENATE(TEXT(B58,"00"),".",TEXT(C58,"000"),".",TEXT(D58,"000"),".",TEXT(E58,"000")),""))))) -> 02.001.001.006 | J58: Tela fachadeira mosqueteiro reforçada simples | K58: m2 | L58: 5118.0753 | M58: 11.8 | N58: =IF(H58="Serviço",M58*L58,IF(H58="CÉLULA CONSTRUTIVA",SUMIFS($N$8:$N$397,$B$8:$B$397,B58,$H$8:$H$397,"Serviço"),IF(H58="ETAPA",SUMIFS($N$8:$N$397,$B$8:$B$397,B58,$C$8:$C$397,C58,$H$8:$H$397,"Serviço"),IF(H58="SUBETAPA",SUMIFS($N$8:$N$397,$B$8:$B$397,B58,$C$8:$C$397,C58,$D$8:$D$397,D58,$H$8:$H$397,"Serviço"),0)))) -> 60393.289 | O58: Previsto confomre NR18 | P58: Lançado ERP
A59: =IF($H59="UNIDADE CONSTRUTIVA",OFFSET(A59,-1,0)+1,LARGE(A$3:A58,1)) -> 0 | B59: =IF(H59="UNIDADE CONSTRUTIVA",0,IF(H59="CÉLULA CONSTRUTIVA",OFFSET(B59,-1,0)+1,OFFSET(B59,-1,0))) -> 2 | C59: =IF(H59="CÉLULA CONSTRUTIVA",0,IF(H59="ETAPA",OFFSET(C59,-1,0)+1,OFFSET(C59,-1,0))) -> 1 | D59: =IF(H59="ETAPA",0,IF(H59="SUBETAPA",OFFSET(D59,-1,0)+1,OFFSET(D59,-1,0))) -> 1 | E59: =IF(H59="Subetapa",0,IF(H59="serviço",OFFSET(E59,-1,0)+1,OFFSET(E59,-1,0))) -> 7 | H59: SERVIÇO | I59: =IF(H59="Unidade Construtiva",TEXT(A59,"00"),IF(H59="Célula Construtiva",TEXT(B59,"00"),IF(H59="Etapa",CONCATENATE(TEXT(B59,"00"),".",TEXT(C59,"000")),IF(H59="Subetapa",CONCATENATE(TEXT(B59,"00"),".",TEXT(C59,"000"),".",TEXT(D59,"000")),IF(H59="Serviço",CONCATENATE(TEXT(B59,"00"),".",TEXT(C59,"000"),".",TEXT(D59,"000"),".",TEXT(E59,"000")),""))))) -> 02.001.001.007 | J59: Sinalização de obra | K59: vb | L59: 1 | M59: 5979.2733 | N59: =IF(H59="Serviço",M59*L59,IF(H59="CÉLULA CONSTRUTIVA",SUMIFS($N$8:$N$397,$B$8:$B$397,B59,$H$8:$H$397,"Serviço"),IF(H59="ETAPA",SUMIFS($N$8:$N$397,$B$8:$B$397,B59,$C$8:$C$397,C59,$H$8:$H$397,"Serviço"),IF(H59="SUBETAPA",SUMIFS($N$8:$N$397,$B$8:$B$397,B59,$C$8:$C$397,C59,$D$8:$D$397,D59,$H$8:$H$397,"Serviço"),0)))) -> 5979.2733 | O59: Previsto confomre NR18 | P59: Lançado ERP
A60: =IF($H60="UNIDADE CONSTRUTIVA",OFFSET(A60,-1,0)+1,LARGE(A$3:A59,1)) -> 0 | B60: =IF(H60="UNIDADE CONSTRUTIVA",0,IF(H60="CÉLULA CONSTRUTIVA",OFFSET(B60,-1,0)+1,OFFSET(B60,-1,0))) -> 2 | C60: =IF(H60="CÉLULA CONSTRUTIVA",0,IF(H60="ETAPA",OFFSET(C60,-1,0)+1,OFFSET(C60,-1,0))) -> 1 | D60: =IF(H60="ETAPA",0,IF(H60="SUBETAPA",OFFSET(D60,-1,0)+1,OFFSET(D60,-1,0))) -> 1 | E60: =IF(H60="Subetapa",0,IF(H60="serviço",OFFSET(E60,-1,0)+1,OFFSET(E60,-1,0))) -> 8 | H60: SERVIÇO | I60: =IF(H60="Unidade Construtiva",TEXT(A60,"00"),IF(H60="Célula Construtiva",TEXT(B60,"00"),IF(H60="Etapa",CONCATENATE(TEXT(B60,"00"),".",TEXT(C60,"000")),IF(H60="Subetapa",CONCATENATE(TEXT(B60,"00"),".",TEXT(C60,"000"),".",TEXT(D60,"000")),IF(H60="Serviço",CONCATENATE(TEXT(B60,"00"),".",TEXT(C60,"000"),".",TEXT(D60,"000"),".",TEXT(E60,"000")),""))))) -> 02.001.001.008 | J60: Linha de vida | K60: m | L60: 474.38 | M60: 87.21 | N60: =IF(H60="Serviço",M60*L60,IF(H60="CÉLULA CONSTRUTIVA",SUMIFS($N$8:$N$397,$B$8:$B$397,B60,$H$8:$H$397,"Serviço"),IF(H60="ETAPA",SUMIFS($N$8:$N$397,$B$8:$B$397,B60,$C$8:$C$397,C60,$H$8:$H$397,"Serviço"),IF(H60="SUBETAPA",SUMIFS($N$8:$N$397,$B$8:$B$397,B60,$C$8:$C$397,C60,$D$8:$D$397,D60,$H$8:$H$397,"Serviço"),0)))) -> 41370.68 | O60: Previsto confomre NR18 | P60: Lançado ERP
A61: =IF($H61="UNIDADE CONSTRUTIVA",OFFSET(A61,-1,0)+1,LARGE(A$3:A60,1)) -> 0 | B61: =IF(H61="UNIDADE CONSTRUTIVA",0,IF(H61="CÉLULA CONSTRUTIVA",OFFSET(B61,-1,0)+1,OFFSET(B61,-1,0))) -> 2 | C61: =IF(H61="CÉLULA CONSTRUTIVA",0,IF(H61="ETAPA",OFFSET(C61,-1,0)+1,OFFSET(C61,-1,0))) -> 1 | D61: =IF(H61="ETAPA",0,IF(H61="SUBETAPA",OFFSET(D61,-1,0)+1,OFFSET(D61,-1,0))) -> 2 | E61: =IF(H61="Subetapa",0,IF(H61="serviço",OFFSET(E61,-1,0)+1,OFFSET(E61,-1,0))) -> 0 | H61: SUBETAPA | I61: =IF(H61="Unidade Construtiva",TEXT(A61,"00"),IF(H61="Célula Construtiva",TEXT(B61,"00"),IF(H61="Etapa",CONCATENATE(TEXT(B61,"00"),".",TEXT(C61,"000")),IF(H61="Subetapa",CONCATENATE(TEXT(B61,"00"),".",TEXT(C61,"000"),".",TEXT(D61,"000")),IF(H61="Serviço",CONCATENATE(TEXT(B61,"00"),".",TEXT(C61,"000"),".",TEXT(D61,"000"),".",TEXT(E61,"000")),""))))) -> 02.001.002 | J61: Meio Ambiente | N61: =IF(H61="Serviço",M61*L61,IF(H61="CÉLULA CONSTRUTIVA",SUMIFS($N$8:$N$397,$B$8:$B$397,B61,$H$8:$H$397,"Serviço"),IF(H61="ETAPA",SUMIFS($N$8:$N$397,$B$8:$B$397,B61,$C$8:$C$397,C61,$H$8:$H$397,"Serviço"),IF(H61="SUBETAPA",SUMIFS($N$8:$N$397,$B$8:$B$397,B61,$C$8:$C$397,C61,$D$8:$D$397,D61,$H$8:$H$397,"Serviço"),0)))) -> 82873.775
A62: =IF($H62="UNIDADE CONSTRUTIVA",OFFSET(A62,-1,0)+1,LARGE(A$3:A61,1)) -> 0 | B62: =IF(H62="UNIDADE CONSTRUTIVA",0,IF(H62="CÉLULA CONSTRUTIVA",OFFSET(B62,-1,0)+1,OFFSET(B62,-1,0))) -> 2 | C62: =IF(H62="CÉLULA CONSTRUTIVA",0,IF(H62="ETAPA",OFFSET(C62,-1,0)+1,OFFSET(C62,-1,0))) -> 1 | D62: =IF(H62="ETAPA",0,IF(H62="SUBETAPA",OFFSET(D62,-1,0)+1,OFFSET(D62,-1,0))) -> 2 | E62: =IF(H62="Subetapa",0,IF(H62="serviço",OFFSET(E62,-1,0)+1,OFFSET(E62,-1,0))) -> 1 | H62: SERVIÇO | I62: =IF(H62="Unidade Construtiva",TEXT(A62,"00"),IF(H62="Célula Construtiva",TEXT(B62,"00"),IF(H62="Etapa",CONCATENATE(TEXT(B62,"00"),".",TEXT(C62,"000")),IF(H62="Subetapa",CONCATENATE(TEXT(B62,"00"),".",TEXT(C62,"000"),".",TEXT(D62,"000")),IF(H62="Serviço",CONCATENATE(TEXT(B62,"00"),".",TEXT(C62,"000"),".",TEXT(D62,"000"),".",TEXT(E62,"000")),""))))) -> 02.001.002.001 | J62: Elaboração do Plano de Gerenciamento de Riscos (PGR) | K62: vb | L62: 1 | M62: 7085.0604 | N62: =IF(H62="Serviço",M62*L62,IF(H62="CÉLULA CONSTRUTIVA",SUMIFS($N$8:$N$397,$B$8:$B$397,B62,$H$8:$H$397,"Serviço"),IF(H62="ETAPA",SUMIFS($N$8:$N$397,$B$8:$B$397,B62,$C$8:$C$397,C62,$H$8:$H$397,"Serviço"),IF(H62="SUBETAPA",SUMIFS($N$8:$N$397,$B$8:$B$397,B62,$C$8:$C$397,C62,$D$8:$D$397,D62,$H$8:$H$397,"Serviço"),0)))) -> 7085.0604 | P62: Lançado ERP
A63: =IF($H63="UNIDADE CONSTRUTIVA",OFFSET(A63,-1,0)+1,LARGE(A$3:A62,1)) -> 0 | B63: =IF(H63="UNIDADE CONSTRUTIVA",0,IF(H63="CÉLULA CONSTRUTIVA",OFFSET(B63,-1,0)+1,OFFSET(B63,-1,0))) -> 2 | C63: =IF(H63="CÉLULA CONSTRUTIVA",0,IF(H63="ETAPA",OFFSET(C63,-1,0)+1,OFFSET(C63,-1,0))) -> 1 | D63: =IF(H63="ETAPA",0,IF(H63="SUBETAPA",OFFSET(D63,-1,0)+1,OFFSET(D63,-1,0))) -> 2 | E63: =IF(H63="Subetapa",0,IF(H63="serviço",OFFSET(E63,-1,0)+1,OFFSET(E63,-1,0))) -> 2 | H63: SERVIÇO | I63: =IF(H63="Unidade Construtiva",TEXT(A63,"00"),IF(H63="Célula Construtiva",TEXT(B63,"00"),IF(H63="Etapa",CONCATENATE(TEXT(B63,"00"),".",TEXT(C63,"000")),IF(H63="Subetapa",CONCATENATE(TEXT(B63,"00"),".",TEXT(C63,"000"),".",TEXT(D63,"000")),IF(H63="Serviço",CONCATENATE(TEXT(B63,"00"),".",TEXT(C63,"000"),".",TEXT(D63,"000"),".",TEXT(E63,"000")),""))))) -> 02.001.002.002 | J63: Remoção de entulhos e resíduos | K63: mes | L63: 40 | M63: 1894.7179 | N63: =IF(H63="Serviço",M63*L63,IF(H63="CÉLULA CONSTRUTIVA",SUMIFS($N$8:$N$397,$B$8:$B$397,B63,$H$8:$H$397,"Serviço"),IF(H63="ETAPA",SUMIFS($N$8:$N$397,$B$8:$B$397,B63,$C$8:$C$397,C63,$H$8:$H$397,"Serviço"),IF(H63="SUBETAPA",SUMIFS($N$8:$N$397,$B$8:$B$397,B63,$C$8:$C$397,C63,$D$8:$D$397,D63,$H$8:$H$397,"Serviço"),0)))) -> 75788.715 | P63: Lançado ERP
A64: =IF($H64="UNIDADE CONSTRUTIVA",OFFSET(A64,-1,0)+1,LARGE(A$3:A63,1)) -> 0 | B64: =IF(H64="UNIDADE CONSTRUTIVA",0,IF(H64="CÉLULA CONSTRUTIVA",OFFSET(B64,-1,0)+1,OFFSET(B64,-1,0))) -> 2 | C64: =IF(H64="CÉLULA CONSTRUTIVA",0,IF(H64="ETAPA",OFFSET(C64,-1,0)+1,OFFSET(C64,-1,0))) -> 2 | D64: =IF(H64="ETAPA",0,IF(H64="SUBETAPA",OFFSET(D64,-1,0)+1,OFFSET(D64,-1,0))) -> 0 | E64: =IF(H64="Subetapa",0,IF(H64="serviço",OFFSET(E64,-1,0)+1,OFFSET(E64,-1,0))) -> 2 | H64: ETAPA | I64: =IF(H64="Unidade Construtiva",TEXT(A64,"00"),IF(H64="Célula Construtiva",TEXT(B64,"00"),IF(H64="Etapa",CONCATENATE(TEXT(B64,"00"),".",TEXT(C64,"000")),IF(H64="Subetapa",CONCATENATE(TEXT(B64,"00"),".",TEXT(C64,"000"),".",TEXT(D64,"000")),IF(H64="Serviço",CONCATENATE(TEXT(B64,"00"),".",TEXT(C64,"000"),".",TEXT(D64,"000"),".",TEXT(E64,"000")),""))))) -> 02.002 | J64: ADMINISTRAÇÃO E CANTEIRO DE OBRA | N64: =IF(H64="Serviço",M64*L64,IF(H64="CÉLULA CONSTRUTIVA",SUMIFS($N$8:$N$397,$B$8:$B$397,B64,$H$8:$H$397,"Serviço"),IF(H64="ETAPA",SUMIFS($N$8:$N$397,$B$8:$B$397,B64,$C$8:$C$397,C64,$H$8:$H$397,"Serviço"),IF(H64="SUBETAPA",SUMIFS($N$8:$N$397,$B$8:$B$397,B64,$C$8:$C$397,C64,$D$8:$D$397,D64,$H$8:$H$397,"Serviço"),0)))) -> 1499680.4
A65: =IF($H65="UNIDADE CONSTRUTIVA",OFFSET(A65,-1,0)+1,LARGE(A$3:A64,1)) -> 0 | B65: =IF(H65="UNIDADE CONSTRUTIVA",0,IF(H65="CÉLULA CONSTRUTIVA",OFFSET(B65,-1,0)+1,OFFSET(B65,-1,0))) -> 2 | C65: =IF(H65="CÉLULA CONSTRUTIVA",0,IF(H65="ETAPA",OFFSET(C65,-1,0)+1,OFFSET(C65,-1,0))) -> 2 | D65: =IF(H65="ETAPA",0,IF(H65="SUBETAPA",OFFSET(D65,-1,0)+1,OFFSET(D65,-1,0))) -> 1 | E65: =IF(H65="Subetapa",0,IF(H65="serviço",OFFSET(E65,-1,0)+1,OFFSET(E65,-1,0))) -> 0 | H65: SUBETAPA | I65: =IF(H65="Unidade Construtiva",TEXT(A65,"00"),IF(H65="Célula Construtiva",TEXT(B65,"00"),IF(H65="Etapa",CONCATENATE(TEXT(B65,"00"),".",TEXT(C65,"000")),IF(H65="Subetapa",CONCATENATE(TEXT(B65,"00"),".",TEXT(C65,"000"),".",TEXT(D65,"000")),IF(H65="Serviço",CONCATENATE(TEXT(B65,"00"),".",TEXT(C65,"000"),".",TEXT(D65,"000"),".",TEXT(E65,"000")),""))))) -> 02.002.001 | J65: Equipe de Gestão e Apoio | N65: =IF(H65="Serviço",M65*L65,IF(H65="CÉLULA CONSTRUTIVA",SUMIFS($N$8:$N$397,$B$8:$B$397,B65,$H$8:$H$397,"Serviço"),IF(H65="ETAPA",SUMIFS($N$8:$N$397,$B$8:$B$397,B65,$C$8:$C$397,C65,$H$8:$H$397,"Serviço"),IF(H65="SUBETAPA",SUMIFS($N$8:$N$397,$B$8:$B$397,B65,$C$8:$C$397,C65,$D$8:$D$397,D65,$H$8:$H$397,"Serviço"),0)))) -> 838792.57
A66: =IF($H66="UNIDADE CONSTRUTIVA",OFFSET(A66,-1,0)+1,LARGE(A$3:A65,1)) -> 0 | B66: =IF(H66="UNIDADE CONSTRUTIVA",0,IF(H66="CÉLULA CONSTRUTIVA",OFFSET(B66,-1,0)+1,OFFSET(B66,-1,0))) -> 2 | C66: =IF(H66="CÉLULA CONSTRUTIVA",0,IF(H66="ETAPA",OFFSET(C66,-1,0)+1,OFFSET(C66,-1,0))) -> 2 | D66: =IF(H66="ETAPA",0,IF(H66="SUBETAPA",OFFSET(D66,-1,0)+1,OFFSET(D66,-1,0))) -> 1 | E66: =IF(H66="Subetapa",0,IF(H66="serviço",OFFSET(E66,-1,0)+1,OFFSET(E66,-1,0))) -> 1 | H66: SERVIÇO | I66: =IF(H66="Unidade Construtiva",TEXT(A66,"00"),IF(H66="Célula Construtiva",TEXT(B66,"00"),IF(H66="Etapa",CONCATENATE(TEXT(B66,"00"),".",TEXT(C66,"000")),IF(H66="Subetapa",CONCATENATE(TEXT(B66,"00"),".",TEXT(C66,"000"),".",TEXT(D66,"000")),IF(H66="Serviço",CONCATENATE(TEXT(B66,"00"),".",TEXT(C66,"000"),".",TEXT(D66,"000"),".",TEXT(E66,"000")),""))))) -> 02.002.001.001 | J66: Engenheiro Civil | K66: mes | L66: ='Obra '!$E$7 -> 43 | M66: 11609.074 | N66: =IF(H66="Serviço",M66*L66,IF(H66="CÉLULA CONSTRUTIVA",SUMIFS($N$8:$N$397,$B$8:$B$397,B66,$H$8:$H$397,"Serviço"),IF(H66="ETAPA",SUMIFS($N$8:$N$397,$B$8:$B$397,B66,$C$8:$C$397,C66,$H$8:$H$397,"Serviço"),IF(H66="SUBETAPA",SUMIFS($N$8:$N$397,$B$8:$B$397,B66,$C$8:$C$397,C66,$D$8:$D$397,D66,$H$8:$H$397,"Serviço"),0)))) -> 499190.19 | P66: Lançado ERP
A67: =IF($H67="UNIDADE CONSTRUTIVA",OFFSET(A67,-1,0)+1,LARGE(A$3:A66,1)) -> 0 | B67: =IF(H67="UNIDADE CONSTRUTIVA",0,IF(H67="CÉLULA CONSTRUTIVA",OFFSET(B67,-1,0)+1,OFFSET(B67,-1,0))) -> 2 | C67: =IF(H67="CÉLULA CONSTRUTIVA",0,IF(H67="ETAPA",OFFSET(C67,-1,0)+1,OFFSET(C67,-1,0))) -> 2 | D67: =IF(H67="ETAPA",0,IF(H67="SUBETAPA",OFFSET(D67,-1,0)+1,OFFSET(D67,-1,0))) -> 1 | E67: =IF(H67="Subetapa",0,IF(H67="serviço",OFFSET(E67,-1,0)+1,OFFSET(E67,-1,0))) -> 2 | H67: SERVIÇO | I67: =IF(H67="Unidade Construtiva",TEXT(A67,"00"),IF(H67="Célula Construtiva",TEXT(B67,"00"),IF(H67="Etapa",CONCATENATE(TEXT(B67,"00"),".",TEXT(C67,"000")),IF(H67="Subetapa",CONCATENATE(TEXT(B67,"00"),".",TEXT(C67,"000"),".",TEXT(D67,"000")),IF(H67="Serviço",CONCATENATE(TEXT(B67,"00"),".",TEXT(C67,"000"),".",TEXT(D67,"000"),".",TEXT(E67,"000")),""))))) -> 02.002.001.002 | J67: Arquiteto | K67: mes | L67: 10 | M67: 3926.6748 | N67: =IF(H67="Serviço",M67*L67,IF(H67="CÉLULA CONSTRUTIVA",SUMIFS($N$8:$N$397,$B$8:$B$397,B67,$H$8:$H$397,"Serviço"),IF(H67="ETAPA",SUMIFS($N$8:$N$397,$B$8:$B$397,B67,$C$8:$C$397,C67,$H$8:$H$397,"Serviço"),IF(H67="SUBETAPA",SUMIFS($N$8:$N$397,$B$8:$B$397,B67,$C$8:$C$397,C67,$D$8:$D$397,D67,$H$8:$H$397,"Serviço"),0)))) -> 39266.748 | P67: Lançado ERP
A68: =IF($H68="UNIDADE CONSTRUTIVA",OFFSET(A68,-1,0)+1,LARGE(A$3:A67,1)) -> 0 | B68: =IF(H68="UNIDADE CONSTRUTIVA",0,IF(H68="CÉLULA CONSTRUTIVA",OFFSET(B68,-1,0)+1,OFFSET(B68,-1,0))) -> 2 | C68: =IF(H68="CÉLULA CONSTRUTIVA",0,IF(H68="ETAPA",OFFSET(C68,-1,0)+1,OFFSET(C68,-1,0))) -> 2 | D68: =IF(H68="ETAPA",0,IF(H68="SUBETAPA",OFFSET(D68,-1,0)+1,OFFSET(D68,-1,0))) -> 1 | E68: =IF(H68="Subetapa",0,IF(H68="serviço",OFFSET(E68,-1,0)+1,OFFSET(E68,-1,0))) -> 3 | H68: SERVIÇO | I68: =IF(H68="Unidade Construtiva",TEXT(A68,"00"),IF(H68="Célula Construtiva",TEXT(B68,"00"),IF(H68="Etapa",CONCATENATE(TEXT(B68,"00"),".",TEXT(C68,"000")),IF(H68="Subetapa",CONCATENATE(TEXT(B68,"00"),".",TEXT(C68,"000"),".",TEXT(D68,"000")),IF(H68="Serviço",CONCATENATE(TEXT(B68,"00"),".",TEXT(C68,"000"),".",TEXT(D68,"000"),".",TEXT(E68,"000")),""))))) -> 02.002.001.003 | J68: Tecnico em edificações | K68: mes | L68: ='Obra '!$E$7 -> 43 | M68: 1280.6397 | N68: =IF(H68="Serviço",M68*L68,IF(H68="CÉLULA CONSTRUTIVA",SUMIFS($N$8:$N$397,$B$8:$B$397,B68,$H$8:$H$397,"Serviço"),IF(H68="ETAPA",SUMIFS($N$8:$N$397,$B$8:$B$397,B68,$C$8:$C$397,C68,$H$8:$H$397,"Serviço"),IF(H68="SUBETAPA",SUMIFS($N$8:$N$397,$B$8:$B$397,B68,$C$8:$C$397,C68,$D$8:$D$397,D68,$H$8:$H$397,"Serviço"),0)))) -> 55067.506 | P68: Lançado ERP
A69: =IF($H69="UNIDADE CONSTRUTIVA",OFFSET(A69,-1,0)+1,LARGE(A$3:A68,1)) -> 0 | B69: =IF(H69="UNIDADE CONSTRUTIVA",0,IF(H69="CÉLULA CONSTRUTIVA",OFFSET(B69,-1,0)+1,OFFSET(B69,-1,0))) -> 2 | C69: =IF(H69="CÉLULA CONSTRUTIVA",0,IF(H69="ETAPA",OFFSET(C69,-1,0)+1,OFFSET(C69,-1,0))) -> 2 | D69: =IF(H69="ETAPA",0,IF(H69="SUBETAPA",OFFSET(D69,-1,0)+1,OFFSET(D69,-1,0))) -> 1 | E69: =IF(H69="Subetapa",0,IF(H69="serviço",OFFSET(E69,-1,0)+1,OFFSET(E69,-1,0))) -> 4 | H69: SERVIÇO | I69: =IF(H69="Unidade Construtiva",TEXT(A69,"00"),IF(H69="Célula Construtiva",TEXT(B69,"00"),IF(H69="Etapa",CONCATENATE(TEXT(B69,"00"),".",TEXT(C69,"000")),IF(H69="Subetapa",CONCATENATE(TEXT(B69,"00"),".",TEXT(C69,"000"),".",TEXT(D69,"000")),IF(H69="Serviço",CONCATENATE(TEXT(B69,"00"),".",TEXT(C69,"000"),".",TEXT(D69,"000"),".",TEXT(E69,"000")),""))))) -> 02.002.001.004 | J69: Almoxarife | K69: mes | L69: ='Obra '!$E$7 -> 43 | M69: 2134.3995 | N69: =IF(H69="Serviço",M69*L69,IF(H69="CÉLULA CONSTRUTIVA",SUMIFS($N$8:$N$397,$B$8:$B$397,B69,$H$8:$H$397,"Serviço"),IF(H69="ETAPA",SUMIFS($N$8:$N$397,$B$8:$B$397,B69,$C$8:$C$397,C69,$H$8:$H$397,"Serviço"),IF(H69="SUBETAPA",SUMIFS($N$8:$N$397,$B$8:$B$397,B69,$C$8:$C$397,C69,$D$8:$D$397,D69,$H$8:$H$397,"Serviço"),0)))) -> 91779.177 | P69: Lançado ERP
A70: =IF($H70="UNIDADE CONSTRUTIVA",OFFSET(A70,-1,0)+1,LARGE(A$3:A69,1)) -> 0 | B70: =IF(H70="UNIDADE CONSTRUTIVA",0,IF(H70="CÉLULA CONSTRUTIVA",OFFSET(B70,-1,0)+1,OFFSET(B70,-1,0))) -> 2 | C70: =IF(H70="CÉLULA CONSTRUTIVA",0,IF(H70="ETAPA",OFFSET(C70,-1,0)+1,OFFSET(C70,-1,0))) -> 2 | D70: =IF(H70="ETAPA",0,IF(H70="SUBETAPA",OFFSET(D70,-1,0)+1,OFFSET(D70,-1,0))) -> 1 | E70: =IF(H70="Subetapa",0,IF(H70="serviço",OFFSET(E70,-1,0)+1,OFFSET(E70,-1,0))) -> 5 | H70: SERVIÇO | I70: =IF(H70="Unidade Construtiva",TEXT(A70,"00"),IF(H70="Célula Construtiva",TEXT(B70,"00"),IF(H70="Etapa",CONCATENATE(TEXT(B70,"00"),".",TEXT(C70,"000")),IF(H70="Subetapa",CONCATENATE(TEXT(B70,"00"),".",TEXT(C70,"000"),".",TEXT(D70,"000")),IF(H70="Serviço",CONCATENATE(TEXT(B70,"00"),".",TEXT(C70,"000"),".",TEXT(D70,"000"),".",TEXT(E70,"000")),""))))) -> 02.002.001.005 | J70: Vigilância / portaria | K70: mes | L70: ='Obra '!$E$7 -> 43 | M70: 3569.5104 | N70: =IF(H70="Serviço",M70*L70,IF(H70="CÉLULA CONSTRUTIVA",SUMIFS($N$8:$N$397,$B$8:$B$397,B70,$H$8:$H$397,"Serviço"),IF(H70="ETAPA",SUMIFS($N$8:$N$397,$B$8:$B$397,B70,$C$8:$C$397,C70,$H$8:$H$397,"Serviço"),IF(H70="SUBETAPA",SUMIFS($N$8:$N$397,$B$8:$B$397,B70,$C$8:$C$397,C70,$D$8:$D$397,D70,$H$8:$H$397,"Serviço"),0)))) -> 153488.95 | P70: Lançado ERP
A71: =IF($H71="UNIDADE CONSTRUTIVA",OFFSET(A71,-1,0)+1,LARGE(A$3:A70,1)) -> 0 | B71: =IF(H71="UNIDADE CONSTRUTIVA",0,IF(H71="CÉLULA CONSTRUTIVA",OFFSET(B71,-1,0)+1,OFFSET(B71,-1,0))) -> 2 | C71: =IF(H71="CÉLULA CONSTRUTIVA",0,IF(H71="ETAPA",OFFSET(C71,-1,0)+1,OFFSET(C71,-1,0))) -> 2 | D71: =IF(H71="ETAPA",0,IF(H71="SUBETAPA",OFFSET(D71,-1,0)+1,OFFSET(D71,-1,0))) -> 2 | E71: =IF(H71="Subetapa",0,IF(H71="serviço",OFFSET(E71,-1,0)+1,OFFSET(E71,-1,0))) -> 0 | H71: SUBETAPA | I71: =IF(H71="Unidade Construtiva",TEXT(A71,"00"),IF(H71="Célula Construtiva",TEXT(B71,"00"),IF(H71="Etapa",CONCATENATE(TEXT(B71,"00"),".",TEXT(C71,"000")),IF(H71="Subetapa",CONCATENATE(TEXT(B71,"00"),".",TEXT(C71,"000"),".",TEXT(D71,"000")),IF(H71="Serviço",CONCATENATE(TEXT(B71,"00"),".",TEXT(C71,"000"),".",TEXT(D71,"000"),".",TEXT(E71,"000")),""))))) -> 02.002.002 | J71: Serviços Iniciais | N71: =IF(H71="Serviço",M71*L71,IF(H71="CÉLULA CONSTRUTIVA",SUMIFS($N$8:$N$397,$B$8:$B$397,B71,$H$8:$H$397,"Serviço"),IF(H71="ETAPA",SUMIFS($N$8:$N$397,$B$8:$B$397,B71,$C$8:$C$397,C71,$H$8:$H$397,"Serviço"),IF(H71="SUBETAPA",SUMIFS($N$8:$N$397,$B$8:$B$397,B71,$C$8:$C$397,C71,$D$8:$D$397,D71,$H$8:$H$397,"Serviço"),0)))) -> 91752.54
A72: =IF($H72="UNIDADE CONSTRUTIVA",OFFSET(A72,-1,0)+1,LARGE(A$3:A71,1)) -> 0 | B72: =IF(H72="UNIDADE CONSTRUTIVA",0,IF(H72="CÉLULA CONSTRUTIVA",OFFSET(B72,-1,0)+1,OFFSET(B72,-1,0))) -> 2 | C72: =IF(H72="CÉLULA CONSTRUTIVA",0,IF(H72="ETAPA",OFFSET(C72,-1,0)+1,OFFSET(C72,-1,0))) -> 2 | D72: =IF(H72="ETAPA",0,IF(H72="SUBETAPA",OFFSET(D72,-1,0)+1,OFFSET(D72,-1,0))) -> 2 | E72: =IF(H72="Subetapa",0,IF(H72="serviço",OFFSET(E72,-1,0)+1,OFFSET(E72,-1,0))) -> 1 | H72: SERVIÇO | I72: =IF(H72="Unidade Construtiva",TEXT(A72,"00"),IF(H72="Célula Construtiva",TEXT(B72,"00"),IF(H72="Etapa",CONCATENATE(TEXT(B72,"00"),".",TEXT(C72,"000")),IF(H72="Subetapa",CONCATENATE(TEXT(B72,"00"),".",TEXT(C72,"000"),".",TEXT(D72,"000")),IF(H72="Serviço",CONCATENATE(TEXT(B72,"00"),".",TEXT(C72,"000"),".",TEXT(D72,"000"),".",TEXT(E72,"000")),""))))) -> 02.002.002.001 | J72: Limpeza mecanizada de camada vegetal | K72: m² | L72: ='Obra '!E8 -> 2133.78 | M72: 5.5 | N72: =IF(H72="Serviço",M72*L72,IF(H72="CÉLULA CONSTRUTIVA",SUMIFS($N$8:$N$397,$B$8:$B$397,B72,$H$8:$H$397,"Serviço"),IF(H72="ETAPA",SUMIFS($N$8:$N$397,$B$8:$B$397,B72,$C$8:$C$397,C72,$H$8:$H$397,"Serviço"),IF(H72="SUBETAPA",SUMIFS($N$8:$N$397,$B$8:$B$397,B72,$C$8:$C$397,C72,$D$8:$D$397,D72,$H$8:$H$397,"Serviço"),0)))) -> 11735.79 | O72: Estimado com base em índices históricos | P72: Lançado ERP
A73: =IF($H73="UNIDADE CONSTRUTIVA",OFFSET(A73,-1,0)+1,LARGE(A$3:A72,1)) -> 0 | B73: =IF(H73="UNIDADE CONSTRUTIVA",0,IF(H73="CÉLULA CONSTRUTIVA",OFFSET(B73,-1,0)+1,OFFSET(B73,-1,0))) -> 2 | C73: =IF(H73="CÉLULA CONSTRUTIVA",0,IF(H73="ETAPA",OFFSET(C73,-1,0)+1,OFFSET(C73,-1,0))) -> 2 | D73: =IF(H73="ETAPA",0,IF(H73="SUBETAPA",OFFSET(D73,-1,0)+1,OFFSET(D73,-1,0))) -> 2 | E73: =IF(H73="Subetapa",0,IF(H73="serviço",OFFSET(E73,-1,0)+1,OFFSET(E73,-1,0))) -> 2 | H73: SERVIÇO | I73: =IF(H73="Unidade Construtiva",TEXT(A73,"00"),IF(H73="Célula Construtiva",TEXT(B73,"00"),IF(H73="Etapa",CONCATENATE(TEXT(B73,"00"),".",TEXT(C73,"000")),IF(H73="Subetapa",CONCATENATE(TEXT(B73,"00"),".",TEXT(C73,"000"),".",TEXT(D73,"000")),IF(H73="Serviço",CONCATENATE(TEXT(B73,"00"),".",TEXT(C73,"000"),".",TEXT(D73,"000"),".",TEXT(E73,"000")),""))))) -> 02.002.002.002 | J73: Demolições | K73: m² | L73: ='Obra '!E8/4 -> 533.445 | M73: 150 | N73: =IF(H73="Serviço",M73*L73,IF(H73="CÉLULA CONSTRUTIVA",SUMIFS($N$8:$N$397,$B$8:$B$397,B73,$H$8:$H$397,"Serviço"),IF(H73="ETAPA",SUMIFS($N$8:$N$397,$B$8:$B$397,B73,$C$8:$C$397,C73,$H$8:$H$397,"Serviço"),IF(H73="SUBETAPA",SUMIFS($N$8:$N$397,$B$8:$B$397,B73,$C$8:$C$397,C73,$D$8:$D$397,D73,$H$8:$H$397,"Serviço"),0)))) -> 80016.75 | O73: Estimado com base em índices históricos | P73: Lançado ERP
A74: =IF($H74="UNIDADE CONSTRUTIVA",OFFSET(A74,-1,0)+1,LARGE(A$3:A69,1)) -> 0 | B74: =IF(H74="UNIDADE CONSTRUTIVA",0,IF(H74="CÉLULA CONSTRUTIVA",OFFSET(B74,-1,0)+1,OFFSET(B74,-1,0))) -> 2 | C74: =IF(H74="CÉLULA CONSTRUTIVA",0,IF(H74="ETAPA",OFFSET(C74,-1,0)+1,OFFSET(C74,-1,0))) -> 2 | D74: =IF(H74="ETAPA",0,IF(H74="SUBETAPA",OFFSET(D74,-1,0)+1,OFFSET(D74,-1,0))) -> 3 | E74: =IF(H74="Subetapa",0,IF(H74="serviço",OFFSET(E74,-1,0)+1,OFFSET(E74,-1,0))) -> 0 | H74: SUBETAPA | I74: =IF(H74="Unidade Construtiva",TEXT(A74,"00"),IF(H74="Célula Construtiva",TEXT(B74,"00"),IF(H74="Etapa",CONCATENATE(TEXT(B74,"00"),".",TEXT(C74,"000")),IF(H74="Subetapa",CONCATENATE(TEXT(B74,"00"),".",TEXT(C74,"000"),".",TEXT(D74,"000")),IF(H74="Serviço",CONCATENATE(TEXT(B74,"00"),".",TEXT(C74,"000"),".",TEXT(D74,"000"),".",TEXT(E74,"000")),""))))) -> 02.002.003 | J74: Despesas de consumo e manutenção | N74: =IF(H74="Serviço",M74*L74,IF(H74="CÉLULA CONSTRUTIVA",SUMIFS($N$8:$N$397,$B$8:$B$397,B74,$H$8:$H$397,"Serviço"),IF(H74="ETAPA",SUMIFS($N$8:$N$397,$B$8:$B$397,B74,$C$8:$C$397,C74,$H$8:$H$397,"Serviço"),IF(H74="SUBETAPA",SUMIFS($N$8:$N$397,$B$8:$B$397,B74,$C$8:$C$397,C74,$D$8:$D$397,D74,$H$8:$H$397,"Serviço"),0)))) -> 409785.33
A75: =IF($H75="UNIDADE CONSTRUTIVA",OFFSET(A75,-1,0)+1,LARGE(A$3:A74,1)) -> 0 | B75: =IF(H75="UNIDADE CONSTRUTIVA",0,IF(H75="CÉLULA CONSTRUTIVA",OFFSET(B75,-1,0)+1,OFFSET(B75,-1,0))) -> 2 | C75: =IF(H75="CÉLULA CONSTRUTIVA",0,IF(H75="ETAPA",OFFSET(C75,-1,0)+1,OFFSET(C75,-1,0))) -> 2 | D75: =IF(H75="ETAPA",0,IF(H75="SUBETAPA",OFFSET(D75,-1,0)+1,OFFSET(D75,-1,0))) -> 3 | E75: =IF(H75="Subetapa",0,IF(H75="serviço",OFFSET(E75,-1,0)+1,OFFSET(E75,-1,0))) -> 1 | H75: SERVIÇO | I75: =IF(H75="Unidade Construtiva",TEXT(A75,"00"),IF(H75="Célula Construtiva",TEXT(B75,"00"),IF(H75="Etapa",CONCATENATE(TEXT(B75,"00"),".",TEXT(C75,"000")),IF(H75="Subetapa",CONCATENATE(TEXT(B75,"00"),".",TEXT(C75,"000"),".",TEXT(D75,"000")),IF(H75="Serviço",CONCATENATE(TEXT(B75,"00"),".",TEXT(C75,"000"),".",TEXT(D75,"000"),".",TEXT(E75,"000")),""))))) -> 02.002.003.001 | J75: Consumo de água e esgoto | K75: mes | L75: ='Obra '!$E$7 -> 43 | M75: 1863.2543 | N75: =IF(H75="Serviço",M75*L75,IF(H75="CÉLULA CONSTRUTIVA",SUMIFS($N$8:$N$397,$B$8:$B$397,B75,$H$8:$H$397,"Serviço"),IF(H75="ETAPA",SUMIFS($N$8:$N$397,$B$8:$B$397,B75,$C$8:$C$397,C75,$H$8:$H$397,"Serviço"),IF(H75="SUBETAPA",SUMIFS($N$8:$N$397,$B$8:$B$397,B75,$C$8:$C$397,C75,$D$8:$D$397,D75,$H$8:$H$397,"Serviço"),0)))) -> 80119.934 | P75: Lançado ERP
A76: =IF($H76="UNIDADE CONSTRUTIVA",OFFSET(A76,-1,0)+1,LARGE(A$3:A75,1)) -> 0 | B76: =IF(H76="UNIDADE CONSTRUTIVA",0,IF(H76="CÉLULA CONSTRUTIVA",OFFSET(B76,-1,0)+1,OFFSET(B76,-1,0))) -> 2 | C76: =IF(H76="CÉLULA CONSTRUTIVA",0,IF(H76="ETAPA",OFFSET(C76,-1,0)+1,OFFSET(C76,-1,0))) -> 2 | D76: =IF(H76="ETAPA",0,IF(H76="SUBETAPA",OFFSET(D76,-1,0)+1,OFFSET(D76,-1,0))) -> 3 | E76: =IF(H76="Subetapa",0,IF(H76="serviço",OFFSET(E76,-1,0)+1,OFFSET(E76,-1,0))) -> 2 | H76: SERVIÇO | I76: =IF(H76="Unidade Construtiva",TEXT(A76,"00"),IF(H76="Célula Construtiva",TEXT(B76,"00"),IF(H76="Etapa",CONCATENATE(TEXT(B76,"00"),".",TEXT(C76,"000")),IF(H76="Subetapa",CONCATENATE(TEXT(B76,"00"),".",TEXT(C76,"000"),".",TEXT(D76,"000")),IF(H76="Serviço",CONCATENATE(TEXT(B76,"00"),".",TEXT(C76,"000"),".",TEXT(D76,"000"),".",TEXT(E76,"000")),""))))) -> 02.002.003.002 | J76: Consumo de luz/energia | K76: mes | L76: ='Obra '!$E$7 -> 43 | M76: 3340.5382 | N76: =IF(H76="Serviço",M76*L76,IF(H76="CÉLULA CONSTRUTIVA",SUMIFS($N$8:$N$397,$B$8:$B$397,B76,$H$8:$H$397,"Serviço"),IF(H76="ETAPA",SUMIFS($N$8:$N$397,$B$8:$B$397,B76,$C$8:$C$397,C76,$H$8:$H$397,"Serviço"),IF(H76="SUBETAPA",SUMIFS($N$8:$N$397,$B$8:$B$397,B76,$C$8:$C$397,C76,$D$8:$D$397,D76,$H$8:$H$397,"Serviço"),0)))) -> 143643.14 | P76: Lançado ERP
A77: =IF($H77="UNIDADE CONSTRUTIVA",OFFSET(A77,-1,0)+1,LARGE(A$3:A76,1)) -> 0 | B77: =IF(H77="UNIDADE CONSTRUTIVA",0,IF(H77="CÉLULA CONSTRUTIVA",OFFSET(B77,-1,0)+1,OFFSET(B77,-1,0))) -> 2 | C77: =IF(H77="CÉLULA CONSTRUTIVA",0,IF(H77="ETAPA",OFFSET(C77,-1,0)+1,OFFSET(C77,-1,0))) -> 2 | D77: =IF(H77="ETAPA",0,IF(H77="SUBETAPA",OFFSET(D77,-1,0)+1,OFFSET(D77,-1,0))) -> 3 | E77: =IF(H77="Subetapa",0,IF(H77="serviço",OFFSET(E77,-1,0)+1,OFFSET(E77,-1,0))) -> 3 | H77: SERVIÇO | I77: =IF(H77="Unidade Construtiva",TEXT(A77,"00"),IF(H77="Célula Construtiva",TEXT(B77,"00"),IF(H77="Etapa",CONCATENATE(TEXT(B77,"00"),".",TEXT(C77,"000")),IF(H77="Subetapa",CONCATENATE(TEXT(B77,"00"),".",TEXT(C77,"000"),".",TEXT(D77,"000")),IF(H77="Serviço",CONCATENATE(TEXT(B77,"00"),".",TEXT(C77,"000"),".",TEXT(D77,"000"),".",TEXT(E77,"000")),""))))) -> 02.002.003.003 | J77: Consumo internet | K77: mes | L77: ='Obra '!$E$7 -> 43 | M77: 572.34855 | N77: =IF(H77="Serviço",M77*L77,IF(H77="CÉLULA CONSTRUTIVA",SUMIFS($N$8:$N$397,$B$8:$B$397,B77,$H$8:$H$397,"Serviço"),IF(H77="ETAPA",SUMIFS($N$8:$N$397,$B$8:$B$397,B77,$C$8:$C$397,C77,$H$8:$H$397,"Serviço"),IF(H77="SUBETAPA",SUMIFS($N$8:$N$397,$B$8:$B$397,B77,$C$8:$C$397,C77,$D$8:$D$397,D77,$H$8:$H$397,"Serviço"),0)))) -> 24610.988 | P77: Lançado ERP
A78: =IF($H78="UNIDADE CONSTRUTIVA",OFFSET(A78,-1,0)+1,LARGE(A$3:A77,1)) -> 0 | B78: =IF(H78="UNIDADE CONSTRUTIVA",0,IF(H78="CÉLULA CONSTRUTIVA",OFFSET(B78,-1,0)+1,OFFSET(B78,-1,0))) -> 2 | C78: =IF(H78="CÉLULA CONSTRUTIVA",0,IF(H78="ETAPA",OFFSET(C78,-1,0)+1,OFFSET(C78,-1,0))) -> 2 | D78: =IF(H78="ETAPA",0,IF(H78="SUBETAPA",OFFSET(D78,-1,0)+1,OFFSET(D78,-1,0))) -> 3 | E78: =IF(H78="Subetapa",0,IF(H78="serviço",OFFSET(E78,-1,0)+1,OFFSET(E78,-1,0))) -> 4 | H78: SERVIÇO | I78: =IF(H78="Unidade Construtiva",TEXT(A78,"00"),IF(H78="Célula Construtiva",TEXT(B78,"00"),IF(H78="Etapa",CONCATENATE(TEXT(B78,"00"),".",TEXT(C78,"000")),IF(H78="Subetapa",CONCATENATE(TEXT(B78,"00"),".",TEXT(C78,"000"),".",TEXT(D78,"000")),IF(H78="Serviço",CONCATENATE(TEXT(B78,"00"),".",TEXT(C78,"000"),".",TEXT(D78,"000"),".",TEXT(E78,"000")),""))))) -> 02.002.003.004 | J78: Consumo de telefone | K78: mes | L78: ='Obra '!$E$7 -> 43 | M78: 188.82474 | N78: =IF(H78="Serviço",M78*L78,IF(H78="CÉLULA CONSTRUTIVA",SUMIFS($N$8:$N$397,$B$8:$B$397,B78,$H$8:$H$397,"Serviço"),IF(H78="ETAPA",SUMIFS($N$8:$N$397,$B$8:$B$397,B78,$C$8:$C$397,C78,$H$8:$H$397,"Serviço"),IF(H78="SUBETAPA",SUMIFS($N$8:$N$397,$B$8:$B$397,B78,$C$8:$C$397,C78,$D$8:$D$397,D78,$H$8:$H$397,"Serviço"),0)))) -> 8119.4637 | P78: Lançado ERP
A79: =IF($H79="UNIDADE CONSTRUTIVA",OFFSET(A79,-1,0)+1,LARGE(A$3:A78,1)) -> 0 | B79: =IF(H79="UNIDADE CONSTRUTIVA",0,IF(H79="CÉLULA CONSTRUTIVA",OFFSET(B79,-1,0)+1,OFFSET(B79,-1,0))) -> 2 | C79: =IF(H79="CÉLULA CONSTRUTIVA",0,IF(H79="ETAPA",OFFSET(C79,-1,0)+1,OFFSET(C79,-1,0))) -> 2 | D79: =IF(H79="ETAPA",0,IF(H79="SUBETAPA",OFFSET(D79,-1,0)+1,OFFSET(D79,-1,0))) -> 3 | E79: =IF(H79="Subetapa",0,IF(H79="serviço",OFFSET(E79,-1,0)+1,OFFSET(E79,-1,0))) -> 5 | H79: SERVIÇO | I79: =IF(H79="Unidade Construtiva",TEXT(A79,"00"),IF(H79="Célula Construtiva",TEXT(B79,"00"),IF(H79="Etapa",CONCATENATE(TEXT(B79,"00"),".",TEXT(C79,"000")),IF(H79="Subetapa",CONCATENATE(TEXT(B79,"00"),".",TEXT(C79,"000"),".",TEXT(D79,"000")),IF(H79="Serviço",CONCATENATE(TEXT(B79,"00"),".",TEXT(C79,"000"),".",TEXT(D79,"000"),".",TEXT(E79,"000")),""))))) -> 02.002.003.005 | J79: Coleta de lixo | K79: mes | L79: ='Obra '!$E$7 -> 43 | M79: 133.76756 | N79: =IF(H79="Serviço",M79*L79,IF(H79="CÉLULA CONSTRUTIVA",SUMIFS($N$8:$N$397,$B$8:$B$397,B79,$H$8:$H$397,"Serviço"),IF(H79="ETAPA",SUMIFS($N$8:$N$397,$B$8:$B$397,B79,$C$8:$C$397,C79,$H$8:$H$397,"Serviço"),IF(H79="SUBETAPA",SUMIFS($N$8:$N$397,$B$8:$B$397,B79,$C$8:$C$397,C79,$D$8:$D$397,D79,$H$8:$H$397,"Serviço"),0)))) -> 5752.0052 | P79: Lançado ERP
A80: =IF($H80="UNIDADE CONSTRUTIVA",OFFSET(A80,-1,0)+1,LARGE(A$3:A79,1)) -> 0 | B80: =IF(H80="UNIDADE CONSTRUTIVA",0,IF(H80="CÉLULA CONSTRUTIVA",OFFSET(B80,-1,0)+1,OFFSET(B80,-1,0))) -> 2 | C80: =IF(H80="CÉLULA CONSTRUTIVA",0,IF(H80="ETAPA",OFFSET(C80,-1,0)+1,OFFSET(C80,-1,0))) -> 2 | D80: =IF(H80="ETAPA",0,IF(H80="SUBETAPA",OFFSET(D80,-1,0)+1,OFFSET(D80,-1,0))) -> 3 | E80: =IF(H80="Subetapa",0,IF(H80="serviço",OFFSET(E80,-1,0)+1,OFFSET(E80,-1,0))) -> 6 | H80: SERVIÇO | I80: =IF(H80="Unidade Construtiva",TEXT(A80,"00"),IF(H80="Célula Construtiva",TEXT(B80,"00"),IF(H80="Etapa",CONCATENATE(TEXT(B80,"00"),".",TEXT(C80,"000")),IF(H80="Subetapa",CONCATENATE(TEXT(B80,"00"),".",TEXT(C80,"000"),".",TEXT(D80,"000")),IF(H80="Serviço",CONCATENATE(TEXT(B80,"00"),".",TEXT(C80,"000"),".",TEXT(D80,"000"),".",TEXT(E80,"000")),""))))) -> 02.002.003.006 | J80: Consumo de material de expediente/escritório | K80: mes | L80: ='Obra '!$E$7 -> 43 | M80: 548.38097 | N80: =IF(H80="Serviço",M80*L80,IF(H80="CÉLULA CONSTRUTIVA",SUMIFS($N$8:$N$397,$B$8:$B$397,B80,$H$8:$H$397,"Serviço"),IF(H80="ETAPA",SUMIFS($N$8:$N$397,$B$8:$B$397,B80,$C$8:$C$397,C80,$H$8:$H$397,"Serviço"),IF(H80="SUBETAPA",SUMIFS($N$8:$N$397,$B$8:$B$397,B80,$C$8:$C$397,C80,$D$8:$D$397,D80,$H$8:$H$397,"Serviço"),0)))) -> 23580.382 | P80: Lançado ERP
A81: =IF($H81="UNIDADE CONSTRUTIVA",OFFSET(A81,-1,0)+1,LARGE(A$3:A80,1)) -> 0 | B81: =IF(H81="UNIDADE CONSTRUTIVA",0,IF(H81="CÉLULA CONSTRUTIVA",OFFSET(B81,-1,0)+1,OFFSET(B81,-1,0))) -> 2 | C81: =IF(H81="CÉLULA CONSTRUTIVA",0,IF(H81="ETAPA",OFFSET(C81,-1,0)+1,OFFSET(C81,-1,0))) -> 2 | D81: =IF(H81="ETAPA",0,IF(H81="SUBETAPA",OFFSET(D81,-1,0)+1,OFFSET(D81,-1,0))) -> 3 | E81: =IF(H81="Subetapa",0,IF(H81="serviço",OFFSET(E81,-1,0)+1,OFFSET(E81,-1,0))) -> 7 | H81: SERVIÇO | I81: =IF(H81="Unidade Construtiva",TEXT(A81,"00"),IF(H81="Célula Construtiva",TEXT(B81,"00"),IF(H81="Etapa",CONCATENATE(TEXT(B81,"00"),".",TEXT(C81,"000")),IF(H81="Subetapa",CONCATENATE(TEXT(B81,"00"),".",TEXT(C81,"000"),".",TEXT(D81,"000")),IF(H81="Serviço",CONCATENATE(TEXT(B81,"00"),".",TEXT(C81,"000"),".",TEXT(D81,"000"),".",TEXT(E81,"000")),""))))) -> 02.002.003.007 | J81: Consumo de material de higiene e limpeza | K81: mes | L81: ='Obra '!$E$7 -> 43 | M81: 693.93387 | N81: =IF(H81="Serviço",M81*L81,IF(H81="CÉLULA CONSTRUTIVA",SUMIFS($N$8:$N$397,$B$8:$B$397,B81,$H$8:$H$397,"Serviço"),IF(H81="ETAPA",SUMIFS($N$8:$N$397,$B$8:$B$397,B81,$C$8:$C$397,C81,$H$8:$H$397,"Serviço"),IF(H81="SUBETAPA",SUMIFS($N$8:$N$397,$B$8:$B$397,B81,$C$8:$C$397,C81,$D$8:$D$397,D81,$H$8:$H$397,"Serviço"),0)))) -> 29839.156 | P81: Lançado ERP
A82: =IF($H82="UNIDADE CONSTRUTIVA",OFFSET(A82,-1,0)+1,LARGE(A$3:A81,1)) -> 0 | B82: =IF(H82="UNIDADE CONSTRUTIVA",0,IF(H82="CÉLULA CONSTRUTIVA",OFFSET(B82,-1,0)+1,OFFSET(B82,-1,0))) -> 2 | C82: =IF(H82="CÉLULA CONSTRUTIVA",0,IF(H82="ETAPA",OFFSET(C82,-1,0)+1,OFFSET(C82,-1,0))) -> 2 | D82: =IF(H82="ETAPA",0,IF(H82="SUBETAPA",OFFSET(D82,-1,0)+1,OFFSET(D82,-1,0))) -> 3 | E82: =IF(H82="Subetapa",0,IF(H82="serviço",OFFSET(E82,-1,0)+1,OFFSET(E82,-1,0))) -> 8 | H82: SERVIÇO | I82: =IF(H82="Unidade Construtiva",TEXT(A82,"00"),IF(H82="Célula Construtiva",TEXT(B82,"00"),IF(H82="Etapa",CONCATENATE(TEXT(B82,"00"),".",TEXT(C82,"000")),IF(H82="Subetapa",CONCATENATE(TEXT(B82,"00"),".",TEXT(C82,"000"),".",TEXT(D82,"000")),IF(H82="Serviço",CONCATENATE(TEXT(B82,"00"),".",TEXT(C82,"000"),".",TEXT(D82,"000"),".",TEXT(E82,"000")),""))))) -> 02.002.003.008 | J82: Fotocópias e Heliográficas | K82: mes | L82: ='Obra '!$E$7 -> 43 | M82: 540.19762 | N82: =IF(H82="Serviço",M82*L82,IF(H82="CÉLULA CONSTRUTIVA",SUMIFS($N$8:$N$397,$B$8:$B$397,B82,$H$8:$H$397,"Serviço"),IF(H82="ETAPA",SUMIFS($N$8:$N$397,$B$8:$B$397,B82,$C$8:$C$397,C82,$H$8:$H$397,"Serviço"),IF(H82="SUBETAPA",SUMIFS($N$8:$N$397,$B$8:$B$397,B82,$C$8:$C$397,C82,$D$8:$D$397,D82,$H$8:$H$397,"Serviço"),0)))) -> 23228.497 | P82: Lançado ERP
A83: =IF($H83="UNIDADE CONSTRUTIVA",OFFSET(A83,-1,0)+1,LARGE(A$3:A82,1)) -> 0 | B83: =IF(H83="UNIDADE CONSTRUTIVA",0,IF(H83="CÉLULA CONSTRUTIVA",OFFSET(B83,-1,0)+1,OFFSET(B83,-1,0))) -> 2 | C83: =IF(H83="CÉLULA CONSTRUTIVA",0,IF(H83="ETAPA",OFFSET(C83,-1,0)+1,OFFSET(C83,-1,0))) -> 2 | D83: =IF(H83="ETAPA",0,IF(H83="SUBETAPA",OFFSET(D83,-1,0)+1,OFFSET(D83,-1,0))) -> 3 | E83: =IF(H83="Subetapa",0,IF(H83="serviço",OFFSET(E83,-1,0)+1,OFFSET(E83,-1,0))) -> 9 | H83: SERVIÇO | I83: =IF(H83="Unidade Construtiva",TEXT(A83,"00"),IF(H83="Célula Construtiva",TEXT(B83,"00"),IF(H83="Etapa",CONCATENATE(TEXT(B83,"00"),".",TEXT(C83,"000")),IF(H83="Subetapa",CONCATENATE(TEXT(B83,"00"),".",TEXT(C83,"000"),".",TEXT(D83,"000")),IF(H83="Serviço",CONCATENATE(TEXT(B83,"00"),".",TEXT(C83,"000"),".",TEXT(D83,"000"),".",TEXT(E83,"000")),""))))) -> 02.002.003.009 | J83: Manutenção provisória do canteiro | K83: mes | L83: ='Obra '!$E$7 -> 43 | M83: 661.87364 | N83: =IF(H83="Serviço",M83*L83,IF(H83="CÉLULA CONSTRUTIVA",SUMIFS($N$8:$N$397,$B$8:$B$397,B83,$H$8:$H$397,"Serviço"),IF(H83="ETAPA",SUMIFS($N$8:$N$397,$B$8:$B$397,B83,$C$8:$C$397,C83,$H$8:$H$397,"Serviço"),IF(H83="SUBETAPA",SUMIFS($N$8:$N$397,$B$8:$B$397,B83,$C$8:$C$397,C83,$D$8:$D$397,D83,$H$8:$H$397,"Serviço"),0)))) -> 28460.567 | P83: Lançado ERP
A84: =IF($H84="UNIDADE CONSTRUTIVA",OFFSET(A84,-1,0)+1,LARGE(A$3:A83,1)) -> 0 | B84: =IF(H84="UNIDADE CONSTRUTIVA",0,IF(H84="CÉLULA CONSTRUTIVA",OFFSET(B84,-1,0)+1,OFFSET(B84,-1,0))) -> 2 | C84: =IF(H84="CÉLULA CONSTRUTIVA",0,IF(H84="ETAPA",OFFSET(C84,-1,0)+1,OFFSET(C84,-1,0))) -> 2 | D84: =IF(H84="ETAPA",0,IF(H84="SUBETAPA",OFFSET(D84,-1,0)+1,OFFSET(D84,-1,0))) -> 3 | E84: =IF(H84="Subetapa",0,IF(H84="serviço",OFFSET(E84,-1,0)+1,OFFSET(E84,-1,0))) -> 10 | H84: SERVIÇO | I84: =IF(H84="Unidade Construtiva",TEXT(A84,"00"),IF(H84="Célula Construtiva",TEXT(B84,"00"),IF(H84="Etapa",CONCATENATE(TEXT(B84,"00"),".",TEXT(C84,"000")),IF(H84="Subetapa",CONCATENATE(TEXT(B84,"00"),".",TEXT(C84,"000"),".",TEXT(D84,"000")),IF(H84="Serviço",CONCATENATE(TEXT(B84,"00"),".",TEXT(C84,"000"),".",TEXT(D84,"000"),".",TEXT(E84,"000")),""))))) -> 02.002.003.010 | J84: Manutenção provisória elétrica | K84: mes | L84: ='Obra '!$E$7 -> 43 | M84: 481.30896 | N84: =IF(H84="Serviço",M84*L84,IF(H84="CÉLULA CONSTRUTIVA",SUMIFS($N$8:$N$397,$B$8:$B$397,B84,$H$8:$H$397,"Serviço"),IF(H84="ETAPA",SUMIFS($N$8:$N$397,$B$8:$B$397,B84,$C$8:$C$397,C84,$H$8:$H$397,"Serviço"),IF(H84="SUBETAPA",SUMIFS($N$8:$N$397,$B$8:$B$397,B84,$C$8:$C$397,C84,$D$8:$D$397,D84,$H$8:$H$397,"Serviço"),0)))) -> 20696.285 | P84: Lançado ERP
A85: =IF($H85="UNIDADE CONSTRUTIVA",OFFSET(A85,-1,0)+1,LARGE(A$3:A84,1)) -> 0 | B85: =IF(H85="UNIDADE CONSTRUTIVA",0,IF(H85="CÉLULA CONSTRUTIVA",OFFSET(B85,-1,0)+1,OFFSET(B85,-1,0))) -> 2 | C85: =IF(H85="CÉLULA CONSTRUTIVA",0,IF(H85="ETAPA",OFFSET(C85,-1,0)+1,OFFSET(C85,-1,0))) -> 2 | D85: =IF(H85="ETAPA",0,IF(H85="SUBETAPA",OFFSET(D85,-1,0)+1,OFFSET(D85,-1,0))) -> 3 | E85: =IF(H85="Subetapa",0,IF(H85="serviço",OFFSET(E85,-1,0)+1,OFFSET(E85,-1,0))) -> 11 | H85: SERVIÇO | I85: =IF(H85="Unidade Construtiva",TEXT(A85,"00"),IF(H85="Célula Construtiva",TEXT(B85,"00"),IF(H85="Etapa",CONCATENATE(TEXT(B85,"00"),".",TEXT(C85,"000")),IF(H85="Subetapa",CONCATENATE(TEXT(B85,"00"),".",TEXT(C85,"000"),".",TEXT(D85,"000")),IF(H85="Serviço",CONCATENATE(TEXT(B85,"00"),".",TEXT(C85,"000"),".",TEXT(D85,"000"),".",TEXT(E85,"000")),""))))) -> 02.002.003.011 | J85: Manutenção provisória hidrossanitária | K85: mes | L85: ='Obra '!$E$7 -> 43 | M85: 204.71872 | N85: =IF(H85="Serviço",M85*L85,IF(H85="CÉLULA CONSTRUTIVA",SUMIFS($N$8:$N$397,$B$8:$B$397,B85,$H$8:$H$397,"Serviço"),IF(H85="ETAPA",SUMIFS($N$8:$N$397,$B$8:$B$397,B85,$C$8:$C$397,C85,$H$8:$H$397,"Serviço"),IF(H85="SUBETAPA",SUMIFS($N$8:$N$397,$B$8:$B$397,B85,$C$8:$C$397,C85,$D$8:$D$397,D85,$H$8:$H$397,"Serviço"),0)))) -> 8802.905 | P85: Lançado ERP
A86: =IF($H86="UNIDADE CONSTRUTIVA",OFFSET(A86,-1,0)+1,LARGE(A$3:A85,1)) -> 0 | B86: =IF(H86="UNIDADE CONSTRUTIVA",0,IF(H86="CÉLULA CONSTRUTIVA",OFFSET(B86,-1,0)+1,OFFSET(B86,-1,0))) -> 2 | C86: =IF(H86="CÉLULA CONSTRUTIVA",0,IF(H86="ETAPA",OFFSET(C86,-1,0)+1,OFFSET(C86,-1,0))) -> 2 | D86: =IF(H86="ETAPA",0,IF(H86="SUBETAPA",OFFSET(D86,-1,0)+1,OFFSET(D86,-1,0))) -> 3 | E86: =IF(H86="Subetapa",0,IF(H86="serviço",OFFSET(E86,-1,0)+1,OFFSET(E86,-1,0))) -> 12 | H86: SERVIÇO | I86: =IF(H86="Unidade Construtiva",TEXT(A86,"00"),IF(H86="Célula Construtiva",TEXT(B86,"00"),IF(H86="Etapa",CONCATENATE(TEXT(B86,"00"),".",TEXT(C86,"000")),IF(H86="Subetapa",CONCATENATE(TEXT(B86,"00"),".",TEXT(C86,"000"),".",TEXT(D86,"000")),IF(H86="Serviço",CONCATENATE(TEXT(B86,"00"),".",TEXT(C86,"000"),".",TEXT(D86,"000"),".",TEXT(E86,"000")),""))))) -> 02.002.003.012 | J86: Manutenção provisória de vigilância e acessos | K86: mes | L86: ='Obra '!$E$7 -> 43 | M86: 300.74427 | N86: =IF(H86="Serviço",M86*L86,IF(H86="CÉLULA CONSTRUTIVA",SUMIFS($N$8:$N$397,$B$8:$B$397,B86,$H$8:$H$397,"Serviço"),IF(H86="ETAPA",SUMIFS($N$8:$N$397,$B$8:$B$397,B86,$C$8:$C$397,C86,$H$8:$H$397,"Serviço"),IF(H86="SUBETAPA",SUMIFS($N$8:$N$397,$B$8:$B$397,B86,$C$8:$C$397,C86,$D$8:$D$397,D86,$H$8:$H$397,"Serviço"),0)))) -> 12932.004 | P86: Lançado ERP
A87: =IF($H87="UNIDADE CONSTRUTIVA",OFFSET(A87,-1,0)+1,LARGE(A$3:A83,1)) -> 0 | B87: =IF(H87="UNIDADE CONSTRUTIVA",0,IF(H87="CÉLULA CONSTRUTIVA",OFFSET(B87,-1,0)+1,OFFSET(B87,-1,0))) -> 2 | C87: =IF(H87="CÉLULA CONSTRUTIVA",0,IF(H87="ETAPA",OFFSET(C87,-1,0)+1,OFFSET(C87,-1,0))) -> 2 | D87: =IF(H87="ETAPA",0,IF(H87="SUBETAPA",OFFSET(D87,-1,0)+1,OFFSET(D87,-1,0))) -> 4 | E87: =IF(H87="Subetapa",0,IF(H87="serviço",OFFSET(E87,-1,0)+1,OFFSET(E87,-1,0))) -> 0 | H87: SUBETAPA | I87: =IF(H87="Unidade Construtiva",TEXT(A87,"00"),IF(H87="Célula Construtiva",TEXT(B87,"00"),IF(H87="Etapa",CONCATENATE(TEXT(B87,"00"),".",TEXT(C87,"000")),IF(H87="Subetapa",CONCATENATE(TEXT(B87,"00"),".",TEXT(C87,"000"),".",TEXT(D87,"000")),IF(H87="Serviço",CONCATENATE(TEXT(B87,"00"),".",TEXT(C87,"000"),".",TEXT(D87,"000"),".",TEXT(E87,"000")),""))))) -> 02.002.004 | J87: Instalações Provisórias de Canteiro de Obra | N87: =IF(H87="Serviço",M87*L87,IF(H87="CÉLULA CONSTRUTIVA",SUMIFS($N$8:$N$397,$B$8:$B$397,B87,$H$8:$H$397,"Serviço"),IF(H87="ETAPA",SUMIFS($N$8:$N$397,$B$8:$B$397,B87,$C$8:$C$397,C87,$H$8:$H$397,"Serviço"),IF(H87="SUBETAPA",SUMIFS($N$8:$N$397,$B$8:$B$397,B87,$C$8:$C$397,C87,$D$8:$D$397,D87,$H$8:$H$397,"Serviço"),0)))) -> 111713.63
A88: =IF($H88="UNIDADE CONSTRUTIVA",OFFSET(A88,-1,0)+1,LARGE(A$3:A83,1)) -> 0 | B88: =IF(H88="UNIDADE CONSTRUTIVA",0,IF(H88="CÉLULA CONSTRUTIVA",OFFSET(B88,-1,0)+1,OFFSET(B88,-1,0))) -> 2 | C88: =IF(H88="CÉLULA CONSTRUTIVA",0,IF(H88="ETAPA",OFFSET(C88,-1,0)+1,OFFSET(C88,-1,0))) -> 2 | D88: =IF(H88="ETAPA",0,IF(H88="SUBETAPA",OFFSET(D88,-1,0)+1,OFFSET(D88,-1,0))) -> 4 | E88: =IF(H88="Subetapa",0,IF(H88="serviço",OFFSET(E88,-1,0)+1,OFFSET(E88,-1,0))) -> 1 | H88: SERVIÇO | I88: =IF(H88="Unidade Construtiva",TEXT(A88,"00"),IF(H88="Célula Construtiva",TEXT(B88,"00"),IF(H88="Etapa",CONCATENATE(TEXT(B88,"00"),".",TEXT(C88,"000")),IF(H88="Subetapa",CONCATENATE(TEXT(B88,"00"),".",TEXT(C88,"000"),".",TEXT(D88,"000")),IF(H88="Serviço",CONCATENATE(TEXT(B88,"00"),".",TEXT(C88,"000"),".",TEXT(D88,"000"),".",TEXT(E88,"000")),""))))) -> 02.002.004.001 | J88: Locação de container | K88: mes | L88: 17 | M88: 1950 | N88: =IF(H88="Serviço",M88*L88,IF(H88="CÉLULA CONSTRUTIVA",SUMIFS($N$8:$N$397,$B$8:$B$397,B88,$H$8:$H$397,"Serviço"),IF(H88="ETAPA",SUMIFS($N$8:$N$397,$B$8:$B$397,B88,$C$8:$C$397,C88,$H$8:$H$397,"Serviço"),IF(H88="SUBETAPA",SUMIFS($N$8:$N$397,$B$8:$B$397,B88,$C$8:$C$397,C88,$D$8:$D$397,D88,$H$8:$H$397,"Serviço"),0)))) -> 33150 | O88: Período da fundação + 6 meses | P88: Lançado ERP
A89: =IF($H89="UNIDADE CONSTRUTIVA",OFFSET(A89,-1,0)+1,LARGE(A$3:A87,1)) -> 0 | B89: =IF(H89="UNIDADE CONSTRUTIVA",0,IF(H89="CÉLULA CONSTRUTIVA",OFFSET(B89,-1,0)+1,OFFSET(B89,-1,0))) -> 2 | C89: =IF(H89="CÉLULA CONSTRUTIVA",0,IF(H89="ETAPA",OFFSET(C89,-1,0)+1,OFFSET(C89,-1,0))) -> 2 | D89: =IF(H89="ETAPA",0,IF(H89="SUBETAPA",OFFSET(D89,-1,0)+1,OFFSET(D89,-1,0))) -> 4 | E89: =IF(H89="Subetapa",0,IF(H89="serviço",OFFSET(E89,-1,0)+1,OFFSET(E89,-1,0))) -> 2 | H89: SERVIÇO | I89: =IF(H89="Unidade Construtiva",TEXT(A89,"00"),IF(H89="Célula Construtiva",TEXT(B89,"00"),IF(H89="Etapa",CONCATENATE(TEXT(B89,"00"),".",TEXT(C89,"000")),IF(H89="Subetapa",CONCATENATE(TEXT(B89,"00"),".",TEXT(C89,"000"),".",TEXT(D89,"000")),IF(H89="Serviço",CONCATENATE(TEXT(B89,"00"),".",TEXT(C89,"000"),".",TEXT(D89,"000"),".",TEXT(E89,"000")),""))))) -> 02.002.004.002 | J89: Instalações Provisórias (central de aço, formas, argamassa, almoxarifado geral, construções temporárias) | K89: vb | L89: 1 | M89: 25030.458 | N89: =IF(H89="Serviço",M89*L89,IF(H89="CÉLULA CONSTRUTIVA",SUMIFS($N$8:$N$397,$B$8:$B$397,B89,$H$8:$H$397,"Serviço"),IF(H89="ETAPA",SUMIFS($N$8:$N$397,$B$8:$B$397,B89,$C$8:$C$397,C89,$H$8:$H$397,"Serviço"),IF(H89="SUBETAPA",SUMIFS($N$8:$N$397,$B$8:$B$397,B89,$C$8:$C$397,C89,$D$8:$D$397,D89,$H$8:$H$397,"Serviço"),0)))) -> 25030.458 | P89: Lançado ERP
A90: =IF($H90="UNIDADE CONSTRUTIVA",OFFSET(A90,-1,0)+1,LARGE(A$3:A89,1)) -> 0 | B90: =IF(H90="UNIDADE CONSTRUTIVA",0,IF(H90="CÉLULA CONSTRUTIVA",OFFSET(B90,-1,0)+1,OFFSET(B90,-1,0))) -> 2 | C90: =IF(H90="CÉLULA CONSTRUTIVA",0,IF(H90="ETAPA",OFFSET(C90,-1,0)+1,OFFSET(C90,-1,0))) -> 2 | D90: =IF(H90="ETAPA",0,IF(H90="SUBETAPA",OFFSET(D90,-1,0)+1,OFFSET(D90,-1,0))) -> 4 | E90: =IF(H90="Subetapa",0,IF(H90="serviço",OFFSET(E90,-1,0)+1,OFFSET(E90,-1,0))) -> 3 | H90: SERVIÇO | I90: =IF(H90="Unidade Construtiva",TEXT(A90,"00"),IF(H90="Célula Construtiva",TEXT(B90,"00"),IF(H90="Etapa",CONCATENATE(TEXT(B90,"00"),".",TEXT(C90,"000")),IF(H90="Subetapa",CONCATENATE(TEXT(B90,"00"),".",TEXT(C90,"000"),".",TEXT(D90,"000")),IF(H90="Serviço",CONCATENATE(TEXT(B90,"00"),".",TEXT(C90,"000"),".",TEXT(D90,"000"),".",TEXT(E90,"000")),""))))) -> 02.002.004.003 | J90: Locação de banheiro químico | K90: mes | L90: =L88 -> 17 | M90: 980 | N90: =IF(H90="Serviço",M90*L90,IF(H90="CÉLULA CONSTRUTIVA",SUMIFS($N$8:$N$397,$B$8:$B$397,B90,$H$8:$H$397,"Serviço"),IF(H90="ETAPA",SUMIFS($N$8:$N$397,$B$8:$B$397,B90,$C$8:$C$397,C90,$H$8:$H$397,"Serviço"),IF(H90="SUBETAPA",SUMIFS($N$8:$N$397,$B$8:$B$397,B90,$C$8:$C$397,C90,$D$8:$D$397,D90,$H$8:$H$397,"Serviço"),0)))) -> 16660 | P90: Lançado ERP
A91: =IF($H91="UNIDADE CONSTRUTIVA",OFFSET(A91,-1,0)+1,LARGE(A$3:A90,1)) -> 0 | B91: =IF(H91="UNIDADE CONSTRUTIVA",0,IF(H91="CÉLULA CONSTRUTIVA",OFFSET(B91,-1,0)+1,OFFSET(B91,-1,0))) -> 2 | C91: =IF(H91="CÉLULA CONSTRUTIVA",0,IF(H91="ETAPA",OFFSET(C91,-1,0)+1,OFFSET(C91,-1,0))) -> 2 | D91: =IF(H91="ETAPA",0,IF(H91="SUBETAPA",OFFSET(D91,-1,0)+1,OFFSET(D91,-1,0))) -> 4 | E91: =IF(H91="Subetapa",0,IF(H91="serviço",OFFSET(E91,-1,0)+1,OFFSET(E91,-1,0))) -> 4 | H91: SERVIÇO | I91: =IF(H91="Unidade Construtiva",TEXT(A91,"00"),IF(H91="Célula Construtiva",TEXT(B91,"00"),IF(H91="Etapa",CONCATENATE(TEXT(B91,"00"),".",TEXT(C91,"000")),IF(H91="Subetapa",CONCATENATE(TEXT(B91,"00"),".",TEXT(C91,"000"),".",TEXT(D91,"000")),IF(H91="Serviço",CONCATENATE(TEXT(B91,"00"),".",TEXT(C91,"000"),".",TEXT(D91,"000"),".",TEXT(E91,"000")),""))))) -> 02.002.004.004 | J91: Mobiliário de apoio a obra | K91: vb | L91: 1 | M91: 14000 | N91: =IF(H91="Serviço",M91*L91,IF(H91="CÉLULA CONSTRUTIVA",SUMIFS($N$8:$N$397,$B$8:$B$397,B91,$H$8:$H$397,"Serviço"),IF(H91="ETAPA",SUMIFS($N$8:$N$397,$B$8:$B$397,B91,$C$8:$C$397,C91,$H$8:$H$397,"Serviço"),IF(H91="SUBETAPA",SUMIFS($N$8:$N$397,$B$8:$B$397,B91,$C$8:$C$397,C91,$D$8:$D$397,D91,$H$8:$H$397,"Serviço"),0)))) -> 14000 | P91: Lançado ERP
A92: =IF($H92="UNIDADE CONSTRUTIVA",OFFSET(A92,-1,0)+1,LARGE(A$3:A91,1)) -> 0 | B92: =IF(H92="UNIDADE CONSTRUTIVA",0,IF(H92="CÉLULA CONSTRUTIVA",OFFSET(B92,-1,0)+1,OFFSET(B92,-1,0))) -> 2 | C92: =IF(H92="CÉLULA CONSTRUTIVA",0,IF(H92="ETAPA",OFFSET(C92,-1,0)+1,OFFSET(C92,-1,0))) -> 2 | D92: =IF(H92="ETAPA",0,IF(H92="SUBETAPA",OFFSET(D92,-1,0)+1,OFFSET(D92,-1,0))) -> 4 | E92: =IF(H92="Subetapa",0,IF(H92="serviço",OFFSET(E92,-1,0)+1,OFFSET(E92,-1,0))) -> 5 | H92: SERVIÇO | I92: =IF(H92="Unidade Construtiva",TEXT(A92,"00"),IF(H92="Célula Construtiva",TEXT(B92,"00"),IF(H92="Etapa",CONCATENATE(TEXT(B92,"00"),".",TEXT(C92,"000")),IF(H92="Subetapa",CONCATENATE(TEXT(B92,"00"),".",TEXT(C92,"000"),".",TEXT(D92,"000")),IF(H92="Serviço",CONCATENATE(TEXT(B92,"00"),".",TEXT(C92,"000"),".",TEXT(D92,"000"),".",TEXT(E92,"000")),""))))) -> 02.002.004.005 | J92: Equipamentos de apoio a obra | K92: vb | L92: 1 | M92: 9500 | N92: =IF(H92="Serviço",M92*L92,IF(H92="CÉLULA CONSTRUTIVA",SUMIFS($N$8:$N$397,$B$8:$B$397,B92,$H$8:$H$397,"Serviço"),IF(H92="ETAPA",SUMIFS($N$8:$N$397,$B$8:$B$397,B92,$C$8:$C$397,C92,$H$8:$H$397,"Serviço"),IF(H92="SUBETAPA",SUMIFS($N$8:$N$397,$B$8:$B$397,B92,$C$8:$C$397,C92,$D$8:$D$397,D92,$H$8:$H$397,"Serviço"),0)))) -> 9500 | P92: Lançado ERP
A93: =IF($H93="UNIDADE CONSTRUTIVA",OFFSET(A93,-1,0)+1,LARGE(A$3:A92,1)) -> 0 | B93: =IF(H93="UNIDADE CONSTRUTIVA",0,IF(H93="CÉLULA CONSTRUTIVA",OFFSET(B93,-1,0)+1,OFFSET(B93,-1,0))) -> 2 | C93: =IF(H93="CÉLULA CONSTRUTIVA",0,IF(H93="ETAPA",OFFSET(C93,-1,0)+1,OFFSET(C93,-1,0))) -> 2 | D93: =IF(H93="ETAPA",0,IF(H93="SUBETAPA",OFFSET(D93,-1,0)+1,OFFSET(D93,-1,0))) -> 4 | E93: =IF(H93="Subetapa",0,IF(H93="serviço",OFFSET(E93,-1,0)+1,OFFSET(E93,-1,0))) -> 6 | H93: SERVIÇO | I93: =IF(H93="Unidade Construtiva",TEXT(A93,"00"),IF(H93="Célula Construtiva",TEXT(B93,"00"),IF(H93="Etapa",CONCATENATE(TEXT(B93,"00"),".",TEXT(C93,"000")),IF(H93="Subetapa",CONCATENATE(TEXT(B93,"00"),".",TEXT(C93,"000"),".",TEXT(D93,"000")),IF(H93="Serviço",CONCATENATE(TEXT(B93,"00"),".",TEXT(C93,"000"),".",TEXT(D93,"000"),".",TEXT(E93,"000")),""))))) -> 02.002.004.006 | J93: Tapume de telha metálica trapezoidal | K93: m2 | L93: 81.504 | M93: 164.08 | N93: =IF(H93="Serviço",M93*L93,IF(H93="CÉLULA CONSTRUTIVA",SUMIFS($N$8:$N$397,$B$8:$B$397,B93,$H$8:$H$397,"Serviço"),IF(H93="ETAPA",SUMIFS($N$8:$N$397,$B$8:$B$397,B93,$C$8:$C$397,C93,$H$8:$H$397,"Serviço"),IF(H93="SUBETAPA",SUMIFS($N$8:$N$397,$B$8:$B$397,B93,$C$8:$C$397,C93,$D$8:$D$397,D93,$H$8:$H$397,"Serviço"),0)))) -> 13373.176 | P93: Lançado ERP
A94: =IF($H94="UNIDADE CONSTRUTIVA",OFFSET(A94,-1,0)+1,LARGE(A$3:A93,1)) -> 0 | B94: =IF(H94="UNIDADE CONSTRUTIVA",0,IF(H94="CÉLULA CONSTRUTIVA",OFFSET(B94,-1,0)+1,OFFSET(B94,-1,0))) -> 2 | C94: =IF(H94="CÉLULA CONSTRUTIVA",0,IF(H94="ETAPA",OFFSET(C94,-1,0)+1,OFFSET(C94,-1,0))) -> 2 | D94: =IF(H94="ETAPA",0,IF(H94="SUBETAPA",OFFSET(D94,-1,0)+1,OFFSET(D94,-1,0))) -> 5 | E94: =IF(H94="Subetapa",0,IF(H94="serviço",OFFSET(E94,-1,0)+1,OFFSET(E94,-1,0))) -> 0 | H94: SUBETAPA | I94: =IF(H94="Unidade Construtiva",TEXT(A94,"00"),IF(H94="Célula Construtiva",TEXT(B94,"00"),IF(H94="Etapa",CONCATENATE(TEXT(B94,"00"),".",TEXT(C94,"000")),IF(H94="Subetapa",CONCATENATE(TEXT(B94,"00"),".",TEXT(C94,"000"),".",TEXT(D94,"000")),IF(H94="Serviço",CONCATENATE(TEXT(B94,"00"),".",TEXT(C94,"000"),".",TEXT(D94,"000"),".",TEXT(E94,"000")),""))))) -> 02.002.005 | J94: Ligações Provisórias | N94: =IF(H94="Serviço",M94*L94,IF(H94="CÉLULA CONSTRUTIVA",SUMIFS($N$8:$N$397,$B$8:$B$397,B94,$H$8:$H$397,"Serviço"),IF(H94="ETAPA",SUMIFS($N$8:$N$397,$B$8:$B$397,B94,$C$8:$C$397,C94,$H$8:$H$397,"Serviço"),IF(H94="SUBETAPA",SUMIFS($N$8:$N$397,$B$8:$B$397,B94,$C$8:$C$397,C94,$D$8:$D$397,D94,$H$8:$H$397,"Serviço"),0)))) -> 47636.348
A95: =IF($H95="UNIDADE CONSTRUTIVA",OFFSET(A95,-1,0)+1,LARGE(A$3:A94,1)) -> 0 | B95: =IF(H95="UNIDADE CONSTRUTIVA",0,IF(H95="CÉLULA CONSTRUTIVA",OFFSET(B95,-1,0)+1,OFFSET(B95,-1,0))) -> 2 | C95: =IF(H95="CÉLULA CONSTRUTIVA",0,IF(H95="ETAPA",OFFSET(C95,-1,0)+1,OFFSET(C95,-1,0))) -> 2 | D95: =IF(H95="ETAPA",0,IF(H95="SUBETAPA",OFFSET(D95,-1,0)+1,OFFSET(D95,-1,0))) -> 5 | E95: =IF(H95="Subetapa",0,IF(H95="serviço",OFFSET(E95,-1,0)+1,OFFSET(E95,-1,0))) -> 1 | H95: SERVIÇO | I95: =IF(H95="Unidade Construtiva",TEXT(A95,"00"),IF(H95="Célula Construtiva",TEXT(B95,"00"),IF(H95="Etapa",CONCATENATE(TEXT(B95,"00"),".",TEXT(C95,"000")),IF(H95="Subetapa",CONCATENATE(TEXT(B95,"00"),".",TEXT(C95,"000"),".",TEXT(D95,"000")),IF(H95="Serviço",CONCATENATE(TEXT(B95,"00"),".",TEXT(C95,"000"),".",TEXT(D95,"000"),".",TEXT(E95,"000")),""))))) -> 02.002.005.001 | J95: Rede de água fria, esgoto e drenagem | K95: vb | L95: 1 | M95: 24815.472 | N95: =IF(H95="Serviço",M95*L95,IF(H95="CÉLULA CONSTRUTIVA",SUMIFS($N$8:$N$397,$B$8:$B$397,B95,$H$8:$H$397,"Serviço"),IF(H95="ETAPA",SUMIFS($N$8:$N$397,$B$8:$B$397,B95,$C$8:$C$397,C95,$H$8:$H$397,"Serviço"),IF(H95="SUBETAPA",SUMIFS($N$8:$N$397,$B$8:$B$397,B95,$C$8:$C$397,C95,$D$8:$D$397,D95,$H$8:$H$397,"Serviço"),0)))) -> 24815.472 | P95: Lançado ERP
A96: =IF($H96="UNIDADE CONSTRUTIVA",OFFSET(A96,-1,0)+1,LARGE(A$3:A95,1)) -> 0 | B96: =IF(H96="UNIDADE CONSTRUTIVA",0,IF(H96="CÉLULA CONSTRUTIVA",OFFSET(B96,-1,0)+1,OFFSET(B96,-1,0))) -> 2 | C96: =IF(H96="CÉLULA CONSTRUTIVA",0,IF(H96="ETAPA",OFFSET(C96,-1,0)+1,OFFSET(C96,-1,0))) -> 2 | D96: =IF(H96="ETAPA",0,IF(H96="SUBETAPA",OFFSET(D96,-1,0)+1,OFFSET(D96,-1,0))) -> 5 | E96: =IF(H96="Subetapa",0,IF(H96="serviço",OFFSET(E96,-1,0)+1,OFFSET(E96,-1,0))) -> 2 | H96: SERVIÇO | I96: =IF(H96="Unidade Construtiva",TEXT(A96,"00"),IF(H96="Célula Construtiva",TEXT(B96,"00"),IF(H96="Etapa",CONCATENATE(TEXT(B96,"00"),".",TEXT(C96,"000")),IF(H96="Subetapa",CONCATENATE(TEXT(B96,"00"),".",TEXT(C96,"000"),".",TEXT(D96,"000")),IF(H96="Serviço",CONCATENATE(TEXT(B96,"00"),".",TEXT(C96,"000"),".",TEXT(D96,"000"),".",TEXT(E96,"000")),""))))) -> 02.002.005.002 | J96: Redes elétricas, comunicação e dados | K96: vb | L96: 1 | M96: 22820.875 | N96: =IF(H96="Serviço",M96*L96,IF(H96="CÉLULA CONSTRUTIVA",SUMIFS($N$8:$N$397,$B$8:$B$397,B96,$H$8:$H$397,"Serviço"),IF(H96="ETAPA",SUMIFS($N$8:$N$397,$B$8:$B$397,B96,$C$8:$C$397,C96,$H$8:$H$397,"Serviço"),IF(H96="SUBETAPA",SUMIFS($N$8:$N$397,$B$8:$B$397,B96,$C$8:$C$397,C96,$D$8:$D$397,D96,$H$8:$H$397,"Serviço"),0)))) -> 22820.875 | P96: Lançado ERP
A97: =IF($H97="UNIDADE CONSTRUTIVA",OFFSET(A97,-1,0)+1,LARGE(A$3:A96,1)) -> 0 | B97: =IF(H97="UNIDADE CONSTRUTIVA",0,IF(H97="CÉLULA CONSTRUTIVA",OFFSET(B97,-1,0)+1,OFFSET(B97,-1,0))) -> 3 | C97: =IF(H97="CÉLULA CONSTRUTIVA",0,IF(H97="ETAPA",OFFSET(C97,-1,0)+1,OFFSET(C97,-1,0))) -> 0 | D97: =IF(H97="ETAPA",0,IF(H97="SUBETAPA",OFFSET(D97,-1,0)+1,OFFSET(D97,-1,0))) -> 5 | E97: =IF(H97="Subetapa",0,IF(H97="serviço",OFFSET(E97,-1,0)+1,OFFSET(E97,-1,0))) -> 2 | H97: CÉLULA CONSTRUTIVA | I97: =IF(H97="Unidade Construtiva",TEXT(A97,"00"),IF(H97="Célula Construtiva",TEXT(B97,"00"),IF(H97="Etapa",CONCATENATE(TEXT(B97,"00"),".",TEXT(C97,"000")),IF(H97="Subetapa",CONCATENATE(TEXT(B97,"00"),".",TEXT(C97,"000"),".",TEXT(D97,"000")),IF(H97="Serviço",CONCATENATE(TEXT(B97,"00"),".",TEXT(C97,"000"),".",TEXT(D97,"000"),".",TEXT(E97,"000")),""))))) -> 03 | J97: EQUIPAMENTOS | N97: =IF(H97="Serviço",M97*L97,IF(H97="CÉLULA CONSTRUTIVA",SUMIFS($N$8:$N$397,$B$8:$B$397,B97,$H$8:$H$397,"Serviço"),IF(H97="ETAPA",SUMIFS($N$8:$N$397,$B$8:$B$397,B97,$C$8:$C$397,C97,$H$8:$H$397,"Serviço"),IF(H97="SUBETAPA",SUMIFS($N$8:$N$397,$B$8:$B$397,B97,$C$8:$C$397,C97,$D$8:$D$397,D97,$H$8:$H$397,"Serviço"),0)))) -> 92299.233
A98: =IF($H98="UNIDADE CONSTRUTIVA",OFFSET(A98,-1,0)+1,LARGE(A$3:A97,1)) -> 0 | B98: =IF(H98="UNIDADE CONSTRUTIVA",0,IF(H98="CÉLULA CONSTRUTIVA",OFFSET(B98,-1,0)+1,OFFSET(B98,-1,0))) -> 3 | C98: =IF(H98="CÉLULA CONSTRUTIVA",0,IF(H98="ETAPA",OFFSET(C98,-1,0)+1,OFFSET(C98,-1,0))) -> 1 | D98: =IF(H98="ETAPA",0,IF(H98="SUBETAPA",OFFSET(D98,-1,0)+1,OFFSET(D98,-1,0))) -> 0 | E98: =IF(H98="Subetapa",0,IF(H98="serviço",OFFSET(E98,-1,0)+1,OFFSET(E98,-1,0))) -> 2 | H98: ETAPA | I98: =IF(H98="Unidade Construtiva",TEXT(A98,"00"),IF(H98="Célula Construtiva",TEXT(B98,"00"),IF(H98="Etapa",CONCATENATE(TEXT(B98,"00"),".",TEXT(C98,"000")),IF(H98="Subetapa",CONCATENATE(TEXT(B98,"00"),".",TEXT(C98,"000"),".",TEXT(D98,"000")),IF(H98="Serviço",CONCATENATE(TEXT(B98,"00"),".",TEXT(C98,"000"),".",TEXT(D98,"000"),".",TEXT(E98,"000")),""))))) -> 03.001 | J98: EQUIPAMENTOS | N98: =IF(H98="Serviço",M98*L98,IF(H98="CÉLULA CONSTRUTIVA",SUMIFS($N$8:$N$397,$B$8:$B$397,B98,$H$8:$H$397,"Serviço"),IF(H98="ETAPA",SUMIFS($N$8:$N$397,$B$8:$B$397,B98,$C$8:$C$397,C98,$H$8:$H$397,"Serviço"),IF(H98="SUBETAPA",SUMIFS($N$8:$N$397,$B$8:$B$397,B98,$C$8:$C$397,C98,$D$8:$D$397,D98,$H$8:$H$397,"Serviço"),0)))) -> 92299.233
A99: =IF($H99="UNIDADE CONSTRUTIVA",OFFSET(A99,-1,0)+1,LARGE(A$3:A98,1)) -> 0 | B99: =IF(H99="UNIDADE CONSTRUTIVA",0,IF(H99="CÉLULA CONSTRUTIVA",OFFSET(B99,-1,0)+1,OFFSET(B99,-1,0))) -> 3 | C99: =IF(H99="CÉLULA CONSTRUTIVA",0,IF(H99="ETAPA",OFFSET(C99,-1,0)+1,OFFSET(C99,-1,0))) -> 1 | D99: =IF(H99="ETAPA",0,IF(H99="SUBETAPA",OFFSET(D99,-1,0)+1,OFFSET(D99,-1,0))) -> 1 | E99: =IF(H99="Subetapa",0,IF(H99="serviço",OFFSET(E99,-1,0)+1,OFFSET(E99,-1,0))) -> 0 | H99: SUBETAPA | I99: =IF(H99="Unidade Construtiva",TEXT(A99,"00"),IF(H99="Célula Construtiva",TEXT(B99,"00"),IF(H99="Etapa",CONCATENATE(TEXT(B99,"00"),".",TEXT(C99,"000")),IF(H99="Subetapa",CONCATENATE(TEXT(B99,"00"),".",TEXT(C99,"000"),".",TEXT(D99,"000")),IF(H99="Serviço",CONCATENATE(TEXT(B99,"00"),".",TEXT(C99,"000"),".",TEXT(D99,"000"),".",TEXT(E99,"000")),""))))) -> 03.001.001 | J99: Equipamentos de Obra | N99: =IF(H99="Serviço",M99*L99,IF(H99="CÉLULA CONSTRUTIVA",SUMIFS($N$8:$N$397,$B$8:$B$397,B99,$H$8:$H$397,"Serviço"),IF(H99="ETAPA",SUMIFS($N$8:$N$397,$B$8:$B$397,B99,$C$8:$C$397,C99,$H$8:$H$397,"Serviço"),IF(H99="SUBETAPA",SUMIFS($N$8:$N$397,$B$8:$B$397,B99,$C$8:$C$397,C99,$D$8:$D$397,D99,$H$8:$H$397,"Serviço"),0)))) -> 92299.233
A100: =IF($H100="UNIDADE CONSTRUTIVA",OFFSET(A100,-1,0)+1,LARGE(A$3:A99,1)) -> 0 | B100: =IF(H100="UNIDADE CONSTRUTIVA",0,IF(H100="CÉLULA CONSTRUTIVA",OFFSET(B100,-1,0)+1,OFFSET(B100,-1,0))) -> 3 | C100: =IF(H100="CÉLULA CONSTRUTIVA",0,IF(H100="ETAPA",OFFSET(C100,-1,0)+1,OFFSET(C100,-1,0))) -> 1 | D100: =IF(H100="ETAPA",0,IF(H100="SUBETAPA",OFFSET(D100,-1,0)+1,OFFSET(D100,-1,0))) -> 1 | E100: =IF(H100="Subetapa",0,IF(H100="serviço",OFFSET(E100,-1,0)+1,OFFSET(E100,-1,0))) -> 1 | H100: SERVIÇO | I100: =IF(H100="Unidade Construtiva",TEXT(A100,"00"),IF(H100="Célula Construtiva",TEXT(B100,"00"),IF(H100="Etapa",CONCATENATE(TEXT(B100,"00"),".",TEXT(C100,"000")),IF(H100="Subetapa",CONCATENATE(TEXT(B100,"00"),".",TEXT(C100,"000"),".",TEXT(D100,"000")),IF(H100="Serviço",CONCATENATE(TEXT(B100,"00"),".",TEXT(C100,"000"),".",TEXT(D100,"000"),".",TEXT(E100,"000")),""))))) -> 03.001.001.001 | J100: Manutenção periódica para grua ascencional | K100: mes | L100: 27 | M100: 3418.4901 | N100: =IF(H100="Serviço",M100*L100,IF(H100="CÉLULA CONSTRUTIVA",SUMIFS($N$8:$N$397,$B$8:$B$397,B100,$H$8:$H$397,"Serviço"),IF(H100="ETAPA",SUMIFS($N$8:$N$397,$B$8:$B$397,B100,$C$8:$C$397,C100,$H$8:$H$397,"Serviço"),IF(H100="SUBETAPA",SUMIFS($N$8:$N$397,$B$8:$B$397,B100,$C$8:$C$397,C100,$D$8:$D$397,D100,$H$8:$H$397,"Serviço"),0)))) -> 92299.233 | P100: Lançado ERP
A101: =IF($H101="UNIDADE CONSTRUTIVA",OFFSET(A101,-1,0)+1,LARGE(A$3:A100,1)) -> 0 | B101: =IF(H101="UNIDADE CONSTRUTIVA",0,IF(H101="CÉLULA CONSTRUTIVA",OFFSET(B101,-1,0)+1,OFFSET(B101,-1,0))) -> 3 | C101: =IF(H101="CÉLULA CONSTRUTIVA",0,IF(H101="ETAPA",OFFSET(C101,-1,0)+1,OFFSET(C101,-1,0))) -> 1 | D101: =IF(H101="ETAPA",0,IF(H101="SUBETAPA",OFFSET(D101,-1,0)+1,OFFSET(D101,-1,0))) -> 1 | E101: =IF(H101="Subetapa",0,IF(H101="serviço",OFFSET(E101,-1,0)+1,OFFSET(E101,-1,0))) -> 1 | J101: TOTAL | N101: =N97+N50+N8 -> 3667981.1
A102: =IF($H102="UNIDADE CONSTRUTIVA",OFFSET(A102,-1,0)+1,LARGE(A$3:A101,1)) -> 0 | B102: =IF(H102="UNIDADE CONSTRUTIVA",0,IF(H102="CÉLULA CONSTRUTIVA",OFFSET(B102,-1,0)+1,OFFSET(B102,-1,0))) -> 3 | C102: =IF(H102="CÉLULA CONSTRUTIVA",0,IF(H102="ETAPA",OFFSET(C102,-1,0)+1,OFFSET(C102,-1,0))) -> 1 | D102: =IF(H102="ETAPA",0,IF(H102="SUBETAPA",OFFSET(D102,-1,0)+1,OFFSET(D102,-1,0))) -> 1 | E102: =IF(H102="Subetapa",0,IF(H102="serviço",OFFSET(E102,-1,0)+1,OFFSET(E102,-1,0))) -> 1 | M102: =SUMIFS($N$7:$N$392,$H$7:$H$392,N102) -> 3667981.1 | N102: CÉLULA CONSTRUTIVA
A103: =IF($H103="UNIDADE CONSTRUTIVA",OFFSET(A103,-1,0)+1,LARGE(A$3:A102,1)) -> 0 | B103: =IF(H103="UNIDADE CONSTRUTIVA",0,IF(H103="CÉLULA CONSTRUTIVA",OFFSET(B103,-1,0)+1,OFFSET(B103,-1,0))) -> 3 | C103: =IF(H103="CÉLULA CONSTRUTIVA",0,IF(H103="ETAPA",OFFSET(C103,-1,0)+1,OFFSET(C103,-1,0))) -> 1 | D103: =IF(H103="ETAPA",0,IF(H103="SUBETAPA",OFFSET(D103,-1,0)+1,OFFSET(D103,-1,0))) -> 1 | E103: =IF(H103="Subetapa",0,IF(H103="serviço",OFFSET(E103,-1,0)+1,OFFSET(E103,-1,0))) -> 1 | M103: =SUMIFS($N$7:$N$392,$H$7:$H$392,N103) -> 3667981.1 | N103: ETAPA
...

Sheet Ger_Executivo
G4: PROJETO: | I4: ='Ger_Tec e Adm'!I4 -> 365 | O4: REVISÃO: | P4: DATA
G5: EMPRESA: | I5: ='Ger_Tec e Adm'!I5 -> COTA | O5: R00
A6: Unidade Construtiva | B6: Célula Construtiva | C6: Etapa | D6: Subetapa | E6: Serviço | G6: GERENCIAMENTO EXECUTIVO
A7: 0 | B7: 0 | C7: 0 | D7: 0 | E7: 0 | G7: Atalho | H7: NIVEL | I7: Item | J7: Descrição | K7: Unidade | L7: Quant. | M7: Preço un | N7: Total | O7: Considerações | P7: Situação
A8: =IF($H8="UNIDADE CONSTRUTIVA",OFFSET(A8,-1,0)+1,LARGE(A$3:A7,1)) -> 0 | B8: =IF(H8="UNIDADE CONSTRUTIVA",0,IF(H8="CÉLULA CONSTRUTIVA",OFFSET(B8,-1,0)+1,OFFSET(B8,-1,0))) -> 1 | C8: =IF(H8="CÉLULA CONSTRUTIVA",0,IF(H8="ETAPA",OFFSET(C8,-1,0)+1,OFFSET(C8,-1,0))) -> 0 | D8: =IF(H8="ETAPA",0,IF(H8="SUBETAPA",OFFSET(D8,-1,0)+1,OFFSET(D8,-1,0))) -> 0 | E8: =IF(H8="Subetapa",0,IF(H8="serviço",OFFSET(E8,-1,0)+1,OFFSET(E8,-1,0))) -> 0 | H8: CÉLULA CONSTRUTIVA | I8: =IF(H8="Unidade Construtiva",TEXT(A8,"00"),IF(H8="Célula Construtiva",TEXT(B8,"00"),IF(H8="Etapa",CONCATENATE(TEXT(B8,"00"),".",TEXT(C8,"000")),IF(H8="Subetapa",CONCATENATE(TEXT(B8,"00"),".",TEXT(C8,"000"),".",TEXT(D8,"000")),IF(H8="Serviço",CONCATENATE(TEXT(B8,"00"),".",TEXT(C8,"000"),".",TEXT(D8,"000"),".",TEXT(E8,"000")),""))))) -> 01 | J8: MOVIMENTAÇÃO DE TERRA | N8: =IF(H8="Serviço",M8*L8,IF(H8="CÉLULA CONSTRUTIVA",SUMIFS($N$8:$N$335,$B$8:$B$335,B8,$H$8:$H$335,"Serviço"),IF(H8="ETAPA",SUMIFS($N$8:$N$335,$B$8:$B$335,B8,$C$8:$C$335,C8,$H$8:$H$335,"Serviço"),IF(H8="SUBETAPA",SUMIFS($N$8:$N$335,$B$8:$B$335,B8,$C$8:$C$335,C8,$D$8:$D$335,D8,$H$8:$H$335,"Serviço"),0)))) -> 1400464.9
A9: =IF($H9="UNIDADE CONSTRUTIVA",OFFSET(A9,-1,0)+1,LARGE(A$3:A8,1)) -> 0 | B9: =IF(H9="UNIDADE CONSTRUTIVA",0,IF(H9="CÉLULA CONSTRUTIVA",OFFSET(B9,-1,0)+1,OFFSET(B9,-1,0))) -> 1 | C9: =IF(H9="CÉLULA CONSTRUTIVA",0,IF(H9="ETAPA",OFFSET(C9,-1,0)+1,OFFSET(C9,-1,0))) -> 1 | D9: =IF(H9="ETAPA",0,IF(H9="SUBETAPA",OFFSET(D9,-1,0)+1,OFFSET(D9,-1,0))) -> 0 | E9: =IF(H9="Subetapa",0,IF(H9="serviço",OFFSET(E9,-1,0)+1,OFFSET(E9,-1,0))) -> 0 | H9: ETAPA | I9: =IF(H9="Unidade Construtiva",TEXT(A9,"00"),IF(H9="Célula Construtiva",TEXT(B9,"00"),IF(H9="Etapa",CONCATENATE(TEXT(B9,"00"),".",TEXT(C9,"000")),IF(H9="Subetapa",CONCATENATE(TEXT(B9,"00"),".",TEXT(C9,"000"),".",TEXT(D9,"000")),IF(H9="Serviço",CONCATENATE(TEXT(B9,"00"),".",TEXT(C9,"000"),".",TEXT(D9,"000"),".",TEXT(E9,"000")),""))))) -> 01.001 | J9: MOVIMENTAÇÃO DE TERRA | N9: =IF(H9="Serviço",M9*L9,IF(H9="CÉLULA CONSTRUTIVA",SUMIFS($N$8:$N$335,$B$8:$B$335,B9,$H$8:$H$335,"Serviço"),IF(H9="ETAPA",SUMIFS($N$8:$N$335,$B$8:$B$335,B9,$C$8:$C$335,C9,$H$8:$H$335,"Serviço"),IF(H9="SUBETAPA",SUMIFS($N$8:$N$335,$B$8:$B$335,B9,$C$8:$C$335,C9,$D$8:$D$335,D9,$H$8:$H$335,"Serviço"),0)))) -> 1400464.9
A10: =IF($H10="UNIDADE CONSTRUTIVA",OFFSET(A10,-1,0)+1,LARGE(A$3:A7,1)) -> 0 | B10: =IF(H10="UNIDADE CONSTRUTIVA",0,IF(H10="CÉLULA CONSTRUTIVA",OFFSET(B10,-1,0)+1,OFFSET(B10,-1,0))) -> 1 | C10: =IF(H10="CÉLULA CONSTRUTIVA",0,IF(H10="ETAPA",OFFSET(C10,-1,0)+1,OFFSET(C10,-1,0))) -> 1 | D10: =IF(H10="ETAPA",0,IF(H10="SUBETAPA",OFFSET(D10,-1,0)+1,OFFSET(D10,-1,0))) -> 1 | E10: =IF(H10="Subetapa",0,IF(H10="serviço",OFFSET(E10,-1,0)+1,OFFSET(E10,-1,0))) -> 0 | H10: SUBETAPA | I10: =IF(H10="Unidade Construtiva",TEXT(A10,"00"),IF(H10="Célula Construtiva",TEXT(B10,"00"),IF(H10="Etapa",CONCATENATE(TEXT(B10,"00"),".",TEXT(C10,"000")),IF(H10="Subetapa",CONCATENATE(TEXT(B10,"00"),".",TEXT(C10,"000"),".",TEXT(D10,"000")),IF(H10="Serviço",CONCATENATE(TEXT(B10,"00"),".",TEXT(C10,"000"),".",TEXT(D10,"000"),".",TEXT(E10,"000")),""))))) -> 01.001.001 | J10: Rebaixamento de Lençol Freático | N10: =IF(H10="Serviço",M10*L10,IF(H10="CÉLULA CONSTRUTIVA",SUMIFS($N$8:$N$335,$B$8:$B$335,B10,$H$8:$H$335,"Serviço"),IF(H10="ETAPA",SUMIFS($N$8:$N$335,$B$8:$B$335,B10,$C$8:$C$335,C10,$H$8:$H$335,"Serviço"),IF(H10="SUBETAPA",SUMIFS($N$8:$N$335,$B$8:$B$335,B10,$C$8:$C$335,C10,$D$8:$D$335,D10,$H$8:$H$335,"Serviço"),0)))) -> 18000
A11: =IF($H11="UNIDADE CONSTRUTIVA",OFFSET(A11,-1,0)+1,LARGE(A$3:A8,1)) -> 0 | B11: =IF(H11="UNIDADE CONSTRUTIVA",0,IF(H11="CÉLULA CONSTRUTIVA",OFFSET(B11,-1,0)+1,OFFSET(B11,-1,0))) -> 1 | C11: =IF(H11="CÉLULA CONSTRUTIVA",0,IF(H11="ETAPA",OFFSET(C11,-1,0)+1,OFFSET(C11,-1,0))) -> 1 | D11: =IF(H11="ETAPA",0,IF(H11="SUBETAPA",OFFSET(D11,-1,0)+1,OFFSET(D11,-1,0))) -> 1 | E11: =IF(H11="Subetapa",0,IF(H11="serviço",OFFSET(E11,-1,0)+1,OFFSET(E11,-1,0))) -> 1 | H11: SERVIÇO | I11: =IF(H11="Unidade Construtiva",TEXT(A11,"00"),IF(H11="Célula Construtiva",TEXT(B11,"00"),IF(H11="Etapa",CONCATENATE(TEXT(B11,"00"),".",TEXT(C11,"000")),IF(H11="Subetapa",CONCATENATE(TEXT(B11,"00"),".",TEXT(C11,"000"),".",TEXT(D11,"000")),IF(H11="Serviço",CONCATENATE(TEXT(B11,"00"),".",TEXT(C11,"000"),".",TEXT(D11,"000"),".",TEXT(E11,"000")),""))))) -> 01.001.001.001 | J11: Rebaixamento de Lençol Freático | K11: vb | L11: 1 | M11: 18000 | N11: =IF(H11="Serviço",M11*L11,IF(H11="CÉLULA CONSTRUTIVA",SUMIFS($N$8:$N$335,$B$8:$B$335,B11,$H$8:$H$335,"Serviço"),IF(H11="ETAPA",SUMIFS($N$8:$N$335,$B$8:$B$335,B11,$C$8:$C$335,C11,$H$8:$H$335,"Serviço"),IF(H11="SUBETAPA",SUMIFS($N$8:$N$335,$B$8:$B$335,B11,$C$8:$C$335,C11,$D$8:$D$335,D11,$H$8:$H$335,"Serviço"),0)))) -> 18000 | P11: Lançado ERP
A12: =IF($H12="UNIDADE CONSTRUTIVA",OFFSET(A12,-1,0)+1,LARGE(A$3:A7,1)) -> 0 | B12: =IF(H12="UNIDADE CONSTRUTIVA",0,IF(H12="CÉLULA CONSTRUTIVA",OFFSET(B12,-1,0)+1,OFFSET(B12,-1,0))) -> 1 | C12: =IF(H12="CÉLULA CONSTRUTIVA",0,IF(H12="ETAPA",OFFSET(C12,-1,0)+1,OFFSET(C12,-1,0))) -> 1 | D12: =IF(H12="ETAPA",0,IF(H12="SUBETAPA",OFFSET(D12,-1,0)+1,OFFSET(D12,-1,0))) -> 2 | E12: =IF(H12="Subetapa",0,IF(H12="serviço",OFFSET(E12,-1,0)+1,OFFSET(E12,-1,0))) -> 0 | H12: SUBETAPA | I12: =IF(H12="Unidade Construtiva",TEXT(A12,"00"),IF(H12="Célula Construtiva",TEXT(B12,"00"),IF(H12="Etapa",CONCATENATE(TEXT(B12,"00"),".",TEXT(C12,"000")),IF(H12="Subetapa",CONCATENATE(TEXT(B12,"00"),".",TEXT(C12,"000"),".",TEXT(D12,"000")),IF(H12="Serviço",CONCATENATE(TEXT(B12,"00"),".",TEXT(C12,"000"),".",TEXT(D12,"000"),".",TEXT(E12,"000")),""))))) -> 01.001.002 | J12: Escavação de Subsolo | N12: =IF(H12="Serviço",M12*L12,IF(H12="CÉLULA CONSTRUTIVA",SUMIFS($N$8:$N$335,$B$8:$B$335,B12,$H$8:$H$335,"Serviço"),IF(H12="ETAPA",SUMIFS($N$8:$N$335,$B$8:$B$335,B12,$C$8:$C$335,C12,$H$8:$H$335,"Serviço"),IF(H12="SUBETAPA",SUMIFS($N$8:$N$335,$B$8:$B$335,B12,$C$8:$C$335,C12,$D$8:$D$335,D12,$H$8:$H$335,"Serviço"),0)))) -> 451264.88
A13: =IF($H13="UNIDADE CONSTRUTIVA",OFFSET(A13,-1,0)+1,LARGE(A$3:A8,1)) -> 0 | B13: =IF(H13="UNIDADE CONSTRUTIVA",0,IF(H13="CÉLULA CONSTRUTIVA",OFFSET(B13,-1,0)+1,OFFSET(B13,-1,0))) -> 1 | C13: =IF(H13="CÉLULA CONSTRUTIVA",0,IF(H13="ETAPA",OFFSET(C13,-1,0)+1,OFFSET(C13,-1,0))) -> 1 | D13: =IF(H13="ETAPA",0,IF(H13="SUBETAPA",OFFSET(D13,-1,0)+1,OFFSET(D13,-1,0))) -> 2 | E13: =IF(H13="Subetapa",0,IF(H13="serviço",OFFSET(E13,-1,0)+1,OFFSET(E13,-1,0))) -> 1 | H13: SERVIÇO | I13: =IF(H13="Unidade Construtiva",TEXT(A13,"00"),IF(H13="Célula Construtiva",TEXT(B13,"00"),IF(H13="Etapa",CONCATENATE(TEXT(B13,"00"),".",TEXT(C13,"000")),IF(H13="Subetapa",CONCATENATE(TEXT(B13,"00"),".",TEXT(C13,"000"),".",TEXT(D13,"000")),IF(H13="Serviço",CONCATENATE(TEXT(B13,"00"),".",TEXT(C13,"000"),".",TEXT(D13,"000"),".",TEXT(E13,"000")),""))))) -> 01.001.002.001 | J13: Escavação mecanizada para subsolo | K13: m3 | L13: 12411.025 | M13: 36.36 | N13: =IF(H13="Serviço",M13*L13,IF(H13="CÉLULA CONSTRUTIVA",SUMIFS($N$8:$N$335,$B$8:$B$335,B13,$H$8:$H$335,"Serviço"),IF(H13="ETAPA",SUMIFS($N$8:$N$335,$B$8:$B$335,B13,$C$8:$C$335,C13,$H$8:$H$335,"Serviço"),IF(H13="SUBETAPA",SUMIFS($N$8:$N$335,$B$8:$B$335,B13,$C$8:$C$335,C13,$D$8:$D$335,D13,$H$8:$H$335,"Serviço"),0)))) -> 451264.88 | O13: Considerado blocos, vigas de fundação, duto e cisterna | P13: Lançado ERP
A14: =IF($H14="UNIDADE CONSTRUTIVA",OFFSET(A14,-1,0)+1,LARGE(A$3:A9,1)) -> 0 | B14: =IF(H14="UNIDADE CONSTRUTIVA",0,IF(H14="CÉLULA CONSTRUTIVA",OFFSET(B14,-1,0)+1,OFFSET(B14,-1,0))) -> 1 | C14: =IF(H14="CÉLULA CONSTRUTIVA",0,IF(H14="ETAPA",OFFSET(C14,-1,0)+1,OFFSET(C14,-1,0))) -> 1 | D14: =IF(H14="ETAPA",0,IF(H14="SUBETAPA",OFFSET(D14,-1,0)+1,OFFSET(D14,-1,0))) -> 3 | E14: =IF(H14="Subetapa",0,IF(H14="serviço",OFFSET(E14,-1,0)+1,OFFSET(E14,-1,0))) -> 0 | H14: SUBETAPA | I14: =IF(H14="Unidade Construtiva",TEXT(A14,"00"),IF(H14="Célula Construtiva",TEXT(B14,"00"),IF(H14="Etapa",CONCATENATE(TEXT(B14,"00"),".",TEXT(C14,"000")),IF(H14="Subetapa",CONCATENATE(TEXT(B14,"00"),".",TEXT(C14,"000"),".",TEXT(D14,"000")),IF(H14="Serviço",CONCATENATE(TEXT(B14,"00"),".",TEXT(C14,"000"),".",TEXT(D14,"000"),".",TEXT(E14,"000")),""))))) -> 01.001.003 | J14: Escavação e Reaterro de Valas | N14: =IF(H14="Serviço",M14*L14,IF(H14="CÉLULA CONSTRUTIVA",SUMIFS($N$8:$N$335,$B$8:$B$335,B14,$H$8:$H$335,"Serviço"),IF(H14="ETAPA",SUMIFS($N$8:$N$335,$B$8:$B$335,B14,$C$8:$C$335,C14,$H$8:$H$335,"Serviço"),IF(H14="SUBETAPA",SUMIFS($N$8:$N$335,$B$8:$B$335,B14,$C$8:$C$335,C14,$D$8:$D$335,D14,$H$8:$H$335,"Serviço"),0)))) -> 22921.982
A15: =IF($H15="UNIDADE CONSTRUTIVA",OFFSET(A15,-1,0)+1,LARGE(A$3:A10,1)) -> 0 | B15: =IF(H15="UNIDADE CONSTRUTIVA",0,IF(H15="CÉLULA CONSTRUTIVA",OFFSET(B15,-1,0)+1,OFFSET(B15,-1,0))) -> 1 | C15: =IF(H15="CÉLULA CONSTRUTIVA",0,IF(H15="ETAPA",OFFSET(C15,-1,0)+1,OFFSET(C15,-1,0))) -> 1 | D15: =IF(H15="ETAPA",0,IF(H15="SUBETAPA",OFFSET(D15,-1,0)+1,OFFSET(D15,-1,0))) -> 3 | E15: =IF(H15="Subetapa",0,IF(H15="serviço",OFFSET(E15,-1,0)+1,OFFSET(E15,-1,0))) -> 1 | H15: SERVIÇO | I15: =IF(H15="Unidade Construtiva",TEXT(A15,"00"),IF(H15="Célula Construtiva",TEXT(B15,"00"),IF(H15="Etapa",CONCATENATE(TEXT(B15,"00"),".",TEXT(C15,"000")),IF(H15="Subetapa",CONCATENATE(TEXT(B15,"00"),".",TEXT(C15,"000"),".",TEXT(D15,"000")),IF(H15="Serviço",CONCATENATE(TEXT(B15,"00"),".",TEXT(C15,"000"),".",TEXT(D15,"000"),".",TEXT(E15,"000")),""))))) -> 01.001.003.001 | J15: Escavação mecanizada para blocos de fundação, vigas de fundação e poço de elevador, com retroescavadeira | K15: m3 | L15: 591.0012 | M15: 36.36 | N15: =IF(H15="Serviço",M15*L15,IF(H15="CÉLULA CONSTRUTIVA",SUMIFS($N$8:$N$335,$B$8:$B$335,B15,$H$8:$H$335,"Serviço"),IF(H15="ETAPA",SUMIFS($N$8:$N$335,$B$8:$B$335,B15,$C$8:$C$335,C15,$H$8:$H$335,"Serviço"),IF(H15="SUBETAPA",SUMIFS($N$8:$N$335,$B$8:$B$335,B15,$C$8:$C$335,C15,$D$8:$D$335,D15,$H$8:$H$335,"Serviço"),0)))) -> 21488.804 | O15: Considerado blocos, vigas de fundação, duto e cisterna | P15: Lançado ERP
A16: =IF($H16="UNIDADE CONSTRUTIVA",OFFSET(A16,-1,0)+1,LARGE(A$3:A11,1)) -> 0 | B16: =IF(H16="UNIDADE CONSTRUTIVA",0,IF(H16="CÉLULA CONSTRUTIVA",OFFSET(B16,-1,0)+1,OFFSET(B16,-1,0))) -> 1 | C16: =IF(H16="CÉLULA CONSTRUTIVA",0,IF(H16="ETAPA",OFFSET(C16,-1,0)+1,OFFSET(C16,-1,0))) -> 1 | D16: =IF(H16="ETAPA",0,IF(H16="SUBETAPA",OFFSET(D16,-1,0)+1,OFFSET(D16,-1,0))) -> 3 | E16: =IF(H16="Subetapa",0,IF(H16="serviço",OFFSET(E16,-1,0)+1,OFFSET(E16,-1,0))) -> 2 | H16: SERVIÇO | I16: =IF(H16="Unidade Construtiva",TEXT(A16,"00"),IF(H16="Célula Construtiva",TEXT(B16,"00"),IF(H16="Etapa",CONCATENATE(TEXT(B16,"00"),".",TEXT(C16,"000")),IF(H16="Subetapa",CONCATENATE(TEXT(B16,"00"),".",TEXT(C16,"000"),".",TEXT(D16,"000")),IF(H16="Serviço",CONCATENATE(TEXT(B16,"00"),".",TEXT(C16,"000"),".",TEXT(D16,"000"),".",TEXT(E16,"000")),""))))) -> 01.001.003.002 | J16: Reaterro mecanizado de valas para blocos e vigas de fundação, com retroescavadeira | K16: m3 | L16: 98.5002 | M16: 14.55 | N16: =IF(H16="Serviço",M16*L16,IF(H16="CÉLULA CONSTRUTIVA",SUMIFS($N$8:$N$335,$B$8:$B$335,B16,$H$8:$H$335,"Serviço"),IF(H16="ETAPA",SUMIFS($N$8:$N$335,$B$8:$B$335,B16,$C$8:$C$335,C16,$H$8:$H$335,"Serviço"),IF(H16="SUBETAPA",SUMIFS($N$8:$N$335,$B$8:$B$335,B16,$C$8:$C$335,C16,$D$8:$D$335,D16,$H$8:$H$335,"Serviço"),0)))) -> 1433.1779 | O16: Arbitrado tamanho de cisterna de 3,5x8m com espessura de 10cm | P16: Lançado ERP
A17: =IF($H17="UNIDADE CONSTRUTIVA",OFFSET(A17,-1,0)+1,LARGE(A$3:A14,1)) -> 0 | B17: =IF(H17="UNIDADE CONSTRUTIVA",0,IF(H17="CÉLULA CONSTRUTIVA",OFFSET(B17,-1,0)+1,OFFSET(B17,-1,0))) -> 1 | C17: =IF(H17="CÉLULA CONSTRUTIVA",0,IF(H17="ETAPA",OFFSET(C17,-1,0)+1,OFFSET(C17,-1,0))) -> 1 | D17: =IF(H17="ETAPA",0,IF(H17="SUBETAPA",OFFSET(D17,-1,0)+1,OFFSET(D17,-1,0))) -> 4 | E17: =IF(H17="Subetapa",0,IF(H17="serviço",OFFSET(E17,-1,0)+1,OFFSET(E17,-1,0))) -> 0 | H17: SUBETAPA | I17: =IF(H17="Unidade Construtiva",TEXT(A17,"00"),IF(H17="Célula Construtiva",TEXT(B17,"00"),IF(H17="Etapa",CONCATENATE(TEXT(B17,"00"),".",TEXT(C17,"000")),IF(H17="Subetapa",CONCATENATE(TEXT(B17,"00"),".",TEXT(C17,"000"),".",TEXT(D17,"000")),IF(H17="Serviço",CONCATENATE(TEXT(B17,"00"),".",TEXT(C17,"000"),".",TEXT(D17,"000"),".",TEXT(E17,"000")),""))))) -> 01.001.004 | J17: Lastro de brita | N17: =IF(H17="Serviço",M17*L17,IF(H17="CÉLULA CONSTRUTIVA",SUMIFS($N$8:$N$335,$B$8:$B$335,B17,$H$8:$H$335,"Serviço"),IF(H17="ETAPA",SUMIFS($N$8:$N$335,$B$8:$B$335,B17,$C$8:$C$335,C17,$H$8:$H$335,"Serviço"),IF(H17="SUBETAPA",SUMIFS($N$8:$N$335,$B$8:$B$335,B17,$C$8:$C$335,C17,$D$8:$D$335,D17,$H$8:$H$335,"Serviço"),0)))) -> 22649.83
A18: =IF($H18="UNIDADE CONSTRUTIVA",OFFSET(A18,-1,0)+1,LARGE(A$3:A15,1)) -> 0 | B18: =IF(H18="UNIDADE CONSTRUTIVA",0,IF(H18="CÉLULA CONSTRUTIVA",OFFSET(B18,-1,0)+1,OFFSET(B18,-1,0))) -> 1 | C18: =IF(H18="CÉLULA CONSTRUTIVA",0,IF(H18="ETAPA",OFFSET(C18,-1,0)+1,OFFSET(C18,-1,0))) -> 1 | D18: =IF(H18="ETAPA",0,IF(H18="SUBETAPA",OFFSET(D18,-1,0)+1,OFFSET(D18,-1,0))) -> 4 | E18: =IF(H18="Subetapa",0,IF(H18="serviço",OFFSET(E18,-1,0)+1,OFFSET(E18,-1,0))) -> 1 | H18: SERVIÇO | I18: =IF(H18="Unidade Construtiva",TEXT(A18,"00"),IF(H18="Célula Construtiva",TEXT(B18,"00"),IF(H18="Etapa",CONCATENATE(TEXT(B18,"00"),".",TEXT(C18,"000")),IF(H18="Subetapa",CONCATENATE(TEXT(B18,"00"),".",TEXT(C18,"000"),".",TEXT(D18,"000")),IF(H18="Serviço",CONCATENATE(TEXT(B18,"00"),".",TEXT(C18,"000"),".",TEXT(D18,"000"),".",TEXT(E18,"000")),""))))) -> 01.001.004.001 | J18: Lastro de Concreto Magro, Aplicado em Blocos de Fundação, e=10cm | K18: m3 | L18: 28.729225 | M18: 495.247 | N18: =IF(H18="Serviço",M18*L18,IF(H18="CÉLULA CONSTRUTIVA",SUMIFS($N$8:$N$335,$B$8:$B$335,B18,$H$8:$H$335,"Serviço"),IF(H18="ETAPA",SUMIFS($N$8:$N$335,$B$8:$B$335,B18,$C$8:$C$335,C18,$H$8:$H$335,"Serviço"),IF(H18="SUBETAPA",SUMIFS($N$8:$N$335,$B$8:$B$335,B18,$C$8:$C$335,C18,$D$8:$D$335,D18,$H$8:$H$335,"Serviço"),0)))) -> 14228.062 | O18: Considerado sem indicação em projeto, consideração de 13% de perda | P18: Lançado ERP
A19: =IF($H19="UNIDADE CONSTRUTIVA",OFFSET(A19,-1,0)+1,LARGE(A$3:A16,1)) -> 0 | B19: =IF(H19="UNIDADE CONSTRUTIVA",0,IF(H19="CÉLULA CONSTRUTIVA",OFFSET(B19,-1,0)+1,OFFSET(B19,-1,0))) -> 1 | C19: =IF(H19="CÉLULA CONSTRUTIVA",0,IF(H19="ETAPA",OFFSET(C19,-1,0)+1,OFFSET(C19,-1,0))) -> 1 | D19: =IF(H19="ETAPA",0,IF(H19="SUBETAPA",OFFSET(D19,-1,0)+1,OFFSET(D19,-1,0))) -> 4 | E19: =IF(H19="Subetapa",0,IF(H19="serviço",OFFSET(E19,-1,0)+1,OFFSET(E19,-1,0))) -> 2 | H19: SERVIÇO | I19: =IF(H19="Unidade Construtiva",TEXT(A19,"00"),IF(H19="Célula Construtiva",TEXT(B19,"00"),IF(H19="Etapa",CONCATENATE(TEXT(B19,"00"),".",TEXT(C19,"000")),IF(H19="Subetapa",CONCATENATE(TEXT(B19,"00"),".",TEXT(C19,"000"),".",TEXT(D19,"000")),IF(H19="Serviço",CONCATENATE(TEXT(B19,"00"),".",TEXT(C19,"000"),".",TEXT(D19,"000"),".",TEXT(E19,"000")),""))))) -> 01.001.004.002 | J19: Lastro de Brita, Aplicado em Blocos de Fundação, e= 5cm | K19: m3 | L19: 77.979325 | M19: 108 | N19: =IF(H19="Serviço",M19*L19,IF(H19="CÉLULA CONSTRUTIVA",SUMIFS($N$8:$N$335,$B$8:$B$335,B19,$H$8:$H$335,"Serviço"),IF(H19="ETAPA",SUMIFS($N$8:$N$335,$B$8:$B$335,B19,$C$8:$C$335,C19,$H$8:$H$335,"Serviço"),IF(H19="SUBETAPA",SUMIFS($N$8:$N$335,$B$8:$B$335,B19,$C$8:$C$335,C19,$D$8:$D$335,D19,$H$8:$H$335,"Serviço"),0)))) -> 8421.7671 | O19: Considerado sem indicação em projeto, consideração de 13% de perda | P19: Lançado ERP
A20: =IF($H20="UNIDADE CONSTRUTIVA",OFFSET(A20,-1,0)+1,LARGE(A$3:A17,1)) -> 0 | B20: =IF(H20="UNIDADE CONSTRUTIVA",0,IF(H20="CÉLULA CONSTRUTIVA",OFFSET(B20,-1,0)+1,OFFSET(B20,-1,0))) -> 1 | C20: =IF(H20="CÉLULA CONSTRUTIVA",0,IF(H20="ETAPA",OFFSET(C20,-1,0)+1,OFFSET(C20,-1,0))) -> 1 | D20: =IF(H20="ETAPA",0,IF(H20="SUBETAPA",OFFSET(D20,-1,0)+1,OFFSET(D20,-1,0))) -> 5 | E20: =IF(H20="Subetapa",0,IF(H20="serviço",OFFSET(E20,-1,0)+1,OFFSET(E20,-1,0))) -> 0 | H20: SUBETAPA | I20: =IF(H20="Unidade Construtiva",TEXT(A20,"00"),IF(H20="Célula Construtiva",TEXT(B20,"00"),IF(H20="Etapa",CONCATENATE(TEXT(B20,"00"),".",TEXT(C20,"000")),IF(H20="Subetapa",CONCATENATE(TEXT(B20,"00"),".",TEXT(C20,"000"),".",TEXT(D20,"000")),IF(H20="Serviço",CONCATENATE(TEXT(B20,"00"),".",TEXT(C20,"000"),".",TEXT(D20,"000"),".",TEXT(E20,"000")),""))))) -> 01.001.005 | J20: Movimentação de bota - fora | N20: =IF(H20="Serviço",M20*L20,IF(H20="CÉLULA CONSTRUTIVA",SUMIFS($N$8:$N$335,$B$8:$B$335,B20,$H$8:$H$335,"Serviço"),IF(H20="ETAPA",SUMIFS($N$8:$N$335,$B$8:$B$335,B20,$C$8:$C$335,C20,$H$8:$H$335,"Serviço"),IF(H20="SUBETAPA",SUMIFS($N$8:$N$335,$B$8:$B$335,B20,$C$8:$C$335,C20,$D$8:$D$335,D20,$H$8:$H$335,"Serviço"),0)))) -> 885628.18
A21: =IF($H21="UNIDADE CONSTRUTIVA",OFFSET(A21,-1,0)+1,LARGE(A$3:A18,1)) -> 0 | B21: =IF(H21="UNIDADE CONSTRUTIVA",0,IF(H21="CÉLULA CONSTRUTIVA",OFFSET(B21,-1,0)+1,OFFSET(B21,-1,0))) -> 1 | C21: =IF(H21="CÉLULA CONSTRUTIVA",0,IF(H21="ETAPA",OFFSET(C21,-1,0)+1,OFFSET(C21,-1,0))) -> 1 | D21: =IF(H21="ETAPA",0,IF(H21="SUBETAPA",OFFSET(D21,-1,0)+1,OFFSET(D21,-1,0))) -> 5 | E21: =IF(H21="Subetapa",0,IF(H21="serviço",OFFSET(E21,-1,0)+1,OFFSET(E21,-1,0))) -> 1 | H21: SERVIÇO | I21: =IF(H21="Unidade Construtiva",TEXT(A21,"00"),IF(H21="Célula Construtiva",TEXT(B21,"00"),IF(H21="Etapa",CONCATENATE(TEXT(B21,"00"),".",TEXT(C21,"000")),IF(H21="Subetapa",CONCATENATE(TEXT(B21,"00"),".",TEXT(C21,"000"),".",TEXT(D21,"000")),IF(H21="Serviço",CONCATENATE(TEXT(B21,"00"),".",TEXT(C21,"000"),".",TEXT(D21,"000"),".",TEXT(E21,"000")),""))))) -> 01.001.005.001 | J21: Movimentação de terra para bota-fora - Blocos e subsolo | K21: m3 | L21: 16774.584 | M21: 45.45 | N21: =IF(H21="Serviço",M21*L21,IF(H21="CÉLULA CONSTRUTIVA",SUMIFS($N$8:$N$335,$B$8:$B$335,B21,$H$8:$H$335,"Serviço"),IF(H21="ETAPA",SUMIFS($N$8:$N$335,$B$8:$B$335,B21,$C$8:$C$335,C21,$H$8:$H$335,"Serviço"),IF(H21="SUBETAPA",SUMIFS($N$8:$N$335,$B$8:$B$335,B21,$C$8:$C$335,C21,$D$8:$D$335,D21,$H$8:$H$335,"Serviço"),0)))) -> 762404.85 | O21: Considerado empolamento 30% da escavação | P21: Lançado ERP
A22: =IF($H22="UNIDADE CONSTRUTIVA",OFFSET(A22,-1,0)+1,LARGE(A$3:A19,1)) -> 0 | B22: =IF(H22="UNIDADE CONSTRUTIVA",0,IF(H22="CÉLULA CONSTRUTIVA",OFFSET(B22,-1,0)+1,OFFSET(B22,-1,0))) -> 1 | C22: =IF(H22="CÉLULA CONSTRUTIVA",0,IF(H22="ETAPA",OFFSET(C22,-1,0)+1,OFFSET(C22,-1,0))) -> 1 | D22: =IF(H22="ETAPA",0,IF(H22="SUBETAPA",OFFSET(D22,-1,0)+1,OFFSET(D22,-1,0))) -> 5 | E22: =IF(H22="Subetapa",0,IF(H22="serviço",OFFSET(E22,-1,0)+1,OFFSET(E22,-1,0))) -> 2 | H22: SERVIÇO | I22: =IF(H22="Unidade Construtiva",TEXT(A22,"00"),IF(H22="Célula Construtiva",TEXT(B22,"00"),IF(H22="Etapa",CONCATENATE(TEXT(B22,"00"),".",TEXT(C22,"000")),IF(H22="Subetapa",CONCATENATE(TEXT(B22,"00"),".",TEXT(C22,"000"),".",TEXT(D22,"000")),IF(H22="Serviço",CONCATENATE(TEXT(B22,"00"),".",TEXT(C22,"000"),".",TEXT(D22,"000"),".",TEXT(E22,"000")),""))))) -> 01.001.005.002 | J22: Movimentação de terra para bota-fora - Estacas | K22: m3 | L22: =Estacas!J11 -> 1807.3237 | M22: 68.18 | N22: =IF(H22="Serviço",M22*L22,IF(H22="CÉLULA CONSTRUTIVA",SUMIFS($N$8:$N$335,$B$8:$B$335,B22,$H$8:$H$335,"Serviço"),IF(H22="ETAPA",SUMIFS($N$8:$N$335,$B$8:$B$335,B22,$C$8:$C$335,C22,$H$8:$H$335,"Serviço"),IF(H22="SUBETAPA",SUMIFS($N$8:$N$335,$B$8:$B$335,B22,$C$8:$C$335,C22,$D$8:$D$335,D22,$H$8:$H$335,"Serviço"),0)))) -> 123223.33 | O22: Considerado empolamento 30% da escavação | P22: Lançado ERP
A23: =IF($H23="UNIDADE CONSTRUTIVA",OFFSET(A23,-1,0)+1,LARGE(A$3:A20,1)) -> 0 | B23: =IF(H23="UNIDADE CONSTRUTIVA",0,IF(H23="CÉLULA CONSTRUTIVA",OFFSET(B23,-1,0)+1,OFFSET(B23,-1,0))) -> 2 | C23: =IF(H23="CÉLULA CONSTRUTIVA",0,IF(H23="ETAPA",OFFSET(C23,-1,0)+1,OFFSET(C23,-1,0))) -> 0 | D23: =IF(H23="ETAPA",0,IF(H23="SUBETAPA",OFFSET(D23,-1,0)+1,OFFSET(D23,-1,0))) -> 5 | E23: =IF(H23="Subetapa",0,IF(H23="serviço",OFFSET(E23,-1,0)+1,OFFSET(E23,-1,0))) -> 2 | H23: CÉLULA CONSTRUTIVA | I23: =IF(H23="Unidade Construtiva",TEXT(A23,"00"),IF(H23="Célula Construtiva",TEXT(B23,"00"),IF(H23="Etapa",CONCATENATE(TEXT(B23,"00"),".",TEXT(C23,"000")),IF(H23="Subetapa",CONCATENATE(TEXT(B23,"00"),".",TEXT(C23,"000"),".",TEXT(D23,"000")),IF(H23="Serviço",CONCATENATE(TEXT(B23,"00"),".",TEXT(C23,"000"),".",TEXT(D23,"000"),".",TEXT(E23,"000")),""))))) -> 02 | J23: INFRAESTRUTURA | N23: =IF(H23="Serviço",M23*L23,IF(H23="CÉLULA CONSTRUTIVA",SUMIFS($N$8:$N$335,$B$8:$B$335,B23,$H$8:$H$335,"Serviço"),IF(H23="ETAPA",SUMIFS($N$8:$N$335,$B$8:$B$335,B23,$C$8:$C$335,C23,$H$8:$H$335,"Serviço"),IF(H23="SUBETAPA",SUMIFS($N$8:$N$335,$B$8:$B$335,B23,$C$8:$C$335,C23,$D$8:$D$335,D23,$H$8:$H$335,"Serviço"),0)))) -> 2627275.7
A24: =IF($H24="UNIDADE CONSTRUTIVA",OFFSET(A24,-1,0)+1,LARGE(A$3:A21,1)) -> 0 | B24: =IF(H24="UNIDADE CONSTRUTIVA",0,IF(H24="CÉLULA CONSTRUTIVA",OFFSET(B24,-1,0)+1,OFFSET(B24,-1,0))) -> 2 | C24: =IF(H24="CÉLULA CONSTRUTIVA",0,IF(H24="ETAPA",OFFSET(C24,-1,0)+1,OFFSET(C24,-1,0))) -> 1 | D24: =IF(H24="ETAPA",0,IF(H24="SUBETAPA",OFFSET(D24,-1,0)+1,OFFSET(D24,-1,0))) -> 0 | E24: =IF(H24="Subetapa",0,IF(H24="serviço",OFFSET(E24,-1,0)+1,OFFSET(E24,-1,0))) -> 2 | H24: ETAPA | I24: =IF(H24="Unidade Construtiva",TEXT(A24,"00"),IF(H24="Célula Construtiva",TEXT(B24,"00"),IF(H24="Etapa",CONCATENATE(TEXT(B24,"00"),".",TEXT(C24,"000")),IF(H24="Subetapa",CONCATENATE(TEXT(B24,"00"),".",TEXT(C24,"000"),".",TEXT(D24,"000")),IF(H24="Serviço",CONCATENATE(TEXT(B24,"00"),".",TEXT(C24,"000"),".",TEXT(D24,"000"),".",TEXT(E24,"000")),""))))) -> 02.001 | J24: FUNDAÇÃO PROFUNDA | N24: =IF(H24="Serviço",M24*L24,IF(H24="CÉLULA CONSTRUTIVA",SUMIFS($N$8:$N$335,$B$8:$B$335,B24,$H$8:$H$335,"Serviço"),IF(H24="ETAPA",SUMIFS($N$8:$N$335,$B$8:$B$335,B24,$C$8:$C$335,C24,$H$8:$H$335,"Serviço"),IF(H24="SUBETAPA",SUMIFS($N$8:$N$335,$B$8:$B$335,B24,$C$8:$C$335,C24,$D$8:$D$335,D24,$H$8:$H$335,"Serviço"),0)))) -> 1788264.7
A25: =IF($H25="UNIDADE CONSTRUTIVA",OFFSET(A25,-1,0)+1,LARGE(A$3:A22,1)) -> 0 | B25: =IF(H25="UNIDADE CONSTRUTIVA",0,IF(H25="CÉLULA CONSTRUTIVA",OFFSET(B25,-1,0)+1,OFFSET(B25,-1,0))) -> 2 | C25: =IF(H25="CÉLULA CONSTRUTIVA",0,IF(H25="ETAPA",OFFSET(C25,-1,0)+1,OFFSET(C25,-1,0))) -> 1 | D25: =IF(H25="ETAPA",0,IF(H25="SUBETAPA",OFFSET(D25,-1,0)+1,OFFSET(D25,-1,0))) -> 1 | E25: =IF(H25="Subetapa",0,IF(H25="serviço",OFFSET(E25,-1,0)+1,OFFSET(E25,-1,0))) -> 0 | H25: SUBETAPA | I25: =IF(H25="Unidade Construtiva",TEXT(A25,"00"),IF(H25="Célula Construtiva",TEXT(B25,"00"),IF(H25="Etapa",CONCATENATE(TEXT(B25,"00"),".",TEXT(C25,"000")),IF(H25="Subetapa",CONCATENATE(TEXT(B25,"00"),".",TEXT(C25,"000"),".",TEXT(D25,"000")),IF(H25="Serviço",CONCATENATE(TEXT(B25,"00"),".",TEXT(C25,"000"),".",TEXT(D25,"000"),".",TEXT(E25,"000")),""))))) -> 02.001.001 | J25: Perfuração | N25: =IF(H25="Serviço",M25*L25,IF(H25="CÉLULA CONSTRUTIVA",SUMIFS($N$8:$N$335,$B$8:$B$335,B25,$H$8:$H$335,"Serviço"),IF(H25="ETAPA",SUMIFS($N$8:$N$335,$B$8:$B$335,B25,$C$8:$C$335,C25,$H$8:$H$335,"Serviço"),IF(H25="SUBETAPA",SUMIFS($N$8:$N$335,$B$8:$B$335,B25,$C$8:$C$335,C25,$D$8:$D$335,D25,$H$8:$H$335,"Serviço"),0)))) -> 473420
A26: =IF($H26="UNIDADE CONSTRUTIVA",OFFSET(A26,-1,0)+1,LARGE(A$3:A23,1)) -> 0 | B26: =IF(H26="UNIDADE CONSTRUTIVA",0,IF(H26="CÉLULA CONSTRUTIVA",OFFSET(B26,-1,0)+1,OFFSET(B26,-1,0))) -> 2 | C26: =IF(H26="CÉLULA CONSTRUTIVA",0,IF(H26="ETAPA",OFFSET(C26,-1,0)+1,OFFSET(C26,-1,0))) -> 1 | D26: =IF(H26="ETAPA",0,IF(H26="SUBETAPA",OFFSET(D26,-1,0)+1,OFFSET(D26,-1,0))) -> 1 | E26: =IF(H26="Subetapa",0,IF(H26="serviço",OFFSET(E26,-1,0)+1,OFFSET(E26,-1,0))) -> 1 | H26: SERVIÇO | I26: =IF(H26="Unidade Construtiva",TEXT(A26,"00"),IF(H26="Célula Construtiva",TEXT(B26,"00"),IF(H26="Etapa",CONCATENATE(TEXT(B26,"00"),".",TEXT(C26,"000")),IF(H26="Subetapa",CONCATENATE(TEXT(B26,"00"),".",TEXT(C26,"000"),".",TEXT(D26,"000")),IF(H26="Serviço",CONCATENATE(TEXT(B26,"00"),".",TEXT(C26,"000"),".",TEXT(D26,"000"),".",TEXT(E26,"000")),""))))) -> 02.001.001.001 | J26: Perfuração de estaca hélice contínua Ø 60cm | K26: m | L26: =Estacas!H15 -> 1144 | M26: 90 | N26: =IF(H26="Serviço",M26*L26,IF(H26="CÉLULA CONSTRUTIVA",SUMIFS($N$8:$N$335,$B$8:$B$335,B26,$H$8:$H$335,"Serviço"),IF(H26="ETAPA",SUMIFS($N$8:$N$335,$B$8:$B$335,B26,$C$8:$C$335,C26,$H$8:$H$335,"Serviço"),IF(H26="SUBETAPA",SUMIFS($N$8:$N$335,$B$8:$B$335,B26,$C$8:$C$335,C26,$D$8:$D$335,D26,$H$8:$H$335,"Serviço"),0)))) -> 102960 | P26: Lançado ERP
A27: =IF($H27="UNIDADE CONSTRUTIVA",OFFSET(A27,-1,0)+1,LARGE(A$3:A24,1)) -> 0 | B27: =IF(H27="UNIDADE CONSTRUTIVA",0,IF(H27="CÉLULA CONSTRUTIVA",OFFSET(B27,-1,0)+1,OFFSET(B27,-1,0))) -> 2 | C27: =IF(H27="CÉLULA CONSTRUTIVA",0,IF(H27="ETAPA",OFFSET(C27,-1,0)+1,OFFSET(C27,-1,0))) -> 1 | D27: =IF(H27="ETAPA",0,IF(H27="SUBETAPA",OFFSET(D27,-1,0)+1,OFFSET(D27,-1,0))) -> 1 | E27: =IF(H27="Subetapa",0,IF(H27="serviço",OFFSET(E27,-1,0)+1,OFFSET(E27,-1,0))) -> 2 | H27: SERVIÇO | I27: =IF(H27="Unidade Construtiva",TEXT(A27,"00"),IF(H27="Célula Construtiva",TEXT(B27,"00"),IF(H27="Etapa",CONCATENATE(TEXT(B27,"00"),".",TEXT(C27,"000")),IF(H27="Subetapa",CONCATENATE(TEXT(B27,"00"),".",TEXT(C27,"000"),".",TEXT(D27,"000")),IF(H27="Serviço",CONCATENATE(TEXT(B27,"00"),".",TEXT(C27,"000"),".",TEXT(D27,"000"),".",TEXT(E27,"000")),""))))) -> 02.001.001.002 | J27: Perfuração de estaca hélice contínua Ø 70cm | K27: m | L27: =Estacas!H16 -> 2772 | M27: 105 | N27: =IF(H27="Serviço",M27*L27,IF(H27="CÉLULA CONSTRUTIVA",SUMIFS($N$8:$N$335,$B$8:$B$335,B27,$H$8:$H$335,"Serviço"),IF(H27="ETAPA",SUMIFS($N$8:$N$335,$B$8:$B$335,B27,$C$8:$C$335,C27,$H$8:$H$335,"Serviço"),IF(H27="SUBETAPA",SUMIFS($N$8:$N$335,$B$8:$B$335,B27,$C$8:$C$335,C27,$D$8:$D$335,D27,$H$8:$H$335,"Serviço"),0)))) -> 291060 | P27: Lançado ERP
A28: =IF($H28="UNIDADE CONSTRUTIVA",OFFSET(A28,-1,0)+1,LARGE(A$3:A25,1)) -> 0 | B28: =IF(H28="UNIDADE CONSTRUTIVA",0,IF(H28="CÉLULA CONSTRUTIVA",OFFSET(B28,-1,0)+1,OFFSET(B28,-1,0))) -> 2 | C28: =IF(H28="CÉLULA CONSTRUTIVA",0,IF(H28="ETAPA",OFFSET(C28,-1,0)+1,OFFSET(C28,-1,0))) -> 1 | D28: =IF(H28="ETAPA",0,IF(H28="SUBETAPA",OFFSET(D28,-1,0)+1,OFFSET(D28,-1,0))) -> 1 | E28: =IF(H28="Subetapa",0,IF(H28="serviço",OFFSET(E28,-1,0)+1,OFFSET(E28,-1,0))) -> 3 | H28: SERVIÇO | I28: =IF(H28="Unidade Construtiva",TEXT(A28,"00"),IF(H28="Célula Construtiva",TEXT(B28,"00"),IF(H28="Etapa",CONCATENATE(TEXT(B28,"00"),".",TEXT(C28,"000")),IF(H28="Subetapa",CONCATENATE(TEXT(B28,"00"),".",TEXT(C28,"000"),".",TEXT(D28,"000")),IF(H28="Serviço",CONCATENATE(TEXT(B28,"00"),".",TEXT(C28,"000"),".",TEXT(D28,"000"),".",TEXT(E28,"000")),""))))) -> 02.001.001.003 | J28: Mobilização e desmobilização de equipamentos - Para execução de estaca hélice | K28: vb | L28: 1 | M28: 26000 | N28: =IF(H28="Serviço",M28*L28,IF(H28="CÉLULA CONSTRUTIVA",SUMIFS($N$8:$N$335,$B$8:$B$335,B28,$H$8:$H$335,"Serviço"),IF(H28="ETAPA",SUMIFS($N$8:$N$335,$B$8:$B$335,B28,$C$8:$C$335,C28,$H$8:$H$335,"Serviço"),IF(H28="SUBETAPA",SUMIFS($N$8:$N$335,$B$8:$B$335,B28,$C$8:$C$335,C28,$D$8:$D$335,D28,$H$8:$H$335,"Serviço"),0)))) -> 26000 | P28: Lançado ERP
A29: =IF($H29="UNIDADE CONSTRUTIVA",OFFSET(A29,-1,0)+1,LARGE(A$3:A26,1)) -> 0 | B29: =IF(H29="UNIDADE CONSTRUTIVA",0,IF(H29="CÉLULA CONSTRUTIVA",OFFSET(B29,-1,0)+1,OFFSET(B29,-1,0))) -> 2 | C29: =IF(H29="CÉLULA CONSTRUTIVA",0,IF(H29="ETAPA",OFFSET(C29,-1,0)+1,OFFSET(C29,-1,0))) -> 1 | D29: =IF(H29="ETAPA",0,IF(H29="SUBETAPA",OFFSET(D29,-1,0)+1,OFFSET(D29,-1,0))) -> 1 | E29: =IF(H29="Subetapa",0,IF(H29="serviço",OFFSET(E29,-1,0)+1,OFFSET(E29,-1,0))) -> 4 | H29: SERVIÇO | I29: =IF(H29="Unidade Construtiva",TEXT(A29,"00"),IF(H29="Célula Construtiva",TEXT(B29,"00"),IF(H29="Etapa",CONCATENATE(TEXT(B29,"00"),".",TEXT(C29,"000")),IF(H29="Subetapa",CONCATENATE(TEXT(B29,"00"),".",TEXT(C29,"000"),".",TEXT(D29,"000")),IF(H29="Serviço",CONCATENATE(TEXT(B29,"00"),".",TEXT(C29,"000"),".",TEXT(D29,"000"),".",TEXT(E29,"000")),""))))) -> 02.001.001.004 | J29: Corte e Preparo de Cabeça de Estaca | K29: un | L29: =Estacas!C11 -> 178 | M29: 300 | N29: =IF(H29="Serviço",M29*L29,IF(H29="CÉLULA CONSTRUTIVA",SUMIFS($N$8:$N$335,$B$8:$B$335,B29,$H$8:$H$335,"Serviço"),IF(H29="ETAPA",SUMIFS($N$8:$N$335,$B$8:$B$335,B29,$C$8:$C$335,C29,$H$8:$H$335,"Serviço"),IF(H29="SUBETAPA",SUMIFS($N$8:$N$335,$B$8:$B$335,B29,$C$8:$C$335,C29,$D$8:$D$335,D29,$H$8:$H$335,"Serviço"),0)))) -> 53400 | P29: Lançado ERP
A30: =IF($H30="UNIDADE CONSTRUTIVA",OFFSET(A30,-1,0)+1,LARGE(A$3:A27,1)) -> 0 | B30: =IF(H30="UNIDADE CONSTRUTIVA",0,IF(H30="CÉLULA CONSTRUTIVA",OFFSET(B30,-1,0)+1,OFFSET(B30,-1,0))) -> 2 | C30: =IF(H30="CÉLULA CONSTRUTIVA",0,IF(H30="ETAPA",OFFSET(C30,-1,0)+1,OFFSET(C30,-1,0))) -> 1 | D30: =IF(H30="ETAPA",0,IF(H30="SUBETAPA",OFFSET(D30,-1,0)+1,OFFSET(D30,-1,0))) -> 2 | E30: =IF(H30="Subetapa",0,IF(H30="serviço",OFFSET(E30,-1,0)+1,OFFSET(E30,-1,0))) -> 0 | H30: SUBETAPA | I30: =IF(H30="Unidade Construtiva",TEXT(A30,"00"),IF(H30="Célula Construtiva",TEXT(B30,"00"),IF(H30="Etapa",CONCATENATE(TEXT(B30,"00"),".",TEXT(C30,"000")),IF(H30="Subetapa",CONCATENATE(TEXT(B30,"00"),".",TEXT(C30,"000"),".",TEXT(D30,"000")),IF(H30="Serviço",CONCATENATE(TEXT(B30,"00"),".",TEXT(C30,"000"),".",TEXT(D30,"000"),".",TEXT(E30,"000")),""))))) -> 02.001.002 | J30: Armadura | N30: =IF(H30="Serviço",M30*L30,IF(H30="CÉLULA CONSTRUTIVA",SUMIFS($N$8:$N$335,$B$8:$B$335,B30,$H$8:$H$335,"Serviço"),IF(H30="ETAPA",SUMIFS($N$8:$N$335,$B$8:$B$335,B30,$C$8:$C$335,C30,$H$8:$H$335,"Serviço"),IF(H30="SUBETAPA",SUMIFS($N$8:$N$335,$B$8:$B$335,B30,$C$8:$C$335,C30,$D$8:$D$335,D30,$H$8:$H$335,"Serviço"),0)))) -> 166137.54
A31: =IF($H31="UNIDADE CONSTRUTIVA",OFFSET(A31,-1,0)+1,LARGE(A$3:A28,1)) -> 0 | B31: =IF(H31="UNIDADE CONSTRUTIVA",0,IF(H31="CÉLULA CONSTRUTIVA",OFFSET(B31,-1,0)+1,OFFSET(B31,-1,0))) -> 2 | C31: =IF(H31="CÉLULA CONSTRUTIVA",0,IF(H31="ETAPA",OFFSET(C31,-1,0)+1,OFFSET(C31,-1,0))) -> 1 | D31: =IF(H31="ETAPA",0,IF(H31="SUBETAPA",OFFSET(D31,-1,0)+1,OFFSET(D31,-1,0))) -> 2 | E31: =IF(H31="Subetapa",0,IF(H31="serviço",OFFSET(E31,-1,0)+1,OFFSET(E31,-1,0))) -> 1 | H31: SERVIÇO | I31: =IF(H31="Unidade Construtiva",TEXT(A31,"00"),IF(H31="Célula Construtiva",TEXT(B31,"00"),IF(H31="Etapa",CONCATENATE(TEXT(B31,"00"),".",TEXT(C31,"000")),IF(H31="Subetapa",CONCATENATE(TEXT(B31,"00"),".",TEXT(C31,"000"),".",TEXT(D31,"000")),IF(H31="Serviço",CONCATENATE(TEXT(B31,"00"),".",TEXT(C31,"000"),".",TEXT(D31,"000"),".",TEXT(E31,"000")),""))))) -> 02.001.002.001 | J31: Armação aço CA-50 ø 6,3mm para estaca (corte e dobra em obra) | K31: kg | L31: =Estacas!M11 -> 7507.3446 | M31: 7.33 | N31: =IF(H31="Serviço",M31*L31,IF(H31="CÉLULA CONSTRUTIVA",SUMIFS($N$8:$N$335,$B$8:$B$335,B31,$H$8:$H$335,"Serviço"),IF(H31="ETAPA",SUMIFS($N$8:$N$335,$B$8:$B$335,B31,$C$8:$C$335,C31,$H$8:$H$335,"Serviço"),IF(H31="SUBETAPA",SUMIFS($N$8:$N$335,$B$8:$B$335,B31,$C$8:$C$335,C31,$D$8:$D$335,D31,$H$8:$H$335,"Serviço"),0)))) -> 55028.836 | P31: Lançado ERP
A32: =IF($H32="UNIDADE CONSTRUTIVA",OFFSET(A32,-1,0)+1,LARGE(A$3:A29,1)) -> 0 | B32: =IF(H32="UNIDADE CONSTRUTIVA",0,IF(H32="CÉLULA CONSTRUTIVA",OFFSET(B32,-1,0)+1,OFFSET(B32,-1,0))) -> 2 | C32: =IF(H32="CÉLULA CONSTRUTIVA",0,IF(H32="ETAPA",OFFSET(C32,-1,0)+1,OFFSET(C32,-1,0))) -> 1 | D32: =IF(H32="ETAPA",0,IF(H32="SUBETAPA",OFFSET(D32,-1,0)+1,OFFSET(D32,-1,0))) -> 2 | E32: =IF(H32="Subetapa",0,IF(H32="serviço",OFFSET(E32,-1,0)+1,OFFSET(E32,-1,0))) -> 2 | H32: SERVIÇO | I32: =IF(H32="Unidade Construtiva",TEXT(A32,"00"),IF(H32="Célula Construtiva",TEXT(B32,"00"),IF(H32="Etapa",CONCATENATE(TEXT(B32,"00"),".",TEXT(C32,"000")),IF(H32="Subetapa",CONCATENATE(TEXT(B32,"00"),".",TEXT(C32,"000"),".",TEXT(D32,"000")),IF(H32="Serviço",CONCATENATE(TEXT(B32,"00"),".",TEXT(C32,"000"),".",TEXT(D32,"000"),".",TEXT(E32,"000")),""))))) -> 02.001.002.002 | J32: Armação aço CA-50 ø 16,0mm para estaca (corte e dobra em obra) | K32: kg | L32: =Estacas!N11 -> 16682.988 | M32: 6.66 | N32: =IF(H32="Serviço",M32*L32,IF(H32="CÉLULA CONSTRUTIVA",SUMIFS($N$8:$N$335,$B$8:$B$335,B32,$H$8:$H$335,"Serviço"),IF(H32="ETAPA",SUMIFS($N$8:$N$335,$B$8:$B$335,B32,$C$8:$C$335,C32,$H$8:$H$335,"Serviço"),IF(H32="SUBETAPA",SUMIFS($N$8:$N$335,$B$8:$B$335,B32,$C$8:$C$335,C32,$D$8:$D$335,D32,$H$8:$H$335,"Serviço"),0)))) -> 111108.7 | P32: Lançado ERP
A33: =IF($H33="UNIDADE CONSTRUTIVA",OFFSET(A33,-1,0)+1,LARGE(A$3:A31,1)) -> 0 | B33: =IF(H33="UNIDADE CONSTRUTIVA",0,IF(H33="CÉLULA CONSTRUTIVA",OFFSET(B33,-1,0)+1,OFFSET(B33,-1,0))) -> 2 | C33: =IF(H33="CÉLULA CONSTRUTIVA",0,IF(H33="ETAPA",OFFSET(C33,-1,0)+1,OFFSET(C33,-1,0))) -> 1 | D33: =IF(H33="ETAPA",0,IF(H33="SUBETAPA",OFFSET(D33,-1,0)+1,OFFSET(D33,-1,0))) -> 3 | E33: =IF(H33="Subetapa",0,IF(H33="serviço",OFFSET(E33,-1,0)+1,OFFSET(E33,-1,0))) -> 0 | H33: SUBETAPA | I33: =IF(H33="Unidade Construtiva",TEXT(A33,"00"),IF(H33="Célula Construtiva",TEXT(B33,"00"),IF(H33="Etapa",CONCATENATE(TEXT(B33,"00"),".",TEXT(C33,"000")),IF(H33="Subetapa",CONCATENATE(TEXT(B33,"00"),".",TEXT(C33,"000"),".",TEXT(D33,"000")),IF(H33="Serviço",CONCATENATE(TEXT(B33,"00"),".",TEXT(C33,"000"),".",TEXT(D33,"000"),".",TEXT(E33,"000")),""))))) -> 02.001.003 | J33: Lançamento de Concreto para Estacas (Edifícios) | N33: =IF(H33="Serviço",M33*L33,IF(H33="CÉLULA CONSTRUTIVA",SUMIFS($N$8:$N$335,$B$8:$B$335,B33,$H$8:$H$335,"Serviço"),IF(H33="ETAPA",SUMIFS($N$8:$N$335,$B$8:$B$335,B33,$C$8:$C$335,C33,$H$8:$H$335,"Serviço"),IF(H33="SUBETAPA",SUMIFS($N$8:$N$335,$B$8:$B$335,B33,$C$8:$C$335,C33,$D$8:$D$335,D33,$H$8:$H$335,"Serviço"),0)))) -> 1148707.1
A34: =IF($H34="UNIDADE CONSTRUTIVA",OFFSET(A34,-1,0)+1,LARGE(A$3:A32,1)) -> 0 | B34: =IF(H34="UNIDADE CONSTRUTIVA",0,IF(H34="CÉLULA CONSTRUTIVA",OFFSET(B34,-1,0)+1,OFFSET(B34,-1,0))) -> 2 | C34: =IF(H34="CÉLULA CONSTRUTIVA",0,IF(H34="ETAPA",OFFSET(C34,-1,0)+1,OFFSET(C34,-1,0))) -> 1 | D34: =IF(H34="ETAPA",0,IF(H34="SUBETAPA",OFFSET(D34,-1,0)+1,OFFSET(D34,-1,0))) -> 3 | E34: =IF(H34="Subetapa",0,IF(H34="serviço",OFFSET(E34,-1,0)+1,OFFSET(E34,-1,0))) -> 1 | H34: SERVIÇO | I34: =IF(H34="Unidade Construtiva",TEXT(A34,"00"),IF(H34="Célula Construtiva",TEXT(B34,"00"),IF(H34="Etapa",CONCATENATE(TEXT(B34,"00"),".",TEXT(C34,"000")),IF(H34="Subetapa",CONCATENATE(TEXT(B34,"00"),".",TEXT(C34,"000"),".",TEXT(D34,"000")),IF(H34="Serviço",CONCATENATE(TEXT(B34,"00"),".",TEXT(C34,"000"),".",TEXT(D34,"000"),".",TEXT(E34,"000")),""))))) -> 02.001.003.001 | J34: Concreto Usinado bombeável para estacas 40MPa - incluindo serviço de bombeamento | K34: m3 | L34: =Estacas!K16 -> 1390.249 | M34: 826.26 | N34: =IF(H34="Serviço",M34*L34,IF(H34="CÉLULA CONSTRUTIVA",SUMIFS($N$8:$N$335,$B$8:$B$335,B34,$H$8:$H$335,"Serviço"),IF(H34="ETAPA",SUMIFS($N$8:$N$335,$B$8:$B$335,B34,$C$8:$C$335,C34,$H$8:$H$335,"Serviço"),IF(H34="SUBETAPA",SUMIFS($N$8:$N$335,$B$8:$B$335,B34,$C$8:$C$335,C34,$D$8:$D$335,D34,$H$8:$H$335,"Serviço"),0)))) -> 1148707.1 | P34: Lançado ERP
A35: =IF($H35="UNIDADE CONSTRUTIVA",OFFSET(A35,-1,0)+1,LARGE(A$3:A32,1)) -> 0 | B35: =IF(H35="UNIDADE CONSTRUTIVA",0,IF(H35="CÉLULA CONSTRUTIVA",OFFSET(B35,-1,0)+1,OFFSET(B35,-1,0))) -> 2 | C35: =IF(H35="CÉLULA CONSTRUTIVA",0,IF(H35="ETAPA",OFFSET(C35,-1,0)+1,OFFSET(C35,-1,0))) -> 2 | D35: =IF(H35="ETAPA",0,IF(H35="SUBETAPA",OFFSET(D35,-1,0)+1,OFFSET(D35,-1,0))) -> 0 | E35: =IF(H35="Subetapa",0,IF(H35="serviço",OFFSET(E35,-1,0)+1,OFFSET(E35,-1,0))) -> 1 | H35: ETAPA | I35: =IF(H35="Unidade Construtiva",TEXT(A35,"00"),IF(H35="Célula Construtiva",TEXT(B35,"00"),IF(H35="Etapa",CONCATENATE(TEXT(B35,"00"),".",TEXT(C35,"000")),IF(H35="Subetapa",CONCATENATE(TEXT(B35,"00"),".",TEXT(C35,"000"),".",TEXT(D35,"000")),IF(H35="Serviço",CONCATENATE(TEXT(B35,"00"),".",TEXT(C35,"000"),".",TEXT(D35,"000"),".",TEXT(E35,"000")),""))))) -> 02.002 | J35: FUNDAÇÃO RASA | N35: =IF(H35="Serviço",M35*L35,IF(H35="CÉLULA CONSTRUTIVA",SUMIFS($N$8:$N$335,$B$8:$B$335,B35,$H$8:$H$335,"Serviço"),IF(H35="ETAPA",SUMIFS($N$8:$N$335,$B$8:$B$335,B35,$C$8:$C$335,C35,$H$8:$H$335,"Serviço"),IF(H35="SUBETAPA",SUMIFS($N$8:$N$335,$B$8:$B$335,B35,$C$8:$C$335,C35,$D$8:$D$335,D35,$H$8:$H$335,"Serviço"),0)))) -> 839010.98
A36: =IF($H36="UNIDADE CONSTRUTIVA",OFFSET(A36,-1,0)+1,LARGE(A$3:A33,1)) -> 0 | B36: =IF(H36="UNIDADE CONSTRUTIVA",0,IF(H36="CÉLULA CONSTRUTIVA",OFFSET(B36,-1,0)+1,OFFSET(B36,-1,0))) -> 2 | C36: =IF(H36="CÉLULA CONSTRUTIVA",0,IF(H36="ETAPA",OFFSET(C36,-1,0)+1,OFFSET(C36,-1,0))) -> 2 | D36: =IF(H36="ETAPA",0,IF(H36="SUBETAPA",OFFSET(D36,-1,0)+1,OFFSET(D36,-1,0))) -> 1 | E36: =IF(H36="Subetapa",0,IF(H36="serviço",OFFSET(E36,-1,0)+1,OFFSET(E36,-1,0))) -> 0 | H36: SUBETAPA | I36: =IF(H36="Unidade Construtiva",TEXT(A36,"00"),IF(H36="Célula Construtiva",TEXT(B36,"00"),IF(H36="Etapa",CONCATENATE(TEXT(B36,"00"),".",TEXT(C36,"000")),IF(H36="Subetapa",CONCATENATE(TEXT(B36,"00"),".",TEXT(C36,"000"),".",TEXT(D36,"000")),IF(H36="Serviço",CONCATENATE(TEXT(B36,"00"),".",TEXT(C36,"000"),".",TEXT(D36,"000"),".",TEXT(E36,"000")),""))))) -> 02.002.001 | J36: Forma | N36: =IF(H36="Serviço",M36*L36,IF(H36="CÉLULA CONSTRUTIVA",SUMIFS($N$8:$N$335,$B$8:$B$335,B36,$H$8:$H$335,"Serviço"),IF(H36="ETAPA",SUMIFS($N$8:$N$335,$B$8:$B$335,B36,$C$8:$C$335,C36,$H$8:$H$335,"Serviço"),IF(H36="SUBETAPA",SUMIFS($N$8:$N$335,$B$8:$B$335,B36,$C$8:$C$335,C36,$D$8:$D$335,D36,$H$8:$H$335,"Serviço"),0)))) -> 77803.075
A37: =IF($H37="UNIDADE CONSTRUTIVA",OFFSET(A37,-1,0)+1,LARGE(A$3:A34,1)) -> 0 | B37: =IF(H37="UNIDADE CONSTRUTIVA",0,IF(H37="CÉLULA CONSTRUTIVA",OFFSET(B37,-1,0)+1,OFFSET(B37,-1,0))) -> 2 | C37: =IF(H37="CÉLULA CONSTRUTIVA",0,IF(H37="ETAPA",OFFSET(C37,-1,0)+1,OFFSET(C37,-1,0))) -> 2 | D37: =IF(H37="ETAPA",0,IF(H37="SUBETAPA",OFFSET(D37,-1,0)+1,OFFSET(D37,-1,0))) -> 1 | E37: =IF(H37="Subetapa",0,IF(H37="serviço",OFFSET(E37,-1,0)+1,OFFSET(E37,-1,0))) -> 1 | H37: SERVIÇO | I37: =IF(H37="Unidade Construtiva",TEXT(A37,"00"),IF(H37="Célula Construtiva",TEXT(B37,"00"),IF(H37="Etapa",CONCATENATE(TEXT(B37,"00"),".",TEXT(C37,"000")),IF(H37="Subetapa",CONCATENATE(TEXT(B37,"00"),".",TEXT(C37,"000"),".",TEXT(D37,"000")),IF(H37="Serviço",CONCATENATE(TEXT(B37,"00"),".",TEXT(C37,"000"),".",TEXT(D37,"000"),".",TEXT(E37,"000")),""))))) -> 02.002.001.001 | J37: Forma para infraestrutura em Tábuas de Madeira Serrada 4x reaproveitamento | K37: m2 | L37: 1313.336 | M37: 59.2408 | N37: =IF(H37="Serviço",M37*L37,IF(H37="CÉLULA CONSTRUTIVA",SUMIFS($N$8:$N$335,$B$8:$B$335,B37,$H$8:$H$335,"Serviço"),IF(H37="ETAPA",SUMIFS($N$8:$N$335,$B$8:$B$335,B37,$C$8:$C$335,C37,$H$8:$H$335,"Serviço"),IF(H37="SUBETAPA",SUMIFS($N$8:$N$335,$B$8:$B$335,B37,$C$8:$C$335,C37,$D$8:$D$335,D37,$H$8:$H$335,"Serviço"),0)))) -> 77803.075 | P37: Lançado ERP
A38: =IF($H38="UNIDADE CONSTRUTIVA",OFFSET(A38,-1,0)+1,LARGE(A$3:A35,1)) -> 0 | B38: =IF(H38="UNIDADE CONSTRUTIVA",0,IF(H38="CÉLULA CONSTRUTIVA",OFFSET(B38,-1,0)+1,OFFSET(B38,-1,0))) -> 2 | C38: =IF(H38="CÉLULA CONSTRUTIVA",0,IF(H38="ETAPA",OFFSET(C38,-1,0)+1,OFFSET(C38,-1,0))) -> 2 | D38: =IF(H38="ETAPA",0,IF(H38="SUBETAPA",OFFSET(D38,-1,0)+1,OFFSET(D38,-1,0))) -> 2 | E38: =IF(H38="Subetapa",0,IF(H38="serviço",OFFSET(E38,-1,0)+1,OFFSET(E38,-1,0))) -> 0 | H38: SUBETAPA | I38: =IF(H38="Unidade Construtiva",TEXT(A38,"00"),IF(H38="Célula Construtiva",TEXT(B38,"00"),IF(H38="Etapa",CONCATENATE(TEXT(B38,"00"),".",TEXT(C38,"000")),IF(H38="Subetapa",CONCATENATE(TEXT(B38,"00"),".",TEXT(C38,"000"),".",TEXT(D38,"000")),IF(H38="Serviço",CONCATENATE(TEXT(B38,"00"),".",TEXT(C38,"000"),".",TEXT(D38,"000"),".",TEXT(E38,"000")),""))))) -> 02.002.002 | J38: Armadura | N38: =IF(H38="Serviço",M38*L38,IF(H38="CÉLULA CONSTRUTIVA",SUMIFS($N$8:$N$335,$B$8:$B$335,B38,$H$8:$H$335,"Serviço"),IF(H38="ETAPA",SUMIFS($N$8:$N$335,$B$8:$B$335,B38,$C$8:$C$335,C38,$H$8:$H$335,"Serviço"),IF(H38="SUBETAPA",SUMIFS($N$8:$N$335,$B$8:$B$335,B38,$C$8:$C$335,C38,$D$8:$D$335,D38,$H$8:$H$335,"Serviço"),0)))) -> 435157.47
A39: =IF($H39="UNIDADE CONSTRUTIVA",OFFSET(A39,-1,0)+1,LARGE(A$3:A36,1)) -> 0 | B39: =IF(H39="UNIDADE CONSTRUTIVA",0,IF(H39="CÉLULA CONSTRUTIVA",OFFSET(B39,-1,0)+1,OFFSET(B39,-1,0))) -> 2 | C39: =IF(H39="CÉLULA CONSTRUTIVA",0,IF(H39="ETAPA",OFFSET(C39,-1,0)+1,OFFSET(C39,-1,0))) -> 2 | D39: =IF(H39="ETAPA",0,IF(H39="SUBETAPA",OFFSET(D39,-1,0)+1,OFFSET(D39,-1,0))) -> 2 | E39: =IF(H39="Subetapa",0,IF(H39="serviço",OFFSET(E39,-1,0)+1,OFFSET(E39,-1,0))) -> 1 | H39: SERVIÇO | I39: =IF(H39="Unidade Construtiva",TEXT(A39,"00"),IF(H39="Célula Construtiva",TEXT(B39,"00"),IF(H39="Etapa",CONCATENATE(TEXT(B39,"00"),".",TEXT(C39,"000")),IF(H39="Subetapa",CONCATENATE(TEXT(B39,"00"),".",TEXT(C39,"000"),".",TEXT(D39,"000")),IF(H39="Serviço",CONCATENATE(TEXT(B39,"00"),".",TEXT(C39,"000"),".",TEXT(D39,"000"),".",TEXT(E39,"000")),""))))) -> 02.002.002.001 | J39: Armação aço CA-50 ø 6,3mm para infraestrutura (corte e dobra em obra) | K39: kg | L39: 10670.855 | M39: 7.33 | N39: =IF(H39="Serviço",M39*L39,IF(H39="CÉLULA CONSTRUTIVA",SUMIFS($N$8:$N$335,$B$8:$B$335,B39,$H$8:$H$335,"Serviço"),IF(H39="ETAPA",SUMIFS($N$8:$N$335,$B$8:$B$335,B39,$C$8:$C$335,C39,$H$8:$H$335,"Serviço"),IF(H39="SUBETAPA",SUMIFS($N$8:$N$335,$B$8:$B$335,B39,$C$8:$C$335,C39,$D$8:$D$335,D39,$H$8:$H$335,"Serviço"),0)))) -> 78217.367 | P39: Lançado ERP
A40: =IF($H40="UNIDADE CONSTRUTIVA",OFFSET(A40,-1,0)+1,LARGE(A$3:A37,1)) -> 0 | B40: =IF(H40="UNIDADE CONSTRUTIVA",0,IF(H40="CÉLULA CONSTRUTIVA",OFFSET(B40,-1,0)+1,OFFSET(B40,-1,0))) -> 2 | C40: =IF(H40="CÉLULA CONSTRUTIVA",0,IF(H40="ETAPA",OFFSET(C40,-1,0)+1,OFFSET(C40,-1,0))) -> 2 | D40: =IF(H40="ETAPA",0,IF(H40="SUBETAPA",OFFSET(D40,-1,0)+1,OFFSET(D40,-1,0))) -> 2 | E40: =IF(H40="Subetapa",0,IF(H40="serviço",OFFSET(E40,-1,0)+1,OFFSET(E40,-1,0))) -> 2 | H40: SERVIÇO | I40: =IF(H40="Unidade Construtiva",TEXT(A40,"00"),IF(H40="Célula Construtiva",TEXT(B40,"00"),IF(H40="Etapa",CONCATENATE(TEXT(B40,"00"),".",TEXT(C40,"000")),IF(H40="Subetapa",CONCATENATE(TEXT(B40,"00"),".",TEXT(C40,"000"),".",TEXT(D40,"000")),IF(H40="Serviço",CONCATENATE(TEXT(B40,"00"),".",TEXT(C40,"000"),".",TEXT(D40,"000"),".",TEXT(E40,"000")),""))))) -> 02.002.002.002 | J40: Armação aço CA-50 ø 8,0mm para infraestrutura (corte e dobra em obra) | K40: kg | L40: 10670.855 | M40: 7.07 | N40: =IF(H40="Serviço",M40*L40,IF(H40="CÉLULA CONSTRUTIVA",SUMIFS($N$8:$N$335,$B$8:$B$335,B40,$H$8:$H$335,"Serviço"),IF(H40="ETAPA",SUMIFS($N$8:$N$335,$B$8:$B$335,B40,$C$8:$C$335,C40,$H$8:$H$335,"Serviço"),IF(H40="SUBETAPA",SUMIFS($N$8:$N$335,$B$8:$B$335,B40,$C$8:$C$335,C40,$D$8:$D$335,D40,$H$8:$H$335,"Serviço"),0)))) -> 75442.945 | P40: Lançado ERP
A41: =IF($H41="UNIDADE CONSTRUTIVA",OFFSET(A41,-1,0)+1,LARGE(A$3:A38,1)) -> 0 | B41: =IF(H41="UNIDADE CONSTRUTIVA",0,IF(H41="CÉLULA CONSTRUTIVA",OFFSET(B41,-1,0)+1,OFFSET(B41,-1,0))) -> 2 | C41: =IF(H41="CÉLULA CONSTRUTIVA",0,IF(H41="ETAPA",OFFSET(C41,-1,0)+1,OFFSET(C41,-1,0))) -> 2 | D41: =IF(H41="ETAPA",0,IF(H41="SUBETAPA",OFFSET(D41,-1,0)+1,OFFSET(D41,-1,0))) -> 2 | E41: =IF(H41="Subetapa",0,IF(H41="serviço",OFFSET(E41,-1,0)+1,OFFSET(E41,-1,0))) -> 3 | H41: SERVIÇO | I41: =IF(H41="Unidade Construtiva",TEXT(A41,"00"),IF(H41="Célula Construtiva",TEXT(B41,"00"),IF(H41="Etapa",CONCATENATE(TEXT(B41,"00"),".",TEXT(C41,"000")),IF(H41="Subetapa",CONCATENATE(TEXT(B41,"00"),".",TEXT(C41,"000"),".",TEXT(D41,"000")),IF(H41="Serviço",CONCATENATE(TEXT(B41,"00"),".",TEXT(C41,"000"),".",TEXT(D41,"000"),".",TEXT(E41,"000")),""))))) -> 02.002.002.003 | J41: Armação aço CA-50 ø 10,0mm para infraestrutura (corte e dobra em obra) | K41: kg | L41: 10670.855 | M41: 6.51 | N41: =IF(H41="Serviço",M41*L41,IF(H41="CÉLULA CONSTRUTIVA",SUMIFS($N$8:$N$335,$B$8:$B$335,B41,$H$8:$H$335,"Serviço"),IF(H41="ETAPA",SUMIFS($N$8:$N$335,$B$8:$B$335,B41,$C$8:$C$335,C41,$H$8:$H$335,"Serviço"),IF(H41="SUBETAPA",SUMIFS($N$8:$N$335,$B$8:$B$335,B41,$C$8:$C$335,C41,$D$8:$D$335,D41,$H$8:$H$335,"Serviço"),0)))) -> 69467.266 | P41: Lançado ERP
A42: =IF($H42="UNIDADE CONSTRUTIVA",OFFSET(A42,-1,0)+1,LARGE(A$3:A39,1)) -> 0 | B42: =IF(H42="UNIDADE CONSTRUTIVA",0,IF(H42="CÉLULA CONSTRUTIVA",OFFSET(B42,-1,0)+1,OFFSET(B42,-1,0))) -> 2 | C42: =IF(H42="CÉLULA CONSTRUTIVA",0,IF(H42="ETAPA",OFFSET(C42,-1,0)+1,OFFSET(C42,-1,0))) -> 2 | D42: =IF(H42="ETAPA",0,IF(H42="SUBETAPA",OFFSET(D42,-1,0)+1,OFFSET(D42,-1,0))) -> 2 | E42: =IF(H42="Subetapa",0,IF(H42="serviço",OFFSET(E42,-1,0)+1,OFFSET(E42,-1,0))) -> 4 | H42: SERVIÇO | I42: =IF(H42="Unidade Construtiva",TEXT(A42,"00"),IF(H42="Célula Construtiva",TEXT(B42,"00"),IF(H42="Etapa",CONCATENATE(TEXT(B42,"00"),".",TEXT(C42,"000")),IF(H42="Subetapa",CONCATENATE(TEXT(B42,"00"),".",TEXT(C42,"000"),".",TEXT(D42,"000")),IF(H42="Serviço",CONCATENATE(TEXT(B42,"00"),".",TEXT(C42,"000"),".",TEXT(D42,"000"),".",TEXT(E42,"000")),""))))) -> 02.002.002.004 | J42: Armação aço CA-50 ø 12,5mm para infraestrutura (corte e dobra em obra) | K42: kg | L42: 10670.855 | M42: 6.69 | N42: =IF(H42="Serviço",M42*L42,IF(H42="CÉLULA CONSTRUTIVA",SUMIFS($N$8:$N$335,$B$8:$B$335,B42,$H$8:$H$335,"Serviço"),IF(H42="ETAPA",SUMIFS($N$8:$N$335,$B$8:$B$335,B42,$C$8:$C$335,C42,$H$8:$H$335,"Serviço"),IF(H42="SUBETAPA",SUMIFS($N$8:$N$335,$B$8:$B$335,B42,$C$8:$C$335,C42,$D$8:$D$335,D42,$H$8:$H$335,"Serviço"),0)))) -> 71388.02 | P42: Lançado ERP
A43: =IF($H43="UNIDADE CONSTRUTIVA",OFFSET(A43,-1,0)+1,LARGE(A$3:A40,1)) -> 0 | B43: =IF(H43="UNIDADE CONSTRUTIVA",0,IF(H43="CÉLULA CONSTRUTIVA",OFFSET(B43,-1,0)+1,OFFSET(B43,-1,0))) -> 2 | C43: =IF(H43="CÉLULA CONSTRUTIVA",0,IF(H43="ETAPA",OFFSET(C43,-1,0)+1,OFFSET(C43,-1,0))) -> 2 | D43: =IF(H43="ETAPA",0,IF(H43="SUBETAPA",OFFSET(D43,-1,0)+1,OFFSET(D43,-1,0))) -> 2 | E43: =IF(H43="Subetapa",0,IF(H43="serviço",OFFSET(E43,-1,0)+1,OFFSET(E43,-1,0))) -> 5 | H43: SERVIÇO | I43: =IF(H43="Unidade Construtiva",TEXT(A43,"00"),IF(H43="Célula Construtiva",TEXT(B43,"00"),IF(H43="Etapa",CONCATENATE(TEXT(B43,"00"),".",TEXT(C43,"000")),IF(H43="Subetapa",CONCATENATE(TEXT(B43,"00"),".",TEXT(C43,"000"),".",TEXT(D43,"000")),IF(H43="Serviço",CONCATENATE(TEXT(B43,"00"),".",TEXT(C43,"000"),".",TEXT(D43,"000"),".",TEXT(E43,"000")),""))))) -> 02.002.002.005 | J43: Armação aço CA-50 ø 16,0mm para infraestrutura (corte e dobra em obra) | K43: kg | L43: 10670.855 | M43: 6.66 | N43: =IF(H43="Serviço",M43*L43,IF(H43="CÉLULA CONSTRUTIVA",SUMIFS($N$8:$N$335,$B$8:$B$335,B43,$H$8:$H$335,"Serviço"),IF(H43="ETAPA",SUMIFS($N$8:$N$335,$B$8:$B$335,B43,$C$8:$C$335,C43,$H$8:$H$335,"Serviço"),IF(H43="SUBETAPA",SUMIFS($N$8:$N$335,$B$8:$B$335,B43,$C$8:$C$335,C43,$D$8:$D$335,D43,$H$8:$H$335,"Serviço"),0)))) -> 71067.894 | P43: Lançado ERP
A44: =IF($H44="UNIDADE CONSTRUTIVA",OFFSET(A44,-1,0)+1,LARGE(A$3:A41,1)) -> 0 | B44: =IF(H44="UNIDADE CONSTRUTIVA",0,IF(H44="CÉLULA CONSTRUTIVA",OFFSET(B44,-1,0)+1,OFFSET(B44,-1,0))) -> 2 | C44: =IF(H44="CÉLULA CONSTRUTIVA",0,IF(H44="ETAPA",OFFSET(C44,-1,0)+1,OFFSET(C44,-1,0))) -> 2 | D44: =IF(H44="ETAPA",0,IF(H44="SUBETAPA",OFFSET(D44,-1,0)+1,OFFSET(D44,-1,0))) -> 2 | E44: =IF(H44="Subetapa",0,IF(H44="serviço",OFFSET(E44,-1,0)+1,OFFSET(E44,-1,0))) -> 6 | H44: SERVIÇO | I44: =IF(H44="Unidade Construtiva",TEXT(A44,"00"),IF(H44="Célula Construtiva",TEXT(B44,"00"),IF(H44="Etapa",CONCATENATE(TEXT(B44,"00"),".",TEXT(C44,"000")),IF(H44="Subetapa",CONCATENATE(TEXT(B44,"00"),".",TEXT(C44,"000"),".",TEXT(D44,"000")),IF(H44="Serviço",CONCATENATE(TEXT(B44,"00"),".",TEXT(C44,"000"),".",TEXT(D44,"000"),".",TEXT(E44,"000")),""))))) -> 02.002.002.006 | J44: Armação aço CA-50 ø 20,0mm para infraestrutura (corte e dobra em obra) | K44: kg | L44: 10670.855 | M44: 6.52 | N44: =IF(H44="Serviço",M44*L44,IF(H44="CÉLULA CONSTRUTIVA",SUMIFS($N$8:$N$335,$B$8:$B$335,B44,$H$8:$H$335,"Serviço"),IF(H44="ETAPA",SUMIFS($N$8:$N$335,$B$8:$B$335,B44,$C$8:$C$335,C44,$H$8:$H$335,"Serviço"),IF(H44="SUBETAPA",SUMIFS($N$8:$N$335,$B$8:$B$335,B44,$C$8:$C$335,C44,$D$8:$D$335,D44,$H$8:$H$335,"Serviço"),0)))) -> 69573.975 | P44: Lançado ERP
A45: =IF($H45="UNIDADE CONSTRUTIVA",OFFSET(A45,-1,0)+1,LARGE(A$3:A44,1)) -> 0 | B45: =IF(H45="UNIDADE CONSTRUTIVA",0,IF(H45="CÉLULA CONSTRUTIVA",OFFSET(B45,-1,0)+1,OFFSET(B45,-1,0))) -> 2 | C45: =IF(H45="CÉLULA CONSTRUTIVA",0,IF(H45="ETAPA",OFFSET(C45,-1,0)+1,OFFSET(C45,-1,0))) -> 2 | D45: =IF(H45="ETAPA",0,IF(H45="SUBETAPA",OFFSET(D45,-1,0)+1,OFFSET(D45,-1,0))) -> 3 | E45: =IF(H45="Subetapa",0,IF(H45="serviço",OFFSET(E45,-1,0)+1,OFFSET(E45,-1,0))) -> 0 | H45: SUBETAPA | I45: =IF(H45="Unidade Construtiva",TEXT(A45,"00"),IF(H45="Célula Construtiva",TEXT(B45,"00"),IF(H45="Etapa",CONCATENATE(TEXT(B45,"00"),".",TEXT(C45,"000")),IF(H45="Subetapa",CONCATENATE(TEXT(B45,"00"),".",TEXT(C45,"000"),".",TEXT(D45,"000")),IF(H45="Serviço",CONCATENATE(TEXT(B45,"00"),".",TEXT(C45,"000"),".",TEXT(D45,"000"),".",TEXT(E45,"000")),""))))) -> 02.002.003 | J45: Concreto | N45: =IF(H45="Serviço",M45*L45,IF(H45="CÉLULA CONSTRUTIVA",SUMIFS($N$8:$N$335,$B$8:$B$335,B45,$H$8:$H$335,"Serviço"),IF(H45="ETAPA",SUMIFS($N$8:$N$335,$B$8:$B$335,B45,$C$8:$C$335,C45,$H$8:$H$335,"Serviço"),IF(H45="SUBETAPA",SUMIFS($N$8:$N$335,$B$8:$B$335,B45,$C$8:$C$335,C45,$D$8:$D$335,D45,$H$8:$H$335,"Serviço"),0)))) -> 326050.44
A46: =IF($H46="UNIDADE CONSTRUTIVA",OFFSET(A46,-1,0)+1,LARGE(A$3:A44,1)) -> 0 | B46: =IF(H46="UNIDADE CONSTRUTIVA",0,IF(H46="CÉLULA CONSTRUTIVA",OFFSET(B46,-1,0)+1,OFFSET(B46,-1,0))) -> 2 | C46: =IF(H46="CÉLULA CONSTRUTIVA",0,IF(H46="ETAPA",OFFSET(C46,-1,0)+1,OFFSET(C46,-1,0))) -> 2 | D46: =IF(H46="ETAPA",0,IF(H46="SUBETAPA",OFFSET(D46,-1,0)+1,OFFSET(D46,-1,0))) -> 3 | E46: =IF(H46="Subetapa",0,IF(H46="serviço",OFFSET(E46,-1,0)+1,OFFSET(E46,-1,0))) -> 1 | H46: SERVIÇO | I46: =IF(H46="Unidade Construtiva",TEXT(A46,"00"),IF(H46="Célula Construtiva",TEXT(B46,"00"),IF(H46="Etapa",CONCATENATE(TEXT(B46,"00"),".",TEXT(C46,"000")),IF(H46="Subetapa",CONCATENATE(TEXT(B46,"00"),".",TEXT(C46,"000"),".",TEXT(D46,"000")),IF(H46="Serviço",CONCATENATE(TEXT(B46,"00"),".",TEXT(C46,"000"),".",TEXT(D46,"000"),".",TEXT(E46,"000")),""))))) -> 02.002.003.001 | J46: Concreto Usinado bombeável 45MPa para infraestrutura- incluindo serviço de bombeamento | K46: m3 | L46: 492.501 | M46: 662.03 | N46: =IF(H46="Serviço",M46*L46,IF(H46="CÉLULA CONSTRUTIVA",SUMIFS($N$8:$N$335,$B$8:$B$335,B46,$H$8:$H$335,"Serviço"),IF(H46="ETAPA",SUMIFS($N$8:$N$335,$B$8:$B$335,B46,$C$8:$C$335,C46,$H$8:$H$335,"Serviço"),IF(H46="SUBETAPA",SUMIFS($N$8:$N$335,$B$8:$B$335,B46,$C$8:$C$335,C46,$D$8:$D$335,D46,$H$8:$H$335,"Serviço"),0)))) -> 326050.44 | P46: Lançado ERP
A47: =IF($H47="UNIDADE CONSTRUTIVA",OFFSET(A47,-1,0)+1,LARGE(A$3:A46,1)) -> 0 | B47: =IF(H47="UNIDADE CONSTRUTIVA",0,IF(H47="CÉLULA CONSTRUTIVA",OFFSET(B47,-1,0)+1,OFFSET(B47,-1,0))) -> 3 | C47: =IF(H47="CÉLULA CONSTRUTIVA",0,IF(H47="ETAPA",OFFSET(C47,-1,0)+1,OFFSET(C47,-1,0))) -> 0 | D47: =IF(H47="ETAPA",0,IF(H47="SUBETAPA",OFFSET(D47,-1,0)+1,OFFSET(D47,-1,0))) -> 3 | E47: =IF(H47="Subetapa",0,IF(H47="serviço",OFFSET(E47,-1,0)+1,OFFSET(E47,-1,0))) -> 1 | H47: CÉLULA CONSTRUTIVA | I47: =IF(H47="Unidade Construtiva",TEXT(A47,"00"),IF(H47="Célula Construtiva",TEXT(B47,"00"),IF(H47="Etapa",CONCATENATE(TEXT(B47,"00"),".",TEXT(C47,"000")),IF(H47="Subetapa",CONCATENATE(TEXT(B47,"00"),".",TEXT(C47,"000"),".",TEXT(D47,"000")),IF(H47="Serviço",CONCATENATE(TEXT(B47,"00"),".",TEXT(C47,"000"),".",TEXT(D47,"000"),".",TEXT(E47,"000")),""))))) -> 03 | J47: CONTENÇAO | N47: =IF(H47="Serviço",M47*L47,IF(H47="CÉLULA CONSTRUTIVA",SUMIFS($N$8:$N$335,$B$8:$B$335,B47,$H$8:$H$335,"Serviço"),IF(H47="ETAPA",SUMIFS($N$8:$N$335,$B$8:$B$335,B47,$C$8:$C$335,C47,$H$8:$H$335,"Serviço"),IF(H47="SUBETAPA",SUMIFS($N$8:$N$335,$B$8:$B$335,B47,$C$8:$C$335,C47,$D$8:$D$335,D47,$H$8:$H$335,"Serviço"),0)))) -> 1381816.6
A48: =IF($H48="UNIDADE CONSTRUTIVA",OFFSET(A48,-1,0)+1,LARGE(A$3:A46,1)) -> 0 | B48: =IF(H48="UNIDADE CONSTRUTIVA",0,IF(H48="CÉLULA CONSTRUTIVA",OFFSET(B48,-1,0)+1,OFFSET(B48,-1,0))) -> 3 | C48: =IF(H48="CÉLULA CONSTRUTIVA",0,IF(H48="ETAPA",OFFSET(C48,-1,0)+1,OFFSET(C48,-1,0))) -> 1 | D48: =IF(H48="ETAPA",0,IF(H48="SUBETAPA",OFFSET(D48,-1,0)+1,OFFSET(D48,-1,0))) -> 0 | E48: =IF(H48="Subetapa",0,IF(H48="serviço",OFFSET(E48,-1,0)+1,OFFSET(E48,-1,0))) -> 1 | H48: ETAPA | I48: =IF(H48="Unidade Construtiva",TEXT(A48,"00"),IF(H48="Célula Construtiva",TEXT(B48,"00"),IF(H48="Etapa",CONCATENATE(TEXT(B48,"00"),".",TEXT(C48,"000")),IF(H48="Subetapa",CONCATENATE(TEXT(B48,"00"),".",TEXT(C48,"000"),".",TEXT(D48,"000")),IF(H48="Serviço",CONCATENATE(TEXT(B48,"00"),".",TEXT(C48,"000"),".",TEXT(D48,"000"),".",TEXT(E48,"000")),""))))) -> 03.001 | J48: CONTENÇÃO | N48: =IF(H48="Serviço",M48*L48,IF(H48="CÉLULA CONSTRUTIVA",SUMIFS($N$8:$N$335,$B$8:$B$335,B48,$H$8:$H$335,"Serviço"),IF(H48="ETAPA",SUMIFS($N$8:$N$335,$B$8:$B$335,B48,$C$8:$C$335,C48,$H$8:$H$335,"Serviço"),IF(H48="SUBETAPA",SUMIFS($N$8:$N$335,$B$8:$B$335,B48,$C$8:$C$335,C48,$D$8:$D$335,D48,$H$8:$H$335,"Serviço"),0)))) -> 1381816.6
A49: =IF($H49="UNIDADE CONSTRUTIVA",OFFSET(A49,-1,0)+1,LARGE(A$3:A48,1)) -> 0 | B49: =IF(H49="UNIDADE CONSTRUTIVA",0,IF(H49="CÉLULA CONSTRUTIVA",OFFSET(B49,-1,0)+1,OFFSET(B49,-1,0))) -> 3 | C49: =IF(H49="CÉLULA CONSTRUTIVA",0,IF(H49="ETAPA",OFFSET(C49,-1,0)+1,OFFSET(C49,-1,0))) -> 1 | D49: =IF(H49="ETAPA",0,IF(H49="SUBETAPA",OFFSET(D49,-1,0)+1,OFFSET(D49,-1,0))) -> 1 | E49: =IF(H49="Subetapa",0,IF(H49="serviço",OFFSET(E49,-1,0)+1,OFFSET(E49,-1,0))) -> 0 | H49: SUBETAPA | I49: =IF(H49="Unidade Construtiva",TEXT(A49,"00"),IF(H49="Célula Construtiva",TEXT(B49,"00"),IF(H49="Etapa",CONCATENATE(TEXT(B49,"00"),".",TEXT(C49,"000")),IF(H49="Subetapa",CONCATENATE(TEXT(B49,"00"),".",TEXT(C49,"000"),".",TEXT(D49,"000")),IF(H49="Serviço",CONCATENATE(TEXT(B49,"00"),".",TEXT(C49,"000"),".",TEXT(D49,"000"),".",TEXT(E49,"000")),""))))) -> 03.001.001 | J49: Execução de contenção | N49: =IF(H49="Serviço",M49*L49,IF(H49="CÉLULA CONSTRUTIVA",SUMIFS($N$8:$N$335,$B$8:$B$335,B49,$H$8:$H$335,"Serviço"),IF(H49="ETAPA",SUMIFS($N$8:$N$335,$B$8:$B$335,B49,$C$8:$C$335,C49,$H$8:$H$335,"Serviço"),IF(H49="SUBETAPA",SUMIFS($N$8:$N$335,$B$8:$B$335,B49,$C$8:$C$335,C49,$D$8:$D$335,D49,$H$8:$H$335,"Serviço"),0)))) -> 987639.62
A50: =IF($H50="UNIDADE CONSTRUTIVA",OFFSET(A50,-1,0)+1,LARGE(A$3:A48,1)) -> 0 | B50: =IF(H50="UNIDADE CONSTRUTIVA",0,IF(H50="CÉLULA CONSTRUTIVA",OFFSET(B50,-1,0)+1,OFFSET(B50,-1,0))) -> 3 | C50: =IF(H50="CÉLULA CONSTRUTIVA",0,IF(H50="ETAPA",OFFSET(C50,-1,0)+1,OFFSET(C50,-1,0))) -> 1 | D50: =IF(H50="ETAPA",0,IF(H50="SUBETAPA",OFFSET(D50,-1,0)+1,OFFSET(D50,-1,0))) -> 1 | E50: =IF(H50="Subetapa",0,IF(H50="serviço",OFFSET(E50,-1,0)+1,OFFSET(E50,-1,0))) -> 1 | H50: SERVIÇO | I50: =IF(H50="Unidade Construtiva",TEXT(A50,"00"),IF(H50="Célula Construtiva",TEXT(B50,"00"),IF(H50="Etapa",CONCATENATE(TEXT(B50,"00"),".",TEXT(C50,"000")),IF(H50="Subetapa",CONCATENATE(TEXT(B50,"00"),".",TEXT(C50,"000"),".",TEXT(D50,"000")),IF(H50="Serviço",CONCATENATE(TEXT(B50,"00"),".",TEXT(C50,"000"),".",TEXT(D50,"000"),".",TEXT(E50,"000")),""))))) -> 03.001.001.001 | J50: Serviço para execução de contenção com material | K50: m3 | L50: =Estrutura!H30 -> 458.1165 | M50: =2155.87 -> 2155.87 | N50: =IF(H50="Serviço",M50*L50,IF(H50="CÉLULA CONSTRUTIVA",SUMIFS($N$8:$N$335,$B$8:$B$335,B50,$H$8:$H$335,"Serviço"),IF(H50="ETAPA",SUMIFS($N$8:$N$335,$B$8:$B$335,B50,$C$8:$C$335,C50,$H$8:$H$335,"Serviço"),IF(H50="SUBETAPA",SUMIFS($N$8:$N$335,$B$8:$B$335,B50,$C$8:$C$335,C50,$D$8:$D$335,D50,$H$8:$H$335,"Serviço"),0)))) -> 987639.62 | O50: Composição orçamentária com aço, concreto e outros itens - retirado mão de obra da composição | P50: Lançado ERP
A51: =IF($H51="UNIDADE CONSTRUTIVA",OFFSET(A51,-1,0)+1,LARGE(A$3:A50,1)) -> 0 | B51: =IF(H51="UNIDADE CONSTRUTIVA",0,IF(H51="CÉLULA CONSTRUTIVA",OFFSET(B51,-1,0)+1,OFFSET(B51,-1,0))) -> 3 | C51: =IF(H51="CÉLULA CONSTRUTIVA",0,IF(H51="ETAPA",OFFSET(C51,-1,0)+1,OFFSET(C51,-1,0))) -> 1 | D51: =IF(H51="ETAPA",0,IF(H51="SUBETAPA",OFFSET(D51,-1,0)+1,OFFSET(D51,-1,0))) -> 2 | E51: =IF(H51="Subetapa",0,IF(H51="serviço",OFFSET(E51,-1,0)+1,OFFSET(E51,-1,0))) -> 0 | H51: SUBETAPA | I51: =IF(H51="Unidade Construtiva",TEXT(A51,"00"),IF(H51="Célula Construtiva",TEXT(B51,"00"),IF(H51="Etapa",CONCATENATE(TEXT(B51,"00"),".",TEXT(C51,"000")),IF(H51="Subetapa",CONCATENATE(TEXT(B51,"00"),".",TEXT(C51,"000"),".",TEXT(D51,"000")),IF(H51="Serviço",CONCATENATE(TEXT(B51,"00"),".",TEXT(C51,"000"),".",TEXT(D51,"000"),".",TEXT(E51,"000")),""))))) -> 03.001.002 | J51: Serviços complemetares | N51: =IF(H51="Serviço",M51*L51,IF(H51="CÉLULA CONSTRUTIVA",SUMIFS($N$8:$N$335,$B$8:$B$335,B51,$H$8:$H$335,"Serviço"),IF(H51="ETAPA",SUMIFS($N$8:$N$335,$B$8:$B$335,B51,$C$8:$C$335,C51,$H$8:$H$335,"Serviço"),IF(H51="SUBETAPA",SUMIFS($N$8:$N$335,$B$8:$B$335,B51,$C$8:$C$335,C51,$D$8:$D$335,D51,$H$8:$H$335,"Serviço"),0)))) -> 277884.6
A52: =IF($H52="UNIDADE CONSTRUTIVA",OFFSET(A52,-1,0)+1,LARGE(A$3:A50,1)) -> 0 | B52: =IF(H52="UNIDADE CONSTRUTIVA",0,IF(H52="CÉLULA CONSTRUTIVA",OFFSET(B52,-1,0)+1,OFFSET(B52,-1,0))) -> 3 | C52: =IF(H52="CÉLULA CONSTRUTIVA",0,IF(H52="ETAPA",OFFSET(C52,-1,0)+1,OFFSET(C52,-1,0))) -> 1 | D52: =IF(H52="ETAPA",0,IF(H52="SUBETAPA",OFFSET(D52,-1,0)+1,OFFSET(D52,-1,0))) -> 2 | E52: =IF(H52="Subetapa",0,IF(H52="serviço",OFFSET(E52,-1,0)+1,OFFSET(E52,-1,0))) -> 1 | H52: SERVIÇO | I52: =IF(H52="Unidade Construtiva",TEXT(A52,"00"),IF(H52="Célula Construtiva",TEXT(B52,"00"),IF(H52="Etapa",CONCATENATE(TEXT(B52,"00"),".",TEXT(C52,"000")),IF(H52="Subetapa",CONCATENATE(TEXT(B52,"00"),".",TEXT(C52,"000"),".",TEXT(D52,"000")),IF(H52="Serviço",CONCATENATE(TEXT(B52,"00"),".",TEXT(C52,"000"),".",TEXT(D52,"000"),".",TEXT(E52,"000")),""))))) -> 03.001.002.001 | J52: Execução de tirantes | K52: vb | L52: 1 | M52: =210*Estrutura!H29 -> 277884.6 | N52: =IF(H52="Serviço",M52*L52,IF(H52="CÉLULA CONSTRUTIVA",SUMIFS($N$8:$N$335,$B$8:$B$335,B52,$H$8:$H$335,"Serviço"),IF(H52="ETAPA",SUMIFS($N$8:$N$335,$B$8:$B$335,B52,$C$8:$C$335,C52,$H$8:$H$335,"Serviço"),IF(H52="SUBETAPA",SUMIFS($N$8:$N$335,$B$8:$B$335,B52,$C$8:$C$335,C52,$D$8:$D$335,D52,$H$8:$H$335,"Serviço"),0)))) -> 277884.6 | P52: Lançado ERP
A53: =IF($H53="UNIDADE CONSTRUTIVA",OFFSET(A53,-1,0)+1,LARGE(A$3:A49,1)) -> 0 | B53: =IF(H53="UNIDADE CONSTRUTIVA",0,IF(H53="CÉLULA CONSTRUTIVA",OFFSET(B53,-1,0)+1,OFFSET(B53,-1,0))) -> 3 | C53: =IF(H53="CÉLULA CONSTRUTIVA",0,IF(H53="ETAPA",OFFSET(C53,-1,0)+1,OFFSET(C53,-1,0))) -> 1 | D53: =IF(H53="ETAPA",0,IF(H53="SUBETAPA",OFFSET(D53,-1,0)+1,OFFSET(D53,-1,0))) -> 3 | E53: =IF(H53="Subetapa",0,IF(H53="serviço",OFFSET(E53,-1,0)+1,OFFSET(E53,-1,0))) -> 0 | H53: SUBETAPA | I53: =IF(H53="Unidade Construtiva",TEXT(A53,"00"),IF(H53="Célula Construtiva",TEXT(B53,"00"),IF(H53="Etapa",CONCATENATE(TEXT(B53,"00"),".",TEXT(C53,"000")),IF(H53="Subetapa",CONCATENATE(TEXT(B53,"00"),".",TEXT(C53,"000"),".",TEXT(D53,"000")),IF(H53="Serviço",CONCATENATE(TEXT(B53,"00"),".",TEXT(C53,"000"),".",TEXT(D53,"000"),".",TEXT(E53,"000")),""))))) -> 03.001.003 | J53: Mureta guia | N53: =IF(H53="Serviço",M53*L53,IF(H53="CÉLULA CONSTRUTIVA",SUMIFS($N$8:$N$335,$B$8:$B$335,B53,$H$8:$H$335,"Serviço"),IF(H53="ETAPA",SUMIFS($N$8:$N$335,$B$8:$B$335,B53,$C$8:$C$335,C53,$H$8:$H$335,"Serviço"),IF(H53="SUBETAPA",SUMIFS($N$8:$N$335,$B$8:$B$335,B53,$C$8:$C$335,C53,$D$8:$D$335,D53,$H$8:$H$335,"Serviço"),0)))) -> 116292.37
A54: =IF($H54="UNIDADE CONSTRUTIVA",OFFSET(A54,-1,0)+1,LARGE(A$3:A49,1)) -> 0 | B54: =IF(H54="UNIDADE CONSTRUTIVA",0,IF(H54="CÉLULA CONSTRUTIVA",OFFSET(B54,-1,0)+1,OFFSET(B54,-1,0))) -> 3 | C54: =IF(H54="CÉLULA CONSTRUTIVA",0,IF(H54="ETAPA",OFFSET(C54,-1,0)+1,OFFSET(C54,-1,0))) -> 1 | D54: =IF(H54="ETAPA",0,IF(H54="SUBETAPA",OFFSET(D54,-1,0)+1,OFFSET(D54,-1,0))) -> 3 | E54: =IF(H54="Subetapa",0,IF(H54="serviço",OFFSET(E54,-1,0)+1,OFFSET(E54,-1,0))) -> 1 | H54: SERVIÇO | I54: =IF(H54="Unidade Construtiva",TEXT(A54,"00"),IF(H54="Célula Construtiva",TEXT(B54,"00"),IF(H54="Etapa",CONCATENATE(TEXT(B54,"00"),".",TEXT(C54,"000")),IF(H54="Subetapa",CONCATENATE(TEXT(B54,"00"),".",TEXT(C54,"000"),".",TEXT(D54,"000")),IF(H54="Serviço",CONCATENATE(TEXT(B54,"00"),".",TEXT(C54,"000"),".",TEXT(D54,"000"),".",TEXT(E54,"000")),""))))) -> 03.001.003.001 | J54: Execução de mureta guia para contenção/fundação | K54: m | L54: 154.146 | M54: 754.43 | N54: =IF(H54="Serviço",M54*L54,IF(H54="CÉLULA CONSTRUTIVA",SUMIFS($N$8:$N$335,$B$8:$B$335,B54,$H$8:$H$335,"Serviço"),IF(H54="ETAPA",SUMIFS($N$8:$N$335,$B$8:$B$335,B54,$C$8:$C$335,C54,$H$8:$H$335,"Serviço"),IF(H54="SUBETAPA",SUMIFS($N$8:$N$335,$B$8:$B$335,B54,$C$8:$C$335,C54,$D$8:$D$335,D54,$H$8:$H$335,"Serviço"),0)))) -> 116292.37 | O54: Composição orçamentárica com material e mão de obra | P54: Lançado ERP
A55: =IF($H55="UNIDADE CONSTRUTIVA",OFFSET(A55,-1,0)+1,LARGE(A$3:A46,1)) -> 0 | B55: =IF(H55="UNIDADE CONSTRUTIVA",0,IF(H55="CÉLULA CONSTRUTIVA",OFFSET(B55,-1,0)+1,OFFSET(B55,-1,0))) -> 4 | C55: =IF(H55="CÉLULA CONSTRUTIVA",0,IF(H55="ETAPA",OFFSET(C55,-1,0)+1,OFFSET(C55,-1,0))) -> 0 | D55: =IF(H55="ETAPA",0,IF(H55="SUBETAPA",OFFSET(D55,-1,0)+1,OFFSET(D55,-1,0))) -> 3 | E55: =IF(H55="Subetapa",0,IF(H55="serviço",OFFSET(E55,-1,0)+1,OFFSET(E55,-1,0))) -> 1 | H55: CÉLULA CONSTRUTIVA | I55: =IF(H55="Unidade Construtiva",TEXT(A55,"00"),IF(H55="Célula Construtiva",TEXT(B55,"00"),IF(H55="Etapa",CONCATENATE(TEXT(B55,"00"),".",TEXT(C55,"000")),IF(H55="Subetapa",CONCATENATE(TEXT(B55,"00"),".",TEXT(C55,"000"),".",TEXT(D55,"000")),IF(H55="Serviço",CONCATENATE(TEXT(B55,"00"),".",TEXT(C55,"000"),".",TEXT(D55,"000"),".",TEXT(E55,"000")),""))))) -> 04 | J55: SUPRAESTRUTURA | N55: =IF(H55="Serviço",M55*L55,IF(H55="CÉLULA CONSTRUTIVA",SUMIFS($N$8:$N$335,$B$8:$B$335,B55,$H$8:$H$335,"Serviço"),IF(H55="ETAPA",SUMIFS($N$8:$N$335,$B$8:$B$335,B55,$C$8:$C$335,C55,$H$8:$H$335,"Serviço"),IF(H55="SUBETAPA",SUMIFS($N$8:$N$335,$B$8:$B$335,B55,$C$8:$C$335,C55,$D$8:$D$335,D55,$H$8:$H$335,"Serviço"),0)))) -> 6463760.8
A56: =IF($H56="UNIDADE CONSTRUTIVA",OFFSET(A56,-1,0)+1,LARGE(A$3:A46,1)) -> 0 | B56: =IF(H56="UNIDADE CONSTRUTIVA",0,IF(H56="CÉLULA CONSTRUTIVA",OFFSET(B56,-1,0)+1,OFFSET(B56,-1,0))) -> 4 | C56: =IF(H56="CÉLULA CONSTRUTIVA",0,IF(H56="ETAPA",OFFSET(C56,-1,0)+1,OFFSET(C56,-1,0))) -> 1 | D56: =IF(H56="ETAPA",0,IF(H56="SUBETAPA",OFFSET(D56,-1,0)+1,OFFSET(D56,-1,0))) -> 0 | E56: =IF(H56="Subetapa",0,IF(H56="serviço",OFFSET(E56,-1,0)+1,OFFSET(E56,-1,0))) -> 1 | H56: ETAPA | I56: =IF(H56="Unidade Construtiva",TEXT(A56,"00"),IF(H56="Célula Construtiva",TEXT(B56,"00"),IF(H56="Etapa",CONCATENATE(TEXT(B56,"00"),".",TEXT(C56,"000")),IF(H56="Subetapa",CONCATENATE(TEXT(B56,"00"),".",TEXT(C56,"000"),".",TEXT(D56,"000")),IF(H56="Serviço",CONCATENATE(TEXT(B56,"00"),".",TEXT(C56,"000"),".",TEXT(D56,"000"),".",TEXT(E56,"000")),""))))) -> 04.001 | J56: SUPRAESTRUTURA | N56: =IF(H56="Serviço",M56*L56,IF(H56="CÉLULA CONSTRUTIVA",SUMIFS($N$8:$N$335,$B$8:$B$335,B56,$H$8:$H$335,"Serviço"),IF(H56="ETAPA",SUMIFS($N$8:$N$335,$B$8:$B$335,B56,$C$8:$C$335,C56,$H$8:$H$335,"Serviço"),IF(H56="SUBETAPA",SUMIFS($N$8:$N$335,$B$8:$B$335,B56,$C$8:$C$335,C56,$D$8:$D$335,D56,$H$8:$H$335,"Serviço"),0)))) -> 6463760.8
A57: =IF($H57="UNIDADE CONSTRUTIVA",OFFSET(A57,-1,0)+1,LARGE(A$3:A46,1)) -> 0 | B57: =IF(H57="UNIDADE CONSTRUTIVA",0,IF(H57="CÉLULA CONSTRUTIVA",OFFSET(B57,-1,0)+1,OFFSET(B57,-1,0))) -> 4 | C57: =IF(H57="CÉLULA CONSTRUTIVA",0,IF(H57="ETAPA",OFFSET(C57,-1,0)+1,OFFSET(C57,-1,0))) -> 1 | D57: =IF(H57="ETAPA",0,IF(H57="SUBETAPA",OFFSET(D57,-1,0)+1,OFFSET(D57,-1,0))) -> 1 | E57: =IF(H57="Subetapa",0,IF(H57="serviço",OFFSET(E57,-1,0)+1,OFFSET(E57,-1,0))) -> 0 | H57: SUBETAPA | I57: =IF(H57="Unidade Construtiva",TEXT(A57,"00"),IF(H57="Célula Construtiva",TEXT(B57,"00"),IF(H57="Etapa",CONCATENATE(TEXT(B57,"00"),".",TEXT(C57,"000")),IF(H57="Subetapa",CONCATENATE(TEXT(B57,"00"),".",TEXT(C57,"000"),".",TEXT(D57,"000")),IF(H57="Serviço",CONCATENATE(TEXT(B57,"00"),".",TEXT(C57,"000"),".",TEXT(D57,"000"),".",TEXT(E57,"000")),""))))) -> 04.001.001 | J57: Forma | N57: =IF(H57="Serviço",M57*L57,IF(H57="CÉLULA CONSTRUTIVA",SUMIFS($N$8:$N$335,$B$8:$B$335,B57,$H$8:$H$335,"Serviço"),IF(H57="ETAPA",SUMIFS($N$8:$N$335,$B$8:$B$335,B57,$C$8:$C$335,C57,$H$8:$H$335,"Serviço"),IF(H57="SUBETAPA",SUMIFS($N$8:$N$335,$B$8:$B$335,B57,$C$8:$C$335,C57,$D$8:$D$335,D57,$H$8:$H$335,"Serviço"),0)))) -> 550229.6
A58: =IF($H58="UNIDADE CONSTRUTIVA",OFFSET(A58,-1,0)+1,LARGE(A$3:A56,1)) -> 0 | B58: =IF(H58="UNIDADE CONSTRUTIVA",0,IF(H58="CÉLULA CONSTRUTIVA",OFFSET(B58,-1,0)+1,OFFSET(B58,-1,0))) -> 4 | C58: =IF(H58="CÉLULA CONSTRUTIVA",0,IF(H58="ETAPA",OFFSET(C58,-1,0)+1,OFFSET(C58,-1,0))) -> 1 | D58: =IF(H58="ETAPA",0,IF(H58="SUBETAPA",OFFSET(D58,-1,0)+1,OFFSET(D58,-1,0))) -> 1 | E58: =IF(H58="Subetapa",0,IF(H58="serviço",OFFSET(E58,-1,0)+1,OFFSET(E58,-1,0))) -> 1 | H58: SERVIÇO | I58: =IF(H58="Unidade Construtiva",TEXT(A58,"00"),IF(H58="Célula Construtiva",TEXT(B58,"00"),IF(H58="Etapa",CONCATENATE(TEXT(B58,"00"),".",TEXT(C58,"000")),IF(H58="Subetapa",CONCATENATE(TEXT(B58,"00"),".",TEXT(C58,"000"),".",TEXT(D58,"000")),IF(H58="Serviço",CONCATENATE(TEXT(B58,"00"),".",TEXT(C58,"000"),".",TEXT(D58,"000"),".",TEXT(E58,"000")),""))))) -> 04.001.001.001 | J58: Fabricação de Fôrma para Pilares, em Chapa de Madeira Compensada Resinada, E=17mm | K58: m2 | L58: =Estrutura!H38 -> 1119.95 | M58: 110.39343 | N58: =IF(H58="Serviço",M58*L58,IF(H58="CÉLULA CONSTRUTIVA",SUMIFS($N$8:$N$335,$B$8:$B$335,B58,$H$8:$H$335,"Serviço"),IF(H58="ETAPA",SUMIFS($N$8:$N$335,$B$8:$B$335,B58,$C$8:$C$335,C58,$H$8:$H$335,"Serviço"),IF(H58="SUBETAPA",SUMIFS($N$8:$N$335,$B$8:$B$335,B58,$C$8:$C$335,C58,$D$8:$D$335,D58,$H$8:$H$335,"Serviço"),0)))) -> 123635.12 | O58: Considerado 1 jogo embasamento + 3 Jogos torre | P58: Lançado ERP
A59: =IF($H59="UNIDADE CONSTRUTIVA",OFFSET(A59,-1,0)+1,LARGE(A$3:A57,1)) -> 0 | B59: =IF(H59="UNIDADE CONSTRUTIVA",0,IF(H59="CÉLULA CONSTRUTIVA",OFFSET(B59,-1,0)+1,OFFSET(B59,-1,0))) -> 4 | C59: =IF(H59="CÉLULA CONSTRUTIVA",0,IF(H59="ETAPA",OFFSET(C59,-1,0)+1,OFFSET(C59,-1,0))) -> 1 | D59: =IF(H59="ETAPA",0,IF(H59="SUBETAPA",OFFSET(D59,-1,0)+1,OFFSET(D59,-1,0))) -> 1 | E59: =IF(H59="Subetapa",0,IF(H59="serviço",OFFSET(E59,-1,0)+1,OFFSET(E59,-1,0))) -> 2 | H59: SERVIÇO | I59: =IF(H59="Unidade Construtiva",TEXT(A59,"00"),IF(H59="Célula Construtiva",TEXT(B59,"00"),IF(H59="Etapa",CONCATENATE(TEXT(B59,"00"),".",TEXT(C59,"000")),IF(H59="Subetapa",CONCATENATE(TEXT(B59,"00"),".",TEXT(C59,"000"),".",TEXT(D59,"000")),IF(H59="Serviço",CONCATENATE(TEXT(B59,"00"),".",TEXT(C59,"000"),".",TEXT(D59,"000"),".",TEXT(E59,"000")),""))))) -> 04.001.001.002 | J59: Fabricação de Fôrma para Vigas, em Chapa de Madeira Compensada Resinada, E=17mm | K59: m2 | L59: =Estrutura!H39 -> 2167.46 | M59: 91.561495 | N59: =IF(H59="Serviço",M59*L59,IF(H59="CÉLULA CONSTRUTIVA",SUMIFS($N$8:$N$335,$B$8:$B$335,B59,$H$8:$H$335,"Serviço"),IF(H59="ETAPA",SUMIFS($N$8:$N$335,$B$8:$B$335,B59,$C$8:$C$335,C59,$H$8:$H$335,"Serviço"),IF(H59="SUBETAPA",SUMIFS($N$8:$N$335,$B$8:$B$335,B59,$C$8:$C$335,C59,$D$8:$D$335,D59,$H$8:$H$335,"Serviço"),0)))) -> 198455.88 | O59: Considerado 1 jogo embasamento + 3 Jogos torre | P59: Lançado ERP
