Workbook
Name \0: #REF!
Name \0: #REF!
Name \0: #REF!
Name \0: #REF!
Name \0: #REF!
Name \0: #REF!
Name \0: #REF!
Name \0: #REF!
Name \0: #REF!
Name \1: #REF!
Name \1: #REF!
Name \1: #REF!
Name \1: #REF!
Name \1: #REF!
Name \a: #REF!
Name \a: #REF!
Name \a: #REF!
Name \a: #REF!
Name \a: #REF!
Name \a: #REF!
Name \a: #REF!
Name \a: #REF!
Name \a: #REF!
Name \b: #REF!
Name \b: #REF!
Name \b: #REF!
Name \c: #REF!
Name \c: #REF!
Name \c: #REF!
Name \d: #REF!
Name \d: #REF!
Name \d: #REF!
Name \e: #REF!
Name \e: #REF!
Name \e: #REF!
Name \i: #REF!
Name \i: #REF!
Name \i: #REF!
Name \J: #REF!
Name \J: #REF!
Name \J: #REF!
Name \k: #REF!
Name \k: #REF!
Name \k: #REF!
Name \k: #REF!
Name \l: #N/A
Name \m: #REF!
Name \m: #REF!
Name \m: #REF!
Name \m: #REF!
Name \m: #REF!
Name \m: #REF!
Name \m: #REF!
Name \m: #REF!
Name \m: #REF!
Name \o: #REF!
Name \o: #REF!
Name \o: #REF!
Name \p: #REF!
Name \p: #REF!

Sheet Obra 
C1: Projeto | D1: Mowe
C2: Empresa | D2: MARTINS|FRANCEZ ENGENHARIA
C3: Revisão | D3: R00
A4: QUADRO DE ÁREAS
B6: Descrição | C6: Unidade | E6: Quantidade | G6: Imagens
B7: MESES DE OBRA | C7: MÊS | E7: 14
B8: ÁREA DO TERRENO | C8: M² | E8: 434.37
B9: ÁREA CONSTRUÍDA | C9: M² | E9: 329.57
B10: NÚMERO DE UNIDADES HABITACIONAIS | C10: UN | E10: 1
B11: NÚMERO DE UNIDADES COMERCIAIS | C11: UN | E11: 0
B12: ÁREA PRIVATIVA | C12: M² | E12: 329.57
B13: NÚMERO DE PAVIMENTOS | C13: UN | E13: 4
B15: Térreo | C15: M² | E15: 162.78
B16: Segundo Pavimento | C16: M² | E16: 166.79
B17: Cobertura | C17: M² | E17: 188.81
B18: Reservatório | C18: M² | E18: 10.04
B31: ETAPA | C31: VALOR ORÇADO | D31: % | E31: VALOR / m²
B32: GERENCIAMENTO TÉCNICO E ADMINISTRATIVO | C32: ='Ger_Tec e Adm'!N71 -> 243899.47 | D32: =C32/C$47 -> 0.15212846 | E32: =C32/$E$9 -> 740.0536
B33: INFRAESTRUTURA | C33: =Ger_Executivo!N8 -> 113009.8 | D33: =C33/C$47 -> 0.070488085 | E33: =C33/$E$9 -> 342.90075
B34: SUPRAESTRUTURA | C34: =Ger_Executivo!N35 -> 190194.42 | D34: =C34/C$47 -> 0.11863078 | E34: =C34/$E$9 -> 577.09871
B35: ALVENARIA | C35: =Ger_Executivo!N59 -> 60429.042 | D35: =C35/C$47 -> 0.037691665 | E35: =C35/$E$9 -> 183.35723
B36: INSTALAÇÕES ELÉTRICAS, HIDRÁULICAS, GLP E PREVENTIVAS | C36: =Ger_Executivo!N76+Ger_Executivo!N85+Ger_Executivo!N101 -> 207012.27 | D36: =C36/C$47 -> 0.12912065 | E36: =C36/$E$9 -> 628.12839
B37: CLIMATIZAÇÃO, EXAUSTÃO MECÂNICA E PRESSURIZAÇÃO | C37: =Ger_Executivo!N107 -> 11221.223 | D37: =C37/C$47 -> 0.0069990614 | E37: =C37/$E$9 -> 34.048072
B38: REVESTIMENTOS ARGAMASSADOS PISO E PAREDE | C38: =Ger_Executivo!N113 -> 80151.686 | D38: =C38/C$47 -> 0.049993354 | E38: =C38/$E$9 -> 243.2008
B39: IMPERMEABILIZAÇÃO | C39: =Ger_Executivo!N131 -> 70071.758 | D39: =C39/C$47 -> 0.043706157 | E39: =C39/$E$9 -> 212.61571
B40: ACABAMENTOS INTERNOS EM PAREDE E PISO | C40: =Ger_Executivo!N148 -> 150930.3 | D40: =C40/C$47 -> 0.094140399 | E40: =C40/$E$9 -> 457.96127
B41: ACABAMENTOS E REVESTIMENTOS INTERNOS EM TETO | C41: =Ger_Executivo!N174 -> 50473.202 | D41: =C41/C$47 -> 0.031481866 | E41: =C41/$E$9 -> 153.14865
B42: PINTURA INTERNA | C42: =Ger_Executivo!N187 -> 41028.634 | D42: =C42/C$47 -> 0.025590965 | E42: =C42/$E$9 -> 124.49141
B43: REVESTIMENTOS E ACABAMENTOS DE FACHADA | C43: =Ger_Executivo!N216 -> 184438.31 | D43: =C43/C$47 -> 0.11504049 | E43: =C43/$E$9 -> 559.63318
B44: ESQUADRIAS, VIDROS E FERRAGENS | C44: =Ger_Executivo!N197 -> 137257 | D44: =C44/C$47 -> 0.085611897 | E44: =C44/$E$9 -> 416.47299
B45: SERVIÇOS COMPLEMENTARES | C45: =Ger_Executivo!N234 -> 36475.844 | D45: =C45/C$47 -> 0.022751234 | E45: =C45/$E$9 -> 110.67708
B46: IMPREVISTOS | C46: =Ger_Executivo!N250 -> 26653.87 | D46: =C46/C$47 -> 0.016624932 | E46: =C46/$E$9 -> 80.874685
B47: TOTAL | C47: =SUM(C32:C46) -> 1603246.8 | D47: =SUM(D32:D46) -> 1 | E47: =SUM(E32:E46) -> 4864.6625
B48: CUB/SC | C48: 2978.02 | D48: 45870 | E48: =ROUNDUP(+E47/C48,2)&" CUB" -> 1,64 CUB
C53: =SUM(C33:C45)*0.19 -> 253211.76 | D53: =190649.26/964799.8 -> 0.197605
C54: =C53*0.11 -> 27853.294

Sheet EAP Análise
A1: ETAPA | B1: VALOR ORÇADO | C1: % | D1: VALOR / m²
A2: GERENCIAMENTO TÉCNICO E ADMINISTRATIVO | B2: ='Obra '!C32 -> 243899.47 | C2: =B2/$B$27 -> 0.15212846 | D2: =B2/'Obra '!$E$9 -> 740.0536
A3: MOVIMENTAÇÃO DE TERRA | B3: =Ger_Executivo!N9 -> 10084.168 | C3: =B3/$B$27 -> 0.0062898411 | D3: =B3/'Obra '!$E$9 -> 30.597954
A4: INFRAESTRUTURA | B4: =Ger_Executivo!N19 -> 102925.63 | C4: =B4/$B$27 -> 0.064198244 | D4: =B4/'Obra '!$E$9 -> 312.30279
A5: SUPRAESTRUTURA | B5: =Ger_Executivo!N35 -> 190194.42 | C5: =B5/$B$27 -> 0.11863078 | D5: =B5/'Obra '!$E$9 -> 577.09871
A6: ALVENARIA | B6: =Ger_Executivo!N59 -> 60429.042 | C6: =B6/$B$27 -> 0.037691665 | D6: =B6/'Obra '!$E$9 -> 183.35723
A7: INSTALAÇÕES ELÉTRICAS, HIDRÁULICAS, GLP E PREVENTIVAS | B7: =Ger_Executivo!N76+Ger_Executivo!N85+Ger_Executivo!N101-B10-B23 -> 127201.76 | C7: =B7/$B$27 -> 0.079340098 | D7: =B7/'Obra '!$E$9 -> 385.9628
A8: CLIMATIZAÇÃO, EXAUSTÃO MECÂNICA E PRESSURIZAÇÃO | B8: =Ger_Executivo!N107 -> 11221.223 | C8: =B8/$B$27 -> 0.0069990614 | D8: =B8/'Obra '!$E$9 -> 34.048072
A9: EQUIPAMENTOS E SISTEMAS ESPECIAIS | B9: 0 | C9: =B9/$B$27 -> 0 | D9: =B9/'Obra '!$E$9 -> 0
A10: INSTALAÇÕES ESPECIAIS | B10: =Ger_Executivo!N97 -> 10955.698 | C10: =B10/$B$27 -> 0.0068334444 | D10: =B10/'Obra '!$E$9 -> 33.242401
A11: REVESTIMENTOS ARGAMASSADOS PISO | B11: =SUMIF(Ger_Executivo!Q:Q,A11,Ger_Executivo!N:N) -> 26511.96 | C11: =B11/$B$27 -> 0.016536418 | D11: =B11/'Obra '!$E$9 -> 80.444092
A12: REVESTIMENTOS ARGAMASSADOS PAREDE | B12: =SUMIF(Ger_Executivo!Q:Q,A12,Ger_Executivo!N:N) -> 33446.834 | C12: =B12/$B$27 -> 0.020861937 | D12: =B12/'Obra '!$E$9 -> 101.48628
A13: REVESTIMENTOS ARGAMASSADOS TETO | B13: =SUMIF(Ger_Executivo!Q:Q,A13,Ger_Executivo!N:N) -> 380.6722 | C13: =B13/$B$27 -> 0.0002374383 | D13: =B13/'Obra '!$E$9 -> 1.1550572
A14: IMPERMEABILIZAÇÃO | B14: =SUMIF(Ger_Executivo!Q:Q,A14,Ger_Executivo!N:N) -> 90264.65 | C14: =B14/$B$27 -> 0.056301156 | D14: =B14/'Obra '!$E$9 -> 273.88612
A15: ACABAMENTOS INTERNOS EM PAREDE | B15: =SUMIF(Ger_Executivo!Q:Q,A15,Ger_Executivo!N:N) -> 28197.117 | C15: =B15/$B$27 -> 0.017587508 | D15: =B15/'Obra '!$E$9 -> 85.557292
A16: ACABAMENTOS EM PISOS E PAVIMENTAÇÕES | B16: =SUMIF(Ger_Executivo!Q:Q,A16,Ger_Executivo!N:N) -> 122733.18 | C16: =B16/$B$27 -> 0.076552891 | D16: =B16/'Obra '!$E$9 -> 372.40398
A17: ACABAMENTOS INTERNOS EM TETO | B17: =SUMIF(Ger_Executivo!Q:Q,A17,Ger_Executivo!N:N) -> 50092.53 | C17: =B17/$B$27 -> 0.031244428 | D17: =B17/'Obra '!$E$9 -> 151.9936
A18: PINTURA INTERNA | B18: =SUMIF(Ger_Executivo!Q:Q,A18,Ger_Executivo!N:N) -> 41028.634 | C18: =B18/$B$27 -> 0.025590965 | D18: =B18/'Obra '!$E$9 -> 124.49141
A19: PINTURA DE FACHADA | B19: =SUMIF(Ger_Executivo!Q:Q,A19,Ger_Executivo!N:N) -> 49075.814 | C19: =B19/$B$27 -> 0.030610268 | D19: =B19/'Obra '!$E$9 -> 148.90862
A20: REVESTIMENTOS ARGAMASSADOS DE FACHADA | B20: =SUMIF(Ger_Executivo!Q:Q,A20,Ger_Executivo!N:N) -> 48409.092 | C20: =B20/$B$27 -> 0.03019441 | D20: =B20/'Obra '!$E$9 -> 146.88561
A21: ACABAMENTOS DE FACHADA | B21: =SUMIF(Ger_Executivo!Q:Q,A21,Ger_Executivo!N:N) -> 100308.05 | C21: =B21/$B$27 -> 0.06256557 | D21: =B21/'Obra '!$E$9 -> 304.36038
A22: ESQUADRIAS, VIDROS E FERRAGENS | B22: =SUMIF(Ger_Executivo!Q:Q,A22,Ger_Executivo!N:N) -> 137257 | C22: =B22/$B$27 -> 0.085611897 | D22: =B22/'Obra '!$E$9 -> 416.47299
A23: LOUÇAS E METAIS | B23: =Ger_Executivo!N81 -> 68854.816 | C23: =B23/$B$27 -> 0.042947109 | D23: =B23/'Obra '!$E$9 -> 208.92319
A24: COBERTURA | B24: =Ger_Executivo!N379 -> 0 | C24: =B24/$B$27 -> 0 | D24: =B24/'Obra '!$E$9 -> 0
A25: SERVIÇOS COMPLEMENTARES | B25: =Ger_Executivo!N242+Ger_Executivo!N236 -> 23121.192 | C25: =B25/$B$27 -> 0.01442148 | D25: =B25/'Obra '!$E$9 -> 70.155632
A26: IMPREVISTOS | B26: =Ger_Executivo!N250 -> 26653.87 | C26: =B26/$B$27 -> 0.016624932 | D26: =B26/'Obra '!$E$9 -> 80.874685
A27: TOTAL | B27: =SUM(B2:B26) -> 1603246.8 | C27: =SUM(C2:C26) -> 1 | D27: =SUM(D2:D26) -> 4864.6625
A28: CUB/SC | B28: 2978.02 | C28: 45870 | D28: =ROUNDUP(+D27/B28,2)&" CUB" -> 1,64 CUB

Sheet Ensaios 
C1: Projeto | D1: ='Obra '!D1 -> Mowe
C2: Empresa | D2: ='Obra '!D2 -> MARTINS|FRANCEZ ENGENHARIA
C3: Revisão | D3: ='Obra '!D3 -> R00
A4: ENSAIOS
A5: Item | B5: Descrição/Especificação | C5: Unid. | D5: V. Unit. (R$) | E5: Qtde. | F5: V. Total (R$) | G5: Observações
B6: CONTROLE TECNOLÓGICO - CONCRETO | F6: =SUM(F7:F11) -> 3490
A7: 1 | B7: Laudo e ART | C7: vb | D7: 1450 | E7: 1 | F7: =$D7*E7 -> 1450
A8: =A7+1 -> 2 | B8: Controle Tecnologico Infraestrutura - Coleta materiais da obra | C8: unid. | D8: 20 | E8: =ROUNDUP(Ger_Executivo!L32/8,0)*4 -> 16 | F8: =$D8*E8 -> 320 | G8: 4 CPs por caminhão betoneira de 8m³
A9: =#REF!+1 -> #REF! | B9: Controle Tecnologico Supraestrutura - Coleta materiais da obra | C9: unid. | D9: 20 | E9: =ROUNDUP(Ger_Executivo!L54/8,0)*4 -> 32 | F9: =$D9*E9 -> 640 | G9: 4 CPs por caminhão betoneira de 8m³
A10: =A8+1 -> 3 | B10: Controle Tecnológico - Ensaio de concreto endurecido/grouth - compressão simples / Detalhe: Concreto | C10: cps | D10: 12.5 | E10: =E8+E9 -> 48 | F10: =$D10*E10 -> 600
A11: =A10+1 -> 4 | B11: Determinação do módulo de deformação tangente inicial (Eci) (módulo de elasticidade), Incluindo Avaliação Estática dos Resultados (NBR 8522 e NBR 12655) | C11: ensaio | D11: 480 | E11: 1 | F11: =$D11*E11 -> 480 | G11: A cada 5 pav. (e quando houver troca de fornecedor)
C12: SUBTOTAL: | F12: =F6 -> 3490

Sheet CANTEIRO
A1: Obra | B1: ='Obra '!D1 -> Mowe
A2: Empresa | B2: ='Obra '!D2 -> MARTINS|FRANCEZ ENGENHARIA
A3: Revisão | B3: ='Obra '!D3 -> R00
A4: Instalações de canteiro
A5: Instalações de canteiro
B7: Descrição | C7: Unidade | D7: Quantidade
B8: Produtividade média | C8: m2 / mês | D8: ='Obra '!$E$9/'Obra '!$E$7 -> 23.540714
B9: Pm | C9: h/m2 | D9: 49
B10: Numero de funcionários | C10: un | D10: =ROUNDUP(('Obra '!E9*D9)/'Obra '!E7/180,) -> 7
B11: Equipe administrativa | C11: un | D11: 2
B12: Pontos de água e esgoto | C12: un | D12: =ROUNDUP($D$10/20,0) -> 1 | E12: 20 funcionários/ponto
B13: Bebedouro | C13: un | D13: =ROUNDUP('Obra '!$E$13/5,0) -> 1 | E13: 1 / 5 pav.
B14: Ferramentas | C14: R$ | D14: =800*D10 -> 5600 | E14: 800,00/func.
B15: EPI | C15: R$ | D15: =500*(D10+D11) -> 4500 | E15: 500,00/func.
B16: Banheiro | C16: un | D16: =ROUNDUP($D$10/20,0) -> 1 | E16: 1/20 func

Sheet Ger_Tec e Adm
G4: PROJETO: | I4: ='Obra '!D1 -> Mowe | O4: REVISÃO: | P4: DATA
G5: EMPRESA: | I5: ='Obra '!D2 -> MARTINS|FRANCEZ ENGENHARIA | O5: ='Obra '!D3 -> R00 | P5: 45551
A6: Unidade Construtiva | B6: Célula Construtiva | C6: Etapa | D6: Subetapa | E6: Serviço | G6: GERENCIAMENTO EXECUTIVO
A7: 0 | B7: 0 | C7: 0 | D7: 0 | E7: 0 | G7: Atalho | H7: NIVEL | I7: Item | J7: Descrição | K7: Unidade | L7: Quant. | M7: Preço un | N7: Total | O7: Considerações | P7: Situação
A8: =IF($H8="UNIDADE CONSTRUTIVA",OFFSET(A8,-1,0)+1,LARGE(A$3:A7,1)) -> 0 | B8: =IF(H8="UNIDADE CONSTRUTIVA",0,IF(H8="CÉLULA CONSTRUTIVA",OFFSET(B8,-1,0)+1,OFFSET(B8,-1,0))) -> 1 | C8: =IF(H8="CÉLULA CONSTRUTIVA",0,IF(H8="ETAPA",OFFSET(C8,-1,0)+1,OFFSET(C8,-1,0))) -> 0 | D8: =IF(H8="ETAPA",0,IF(H8="SUBETAPA",OFFSET(D8,-1,0)+1,OFFSET(D8,-1,0))) -> 0 | E8: =IF(H8="Subetapa",0,IF(H8="serviço",OFFSET(E8,-1,0)+1,OFFSET(E8,-1,0))) -> 0 | H8: CÉLULA CONSTRUTIVA | I8: =IF(H8="Unidade Construtiva",TEXT(A8,"00"),IF(H8="Célula Construtiva",TEXT(B8,"00"),IF(H8="Etapa",CONCATENATE(TEXT(B8,"00"),".",TEXT(C8,"000")),IF(H8="Subetapa",CONCATENATE(TEXT(B8,"00"),".",TEXT(C8,"000"),".",TEXT(D8,"000")),IF(H8="Serviço",CONCATENATE(TEXT(B8,"00"),".",TEXT(C8,"000"),".",TEXT(D8,"000"),".",TEXT(E8,"000")),""))))) -> 01 | J8: SERVIÇOS TÉCNICOS | N8: =IF(H8="Serviço",M8*L8,IF(H8="CÉLULA CONSTRUTIVA",SUMIFS($N$8:$N$368,$B$8:$B$368,B8,$H$8:$H$368,"Serviço"),IF(H8="ETAPA",SUMIFS($N$8:$N$368,$B$8:$B$368,B8,$C$8:$C$368,C8,$H$8:$H$368,"Serviço"),IF(H8="SUBETAPA",SUMIFS($N$8:$N$368,$B$8:$B$368,B8,$C$8:$C$368,C8,$D$8:$D$368,D8,$H$8:$H$368,"Serviço"),0)))) -> 103622.51 | Q8: =N8/'Obra '!$E$9 -> 314.4173
A9: =IF($H9="UNIDADE CONSTRUTIVA",OFFSET(A9,-1,0)+1,LARGE(A$3:A8,1)) -> 0 | B9: =IF(H9="UNIDADE CONSTRUTIVA",0,IF(H9="CÉLULA CONSTRUTIVA",OFFSET(B9,-1,0)+1,OFFSET(B9,-1,0))) -> 1 | C9: =IF(H9="CÉLULA CONSTRUTIVA",0,IF(H9="ETAPA",OFFSET(C9,-1,0)+1,OFFSET(C9,-1,0))) -> 1 | D9: =IF(H9="ETAPA",0,IF(H9="SUBETAPA",OFFSET(D9,-1,0)+1,OFFSET(D9,-1,0))) -> 0 | E9: =IF(H9="Subetapa",0,IF(H9="serviço",OFFSET(E9,-1,0)+1,OFFSET(E9,-1,0))) -> 0 | H9: ETAPA | I9: =IF(H9="Unidade Construtiva",TEXT(A9,"00"),IF(H9="Célula Construtiva",TEXT(B9,"00"),IF(H9="Etapa",CONCATENATE(TEXT(B9,"00"),".",TEXT(C9,"000")),IF(H9="Subetapa",CONCATENATE(TEXT(B9,"00"),".",TEXT(C9,"000"),".",TEXT(D9,"000")),IF(H9="Serviço",CONCATENATE(TEXT(B9,"00"),".",TEXT(C9,"000"),".",TEXT(D9,"000"),".",TEXT(E9,"000")),""))))) -> 01.001 | J9: ESTUDOS, PROJETOS E CONSULTORIAS | N9: =IF(H9="Serviço",M9*L9,IF(H9="CÉLULA CONSTRUTIVA",SUMIFS($N$8:$N$368,$B$8:$B$368,B9,$H$8:$H$368,"Serviço"),IF(H9="ETAPA",SUMIFS($N$8:$N$368,$B$8:$B$368,B9,$C$8:$C$368,C9,$H$8:$H$368,"Serviço"),IF(H9="SUBETAPA",SUMIFS($N$8:$N$368,$B$8:$B$368,B9,$C$8:$C$368,C9,$D$8:$D$368,D9,$H$8:$H$368,"Serviço"),0)))) -> 78606.076
A10: =IF($H10="UNIDADE CONSTRUTIVA",OFFSET(A10,-1,0)+1,LARGE(A$3:A9,1)) -> 0 | B10: =IF(H10="UNIDADE CONSTRUTIVA",0,IF(H10="CÉLULA CONSTRUTIVA",OFFSET(B10,-1,0)+1,OFFSET(B10,-1,0))) -> 1 | C10: =IF(H10="CÉLULA CONSTRUTIVA",0,IF(H10="ETAPA",OFFSET(C10,-1,0)+1,OFFSET(C10,-1,0))) -> 1 | D10: =IF(H10="ETAPA",0,IF(H10="SUBETAPA",OFFSET(D10,-1,0)+1,OFFSET(D10,-1,0))) -> 1 | E10: =IF(H10="Subetapa",0,IF(H10="serviço",OFFSET(E10,-1,0)+1,OFFSET(E10,-1,0))) -> 0 | H10: SUBETAPA | I10: =IF(H10="Unidade Construtiva",TEXT(A10,"00"),IF(H10="Célula Construtiva",TEXT(B10,"00"),IF(H10="Etapa",CONCATENATE(TEXT(B10,"00"),".",TEXT(C10,"000")),IF(H10="Subetapa",CONCATENATE(TEXT(B10,"00"),".",TEXT(C10,"000"),".",TEXT(D10,"000")),IF(H10="Serviço",CONCATENATE(TEXT(B10,"00"),".",TEXT(C10,"000"),".",TEXT(D10,"000"),".",TEXT(E10,"000")),""))))) -> 01.001.001 | J10: Estudos | N10: =IF(H10="Serviço",M10*L10,IF(H10="CÉLULA CONSTRUTIVA",SUMIFS($N$8:$N$368,$B$8:$B$368,B10,$H$8:$H$368,"Serviço"),IF(H10="ETAPA",SUMIFS($N$8:$N$368,$B$8:$B$368,B10,$C$8:$C$368,C10,$H$8:$H$368,"Serviço"),IF(H10="SUBETAPA",SUMIFS($N$8:$N$368,$B$8:$B$368,B10,$C$8:$C$368,C10,$D$8:$D$368,D10,$H$8:$H$368,"Serviço"),0)))) -> 8070.3784
A11: =IF($H11="UNIDADE CONSTRUTIVA",OFFSET(A11,-1,0)+1,LARGE(A$3:A10,1)) -> 0 | B11: =IF(H11="UNIDADE CONSTRUTIVA",0,IF(H11="CÉLULA CONSTRUTIVA",OFFSET(B11,-1,0)+1,OFFSET(B11,-1,0))) -> 1 | C11: =IF(H11="CÉLULA CONSTRUTIVA",0,IF(H11="ETAPA",OFFSET(C11,-1,0)+1,OFFSET(C11,-1,0))) -> 1 | D11: =IF(H11="ETAPA",0,IF(H11="SUBETAPA",OFFSET(D11,-1,0)+1,OFFSET(D11,-1,0))) -> 1 | E11: =IF(H11="Subetapa",0,IF(H11="serviço",OFFSET(E11,-1,0)+1,OFFSET(E11,-1,0))) -> 1 | H11: SERVIÇO | I11: =IF(H11="Unidade Construtiva",TEXT(A11,"00"),IF(H11="Célula Construtiva",TEXT(B11,"00"),IF(H11="Etapa",CONCATENATE(TEXT(B11,"00"),".",TEXT(C11,"000")),IF(H11="Subetapa",CONCATENATE(TEXT(B11,"00"),".",TEXT(C11,"000"),".",TEXT(D11,"000")),IF(H11="Serviço",CONCATENATE(TEXT(B11,"00"),".",TEXT(C11,"000"),".",TEXT(D11,"000"),".",TEXT(E11,"000")),""))))) -> 01.001.001.001 | J11: Levantamento Topográfico | K11: vb | L11: 1 | M11: 3769.3983 | N11: =IF(H11="Serviço",M11*L11,IF(H11="CÉLULA CONSTRUTIVA",SUMIFS($N$8:$N$368,$B$8:$B$368,B11,$H$8:$H$368,"Serviço"),IF(H11="ETAPA",SUMIFS($N$8:$N$368,$B$8:$B$368,B11,$C$8:$C$368,C11,$H$8:$H$368,"Serviço"),IF(H11="SUBETAPA",SUMIFS($N$8:$N$368,$B$8:$B$368,B11,$C$8:$C$368,C11,$D$8:$D$368,D11,$H$8:$H$368,"Serviço"),0)))) -> 3769.3983 | O11: Estimado com base em índices históricos | P11: Finalizado
A12: =IF($H12="UNIDADE CONSTRUTIVA",OFFSET(A12,-1,0)+1,LARGE(A$3:A11,1)) -> 0 | B12: =IF(H12="UNIDADE CONSTRUTIVA",0,IF(H12="CÉLULA CONSTRUTIVA",OFFSET(B12,-1,0)+1,OFFSET(B12,-1,0))) -> 1 | C12: =IF(H12="CÉLULA CONSTRUTIVA",0,IF(H12="ETAPA",OFFSET(C12,-1,0)+1,OFFSET(C12,-1,0))) -> 1 | D12: =IF(H12="ETAPA",0,IF(H12="SUBETAPA",OFFSET(D12,-1,0)+1,OFFSET(D12,-1,0))) -> 1 | E12: =IF(H12="Subetapa",0,IF(H12="serviço",OFFSET(E12,-1,0)+1,OFFSET(E12,-1,0))) -> 2 | H12: SERVIÇO | I12: =IF(H12="Unidade Construtiva",TEXT(A12,"00"),IF(H12="Célula Construtiva",TEXT(B12,"00"),IF(H12="Etapa",CONCATENATE(TEXT(B12,"00"),".",TEXT(C12,"000")),IF(H12="Subetapa",CONCATENATE(TEXT(B12,"00"),".",TEXT(C12,"000"),".",TEXT(D12,"000")),IF(H12="Serviço",CONCATENATE(TEXT(B12,"00"),".",TEXT(C12,"000"),".",TEXT(D12,"000"),".",TEXT(E12,"000")),""))))) -> 01.001.001.002 | J12: Sondagem do terreno | K12: vb | L12: 1 | M12: 4300.9801 | N12: =IF(H12="Serviço",M12*L12,IF(H12="CÉLULA CONSTRUTIVA",SUMIFS($N$8:$N$368,$B$8:$B$368,B12,$H$8:$H$368,"Serviço"),IF(H12="ETAPA",SUMIFS($N$8:$N$368,$B$8:$B$368,B12,$C$8:$C$368,C12,$H$8:$H$368,"Serviço"),IF(H12="SUBETAPA",SUMIFS($N$8:$N$368,$B$8:$B$368,B12,$C$8:$C$368,C12,$D$8:$D$368,D12,$H$8:$H$368,"Serviço"),0)))) -> 4300.9801 | O12: Estimado com base em índices históricos | P12: Finalizado
A13: =IF($H13="UNIDADE CONSTRUTIVA",OFFSET(A13,-1,0)+1,LARGE(A$3:A12,1)) -> 0 | B13: =IF(H13="UNIDADE CONSTRUTIVA",0,IF(H13="CÉLULA CONSTRUTIVA",OFFSET(B13,-1,0)+1,OFFSET(B13,-1,0))) -> 1 | C13: =IF(H13="CÉLULA CONSTRUTIVA",0,IF(H13="ETAPA",OFFSET(C13,-1,0)+1,OFFSET(C13,-1,0))) -> 1 | D13: =IF(H13="ETAPA",0,IF(H13="SUBETAPA",OFFSET(D13,-1,0)+1,OFFSET(D13,-1,0))) -> 2 | E13: =IF(H13="Subetapa",0,IF(H13="serviço",OFFSET(E13,-1,0)+1,OFFSET(E13,-1,0))) -> 0 | H13: SUBETAPA | I13: =IF(H13="Unidade Construtiva",TEXT(A13,"00"),IF(H13="Célula Construtiva",TEXT(B13,"00"),IF(H13="Etapa",CONCATENATE(TEXT(B13,"00"),".",TEXT(C13,"000")),IF(H13="Subetapa",CONCATENATE(TEXT(B13,"00"),".",TEXT(C13,"000"),".",TEXT(D13,"000")),IF(H13="Serviço",CONCATENATE(TEXT(B13,"00"),".",TEXT(C13,"000"),".",TEXT(D13,"000"),".",TEXT(E13,"000")),""))))) -> 01.001.002 | J13: Projetos | N13: =IF(H13="Serviço",M13*L13,IF(H13="CÉLULA CONSTRUTIVA",SUMIFS($N$8:$N$368,$B$8:$B$368,B13,$H$8:$H$368,"Serviço"),IF(H13="ETAPA",SUMIFS($N$8:$N$368,$B$8:$B$368,B13,$C$8:$C$368,C13,$H$8:$H$368,"Serviço"),IF(H13="SUBETAPA",SUMIFS($N$8:$N$368,$B$8:$B$368,B13,$C$8:$C$368,C13,$D$8:$D$368,D13,$H$8:$H$368,"Serviço"),0)))) -> 49545.697
A14: =IF($H14="UNIDADE CONSTRUTIVA",OFFSET(A14,-1,0)+1,LARGE(A$3:A13,1)) -> 0 | B14: =IF(H14="UNIDADE CONSTRUTIVA",0,IF(H14="CÉLULA CONSTRUTIVA",OFFSET(B14,-1,0)+1,OFFSET(B14,-1,0))) -> 1 | C14: =IF(H14="CÉLULA CONSTRUTIVA",0,IF(H14="ETAPA",OFFSET(C14,-1,0)+1,OFFSET(C14,-1,0))) -> 1 | D14: =IF(H14="ETAPA",0,IF(H14="SUBETAPA",OFFSET(D14,-1,0)+1,OFFSET(D14,-1,0))) -> 2 | E14: =IF(H14="Subetapa",0,IF(H14="serviço",OFFSET(E14,-1,0)+1,OFFSET(E14,-1,0))) -> 1 | H14: SERVIÇO | I14: =IF(H14="Unidade Construtiva",TEXT(A14,"00"),IF(H14="Célula Construtiva",TEXT(B14,"00"),IF(H14="Etapa",CONCATENATE(TEXT(B14,"00"),".",TEXT(C14,"000")),IF(H14="Subetapa",CONCATENATE(TEXT(B14,"00"),".",TEXT(C14,"000"),".",TEXT(D14,"000")),IF(H14="Serviço",CONCATENATE(TEXT(B14,"00"),".",TEXT(C14,"000"),".",TEXT(D14,"000"),".",TEXT(E14,"000")),""))))) -> 01.001.002.001 | J14: Projeto arquitetônico interiores/ambientação | K14: vb | L14: 1 | M14: 24522.284 | N14: =IF(H14="Serviço",M14*L14,IF(H14="CÉLULA CONSTRUTIVA",SUMIFS($N$8:$N$368,$B$8:$B$368,B14,$H$8:$H$368,"Serviço"),IF(H14="ETAPA",SUMIFS($N$8:$N$368,$B$8:$B$368,B14,$C$8:$C$368,C14,$H$8:$H$368,"Serviço"),IF(H14="SUBETAPA",SUMIFS($N$8:$N$368,$B$8:$B$368,B14,$C$8:$C$368,C14,$D$8:$D$368,D14,$H$8:$H$368,"Serviço"),0)))) -> 24522.284 | O14: Estimado com base em índices históricos | P14: Finalizado
A15: =IF($H15="UNIDADE CONSTRUTIVA",OFFSET(A15,-1,0)+1,LARGE(A$3:A14,1)) -> 0 | B15: =IF(H15="UNIDADE CONSTRUTIVA",0,IF(H15="CÉLULA CONSTRUTIVA",OFFSET(B15,-1,0)+1,OFFSET(B15,-1,0))) -> 1 | C15: =IF(H15="CÉLULA CONSTRUTIVA",0,IF(H15="ETAPA",OFFSET(C15,-1,0)+1,OFFSET(C15,-1,0))) -> 1 | D15: =IF(H15="ETAPA",0,IF(H15="SUBETAPA",OFFSET(D15,-1,0)+1,OFFSET(D15,-1,0))) -> 2 | E15: =IF(H15="Subetapa",0,IF(H15="serviço",OFFSET(E15,-1,0)+1,OFFSET(E15,-1,0))) -> 2 | H15: SERVIÇO | I15: =IF(H15="Unidade Construtiva",TEXT(A15,"00"),IF(H15="Célula Construtiva",TEXT(B15,"00"),IF(H15="Etapa",CONCATENATE(TEXT(B15,"00"),".",TEXT(C15,"000")),IF(H15="Subetapa",CONCATENATE(TEXT(B15,"00"),".",TEXT(C15,"000"),".",TEXT(D15,"000")),IF(H15="Serviço",CONCATENATE(TEXT(B15,"00"),".",TEXT(C15,"000"),".",TEXT(D15,"000"),".",TEXT(E15,"000")),""))))) -> 01.001.002.002 | J15: Projeto Estrutura | K15: vb | L15: 1 | M15: 8348.0116 | N15: =IF(H15="Serviço",M15*L15,IF(H15="CÉLULA CONSTRUTIVA",SUMIFS($N$8:$N$368,$B$8:$B$368,B15,$H$8:$H$368,"Serviço"),IF(H15="ETAPA",SUMIFS($N$8:$N$368,$B$8:$B$368,B15,$C$8:$C$368,C15,$H$8:$H$368,"Serviço"),IF(H15="SUBETAPA",SUMIFS($N$8:$N$368,$B$8:$B$368,B15,$C$8:$C$368,C15,$D$8:$D$368,D15,$H$8:$H$368,"Serviço"),0)))) -> 8348.0116 | O15: Estimado com base em índices históricos | P15: Finalizado
A16: =IF($H16="UNIDADE CONSTRUTIVA",OFFSET(A16,-1,0)+1,LARGE(A$3:A15,1)) -> 0 | B16: =IF(H16="UNIDADE CONSTRUTIVA",0,IF(H16="CÉLULA CONSTRUTIVA",OFFSET(B16,-1,0)+1,OFFSET(B16,-1,0))) -> 1 | C16: =IF(H16="CÉLULA CONSTRUTIVA",0,IF(H16="ETAPA",OFFSET(C16,-1,0)+1,OFFSET(C16,-1,0))) -> 1 | D16: =IF(H16="ETAPA",0,IF(H16="SUBETAPA",OFFSET(D16,-1,0)+1,OFFSET(D16,-1,0))) -> 2 | E16: =IF(H16="Subetapa",0,IF(H16="serviço",OFFSET(E16,-1,0)+1,OFFSET(E16,-1,0))) -> 3 | H16: SERVIÇO | I16: =IF(H16="Unidade Construtiva",TEXT(A16,"00"),IF(H16="Célula Construtiva",TEXT(B16,"00"),IF(H16="Etapa",CONCATENATE(TEXT(B16,"00"),".",TEXT(C16,"000")),IF(H16="Subetapa",CONCATENATE(TEXT(B16,"00"),".",TEXT(C16,"000"),".",TEXT(D16,"000")),IF(H16="Serviço",CONCATENATE(TEXT(B16,"00"),".",TEXT(C16,"000"),".",TEXT(D16,"000"),".",TEXT(E16,"000")),""))))) -> 01.001.002.003 | J16: Projeto Fundações | K16: vb | L16: 1 | M16: 2066.3815 | N16: =IF(H16="Serviço",M16*L16,IF(H16="CÉLULA CONSTRUTIVA",SUMIFS($N$8:$N$368,$B$8:$B$368,B16,$H$8:$H$368,"Serviço"),IF(H16="ETAPA",SUMIFS($N$8:$N$368,$B$8:$B$368,B16,$C$8:$C$368,C16,$H$8:$H$368,"Serviço"),IF(H16="SUBETAPA",SUMIFS($N$8:$N$368,$B$8:$B$368,B16,$C$8:$C$368,C16,$D$8:$D$368,D16,$H$8:$H$368,"Serviço"),0)))) -> 2066.3815 | O16: Estimado com base em índices históricos | P16: Finalizado
A17: =IF($H17="UNIDADE CONSTRUTIVA",OFFSET(A17,-1,0)+1,LARGE(A$3:A16,1)) -> 0 | B17: =IF(H17="UNIDADE CONSTRUTIVA",0,IF(H17="CÉLULA CONSTRUTIVA",OFFSET(B17,-1,0)+1,OFFSET(B17,-1,0))) -> 1 | C17: =IF(H17="CÉLULA CONSTRUTIVA",0,IF(H17="ETAPA",OFFSET(C17,-1,0)+1,OFFSET(C17,-1,0))) -> 1 | D17: =IF(H17="ETAPA",0,IF(H17="SUBETAPA",OFFSET(D17,-1,0)+1,OFFSET(D17,-1,0))) -> 2 | E17: =IF(H17="Subetapa",0,IF(H17="serviço",OFFSET(E17,-1,0)+1,OFFSET(E17,-1,0))) -> 4 | H17: SERVIÇO | I17: =IF(H17="Unidade Construtiva",TEXT(A17,"00"),IF(H17="Célula Construtiva",TEXT(B17,"00"),IF(H17="Etapa",CONCATENATE(TEXT(B17,"00"),".",TEXT(C17,"000")),IF(H17="Subetapa",CONCATENATE(TEXT(B17,"00"),".",TEXT(C17,"000"),".",TEXT(D17,"000")),IF(H17="Serviço",CONCATENATE(TEXT(B17,"00"),".",TEXT(C17,"000"),".",TEXT(D17,"000"),".",TEXT(E17,"000")),""))))) -> 01.001.002.004 | J17: Projeto elétrico | K17: vb | L17: 1 | M17: 7304.5102 | N17: =IF(H17="Serviço",M17*L17,IF(H17="CÉLULA CONSTRUTIVA",SUMIFS($N$8:$N$368,$B$8:$B$368,B17,$H$8:$H$368,"Serviço"),IF(H17="ETAPA",SUMIFS($N$8:$N$368,$B$8:$B$368,B17,$C$8:$C$368,C17,$H$8:$H$368,"Serviço"),IF(H17="SUBETAPA",SUMIFS($N$8:$N$368,$B$8:$B$368,B17,$C$8:$C$368,C17,$D$8:$D$368,D17,$H$8:$H$368,"Serviço"),0)))) -> 7304.5102 | O17: Estimado com base em índices históricos | P17: Finalizado
A18: =IF($H18="UNIDADE CONSTRUTIVA",OFFSET(A18,-1,0)+1,LARGE(A$3:A17,1)) -> 0 | B18: =IF(H18="UNIDADE CONSTRUTIVA",0,IF(H18="CÉLULA CONSTRUTIVA",OFFSET(B18,-1,0)+1,OFFSET(B18,-1,0))) -> 1 | C18: =IF(H18="CÉLULA CONSTRUTIVA",0,IF(H18="ETAPA",OFFSET(C18,-1,0)+1,OFFSET(C18,-1,0))) -> 1 | D18: =IF(H18="ETAPA",0,IF(H18="SUBETAPA",OFFSET(D18,-1,0)+1,OFFSET(D18,-1,0))) -> 2 | E18: =IF(H18="Subetapa",0,IF(H18="serviço",OFFSET(E18,-1,0)+1,OFFSET(E18,-1,0))) -> 5 | H18: SERVIÇO | I18: =IF(H18="Unidade Construtiva",TEXT(A18,"00"),IF(H18="Célula Construtiva",TEXT(B18,"00"),IF(H18="Etapa",CONCATENATE(TEXT(B18,"00"),".",TEXT(C18,"000")),IF(H18="Subetapa",CONCATENATE(TEXT(B18,"00"),".",TEXT(C18,"000"),".",TEXT(D18,"000")),IF(H18="Serviço",CONCATENATE(TEXT(B18,"00"),".",TEXT(C18,"000"),".",TEXT(D18,"000"),".",TEXT(E18,"000")),""))))) -> 01.001.002.005 | J18: Projeto hidrossanitário | K18: vb | L18: 1 | M18: 7304.5102 | N18: =IF(H18="Serviço",M18*L18,IF(H18="CÉLULA CONSTRUTIVA",SUMIFS($N$8:$N$368,$B$8:$B$368,B18,$H$8:$H$368,"Serviço"),IF(H18="ETAPA",SUMIFS($N$8:$N$368,$B$8:$B$368,B18,$C$8:$C$368,C18,$H$8:$H$368,"Serviço"),IF(H18="SUBETAPA",SUMIFS($N$8:$N$368,$B$8:$B$368,B18,$C$8:$C$368,C18,$D$8:$D$368,D18,$H$8:$H$368,"Serviço"),0)))) -> 7304.5102 | O18: Estimado com base em índices históricos | P18: Finalizado
A19: =IF($H19="UNIDADE CONSTRUTIVA",OFFSET(A19,-1,0)+1,LARGE(A$3:A17,1)) -> 0 | B19: =IF(H19="UNIDADE CONSTRUTIVA",0,IF(H19="CÉLULA CONSTRUTIVA",OFFSET(B19,-1,0)+1,OFFSET(B19,-1,0))) -> 1 | C19: =IF(H19="CÉLULA CONSTRUTIVA",0,IF(H19="ETAPA",OFFSET(C19,-1,0)+1,OFFSET(C19,-1,0))) -> 1 | D19: =IF(H19="ETAPA",0,IF(H19="SUBETAPA",OFFSET(D19,-1,0)+1,OFFSET(D19,-1,0))) -> 3 | E19: =IF(H19="Subetapa",0,IF(H19="serviço",OFFSET(E19,-1,0)+1,OFFSET(E19,-1,0))) -> 0 | H19: SUBETAPA | I19: =IF(H19="Unidade Construtiva",TEXT(A19,"00"),IF(H19="Célula Construtiva",TEXT(B19,"00"),IF(H19="Etapa",CONCATENATE(TEXT(B19,"00"),".",TEXT(C19,"000")),IF(H19="Subetapa",CONCATENATE(TEXT(B19,"00"),".",TEXT(C19,"000"),".",TEXT(D19,"000")),IF(H19="Serviço",CONCATENATE(TEXT(B19,"00"),".",TEXT(C19,"000"),".",TEXT(D19,"000"),".",TEXT(E19,"000")),""))))) -> 01.001.003 | J19: Consultorias | N19: =IF(H19="Serviço",M19*L19,IF(H19="CÉLULA CONSTRUTIVA",SUMIFS($N$8:$N$368,$B$8:$B$368,B19,$H$8:$H$368,"Serviço"),IF(H19="ETAPA",SUMIFS($N$8:$N$368,$B$8:$B$368,B19,$C$8:$C$368,C19,$H$8:$H$368,"Serviço"),IF(H19="SUBETAPA",SUMIFS($N$8:$N$368,$B$8:$B$368,B19,$C$8:$C$368,C19,$D$8:$D$368,D19,$H$8:$H$368,"Serviço"),0)))) -> 17500
A20: =IF($H20="UNIDADE CONSTRUTIVA",OFFSET(A20,-1,0)+1,LARGE(A$3:A19,1)) -> 0 | B20: =IF(H20="UNIDADE CONSTRUTIVA",0,IF(H20="CÉLULA CONSTRUTIVA",OFFSET(B20,-1,0)+1,OFFSET(B20,-1,0))) -> 1 | C20: =IF(H20="CÉLULA CONSTRUTIVA",0,IF(H20="ETAPA",OFFSET(C20,-1,0)+1,OFFSET(C20,-1,0))) -> 1 | D20: =IF(H20="ETAPA",0,IF(H20="SUBETAPA",OFFSET(D20,-1,0)+1,OFFSET(D20,-1,0))) -> 3 | E20: =IF(H20="Subetapa",0,IF(H20="serviço",OFFSET(E20,-1,0)+1,OFFSET(E20,-1,0))) -> 1 | H20: SERVIÇO | I20: =IF(H20="Unidade Construtiva",TEXT(A20,"00"),IF(H20="Célula Construtiva",TEXT(B20,"00"),IF(H20="Etapa",CONCATENATE(TEXT(B20,"00"),".",TEXT(C20,"000")),IF(H20="Subetapa",CONCATENATE(TEXT(B20,"00"),".",TEXT(C20,"000"),".",TEXT(D20,"000")),IF(H20="Serviço",CONCATENATE(TEXT(B20,"00"),".",TEXT(C20,"000"),".",TEXT(D20,"000"),".",TEXT(E20,"000")),""))))) -> 01.001.003.001 | J20: Modelagem BIM arquitetônica | K20: vb | L20: 1 | M20: 3638.39 | N20: =IF(H20="Serviço",M20*L20,IF(H20="CÉLULA CONSTRUTIVA",SUMIFS($N$8:$N$368,$B$8:$B$368,B20,$H$8:$H$368,"Serviço"),IF(H20="ETAPA",SUMIFS($N$8:$N$368,$B$8:$B$368,B20,$C$8:$C$368,C20,$H$8:$H$368,"Serviço"),IF(H20="SUBETAPA",SUMIFS($N$8:$N$368,$B$8:$B$368,B20,$C$8:$C$368,C20,$D$8:$D$368,D20,$H$8:$H$368,"Serviço"),0)))) -> 3638.39 | O20: Contrato Cartesian | P20: Finalizado
A21: =IF($H21="UNIDADE CONSTRUTIVA",OFFSET(A21,-1,0)+1,LARGE(A$3:A20,1)) -> 0 | B21: =IF(H21="UNIDADE CONSTRUTIVA",0,IF(H21="CÉLULA CONSTRUTIVA",OFFSET(B21,-1,0)+1,OFFSET(B21,-1,0))) -> 1 | C21: =IF(H21="CÉLULA CONSTRUTIVA",0,IF(H21="ETAPA",OFFSET(C21,-1,0)+1,OFFSET(C21,-1,0))) -> 1 | D21: =IF(H21="ETAPA",0,IF(H21="SUBETAPA",OFFSET(D21,-1,0)+1,OFFSET(D21,-1,0))) -> 3 | E21: =IF(H21="Subetapa",0,IF(H21="serviço",OFFSET(E21,-1,0)+1,OFFSET(E21,-1,0))) -> 2 | H21: SERVIÇO | I21: =IF(H21="Unidade Construtiva",TEXT(A21,"00"),IF(H21="Célula Construtiva",TEXT(B21,"00"),IF(H21="Etapa",CONCATENATE(TEXT(B21,"00"),".",TEXT(C21,"000")),IF(H21="Subetapa",CONCATENATE(TEXT(B21,"00"),".",TEXT(C21,"000"),".",TEXT(D21,"000")),IF(H21="Serviço",CONCATENATE(TEXT(B21,"00"),".",TEXT(C21,"000"),".",TEXT(D21,"000"),".",TEXT(E21,"000")),""))))) -> 01.001.003.002 | J21: Orçamento e planejamento | K21: vb | L21: 1 | M21: =8083.27+4032.46+1745.88 -> 13861.61 | N21: =IF(H21="Serviço",M21*L21,IF(H21="CÉLULA CONSTRUTIVA",SUMIFS($N$8:$N$368,$B$8:$B$368,B21,$H$8:$H$368,"Serviço"),IF(H21="ETAPA",SUMIFS($N$8:$N$368,$B$8:$B$368,B21,$C$8:$C$368,C21,$H$8:$H$368,"Serviço"),IF(H21="SUBETAPA",SUMIFS($N$8:$N$368,$B$8:$B$368,B21,$C$8:$C$368,C21,$D$8:$D$368,D21,$H$8:$H$368,"Serviço"),0)))) -> 13861.61 | O21: Contrato Cartesian | P21: Finalizado
A22: =IF($H22="UNIDADE CONSTRUTIVA",OFFSET(A22,-1,0)+1,LARGE(A$3:A21,1)) -> 0 | B22: =IF(H22="UNIDADE CONSTRUTIVA",0,IF(H22="CÉLULA CONSTRUTIVA",OFFSET(B22,-1,0)+1,OFFSET(B22,-1,0))) -> 1 | C22: =IF(H22="CÉLULA CONSTRUTIVA",0,IF(H22="ETAPA",OFFSET(C22,-1,0)+1,OFFSET(C22,-1,0))) -> 1 | D22: =IF(H22="ETAPA",0,IF(H22="SUBETAPA",OFFSET(D22,-1,0)+1,OFFSET(D22,-1,0))) -> 4 | E22: =IF(H22="Subetapa",0,IF(H22="serviço",OFFSET(E22,-1,0)+1,OFFSET(E22,-1,0))) -> 0 | H22: SUBETAPA | I22: =IF(H22="Unidade Construtiva",TEXT(A22,"00"),IF(H22="Célula Construtiva",TEXT(B22,"00"),IF(H22="Etapa",CONCATENATE(TEXT(B22,"00"),".",TEXT(C22,"000")),IF(H22="Subetapa",CONCATENATE(TEXT(B22,"00"),".",TEXT(C22,"000"),".",TEXT(D22,"000")),IF(H22="Serviço",CONCATENATE(TEXT(B22,"00"),".",TEXT(C22,"000"),".",TEXT(D22,"000"),".",TEXT(E22,"000")),""))))) -> 01.001.004 | J22: Ensaios | N22: =IF(H22="Serviço",M22*L22,IF(H22="CÉLULA CONSTRUTIVA",SUMIFS($N$8:$N$368,$B$8:$B$368,B22,$H$8:$H$368,"Serviço"),IF(H22="ETAPA",SUMIFS($N$8:$N$368,$B$8:$B$368,B22,$C$8:$C$368,C22,$H$8:$H$368,"Serviço"),IF(H22="SUBETAPA",SUMIFS($N$8:$N$368,$B$8:$B$368,B22,$C$8:$C$368,C22,$D$8:$D$368,D22,$H$8:$H$368,"Serviço"),0)))) -> 3490
A23: =IF($H23="UNIDADE CONSTRUTIVA",OFFSET(A23,-1,0)+1,LARGE(A$3:A22,1)) -> 0 | B23: =IF(H23="UNIDADE CONSTRUTIVA",0,IF(H23="CÉLULA CONSTRUTIVA",OFFSET(B23,-1,0)+1,OFFSET(B23,-1,0))) -> 1 | C23: =IF(H23="CÉLULA CONSTRUTIVA",0,IF(H23="ETAPA",OFFSET(C23,-1,0)+1,OFFSET(C23,-1,0))) -> 1 | D23: =IF(H23="ETAPA",0,IF(H23="SUBETAPA",OFFSET(D23,-1,0)+1,OFFSET(D23,-1,0))) -> 4 | E23: =IF(H23="Subetapa",0,IF(H23="serviço",OFFSET(E23,-1,0)+1,OFFSET(E23,-1,0))) -> 1 | H23: SERVIÇO | I23: =IF(H23="Unidade Construtiva",TEXT(A23,"00"),IF(H23="Célula Construtiva",TEXT(B23,"00"),IF(H23="Etapa",CONCATENATE(TEXT(B23,"00"),".",TEXT(C23,"000")),IF(H23="Subetapa",CONCATENATE(TEXT(B23,"00"),".",TEXT(C23,"000"),".",TEXT(D23,"000")),IF(H23="Serviço",CONCATENATE(TEXT(B23,"00"),".",TEXT(C23,"000"),".",TEXT(D23,"000"),".",TEXT(E23,"000")),""))))) -> 01.001.004.001 | J23: Controle Tecnologico de Concreto | K23: vb | L23: 1 | M23: ='Ensaios '!F12 -> 3490 | N23: =IF(H23="Serviço",M23*L23,IF(H23="CÉLULA CONSTRUTIVA",SUMIFS($N$8:$N$368,$B$8:$B$368,B23,$H$8:$H$368,"Serviço"),IF(H23="ETAPA",SUMIFS($N$8:$N$368,$B$8:$B$368,B23,$C$8:$C$368,C23,$H$8:$H$368,"Serviço"),IF(H23="SUBETAPA",SUMIFS($N$8:$N$368,$B$8:$B$368,B23,$C$8:$C$368,C23,$D$8:$D$368,D23,$H$8:$H$368,"Serviço"),0)))) -> 3490 | O23: Cnoforme aba auxiliar | P23: Finalizado
A24: =IF($H24="UNIDADE CONSTRUTIVA",OFFSET(A24,-1,0)+1,LARGE(A$3:A23,1)) -> 0 | B24: =IF(H24="UNIDADE CONSTRUTIVA",0,IF(H24="CÉLULA CONSTRUTIVA",OFFSET(B24,-1,0)+1,OFFSET(B24,-1,0))) -> 1 | C24: =IF(H24="CÉLULA CONSTRUTIVA",0,IF(H24="ETAPA",OFFSET(C24,-1,0)+1,OFFSET(C24,-1,0))) -> 2 | D24: =IF(H24="ETAPA",0,IF(H24="SUBETAPA",OFFSET(D24,-1,0)+1,OFFSET(D24,-1,0))) -> 0 | E24: =IF(H24="Subetapa",0,IF(H24="serviço",OFFSET(E24,-1,0)+1,OFFSET(E24,-1,0))) -> 1 | H24: ETAPA | I24: =IF(H24="Unidade Construtiva",TEXT(A24,"00"),IF(H24="Célula Construtiva",TEXT(B24,"00"),IF(H24="Etapa",CONCATENATE(TEXT(B24,"00"),".",TEXT(C24,"000")),IF(H24="Subetapa",CONCATENATE(TEXT(B24,"00"),".",TEXT(C24,"000"),".",TEXT(D24,"000")),IF(H24="Serviço",CONCATENATE(TEXT(B24,"00"),".",TEXT(C24,"000"),".",TEXT(D24,"000"),".",TEXT(E24,"000")),""))))) -> 01.002 | J24: TAXAS E DOCUMENTOS | N24: =IF(H24="Serviço",M24*L24,IF(H24="CÉLULA CONSTRUTIVA",SUMIFS($N$8:$N$368,$B$8:$B$368,B24,$H$8:$H$368,"Serviço"),IF(H24="ETAPA",SUMIFS($N$8:$N$368,$B$8:$B$368,B24,$C$8:$C$368,C24,$H$8:$H$368,"Serviço"),IF(H24="SUBETAPA",SUMIFS($N$8:$N$368,$B$8:$B$368,B24,$C$8:$C$368,C24,$D$8:$D$368,D24,$H$8:$H$368,"Serviço"),0)))) -> 25016.432 | P24: -
A25: =IF($H25="UNIDADE CONSTRUTIVA",OFFSET(A25,-1,0)+1,LARGE(A$3:A24,1)) -> 0 | B25: =IF(H25="UNIDADE CONSTRUTIVA",0,IF(H25="CÉLULA CONSTRUTIVA",OFFSET(B25,-1,0)+1,OFFSET(B25,-1,0))) -> 1 | C25: =IF(H25="CÉLULA CONSTRUTIVA",0,IF(H25="ETAPA",OFFSET(C25,-1,0)+1,OFFSET(C25,-1,0))) -> 2 | D25: =IF(H25="ETAPA",0,IF(H25="SUBETAPA",OFFSET(D25,-1,0)+1,OFFSET(D25,-1,0))) -> 1 | E25: =IF(H25="Subetapa",0,IF(H25="serviço",OFFSET(E25,-1,0)+1,OFFSET(E25,-1,0))) -> 0 | H25: SUBETAPA | I25: =IF(H25="Unidade Construtiva",TEXT(A25,"00"),IF(H25="Célula Construtiva",TEXT(B25,"00"),IF(H25="Etapa",CONCATENATE(TEXT(B25,"00"),".",TEXT(C25,"000")),IF(H25="Subetapa",CONCATENATE(TEXT(B25,"00"),".",TEXT(C25,"000"),".",TEXT(D25,"000")),IF(H25="Serviço",CONCATENATE(TEXT(B25,"00"),".",TEXT(C25,"000"),".",TEXT(D25,"000"),".",TEXT(E25,"000")),""))))) -> 01.002.001 | J25: Licenciamentos, Taxas, Impostos, Aprovações e Seguros | N25: =IF(H25="Serviço",M25*L25,IF(H25="CÉLULA CONSTRUTIVA",SUMIFS($N$8:$N$368,$B$8:$B$368,B25,$H$8:$H$368,"Serviço"),IF(H25="ETAPA",SUMIFS($N$8:$N$368,$B$8:$B$368,B25,$C$8:$C$368,C25,$H$8:$H$368,"Serviço"),IF(H25="SUBETAPA",SUMIFS($N$8:$N$368,$B$8:$B$368,B25,$C$8:$C$368,C25,$D$8:$D$368,D25,$H$8:$H$368,"Serviço"),0)))) -> 6545.3003
A26: =IF($H26="UNIDADE CONSTRUTIVA",OFFSET(A26,-1,0)+1,LARGE(A$3:A25,1)) -> 0 | B26: =IF(H26="UNIDADE CONSTRUTIVA",0,IF(H26="CÉLULA CONSTRUTIVA",OFFSET(B26,-1,0)+1,OFFSET(B26,-1,0))) -> 1 | C26: =IF(H26="CÉLULA CONSTRUTIVA",0,IF(H26="ETAPA",OFFSET(C26,-1,0)+1,OFFSET(C26,-1,0))) -> 2 | D26: =IF(H26="ETAPA",0,IF(H26="SUBETAPA",OFFSET(D26,-1,0)+1,OFFSET(D26,-1,0))) -> 1 | E26: =IF(H26="Subetapa",0,IF(H26="serviço",OFFSET(E26,-1,0)+1,OFFSET(E26,-1,0))) -> 1 | H26: SERVIÇO | I26: =IF(H26="Unidade Construtiva",TEXT(A26,"00"),IF(H26="Célula Construtiva",TEXT(B26,"00"),IF(H26="Etapa",CONCATENATE(TEXT(B26,"00"),".",TEXT(C26,"000")),IF(H26="Subetapa",CONCATENATE(TEXT(B26,"00"),".",TEXT(C26,"000"),".",TEXT(D26,"000")),IF(H26="Serviço",CONCATENATE(TEXT(B26,"00"),".",TEXT(C26,"000"),".",TEXT(D26,"000"),".",TEXT(E26,"000")),""))))) -> 01.002.001.001 | J26: Despesas de Seguros | K26: vb | L26: 1 | M26: 1200 | N26: =IF(H26="Serviço",M26*L26,IF(H26="CÉLULA CONSTRUTIVA",SUMIFS($N$8:$N$368,$B$8:$B$368,B26,$H$8:$H$368,"Serviço"),IF(H26="ETAPA",SUMIFS($N$8:$N$368,$B$8:$B$368,B26,$C$8:$C$368,C26,$H$8:$H$368,"Serviço"),IF(H26="SUBETAPA",SUMIFS($N$8:$N$368,$B$8:$B$368,B26,$C$8:$C$368,C26,$D$8:$D$368,D26,$H$8:$H$368,"Serviço"),0)))) -> 1200 | O26: Estimado com base em índices históricos | P26: Finalizado
A27: =IF($H27="UNIDADE CONSTRUTIVA",OFFSET(A27,-1,0)+1,LARGE(A$3:A26,1)) -> 0 | B27: =IF(H27="UNIDADE CONSTRUTIVA",0,IF(H27="CÉLULA CONSTRUTIVA",OFFSET(B27,-1,0)+1,OFFSET(B27,-1,0))) -> 1 | C27: =IF(H27="CÉLULA CONSTRUTIVA",0,IF(H27="ETAPA",OFFSET(C27,-1,0)+1,OFFSET(C27,-1,0))) -> 2 | D27: =IF(H27="ETAPA",0,IF(H27="SUBETAPA",OFFSET(D27,-1,0)+1,OFFSET(D27,-1,0))) -> 1 | E27: =IF(H27="Subetapa",0,IF(H27="serviço",OFFSET(E27,-1,0)+1,OFFSET(E27,-1,0))) -> 2 | H27: SERVIÇO | I27: =IF(H27="Unidade Construtiva",TEXT(A27,"00"),IF(H27="Célula Construtiva",TEXT(B27,"00"),IF(H27="Etapa",CONCATENATE(TEXT(B27,"00"),".",TEXT(C27,"000")),IF(H27="Subetapa",CONCATENATE(TEXT(B27,"00"),".",TEXT(C27,"000"),".",TEXT(D27,"000")),IF(H27="Serviço",CONCATENATE(TEXT(B27,"00"),".",TEXT(C27,"000"),".",TEXT(D27,"000"),".",TEXT(E27,"000")),""))))) -> 01.002.001.002 | J27: Taxas de ART | K27: vb | L27: 1 | M27: 1000 | N27: =IF(H27="Serviço",M27*L27,IF(H27="CÉLULA CONSTRUTIVA",SUMIFS($N$8:$N$368,$B$8:$B$368,B27,$H$8:$H$368,"Serviço"),IF(H27="ETAPA",SUMIFS($N$8:$N$368,$B$8:$B$368,B27,$C$8:$C$368,C27,$H$8:$H$368,"Serviço"),IF(H27="SUBETAPA",SUMIFS($N$8:$N$368,$B$8:$B$368,B27,$C$8:$C$368,C27,$D$8:$D$368,D27,$H$8:$H$368,"Serviço"),0)))) -> 1000 | O27: Estimado com base em índices históricos | P27: Finalizado
A28: =IF($H28="UNIDADE CONSTRUTIVA",OFFSET(A28,-1,0)+1,LARGE(A$3:A27,1)) -> 0 | B28: =IF(H28="UNIDADE CONSTRUTIVA",0,IF(H28="CÉLULA CONSTRUTIVA",OFFSET(B28,-1,0)+1,OFFSET(B28,-1,0))) -> 1 | C28: =IF(H28="CÉLULA CONSTRUTIVA",0,IF(H28="ETAPA",OFFSET(C28,-1,0)+1,OFFSET(C28,-1,0))) -> 2 | D28: =IF(H28="ETAPA",0,IF(H28="SUBETAPA",OFFSET(D28,-1,0)+1,OFFSET(D28,-1,0))) -> 1 | E28: =IF(H28="Subetapa",0,IF(H28="serviço",OFFSET(E28,-1,0)+1,OFFSET(E28,-1,0))) -> 3 | H28: SERVIÇO | I28: =IF(H28="Unidade Construtiva",TEXT(A28,"00"),IF(H28="Célula Construtiva",TEXT(B28,"00"),IF(H28="Etapa",CONCATENATE(TEXT(B28,"00"),".",TEXT(C28,"000")),IF(H28="Subetapa",CONCATENATE(TEXT(B28,"00"),".",TEXT(C28,"000"),".",TEXT(D28,"000")),IF(H28="Serviço",CONCATENATE(TEXT(B28,"00"),".",TEXT(C28,"000"),".",TEXT(D28,"000"),".",TEXT(E28,"000")),""))))) -> 01.002.001.003 | J28: Alvará Construção | K28: vb | L28: 1 | M28: 1080.1762 | N28: =IF(H28="Serviço",M28*L28,IF(H28="CÉLULA CONSTRUTIVA",SUMIFS($N$8:$N$368,$B$8:$B$368,B28,$H$8:$H$368,"Serviço"),IF(H28="ETAPA",SUMIFS($N$8:$N$368,$B$8:$B$368,B28,$C$8:$C$368,C28,$H$8:$H$368,"Serviço"),IF(H28="SUBETAPA",SUMIFS($N$8:$N$368,$B$8:$B$368,B28,$C$8:$C$368,C28,$D$8:$D$368,D28,$H$8:$H$368,"Serviço"),0)))) -> 1080.1762 | O28: Estimado com base em índices históricos | P28: Finalizado
A29: =IF($H29="UNIDADE CONSTRUTIVA",OFFSET(A29,-1,0)+1,LARGE(A$3:A28,1)) -> 0 | B29: =IF(H29="UNIDADE CONSTRUTIVA",0,IF(H29="CÉLULA CONSTRUTIVA",OFFSET(B29,-1,0)+1,OFFSET(B29,-1,0))) -> 1 | C29: =IF(H29="CÉLULA CONSTRUTIVA",0,IF(H29="ETAPA",OFFSET(C29,-1,0)+1,OFFSET(C29,-1,0))) -> 2 | D29: =IF(H29="ETAPA",0,IF(H29="SUBETAPA",OFFSET(D29,-1,0)+1,OFFSET(D29,-1,0))) -> 1 | E29: =IF(H29="Subetapa",0,IF(H29="serviço",OFFSET(E29,-1,0)+1,OFFSET(E29,-1,0))) -> 4 | H29: SERVIÇO | I29: =IF(H29="Unidade Construtiva",TEXT(A29,"00"),IF(H29="Célula Construtiva",TEXT(B29,"00"),IF(H29="Etapa",CONCATENATE(TEXT(B29,"00"),".",TEXT(C29,"000")),IF(H29="Subetapa",CONCATENATE(TEXT(B29,"00"),".",TEXT(C29,"000"),".",TEXT(D29,"000")),IF(H29="Serviço",CONCATENATE(TEXT(B29,"00"),".",TEXT(C29,"000"),".",TEXT(D29,"000"),".",TEXT(E29,"000")),""))))) -> 01.002.001.004 | J29: Despesas cartório, licenças, certidões e jurídicas | K29: vb | L29: 1 | M29: 1857.0059 | N29: =IF(H29="Serviço",M29*L29,IF(H29="CÉLULA CONSTRUTIVA",SUMIFS($N$8:$N$368,$B$8:$B$368,B29,$H$8:$H$368,"Serviço"),IF(H29="ETAPA",SUMIFS($N$8:$N$368,$B$8:$B$368,B29,$C$8:$C$368,C29,$H$8:$H$368,"Serviço"),IF(H29="SUBETAPA",SUMIFS($N$8:$N$368,$B$8:$B$368,B29,$C$8:$C$368,C29,$D$8:$D$368,D29,$H$8:$H$368,"Serviço"),0)))) -> 1857.0059 | O29: Estimado com base em índices históricos | P29: Finalizado
A30: =IF($H30="UNIDADE CONSTRUTIVA",OFFSET(A30,-1,0)+1,LARGE(A$3:A29,1)) -> 0 | B30: =IF(H30="UNIDADE CONSTRUTIVA",0,IF(H30="CÉLULA CONSTRUTIVA",OFFSET(B30,-1,0)+1,OFFSET(B30,-1,0))) -> 1 | C30: =IF(H30="CÉLULA CONSTRUTIVA",0,IF(H30="ETAPA",OFFSET(C30,-1,0)+1,OFFSET(C30,-1,0))) -> 2 | D30: =IF(H30="ETAPA",0,IF(H30="SUBETAPA",OFFSET(D30,-1,0)+1,OFFSET(D30,-1,0))) -> 1 | E30: =IF(H30="Subetapa",0,IF(H30="serviço",OFFSET(E30,-1,0)+1,OFFSET(E30,-1,0))) -> 5 | H30: SERVIÇO | I30: =IF(H30="Unidade Construtiva",TEXT(A30,"00"),IF(H30="Célula Construtiva",TEXT(B30,"00"),IF(H30="Etapa",CONCATENATE(TEXT(B30,"00"),".",TEXT(C30,"000")),IF(H30="Subetapa",CONCATENATE(TEXT(B30,"00"),".",TEXT(C30,"000"),".",TEXT(D30,"000")),IF(H30="Serviço",CONCATENATE(TEXT(B30,"00"),".",TEXT(C30,"000"),".",TEXT(D30,"000"),".",TEXT(E30,"000")),""))))) -> 01.002.001.005 | J30: Iptu | K30: vb | L30: 1 | M30: 390 | N30: =IF(H30="Serviço",M30*L30,IF(H30="CÉLULA CONSTRUTIVA",SUMIFS($N$8:$N$368,$B$8:$B$368,B30,$H$8:$H$368,"Serviço"),IF(H30="ETAPA",SUMIFS($N$8:$N$368,$B$8:$B$368,B30,$C$8:$C$368,C30,$H$8:$H$368,"Serviço"),IF(H30="SUBETAPA",SUMIFS($N$8:$N$368,$B$8:$B$368,B30,$C$8:$C$368,C30,$D$8:$D$368,D30,$H$8:$H$368,"Serviço"),0)))) -> 390 | O30: Estimado com base em índices históricos | P30: Finalizado
A31: =IF($H31="UNIDADE CONSTRUTIVA",OFFSET(A31,-1,0)+1,LARGE(A$3:A30,1)) -> 0 | B31: =IF(H31="UNIDADE CONSTRUTIVA",0,IF(H31="CÉLULA CONSTRUTIVA",OFFSET(B31,-1,0)+1,OFFSET(B31,-1,0))) -> 1 | C31: =IF(H31="CÉLULA CONSTRUTIVA",0,IF(H31="ETAPA",OFFSET(C31,-1,0)+1,OFFSET(C31,-1,0))) -> 2 | D31: =IF(H31="ETAPA",0,IF(H31="SUBETAPA",OFFSET(D31,-1,0)+1,OFFSET(D31,-1,0))) -> 1 | E31: =IF(H31="Subetapa",0,IF(H31="serviço",OFFSET(E31,-1,0)+1,OFFSET(E31,-1,0))) -> 6 | H31: SERVIÇO | I31: =IF(H31="Unidade Construtiva",TEXT(A31,"00"),IF(H31="Célula Construtiva",TEXT(B31,"00"),IF(H31="Etapa",CONCATENATE(TEXT(B31,"00"),".",TEXT(C31,"000")),IF(H31="Subetapa",CONCATENATE(TEXT(B31,"00"),".",TEXT(C31,"000"),".",TEXT(D31,"000")),IF(H31="Serviço",CONCATENATE(TEXT(B31,"00"),".",TEXT(C31,"000"),".",TEXT(D31,"000"),".",TEXT(E31,"000")),""))))) -> 01.002.001.006 | J31: Alvará Habite-se | K31: vb | L31: 1 | M31: 1018.1182 | N31: =IF(H31="Serviço",M31*L31,IF(H31="CÉLULA CONSTRUTIVA",SUMIFS($N$8:$N$368,$B$8:$B$368,B31,$H$8:$H$368,"Serviço"),IF(H31="ETAPA",SUMIFS($N$8:$N$368,$B$8:$B$368,B31,$C$8:$C$368,C31,$H$8:$H$368,"Serviço"),IF(H31="SUBETAPA",SUMIFS($N$8:$N$368,$B$8:$B$368,B31,$C$8:$C$368,C31,$D$8:$D$368,D31,$H$8:$H$368,"Serviço"),0)))) -> 1018.1182 | O31: Estimado com base em índices históricos | P31: Finalizado
A32: =IF($H32="UNIDADE CONSTRUTIVA",OFFSET(A32,-1,0)+1,LARGE(A$3:A31,1)) -> 0 | B32: =IF(H32="UNIDADE CONSTRUTIVA",0,IF(H32="CÉLULA CONSTRUTIVA",OFFSET(B32,-1,0)+1,OFFSET(B32,-1,0))) -> 1 | C32: =IF(H32="CÉLULA CONSTRUTIVA",0,IF(H32="ETAPA",OFFSET(C32,-1,0)+1,OFFSET(C32,-1,0))) -> 2 | D32: =IF(H32="ETAPA",0,IF(H32="SUBETAPA",OFFSET(D32,-1,0)+1,OFFSET(D32,-1,0))) -> 2 | E32: =IF(H32="Subetapa",0,IF(H32="serviço",OFFSET(E32,-1,0)+1,OFFSET(E32,-1,0))) -> 0 | H32: SUBETAPA | I32: =IF(H32="Unidade Construtiva",TEXT(A32,"00"),IF(H32="Célula Construtiva",TEXT(B32,"00"),IF(H32="Etapa",CONCATENATE(TEXT(B32,"00"),".",TEXT(C32,"000")),IF(H32="Subetapa",CONCATENATE(TEXT(B32,"00"),".",TEXT(C32,"000"),".",TEXT(D32,"000")),IF(H32="Serviço",CONCATENATE(TEXT(B32,"00"),".",TEXT(C32,"000"),".",TEXT(D32,"000"),".",TEXT(E32,"000")),""))))) -> 01.002.002 | J32: Documentos | N32: =IF(H32="Serviço",M32*L32,IF(H32="CÉLULA CONSTRUTIVA",SUMIFS($N$8:$N$368,$B$8:$B$368,B32,$H$8:$H$368,"Serviço"),IF(H32="ETAPA",SUMIFS($N$8:$N$368,$B$8:$B$368,B32,$C$8:$C$368,C32,$H$8:$H$368,"Serviço"),IF(H32="SUBETAPA",SUMIFS($N$8:$N$368,$B$8:$B$368,B32,$C$8:$C$368,C32,$D$8:$D$368,D32,$H$8:$H$368,"Serviço"),0)))) -> 18471.132
A33: =IF($H33="UNIDADE CONSTRUTIVA",OFFSET(A33,-1,0)+1,LARGE(A$3:A32,1)) -> 0 | B33: =IF(H33="UNIDADE CONSTRUTIVA",0,IF(H33="CÉLULA CONSTRUTIVA",OFFSET(B33,-1,0)+1,OFFSET(B33,-1,0))) -> 1 | C33: =IF(H33="CÉLULA CONSTRUTIVA",0,IF(H33="ETAPA",OFFSET(C33,-1,0)+1,OFFSET(C33,-1,0))) -> 2 | D33: =IF(H33="ETAPA",0,IF(H33="SUBETAPA",OFFSET(D33,-1,0)+1,OFFSET(D33,-1,0))) -> 2 | E33: =IF(H33="Subetapa",0,IF(H33="serviço",OFFSET(E33,-1,0)+1,OFFSET(E33,-1,0))) -> 1 | H33: SERVIÇO | I33: =IF(H33="Unidade Construtiva",TEXT(A33,"00"),IF(H33="Célula Construtiva",TEXT(B33,"00"),IF(H33="Etapa",CONCATENATE(TEXT(B33,"00"),".",TEXT(C33,"000")),IF(H33="Subetapa",CONCATENATE(TEXT(B33,"00"),".",TEXT(C33,"000"),".",TEXT(D33,"000")),IF(H33="Serviço",CONCATENATE(TEXT(B33,"00"),".",TEXT(C33,"000"),".",TEXT(D33,"000"),".",TEXT(E33,"000")),""))))) -> 01.002.002.001 | J33: Certidão INSS | K33: vb | L33: 1 | M33: =(SUM('Obra '!C33:C45)*0.18)*0.11*0.7 -> 18471.132 | N33: =IF(H33="Serviço",M33*L33,IF(H33="CÉLULA CONSTRUTIVA",SUMIFS($N$8:$N$368,$B$8:$B$368,B33,$H$8:$H$368,"Serviço"),IF(H33="ETAPA",SUMIFS($N$8:$N$368,$B$8:$B$368,B33,$C$8:$C$368,C33,$H$8:$H$368,"Serviço"),IF(H33="SUBETAPA",SUMIFS($N$8:$N$368,$B$8:$B$368,B33,$C$8:$C$368,C33,$D$8:$D$368,D33,$H$8:$H$368,"Serviço"),0)))) -> 18471.132 | O33: Estimado como 11% da mão de obra da obra com indice de redução de 0,7 | P33: Finalizado
A34: =IF($H34="UNIDADE CONSTRUTIVA",OFFSET(A34,-1,0)+1,LARGE(A$3:A33,1)) -> 0 | B34: =IF(H34="UNIDADE CONSTRUTIVA",0,IF(H34="CÉLULA CONSTRUTIVA",OFFSET(B34,-1,0)+1,OFFSET(B34,-1,0))) -> 2 | C34: =IF(H34="CÉLULA CONSTRUTIVA",0,IF(H34="ETAPA",OFFSET(C34,-1,0)+1,OFFSET(C34,-1,0))) -> 0 | D34: =IF(H34="ETAPA",0,IF(H34="SUBETAPA",OFFSET(D34,-1,0)+1,OFFSET(D34,-1,0))) -> 2 | E34: =IF(H34="Subetapa",0,IF(H34="serviço",OFFSET(E34,-1,0)+1,OFFSET(E34,-1,0))) -> 1 | H34: CÉLULA CONSTRUTIVA | I34: =IF(H34="Unidade Construtiva",TEXT(A34,"00"),IF(H34="Célula Construtiva",TEXT(B34,"00"),IF(H34="Etapa",CONCATENATE(TEXT(B34,"00"),".",TEXT(C34,"000")),IF(H34="Subetapa",CONCATENATE(TEXT(B34,"00"),".",TEXT(C34,"000"),".",TEXT(D34,"000")),IF(H34="Serviço",CONCATENATE(TEXT(B34,"00"),".",TEXT(C34,"000"),".",TEXT(D34,"000"),".",TEXT(E34,"000")),""))))) -> 02 | J34: SERVIÇOS INICIAIS | N34: =IF(H34="Serviço",M34*L34,IF(H34="CÉLULA CONSTRUTIVA",SUMIFS($N$8:$N$368,$B$8:$B$368,B34,$H$8:$H$368,"Serviço"),IF(H34="ETAPA",SUMIFS($N$8:$N$368,$B$8:$B$368,B34,$C$8:$C$368,C34,$H$8:$H$368,"Serviço"),IF(H34="SUBETAPA",SUMIFS($N$8:$N$368,$B$8:$B$368,B34,$C$8:$C$368,C34,$D$8:$D$368,D34,$H$8:$H$368,"Serviço"),0)))) -> 125416.66 | Q34: =N34/'Obra '!$E$9 -> 380.54636
A35: =IF($H35="UNIDADE CONSTRUTIVA",OFFSET(A35,-1,0)+1,LARGE(A$3:A34,1)) -> 0 | B35: =IF(H35="UNIDADE CONSTRUTIVA",0,IF(H35="CÉLULA CONSTRUTIVA",OFFSET(B35,-1,0)+1,OFFSET(B35,-1,0))) -> 2 | C35: =IF(H35="CÉLULA CONSTRUTIVA",0,IF(H35="ETAPA",OFFSET(C35,-1,0)+1,OFFSET(C35,-1,0))) -> 1 | D35: =IF(H35="ETAPA",0,IF(H35="SUBETAPA",OFFSET(D35,-1,0)+1,OFFSET(D35,-1,0))) -> 0 | E35: =IF(H35="Subetapa",0,IF(H35="serviço",OFFSET(E35,-1,0)+1,OFFSET(E35,-1,0))) -> 1 | H35: ETAPA | I35: =IF(H35="Unidade Construtiva",TEXT(A35,"00"),IF(H35="Célula Construtiva",TEXT(B35,"00"),IF(H35="Etapa",CONCATENATE(TEXT(B35,"00"),".",TEXT(C35,"000")),IF(H35="Subetapa",CONCATENATE(TEXT(B35,"00"),".",TEXT(C35,"000"),".",TEXT(D35,"000")),IF(H35="Serviço",CONCATENATE(TEXT(B35,"00"),".",TEXT(C35,"000"),".",TEXT(D35,"000"),".",TEXT(E35,"000")),""))))) -> 02.001 | J35: SEGURANÇA, MEIO AMBIENTE E SAÚDE | N35: =IF(H35="Serviço",M35*L35,IF(H35="CÉLULA CONSTRUTIVA",SUMIFS($N$8:$N$368,$B$8:$B$368,B35,$H$8:$H$368,"Serviço"),IF(H35="ETAPA",SUMIFS($N$8:$N$368,$B$8:$B$368,B35,$C$8:$C$368,C35,$H$8:$H$368,"Serviço"),IF(H35="SUBETAPA",SUMIFS($N$8:$N$368,$B$8:$B$368,B35,$C$8:$C$368,C35,$D$8:$D$368,D35,$H$8:$H$368,"Serviço"),0)))) -> 9321.249
A36: =IF($H36="UNIDADE CONSTRUTIVA",OFFSET(A36,-1,0)+1,LARGE(A$3:A35,1)) -> 0 | B36: =IF(H36="UNIDADE CONSTRUTIVA",0,IF(H36="CÉLULA CONSTRUTIVA",OFFSET(B36,-1,0)+1,OFFSET(B36,-1,0))) -> 2 | C36: =IF(H36="CÉLULA CONSTRUTIVA",0,IF(H36="ETAPA",OFFSET(C36,-1,0)+1,OFFSET(C36,-1,0))) -> 1 | D36: =IF(H36="ETAPA",0,IF(H36="SUBETAPA",OFFSET(D36,-1,0)+1,OFFSET(D36,-1,0))) -> 1 | E36: =IF(H36="Subetapa",0,IF(H36="serviço",OFFSET(E36,-1,0)+1,OFFSET(E36,-1,0))) -> 0 | H36: SUBETAPA | I36: =IF(H36="Unidade Construtiva",TEXT(A36,"00"),IF(H36="Célula Construtiva",TEXT(B36,"00"),IF(H36="Etapa",CONCATENATE(TEXT(B36,"00"),".",TEXT(C36,"000")),IF(H36="Subetapa",CONCATENATE(TEXT(B36,"00"),".",TEXT(C36,"000"),".",TEXT(D36,"000")),IF(H36="Serviço",CONCATENATE(TEXT(B36,"00"),".",TEXT(C36,"000"),".",TEXT(D36,"000"),".",TEXT(E36,"000")),""))))) -> 02.001.001 | J36: Segurança do Trabalho | N36: =IF(H36="Serviço",M36*L36,IF(H36="CÉLULA CONSTRUTIVA",SUMIFS($N$8:$N$368,$B$8:$B$368,B36,$H$8:$H$368,"Serviço"),IF(H36="ETAPA",SUMIFS($N$8:$N$368,$B$8:$B$368,B36,$C$8:$C$368,C36,$H$8:$H$368,"Serviço"),IF(H36="SUBETAPA",SUMIFS($N$8:$N$368,$B$8:$B$368,B36,$C$8:$C$368,C36,$D$8:$D$368,D36,$H$8:$H$368,"Serviço"),0)))) -> 4500
A37: =IF($H37="UNIDADE CONSTRUTIVA",OFFSET(A37,-1,0)+1,LARGE(A$3:A36,1)) -> 0 | B37: =IF(H37="UNIDADE CONSTRUTIVA",0,IF(H37="CÉLULA CONSTRUTIVA",OFFSET(B37,-1,0)+1,OFFSET(B37,-1,0))) -> 2 | C37: =IF(H37="CÉLULA CONSTRUTIVA",0,IF(H37="ETAPA",OFFSET(C37,-1,0)+1,OFFSET(C37,-1,0))) -> 1 | D37: =IF(H37="ETAPA",0,IF(H37="SUBETAPA",OFFSET(D37,-1,0)+1,OFFSET(D37,-1,0))) -> 1 | E37: =IF(H37="Subetapa",0,IF(H37="serviço",OFFSET(E37,-1,0)+1,OFFSET(E37,-1,0))) -> 1 | H37: SERVIÇO | I37: =IF(H37="Unidade Construtiva",TEXT(A37,"00"),IF(H37="Célula Construtiva",TEXT(B37,"00"),IF(H37="Etapa",CONCATENATE(TEXT(B37,"00"),".",TEXT(C37,"000")),IF(H37="Subetapa",CONCATENATE(TEXT(B37,"00"),".",TEXT(C37,"000"),".",TEXT(D37,"000")),IF(H37="Serviço",CONCATENATE(TEXT(B37,"00"),".",TEXT(C37,"000"),".",TEXT(D37,"000"),".",TEXT(E37,"000")),""))))) -> 02.001.001.001 | J37: Equipamentos de proteção individual - EPI | K37: vb | L37: 1 | M37: =CANTEIRO!D15 -> 4500 | N37: =IF(H37="Serviço",M37*L37,IF(H37="CÉLULA CONSTRUTIVA",SUMIFS($N$8:$N$368,$B$8:$B$368,B37,$H$8:$H$368,"Serviço"),IF(H37="ETAPA",SUMIFS($N$8:$N$368,$B$8:$B$368,B37,$C$8:$C$368,C37,$H$8:$H$368,"Serviço"),IF(H37="SUBETAPA",SUMIFS($N$8:$N$368,$B$8:$B$368,B37,$C$8:$C$368,C37,$D$8:$D$368,D37,$H$8:$H$368,"Serviço"),0)))) -> 4500 | O37: Confrome cálculo da aba "Canteiro" | P37: Finalizado
A38: =IF($H38="UNIDADE CONSTRUTIVA",OFFSET(A38,-1,0)+1,LARGE(A$3:A37,1)) -> 0 | B38: =IF(H38="UNIDADE CONSTRUTIVA",0,IF(H38="CÉLULA CONSTRUTIVA",OFFSET(B38,-1,0)+1,OFFSET(B38,-1,0))) -> 2 | C38: =IF(H38="CÉLULA CONSTRUTIVA",0,IF(H38="ETAPA",OFFSET(C38,-1,0)+1,OFFSET(C38,-1,0))) -> 1 | D38: =IF(H38="ETAPA",0,IF(H38="SUBETAPA",OFFSET(D38,-1,0)+1,OFFSET(D38,-1,0))) -> 2 | E38: =IF(H38="Subetapa",0,IF(H38="serviço",OFFSET(E38,-1,0)+1,OFFSET(E38,-1,0))) -> 0 | H38: SUBETAPA | I38: =IF(H38="Unidade Construtiva",TEXT(A38,"00"),IF(H38="Célula Construtiva",TEXT(B38,"00"),IF(H38="Etapa",CONCATENATE(TEXT(B38,"00"),".",TEXT(C38,"000")),IF(H38="Subetapa",CONCATENATE(TEXT(B38,"00"),".",TEXT(C38,"000"),".",TEXT(D38,"000")),IF(H38="Serviço",CONCATENATE(TEXT(B38,"00"),".",TEXT(C38,"000"),".",TEXT(D38,"000"),".",TEXT(E38,"000")),""))))) -> 02.001.002 | J38: Equipamentos de proteção | N38: =IF(H38="Serviço",M38*L38,IF(H38="CÉLULA CONSTRUTIVA",SUMIFS($N$8:$N$368,$B$8:$B$368,B38,$H$8:$H$368,"Serviço"),IF(H38="ETAPA",SUMIFS($N$8:$N$368,$B$8:$B$368,B38,$C$8:$C$368,C38,$H$8:$H$368,"Serviço"),IF(H38="SUBETAPA",SUMIFS($N$8:$N$368,$B$8:$B$368,B38,$C$8:$C$368,C38,$D$8:$D$368,D38,$H$8:$H$368,"Serviço"),0)))) -> 821.24899
A39: =IF($H39="UNIDADE CONSTRUTIVA",OFFSET(A39,-1,0)+1,LARGE(A$3:A38,1)) -> 0 | B39: =IF(H39="UNIDADE CONSTRUTIVA",0,IF(H39="CÉLULA CONSTRUTIVA",OFFSET(B39,-1,0)+1,OFFSET(B39,-1,0))) -> 2 | C39: =IF(H39="CÉLULA CONSTRUTIVA",0,IF(H39="ETAPA",OFFSET(C39,-1,0)+1,OFFSET(C39,-1,0))) -> 1 | D39: =IF(H39="ETAPA",0,IF(H39="SUBETAPA",OFFSET(D39,-1,0)+1,OFFSET(D39,-1,0))) -> 2 | E39: =IF(H39="Subetapa",0,IF(H39="serviço",OFFSET(E39,-1,0)+1,OFFSET(E39,-1,0))) -> 1 | H39: SERVIÇO | I39: =IF(H39="Unidade Construtiva",TEXT(A39,"00"),IF(H39="Célula Construtiva",TEXT(B39,"00"),IF(H39="Etapa",CONCATENATE(TEXT(B39,"00"),".",TEXT(C39,"000")),IF(H39="Subetapa",CONCATENATE(TEXT(B39,"00"),".",TEXT(C39,"000"),".",TEXT(D39,"000")),IF(H39="Serviço",CONCATENATE(TEXT(B39,"00"),".",TEXT(C39,"000"),".",TEXT(D39,"000"),".",TEXT(E39,"000")),""))))) -> 02.001.002.001 | J39: Guarda-corpo de vãos, fixado em fôrma de madeira, em trama de madeira com tela de polipropileno | K39: m | L39: =Ger_Executivo!L203/1.1 -> 13.583636 | M39: =CPU!H164 -> 38.622647 | N39: =IF(H39="Serviço",M39*L39,IF(H39="CÉLULA CONSTRUTIVA",SUMIFS($N$8:$N$368,$B$8:$B$368,B39,$H$8:$H$368,"Serviço"),IF(H39="ETAPA",SUMIFS($N$8:$N$368,$B$8:$B$368,B39,$C$8:$C$368,C39,$H$8:$H$368,"Serviço"),IF(H39="SUBETAPA",SUMIFS($N$8:$N$368,$B$8:$B$368,B39,$C$8:$C$368,C39,$D$8:$D$368,D39,$H$8:$H$368,"Serviço"),0)))) -> 524.63599 | P39: Finalizado
A40: =IF($H40="UNIDADE CONSTRUTIVA",OFFSET(A40,-1,0)+1,LARGE(A$3:A39,1)) -> 0 | B40: =IF(H40="UNIDADE CONSTRUTIVA",0,IF(H40="CÉLULA CONSTRUTIVA",OFFSET(B40,-1,0)+1,OFFSET(B40,-1,0))) -> 2 | C40: =IF(H40="CÉLULA CONSTRUTIVA",0,IF(H40="ETAPA",OFFSET(C40,-1,0)+1,OFFSET(C40,-1,0))) -> 1 | D40: =IF(H40="ETAPA",0,IF(H40="SUBETAPA",OFFSET(D40,-1,0)+1,OFFSET(D40,-1,0))) -> 2 | E40: =IF(H40="Subetapa",0,IF(H40="serviço",OFFSET(E40,-1,0)+1,OFFSET(E40,-1,0))) -> 2 | H40: SERVIÇO | I40: =IF(H40="Unidade Construtiva",TEXT(A40,"00"),IF(H40="Célula Construtiva",TEXT(B40,"00"),IF(H40="Etapa",CONCATENATE(TEXT(B40,"00"),".",TEXT(C40,"000")),IF(H40="Subetapa",CONCATENATE(TEXT(B40,"00"),".",TEXT(C40,"000"),".",TEXT(D40,"000")),IF(H40="Serviço",CONCATENATE(TEXT(B40,"00"),".",TEXT(C40,"000"),".",TEXT(D40,"000"),".",TEXT(E40,"000")),""))))) -> 02.001.002.002 | J40: Sinalização geral da obra | K40: un | L40: 1 | M40: 296.613 | N40: =IF(H40="Serviço",M40*L40,IF(H40="CÉLULA CONSTRUTIVA",SUMIFS($N$8:$N$368,$B$8:$B$368,B40,$H$8:$H$368,"Serviço"),IF(H40="ETAPA",SUMIFS($N$8:$N$368,$B$8:$B$368,B40,$C$8:$C$368,C40,$H$8:$H$368,"Serviço"),IF(H40="SUBETAPA",SUMIFS($N$8:$N$368,$B$8:$B$368,B40,$C$8:$C$368,C40,$D$8:$D$368,D40,$H$8:$H$368,"Serviço"),0)))) -> 296.613 | O40: Estimado com base em índices históricos | P40: Finalizado
A41: =IF($H41="UNIDADE CONSTRUTIVA",OFFSET(A41,-1,0)+1,LARGE(A$3:A39,1)) -> 0 | B41: =IF(H41="UNIDADE CONSTRUTIVA",0,IF(H41="CÉLULA CONSTRUTIVA",OFFSET(B41,-1,0)+1,OFFSET(B41,-1,0))) -> 2 | C41: =IF(H41="CÉLULA CONSTRUTIVA",0,IF(H41="ETAPA",OFFSET(C41,-1,0)+1,OFFSET(C41,-1,0))) -> 1 | D41: =IF(H41="ETAPA",0,IF(H41="SUBETAPA",OFFSET(D41,-1,0)+1,OFFSET(D41,-1,0))) -> 3 | E41: =IF(H41="Subetapa",0,IF(H41="serviço",OFFSET(E41,-1,0)+1,OFFSET(E41,-1,0))) -> 0 | H41: SUBETAPA | I41: =IF(H41="Unidade Construtiva",TEXT(A41,"00"),IF(H41="Célula Construtiva",TEXT(B41,"00"),IF(H41="Etapa",CONCATENATE(TEXT(B41,"00"),".",TEXT(C41,"000")),IF(H41="Subetapa",CONCATENATE(TEXT(B41,"00"),".",TEXT(C41,"000"),".",TEXT(D41,"000")),IF(H41="Serviço",CONCATENATE(TEXT(B41,"00"),".",TEXT(C41,"000"),".",TEXT(D41,"000"),".",TEXT(E41,"000")),""))))) -> 02.001.003 | J41: Meio Ambiente | N41: =IF(H41="Serviço",M41*L41,IF(H41="CÉLULA CONSTRUTIVA",SUMIFS($N$8:$N$368,$B$8:$B$368,B41,$H$8:$H$368,"Serviço"),IF(H41="ETAPA",SUMIFS($N$8:$N$368,$B$8:$B$368,B41,$C$8:$C$368,C41,$H$8:$H$368,"Serviço"),IF(H41="SUBETAPA",SUMIFS($N$8:$N$368,$B$8:$B$368,B41,$C$8:$C$368,C41,$D$8:$D$368,D41,$H$8:$H$368,"Serviço"),0)))) -> 4000
A42: =IF($H42="UNIDADE CONSTRUTIVA",OFFSET(A42,-1,0)+1,LARGE(A$3:A41,1)) -> 0 | B42: =IF(H42="UNIDADE CONSTRUTIVA",0,IF(H42="CÉLULA CONSTRUTIVA",OFFSET(B42,-1,0)+1,OFFSET(B42,-1,0))) -> 2 | C42: =IF(H42="CÉLULA CONSTRUTIVA",0,IF(H42="ETAPA",OFFSET(C42,-1,0)+1,OFFSET(C42,-1,0))) -> 1 | D42: =IF(H42="ETAPA",0,IF(H42="SUBETAPA",OFFSET(D42,-1,0)+1,OFFSET(D42,-1,0))) -> 3 | E42: =IF(H42="Subetapa",0,IF(H42="serviço",OFFSET(E42,-1,0)+1,OFFSET(E42,-1,0))) -> 1 | H42: SERVIÇO | I42: =IF(H42="Unidade Construtiva",TEXT(A42,"00"),IF(H42="Célula Construtiva",TEXT(B42,"00"),IF(H42="Etapa",CONCATENATE(TEXT(B42,"00"),".",TEXT(C42,"000")),IF(H42="Subetapa",CONCATENATE(TEXT(B42,"00"),".",TEXT(C42,"000"),".",TEXT(D42,"000")),IF(H42="Serviço",CONCATENATE(TEXT(B42,"00"),".",TEXT(C42,"000"),".",TEXT(D42,"000"),".",TEXT(E42,"000")),""))))) -> 02.001.003.001 | J42: Remoção de entulhos e resíduos | K42: vb | L42: 1 | M42: =400*10 -> 4000 | N42: =IF(H42="Serviço",M42*L42,IF(H42="CÉLULA CONSTRUTIVA",SUMIFS($N$8:$N$368,$B$8:$B$368,B42,$H$8:$H$368,"Serviço"),IF(H42="ETAPA",SUMIFS($N$8:$N$368,$B$8:$B$368,B42,$C$8:$C$368,C42,$H$8:$H$368,"Serviço"),IF(H42="SUBETAPA",SUMIFS($N$8:$N$368,$B$8:$B$368,B42,$C$8:$C$368,C42,$D$8:$D$368,D42,$H$8:$H$368,"Serviço"),0)))) -> 4000 | O42: Estimado uma caçamba ao mês por 10 meses | P42: Finalizado
A43: =IF($H43="UNIDADE CONSTRUTIVA",OFFSET(A43,-1,0)+1,LARGE(A$3:A42,1)) -> 0 | B43: =IF(H43="UNIDADE CONSTRUTIVA",0,IF(H43="CÉLULA CONSTRUTIVA",OFFSET(B43,-1,0)+1,OFFSET(B43,-1,0))) -> 2 | C43: =IF(H43="CÉLULA CONSTRUTIVA",0,IF(H43="ETAPA",OFFSET(C43,-1,0)+1,OFFSET(C43,-1,0))) -> 2 | D43: =IF(H43="ETAPA",0,IF(H43="SUBETAPA",OFFSET(D43,-1,0)+1,OFFSET(D43,-1,0))) -> 0 | E43: =IF(H43="Subetapa",0,IF(H43="serviço",OFFSET(E43,-1,0)+1,OFFSET(E43,-1,0))) -> 1 | H43: ETAPA | I43: =IF(H43="Unidade Construtiva",TEXT(A43,"00"),IF(H43="Célula Construtiva",TEXT(B43,"00"),IF(H43="Etapa",CONCATENATE(TEXT(B43,"00"),".",TEXT(C43,"000")),IF(H43="Subetapa",CONCATENATE(TEXT(B43,"00"),".",TEXT(C43,"000"),".",TEXT(D43,"000")),IF(H43="Serviço",CONCATENATE(TEXT(B43,"00"),".",TEXT(C43,"000"),".",TEXT(D43,"000"),".",TEXT(E43,"000")),""))))) -> 02.002 | J43: ADMINISTRAÇÃO E CANTEIRO DE OBRA | N43: =IF(H43="Serviço",M43*L43,IF(H43="CÉLULA CONSTRUTIVA",SUMIFS($N$8:$N$368,$B$8:$B$368,B43,$H$8:$H$368,"Serviço"),IF(H43="ETAPA",SUMIFS($N$8:$N$368,$B$8:$B$368,B43,$C$8:$C$368,C43,$H$8:$H$368,"Serviço"),IF(H43="SUBETAPA",SUMIFS($N$8:$N$368,$B$8:$B$368,B43,$C$8:$C$368,C43,$D$8:$D$368,D43,$H$8:$H$368,"Serviço"),0)))) -> 116095.41
A44: =IF($H44="UNIDADE CONSTRUTIVA",OFFSET(A44,-1,0)+1,LARGE(A$3:A43,1)) -> 0 | B44: =IF(H44="UNIDADE CONSTRUTIVA",0,IF(H44="CÉLULA CONSTRUTIVA",OFFSET(B44,-1,0)+1,OFFSET(B44,-1,0))) -> 2 | C44: =IF(H44="CÉLULA CONSTRUTIVA",0,IF(H44="ETAPA",OFFSET(C44,-1,0)+1,OFFSET(C44,-1,0))) -> 2 | D44: =IF(H44="ETAPA",0,IF(H44="SUBETAPA",OFFSET(D44,-1,0)+1,OFFSET(D44,-1,0))) -> 1 | E44: =IF(H44="Subetapa",0,IF(H44="serviço",OFFSET(E44,-1,0)+1,OFFSET(E44,-1,0))) -> 0 | H44: SUBETAPA | I44: =IF(H44="Unidade Construtiva",TEXT(A44,"00"),IF(H44="Célula Construtiva",TEXT(B44,"00"),IF(H44="Etapa",CONCATENATE(TEXT(B44,"00"),".",TEXT(C44,"000")),IF(H44="Subetapa",CONCATENATE(TEXT(B44,"00"),".",TEXT(C44,"000"),".",TEXT(D44,"000")),IF(H44="Serviço",CONCATENATE(TEXT(B44,"00"),".",TEXT(C44,"000"),".",TEXT(D44,"000"),".",TEXT(E44,"000")),""))))) -> 02.002.001 | J44: Equipe de Gestão e Apoio | N44: =IF(H44="Serviço",M44*L44,IF(H44="CÉLULA CONSTRUTIVA",SUMIFS($N$8:$N$368,$B$8:$B$368,B44,$H$8:$H$368,"Serviço"),IF(H44="ETAPA",SUMIFS($N$8:$N$368,$B$8:$B$368,B44,$C$8:$C$368,C44,$H$8:$H$368,"Serviço"),IF(H44="SUBETAPA",SUMIFS($N$8:$N$368,$B$8:$B$368,B44,$C$8:$C$368,C44,$D$8:$D$368,D44,$H$8:$H$368,"Serviço"),0)))) -> 56000
A45: =IF($H45="UNIDADE CONSTRUTIVA",OFFSET(A45,-1,0)+1,LARGE(A$3:A44,1)) -> 0 | B45: =IF(H45="UNIDADE CONSTRUTIVA",0,IF(H45="CÉLULA CONSTRUTIVA",OFFSET(B45,-1,0)+1,OFFSET(B45,-1,0))) -> 2 | C45: =IF(H45="CÉLULA CONSTRUTIVA",0,IF(H45="ETAPA",OFFSET(C45,-1,0)+1,OFFSET(C45,-1,0))) -> 2 | D45: =IF(H45="ETAPA",0,IF(H45="SUBETAPA",OFFSET(D45,-1,0)+1,OFFSET(D45,-1,0))) -> 1 | E45: =IF(H45="Subetapa",0,IF(H45="serviço",OFFSET(E45,-1,0)+1,OFFSET(E45,-1,0))) -> 1 | H45: SERVIÇO | I45: =IF(H45="Unidade Construtiva",TEXT(A45,"00"),IF(H45="Célula Construtiva",TEXT(B45,"00"),IF(H45="Etapa",CONCATENATE(TEXT(B45,"00"),".",TEXT(C45,"000")),IF(H45="Subetapa",CONCATENATE(TEXT(B45,"00"),".",TEXT(C45,"000"),".",TEXT(D45,"000")),IF(H45="Serviço",CONCATENATE(TEXT(B45,"00"),".",TEXT(C45,"000"),".",TEXT(D45,"000"),".",TEXT(E45,"000")),""))))) -> 02.002.001.001 | J45: Engenheiro | K45: mes | L45: ='Obra '!E7 -> 14 | M45: =8000/2 -> 4000 | N45: =IF(H45="Serviço",M45*L45,IF(H45="CÉLULA CONSTRUTIVA",SUMIFS($N$8:$N$368,$B$8:$B$368,B45,$H$8:$H$368,"Serviço"),IF(H45="ETAPA",SUMIFS($N$8:$N$368,$B$8:$B$368,B45,$C$8:$C$368,C45,$H$8:$H$368,"Serviço"),IF(H45="SUBETAPA",SUMIFS($N$8:$N$368,$B$8:$B$368,B45,$C$8:$C$368,C45,$D$8:$D$368,D45,$H$8:$H$368,"Serviço"),0)))) -> 56000 | O45: Contratação PJ (rateado em 2 obras) | P45: Finalizado
A46: =IF($H46="UNIDADE CONSTRUTIVA",OFFSET(A46,-1,0)+1,LARGE(A$3:A45,1)) -> 0 | B46: =IF(H46="UNIDADE CONSTRUTIVA",0,IF(H46="CÉLULA CONSTRUTIVA",OFFSET(B46,-1,0)+1,OFFSET(B46,-1,0))) -> 2 | C46: =IF(H46="CÉLULA CONSTRUTIVA",0,IF(H46="ETAPA",OFFSET(C46,-1,0)+1,OFFSET(C46,-1,0))) -> 2 | D46: =IF(H46="ETAPA",0,IF(H46="SUBETAPA",OFFSET(D46,-1,0)+1,OFFSET(D46,-1,0))) -> 2 | E46: =IF(H46="Subetapa",0,IF(H46="serviço",OFFSET(E46,-1,0)+1,OFFSET(E46,-1,0))) -> 0 | H46: SUBETAPA | I46: =IF(H46="Unidade Construtiva",TEXT(A46,"00"),IF(H46="Célula Construtiva",TEXT(B46,"00"),IF(H46="Etapa",CONCATENATE(TEXT(B46,"00"),".",TEXT(C46,"000")),IF(H46="Subetapa",CONCATENATE(TEXT(B46,"00"),".",TEXT(C46,"000"),".",TEXT(D46,"000")),IF(H46="Serviço",CONCATENATE(TEXT(B46,"00"),".",TEXT(C46,"000"),".",TEXT(D46,"000"),".",TEXT(E46,"000")),""))))) -> 02.002.002 | J46: Despesas de Consumo e Manutenção | N46: =IF(H46="Serviço",M46*L46,IF(H46="CÉLULA CONSTRUTIVA",SUMIFS($N$8:$N$368,$B$8:$B$368,B46,$H$8:$H$368,"Serviço"),IF(H46="ETAPA",SUMIFS($N$8:$N$368,$B$8:$B$368,B46,$C$8:$C$368,C46,$H$8:$H$368,"Serviço"),IF(H46="SUBETAPA",SUMIFS($N$8:$N$368,$B$8:$B$368,B46,$C$8:$C$368,C46,$D$8:$D$368,D46,$H$8:$H$368,"Serviço"),0)))) -> 35144.512
A47: =IF($H47="UNIDADE CONSTRUTIVA",OFFSET(A47,-1,0)+1,LARGE(A$3:A46,1)) -> 0 | B47: =IF(H47="UNIDADE CONSTRUTIVA",0,IF(H47="CÉLULA CONSTRUTIVA",OFFSET(B47,-1,0)+1,OFFSET(B47,-1,0))) -> 2 | C47: =IF(H47="CÉLULA CONSTRUTIVA",0,IF(H47="ETAPA",OFFSET(C47,-1,0)+1,OFFSET(C47,-1,0))) -> 2 | D47: =IF(H47="ETAPA",0,IF(H47="SUBETAPA",OFFSET(D47,-1,0)+1,OFFSET(D47,-1,0))) -> 2 | E47: =IF(H47="Subetapa",0,IF(H47="serviço",OFFSET(E47,-1,0)+1,OFFSET(E47,-1,0))) -> 1 | H47: SERVIÇO | I47: =IF(H47="Unidade Construtiva",TEXT(A47,"00"),IF(H47="Célula Construtiva",TEXT(B47,"00"),IF(H47="Etapa",CONCATENATE(TEXT(B47,"00"),".",TEXT(C47,"000")),IF(H47="Subetapa",CONCATENATE(TEXT(B47,"00"),".",TEXT(C47,"000"),".",TEXT(D47,"000")),IF(H47="Serviço",CONCATENATE(TEXT(B47,"00"),".",TEXT(C47,"000"),".",TEXT(D47,"000"),".",TEXT(E47,"000")),""))))) -> 02.002.002.001 | J47: Consumo de água e esgoto | K47: mes | L47: ='Obra '!$E$7 -> 14 | M47: 821.1 | N47: =IF(H47="Serviço",M47*L47,IF(H47="CÉLULA CONSTRUTIVA",SUMIFS($N$8:$N$368,$B$8:$B$368,B47,$H$8:$H$368,"Serviço"),IF(H47="ETAPA",SUMIFS($N$8:$N$368,$B$8:$B$368,B47,$C$8:$C$368,C47,$H$8:$H$368,"Serviço"),IF(H47="SUBETAPA",SUMIFS($N$8:$N$368,$B$8:$B$368,B47,$C$8:$C$368,C47,$D$8:$D$368,D47,$H$8:$H$368,"Serviço"),0)))) -> 11495.4 | O47: Estimado com base em índices históricos | P47: Finalizado
A48: =IF($H48="UNIDADE CONSTRUTIVA",OFFSET(A48,-1,0)+1,LARGE(A$3:A47,1)) -> 0 | B48: =IF(H48="UNIDADE CONSTRUTIVA",0,IF(H48="CÉLULA CONSTRUTIVA",OFFSET(B48,-1,0)+1,OFFSET(B48,-1,0))) -> 2 | C48: =IF(H48="CÉLULA CONSTRUTIVA",0,IF(H48="ETAPA",OFFSET(C48,-1,0)+1,OFFSET(C48,-1,0))) -> 2 | D48: =IF(H48="ETAPA",0,IF(H48="SUBETAPA",OFFSET(D48,-1,0)+1,OFFSET(D48,-1,0))) -> 2 | E48: =IF(H48="Subetapa",0,IF(H48="serviço",OFFSET(E48,-1,0)+1,OFFSET(E48,-1,0))) -> 2 | H48: SERVIÇO | I48: =IF(H48="Unidade Construtiva",TEXT(A48,"00"),IF(H48="Célula Construtiva",TEXT(B48,"00"),IF(H48="Etapa",CONCATENATE(TEXT(B48,"00"),".",TEXT(C48,"000")),IF(H48="Subetapa",CONCATENATE(TEXT(B48,"00"),".",TEXT(C48,"000"),".",TEXT(D48,"000")),IF(H48="Serviço",CONCATENATE(TEXT(B48,"00"),".",TEXT(C48,"000"),".",TEXT(D48,"000"),".",TEXT(E48,"000")),""))))) -> 02.002.002.002 | J48: Consumo de luz/energia | K48: mes | L48: ='Obra '!$E$7 -> 14 | M48: 1000 | N48: =IF(H48="Serviço",M48*L48,IF(H48="CÉLULA CONSTRUTIVA",SUMIFS($N$8:$N$368,$B$8:$B$368,B48,$H$8:$H$368,"Serviço"),IF(H48="ETAPA",SUMIFS($N$8:$N$368,$B$8:$B$368,B48,$C$8:$C$368,C48,$H$8:$H$368,"Serviço"),IF(H48="SUBETAPA",SUMIFS($N$8:$N$368,$B$8:$B$368,B48,$C$8:$C$368,C48,$D$8:$D$368,D48,$H$8:$H$368,"Serviço"),0)))) -> 14000 | O48: Estimado com base em índices históricos | P48: Finalizado
A49: =IF($H49="UNIDADE CONSTRUTIVA",OFFSET(A49,-1,0)+1,LARGE(A$3:A48,1)) -> 0 | B49: =IF(H49="UNIDADE CONSTRUTIVA",0,IF(H49="CÉLULA CONSTRUTIVA",OFFSET(B49,-1,0)+1,OFFSET(B49,-1,0))) -> 2 | C49: =IF(H49="CÉLULA CONSTRUTIVA",0,IF(H49="ETAPA",OFFSET(C49,-1,0)+1,OFFSET(C49,-1,0))) -> 2 | D49: =IF(H49="ETAPA",0,IF(H49="SUBETAPA",OFFSET(D49,-1,0)+1,OFFSET(D49,-1,0))) -> 2 | E49: =IF(H49="Subetapa",0,IF(H49="serviço",OFFSET(E49,-1,0)+1,OFFSET(E49,-1,0))) -> 3 | H49: SERVIÇO | I49: =IF(H49="Unidade Construtiva",TEXT(A49,"00"),IF(H49="Célula Construtiva",TEXT(B49,"00"),IF(H49="Etapa",CONCATENATE(TEXT(B49,"00"),".",TEXT(C49,"000")),IF(H49="Subetapa",CONCATENATE(TEXT(B49,"00"),".",TEXT(C49,"000"),".",TEXT(D49,"000")),IF(H49="Serviço",CONCATENATE(TEXT(B49,"00"),".",TEXT(C49,"000"),".",TEXT(D49,"000"),".",TEXT(E49,"000")),""))))) -> 02.002.002.003 | J49: Consumo internet | K49: mes | L49: ='Obra '!$E$7 -> 14 | M49: 120 | N49: =IF(H49="Serviço",M49*L49,IF(H49="CÉLULA CONSTRUTIVA",SUMIFS($N$8:$N$368,$B$8:$B$368,B49,$H$8:$H$368,"Serviço"),IF(H49="ETAPA",SUMIFS($N$8:$N$368,$B$8:$B$368,B49,$C$8:$C$368,C49,$H$8:$H$368,"Serviço"),IF(H49="SUBETAPA",SUMIFS($N$8:$N$368,$B$8:$B$368,B49,$C$8:$C$368,C49,$D$8:$D$368,D49,$H$8:$H$368,"Serviço"),0)))) -> 1680 | O49: Estimado com base em índices históricos | P49: Finalizado
A50: =IF($H50="UNIDADE CONSTRUTIVA",OFFSET(A50,-1,0)+1,LARGE(A$3:A49,1)) -> 0 | B50: =IF(H50="UNIDADE CONSTRUTIVA",0,IF(H50="CÉLULA CONSTRUTIVA",OFFSET(B50,-1,0)+1,OFFSET(B50,-1,0))) -> 2 | C50: =IF(H50="CÉLULA CONSTRUTIVA",0,IF(H50="ETAPA",OFFSET(C50,-1,0)+1,OFFSET(C50,-1,0))) -> 2 | D50: =IF(H50="ETAPA",0,IF(H50="SUBETAPA",OFFSET(D50,-1,0)+1,OFFSET(D50,-1,0))) -> 2 | E50: =IF(H50="Subetapa",0,IF(H50="serviço",OFFSET(E50,-1,0)+1,OFFSET(E50,-1,0))) -> 4 | H50: SERVIÇO | I50: =IF(H50="Unidade Construtiva",TEXT(A50,"00"),IF(H50="Célula Construtiva",TEXT(B50,"00"),IF(H50="Etapa",CONCATENATE(TEXT(B50,"00"),".",TEXT(C50,"000")),IF(H50="Subetapa",CONCATENATE(TEXT(B50,"00"),".",TEXT(C50,"000"),".",TEXT(D50,"000")),IF(H50="Serviço",CONCATENATE(TEXT(B50,"00"),".",TEXT(C50,"000"),".",TEXT(D50,"000"),".",TEXT(E50,"000")),""))))) -> 02.002.002.004 | J50: Coleta de lixo | K50: mes | L50: ='Obra '!$E$7 -> 14 | M50: 61.53 | N50: =IF(H50="Serviço",M50*L50,IF(H50="CÉLULA CONSTRUTIVA",SUMIFS($N$8:$N$368,$B$8:$B$368,B50,$H$8:$H$368,"Serviço"),IF(H50="ETAPA",SUMIFS($N$8:$N$368,$B$8:$B$368,B50,$C$8:$C$368,C50,$H$8:$H$368,"Serviço"),IF(H50="SUBETAPA",SUMIFS($N$8:$N$368,$B$8:$B$368,B50,$C$8:$C$368,C50,$D$8:$D$368,D50,$H$8:$H$368,"Serviço"),0)))) -> 861.42 | O50: Estimado com base em índices históricos | P50: Finalizado
A51: =IF($H51="UNIDADE CONSTRUTIVA",OFFSET(A51,-1,0)+1,LARGE(A$3:A50,1)) -> 0 | B51: =IF(H51="UNIDADE CONSTRUTIVA",0,IF(H51="CÉLULA CONSTRUTIVA",OFFSET(B51,-1,0)+1,OFFSET(B51,-1,0))) -> 2 | C51: =IF(H51="CÉLULA CONSTRUTIVA",0,IF(H51="ETAPA",OFFSET(C51,-1,0)+1,OFFSET(C51,-1,0))) -> 2 | D51: =IF(H51="ETAPA",0,IF(H51="SUBETAPA",OFFSET(D51,-1,0)+1,OFFSET(D51,-1,0))) -> 2 | E51: =IF(H51="Subetapa",0,IF(H51="serviço",OFFSET(E51,-1,0)+1,OFFSET(E51,-1,0))) -> 5 | H51: SERVIÇO | I51: =IF(H51="Unidade Construtiva",TEXT(A51,"00"),IF(H51="Célula Construtiva",TEXT(B51,"00"),IF(H51="Etapa",CONCATENATE(TEXT(B51,"00"),".",TEXT(C51,"000")),IF(H51="Subetapa",CONCATENATE(TEXT(B51,"00"),".",TEXT(C51,"000"),".",TEXT(D51,"000")),IF(H51="Serviço",CONCATENATE(TEXT(B51,"00"),".",TEXT(C51,"000"),".",TEXT(D51,"000"),".",TEXT(E51,"000")),""))))) -> 02.002.002.005 | J51: Consumo de material de higiene e limpeza | K51: mes | L51: ='Obra '!$E$7 -> 14 | M51: 307.92 | N51: =IF(H51="Serviço",M51*L51,IF(H51="CÉLULA CONSTRUTIVA",SUMIFS($N$8:$N$368,$B$8:$B$368,B51,$H$8:$H$368,"Serviço"),IF(H51="ETAPA",SUMIFS($N$8:$N$368,$B$8:$B$368,B51,$C$8:$C$368,C51,$H$8:$H$368,"Serviço"),IF(H51="SUBETAPA",SUMIFS($N$8:$N$368,$B$8:$B$368,B51,$C$8:$C$368,C51,$D$8:$D$368,D51,$H$8:$H$368,"Serviço"),0)))) -> 4310.88 | O51: Estimado com base em índices históricos | P51: Finalizado
A52: =IF($H52="UNIDADE CONSTRUTIVA",OFFSET(A52,-1,0)+1,LARGE(A$3:A51,1)) -> 0 | B52: =IF(H52="UNIDADE CONSTRUTIVA",0,IF(H52="CÉLULA CONSTRUTIVA",OFFSET(B52,-1,0)+1,OFFSET(B52,-1,0))) -> 2 | C52: =IF(H52="CÉLULA CONSTRUTIVA",0,IF(H52="ETAPA",OFFSET(C52,-1,0)+1,OFFSET(C52,-1,0))) -> 2 | D52: =IF(H52="ETAPA",0,IF(H52="SUBETAPA",OFFSET(D52,-1,0)+1,OFFSET(D52,-1,0))) -> 2 | E52: =IF(H52="Subetapa",0,IF(H52="serviço",OFFSET(E52,-1,0)+1,OFFSET(E52,-1,0))) -> 6 | H52: SERVIÇO | I52: =IF(H52="Unidade Construtiva",TEXT(A52,"00"),IF(H52="Célula Construtiva",TEXT(B52,"00"),IF(H52="Etapa",CONCATENATE(TEXT(B52,"00"),".",TEXT(C52,"000")),IF(H52="Subetapa",CONCATENATE(TEXT(B52,"00"),".",TEXT(C52,"000"),".",TEXT(D52,"000")),IF(H52="Serviço",CONCATENATE(TEXT(B52,"00"),".",TEXT(C52,"000"),".",TEXT(D52,"000"),".",TEXT(E52,"000")),""))))) -> 02.002.002.006 | J52: Frete | K52: vb | L52: 1 | M52: 2796.812 | N52: =IF(H52="Serviço",M52*L52,IF(H52="CÉLULA CONSTRUTIVA",SUMIFS($N$8:$N$368,$B$8:$B$368,B52,$H$8:$H$368,"Serviço"),IF(H52="ETAPA",SUMIFS($N$8:$N$368,$B$8:$B$368,B52,$C$8:$C$368,C52,$H$8:$H$368,"Serviço"),IF(H52="SUBETAPA",SUMIFS($N$8:$N$368,$B$8:$B$368,B52,$C$8:$C$368,C52,$D$8:$D$368,D52,$H$8:$H$368,"Serviço"),0)))) -> 2796.812 | O52: Estimado com base em índices históricos | P52: Finalizado
A53: =IF($H53="UNIDADE CONSTRUTIVA",OFFSET(A53,-1,0)+1,LARGE(A$3:A52,1)) -> 0 | B53: =IF(H53="UNIDADE CONSTRUTIVA",0,IF(H53="CÉLULA CONSTRUTIVA",OFFSET(B53,-1,0)+1,OFFSET(B53,-1,0))) -> 2 | C53: =IF(H53="CÉLULA CONSTRUTIVA",0,IF(H53="ETAPA",OFFSET(C53,-1,0)+1,OFFSET(C53,-1,0))) -> 2 | D53: =IF(H53="ETAPA",0,IF(H53="SUBETAPA",OFFSET(D53,-1,0)+1,OFFSET(D53,-1,0))) -> 3 | E53: =IF(H53="Subetapa",0,IF(H53="serviço",OFFSET(E53,-1,0)+1,OFFSET(E53,-1,0))) -> 0 | H53: SUBETAPA | I53: =IF(H53="Unidade Construtiva",TEXT(A53,"00"),IF(H53="Célula Construtiva",TEXT(B53,"00"),IF(H53="Etapa",CONCATENATE(TEXT(B53,"00"),".",TEXT(C53,"000")),IF(H53="Subetapa",CONCATENATE(TEXT(B53,"00"),".",TEXT(C53,"000"),".",TEXT(D53,"000")),IF(H53="Serviço",CONCATENATE(TEXT(B53,"00"),".",TEXT(C53,"000"),".",TEXT(D53,"000"),".",TEXT(E53,"000")),""))))) -> 02.002.003 | J53: Instalações Provisórias | N53: =IF(H53="Serviço",M53*L53,IF(H53="CÉLULA CONSTRUTIVA",SUMIFS($N$8:$N$368,$B$8:$B$368,B53,$H$8:$H$368,"Serviço"),IF(H53="ETAPA",SUMIFS($N$8:$N$368,$B$8:$B$368,B53,$C$8:$C$368,C53,$H$8:$H$368,"Serviço"),IF(H53="SUBETAPA",SUMIFS($N$8:$N$368,$B$8:$B$368,B53,$C$8:$C$368,C53,$D$8:$D$368,D53,$H$8:$H$368,"Serviço"),0)))) -> 22950.902
A54: =IF($H54="UNIDADE CONSTRUTIVA",OFFSET(A54,-1,0)+1,LARGE(A$3:A53,1)) -> 0 | B54: =IF(H54="UNIDADE CONSTRUTIVA",0,IF(H54="CÉLULA CONSTRUTIVA",OFFSET(B54,-1,0)+1,OFFSET(B54,-1,0))) -> 2 | C54: =IF(H54="CÉLULA CONSTRUTIVA",0,IF(H54="ETAPA",OFFSET(C54,-1,0)+1,OFFSET(C54,-1,0))) -> 2 | D54: =IF(H54="ETAPA",0,IF(H54="SUBETAPA",OFFSET(D54,-1,0)+1,OFFSET(D54,-1,0))) -> 3 | E54: =IF(H54="Subetapa",0,IF(H54="serviço",OFFSET(E54,-1,0)+1,OFFSET(E54,-1,0))) -> 1 | H54: SERVIÇO | I54: =IF(H54="Unidade Construtiva",TEXT(A54,"00"),IF(H54="Célula Construtiva",TEXT(B54,"00"),IF(H54="Etapa",CONCATENATE(TEXT(B54,"00"),".",TEXT(C54,"000")),IF(H54="Subetapa",CONCATENATE(TEXT(B54,"00"),".",TEXT(C54,"000"),".",TEXT(D54,"000")),IF(H54="Serviço",CONCATENATE(TEXT(B54,"00"),".",TEXT(C54,"000"),".",TEXT(D54,"000"),".",TEXT(E54,"000")),""))))) -> 02.002.003.001 | J54: Instalações Provisórias (central de aço, formas, argamassa, almoxarifado geral, construções temporárias) | K54: vb | L54: 1 | M54: 2938.54 | N54: =IF(H54="Serviço",M54*L54,IF(H54="CÉLULA CONSTRUTIVA",SUMIFS($N$8:$N$368,$B$8:$B$368,B54,$H$8:$H$368,"Serviço"),IF(H54="ETAPA",SUMIFS($N$8:$N$368,$B$8:$B$368,B54,$C$8:$C$368,C54,$H$8:$H$368,"Serviço"),IF(H54="SUBETAPA",SUMIFS($N$8:$N$368,$B$8:$B$368,B54,$C$8:$C$368,C54,$D$8:$D$368,D54,$H$8:$H$368,"Serviço"),0)))) -> 2938.54 | O54: Estimado com base em índices históricos | P54: Finalizado
A55: =IF($H55="UNIDADE CONSTRUTIVA",OFFSET(A55,-1,0)+1,LARGE(A$3:A54,1)) -> 0 | B55: =IF(H55="UNIDADE CONSTRUTIVA",0,IF(H55="CÉLULA CONSTRUTIVA",OFFSET(B55,-1,0)+1,OFFSET(B55,-1,0))) -> 2 | C55: =IF(H55="CÉLULA CONSTRUTIVA",0,IF(H55="ETAPA",OFFSET(C55,-1,0)+1,OFFSET(C55,-1,0))) -> 2 | D55: =IF(H55="ETAPA",0,IF(H55="SUBETAPA",OFFSET(D55,-1,0)+1,OFFSET(D55,-1,0))) -> 3 | E55: =IF(H55="Subetapa",0,IF(H55="serviço",OFFSET(E55,-1,0)+1,OFFSET(E55,-1,0))) -> 2 | H55: SERVIÇO | I55: =IF(H55="Unidade Construtiva",TEXT(A55,"00"),IF(H55="Célula Construtiva",TEXT(B55,"00"),IF(H55="Etapa",CONCATENATE(TEXT(B55,"00"),".",TEXT(C55,"000")),IF(H55="Subetapa",CONCATENATE(TEXT(B55,"00"),".",TEXT(C55,"000"),".",TEXT(D55,"000")),IF(H55="Serviço",CONCATENATE(TEXT(B55,"00"),".",TEXT(C55,"000"),".",TEXT(D55,"000"),".",TEXT(E55,"000")),""))))) -> 02.002.003.002 | J55: Locação de banheiro químico | K55: mes | L55: 6 | M55: =800 -> 800 | N55: =IF(H55="Serviço",M55*L55,IF(H55="CÉLULA CONSTRUTIVA",SUMIFS($N$8:$N$368,$B$8:$B$368,B55,$H$8:$H$368,"Serviço"),IF(H55="ETAPA",SUMIFS($N$8:$N$368,$B$8:$B$368,B55,$C$8:$C$368,C55,$H$8:$H$368,"Serviço"),IF(H55="SUBETAPA",SUMIFS($N$8:$N$368,$B$8:$B$368,B55,$C$8:$C$368,C55,$D$8:$D$368,D55,$H$8:$H$368,"Serviço"),0)))) -> 4800 | O55: Previsto locação de um banheiro | P55: Finalizado
A56: =IF($H56="UNIDADE CONSTRUTIVA",OFFSET(A56,-1,0)+1,LARGE(A$3:A55,1)) -> 0 | B56: =IF(H56="UNIDADE CONSTRUTIVA",0,IF(H56="CÉLULA CONSTRUTIVA",OFFSET(B56,-1,0)+1,OFFSET(B56,-1,0))) -> 2 | C56: =IF(H56="CÉLULA CONSTRUTIVA",0,IF(H56="ETAPA",OFFSET(C56,-1,0)+1,OFFSET(C56,-1,0))) -> 2 | D56: =IF(H56="ETAPA",0,IF(H56="SUBETAPA",OFFSET(D56,-1,0)+1,OFFSET(D56,-1,0))) -> 3 | E56: =IF(H56="Subetapa",0,IF(H56="serviço",OFFSET(E56,-1,0)+1,OFFSET(E56,-1,0))) -> 3 | H56: SERVIÇO | I56: =IF(H56="Unidade Construtiva",TEXT(A56,"00"),IF(H56="Célula Construtiva",TEXT(B56,"00"),IF(H56="Etapa",CONCATENATE(TEXT(B56,"00"),".",TEXT(C56,"000")),IF(H56="Subetapa",CONCATENATE(TEXT(B56,"00"),".",TEXT(C56,"000"),".",TEXT(D56,"000")),IF(H56="Serviço",CONCATENATE(TEXT(B56,"00"),".",TEXT(C56,"000"),".",TEXT(D56,"000"),".",TEXT(E56,"000")),""))))) -> 02.002.003.003 | J56: Tapume de telha metálica trapezoidal | K56: m2 | L56: =(30.29+13.86)*2.1 -> 92.715 | M56: =CPU!H191 -> 164.0766 | N56: =IF(H56="Serviço",M56*L56,IF(H56="CÉLULA CONSTRUTIVA",SUMIFS($N$8:$N$368,$B$8:$B$368,B56,$H$8:$H$368,"Serviço"),IF(H56="ETAPA",SUMIFS($N$8:$N$368,$B$8:$B$368,B56,$C$8:$C$368,C56,$H$8:$H$368,"Serviço"),IF(H56="SUBETAPA",SUMIFS($N$8:$N$368,$B$8:$B$368,B56,$C$8:$C$368,C56,$D$8:$D$368,D56,$H$8:$H$368,"Serviço"),0)))) -> 15212.362 | O56: Fechamento de laterais de encontro com a rua | P56: Finalizado
A57: =IF($H57="UNIDADE CONSTRUTIVA",OFFSET(A57,-1,0)+1,LARGE(A$3:A56,1)) -> 0 | B57: =IF(H57="UNIDADE CONSTRUTIVA",0,IF(H57="CÉLULA CONSTRUTIVA",OFFSET(B57,-1,0)+1,OFFSET(B57,-1,0))) -> 2 | C57: =IF(H57="CÉLULA CONSTRUTIVA",0,IF(H57="ETAPA",OFFSET(C57,-1,0)+1,OFFSET(C57,-1,0))) -> 2 | D57: =IF(H57="ETAPA",0,IF(H57="SUBETAPA",OFFSET(D57,-1,0)+1,OFFSET(D57,-1,0))) -> 4 | E57: =IF(H57="Subetapa",0,IF(H57="serviço",OFFSET(E57,-1,0)+1,OFFSET(E57,-1,0))) -> 0 | H57: SUBETAPA | I57: =IF(H57="Unidade Construtiva",TEXT(A57,"00"),IF(H57="Célula Construtiva",TEXT(B57,"00"),IF(H57="Etapa",CONCATENATE(TEXT(B57,"00"),".",TEXT(C57,"000")),IF(H57="Subetapa",CONCATENATE(TEXT(B57,"00"),".",TEXT(C57,"000"),".",TEXT(D57,"000")),IF(H57="Serviço",CONCATENATE(TEXT(B57,"00"),".",TEXT(C57,"000"),".",TEXT(D57,"000"),".",TEXT(E57,"000")),""))))) -> 02.002.004 | J57: Ligações Provisórias | N57: =IF(H57="Serviço",M57*L57,IF(H57="CÉLULA CONSTRUTIVA",SUMIFS($N$8:$N$368,$B$8:$B$368,B57,$H$8:$H$368,"Serviço"),IF(H57="ETAPA",SUMIFS($N$8:$N$368,$B$8:$B$368,B57,$C$8:$C$368,C57,$H$8:$H$368,"Serviço"),IF(H57="SUBETAPA",SUMIFS($N$8:$N$368,$B$8:$B$368,B57,$C$8:$C$368,C57,$D$8:$D$368,D57,$H$8:$H$368,"Serviço"),0)))) -> 2000
A58: =IF($H58="UNIDADE CONSTRUTIVA",OFFSET(A58,-1,0)+1,LARGE(A$3:A57,1)) -> 0 | B58: =IF(H58="UNIDADE CONSTRUTIVA",0,IF(H58="CÉLULA CONSTRUTIVA",OFFSET(B58,-1,0)+1,OFFSET(B58,-1,0))) -> 2 | C58: =IF(H58="CÉLULA CONSTRUTIVA",0,IF(H58="ETAPA",OFFSET(C58,-1,0)+1,OFFSET(C58,-1,0))) -> 2 | D58: =IF(H58="ETAPA",0,IF(H58="SUBETAPA",OFFSET(D58,-1,0)+1,OFFSET(D58,-1,0))) -> 4 | E58: =IF(H58="Subetapa",0,IF(H58="serviço",OFFSET(E58,-1,0)+1,OFFSET(E58,-1,0))) -> 1 | H58: SERVIÇO | I58: =IF(H58="Unidade Construtiva",TEXT(A58,"00"),IF(H58="Célula Construtiva",TEXT(B58,"00"),IF(H58="Etapa",CONCATENATE(TEXT(B58,"00"),".",TEXT(C58,"000")),IF(H58="Subetapa",CONCATENATE(TEXT(B58,"00"),".",TEXT(C58,"000"),".",TEXT(D58,"000")),IF(H58="Serviço",CONCATENATE(TEXT(B58,"00"),".",TEXT(C58,"000"),".",TEXT(D58,"000"),".",TEXT(E58,"000")),""))))) -> 02.002.004.001 | J58: Rede de água fria, esgoto e drenagem | K58: vb | L58: 1 | M58: 1100 | N58: =IF(H58="Serviço",M58*L58,IF(H58="CÉLULA CONSTRUTIVA",SUMIFS($N$8:$N$368,$B$8:$B$368,B58,$H$8:$H$368,"Serviço"),IF(H58="ETAPA",SUMIFS($N$8:$N$368,$B$8:$B$368,B58,$C$8:$C$368,C58,$H$8:$H$368,"Serviço"),IF(H58="SUBETAPA",SUMIFS($N$8:$N$368,$B$8:$B$368,B58,$C$8:$C$368,C58,$D$8:$D$368,D58,$H$8:$H$368,"Serviço"),0)))) -> 1100 | O58: Estimado com base em índices históricos | P58: Finalizado
A59: =IF($H59="UNIDADE CONSTRUTIVA",OFFSET(A59,-1,0)+1,LARGE(A$3:A58,1)) -> 0 | B59: =IF(H59="UNIDADE CONSTRUTIVA",0,IF(H59="CÉLULA CONSTRUTIVA",OFFSET(B59,-1,0)+1,OFFSET(B59,-1,0))) -> 2 | C59: =IF(H59="CÉLULA CONSTRUTIVA",0,IF(H59="ETAPA",OFFSET(C59,-1,0)+1,OFFSET(C59,-1,0))) -> 2 | D59: =IF(H59="ETAPA",0,IF(H59="SUBETAPA",OFFSET(D59,-1,0)+1,OFFSET(D59,-1,0))) -> 4 | E59: =IF(H59="Subetapa",0,IF(H59="serviço",OFFSET(E59,-1,0)+1,OFFSET(E59,-1,0))) -> 2 | H59: SERVIÇO | I59: =IF(H59="Unidade Construtiva",TEXT(A59,"00"),IF(H59="Célula Construtiva",TEXT(B59,"00"),IF(H59="Etapa",CONCATENATE(TEXT(B59,"00"),".",TEXT(C59,"000")),IF(H59="Subetapa",CONCATENATE(TEXT(B59,"00"),".",TEXT(C59,"000"),".",TEXT(D59,"000")),IF(H59="Serviço",CONCATENATE(TEXT(B59,"00"),".",TEXT(C59,"000"),".",TEXT(D59,"000"),".",TEXT(E59,"000")),""))))) -> 02.002.004.002 | J59: Redes elétricas, comunicação e dados | K59: vb | L59: 1 | M59: 900 | N59: =IF(H59="Serviço",M59*L59,IF(H59="CÉLULA CONSTRUTIVA",SUMIFS($N$8:$N$368,$B$8:$B$368,B59,$H$8:$H$368,"Serviço"),IF(H59="ETAPA",SUMIFS($N$8:$N$368,$B$8:$B$368,B59,$C$8:$C$368,C59,$H$8:$H$368,"Serviço"),IF(H59="SUBETAPA",SUMIFS($N$8:$N$368,$B$8:$B$368,B59,$C$8:$C$368,C59,$D$8:$D$368,D59,$H$8:$H$368,"Serviço"),0)))) -> 900 | O59: Estimado com base em índices históricos | P59: Finalizado
A60: =IF($H60="UNIDADE CONSTRUTIVA",OFFSET(A60,-1,0)+1,LARGE(A$3:A59,1)) -> 0 | B60: =IF(H60="UNIDADE CONSTRUTIVA",0,IF(H60="CÉLULA CONSTRUTIVA",OFFSET(B60,-1,0)+1,OFFSET(B60,-1,0))) -> 3 | C60: =IF(H60="CÉLULA CONSTRUTIVA",0,IF(H60="ETAPA",OFFSET(C60,-1,0)+1,OFFSET(C60,-1,0))) -> 0 | D60: =IF(H60="ETAPA",0,IF(H60="SUBETAPA",OFFSET(D60,-1,0)+1,OFFSET(D60,-1,0))) -> 4 | E60: =IF(H60="Subetapa",0,IF(H60="serviço",OFFSET(E60,-1,0)+1,OFFSET(E60,-1,0))) -> 2 | H60: CÉLULA CONSTRUTIVA | I60: =IF(H60="Unidade Construtiva",TEXT(A60,"00"),IF(H60="Célula Construtiva",TEXT(B60,"00"),IF(H60="Etapa",CONCATENATE(TEXT(B60,"00"),".",TEXT(C60,"000")),IF(H60="Subetapa",CONCATENATE(TEXT(B60,"00"),".",TEXT(C60,"000"),".",TEXT(D60,"000")),IF(H60="Serviço",CONCATENATE(TEXT(B60,"00"),".",TEXT(C60,"000"),".",TEXT(D60,"000"),".",TEXT(E60,"000")),""))))) -> 03 | J60: SERVIÇOS PRELIMINARES | N60: =IF(H60="Serviço",M60*L60,IF(H60="CÉLULA CONSTRUTIVA",SUMIFS($N$8:$N$368,$B$8:$B$368,B60,$H$8:$H$368,"Serviço"),IF(H60="ETAPA",SUMIFS($N$8:$N$368,$B$8:$B$368,B60,$C$8:$C$368,C60,$H$8:$H$368,"Serviço"),IF(H60="SUBETAPA",SUMIFS($N$8:$N$368,$B$8:$B$368,B60,$C$8:$C$368,C60,$D$8:$D$368,D60,$H$8:$H$368,"Serviço"),0)))) -> 1977.42
A61: =IF($H61="UNIDADE CONSTRUTIVA",OFFSET(A61,-1,0)+1,LARGE(A$3:A60,1)) -> 0 | B61: =IF(H61="UNIDADE CONSTRUTIVA",0,IF(H61="CÉLULA CONSTRUTIVA",OFFSET(B61,-1,0)+1,OFFSET(B61,-1,0))) -> 3 | C61: =IF(H61="CÉLULA CONSTRUTIVA",0,IF(H61="ETAPA",OFFSET(C61,-1,0)+1,OFFSET(C61,-1,0))) -> 0 | D61: =IF(H61="ETAPA",0,IF(H61="SUBETAPA",OFFSET(D61,-1,0)+1,OFFSET(D61,-1,0))) -> 5 | E61: =IF(H61="Subetapa",0,IF(H61="serviço",OFFSET(E61,-1,0)+1,OFFSET(E61,-1,0))) -> 0 | H61: SUBETAPA | I61: =IF(H61="Unidade Construtiva",TEXT(A61,"00"),IF(H61="Célula Construtiva",TEXT(B61,"00"),IF(H61="Etapa",CONCATENATE(TEXT(B61,"00"),".",TEXT(C61,"000")),IF(H61="Subetapa",CONCATENATE(TEXT(B61,"00"),".",TEXT(C61,"000"),".",TEXT(D61,"000")),IF(H61="Serviço",CONCATENATE(TEXT(B61,"00"),".",TEXT(C61,"000"),".",TEXT(D61,"000"),".",TEXT(E61,"000")),""))))) -> 03.000.005 | J61: Desmobilização de canteiro | N61: =IF(H61="Serviço",M61*L61,IF(H61="CÉLULA CONSTRUTIVA",SUMIFS($N$8:$N$368,$B$8:$B$368,B61,$H$8:$H$368,"Serviço"),IF(H61="ETAPA",SUMIFS($N$8:$N$368,$B$8:$B$368,B61,$C$8:$C$368,C61,$H$8:$H$368,"Serviço"),IF(H61="SUBETAPA",SUMIFS($N$8:$N$368,$B$8:$B$368,B61,$C$8:$C$368,C61,$D$8:$D$368,D61,$H$8:$H$368,"Serviço"),0)))) -> 659.14
A62: =IF($H62="UNIDADE CONSTRUTIVA",OFFSET(A62,-1,0)+1,LARGE(A$3:A61,1)) -> 0 | B62: =IF(H62="UNIDADE CONSTRUTIVA",0,IF(H62="CÉLULA CONSTRUTIVA",OFFSET(B62,-1,0)+1,OFFSET(B62,-1,0))) -> 3 | C62: =IF(H62="CÉLULA CONSTRUTIVA",0,IF(H62="ETAPA",OFFSET(C62,-1,0)+1,OFFSET(C62,-1,0))) -> 0 | D62: =IF(H62="ETAPA",0,IF(H62="SUBETAPA",OFFSET(D62,-1,0)+1,OFFSET(D62,-1,0))) -> 5 | E62: =IF(H62="Subetapa",0,IF(H62="serviço",OFFSET(E62,-1,0)+1,OFFSET(E62,-1,0))) -> 1 | H62: SERVIÇO | I62: =IF(H62="Unidade Construtiva",TEXT(A62,"00"),IF(H62="Célula Construtiva",TEXT(B62,"00"),IF(H62="Etapa",CONCATENATE(TEXT(B62,"00"),".",TEXT(C62,"000")),IF(H62="Subetapa",CONCATENATE(TEXT(B62,"00"),".",TEXT(C62,"000"),".",TEXT(D62,"000")),IF(H62="Serviço",CONCATENATE(TEXT(B62,"00"),".",TEXT(C62,"000"),".",TEXT(D62,"000"),".",TEXT(E62,"000")),""))))) -> 03.000.005.001 | J62: Mobilização/Desmobilização Canteiro | K62: vb | L62: 1 | M62: =2*'Obra '!E9 -> 659.14 | N62: =IF(H62="Serviço",M62*L62,IF(H62="CÉLULA CONSTRUTIVA",SUMIFS($N$8:$N$368,$B$8:$B$368,B62,$H$8:$H$368,"Serviço"),IF(H62="ETAPA",SUMIFS($N$8:$N$368,$B$8:$B$368,B62,$C$8:$C$368,C62,$H$8:$H$368,"Serviço"),IF(H62="SUBETAPA",SUMIFS($N$8:$N$368,$B$8:$B$368,B62,$C$8:$C$368,C62,$D$8:$D$368,D62,$H$8:$H$368,"Serviço"),0)))) -> 659.14 | O62: Estimado com base em índices históricos | P62: Finalizado
A63: =IF($H63="UNIDADE CONSTRUTIVA",OFFSET(A63,-1,0)+1,LARGE(A$3:A62,1)) -> 0 | B63: =IF(H63="UNIDADE CONSTRUTIVA",0,IF(H63="CÉLULA CONSTRUTIVA",OFFSET(B63,-1,0)+1,OFFSET(B63,-1,0))) -> 3 | C63: =IF(H63="CÉLULA CONSTRUTIVA",0,IF(H63="ETAPA",OFFSET(C63,-1,0)+1,OFFSET(C63,-1,0))) -> 0 | D63: =IF(H63="ETAPA",0,IF(H63="SUBETAPA",OFFSET(D63,-1,0)+1,OFFSET(D63,-1,0))) -> 6 | E63: =IF(H63="Subetapa",0,IF(H63="serviço",OFFSET(E63,-1,0)+1,OFFSET(E63,-1,0))) -> 0 | H63: SUBETAPA | I63: =IF(H63="Unidade Construtiva",TEXT(A63,"00"),IF(H63="Célula Construtiva",TEXT(B63,"00"),IF(H63="Etapa",CONCATENATE(TEXT(B63,"00"),".",TEXT(C63,"000")),IF(H63="Subetapa",CONCATENATE(TEXT(B63,"00"),".",TEXT(C63,"000"),".",TEXT(D63,"000")),IF(H63="Serviço",CONCATENATE(TEXT(B63,"00"),".",TEXT(C63,"000"),".",TEXT(D63,"000"),".",TEXT(E63,"000")),""))))) -> 03.000.006 | J63: Alteração de infraestrutura existente | N63: =IF(H63="Serviço",M63*L63,IF(H63="CÉLULA CONSTRUTIVA",SUMIFS($N$8:$N$368,$B$8:$B$368,B63,$H$8:$H$368,"Serviço"),IF(H63="ETAPA",SUMIFS($N$8:$N$368,$B$8:$B$368,B63,$C$8:$C$368,C63,$H$8:$H$368,"Serviço"),IF(H63="SUBETAPA",SUMIFS($N$8:$N$368,$B$8:$B$368,B63,$C$8:$C$368,C63,$D$8:$D$368,D63,$H$8:$H$368,"Serviço"),0)))) -> 1318.28
A64: =IF($H64="UNIDADE CONSTRUTIVA",OFFSET(A64,-1,0)+1,LARGE(A$3:A63,1)) -> 0 | B64: =IF(H64="UNIDADE CONSTRUTIVA",0,IF(H64="CÉLULA CONSTRUTIVA",OFFSET(B64,-1,0)+1,OFFSET(B64,-1,0))) -> 3 | C64: =IF(H64="CÉLULA CONSTRUTIVA",0,IF(H64="ETAPA",OFFSET(C64,-1,0)+1,OFFSET(C64,-1,0))) -> 0 | D64: =IF(H64="ETAPA",0,IF(H64="SUBETAPA",OFFSET(D64,-1,0)+1,OFFSET(D64,-1,0))) -> 6 | E64: =IF(H64="Subetapa",0,IF(H64="serviço",OFFSET(E64,-1,0)+1,OFFSET(E64,-1,0))) -> 1 | H64: SERVIÇO | I64: =IF(H64="Unidade Construtiva",TEXT(A64,"00"),IF(H64="Célula Construtiva",TEXT(B64,"00"),IF(H64="Etapa",CONCATENATE(TEXT(B64,"00"),".",TEXT(C64,"000")),IF(H64="Subetapa",CONCATENATE(TEXT(B64,"00"),".",TEXT(C64,"000"),".",TEXT(D64,"000")),IF(H64="Serviço",CONCATENATE(TEXT(B64,"00"),".",TEXT(C64,"000"),".",TEXT(D64,"000"),".",TEXT(E64,"000")),""))))) -> 03.000.006.001 | J64: Alteração de infraestrutura existente | K64: vb | L64: 1 | M64: =4*'Obra '!E9 -> 1318.28 | N64: =IF(H64="Serviço",M64*L64,IF(H64="CÉLULA CONSTRUTIVA",SUMIFS($N$8:$N$368,$B$8:$B$368,B64,$H$8:$H$368,"Serviço"),IF(H64="ETAPA",SUMIFS($N$8:$N$368,$B$8:$B$368,B64,$C$8:$C$368,C64,$H$8:$H$368,"Serviço"),IF(H64="SUBETAPA",SUMIFS($N$8:$N$368,$B$8:$B$368,B64,$C$8:$C$368,C64,$D$8:$D$368,D64,$H$8:$H$368,"Serviço"),0)))) -> 1318.28 | O64: Estimado com base em índices históricos | P64: Finalizado
A65: =IF($H65="UNIDADE CONSTRUTIVA",OFFSET(A65,-1,0)+1,LARGE(A$3:A64,1)) -> 0 | B65: =IF(H65="UNIDADE CONSTRUTIVA",0,IF(H65="CÉLULA CONSTRUTIVA",OFFSET(B65,-1,0)+1,OFFSET(B65,-1,0))) -> 4 | C65: =IF(H65="CÉLULA CONSTRUTIVA",0,IF(H65="ETAPA",OFFSET(C65,-1,0)+1,OFFSET(C65,-1,0))) -> 0 | D65: =IF(H65="ETAPA",0,IF(H65="SUBETAPA",OFFSET(D65,-1,0)+1,OFFSET(D65,-1,0))) -> 6 | E65: =IF(H65="Subetapa",0,IF(H65="serviço",OFFSET(E65,-1,0)+1,OFFSET(E65,-1,0))) -> 1 | H65: CÉLULA CONSTRUTIVA | I65: =IF(H65="Unidade Construtiva",TEXT(A65,"00"),IF(H65="Célula Construtiva",TEXT(B65,"00"),IF(H65="Etapa",CONCATENATE(TEXT(B65,"00"),".",TEXT(C65,"000")),IF(H65="Subetapa",CONCATENATE(TEXT(B65,"00"),".",TEXT(C65,"000"),".",TEXT(D65,"000")),IF(H65="Serviço",CONCATENATE(TEXT(B65,"00"),".",TEXT(C65,"000"),".",TEXT(D65,"000"),".",TEXT(E65,"000")),""))))) -> 04 | J65: EQUIPAMENTOS | N65: =IF(H65="Serviço",M65*L65,IF(H65="CÉLULA CONSTRUTIVA",SUMIFS($N$8:$N$368,$B$8:$B$368,B65,$H$8:$H$368,"Serviço"),IF(H65="ETAPA",SUMIFS($N$8:$N$368,$B$8:$B$368,B65,$C$8:$C$368,C65,$H$8:$H$368,"Serviço"),IF(H65="SUBETAPA",SUMIFS($N$8:$N$368,$B$8:$B$368,B65,$C$8:$C$368,C65,$D$8:$D$368,D65,$H$8:$H$368,"Serviço"),0)))) -> 12882.875
A66: =IF($H66="UNIDADE CONSTRUTIVA",OFFSET(A66,-1,0)+1,LARGE(A$3:A65,1)) -> 0 | B66: =IF(H66="UNIDADE CONSTRUTIVA",0,IF(H66="CÉLULA CONSTRUTIVA",OFFSET(B66,-1,0)+1,OFFSET(B66,-1,0))) -> 4 | C66: =IF(H66="CÉLULA CONSTRUTIVA",0,IF(H66="ETAPA",OFFSET(C66,-1,0)+1,OFFSET(C66,-1,0))) -> 1 | D66: =IF(H66="ETAPA",0,IF(H66="SUBETAPA",OFFSET(D66,-1,0)+1,OFFSET(D66,-1,0))) -> 0 | E66: =IF(H66="Subetapa",0,IF(H66="serviço",OFFSET(E66,-1,0)+1,OFFSET(E66,-1,0))) -> 1 | H66: ETAPA | I66: =IF(H66="Unidade Construtiva",TEXT(A66,"00"),IF(H66="Célula Construtiva",TEXT(B66,"00"),IF(H66="Etapa",CONCATENATE(TEXT(B66,"00"),".",TEXT(C66,"000")),IF(H66="Subetapa",CONCATENATE(TEXT(B66,"00"),".",TEXT(C66,"000"),".",TEXT(D66,"000")),IF(H66="Serviço",CONCATENATE(TEXT(B66,"00"),".",TEXT(C66,"000"),".",TEXT(D66,"000"),".",TEXT(E66,"000")),""))))) -> 04.001 | J66: EQUIPAMENTOS | N66: =IF(H66="Serviço",M66*L66,IF(H66="CÉLULA CONSTRUTIVA",SUMIFS($N$8:$N$368,$B$8:$B$368,B66,$H$8:$H$368,"Serviço"),IF(H66="ETAPA",SUMIFS($N$8:$N$368,$B$8:$B$368,B66,$C$8:$C$368,C66,$H$8:$H$368,"Serviço"),IF(H66="SUBETAPA",SUMIFS($N$8:$N$368,$B$8:$B$368,B66,$C$8:$C$368,C66,$D$8:$D$368,D66,$H$8:$H$368,"Serviço"),0)))) -> 12882.875
A67: =IF($H67="UNIDADE CONSTRUTIVA",OFFSET(A67,-1,0)+1,LARGE(A$3:A66,1)) -> 0 | B67: =IF(H67="UNIDADE CONSTRUTIVA",0,IF(H67="CÉLULA CONSTRUTIVA",OFFSET(B67,-1,0)+1,OFFSET(B67,-1,0))) -> 4 | C67: =IF(H67="CÉLULA CONSTRUTIVA",0,IF(H67="ETAPA",OFFSET(C67,-1,0)+1,OFFSET(C67,-1,0))) -> 1 | D67: =IF(H67="ETAPA",0,IF(H67="SUBETAPA",OFFSET(D67,-1,0)+1,OFFSET(D67,-1,0))) -> 1 | E67: =IF(H67="Subetapa",0,IF(H67="serviço",OFFSET(E67,-1,0)+1,OFFSET(E67,-1,0))) -> 0 | H67: SUBETAPA | I67: =IF(H67="Unidade Construtiva",TEXT(A67,"00"),IF(H67="Célula Construtiva",TEXT(B67,"00"),IF(H67="Etapa",CONCATENATE(TEXT(B67,"00"),".",TEXT(C67,"000")),IF(H67="Subetapa",CONCATENATE(TEXT(B67,"00"),".",TEXT(C67,"000"),".",TEXT(D67,"000")),IF(H67="Serviço",CONCATENATE(TEXT(B67,"00"),".",TEXT(C67,"000"),".",TEXT(D67,"000"),".",TEXT(E67,"000")),""))))) -> 04.001.001 | J67: Equipamentos de Obra | N67: =IF(H67="Serviço",M67*L67,IF(H67="CÉLULA CONSTRUTIVA",SUMIFS($N$8:$N$368,$B$8:$B$368,B67,$H$8:$H$368,"Serviço"),IF(H67="ETAPA",SUMIFS($N$8:$N$368,$B$8:$B$368,B67,$C$8:$C$368,C67,$H$8:$H$368,"Serviço"),IF(H67="SUBETAPA",SUMIFS($N$8:$N$368,$B$8:$B$368,B67,$C$8:$C$368,C67,$D$8:$D$368,D67,$H$8:$H$368,"Serviço"),0)))) -> 3200
A68: =IF($H68="UNIDADE CONSTRUTIVA",OFFSET(A68,-1,0)+1,LARGE(A$3:A67,1)) -> 0 | B68: =IF(H68="UNIDADE CONSTRUTIVA",0,IF(H68="CÉLULA CONSTRUTIVA",OFFSET(B68,-1,0)+1,OFFSET(B68,-1,0))) -> 4 | C68: =IF(H68="CÉLULA CONSTRUTIVA",0,IF(H68="ETAPA",OFFSET(C68,-1,0)+1,OFFSET(C68,-1,0))) -> 1 | D68: =IF(H68="ETAPA",0,IF(H68="SUBETAPA",OFFSET(D68,-1,0)+1,OFFSET(D68,-1,0))) -> 1 | E68: =IF(H68="Subetapa",0,IF(H68="serviço",OFFSET(E68,-1,0)+1,OFFSET(E68,-1,0))) -> 1 | H68: SERVIÇO | I68: =IF(H68="Unidade Construtiva",TEXT(A68,"00"),IF(H68="Célula Construtiva",TEXT(B68,"00"),IF(H68="Etapa",CONCATENATE(TEXT(B68,"00"),".",TEXT(C68,"000")),IF(H68="Subetapa",CONCATENATE(TEXT(B68,"00"),".",TEXT(C68,"000"),".",TEXT(D68,"000")),IF(H68="Serviço",CONCATENATE(TEXT(B68,"00"),".",TEXT(C68,"000"),".",TEXT(D68,"000"),".",TEXT(E68,"000")),""))))) -> 04.001.001.001 | J68: Locação de guincho de coluna | K68: mes | L68: 8 | M68: 400 | N68: =IF(H68="Serviço",M68*L68,IF(H68="CÉLULA CONSTRUTIVA",SUMIFS($N$8:$N$368,$B$8:$B$368,B68,$H$8:$H$368,"Serviço"),IF(H68="ETAPA",SUMIFS($N$8:$N$368,$B$8:$B$368,B68,$C$8:$C$368,C68,$H$8:$H$368,"Serviço"),IF(H68="SUBETAPA",SUMIFS($N$8:$N$368,$B$8:$B$368,B68,$C$8:$C$368,C68,$D$8:$D$368,D68,$H$8:$H$368,"Serviço"),0)))) -> 3200 | O68: Adotado periodo de 8 meses para locação | P68: Finalizado
A69: =IF($H69="UNIDADE CONSTRUTIVA",OFFSET(A69,-1,0)+1,LARGE(A$3:A68,1)) -> 0 | B69: =IF(H69="UNIDADE CONSTRUTIVA",0,IF(H69="CÉLULA CONSTRUTIVA",OFFSET(B69,-1,0)+1,OFFSET(B69,-1,0))) -> 4 | C69: =IF(H69="CÉLULA CONSTRUTIVA",0,IF(H69="ETAPA",OFFSET(C69,-1,0)+1,OFFSET(C69,-1,0))) -> 1 | D69: =IF(H69="ETAPA",0,IF(H69="SUBETAPA",OFFSET(D69,-1,0)+1,OFFSET(D69,-1,0))) -> 2 | E69: =IF(H69="Subetapa",0,IF(H69="serviço",OFFSET(E69,-1,0)+1,OFFSET(E69,-1,0))) -> 0 | H69: SUBETAPA | I69: =IF(H69="Unidade Construtiva",TEXT(A69,"00"),IF(H69="Célula Construtiva",TEXT(B69,"00"),IF(H69="Etapa",CONCATENATE(TEXT(B69,"00"),".",TEXT(C69,"000")),IF(H69="Subetapa",CONCATENATE(TEXT(B69,"00"),".",TEXT(C69,"000"),".",TEXT(D69,"000")),IF(H69="Serviço",CONCATENATE(TEXT(B69,"00"),".",TEXT(C69,"000"),".",TEXT(D69,"000"),".",TEXT(E69,"000")),""))))) -> 04.001.002 | J69: Andaimes | N69: =IF(H69="Serviço",M69*L69,IF(H69="CÉLULA CONSTRUTIVA",SUMIFS($N$8:$N$368,$B$8:$B$368,B69,$H$8:$H$368,"Serviço"),IF(H69="ETAPA",SUMIFS($N$8:$N$368,$B$8:$B$368,B69,$C$8:$C$368,C69,$H$8:$H$368,"Serviço"),IF(H69="SUBETAPA",SUMIFS($N$8:$N$368,$B$8:$B$368,B69,$C$8:$C$368,C69,$D$8:$D$368,D69,$H$8:$H$368,"Serviço"),0)))) -> 9682.875
A70: =IF($H70="UNIDADE CONSTRUTIVA",OFFSET(A70,-1,0)+1,LARGE(A$3:A69,1)) -> 0 | B70: =IF(H70="UNIDADE CONSTRUTIVA",0,IF(H70="CÉLULA CONSTRUTIVA",OFFSET(B70,-1,0)+1,OFFSET(B70,-1,0))) -> 4 | C70: =IF(H70="CÉLULA CONSTRUTIVA",0,IF(H70="ETAPA",OFFSET(C70,-1,0)+1,OFFSET(C70,-1,0))) -> 1 | D70: =IF(H70="ETAPA",0,IF(H70="SUBETAPA",OFFSET(D70,-1,0)+1,OFFSET(D70,-1,0))) -> 2 | E70: =IF(H70="Subetapa",0,IF(H70="serviço",OFFSET(E70,-1,0)+1,OFFSET(E70,-1,0))) -> 1 | H70: SERVIÇO | I70: =IF(H70="Unidade Construtiva",TEXT(A70,"00"),IF(H70="Célula Construtiva",TEXT(B70,"00"),IF(H70="Etapa",CONCATENATE(TEXT(B70,"00"),".",TEXT(C70,"000")),IF(H70="Subetapa",CONCATENATE(TEXT(B70,"00"),".",TEXT(C70,"000"),".",TEXT(D70,"000")),IF(H70="Serviço",CONCATENATE(TEXT(B70,"00"),".",TEXT(C70,"000"),".",TEXT(D70,"000"),".",TEXT(E70,"000")),""))))) -> 04.001.002.001 | J70: Locação e andaime fachadeiro | K70: mes | L70: 2 | M70: =(25*(10.44*2+(1.7+6.46+3.19+6.9)*2)*(3+0.15+3.6))/2 -> 4841.4375 | N70: =IF(H70="Serviço",M70*L70,IF(H70="CÉLULA CONSTRUTIVA",SUMIFS($N$8:$N$368,$B$8:$B$368,B70,$H$8:$H$368,"Serviço"),IF(H70="ETAPA",SUMIFS($N$8:$N$368,$B$8:$B$368,B70,$C$8:$C$368,C70,$H$8:$H$368,"Serviço"),IF(H70="SUBETAPA",SUMIFS($N$8:$N$368,$B$8:$B$368,B70,$C$8:$C$368,C70,$D$8:$D$368,D70,$H$8:$H$368,"Serviço"),0)))) -> 9682.875 | O70: Adotado andaime fachadeiro em duas fachadas simultaneas | P70: Finalizado
A71: =IF($H71="UNIDADE CONSTRUTIVA",OFFSET(A71,-1,0)+1,LARGE(A$3:A68,1)) -> 0 | B71: =IF(H71="UNIDADE CONSTRUTIVA",0,IF(H71="CÉLULA CONSTRUTIVA",OFFSET(B71,-1,0)+1,OFFSET(B71,-1,0))) -> 4 | C71: =IF(H71="CÉLULA CONSTRUTIVA",0,IF(H71="ETAPA",OFFSET(C71,-1,0)+1,OFFSET(C71,-1,0))) -> 1 | D71: =IF(H71="ETAPA",0,IF(H71="SUBETAPA",OFFSET(D71,-1,0)+1,OFFSET(D71,-1,0))) -> 2 | E71: =IF(H71="Subetapa",0,IF(H71="serviço",OFFSET(E71,-1,0)+1,OFFSET(E71,-1,0))) -> 1 | J71: TOTAL | N71: =N65+N34+N8+N60 -> 243899.47
A72: =IF($H72="UNIDADE CONSTRUTIVA",OFFSET(A72,-1,0)+1,LARGE(A$3:A71,1)) -> 0 | B72: =IF(H72="UNIDADE CONSTRUTIVA",0,IF(H72="CÉLULA CONSTRUTIVA",OFFSET(B72,-1,0)+1,OFFSET(B72,-1,0))) -> 4 | C72: =IF(H72="CÉLULA CONSTRUTIVA",0,IF(H72="ETAPA",OFFSET(C72,-1,0)+1,OFFSET(C72,-1,0))) -> 1 | D72: =IF(H72="ETAPA",0,IF(H72="SUBETAPA",OFFSET(D72,-1,0)+1,OFFSET(D72,-1,0))) -> 2 | E72: =IF(H72="Subetapa",0,IF(H72="serviço",OFFSET(E72,-1,0)+1,OFFSET(E72,-1,0))) -> 1 | M72: =SUMIFS($N$7:$N$363,$H$7:$H$363,N72) -> 243899.47 | N72: CÉLULA CONSTRUTIVA
A73: =IF($H73="UNIDADE CONSTRUTIVA",OFFSET(A73,-1,0)+1,LARGE(A$3:A72,1)) -> 0 | B73: =IF(H73="UNIDADE CONSTRUTIVA",0,IF(H73="CÉLULA CONSTRUTIVA",OFFSET(B73,-1,0)+1,OFFSET(B73,-1,0))) -> 4 | C73: =IF(H73="CÉLULA CONSTRUTIVA",0,IF(H73="ETAPA",OFFSET(C73,-1,0)+1,OFFSET(C73,-1,0))) -> 1 | D73: =IF(H73="ETAPA",0,IF(H73="SUBETAPA",OFFSET(D73,-1,0)+1,OFFSET(D73,-1,0))) -> 2 | E73: =IF(H73="Subetapa",0,IF(H73="serviço",OFFSET(E73,-1,0)+1,OFFSET(E73,-1,0))) -> 1 | M73: =SUMIFS($N$7:$N$363,$H$7:$H$363,N73) -> 241922.05 | N73: ETAPA
A74: =IF($H74="UNIDADE CONSTRUTIVA",OFFSET(A74,-1,0)+1,LARGE(A$3:A73,1)) -> 0 | B74: =IF(H74="UNIDADE CONSTRUTIVA",0,IF(H74="CÉLULA CONSTRUTIVA",OFFSET(B74,-1,0)+1,OFFSET(B74,-1,0))) -> 4 | C74: =IF(H74="CÉLULA CONSTRUTIVA",0,IF(H74="ETAPA",OFFSET(C74,-1,0)+1,OFFSET(C74,-1,0))) -> 1 | D74: =IF(H74="ETAPA",0,IF(H74="SUBETAPA",OFFSET(D74,-1,0)+1,OFFSET(D74,-1,0))) -> 2 | E74: =IF(H74="Subetapa",0,IF(H74="serviço",OFFSET(E74,-1,0)+1,OFFSET(E74,-1,0))) -> 1 | M74: =SUMIFS($N$7:$N$363,$H$7:$H$363,N74) -> 243899.47 | N74: SUBETAPA
A75: =IF($H75="UNIDADE CONSTRUTIVA",OFFSET(A75,-1,0)+1,LARGE(A$3:A74,1)) -> 0 | B75: =IF(H75="UNIDADE CONSTRUTIVA",0,IF(H75="CÉLULA CONSTRUTIVA",OFFSET(B75,-1,0)+1,OFFSET(B75,-1,0))) -> 4 | C75: =IF(H75="CÉLULA CONSTRUTIVA",0,IF(H75="ETAPA",OFFSET(C75,-1,0)+1,OFFSET(C75,-1,0))) -> 1 | D75: =IF(H75="ETAPA",0,IF(H75="SUBETAPA",OFFSET(D75,-1,0)+1,OFFSET(D75,-1,0))) -> 2 | E75: =IF(H75="Subetapa",0,IF(H75="serviço",OFFSET(E75,-1,0)+1,OFFSET(E75,-1,0))) -> 1 | M75: =SUMIFS($N$7:$N$363,$H$7:$H$363,N75) -> 243899.47 | N75: SERVIÇO
A76: =IF($H76="UNIDADE CONSTRUTIVA",OFFSET(A76,-1,0)+1,LARGE(A$3:A75,1)) -> 0 | B76: =IF(H76="UNIDADE CONSTRUTIVA",0,IF(H76="CÉLULA CONSTRUTIVA",OFFSET(B76,-1,0)+1,OFFSET(B76,-1,0))) -> 4 | C76: =IF(H76="CÉLULA CONSTRUTIVA",0,IF(H76="ETAPA",OFFSET(C76,-1,0)+1,OFFSET(C76,-1,0))) -> 1 | D76: =IF(H76="ETAPA",0,IF(H76="SUBETAPA",OFFSET(D76,-1,0)+1,OFFSET(D76,-1,0))) -> 2 | E76: =IF(H76="Subetapa",0,IF(H76="serviço",OFFSET(E76,-1,0)+1,OFFSET(E76,-1,0))) -> 1 | M76: ='Obra '!C32 -> 243899.47 | N76: OBRA
A77: =IF($H77="UNIDADE CONSTRUTIVA",OFFSET(A77,-1,0)+1,LARGE(A$3:A76,1)) -> 0 | B77: =IF(H77="UNIDADE CONSTRUTIVA",0,IF(H77="CÉLULA CONSTRUTIVA",OFFSET(B77,-1,0)+1,OFFSET(B77,-1,0))) -> 4 | C77: =IF(H77="CÉLULA CONSTRUTIVA",0,IF(H77="ETAPA",OFFSET(C77,-1,0)+1,OFFSET(C77,-1,0))) -> 1 | D77: =IF(H77="ETAPA",0,IF(H77="SUBETAPA",OFFSET(D77,-1,0)+1,OFFSET(D77,-1,0))) -> 2 | E77: =IF(H77="Subetapa",0,IF(H77="serviço",OFFSET(E77,-1,0)+1,OFFSET(E77,-1,0))) -> 1 | M77: =#REF! -> #REF! | N77: BASES
A78: =IF($H78="UNIDADE CONSTRUTIVA",OFFSET(A78,-1,0)+1,LARGE(A$3:A77,1)) -> 0 | B78: =IF(H78="UNIDADE CONSTRUTIVA",0,IF(H78="CÉLULA CONSTRUTIVA",OFFSET(B78,-1,0)+1,OFFSET(B78,-1,0))) -> 4 | C78: =IF(H78="CÉLULA CONSTRUTIVA",0,IF(H78="ETAPA",OFFSET(C78,-1,0)+1,OFFSET(C78,-1,0))) -> 1 | D78: =IF(H78="ETAPA",0,IF(H78="SUBETAPA",OFFSET(D78,-1,0)+1,OFFSET(D78,-1,0))) -> 2 | E78: =IF(H78="Subetapa",0,IF(H78="serviço",OFFSET(E78,-1,0)+1,OFFSET(E78,-1,0))) -> 1
A79: =IF($H79="UNIDADE CONSTRUTIVA",OFFSET(A79,-1,0)+1,LARGE(A$3:A78,1)) -> 0 | B79: =IF(H79="UNIDADE CONSTRUTIVA",0,IF(H79="CÉLULA CONSTRUTIVA",OFFSET(B79,-1,0)+1,OFFSET(B79,-1,0))) -> 4 | C79: =IF(H79="CÉLULA CONSTRUTIVA",0,IF(H79="ETAPA",OFFSET(C79,-1,0)+1,OFFSET(C79,-1,0))) -> 1 | D79: =IF(H79="ETAPA",0,IF(H79="SUBETAPA",OFFSET(D79,-1,0)+1,OFFSET(D79,-1,0))) -> 2 | E79: =IF(H79="Subetapa",0,IF(H79="serviço",OFFSET(E79,-1,0)+1,OFFSET(E79,-1,0))) -> 1
A80: =IF($H80="UNIDADE CONSTRUTIVA",OFFSET(A80,-1,0)+1,LARGE(A$3:A79,1)) -> 0 | B80: =IF(H80="UNIDADE CONSTRUTIVA",0,IF(H80="CÉLULA CONSTRUTIVA",OFFSET(B80,-1,0)+1,OFFSET(B80,-1,0))) -> 4 | C80: =IF(H80="CÉLULA CONSTRUTIVA",0,IF(H80="ETAPA",OFFSET(C80,-1,0)+1,OFFSET(C80,-1,0))) -> 1 | D80: =IF(H80="ETAPA",0,IF(H80="SUBETAPA",OFFSET(D80,-1,0)+1,OFFSET(D80,-1,0))) -> 2 | E80: =IF(H80="Subetapa",0,IF(H80="serviço",OFFSET(E80,-1,0)+1,OFFSET(E80,-1,0))) -> 1
A81: =IF($H81="UNIDADE CONSTRUTIVA",OFFSET(A81,-1,0)+1,LARGE(A$3:A80,1)) -> 0 | B81: =IF(H81="UNIDADE CONSTRUTIVA",0,IF(H81="CÉLULA CONSTRUTIVA",OFFSET(B81,-1,0)+1,OFFSET(B81,-1,0))) -> 4 | C81: =IF(H81="CÉLULA CONSTRUTIVA",0,IF(H81="ETAPA",OFFSET(C81,-1,0)+1,OFFSET(C81,-1,0))) -> 1 | D81: =IF(H81="ETAPA",0,IF(H81="SUBETAPA",OFFSET(D81,-1,0)+1,OFFSET(D81,-1,0))) -> 2 | E81: =IF(H81="Subetapa",0,IF(H81="serviço",OFFSET(E81,-1,0)+1,OFFSET(E81,-1,0))) -> 1
A82: =IF($H82="UNIDADE CONSTRUTIVA",OFFSET(A82,-1,0)+1,LARGE(A$3:A81,1)) -> 0 | B82: =IF(H82="UNIDADE CONSTRUTIVA",0,IF(H82="CÉLULA CONSTRUTIVA",OFFSET(B82,-1,0)+1,OFFSET(B82,-1,0))) -> 4 | C82: =IF(H82="CÉLULA CONSTRUTIVA",0,IF(H82="ETAPA",OFFSET(C82,-1,0)+1,OFFSET(C82,-1,0))) -> 1 | D82: =IF(H82="ETAPA",0,IF(H82="SUBETAPA",OFFSET(D82,-1,0)+1,OFFSET(D82,-1,0))) -> 2 | E82: =IF(H82="Subetapa",0,IF(H82="serviço",OFFSET(E82,-1,0)+1,OFFSET(E82,-1,0))) -> 1
A83: =IF($H83="UNIDADE CONSTRUTIVA",OFFSET(A83,-1,0)+1,LARGE(A$3:A82,1)) -> 0 | B83: =IF(H83="UNIDADE CONSTRUTIVA",0,IF(H83="CÉLULA CONSTRUTIVA",OFFSET(B83,-1,0)+1,OFFSET(B83,-1,0))) -> 4 | C83: =IF(H83="CÉLULA CONSTRUTIVA",0,IF(H83="ETAPA",OFFSET(C83,-1,0)+1,OFFSET(C83,-1,0))) -> 1 | D83: =IF(H83="ETAPA",0,IF(H83="SUBETAPA",OFFSET(D83,-1,0)+1,OFFSET(D83,-1,0))) -> 2 | E83: =IF(H83="Subetapa",0,IF(H83="serviço",OFFSET(E83,-1,0)+1,OFFSET(E83,-1,0))) -> 1
A84: =IF($H84="UNIDADE CONSTRUTIVA",OFFSET(A84,-1,0)+1,LARGE(A$3:A83,1)) -> 0 | B84: =IF(H84="UNIDADE CONSTRUTIVA",0,IF(H84="CÉLULA CONSTRUTIVA",OFFSET(B84,-1,0)+1,OFFSET(B84,-1,0))) -> 4 | C84: =IF(H84="CÉLULA CONSTRUTIVA",0,IF(H84="ETAPA",OFFSET(C84,-1,0)+1,OFFSET(C84,-1,0))) -> 1 | D84: =IF(H84="ETAPA",0,IF(H84="SUBETAPA",OFFSET(D84,-1,0)+1,OFFSET(D84,-1,0))) -> 2 | E84: =IF(H84="Subetapa",0,IF(H84="serviço",OFFSET(E84,-1,0)+1,OFFSET(E84,-1,0))) -> 1
A85: =IF($H85="UNIDADE CONSTRUTIVA",OFFSET(A85,-1,0)+1,LARGE(A$3:A84,1)) -> 0 | B85: =IF(H85="UNIDADE CONSTRUTIVA",0,IF(H85="CÉLULA CONSTRUTIVA",OFFSET(B85,-1,0)+1,OFFSET(B85,-1,0))) -> 4 | C85: =IF(H85="CÉLULA CONSTRUTIVA",0,IF(H85="ETAPA",OFFSET(C85,-1,0)+1,OFFSET(C85,-1,0))) -> 1 | D85: =IF(H85="ETAPA",0,IF(H85="SUBETAPA",OFFSET(D85,-1,0)+1,OFFSET(D85,-1,0))) -> 2 | E85: =IF(H85="Subetapa",0,IF(H85="serviço",OFFSET(E85,-1,0)+1,OFFSET(E85,-1,0))) -> 1
A86: =IF($H86="UNIDADE CONSTRUTIVA",OFFSET(A86,-1,0)+1,LARGE(A$3:A85,1)) -> 0 | B86: =IF(H86="UNIDADE CONSTRUTIVA",0,IF(H86="CÉLULA CONSTRUTIVA",OFFSET(B86,-1,0)+1,OFFSET(B86,-1,0))) -> 4 | C86: =IF(H86="CÉLULA CONSTRUTIVA",0,IF(H86="ETAPA",OFFSET(C86,-1,0)+1,OFFSET(C86,-1,0))) -> 1 | D86: =IF(H86="ETAPA",0,IF(H86="SUBETAPA",OFFSET(D86,-1,0)+1,OFFSET(D86,-1,0))) -> 2 | E86: =IF(H86="Subetapa",0,IF(H86="serviço",OFFSET(E86,-1,0)+1,OFFSET(E86,-1,0))) -> 1
A87: =IF($H87="UNIDADE CONSTRUTIVA",OFFSET(A87,-1,0)+1,LARGE(A$3:A86,1)) -> 0 | B87: =IF(H87="UNIDADE CONSTRUTIVA",0,IF(H87="CÉLULA CONSTRUTIVA",OFFSET(B87,-1,0)+1,OFFSET(B87,-1,0))) -> 4 | C87: =IF(H87="CÉLULA CONSTRUTIVA",0,IF(H87="ETAPA",OFFSET(C87,-1,0)+1,OFFSET(C87,-1,0))) -> 1 | D87: =IF(H87="ETAPA",0,IF(H87="SUBETAPA",OFFSET(D87,-1,0)+1,OFFSET(D87,-1,0))) -> 2 | E87: =IF(H87="Subetapa",0,IF(H87="serviço",OFFSET(E87,-1,0)+1,OFFSET(E87,-1,0))) -> 1
A88: =IF($H88="UNIDADE CONSTRUTIVA",OFFSET(A88,-1,0)+1,LARGE(A$3:A87,1)) -> 0 | B88: =IF(H88="UNIDADE CONSTRUTIVA",0,IF(H88="CÉLULA CONSTRUTIVA",OFFSET(B88,-1,0)+1,OFFSET(B88,-1,0))) -> 4 | C88: =IF(H88="CÉLULA CONSTRUTIVA",0,IF(H88="ETAPA",OFFSET(C88,-1,0)+1,OFFSET(C88,-1,0))) -> 1 | D88: =IF(H88="ETAPA",0,IF(H88="SUBETAPA",OFFSET(D88,-1,0)+1,OFFSET(D88,-1,0))) -> 2 | E88: =IF(H88="Subetapa",0,IF(H88="serviço",OFFSET(E88,-1,0)+1,OFFSET(E88,-1,0))) -> 1
A89: =IF($H89="UNIDADE CONSTRUTIVA",OFFSET(A89,-1,0)+1,LARGE(A$3:A88,1)) -> 0 | B89: =IF(H89="UNIDADE CONSTRUTIVA",0,IF(H89="CÉLULA CONSTRUTIVA",OFFSET(B89,-1,0)+1,OFFSET(B89,-1,0))) -> 4 | C89: =IF(H89="CÉLULA CONSTRUTIVA",0,IF(H89="ETAPA",OFFSET(C89,-1,0)+1,OFFSET(C89,-1,0))) -> 1 | D89: =IF(H89="ETAPA",0,IF(H89="SUBETAPA",OFFSET(D89,-1,0)+1,OFFSET(D89,-1,0))) -> 2 | E89: =IF(H89="Subetapa",0,IF(H89="serviço",OFFSET(E89,-1,0)+1,OFFSET(E89,-1,0))) -> 1
... A708: =IF($H708="UNIDADE CONSTRUTIVA",OFFSET(A708,-1,0)+1,LARGE(A$3:A707,1)) -> 0 | B708: =IF(H708="UNIDADE CONSTRUTIVA",0,IF(H708="CÉLULA CONSTRUTIVA",OFFSET(B708,-1,0)+1,OFFSET(B708,-1,0))) -> 4 | C708: =IF(H708="CÉLULA CONSTRUTIVA",0,IF(H708="ETAPA",OFFSET(C708,-1,0)+1,OFFSET(C708,-1,0))) -> 1 | D708: =IF(H708="ETAPA",0,IF(H708="SUBETAPA",OFFSET(D708,-1,0)+1,OFFSET(D708,-1,0))) -> 2 | E708: =IF(H708="Subetapa",0,IF(H708="serviço",OFFSET(E708,-1,0)+1,OFFSET(E708,-1,0))) -> 1

Sheet Ger_Executivo
G4: PROJETO: | I4: ='Ger_Tec e Adm'!I4 -> Mowe | O4: REVISÃO: | P4: DATA
G5: EMPRESA: | I5: ='Ger_Tec e Adm'!I5 -> MARTINS|FRANCEZ ENGENHARIA | O5: R00
A6: Unidade Construtiva | B6: Célula Construtiva | C6: Etapa | D6: Subetapa | E6: Serviço | G6: GERENCIAMENTO EXECUTIVO
A7: 0 | B7: 0 | C7: 0 | D7: 0 | E7: 0 | G7: Atalho | H7: NIVEL | I7: Item | J7: Descrição | K7: Unidade | L7: Quant. | M7: Preço un | N7: Total | O7: Considerações | P7: Situação
A8: =IF($H8="UNIDADE CONSTRUTIVA",OFFSET(A8,-1,0)+1,LARGE(A$3:A7,1)) -> 0 | B8: =IF(H8="UNIDADE CONSTRUTIVA",0,IF(H8="CÉLULA CONSTRUTIVA",OFFSET(B8,-1,0)+1,OFFSET(B8,-1,0))) -> 1 | C8: =IF(H8="CÉLULA CONSTRUTIVA",0,IF(H8="ETAPA",OFFSET(C8,-1,0)+1,OFFSET(C8,-1,0))) -> 0 | D8: =IF(H8="ETAPA",0,IF(H8="SUBETAPA",OFFSET(D8,-1,0)+1,OFFSET(D8,-1,0))) -> 0 | E8: =IF(H8="Subetapa",0,IF(H8="serviço",OFFSET(E8,-1,0)+1,OFFSET(E8,-1,0))) -> 0 | H8: CÉLULA CONSTRUTIVA | I8: =IF(H8="Unidade Construtiva",TEXT(A8,"00"),IF(H8="Célula Construtiva",TEXT(B8,"00"),IF(H8="Etapa",CONCATENATE(TEXT(B8,"00"),".",TEXT(C8,"000")),IF(H8="Subetapa",CONCATENATE(TEXT(B8,"00"),".",TEXT(C8,"000"),".",TEXT(D8,"000")),IF(H8="Serviço",CONCATENATE(TEXT(B8,"00"),".",TEXT(C8,"000"),".",TEXT(D8,"000"),".",TEXT(E8,"000")),""))))) -> 01 | J8: INFRAESTRUTURA | N8: =IF(H8="Serviço",M8*L8,IF(H8="CÉLULA CONSTRUTIVA",SUMIFS($N$8:$N$258,$B$8:$B$258,B8,$H$8:$H$258,"Serviço"),IF(H8="ETAPA",SUMIFS($N$8:$N$258,$B$8:$B$258,B8,$C$8:$C$258,C8,$H$8:$H$258,"Serviço"),IF(H8="SUBETAPA",SUMIFS($N$8:$N$258,$B$8:$B$258,B8,$C$8:$C$258,C8,$D$8:$D$258,D8,$H$8:$H$258,"Serviço"),0)))) -> 113009.8 | O8: =N8/'Obra '!E$9 -> 342.90075
A9: =IF($H9="UNIDADE CONSTRUTIVA",OFFSET(A9,-1,0)+1,LARGE(A$3:A8,1)) -> 0 | B9: =IF(H9="UNIDADE CONSTRUTIVA",0,IF(H9="CÉLULA CONSTRUTIVA",OFFSET(B9,-1,0)+1,OFFSET(B9,-1,0))) -> 1 | C9: =IF(H9="CÉLULA CONSTRUTIVA",0,IF(H9="ETAPA",OFFSET(C9,-1,0)+1,OFFSET(C9,-1,0))) -> 1 | D9: =IF(H9="ETAPA",0,IF(H9="SUBETAPA",OFFSET(D9,-1,0)+1,OFFSET(D9,-1,0))) -> 0 | E9: =IF(H9="Subetapa",0,IF(H9="serviço",OFFSET(E9,-1,0)+1,OFFSET(E9,-1,0))) -> 0 | H9: ETAPA | I9: =IF(H9="Unidade Construtiva",TEXT(A9,"00"),IF(H9="Célula Construtiva",TEXT(B9,"00"),IF(H9="Etapa",CONCATENATE(TEXT(B9,"00"),".",TEXT(C9,"000")),IF(H9="Subetapa",CONCATENATE(TEXT(B9,"00"),".",TEXT(C9,"000"),".",TEXT(D9,"000")),IF(H9="Serviço",CONCATENATE(TEXT(B9,"00"),".",TEXT(C9,"000"),".",TEXT(D9,"000"),".",TEXT(E9,"000")),""))))) -> 01.001 | J9: LIMPEZA E MOVIMENTAÇÃO DE TERRA | N9: =IF(H9="Serviço",M9*L9,IF(H9="CÉLULA CONSTRUTIVA",SUMIFS($N$8:$N$258,$B$8:$B$258,B9,$H$8:$H$258,"Serviço"),IF(H9="ETAPA",SUMIFS($N$8:$N$258,$B$8:$B$258,B9,$C$8:$C$258,C9,$H$8:$H$258,"Serviço"),IF(H9="SUBETAPA",SUMIFS($N$8:$N$258,$B$8:$B$258,B9,$C$8:$C$258,C9,$D$8:$D$258,D9,$H$8:$H$258,"Serviço"),0)))) -> 10084.168 | O9: =N9/'Obra '!E$9 -> 30.597954
A10: =IF($H10="UNIDADE CONSTRUTIVA",OFFSET(A10,-1,0)+1,LARGE(A$3:A7,1)) -> 0 | B10: =IF(H10="UNIDADE CONSTRUTIVA",0,IF(H10="CÉLULA CONSTRUTIVA",OFFSET(B10,-1,0)+1,OFFSET(B10,-1,0))) -> 1 | C10: =IF(H10="CÉLULA CONSTRUTIVA",0,IF(H10="ETAPA",OFFSET(C10,-1,0)+1,OFFSET(C10,-1,0))) -> 1 | D10: =IF(H10="ETAPA",0,IF(H10="SUBETAPA",OFFSET(D10,-1,0)+1,OFFSET(D10,-1,0))) -> 1 | E10: =IF(H10="Subetapa",0,IF(H10="serviço",OFFSET(E10,-1,0)+1,OFFSET(E10,-1,0))) -> 0 | H10: SUBETAPA | I10: =IF(H10="Unidade Construtiva",TEXT(A10,"00"),IF(H10="Célula Construtiva",TEXT(B10,"00"),IF(H10="Etapa",CONCATENATE(TEXT(B10,"00"),".",TEXT(C10,"000")),IF(H10="Subetapa",CONCATENATE(TEXT(B10,"00"),".",TEXT(C10,"000"),".",TEXT(D10,"000")),IF(H10="Serviço",CONCATENATE(TEXT(B10,"00"),".",TEXT(C10,"000"),".",TEXT(D10,"000"),".",TEXT(E10,"000")),""))))) -> 01.001.001 | J10: Limpeza e Preparação do Terreno | N10: =IF(H10="Serviço",M10*L10,IF(H10="CÉLULA CONSTRUTIVA",SUMIFS($N$8:$N$258,$B$8:$B$258,B10,$H$8:$H$258,"Serviço"),IF(H10="ETAPA",SUMIFS($N$8:$N$258,$B$8:$B$258,B10,$C$8:$C$258,C10,$H$8:$H$258,"Serviço"),IF(H10="SUBETAPA",SUMIFS($N$8:$N$258,$B$8:$B$258,B10,$C$8:$C$258,C10,$D$8:$D$258,D10,$H$8:$H$258,"Serviço"),0)))) -> 2389.035
A11: =IF($H11="UNIDADE CONSTRUTIVA",OFFSET(A11,-1,0)+1,LARGE(A$3:A10,1)) -> 0 | B11: =IF(H11="UNIDADE CONSTRUTIVA",0,IF(H11="CÉLULA CONSTRUTIVA",OFFSET(B11,-1,0)+1,OFFSET(B11,-1,0))) -> 1 | C11: =IF(H11="CÉLULA CONSTRUTIVA",0,IF(H11="ETAPA",OFFSET(C11,-1,0)+1,OFFSET(C11,-1,0))) -> 1 | D11: =IF(H11="ETAPA",0,IF(H11="SUBETAPA",OFFSET(D11,-1,0)+1,OFFSET(D11,-1,0))) -> 1 | E11: =IF(H11="Subetapa",0,IF(H11="serviço",OFFSET(E11,-1,0)+1,OFFSET(E11,-1,0))) -> 1 | H11: SERVIÇO | I11: =IF(H11="Unidade Construtiva",TEXT(A11,"00"),IF(H11="Célula Construtiva",TEXT(B11,"00"),IF(H11="Etapa",CONCATENATE(TEXT(B11,"00"),".",TEXT(C11,"000")),IF(H11="Subetapa",CONCATENATE(TEXT(B11,"00"),".",TEXT(C11,"000"),".",TEXT(D11,"000")),IF(H11="Serviço",CONCATENATE(TEXT(B11,"00"),".",TEXT(C11,"000"),".",TEXT(D11,"000"),".",TEXT(E11,"000")),""))))) -> 01.001.001.001 | J11: Limpeza da camada vegetal | K11: m2 | L11: ='Obra '!E8 -> 434.37 | M11: 5.5 | N11: =IF(H11="Serviço",M11*L11,IF(H11="CÉLULA CONSTRUTIVA",SUMIFS($N$8:$N$258,$B$8:$B$258,B11,$H$8:$H$258,"Serviço"),IF(H11="ETAPA",SUMIFS($N$8:$N$258,$B$8:$B$258,B11,$C$8:$C$258,C11,$H$8:$H$258,"Serviço"),IF(H11="SUBETAPA",SUMIFS($N$8:$N$258,$B$8:$B$258,B11,$C$8:$C$258,C11,$D$8:$D$258,D11,$H$8:$H$258,"Serviço"),0)))) -> 2389.035 | P11: Finalizado
A12: =IF($H12="UNIDADE CONSTRUTIVA",OFFSET(A12,-1,0)+1,LARGE(A$3:A9,1)) -> 0 | B12: =IF(H12="UNIDADE CONSTRUTIVA",0,IF(H12="CÉLULA CONSTRUTIVA",OFFSET(B12,-1,0)+1,OFFSET(B12,-1,0))) -> 1 | C12: =IF(H12="CÉLULA CONSTRUTIVA",0,IF(H12="ETAPA",OFFSET(C12,-1,0)+1,OFFSET(C12,-1,0))) -> 1 | D12: =IF(H12="ETAPA",0,IF(H12="SUBETAPA",OFFSET(D12,-1,0)+1,OFFSET(D12,-1,0))) -> 2 | E12: =IF(H12="Subetapa",0,IF(H12="serviço",OFFSET(E12,-1,0)+1,OFFSET(E12,-1,0))) -> 0 | H12: SUBETAPA | I12: =IF(H12="Unidade Construtiva",TEXT(A12,"00"),IF(H12="Célula Construtiva",TEXT(B12,"00"),IF(H12="Etapa",CONCATENATE(TEXT(B12,"00"),".",TEXT(C12,"000")),IF(H12="Subetapa",CONCATENATE(TEXT(B12,"00"),".",TEXT(C12,"000"),".",TEXT(D12,"000")),IF(H12="Serviço",CONCATENATE(TEXT(B12,"00"),".",TEXT(C12,"000"),".",TEXT(D12,"000"),".",TEXT(E12,"000")),""))))) -> 01.001.002 | J12: Escavação e Reaterro de Valas | N12: =IF(H12="Serviço",M12*L12,IF(H12="CÉLULA CONSTRUTIVA",SUMIFS($N$8:$N$258,$B$8:$B$258,B12,$H$8:$H$258,"Serviço"),IF(H12="ETAPA",SUMIFS($N$8:$N$258,$B$8:$B$258,B12,$C$8:$C$258,C12,$H$8:$H$258,"Serviço"),IF(H12="SUBETAPA",SUMIFS($N$8:$N$258,$B$8:$B$258,B12,$C$8:$C$258,C12,$D$8:$D$258,D12,$H$8:$H$258,"Serviço"),0)))) -> 5955.0562
A13: =IF($H13="UNIDADE CONSTRUTIVA",OFFSET(A13,-1,0)+1,LARGE(A$3:A12,1)) -> 0 | B13: =IF(H13="UNIDADE CONSTRUTIVA",0,IF(H13="CÉLULA CONSTRUTIVA",OFFSET(B13,-1,0)+1,OFFSET(B13,-1,0))) -> 1 | C13: =IF(H13="CÉLULA CONSTRUTIVA",0,IF(H13="ETAPA",OFFSET(C13,-1,0)+1,OFFSET(C13,-1,0))) -> 1 | D13: =IF(H13="ETAPA",0,IF(H13="SUBETAPA",OFFSET(D13,-1,0)+1,OFFSET(D13,-1,0))) -> 2 | E13: =IF(H13="Subetapa",0,IF(H13="serviço",OFFSET(E13,-1,0)+1,OFFSET(E13,-1,0))) -> 1 | H13: SERVIÇO | I13: =IF(H13="Unidade Construtiva",TEXT(A13,"00"),IF(H13="Célula Construtiva",TEXT(B13,"00"),IF(H13="Etapa",CONCATENATE(TEXT(B13,"00"),".",TEXT(C13,"000")),IF(H13="Subetapa",CONCATENATE(TEXT(B13,"00"),".",TEXT(C13,"000"),".",TEXT(D13,"000")),IF(H13="Serviço",CONCATENATE(TEXT(B13,"00"),".",TEXT(C13,"000"),".",TEXT(D13,"000"),".",TEXT(E13,"000")),""))))) -> 01.001.002.001 | J13: Escavação mecanizada para blocos de fundação, vigas de fundação e poço de elevador, com retroescavadeira | K13: m3 | L13: ='Fundação Rasa'!G7 -> 124.13619 | M13: =_xlfn.XLOOKUP($J13,CPU!$D$1:$D$2521,CPU!$H$1:$H$2521) -> 36.36 | N13: =IF(H13="Serviço",M13*L13,IF(H13="CÉLULA CONSTRUTIVA",SUMIFS($N$8:$N$258,$B$8:$B$258,B13,$H$8:$H$258,"Serviço"),IF(H13="ETAPA",SUMIFS($N$8:$N$258,$B$8:$B$258,B13,$C$8:$C$258,C13,$H$8:$H$258,"Serviço"),IF(H13="SUBETAPA",SUMIFS($N$8:$N$258,$B$8:$B$258,B13,$C$8:$C$258,C13,$D$8:$D$258,D13,$H$8:$H$258,"Serviço"),0)))) -> 4513.5919 | P13: Finalizado
A14: =IF($H14="UNIDADE CONSTRUTIVA",OFFSET(A14,-1,0)+1,LARGE(A$3:A13,1)) -> 0 | B14: =IF(H14="UNIDADE CONSTRUTIVA",0,IF(H14="CÉLULA CONSTRUTIVA",OFFSET(B14,-1,0)+1,OFFSET(B14,-1,0))) -> 1 | C14: =IF(H14="CÉLULA CONSTRUTIVA",0,IF(H14="ETAPA",OFFSET(C14,-1,0)+1,OFFSET(C14,-1,0))) -> 1 | D14: =IF(H14="ETAPA",0,IF(H14="SUBETAPA",OFFSET(D14,-1,0)+1,OFFSET(D14,-1,0))) -> 2 | E14: =IF(H14="Subetapa",0,IF(H14="serviço",OFFSET(E14,-1,0)+1,OFFSET(E14,-1,0))) -> 2 | H14: SERVIÇO | I14: =IF(H14="Unidade Construtiva",TEXT(A14,"00"),IF(H14="Célula Construtiva",TEXT(B14,"00"),IF(H14="Etapa",CONCATENATE(TEXT(B14,"00"),".",TEXT(C14,"000")),IF(H14="Subetapa",CONCATENATE(TEXT(B14,"00"),".",TEXT(C14,"000"),".",TEXT(D14,"000")),IF(H14="Serviço",CONCATENATE(TEXT(B14,"00"),".",TEXT(C14,"000"),".",TEXT(D14,"000"),".",TEXT(E14,"000")),""))))) -> 01.001.002.002 | J14: Reaterro mecanizado de valas para blocos e vigas de fundação, com retroescavadeira | K14: m3 | L14: ='Fundação Rasa'!I7 -> 99.069709 | M14: =_xlfn.XLOOKUP($J14,CPU!$D$1:$D$2521,CPU!$H$1:$H$2521) -> 14.55 | N14: =IF(H14="Serviço",M14*L14,IF(H14="CÉLULA CONSTRUTIVA",SUMIFS($N$8:$N$258,$B$8:$B$258,B14,$H$8:$H$258,"Serviço"),IF(H14="ETAPA",SUMIFS($N$8:$N$258,$B$8:$B$258,B14,$C$8:$C$258,C14,$H$8:$H$258,"Serviço"),IF(H14="SUBETAPA",SUMIFS($N$8:$N$258,$B$8:$B$258,B14,$C$8:$C$258,C14,$D$8:$D$258,D14,$H$8:$H$258,"Serviço"),0)))) -> 1441.4643 | P14: Finalizado
A15: =IF($H15="UNIDADE CONSTRUTIVA",OFFSET(A15,-1,0)+1,LARGE(A$3:A14,1)) -> 0 | B15: =IF(H15="UNIDADE CONSTRUTIVA",0,IF(H15="CÉLULA CONSTRUTIVA",OFFSET(B15,-1,0)+1,OFFSET(B15,-1,0))) -> 1 | C15: =IF(H15="CÉLULA CONSTRUTIVA",0,IF(H15="ETAPA",OFFSET(C15,-1,0)+1,OFFSET(C15,-1,0))) -> 1 | D15: =IF(H15="ETAPA",0,IF(H15="SUBETAPA",OFFSET(D15,-1,0)+1,OFFSET(D15,-1,0))) -> 3 | E15: =IF(H15="Subetapa",0,IF(H15="serviço",OFFSET(E15,-1,0)+1,OFFSET(E15,-1,0))) -> 0 | H15: SUBETAPA | I15: =IF(H15="Unidade Construtiva",TEXT(A15,"00"),IF(H15="Célula Construtiva",TEXT(B15,"00"),IF(H15="Etapa",CONCATENATE(TEXT(B15,"00"),".",TEXT(C15,"000")),IF(H15="Subetapa",CONCATENATE(TEXT(B15,"00"),".",TEXT(C15,"000"),".",TEXT(D15,"000")),IF(H15="Serviço",CONCATENATE(TEXT(B15,"00"),".",TEXT(C15,"000"),".",TEXT(D15,"000"),".",TEXT(E15,"000")),""))))) -> 01.001.003 | J15: Lastro de estrutura de concreto | N15: =IF(H15="Serviço",M15*L15,IF(H15="CÉLULA CONSTRUTIVA",SUMIFS($N$8:$N$258,$B$8:$B$258,B15,$H$8:$H$258,"Serviço"),IF(H15="ETAPA",SUMIFS($N$8:$N$258,$B$8:$B$258,B15,$C$8:$C$258,C15,$H$8:$H$258,"Serviço"),IF(H15="SUBETAPA",SUMIFS($N$8:$N$258,$B$8:$B$258,B15,$C$8:$C$258,C15,$D$8:$D$258,D15,$H$8:$H$258,"Serviço"),0)))) -> 259.02347
A16: =IF($H16="UNIDADE CONSTRUTIVA",OFFSET(A16,-1,0)+1,LARGE(A$3:A15,1)) -> 0 | B16: =IF(H16="UNIDADE CONSTRUTIVA",0,IF(H16="CÉLULA CONSTRUTIVA",OFFSET(B16,-1,0)+1,OFFSET(B16,-1,0))) -> 1 | C16: =IF(H16="CÉLULA CONSTRUTIVA",0,IF(H16="ETAPA",OFFSET(C16,-1,0)+1,OFFSET(C16,-1,0))) -> 1 | D16: =IF(H16="ETAPA",0,IF(H16="SUBETAPA",OFFSET(D16,-1,0)+1,OFFSET(D16,-1,0))) -> 3 | E16: =IF(H16="Subetapa",0,IF(H16="serviço",OFFSET(E16,-1,0)+1,OFFSET(E16,-1,0))) -> 1 | H16: SERVIÇO | I16: =IF(H16="Unidade Construtiva",TEXT(A16,"00"),IF(H16="Célula Construtiva",TEXT(B16,"00"),IF(H16="Etapa",CONCATENATE(TEXT(B16,"00"),".",TEXT(C16,"000")),IF(H16="Subetapa",CONCATENATE(TEXT(B16,"00"),".",TEXT(C16,"000"),".",TEXT(D16,"000")),IF(H16="Serviço",CONCATENATE(TEXT(B16,"00"),".",TEXT(C16,"000"),".",TEXT(D16,"000"),".",TEXT(E16,"000")),""))))) -> 01.001.003.001 | J16: Lastro de Concreto Magro, Aplicado em Blocos de Fundação, e=4cm | K16: m3 | L16: =SUM('Fundação Rasa'!L7:L7) -> 1.2482 | M16: =_xlfn.XLOOKUP($J16,CPU!$D$1:$D$2521,CPU!$H$1:$H$2521) -> 207.5176 | N16: =IF(H16="Serviço",M16*L16,IF(H16="CÉLULA CONSTRUTIVA",SUMIFS($N$8:$N$258,$B$8:$B$258,B16,$H$8:$H$258,"Serviço"),IF(H16="ETAPA",SUMIFS($N$8:$N$258,$B$8:$B$258,B16,$C$8:$C$258,C16,$H$8:$H$258,"Serviço"),IF(H16="SUBETAPA",SUMIFS($N$8:$N$258,$B$8:$B$258,B16,$C$8:$C$258,C16,$D$8:$D$258,D16,$H$8:$H$258,"Serviço"),0)))) -> 259.02347 | P16: Finalizado
A17: =IF($H17="UNIDADE CONSTRUTIVA",OFFSET(A17,-1,0)+1,LARGE(A$3:A16,1)) -> 0 | B17: =IF(H17="UNIDADE CONSTRUTIVA",0,IF(H17="CÉLULA CONSTRUTIVA",OFFSET(B17,-1,0)+1,OFFSET(B17,-1,0))) -> 1 | C17: =IF(H17="CÉLULA CONSTRUTIVA",0,IF(H17="ETAPA",OFFSET(C17,-1,0)+1,OFFSET(C17,-1,0))) -> 1 | D17: =IF(H17="ETAPA",0,IF(H17="SUBETAPA",OFFSET(D17,-1,0)+1,OFFSET(D17,-1,0))) -> 4 | E17: =IF(H17="Subetapa",0,IF(H17="serviço",OFFSET(E17,-1,0)+1,OFFSET(E17,-1,0))) -> 0 | H17: SUBETAPA | I17: =IF(H17="Unidade Construtiva",TEXT(A17,"00"),IF(H17="Célula Construtiva",TEXT(B17,"00"),IF(H17="Etapa",CONCATENATE(TEXT(B17,"00"),".",TEXT(C17,"000")),IF(H17="Subetapa",CONCATENATE(TEXT(B17,"00"),".",TEXT(C17,"000"),".",TEXT(D17,"000")),IF(H17="Serviço",CONCATENATE(TEXT(B17,"00"),".",TEXT(C17,"000"),".",TEXT(D17,"000"),".",TEXT(E17,"000")),""))))) -> 01.001.004 | J17: Movimentação de bota - fora | N17: =IF(H17="Serviço",M17*L17,IF(H17="CÉLULA CONSTRUTIVA",SUMIFS($N$8:$N$258,$B$8:$B$258,B17,$H$8:$H$258,"Serviço"),IF(H17="ETAPA",SUMIFS($N$8:$N$258,$B$8:$B$258,B17,$C$8:$C$258,C17,$H$8:$H$258,"Serviço"),IF(H17="SUBETAPA",SUMIFS($N$8:$N$258,$B$8:$B$258,B17,$C$8:$C$258,C17,$D$8:$D$258,D17,$H$8:$H$258,"Serviço"),0)))) -> 1481.0532
A18: =IF($H18="UNIDADE CONSTRUTIVA",OFFSET(A18,-1,0)+1,LARGE(A$3:A17,1)) -> 0 | B18: =IF(H18="UNIDADE CONSTRUTIVA",0,IF(H18="CÉLULA CONSTRUTIVA",OFFSET(B18,-1,0)+1,OFFSET(B18,-1,0))) -> 1 | C18: =IF(H18="CÉLULA CONSTRUTIVA",0,IF(H18="ETAPA",OFFSET(C18,-1,0)+1,OFFSET(C18,-1,0))) -> 1 | D18: =IF(H18="ETAPA",0,IF(H18="SUBETAPA",OFFSET(D18,-1,0)+1,OFFSET(D18,-1,0))) -> 4 | E18: =IF(H18="Subetapa",0,IF(H18="serviço",OFFSET(E18,-1,0)+1,OFFSET(E18,-1,0))) -> 1 | H18: SERVIÇO | I18: =IF(H18="Unidade Construtiva",TEXT(A18,"00"),IF(H18="Célula Construtiva",TEXT(B18,"00"),IF(H18="Etapa",CONCATENATE(TEXT(B18,"00"),".",TEXT(C18,"000")),IF(H18="Subetapa",CONCATENATE(TEXT(B18,"00"),".",TEXT(C18,"000"),".",TEXT(D18,"000")),IF(H18="Serviço",CONCATENATE(TEXT(B18,"00"),".",TEXT(C18,"000"),".",TEXT(D18,"000"),".",TEXT(E18,"000")),""))))) -> 01.001.004.001 | J18: Movimentação de terra para bota-fora - Escavação de Valas | K18: m3 | L18: ='Fundação Rasa'!J7 -> 32.586428 | M18: =_xlfn.XLOOKUP($J18,CPU!$D$1:$D$2521,CPU!$H$1:$H$2521) -> 45.45 | N18: =IF(H18="Serviço",M18*L18,IF(H18="CÉLULA CONSTRUTIVA",SUMIFS($N$8:$N$258,$B$8:$B$258,B18,$H$8:$H$258,"Serviço"),IF(H18="ETAPA",SUMIFS($N$8:$N$258,$B$8:$B$258,B18,$C$8:$C$258,C18,$H$8:$H$258,"Serviço"),IF(H18="SUBETAPA",SUMIFS($N$8:$N$258,$B$8:$B$258,B18,$C$8:$C$258,C18,$D$8:$D$258,D18,$H$8:$H$258,"Serviço"),0)))) -> 1481.0532 | P18: Finalizado
A19: =IF($H19="UNIDADE CONSTRUTIVA",OFFSET(A19,-1,0)+1,LARGE(A$3:A18,1)) -> 0 | B19: =IF(H19="UNIDADE CONSTRUTIVA",0,IF(H19="CÉLULA CONSTRUTIVA",OFFSET(B19,-1,0)+1,OFFSET(B19,-1,0))) -> 1 | C19: =IF(H19="CÉLULA CONSTRUTIVA",0,IF(H19="ETAPA",OFFSET(C19,-1,0)+1,OFFSET(C19,-1,0))) -> 2 | D19: =IF(H19="ETAPA",0,IF(H19="SUBETAPA",OFFSET(D19,-1,0)+1,OFFSET(D19,-1,0))) -> 0 | E19: =IF(H19="Subetapa",0,IF(H19="serviço",OFFSET(E19,-1,0)+1,OFFSET(E19,-1,0))) -> 1 | H19: ETAPA | I19: =IF(H19="Unidade Construtiva",TEXT(A19,"00"),IF(H19="Célula Construtiva",TEXT(B19,"00"),IF(H19="Etapa",CONCATENATE(TEXT(B19,"00"),".",TEXT(C19,"000")),IF(H19="Subetapa",CONCATENATE(TEXT(B19,"00"),".",TEXT(C19,"000"),".",TEXT(D19,"000")),IF(H19="Serviço",CONCATENATE(TEXT(B19,"00"),".",TEXT(C19,"000"),".",TEXT(D19,"000"),".",TEXT(E19,"000")),""))))) -> 01.002 | J19: FUNDAÇÃO RASA (SAPATAS E BALDRAMES) | N19: =IF(H19="Serviço",M19*L19,IF(H19="CÉLULA CONSTRUTIVA",SUMIFS($N$8:$N$258,$B$8:$B$258,B19,$H$8:$H$258,"Serviço"),IF(H19="ETAPA",SUMIFS($N$8:$N$258,$B$8:$B$258,B19,$C$8:$C$258,C19,$H$8:$H$258,"Serviço"),IF(H19="SUBETAPA",SUMIFS($N$8:$N$258,$B$8:$B$258,B19,$C$8:$C$258,C19,$D$8:$D$258,D19,$H$8:$H$258,"Serviço"),0)))) -> 102925.63 | O19: =N19/'Obra '!E$9 -> 312.30279
A20: =IF($H20="UNIDADE CONSTRUTIVA",OFFSET(A20,-1,0)+1,LARGE(A$3:A19,1)) -> 0 | B20: =IF(H20="UNIDADE CONSTRUTIVA",0,IF(H20="CÉLULA CONSTRUTIVA",OFFSET(B20,-1,0)+1,OFFSET(B20,-1,0))) -> 1 | C20: =IF(H20="CÉLULA CONSTRUTIVA",0,IF(H20="ETAPA",OFFSET(C20,-1,0)+1,OFFSET(C20,-1,0))) -> 2 | D20: =IF(H20="ETAPA",0,IF(H20="SUBETAPA",OFFSET(D20,-1,0)+1,OFFSET(D20,-1,0))) -> 1 | E20: =IF(H20="Subetapa",0,IF(H20="serviço",OFFSET(E20,-1,0)+1,OFFSET(E20,-1,0))) -> 0 | H20: SUBETAPA | I20: =IF(H20="Unidade Construtiva",TEXT(A20,"00"),IF(H20="Célula Construtiva",TEXT(B20,"00"),IF(H20="Etapa",CONCATENATE(TEXT(B20,"00"),".",TEXT(C20,"000")),IF(H20="Subetapa",CONCATENATE(TEXT(B20,"00"),".",TEXT(C20,"000"),".",TEXT(D20,"000")),IF(H20="Serviço",CONCATENATE(TEXT(B20,"00"),".",TEXT(C20,"000"),".",TEXT(D20,"000"),".",TEXT(E20,"000")),""))))) -> 01.002.001 | J20: Forma | N20: =IF(H20="Serviço",M20*L20,IF(H20="CÉLULA CONSTRUTIVA",SUMIFS($N$8:$N$258,$B$8:$B$258,B20,$H$8:$H$258,"Serviço"),IF(H20="ETAPA",SUMIFS($N$8:$N$258,$B$8:$B$258,B20,$C$8:$C$258,C20,$H$8:$H$258,"Serviço"),IF(H20="SUBETAPA",SUMIFS($N$8:$N$258,$B$8:$B$258,B20,$C$8:$C$258,C20,$D$8:$D$258,D20,$H$8:$H$258,"Serviço"),0)))) -> 21358.77 | O20: =N20/'Obra '!E$9 -> 64.807993
A21: =IF($H21="UNIDADE CONSTRUTIVA",OFFSET(A21,-1,0)+1,LARGE(A$3:A20,1)) -> 0 | B21: =IF(H21="UNIDADE CONSTRUTIVA",0,IF(H21="CÉLULA CONSTRUTIVA",OFFSET(B21,-1,0)+1,OFFSET(B21,-1,0))) -> 1 | C21: =IF(H21="CÉLULA CONSTRUTIVA",0,IF(H21="ETAPA",OFFSET(C21,-1,0)+1,OFFSET(C21,-1,0))) -> 2 | D21: =IF(H21="ETAPA",0,IF(H21="SUBETAPA",OFFSET(D21,-1,0)+1,OFFSET(D21,-1,0))) -> 1 | E21: =IF(H21="Subetapa",0,IF(H21="serviço",OFFSET(E21,-1,0)+1,OFFSET(E21,-1,0))) -> 1 | H21: SERVIÇO | I21: =IF(H21="Unidade Construtiva",TEXT(A21,"00"),IF(H21="Célula Construtiva",TEXT(B21,"00"),IF(H21="Etapa",CONCATENATE(TEXT(B21,"00"),".",TEXT(C21,"000")),IF(H21="Subetapa",CONCATENATE(TEXT(B21,"00"),".",TEXT(C21,"000"),".",TEXT(D21,"000")),IF(H21="Serviço",CONCATENATE(TEXT(B21,"00"),".",TEXT(C21,"000"),".",TEXT(D21,"000"),".",TEXT(E21,"000")),""))))) -> 01.002.001.001 | J21: Forma para infraestrutura em Tábuas de Madeira Serrada 4x reaproveitamento | K21: m2 | L21: =Aço_Infraestrutura!N7+Aço_Infraestrutura!N13+Aço_Infraestrutura!N9 -> 162.44 | M21: =_xlfn.XLOOKUP($J21,CPU!$D$1:$D$2521,CPU!$H$1:$H$2521) -> 59.956229 | N21: =IF(H21="Serviço",M21*L21,IF(H21="CÉLULA CONSTRUTIVA",SUMIFS($N$8:$N$258,$B$8:$B$258,B21,$H$8:$H$258,"Serviço"),IF(H21="ETAPA",SUMIFS($N$8:$N$258,$B$8:$B$258,B21,$C$8:$C$258,C21,$H$8:$H$258,"Serviço"),IF(H21="SUBETAPA",SUMIFS($N$8:$N$258,$B$8:$B$258,B21,$C$8:$C$258,C21,$D$8:$D$258,D21,$H$8:$H$258,"Serviço"),0)))) -> 9739.2898 | O21: Quantidade disponibilizada pelo projetista de sapatas e levantameto da Cartesian de vigas e pilares | P21: Finalizado
A22: =IF($H22="UNIDADE CONSTRUTIVA",OFFSET(A22,-1,0)+1,LARGE(A$3:A21,1)) -> 0 | B22: =IF(H22="UNIDADE CONSTRUTIVA",0,IF(H22="CÉLULA CONSTRUTIVA",OFFSET(B22,-1,0)+1,OFFSET(B22,-1,0))) -> 1 | C22: =IF(H22="CÉLULA CONSTRUTIVA",0,IF(H22="ETAPA",OFFSET(C22,-1,0)+1,OFFSET(C22,-1,0))) -> 2 | D22: =IF(H22="ETAPA",0,IF(H22="SUBETAPA",OFFSET(D22,-1,0)+1,OFFSET(D22,-1,0))) -> 1 | E22: =IF(H22="Subetapa",0,IF(H22="serviço",OFFSET(E22,-1,0)+1,OFFSET(E22,-1,0))) -> 2 | H22: SERVIÇO | I22: =IF(H22="Unidade Construtiva",TEXT(A22,"00"),IF(H22="Célula Construtiva",TEXT(B22,"00"),IF(H22="Etapa",CONCATENATE(TEXT(B22,"00"),".",TEXT(C22,"000")),IF(H22="Subetapa",CONCATENATE(TEXT(B22,"00"),".",TEXT(C22,"000"),".",TEXT(D22,"000")),IF(H22="Serviço",CONCATENATE(TEXT(B22,"00"),".",TEXT(C22,"000"),".",TEXT(D22,"000"),".",TEXT(E22,"000")),""))))) -> 01.002.001.002 | J22: Fornecimento de Lajes Treliçadas TR8 com cerâmica H8 | K22: m2 | L22: =LAJE_TRELIÇADA!G7 -> 162.78 | M22: 71.3815 | N22: =IF(H22="Serviço",M22*L22,IF(H22="CÉLULA CONSTRUTIVA",SUMIFS($N$8:$N$258,$B$8:$B$258,B22,$H$8:$H$258,"Serviço"),IF(H22="ETAPA",SUMIFS($N$8:$N$258,$B$8:$B$258,B22,$C$8:$C$258,C22,$H$8:$H$258,"Serviço"),IF(H22="SUBETAPA",SUMIFS($N$8:$N$258,$B$8:$B$258,B22,$C$8:$C$258,C22,$D$8:$D$258,D22,$H$8:$H$258,"Serviço"),0)))) -> 11619.481 | O22: Quantidade de levantameto da Cartesian | P22: Finalizado
A23: =IF($H23="UNIDADE CONSTRUTIVA",OFFSET(A23,-1,0)+1,LARGE(A$3:A22,1)) -> 0 | B23: =IF(H23="UNIDADE CONSTRUTIVA",0,IF(H23="CÉLULA CONSTRUTIVA",OFFSET(B23,-1,0)+1,OFFSET(B23,-1,0))) -> 1 | C23: =IF(H23="CÉLULA CONSTRUTIVA",0,IF(H23="ETAPA",OFFSET(C23,-1,0)+1,OFFSET(C23,-1,0))) -> 2 | D23: =IF(H23="ETAPA",0,IF(H23="SUBETAPA",OFFSET(D23,-1,0)+1,OFFSET(D23,-1,0))) -> 2 | E23: =IF(H23="Subetapa",0,IF(H23="serviço",OFFSET(E23,-1,0)+1,OFFSET(E23,-1,0))) -> 0 | H23: SUBETAPA | I23: =IF(H23="Unidade Construtiva",TEXT(A23,"00"),IF(H23="Célula Construtiva",TEXT(B23,"00"),IF(H23="Etapa",CONCATENATE(TEXT(B23,"00"),".",TEXT(C23,"000")),IF(H23="Subetapa",CONCATENATE(TEXT(B23,"00"),".",TEXT(C23,"000"),".",TEXT(D23,"000")),IF(H23="Serviço",CONCATENATE(TEXT(B23,"00"),".",TEXT(C23,"000"),".",TEXT(D23,"000"),".",TEXT(E23,"000")),""))))) -> 01.002.002 | J23: Armadura | N23: =IF(H23="Serviço",M23*L23,IF(H23="CÉLULA CONSTRUTIVA",SUMIFS($N$8:$N$258,$B$8:$B$258,B23,$H$8:$H$258,"Serviço"),IF(H23="ETAPA",SUMIFS($N$8:$N$258,$B$8:$B$258,B23,$C$8:$C$258,C23,$H$8:$H$258,"Serviço"),IF(H23="SUBETAPA",SUMIFS($N$8:$N$258,$B$8:$B$258,B23,$C$8:$C$258,C23,$D$8:$D$258,D23,$H$8:$H$258,"Serviço"),0)))) -> 17928.352 | O23: =N23/'Obra '!E$9 -> 54.399222
A24: =IF($H24="UNIDADE CONSTRUTIVA",OFFSET(A24,-1,0)+1,LARGE(A$3:A23,1)) -> 0 | B24: =IF(H24="UNIDADE CONSTRUTIVA",0,IF(H24="CÉLULA CONSTRUTIVA",OFFSET(B24,-1,0)+1,OFFSET(B24,-1,0))) -> 1 | C24: =IF(H24="CÉLULA CONSTRUTIVA",0,IF(H24="ETAPA",OFFSET(C24,-1,0)+1,OFFSET(C24,-1,0))) -> 2 | D24: =IF(H24="ETAPA",0,IF(H24="SUBETAPA",OFFSET(D24,-1,0)+1,OFFSET(D24,-1,0))) -> 2 | E24: =IF(H24="Subetapa",0,IF(H24="serviço",OFFSET(E24,-1,0)+1,OFFSET(E24,-1,0))) -> 1 | H24: SERVIÇO | I24: =IF(H24="Unidade Construtiva",TEXT(A24,"00"),IF(H24="Célula Construtiva",TEXT(B24,"00"),IF(H24="Etapa",CONCATENATE(TEXT(B24,"00"),".",TEXT(C24,"000")),IF(H24="Subetapa",CONCATENATE(TEXT(B24,"00"),".",TEXT(C24,"000"),".",TEXT(D24,"000")),IF(H24="Serviço",CONCATENATE(TEXT(B24,"00"),".",TEXT(C24,"000"),".",TEXT(D24,"000"),".",TEXT(E24,"000")),""))))) -> 01.002.002.001 | J24: Armação aço CA-50 ø 6,3mm para infraestrutura (corte e dobra em obra) | K24: kg | L24: =Aço_Infraestrutura!D16 -> 245.8 | M24: =_xlfn.XLOOKUP($J24,CPU!$D$1:$D$2521,CPU!$H$1:$H$2521) -> 6.938145 | N24: =IF(H24="Serviço",M24*L24,IF(H24="CÉLULA CONSTRUTIVA",SUMIFS($N$8:$N$258,$B$8:$B$258,B24,$H$8:$H$258,"Serviço"),IF(H24="ETAPA",SUMIFS($N$8:$N$258,$B$8:$B$258,B24,$C$8:$C$258,C24,$H$8:$H$258,"Serviço"),IF(H24="SUBETAPA",SUMIFS($N$8:$N$258,$B$8:$B$258,B24,$C$8:$C$258,C24,$D$8:$D$258,D24,$H$8:$H$258,"Serviço"),0)))) -> 1705.396 | O24: Quantidade disponibilizada pelo projetista | P24: Finalizado
A25: =IF($H25="UNIDADE CONSTRUTIVA",OFFSET(A25,-1,0)+1,LARGE(A$3:A24,1)) -> 0 | B25: =IF(H25="UNIDADE CONSTRUTIVA",0,IF(H25="CÉLULA CONSTRUTIVA",OFFSET(B25,-1,0)+1,OFFSET(B25,-1,0))) -> 1 | C25: =IF(H25="CÉLULA CONSTRUTIVA",0,IF(H25="ETAPA",OFFSET(C25,-1,0)+1,OFFSET(C25,-1,0))) -> 2 | D25: =IF(H25="ETAPA",0,IF(H25="SUBETAPA",OFFSET(D25,-1,0)+1,OFFSET(D25,-1,0))) -> 2 | E25: =IF(H25="Subetapa",0,IF(H25="serviço",OFFSET(E25,-1,0)+1,OFFSET(E25,-1,0))) -> 2 | H25: SERVIÇO | I25: =IF(H25="Unidade Construtiva",TEXT(A25,"00"),IF(H25="Célula Construtiva",TEXT(B25,"00"),IF(H25="Etapa",CONCATENATE(TEXT(B25,"00"),".",TEXT(C25,"000")),IF(H25="Subetapa",CONCATENATE(TEXT(B25,"00"),".",TEXT(C25,"000"),".",TEXT(D25,"000")),IF(H25="Serviço",CONCATENATE(TEXT(B25,"00"),".",TEXT(C25,"000"),".",TEXT(D25,"000"),".",TEXT(E25,"000")),""))))) -> 01.002.002.002 | J25: Armação aço CA-50 ø 8,0mm para infraestrutura (corte e dobra em obra) | K25: kg | L25: =Aço_Infraestrutura!E16 -> 285.2 | M25: =_xlfn.XLOOKUP($J25,CPU!$D$1:$D$2521,CPU!$H$1:$H$2521) -> 6.938145 | N25: =IF(H25="Serviço",M25*L25,IF(H25="CÉLULA CONSTRUTIVA",SUMIFS($N$8:$N$258,$B$8:$B$258,B25,$H$8:$H$258,"Serviço"),IF(H25="ETAPA",SUMIFS($N$8:$N$258,$B$8:$B$258,B25,$C$8:$C$258,C25,$H$8:$H$258,"Serviço"),IF(H25="SUBETAPA",SUMIFS($N$8:$N$258,$B$8:$B$258,B25,$C$8:$C$258,C25,$D$8:$D$258,D25,$H$8:$H$258,"Serviço"),0)))) -> 1978.759 | O25: Quantidade disponibilizada pelo projetista | P25: Finalizado
A26: =IF($H26="UNIDADE CONSTRUTIVA",OFFSET(A26,-1,0)+1,LARGE(A$3:A25,1)) -> 0 | B26: =IF(H26="UNIDADE CONSTRUTIVA",0,IF(H26="CÉLULA CONSTRUTIVA",OFFSET(B26,-1,0)+1,OFFSET(B26,-1,0))) -> 1 | C26: =IF(H26="CÉLULA CONSTRUTIVA",0,IF(H26="ETAPA",OFFSET(C26,-1,0)+1,OFFSET(C26,-1,0))) -> 2 | D26: =IF(H26="ETAPA",0,IF(H26="SUBETAPA",OFFSET(D26,-1,0)+1,OFFSET(D26,-1,0))) -> 2 | E26: =IF(H26="Subetapa",0,IF(H26="serviço",OFFSET(E26,-1,0)+1,OFFSET(E26,-1,0))) -> 3 | H26: SERVIÇO | I26: =IF(H26="Unidade Construtiva",TEXT(A26,"00"),IF(H26="Célula Construtiva",TEXT(B26,"00"),IF(H26="Etapa",CONCATENATE(TEXT(B26,"00"),".",TEXT(C26,"000")),IF(H26="Subetapa",CONCATENATE(TEXT(B26,"00"),".",TEXT(C26,"000"),".",TEXT(D26,"000")),IF(H26="Serviço",CONCATENATE(TEXT(B26,"00"),".",TEXT(C26,"000"),".",TEXT(D26,"000"),".",TEXT(E26,"000")),""))))) -> 01.002.002.003 | J26: Armação aço CA-50 ø 10,0mm para infraestrutura (corte e dobra em obra) | K26: kg | L26: =Aço_Infraestrutura!F16 -> 303.5 | M26: =_xlfn.XLOOKUP($J26,CPU!$D$1:$D$2521,CPU!$H$1:$H$2521) -> 6.630145 | N26: =IF(H26="Serviço",M26*L26,IF(H26="CÉLULA CONSTRUTIVA",SUMIFS($N$8:$N$258,$B$8:$B$258,B26,$H$8:$H$258,"Serviço"),IF(H26="ETAPA",SUMIFS($N$8:$N$258,$B$8:$B$258,B26,$C$8:$C$258,C26,$H$8:$H$258,"Serviço"),IF(H26="SUBETAPA",SUMIFS($N$8:$N$258,$B$8:$B$258,B26,$C$8:$C$258,C26,$D$8:$D$258,D26,$H$8:$H$258,"Serviço"),0)))) -> 2012.249 | O26: Quantidade disponibilizada pelo projetista | P26: Finalizado
A27: =IF($H27="UNIDADE CONSTRUTIVA",OFFSET(A27,-1,0)+1,LARGE(A$3:A26,1)) -> 0 | B27: =IF(H27="UNIDADE CONSTRUTIVA",0,IF(H27="CÉLULA CONSTRUTIVA",OFFSET(B27,-1,0)+1,OFFSET(B27,-1,0))) -> 1 | C27: =IF(H27="CÉLULA CONSTRUTIVA",0,IF(H27="ETAPA",OFFSET(C27,-1,0)+1,OFFSET(C27,-1,0))) -> 2 | D27: =IF(H27="ETAPA",0,IF(H27="SUBETAPA",OFFSET(D27,-1,0)+1,OFFSET(D27,-1,0))) -> 2 | E27: =IF(H27="Subetapa",0,IF(H27="serviço",OFFSET(E27,-1,0)+1,OFFSET(E27,-1,0))) -> 4 | H27: SERVIÇO | I27: =IF(H27="Unidade Construtiva",TEXT(A27,"00"),IF(H27="Célula Construtiva",TEXT(B27,"00"),IF(H27="Etapa",CONCATENATE(TEXT(B27,"00"),".",TEXT(C27,"000")),IF(H27="Subetapa",CONCATENATE(TEXT(B27,"00"),".",TEXT(C27,"000"),".",TEXT(D27,"000")),IF(H27="Serviço",CONCATENATE(TEXT(B27,"00"),".",TEXT(C27,"000"),".",TEXT(D27,"000"),".",TEXT(E27,"000")),""))))) -> 01.002.002.004 | J27: Armação aço CA-50 ø 12,5mm para infraestrutura (corte e dobra em obra) | K27: kg | L27: =Aço_Infraestrutura!G16 -> 260.6 | M27: =_xlfn.XLOOKUP($J27,CPU!$D$1:$D$2521,CPU!$H$1:$H$2521) -> 6.443145 | N27: =IF(H27="Serviço",M27*L27,IF(H27="CÉLULA CONSTRUTIVA",SUMIFS($N$8:$N$258,$B$8:$B$258,B27,$H$8:$H$258,"Serviço"),IF(H27="ETAPA",SUMIFS($N$8:$N$258,$B$8:$B$258,B27,$C$8:$C$258,C27,$H$8:$H$258,"Serviço"),IF(H27="SUBETAPA",SUMIFS($N$8:$N$258,$B$8:$B$258,B27,$C$8:$C$258,C27,$D$8:$D$258,D27,$H$8:$H$258,"Serviço"),0)))) -> 1679.0836 | O27: Quantidade disponibilizada pelo projetista | P27: Finalizado
A28: =IF($H28="UNIDADE CONSTRUTIVA",OFFSET(A28,-1,0)+1,LARGE(A$3:A27,1)) -> 0 | B28: =IF(H28="UNIDADE CONSTRUTIVA",0,IF(H28="CÉLULA CONSTRUTIVA",OFFSET(B28,-1,0)+1,OFFSET(B28,-1,0))) -> 1 | C28: =IF(H28="CÉLULA CONSTRUTIVA",0,IF(H28="ETAPA",OFFSET(C28,-1,0)+1,OFFSET(C28,-1,0))) -> 2 | D28: =IF(H28="ETAPA",0,IF(H28="SUBETAPA",OFFSET(D28,-1,0)+1,OFFSET(D28,-1,0))) -> 2 | E28: =IF(H28="Subetapa",0,IF(H28="serviço",OFFSET(E28,-1,0)+1,OFFSET(E28,-1,0))) -> 5 | H28: SERVIÇO | I28: =IF(H28="Unidade Construtiva",TEXT(A28,"00"),IF(H28="Célula Construtiva",TEXT(B28,"00"),IF(H28="Etapa",CONCATENATE(TEXT(B28,"00"),".",TEXT(C28,"000")),IF(H28="Subetapa",CONCATENATE(TEXT(B28,"00"),".",TEXT(C28,"000"),".",TEXT(D28,"000")),IF(H28="Serviço",CONCATENATE(TEXT(B28,"00"),".",TEXT(C28,"000"),".",TEXT(D28,"000"),".",TEXT(E28,"000")),""))))) -> 01.002.002.005 | J28: Armação aço CA-50 ø 16,0mm para infraestrutura (corte e dobra em obra) | K28: kg | L28: =Aço_Infraestrutura!H16 -> 222.2 | M28: =_xlfn.XLOOKUP($J28,CPU!$D$1:$D$2521,CPU!$H$1:$H$2521) -> 6.443145 | N28: =IF(H28="Serviço",M28*L28,IF(H28="CÉLULA CONSTRUTIVA",SUMIFS($N$8:$N$258,$B$8:$B$258,B28,$H$8:$H$258,"Serviço"),IF(H28="ETAPA",SUMIFS($N$8:$N$258,$B$8:$B$258,B28,$C$8:$C$258,C28,$H$8:$H$258,"Serviço"),IF(H28="SUBETAPA",SUMIFS($N$8:$N$258,$B$8:$B$258,B28,$C$8:$C$258,C28,$D$8:$D$258,D28,$H$8:$H$258,"Serviço"),0)))) -> 1431.6668 | O28: Quantidade disponibilizada pelo projetista | P28: Finalizado
A29: =IF($H29="UNIDADE CONSTRUTIVA",OFFSET(A29,-1,0)+1,LARGE(A$3:A28,1)) -> 0 | B29: =IF(H29="UNIDADE CONSTRUTIVA",0,IF(H29="CÉLULA CONSTRUTIVA",OFFSET(B29,-1,0)+1,OFFSET(B29,-1,0))) -> 1 | C29: =IF(H29="CÉLULA CONSTRUTIVA",0,IF(H29="ETAPA",OFFSET(C29,-1,0)+1,OFFSET(C29,-1,0))) -> 2 | D29: =IF(H29="ETAPA",0,IF(H29="SUBETAPA",OFFSET(D29,-1,0)+1,OFFSET(D29,-1,0))) -> 2 | E29: =IF(H29="Subetapa",0,IF(H29="serviço",OFFSET(E29,-1,0)+1,OFFSET(E29,-1,0))) -> 6 | H29: SERVIÇO | I29: =IF(H29="Unidade Construtiva",TEXT(A29,"00"),IF(H29="Célula Construtiva",TEXT(B29,"00"),IF(H29="Etapa",CONCATENATE(TEXT(B29,"00"),".",TEXT(C29,"000")),IF(H29="Subetapa",CONCATENATE(TEXT(B29,"00"),".",TEXT(C29,"000"),".",TEXT(D29,"000")),IF(H29="Serviço",CONCATENATE(TEXT(B29,"00"),".",TEXT(C29,"000"),".",TEXT(D29,"000"),".",TEXT(E29,"000")),""))))) -> 01.002.002.006 | J29: Armação aço CA-60 ø 5,00mm para infraestrutura (corte e dobra em obra) | K29: kg | L29: =Aço_Infraestrutura!K16 -> 441.6 | M29: =_xlfn.XLOOKUP($J29,CPU!$D$1:$D$2521,CPU!$H$1:$H$2521) -> 7.488145 | N29: =IF(H29="Serviço",M29*L29,IF(H29="CÉLULA CONSTRUTIVA",SUMIFS($N$8:$N$258,$B$8:$B$258,B29,$H$8:$H$258,"Serviço"),IF(H29="ETAPA",SUMIFS($N$8:$N$258,$B$8:$B$258,B29,$C$8:$C$258,C29,$H$8:$H$258,"Serviço"),IF(H29="SUBETAPA",SUMIFS($N$8:$N$258,$B$8:$B$258,B29,$C$8:$C$258,C29,$D$8:$D$258,D29,$H$8:$H$258,"Serviço"),0)))) -> 3306.7648 | O29: Quantidade disponibilizada pelo projetista | P29: Finalizado
A30: =IF($H30="UNIDADE CONSTRUTIVA",OFFSET(A30,-1,0)+1,LARGE(A$3:A29,1)) -> 0 | B30: =IF(H30="UNIDADE CONSTRUTIVA",0,IF(H30="CÉLULA CONSTRUTIVA",OFFSET(B30,-1,0)+1,OFFSET(B30,-1,0))) -> 1 | C30: =IF(H30="CÉLULA CONSTRUTIVA",0,IF(H30="ETAPA",OFFSET(C30,-1,0)+1,OFFSET(C30,-1,0))) -> 2 | D30: =IF(H30="ETAPA",0,IF(H30="SUBETAPA",OFFSET(D30,-1,0)+1,OFFSET(D30,-1,0))) -> 2 | E30: =IF(H30="Subetapa",0,IF(H30="serviço",OFFSET(E30,-1,0)+1,OFFSET(E30,-1,0))) -> 7 | H30: SERVIÇO | I30: =IF(H30="Unidade Construtiva",TEXT(A30,"00"),IF(H30="Célula Construtiva",TEXT(B30,"00"),IF(H30="Etapa",CONCATENATE(TEXT(B30,"00"),".",TEXT(C30,"000")),IF(H30="Subetapa",CONCATENATE(TEXT(B30,"00"),".",TEXT(C30,"000"),".",TEXT(D30,"000")),IF(H30="Serviço",CONCATENATE(TEXT(B30,"00"),".",TEXT(C30,"000"),".",TEXT(D30,"000"),".",TEXT(E30,"000")),""))))) -> 01.002.002.007 | J30: Armação Malha Ø5,0 c/25, para ContraPiso Armado (corte e dobra em Obra) | K30: m2 | L30: =LAJE_TRELIÇADA!J7 -> 154 | M30: =_xlfn.XLOOKUP($J30,CPU!$D$1:$D$2521,CPU!$H$1:$H$2521) -> 37.756055 | N30: =IF(H30="Serviço",M30*L30,IF(H30="CÉLULA CONSTRUTIVA",SUMIFS($N$8:$N$258,$B$8:$B$258,B30,$H$8:$H$258,"Serviço"),IF(H30="ETAPA",SUMIFS($N$8:$N$258,$B$8:$B$258,B30,$C$8:$C$258,C30,$H$8:$H$258,"Serviço"),IF(H30="SUBETAPA",SUMIFS($N$8:$N$258,$B$8:$B$258,B30,$C$8:$C$258,C30,$D$8:$D$258,D30,$H$8:$H$258,"Serviço"),0)))) -> 5814.4325 | O30: Quantidade de levantameto da Cartesian | P30: Finalizado
A31: =IF($H31="UNIDADE CONSTRUTIVA",OFFSET(A31,-1,0)+1,LARGE(A$3:A30,1)) -> 0 | B31: =IF(H31="UNIDADE CONSTRUTIVA",0,IF(H31="CÉLULA CONSTRUTIVA",OFFSET(B31,-1,0)+1,OFFSET(B31,-1,0))) -> 1 | C31: =IF(H31="CÉLULA CONSTRUTIVA",0,IF(H31="ETAPA",OFFSET(C31,-1,0)+1,OFFSET(C31,-1,0))) -> 2 | D31: =IF(H31="ETAPA",0,IF(H31="SUBETAPA",OFFSET(D31,-1,0)+1,OFFSET(D31,-1,0))) -> 3 | E31: =IF(H31="Subetapa",0,IF(H31="serviço",OFFSET(E31,-1,0)+1,OFFSET(E31,-1,0))) -> 0 | H31: SUBETAPA | I31: =IF(H31="Unidade Construtiva",TEXT(A31,"00"),IF(H31="Célula Construtiva",TEXT(B31,"00"),IF(H31="Etapa",CONCATENATE(TEXT(B31,"00"),".",TEXT(C31,"000")),IF(H31="Subetapa",CONCATENATE(TEXT(B31,"00"),".",TEXT(C31,"000"),".",TEXT(D31,"000")),IF(H31="Serviço",CONCATENATE(TEXT(B31,"00"),".",TEXT(C31,"000"),".",TEXT(D31,"000"),".",TEXT(E31,"000")),""))))) -> 01.002.003 | J31: Concreto | N31: =IF(H31="Serviço",M31*L31,IF(H31="CÉLULA CONSTRUTIVA",SUMIFS($N$8:$N$258,$B$8:$B$258,B31,$H$8:$H$258,"Serviço"),IF(H31="ETAPA",SUMIFS($N$8:$N$258,$B$8:$B$258,B31,$C$8:$C$258,C31,$H$8:$H$258,"Serviço"),IF(H31="SUBETAPA",SUMIFS($N$8:$N$258,$B$8:$B$258,B31,$C$8:$C$258,C31,$D$8:$D$258,D31,$H$8:$H$258,"Serviço"),0)))) -> 16432.309 | O31: =N31/'Obra '!E$9 -> 49.859844
A32: =IF($H32="UNIDADE CONSTRUTIVA",OFFSET(A32,-1,0)+1,LARGE(A$3:A31,1)) -> 0 | B32: =IF(H32="UNIDADE CONSTRUTIVA",0,IF(H32="CÉLULA CONSTRUTIVA",OFFSET(B32,-1,0)+1,OFFSET(B32,-1,0))) -> 1 | C32: =IF(H32="CÉLULA CONSTRUTIVA",0,IF(H32="ETAPA",OFFSET(C32,-1,0)+1,OFFSET(C32,-1,0))) -> 2 | D32: =IF(H32="ETAPA",0,IF(H32="SUBETAPA",OFFSET(D32,-1,0)+1,OFFSET(D32,-1,0))) -> 3 | E32: =IF(H32="Subetapa",0,IF(H32="serviço",OFFSET(E32,-1,0)+1,OFFSET(E32,-1,0))) -> 1 | H32: SERVIÇO | I32: =IF(H32="Unidade Construtiva",TEXT(A32,"00"),IF(H32="Célula Construtiva",TEXT(B32,"00"),IF(H32="Etapa",CONCATENATE(TEXT(B32,"00"),".",TEXT(C32,"000")),IF(H32="Subetapa",CONCATENATE(TEXT(B32,"00"),".",TEXT(C32,"000"),".",TEXT(D32,"000")),IF(H32="Serviço",CONCATENATE(TEXT(B32,"00"),".",TEXT(C32,"000"),".",TEXT(D32,"000"),".",TEXT(E32,"000")),""))))) -> 01.002.003.001 | J32: Concreto Usinado bombeável 30MPa para infraestrutura - incluindo serviço de bombeamento | K32: m3 | L32: =Aço_Infraestrutura!O7+Aço_Infraestrutura!O9+Aço_Infraestrutura!O11+Aço_Infraestrutura!O13 -> 28.51 | M32: 576.37 | N32: =IF(H32="Serviço",M32*L32,IF(H32="CÉLULA CONSTRUTIVA",SUMIFS($N$8:$N$258,$B$8:$B$258,B32,$H$8:$H$258,"Serviço"),IF(H32="ETAPA",SUMIFS($N$8:$N$258,$B$8:$B$258,B32,$C$8:$C$258,C32,$H$8:$H$258,"Serviço"),IF(H32="SUBETAPA",SUMIFS($N$8:$N$258,$B$8:$B$258,B32,$C$8:$C$258,C32,$D$8:$D$258,D32,$H$8:$H$258,"Serviço"),0)))) -> 16432.309 | O32: Quantidade disponibilizada pelo projetista | P32: Finalizado
A33: =IF($H33="UNIDADE CONSTRUTIVA",OFFSET(A33,-1,0)+1,LARGE(A$3:A32,1)) -> 0 | B33: =IF(H33="UNIDADE CONSTRUTIVA",0,IF(H33="CÉLULA CONSTRUTIVA",OFFSET(B33,-1,0)+1,OFFSET(B33,-1,0))) -> 1 | C33: =IF(H33="CÉLULA CONSTRUTIVA",0,IF(H33="ETAPA",OFFSET(C33,-1,0)+1,OFFSET(C33,-1,0))) -> 2 | D33: =IF(H33="ETAPA",0,IF(H33="SUBETAPA",OFFSET(D33,-1,0)+1,OFFSET(D33,-1,0))) -> 4 | E33: =IF(H33="Subetapa",0,IF(H33="serviço",OFFSET(E33,-1,0)+1,OFFSET(E33,-1,0))) -> 0 | H33: SUBETAPA | I33: =IF(H33="Unidade Construtiva",TEXT(A33,"00"),IF(H33="Célula Construtiva",TEXT(B33,"00"),IF(H33="Etapa",CONCATENATE(TEXT(B33,"00"),".",TEXT(C33,"000")),IF(H33="Subetapa",CONCATENATE(TEXT(B33,"00"),".",TEXT(C33,"000"),".",TEXT(D33,"000")),IF(H33="Serviço",CONCATENATE(TEXT(B33,"00"),".",TEXT(C33,"000"),".",TEXT(D33,"000"),".",TEXT(E33,"000")),""))))) -> 01.002.004 | J33: Mão de Obra | N33: =IF(H33="Serviço",M33*L33,IF(H33="CÉLULA CONSTRUTIVA",SUMIFS($N$8:$N$258,$B$8:$B$258,B33,$H$8:$H$258,"Serviço"),IF(H33="ETAPA",SUMIFS($N$8:$N$258,$B$8:$B$258,B33,$C$8:$C$258,C33,$H$8:$H$258,"Serviço"),IF(H33="SUBETAPA",SUMIFS($N$8:$N$258,$B$8:$B$258,B33,$C$8:$C$258,C33,$D$8:$D$258,D33,$H$8:$H$258,"Serviço"),0)))) -> 47206.2 | O33: =N33/'Obra '!E$9 -> 143.23573
A34: =IF($H34="UNIDADE CONSTRUTIVA",OFFSET(A34,-1,0)+1,LARGE(A$3:A33,1)) -> 0 | B34: =IF(H34="UNIDADE CONSTRUTIVA",0,IF(H34="CÉLULA CONSTRUTIVA",OFFSET(B34,-1,0)+1,OFFSET(B34,-1,0))) -> 1 | C34: =IF(H34="CÉLULA CONSTRUTIVA",0,IF(H34="ETAPA",OFFSET(C34,-1,0)+1,OFFSET(C34,-1,0))) -> 2 | D34: =IF(H34="ETAPA",0,IF(H34="SUBETAPA",OFFSET(D34,-1,0)+1,OFFSET(D34,-1,0))) -> 4 | E34: =IF(H34="Subetapa",0,IF(H34="serviço",OFFSET(E34,-1,0)+1,OFFSET(E34,-1,0))) -> 1 | H34: SERVIÇO | I34: =IF(H34="Unidade Construtiva",TEXT(A34,"00"),IF(H34="Célula Construtiva",TEXT(B34,"00"),IF(H34="Etapa",CONCATENATE(TEXT(B34,"00"),".",TEXT(C34,"000")),IF(H34="Subetapa",CONCATENATE(TEXT(B34,"00"),".",TEXT(C34,"000"),".",TEXT(D34,"000")),IF(H34="Serviço",CONCATENATE(TEXT(B34,"00"),".",TEXT(C34,"000"),".",TEXT(D34,"000"),".",TEXT(E34,"000")),""))))) -> 01.002.004.001 | J34: Mão de obra para execução de fundação | K34: m2 | L34: ='Obra '!E15 -> 162.78 | M34: =_xlfn.XLOOKUP($J34,CPU!$D$1:$D$2521,CPU!$H$1:$H$2521) -> 290 | N34: =IF(H34="Serviço",M34*L34,IF(H34="CÉLULA CONSTRUTIVA",SUMIFS($N$8:$N$258,$B$8:$B$258,B34,$H$8:$H$258,"Serviço"),IF(H34="ETAPA",SUMIFS($N$8:$N$258,$B$8:$B$258,B34,$C$8:$C$258,C34,$H$8:$H$258,"Serviço"),IF(H34="SUBETAPA",SUMIFS($N$8:$N$258,$B$8:$B$258,B34,$C$8:$C$258,C34,$D$8:$D$258,D34,$H$8:$H$258,"Serviço"),0)))) -> 47206.2 | P34: Finalizado
A35: =IF($H35="UNIDADE CONSTRUTIVA",OFFSET(A35,-1,0)+1,LARGE(A$3:A34,1)) -> 0 | B35: =IF(H35="UNIDADE CONSTRUTIVA",0,IF(H35="CÉLULA CONSTRUTIVA",OFFSET(B35,-1,0)+1,OFFSET(B35,-1,0))) -> 2 | C35: =IF(H35="CÉLULA CONSTRUTIVA",0,IF(H35="ETAPA",OFFSET(C35,-1,0)+1,OFFSET(C35,-1,0))) -> 0 | D35: =IF(H35="ETAPA",0,IF(H35="SUBETAPA",OFFSET(D35,-1,0)+1,OFFSET(D35,-1,0))) -> 4 | E35: =IF(H35="Subetapa",0,IF(H35="serviço",OFFSET(E35,-1,0)+1,OFFSET(E35,-1,0))) -> 1 | H35: CÉLULA CONSTRUTIVA | I35: =IF(H35="Unidade Construtiva",TEXT(A35,"00"),IF(H35="Célula Construtiva",TEXT(B35,"00"),IF(H35="Etapa",CONCATENATE(TEXT(B35,"00"),".",TEXT(C35,"000")),IF(H35="Subetapa",CONCATENATE(TEXT(B35,"00"),".",TEXT(C35,"000"),".",TEXT(D35,"000")),IF(H35="Serviço",CONCATENATE(TEXT(B35,"00"),".",TEXT(C35,"000"),".",TEXT(D35,"000"),".",TEXT(E35,"000")),""))))) -> 02 | J35: SUPRAESTRUTURA | N35: =IF(H35="Serviço",M35*L35,IF(H35="CÉLULA CONSTRUTIVA",SUMIFS($N$8:$N$258,$B$8:$B$258,B35,$H$8:$H$258,"Serviço"),IF(H35="ETAPA",SUMIFS($N$8:$N$258,$B$8:$B$258,B35,$C$8:$C$258,C35,$H$8:$H$258,"Serviço"),IF(H35="SUBETAPA",SUMIFS($N$8:$N$258,$B$8:$B$258,B35,$C$8:$C$258,C35,$D$8:$D$258,D35,$H$8:$H$258,"Serviço"),0)))) -> 190194.42 | O35: =N35/'Obra '!E$9 -> 577.09871
A36: =IF($H36="UNIDADE CONSTRUTIVA",OFFSET(A36,-1,0)+1,LARGE(A$3:A35,1)) -> 0 | B36: =IF(H36="UNIDADE CONSTRUTIVA",0,IF(H36="CÉLULA CONSTRUTIVA",OFFSET(B36,-1,0)+1,OFFSET(B36,-1,0))) -> 2 | C36: =IF(H36="CÉLULA CONSTRUTIVA",0,IF(H36="ETAPA",OFFSET(C36,-1,0)+1,OFFSET(C36,-1,0))) -> 1 | D36: =IF(H36="ETAPA",0,IF(H36="SUBETAPA",OFFSET(D36,-1,0)+1,OFFSET(D36,-1,0))) -> 0 | E36: =IF(H36="Subetapa",0,IF(H36="serviço",OFFSET(E36,-1,0)+1,OFFSET(E36,-1,0))) -> 1 | H36: ETAPA | I36: =IF(H36="Unidade Construtiva",TEXT(A36,"00"),IF(H36="Célula Construtiva",TEXT(B36,"00"),IF(H36="Etapa",CONCATENATE(TEXT(B36,"00"),".",TEXT(C36,"000")),IF(H36="Subetapa",CONCATENATE(TEXT(B36,"00"),".",TEXT(C36,"000"),".",TEXT(D36,"000")),IF(H36="Serviço",CONCATENATE(TEXT(B36,"00"),".",TEXT(C36,"000"),".",TEXT(D36,"000"),".",TEXT(E36,"000")),""))))) -> 02.001 | J36: SUPRAESTRUTURA | N36: =IF(H36="Serviço",M36*L36,IF(H36="CÉLULA CONSTRUTIVA",SUMIFS($N$8:$N$258,$B$8:$B$258,B36,$H$8:$H$258,"Serviço"),IF(H36="ETAPA",SUMIFS($N$8:$N$258,$B$8:$B$258,B36,$C$8:$C$258,C36,$H$8:$H$258,"Serviço"),IF(H36="SUBETAPA",SUMIFS($N$8:$N$258,$B$8:$B$258,B36,$C$8:$C$258,C36,$D$8:$D$258,D36,$H$8:$H$258,"Serviço"),0)))) -> 190194.42
A37: =IF($H37="UNIDADE CONSTRUTIVA",OFFSET(A37,-1,0)+1,LARGE(A$3:A36,1)) -> 0 | B37: =IF(H37="UNIDADE CONSTRUTIVA",0,IF(H37="CÉLULA CONSTRUTIVA",OFFSET(B37,-1,0)+1,OFFSET(B37,-1,0))) -> 2 | C37: =IF(H37="CÉLULA CONSTRUTIVA",0,IF(H37="ETAPA",OFFSET(C37,-1,0)+1,OFFSET(C37,-1,0))) -> 1 | D37: =IF(H37="ETAPA",0,IF(H37="SUBETAPA",OFFSET(D37,-1,0)+1,OFFSET(D37,-1,0))) -> 1 | E37: =IF(H37="Subetapa",0,IF(H37="serviço",OFFSET(E37,-1,0)+1,OFFSET(E37,-1,0))) -> 0 | H37: SUBETAPA | I37: =IF(H37="Unidade Construtiva",TEXT(A37,"00"),IF(H37="Célula Construtiva",TEXT(B37,"00"),IF(H37="Etapa",CONCATENATE(TEXT(B37,"00"),".",TEXT(C37,"000")),IF(H37="Subetapa",CONCATENATE(TEXT(B37,"00"),".",TEXT(C37,"000"),".",TEXT(D37,"000")),IF(H37="Serviço",CONCATENATE(TEXT(B37,"00"),".",TEXT(C37,"000"),".",TEXT(D37,"000"),".",TEXT(E37,"000")),""))))) -> 02.001.001 | J37: Forma | N37: =IF(H37="Serviço",M37*L37,IF(H37="CÉLULA CONSTRUTIVA",SUMIFS($N$8:$N$258,$B$8:$B$258,B37,$H$8:$H$258,"Serviço"),IF(H37="ETAPA",SUMIFS($N$8:$N$258,$B$8:$B$258,B37,$C$8:$C$258,C37,$H$8:$H$258,"Serviço"),IF(H37="SUBETAPA",SUMIFS($N$8:$N$258,$B$8:$B$258,B37,$C$8:$C$258,C37,$D$8:$D$258,D37,$H$8:$H$258,"Serviço"),0)))) -> 59399.451
A38: =IF($H38="UNIDADE CONSTRUTIVA",OFFSET(A38,-1,0)+1,LARGE(A$3:A37,1)) -> 0 | B38: =IF(H38="UNIDADE CONSTRUTIVA",0,IF(H38="CÉLULA CONSTRUTIVA",OFFSET(B38,-1,0)+1,OFFSET(B38,-1,0))) -> 2 | C38: =IF(H38="CÉLULA CONSTRUTIVA",0,IF(H38="ETAPA",OFFSET(C38,-1,0)+1,OFFSET(C38,-1,0))) -> 1 | D38: =IF(H38="ETAPA",0,IF(H38="SUBETAPA",OFFSET(D38,-1,0)+1,OFFSET(D38,-1,0))) -> 1 | E38: =IF(H38="Subetapa",0,IF(H38="serviço",OFFSET(E38,-1,0)+1,OFFSET(E38,-1,0))) -> 1 | H38: SERVIÇO | I38: =IF(H38="Unidade Construtiva",TEXT(A38,"00"),IF(H38="Célula Construtiva",TEXT(B38,"00"),IF(H38="Etapa",CONCATENATE(TEXT(B38,"00"),".",TEXT(C38,"000")),IF(H38="Subetapa",CONCATENATE(TEXT(B38,"00"),".",TEXT(C38,"000"),".",TEXT(D38,"000")),IF(H38="Serviço",CONCATENATE(TEXT(B38,"00"),".",TEXT(C38,"000"),".",TEXT(D38,"000"),".",TEXT(E38,"000")),""))))) -> 02.001.001.001 | J38: Fabricação de Fôrma para Pilares, em Chapa de Madeira Compensada Plastificada, E=18mm | K38: m2 | L38: =L42*0.5 -> 72.635 | M38: =_xlfn.XLOOKUP($J38,CPU!$D$1:$D$2521,CPU!$H$1:$H$2521) -> 117.15403 | N38: =IF(H38="Serviço",M38*L38,IF(H38="CÉLULA CONSTRUTIVA",SUMIFS($N$8:$N$258,$B$8:$B$258,B38,$H$8:$H$258,"Serviço"),IF(H38="ETAPA",SUMIFS($N$8:$N$258,$B$8:$B$258,B38,$C$8:$C$258,C38,$H$8:$H$258,"Serviço"),IF(H38="SUBETAPA",SUMIFS($N$8:$N$258,$B$8:$B$258,B38,$C$8:$C$258,C38,$D$8:$D$258,D38,$H$8:$H$258,"Serviço"),0)))) -> 8509.4828 | O38: Quantidade disponibilizada pelo projetista, considerando sem reutilização | P38: Finalizado
A39: =IF($H39="UNIDADE CONSTRUTIVA",OFFSET(A39,-1,0)+1,LARGE(A$3:A38,1)) -> 0 | B39: =IF(H39="UNIDADE CONSTRUTIVA",0,IF(H39="CÉLULA CONSTRUTIVA",OFFSET(B39,-1,0)+1,OFFSET(B39,-1,0))) -> 2 | C39: =IF(H39="CÉLULA CONSTRUTIVA",0,IF(H39="ETAPA",OFFSET(C39,-1,0)+1,OFFSET(C39,-1,0))) -> 1 | D39: =IF(H39="ETAPA",0,IF(H39="SUBETAPA",OFFSET(D39,-1,0)+1,OFFSET(D39,-1,0))) -> 1 | E39: =IF(H39="Subetapa",0,IF(H39="serviço",OFFSET(E39,-1,0)+1,OFFSET(E39,-1,0))) -> 2 | H39: SERVIÇO | I39: =IF(H39="Unidade Construtiva",TEXT(A39,"00"),IF(H39="Célula Construtiva",TEXT(B39,"00"),IF(H39="Etapa",CONCATENATE(TEXT(B39,"00"),".",TEXT(C39,"000")),IF(H39="Subetapa",CONCATENATE(TEXT(B39,"00"),".",TEXT(C39,"000"),".",TEXT(D39,"000")),IF(H39="Serviço",CONCATENATE(TEXT(B39,"00"),".",TEXT(C39,"000"),".",TEXT(D39,"000"),".",TEXT(E39,"000")),""))))) -> 02.001.001.002 | J39: Fabricação de Fôrma para Vigas, em Chapa de Madeira Compensada Plastificada, E=18mm | K39: m2 | L39: =L43*0.8 -> 224.904 | M39: =_xlfn.XLOOKUP($J39,CPU!$D$1:$D$2521,CPU!$H$1:$H$2521) -> 96.647629 | N39: =IF(H39="Serviço",M39*L39,IF(H39="CÉLULA CONSTRUTIVA",SUMIFS($N$8:$N$258,$B$8:$B$258,B39,$H$8:$H$258,"Serviço"),IF(H39="ETAPA",SUMIFS($N$8:$N$258,$B$8:$B$258,B39,$C$8:$C$258,C39,$H$8:$H$258,"Serviço"),IF(H39="SUBETAPA",SUMIFS($N$8:$N$258,$B$8:$B$258,B39,$C$8:$C$258,C39,$D$8:$D$258,D39,$H$8:$H$258,"Serviço"),0)))) -> 21736.438 | O39: Quantidade disponibilizada pelo projetista, considerando sem reutilização | P39: Finalizado
A40: =IF($H40="UNIDADE CONSTRUTIVA",OFFSET(A40,-1,0)+1,LARGE(A$3:A39,1)) -> 0 | B40: =IF(H40="UNIDADE CONSTRUTIVA",0,IF(H40="CÉLULA CONSTRUTIVA",OFFSET(B40,-1,0)+1,OFFSET(B40,-1,0))) -> 2 | C40: =IF(H40="CÉLULA CONSTRUTIVA",0,IF(H40="ETAPA",OFFSET(C40,-1,0)+1,OFFSET(C40,-1,0))) -> 1 | D40: =IF(H40="ETAPA",0,IF(H40="SUBETAPA",OFFSET(D40,-1,0)+1,OFFSET(D40,-1,0))) -> 1 | E40: =IF(H40="Subetapa",0,IF(H40="serviço",OFFSET(E40,-1,0)+1,OFFSET(E40,-1,0))) -> 3 | H40: SERVIÇO | I40: =IF(H40="Unidade Construtiva",TEXT(A40,"00"),IF(H40="Célula Construtiva",TEXT(B40,"00"),IF(H40="Etapa",CONCATENATE(TEXT(B40,"00"),".",TEXT(C40,"000")),IF(H40="Subetapa",CONCATENATE(TEXT(B40,"00"),".",TEXT(C40,"000"),".",TEXT(D40,"000")),IF(H40="Serviço",CONCATENATE(TEXT(B40,"00"),".",TEXT(C40,"000"),".",TEXT(D40,"000"),".",TEXT(E40,"000")),""))))) -> 02.001.001.003 | J40: Fornecimento de Lajes Treliçadas TR8 com cerâmica H8 | K40: m2 | L40: =LAJE_TRELIÇADA!G12 -> 365.64 | M40: 71.3815 | N40: =IF(H40="Serviço",M40*L40,IF(H40="CÉLULA CONSTRUTIVA",SUMIFS($N$8:$N$258,$B$8:$B$258,B40,$H$8:$H$258,"Serviço"),IF(H40="ETAPA",SUMIFS($N$8:$N$258,$B$8:$B$258,B40,$C$8:$C$258,C40,$H$8:$H$258,"Serviço"),IF(H40="SUBETAPA",SUMIFS($N$8:$N$258,$B$8:$B$258,B40,$C$8:$C$258,C40,$D$8:$D$258,D40,$H$8:$H$258,"Serviço"),0)))) -> 26099.932 | O40: Quantidade levantada em projeto | P40: Finalizado
A41: =IF($H41="UNIDADE CONSTRUTIVA",OFFSET(A41,-1,0)+1,LARGE(A$3:A40,1)) -> 0 | B41: =IF(H41="UNIDADE CONSTRUTIVA",0,IF(H41="CÉLULA CONSTRUTIVA",OFFSET(B41,-1,0)+1,OFFSET(B41,-1,0))) -> 2 | C41: =IF(H41="CÉLULA CONSTRUTIVA",0,IF(H41="ETAPA",OFFSET(C41,-1,0)+1,OFFSET(C41,-1,0))) -> 1 | D41: =IF(H41="ETAPA",0,IF(H41="SUBETAPA",OFFSET(D41,-1,0)+1,OFFSET(D41,-1,0))) -> 1 | E41: =IF(H41="Subetapa",0,IF(H41="serviço",OFFSET(E41,-1,0)+1,OFFSET(E41,-1,0))) -> 4 | H41: SERVIÇO | I41: =IF(H41="Unidade Construtiva",TEXT(A41,"00"),IF(H41="Célula Construtiva",TEXT(B41,"00"),IF(H41="Etapa",CONCATENATE(TEXT(B41,"00"),".",TEXT(C41,"000")),IF(H41="Subetapa",CONCATENATE(TEXT(B41,"00"),".",TEXT(C41,"000"),".",TEXT(D41,"000")),IF(H41="Serviço",CONCATENATE(TEXT(B41,"00"),".",TEXT(C41,"000"),".",TEXT(D41,"000"),".",TEXT(E41,"000")),""))))) -> 02.001.001.004 | J41: Fabricação de Fôrma para Escadas, em Chapa de Madeira Compensada Resinada, E=18mm | K41: m2 | L41: =L44 -> 14.1 | M41: =_xlfn.XLOOKUP($J41,CPU!$D$1:$D$2521,CPU!$H$1:$H$2521) -> 115.0547 | N41: =IF(H41="Serviço",M41*L41,IF(H41="CÉLULA CONSTRUTIVA",SUMIFS($N$8:$N$258,$B$8:$B$258,B41,$H$8:$H$258,"Serviço"),IF(H41="ETAPA",SUMIFS($N$8:$N$258,$B$8:$B$258,B41,$C$8:$C$258,C41,$H$8:$H$258,"Serviço"),IF(H41="SUBETAPA",SUMIFS($N$8:$N$258,$B$8:$B$258,B41,$C$8:$C$258,C41,$D$8:$D$258,D41,$H$8:$H$258,"Serviço"),0)))) -> 1622.2712 | O41: Quantidade disponibilizada pelo projetista, considerando sem reutilização | P41: Finalizado
A42: =IF($H42="UNIDADE CONSTRUTIVA",OFFSET(A42,-1,0)+1,LARGE(A$3:A41,1)) -> 0 | B42: =IF(H42="UNIDADE CONSTRUTIVA",0,IF(H42="CÉLULA CONSTRUTIVA",OFFSET(B42,-1,0)+1,OFFSET(B42,-1,0))) -> 2 | C42: =IF(H42="CÉLULA CONSTRUTIVA",0,IF(H42="ETAPA",OFFSET(C42,-1,0)+1,OFFSET(C42,-1,0))) -> 1 | D42: =IF(H42="ETAPA",0,IF(H42="SUBETAPA",OFFSET(D42,-1,0)+1,OFFSET(D42,-1,0))) -> 1 | E42: =IF(H42="Subetapa",0,IF(H42="serviço",OFFSET(E42,-1,0)+1,OFFSET(E42,-1,0))) -> 5 | H42: SERVIÇO | I42: =IF(H42="Unidade Construtiva",TEXT(A42,"00"),IF(H42="Célula Construtiva",TEXT(B42,"00"),IF(H42="Etapa",CONCATENATE(TEXT(B42,"00"),".",TEXT(C42,"000")),IF(H42="Subetapa",CONCATENATE(TEXT(B42,"00"),".",TEXT(C42,"000"),".",TEXT(D42,"000")),IF(H42="Serviço",CONCATENATE(TEXT(B42,"00"),".",TEXT(C42,"000"),".",TEXT(D42,"000"),".",TEXT(E42,"000")),""))))) -> 02.001.001.005 | J42: Montagem e Desmontagem de Fôrma de Pilares | K42: m2 | L42: =Supraestrutura!B33 -> 145.27 | M42: =_xlfn.XLOOKUP($J42,CPU!$D$1:$D$2521,CPU!$H$1:$H$2521) -> 0.69166 | N42: =IF(H42="Serviço",M42*L42,IF(H42="CÉLULA CONSTRUTIVA",SUMIFS($N$8:$N$258,$B$8:$B$258,B42,$H$8:$H$258,"Serviço"),IF(H42="ETAPA",SUMIFS($N$8:$N$258,$B$8:$B$258,B42,$C$8:$C$258,C42,$H$8:$H$258,"Serviço"),IF(H42="SUBETAPA",SUMIFS($N$8:$N$258,$B$8:$B$258,B42,$C$8:$C$258,C42,$D$8:$D$258,D42,$H$8:$H$258,"Serviço"),0)))) -> 100.47745 | P42: Finalizado
A43: =IF($H43="UNIDADE CONSTRUTIVA",OFFSET(A43,-1,0)+1,LARGE(A$3:A42,1)) -> 0 | B43: =IF(H43="UNIDADE CONSTRUTIVA",0,IF(H43="CÉLULA CONSTRUTIVA",OFFSET(B43,-1,0)+1,OFFSET(B43,-1,0))) -> 2 | C43: =IF(H43="CÉLULA CONSTRUTIVA",0,IF(H43="ETAPA",OFFSET(C43,-1,0)+1,OFFSET(C43,-1,0))) -> 1 | D43: =IF(H43="ETAPA",0,IF(H43="SUBETAPA",OFFSET(D43,-1,0)+1,OFFSET(D43,-1,0))) -> 1 | E43: =IF(H43="Subetapa",0,IF(H43="serviço",OFFSET(E43,-1,0)+1,OFFSET(E43,-1,0))) -> 6 | H43: SERVIÇO | I43: =IF(H43="Unidade Construtiva",TEXT(A43,"00"),IF(H43="Célula Construtiva",TEXT(B43,"00"),IF(H43="Etapa",CONCATENATE(TEXT(B43,"00"),".",TEXT(C43,"000")),IF(H43="Subetapa",CONCATENATE(TEXT(B43,"00"),".",TEXT(C43,"000"),".",TEXT(D43,"000")),IF(H43="Serviço",CONCATENATE(TEXT(B43,"00"),".",TEXT(C43,"000"),".",TEXT(D43,"000"),".",TEXT(E43,"000")),""))))) -> 02.001.001.006 | J43: Montagem e Desmontagem de Fôrma de Vigas | K43: m2 | L43: =Supraestrutura!B34+Supraestrutura!B37 -> 281.13 | M43: =_xlfn.XLOOKUP($J43,CPU!$D$1:$D$2521,CPU!$H$1:$H$2521) -> 4.6844188 | N43: =IF(H43="Serviço",M43*L43,IF(H43="CÉLULA CONSTRUTIVA",SUMIFS($N$8:$N$258,$B$8:$B$258,B43,$H$8:$H$258,"Serviço"),IF(H43="ETAPA",SUMIFS($N$8:$N$258,$B$8:$B$258,B43,$C$8:$C$258,C43,$H$8:$H$258,"Serviço"),IF(H43="SUBETAPA",SUMIFS($N$8:$N$258,$B$8:$B$258,B43,$C$8:$C$258,C43,$D$8:$D$258,D43,$H$8:$H$258,"Serviço"),0)))) -> 1316.9307 | O43: Considerado o item de piscinas aqui | P43: Finalizado
A44: =IF($H44="UNIDADE CONSTRUTIVA",OFFSET(A44,-1,0)+1,LARGE(A$3:A43,1)) -> 0 | B44: =IF(H44="UNIDADE CONSTRUTIVA",0,IF(H44="CÉLULA CONSTRUTIVA",OFFSET(B44,-1,0)+1,OFFSET(B44,-1,0))) -> 2 | C44: =IF(H44="CÉLULA CONSTRUTIVA",0,IF(H44="ETAPA",OFFSET(C44,-1,0)+1,OFFSET(C44,-1,0))) -> 1 | D44: =IF(H44="ETAPA",0,IF(H44="SUBETAPA",OFFSET(D44,-1,0)+1,OFFSET(D44,-1,0))) -> 1 | E44: =IF(H44="Subetapa",0,IF(H44="serviço",OFFSET(E44,-1,0)+1,OFFSET(E44,-1,0))) -> 7 | H44: SERVIÇO | I44: =IF(H44="Unidade Construtiva",TEXT(A44,"00"),IF(H44="Célula Construtiva",TEXT(B44,"00"),IF(H44="Etapa",CONCATENATE(TEXT(B44,"00"),".",TEXT(C44,"000")),IF(H44="Subetapa",CONCATENATE(TEXT(B44,"00"),".",TEXT(C44,"000"),".",TEXT(D44,"000")),IF(H44="Serviço",CONCATENATE(TEXT(B44,"00"),".",TEXT(C44,"000"),".",TEXT(D44,"000"),".",TEXT(E44,"000")),""))))) -> 02.001.001.007 | J44: Montagem e Desmontagem de Fôrma de Escadas | K44: m2 | L44: =Supraestrutura!B36 -> 14.1 | M44: =_xlfn.XLOOKUP($J44,CPU!$D$1:$D$2521,CPU!$H$1:$H$2521) -> 0.98718 | N44: =IF(H44="Serviço",M44*L44,IF(H44="CÉLULA CONSTRUTIVA",SUMIFS($N$8:$N$258,$B$8:$B$258,B44,$H$8:$H$258,"Serviço"),IF(H44="ETAPA",SUMIFS($N$8:$N$258,$B$8:$B$258,B44,$C$8:$C$258,C44,$H$8:$H$258,"Serviço"),IF(H44="SUBETAPA",SUMIFS($N$8:$N$258,$B$8:$B$258,B44,$C$8:$C$258,C44,$D$8:$D$258,D44,$H$8:$H$258,"Serviço"),0)))) -> 13.919238 | P44: Finalizado
A45: =IF($H45="UNIDADE CONSTRUTIVA",OFFSET(A45,-1,0)+1,LARGE(A$3:A44,1)) -> 0 | B45: =IF(H45="UNIDADE CONSTRUTIVA",0,IF(H45="CÉLULA CONSTRUTIVA",OFFSET(B45,-1,0)+1,OFFSET(B45,-1,0))) -> 2 | C45: =IF(H45="CÉLULA CONSTRUTIVA",0,IF(H45="ETAPA",OFFSET(C45,-1,0)+1,OFFSET(C45,-1,0))) -> 1 | D45: =IF(H45="ETAPA",0,IF(H45="SUBETAPA",OFFSET(D45,-1,0)+1,OFFSET(D45,-1,0))) -> 2 | E45: =IF(H45="Subetapa",0,IF(H45="serviço",OFFSET(E45,-1,0)+1,OFFSET(E45,-1,0))) -> 0 | H45: SUBETAPA | I45: =IF(H45="Unidade Construtiva",TEXT(A45,"00"),IF(H45="Célula Construtiva",TEXT(B45,"00"),IF(H45="Etapa",CONCATENATE(TEXT(B45,"00"),".",TEXT(C45,"000")),IF(H45="Subetapa",CONCATENATE(TEXT(B45,"00"),".",TEXT(C45,"000"),".",TEXT(D45,"000")),IF(H45="Serviço",CONCATENATE(TEXT(B45,"00"),".",TEXT(C45,"000"),".",TEXT(D45,"000"),".",TEXT(E45,"000")),""))))) -> 02.001.002 | J45: Armadura | N45: =IF(H45="Serviço",M45*L45,IF(H45="CÉLULA CONSTRUTIVA",SUMIFS($N$8:$N$258,$B$8:$B$258,B45,$H$8:$H$258,"Serviço"),IF(H45="ETAPA",SUMIFS($N$8:$N$258,$B$8:$B$258,B45,$C$8:$C$258,C45,$H$8:$H$258,"Serviço"),IF(H45="SUBETAPA",SUMIFS($N$8:$N$258,$B$8:$B$258,B45,$C$8:$C$258,C45,$D$8:$D$258,D45,$H$8:$H$258,"Serviço"),0)))) -> 44878.323
A46: =IF($H46="UNIDADE CONSTRUTIVA",OFFSET(A46,-1,0)+1,LARGE(A$3:A45,1)) -> 0 | B46: =IF(H46="UNIDADE CONSTRUTIVA",0,IF(H46="CÉLULA CONSTRUTIVA",OFFSET(B46,-1,0)+1,OFFSET(B46,-1,0))) -> 2 | C46: =IF(H46="CÉLULA CONSTRUTIVA",0,IF(H46="ETAPA",OFFSET(C46,-1,0)+1,OFFSET(C46,-1,0))) -> 1 | D46: =IF(H46="ETAPA",0,IF(H46="SUBETAPA",OFFSET(D46,-1,0)+1,OFFSET(D46,-1,0))) -> 2 | E46: =IF(H46="Subetapa",0,IF(H46="serviço",OFFSET(E46,-1,0)+1,OFFSET(E46,-1,0))) -> 1 | H46: SERVIÇO | I46: =IF(H46="Unidade Construtiva",TEXT(A46,"00"),IF(H46="Célula Construtiva",TEXT(B46,"00"),IF(H46="Etapa",CONCATENATE(TEXT(B46,"00"),".",TEXT(C46,"000")),IF(H46="Subetapa",CONCATENATE(TEXT(B46,"00"),".",TEXT(C46,"000"),".",TEXT(D46,"000")),IF(H46="Serviço",CONCATENATE(TEXT(B46,"00"),".",TEXT(C46,"000"),".",TEXT(D46,"000"),".",TEXT(E46,"000")),""))))) -> 02.001.002.001 | J46: Armação Aço CA-60, Diâmetro de 5,0mm para Supraestrutura, Corte e Dobra em Obra | K46: kg | L46: =Supraestrutura!B31 -> 1053.7 | M46: =_xlfn.XLOOKUP($J46,CPU!$D$1:$D$2521,CPU!$H$1:$H$2521) -> 7.550055 | N46: =IF(H46="Serviço",M46*L46,IF(H46="CÉLULA CONSTRUTIVA",SUMIFS($N$8:$N$258,$B$8:$B$258,B46,$H$8:$H$258,"Serviço"),IF(H46="ETAPA",SUMIFS($N$8:$N$258,$B$8:$B$258,B46,$C$8:$C$258,C46,$H$8:$H$258,"Serviço"),IF(H46="SUBETAPA",SUMIFS($N$8:$N$258,$B$8:$B$258,B46,$C$8:$C$258,C46,$D$8:$D$258,D46,$H$8:$H$258,"Serviço"),0)))) -> 7955.493 | O46: Quantidade disponibilizada pelo projetista | P46: Finalizado
A47: =IF($H47="UNIDADE CONSTRUTIVA",OFFSET(A47,-1,0)+1,LARGE(A$3:A46,1)) -> 0 | B47: =IF(H47="UNIDADE CONSTRUTIVA",0,IF(H47="CÉLULA CONSTRUTIVA",OFFSET(B47,-1,0)+1,OFFSET(B47,-1,0))) -> 2 | C47: =IF(H47="CÉLULA CONSTRUTIVA",0,IF(H47="ETAPA",OFFSET(C47,-1,0)+1,OFFSET(C47,-1,0))) -> 1 | D47: =IF(H47="ETAPA",0,IF(H47="SUBETAPA",OFFSET(D47,-1,0)+1,OFFSET(D47,-1,0))) -> 2 | E47: =IF(H47="Subetapa",0,IF(H47="serviço",OFFSET(E47,-1,0)+1,OFFSET(E47,-1,0))) -> 2 | H47: SERVIÇO | I47: =IF(H47="Unidade Construtiva",TEXT(A47,"00"),IF(H47="Célula Construtiva",TEXT(B47,"00"),IF(H47="Etapa",CONCATENATE(TEXT(B47,"00"),".",TEXT(C47,"000")),IF(H47="Subetapa",CONCATENATE(TEXT(B47,"00"),".",TEXT(C47,"000"),".",TEXT(D47,"000")),IF(H47="Serviço",CONCATENATE(TEXT(B47,"00"),".",TEXT(C47,"000"),".",TEXT(D47,"000"),".",TEXT(E47,"000")),""))))) -> 02.001.002.002 | J47: Armação Aço CA-50, Diâmetro de 6,3mm para Supraestrutura, Corte e Dobra em Obra | K47: kg | L47: =Supraestrutura!C31 -> 596.9 | M47: =_xlfn.XLOOKUP($J47,CPU!$D$1:$D$2521,CPU!$H$1:$H$2521) -> 7.000055 | N47: =IF(H47="Serviço",M47*L47,IF(H47="CÉLULA CONSTRUTIVA",SUMIFS($N$8:$N$258,$B$8:$B$258,B47,$H$8:$H$258,"Serviço"),IF(H47="ETAPA",SUMIFS($N$8:$N$258,$B$8:$B$258,B47,$C$8:$C$258,C47,$H$8:$H$258,"Serviço"),IF(H47="SUBETAPA",SUMIFS($N$8:$N$258,$B$8:$B$258,B47,$C$8:$C$258,C47,$D$8:$D$258,D47,$H$8:$H$258,"Serviço"),0)))) -> 4178.3328 | O47: Quantidade disponibilizada pelo projetista | P47: Finalizado
A48: =IF($H48="UNIDADE CONSTRUTIVA",OFFSET(A48,-1,0)+1,LARGE(A$3:A47,1)) -> 0 | B48: =IF(H48="UNIDADE CONSTRUTIVA",0,IF(H48="CÉLULA CONSTRUTIVA",OFFSET(B48,-1,0)+1,OFFSET(B48,-1,0))) -> 2 | C48: =IF(H48="CÉLULA CONSTRUTIVA",0,IF(H48="ETAPA",OFFSET(C48,-1,0)+1,OFFSET(C48,-1,0))) -> 1 | D48: =IF(H48="ETAPA",0,IF(H48="SUBETAPA",OFFSET(D48,-1,0)+1,OFFSET(D48,-1,0))) -> 2 | E48: =IF(H48="Subetapa",0,IF(H48="serviço",OFFSET(E48,-1,0)+1,OFFSET(E48,-1,0))) -> 3 | H48: SERVIÇO | I48: =IF(H48="Unidade Construtiva",TEXT(A48,"00"),IF(H48="Célula Construtiva",TEXT(B48,"00"),IF(H48="Etapa",CONCATENATE(TEXT(B48,"00"),".",TEXT(C48,"000")),IF(H48="Subetapa",CONCATENATE(TEXT(B48,"00"),".",TEXT(C48,"000"),".",TEXT(D48,"000")),IF(H48="Serviço",CONCATENATE(TEXT(B48,"00"),".",TEXT(C48,"000"),".",TEXT(D48,"000"),".",TEXT(E48,"000")),""))))) -> 02.001.002.003 | J48: Armação Aço CA-50, Diâmetro de 8,0mm para Supraestrutura, Corte e Dobra em Obra | K48: kg | L48: =Supraestrutura!D31 -> 941.9 | M48: =_xlfn.XLOOKUP($J48,CPU!$D$1:$D$2521,CPU!$H$1:$H$2521) -> 7.000055 | N48: =IF(H48="Serviço",M48*L48,IF(H48="CÉLULA CONSTRUTIVA",SUMIFS($N$8:$N$258,$B$8:$B$258,B48,$H$8:$H$258,"Serviço"),IF(H48="ETAPA",SUMIFS($N$8:$N$258,$B$8:$B$258,B48,$C$8:$C$258,C48,$H$8:$H$258,"Serviço"),IF(H48="SUBETAPA",SUMIFS($N$8:$N$258,$B$8:$B$258,B48,$C$8:$C$258,C48,$D$8:$D$258,D48,$H$8:$H$258,"Serviço"),0)))) -> 6593.3518 | O48: Quantidade disponibilizada pelo projetista | P48: Finalizado
A49: =IF($H49="UNIDADE CONSTRUTIVA",OFFSET(A49,-1,0)+1,LARGE(A$3:A48,1)) -> 0 | B49: =IF(H49="UNIDADE CONSTRUTIVA",0,IF(H49="CÉLULA CONSTRUTIVA",OFFSET(B49,-1,0)+1,OFFSET(B49,-1,0))) -> 2 | C49: =IF(H49="CÉLULA CONSTRUTIVA",0,IF(H49="ETAPA",OFFSET(C49,-1,0)+1,OFFSET(C49,-1,0))) -> 1 | D49: =IF(H49="ETAPA",0,IF(H49="SUBETAPA",OFFSET(D49,-1,0)+1,OFFSET(D49,-1,0))) -> 2 | E49: =IF(H49="Subetapa",0,IF(H49="serviço",OFFSET(E49,-1,0)+1,OFFSET(E49,-1,0))) -> 4 | H49: SERVIÇO | I49: =IF(H49="Unidade Construtiva",TEXT(A49,"00"),IF(H49="Célula Construtiva",TEXT(B49,"00"),IF(H49="Etapa",CONCATENATE(TEXT(B49,"00"),".",TEXT(C49,"000")),IF(H49="Subetapa",CONCATENATE(TEXT(B49,"00"),".",TEXT(C49,"000"),".",TEXT(D49,"000")),IF(H49="Serviço",CONCATENATE(TEXT(B49,"00"),".",TEXT(C49,"000"),".",TEXT(D49,"000"),".",TEXT(E49,"000")),""))))) -> 02.001.002.004 | J49: Armação Aço CA-50, Diâmetro de 10,0mm para Supraestrutura, Corte e Dobra em Obra | K49: kg | L49: =Supraestrutura!E31 -> 701.6 | M49: =_xlfn.XLOOKUP($J49,CPU!$D$1:$D$2521,CPU!$H$1:$H$2521) -> 6.692055 | N49: =IF(H49="Serviço",M49*L49,IF(H49="CÉLULA CONSTRUTIVA",SUMIFS($N$8:$N$258,$B$8:$B$258,B49,$H$8:$H$258,"Serviço"),IF(H49="ETAPA",SUMIFS($N$8:$N$258,$B$8:$B$258,B49,$C$8:$C$258,C49,$H$8:$H$258,"Serviço"),IF(H49="SUBETAPA",SUMIFS($N$8:$N$258,$B$8:$B$258,B49,$C$8:$C$258,C49,$D$8:$D$258,D49,$H$8:$H$258,"Serviço"),0)))) -> 4695.1458 | O49: Quantidade disponibilizada pelo projetista | P49: Finalizado
A50: =IF($H50="UNIDADE CONSTRUTIVA",OFFSET(A50,-1,0)+1,LARGE(A$3:A49,1)) -> 0 | B50: =IF(H50="UNIDADE CONSTRUTIVA",0,IF(H50="CÉLULA CONSTRUTIVA",OFFSET(B50,-1,0)+1,OFFSET(B50,-1,0))) -> 2 | C50: =IF(H50="CÉLULA CONSTRUTIVA",0,IF(H50="ETAPA",OFFSET(C50,-1,0)+1,OFFSET(C50,-1,0))) -> 1 | D50: =IF(H50="ETAPA",0,IF(H50="SUBETAPA",OFFSET(D50,-1,0)+1,OFFSET(D50,-1,0))) -> 2 | E50: =IF(H50="Subetapa",0,IF(H50="serviço",OFFSET(E50,-1,0)+1,OFFSET(E50,-1,0))) -> 5 | H50: SERVIÇO | I50: =IF(H50="Unidade Construtiva",TEXT(A50,"00"),IF(H50="Célula Construtiva",TEXT(B50,"00"),IF(H50="Etapa",CONCATENATE(TEXT(B50,"00"),".",TEXT(C50,"000")),IF(H50="Subetapa",CONCATENATE(TEXT(B50,"00"),".",TEXT(C50,"000"),".",TEXT(D50,"000")),IF(H50="Serviço",CONCATENATE(TEXT(B50,"00"),".",TEXT(C50,"000"),".",TEXT(D50,"000"),".",TEXT(E50,"000")),""))))) -> 02.001.002.005 | J50: Armação Aço CA-50, Diâmetro de 12,5mm para Supraestrutura, Corte e Dobra em Obra | K50: kg | L50: =Supraestrutura!F31 -> 879.5 | M50: =_xlfn.XLOOKUP($J50,CPU!$D$1:$D$2521,CPU!$H$1:$H$2521) -> 6.505055 | N50: =IF(H50="Serviço",M50*L50,IF(H50="CÉLULA CONSTRUTIVA",SUMIFS($N$8:$N$258,$B$8:$B$258,B50,$H$8:$H$258,"Serviço"),IF(H50="ETAPA",SUMIFS($N$8:$N$258,$B$8:$B$258,B50,$C$8:$C$258,C50,$H$8:$H$258,"Serviço"),IF(H50="SUBETAPA",SUMIFS($N$8:$N$258,$B$8:$B$258,B50,$C$8:$C$258,C50,$D$8:$D$258,D50,$H$8:$H$258,"Serviço"),0)))) -> 5721.1959 | O50: Quantidade disponibilizada pelo projetista | P50: Finalizado
A51: =IF($H51="UNIDADE CONSTRUTIVA",OFFSET(A51,-1,0)+1,LARGE(A$3:A50,1)) -> 0 | B51: =IF(H51="UNIDADE CONSTRUTIVA",0,IF(H51="CÉLULA CONSTRUTIVA",OFFSET(B51,-1,0)+1,OFFSET(B51,-1,0))) -> 2 | C51: =IF(H51="CÉLULA CONSTRUTIVA",0,IF(H51="ETAPA",OFFSET(C51,-1,0)+1,OFFSET(C51,-1,0))) -> 1 | D51: =IF(H51="ETAPA",0,IF(H51="SUBETAPA",OFFSET(D51,-1,0)+1,OFFSET(D51,-1,0))) -> 2 | E51: =IF(H51="Subetapa",0,IF(H51="serviço",OFFSET(E51,-1,0)+1,OFFSET(E51,-1,0))) -> 6 | H51: SERVIÇO | I51: =IF(H51="Unidade Construtiva",TEXT(A51,"00"),IF(H51="Célula Construtiva",TEXT(B51,"00"),IF(H51="Etapa",CONCATENATE(TEXT(B51,"00"),".",TEXT(C51,"000")),IF(H51="Subetapa",CONCATENATE(TEXT(B51,"00"),".",TEXT(C51,"000"),".",TEXT(D51,"000")),IF(H51="Serviço",CONCATENATE(TEXT(B51,"00"),".",TEXT(C51,"000"),".",TEXT(D51,"000"),".",TEXT(E51,"000")),""))))) -> 02.001.002.006 | J51: Armação Aço CA-50, Diâmetro de 16,0mm para Supraestrutura, Corte e Dobra em Obra | K51: kg | L51: =Supraestrutura!G31 -> 659.4 | M51: =_xlfn.XLOOKUP($J51,CPU!$D$1:$D$2521,CPU!$H$1:$H$2521) -> 6.505055 | N51: =IF(H51="Serviço",M51*L51,IF(H51="CÉLULA CONSTRUTIVA",SUMIFS($N$8:$N$258,$B$8:$B$258,B51,$H$8:$H$258,"Serviço"),IF(H51="ETAPA",SUMIFS($N$8:$N$258,$B$8:$B$258,B51,$C$8:$C$258,C51,$H$8:$H$258,"Serviço"),IF(H51="SUBETAPA",SUMIFS($N$8:$N$258,$B$8:$B$258,B51,$C$8:$C$258,C51,$D$8:$D$258,D51,$H$8:$H$258,"Serviço"),0)))) -> 4289.4333 | O51: Quantidade disponibilizada pelo projetista | P51: Finalizado
A52: =IF($H52="UNIDADE CONSTRUTIVA",OFFSET(A52,-1,0)+1,LARGE(A$3:A51,1)) -> 0 | B52: =IF(H52="UNIDADE CONSTRUTIVA",0,IF(H52="CÉLULA CONSTRUTIVA",OFFSET(B52,-1,0)+1,OFFSET(B52,-1,0))) -> 2 | C52: =IF(H52="CÉLULA CONSTRUTIVA",0,IF(H52="ETAPA",OFFSET(C52,-1,0)+1,OFFSET(C52,-1,0))) -> 1 | D52: =IF(H52="ETAPA",0,IF(H52="SUBETAPA",OFFSET(D52,-1,0)+1,OFFSET(D52,-1,0))) -> 2 | E52: =IF(H52="Subetapa",0,IF(H52="serviço",OFFSET(E52,-1,0)+1,OFFSET(E52,-1,0))) -> 7 | H52: SERVIÇO | I52: =IF(H52="Unidade Construtiva",TEXT(A52,"00"),IF(H52="Célula Construtiva",TEXT(B52,"00"),IF(H52="Etapa",CONCATENATE(TEXT(B52,"00"),".",TEXT(C52,"000")),IF(H52="Subetapa",CONCATENATE(TEXT(B52,"00"),".",TEXT(C52,"000"),".",TEXT(D52,"000")),IF(H52="Serviço",CONCATENATE(TEXT(B52,"00"),".",TEXT(C52,"000"),".",TEXT(D52,"000"),".",TEXT(E52,"000")),""))))) -> 02.001.002.007 | J52: Armação Malha Ø5,0 c/25, para ContraPiso Armado (corte e dobra em Obra) | K52: m2 | L52: =LAJE_TRELIÇADA!J8+LAJE_TRELIÇADA!J9+LAJE_TRELIÇADA!J10 -> 303.14 | M52: =_xlfn.XLOOKUP($J52,CPU!$D$1:$D$2521,CPU!$H$1:$H$2521) -> 37.756055 | N52: =IF(H52="Serviço",M52*L52,IF(H52="CÉLULA CONSTRUTIVA",SUMIFS($N$8:$N$258,$B$8:$B$258,B52,$H$8:$H$258,"Serviço"),IF(H52="ETAPA",SUMIFS($N$8:$N$258,$B$8:$B$258,B52,$C$8:$C$258,C52,$H$8:$H$258,"Serviço"),IF(H52="SUBETAPA",SUMIFS($N$8:$N$258,$B$8:$B$258,B52,$C$8:$C$258,C52,$D$8:$D$258,D52,$H$8:$H$258,"Serviço"),0)))) -> 11445.371 | O52: Quantidade de levantameto da Cartesian | P52: Finalizado
A53: =IF($H53="UNIDADE CONSTRUTIVA",OFFSET(A53,-1,0)+1,LARGE(A$3:A52,1)) -> 0 | B53: =IF(H53="UNIDADE CONSTRUTIVA",0,IF(H53="CÉLULA CONSTRUTIVA",OFFSET(B53,-1,0)+1,OFFSET(B53,-1,0))) -> 2 | C53: =IF(H53="CÉLULA CONSTRUTIVA",0,IF(H53="ETAPA",OFFSET(C53,-1,0)+1,OFFSET(C53,-1,0))) -> 1 | D53: =IF(H53="ETAPA",0,IF(H53="SUBETAPA",OFFSET(D53,-1,0)+1,OFFSET(D53,-1,0))) -> 3 | E53: =IF(H53="Subetapa",0,IF(H53="serviço",OFFSET(E53,-1,0)+1,OFFSET(E53,-1,0))) -> 0 | H53: SUBETAPA | I53: =IF(H53="Unidade Construtiva",TEXT(A53,"00"),IF(H53="Célula Construtiva",TEXT(B53,"00"),IF(H53="Etapa",CONCATENATE(TEXT(B53,"00"),".",TEXT(C53,"000")),IF(H53="Subetapa",CONCATENATE(TEXT(B53,"00"),".",TEXT(C53,"000"),".",TEXT(D53,"000")),IF(H53="Serviço",CONCATENATE(TEXT(B53,"00"),".",TEXT(C53,"000"),".",TEXT(D53,"000"),".",TEXT(E53,"000")),""))))) -> 02.001.003 | J53: Concreto | N53: =IF(H53="Serviço",M53*L53,IF(H53="CÉLULA CONSTRUTIVA",SUMIFS($N$8:$N$258,$B$8:$B$258,B53,$H$8:$H$258,"Serviço"),IF(H53="ETAPA",SUMIFS($N$8:$N$258,$B$8:$B$258,B53,$C$8:$C$258,C53,$H$8:$H$258,"Serviço"),IF(H53="SUBETAPA",SUMIFS($N$8:$N$258,$B$8:$B$258,B53,$C$8:$C$258,C53,$D$8:$D$258,D53,$H$8:$H$258,"Serviço"),0)))) -> 33735.688
A54: =IF($H54="UNIDADE CONSTRUTIVA",OFFSET(A54,-1,0)+1,LARGE(A$3:A53,1)) -> 0 | B54: =IF(H54="UNIDADE CONSTRUTIVA",0,IF(H54="CÉLULA CONSTRUTIVA",OFFSET(B54,-1,0)+1,OFFSET(B54,-1,0))) -> 2 | C54: =IF(H54="CÉLULA CONSTRUTIVA",0,IF(H54="ETAPA",OFFSET(C54,-1,0)+1,OFFSET(C54,-1,0))) -> 1 | D54: =IF(H54="ETAPA",0,IF(H54="SUBETAPA",OFFSET(D54,-1,0)+1,OFFSET(D54,-1,0))) -> 3 | E54: =IF(H54="Subetapa",0,IF(H54="serviço",OFFSET(E54,-1,0)+1,OFFSET(E54,-1,0))) -> 1 | H54: SERVIÇO | I54: =IF(H54="Unidade Construtiva",TEXT(A54,"00"),IF(H54="Célula Construtiva",TEXT(B54,"00"),IF(H54="Etapa",CONCATENATE(TEXT(B54,"00"),".",TEXT(C54,"000")),IF(H54="Subetapa",CONCATENATE(TEXT(B54,"00"),".",TEXT(C54,"000"),".",TEXT(D54,"000")),IF(H54="Serviço",CONCATENATE(TEXT(B54,"00"),".",TEXT(C54,"000"),".",TEXT(D54,"000"),".",TEXT(E54,"000")),""))))) -> 02.001.003.001 | J54: Concreto Usinado FCK = 30MPa Bombeavel Para Supraestrutura | K54: m3 | L54: =Supraestrutura!M31 -> 58.34 | M54: =_xlfn.XLOOKUP($J54,CPU!$D$1:$D$2521,CPU!$H$1:$H$2521) -> 578.26 | N54: =IF(H54="Serviço",M54*L54,IF(H54="CÉLULA CONSTRUTIVA",SUMIFS($N$8:$N$258,$B$8:$B$258,B54,$H$8:$H$258,"Serviço"),IF(H54="ETAPA",SUMIFS($N$8:$N$258,$B$8:$B$258,B54,$C$8:$C$258,C54,$H$8:$H$258,"Serviço"),IF(H54="SUBETAPA",SUMIFS($N$8:$N$258,$B$8:$B$258,B54,$C$8:$C$258,C54,$D$8:$D$258,D54,$H$8:$H$258,"Serviço"),0)))) -> 33735.688 | O54: Quantidade disponibilizada pelo projetista | P54: Finalizado
A55: =IF($H55="UNIDADE CONSTRUTIVA",OFFSET(A55,-1,0)+1,LARGE(A$3:A54,1)) -> 0 | B55: =IF(H55="UNIDADE CONSTRUTIVA",0,IF(H55="CÉLULA CONSTRUTIVA",OFFSET(B55,-1,0)+1,OFFSET(B55,-1,0))) -> 2 | C55: =IF(H55="CÉLULA CONSTRUTIVA",0,IF(H55="ETAPA",OFFSET(C55,-1,0)+1,OFFSET(C55,-1,0))) -> 1 | D55: =IF(H55="ETAPA",0,IF(H55="SUBETAPA",OFFSET(D55,-1,0)+1,OFFSET(D55,-1,0))) -> 4 | E55: =IF(H55="Subetapa",0,IF(H55="serviço",OFFSET(E55,-1,0)+1,OFFSET(E55,-1,0))) -> 0 | H55: SUBETAPA | I55: =IF(H55="Unidade Construtiva",TEXT(A55,"00"),IF(H55="Célula Construtiva",TEXT(B55,"00"),IF(H55="Etapa",CONCATENATE(TEXT(B55,"00"),".",TEXT(C55,"000")),IF(H55="Subetapa",CONCATENATE(TEXT(B55,"00"),".",TEXT(C55,"000"),".",TEXT(D55,"000")),IF(H55="Serviço",CONCATENATE(TEXT(B55,"00"),".",TEXT(C55,"000"),".",TEXT(D55,"000"),".",TEXT(E55,"000")),""))))) -> 02.001.004 | J55: Complementares | N55: =IF(H55="Serviço",M55*L55,IF(H55="CÉLULA CONSTRUTIVA",SUMIFS($N$8:$N$258,$B$8:$B$258,B55,$H$8:$H$258,"Serviço"),IF(H55="ETAPA",SUMIFS($N$8:$N$258,$B$8:$B$258,B55,$C$8:$C$258,C55,$H$8:$H$258,"Serviço"),IF(H55="SUBETAPA",SUMIFS($N$8:$N$258,$B$8:$B$258,B55,$C$8:$C$258,C55,$D$8:$D$258,D55,$H$8:$H$258,"Serviço"),0)))) -> 14259.96
A56: =IF($H56="UNIDADE CONSTRUTIVA",OFFSET(A56,-1,0)+1,LARGE(A$3:A55,1)) -> 0 | B56: =IF(H56="UNIDADE CONSTRUTIVA",0,IF(H56="CÉLULA CONSTRUTIVA",OFFSET(B56,-1,0)+1,OFFSET(B56,-1,0))) -> 2 | C56: =IF(H56="CÉLULA CONSTRUTIVA",0,IF(H56="ETAPA",OFFSET(C56,-1,0)+1,OFFSET(C56,-1,0))) -> 1 | D56: =IF(H56="ETAPA",0,IF(H56="SUBETAPA",OFFSET(D56,-1,0)+1,OFFSET(D56,-1,0))) -> 4 | E56: =IF(H56="Subetapa",0,IF(H56="serviço",OFFSET(E56,-1,0)+1,OFFSET(E56,-1,0))) -> 1 | H56: SERVIÇO | I56: =IF(H56="Unidade Construtiva",TEXT(A56,"00"),IF(H56="Célula Construtiva",TEXT(B56,"00"),IF(H56="Etapa",CONCATENATE(TEXT(B56,"00"),".",TEXT(C56,"000")),IF(H56="Subetapa",CONCATENATE(TEXT(B56,"00"),".",TEXT(C56,"000"),".",TEXT(D56,"000")),IF(H56="Serviço",CONCATENATE(TEXT(B56,"00"),".",TEXT(C56,"000"),".",TEXT(D56,"000"),".",TEXT(E56,"000")),""))))) -> 02.001.004.001 | J56: Locação de escoramento metálico pe direito simples | K56: m2 | L56: =LAJE_TRELIÇADA!K12 -> 365.64 | M56: =_xlfn.XLOOKUP($J56,CPU!$D$1:$D$2521,CPU!$H$1:$H$2521) -> 39 | N56: =IF(H56="Serviço",M56*L56,IF(H56="CÉLULA CONSTRUTIVA",SUMIFS($N$8:$N$258,$B$8:$B$258,B56,$H$8:$H$258,"Serviço"),IF(H56="ETAPA",SUMIFS($N$8:$N$258,$B$8:$B$258,B56,$C$8:$C$258,C56,$H$8:$H$258,"Serviço"),IF(H56="SUBETAPA",SUMIFS($N$8:$N$258,$B$8:$B$258,B56,$C$8:$C$258,C56,$D$8:$D$258,D56,$H$8:$H$258,"Serviço"),0)))) -> 14259.96 | O56: Estimado devido a ausência de projeto | P56: Finalizado
A57: =IF($H57="UNIDADE CONSTRUTIVA",OFFSET(A57,-1,0)+1,LARGE(A$3:A56,1)) -> 0 | B57: =IF(H57="UNIDADE CONSTRUTIVA",0,IF(H57="CÉLULA CONSTRUTIVA",OFFSET(B57,-1,0)+1,OFFSET(B57,-1,0))) -> 2 | C57: =IF(H57="CÉLULA CONSTRUTIVA",0,IF(H57="ETAPA",OFFSET(C57,-1,0)+1,OFFSET(C57,-1,0))) -> 1 | D57: =IF(H57="ETAPA",0,IF(H57="SUBETAPA",OFFSET(D57,-1,0)+1,OFFSET(D57,-1,0))) -> 5 | E57: =IF(H57="Subetapa",0,IF(H57="serviço",OFFSET(E57,-1,0)+1,OFFSET(E57,-1,0))) -> 0 | H57: SUBETAPA | I57: =IF(H57="Unidade Construtiva",TEXT(A57,"00"),IF(H57="Célula Construtiva",TEXT(B57,"00"),IF(H57="Etapa",CONCATENATE(TEXT(B57,"00"),".",TEXT(C57,"000")),IF(H57="Subetapa",CONCATENATE(TEXT(B57,"00"),".",TEXT(C57,"000"),".",TEXT(D57,"000")),IF(H57="Serviço",CONCATENATE(TEXT(B57,"00"),".",TEXT(C57,"000"),".",TEXT(D57,"000"),".",TEXT(E57,"000")),""))))) -> 02.001.005 | J57: Mão de obra | N57: =IF(H57="Serviço",M57*L57,IF(H57="CÉLULA CONSTRUTIVA",SUMIFS($N$8:$N$258,$B$8:$B$258,B57,$H$8:$H$258,"Serviço"),IF(H57="ETAPA",SUMIFS($N$8:$N$258,$B$8:$B$258,B57,$C$8:$C$258,C57,$H$8:$H$258,"Serviço"),IF(H57="SUBETAPA",SUMIFS($N$8:$N$258,$B$8:$B$258,B57,$C$8:$C$258,C57,$D$8:$D$258,D57,$H$8:$H$258,"Serviço"),0)))) -> 37921
A58: =IF($H58="UNIDADE CONSTRUTIVA",OFFSET(A58,-1,0)+1,LARGE(A$3:A57,1)) -> 0 | B58: =IF(H58="UNIDADE CONSTRUTIVA",0,IF(H58="CÉLULA CONSTRUTIVA",OFFSET(B58,-1,0)+1,OFFSET(B58,-1,0))) -> 2 | C58: =IF(H58="CÉLULA CONSTRUTIVA",0,IF(H58="ETAPA",OFFSET(C58,-1,0)+1,OFFSET(C58,-1,0))) -> 1 | D58: =IF(H58="ETAPA",0,IF(H58="SUBETAPA",OFFSET(D58,-1,0)+1,OFFSET(D58,-1,0))) -> 5 | E58: =IF(H58="Subetapa",0,IF(H58="serviço",OFFSET(E58,-1,0)+1,OFFSET(E58,-1,0))) -> 1 | H58: SERVIÇO | I58: =IF(H58="Unidade Construtiva",TEXT(A58,"00"),IF(H58="Célula Construtiva",TEXT(B58,"00"),IF(H58="Etapa",CONCATENATE(TEXT(B58,"00"),".",TEXT(C58,"000")),IF(H58="Subetapa",CONCATENATE(TEXT(B58,"00"),".",TEXT(C58,"000"),".",TEXT(D58,"000")),IF(H58="Serviço",CONCATENATE(TEXT(B58,"00"),".",TEXT(C58,"000"),".",TEXT(D58,"000"),".",TEXT(E58,"000")),""))))) -> 02.001.005.001 | J58: Mão de obra para execução de supraestrutura de concreto armado | K58: m3 | L58: =L54 -> 58.34 | M58: 650 | N58: =IF(H58="Serviço",M58*L58,IF(H58="CÉLULA CONSTRUTIVA",SUMIFS($N$8:$N$258,$B$8:$B$258,B58,$H$8:$H$258,"Serviço"),IF(H58="ETAPA",SUMIFS($N$8:$N$258,$B$8:$B$258,B58,$C$8:$C$258,C58,$H$8:$H$258,"Serviço"),IF(H58="SUBETAPA",SUMIFS($N$8:$N$258,$B$8:$B$258,B58,$C$8:$C$258,C58,$D$8:$D$258,D58,$H$8:$H$258,"Serviço"),0)))) -> 37921 | P58: Finalizado
A59: =IF($H59="UNIDADE CONSTRUTIVA",OFFSET(A59,-1,0)+1,LARGE(A$3:A58,1)) -> 0 | B59: =IF(H59="UNIDADE CONSTRUTIVA",0,IF(H59="CÉLULA CONSTRUTIVA",OFFSET(B59,-1,0)+1,OFFSET(B59,-1,0))) -> 3 | C59: =IF(H59="CÉLULA CONSTRUTIVA",0,IF(H59="ETAPA",OFFSET(C59,-1,0)+1,OFFSET(C59,-1,0))) -> 0 | D59: =IF(H59="ETAPA",0,IF(H59="SUBETAPA",OFFSET(D59,-1,0)+1,OFFSET(D59,-1,0))) -> 5 | E59: =IF(H59="Subetapa",0,IF(H59="serviço",OFFSET(E59,-1,0)+1,OFFSET(E59,-1,0))) -> 1 | H59: CÉLULA CONSTRUTIVA | I59: =IF(H59="Unidade Construtiva",TEXT(A59,"00"),IF(H59="Célula Construtiva",TEXT(B59,"00"),IF(H59="Etapa",CONCATENATE(TEXT(B59,"00"),".",TEXT(C59,"000")),IF(H59="Subetapa",CONCATENATE(TEXT(B59,"00"),".",TEXT(C59,"000"),".",TEXT(D59,"000")),IF(H59="Serviço",CONCATENATE(TEXT(B59,"00"),".",TEXT(C59,"000"),".",TEXT(D59,"000"),".",TEXT(E59,"000")),""))))) -> 03 | J59: ALVENARIA, VEDAÇÕES E DIVISÓRIAS | N59: =IF(H59="Serviço",M59*L59,IF(H59="CÉLULA CONSTRUTIVA",SUMIFS($N$8:$N$258,$B$8:$B$258,B59,$H$8:$H$258,"Serviço"),IF(H59="ETAPA",SUMIFS($N$8:$N$258,$B$8:$B$258,B59,$C$8:$C$258,C59,$H$8:$H$258,"Serviço"),IF(H59="SUBETAPA",SUMIFS($N$8:$N$258,$B$8:$B$258,B59,$C$8:$C$258,C59,$D$8:$D$258,D59,$H$8:$H$258,"Serviço"),0)))) -> 60429.042 | O59: =N59/'Obra '!E$9 -> 183.35723
A60: =IF($H60="UNIDADE CONSTRUTIVA",OFFSET(A60,-1,0)+1,LARGE(A$3:A59,1)) -> 0 | B60: =IF(H60="UNIDADE CONSTRUTIVA",0,IF(H60="CÉLULA CONSTRUTIVA",OFFSET(B60,-1,0)+1,OFFSET(B60,-1,0))) -> 3 | C60: =IF(H60="CÉLULA CONSTRUTIVA",0,IF(H60="ETAPA",OFFSET(C60,-1,0)+1,OFFSET(C60,-1,0))) -> 1 | D60: =IF(H60="ETAPA",0,IF(H60="SUBETAPA",OFFSET(D60,-1,0)+1,OFFSET(D60,-1,0))) -> 0 | E60: =IF(H60="Subetapa",0,IF(H60="serviço",OFFSET(E60,-1,0)+1,OFFSET(E60,-1,0))) -> 1 | H60: ETAPA | I60: =IF(H60="Unidade Construtiva",TEXT(A60,"00"),IF(H60="Célula Construtiva",TEXT(B60,"00"),IF(H60="Etapa",CONCATENATE(TEXT(B60,"00"),".",TEXT(C60,"000")),IF(H60="Subetapa",CONCATENATE(TEXT(B60,"00"),".",TEXT(C60,"000"),".",TEXT(D60,"000")),IF(H60="Serviço",CONCATENATE(TEXT(B60,"00"),".",TEXT(C60,"000"),".",TEXT(D60,"000"),".",TEXT(E60,"000")),""))))) -> 03.001 | J60: ALVENARIA, VEDAÇÕES E DIVISÓRIAS | N60: =IF(H60="Serviço",M60*L60,IF(H60="CÉLULA CONSTRUTIVA",SUMIFS($N$8:$N$258,$B$8:$B$258,B60,$H$8:$H$258,"Serviço"),IF(H60="ETAPA",SUMIFS($N$8:$N$258,$B$8:$B$258,B60,$C$8:$C$258,C60,$H$8:$H$258,"Serviço"),IF(H60="SUBETAPA",SUMIFS($N$8:$N$258,$B$8:$B$258,B60,$C$8:$C$258,C60,$D$8:$D$258,D60,$H$8:$H$258,"Serviço"),0)))) -> 60429.042
A61: =IF($H61="UNIDADE CONSTRUTIVA",OFFSET(A61,-1,0)+1,LARGE(A$3:A60,1)) -> 0 | B61: =IF(H61="UNIDADE CONSTRUTIVA",0,IF(H61="CÉLULA CONSTRUTIVA",OFFSET(B61,-1,0)+1,OFFSET(B61,-1,0))) -> 3 | C61: =IF(H61="CÉLULA CONSTRUTIVA",0,IF(H61="ETAPA",OFFSET(C61,-1,0)+1,OFFSET(C61,-1,0))) -> 1 | D61: =IF(H61="ETAPA",0,IF(H61="SUBETAPA",OFFSET(D61,-1,0)+1,OFFSET(D61,-1,0))) -> 1 | E61: =IF(H61="Subetapa",0,IF(H61="serviço",OFFSET(E61,-1,0)+1,OFFSET(E61,-1,0))) -> 0 | H61: SUBETAPA | I61: =IF(H61="Unidade Construtiva",TEXT(A61,"00"),IF(H61="Célula Construtiva",TEXT(B61,"00"),IF(H61="Etapa",CONCATENATE(TEXT(B61,"00"),".",TEXT(C61,"000")),IF(H61="Subetapa",CONCATENATE(TEXT(B61,"00"),".",TEXT(C61,"000"),".",TEXT(D61,"000")),IF(H61="Serviço",CONCATENATE(TEXT(B61,"00"),".",TEXT(C61,"000"),".",TEXT(D61,"000"),".",TEXT(E61,"000")),""))))) -> 03.001.001 | J61: Alvenaria de vedação com blocos cerâmicos | N61: =IF(H61="Serviço",M61*L61,IF(H61="CÉLULA CONSTRUTIVA",SUMIFS($N$8:$N$258,$B$8:$B$258,B61,$H$8:$H$258,"Serviço"),IF(H61="ETAPA",SUMIFS($N$8:$N$258,$B$8:$B$258,B61,$C$8:$C$258,C61,$H$8:$H$258,"Serviço"),IF(H61="SUBETAPA",SUMIFS($N$8:$N$258,$B$8:$B$258,B61,$C$8:$C$258,C61,$D$8:$D$258,D61,$H$8:$H$258,"Serviço"),0)))) -> 26665.198
A62: =IF($H62="UNIDADE CONSTRUTIVA",OFFSET(A62,-1,0)+1,LARGE(A$3:A61,1)) -> 0 | B62: =IF(H62="UNIDADE CONSTRUTIVA",0,IF(H62="CÉLULA CONSTRUTIVA",OFFSET(B62,-1,0)+1,OFFSET(B62,-1,0))) -> 3 | C62: =IF(H62="CÉLULA CONSTRUTIVA",0,IF(H62="ETAPA",OFFSET(C62,-1,0)+1,OFFSET(C62,-1,0))) -> 1 | D62: =IF(H62="ETAPA",0,IF(H62="SUBETAPA",OFFSET(D62,-1,0)+1,OFFSET(D62,-1,0))) -> 1 | E62: =IF(H62="Subetapa",0,IF(H62="serviço",OFFSET(E62,-1,0)+1,OFFSET(E62,-1,0))) -> 1 | H62: SERVIÇO | I62: =IF(H62="Unidade Construtiva",TEXT(A62,"00"),IF(H62="Célula Construtiva",TEXT(B62,"00"),IF(H62="Etapa",CONCATENATE(TEXT(B62,"00"),".",TEXT(C62,"000")),IF(H62="Subetapa",CONCATENATE(TEXT(B62,"00"),".",TEXT(C62,"000"),".",TEXT(D62,"000")),IF(H62="Serviço",CONCATENATE(TEXT(B62,"00"),".",TEXT(C62,"000"),".",TEXT(D62,"000"),".",TEXT(E62,"000")),""))))) -> 03.001.001.001 | J62: Alvenaria de vedacao de blocos ceramicos furados na horizontal de 9x19x19cm (espessura 9cm) com argamassa industrializada de assentamento | K62: m2 | L62: =ARQUITETURA!D17+ARQUITETURA!D21 -> 22.85 | M62: =_xlfn.XLOOKUP($J62,CPU!$D$1:$D$2521,CPU!$H$1:$H$2521) -> 32.02 | N62: =IF(H62="Serviço",M62*L62,IF(H62="CÉLULA CONSTRUTIVA",SUMIFS($N$8:$N$258,$B$8:$B$258,B62,$H$8:$H$258,"Serviço"),IF(H62="ETAPA",SUMIFS($N$8:$N$258,$B$8:$B$258,B62,$C$8:$C$258,C62,$H$8:$H$258,"Serviço"),IF(H62="SUBETAPA",SUMIFS($N$8:$N$258,$B$8:$B$258,B62,$C$8:$C$258,C62,$D$8:$D$258,D62,$H$8:$H$258,"Serviço"),0)))) -> 731.657 | P62: Finalizado
A63: =IF($H63="UNIDADE CONSTRUTIVA",OFFSET(A63,-1,0)+1,LARGE(A$3:A62,1)) -> 0 | B63: =IF(H63="UNIDADE CONSTRUTIVA",0,IF(H63="CÉLULA CONSTRUTIVA",OFFSET(B63,-1,0)+1,OFFSET(B63,-1,0))) -> 3 | C63: =IF(H63="CÉLULA CONSTRUTIVA",0,IF(H63="ETAPA",OFFSET(C63,-1,0)+1,OFFSET(C63,-1,0))) -> 1 | D63: =IF(H63="ETAPA",0,IF(H63="SUBETAPA",OFFSET(D63,-1,0)+1,OFFSET(D63,-1,0))) -> 1 | E63: =IF(H63="Subetapa",0,IF(H63="serviço",OFFSET(E63,-1,0)+1,OFFSET(E63,-1,0))) -> 2 | H63: SERVIÇO | I63: =IF(H63="Unidade Construtiva",TEXT(A63,"00"),IF(H63="Célula Construtiva",TEXT(B63,"00"),IF(H63="Etapa",CONCATENATE(TEXT(B63,"00"),".",TEXT(C63,"000")),IF(H63="Subetapa",CONCATENATE(TEXT(B63,"00"),".",TEXT(C63,"000"),".",TEXT(D63,"000")),IF(H63="Serviço",CONCATENATE(TEXT(B63,"00"),".",TEXT(C63,"000"),".",TEXT(D63,"000"),".",TEXT(E63,"000")),""))))) -> 03.001.001.002 | J63: Alvenaria de vedacao de blocos ceramicos furados na horizontal de 11.5x19x19cm (espessura 11.5cm) com argamassa industrializada de assentamento | K63: m2 | L63: =ARQUITETURA!D14 -> 4.06 | M63: =_xlfn.XLOOKUP($J63,CPU!$D$1:$D$2521,CPU!$H$1:$H$2521) -> 34.82 | N63: =IF(H63="Serviço",M63*L63,IF(H63="CÉLULA CONSTRUTIVA",SUMIFS($N$8:$N$258,$B$8:$B$258,B63,$H$8:$H$258,"Serviço"),IF(H63="ETAPA",SUMIFS($N$8:$N$258,$B$8:$B$258,B63,$C$8:$C$258,C63,$H$8:$H$258,"Serviço"),IF(H63="SUBETAPA",SUMIFS($N$8:$N$258,$B$8:$B$258,B63,$C$8:$C$258,C63,$D$8:$D$258,D63,$H$8:$H$258,"Serviço"),0)))) -> 141.3692 | P63: Finalizado
A64: =IF($H64="UNIDADE CONSTRUTIVA",OFFSET(A64,-1,0)+1,LARGE(A$3:A63,1)) -> 0 | B64: =IF(H64="UNIDADE CONSTRUTIVA",0,IF(H64="CÉLULA CONSTRUTIVA",OFFSET(B64,-1,0)+1,OFFSET(B64,-1,0))) -> 3 | C64: =IF(H64="CÉLULA CONSTRUTIVA",0,IF(H64="ETAPA",OFFSET(C64,-1,0)+1,OFFSET(C64,-1,0))) -> 1 | D64: =IF(H64="ETAPA",0,IF(H64="SUBETAPA",OFFSET(D64,-1,0)+1,OFFSET(D64,-1,0))) -> 1 | E64: =IF(H64="Subetapa",0,IF(H64="serviço",OFFSET(E64,-1,0)+1,OFFSET(E64,-1,0))) -> 3 | H64: SERVIÇO | I64: =IF(H64="Unidade Construtiva",TEXT(A64,"00"),IF(H64="Célula Construtiva",TEXT(B64,"00"),IF(H64="Etapa",CONCATENATE(TEXT(B64,"00"),".",TEXT(C64,"000")),IF(H64="Subetapa",CONCATENATE(TEXT(B64,"00"),".",TEXT(C64,"000"),".",TEXT(D64,"000")),IF(H64="Serviço",CONCATENATE(TEXT(B64,"00"),".",TEXT(C64,"000"),".",TEXT(D64,"000"),".",TEXT(E64,"000")),""))))) -> 03.001.001.003 | J64: Alvenaria de vedacao de blocos ceramicos furados na horizontal de 14x19x19cm (espessura 14cm) com argamassa industrializada de assentamento | K64: m2 | L64: =ARQUITETURA!D15+ARQUITETURA!D19+ARQUITETURA!D23 -> 546.01 | M64: =_xlfn.XLOOKUP($J64,CPU!$D$1:$D$2521,CPU!$H$1:$H$2521) -> 45.46 | N64: =IF(H64="Serviço",M64*L64,IF(H64="CÉLULA CONSTRUTIVA",SUMIFS($N$8:$N$258,$B$8:$B$258,B64,$H$8:$H$258,"Serviço"),IF(H64="ETAPA",SUMIFS($N$8:$N$258,$B$8:$B$258,B64,$C$8:$C$258,C64,$H$8:$H$258,"Serviço"),IF(H64="SUBETAPA",SUMIFS($N$8:$N$258,$B$8:$B$258,B64,$C$8:$C$258,C64,$D$8:$D$258,D64,$H$8:$H$258,"Serviço"),0)))) -> 24821.615 | P64: Finalizado
A65: =IF($H65="UNIDADE CONSTRUTIVA",OFFSET(A65,-1,0)+1,LARGE(A$3:A64,1)) -> 0 | B65: =IF(H65="UNIDADE CONSTRUTIVA",0,IF(H65="CÉLULA CONSTRUTIVA",OFFSET(B65,-1,0)+1,OFFSET(B65,-1,0))) -> 3 | C65: =IF(H65="CÉLULA CONSTRUTIVA",0,IF(H65="ETAPA",OFFSET(C65,-1,0)+1,OFFSET(C65,-1,0))) -> 1 | D65: =IF(H65="ETAPA",0,IF(H65="SUBETAPA",OFFSET(D65,-1,0)+1,OFFSET(D65,-1,0))) -> 1 | E65: =IF(H65="Subetapa",0,IF(H65="serviço",OFFSET(E65,-1,0)+1,OFFSET(E65,-1,0))) -> 4 | H65: SERVIÇO | I65: =IF(H65="Unidade Construtiva",TEXT(A65,"00"),IF(H65="Célula Construtiva",TEXT(B65,"00"),IF(H65="Etapa",CONCATENATE(TEXT(B65,"00"),".",TEXT(C65,"000")),IF(H65="Subetapa",CONCATENATE(TEXT(B65,"00"),".",TEXT(C65,"000"),".",TEXT(D65,"000")),IF(H65="Serviço",CONCATENATE(TEXT(B65,"00"),".",TEXT(C65,"000"),".",TEXT(D65,"000"),".",TEXT(E65,"000")),""))))) -> 03.001.001.004 | J65: Alvenaria de vedacao de blocos ceramicos furados na horizontal de 19x19x19cm (espessura 19cm) com argamassa industrializada de assentamento | K65: m2 | L65: =ARQUITETURA!D16+ARQUITETURA!D20 -> 18.02 | M65: =_xlfn.XLOOKUP($J65,CPU!$D$1:$D$2521,CPU!$H$1:$H$2521) -> 53.86 | N65: =IF(H65="Serviço",M65*L65,IF(H65="CÉLULA CONSTRUTIVA",SUMIFS($N$8:$N$258,$B$8:$B$258,B65,$H$8:$H$258,"Serviço"),IF(H65="ETAPA",SUMIFS($N$8:$N$258,$B$8:$B$258,B65,$C$8:$C$258,C65,$H$8:$H$258,"Serviço"),IF(H65="SUBETAPA",SUMIFS($N$8:$N$258,$B$8:$B$258,B65,$C$8:$C$258,C65,$D$8:$D$258,D65,$H$8:$H$258,"Serviço"),0)))) -> 970.5572 | P65: Finalizado
A66: =IF($H66="UNIDADE CONSTRUTIVA",OFFSET(A66,-1,0)+1,LARGE(A$3:A65,1)) -> 0 | B66: =IF(H66="UNIDADE CONSTRUTIVA",0,IF(H66="CÉLULA CONSTRUTIVA",OFFSET(B66,-1,0)+1,OFFSET(B66,-1,0))) -> 3 | C66: =IF(H66="CÉLULA CONSTRUTIVA",0,IF(H66="ETAPA",OFFSET(C66,-1,0)+1,OFFSET(C66,-1,0))) -> 1 | D66: =IF(H66="ETAPA",0,IF(H66="SUBETAPA",OFFSET(D66,-1,0)+1,OFFSET(D66,-1,0))) -> 2 | E66: =IF(H66="Subetapa",0,IF(H66="serviço",OFFSET(E66,-1,0)+1,OFFSET(E66,-1,0))) -> 0 | H66: SUBETAPA | I66: =IF(H66="Unidade Construtiva",TEXT(A66,"00"),IF(H66="Célula Construtiva",TEXT(B66,"00"),IF(H66="Etapa",CONCATENATE(TEXT(B66,"00"),".",TEXT(C66,"000")),IF(H66="Subetapa",CONCATENATE(TEXT(B66,"00"),".",TEXT(C66,"000"),".",TEXT(D66,"000")),IF(H66="Serviço",CONCATENATE(TEXT(B66,"00"),".",TEXT(C66,"000"),".",TEXT(D66,"000"),".",TEXT(E66,"000")),""))))) -> 03.001.002 | J66: Alvenaria de vedação com blocos de concreto | N66: =IF(H66="Serviço",M66*L66,IF(H66="CÉLULA CONSTRUTIVA",SUMIFS($N$8:$N$258,$B$8:$B$258,B66,$H$8:$H$258,"Serviço"),IF(H66="ETAPA",SUMIFS($N$8:$N$258,$B$8:$B$258,B66,$C$8:$C$258,C66,$H$8:$H$258,"Serviço"),IF(H66="SUBETAPA",SUMIFS($N$8:$N$258,$B$8:$B$258,B66,$C$8:$C$258,C66,$D$8:$D$258,D66,$H$8:$H$258,"Serviço"),0)))) -> 962.63837
A67: =IF($H67="UNIDADE CONSTRUTIVA",OFFSET(A67,-1,0)+1,LARGE(A$3:A66,1)) -> 0 | B67: =IF(H67="UNIDADE CONSTRUTIVA",0,IF(H67="CÉLULA CONSTRUTIVA",OFFSET(B67,-1,0)+1,OFFSET(B67,-1,0))) -> 3 | C67: =IF(H67="CÉLULA CONSTRUTIVA",0,IF(H67="ETAPA",OFFSET(C67,-1,0)+1,OFFSET(C67,-1,0))) -> 1 | D67: =IF(H67="ETAPA",0,IF(H67="SUBETAPA",OFFSET(D67,-1,0)+1,OFFSET(D67,-1,0))) -> 2 | E67: =IF(H67="Subetapa",0,IF(H67="serviço",OFFSET(E67,-1,0)+1,OFFSET(E67,-1,0))) -> 1 | H67: SERVIÇO | I67: =IF(H67="Unidade Construtiva",TEXT(A67,"00"),IF(H67="Célula Construtiva",TEXT(B67,"00"),IF(H67="Etapa",CONCATENATE(TEXT(B67,"00"),".",TEXT(C67,"000")),IF(H67="Subetapa",CONCATENATE(TEXT(B67,"00"),".",TEXT(C67,"000"),".",TEXT(D67,"000")),IF(H67="Serviço",CONCATENATE(TEXT(B67,"00"),".",TEXT(C67,"000"),".",TEXT(D67,"000"),".",TEXT(E67,"000")),""))))) -> 03.001.002.001 | J67: Tijolo refratário para churrasqueiras 2,5x11,5x23cm com argamassa | K67: m2 | L67: ='Tijolos refratários'!J10 -> 3.995 | M67: =_xlfn.XLOOKUP($J67,CPU!$D$1:$D$2521,CPU!$H$1:$H$2521) -> 226.12625 | N67: =IF(H67="Serviço",M67*L67,IF(H67="CÉLULA CONSTRUTIVA",SUMIFS($N$8:$N$258,$B$8:$B$258,B67,$H$8:$H$258,"Serviço"),IF(H67="ETAPA",SUMIFS($N$8:$N$258,$B$8:$B$258,B67,$C$8:$C$258,C67,$H$8:$H$258,"Serviço"),IF(H67="SUBETAPA",SUMIFS($N$8:$N$258,$B$8:$B$258,B67,$C$8:$C$258,C67,$D$8:$D$258,D67,$H$8:$H$258,"Serviço"),0)))) -> 903.37437 | P67: Finalizado
A68: =IF($H68="UNIDADE CONSTRUTIVA",OFFSET(A68,-1,0)+1,LARGE(A$3:A67,1)) -> 0 | B68: =IF(H68="UNIDADE CONSTRUTIVA",0,IF(H68="CÉLULA CONSTRUTIVA",OFFSET(B68,-1,0)+1,OFFSET(B68,-1,0))) -> 3 | C68: =IF(H68="CÉLULA CONSTRUTIVA",0,IF(H68="ETAPA",OFFSET(C68,-1,0)+1,OFFSET(C68,-1,0))) -> 1 | D68: =IF(H68="ETAPA",0,IF(H68="SUBETAPA",OFFSET(D68,-1,0)+1,OFFSET(D68,-1,0))) -> 2 | E68: =IF(H68="Subetapa",0,IF(H68="serviço",OFFSET(E68,-1,0)+1,OFFSET(E68,-1,0))) -> 2 | H68: SERVIÇO | I68: =IF(H68="Unidade Construtiva",TEXT(A68,"00"),IF(H68="Célula Construtiva",TEXT(B68,"00"),IF(H68="Etapa",CONCATENATE(TEXT(B68,"00"),".",TEXT(C68,"000")),IF(H68="Subetapa",CONCATENATE(TEXT(B68,"00"),".",TEXT(C68,"000"),".",TEXT(D68,"000")),IF(H68="Serviço",CONCATENATE(TEXT(B68,"00"),".",TEXT(C68,"000"),".",TEXT(D68,"000"),".",TEXT(E68,"000")),""))))) -> 03.001.002.002 | J68: Alvenaria de vedação de blocos de concreto de 09x19x39cm, com argamassa estabilizada | K68: m2 | L68: =ARQUITETURA!D26 -> 1.28 | M68: =_xlfn.XLOOKUP($J68,CPU!$D$1:$D$2521,CPU!$H$1:$H$2521) -> 46.3 | N68: =IF(H68="Serviço",M68*L68,IF(H68="CÉLULA CONSTRUTIVA",SUMIFS($N$8:$N$258,$B$8:$B$258,B68,$H$8:$H$258,"Serviço"),IF(H68="ETAPA",SUMIFS($N$8:$N$258,$B$8:$B$258,B68,$C$8:$C$258,C68,$H$8:$H$258,"Serviço"),IF(H68="SUBETAPA",SUMIFS($N$8:$N$258,$B$8:$B$258,B68,$C$8:$C$258,C68,$D$8:$D$258,D68,$H$8:$H$258,"Serviço"),0)))) -> 59.264 | P68: Finalizado
A69: =IF($H69="UNIDADE CONSTRUTIVA",OFFSET(A69,-1,0)+1,LARGE(A$3:A68,1)) -> 0 | B69: =IF(H69="UNIDADE CONSTRUTIVA",0,IF(H69="CÉLULA CONSTRUTIVA",OFFSET(B69,-1,0)+1,OFFSET(B69,-1,0))) -> 3 | C69: =IF(H69="CÉLULA CONSTRUTIVA",0,IF(H69="ETAPA",OFFSET(C69,-1,0)+1,OFFSET(C69,-1,0))) -> 1 | D69: =IF(H69="ETAPA",0,IF(H69="SUBETAPA",OFFSET(D69,-1,0)+1,OFFSET(D69,-1,0))) -> 3 | E69: =IF(H69="Subetapa",0,IF(H69="serviço",OFFSET(E69,-1,0)+1,OFFSET(E69,-1,0))) -> 0 | H69: SUBETAPA | I69: =IF(H69="Unidade Construtiva",TEXT(A69,"00"),IF(H69="Célula Construtiva",TEXT(B69,"00"),IF(H69="Etapa",CONCATENATE(TEXT(B69,"00"),".",TEXT(C69,"000")),IF(H69="Subetapa",CONCATENATE(TEXT(B69,"00"),".",TEXT(C69,"000"),".",TEXT(D69,"000")),IF(H69="Serviço",CONCATENATE(TEXT(B69,"00"),".",TEXT(C69,"000"),".",TEXT(D69,"000"),".",TEXT(E69,"000")),""))))) -> 03.001.003 | J69: Serviços complementares para alvenaria de vedação | N69: =IF(H69="Serviço",M69*L69,IF(H69="CÉLULA CONSTRUTIVA",SUMIFS($N$8:$N$258,$B$8:$B$258,B69,$H$8:$H$258,"Serviço"),IF(H69="ETAPA",SUMIFS($N$8:$N$258,$B$8:$B$258,B69,$C$8:$C$258,C69,$H$8:$H$258,"Serviço"),IF(H69="SUBETAPA",SUMIFS($N$8:$N$258,$B$8:$B$258,B69,$C$8:$C$258,C69,$D$8:$D$258,D69,$H$8:$H$258,"Serviço"),0)))) -> 11873.756
A70: =IF($H70="UNIDADE CONSTRUTIVA",OFFSET(A70,-1,0)+1,LARGE(A$3:A69,1)) -> 0 | B70: =IF(H70="UNIDADE CONSTRUTIVA",0,IF(H70="CÉLULA CONSTRUTIVA",OFFSET(B70,-1,0)+1,OFFSET(B70,-1,0))) -> 3 | C70: =IF(H70="CÉLULA CONSTRUTIVA",0,IF(H70="ETAPA",OFFSET(C70,-1,0)+1,OFFSET(C70,-1,0))) -> 1 | D70: =IF(H70="ETAPA",0,IF(H70="SUBETAPA",OFFSET(D70,-1,0)+1,OFFSET(D70,-1,0))) -> 3 | E70: =IF(H70="Subetapa",0,IF(H70="serviço",OFFSET(E70,-1,0)+1,OFFSET(E70,-1,0))) -> 1 | H70: SERVIÇO | I70: =IF(H70="Unidade Construtiva",TEXT(A70,"00"),IF(H70="Célula Construtiva",TEXT(B70,"00"),IF(H70="Etapa",CONCATENATE(TEXT(B70,"00"),".",TEXT(C70,"000")),IF(H70="Subetapa",CONCATENATE(TEXT(B70,"00"),".",TEXT(C70,"000"),".",TEXT(D70,"000")),IF(H70="Serviço",CONCATENATE(TEXT(B70,"00"),".",TEXT(C70,"000"),".",TEXT(D70,"000"),".",TEXT(E70,"000")),""))))) -> 03.001.003.001 | J70: Encunhamento de alvenaria de vedação com argamassa expansiva | K70: m | L70: =ARQUITETURA!F275 -> 195.1 | M70: =_xlfn.XLOOKUP($J70,CPU!$D$1:$D$2521,CPU!$H$1:$H$2521) -> 14.7875 | N70: =IF(H70="Serviço",M70*L70,IF(H70="CÉLULA CONSTRUTIVA",SUMIFS($N$8:$N$258,$B$8:$B$258,B70,$H$8:$H$258,"Serviço"),IF(H70="ETAPA",SUMIFS($N$8:$N$258,$B$8:$B$258,B70,$C$8:$C$258,C70,$H$8:$H$258,"Serviço"),IF(H70="SUBETAPA",SUMIFS($N$8:$N$258,$B$8:$B$258,B70,$C$8:$C$258,C70,$D$8:$D$258,D70,$H$8:$H$258,"Serviço"),0)))) -> 2885.0413 | P70: Finalizado
A71: =IF($H71="UNIDADE CONSTRUTIVA",OFFSET(A71,-1,0)+1,LARGE(A$3:A70,1)) -> 0 | B71: =IF(H71="UNIDADE CONSTRUTIVA",0,IF(H71="CÉLULA CONSTRUTIVA",OFFSET(B71,-1,0)+1,OFFSET(B71,-1,0))) -> 3 | C71: =IF(H71="CÉLULA CONSTRUTIVA",0,IF(H71="ETAPA",OFFSET(C71,-1,0)+1,OFFSET(C71,-1,0))) -> 1 | D71: =IF(H71="ETAPA",0,IF(H71="SUBETAPA",OFFSET(D71,-1,0)+1,OFFSET(D71,-1,0))) -> 3 | E71: =IF(H71="Subetapa",0,IF(H71="serviço",OFFSET(E71,-1,0)+1,OFFSET(E71,-1,0))) -> 2 | H71: SERVIÇO | I71: =IF(H71="Unidade Construtiva",TEXT(A71,"00"),IF(H71="Célula Construtiva",TEXT(B71,"00"),IF(H71="Etapa",CONCATENATE(TEXT(B71,"00"),".",TEXT(C71,"000")),IF(H71="Subetapa",CONCATENATE(TEXT(B71,"00"),".",TEXT(C71,"000"),".",TEXT(D71,"000")),IF(H71="Serviço",CONCATENATE(TEXT(B71,"00"),".",TEXT(C71,"000"),".",TEXT(D71,"000"),".",TEXT(E71,"000")),""))))) -> 03.001.003.002 | J71: Tela soldada para ligacao alvenaria/estrutura | K71: un | L71: =ROUNDUP(ARQUITETURA!F276,0) -> 297 | M71: =_xlfn.XLOOKUP($J71,CPU!$D$1:$D$2521,CPU!$H$1:$H$2521) -> 4.1072 | N71: =IF(H71="Serviço",M71*L71,IF(H71="CÉLULA CONSTRUTIVA",SUMIFS($N$8:$N$258,$B$8:$B$258,B71,$H$8:$H$258,"Serviço"),IF(H71="ETAPA",SUMIFS($N$8:$N$258,$B$8:$B$258,B71,$C$8:$C$258,C71,$H$8:$H$258,"Serviço"),IF(H71="SUBETAPA",SUMIFS($N$8:$N$258,$B$8:$B$258,B71,$C$8:$C$258,C71,$D$8:$D$258,D71,$H$8:$H$258,"Serviço"),0)))) -> 1219.8384 | P71: Finalizado
A72: =IF($H72="UNIDADE CONSTRUTIVA",OFFSET(A72,-1,0)+1,LARGE(A$3:A71,1)) -> 0 | B72: =IF(H72="UNIDADE CONSTRUTIVA",0,IF(H72="CÉLULA CONSTRUTIVA",OFFSET(B72,-1,0)+1,OFFSET(B72,-1,0))) -> 3 | C72: =IF(H72="CÉLULA CONSTRUTIVA",0,IF(H72="ETAPA",OFFSET(C72,-1,0)+1,OFFSET(C72,-1,0))) -> 1 | D72: =IF(H72="ETAPA",0,IF(H72="SUBETAPA",OFFSET(D72,-1,0)+1,OFFSET(D72,-1,0))) -> 3 | E72: =IF(H72="Subetapa",0,IF(H72="serviço",OFFSET(E72,-1,0)+1,OFFSET(E72,-1,0))) -> 3 | H72: SERVIÇO | I72: =IF(H72="Unidade Construtiva",TEXT(A72,"00"),IF(H72="Célula Construtiva",TEXT(B72,"00"),IF(H72="Etapa",CONCATENATE(TEXT(B72,"00"),".",TEXT(C72,"000")),IF(H72="Subetapa",CONCATENATE(TEXT(B72,"00"),".",TEXT(C72,"000"),".",TEXT(D72,"000")),IF(H72="Serviço",CONCATENATE(TEXT(B72,"00"),".",TEXT(C72,"000"),".",TEXT(D72,"000"),".",TEXT(E72,"000")),""))))) -> 03.001.003.003 | J72: Verga/contraverga de concreto, moldada in loco | K72: m | L72: =ARQUITETURA!G277 -> 96.65 | M72: =_xlfn.XLOOKUP($J72,CPU!$D$1:$D$2521,CPU!$H$1:$H$2521) -> 80.381545 | N72: =IF(H72="Serviço",M72*L72,IF(H72="CÉLULA CONSTRUTIVA",SUMIFS($N$8:$N$258,$B$8:$B$258,B72,$H$8:$H$258,"Serviço"),IF(H72="ETAPA",SUMIFS($N$8:$N$258,$B$8:$B$258,B72,$C$8:$C$258,C72,$H$8:$H$258,"Serviço"),IF(H72="SUBETAPA",SUMIFS($N$8:$N$258,$B$8:$B$258,B72,$C$8:$C$258,C72,$D$8:$D$258,D72,$H$8:$H$258,"Serviço"),0)))) -> 7768.8763 | P72: Finalizado
A73: =IF($H73="UNIDADE CONSTRUTIVA",OFFSET(A73,-1,0)+1,LARGE(A$3:A72,1)) -> 0 | B73: =IF(H73="UNIDADE CONSTRUTIVA",0,IF(H73="CÉLULA CONSTRUTIVA",OFFSET(B73,-1,0)+1,OFFSET(B73,-1,0))) -> 3 | C73: =IF(H73="CÉLULA CONSTRUTIVA",0,IF(H73="ETAPA",OFFSET(C73,-1,0)+1,OFFSET(C73,-1,0))) -> 1 | D73: =IF(H73="ETAPA",0,IF(H73="SUBETAPA",OFFSET(D73,-1,0)+1,OFFSET(D73,-1,0))) -> 4 | E73: =IF(H73="Subetapa",0,IF(H73="serviço",OFFSET(E73,-1,0)+1,OFFSET(E73,-1,0))) -> 0 | H73: SUBETAPA | I73: =IF(H73="Unidade Construtiva",TEXT(A73,"00"),IF(H73="Célula Construtiva",TEXT(B73,"00"),IF(H73="Etapa",CONCATENATE(TEXT(B73,"00"),".",TEXT(C73,"000")),IF(H73="Subetapa",CONCATENATE(TEXT(B73,"00"),".",TEXT(C73,"000"),".",TEXT(D73,"000")),IF(H73="Serviço",CONCATENATE(TEXT(B73,"00"),".",TEXT(C73,"000"),".",TEXT(D73,"000"),".",TEXT(E73,"000")),""))))) -> 03.001.004 | J73: Mão de obra | N73: =IF(H73="Serviço",M73*L73,IF(H73="CÉLULA CONSTRUTIVA",SUMIFS($N$8:$N$258,$B$8:$B$258,B73,$H$8:$H$258,"Serviço"),IF(H73="ETAPA",SUMIFS($N$8:$N$258,$B$8:$B$258,B73,$C$8:$C$258,C73,$H$8:$H$258,"Serviço"),IF(H73="SUBETAPA",SUMIFS($N$8:$N$258,$B$8:$B$258,B73,$C$8:$C$258,C73,$D$8:$D$258,D73,$H$8:$H$258,"Serviço"),0)))) -> 20927.45
A74: =IF($H74="UNIDADE CONSTRUTIVA",OFFSET(A74,-1,0)+1,LARGE(A$3:A73,1)) -> 0 | B74: =IF(H74="UNIDADE CONSTRUTIVA",0,IF(H74="CÉLULA CONSTRUTIVA",OFFSET(B74,-1,0)+1,OFFSET(B74,-1,0))) -> 3 | C74: =IF(H74="CÉLULA CONSTRUTIVA",0,IF(H74="ETAPA",OFFSET(C74,-1,0)+1,OFFSET(C74,-1,0))) -> 1 | D74: =IF(H74="ETAPA",0,IF(H74="SUBETAPA",OFFSET(D74,-1,0)+1,OFFSET(D74,-1,0))) -> 4 | E74: =IF(H74="Subetapa",0,IF(H74="serviço",OFFSET(E74,-1,0)+1,OFFSET(E74,-1,0))) -> 1 | H74: SERVIÇO | I74: =IF(H74="Unidade Construtiva",TEXT(A74,"00"),IF(H74="Célula Construtiva",TEXT(B74,"00"),IF(H74="Etapa",CONCATENATE(TEXT(B74,"00"),".",TEXT(C74,"000")),IF(H74="Subetapa",CONCATENATE(TEXT(B74,"00"),".",TEXT(C74,"000"),".",TEXT(D74,"000")),IF(H74="Serviço",CONCATENATE(TEXT(B74,"00"),".",TEXT(C74,"000"),".",TEXT(D74,"000"),".",TEXT(E74,"000")),""))))) -> 03.001.004.001 | J74: Mão de obra para assentamento de blocos cerâmicos | K74: m2 | L74: =SUM(L62:L65)+L68 -> 592.22 | M74: =_xlfn.XLOOKUP($J74,CPU!$D$1:$D$2521,CPU!$H$1:$H$2521) -> 35 | N74: =IF(H74="Serviço",M74*L74,IF(H74="CÉLULA CONSTRUTIVA",SUMIFS($N$8:$N$258,$B$8:$B$258,B74,$H$8:$H$258,"Serviço"),IF(H74="ETAPA",SUMIFS($N$8:$N$258,$B$8:$B$258,B74,$C$8:$C$258,C74,$H$8:$H$258,"Serviço"),IF(H74="SUBETAPA",SUMIFS($N$8:$N$258,$B$8:$B$258,B74,$C$8:$C$258,C74,$D$8:$D$258,D74,$H$8:$H$258,"Serviço"),0)))) -> 20727.7 | P74: Finalizado
A75: =IF($H75="UNIDADE CONSTRUTIVA",OFFSET(A75,-1,0)+1,LARGE(A$3:A74,1)) -> 0 | B75: =IF(H75="UNIDADE CONSTRUTIVA",0,IF(H75="CÉLULA CONSTRUTIVA",OFFSET(B75,-1,0)+1,OFFSET(B75,-1,0))) -> 3 | C75: =IF(H75="CÉLULA CONSTRUTIVA",0,IF(H75="ETAPA",OFFSET(C75,-1,0)+1,OFFSET(C75,-1,0))) -> 1 | D75: =IF(H75="ETAPA",0,IF(H75="SUBETAPA",OFFSET(D75,-1,0)+1,OFFSET(D75,-1,0))) -> 4 | E75: =IF(H75="Subetapa",0,IF(H75="serviço",OFFSET(E75,-1,0)+1,OFFSET(E75,-1,0))) -> 2 | H75: SERVIÇO | I75: =IF(H75="Unidade Construtiva",TEXT(A75,"00"),IF(H75="Célula Construtiva",TEXT(B75,"00"),IF(H75="Etapa",CONCATENATE(TEXT(B75,"00"),".",TEXT(C75,"000")),IF(H75="Subetapa",CONCATENATE(TEXT(B75,"00"),".",TEXT(C75,"000"),".",TEXT(D75,"000")),IF(H75="Serviço",CONCATENATE(TEXT(B75,"00"),".",TEXT(C75,"000"),".",TEXT(D75,"000"),".",TEXT(E75,"000")),""))))) -> 03.001.004.002 | J75: Mão de obra para assentamento de blocos de Refratário | K75: m2 | L75: =L67 -> 3.995 | M75: =_xlfn.XLOOKUP($J75,CPU!$D$1:$D$2521,CPU!$H$1:$H$2521) -> 50 | N75: =IF(H75="Serviço",M75*L75,IF(H75="CÉLULA CONSTRUTIVA",SUMIFS($N$8:$N$258,$B$8:$B$258,B75,$H$8:$H$258,"Serviço"),IF(H75="ETAPA",SUMIFS($N$8:$N$258,$B$8:$B$258,B75,$C$8:$C$258,C75,$H$8:$H$258,"Serviço"),IF(H75="SUBETAPA",SUMIFS($N$8:$N$258,$B$8:$B$258,B75,$C$8:$C$258,C75,$D$8:$D$258,D75,$H$8:$H$258,"Serviço"),0)))) -> 199.75 | P75: Finalizado
A76: =IF($H76="UNIDADE CONSTRUTIVA",OFFSET(A76,-1,0)+1,LARGE(A$3:A75,1)) -> 0 | B76: =IF(H76="UNIDADE CONSTRUTIVA",0,IF(H76="CÉLULA CONSTRUTIVA",OFFSET(B76,-1,0)+1,OFFSET(B76,-1,0))) -> 4 | C76: =IF(H76="CÉLULA CONSTRUTIVA",0,IF(H76="ETAPA",OFFSET(C76,-1,0)+1,OFFSET(C76,-1,0))) -> 0 | D76: =IF(H76="ETAPA",0,IF(H76="SUBETAPA",OFFSET(D76,-1,0)+1,OFFSET(D76,-1,0))) -> 4 | E76: =IF(H76="Subetapa",0,IF(H76="serviço",OFFSET(E76,-1,0)+1,OFFSET(E76,-1,0))) -> 2 | H76: CÉLULA CONSTRUTIVA | I76: =IF(H76="Unidade Construtiva",TEXT(A76,"00"),IF(H76="Célula Construtiva",TEXT(B76,"00"),IF(H76="Etapa",CONCATENATE(TEXT(B76,"00"),".",TEXT(C76,"000")),IF(H76="Subetapa",CONCATENATE(TEXT(B76,"00"),".",TEXT(C76,"000"),".",TEXT(D76,"000")),IF(H76="Serviço",CONCATENATE(TEXT(B76,"00"),".",TEXT(C76,"000"),".",TEXT(D76,"000"),".",TEXT(E76,"000")),""))))) -> 04 | J76: SISTEMAS E INSTALAÇÕES HIDROSSANITÁRIAS E DRENAGEM | N76: =IF(H76="Serviço",M76*L76,IF(H76="CÉLULA CONSTRUTIVA",SUMIFS($N$8:$N$258,$B$8:$B$258,B76,$H$8:$H$258,"Serviço"),IF(H76="ETAPA",SUMIFS($N$8:$N$258,$B$8:$B$258,B76,$C$8:$C$258,C76,$H$8:$H$258,"Serviço"),IF(H76="SUBETAPA",SUMIFS($N$8:$N$258,$B$8:$B$258,B76,$C$8:$C$258,C76,$D$8:$D$258,D76,$H$8:$H$258,"Serviço"),0)))) -> 150074.68 | O76: =N76/'Obra '!E$9 -> 455.3651
A77: =IF($H77="UNIDADE CONSTRUTIVA",OFFSET(A77,-1,0)+1,LARGE(A$3:A76,1)) -> 0 | B77: =IF(H77="UNIDADE CONSTRUTIVA",0,IF(H77="CÉLULA CONSTRUTIVA",OFFSET(B77,-1,0)+1,OFFSET(B77,-1,0))) -> 4 | C77: =IF(H77="CÉLULA CONSTRUTIVA",0,IF(H77="ETAPA",OFFSET(C77,-1,0)+1,OFFSET(C77,-1,0))) -> 1 | D77: =IF(H77="ETAPA",0,IF(H77="SUBETAPA",OFFSET(D77,-1,0)+1,OFFSET(D77,-1,0))) -> 0 | E77: =IF(H77="Subetapa",0,IF(H77="serviço",OFFSET(E77,-1,0)+1,OFFSET(E77,-1,0))) -> 2 | H77: ETAPA | I77: =IF(H77="Unidade Construtiva",TEXT(A77,"00"),IF(H77="Célula Construtiva",TEXT(B77,"00"),IF(H77="Etapa",CONCATENATE(TEXT(B77,"00"),".",TEXT(C77,"000")),IF(H77="Subetapa",CONCATENATE(TEXT(B77,"00"),".",TEXT(C77,"000"),".",TEXT(D77,"000")),IF(H77="Serviço",CONCATENATE(TEXT(B77,"00"),".",TEXT(C77,"000"),".",TEXT(D77,"000"),".",TEXT(E77,"000")),""))))) -> 04.001 | J77: SISTEMAS E INSTALAÇÕES HIDROSSANITÁRIAS E DRENAGEM | N77: =IF(H77="Serviço",M77*L77,IF(H77="CÉLULA CONSTRUTIVA",SUMIFS($N$8:$N$258,$B$8:$B$258,B77,$H$8:$H$258,"Serviço"),IF(H77="ETAPA",SUMIFS($N$8:$N$258,$B$8:$B$258,B77,$C$8:$C$258,C77,$H$8:$H$258,"Serviço"),IF(H77="SUBETAPA",SUMIFS($N$8:$N$258,$B$8:$B$258,B77,$C$8:$C$258,C77,$D$8:$D$258,D77,$H$8:$H$258,"Serviço"),0)))) -> 150074.68
A78: =IF($H78="UNIDADE CONSTRUTIVA",OFFSET(A78,-1,0)+1,LARGE(A$3:A77,1)) -> 0 | B78: =IF(H78="UNIDADE CONSTRUTIVA",0,IF(H78="CÉLULA CONSTRUTIVA",OFFSET(B78,-1,0)+1,OFFSET(B78,-1,0))) -> 4 | C78: =IF(H78="CÉLULA CONSTRUTIVA",0,IF(H78="ETAPA",OFFSET(C78,-1,0)+1,OFFSET(C78,-1,0))) -> 1 | D78: =IF(H78="ETAPA",0,IF(H78="SUBETAPA",OFFSET(D78,-1,0)+1,OFFSET(D78,-1,0))) -> 1 | E78: =IF(H78="Subetapa",0,IF(H78="serviço",OFFSET(E78,-1,0)+1,OFFSET(E78,-1,0))) -> 0 | H78: SUBETAPA | I78: =IF(H78="Unidade Construtiva",TEXT(A78,"00"),IF(H78="Célula Construtiva",TEXT(B78,"00"),IF(H78="Etapa",CONCATENATE(TEXT(B78,"00"),".",TEXT(C78,"000")),IF(H78="Subetapa",CONCATENATE(TEXT(B78,"00"),".",TEXT(C78,"000"),".",TEXT(D78,"000")),IF(H78="Serviço",CONCATENATE(TEXT(B78,"00"),".",TEXT(C78,"000"),".",TEXT(D78,"000"),".",TEXT(E78,"000")),""))))) -> 04.001.001 | J78: Hidrossanitário | N78: =IF(H78="Serviço",M78*L78,IF(H78="CÉLULA CONSTRUTIVA",SUMIFS($N$8:$N$258,$B$8:$B$258,B78,$H$8:$H$258,"Serviço"),IF(H78="ETAPA",SUMIFS($N$8:$N$258,$B$8:$B$258,B78,$C$8:$C$258,C78,$H$8:$H$258,"Serviço"),IF(H78="SUBETAPA",SUMIFS($N$8:$N$258,$B$8:$B$258,B78,$C$8:$C$258,C78,$D$8:$D$258,D78,$H$8:$H$258,"Serviço"),0)))) -> 78583.302
A79: =IF($H79="UNIDADE CONSTRUTIVA",OFFSET(A79,-1,0)+1,LARGE(A$3:A78,1)) -> 0 | B79: =IF(H79="UNIDADE CONSTRUTIVA",0,IF(H79="CÉLULA CONSTRUTIVA",OFFSET(B79,-1,0)+1,OFFSET(B79,-1,0))) -> 4 | C79: =IF(H79="CÉLULA CONSTRUTIVA",0,IF(H79="ETAPA",OFFSET(C79,-1,0)+1,OFFSET(C79,-1,0))) -> 1 | D79: =IF(H79="ETAPA",0,IF(H79="SUBETAPA",OFFSET(D79,-1,0)+1,OFFSET(D79,-1,0))) -> 1 | E79: =IF(H79="Subetapa",0,IF(H79="serviço",OFFSET(E79,-1,0)+1,OFFSET(E79,-1,0))) -> 1 | H79: SERVIÇO | I79: =IF(H79="Unidade Construtiva",TEXT(A79,"00"),IF(H79="Célula Construtiva",TEXT(B79,"00"),IF(H79="Etapa",CONCATENATE(TEXT(B79,"00"),".",TEXT(C79,"000")),IF(H79="Subetapa",CONCATENATE(TEXT(B79,"00"),".",TEXT(C79,"000"),".",TEXT(D79,"000")),IF(H79="Serviço",CONCATENATE(TEXT(B79,"00"),".",TEXT(C79,"000"),".",TEXT(D79,"000"),".",TEXT(E79,"000")),""))))) -> 04.001.001.001 | J79: Instalações hidrossanitarias | K79: vb | L79: 1 | M79: =INSTALAÇÕES!E28+INSTALAÇÕES!E29+INSTALAÇÕES!E30+INSTALAÇÕES!E31+INSTALAÇÕES!E32 -> 37021.75 | N79: =IF(H79="Serviço",M79*L79,IF(H79="CÉLULA CONSTRUTIVA",SUMIFS($N$8:$N$258,$B$8:$B$258,B79,$H$8:$H$258,"Serviço"),IF(H79="ETAPA",SUMIFS($N$8:$N$258,$B$8:$B$258,B79,$C$8:$C$258,C79,$H$8:$H$258,"Serviço"),IF(H79="SUBETAPA",SUMIFS($N$8:$N$258,$B$8:$B$258,B79,$C$8:$C$258,C79,$D$8:$D$258,D79,$H$8:$H$258,"Serviço"),0)))) -> 37021.75 | P79: Finalizado
A80: =IF($H80="UNIDADE CONSTRUTIVA",OFFSET(A80,-1,0)+1,LARGE(A$3:A79,1)) -> 0 | B80: =IF(H80="UNIDADE CONSTRUTIVA",0,IF(H80="CÉLULA CONSTRUTIVA",OFFSET(B80,-1,0)+1,OFFSET(B80,-1,0))) -> 4 | C80: =IF(H80="CÉLULA CONSTRUTIVA",0,IF(H80="ETAPA",OFFSET(C80,-1,0)+1,OFFSET(C80,-1,0))) -> 1 | D80: =IF(H80="ETAPA",0,IF(H80="SUBETAPA",OFFSET(D80,-1,0)+1,OFFSET(D80,-1,0))) -> 1 | E80: =IF(H80="Subetapa",0,IF(H80="serviço",OFFSET(E80,-1,0)+1,OFFSET(E80,-1,0))) -> 2 | H80: SERVIÇO | I80: =IF(H80="Unidade Construtiva",TEXT(A80,"00"),IF(H80="Célula Construtiva",TEXT(B80,"00"),IF(H80="Etapa",CONCATENATE(TEXT(B80,"00"),".",TEXT(C80,"000")),IF(H80="Subetapa",CONCATENATE(TEXT(B80,"00"),".",TEXT(C80,"000"),".",TEXT(D80,"000")),IF(H80="Serviço",CONCATENATE(TEXT(B80,"00"),".",TEXT(C80,"000"),".",TEXT(D80,"000"),".",TEXT(E80,"000")),""))))) -> 04.001.001.002 | J80: Sistema de tratamento de esgoto | K80: vb | L80: 1 | M80: =INSTALAÇÕES!E33 -> 41561.552 | N80: =IF(H80="Serviço",M80*L80,IF(H80="CÉLULA CONSTRUTIVA",SUMIFS($N$8:$N$258,$B$8:$B$258,B80,$H$8:$H$258,"Serviço"),IF(H80="ETAPA",SUMIFS($N$8:$N$258,$B$8:$B$258,B80,$C$8:$C$258,C80,$H$8:$H$258,"Serviço"),IF(H80="SUBETAPA",SUMIFS($N$8:$N$258,$B$8:$B$258,B80,$C$8:$C$258,C80,$D$8:$D$258,D80,$H$8:$H$258,"Serviço"),0)))) -> 41561.552 | P80: Finalizado
