Workbook

Sheet INSUMOS
A1: Código | B1: Descrição | C1: Un. | D1: Quantidade | E1: Preço unitário | F1: Preço total | G1: Data do preço
A2: 6726 | B2: Empreitada de Mão de Obra para Parte Civil * | C2: vb | D2: 1 | E2: 3670000 | F2: 3670000 | G2: 28/11/2023
A3: 5181 | B3: ESQUADRIAS DE ALUMÍNIO, FORNECIMENTO E INSTALAÇÃO * | C3: vb | D3: 1 | E3: 982359.81 | F3: 982359.81 | G3: 28/11/2023
A4: 7575 | B4: IMPREVISTOS E CONTINGÊNCIAS * | C4: vb | D4: 1 | E4: 187036.67 | F4: 187036.67 | G4: 05/12/2023
A5: 5006 | B5: Elevador de Pessoas * | C5: un | D5: 1 | E5: 152799.2 | F5: 152799.2 | G5: 27/11/2023
A6: 8651 | B6: BRISE METÁLICO 1400 X 1100 * | C6: vb | D6: 1 | E6: 96675 | F6: 96675 | G6: 28/11/2023
A7: 7569 | B7: LOUÇAS E METAIS* | C7: vb | D7: 1 | E7: 83451.16 | F7: 83451.16 | G7: 27/11/2023
A8: 7488 | B8: INSTALACOES DE AGUA FRIA * | C8: vb | D8: 1 | E8: 77643.74 | F8: 77643.74 | G8: 24/11/2023
A9: 6406 | B9: AMBIENTAÇÃO E DECORAÇÃO * | C9: vb | D9: 1 | E9: 73904.11 | F9: 73904.11 | G9: 29/11/2023
A10: 7484 | B10: FIOS E CABOS ELETRICOS * | C10: vb | D10: 1 | E10: 57327.856 | F10: 57327.86 | G10: 10/11/2023
A11: 5428 | B11: Empreitada de Paisagismo e Arborização * | C11: vb | D11: 1 | E11: 53582 | F11: 53582 | G11: 28/11/2023
A12: 7593 | B12: SERRALHERIAS * | C12: vb | D12: 1 | E12: 46449 | F12: 46449 | G12: 28/11/2023
A13: 5142 | B13: INSTALAÇÃO DE GÁS - MATERIAL* | C13: vb | D13: 1 | E13: 44600 | F13: 44600 | G13: 10/11/2023
... A158: 44 | B158: Azulejista * | C158: h | D158: 843.56 | E158: 0 | F158: 0 | G158: 20/03/2014
A159: Total da obra
A161: 06/12/2023 - 08:57:33

Sheet ABC
A1: Família | L1: Preço total | M1: %Part. | N1: %Acum.
A2: 04.007 - Empreitada Global | L2: 3670000 | M2: 32.6891 | N2: 32.6891
A3: Código | B3: Descrição | F3: Un. | G3: Quantidade | H3: Preço unitário | L3: Preço total
A4: 6726 | B4: Empreitada de Mão de Obra para Parte Civil * | F4: vb | G4: 1 | I4: 3670000 | L4: 3670000
A6: Família | L6: Preço total | M6: %Part. | N6: %Acum.
A7: 02.010 - Esquadrias de Alumínio | L7: 1134294.1 | M7: 10.1033 | N7: 42.7924
A8: Código | B8: Descrição | F8: Un. | G8: Quantidade | H8: Preço unitário | L8: Preço total
A9: 5181 | B9: ESQUADRIAS DE ALUMÍNIO, FORNECIMENTO E INSTALAÇÃO * | F9: vb | G9: 1 | I9: 982359.81 | L9: 982359.81
A10: 8651 | B10: BRISE METÁLICO 1400 X 1100 * | F10: vb | G10: 1 | I10: 96675 | L10: 96675
A11: 1370 | B11: PORTÃO DE ELEVAÇÃO GARAGEM * | F11: vb | G11: 1 | I11: 41259.26 | L11: 41259.26
A12: 1807 | B12: CONTRAMARCO DE ALUMÍNIO CONVENCIONAL* | F12: m | G12: 995.28 | I12: 14.0664 | L12: 14000.01
A14: Família | L14: Preço total | M14: %Part. | N14: %Acum.
A15: 02.005 - Armadura | L15: 931537.32 | M15: 8.2973 | N15: 51.0897
A16: Código | B16: Descrição | F16: Un. | G16: Quantidade | H16: Preço unitário | L16: Preço total
A17: 1348 | B17: Aco CA-50 Diametro 12,5mm * | F17: kg | G17: 18138.51 | I17: 6.5 | L17: 117900.31
A18: 1214 | B18: Aco CA-50 Diametro 10,0mm * | F18: kg | G18: 15311.34 | I18: 6.7 | L18: 102585.98
A19: 1444 | B19: Aco CA-50 Diametro 16,0mm * | F19: kg | G19: 15695.4 | I19: 6.5 | L19: 102020.1
A20: 1347 | B20: Aco CA-50 Diametro 8,00mm * | F20: kg | G20: 13308.9 | I20: 7.02 | L20: 93428.48
A21: 1445 | B21: Aco CA-60 Diametro 5,00mm * | F21: kg | G21: 12240.8 | I21: 7.61 | L21: 93152.49
A22: 7121 | B22: PINO LISO EM AÇO GALVANIZADO 1/2 X 22MM COM ARRUELA* | F22: un | G22: 67802.934 | I22: 1.12 | L22: 75939.29
A23: 4708 | B23: Aco CA-50 Diametro 20,0mm * | F23: kg | G23: 9368.52 | I23: 6.5 | L23: 60895.38
A24: 4709 | B24: Aco CA-50 Diametro 25,0mm * | F24: kg | G24: 9221.46 | I24: 6.5 | L24: 59939.49
A25: 7198 | B25: TELA DE ACO SOLDADA GALVANIZADA/ZINCADA PARA ALVENARIA, FIO D = 1,24 MM, MALHA 25 X 25 MM * | F25: m2 | G25: 1349.838 | I25: 34.92 | L25: 47136.34
A26: 1216 | B26: Aco CA-50 Diametro 6,30mm * | F26: kg | G26: 14855.537 | I26: 3.1 | L26: 46052.17
A27: 7667 | B27: TELA DE ACO SOLDADA GALVANIZADA/ZINCADA PARA REBOCO/EMBOÇO, FIO D = 1,24 MM, MALHA 25 X 25 MM * | F27: m2 | G27: 1227.45 | I27: 34.92 | L27: 42862.55
A28: 7439 | B28: ESPAÇADOR TIPO CARANGUEIJO PARA ARMADURA * | F28: un | G28: 7645.5 | I28: 4.07 | L28: 31117.19
... A34: 7120 | B34: PREGO COM CABECA 17X21 * | F34: kg | G34: 51.6901 | I34: 23.75 | L34: 1227.64
A36: Família | L36: Preço total | M36: %Part. | N36: %Acum.
A37: 01.002 - Mão de Obra de Terceiros | L37: 919558.89 | M37: 8.1906 | N37: 59.2803
A38: Código | B38: Descrição | F38: Un. | G38: Quantidade | H38: Preço unitário | L38: Preço total
A39: 848 | B39: MÃO DE OBRA EMPREITADA PARA APLICAÇÃO E LIXAMENTO DE MASSA EM PAREDES, 2 DEMÃOS * | F39: m2 | G39: 6696.3 | I39: 22 | L39: 147318.6
A40: 7181 | B40: MÃO DE OBRA EMPREITADA PARA APLICAÇÃO DE TEXTURA ACRÍLICA EM PAREDES INTERNAS, 1 DEMÃO * | F40: m2 | G40: 6696.3 | I40: 15 | L40: 100444.5
A41: 7173 | B41: MÃO DE OBRA EMPREITADA PARA PINTURA COM TINTA LÁTEX ACRÍLICA EM PAREDES INTERNAS, 2 DEMÃOS * | F41: m2 | G41: 6696.3 | I41: 14 | L41: 93748.2
A42: 7178 | B42: MÃO DE OBRA EMPREITADA PARA APLICAÇÃO E LIXAMENTO DE MASSA TETO, 2 DEMÃOS * | F42: m2 | G42: 3655.6 | I42: 20 | L42: 73112
A43: 1248 | B43: Mão de Obra Bombeamento Concreto Usinado* | F43: m3 | G43: 1389.822 | I43: 42.93 | L43: 59665.06
A44: 7265 | B44: MÃO DE OBRA EMPREITADA PARA PINTURA COM TINTA LÁTEX ACRÍLICA EM PAREDES EXTERNAS, 2 DEMÃOS * | F44: m2 | G44: 1958.59 | I44: 30 | L44: 58757.7
A45: 7182 | B45: MÃO DE OBRA EMPREITADA PARA APLICAÇÃO DE TEXTURA ACRÍLICA EM TETO, 1 DEMÃO * | F45: m2 | G45: 3655.6 | I45: 15 | L45: 54834
A46: 5136 | B46: MÃO DE OBRA EMPREITADA PARA PINTURA COM TINTA LÁTEX ACRÍLICA EM TETO, 2 DEMÃOS * | F46: m2 | G46: 3655.6 | I46: 14 | L46: 51178.4
A47: 7222 | B47: MÃO DE OBRA PARA IMPERMEABILIZAÇÃO COM ARGAMASSA POLIMÉRICA * | F47: m2 | G47: 937.56 | I47: 45.48 | L47: 42640.23
A48: 7269 | B48: MÃO DE OBRA EMPREITADA PARA APLICAÇÃO DE TEXTURA ACRÍLICA EM PAREDES EXTERNAS, 1 DEMÃO * | F48: m2 | G48: 1156.28 | I48: 35 | L48: 40469.8
A49: 7170 | B49: MÃO DE OBRA EMPREITADA PARA APLICAÇÃO DE FUNDO SELADOR PAREDES INTERNAS, 1 DEMÃO * | F49: m2 | G49: 6696.3 | I49: 5 | L49: 33481.5
A50: 7279 | B50: LIMPEZA FINAL * | F50: vb | G50: 1 | I50: 27791.56 | L50: 27791.56
... A65: 7426 | B65: MÃO DE OBRA PARA EXECUÇÃO DE PISO DE CONCRETO * | F65: m2 | G65: 0 | I65: 37.5 | L65: 0
A67: Família | L67: Preço total | M67: %Part. | N67: %Acum.
A68: 02.006 - Concretos | L68: 900664.76 | M68: 8.0223 | N68: 67.3027
A69: Código | B69: Descrição | F69: Un. | G69: Quantidade | H69: Preço unitário | L69: Preço total
A70: 8673 | B70: CONCRETO USINADO FCK=30 MPA, SLUMP 16 BOMBEADO B1 * | F70: m3 | G70: 1236.1965 | I70: 612.34 | L70: 756972.56
A71: 4730 | B71: Concreto Usinado Fck 30 MPa * | F71: m3 | G71: 153.6255 | I71: 605 | L71: 92943.43
A72: 4732 | B72: Concreto Usinado Fck 25 MPa * | F72: m3 | G72: 67.2804 | I72: 585 | L72: 39359.03
A73: 4731 | B73: CONCRETO USINADO FCK 20MPA, SLUMP 14 +/- 2 BOMBEADO B01* | F73: m3 | G73: 28.3355 | I73: 401.96 | L73: 11389.74
A75: Família | L75: Preço total | M75: %Part. | N75: %Acum.
A76: 02.048 - Revestimentos | L76: 744861.17 | M76: 6.6346 | N76: 73.9372
A77: Código | B77: Descrição | F77: Un. | G77: Quantidade | H77: Preço unitário | L77: Preço total
A78: 5837 | B78: Pedra Ferro * | F78: m2 | G78: 2134.5231 | I78: 184.9 | L78: 394673.32
A79: 7255 | B79: PISO PORCELANATO 80 CM X 80 CM * | F79: m2 | G79: 2104.718 | I79: 45.88 | L79: 96564.46
A80: 7266 | B80: REVESTIMENTO CERÂMICO PARA PAREDE 30X60CM * | F80: m2 | G80: 1092.091 | I80: 50 | L80: 54604.55
A81: 7499 | B81: REVESTIMENTO DE PORCELANATO PARA PAREDE 30X60CM * | F81: m2 | G81: 477.7095 | I81: 99 | L81: 47293.24
A82: 7460 | B82: RODAPÉ DE POLIESTIRENO, ALTURA 10 CM * | F82: m | G82: 2899.336 | I82: 15.5 | L82: 44939.71
A83: 5107 | B83: Piso Laminado de Madeira * | F83: m2 | G83: 744.084 | I83: 59.5 | L83: 44273
A84: 2042 | B84: GRANITO POLIDO * | F84: m2 | G84: 98.3955 | I84: 440 | L84: 43294.02
A85: 4976 | B85: Espaçador para Revestimentos Cerâmicos * | F85: un | G85: 15339.82 | I85: 0.898 | L85: 13775.16
A86: 5108 | B86: Manta para Piso Laminado de Madeira * | F86: m2 | G86: 744.084 | I86: 6.33 | L86: 4710.05
A87: 7463 | B87: PISO CERÂMICO, PLACA 45X45CM * | F87: m2 | G87: 9.9143 | I87: 74 | L87: 733.66
A89: Família | L89: Preço total | M89: %Part. | N89: %Acum.
A90: 02.022 - Pintura | L90: 333007.85 | M90: 2.9661 | N90: 76.9034
A91: Código | B91: Descrição | F91: Un. | G91: Quantidade | H91: Preço unitário | L91: Preço total
A92: 7188 | B92: TEXTURA ACRÍLICA * | F92: kg | G92: 17556.554 | I92: 6.8886 | L92: 120940.08
A93: 1668 | B93: TINTA ACRÍLICA * | F93: l | G93: 2155.6785 | I93: 51.0554 | L93: 110059.03
A94: 5014 | B94: Massa Corrida PVA * | F94: kg | G94: 7313.082 | I94: 5.396 | L94: 39461.39
A95: 1772 | B95: Selador * | F95: l | G95: 1290.2272 | I95: 29.87 | L95: 38539.09
A96: 7190 | B96: PRIMER EPOXI * | F96: l | G96: 82.973 | I96: 146 | L96: 12114.06
A97: 7192 | B97: DILUENTE EPÓXI * | F97: l | G97: 96.124 | I97: 40.14 | L97: 3858.42
A98: 7474 | B98: SELADOR IMPERMEABILIZANTE DE BASE ACRÍLICA PARA FACHADA * | F98: l | G98: 183.6178 | I98: 18.3333 | L98: 3366.32
A99: 30 | B99: TINTA EPOXI PREMIUM * | F99: m2 | G99: 30.6282 | I99: 87.7417 | L99: 2687.37
A100: 7184 | B100: LIXA EM FOLHA PARA PAREDE OU MADEIRA, NUMERO 100 * | F100: un | G100: 679.166 | I100: 1.3 | L100: 882.92
A101: 7335 | B101: SELANTE A BASE DE POLIURETANO (PU) * | F101: un | G101: 22.9365 | I101: 33.7 | L101: 772.96
A102: 5794 | B102: Fita Crepe 25mm X 50mts * | F102: un | G102: 23.4686 | I102: 13.9 | L102: 326.21
A104: Família | L104: Preço total | M104: %Part. | N104: %Acum.
A105: 02.001 - Aglomerantes | L105: 309488.19 | M105: 2.7566 | N105: 79.66
A106: Código | B106: Descrição | F106: Un. | G106: Quantidade | H106: Preço unitário | L106: Preço total
A107: 5751 | B107: ARGAMASSA REBOCO / ASSENTAMENTO* | F107: m3 | G107: 483.8396 | I107: 580 | L107: 280626.97
A108: 7193 | B108: CIMENTO PORTLAND CP II 32 * | F108: kg | G108: 24408.363 | I108: 0.792 | L108: 19331.42
A109: 4667 | B109: REJUNTE PORCELANATO* | F109: kg | G109: 532.391 | I109: 17.9 | L109: 9529.8
A111: Família | L111: Preço total | M111: %Part. | N111: %Acum.
A112: 02.008 - Materiais Elétricos Em Geral | L112: 229096.3 | M112: 2.0406 | N112: 81.7006
A113: Código | B113: Descrição | F113: Un. | G113: Quantidade | H113: Preço unitário | L113: Preço total
A114: 7484 | B114: FIOS E CABOS ELETRICOS * | F114: vb | G114: 1 | I114: 57327.856 | L114: 57327.86
A115: 7291 | B115: SISTEMA DE DUTOS E EXAUSTÃO PARA CHURRASQUEIRAS * | F115: vb | G115: 29 | I115: 1750 | L115: 50750
A116: 7482 | B116: QUADROS ELETRICOS E DISJUNTORES * | F116: vb | G116: 1 | I116: 41308.16 | L116: 41308.16
A117: 7483 | B117: ELETRODUTOS E ELETROCALHAS * | F117: vb | G117: 1 | I117: 29446.072 | L117: 29446.07
A118: 7485 | B118: PONTOS DE TOMADAS E INTERRUPTORES * | F118: vb | G118: 1 | I118: 28200.272 | L118: 28200.27
A119: 7486 | B119: LUMINARIAS, LAMPADAS E ACESSORIOS * | F119: vb | G119: 1 | I119: 16300.38 | L119: 16300.38
A120: 5070 | B120: Exaustor Tipo Vento Kit * | F120: un | G120: 55 | I120: 104.792 | L120: 5763.56
A122: Família | L122: Preço total | M122: %Part. | N122: %Acum.
A123: 02.050 - Forro | L123: 202607.02 | M123: 1.8046 | N123: 83.5052
A124: Código | B124: Descrição | F124: Un. | G124: Quantidade | H124: Preço unitário | L124: Preço total
A125: 7411 | B125: FORRO DE GESSO LISO * | F125: m2 | G125: 2355.51 | I125: 54.5455 | L125: 128482.47
A126: 4985 | B126: Negativo para Forro de Gesso * | F126: m | G126: 2945.6 | I126: 25.1645 | L126: 74124.55
A128: Família | L128: Preço total | M128: %Part. | N128: %Acum.
A129: 05.001 - Verbas, Taxas e Impostos | L129: 199781.25 | M129: 1.7795 | N129: 85.2847
...

Sheet ORÇAMENTO_EXECUTIVO
A1: ETAPA | B1: VALOR ORÇADO | C1: % | D1: VALOR / m²
A2: GERENCIAMENTO TÉCNICO E ADMINISTRATIVO | B2: 994642.42 | C2: =B2/B$20 -> 0.07968881 | D2: =B2/ORÇAMENTO_EXECUTIVO!G$2 -> 250.39459 | F2: ÁREA CONSTRUÍDA | G2: 3972.3 | H2: m²
A3: EMPREITADA GLOBAL | B3: 3670000 | C3: =B3/B$20 -> 0.29403324 | D3: =B3/ORÇAMENTO_EXECUTIVO!G$2 -> 923.89799
A4: MOVIMENTAÇÃO DE TERRA | B4: 130570.37 | C4: =B4/B$20 -> 0.010461043 | D4: =B4/ORÇAMENTO_EXECUTIVO!G$2 -> 32.870219
A5: INFRAESTRUTURA | B5: 240463.03 | C5: =B5/B$20 -> 0.019265429 | D5: =B5/ORÇAMENTO_EXECUTIVO!G$2 -> 60.534962
A6: SUPRAESTRUTURA | B6: 1904909.2 | C6: =B6/B$20 -> 0.15261761 | D6: =B6/ORÇAMENTO_EXECUTIVO!G$2 -> 479.54817
A7: ALVENARIA | B7: 281224 | C7: =B7/B$20 -> 0.022531118 | D7: =B7/ORÇAMENTO_EXECUTIVO!G$2 -> 70.796264
A8: INSTALAÇÕES ELÉTRICAS, HIDRÁULICAS, GLP E PREVENTIVAS | B8: 668527.92 | C8: =B8/B$20 -> 0.053561153 | D8: =B8/ORÇAMENTO_EXECUTIVO!G$2 -> 168.29744
A9: EQUIPAMENTOS E SISTEMAS ESPECIAIS | B9: 392311.51 | C9: =B9/B$20 -> 0.031431233 | D9: =B9/ORÇAMENTO_EXECUTIVO!G$2 -> 98.761803
A10: IMPERMEABILIZAÇÃO | B10: 281940.13 | C10: =B10/B$20 -> 0.022588493 | D10: =B10/ORÇAMENTO_EXECUTIVO!G$2 -> 70.976545
A11: REVESTIMENTOS INTERNOS EM PISO E PAREDE | B11: 503481.16 | C11: =B11/B$20 -> 0.040337928 | D11: =B11/ORÇAMENTO_EXECUTIVO!G$2 -> 126.74802
A12: REVESTIMENTOS E ACABAMENTOS INTERNOS EM TETO | B12: 215027.2 | C12: =B12/B$20 -> 0.01722756 | D12: =B12/ORÇAMENTO_EXECUTIVO!G$2 -> 54.131662
A13: ACABAMENTOS EM PISO E PAREDE | B13: 369121.22 | C13: =B13/B$20 -> 0.029573272 | D13: =B13/ORÇAMENTO_EXECUTIVO!G$2 -> 92.923802
A14: PINTURA INTERNA | B14: 657280.97 | C14: =B14/B$20 -> 0.052660069 | D14: =B14/ORÇAMENTO_EXECUTIVO!G$2 -> 165.4661
... A19: IMPREVISTOS E CONTINGENCIAS | B19: 185693.21 | C19: =B19/B$20 -> 0.014877378 | D19: =B19/ORÇAMENTO_EXECUTIVO!G$2 -> 46.747026
A20: TOTAL | B20: =SUM(B2:B19) -> 12481582 | C20: =SUM(C2:C19) -> 1 | D20: =SUM(D2:D19) -> 3142.1549
A21: CUB/RS | B21: 2418.97 | C21: 45200 | D21: =+D20/B21 -> 1.298964

Sheet ANÁLISE_CUSTOS
A1: ETAPA | B1: OBRA | D1: OBRA SIMILAR | J1: ETAPA | K1: VOLO HOME | L1: VOLO OCEAN
B2: VALOR | C2: VALOR / m² | D2: VALOR / m² | K2: VALOR / m² | L2: VALOR / m²
A3: GERENCIAMENTO TÉCNICO E ADMINISTRATIVO | B3: =ORÇAMENTO_EXECUTIVO!B2 -> 994642.42 | C3: =ORÇAMENTO_EXECUTIVO!D2 -> 250.39459 | D3: =FIXED(CÁLCULO_MÉDIAS!L8,2,FALSE)&" "&"-"&FIXED(CÁLCULO_MÉDIAS!M8,2,FALSE) -> 240,00 -272,00 | E3: OK | J3: GERENCIAMENTO TÉCNICO E ADMINISTRATIVO | K3: =C3 -> 250.39459 | L3: 241.06091
A4: EMPREITADA GLOBAL | B4: =ORÇAMENTO_EXECUTIVO!B3 -> 3670000 | C4: =ORÇAMENTO_EXECUTIVO!D3 -> 923.89799 | D4: =FIXED(CÁLCULO_MÉDIAS!L9,2,FALSE)&" "&"-"&FIXED(CÁLCULO_MÉDIAS!M9,2,FALSE) -> 802,00 -990,00 | E4: OK | J4: EMPREITADA GLOBAL | K4: =C4 -> 923.89799 | L4: 988.82646
A5: =ORÇAMENTO_EXECUTIVO!A4 -> MOVIMENTAÇÃO DE TERRA | B5: =ORÇAMENTO_EXECUTIVO!B4 -> 130570.37 | C5: =ORÇAMENTO_EXECUTIVO!D4 -> 32.870219 | D5: =FIXED(CÁLCULO_MÉDIAS!L10,2,FALSE)&" "&"-"&FIXED(CÁLCULO_MÉDIAS!M10,2,FALSE) -> 18,00 -24,00 | E5: A | J5: MOVIMENTAÇÃO DE TERRA | K5: =C5 -> 32.870219 | L5: 22.456999
A6: =ORÇAMENTO_EXECUTIVO!A5 -> INFRAESTRUTURA | B6: =ORÇAMENTO_EXECUTIVO!B5 -> 240463.03 | C6: =ORÇAMENTO_EXECUTIVO!D5 -> 60.534962 | D6: =FIXED(CÁLCULO_MÉDIAS!L11,2,FALSE)&" "&"-"&FIXED(CÁLCULO_MÉDIAS!M11,2,FALSE) -> 103,00 -132,00 | E6: B | J6: INFRAESTRUTURA | K6: =C6 -> 60.534962 | L6: 130.87253
A7: =ORÇAMENTO_EXECUTIVO!A6 -> SUPRAESTRUTURA | B7: =ORÇAMENTO_EXECUTIVO!B6 -> 1904909.2 | C7: =ORÇAMENTO_EXECUTIVO!D6 -> 479.54817 | D7: =FIXED(CÁLCULO_MÉDIAS!L12,2,FALSE)&" "&"-"&FIXED(CÁLCULO_MÉDIAS!M12,2,FALSE) -> 400,00 -458,00 | E7: OK | J7: SUPRAESTRUTURA | K7: =C7 -> 479.54817 | L7: 403.77303
A8: =ORÇAMENTO_EXECUTIVO!A7 -> ALVENARIA | B8: =ORÇAMENTO_EXECUTIVO!B7 -> 281224 | C8: =ORÇAMENTO_EXECUTIVO!D7 -> 70.796264 | D8: =FIXED(CÁLCULO_MÉDIAS!L13,2,FALSE)&" "&"-"&FIXED(CÁLCULO_MÉDIAS!M13,2,FALSE) -> 53,00 -65,00 | E8: OK | J8: ALVENARIA | K8: =C8 -> 70.796264 | L8: 63.000855
A9: =ORÇAMENTO_EXECUTIVO!A8 -> INSTALAÇÕES ELÉTRICAS, HIDRÁULICAS, GLP E PREVENTIVAS | B9: =ORÇAMENTO_EXECUTIVO!B8 -> 668527.92 | C9: =ORÇAMENTO_EXECUTIVO!D8 -> 168.29744 | D9: =FIXED(CÁLCULO_MÉDIAS!L14,2,FALSE)&" "&"-"&FIXED(CÁLCULO_MÉDIAS!M14,2,FALSE) -> 173,00 -186,00 | E9: B | J9: INSTALAÇÕES ELÉTRICAS, HIDRÁULICAS, GLP E PREVENTIVAS | K9: =C9 -> 168.29744 | L9: 174.12487
A10: =ORÇAMENTO_EXECUTIVO!A9 -> EQUIPAMENTOS E SISTEMAS ESPECIAIS | B10: =ORÇAMENTO_EXECUTIVO!B9 -> 392311.51 | C10: =ORÇAMENTO_EXECUTIVO!D9 -> 98.761803 | D10: =FIXED(CÁLCULO_MÉDIAS!L15,2,FALSE)&" "&"-"&FIXED(CÁLCULO_MÉDIAS!M15,2,FALSE) -> 173,00 -206,00 | E10: BB | J10: EQUIPAMENTOS E SISTEMAS ESPECIAIS | K10: =C10 -> 98.761803 | L10: 199.90422
A11: =ORÇAMENTO_EXECUTIVO!A10 -> IMPERMEABILIZAÇÃO | B11: =ORÇAMENTO_EXECUTIVO!B10 -> 281940.13 | C11: =ORÇAMENTO_EXECUTIVO!D10 -> 70.976545 | D11: =FIXED(CÁLCULO_MÉDIAS!L16,2,FALSE)&" "&"-"&FIXED(CÁLCULO_MÉDIAS!M16,2,FALSE) -> 43,00 -75,00 | E11: OK | J11: IMPERMEABILIZAÇÃO | K11: =C11 -> 70.976545 | L11: 43.004194
A12: =ORÇAMENTO_EXECUTIVO!A11 -> REVESTIMENTOS INTERNOS EM PISO E PAREDE | B12: 502096.02 | C12: =ORÇAMENTO_EXECUTIVO!D11 -> 126.74802 | D12: =FIXED(CÁLCULO_MÉDIAS!L17,2,FALSE)&" "&"-"&FIXED(CÁLCULO_MÉDIAS!M17,2,FALSE) -> 73,00 -127,00 | E12: OK | J12: REVESTIMENTOS INTERNOS EM PISO E PAREDE | K12: =C12 -> 126.74802 | L12: 75.674101
A13: =ORÇAMENTO_EXECUTIVO!A12 -> REVESTIMENTOS E ACABAMENTOS INTERNOS EM TETO | B13: =ORÇAMENTO_EXECUTIVO!B12 -> 215027.2 | C13: =ORÇAMENTO_EXECUTIVO!D12 -> 54.131662 | D13: =FIXED(CÁLCULO_MÉDIAS!L18,2,FALSE)&" "&"-"&FIXED(CÁLCULO_MÉDIAS!M18,2,FALSE) -> 40,00 -60,00 | E13: OK | J13: REVESTIMENTOS E ACABAMENTOS INTERNOS EM TETO | K13: =C13 -> 54.131662 | L13: 41.229893
A14: =ORÇAMENTO_EXECUTIVO!A13 -> ACABAMENTOS EM PISO E PAREDE | B14: =ORÇAMENTO_EXECUTIVO!B13 -> 369121.22 | C14: =ORÇAMENTO_EXECUTIVO!D13 -> 92.923802 | D14: =FIXED(CÁLCULO_MÉDIAS!L19,2,FALSE)&" "&"-"&FIXED(CÁLCULO_MÉDIAS!M19,2,FALSE) -> 85,00 -135,00 | E14: OK | J14: ACABAMENTOS EM PISO E PAREDE | K14: =C14 -> 92.923802 | L14: 87.391237
A15: =ORÇAMENTO_EXECUTIVO!A14 -> PINTURA INTERNA | B15: 640510.24 | C15: =ORÇAMENTO_EXECUTIVO!D14 -> 165.4661 | D15: =FIXED(CÁLCULO_MÉDIAS!L20,2,FALSE)&" "&"-"&FIXED(CÁLCULO_MÉDIAS!M20,2,FALSE) -> 53,00 -145,00 | E15: A | J15: PINTURA INTERNA | K15: =C15 -> 165.4661 | L15: 54.494482
A16: =ORÇAMENTO_EXECUTIVO!A15 -> ESQUADRIAS, VIDROS E FERRAGENS | B16: =ORÇAMENTO_EXECUTIVO!B15 -> 1303914.3 | C16: =ORÇAMENTO_EXECUTIVO!D15 -> 328.25171 | D16: =FIXED(CÁLCULO_MÉDIAS!L21,2,FALSE)&" "&"-"&FIXED(CÁLCULO_MÉDIAS!M21,2,FALSE) -> 275,00 -315,00 | E16: OK | J16: ESQUADRIAS, VIDROS E FERRAGENS | K16: =C16 -> 328.25171 | L16: 314.23691
A17: =ORÇAMENTO_EXECUTIVO!A16 -> COBERTURA | B17: =ORÇAMENTO_EXECUTIVO!B16 -> 56830.39 | C17: =ORÇAMENTO_EXECUTIVO!D16 -> 14.306671 | D17: =FIXED(CÁLCULO_MÉDIAS!L22,2,FALSE)&" "&"-"&FIXED(CÁLCULO_MÉDIAS!M22,2,FALSE) -> 8,00 -35,00 | E17: OK | J17: COBERTURA | K17: =C17 -> 14.306671 | L17: 9.7356262
A18: =ORÇAMENTO_EXECUTIVO!A17 -> REVESTIMENTOS E ACABAMENTOS DE FACHADA | B18: =ORÇAMENTO_EXECUTIVO!B17 -> 395281.33 | C18: =ORÇAMENTO_EXECUTIVO!D17 -> 99.509435 | D18: =FIXED(CÁLCULO_MÉDIAS!L23,2,FALSE)&" "&"-"&FIXED(CÁLCULO_MÉDIAS!M23,2,FALSE) -> 96,00 -142,00 | E18: OK | J18: REVESTIMENTOS E ACABAMENTOS DE FACHADA | K18: =C18 -> 99.509435 | L18: 140.48745
A19: =ORÇAMENTO_EXECUTIVO!A18 -> SERVIÇOS COMPLEMENTARES | B19: =ORÇAMENTO_EXECUTIVO!B18 -> 230363.64 | C19: =ORÇAMENTO_EXECUTIVO!D18 -> 57.992508 | D19: =FIXED(CÁLCULO_MÉDIAS!L24,2,FALSE)&" "&"-"&FIXED(CÁLCULO_MÉDIAS!M24,2,FALSE) -> 123,00 -158,00 | E19: BB | J19: SERVIÇOS COMPLEMENTARES | K19: =C19 -> 57.992508 | L19: 156.03393
A20: =ORÇAMENTO_EXECUTIVO!A19 -> IMPREVISTOS E CONTINGENCIAS | B20: =ORÇAMENTO_EXECUTIVO!B19 -> 185693.21 | C20: =ORÇAMENTO_EXECUTIVO!D19 -> 46.747026 | D20: =FIXED(CÁLCULO_MÉDIAS!L25,2,FALSE)&" "&"-"&FIXED(CÁLCULO_MÉDIAS!M25,2,FALSE) -> 35,00 -102,00 | E20: OK | J20: TOTAL | K20: =SUM(K3:K19) -> 3095.4079 | L20: =SUM(L3:L19) -> 3146.3077
A21: TOTAL | B21: =SUM(B5:B19) -> 7613090.5 | C21: =SUM(C5:C19) -> 1921.1153 | D21: =FIXED(CÁLCULO_MÉDIAS!L24,2,FALSE)&" "&"-"&FIXED(CÁLCULO_MÉDIAS!M24,2,FALSE) -> 123,00 -158,00
F22: =SUM(B3:B19) -> 12277733
B25: 2007.57
B26: 2461.35
B27: =B26/B25 -> 1.2260345
C30: 1.1023
A32: 900,00 - 1100 | B32: 900
A33: 25,00 - 30,00 | B33: 25
A34: 15,00 - 22,00 | B34: 15
A35: 150,00 - 200,00 | B35: 150
A36: 440,00 - 510,00 | B36: 440
A37: -
A38: 55,00 - 70,00 | B38: 55
A39: 170,00 - 200,00 | B39: 170
A40: 165,00 - 230,00 | B40: 165
A41: 40,00 - 70,00 | B41: 40
A42: 55,00 - 77,00 | B42: 55
A43: 35,00 - 50,00 | B43: 35
A44: 130,00 - 175,00 | B44: 130
A45: 35,00 - 65,00 | B45: 35
A46: 35,00 - 55,00 | B46: 35
A47: 430,00 - 550,00 | B47: 430
A48: 35,00 - 50,00 | B48: 35
A49: 150,00 - 220,00 | B49: 150
B78: VOLO HOME | C78: VALOR / m²
B79: 467,62 / m² | C79: 241,06 -270,32

Sheet CÁLCULO_MÉDIAS
C3: DATA BASE | D3: 44470 | E3: DATA BASE | F3: 44409 | G3: DATA BASE | H3: 44896 | I3: DATA BASE
C4: CUB | D4: 2381.34 | E4: CUB | F4: 2329.85 | G4: CUB | H4: 2643.16 | I4: CUB
C6: BARBADOS | E6: NASSAU | G6: VOLO OCEAN | I6: OBRA4 | L6: MÉDIAS
C7: VALOR / M2 | D7: INDEXADO | E7: VALOR / M2 | F7: INDEXADO | G7: VALOR / M2 | H7: INDEXADO | I7: VALOR / M2 | J7: INDEXADO | L7: MÍNIMA | M7: MÁXIMA
B8: GERENCIAMENTO TECNICO E ADMINISTRATIVO | C8: 252.01389 | D8: =ORÇAMENTO_EXECUTIVO!$B$21/CÁLCULO_MÉDIAS!D$4*C8 -> 255.99622 | E8: 260.35641 | F8: =ORÇAMENTO_EXECUTIVO!$B$21/CÁLCULO_MÉDIAS!F$4*E8 -> 270.3154 | G8: 263.40242 | H8: =ORÇAMENTO_EXECUTIVO!$B$21/CÁLCULO_MÉDIAS!H$4*G8 -> 241.06091 | J8: =ORÇAMENTO_EXECUTIVO!$B$21/CÁLCULO_MÉDIAS!J$4*I8 -> #DIV/0! | L8: 240 | M8: 272
B9: EMPREITADA GLOBAL | C9: 791.69167 | D9: =ORÇAMENTO_EXECUTIVO!$B$21/CÁLCULO_MÉDIAS!D$4*C9 -> 804.202 | E9: 808.71698 | F9: =ORÇAMENTO_EXECUTIVO!$B$21/CÁLCULO_MÉDIAS!F$4*E9 -> 839.65153 | G9: 1080.4708 | H9: =ORÇAMENTO_EXECUTIVO!$B$21/CÁLCULO_MÉDIAS!H$4*G9 -> 988.82646 | J9: =ORÇAMENTO_EXECUTIVO!$B$21/CÁLCULO_MÉDIAS!J$4*I9 -> #DIV/0! | L9: 802 | M9: 990
B10: MOVIMENTAÇÃO DE TERRA | C10: 19.800616 | D10: =ORÇAMENTO_EXECUTIVO!$B$21/CÁLCULO_MÉDIAS!D$4*C10 -> 20.113506 | E10: 21.181115 | F10: =ORÇAMENTO_EXECUTIVO!$B$21/CÁLCULO_MÉDIAS!F$4*E10 -> 21.991322 | G10: 24.538313 | H10: =ORÇAMENTO_EXECUTIVO!$B$21/CÁLCULO_MÉDIAS!H$4*G10 -> 22.456999 | J10: =ORÇAMENTO_EXECUTIVO!$B$21/CÁLCULO_MÉDIAS!J$4*I10 -> #DIV/0! | L10: 18 | M10: 24
B11: INFRAESTRUTURA | C11: 115.06333 | D11: =ORÇAMENTO_EXECUTIVO!$B$21/CÁLCULO_MÉDIAS!D$4*C11 -> 116.88157 | E11: 101.68524 | F11: =ORÇAMENTO_EXECUTIVO!$B$21/CÁLCULO_MÉDIAS!F$4*E11 -> 105.57484 | G11: 143.00179 | H11: =ORÇAMENTO_EXECUTIVO!$B$21/CÁLCULO_MÉDIAS!H$4*G11 -> 130.87253 | J11: =ORÇAMENTO_EXECUTIVO!$B$21/CÁLCULO_MÉDIAS!J$4*I11 -> #DIV/0! | L11: 103 | M11: 132
B12: SUPRAESTRUTURA | C12: 449.26532 | D12: =ORÇAMENTO_EXECUTIVO!$B$21/CÁLCULO_MÉDIAS!D$4*C12 -> 456.36462 | E12: 396.66658 | F12: =ORÇAMENTO_EXECUTIVO!$B$21/CÁLCULO_MÉDIAS!F$4*E12 -> 411.83963 | G12: 441.19469 | H12: =ORÇAMENTO_EXECUTIVO!$B$21/CÁLCULO_MÉDIAS!H$4*G12 -> 403.77303 | J12: =ORÇAMENTO_EXECUTIVO!$B$21/CÁLCULO_MÉDIAS!J$4*I12 -> #DIV/0! | L12: 400 | M12: 458
B13: ALVENARIA | C13: 63.497379 | D13: =ORÇAMENTO_EXECUTIVO!$B$21/CÁLCULO_MÉDIAS!D$4*C13 -> 64.500766 | E13: 53.5484 | F13: =ORÇAMENTO_EXECUTIVO!$B$21/CÁLCULO_MÉDIAS!F$4*E13 -> 55.596701 | G13: 68.83977 | H13: =ORÇAMENTO_EXECUTIVO!$B$21/CÁLCULO_MÉDIAS!H$4*G13 -> 63.000855 | J13: =ORÇAMENTO_EXECUTIVO!$B$21/CÁLCULO_MÉDIAS!J$4*I13 -> #DIV/0! | L13: 53 | M13: 65
B14: INSTALAÇÕES ELÉTRICAS, HIDRÁULICAS, GLP E PREVENTIVAS | C14: 176.76267 | D14: =ORÇAMENTO_EXECUTIVO!$B$21/CÁLCULO_MÉDIAS!D$4*C14 -> 179.55588 | E14: 177.67405 | F14: =ORÇAMENTO_EXECUTIVO!$B$21/CÁLCULO_MÉDIAS!F$4*E14 -> 184.47032 | G14: 190.26275 | H14: =ORÇAMENTO_EXECUTIVO!$B$21/CÁLCULO_MÉDIAS!H$4*G14 -> 174.12487 | J14: =ORÇAMENTO_EXECUTIVO!$B$21/CÁLCULO_MÉDIAS!J$4*I14 -> #DIV/0! | L14: 173 | M14: 186
B15: EQUIPAMENTOS E SISTEMAS ESPECIAIS | C15: 173.25539 | D15: =ORÇAMENTO_EXECUTIVO!$B$21/CÁLCULO_MÉDIAS!D$4*C15 -> 175.99318 | E15: 195.74663 | F15: =ORÇAMENTO_EXECUTIVO!$B$21/CÁLCULO_MÉDIAS!F$4*E15 -> 203.23421 | G15: 218.43133 | H15: =ORÇAMENTO_EXECUTIVO!$B$21/CÁLCULO_MÉDIAS!H$4*G15 -> 199.90422 | J15: =ORÇAMENTO_EXECUTIVO!$B$21/CÁLCULO_MÉDIAS!J$4*I15 -> #DIV/0! | L15: 173 | M15: 206
B16: IMPERMEABILIZAÇÃO | C16: 71.499758 | D16: =ORÇAMENTO_EXECUTIVO!$B$21/CÁLCULO_MÉDIAS!D$4*C16 -> 72.629599 | E16: 67.014915 | F16: =ORÇAMENTO_EXECUTIVO!$B$21/CÁLCULO_MÉDIAS!F$4*E16 -> 69.578329 | G16: 46.98982 | H16: =ORÇAMENTO_EXECUTIVO!$B$21/CÁLCULO_MÉDIAS!H$4*G16 -> 43.004194 | J16: =ORÇAMENTO_EXECUTIVO!$B$21/CÁLCULO_MÉDIAS!J$4*I16 -> #DIV/0! | L16: =H16 -> 43.004194 | M16: 75
B17: REVESTIMENTOS INTERNOS EM PISO E PAREDE | C17: 127.17234 | D17: =ORÇAMENTO_EXECUTIVO!$B$21/CÁLCULO_MÉDIAS!D$4*C17 -> 129.18192 | E17: 104.07903 | F17: =ORÇAMENTO_EXECUTIVO!$B$21/CÁLCULO_MÉDIAS!F$4*E17 -> 108.0602 | G17: 82.687573 | H17: =ORÇAMENTO_EXECUTIVO!$B$21/CÁLCULO_MÉDIAS!H$4*G17 -> 75.674101 | J17: =ORÇAMENTO_EXECUTIVO!$B$21/CÁLCULO_MÉDIAS!J$4*I17 -> #DIV/0! | L17: 73 | M17: 127
B18: REVESTIMENTOS E ACABAMENTOS INTERNOS EM TETO | C18: 51.710241 | D18: =ORÇAMENTO_EXECUTIVO!$B$21/CÁLCULO_MÉDIAS!D$4*C18 -> 52.527368 | E18: 55.942195 | F18: =ORÇAMENTO_EXECUTIVO!$B$21/CÁLCULO_MÉDIAS!F$4*E18 -> 58.082062 | G18: 45.051077 | H18: =ORÇAMENTO_EXECUTIVO!$B$21/CÁLCULO_MÉDIAS!H$4*G18 -> 41.229893 | J18: =ORÇAMENTO_EXECUTIVO!$B$21/CÁLCULO_MÉDIAS!J$4*I18 -> #DIV/0! | L18: 40 | M18: 60
B19: ACABAMENTOS EM PISO E PAREDE | C19: 127.19454 | D19: =ORÇAMENTO_EXECUTIVO!$B$21/CÁLCULO_MÉDIAS!D$4*C19 -> 129.20447 | E19: 127.69932 | F19: =ORÇAMENTO_EXECUTIVO!$B$21/CÁLCULO_MÉDIAS!F$4*E19 -> 132.584 | G19: 95.490652 | H19: =ORÇAMENTO_EXECUTIVO!$B$21/CÁLCULO_MÉDIAS!H$4*G19 -> 87.391237 | J19: =ORÇAMENTO_EXECUTIVO!$B$21/CÁLCULO_MÉDIAS!J$4*I19 -> #DIV/0! | L19: 85 | M19: 135
B20: PINTURA INTERNA | C20: 142.0894 | D20: =ORÇAMENTO_EXECUTIVO!$B$21/CÁLCULO_MÉDIAS!D$4*C20 -> 144.3347 | E20: 134.27942 | F20: =ORÇAMENTO_EXECUTIVO!$B$21/CÁLCULO_MÉDIAS!F$4*E20 -> 139.41579 | G20: 59.545028 | H20: =ORÇAMENTO_EXECUTIVO!$B$21/CÁLCULO_MÉDIAS!H$4*G20 -> 54.494482 | J20: =ORÇAMENTO_EXECUTIVO!$B$21/CÁLCULO_MÉDIAS!J$4*I20 -> #DIV/0! | L20: 53 | M20: 145
B21: ESQUADRIAS, VIDROS E FERRAGENS | C21: 285.14441 | D21: =ORÇAMENTO_EXECUTIVO!$B$21/CÁLCULO_MÉDIAS!D$4*C21 -> 289.65027 | E21: 267.60586 | F21: =ORÇAMENTO_EXECUTIVO!$B$21/CÁLCULO_MÉDIAS!F$4*E21 -> 277.84216 | G21: 343.36037 | H21: =ORÇAMENTO_EXECUTIVO!$B$21/CÁLCULO_MÉDIAS!H$4*G21 -> 314.23691 | J21: =ORÇAMENTO_EXECUTIVO!$B$21/CÁLCULO_MÉDIAS!J$4*I21 -> #DIV/0! | L21: 275 | M21: 315
B22: COBERTURA | C22: 19.789517 | D22: =ORÇAMENTO_EXECUTIVO!$B$21/CÁLCULO_MÉDIAS!D$4*C22 -> 20.102231 | E22: 32.594185 | F22: =ORÇAMENTO_EXECUTIVO!$B$21/CÁLCULO_MÉDIAS!F$4*E22 -> 33.840958 | G22: 10.637923 | H22: =ORÇAMENTO_EXECUTIVO!$B$21/CÁLCULO_MÉDIAS!H$4*G22 -> 9.7356262 | J22: =ORÇAMENTO_EXECUTIVO!$B$21/CÁLCULO_MÉDIAS!J$4*I22 -> #DIV/0! | L22: 8 | M22: 35
B23: REVESTIMENTOS E ACABAMENTOS DE FACHADA | C23: 97.260537 | D23: =ORÇAMENTO_EXECUTIVO!$B$21/CÁLCULO_MÉDIAS!D$4*C23 -> 98.797451 | E23: 95.59297 | F23: =ORÇAMENTO_EXECUTIVO!$B$21/CÁLCULO_MÉDIAS!F$4*E23 -> 99.249534 | G23: 153.50782 | H23: =ORÇAMENTO_EXECUTIVO!$B$21/CÁLCULO_MÉDIAS!H$4*G23 -> 140.48745 | J23: =ORÇAMENTO_EXECUTIVO!$B$21/CÁLCULO_MÉDIAS!J$4*I23 -> #DIV/0! | L23: 96 | M23: 142
B24: SERVIÇOS COMPLEMENTARES | C24: 123.79825 | D24: =ORÇAMENTO_EXECUTIVO!$B$21/CÁLCULO_MÉDIAS!D$4*C24 -> 125.75451 | E24: 120.57466 | F24: =ORÇAMENTO_EXECUTIVO!$B$21/CÁLCULO_MÉDIAS!F$4*E24 -> 125.18681 | G24: 170.49514 | H24: =ORÇAMENTO_EXECUTIVO!$B$21/CÁLCULO_MÉDIAS!H$4*G24 -> 156.03393 | J24: =ORÇAMENTO_EXECUTIVO!$B$21/CÁLCULO_MÉDIAS!J$4*I24 -> #DIV/0! | L24: 123 | M24: 158
B25: IMPREVISTOS E CONTINGENCIAS | C25: 97.260537 | D25: =ORÇAMENTO_EXECUTIVO!$B$21/CÁLCULO_MÉDIAS!D$4*C25 -> 98.797451 | E25: 95.59297 | F25: =ORÇAMENTO_EXECUTIVO!$B$21/CÁLCULO_MÉDIAS!F$4*E25 -> 99.249534 | G25: 40.946479 | H25: =ORÇAMENTO_EXECUTIVO!$B$21/CÁLCULO_MÉDIAS!H$4*G25 -> 37.473442 | J25: =ORÇAMENTO_EXECUTIVO!$B$21/CÁLCULO_MÉDIAS!J$4*I25 -> #DIV/0! | L25: 35 | M25: 102
B26: TOTAL | C26: =SUM(C8:C24) -> 3087.0093 | D26: =SUM(D8:D24) -> 3135.7903 | E26: =SUM(E8:E24) -> 3020.9579 | F26: =SUM(F8:F24) -> 3136.5138 | G26: =SUM(G8:G24) -> 3437.9073 | H26: =SUM(H8:H24) -> 3146.3077 | I26: =SUM(I8:I24) -> 0 | J26: =SUM(J8:J24) -> #DIV/0!
