Workbook
Name ____PK2: {"'장비'!$A$3:$M$12"}
Name ____PK2: {"'장비'!$A$3:$M$12"}
Name ____PK2: {"'장비'!$A$3:$M$12"}
Name ____PK2: {"'장비'!$A$3:$M$12"}
Name ____PK2: {"'장비'!$A$3:$M$12"}
Name ____PK2: {"'장비'!$A$3:$M$12"}
Name ____PK2: {"'장비'!$A$3:$M$12"}
Name ____PK2: {"'장비'!$A$3:$M$12"}
Name ____PKG3: {"'장비'!$A$3:$M$12"}
Name ____PKG3: {"'장비'!$A$3:$M$12"}
Name ____PKG3: {"'장비'!$A$3:$M$12"}
Name ____PKG3: {"'장비'!$A$3:$M$12"}
Name ____PKG3: {"'장비'!$A$3:$M$12"}
Name ____PKG3: {"'장비'!$A$3:$M$12"}
Name ____PKG3: {"'장비'!$A$3:$M$12"}
Name ____PKG3: {"'장비'!$A$3:$M$12"}
Name ____qqq222: {"'장비'!$A$3:$M$12"}
Name ____qqq222: {"'장비'!$A$3:$M$12"}
Name ____qqq222: {"'장비'!$A$3:$M$12"}
Name ____qqq222: {"'장비'!$A$3:$M$12"}
Name ____qqq222: {"'장비'!$A$3:$M$12"}
Name ____qqq222: {"'장비'!$A$3:$M$12"}
Name ____qqq222: {"'장비'!$A$3:$M$12"}
Name ____qqq222: {"'장비'!$A$3:$M$12"}
Name ___PK2: {"'장비'!$A$3:$M$12"}
Name ___PK2: {"'장비'!$A$3:$M$12"}
Name ___PK2: {"'장비'!$A$3:$M$12"}
Name ___PK2: {"'장비'!$A$3:$M$12"}
Name ___PK2: {"'장비'!$A$3:$M$12"}
Name ___PK2: {"'장비'!$A$3:$M$12"}
Name ___PK2: {"'장비'!$A$3:$M$12"}
Name ___PK2: {"'장비'!$A$3:$M$12"}
Name ___PKG3: {"'장비'!$A$3:$M$12"}
Name ___PKG3: {"'장비'!$A$3:$M$12"}
Name ___PKG3: {"'장비'!$A$3:$M$12"}
Name ___PKG3: {"'장비'!$A$3:$M$12"}
Name ___PKG3: {"'장비'!$A$3:$M$12"}
Name ___PKG3: {"'장비'!$A$3:$M$12"}
Name ___PKG3: {"'장비'!$A$3:$M$12"}
Name ___PKG3: {"'장비'!$A$3:$M$12"}
Name ___qqq222: {"'장비'!$A$3:$M$12"}
Name ___qqq222: {"'장비'!$A$3:$M$12"}
Name ___qqq222: {"'장비'!$A$3:$M$12"}
Name ___qqq222: {"'장비'!$A$3:$M$12"}
Name ___qqq222: {"'장비'!$A$3:$M$12"}
Name ___qqq222: {"'장비'!$A$3:$M$12"}
Name ___qqq222: {"'장비'!$A$3:$M$12"}
Name ___qqq222: {"'장비'!$A$3:$M$12"}
Name __PK2: {"'장비'!$A$3:$M$12"}
Name __PK2: {"'장비'!$A$3:$M$12"}
Name __PK2: {"'장비'!$A$3:$M$12"}
Name __PK2: {"'장비'!$A$3:$M$12"}
Name __PK2: {"'장비'!$A$3:$M$12"}
Name __PK2: {"'장비'!$A$3:$M$12"}
Name __PK2: {"'장비'!$A$3:$M$12"}
Name __PK2: {"'장비'!$A$3:$M$12"}
Name __PKG3: {"'장비'!$A$3:$M$12"}
Name __PKG3: {"'장비'!$A$3:$M$12"}
Name __PKG3: {"'장비'!$A$3:$M$12"}
Name __PKG3: {"'장비'!$A$3:$M$12"}

Sheet Planilha1
D1: =SUM(D2:D10) -> 10831779
C2: Mão de Obra de Empreitada Civil | D2: =Ger_Executivo!G278 -> 6499067.7 | E2: =-D2/$D$1 -> -0.6
C3: Mão de Obra Contenção | D3: =Ger_Executivo!G279 -> 216635.59 | E3: =-D3/$D$1 -> -0.02 | F3: Movimentação | G3: =0.54/66.25 -> 0.0081509434 | H3: 0.075 | I3: =H3*$D$2 -> 487430.07
C4: Mão de Obra de Empreitada Pintura | D4: =Ger_Executivo!G280 -> 1083177.9 | E4: =-D4/$D$1 -> -0.1 | F4: Infraestrutura | G4: =3.26/66.25 -> 0.049207547 | H4: 0.055 | I4: =H4*$D$2 -> 357448.72
C5: Mão de Obra de Empreitada Revestimento Cerâmicos | D5: =Ger_Executivo!G281 -> 1083177.9 | E5: =-D5/$D$1 -> -0.1 | F5: Supraestrutura | G5: =25/66.25 -> 0.37735849 | H5: 0.35 | I5: =H5*$D$2 -> 2274673.7
C6: Mão de Obra de Empreitada Limpeza Contínua e Ajudantes | D6: =Ger_Executivo!G282 -> 216635.59 | E6: =-D6/$D$1 -> -0.02 | F6: Alvenaria | G6: =10/66.25 -> 0.1509434 | H6: 0.12 | I6: =H6*$D$2 -> 779888.12
C7: Mão de Obra Instalações Hidrossanitárias | D7: =Ger_Executivo!G283 -> 649906.77 | E7: =-D7/$D$1 -> -0.06 | F7: Argamassado | G7: =26/66.25 -> 0.39245283 | H7: 0.35 | I7: =H7*$D$2 -> 2274673.7
C8: Mão de Obra Instalações Elétricas | D8: =Ger_Executivo!G284 -> 649906.77 | E8: =-D8/$D$1 -> -0.06 | F8: Cobertura | G8: =0.3/66.25 -> 0.0045283019 | H8: 0.04 | I8: =H8*$D$2 -> 259962.71
C9: Mão de Obra de Instalação de Louças e Metais | D9: =Ger_Executivo!G285 -> 108317.79 | E9: =-D9/$D$1 -> -0.01 | F9: Complementares | G9: =1.15/66.25 -> 0.017358491 | H9: 0.01 | I9: =H9*$D$2 -> 64990.677
C10: Mão de Obra Instalação de Portas e Rodapés | D10: =Ger_Executivo!G286 -> 324953.38 | E10: =-D10/$D$1 -> -0.03
H11: =SUM(H3:H9) -> 1 | I11: =SUM(G3:G9) -> 1

Sheet Obra 
C1: Projeto | D1: PARKSIDE RIO BRANCO
C2: Empresa | D2: PARKSIDE
C3: Revisão | D3: R00 -
A4: QUADRO DE ÁREAS
B6: Descrição | C6: Unidade | E6: Quantidade | G6: Imagens
B7: MESES DE OBRA | C7: MÊS | E7: =H9 -> 33 | G7: Início obra | H7: 46113
B8: ÁREA DO TERRENO | C8: M² | E8: 884.99 | G8: Conclusão meta | H8: 47088
B9: ÁREA CONSTRUÍDA | C9: M² | E9: =SUM(E14:E22) -> 8660.1 | G9: Total meses obra | H9: =ROUNDUP(((H8-H7)/30),0) -> 33
B10: NÚMERO DE UNIDADES HABITACIONAIS | C10: UN | E10: 160
B11: NÚMERO DE UNIDADES COMERCIAIS | C11: UN | E11: 3
B12: ÁREA PRIVATIVA | C12: M² | E12: 5303.81
B13: NÚMERO DE PAVIMENTOS | C13: UN | E13: 21
B14: Subsolo 2 | E14: 700.82
B15: Subsolo 1 | C15: M² | E15: =613.5 -> 613.5
B16: Térreo | C16: M² | E16: 560.05
B17: Pav 2 | C17: M² | E17: 403.28
B18: Garden | C18: M² | E18: 488.63
B19: Tipo (x15) | C19: M² | E19: =(15*365.41) -> 5481.15
B20: Cobertura | C20: M² | E20: 322.67
B21: Barrilete | C21: M² | E21: 45
B22: Reservatório | C22: M² | E22: 45
B31: ETAPA | C31: VALOR ORÇADO | D31: % | E31: VALOR / m²
B32: GERENCIAMENTO TÉCNICO E ADMINISTRATIVO | C32: =C33+C34 -> 1334002.8 | D32: =C32/C$68 -> 0.032403558 | E32: =C32/$E$9 -> 154.04012
B33: ='Ger_Tec e Adm'!J8 -> SERVIÇOS TÉCNICOS | C33: ='Ger_Tec e Adm'!N8 -> 412448.85 | D33: =C33/C$68 -> 0.010018577 | E33: =C33/$E$9 -> 47.626338
B34: ='Ger_Tec e Adm'!J21 -> SERVIÇOS PRELIMINARES E CANTEIRO | C34: ='Ger_Tec e Adm'!N21 -> 921553.96 | D34: =C34/C$68 -> 0.022384981 | E34: =C34/$E$9 -> 106.41378 | L34: =C35-C62 -> 18658249
B35: GERENCIAMENTO EXECUTIVO | C35: =C36+C41 -> 29490028 | D35: =C35/C$68 -> 0.7163267 | E35: =C35/$E$9 -> 3405.2757 | L35: =L34+C32 -> 19992251
B36: =Ger_Executivo!D8 -> INFRAESTRUTURA | C36: =Ger_Executivo!H8 -> 1566010.8 | D36: =C36/C$68 -> 0.038039142 | E36: =C36/$E$9 -> 180.83057
B37: =Ger_Executivo!D9 -> SERVIÇOS PRELIMINARES | C37: =Ger_Executivo!H9 -> 37755.331 | D37: =C37/C$68 -> 0.0009170948 | E37: =C37/$E$9 -> 4.3596876
B38: =Ger_Executivo!D12 -> SERVIÇOS EM TERRA | C38: =Ger_Executivo!H12 -> 340525.06 | D38: =C38/C$68 -> 0.0082715143 | E38: =C38/$E$9 -> 39.321146
B39: =Ger_Executivo!D22 -> CONTENÇÕES E FUNDAÇÕES | C39: =Ger_Executivo!H22 -> 1163561 | D39: =C39/C$68 -> 0.028263445 | E39: =C39/$E$9 -> 134.35884
B40: =Ger_Executivo!D34 -> DRENAGEM | C40: =Ger_Executivo!H34 -> 24169.458 | D40: =C40/C$68 -> 0.00058708753 | E40: =C40/$E$9 -> 2.7908982
B41: =Ger_Executivo!D39 -> OBRA | C41: =Ger_Executivo!H39 -> 27924017 | D41: =C41/C$68 -> 0.67828755 | E41: =C41/$E$9 -> 3224.4451
B42: =Ger_Executivo!D40 -> EQUIPAMENTOS | C42: =Ger_Executivo!H40 -> 863599.44 | D42: =C42/C$68 -> 0.020977238 | E42: =C42/$E$9 -> 99.721648
B43: =Ger_Executivo!D51 -> ESTRUTURAS | C43: =Ger_Executivo!H51 -> 3324999.5 | D43: =C43/C$68 -> 0.080765807 | E43: =C43/$E$9 -> 383.9447
B44: =Ger_Executivo!D63 -> COBERTURA | C44: =Ger_Executivo!H63 -> 31661.147 | D44: =C44/C$68 -> 0.0007690642 | E44: =C44/$E$9 -> 3.6559794
B45: =Ger_Executivo!D71 -> PAREDES E FECHAMENTOS | C45: =Ger_Executivo!H71 -> 743690.92 | D45: =C45/C$68 -> 0.018064603 | E45: =C45/$E$9 -> 85.875558
B46: =Ger_Executivo!D81 -> REVESTIMENTOS ARGAMASSADOS | C46: =Ger_Executivo!H81 -> 875012.99 | D46: =C46/C$68 -> 0.021254478 | E46: =C46/$E$9 -> 101.03959
B47: =Ger_Executivo!D94 -> IMPERMEABILIZAÇÃO | C47: =Ger_Executivo!H94 -> 411650.95 | D47: =C47/C$68 -> 0.0099991958 | E47: =C47/$E$9 -> 47.534203
B48: =Ger_Executivo!D130 -> INSTALAÇÕES ELÉTRICAS E TELECOMUNICAÇÕES | C48: =Ger_Executivo!H130 -> 1111154.4 | D48: =C48/C$68 -> 0.026990464 | E48: =C48/$E$9 -> 128.30734
B49: =Ger_Executivo!D142 -> INSTALAÇÕES HIDROSSANITÁRIAS | C49: =Ger_Executivo!H142 -> 1252179.6 | D49: =C49/C$68 -> 0.030416035 | E49: =C49/$E$9 -> 144.59182
B50: =Ger_Executivo!D157 -> INSTALAÇÕES DE GÁS E PREVENÇÃO DE INCÊNDIO | C50: =Ger_Executivo!H157 -> 364966.07 | D50: =C50/C$68 -> 0.008865198 | E50: =C50/$E$9 -> 42.143401
B51: =Ger_Executivo!D171 -> INSTALAÇÕES DE CLIMATIZAÇÃO | C51: =Ger_Executivo!H171 -> 476100 | D51: =C51/C$68 -> 0.011564694 | E51: =C51/$E$9 -> 54.97627
B52: =Ger_Executivo!D176 -> REVESTIMENTOS DE PISO E PAREDE | C52: =Ger_Executivo!H176 -> 1218828.7 | D52: =C52/C$68 -> 0.029605924 | E52: =C52/$E$9 -> 140.74072
B53: =Ger_Executivo!D195 -> FORROS | C53: =Ger_Executivo!H195 -> 1074213 | D53: =C53/C$68 -> 0.026093141 | E53: =C53/$E$9 -> 124.04164
B54: =Ger_Executivo!D198 -> PINTURA | C54: =Ger_Executivo!H198 -> 163980.39 | D54: =C54/C$68 -> 0.0039831611 | E54: =C54/$E$9 -> 18.935161
B55: =Ger_Executivo!D212 -> ESQUADRIAS | C55: =Ger_Executivo!H212 -> 1999128.1 | D55: =C55/C$68 -> 0.048559764 | E55: =C55/$E$9 -> 230.84353
B56: =Ger_Executivo!D227 -> MARMORARIA | C56: =Ger_Executivo!H227 -> 249074.93 | D56: =C56/C$68 -> 0.0060501476 | E56: =C56/$E$9 -> 28.761207
B57: =Ger_Executivo!D233 -> ELEVADOR E PLATAFORMA ELEVATÓRIA | C57: =Ger_Executivo!H233 -> 903000 | D57: =C57/C$68 -> 0.021934296 | E57: =C57/$E$9 -> 104.27131
B58: =Ger_Executivo!D236 -> SERRALHERIA | C58: =Ger_Executivo!H236 -> 817721.62 | D58: =C58/C$68 -> 0.019862844 | E58: =C58/$E$9 -> 94.424039
B59: =Ger_Executivo!D246 -> PAISAGISMO | C59: =Ger_Executivo!H246 -> 129901.5 | D59: =C59/C$68 -> 0.0031553687 | E59: =C59/$E$9 -> 15
B60: =Ger_Executivo!D249 -> LOUÇAS E METAIS | C60: =Ger_Executivo!H249 -> 553892.57 | D60: =C60/C$68 -> 0.013454312 | E60: =C60/$E$9 -> 63.959142
B61: =Ger_Executivo!D271 -> LIMPEZA | C61: =Ger_Executivo!H271 -> 235501.5 | D61: =C61/C$68 -> 0.0057204426 | E61: =C61/$E$9 -> 27.193855
B62: =Ger_Executivo!D276 -> CONTRATOS | C62: =Ger_Executivo!H276 -> 10831779 | D62: =C62/C$68 -> 0.26310903 | E62: =C62/$E$9 -> 1250.7684
B63: =Ger_Executivo!D287 -> OUTROS | C63: =Ger_Executivo!H287 -> 291980.48 | D63: =C63/C$68 -> 0.0070923435 | E63: =C63/$E$9 -> 33.715601
B64: CUSTOS ENXOVAL | C64: =C65 -> 10344375 | D64: =C64/C$68 -> 0.25126975 | E64: =C64/$E$9 -> 1194.4868
B65: ='Custos Enxoval'!J8 -> ENXOVAL | C65: ='Custos Enxoval'!N8 -> 10344375 | D65: =C65/C$68 -> 0.25126975 | E65: =C65/$E$9 -> 1194.4868
B66: ='Custos Enxoval'!J9 -> SISTEMAS INTERNOS | C66: ='Custos Enxoval'!N9 -> 95830.55 | D66: =C66/C$68 -> 0.0023277693 | E66: =C66/$E$9 -> 11.065756
B67: ='Custos Enxoval'!J14 -> MOBÍLIA E COMUNICAÇÃO VISUAL | C67: ='Custos Enxoval'!N14 -> 10248544 | D67: =C67/C$68 -> 0.24894198 | E67: =C67/$E$9 -> 1183.421
B68: TOTAL | C68: =C64+C35+C32 -> 41168406 | D68: =SUM(D32:D52) -> 1.7947723 | E68: =C68/E9 -> 4753.8026
B69: CUB/SC | C69: 2978.02 | D69: 45870 | E69: =ROUND(+E68/C69,2)&" CUB" -> 1,6 CUB
B72: Mão de obra Empreitada | C72: =42/100*C69*E9 -> 10831779

Sheet EAP ANALISE
A1: ETAPA | B1: VALOR ORÇADO | C1: % | D1: VALOR / m²
A2: GERENCIAMENTO TÉCNICO E ADMINISTRATIVO | B2: ='Obra '!C32+'Obra '!C42 -> 2197602.3 | C2: =B2/$B$29 -> 0.053380796 | D2: =B2/'Obra '!$E$9 -> 253.76176
A3: MOVIMENTAÇÃO DE TERRA | B3: =Ger_Executivo!H9+Ger_Executivo!H12 -> 378280.39 | C3: =B3/$B$29 -> 0.0091886091 | D3: =B3/'Obra '!$E$9 -> 43.680834
A4: INFRAESTRUTURA | B4: =Ger_Executivo!H23+Ger_Executivo!H34 -> 909261.04 | C4: =B4/$B$29 -> 0.02208638 | D4: =B4/'Obra '!$E$9 -> 104.99429 | G4: Mão de Obra de Empreitada Civil | H4: =Ger_Executivo!H278 -> 6499067.7
A5: CONTEÇÃO | B5: =Ger_Executivo!H29 -> 278469.38 | C5: =B5/$B$29 -> 0.0067641527 | D5: =B5/'Obra '!$E$9 -> 32.155447 | G5: Mão de Obra Mureta Guia | H5: =Ger_Executivo!H279 -> 216635.59
A6: SUPRAESTRUTURA | B6: =Ger_Executivo!H51 -> 3324999.5 | C6: =B6/$B$29 -> 0.080765807 | D6: =B6/'Obra '!$E$9 -> 383.9447 | G6: Estimativas / Mão de Obra Paredes de Diafragma | H6: =Ger_Executivo!#REF! -> #ERROR!
A7: ALVENARIA | B7: =Ger_Executivo!H71 -> 743690.92 | C7: =B7/$B$29 -> 0.018064603 | D7: =B7/'Obra '!$E$9 -> 85.875558 | G7: Mão de Obra de Empreitada Pintura | H7: =Ger_Executivo!H280 -> 1083177.9
A8: INSTALAÇÕES ELÉTRICAS, HIDRÁULICAS, GLP E PREVENTIVAS | B8: =Ger_Executivo!H130+Ger_Executivo!H142+Ger_Executivo!H157 -> 2728300.1 | C8: =B8/$B$29 -> 0.066271697 | D8: =B8/'Obra '!$E$9 -> 315.04256 | G8: Mão de Obra de Empreitada Revestimento Cerâmicos | H8: =Ger_Executivo!H281 -> 1083177.9
A9: CLIMATIZAÇÃO, EXAUSTÃO MECÂNICA E PRESSURIZAÇÃO | B9: =Ger_Executivo!H171 -> 476100 | C9: =B9/$B$29 -> 0.011564694 | D9: =B9/'Obra '!$E$9 -> 54.97627 | G9: Mão de Obra de Empreitada Limpeza Contínua e Ajudantes | H9: =Ger_Executivo!H282 -> 216635.59
A10: EQUIPAMENTOS E SISTEMAS ESPECIAIS | B10: =Ger_Executivo!H233 -> 903000 | C10: =B10/$B$29 -> 0.021934296 | D10: =B10/'Obra '!$E$9 -> 104.27131 | G10: Mão de Obra Instalações Hidrossanitárias | H10: =Ger_Executivo!H283 -> 649906.77
A11: INSTALAÇÕES ESPECIAIS | C11: =B11/$B$29 -> 0 | D11: =B11/'Obra '!$E$9 -> 0 | G11: Mão de Obra Instalações Elétricas | H11: =Ger_Executivo!H284 -> 649906.77
A12: REVESTIMENTOS ARGAMASSADOS PISO | B12: =Ger_Executivo!H90 -> 617052.6 | C12: =B12/$B$29 -> 0.014988499 | D12: =B12/'Obra '!$E$9 -> 71.252364 | G12: Mão de Obra de Instalação de Louças e Metais | H12: =Ger_Executivo!H285 -> 108317.79
A13: REVESTIMENTOS ARGAMASSADOS PAREDE | B13: =Ger_Executivo!H83 -> 148023.32 | C13: =B13/$B$29 -> 0.0035955562 | D13: =B13/'Obra '!$E$9 -> 17.092564 | G13: Mão de Obra Instalação de Portas e Rodapés | H13: =Ger_Executivo!H286 -> 324953.38
A14: REVESTIMENTOS ARGAMASSADOS TETO | C14: =B14/$B$29 -> 0 | D14: =B14/'Obra '!$E$9 -> 0
A15: IMPERMEABILIZAÇÃO | B15: =Ger_Executivo!H94 -> 411650.95 | C15: =B15/$B$29 -> 0.0099991958 | D15: =B15/'Obra '!$E$9 -> 47.534203
A16: ACABAMENTOS INTERNOS EM PAREDE E PISO | B16: =Ger_Executivo!H176+Ger_Executivo!H227 -> 1467903.6 | C16: =B16/$B$29 -> 0.035656072 | D16: =B16/'Obra '!$E$9 -> 169.50193
A17: ACABAMENTOS INTERNOS EM TETO | B17: =Ger_Executivo!H195 -> 1074213 | C17: =B17/$B$29 -> 0.026093141 | D17: =B17/'Obra '!$E$9 -> 124.04164
A18: PINTURA INTERNA | B18: =Ger_Executivo!H199 -> 114895.83 | C18: =B18/$B$29 -> 0.002790874 | D18: =B18/'Obra '!$E$9 -> 13.267264
A19: PINTURA DE FACHADA | B19: =Ger_Executivo!H207 -> 49084.56 | C19: =B19/$B$29 -> 0.0011922871 | D19: =B19/'Obra '!$E$9 -> 5.6678976
A20: REVESTIMENTOS ARGAMASSADOS DE FACHADA | B20: =Ger_Executivo!H86 -> 109937.07 | C20: =B20/$B$29 -> 0.0026704232 | D20: =B20/'Obra '!$E$9 -> 12.694665
A21: ACABAMENTOS DE FACHADA | C21: =B21/$B$29 -> 0 | D21: =B21/'Obra '!$E$9 -> 0
A22: ESQUADRIAS, VIDROS E FERRAGENS | B22: =Ger_Executivo!H212+Ger_Executivo!H236 -> 2816849.7 | C22: =B22/$B$29 -> 0.068422608 | D22: =B22/'Obra '!$E$9 -> 325.26757
A23: LOUÇAS E METAIS | B23: =Ger_Executivo!H249 -> 553892.57 | C23: =B23/$B$29 -> 0.013454312 | D23: =B23/'Obra '!$E$9 -> 63.959142
A24: COBERTURA | B24: =Ger_Executivo!H63 -> 31661.147 | C24: =B24/$B$29 -> 0.0007690642 | D24: =B24/'Obra '!$E$9 -> 3.6559794
A25: SERVIÇOS COMPLEMENTARES | B25: =Ger_Executivo!H246+Ger_Executivo!H271 -> 365403 | C25: =B25/$B$29 -> 0.0088758113 | D25: =B25/'Obra '!$E$9 -> 42.193855
A26: IMPREVISTOS | B26: =Ger_Executivo!H287 -> 291980.48 | C26: =B26/$B$29 -> 0.0070923435 | D26: =B26/'Obra '!$E$9 -> 33.715601
A27: EMPREITADA GLOBAL | B27: =Ger_Executivo!H276 -> 10831779 | C27: =B27/$B$29 -> 0.26310903 | D27: =B27/'Obra '!$E$9 -> 1250.7684
A28: ENXOVAL | B28: ='Custos Enxoval'!N8 -> 10344375 | C28: =B28/$B$29 -> 0.25126975 | D28: =B28/'Obra '!$E$9 -> 1194.4868
A29: TOTAL | B29: =SUM(B2:B28) -> 41168406 | C29: =SUM(C2:C28) -> 1 | D29: =SUM(D2:D28) -> 4753.8026
A30: CUB/SC | B30: ='Obra '!C69 -> 2978.02 | C30: ='Obra '!D69 -> 45870 | D30: =ROUNDUP(+D29/B30,2)&" CUB" -> 1,6 CUB

Sheet Ger_Tec e Adm
G4: PROJETO: | I4: ='Obra '!D1 -> PARKSIDE RIO BRANCO | O4: REVISÃO: | P4: DATA
G5: EMPRESA: | I5: ='Obra '!D2 -> PARKSIDE | O5: ='Obra '!D3 -> R00 - | P5: 45551
A6: Unidade Construtiva | B6: Célula Construtiva | C6: Etapa | D6: Subetapa | E6: Serviço | G6: GERENCIAMENTO EXECUTIVO
A7: 0 | B7: 0 | C7: 0 | D7: 0 | E7: 0 | G7: Atalho | H7: NIVEL | I7: Item | J7: Descrição | K7: Unidade | L7: Quant. | M7: Preço un | N7: Total | O7: Considerações | P7: Situação
A8: =IF($H8="UNIDADE CONSTRUTIVA",OFFSET(A8,-1,0)+1,LARGE(A$3:A7,1)) -> 0 | B8: =IF(H8="UNIDADE CONSTRUTIVA",0,IF(H8="CÉLULA CONSTRUTIVA",OFFSET(B8,-1,0)+1,OFFSET(B8,-1,0))) -> 1 | C8: =IF(H8="CÉLULA CONSTRUTIVA",0,IF(H8="ETAPA",OFFSET(C8,-1,0)+1,OFFSET(C8,-1,0))) -> 0 | D8: =IF(H8="ETAPA",0,IF(H8="SUBETAPA",OFFSET(D8,-1,0)+1,OFFSET(D8,-1,0))) -> 0 | E8: =IF(H8="Subetapa",0,IF(H8="serviço",OFFSET(E8,-1,0)+1,OFFSET(E8,-1,0))) -> 0 | H8: CÉLULA CONSTRUTIVA | I8: =IF(H8="Unidade Construtiva",TEXT(A8,"00"),IF(H8="Célula Construtiva",TEXT(B8,"00"),IF(H8="Etapa",CONCATENATE(TEXT(B8,"00"),".",TEXT(C8,"000")),IF(H8="Subetapa",CONCATENATE(TEXT(B8,"00"),".",TEXT(C8,"000"),".",TEXT(D8,"000")),IF(H8="Serviço",CONCATENATE(TEXT(B8,"00"),".",TEXT(C8,"000"),".",TEXT(D8,"000"),".",TEXT(E8,"000")),""))))) -> 01 | J8: SERVIÇOS TÉCNICOS | N8: =IF(H8="Serviço",M8*L8,IF(H8="CÉLULA CONSTRUTIVA",SUMIFS($N$8:$N$356,$B$8:$B$356,B8,$H$8:$H$356,"Serviço"),IF(H8="ETAPA",SUMIFS($N$8:$N$356,$B$8:$B$356,B8,$C$8:$C$356,C8,$H$8:$H$356,"Serviço"),IF(H8="SUBETAPA",SUMIFS($N$8:$N$356,$B$8:$B$356,B8,$C$8:$C$356,C8,$D$8:$D$356,D8,$H$8:$H$356,"Serviço"),0)))) -> 412448.85
A9: =IF($H9="UNIDADE CONSTRUTIVA",OFFSET(A9,-1,0)+1,LARGE(A$3:A8,1)) -> 0 | B9: =IF(H9="UNIDADE CONSTRUTIVA",0,IF(H9="CÉLULA CONSTRUTIVA",OFFSET(B9,-1,0)+1,OFFSET(B9,-1,0))) -> 1 | C9: =IF(H9="CÉLULA CONSTRUTIVA",0,IF(H9="ETAPA",OFFSET(C9,-1,0)+1,OFFSET(C9,-1,0))) -> 1 | D9: =IF(H9="ETAPA",0,IF(H9="SUBETAPA",OFFSET(D9,-1,0)+1,OFFSET(D9,-1,0))) -> 0 | E9: =IF(H9="Subetapa",0,IF(H9="serviço",OFFSET(E9,-1,0)+1,OFFSET(E9,-1,0))) -> 0 | H9: ETAPA | I9: =IF(H9="Unidade Construtiva",TEXT(A9,"00"),IF(H9="Célula Construtiva",TEXT(B9,"00"),IF(H9="Etapa",CONCATENATE(TEXT(B9,"00"),".",TEXT(C9,"000")),IF(H9="Subetapa",CONCATENATE(TEXT(B9,"00"),".",TEXT(C9,"000"),".",TEXT(D9,"000")),IF(H9="Serviço",CONCATENATE(TEXT(B9,"00"),".",TEXT(C9,"000"),".",TEXT(D9,"000"),".",TEXT(E9,"000")),""))))) -> 01.001 | J9: SERVIÇOS DE ENGENHARIA | N9: =IF(H9="Serviço",M9*L9,IF(H9="CÉLULA CONSTRUTIVA",SUMIFS($N$8:$N$356,$B$8:$B$356,B9,$H$8:$H$356,"Serviço"),IF(H9="ETAPA",SUMIFS($N$8:$N$356,$B$8:$B$356,B9,$C$8:$C$356,C9,$H$8:$H$356,"Serviço"),IF(H9="SUBETAPA",SUMIFS($N$8:$N$356,$B$8:$B$356,B9,$C$8:$C$356,C9,$D$8:$D$356,D9,$H$8:$H$356,"Serviço"),0)))) -> 412448.85
A10: =IF($H10="UNIDADE CONSTRUTIVA",OFFSET(A10,-1,0)+1,LARGE(A$3:A9,1)) -> 0 | B10: =IF(H10="UNIDADE CONSTRUTIVA",0,IF(H10="CÉLULA CONSTRUTIVA",OFFSET(B10,-1,0)+1,OFFSET(B10,-1,0))) -> 1 | C10: =IF(H10="CÉLULA CONSTRUTIVA",0,IF(H10="ETAPA",OFFSET(C10,-1,0)+1,OFFSET(C10,-1,0))) -> 1 | D10: =IF(H10="ETAPA",0,IF(H10="SUBETAPA",OFFSET(D10,-1,0)+1,OFFSET(D10,-1,0))) -> 1 | E10: =IF(H10="Subetapa",0,IF(H10="serviço",OFFSET(E10,-1,0)+1,OFFSET(E10,-1,0))) -> 0 | H10: SUBETAPA | I10: =IF(H10="Unidade Construtiva",TEXT(A10,"00"),IF(H10="Célula Construtiva",TEXT(B10,"00"),IF(H10="Etapa",CONCATENATE(TEXT(B10,"00"),".",TEXT(C10,"000")),IF(H10="Subetapa",CONCATENATE(TEXT(B10,"00"),".",TEXT(C10,"000"),".",TEXT(D10,"000")),IF(H10="Serviço",CONCATENATE(TEXT(B10,"00"),".",TEXT(C10,"000"),".",TEXT(D10,"000"),".",TEXT(E10,"000")),""))))) -> 01.001.001 | J10: PROJETOS | N10: =IF(H10="Serviço",M10*L10,IF(H10="CÉLULA CONSTRUTIVA",SUMIFS($N$8:$N$356,$B$8:$B$356,B10,$H$8:$H$356,"Serviço"),IF(H10="ETAPA",SUMIFS($N$8:$N$356,$B$8:$B$356,B10,$C$8:$C$356,C10,$H$8:$H$356,"Serviço"),IF(H10="SUBETAPA",SUMIFS($N$8:$N$356,$B$8:$B$356,B10,$C$8:$C$356,C10,$D$8:$D$356,D10,$H$8:$H$356,"Serviço"),0)))) -> 17060.944
A11: =IF($H11="UNIDADE CONSTRUTIVA",OFFSET(A11,-1,0)+1,LARGE(A$3:A10,1)) -> 0 | B11: =IF(H11="UNIDADE CONSTRUTIVA",0,IF(H11="CÉLULA CONSTRUTIVA",OFFSET(B11,-1,0)+1,OFFSET(B11,-1,0))) -> 1 | C11: =IF(H11="CÉLULA CONSTRUTIVA",0,IF(H11="ETAPA",OFFSET(C11,-1,0)+1,OFFSET(C11,-1,0))) -> 1 | D11: =IF(H11="ETAPA",0,IF(H11="SUBETAPA",OFFSET(D11,-1,0)+1,OFFSET(D11,-1,0))) -> 1 | E11: =IF(H11="Subetapa",0,IF(H11="serviço",OFFSET(E11,-1,0)+1,OFFSET(E11,-1,0))) -> 1 | H11: SERVIÇO | I11: =IF(H11="Unidade Construtiva",TEXT(A11,"00"),IF(H11="Célula Construtiva",TEXT(B11,"00"),IF(H11="Etapa",CONCATENATE(TEXT(B11,"00"),".",TEXT(C11,"000")),IF(H11="Subetapa",CONCATENATE(TEXT(B11,"00"),".",TEXT(C11,"000"),".",TEXT(D11,"000")),IF(H11="Serviço",CONCATENATE(TEXT(B11,"00"),".",TEXT(C11,"000"),".",TEXT(D11,"000"),".",TEXT(E11,"000")),""))))) -> 01.001.001.001 | J11: Projeto de Canteiro | K11: vb | L11: 1 | M11: 6174.8985 | N11: =IF(H11="Serviço",M11*L11,IF(H11="CÉLULA CONSTRUTIVA",SUMIFS($N$8:$N$356,$B$8:$B$356,B11,$H$8:$H$356,"Serviço"),IF(H11="ETAPA",SUMIFS($N$8:$N$356,$B$8:$B$356,B11,$C$8:$C$356,C11,$H$8:$H$356,"Serviço"),IF(H11="SUBETAPA",SUMIFS($N$8:$N$356,$B$8:$B$356,B11,$C$8:$C$356,C11,$D$8:$D$356,D11,$H$8:$H$356,"Serviço"),0)))) -> 6174.8985 | O11: Estimado com base em índices históricos | P11: Finalizado
A12: =IF($H12="UNIDADE CONSTRUTIVA",OFFSET(A12,-1,0)+1,LARGE(A$3:A11,1)) -> 0 | B12: =IF(H12="UNIDADE CONSTRUTIVA",0,IF(H12="CÉLULA CONSTRUTIVA",OFFSET(B12,-1,0)+1,OFFSET(B12,-1,0))) -> 1 | C12: =IF(H12="CÉLULA CONSTRUTIVA",0,IF(H12="ETAPA",OFFSET(C12,-1,0)+1,OFFSET(C12,-1,0))) -> 1 | D12: =IF(H12="ETAPA",0,IF(H12="SUBETAPA",OFFSET(D12,-1,0)+1,OFFSET(D12,-1,0))) -> 1 | E12: =IF(H12="Subetapa",0,IF(H12="serviço",OFFSET(E12,-1,0)+1,OFFSET(E12,-1,0))) -> 2 | H12: SERVIÇO | I12: =IF(H12="Unidade Construtiva",TEXT(A12,"00"),IF(H12="Célula Construtiva",TEXT(B12,"00"),IF(H12="Etapa",CONCATENATE(TEXT(B12,"00"),".",TEXT(C12,"000")),IF(H12="Subetapa",CONCATENATE(TEXT(B12,"00"),".",TEXT(C12,"000"),".",TEXT(D12,"000")),IF(H12="Serviço",CONCATENATE(TEXT(B12,"00"),".",TEXT(C12,"000"),".",TEXT(D12,"000"),".",TEXT(E12,"000")),""))))) -> 01.001.001.002 | J12: Estimativas / Sondagens | K12: vb | L12: 1 | M12: 10886.045 | N12: =IF(H12="Serviço",M12*L12,IF(H12="CÉLULA CONSTRUTIVA",SUMIFS($N$8:$N$356,$B$8:$B$356,B12,$H$8:$H$356,"Serviço"),IF(H12="ETAPA",SUMIFS($N$8:$N$356,$B$8:$B$356,B12,$C$8:$C$356,C12,$H$8:$H$356,"Serviço"),IF(H12="SUBETAPA",SUMIFS($N$8:$N$356,$B$8:$B$356,B12,$C$8:$C$356,C12,$D$8:$D$356,D12,$H$8:$H$356,"Serviço"),0)))) -> 10886.045 | O12: Estimado com base em índices históricos | P12: Finalizado
A13: =IF($H13="UNIDADE CONSTRUTIVA",OFFSET(A13,-1,0)+1,LARGE(A$3:A12,1)) -> 0 | B13: =IF(H13="UNIDADE CONSTRUTIVA",0,IF(H13="CÉLULA CONSTRUTIVA",OFFSET(B13,-1,0)+1,OFFSET(B13,-1,0))) -> 1 | C13: =IF(H13="CÉLULA CONSTRUTIVA",0,IF(H13="ETAPA",OFFSET(C13,-1,0)+1,OFFSET(C13,-1,0))) -> 1 | D13: =IF(H13="ETAPA",0,IF(H13="SUBETAPA",OFFSET(D13,-1,0)+1,OFFSET(D13,-1,0))) -> 2 | E13: =IF(H13="Subetapa",0,IF(H13="serviço",OFFSET(E13,-1,0)+1,OFFSET(E13,-1,0))) -> 0 | H13: SUBETAPA | I13: =IF(H13="Unidade Construtiva",TEXT(A13,"00"),IF(H13="Célula Construtiva",TEXT(B13,"00"),IF(H13="Etapa",CONCATENATE(TEXT(B13,"00"),".",TEXT(C13,"000")),IF(H13="Subetapa",CONCATENATE(TEXT(B13,"00"),".",TEXT(C13,"000"),".",TEXT(D13,"000")),IF(H13="Serviço",CONCATENATE(TEXT(B13,"00"),".",TEXT(C13,"000"),".",TEXT(D13,"000"),".",TEXT(E13,"000")),""))))) -> 01.001.002 | J13: CONSULTORIAS EXTERNAS | N13: =IF(H13="Serviço",M13*L13,IF(H13="CÉLULA CONSTRUTIVA",SUMIFS($N$8:$N$356,$B$8:$B$356,B13,$H$8:$H$356,"Serviço"),IF(H13="ETAPA",SUMIFS($N$8:$N$356,$B$8:$B$356,B13,$C$8:$C$356,C13,$H$8:$H$356,"Serviço"),IF(H13="SUBETAPA",SUMIFS($N$8:$N$356,$B$8:$B$356,B13,$C$8:$C$356,C13,$D$8:$D$356,D13,$H$8:$H$356,"Serviço"),0)))) -> 367830.52
A14: =IF($H14="UNIDADE CONSTRUTIVA",OFFSET(A14,-1,0)+1,LARGE(A$3:A13,1)) -> 0 | B14: =IF(H14="UNIDADE CONSTRUTIVA",0,IF(H14="CÉLULA CONSTRUTIVA",OFFSET(B14,-1,0)+1,OFFSET(B14,-1,0))) -> 1 | C14: =IF(H14="CÉLULA CONSTRUTIVA",0,IF(H14="ETAPA",OFFSET(C14,-1,0)+1,OFFSET(C14,-1,0))) -> 1 | D14: =IF(H14="ETAPA",0,IF(H14="SUBETAPA",OFFSET(D14,-1,0)+1,OFFSET(D14,-1,0))) -> 2 | E14: =IF(H14="Subetapa",0,IF(H14="serviço",OFFSET(E14,-1,0)+1,OFFSET(E14,-1,0))) -> 1 | H14: SERVIÇO | I14: =IF(H14="Unidade Construtiva",TEXT(A14,"00"),IF(H14="Célula Construtiva",TEXT(B14,"00"),IF(H14="Etapa",CONCATENATE(TEXT(B14,"00"),".",TEXT(C14,"000")),IF(H14="Subetapa",CONCATENATE(TEXT(B14,"00"),".",TEXT(C14,"000"),".",TEXT(D14,"000")),IF(H14="Serviço",CONCATENATE(TEXT(B14,"00"),".",TEXT(C14,"000"),".",TEXT(D14,"000"),".",TEXT(E14,"000")),""))))) -> 01.001.002.001 | J14: Programa de Segurança do Trabalho (PCMAT) | K14: vb | L14: 1 | M14: 5665.1418 | N14: =IF(H14="Serviço",M14*L14,IF(H14="CÉLULA CONSTRUTIVA",SUMIFS($N$8:$N$356,$B$8:$B$356,B14,$H$8:$H$356,"Serviço"),IF(H14="ETAPA",SUMIFS($N$8:$N$356,$B$8:$B$356,B14,$C$8:$C$356,C14,$H$8:$H$356,"Serviço"),IF(H14="SUBETAPA",SUMIFS($N$8:$N$356,$B$8:$B$356,B14,$C$8:$C$356,C14,$D$8:$D$356,D14,$H$8:$H$356,"Serviço"),0)))) -> 5665.1418 | O14: Estimado com base em índices históricos | P14: Finalizado
A15: =IF($H15="UNIDADE CONSTRUTIVA",OFFSET(A15,-1,0)+1,LARGE(A$3:A14,1)) -> 0 | B15: =IF(H15="UNIDADE CONSTRUTIVA",0,IF(H15="CÉLULA CONSTRUTIVA",OFFSET(B15,-1,0)+1,OFFSET(B15,-1,0))) -> 1 | C15: =IF(H15="CÉLULA CONSTRUTIVA",0,IF(H15="ETAPA",OFFSET(C15,-1,0)+1,OFFSET(C15,-1,0))) -> 1 | D15: =IF(H15="ETAPA",0,IF(H15="SUBETAPA",OFFSET(D15,-1,0)+1,OFFSET(D15,-1,0))) -> 2 | E15: =IF(H15="Subetapa",0,IF(H15="serviço",OFFSET(E15,-1,0)+1,OFFSET(E15,-1,0))) -> 2 | H15: SERVIÇO | I15: =IF(H15="Unidade Construtiva",TEXT(A15,"00"),IF(H15="Célula Construtiva",TEXT(B15,"00"),IF(H15="Etapa",CONCATENATE(TEXT(B15,"00"),".",TEXT(C15,"000")),IF(H15="Subetapa",CONCATENATE(TEXT(B15,"00"),".",TEXT(C15,"000"),".",TEXT(D15,"000")),IF(H15="Serviço",CONCATENATE(TEXT(B15,"00"),".",TEXT(C15,"000"),".",TEXT(D15,"000"),".",TEXT(E15,"000")),""))))) -> 01.001.002.002 | J15: Consultoria em Segurança do Trabalho | K15: mês | L15: 33 | M15: 10565.322 | N15: =IF(H15="Serviço",M15*L15,IF(H15="CÉLULA CONSTRUTIVA",SUMIFS($N$8:$N$356,$B$8:$B$356,B15,$H$8:$H$356,"Serviço"),IF(H15="ETAPA",SUMIFS($N$8:$N$356,$B$8:$B$356,B15,$C$8:$C$356,C15,$H$8:$H$356,"Serviço"),IF(H15="SUBETAPA",SUMIFS($N$8:$N$356,$B$8:$B$356,B15,$C$8:$C$356,C15,$D$8:$D$356,D15,$H$8:$H$356,"Serviço"),0)))) -> 348655.63 | O15: Estimado com base em índices históricos | P15: Finalizado
A16: =IF($H16="UNIDADE CONSTRUTIVA",OFFSET(A16,-1,0)+1,LARGE(A$3:A15,1)) -> 0 | B16: =IF(H16="UNIDADE CONSTRUTIVA",0,IF(H16="CÉLULA CONSTRUTIVA",OFFSET(B16,-1,0)+1,OFFSET(B16,-1,0))) -> 1 | C16: =IF(H16="CÉLULA CONSTRUTIVA",0,IF(H16="ETAPA",OFFSET(C16,-1,0)+1,OFFSET(C16,-1,0))) -> 1 | D16: =IF(H16="ETAPA",0,IF(H16="SUBETAPA",OFFSET(D16,-1,0)+1,OFFSET(D16,-1,0))) -> 2 | E16: =IF(H16="Subetapa",0,IF(H16="serviço",OFFSET(E16,-1,0)+1,OFFSET(E16,-1,0))) -> 3 | H16: SERVIÇO | I16: =IF(H16="Unidade Construtiva",TEXT(A16,"00"),IF(H16="Célula Construtiva",TEXT(B16,"00"),IF(H16="Etapa",CONCATENATE(TEXT(B16,"00"),".",TEXT(C16,"000")),IF(H16="Subetapa",CONCATENATE(TEXT(B16,"00"),".",TEXT(C16,"000"),".",TEXT(D16,"000")),IF(H16="Serviço",CONCATENATE(TEXT(B16,"00"),".",TEXT(C16,"000"),".",TEXT(D16,"000"),".",TEXT(E16,"000")),""))))) -> 01.001.002.003 | J16: Laudos e Vistorias / Vistoria Cautelar de Vizinhança | K16: vb | L16: 1 | M16: 13509.756 | N16: =IF(H16="Serviço",M16*L16,IF(H16="CÉLULA CONSTRUTIVA",SUMIFS($N$8:$N$356,$B$8:$B$356,B16,$H$8:$H$356,"Serviço"),IF(H16="ETAPA",SUMIFS($N$8:$N$356,$B$8:$B$356,B16,$C$8:$C$356,C16,$H$8:$H$356,"Serviço"),IF(H16="SUBETAPA",SUMIFS($N$8:$N$356,$B$8:$B$356,B16,$C$8:$C$356,C16,$D$8:$D$356,D16,$H$8:$H$356,"Serviço"),0)))) -> 13509.756 | O16: Estimado com base em índices históricos | P16: Finalizado
A17: =IF($H17="UNIDADE CONSTRUTIVA",OFFSET(A17,-1,0)+1,LARGE(A$3:A16,1)) -> 0 | B17: =IF(H17="UNIDADE CONSTRUTIVA",0,IF(H17="CÉLULA CONSTRUTIVA",OFFSET(B17,-1,0)+1,OFFSET(B17,-1,0))) -> 1 | C17: =IF(H17="CÉLULA CONSTRUTIVA",0,IF(H17="ETAPA",OFFSET(C17,-1,0)+1,OFFSET(C17,-1,0))) -> 1 | D17: =IF(H17="ETAPA",0,IF(H17="SUBETAPA",OFFSET(D17,-1,0)+1,OFFSET(D17,-1,0))) -> 3 | E17: =IF(H17="Subetapa",0,IF(H17="serviço",OFFSET(E17,-1,0)+1,OFFSET(E17,-1,0))) -> 0 | H17: SUBETAPA | I17: =IF(H17="Unidade Construtiva",TEXT(A17,"00"),IF(H17="Célula Construtiva",TEXT(B17,"00"),IF(H17="Etapa",CONCATENATE(TEXT(B17,"00"),".",TEXT(C17,"000")),IF(H17="Subetapa",CONCATENATE(TEXT(B17,"00"),".",TEXT(C17,"000"),".",TEXT(D17,"000")),IF(H17="Serviço",CONCATENATE(TEXT(B17,"00"),".",TEXT(C17,"000"),".",TEXT(D17,"000"),".",TEXT(E17,"000")),""))))) -> 01.001.003 | J17: SEGUROS | N17: =IF(H17="Serviço",M17*L17,IF(H17="CÉLULA CONSTRUTIVA",SUMIFS($N$8:$N$356,$B$8:$B$356,B17,$H$8:$H$356,"Serviço"),IF(H17="ETAPA",SUMIFS($N$8:$N$356,$B$8:$B$356,B17,$C$8:$C$356,C17,$H$8:$H$356,"Serviço"),IF(H17="SUBETAPA",SUMIFS($N$8:$N$356,$B$8:$B$356,B17,$C$8:$C$356,C17,$D$8:$D$356,D17,$H$8:$H$356,"Serviço"),0)))) -> 24373.298
A18: =IF($H18="UNIDADE CONSTRUTIVA",OFFSET(A18,-1,0)+1,LARGE(A$3:A17,1)) -> 0 | B18: =IF(H18="UNIDADE CONSTRUTIVA",0,IF(H18="CÉLULA CONSTRUTIVA",OFFSET(B18,-1,0)+1,OFFSET(B18,-1,0))) -> 1 | C18: =IF(H18="CÉLULA CONSTRUTIVA",0,IF(H18="ETAPA",OFFSET(C18,-1,0)+1,OFFSET(C18,-1,0))) -> 1 | D18: =IF(H18="ETAPA",0,IF(H18="SUBETAPA",OFFSET(D18,-1,0)+1,OFFSET(D18,-1,0))) -> 3 | E18: =IF(H18="Subetapa",0,IF(H18="serviço",OFFSET(E18,-1,0)+1,OFFSET(E18,-1,0))) -> 1 | H18: SERVIÇO | I18: =IF(H18="Unidade Construtiva",TEXT(A18,"00"),IF(H18="Célula Construtiva",TEXT(B18,"00"),IF(H18="Etapa",CONCATENATE(TEXT(B18,"00"),".",TEXT(C18,"000")),IF(H18="Subetapa",CONCATENATE(TEXT(B18,"00"),".",TEXT(C18,"000"),".",TEXT(D18,"000")),IF(H18="Serviço",CONCATENATE(TEXT(B18,"00"),".",TEXT(C18,"000"),".",TEXT(D18,"000"),".",TEXT(E18,"000")),""))))) -> 01.001.003.001 | J18: Seguros de Obra | K18: vb | L18: 1 | M18: 24373.297 | N18: =IF(H18="Serviço",M18*L18,IF(H18="CÉLULA CONSTRUTIVA",SUMIFS($N$8:$N$356,$B$8:$B$356,B18,$H$8:$H$356,"Serviço"),IF(H18="ETAPA",SUMIFS($N$8:$N$356,$B$8:$B$356,B18,$C$8:$C$356,C18,$H$8:$H$356,"Serviço"),IF(H18="SUBETAPA",SUMIFS($N$8:$N$356,$B$8:$B$356,B18,$C$8:$C$356,C18,$D$8:$D$356,D18,$H$8:$H$356,"Serviço"),0)))) -> 24373.298 | O18: Estimado com base em índices históricos | P18: Finalizado
A19: =IF($H19="UNIDADE CONSTRUTIVA",OFFSET(A19,-1,0)+1,LARGE(A$3:A18,1)) -> 0 | B19: =IF(H19="UNIDADE CONSTRUTIVA",0,IF(H19="CÉLULA CONSTRUTIVA",OFFSET(B19,-1,0)+1,OFFSET(B19,-1,0))) -> 1 | C19: =IF(H19="CÉLULA CONSTRUTIVA",0,IF(H19="ETAPA",OFFSET(C19,-1,0)+1,OFFSET(C19,-1,0))) -> 1 | D19: =IF(H19="ETAPA",0,IF(H19="SUBETAPA",OFFSET(D19,-1,0)+1,OFFSET(D19,-1,0))) -> 4 | E19: =IF(H19="Subetapa",0,IF(H19="serviço",OFFSET(E19,-1,0)+1,OFFSET(E19,-1,0))) -> 0 | H19: SUBETAPA | I19: =IF(H19="Unidade Construtiva",TEXT(A19,"00"),IF(H19="Célula Construtiva",TEXT(B19,"00"),IF(H19="Etapa",CONCATENATE(TEXT(B19,"00"),".",TEXT(C19,"000")),IF(H19="Subetapa",CONCATENATE(TEXT(B19,"00"),".",TEXT(C19,"000"),".",TEXT(D19,"000")),IF(H19="Serviço",CONCATENATE(TEXT(B19,"00"),".",TEXT(C19,"000"),".",TEXT(D19,"000"),".",TEXT(E19,"000")),""))))) -> 01.001.004 | J19: TAXAS E OUTROS | N19: =IF(H19="Serviço",M19*L19,IF(H19="CÉLULA CONSTRUTIVA",SUMIFS($N$8:$N$356,$B$8:$B$356,B19,$H$8:$H$356,"Serviço"),IF(H19="ETAPA",SUMIFS($N$8:$N$356,$B$8:$B$356,B19,$C$8:$C$356,C19,$H$8:$H$356,"Serviço"),IF(H19="SUBETAPA",SUMIFS($N$8:$N$356,$B$8:$B$356,B19,$C$8:$C$356,C19,$D$8:$D$356,D19,$H$8:$H$356,"Serviço"),0)))) -> 3184.0855
A20: =IF($H20="UNIDADE CONSTRUTIVA",OFFSET(A20,-1,0)+1,LARGE(A$3:A19,1)) -> 0 | B20: =IF(H20="UNIDADE CONSTRUTIVA",0,IF(H20="CÉLULA CONSTRUTIVA",OFFSET(B20,-1,0)+1,OFFSET(B20,-1,0))) -> 1 | C20: =IF(H20="CÉLULA CONSTRUTIVA",0,IF(H20="ETAPA",OFFSET(C20,-1,0)+1,OFFSET(C20,-1,0))) -> 1 | D20: =IF(H20="ETAPA",0,IF(H20="SUBETAPA",OFFSET(D20,-1,0)+1,OFFSET(D20,-1,0))) -> 4 | E20: =IF(H20="Subetapa",0,IF(H20="serviço",OFFSET(E20,-1,0)+1,OFFSET(E20,-1,0))) -> 1 | H20: SERVIÇO | I20: =IF(H20="Unidade Construtiva",TEXT(A20,"00"),IF(H20="Célula Construtiva",TEXT(B20,"00"),IF(H20="Etapa",CONCATENATE(TEXT(B20,"00"),".",TEXT(C20,"000")),IF(H20="Subetapa",CONCATENATE(TEXT(B20,"00"),".",TEXT(C20,"000"),".",TEXT(D20,"000")),IF(H20="Serviço",CONCATENATE(TEXT(B20,"00"),".",TEXT(C20,"000"),".",TEXT(D20,"000"),".",TEXT(E20,"000")),""))))) -> 01.001.004.001 | J20: ART de Execução | K20: vb | L20: 1 | M20: 3184.0855 | N20: =IF(H20="Serviço",M20*L20,IF(H20="CÉLULA CONSTRUTIVA",SUMIFS($N$8:$N$356,$B$8:$B$356,B20,$H$8:$H$356,"Serviço"),IF(H20="ETAPA",SUMIFS($N$8:$N$356,$B$8:$B$356,B20,$C$8:$C$356,C20,$H$8:$H$356,"Serviço"),IF(H20="SUBETAPA",SUMIFS($N$8:$N$356,$B$8:$B$356,B20,$C$8:$C$356,C20,$D$8:$D$356,D20,$H$8:$H$356,"Serviço"),0)))) -> 3184.0855 | O20: Estimado com base em índices históricos | P20: Finalizado
A21: =IF($H21="UNIDADE CONSTRUTIVA",OFFSET(A21,-1,0)+1,LARGE(A$3:A20,1)) -> 0 | B21: =IF(H21="UNIDADE CONSTRUTIVA",0,IF(H21="CÉLULA CONSTRUTIVA",OFFSET(B21,-1,0)+1,OFFSET(B21,-1,0))) -> 2 | C21: =IF(H21="CÉLULA CONSTRUTIVA",0,IF(H21="ETAPA",OFFSET(C21,-1,0)+1,OFFSET(C21,-1,0))) -> 0 | D21: =IF(H21="ETAPA",0,IF(H21="SUBETAPA",OFFSET(D21,-1,0)+1,OFFSET(D21,-1,0))) -> 4 | E21: =IF(H21="Subetapa",0,IF(H21="serviço",OFFSET(E21,-1,0)+1,OFFSET(E21,-1,0))) -> 1 | H21: CÉLULA CONSTRUTIVA | I21: =IF(H21="Unidade Construtiva",TEXT(A21,"00"),IF(H21="Célula Construtiva",TEXT(B21,"00"),IF(H21="Etapa",CONCATENATE(TEXT(B21,"00"),".",TEXT(C21,"000")),IF(H21="Subetapa",CONCATENATE(TEXT(B21,"00"),".",TEXT(C21,"000"),".",TEXT(D21,"000")),IF(H21="Serviço",CONCATENATE(TEXT(B21,"00"),".",TEXT(C21,"000"),".",TEXT(D21,"000"),".",TEXT(E21,"000")),""))))) -> 02 | J21: SERVIÇOS PRELIMINARES E CANTEIRO | N21: =IF(H21="Serviço",M21*L21,IF(H21="CÉLULA CONSTRUTIVA",SUMIFS($N$8:$N$356,$B$8:$B$356,B21,$H$8:$H$356,"Serviço"),IF(H21="ETAPA",SUMIFS($N$8:$N$356,$B$8:$B$356,B21,$C$8:$C$356,C21,$H$8:$H$356,"Serviço"),IF(H21="SUBETAPA",SUMIFS($N$8:$N$356,$B$8:$B$356,B21,$C$8:$C$356,C21,$D$8:$D$356,D21,$H$8:$H$356,"Serviço"),0)))) -> 921553.96
A22: =IF($H22="UNIDADE CONSTRUTIVA",OFFSET(A22,-1,0)+1,LARGE(A$3:A20,1)) -> 0 | B22: =IF(H22="UNIDADE CONSTRUTIVA",0,IF(H22="CÉLULA CONSTRUTIVA",OFFSET(B22,-1,0)+1,OFFSET(B22,-1,0))) -> 2 | C22: =IF(H22="CÉLULA CONSTRUTIVA",0,IF(H22="ETAPA",OFFSET(C22,-1,0)+1,OFFSET(C22,-1,0))) -> 1 | D22: =IF(H22="ETAPA",0,IF(H22="SUBETAPA",OFFSET(D22,-1,0)+1,OFFSET(D22,-1,0))) -> 0 | E22: =IF(H22="Subetapa",0,IF(H22="serviço",OFFSET(E22,-1,0)+1,OFFSET(E22,-1,0))) -> 1 | H22: ETAPA | I22: =IF(H22="Unidade Construtiva",TEXT(A22,"00"),IF(H22="Célula Construtiva",TEXT(B22,"00"),IF(H22="Etapa",CONCATENATE(TEXT(B22,"00"),".",TEXT(C22,"000")),IF(H22="Subetapa",CONCATENATE(TEXT(B22,"00"),".",TEXT(C22,"000"),".",TEXT(D22,"000")),IF(H22="Serviço",CONCATENATE(TEXT(B22,"00"),".",TEXT(C22,"000"),".",TEXT(D22,"000"),".",TEXT(E22,"000")),""))))) -> 02.001 | J22: DESPESAS INDIRETAS | N22: =IF(H22="Serviço",M22*L22,IF(H22="CÉLULA CONSTRUTIVA",SUMIFS($N$8:$N$356,$B$8:$B$356,B22,$H$8:$H$356,"Serviço"),IF(H22="ETAPA",SUMIFS($N$8:$N$356,$B$8:$B$356,B22,$C$8:$C$356,C22,$H$8:$H$356,"Serviço"),IF(H22="SUBETAPA",SUMIFS($N$8:$N$356,$B$8:$B$356,B22,$C$8:$C$356,C22,$D$8:$D$356,D22,$H$8:$H$356,"Serviço"),0)))) -> 397448.76
A23: =IF($H23="UNIDADE CONSTRUTIVA",OFFSET(A23,-1,0)+1,LARGE(A$3:A22,1)) -> 0 | B23: =IF(H23="UNIDADE CONSTRUTIVA",0,IF(H23="CÉLULA CONSTRUTIVA",OFFSET(B23,-1,0)+1,OFFSET(B23,-1,0))) -> 2 | C23: =IF(H23="CÉLULA CONSTRUTIVA",0,IF(H23="ETAPA",OFFSET(C23,-1,0)+1,OFFSET(C23,-1,0))) -> 1 | D23: =IF(H23="ETAPA",0,IF(H23="SUBETAPA",OFFSET(D23,-1,0)+1,OFFSET(D23,-1,0))) -> 1 | E23: =IF(H23="Subetapa",0,IF(H23="serviço",OFFSET(E23,-1,0)+1,OFFSET(E23,-1,0))) -> 0 | H23: SUBETAPA | I23: =IF(H23="Unidade Construtiva",TEXT(A23,"00"),IF(H23="Célula Construtiva",TEXT(B23,"00"),IF(H23="Etapa",CONCATENATE(TEXT(B23,"00"),".",TEXT(C23,"000")),IF(H23="Subetapa",CONCATENATE(TEXT(B23,"00"),".",TEXT(C23,"000"),".",TEXT(D23,"000")),IF(H23="Serviço",CONCATENATE(TEXT(B23,"00"),".",TEXT(C23,"000"),".",TEXT(D23,"000"),".",TEXT(E23,"000")),""))))) -> 02.001.001 | J23: DESPESAS INDIRETAS | N23: =IF(H23="Serviço",M23*L23,IF(H23="CÉLULA CONSTRUTIVA",SUMIFS($N$8:$N$356,$B$8:$B$356,B23,$H$8:$H$356,"Serviço"),IF(H23="ETAPA",SUMIFS($N$8:$N$356,$B$8:$B$356,B23,$C$8:$C$356,C23,$H$8:$H$356,"Serviço"),IF(H23="SUBETAPA",SUMIFS($N$8:$N$356,$B$8:$B$356,B23,$C$8:$C$356,C23,$D$8:$D$356,D23,$H$8:$H$356,"Serviço"),0)))) -> 397448.76
A24: =IF($H24="UNIDADE CONSTRUTIVA",OFFSET(A24,-1,0)+1,LARGE(A$3:A23,1)) -> 0 | B24: =IF(H24="UNIDADE CONSTRUTIVA",0,IF(H24="CÉLULA CONSTRUTIVA",OFFSET(B24,-1,0)+1,OFFSET(B24,-1,0))) -> 2 | C24: =IF(H24="CÉLULA CONSTRUTIVA",0,IF(H24="ETAPA",OFFSET(C24,-1,0)+1,OFFSET(C24,-1,0))) -> 1 | D24: =IF(H24="ETAPA",0,IF(H24="SUBETAPA",OFFSET(D24,-1,0)+1,OFFSET(D24,-1,0))) -> 1 | E24: =IF(H24="Subetapa",0,IF(H24="serviço",OFFSET(E24,-1,0)+1,OFFSET(E24,-1,0))) -> 1 | H24: SERVIÇO | I24: =IF(H24="Unidade Construtiva",TEXT(A24,"00"),IF(H24="Célula Construtiva",TEXT(B24,"00"),IF(H24="Etapa",CONCATENATE(TEXT(B24,"00"),".",TEXT(C24,"000")),IF(H24="Subetapa",CONCATENATE(TEXT(B24,"00"),".",TEXT(C24,"000"),".",TEXT(D24,"000")),IF(H24="Serviço",CONCATENATE(TEXT(B24,"00"),".",TEXT(C24,"000"),".",TEXT(D24,"000"),".",TEXT(E24,"000")),""))))) -> 02.001.001.001 | J24: Consumo de Água | K24: mes | L24: 33 | M24: 1621.5412 | N24: =IF(H24="Serviço",M24*L24,IF(H24="CÉLULA CONSTRUTIVA",SUMIFS($N$8:$N$356,$B$8:$B$356,B24,$H$8:$H$356,"Serviço"),IF(H24="ETAPA",SUMIFS($N$8:$N$356,$B$8:$B$356,B24,$C$8:$C$356,C24,$H$8:$H$356,"Serviço"),IF(H24="SUBETAPA",SUMIFS($N$8:$N$356,$B$8:$B$356,B24,$C$8:$C$356,C24,$D$8:$D$356,D24,$H$8:$H$356,"Serviço"),0)))) -> 53510.86 | O24: Estimado com base em índices históricos | P24: Finalizado
A25: =IF($H25="UNIDADE CONSTRUTIVA",OFFSET(A25,-1,0)+1,LARGE(A$3:A24,1)) -> 0 | B25: =IF(H25="UNIDADE CONSTRUTIVA",0,IF(H25="CÉLULA CONSTRUTIVA",OFFSET(B25,-1,0)+1,OFFSET(B25,-1,0))) -> 2 | C25: =IF(H25="CÉLULA CONSTRUTIVA",0,IF(H25="ETAPA",OFFSET(C25,-1,0)+1,OFFSET(C25,-1,0))) -> 1 | D25: =IF(H25="ETAPA",0,IF(H25="SUBETAPA",OFFSET(D25,-1,0)+1,OFFSET(D25,-1,0))) -> 1 | E25: =IF(H25="Subetapa",0,IF(H25="serviço",OFFSET(E25,-1,0)+1,OFFSET(E25,-1,0))) -> 2 | H25: SERVIÇO | I25: =IF(H25="Unidade Construtiva",TEXT(A25,"00"),IF(H25="Célula Construtiva",TEXT(B25,"00"),IF(H25="Etapa",CONCATENATE(TEXT(B25,"00"),".",TEXT(C25,"000")),IF(H25="Subetapa",CONCATENATE(TEXT(B25,"00"),".",TEXT(C25,"000"),".",TEXT(D25,"000")),IF(H25="Serviço",CONCATENATE(TEXT(B25,"00"),".",TEXT(C25,"000"),".",TEXT(D25,"000"),".",TEXT(E25,"000")),""))))) -> 02.001.001.002 | J25: Consumo de Telefone e Internet | K25: mes | L25: 33 | M25: 379.4236 | N25: =IF(H25="Serviço",M25*L25,IF(H25="CÉLULA CONSTRUTIVA",SUMIFS($N$8:$N$356,$B$8:$B$356,B25,$H$8:$H$356,"Serviço"),IF(H25="ETAPA",SUMIFS($N$8:$N$356,$B$8:$B$356,B25,$C$8:$C$356,C25,$H$8:$H$356,"Serviço"),IF(H25="SUBETAPA",SUMIFS($N$8:$N$356,$B$8:$B$356,B25,$C$8:$C$356,C25,$D$8:$D$356,D25,$H$8:$H$356,"Serviço"),0)))) -> 12520.979 | O25: Estimado com base em índices históricos | P25: Finalizado
A26: =IF($H26="UNIDADE CONSTRUTIVA",OFFSET(A26,-1,0)+1,LARGE(A$3:A25,1)) -> 0 | B26: =IF(H26="UNIDADE CONSTRUTIVA",0,IF(H26="CÉLULA CONSTRUTIVA",OFFSET(B26,-1,0)+1,OFFSET(B26,-1,0))) -> 2 | C26: =IF(H26="CÉLULA CONSTRUTIVA",0,IF(H26="ETAPA",OFFSET(C26,-1,0)+1,OFFSET(C26,-1,0))) -> 1 | D26: =IF(H26="ETAPA",0,IF(H26="SUBETAPA",OFFSET(D26,-1,0)+1,OFFSET(D26,-1,0))) -> 1 | E26: =IF(H26="Subetapa",0,IF(H26="serviço",OFFSET(E26,-1,0)+1,OFFSET(E26,-1,0))) -> 3 | H26: SERVIÇO | I26: =IF(H26="Unidade Construtiva",TEXT(A26,"00"),IF(H26="Célula Construtiva",TEXT(B26,"00"),IF(H26="Etapa",CONCATENATE(TEXT(B26,"00"),".",TEXT(C26,"000")),IF(H26="Subetapa",CONCATENATE(TEXT(B26,"00"),".",TEXT(C26,"000"),".",TEXT(D26,"000")),IF(H26="Serviço",CONCATENATE(TEXT(B26,"00"),".",TEXT(C26,"000"),".",TEXT(D26,"000"),".",TEXT(E26,"000")),""))))) -> 02.001.001.003 | J26: Consumo de Energia | K26: mes | L26: 33 | M26: 1578.8277 | N26: =IF(H26="Serviço",M26*L26,IF(H26="CÉLULA CONSTRUTIVA",SUMIFS($N$8:$N$356,$B$8:$B$356,B26,$H$8:$H$356,"Serviço"),IF(H26="ETAPA",SUMIFS($N$8:$N$356,$B$8:$B$356,B26,$C$8:$C$356,C26,$H$8:$H$356,"Serviço"),IF(H26="SUBETAPA",SUMIFS($N$8:$N$356,$B$8:$B$356,B26,$C$8:$C$356,C26,$D$8:$D$356,D26,$H$8:$H$356,"Serviço"),0)))) -> 52101.314 | O26: Estimado com base em índices históricos | P26: Finalizado
A27: =IF($H27="UNIDADE CONSTRUTIVA",OFFSET(A27,-1,0)+1,LARGE(A$3:A26,1)) -> 0 | B27: =IF(H27="UNIDADE CONSTRUTIVA",0,IF(H27="CÉLULA CONSTRUTIVA",OFFSET(B27,-1,0)+1,OFFSET(B27,-1,0))) -> 2 | C27: =IF(H27="CÉLULA CONSTRUTIVA",0,IF(H27="ETAPA",OFFSET(C27,-1,0)+1,OFFSET(C27,-1,0))) -> 1 | D27: =IF(H27="ETAPA",0,IF(H27="SUBETAPA",OFFSET(D27,-1,0)+1,OFFSET(D27,-1,0))) -> 1 | E27: =IF(H27="Subetapa",0,IF(H27="serviço",OFFSET(E27,-1,0)+1,OFFSET(E27,-1,0))) -> 4 | H27: SERVIÇO | I27: =IF(H27="Unidade Construtiva",TEXT(A27,"00"),IF(H27="Célula Construtiva",TEXT(B27,"00"),IF(H27="Etapa",CONCATENATE(TEXT(B27,"00"),".",TEXT(C27,"000")),IF(H27="Subetapa",CONCATENATE(TEXT(B27,"00"),".",TEXT(C27,"000"),".",TEXT(D27,"000")),IF(H27="Serviço",CONCATENATE(TEXT(B27,"00"),".",TEXT(C27,"000"),".",TEXT(D27,"000"),".",TEXT(E27,"000")),""))))) -> 02.001.001.004 | J27: Consumo de Fotocópias, Impressões e Plotagens | K27: mes | L27: 33 | M27: 2972.0228 | N27: =IF(H27="Serviço",M27*L27,IF(H27="CÉLULA CONSTRUTIVA",SUMIFS($N$8:$N$356,$B$8:$B$356,B27,$H$8:$H$356,"Serviço"),IF(H27="ETAPA",SUMIFS($N$8:$N$356,$B$8:$B$356,B27,$C$8:$C$356,C27,$H$8:$H$356,"Serviço"),IF(H27="SUBETAPA",SUMIFS($N$8:$N$356,$B$8:$B$356,B27,$C$8:$C$356,C27,$D$8:$D$356,D27,$H$8:$H$356,"Serviço"),0)))) -> 98076.751 | O27: Estimado com base em índices históricos | P27: Finalizado
A28: =IF($H28="UNIDADE CONSTRUTIVA",OFFSET(A28,-1,0)+1,LARGE(A$3:A27,1)) -> 0 | B28: =IF(H28="UNIDADE CONSTRUTIVA",0,IF(H28="CÉLULA CONSTRUTIVA",OFFSET(B28,-1,0)+1,OFFSET(B28,-1,0))) -> 2 | C28: =IF(H28="CÉLULA CONSTRUTIVA",0,IF(H28="ETAPA",OFFSET(C28,-1,0)+1,OFFSET(C28,-1,0))) -> 1 | D28: =IF(H28="ETAPA",0,IF(H28="SUBETAPA",OFFSET(D28,-1,0)+1,OFFSET(D28,-1,0))) -> 1 | E28: =IF(H28="Subetapa",0,IF(H28="serviço",OFFSET(E28,-1,0)+1,OFFSET(E28,-1,0))) -> 5 | H28: SERVIÇO | I28: =IF(H28="Unidade Construtiva",TEXT(A28,"00"),IF(H28="Célula Construtiva",TEXT(B28,"00"),IF(H28="Etapa",CONCATENATE(TEXT(B28,"00"),".",TEXT(C28,"000")),IF(H28="Subetapa",CONCATENATE(TEXT(B28,"00"),".",TEXT(C28,"000"),".",TEXT(D28,"000")),IF(H28="Serviço",CONCATENATE(TEXT(B28,"00"),".",TEXT(C28,"000"),".",TEXT(D28,"000"),".",TEXT(E28,"000")),""))))) -> 02.001.001.005 | J28: Equipamentos de Segurança do Trabalho | K28: vb | L28: 1 | M28: =EPCs!F81+CANTEIRO!D15 -> 143227.82 | N28: =IF(H28="Serviço",M28*L28,IF(H28="CÉLULA CONSTRUTIVA",SUMIFS($N$8:$N$356,$B$8:$B$356,B28,$H$8:$H$356,"Serviço"),IF(H28="ETAPA",SUMIFS($N$8:$N$356,$B$8:$B$356,B28,$C$8:$C$356,C28,$H$8:$H$356,"Serviço"),IF(H28="SUBETAPA",SUMIFS($N$8:$N$356,$B$8:$B$356,B28,$C$8:$C$356,C28,$D$8:$D$356,D28,$H$8:$H$356,"Serviço"),0)))) -> 143227.82 | O28: Conforme abas "CANTEIRO" e "EPC's" - Bandejas, guarda corpo, tela fachadeira, linha de vida, slqa, EPI | P28: Finalizado
A29: =IF($H29="UNIDADE CONSTRUTIVA",OFFSET(A29,-1,0)+1,LARGE(A$3:A28,1)) -> 0 | B29: =IF(H29="UNIDADE CONSTRUTIVA",0,IF(H29="CÉLULA CONSTRUTIVA",OFFSET(B29,-1,0)+1,OFFSET(B29,-1,0))) -> 2 | C29: =IF(H29="CÉLULA CONSTRUTIVA",0,IF(H29="ETAPA",OFFSET(C29,-1,0)+1,OFFSET(C29,-1,0))) -> 1 | D29: =IF(H29="ETAPA",0,IF(H29="SUBETAPA",OFFSET(D29,-1,0)+1,OFFSET(D29,-1,0))) -> 1 | E29: =IF(H29="Subetapa",0,IF(H29="serviço",OFFSET(E29,-1,0)+1,OFFSET(E29,-1,0))) -> 6 | H29: SERVIÇO | I29: =IF(H29="Unidade Construtiva",TEXT(A29,"00"),IF(H29="Célula Construtiva",TEXT(B29,"00"),IF(H29="Etapa",CONCATENATE(TEXT(B29,"00"),".",TEXT(C29,"000")),IF(H29="Subetapa",CONCATENATE(TEXT(B29,"00"),".",TEXT(C29,"000"),".",TEXT(D29,"000")),IF(H29="Serviço",CONCATENATE(TEXT(B29,"00"),".",TEXT(C29,"000"),".",TEXT(D29,"000"),".",TEXT(E29,"000")),""))))) -> 02.001.001.006 | J29: Monitoramento de Vigilância | K29: mes | L29: 33 | M29: 1060 | N29: =IF(H29="Serviço",M29*L29,IF(H29="CÉLULA CONSTRUTIVA",SUMIFS($N$8:$N$356,$B$8:$B$356,B29,$H$8:$H$356,"Serviço"),IF(H29="ETAPA",SUMIFS($N$8:$N$356,$B$8:$B$356,B29,$C$8:$C$356,C29,$H$8:$H$356,"Serviço"),IF(H29="SUBETAPA",SUMIFS($N$8:$N$356,$B$8:$B$356,B29,$C$8:$C$356,C29,$D$8:$D$356,D29,$H$8:$H$356,"Serviço"),0)))) -> 34980 | O29: Estimado com base em índices históricos | P29: Finalizado
A30: =IF($H30="UNIDADE CONSTRUTIVA",OFFSET(A30,-1,0)+1,LARGE(A$3:A29,1)) -> 0 | B30: =IF(H30="UNIDADE CONSTRUTIVA",0,IF(H30="CÉLULA CONSTRUTIVA",OFFSET(B30,-1,0)+1,OFFSET(B30,-1,0))) -> 2 | C30: =IF(H30="CÉLULA CONSTRUTIVA",0,IF(H30="ETAPA",OFFSET(C30,-1,0)+1,OFFSET(C30,-1,0))) -> 1 | D30: =IF(H30="ETAPA",0,IF(H30="SUBETAPA",OFFSET(D30,-1,0)+1,OFFSET(D30,-1,0))) -> 1 | E30: =IF(H30="Subetapa",0,IF(H30="serviço",OFFSET(E30,-1,0)+1,OFFSET(E30,-1,0))) -> 7 | H30: SERVIÇO | I30: =IF(H30="Unidade Construtiva",TEXT(A30,"00"),IF(H30="Célula Construtiva",TEXT(B30,"00"),IF(H30="Etapa",CONCATENATE(TEXT(B30,"00"),".",TEXT(C30,"000")),IF(H30="Subetapa",CONCATENATE(TEXT(B30,"00"),".",TEXT(C30,"000"),".",TEXT(D30,"000")),IF(H30="Serviço",CONCATENATE(TEXT(B30,"00"),".",TEXT(C30,"000"),".",TEXT(D30,"000"),".",TEXT(E30,"000")),""))))) -> 02.001.001.007 | J30: Equipamentos e Instalação para Segurança e Monitoramento | K30: vb | L30: 1 | M30: 3031.035 | N30: =IF(H30="Serviço",M30*L30,IF(H30="CÉLULA CONSTRUTIVA",SUMIFS($N$8:$N$356,$B$8:$B$356,B30,$H$8:$H$356,"Serviço"),IF(H30="ETAPA",SUMIFS($N$8:$N$356,$B$8:$B$356,B30,$C$8:$C$356,C30,$H$8:$H$356,"Serviço"),IF(H30="SUBETAPA",SUMIFS($N$8:$N$356,$B$8:$B$356,B30,$C$8:$C$356,C30,$D$8:$D$356,D30,$H$8:$H$356,"Serviço"),0)))) -> 3031.035 | O30: Estimado com base em índices históricos | P30: Finalizado
A31: =IF($H31="UNIDADE CONSTRUTIVA",OFFSET(A31,-1,0)+1,LARGE(A$3:A30,1)) -> 0 | B31: =IF(H31="UNIDADE CONSTRUTIVA",0,IF(H31="CÉLULA CONSTRUTIVA",OFFSET(B31,-1,0)+1,OFFSET(B31,-1,0))) -> 2 | C31: =IF(H31="CÉLULA CONSTRUTIVA",0,IF(H31="ETAPA",OFFSET(C31,-1,0)+1,OFFSET(C31,-1,0))) -> 2 | D31: =IF(H31="ETAPA",0,IF(H31="SUBETAPA",OFFSET(D31,-1,0)+1,OFFSET(D31,-1,0))) -> 0 | E31: =IF(H31="Subetapa",0,IF(H31="serviço",OFFSET(E31,-1,0)+1,OFFSET(E31,-1,0))) -> 7 | H31: ETAPA | I31: =IF(H31="Unidade Construtiva",TEXT(A31,"00"),IF(H31="Célula Construtiva",TEXT(B31,"00"),IF(H31="Etapa",CONCATENATE(TEXT(B31,"00"),".",TEXT(C31,"000")),IF(H31="Subetapa",CONCATENATE(TEXT(B31,"00"),".",TEXT(C31,"000"),".",TEXT(D31,"000")),IF(H31="Serviço",CONCATENATE(TEXT(B31,"00"),".",TEXT(C31,"000"),".",TEXT(D31,"000"),".",TEXT(E31,"000")),""))))) -> 02.002 | J31: INSTALAÇÕES PROVISÓRIAS | N31: =IF(H31="Serviço",M31*L31,IF(H31="CÉLULA CONSTRUTIVA",SUMIFS($N$8:$N$356,$B$8:$B$356,B31,$H$8:$H$356,"Serviço"),IF(H31="ETAPA",SUMIFS($N$8:$N$356,$B$8:$B$356,B31,$C$8:$C$356,C31,$H$8:$H$356,"Serviço"),IF(H31="SUBETAPA",SUMIFS($N$8:$N$356,$B$8:$B$356,B31,$C$8:$C$356,C31,$D$8:$D$356,D31,$H$8:$H$356,"Serviço"),0)))) -> 524105.2
A32: =IF($H32="UNIDADE CONSTRUTIVA",OFFSET(A32,-1,0)+1,LARGE(A$3:A31,1)) -> 0 | B32: =IF(H32="UNIDADE CONSTRUTIVA",0,IF(H32="CÉLULA CONSTRUTIVA",OFFSET(B32,-1,0)+1,OFFSET(B32,-1,0))) -> 2 | C32: =IF(H32="CÉLULA CONSTRUTIVA",0,IF(H32="ETAPA",OFFSET(C32,-1,0)+1,OFFSET(C32,-1,0))) -> 2 | D32: =IF(H32="ETAPA",0,IF(H32="SUBETAPA",OFFSET(D32,-1,0)+1,OFFSET(D32,-1,0))) -> 1 | E32: =IF(H32="Subetapa",0,IF(H32="serviço",OFFSET(E32,-1,0)+1,OFFSET(E32,-1,0))) -> 0 | H32: SUBETAPA | I32: =IF(H32="Unidade Construtiva",TEXT(A32,"00"),IF(H32="Célula Construtiva",TEXT(B32,"00"),IF(H32="Etapa",CONCATENATE(TEXT(B32,"00"),".",TEXT(C32,"000")),IF(H32="Subetapa",CONCATENATE(TEXT(B32,"00"),".",TEXT(C32,"000"),".",TEXT(D32,"000")),IF(H32="Serviço",CONCATENATE(TEXT(B32,"00"),".",TEXT(C32,"000"),".",TEXT(D32,"000"),".",TEXT(E32,"000")),""))))) -> 02.002.001 | J32: LIGAÇÕES | N32: =IF(H32="Serviço",M32*L32,IF(H32="CÉLULA CONSTRUTIVA",SUMIFS($N$8:$N$356,$B$8:$B$356,B32,$H$8:$H$356,"Serviço"),IF(H32="ETAPA",SUMIFS($N$8:$N$356,$B$8:$B$356,B32,$C$8:$C$356,C32,$H$8:$H$356,"Serviço"),IF(H32="SUBETAPA",SUMIFS($N$8:$N$356,$B$8:$B$356,B32,$C$8:$C$356,C32,$D$8:$D$356,D32,$H$8:$H$356,"Serviço"),0)))) -> 5100
A33: =IF($H33="UNIDADE CONSTRUTIVA",OFFSET(A33,-1,0)+1,LARGE(A$3:A32,1)) -> 0 | B33: =IF(H33="UNIDADE CONSTRUTIVA",0,IF(H33="CÉLULA CONSTRUTIVA",OFFSET(B33,-1,0)+1,OFFSET(B33,-1,0))) -> 2 | C33: =IF(H33="CÉLULA CONSTRUTIVA",0,IF(H33="ETAPA",OFFSET(C33,-1,0)+1,OFFSET(C33,-1,0))) -> 2 | D33: =IF(H33="ETAPA",0,IF(H33="SUBETAPA",OFFSET(D33,-1,0)+1,OFFSET(D33,-1,0))) -> 1 | E33: =IF(H33="Subetapa",0,IF(H33="serviço",OFFSET(E33,-1,0)+1,OFFSET(E33,-1,0))) -> 1 | H33: SERVIÇO | I33: =IF(H33="Unidade Construtiva",TEXT(A33,"00"),IF(H33="Célula Construtiva",TEXT(B33,"00"),IF(H33="Etapa",CONCATENATE(TEXT(B33,"00"),".",TEXT(C33,"000")),IF(H33="Subetapa",CONCATENATE(TEXT(B33,"00"),".",TEXT(C33,"000"),".",TEXT(D33,"000")),IF(H33="Serviço",CONCATENATE(TEXT(B33,"00"),".",TEXT(C33,"000"),".",TEXT(D33,"000"),".",TEXT(E33,"000")),""))))) -> 02.002.001.001 | J33: Ligação Provisória de Água | K33: vb | L33: 1 | M33: 300 | N33: =IF(H33="Serviço",M33*L33,IF(H33="CÉLULA CONSTRUTIVA",SUMIFS($N$8:$N$356,$B$8:$B$356,B33,$H$8:$H$356,"Serviço"),IF(H33="ETAPA",SUMIFS($N$8:$N$356,$B$8:$B$356,B33,$C$8:$C$356,C33,$H$8:$H$356,"Serviço"),IF(H33="SUBETAPA",SUMIFS($N$8:$N$356,$B$8:$B$356,B33,$C$8:$C$356,C33,$D$8:$D$356,D33,$H$8:$H$356,"Serviço"),0)))) -> 300 | O33: Estimado com base em índices históricos - Taxa de ligação | P33: Finalizado
A34: =IF($H34="UNIDADE CONSTRUTIVA",OFFSET(A34,-1,0)+1,LARGE(A$3:A33,1)) -> 0 | B34: =IF(H34="UNIDADE CONSTRUTIVA",0,IF(H34="CÉLULA CONSTRUTIVA",OFFSET(B34,-1,0)+1,OFFSET(B34,-1,0))) -> 2 | C34: =IF(H34="CÉLULA CONSTRUTIVA",0,IF(H34="ETAPA",OFFSET(C34,-1,0)+1,OFFSET(C34,-1,0))) -> 2 | D34: =IF(H34="ETAPA",0,IF(H34="SUBETAPA",OFFSET(D34,-1,0)+1,OFFSET(D34,-1,0))) -> 1 | E34: =IF(H34="Subetapa",0,IF(H34="serviço",OFFSET(E34,-1,0)+1,OFFSET(E34,-1,0))) -> 2 | H34: SERVIÇO | I34: =IF(H34="Unidade Construtiva",TEXT(A34,"00"),IF(H34="Célula Construtiva",TEXT(B34,"00"),IF(H34="Etapa",CONCATENATE(TEXT(B34,"00"),".",TEXT(C34,"000")),IF(H34="Subetapa",CONCATENATE(TEXT(B34,"00"),".",TEXT(C34,"000"),".",TEXT(D34,"000")),IF(H34="Serviço",CONCATENATE(TEXT(B34,"00"),".",TEXT(C34,"000"),".",TEXT(D34,"000"),".",TEXT(E34,"000")),""))))) -> 02.002.001.002 | J34: Ligação Provisória Trifásica Distância=25m | K34: vb | L34: 1 | M34: =1000+3000+800 -> 4800 | N34: =IF(H34="Serviço",M34*L34,IF(H34="CÉLULA CONSTRUTIVA",SUMIFS($N$8:$N$356,$B$8:$B$356,B34,$H$8:$H$356,"Serviço"),IF(H34="ETAPA",SUMIFS($N$8:$N$356,$B$8:$B$356,B34,$C$8:$C$356,C34,$H$8:$H$356,"Serviço"),IF(H34="SUBETAPA",SUMIFS($N$8:$N$356,$B$8:$B$356,B34,$C$8:$C$356,C34,$D$8:$D$356,D34,$H$8:$H$356,"Serviço"),0)))) -> 4800 | O34: Estimado com base em índices históricos - Taxa + ligação | P34: Finalizado
A35: =IF($H35="UNIDADE CONSTRUTIVA",OFFSET(A35,-1,0)+1,LARGE(A$3:A34,1)) -> 0 | B35: =IF(H35="UNIDADE CONSTRUTIVA",0,IF(H35="CÉLULA CONSTRUTIVA",OFFSET(B35,-1,0)+1,OFFSET(B35,-1,0))) -> 2 | C35: =IF(H35="CÉLULA CONSTRUTIVA",0,IF(H35="ETAPA",OFFSET(C35,-1,0)+1,OFFSET(C35,-1,0))) -> 2 | D35: =IF(H35="ETAPA",0,IF(H35="SUBETAPA",OFFSET(D35,-1,0)+1,OFFSET(D35,-1,0))) -> 2 | E35: =IF(H35="Subetapa",0,IF(H35="serviço",OFFSET(E35,-1,0)+1,OFFSET(E35,-1,0))) -> 0 | H35: SUBETAPA | I35: =IF(H35="Unidade Construtiva",TEXT(A35,"00"),IF(H35="Célula Construtiva",TEXT(B35,"00"),IF(H35="Etapa",CONCATENATE(TEXT(B35,"00"),".",TEXT(C35,"000")),IF(H35="Subetapa",CONCATENATE(TEXT(B35,"00"),".",TEXT(C35,"000"),".",TEXT(D35,"000")),IF(H35="Serviço",CONCATENATE(TEXT(B35,"00"),".",TEXT(C35,"000"),".",TEXT(D35,"000"),".",TEXT(E35,"000")),""))))) -> 02.002.002 | J35: REDES PROVISÓRIAS | N35: =IF(H35="Serviço",M35*L35,IF(H35="CÉLULA CONSTRUTIVA",SUMIFS($N$8:$N$356,$B$8:$B$356,B35,$H$8:$H$356,"Serviço"),IF(H35="ETAPA",SUMIFS($N$8:$N$356,$B$8:$B$356,B35,$C$8:$C$356,C35,$H$8:$H$356,"Serviço"),IF(H35="SUBETAPA",SUMIFS($N$8:$N$356,$B$8:$B$356,B35,$C$8:$C$356,C35,$D$8:$D$356,D35,$H$8:$H$356,"Serviço"),0)))) -> 19589.289
A36: =IF($H36="UNIDADE CONSTRUTIVA",OFFSET(A36,-1,0)+1,LARGE(A$3:A35,1)) -> 0 | B36: =IF(H36="UNIDADE CONSTRUTIVA",0,IF(H36="CÉLULA CONSTRUTIVA",OFFSET(B36,-1,0)+1,OFFSET(B36,-1,0))) -> 2 | C36: =IF(H36="CÉLULA CONSTRUTIVA",0,IF(H36="ETAPA",OFFSET(C36,-1,0)+1,OFFSET(C36,-1,0))) -> 2 | D36: =IF(H36="ETAPA",0,IF(H36="SUBETAPA",OFFSET(D36,-1,0)+1,OFFSET(D36,-1,0))) -> 2 | E36: =IF(H36="Subetapa",0,IF(H36="serviço",OFFSET(E36,-1,0)+1,OFFSET(E36,-1,0))) -> 1 | H36: SERVIÇO | I36: =IF(H36="Unidade Construtiva",TEXT(A36,"00"),IF(H36="Célula Construtiva",TEXT(B36,"00"),IF(H36="Etapa",CONCATENATE(TEXT(B36,"00"),".",TEXT(C36,"000")),IF(H36="Subetapa",CONCATENATE(TEXT(B36,"00"),".",TEXT(C36,"000"),".",TEXT(D36,"000")),IF(H36="Serviço",CONCATENATE(TEXT(B36,"00"),".",TEXT(C36,"000"),".",TEXT(D36,"000"),".",TEXT(E36,"000")),""))))) -> 02.002.002.001 | J36: Rede de Água Provisória | K36: vb | L36: 1 | M36: 10439.393 | N36: =IF(H36="Serviço",M36*L36,IF(H36="CÉLULA CONSTRUTIVA",SUMIFS($N$8:$N$356,$B$8:$B$356,B36,$H$8:$H$356,"Serviço"),IF(H36="ETAPA",SUMIFS($N$8:$N$356,$B$8:$B$356,B36,$C$8:$C$356,C36,$H$8:$H$356,"Serviço"),IF(H36="SUBETAPA",SUMIFS($N$8:$N$356,$B$8:$B$356,B36,$C$8:$C$356,C36,$D$8:$D$356,D36,$H$8:$H$356,"Serviço"),0)))) -> 10439.393 | O36: Estimado com base em índices históricos | P36: Finalizado
A37: =IF($H37="UNIDADE CONSTRUTIVA",OFFSET(A37,-1,0)+1,LARGE(A$3:A36,1)) -> 0 | B37: =IF(H37="UNIDADE CONSTRUTIVA",0,IF(H37="CÉLULA CONSTRUTIVA",OFFSET(B37,-1,0)+1,OFFSET(B37,-1,0))) -> 2 | C37: =IF(H37="CÉLULA CONSTRUTIVA",0,IF(H37="ETAPA",OFFSET(C37,-1,0)+1,OFFSET(C37,-1,0))) -> 2 | D37: =IF(H37="ETAPA",0,IF(H37="SUBETAPA",OFFSET(D37,-1,0)+1,OFFSET(D37,-1,0))) -> 2 | E37: =IF(H37="Subetapa",0,IF(H37="serviço",OFFSET(E37,-1,0)+1,OFFSET(E37,-1,0))) -> 2 | H37: SERVIÇO | I37: =IF(H37="Unidade Construtiva",TEXT(A37,"00"),IF(H37="Célula Construtiva",TEXT(B37,"00"),IF(H37="Etapa",CONCATENATE(TEXT(B37,"00"),".",TEXT(C37,"000")),IF(H37="Subetapa",CONCATENATE(TEXT(B37,"00"),".",TEXT(C37,"000"),".",TEXT(D37,"000")),IF(H37="Serviço",CONCATENATE(TEXT(B37,"00"),".",TEXT(C37,"000"),".",TEXT(D37,"000"),".",TEXT(E37,"000")),""))))) -> 02.002.002.002 | J37: Rede de Energia Provisória | K37: vb | L37: 1 | M37: 9149.8965 | N37: =IF(H37="Serviço",M37*L37,IF(H37="CÉLULA CONSTRUTIVA",SUMIFS($N$8:$N$356,$B$8:$B$356,B37,$H$8:$H$356,"Serviço"),IF(H37="ETAPA",SUMIFS($N$8:$N$356,$B$8:$B$356,B37,$C$8:$C$356,C37,$H$8:$H$356,"Serviço"),IF(H37="SUBETAPA",SUMIFS($N$8:$N$356,$B$8:$B$356,B37,$C$8:$C$356,C37,$D$8:$D$356,D37,$H$8:$H$356,"Serviço"),0)))) -> 9149.8965 | O37: Estimado com base em índices históricos | P37: Finalizado
A38: =IF($H38="UNIDADE CONSTRUTIVA",OFFSET(A38,-1,0)+1,LARGE(A$3:A37,1)) -> 0 | B38: =IF(H38="UNIDADE CONSTRUTIVA",0,IF(H38="CÉLULA CONSTRUTIVA",OFFSET(B38,-1,0)+1,OFFSET(B38,-1,0))) -> 2 | C38: =IF(H38="CÉLULA CONSTRUTIVA",0,IF(H38="ETAPA",OFFSET(C38,-1,0)+1,OFFSET(C38,-1,0))) -> 2 | D38: =IF(H38="ETAPA",0,IF(H38="SUBETAPA",OFFSET(D38,-1,0)+1,OFFSET(D38,-1,0))) -> 3 | E38: =IF(H38="Subetapa",0,IF(H38="serviço",OFFSET(E38,-1,0)+1,OFFSET(E38,-1,0))) -> 0 | H38: SUBETAPA | I38: =IF(H38="Unidade Construtiva",TEXT(A38,"00"),IF(H38="Célula Construtiva",TEXT(B38,"00"),IF(H38="Etapa",CONCATENATE(TEXT(B38,"00"),".",TEXT(C38,"000")),IF(H38="Subetapa",CONCATENATE(TEXT(B38,"00"),".",TEXT(C38,"000"),".",TEXT(D38,"000")),IF(H38="Serviço",CONCATENATE(TEXT(B38,"00"),".",TEXT(C38,"000"),".",TEXT(D38,"000"),".",TEXT(E38,"000")),""))))) -> 02.002.003 | J38: TAPUME | N38: =IF(H38="Serviço",M38*L38,IF(H38="CÉLULA CONSTRUTIVA",SUMIFS($N$8:$N$356,$B$8:$B$356,B38,$H$8:$H$356,"Serviço"),IF(H38="ETAPA",SUMIFS($N$8:$N$356,$B$8:$B$356,B38,$C$8:$C$356,C38,$H$8:$H$356,"Serviço"),IF(H38="SUBETAPA",SUMIFS($N$8:$N$356,$B$8:$B$356,B38,$C$8:$C$356,C38,$D$8:$D$356,D38,$H$8:$H$356,"Serviço"),0)))) -> 25153.488
A39: =IF($H39="UNIDADE CONSTRUTIVA",OFFSET(A39,-1,0)+1,LARGE(A$3:A38,1)) -> 0 | B39: =IF(H39="UNIDADE CONSTRUTIVA",0,IF(H39="CÉLULA CONSTRUTIVA",OFFSET(B39,-1,0)+1,OFFSET(B39,-1,0))) -> 2 | C39: =IF(H39="CÉLULA CONSTRUTIVA",0,IF(H39="ETAPA",OFFSET(C39,-1,0)+1,OFFSET(C39,-1,0))) -> 2 | D39: =IF(H39="ETAPA",0,IF(H39="SUBETAPA",OFFSET(D39,-1,0)+1,OFFSET(D39,-1,0))) -> 3 | E39: =IF(H39="Subetapa",0,IF(H39="serviço",OFFSET(E39,-1,0)+1,OFFSET(E39,-1,0))) -> 1 | H39: SERVIÇO | I39: =IF(H39="Unidade Construtiva",TEXT(A39,"00"),IF(H39="Célula Construtiva",TEXT(B39,"00"),IF(H39="Etapa",CONCATENATE(TEXT(B39,"00"),".",TEXT(C39,"000")),IF(H39="Subetapa",CONCATENATE(TEXT(B39,"00"),".",TEXT(C39,"000"),".",TEXT(D39,"000")),IF(H39="Serviço",CONCATENATE(TEXT(B39,"00"),".",TEXT(C39,"000"),".",TEXT(D39,"000"),".",TEXT(E39,"000")),""))))) -> 02.002.003.001 | J39: Tapume Metálico | K39: m2 | L39: 126.6 | M39: 189.68 | N39: =IF(H39="Serviço",M39*L39,IF(H39="CÉLULA CONSTRUTIVA",SUMIFS($N$8:$N$356,$B$8:$B$356,B39,$H$8:$H$356,"Serviço"),IF(H39="ETAPA",SUMIFS($N$8:$N$356,$B$8:$B$356,B39,$C$8:$C$356,C39,$H$8:$H$356,"Serviço"),IF(H39="SUBETAPA",SUMIFS($N$8:$N$356,$B$8:$B$356,B39,$C$8:$C$356,C39,$D$8:$D$356,D39,$H$8:$H$356,"Serviço"),0)))) -> 24013.488 | O39: Frente + lateral terreno | P39: Finalizado
A40: =IF($H40="UNIDADE CONSTRUTIVA",OFFSET(A40,-1,0)+1,LARGE(A$3:A39,1)) -> 0 | B40: =IF(H40="UNIDADE CONSTRUTIVA",0,IF(H40="CÉLULA CONSTRUTIVA",OFFSET(B40,-1,0)+1,OFFSET(B40,-1,0))) -> 2 | C40: =IF(H40="CÉLULA CONSTRUTIVA",0,IF(H40="ETAPA",OFFSET(C40,-1,0)+1,OFFSET(C40,-1,0))) -> 2 | D40: =IF(H40="ETAPA",0,IF(H40="SUBETAPA",OFFSET(D40,-1,0)+1,OFFSET(D40,-1,0))) -> 3 | E40: =IF(H40="Subetapa",0,IF(H40="serviço",OFFSET(E40,-1,0)+1,OFFSET(E40,-1,0))) -> 2 | H40: SERVIÇO | I40: =IF(H40="Unidade Construtiva",TEXT(A40,"00"),IF(H40="Célula Construtiva",TEXT(B40,"00"),IF(H40="Etapa",CONCATENATE(TEXT(B40,"00"),".",TEXT(C40,"000")),IF(H40="Subetapa",CONCATENATE(TEXT(B40,"00"),".",TEXT(C40,"000"),".",TEXT(D40,"000")),IF(H40="Serviço",CONCATENATE(TEXT(B40,"00"),".",TEXT(C40,"000"),".",TEXT(D40,"000"),".",TEXT(E40,"000")),""))))) -> 02.002.003.002 | J40: Aluguel de Mini-Escavadeira / Cravação de Tapume | K40: vb | L40: 1 | M40: =380*3 -> 1140 | N40: =IF(H40="Serviço",M40*L40,IF(H40="CÉLULA CONSTRUTIVA",SUMIFS($N$8:$N$356,$B$8:$B$356,B40,$H$8:$H$356,"Serviço"),IF(H40="ETAPA",SUMIFS($N$8:$N$356,$B$8:$B$356,B40,$C$8:$C$356,C40,$H$8:$H$356,"Serviço"),IF(H40="SUBETAPA",SUMIFS($N$8:$N$356,$B$8:$B$356,B40,$C$8:$C$356,C40,$D$8:$D$356,D40,$H$8:$H$356,"Serviço"),0)))) -> 1140 | O40: Considerado 3 dias para execução (Diária R$ 380) | P40: Finalizado
A41: =IF($H41="UNIDADE CONSTRUTIVA",OFFSET(A41,-1,0)+1,LARGE(A$3:A40,1)) -> 0 | B41: =IF(H41="UNIDADE CONSTRUTIVA",0,IF(H41="CÉLULA CONSTRUTIVA",OFFSET(B41,-1,0)+1,OFFSET(B41,-1,0))) -> 2 | C41: =IF(H41="CÉLULA CONSTRUTIVA",0,IF(H41="ETAPA",OFFSET(C41,-1,0)+1,OFFSET(C41,-1,0))) -> 2 | D41: =IF(H41="ETAPA",0,IF(H41="SUBETAPA",OFFSET(D41,-1,0)+1,OFFSET(D41,-1,0))) -> 4 | E41: =IF(H41="Subetapa",0,IF(H41="serviço",OFFSET(E41,-1,0)+1,OFFSET(E41,-1,0))) -> 0 | H41: SUBETAPA | I41: =IF(H41="Unidade Construtiva",TEXT(A41,"00"),IF(H41="Célula Construtiva",TEXT(B41,"00"),IF(H41="Etapa",CONCATENATE(TEXT(B41,"00"),".",TEXT(C41,"000")),IF(H41="Subetapa",CONCATENATE(TEXT(B41,"00"),".",TEXT(C41,"000"),".",TEXT(D41,"000")),IF(H41="Serviço",CONCATENATE(TEXT(B41,"00"),".",TEXT(C41,"000"),".",TEXT(D41,"000"),".",TEXT(E41,"000")),""))))) -> 02.002.004 | J41: CONTAINERS E ESCRITÓRIOS | N41: =IF(H41="Serviço",M41*L41,IF(H41="CÉLULA CONSTRUTIVA",SUMIFS($N$8:$N$356,$B$8:$B$356,B41,$H$8:$H$356,"Serviço"),IF(H41="ETAPA",SUMIFS($N$8:$N$356,$B$8:$B$356,B41,$C$8:$C$356,C41,$H$8:$H$356,"Serviço"),IF(H41="SUBETAPA",SUMIFS($N$8:$N$356,$B$8:$B$356,B41,$C$8:$C$356,C41,$D$8:$D$356,D41,$H$8:$H$356,"Serviço"),0)))) -> 281301.47
A42: =IF($H42="UNIDADE CONSTRUTIVA",OFFSET(A42,-1,0)+1,LARGE(A$3:A41,1)) -> 0 | B42: =IF(H42="UNIDADE CONSTRUTIVA",0,IF(H42="CÉLULA CONSTRUTIVA",OFFSET(B42,-1,0)+1,OFFSET(B42,-1,0))) -> 2 | C42: =IF(H42="CÉLULA CONSTRUTIVA",0,IF(H42="ETAPA",OFFSET(C42,-1,0)+1,OFFSET(C42,-1,0))) -> 2 | D42: =IF(H42="ETAPA",0,IF(H42="SUBETAPA",OFFSET(D42,-1,0)+1,OFFSET(D42,-1,0))) -> 4 | E42: =IF(H42="Subetapa",0,IF(H42="serviço",OFFSET(E42,-1,0)+1,OFFSET(E42,-1,0))) -> 1 | H42: SERVIÇO | I42: =IF(H42="Unidade Construtiva",TEXT(A42,"00"),IF(H42="Célula Construtiva",TEXT(B42,"00"),IF(H42="Etapa",CONCATENATE(TEXT(B42,"00"),".",TEXT(C42,"000")),IF(H42="Subetapa",CONCATENATE(TEXT(B42,"00"),".",TEXT(C42,"000"),".",TEXT(D42,"000")),IF(H42="Serviço",CONCATENATE(TEXT(B42,"00"),".",TEXT(C42,"000"),".",TEXT(D42,"000"),".",TEXT(E42,"000")),""))))) -> 02.002.004.001 | J42: Container para Escritório - Locação | K42: mes | L42: 11 | M42: 800 | N42: =IF(H42="Serviço",M42*L42,IF(H42="CÉLULA CONSTRUTIVA",SUMIFS($N$8:$N$356,$B$8:$B$356,B42,$H$8:$H$356,"Serviço"),IF(H42="ETAPA",SUMIFS($N$8:$N$356,$B$8:$B$356,B42,$C$8:$C$356,C42,$H$8:$H$356,"Serviço"),IF(H42="SUBETAPA",SUMIFS($N$8:$N$356,$B$8:$B$356,B42,$C$8:$C$356,C42,$D$8:$D$356,D42,$H$8:$H$356,"Serviço"),0)))) -> 8800 | O42: Até 3º mês alvenaria - chegando no pavimento tipo | P42: Finalizado
A43: =IF($H43="UNIDADE CONSTRUTIVA",OFFSET(A43,-1,0)+1,LARGE(A$3:A42,1)) -> 0 | B43: =IF(H43="UNIDADE CONSTRUTIVA",0,IF(H43="CÉLULA CONSTRUTIVA",OFFSET(B43,-1,0)+1,OFFSET(B43,-1,0))) -> 2 | C43: =IF(H43="CÉLULA CONSTRUTIVA",0,IF(H43="ETAPA",OFFSET(C43,-1,0)+1,OFFSET(C43,-1,0))) -> 2 | D43: =IF(H43="ETAPA",0,IF(H43="SUBETAPA",OFFSET(D43,-1,0)+1,OFFSET(D43,-1,0))) -> 4 | E43: =IF(H43="Subetapa",0,IF(H43="serviço",OFFSET(E43,-1,0)+1,OFFSET(E43,-1,0))) -> 2 | H43: SERVIÇO | I43: =IF(H43="Unidade Construtiva",TEXT(A43,"00"),IF(H43="Célula Construtiva",TEXT(B43,"00"),IF(H43="Etapa",CONCATENATE(TEXT(B43,"00"),".",TEXT(C43,"000")),IF(H43="Subetapa",CONCATENATE(TEXT(B43,"00"),".",TEXT(C43,"000"),".",TEXT(D43,"000")),IF(H43="Serviço",CONCATENATE(TEXT(B43,"00"),".",TEXT(C43,"000"),".",TEXT(D43,"000"),".",TEXT(E43,"000")),""))))) -> 02.002.004.002 | J43: Container para Banheiro e Chuveiro - Locação | K43: mes | L43: 10 | M43: 5000 | N43: =IF(H43="Serviço",M43*L43,IF(H43="CÉLULA CONSTRUTIVA",SUMIFS($N$8:$N$356,$B$8:$B$356,B43,$H$8:$H$356,"Serviço"),IF(H43="ETAPA",SUMIFS($N$8:$N$356,$B$8:$B$356,B43,$C$8:$C$356,C43,$H$8:$H$356,"Serviço"),IF(H43="SUBETAPA",SUMIFS($N$8:$N$356,$B$8:$B$356,B43,$C$8:$C$356,C43,$D$8:$D$356,D43,$H$8:$H$356,"Serviço"),0)))) -> 50000 | O43: Até início alvenaria +1 mês para organização | P43: Finalizado
A44: =IF($H44="UNIDADE CONSTRUTIVA",OFFSET(A44,-1,0)+1,LARGE(A$3:A43,1)) -> 0 | B44: =IF(H44="UNIDADE CONSTRUTIVA",0,IF(H44="CÉLULA CONSTRUTIVA",OFFSET(B44,-1,0)+1,OFFSET(B44,-1,0))) -> 2 | C44: =IF(H44="CÉLULA CONSTRUTIVA",0,IF(H44="ETAPA",OFFSET(C44,-1,0)+1,OFFSET(C44,-1,0))) -> 2 | D44: =IF(H44="ETAPA",0,IF(H44="SUBETAPA",OFFSET(D44,-1,0)+1,OFFSET(D44,-1,0))) -> 4 | E44: =IF(H44="Subetapa",0,IF(H44="serviço",OFFSET(E44,-1,0)+1,OFFSET(E44,-1,0))) -> 3 | H44: SERVIÇO | I44: =IF(H44="Unidade Construtiva",TEXT(A44,"00"),IF(H44="Célula Construtiva",TEXT(B44,"00"),IF(H44="Etapa",CONCATENATE(TEXT(B44,"00"),".",TEXT(C44,"000")),IF(H44="Subetapa",CONCATENATE(TEXT(B44,"00"),".",TEXT(C44,"000"),".",TEXT(D44,"000")),IF(H44="Serviço",CONCATENATE(TEXT(B44,"00"),".",TEXT(C44,"000"),".",TEXT(D44,"000"),".",TEXT(E44,"000")),""))))) -> 02.002.004.003 | J44: Taxa de Mobilização e Desmobilização de Container para Escirtório | K44: vb | L44: 1 | M44: 1000 | N44: =IF(H44="Serviço",M44*L44,IF(H44="CÉLULA CONSTRUTIVA",SUMIFS($N$8:$N$356,$B$8:$B$356,B44,$H$8:$H$356,"Serviço"),IF(H44="ETAPA",SUMIFS($N$8:$N$356,$B$8:$B$356,B44,$C$8:$C$356,C44,$H$8:$H$356,"Serviço"),IF(H44="SUBETAPA",SUMIFS($N$8:$N$356,$B$8:$B$356,B44,$C$8:$C$356,C44,$D$8:$D$356,D44,$H$8:$H$356,"Serviço"),0)))) -> 1000 | O44: Estimado com base em índices históricos | P44: Finalizado
A45: =IF($H45="UNIDADE CONSTRUTIVA",OFFSET(A45,-1,0)+1,LARGE(A$3:A44,1)) -> 0 | B45: =IF(H45="UNIDADE CONSTRUTIVA",0,IF(H45="CÉLULA CONSTRUTIVA",OFFSET(B45,-1,0)+1,OFFSET(B45,-1,0))) -> 2 | C45: =IF(H45="CÉLULA CONSTRUTIVA",0,IF(H45="ETAPA",OFFSET(C45,-1,0)+1,OFFSET(C45,-1,0))) -> 2 | D45: =IF(H45="ETAPA",0,IF(H45="SUBETAPA",OFFSET(D45,-1,0)+1,OFFSET(D45,-1,0))) -> 4 | E45: =IF(H45="Subetapa",0,IF(H45="serviço",OFFSET(E45,-1,0)+1,OFFSET(E45,-1,0))) -> 4 | H45: SERVIÇO | I45: =IF(H45="Unidade Construtiva",TEXT(A45,"00"),IF(H45="Célula Construtiva",TEXT(B45,"00"),IF(H45="Etapa",CONCATENATE(TEXT(B45,"00"),".",TEXT(C45,"000")),IF(H45="Subetapa",CONCATENATE(TEXT(B45,"00"),".",TEXT(C45,"000"),".",TEXT(D45,"000")),IF(H45="Serviço",CONCATENATE(TEXT(B45,"00"),".",TEXT(C45,"000"),".",TEXT(D45,"000"),".",TEXT(E45,"000")),""))))) -> 02.002.004.004 | J45: Container para Almoxarifado - Locação | K45: mes | L45: 10 | M45: 5000 | N45: =IF(H45="Serviço",M45*L45,IF(H45="CÉLULA CONSTRUTIVA",SUMIFS($N$8:$N$356,$B$8:$B$356,B45,$H$8:$H$356,"Serviço"),IF(H45="ETAPA",SUMIFS($N$8:$N$356,$B$8:$B$356,B45,$C$8:$C$356,C45,$H$8:$H$356,"Serviço"),IF(H45="SUBETAPA",SUMIFS($N$8:$N$356,$B$8:$B$356,B45,$C$8:$C$356,C45,$D$8:$D$356,D45,$H$8:$H$356,"Serviço"),0)))) -> 50000 | O45: Até início alvenaria +1 mês para organização | P45: Finalizado
A46: =IF($H46="UNIDADE CONSTRUTIVA",OFFSET(A46,-1,0)+1,LARGE(A$3:A45,1)) -> 0 | B46: =IF(H46="UNIDADE CONSTRUTIVA",0,IF(H46="CÉLULA CONSTRUTIVA",OFFSET(B46,-1,0)+1,OFFSET(B46,-1,0))) -> 2 | C46: =IF(H46="CÉLULA CONSTRUTIVA",0,IF(H46="ETAPA",OFFSET(C46,-1,0)+1,OFFSET(C46,-1,0))) -> 2 | D46: =IF(H46="ETAPA",0,IF(H46="SUBETAPA",OFFSET(D46,-1,0)+1,OFFSET(D46,-1,0))) -> 4 | E46: =IF(H46="Subetapa",0,IF(H46="serviço",OFFSET(E46,-1,0)+1,OFFSET(E46,-1,0))) -> 5 | H46: SERVIÇO | I46: =IF(H46="Unidade Construtiva",TEXT(A46,"00"),IF(H46="Célula Construtiva",TEXT(B46,"00"),IF(H46="Etapa",CONCATENATE(TEXT(B46,"00"),".",TEXT(C46,"000")),IF(H46="Subetapa",CONCATENATE(TEXT(B46,"00"),".",TEXT(C46,"000"),".",TEXT(D46,"000")),IF(H46="Serviço",CONCATENATE(TEXT(B46,"00"),".",TEXT(C46,"000"),".",TEXT(D46,"000"),".",TEXT(E46,"000")),""))))) -> 02.002.004.005 | J46: Material de Higiene e Limpeza | K46: mes | L46: ='Obra '!E7 -> 33 | M46: 2149.0854 | N46: =IF(H46="Serviço",M46*L46,IF(H46="CÉLULA CONSTRUTIVA",SUMIFS($N$8:$N$356,$B$8:$B$356,B46,$H$8:$H$356,"Serviço"),IF(H46="ETAPA",SUMIFS($N$8:$N$356,$B$8:$B$356,B46,$C$8:$C$356,C46,$H$8:$H$356,"Serviço"),IF(H46="SUBETAPA",SUMIFS($N$8:$N$356,$B$8:$B$356,B46,$C$8:$C$356,C46,$D$8:$D$356,D46,$H$8:$H$356,"Serviço"),0)))) -> 70919.818 | O46: Estimado com base em índices históricos | P46: Finalizado
A47: =IF($H47="UNIDADE CONSTRUTIVA",OFFSET(A47,-1,0)+1,LARGE(A$3:A46,1)) -> 0 | B47: =IF(H47="UNIDADE CONSTRUTIVA",0,IF(H47="CÉLULA CONSTRUTIVA",OFFSET(B47,-1,0)+1,OFFSET(B47,-1,0))) -> 2 | C47: =IF(H47="CÉLULA CONSTRUTIVA",0,IF(H47="ETAPA",OFFSET(C47,-1,0)+1,OFFSET(C47,-1,0))) -> 2 | D47: =IF(H47="ETAPA",0,IF(H47="SUBETAPA",OFFSET(D47,-1,0)+1,OFFSET(D47,-1,0))) -> 4 | E47: =IF(H47="Subetapa",0,IF(H47="serviço",OFFSET(E47,-1,0)+1,OFFSET(E47,-1,0))) -> 6 | H47: SERVIÇO | I47: =IF(H47="Unidade Construtiva",TEXT(A47,"00"),IF(H47="Célula Construtiva",TEXT(B47,"00"),IF(H47="Etapa",CONCATENATE(TEXT(B47,"00"),".",TEXT(C47,"000")),IF(H47="Subetapa",CONCATENATE(TEXT(B47,"00"),".",TEXT(C47,"000"),".",TEXT(D47,"000")),IF(H47="Serviço",CONCATENATE(TEXT(B47,"00"),".",TEXT(C47,"000"),".",TEXT(D47,"000"),".",TEXT(E47,"000")),""))))) -> 02.002.004.006 | J47: Mobiliário Provisório para Escritório de Engenharia | K47: vb | L47: 1 | M47: =CANTEIRO!F26+CANTEIRO!F31 -> 55700 | N47: =IF(H47="Serviço",M47*L47,IF(H47="CÉLULA CONSTRUTIVA",SUMIFS($N$8:$N$356,$B$8:$B$356,B47,$H$8:$H$356,"Serviço"),IF(H47="ETAPA",SUMIFS($N$8:$N$356,$B$8:$B$356,B47,$C$8:$C$356,C47,$H$8:$H$356,"Serviço"),IF(H47="SUBETAPA",SUMIFS($N$8:$N$356,$B$8:$B$356,B47,$C$8:$C$356,C47,$D$8:$D$356,D47,$H$8:$H$356,"Serviço"),0)))) -> 55700 | O47: Conforme aba "CANTEIRO" - Mobiliário + equipamentos | P47: Finalizado
A48: =IF($H48="UNIDADE CONSTRUTIVA",OFFSET(A48,-1,0)+1,LARGE(A$3:A47,1)) -> 0 | B48: =IF(H48="UNIDADE CONSTRUTIVA",0,IF(H48="CÉLULA CONSTRUTIVA",OFFSET(B48,-1,0)+1,OFFSET(B48,-1,0))) -> 2 | C48: =IF(H48="CÉLULA CONSTRUTIVA",0,IF(H48="ETAPA",OFFSET(C48,-1,0)+1,OFFSET(C48,-1,0))) -> 2 | D48: =IF(H48="ETAPA",0,IF(H48="SUBETAPA",OFFSET(D48,-1,0)+1,OFFSET(D48,-1,0))) -> 4 | E48: =IF(H48="Subetapa",0,IF(H48="serviço",OFFSET(E48,-1,0)+1,OFFSET(E48,-1,0))) -> 7 | H48: SERVIÇO | I48: =IF(H48="Unidade Construtiva",TEXT(A48,"00"),IF(H48="Célula Construtiva",TEXT(B48,"00"),IF(H48="Etapa",CONCATENATE(TEXT(B48,"00"),".",TEXT(C48,"000")),IF(H48="Subetapa",CONCATENATE(TEXT(B48,"00"),".",TEXT(C48,"000"),".",TEXT(D48,"000")),IF(H48="Serviço",CONCATENATE(TEXT(B48,"00"),".",TEXT(C48,"000"),".",TEXT(D48,"000"),".",TEXT(E48,"000")),""))))) -> 02.002.004.007 | J48: Suprimentos de Escritório de Obra | K48: mes | L48: ='Obra '!E7 -> 33 | M48: 1360.05 | N48: =IF(H48="Serviço",M48*L48,IF(H48="CÉLULA CONSTRUTIVA",SUMIFS($N$8:$N$356,$B$8:$B$356,B48,$H$8:$H$356,"Serviço"),IF(H48="ETAPA",SUMIFS($N$8:$N$356,$B$8:$B$356,B48,$C$8:$C$356,C48,$H$8:$H$356,"Serviço"),IF(H48="SUBETAPA",SUMIFS($N$8:$N$356,$B$8:$B$356,B48,$C$8:$C$356,C48,$D$8:$D$356,D48,$H$8:$H$356,"Serviço"),0)))) -> 44881.651 | O48: Estimado com base em índices históricos | P48: Finalizado
A49: =IF($H49="UNIDADE CONSTRUTIVA",OFFSET(A49,-1,0)+1,LARGE(A$3:A48,1)) -> 0 | B49: =IF(H49="UNIDADE CONSTRUTIVA",0,IF(H49="CÉLULA CONSTRUTIVA",OFFSET(B49,-1,0)+1,OFFSET(B49,-1,0))) -> 2 | C49: =IF(H49="CÉLULA CONSTRUTIVA",0,IF(H49="ETAPA",OFFSET(C49,-1,0)+1,OFFSET(C49,-1,0))) -> 2 | D49: =IF(H49="ETAPA",0,IF(H49="SUBETAPA",OFFSET(D49,-1,0)+1,OFFSET(D49,-1,0))) -> 5 | E49: =IF(H49="Subetapa",0,IF(H49="serviço",OFFSET(E49,-1,0)+1,OFFSET(E49,-1,0))) -> 0 | H49: SUBETAPA | I49: =IF(H49="Unidade Construtiva",TEXT(A49,"00"),IF(H49="Célula Construtiva",TEXT(B49,"00"),IF(H49="Etapa",CONCATENATE(TEXT(B49,"00"),".",TEXT(C49,"000")),IF(H49="Subetapa",CONCATENATE(TEXT(B49,"00"),".",TEXT(C49,"000"),".",TEXT(D49,"000")),IF(H49="Serviço",CONCATENATE(TEXT(B49,"00"),".",TEXT(C49,"000"),".",TEXT(D49,"000"),".",TEXT(E49,"000")),""))))) -> 02.002.005 | J49: BARRACOS | N49: =IF(H49="Serviço",M49*L49,IF(H49="CÉLULA CONSTRUTIVA",SUMIFS($N$8:$N$356,$B$8:$B$356,B49,$H$8:$H$356,"Serviço"),IF(H49="ETAPA",SUMIFS($N$8:$N$356,$B$8:$B$356,B49,$C$8:$C$356,C49,$H$8:$H$356,"Serviço"),IF(H49="SUBETAPA",SUMIFS($N$8:$N$356,$B$8:$B$356,B49,$C$8:$C$356,C49,$D$8:$D$356,D49,$H$8:$H$356,"Serviço"),0)))) -> 119743.53
A50: =IF($H50="UNIDADE CONSTRUTIVA",OFFSET(A50,-1,0)+1,LARGE(A$3:A49,1)) -> 0 | B50: =IF(H50="UNIDADE CONSTRUTIVA",0,IF(H50="CÉLULA CONSTRUTIVA",OFFSET(B50,-1,0)+1,OFFSET(B50,-1,0))) -> 2 | C50: =IF(H50="CÉLULA CONSTRUTIVA",0,IF(H50="ETAPA",OFFSET(C50,-1,0)+1,OFFSET(C50,-1,0))) -> 2 | D50: =IF(H50="ETAPA",0,IF(H50="SUBETAPA",OFFSET(D50,-1,0)+1,OFFSET(D50,-1,0))) -> 5 | E50: =IF(H50="Subetapa",0,IF(H50="serviço",OFFSET(E50,-1,0)+1,OFFSET(E50,-1,0))) -> 1 | H50: SERVIÇO | I50: =IF(H50="Unidade Construtiva",TEXT(A50,"00"),IF(H50="Célula Construtiva",TEXT(B50,"00"),IF(H50="Etapa",CONCATENATE(TEXT(B50,"00"),".",TEXT(C50,"000")),IF(H50="Subetapa",CONCATENATE(TEXT(B50,"00"),".",TEXT(C50,"000"),".",TEXT(D50,"000")),IF(H50="Serviço",CONCATENATE(TEXT(B50,"00"),".",TEXT(C50,"000"),".",TEXT(D50,"000"),".",TEXT(E50,"000")),""))))) -> 02.002.005.001 | J50: Barraco Provisório em Madeira | K50: vb | L50: 1 | M50: =CANTEIRO!G51 -> 114154.32 | N50: =IF(H50="Serviço",M50*L50,IF(H50="CÉLULA CONSTRUTIVA",SUMIFS($N$8:$N$356,$B$8:$B$356,B50,$H$8:$H$356,"Serviço"),IF(H50="ETAPA",SUMIFS($N$8:$N$356,$B$8:$B$356,B50,$C$8:$C$356,C50,$H$8:$H$356,"Serviço"),IF(H50="SUBETAPA",SUMIFS($N$8:$N$356,$B$8:$B$356,B50,$C$8:$C$356,C50,$D$8:$D$356,D50,$H$8:$H$356,"Serviço"),0)))) -> 114154.32 | O50: Conforme aba "CANTEIRO" | P50: Finalizado
A51: =IF($H51="UNIDADE CONSTRUTIVA",OFFSET(A51,-1,0)+1,LARGE(A$3:A50,1)) -> 0 | B51: =IF(H51="UNIDADE CONSTRUTIVA",0,IF(H51="CÉLULA CONSTRUTIVA",OFFSET(B51,-1,0)+1,OFFSET(B51,-1,0))) -> 2 | C51: =IF(H51="CÉLULA CONSTRUTIVA",0,IF(H51="ETAPA",OFFSET(C51,-1,0)+1,OFFSET(C51,-1,0))) -> 2 | D51: =IF(H51="ETAPA",0,IF(H51="SUBETAPA",OFFSET(D51,-1,0)+1,OFFSET(D51,-1,0))) -> 5 | E51: =IF(H51="Subetapa",0,IF(H51="serviço",OFFSET(E51,-1,0)+1,OFFSET(E51,-1,0))) -> 2 | H51: SERVIÇO | I51: =IF(H51="Unidade Construtiva",TEXT(A51,"00"),IF(H51="Célula Construtiva",TEXT(B51,"00"),IF(H51="Etapa",CONCATENATE(TEXT(B51,"00"),".",TEXT(C51,"000")),IF(H51="Subetapa",CONCATENATE(TEXT(B51,"00"),".",TEXT(C51,"000"),".",TEXT(D51,"000")),IF(H51="Serviço",CONCATENATE(TEXT(B51,"00"),".",TEXT(C51,"000"),".",TEXT(D51,"000"),".",TEXT(E51,"000")),""))))) -> 02.002.005.002 | J51: Instalações de Canteiro | K51: vb | L51: 1 | M51: 5589.2086 | N51: =IF(H51="Serviço",M51*L51,IF(H51="CÉLULA CONSTRUTIVA",SUMIFS($N$8:$N$356,$B$8:$B$356,B51,$H$8:$H$356,"Serviço"),IF(H51="ETAPA",SUMIFS($N$8:$N$356,$B$8:$B$356,B51,$C$8:$C$356,C51,$H$8:$H$356,"Serviço"),IF(H51="SUBETAPA",SUMIFS($N$8:$N$356,$B$8:$B$356,B51,$C$8:$C$356,C51,$D$8:$D$356,D51,$H$8:$H$356,"Serviço"),0)))) -> 5589.2086 | O51: Estimado com base em índices históricos | P51: Finalizado
A52: =IF($H52="UNIDADE CONSTRUTIVA",OFFSET(A52,-1,0)+1,LARGE(A$3:A51,1)) -> 0 | B52: =IF(H52="UNIDADE CONSTRUTIVA",0,IF(H52="CÉLULA CONSTRUTIVA",OFFSET(B52,-1,0)+1,OFFSET(B52,-1,0))) -> 2 | C52: =IF(H52="CÉLULA CONSTRUTIVA",0,IF(H52="ETAPA",OFFSET(C52,-1,0)+1,OFFSET(C52,-1,0))) -> 2 | D52: =IF(H52="ETAPA",0,IF(H52="SUBETAPA",OFFSET(D52,-1,0)+1,OFFSET(D52,-1,0))) -> 6 | E52: =IF(H52="Subetapa",0,IF(H52="serviço",OFFSET(E52,-1,0)+1,OFFSET(E52,-1,0))) -> 0 | H52: SUBETAPA | I52: =IF(H52="Unidade Construtiva",TEXT(A52,"00"),IF(H52="Célula Construtiva",TEXT(B52,"00"),IF(H52="Etapa",CONCATENATE(TEXT(B52,"00"),".",TEXT(C52,"000")),IF(H52="Subetapa",CONCATENATE(TEXT(B52,"00"),".",TEXT(C52,"000"),".",TEXT(D52,"000")),IF(H52="Serviço",CONCATENATE(TEXT(B52,"00"),".",TEXT(C52,"000"),".",TEXT(D52,"000"),".",TEXT(E52,"000")),""))))) -> 02.002.006 | J52: PLACAS E COMUNICAÇÃO VISUAL | N52: =IF(H52="Serviço",M52*L52,IF(H52="CÉLULA CONSTRUTIVA",SUMIFS($N$8:$N$356,$B$8:$B$356,B52,$H$8:$H$356,"Serviço"),IF(H52="ETAPA",SUMIFS($N$8:$N$356,$B$8:$B$356,B52,$C$8:$C$356,C52,$H$8:$H$356,"Serviço"),IF(H52="SUBETAPA",SUMIFS($N$8:$N$356,$B$8:$B$356,B52,$C$8:$C$356,C52,$D$8:$D$356,D52,$H$8:$H$356,"Serviço"),0)))) -> 10931.15
A53: =IF($H53="UNIDADE CONSTRUTIVA",OFFSET(A53,-1,0)+1,LARGE(A$3:A52,1)) -> 0 | B53: =IF(H53="UNIDADE CONSTRUTIVA",0,IF(H53="CÉLULA CONSTRUTIVA",OFFSET(B53,-1,0)+1,OFFSET(B53,-1,0))) -> 2 | C53: =IF(H53="CÉLULA CONSTRUTIVA",0,IF(H53="ETAPA",OFFSET(C53,-1,0)+1,OFFSET(C53,-1,0))) -> 2 | D53: =IF(H53="ETAPA",0,IF(H53="SUBETAPA",OFFSET(D53,-1,0)+1,OFFSET(D53,-1,0))) -> 6 | E53: =IF(H53="Subetapa",0,IF(H53="serviço",OFFSET(E53,-1,0)+1,OFFSET(E53,-1,0))) -> 1 | H53: SERVIÇO | I53: =IF(H53="Unidade Construtiva",TEXT(A53,"00"),IF(H53="Célula Construtiva",TEXT(B53,"00"),IF(H53="Etapa",CONCATENATE(TEXT(B53,"00"),".",TEXT(C53,"000")),IF(H53="Subetapa",CONCATENATE(TEXT(B53,"00"),".",TEXT(C53,"000"),".",TEXT(D53,"000")),IF(H53="Serviço",CONCATENATE(TEXT(B53,"00"),".",TEXT(C53,"000"),".",TEXT(D53,"000"),".",TEXT(E53,"000")),""))))) -> 02.002.006.001 | J53: Placas Responsáveis Técnicos | K53: vb | L53: 1 | M53: 3040.13 | N53: =IF(H53="Serviço",M53*L53,IF(H53="CÉLULA CONSTRUTIVA",SUMIFS($N$8:$N$356,$B$8:$B$356,B53,$H$8:$H$356,"Serviço"),IF(H53="ETAPA",SUMIFS($N$8:$N$356,$B$8:$B$356,B53,$C$8:$C$356,C53,$H$8:$H$356,"Serviço"),IF(H53="SUBETAPA",SUMIFS($N$8:$N$356,$B$8:$B$356,B53,$C$8:$C$356,C53,$D$8:$D$356,D53,$H$8:$H$356,"Serviço"),0)))) -> 3040.13 | O53: Estimado com base em índices históricos | P53: Finalizado
A54: =IF($H54="UNIDADE CONSTRUTIVA",OFFSET(A54,-1,0)+1,LARGE(A$3:A53,1)) -> 0 | B54: =IF(H54="UNIDADE CONSTRUTIVA",0,IF(H54="CÉLULA CONSTRUTIVA",OFFSET(B54,-1,0)+1,OFFSET(B54,-1,0))) -> 2 | C54: =IF(H54="CÉLULA CONSTRUTIVA",0,IF(H54="ETAPA",OFFSET(C54,-1,0)+1,OFFSET(C54,-1,0))) -> 2 | D54: =IF(H54="ETAPA",0,IF(H54="SUBETAPA",OFFSET(D54,-1,0)+1,OFFSET(D54,-1,0))) -> 6 | E54: =IF(H54="Subetapa",0,IF(H54="serviço",OFFSET(E54,-1,0)+1,OFFSET(E54,-1,0))) -> 2 | H54: SERVIÇO | I54: =IF(H54="Unidade Construtiva",TEXT(A54,"00"),IF(H54="Célula Construtiva",TEXT(B54,"00"),IF(H54="Etapa",CONCATENATE(TEXT(B54,"00"),".",TEXT(C54,"000")),IF(H54="Subetapa",CONCATENATE(TEXT(B54,"00"),".",TEXT(C54,"000"),".",TEXT(D54,"000")),IF(H54="Serviço",CONCATENATE(TEXT(B54,"00"),".",TEXT(C54,"000"),".",TEXT(D54,"000"),".",TEXT(E54,"000")),""))))) -> 02.002.006.002 | J54: Placa Institucional da Empresa | K54: vb | L54: 1 | M54: =CANTEIRO!G64 -> 7891.02 | N54: =IF(H54="Serviço",M54*L54,IF(H54="CÉLULA CONSTRUTIVA",SUMIFS($N$8:$N$356,$B$8:$B$356,B54,$H$8:$H$356,"Serviço"),IF(H54="ETAPA",SUMIFS($N$8:$N$356,$B$8:$B$356,B54,$C$8:$C$356,C54,$H$8:$H$356,"Serviço"),IF(H54="SUBETAPA",SUMIFS($N$8:$N$356,$B$8:$B$356,B54,$C$8:$C$356,C54,$D$8:$D$356,D54,$H$8:$H$356,"Serviço"),0)))) -> 7891.02 | O54: Conforme aba "CANTEIRO" | P54: Finalizado
A55: =IF($H55="UNIDADE CONSTRUTIVA",OFFSET(A55,-1,0)+1,LARGE(A$3:A54,1)) -> 0 | B55: =IF(H55="UNIDADE CONSTRUTIVA",0,IF(H55="CÉLULA CONSTRUTIVA",OFFSET(B55,-1,0)+1,OFFSET(B55,-1,0))) -> 2 | C55: =IF(H55="CÉLULA CONSTRUTIVA",0,IF(H55="ETAPA",OFFSET(C55,-1,0)+1,OFFSET(C55,-1,0))) -> 2 | D55: =IF(H55="ETAPA",0,IF(H55="SUBETAPA",OFFSET(D55,-1,0)+1,OFFSET(D55,-1,0))) -> 7 | E55: =IF(H55="Subetapa",0,IF(H55="serviço",OFFSET(E55,-1,0)+1,OFFSET(E55,-1,0))) -> 0 | H55: SUBETAPA | I55: =IF(H55="Unidade Construtiva",TEXT(A55,"00"),IF(H55="Célula Construtiva",TEXT(B55,"00"),IF(H55="Etapa",CONCATENATE(TEXT(B55,"00"),".",TEXT(C55,"000")),IF(H55="Subetapa",CONCATENATE(TEXT(B55,"00"),".",TEXT(C55,"000"),".",TEXT(D55,"000")),IF(H55="Serviço",CONCATENATE(TEXT(B55,"00"),".",TEXT(C55,"000"),".",TEXT(D55,"000"),".",TEXT(E55,"000")),""))))) -> 02.002.007 | J55: LOCAÇÃO DE OBRA | N55: =IF(H55="Serviço",M55*L55,IF(H55="CÉLULA CONSTRUTIVA",SUMIFS($N$8:$N$356,$B$8:$B$356,B55,$H$8:$H$356,"Serviço"),IF(H55="ETAPA",SUMIFS($N$8:$N$356,$B$8:$B$356,B55,$C$8:$C$356,C55,$H$8:$H$356,"Serviço"),IF(H55="SUBETAPA",SUMIFS($N$8:$N$356,$B$8:$B$356,B55,$C$8:$C$356,C55,$D$8:$D$356,D55,$H$8:$H$356,"Serviço"),0)))) -> 6981.489
A56: =IF($H56="UNIDADE CONSTRUTIVA",OFFSET(A56,-1,0)+1,LARGE(A$3:A55,1)) -> 0 | B56: =IF(H56="UNIDADE CONSTRUTIVA",0,IF(H56="CÉLULA CONSTRUTIVA",OFFSET(B56,-1,0)+1,OFFSET(B56,-1,0))) -> 2 | C56: =IF(H56="CÉLULA CONSTRUTIVA",0,IF(H56="ETAPA",OFFSET(C56,-1,0)+1,OFFSET(C56,-1,0))) -> 2 | D56: =IF(H56="ETAPA",0,IF(H56="SUBETAPA",OFFSET(D56,-1,0)+1,OFFSET(D56,-1,0))) -> 7 | E56: =IF(H56="Subetapa",0,IF(H56="serviço",OFFSET(E56,-1,0)+1,OFFSET(E56,-1,0))) -> 1 | H56: SERVIÇO | I56: =IF(H56="Unidade Construtiva",TEXT(A56,"00"),IF(H56="Célula Construtiva",TEXT(B56,"00"),IF(H56="Etapa",CONCATENATE(TEXT(B56,"00"),".",TEXT(C56,"000")),IF(H56="Subetapa",CONCATENATE(TEXT(B56,"00"),".",TEXT(C56,"000"),".",TEXT(D56,"000")),IF(H56="Serviço",CONCATENATE(TEXT(B56,"00"),".",TEXT(C56,"000"),".",TEXT(D56,"000"),".",TEXT(E56,"000")),""))))) -> 02.002.007.001 | J56: Locação da Obra | K56: vb | L56: 1 | M56: 6981.489 | N56: =IF(H56="Serviço",M56*L56,IF(H56="CÉLULA CONSTRUTIVA",SUMIFS($N$8:$N$356,$B$8:$B$356,B56,$H$8:$H$356,"Serviço"),IF(H56="ETAPA",SUMIFS($N$8:$N$356,$B$8:$B$356,B56,$C$8:$C$356,C56,$H$8:$H$356,"Serviço"),IF(H56="SUBETAPA",SUMIFS($N$8:$N$356,$B$8:$B$356,B56,$C$8:$C$356,C56,$D$8:$D$356,D56,$H$8:$H$356,"Serviço"),0)))) -> 6981.489 | O56: Custo composição sinapi | P56: Finalizado
A57: =IF($H57="UNIDADE CONSTRUTIVA",OFFSET(A57,-1,0)+1,LARGE(A$3:A56,1)) -> 0 | B57: =IF(H57="UNIDADE CONSTRUTIVA",0,IF(H57="CÉLULA CONSTRUTIVA",OFFSET(B57,-1,0)+1,OFFSET(B57,-1,0))) -> 2 | C57: =IF(H57="CÉLULA CONSTRUTIVA",0,IF(H57="ETAPA",OFFSET(C57,-1,0)+1,OFFSET(C57,-1,0))) -> 2 | D57: =IF(H57="ETAPA",0,IF(H57="SUBETAPA",OFFSET(D57,-1,0)+1,OFFSET(D57,-1,0))) -> 8 | E57: =IF(H57="Subetapa",0,IF(H57="serviço",OFFSET(E57,-1,0)+1,OFFSET(E57,-1,0))) -> 0 | H57: SUBETAPA | I57: =IF(H57="Unidade Construtiva",TEXT(A57,"00"),IF(H57="Célula Construtiva",TEXT(B57,"00"),IF(H57="Etapa",CONCATENATE(TEXT(B57,"00"),".",TEXT(C57,"000")),IF(H57="Subetapa",CONCATENATE(TEXT(B57,"00"),".",TEXT(C57,"000"),".",TEXT(D57,"000")),IF(H57="Serviço",CONCATENATE(TEXT(B57,"00"),".",TEXT(C57,"000"),".",TEXT(D57,"000"),".",TEXT(E57,"000")),""))))) -> 02.002.008 | J57: ACESSO DA OBRA | N57: =IF(H57="Serviço",M57*L57,IF(H57="CÉLULA CONSTRUTIVA",SUMIFS($N$8:$N$356,$B$8:$B$356,B57,$H$8:$H$356,"Serviço"),IF(H57="ETAPA",SUMIFS($N$8:$N$356,$B$8:$B$356,B57,$C$8:$C$356,C57,$H$8:$H$356,"Serviço"),IF(H57="SUBETAPA",SUMIFS($N$8:$N$356,$B$8:$B$356,B57,$C$8:$C$356,C57,$D$8:$D$356,D57,$H$8:$H$356,"Serviço"),0)))) -> 55304.788
A58: =IF($H58="UNIDADE CONSTRUTIVA",OFFSET(A58,-1,0)+1,LARGE(A$3:A57,1)) -> 0 | B58: =IF(H58="UNIDADE CONSTRUTIVA",0,IF(H58="CÉLULA CONSTRUTIVA",OFFSET(B58,-1,0)+1,OFFSET(B58,-1,0))) -> 2 | C58: =IF(H58="CÉLULA CONSTRUTIVA",0,IF(H58="ETAPA",OFFSET(C58,-1,0)+1,OFFSET(C58,-1,0))) -> 2 | D58: =IF(H58="ETAPA",0,IF(H58="SUBETAPA",OFFSET(D58,-1,0)+1,OFFSET(D58,-1,0))) -> 8 | E58: =IF(H58="Subetapa",0,IF(H58="serviço",OFFSET(E58,-1,0)+1,OFFSET(E58,-1,0))) -> 1 | H58: SERVIÇO | I58: =IF(H58="Unidade Construtiva",TEXT(A58,"00"),IF(H58="Célula Construtiva",TEXT(B58,"00"),IF(H58="Etapa",CONCATENATE(TEXT(B58,"00"),".",TEXT(C58,"000")),IF(H58="Subetapa",CONCATENATE(TEXT(B58,"00"),".",TEXT(C58,"000"),".",TEXT(D58,"000")),IF(H58="Serviço",CONCATENATE(TEXT(B58,"00"),".",TEXT(C58,"000"),".",TEXT(D58,"000"),".",TEXT(E58,"000")),""))))) -> 02.002.008.001 | J58: Lastro de Brita para Organização do Canteiro | K58: vb | L58: 1 | M58: =('Obra '!E8-'Obra '!E16)*170.2 -> 55304.788 | N58: =IF(H58="Serviço",M58*L58,IF(H58="CÉLULA CONSTRUTIVA",SUMIFS($N$8:$N$356,$B$8:$B$356,B58,$H$8:$H$356,"Serviço"),IF(H58="ETAPA",SUMIFS($N$8:$N$356,$B$8:$B$356,B58,$C$8:$C$356,C58,$H$8:$H$356,"Serviço"),IF(H58="SUBETAPA",SUMIFS($N$8:$N$356,$B$8:$B$356,B58,$C$8:$C$356,C58,$D$8:$D$356,D58,$H$8:$H$356,"Serviço"),0)))) -> 55304.788 | O58: Considerado 10 cm no térreo onde não há laje | P58: Finalizado
A59: =IF($H59="UNIDADE CONSTRUTIVA",OFFSET(A59,-1,0)+1,LARGE(A$3:A58,1)) -> 0 | B59: =IF(H59="UNIDADE CONSTRUTIVA",0,IF(H59="CÉLULA CONSTRUTIVA",OFFSET(B59,-1,0)+1,OFFSET(B59,-1,0))) -> 2 | C59: =IF(H59="CÉLULA CONSTRUTIVA",0,IF(H59="ETAPA",OFFSET(C59,-1,0)+1,OFFSET(C59,-1,0))) -> 2 | D59: =IF(H59="ETAPA",0,IF(H59="SUBETAPA",OFFSET(D59,-1,0)+1,OFFSET(D59,-1,0))) -> 8 | E59: =IF(H59="Subetapa",0,IF(H59="serviço",OFFSET(E59,-1,0)+1,OFFSET(E59,-1,0))) -> 1 | J59: TOTAL | N59: =N21+N8 -> 1334002.8
A60: =IF($H60="UNIDADE CONSTRUTIVA",OFFSET(A60,-1,0)+1,LARGE(A$3:A59,1)) -> 0 | B60: =IF(H60="UNIDADE CONSTRUTIVA",0,IF(H60="CÉLULA CONSTRUTIVA",OFFSET(B60,-1,0)+1,OFFSET(B60,-1,0))) -> 2 | C60: =IF(H60="CÉLULA CONSTRUTIVA",0,IF(H60="ETAPA",OFFSET(C60,-1,0)+1,OFFSET(C60,-1,0))) -> 2 | D60: =IF(H60="ETAPA",0,IF(H60="SUBETAPA",OFFSET(D60,-1,0)+1,OFFSET(D60,-1,0))) -> 8 | E60: =IF(H60="Subetapa",0,IF(H60="serviço",OFFSET(E60,-1,0)+1,OFFSET(E60,-1,0))) -> 1 | M60: =SUMIFS($N$7:$N$351,$H$7:$H$351,N60) -> 1334002.8 | N60: CÉLULA CONSTRUTIVA
A61: =IF($H61="UNIDADE CONSTRUTIVA",OFFSET(A61,-1,0)+1,LARGE(A$3:A60,1)) -> 0 | B61: =IF(H61="UNIDADE CONSTRUTIVA",0,IF(H61="CÉLULA CONSTRUTIVA",OFFSET(B61,-1,0)+1,OFFSET(B61,-1,0))) -> 2 | C61: =IF(H61="CÉLULA CONSTRUTIVA",0,IF(H61="ETAPA",OFFSET(C61,-1,0)+1,OFFSET(C61,-1,0))) -> 2 | D61: =IF(H61="ETAPA",0,IF(H61="SUBETAPA",OFFSET(D61,-1,0)+1,OFFSET(D61,-1,0))) -> 8 | E61: =IF(H61="Subetapa",0,IF(H61="serviço",OFFSET(E61,-1,0)+1,OFFSET(E61,-1,0))) -> 1 | M61: =SUMIFS($N$7:$N$351,$H$7:$H$351,N61) -> 1334002.8 | N61: ETAPA
A62: =IF($H62="UNIDADE CONSTRUTIVA",OFFSET(A62,-1,0)+1,LARGE(A$3:A61,1)) -> 0 | B62: =IF(H62="UNIDADE CONSTRUTIVA",0,IF(H62="CÉLULA CONSTRUTIVA",OFFSET(B62,-1,0)+1,OFFSET(B62,-1,0))) -> 2 | C62: =IF(H62="CÉLULA CONSTRUTIVA",0,IF(H62="ETAPA",OFFSET(C62,-1,0)+1,OFFSET(C62,-1,0))) -> 2 | D62: =IF(H62="ETAPA",0,IF(H62="SUBETAPA",OFFSET(D62,-1,0)+1,OFFSET(D62,-1,0))) -> 8 | E62: =IF(H62="Subetapa",0,IF(H62="serviço",OFFSET(E62,-1,0)+1,OFFSET(E62,-1,0))) -> 1 | M62: =SUMIFS($N$7:$N$351,$H$7:$H$351,N62) -> 1334002.8 | N62: SUBETAPA
A63: =IF($H63="UNIDADE CONSTRUTIVA",OFFSET(A63,-1,0)+1,LARGE(A$3:A62,1)) -> 0 | B63: =IF(H63="UNIDADE CONSTRUTIVA",0,IF(H63="CÉLULA CONSTRUTIVA",OFFSET(B63,-1,0)+1,OFFSET(B63,-1,0))) -> 2 | C63: =IF(H63="CÉLULA CONSTRUTIVA",0,IF(H63="ETAPA",OFFSET(C63,-1,0)+1,OFFSET(C63,-1,0))) -> 2 | D63: =IF(H63="ETAPA",0,IF(H63="SUBETAPA",OFFSET(D63,-1,0)+1,OFFSET(D63,-1,0))) -> 8 | E63: =IF(H63="Subetapa",0,IF(H63="serviço",OFFSET(E63,-1,0)+1,OFFSET(E63,-1,0))) -> 1 | M63: =SUMIFS($N$7:$N$351,$H$7:$H$351,N63) -> 1334002.8 | N63: SERVIÇO
A64: =IF($H64="UNIDADE CONSTRUTIVA",OFFSET(A64,-1,0)+1,LARGE(A$3:A63,1)) -> 0 | B64: =IF(H64="UNIDADE CONSTRUTIVA",0,IF(H64="CÉLULA CONSTRUTIVA",OFFSET(B64,-1,0)+1,OFFSET(B64,-1,0))) -> 2 | C64: =IF(H64="CÉLULA CONSTRUTIVA",0,IF(H64="ETAPA",OFFSET(C64,-1,0)+1,OFFSET(C64,-1,0))) -> 2 | D64: =IF(H64="ETAPA",0,IF(H64="SUBETAPA",OFFSET(D64,-1,0)+1,OFFSET(D64,-1,0))) -> 8 | E64: =IF(H64="Subetapa",0,IF(H64="serviço",OFFSET(E64,-1,0)+1,OFFSET(E64,-1,0))) -> 1 | M64: ='Obra '!C32 -> 1334002.8 | N64: OBRA
A65: =IF($H65="UNIDADE CONSTRUTIVA",OFFSET(A65,-1,0)+1,LARGE(A$3:A64,1)) -> 0 | B65: =IF(H65="UNIDADE CONSTRUTIVA",0,IF(H65="CÉLULA CONSTRUTIVA",OFFSET(B65,-1,0)+1,OFFSET(B65,-1,0))) -> 2 | C65: =IF(H65="CÉLULA CONSTRUTIVA",0,IF(H65="ETAPA",OFFSET(C65,-1,0)+1,OFFSET(C65,-1,0))) -> 2 | D65: =IF(H65="ETAPA",0,IF(H65="SUBETAPA",OFFSET(D65,-1,0)+1,OFFSET(D65,-1,0))) -> 8 | E65: =IF(H65="Subetapa",0,IF(H65="serviço",OFFSET(E65,-1,0)+1,OFFSET(E65,-1,0))) -> 1
A66: =IF($H66="UNIDADE CONSTRUTIVA",OFFSET(A66,-1,0)+1,LARGE(A$3:A65,1)) -> 0 | B66: =IF(H66="UNIDADE CONSTRUTIVA",0,IF(H66="CÉLULA CONSTRUTIVA",OFFSET(B66,-1,0)+1,OFFSET(B66,-1,0))) -> 2 | C66: =IF(H66="CÉLULA CONSTRUTIVA",0,IF(H66="ETAPA",OFFSET(C66,-1,0)+1,OFFSET(C66,-1,0))) -> 2 | D66: =IF(H66="ETAPA",0,IF(H66="SUBETAPA",OFFSET(D66,-1,0)+1,OFFSET(D66,-1,0))) -> 8 | E66: =IF(H66="Subetapa",0,IF(H66="serviço",OFFSET(E66,-1,0)+1,OFFSET(E66,-1,0))) -> 1
A67: =IF($H67="UNIDADE CONSTRUTIVA",OFFSET(A67,-1,0)+1,LARGE(A$3:A66,1)) -> 0 | B67: =IF(H67="UNIDADE CONSTRUTIVA",0,IF(H67="CÉLULA CONSTRUTIVA",OFFSET(B67,-1,0)+1,OFFSET(B67,-1,0))) -> 2 | C67: =IF(H67="CÉLULA CONSTRUTIVA",0,IF(H67="ETAPA",OFFSET(C67,-1,0)+1,OFFSET(C67,-1,0))) -> 2 | D67: =IF(H67="ETAPA",0,IF(H67="SUBETAPA",OFFSET(D67,-1,0)+1,OFFSET(D67,-1,0))) -> 8 | E67: =IF(H67="Subetapa",0,IF(H67="serviço",OFFSET(E67,-1,0)+1,OFFSET(E67,-1,0))) -> 1
A68: =IF($H68="UNIDADE CONSTRUTIVA",OFFSET(A68,-1,0)+1,LARGE(A$3:A67,1)) -> 0 | B68: =IF(H68="UNIDADE CONSTRUTIVA",0,IF(H68="CÉLULA CONSTRUTIVA",OFFSET(B68,-1,0)+1,OFFSET(B68,-1,0))) -> 2 | C68: =IF(H68="CÉLULA CONSTRUTIVA",0,IF(H68="ETAPA",OFFSET(C68,-1,0)+1,OFFSET(C68,-1,0))) -> 2 | D68: =IF(H68="ETAPA",0,IF(H68="SUBETAPA",OFFSET(D68,-1,0)+1,OFFSET(D68,-1,0))) -> 8 | E68: =IF(H68="Subetapa",0,IF(H68="serviço",OFFSET(E68,-1,0)+1,OFFSET(E68,-1,0))) -> 1
A69: =IF($H69="UNIDADE CONSTRUTIVA",OFFSET(A69,-1,0)+1,LARGE(A$3:A68,1)) -> 0 | B69: =IF(H69="UNIDADE CONSTRUTIVA",0,IF(H69="CÉLULA CONSTRUTIVA",OFFSET(B69,-1,0)+1,OFFSET(B69,-1,0))) -> 2 | C69: =IF(H69="CÉLULA CONSTRUTIVA",0,IF(H69="ETAPA",OFFSET(C69,-1,0)+1,OFFSET(C69,-1,0))) -> 2 | D69: =IF(H69="ETAPA",0,IF(H69="SUBETAPA",OFFSET(D69,-1,0)+1,OFFSET(D69,-1,0))) -> 8 | E69: =IF(H69="Subetapa",0,IF(H69="serviço",OFFSET(E69,-1,0)+1,OFFSET(E69,-1,0))) -> 1
A70: =IF($H70="UNIDADE CONSTRUTIVA",OFFSET(A70,-1,0)+1,LARGE(A$3:A69,1)) -> 0 | B70: =IF(H70="UNIDADE CONSTRUTIVA",0,IF(H70="CÉLULA CONSTRUTIVA",OFFSET(B70,-1,0)+1,OFFSET(B70,-1,0))) -> 2 | C70: =IF(H70="CÉLULA CONSTRUTIVA",0,IF(H70="ETAPA",OFFSET(C70,-1,0)+1,OFFSET(C70,-1,0))) -> 2 | D70: =IF(H70="ETAPA",0,IF(H70="SUBETAPA",OFFSET(D70,-1,0)+1,OFFSET(D70,-1,0))) -> 8 | E70: =IF(H70="Subetapa",0,IF(H70="serviço",OFFSET(E70,-1,0)+1,OFFSET(E70,-1,0))) -> 1
A71: =IF($H71="UNIDADE CONSTRUTIVA",OFFSET(A71,-1,0)+1,LARGE(A$3:A70,1)) -> 0 | B71: =IF(H71="UNIDADE CONSTRUTIVA",0,IF(H71="CÉLULA CONSTRUTIVA",OFFSET(B71,-1,0)+1,OFFSET(B71,-1,0))) -> 2 | C71: =IF(H71="CÉLULA CONSTRUTIVA",0,IF(H71="ETAPA",OFFSET(C71,-1,0)+1,OFFSET(C71,-1,0))) -> 2 | D71: =IF(H71="ETAPA",0,IF(H71="SUBETAPA",OFFSET(D71,-1,0)+1,OFFSET(D71,-1,0))) -> 8 | E71: =IF(H71="Subetapa",0,IF(H71="serviço",OFFSET(E71,-1,0)+1,OFFSET(E71,-1,0))) -> 1
A72: =IF($H72="UNIDADE CONSTRUTIVA",OFFSET(A72,-1,0)+1,LARGE(A$3:A71,1)) -> 0 | B72: =IF(H72="UNIDADE CONSTRUTIVA",0,IF(H72="CÉLULA CONSTRUTIVA",OFFSET(B72,-1,0)+1,OFFSET(B72,-1,0))) -> 2 | C72: =IF(H72="CÉLULA CONSTRUTIVA",0,IF(H72="ETAPA",OFFSET(C72,-1,0)+1,OFFSET(C72,-1,0))) -> 2 | D72: =IF(H72="ETAPA",0,IF(H72="SUBETAPA",OFFSET(D72,-1,0)+1,OFFSET(D72,-1,0))) -> 8 | E72: =IF(H72="Subetapa",0,IF(H72="serviço",OFFSET(E72,-1,0)+1,OFFSET(E72,-1,0))) -> 1
A73: =IF($H73="UNIDADE CONSTRUTIVA",OFFSET(A73,-1,0)+1,LARGE(A$3:A72,1)) -> 0 | B73: =IF(H73="UNIDADE CONSTRUTIVA",0,IF(H73="CÉLULA CONSTRUTIVA",OFFSET(B73,-1,0)+1,OFFSET(B73,-1,0))) -> 2 | C73: =IF(H73="CÉLULA CONSTRUTIVA",0,IF(H73="ETAPA",OFFSET(C73,-1,0)+1,OFFSET(C73,-1,0))) -> 2 | D73: =IF(H73="ETAPA",0,IF(H73="SUBETAPA",OFFSET(D73,-1,0)+1,OFFSET(D73,-1,0))) -> 8 | E73: =IF(H73="Subetapa",0,IF(H73="serviço",OFFSET(E73,-1,0)+1,OFFSET(E73,-1,0))) -> 1
A74: =IF($H74="UNIDADE CONSTRUTIVA",OFFSET(A74,-1,0)+1,LARGE(A$3:A73,1)) -> 0 | B74: =IF(H74="UNIDADE CONSTRUTIVA",0,IF(H74="CÉLULA CONSTRUTIVA",OFFSET(B74,-1,0)+1,OFFSET(B74,-1,0))) -> 2 | C74: =IF(H74="CÉLULA CONSTRUTIVA",0,IF(H74="ETAPA",OFFSET(C74,-1,0)+1,OFFSET(C74,-1,0))) -> 2 | D74: =IF(H74="ETAPA",0,IF(H74="SUBETAPA",OFFSET(D74,-1,0)+1,OFFSET(D74,-1,0))) -> 8 | E74: =IF(H74="Subetapa",0,IF(H74="serviço",OFFSET(E74,-1,0)+1,OFFSET(E74,-1,0))) -> 1
A75: =IF($H75="UNIDADE CONSTRUTIVA",OFFSET(A75,-1,0)+1,LARGE(A$3:A74,1)) -> 0 | B75: =IF(H75="UNIDADE CONSTRUTIVA",0,IF(H75="CÉLULA CONSTRUTIVA",OFFSET(B75,-1,0)+1,OFFSET(B75,-1,0))) -> 2 | C75: =IF(H75="CÉLULA CONSTRUTIVA",0,IF(H75="ETAPA",OFFSET(C75,-1,0)+1,OFFSET(C75,-1,0))) -> 2 | D75: =IF(H75="ETAPA",0,IF(H75="SUBETAPA",OFFSET(D75,-1,0)+1,OFFSET(D75,-1,0))) -> 8 | E75: =IF(H75="Subetapa",0,IF(H75="serviço",OFFSET(E75,-1,0)+1,OFFSET(E75,-1,0))) -> 1
A76: =IF($H76="UNIDADE CONSTRUTIVA",OFFSET(A76,-1,0)+1,LARGE(A$3:A75,1)) -> 0 | B76: =IF(H76="UNIDADE CONSTRUTIVA",0,IF(H76="CÉLULA CONSTRUTIVA",OFFSET(B76,-1,0)+1,OFFSET(B76,-1,0))) -> 2 | C76: =IF(H76="CÉLULA CONSTRUTIVA",0,IF(H76="ETAPA",OFFSET(C76,-1,0)+1,OFFSET(C76,-1,0))) -> 2 | D76: =IF(H76="ETAPA",0,IF(H76="SUBETAPA",OFFSET(D76,-1,0)+1,OFFSET(D76,-1,0))) -> 8 | E76: =IF(H76="Subetapa",0,IF(H76="serviço",OFFSET(E76,-1,0)+1,OFFSET(E76,-1,0))) -> 1
... A696: =IF($H696="UNIDADE CONSTRUTIVA",OFFSET(A696,-1,0)+1,LARGE(A$3:A695,1)) -> 0 | B696: =IF(H696="UNIDADE CONSTRUTIVA",0,IF(H696="CÉLULA CONSTRUTIVA",OFFSET(B696,-1,0)+1,OFFSET(B696,-1,0))) -> 2 | C696: =IF(H696="CÉLULA CONSTRUTIVA",0,IF(H696="ETAPA",OFFSET(C696,-1,0)+1,OFFSET(C696,-1,0))) -> 2 | D696: =IF(H696="ETAPA",0,IF(H696="SUBETAPA",OFFSET(D696,-1,0)+1,OFFSET(D696,-1,0))) -> 8 | E696: =IF(H696="Subetapa",0,IF(H696="serviço",OFFSET(E696,-1,0)+1,OFFSET(E696,-1,0))) -> 1

Sheet Ger_Executivo
A4: PROJETO: | C4: ='Ger_Tec e Adm'!I4 -> PARKSIDE RIO BRANCO | I4: REVISÃO: | J4: DATA
A5: EMPRESA: | C5: ='Ger_Tec e Adm'!I5 -> PARKSIDE | I5: R00
A6: GERENCIAMENTO EXECUTIVO
A7: Atalho | B7: NIVEL | C7: Item | D7: Descrição | E7: Unidade | F7: Quant. | G7: Preço un | H7: Total | I7: Considerações | J7: Situação
B8: CÉLULA CONSTRUTIVA | C8: 01 | D8: INFRAESTRUTURA | H8: =H9+H12+H22+H34 -> 1566010.8
B9: ETAPA | C9: 01.001 | D9: SERVIÇOS PRELIMINARES | H9: =H10 -> 37755.331
B10: SUBETAPA | C10: 01.001.001 | D10: DEMOLIÇÃO | H10: =H11 -> 37755.331
B11: SERVIÇO | C11: 01.001.001.001 | D11: Demolição de Estrutura Existente | E11: vb | F11: 1 | G11: 37755.331 | H11: =IF(B11="Serviço",G11*F11,IF(B11="CÉLULA CONSTRUTIVA",SUMIFS($H$8:$H$294,#REF!,#REF!,$B$8:$B$294,"Serviço"),IF(B11="ETAPA",SUMIFS($H$8:$H$294,#REF!,#REF!,#REF!,#REF!,$B$8:$B$294,"Serviço"),IF(B11="SUBETAPA",SUMIFS($H$8:$H$294,#REF!,#REF!,#REF!,#REF!,#REF!,#REF!,$B$8:$B$294,"Serviço"),0)))) -> 37755.331 | J11: Finalizado
B12: ETAPA | C12: 01.002 | D12: SERVIÇOS EM TERRA | H12: =H13 -> 340525.06
B13: SUBETAPA | C13: 01.002.001 | D13: MOVIMENTAÇÕES DE TERRA | H13: =H14+H17 -> 340525.06
B14: SERVIÇO | C14: 01.002.001.001 | D14: Movimentações de Terra Início Obra | E14: vb | F14: 1 | G14: =SUM(H15:H16) -> 272735.74 | H14: =IF(B14="Serviço",G14*F14,IF(B14="CÉLULA CONSTRUTIVA",SUMIFS($H$8:$H$294,#REF!,#REF!,$B$8:$B$294,"Serviço"),IF(B14="ETAPA",SUMIFS($H$8:$H$294,#REF!,#REF!,#REF!,#REF!,$B$8:$B$294,"Serviço"),IF(B14="SUBETAPA",SUMIFS($H$8:$H$294,#REF!,#REF!,#REF!,#REF!,#REF!,#REF!,$B$8:$B$294,"Serviço"),0)))) -> 272735.74 | J14: Finalizado
A15: ITEM | C15: 01 | D15: Limpeza de camada vegetal | E15: m2 | F15: ='Obra '!E8 -> 884.99 | G15: 12.5 | H15: =G15*F15 -> 11062.375
A16: ITEM | C16: 02 | D16: Terraplanagem | E16: m3 | F16: 5439.064 | G16: 48.11 | H16: =G16*F16 -> 261673.37 | I16: Sem projetos - considerado verba para escavação de todo o subsolo
B17: SERVIÇO | C17: 01.002.001.002 | D17: Movimentação de Terra Durante a Obra | E17: vb | F17: 1 | G17: =SUM(H18:H21) -> 67789.312 | H17: =IF(B17="Serviço",G17*F17,IF(B17="CÉLULA CONSTRUTIVA",SUMIFS($H$8:$H$294,#REF!,#REF!,$B$8:$B$294,"Serviço"),IF(B17="ETAPA",SUMIFS($H$8:$H$294,#REF!,#REF!,#REF!,#REF!,$B$8:$B$294,"Serviço"),IF(B17="SUBETAPA",SUMIFS($H$8:$H$294,#REF!,#REF!,#REF!,#REF!,#REF!,#REF!,$B$8:$B$294,"Serviço"),0)))) -> 67789.312 | J17: Finalizado
A18: ITEM | C18: 01 | D18: Escavação mecanizada para blocos de fundação, vigas de fundação e poço de elevador, com retroescavadeira | E18: m3 | F18: 632.94692 | G18: 36.36 | H18: =F18*G18 -> 23013.95
A19: ITEM | C19: 02 | D19: Reaterro mecanizado de valas para blocos e vigas de fundação, com retroescavadeira | E19: m3 | F19: 146.06467 | G19: 14.55 | H19: =F19*G19 -> 2125.241
A20: ITEM | C20: 03 | D20: Lastro de Concreto Magro, Aplicado em Blocos de Fundação, e=10cm | E20: m3 | F20: 28.0328 | G20: 495.23 | H20: =F20*G20 -> 13882.684 | I20: Estimado espessura média de 5cm
A21: ITEM | C21: 04 | D21: Movimentação de terra para bota-fora | E21: m3 | F21: 632.94692 | G21: 45.45 | H21: =F21*G21 -> 28767.438
B22: ETAPA | C22: 01.003 | D22: CONTENÇÕES E FUNDAÇÕES | H22: =H23+H29 -> 1163561
B23: SUBETAPA | C23: 01.003.001 | D23: FUNDAÇÕES RASAS E BLOCOS DE COROAMENTO | H23: =H24 -> 885091.58
B24: SERVIÇO | C24: 01.003.001.001 | D24: Estimativas / Fundação em Sapatas | E24: vb | F24: 1 | G24: =SUM(H25:H28) -> 885091.58 | H24: =IF(B24="Serviço",G24*F24,IF(B24="CÉLULA CONSTRUTIVA",SUMIFS($H$8:$H$294,#REF!,#REF!,$B$8:$B$294,"Serviço"),IF(B24="ETAPA",SUMIFS($H$8:$H$294,#REF!,#REF!,#REF!,#REF!,$B$8:$B$294,"Serviço"),IF(B24="SUBETAPA",SUMIFS($H$8:$H$294,#REF!,#REF!,#REF!,#REF!,#REF!,#REF!,$B$8:$B$294,"Serviço"),0)))) -> 885091.58 | J24: Finalizado
A25: ITEM | C25: 01 | D25: Fabricação, montagem e desmontagem de fôrma para sapata corrida, em madeira serrada, e=25 mm, 2 utilizações | E25: m2 | F25: 480.72 | G25: 111.32 | H25: =F25*G25*1.05 -> 56189.438
A26: ITEM | C26: 02 | D26: Armação aço CA-50 ø 10,0mm para infraestrutura (corte e dobra em obra) | E26: kg | F26: 42569 | G26: 7.66 | H26: =F26*G26*1.05 -> 342382.47
A27: ITEM | C27: 03 | D27: Piso de concreto armado | E27: m2 | F27: 700.82 | G27: 180 | H27: =F27*G27*1.05 -> 132454.98
A28: ITEM | C28: 04 | D28: Concreto Usinado bombeável 30MPa para infraestrutura com cristalizante - incluindo serviço de bombeamento | E28: m3 | F28: 486.88 | G28: 659.6022 | H28: =F28*G28*1.05*1.05 -> 354064.7
B29: SUBETAPA | C29: 01.003.002 | D29: CONTENÇÕES | H29: =H30 -> 278469.38
B30: SERVIÇO | C30: 01.003.002.001 | D30: Estimativas / Paredes de Contenção | E30: vb | F30: 1 | G30: =SUM(H31:H33) -> 278469.38 | H30: =IF(B30="Serviço",G30*F30,IF(B30="CÉLULA CONSTRUTIVA",SUMIFS($H$8:$H$294,#REF!,#REF!,$B$8:$B$294,"Serviço"),IF(B30="ETAPA",SUMIFS($H$8:$H$294,#REF!,#REF!,#REF!,#REF!,$B$8:$B$294,"Serviço"),IF(B30="SUBETAPA",SUMIFS($H$8:$H$294,#REF!,#REF!,#REF!,#REF!,#REF!,#REF!,$B$8:$B$294,"Serviço"),0)))) -> 278469.38 | J30: Finalizado
A31: ITEM | C31: 01 | D31: Fabricação, montagem e desmontagem de fôrma para cortina de contenção, em chapa de madeira compensada plastificada, e = 18 mm, 4 utilizações | E31: m2 | F31: 1254.3268 | G31: 48.24 | H31: =F31*G31 -> 60508.727
A32: ITEM | C32: 02 | D32: Armação aço CA-50 ø 10,0mm para infraestrutura (corte e dobra em obra) | E32: kg | F32: 10452.724 | G32: 7.66 | H32: =F32*G32 -> 80067.864
A33: ITEM | C33: 04 | D33: Concreto Usinado bombeável 30MPa para infraestrutura com cristalizante - incluindo serviço de bombeamento | E33: m3 | F33: 209.05447 | G33: 659.6022 | H33: =F33*G33 -> 137892.79
B34: ETAPA | C34: 01.004 | D34: DRENAGEM | H34: =H35 -> 24169.458
B35: SUBETAPA | C35: 01.004.001 | D35: DRENAGEM | H35: =H36+H37+H38 -> 24169.458
B36: SERVIÇO | C36: 01.004.001.001 | D36: Estimativas / Drenagem de Cortinas de Concreto com Geodreno | E36: m2 | F36: =2.6*107.48 -> 279.448 | G36: 86.49 | H36: =IF(B36="Serviço",G36*F36,IF(B36="CÉLULA CONSTRUTIVA",SUMIFS($H$8:$H$294,#REF!,#REF!,$B$8:$B$294,"Serviço"),IF(B36="ETAPA",SUMIFS($H$8:$H$294,#REF!,#REF!,#REF!,#REF!,$B$8:$B$294,"Serviço"),IF(B36="SUBETAPA",SUMIFS($H$8:$H$294,#REF!,#REF!,#REF!,#REF!,#REF!,#REF!,$B$8:$B$294,"Serviço"),0)))) -> 24169.458 | J36: Finalizado
B37: SERVIÇO | C37: 01.004.001.002 | D37: Drenagem Geral | E37: vb | G37: 0 | H37: =IF(B37="Serviço",G37*F37,IF(B37="CÉLULA CONSTRUTIVA",SUMIFS($H$8:$H$294,#REF!,#REF!,$B$8:$B$294,"Serviço"),IF(B37="ETAPA",SUMIFS($H$8:$H$294,#REF!,#REF!,#REF!,#REF!,$B$8:$B$294,"Serviço"),IF(B37="SUBETAPA",SUMIFS($H$8:$H$294,#REF!,#REF!,#REF!,#REF!,#REF!,#REF!,$B$8:$B$294,"Serviço"),0)))) -> 0 | I37: Aguardando quantitativos | J37: Finalizado
B38: SERVIÇO | C38: 01.004.001.003 | D38: Estimativas | Rebaixamento de Lençol Freático | E38: vb | G38: 0 | H38: =IF(B38="Serviço",G38*F38,IF(B38="CÉLULA CONSTRUTIVA",SUMIFS($H$8:$H$294,#REF!,#REF!,$B$8:$B$294,"Serviço"),IF(B38="ETAPA",SUMIFS($H$8:$H$294,#REF!,#REF!,#REF!,#REF!,$B$8:$B$294,"Serviço"),IF(B38="SUBETAPA",SUMIFS($H$8:$H$294,#REF!,#REF!,#REF!,#REF!,#REF!,#REF!,$B$8:$B$294,"Serviço"),0)))) -> 0 | I38: Informado em formulário que não será necessário | J38: Finalizado
B39: CÉLULA CONSTRUTIVA | C39: 02 | D39: OBRA | H39: =H40+H51+H63+H71+H81+H94+H130+H142+H157+H171+H176+H195+H198+H212+H227+H233+H236+H246+H249+H271+H276+H287 -> 27924017
B40: ETAPA | C40: 02.001 | D40: EQUIPAMENTOS | H40: =H41 -> 863599.44
B41: SUBETAPA | C41: 02.001.001 | D41: EQUIPAMENTOS ALUGADOS | H41: =SUM(H42:H50) -> 863599.44
B42: SERVIÇO | C42: 02.001.001.001 | D42: Aluguel de Equipamentos | E42: vb | F42: 1 | G42: 70990 | H42: =IF(B42="Serviço",G42*F42,IF(B42="CÉLULA CONSTRUTIVA",SUMIFS($H$8:$H$294,#REF!,#REF!,$B$8:$B$294,"Serviço"),IF(B42="ETAPA",SUMIFS($H$8:$H$294,#REF!,#REF!,#REF!,#REF!,$B$8:$B$294,"Serviço"),IF(B42="SUBETAPA",SUMIFS($H$8:$H$294,#REF!,#REF!,#REF!,#REF!,#REF!,#REF!,$B$8:$B$294,"Serviço"),0)))) -> 70990 | I42: Guincho coluna + andaime + verba para ferramentas | J42: Finalizado
A43: ITEM | C43: 01 | D43: Guincho de coluna | E43: mes | F43: 12 | G43: 850 | H43: =F43*G43 -> 10200
A44: ITEM | C44: 02 | D44: Andaime | E44: mes | F44: 6 | G44: 1700 | H44: =F44*G44 -> 10200 | I44: Apoio fachada, andaime tubular
A45: ITEM | C45: 03 | D45: Ferramentas gerais | E45: vb | F45: 1 | G45: =CANTEIRO!D14 -> 57600 | H45: =F45*G45 -> 57600
B46: SERVIÇO | C46: 02.001.001.002 | D46: Aluguel de Jau | E46: mês | F46: 10 | G46: =1850*2 -> 3700 | H46: =IF(B46="Serviço",G46*F46,IF(B46="CÉLULA CONSTRUTIVA",SUMIFS($H$8:$H$294,#REF!,#REF!,$B$8:$B$294,"Serviço"),IF(B46="ETAPA",SUMIFS($H$8:$H$294,#REF!,#REF!,#REF!,#REF!,$B$8:$B$294,"Serviço"),IF(B46="SUBETAPA",SUMIFS($H$8:$H$294,#REF!,#REF!,#REF!,#REF!,#REF!,#REF!,$B$8:$B$294,"Serviço"),0)))) -> 37000 | I46: Balancim - 2 unidades para o período de execução de fachada - Montagem em desmontagem não considerada | J46: Finalizado
B47: SERVIÇO | C47: 02.001.001.004 | D47: Tela Fachadeira | E47: m2 | F47: =EPCs!D41 -> 1643.326 | G47: 7.95 | H47: =IF(B47="Serviço",G47*F47,IF(B47="CÉLULA CONSTRUTIVA",SUMIFS($H$8:$H$294,#REF!,#REF!,$B$8:$B$294,"Serviço"),IF(B47="ETAPA",SUMIFS($H$8:$H$294,#REF!,#REF!,#REF!,#REF!,$B$8:$B$294,"Serviço"),IF(B47="SUBETAPA",SUMIFS($H$8:$H$294,#REF!,#REF!,#REF!,#REF!,#REF!,#REF!,$B$8:$B$294,"Serviço"),0)))) -> 13064.442 | I47: Tela fachadeira em Polietileno Malha 1,5x1,5mm | J47: Finalizado
B48: SERVIÇO | C48: 02.001.001.005 | D48: Elevador | E48: mês | F48: 16 | G48: 39506.25 | H48: =IF(B48="Serviço",G48*F48,IF(B48="CÉLULA CONSTRUTIVA",SUMIFS($H$8:$H$294,#REF!,#REF!,$B$8:$B$294,"Serviço"),IF(B48="ETAPA",SUMIFS($H$8:$H$294,#REF!,#REF!,#REF!,#REF!,$B$8:$B$294,"Serviço"),IF(B48="SUBETAPA",SUMIFS($H$8:$H$294,#REF!,#REF!,#REF!,#REF!,#REF!,#REF!,$B$8:$B$294,"Serviço"),0)))) -> 632100 | I48: Montada no 3º pavimento de supraestrutura, desmontada após a instalação do elevador da obra | J48: Finalizado
B49: SERVIÇO | C49: 02.001.001.006 | D49: Montagem e Desmontagem Elevador | E49: vb | F49: 1 | G49: 12285 | H49: =IF(B49="Serviço",G49*F49,IF(B49="CÉLULA CONSTRUTIVA",SUMIFS($H$8:$H$294,#REF!,#REF!,$B$8:$B$294,"Serviço"),IF(B49="ETAPA",SUMIFS($H$8:$H$294,#REF!,#REF!,#REF!,#REF!,$B$8:$B$294,"Serviço"),IF(B49="SUBETAPA",SUMIFS($H$8:$H$294,#REF!,#REF!,#REF!,#REF!,#REF!,#REF!,$B$8:$B$294,"Serviço"),0)))) -> 12285 | I49: Incluso Mobilização e desmobilização para a obra | J49: Finalizado
B50: SERVIÇO | C50: 02.001.001.007 | D50: Manutenção Elevador | E50: mês | F50: =F48 -> 16 | G50: 1260 | H50: =IF(B50="Serviço",G50*F50,IF(B50="CÉLULA CONSTRUTIVA",SUMIFS($H$8:$H$294,#REF!,#REF!,$B$8:$B$294,"Serviço"),IF(B50="ETAPA",SUMIFS($H$8:$H$294,#REF!,#REF!,#REF!,#REF!,$B$8:$B$294,"Serviço"),IF(B50="SUBETAPA",SUMIFS($H$8:$H$294,#REF!,#REF!,#REF!,#REF!,#REF!,#REF!,$B$8:$B$294,"Serviço"),0)))) -> 20160 | I50: Manutenção preventiva | J50: Finalizado
B51: ETAPA | C51: 02.002 | D51: ESTRUTURAS | H51: =H52 -> 3324999.5
B52: SUBETAPA | C52: 02.002.001 | D52: ESTRUTURAS EM CONCRETO | H52: =H53+H56+H58+H61 -> 3324999.5
B53: SERVIÇO | C53: 02.002.001.001 | D53: Estimativas / Forma para Supraestrutura | E53: vb | F53: 1 | G53: =SUM(H54:H55) -> 273063.29 | H53: =IF(B53="Serviço",G53*F53,IF(B53="CÉLULA CONSTRUTIVA",SUMIFS($H$8:$H$294,#REF!,#REF!,$B$8:$B$294,"Serviço"),IF(B53="ETAPA",SUMIFS($H$8:$H$294,#REF!,#REF!,#REF!,#REF!,$B$8:$B$294,"Serviço"),IF(B53="SUBETAPA",SUMIFS($H$8:$H$294,#REF!,#REF!,#REF!,#REF!,#REF!,#REF!,$B$8:$B$294,"Serviço"),0)))) -> 273063.29 | J53: Finalizado
A54: ITEM | C54: 01 | D54: Fabricação de Fôrma em Chapa de Madeira Compensada Resinada, E=14mm | E54: m2 | F54: 2598.03 | G54: 75.952301 | H54: =F54*G54 -> 197326.36 | I54: 3 jogos
A55: ITEM | C55: 01 | D55: Montagem e Desmontagem de Fôrma de Vigas, em Chapa de Madeira Compensada Resinada | E55: m2 | F55: 18186.21 | G55: 4.1645255 | H55: =F55*G55 -> 75736.935
B56: SERVIÇO | C56: 02.002.001.002 | D56: Estimativas / Armação para Supraestrutura | E56: vb | F56: 1 | G56: =SUM(H57) -> 1492568.2 | H56: =F56*G56 -> 1492568.2 | J56: Finalizado
A57: ITEM | C57: 01 | D57: Armação Aço CA-50, Diâmetro de 10,0mm para Supraestrutura, Corte e Dobra em Obra | E57: kg | F57: 194852.25 | G57: 7.66 | H57: =F57*G57 -> 1492568.2
B58: SERVIÇO | C58: 02.002.001.003 | D58: Estimativas / Complementares | E58: vb | F58: 1 | G58: =SUM(H59:H60) -> 310873.86 | H58: =F58*G58 -> 310873.86 | I58: Reutilização 3 vezes | J58: Finalizado
A59: ITEM | C59: 01 | D59: Escoramento | E59: mes | F59: 11 | G59: =('Obra '!E19/15)*2*18 -> 13154.76 | H59: =F59*G59 -> 144702.36
A60: ITEM | C60: 01 | D60: Cubetas | E60: mes | F60: 11 | G60: =(ROUND(('Obra '!E19/15)/(0.7*0.7),0)*1.5)*0.45*30 -> 15106.5 | H60: =F60*G60 -> 166171.5
B61: SERVIÇO | C61: 02.002.001.005 | D61: Estimativas / Concreto para Estrutura | E61: vb | F61: 1 | G61: =SUM(H62) -> 1248494.1 | H61: =IF(B61="Serviço",G61*F61,IF(B61="CÉLULA CONSTRUTIVA",SUMIFS($H$8:$H$294,#REF!,#REF!,$B$8:$B$294,"Serviço"),IF(B61="ETAPA",SUMIFS($H$8:$H$294,#REF!,#REF!,#REF!,#REF!,$B$8:$B$294,"Serviço"),IF(B61="SUBETAPA",SUMIFS($H$8:$H$294,#REF!,#REF!,#REF!,#REF!,#REF!,#REF!,$B$8:$B$294,"Serviço"),0)))) -> 1248494.1 | J61: Finalizado
A62: ITEM | C62: 01 | D62: Concreto Usinado FCK = 30MPa Bombeavel Para Supraestrutura | E62: m3 | F62: 2165.025 | G62: 576.665 | H62: =F62*G62 -> 1248494.1
B63: ETAPA | C63: 02.003 | D63: COBERTURA | H63: =H64 -> 31661.147
B64: SUBETAPA | C64: 02.003.001 | D64: COBERTURA | H64: =H65+H70 -> 31661.147
B65: SERVIÇO | C65: 02.003.001.001 | D65: Estimativas / Cobertura | E65: vb | F65: 1 | G65: =SUM(H66:H68) -> 31661.147 | H65: =IF(B65="Serviço",G65*F65,IF(B65="CÉLULA CONSTRUTIVA",SUMIFS($H$8:$H$294,#REF!,#REF!,$B$8:$B$294,"Serviço"),IF(B65="ETAPA",SUMIFS($H$8:$H$294,#REF!,#REF!,#REF!,#REF!,$B$8:$B$294,"Serviço"),IF(B65="SUBETAPA",SUMIFS($H$8:$H$294,#REF!,#REF!,#REF!,#REF!,#REF!,#REF!,$B$8:$B$294,"Serviço"),0)))) -> 31661.147 | J65: Finalizado
A66: ITEM | C66: 01 | D66: Estrutura e trama para cobertura em madeira | E66: m2 | F66: =Arquitetura!D15+Arquitetura!D18 -> 129.99 | G66: 119.77 | H66: =F66*G66 -> 15568.902
A67: ITEM | C67: 02 | D67: Telhamento para cobertura em Fribrocimento | E67: m2 | F67: =F66 -> 129.99 | G67: 94.99745 | H67: =F67*G67 -> 12348.719
A68: ITEM | C68: 03 | D68: Calha em alumínio | E68: m | F68: 51.29 | G68: 72.987449 | H68: =F68*G68 -> 3743.5263
A69: ITEM | C69: 03 | D69: Rufo em alumínio | E69: m | F69: =F68+9.3*2+1.86*2 -> 73.61 | G69: 43.100562 | H69: =F69*G69 -> 3172.6324
B70: SERVIÇO | C70: 02.003.001.002 | D70: Estimativas / Cobertura de Vidro | E70: vb | H70: =IF(B70="Serviço",G70*F70,IF(B70="CÉLULA CONSTRUTIVA",SUMIFS($H$8:$H$294,#REF!,#REF!,$B$8:$B$294,"Serviço"),IF(B70="ETAPA",SUMIFS($H$8:$H$294,#REF!,#REF!,#REF!,#REF!,$B$8:$B$294,"Serviço"),IF(B70="SUBETAPA",SUMIFS($H$8:$H$294,#REF!,#REF!,#REF!,#REF!,#REF!,#REF!,$B$8:$B$294,"Serviço"),0)))) -> 0 | I70: Não esta previsto em projeto | J70: Finalizado
B71: ETAPA | C71: 02.004 | D71: PAREDES E FECHAMENTOS | H71: =H72+H79 -> 743690.92
B72: SUBETAPA | C72: 02.004.001 | D72: PAREDES DE VEDAÇÃO EM BLOCOS CERÂMICOS | H72: =H73 -> 477347.39
B73: SERVIÇO | C73: 02.004.001.001 | D73: Alvenaria de Vedação com Blocos Cerâmicos com Argamassa Estabilizada, incluso Vergas, Contravergas e Pilaretes - 19x19x19 cm | E73: vb | F73: 1 | G73: =SUM(H74:H78) -> 477347.39 | H73: =IF(B73="Serviço",G73*F73,IF(B73="CÉLULA CONSTRUTIVA",SUMIFS($H$8:$H$294,#REF!,#REF!,$B$8:$B$294,"Serviço"),IF(B73="ETAPA",SUMIFS($H$8:$H$294,#REF!,#REF!,#REF!,#REF!,$B$8:$B$294,"Serviço"),IF(B73="SUBETAPA",SUMIFS($H$8:$H$294,#REF!,#REF!,#REF!,#REF!,#REF!,#REF!,$B$8:$B$294,"Serviço"),0)))) -> 477347.39 | J73: Finalizado
A74: ITEM | C74: 01 | D74: Alvenaria de vedacao de blocos ceramicos furados na horizontal de 11.5x19x29cm (espessura 11.5cm) com argamassa dosada em obra | E74: m2 | F74: =Arquitetura!G166 -> 2650.29 | G74: 37.57 | H74: =F74*G74 -> 99571.395
A75: ITEM | C75: 02 | D75: Alvenaria de vedacao de blocos ceramicos furados na horizontal de 14x19x29cm (espessura 14cm) com argamassa dosada em obra | E75: m2 | F75: =Arquitetura!G167 -> 4660.19 | G75: 59.61 | H75: =F75*G75 -> 277793.93
A76: ITEM | C76: 03 | D76: Encunhamento De Alvenaria De Vedação Com Argamassa Expansiva | E76: m | F76: =Arquitetura!G181 -> 3640.81 | G76: 14.8225 | H76: =F76*G76 -> 53965.906
A77: ITEM | C77: 04 | D77: Tela soldada para ligacao alvenaria/estrutura - para blocos de 9 a 14cm | E77: un | F77: =(F74+F75)*0.04 -> 292.4192 | G77: 4.1072 | H77: =F77*G77 -> 1201.0241
A78: ITEM | C78: 05 | D78: Verga/contraverga de concreto, moldada in loco | E78: m | F78: =Arquitetura!G182+Arquitetura!G183 -> 738.1 | G78: 60.716898 | H78: =F78*G78 -> 44815.142
B79: SUBETAPA | C79: 02.004.002 | D79: PAREDES DE VEDAÇÃO EM DRYWALL | H79: =H80 -> 266343.53
B80: SERVIÇO | C80: 02.004.002.001 | D80: Parede Drywall, Uso Interno, Montante 70mm, Com Duas Face Simples Standart e Resistente à umidade (ST/70/RU) | E80: m2 | F80: =Arquitetura!G176+Arquitetura!G177 -> 1411.74 | G80: =14.6578+10.0474+2.4948+25.4337+72.3799+2.3855+0.7008+14.815+1.8168+0.0961+3.8355+40 -> 188.6633 | H80: =IF(B80="Serviço",G80*F80,IF(B80="CÉLULA CONSTRUTIVA",SUMIFS($H$8:$H$294,#REF!,#REF!,$B$8:$B$294,"Serviço"),IF(B80="ETAPA",SUMIFS($H$8:$H$294,#REF!,#REF!,#REF!,#REF!,$B$8:$B$294,"Serviço"),IF(B80="SUBETAPA",SUMIFS($H$8:$H$294,#REF!,#REF!,#REF!,#REF!,#REF!,#REF!,$B$8:$B$294,"Serviço"),0)))) -> 266343.53 | J80: Finalizado
B81: ETAPA | C81: 02.005 | D81: REVESTIMENTOS ARGAMASSADOS | H81: =H82+H90 -> 875012.99
B82: SUBETAPA | C82: 02.005.001 | D82: REBOCO E CHAPISCO | H82: =H83+H86 -> 257960.38
B83: SERVIÇO | C83: 02.005.001.001 | D83: Reboco Interno com Argamassa Estabilizada - e=2,0 cm | E83: m2 | F83: =Arquitetura!J168 -> 10316.194 | G83: =G84+G85 -> 14.348636 | H83: =IF(B83="Serviço",G83*F83,IF(B83="CÉLULA CONSTRUTIVA",SUMIFS($H$8:$H$294,#REF!,#REF!,$B$8:$B$294,"Serviço"),IF(B83="ETAPA",SUMIFS($H$8:$H$294,#REF!,#REF!,#REF!,#REF!,$B$8:$B$294,"Serviço"),IF(B83="SUBETAPA",SUMIFS($H$8:$H$294,#REF!,#REF!,#REF!,#REF!,#REF!,#REF!,$B$8:$B$294,"Serviço"),0)))) -> 148023.32 | I83: Custo de chapisco + reboco | J83: Finalizado
A84: ITEM | C84: 01 | D84: Chapisco aplicados em alvenaria, com argamassa (Traço 1:5), aplicação convencional. | E84: m2 | F84: =Arquitetura!J168 -> 10316.194 | G84: 4.2062328 | H84: =F84*G84 -> 43392.313
A85: ITEM | C85: 02 | D85: Massa unica para reboco interno em argamassa (Traço 1:5), espessura de 2,0cm | E85: m2 | F85: =Arquitetura!J168 -> 10316.194 | G85: 10.142404 | H85: =F85*G85 -> 104631
B86: SERVIÇO | C86: 02.005.001.002 | D86: Reboco Externo com Argamassa Estabilizada - e=3,0 cm | E86: m2 | F86: =Arquitetura!G192 -> 4821.666 | G86: =G87+G88 -> 22.800639 | H86: =IF(B86="Serviço",G86*F86,IF(B86="CÉLULA CONSTRUTIVA",SUMIFS($H$8:$H$294,#REF!,#REF!,$B$8:$B$294,"Serviço"),IF(B86="ETAPA",SUMIFS($H$8:$H$294,#REF!,#REF!,#REF!,#REF!,$B$8:$B$294,"Serviço"),IF(B86="SUBETAPA",SUMIFS($H$8:$H$294,#REF!,#REF!,#REF!,#REF!,#REF!,#REF!,$B$8:$B$294,"Serviço"),0)))) -> 109937.07 | I86: Custo de chapisco + reboco - Na planilha informa preparação em obra traço 1:5 | J86: Finalizado
A87: ITEM | C87: 01 | D87: Chapisco aplicados em alvenaria externas, com argamassa (Traço 1:5), aplicação convencional. | E87: m2 | F87: =Arquitetura!G192 -> 4821.666 | G87: 4.2062328 | H87: =F87*G87 -> 20281.05
A88: ITEM | C88: 02 | D88: Massa unica para reboco externo em Argamassa preparada em central / usinada, espessura de 35mm | E88: m2 | F88: =Arquitetura!G192 -> 4821.666 | G88: 18.594407 | H88: =F88*G88 -> 89656.018
B89: SERVIÇO | C89: 02.005.001.002 | D89: Estucamento de estrutura de concreto em pilares,vigas e lajes | E89: m2 | F89: =Arquitetura!H170+Arquitetura!G398 -> 2648.92 | G89: 4.198 | H89: =IF(B89="Serviço",G89*F89,IF(B89="CÉLULA CONSTRUTIVA",SUMIFS($H$8:$H$294,#REF!,#REF!,$B$8:$B$294,"Serviço"),IF(B89="ETAPA",SUMIFS($H$8:$H$294,#REF!,#REF!,#REF!,#REF!,$B$8:$B$294,"Serviço"),IF(B89="SUBETAPA",SUMIFS($H$8:$H$294,#REF!,#REF!,#REF!,#REF!,#REF!,#REF!,$B$8:$B$294,"Serviço"),0)))) -> 11120.166 | I89: Tratamento de elementos aparentes | J89: Finalizado
B90: SUBETAPA | C90: 02.005.002 | D90: CONTRAPISO | H90: =H91 -> 617052.6
B91: SERVIÇO | C91: 02.005.002.001 | D91: Contrapiso em Argamassa Estabilizada - e=7 cm | E91: m2 | F91: =Arquitetura!G414 -> 7457.78 | G91: =(H92+H93)/F91 -> 82.739448 | H91: =IF(B91="Serviço",G91*F91,IF(B91="CÉLULA CONSTRUTIVA",SUMIFS($H$8:$H$294,#REF!,#REF!,$B$8:$B$294,"Serviço"),IF(B91="ETAPA",SUMIFS($H$8:$H$294,#REF!,#REF!,#REF!,#REF!,$B$8:$B$294,"Serviço"),IF(B91="SUBETAPA",SUMIFS($H$8:$H$294,#REF!,#REF!,#REF!,#REF!,#REF!,#REF!,$B$8:$B$294,"Serviço"),0)))) -> 617052.6 | I91: Incluso custo com isolamento - conforme preenchimento de planilha piso autonivelante | J91: Finalizado
A92: ITEM | C92: 01 | D92: Contrapiso comum em argamassa estabilizada, auto nivelado, espessura 8cm | E92: m2 | F92: =Arquitetura!G414 -> 7457.78 | G92: 46.806826 | H92: =F92*G92 -> 349075.01
A93: ITEM | C93: 02 | D93: Acústica para Contrapiso lã de Pet | E93: m2 | F93: =Arquitetura!G415 -> 6864.18 | G93: 39.04 | H93: =F93*G93 -> 267977.59 | I93: Areas privativas
B94: ETAPA | C94: 02.006 | D94: IMPERMEABILIZAÇÃO | H94: =H95 -> 411650.95
B95: SUBETAPA | C95: 02.006.001 | D95: IMPERMEABILIZAÇÃO | H95: =H96+H103+H118+H106+H113+H125 -> 411650.95
B96: SERVIÇO | C96: 02.006.001.001 | D96: Impermeabilização de Banheiros com Argamassa Cristalizante | E96: m2 | F96: 2165.025 | G96: =SUM(H97:H102)/F96 -> 97.971839 | H96: =IF(B96="Serviço",G96*F96,IF(B96="CÉLULA CONSTRUTIVA",SUMIFS($H$8:$H$294,#REF!,#REF!,$B$8:$B$294,"Serviço"),IF(B96="ETAPA",SUMIFS($H$8:$H$294,#REF!,#REF!,#REF!,#REF!,$B$8:$B$294,"Serviço"),IF(B96="SUBETAPA",SUMIFS($H$8:$H$294,#REF!,#REF!,#REF!,#REF!,#REF!,#REF!,$B$8:$B$294,"Serviço"),0)))) -> 212111.48 | I96: Valor regularização + impermeabilização | J96: Finalizado
A97: ITEM | C97: 01 | D97: Regularização de superfície para impermeabilização | E97: m2 | F97: =F96 -> 2165.025 | G97: 6.9391 | H97: =F97*G97 -> 15023.325
A98: ITEM | C98: 02 | D98: Impermeabilização De Superfície Com Argamassa Polimérica / Membrana Acrílica, 3 Demãos | E98: m2 | F98: =F96 -> 2165.025 | G98: 36.256 | H98: =F98*G98 -> 78495.146
A99: ITEM | C99: 02 | D99: Tratamento de ralos com manta poliester | E99: un | F99: =Arquitetura!C654 -> 176 | G99: 8.76 | H99: =F99*G99 -> 1541.76
A100: ITEM | C100: 03 | D100: Mão de obra para regularização de superfície | E100: m2 | F100: =F96 -> 2165.025 | G100: 20 | H100: =F100*G100 -> 43300.5
A101: ITEM | C101: 04 | D101: Mão de obra impermeabilização de argamassa cristalizante | E101: m2 | F101: =F96 -> 2165.025 | G101: 30 | H101: =F101*G101 -> 64950.75
A102: ITEM | C102: 04 | D102: Mão de obra tratamento de ralos com manta poliester | E102: un | F102: =F99 -> 176 | G102: 50 | H102: =F102*G102 -> 8800
B103: SERVIÇO | C103: 02.006.001.002 | D103: Impermeabilização de Requadros com Argamassas Cristalizantes | E103: m2 | F103: =SUM(Arquitetura!D596:D639) -> 585.84 | G103: =SUM(G104:G105) -> 66.256 | H103: =IF(B103="Serviço",G103*F103,IF(B103="CÉLULA CONSTRUTIVA",SUMIFS($H$8:$H$294,#REF!,#REF!,$B$8:$B$294,"Serviço"),IF(B103="ETAPA",SUMIFS($H$8:$H$294,#REF!,#REF!,#REF!,#REF!,$B$8:$B$294,"Serviço"),IF(B103="SUBETAPA",SUMIFS($H$8:$H$294,#REF!,#REF!,#REF!,#REF!,#REF!,#REF!,$B$8:$B$294,"Serviço"),0)))) -> 38815.415 | I103: Considerado 80 cm - 20cm parede + 60 cm descida | J103: Finalizado
...

Sheet Custos Enxoval
G4: PROJETO: | I4: ='Ger_Tec e Adm'!I4 -> PARKSIDE RIO BRANCO | O4: REVISÃO: | P4: DATA
G5: EMPRESA: | I5: ='Ger_Tec e Adm'!I5 -> PARKSIDE | O5: R00
A6: Unidade Construtiva | B6: Célula Construtiva | C6: Etapa | D6: Subetapa | E6: Serviço | G6: GERENCIAMENTO EXECUTIVO
A7: 0 | B7: 0 | C7: 0 | D7: 0 | E7: 0 | G7: Atalho | H7: NIVEL | I7: Item | J7: Descrição | K7: Unidade | L7: Quant. | M7: Preço un | N7: Total | O7: Considerações | P7: Situação
A8: =IF($H8="UNIDADE CONSTRUTIVA",OFFSET(A8,-1,0)+1,LARGE(A$3:A7,1)) -> 0 | B8: =IF(H8="UNIDADE CONSTRUTIVA",0,IF(H8="CÉLULA CONSTRUTIVA",OFFSET(B8,-1,0)+1,OFFSET(B8,-1,0))) -> 1 | C8: =IF(H8="CÉLULA CONSTRUTIVA",0,IF(H8="ETAPA",OFFSET(C8,-1,0)+1,OFFSET(C8,-1,0))) -> 0 | D8: =IF(H8="ETAPA",0,IF(H8="SUBETAPA",OFFSET(D8,-1,0)+1,OFFSET(D8,-1,0))) -> 0 | E8: =IF(H8="Subetapa",0,IF(H8="serviço",OFFSET(E8,-1,0)+1,OFFSET(E8,-1,0))) -> 0 | H8: CÉLULA CONSTRUTIVA | I8: =IF(H8="Unidade Construtiva",TEXT(A8,"00"),IF(H8="Célula Construtiva",TEXT(B8,"00"),IF(H8="Etapa",CONCATENATE(TEXT(B8,"00"),".",TEXT(C8,"000")),IF(H8="Subetapa",CONCATENATE(TEXT(B8,"00"),".",TEXT(C8,"000"),".",TEXT(D8,"000")),IF(H8="Serviço",CONCATENATE(TEXT(B8,"00"),".",TEXT(C8,"000"),".",TEXT(D8,"000"),".",TEXT(E8,"000")),""))))) -> 01 | J8: ENXOVAL | N8: =IF(H8="Serviço",M8*L8,IF(H8="CÉLULA CONSTRUTIVA",SUMIFS($N$8:$N$38,$B$8:$B$38,B8,$H$8:$H$38,"Serviço"),IF(H8="ETAPA",SUMIFS($N$8:$N$38,$B$8:$B$38,B8,$C$8:$C$38,C8,$H$8:$H$38,"Serviço"),IF(H8="SUBETAPA",SUMIFS($N$8:$N$38,$B$8:$B$38,B8,$C$8:$C$38,C8,$D$8:$D$38,D8,$H$8:$H$38,"Serviço"),0)))) -> 10344375
A9: =IF($H9="UNIDADE CONSTRUTIVA",OFFSET(A9,-1,0)+1,LARGE(A$3:A8,1)) -> 0 | B9: =IF(H9="UNIDADE CONSTRUTIVA",0,IF(H9="CÉLULA CONSTRUTIVA",OFFSET(B9,-1,0)+1,OFFSET(B9,-1,0))) -> 1 | C9: =IF(H9="CÉLULA CONSTRUTIVA",0,IF(H9="ETAPA",OFFSET(C9,-1,0)+1,OFFSET(C9,-1,0))) -> 1 | D9: =IF(H9="ETAPA",0,IF(H9="SUBETAPA",OFFSET(D9,-1,0)+1,OFFSET(D9,-1,0))) -> 0 | E9: =IF(H9="Subetapa",0,IF(H9="serviço",OFFSET(E9,-1,0)+1,OFFSET(E9,-1,0))) -> 0 | H9: ETAPA | I9: =IF(H9="Unidade Construtiva",TEXT(A9,"00"),IF(H9="Célula Construtiva",TEXT(B9,"00"),IF(H9="Etapa",CONCATENATE(TEXT(B9,"00"),".",TEXT(C9,"000")),IF(H9="Subetapa",CONCATENATE(TEXT(B9,"00"),".",TEXT(C9,"000"),".",TEXT(D9,"000")),IF(H9="Serviço",CONCATENATE(TEXT(B9,"00"),".",TEXT(C9,"000"),".",TEXT(D9,"000"),".",TEXT(E9,"000")),""))))) -> 01.001 | J9: SISTEMAS INTERNOS | N9: =IF(H9="Serviço",M9*L9,IF(H9="CÉLULA CONSTRUTIVA",SUMIFS($N$8:$N$38,$B$8:$B$38,B9,$H$8:$H$38,"Serviço"),IF(H9="ETAPA",SUMIFS($N$8:$N$38,$B$8:$B$38,B9,$C$8:$C$38,C9,$H$8:$H$38,"Serviço"),IF(H9="SUBETAPA",SUMIFS($N$8:$N$38,$B$8:$B$38,B9,$C$8:$C$38,C9,$D$8:$D$38,D9,$H$8:$H$38,"Serviço"),0)))) -> 95830.55
A10: =IF($H10="UNIDADE CONSTRUTIVA",OFFSET(A10,-1,0)+1,LARGE(A$3:A9,1)) -> 0 | B10: =IF(H10="UNIDADE CONSTRUTIVA",0,IF(H10="CÉLULA CONSTRUTIVA",OFFSET(B10,-1,0)+1,OFFSET(B10,-1,0))) -> 1 | C10: =IF(H10="CÉLULA CONSTRUTIVA",0,IF(H10="ETAPA",OFFSET(C10,-1,0)+1,OFFSET(C10,-1,0))) -> 1 | D10: =IF(H10="ETAPA",0,IF(H10="SUBETAPA",OFFSET(D10,-1,0)+1,OFFSET(D10,-1,0))) -> 1 | E10: =IF(H10="Subetapa",0,IF(H10="serviço",OFFSET(E10,-1,0)+1,OFFSET(E10,-1,0))) -> 0 | H10: SUBETAPA | I10: =IF(H10="Unidade Construtiva",TEXT(A10,"00"),IF(H10="Célula Construtiva",TEXT(B10,"00"),IF(H10="Etapa",CONCATENATE(TEXT(B10,"00"),".",TEXT(C10,"000")),IF(H10="Subetapa",CONCATENATE(TEXT(B10,"00"),".",TEXT(C10,"000"),".",TEXT(D10,"000")),IF(H10="Serviço",CONCATENATE(TEXT(B10,"00"),".",TEXT(C10,"000"),".",TEXT(D10,"000"),".",TEXT(E10,"000")),""))))) -> 01.001.001 | J10: TELECOM | N10: =IF(H10="Serviço",M10*L10,IF(H10="CÉLULA CONSTRUTIVA",SUMIFS($N$8:$N$38,$B$8:$B$38,B10,$H$8:$H$38,"Serviço"),IF(H10="ETAPA",SUMIFS($N$8:$N$38,$B$8:$B$38,B10,$C$8:$C$38,C10,$H$8:$H$38,"Serviço"),IF(H10="SUBETAPA",SUMIFS($N$8:$N$38,$B$8:$B$38,B10,$C$8:$C$38,C10,$D$8:$D$38,D10,$H$8:$H$38,"Serviço"),0)))) -> 47630.55
A11: =IF($H11="UNIDADE CONSTRUTIVA",OFFSET(A11,-1,0)+1,LARGE(A$3:A10,1)) -> 0 | B11: =IF(H11="UNIDADE CONSTRUTIVA",0,IF(H11="CÉLULA CONSTRUTIVA",OFFSET(B11,-1,0)+1,OFFSET(B11,-1,0))) -> 1 | C11: =IF(H11="CÉLULA CONSTRUTIVA",0,IF(H11="ETAPA",OFFSET(C11,-1,0)+1,OFFSET(C11,-1,0))) -> 1 | D11: =IF(H11="ETAPA",0,IF(H11="SUBETAPA",OFFSET(D11,-1,0)+1,OFFSET(D11,-1,0))) -> 1 | E11: =IF(H11="Subetapa",0,IF(H11="serviço",OFFSET(E11,-1,0)+1,OFFSET(E11,-1,0))) -> 1 | H11: SERVIÇO | I11: =IF(H11="Unidade Construtiva",TEXT(A11,"00"),IF(H11="Célula Construtiva",TEXT(B11,"00"),IF(H11="Etapa",CONCATENATE(TEXT(B11,"00"),".",TEXT(C11,"000")),IF(H11="Subetapa",CONCATENATE(TEXT(B11,"00"),".",TEXT(C11,"000"),".",TEXT(D11,"000")),IF(H11="Serviço",CONCATENATE(TEXT(B11,"00"),".",TEXT(C11,"000"),".",TEXT(D11,"000"),".",TEXT(E11,"000")),""))))) -> 01.001.001.001 | J11: Aparelhos telecomunicação | K11: vb | L11: 1 | M11: 47630.55 | N11: =IF(H11="Serviço",M11*L11,IF(H11="CÉLULA CONSTRUTIVA",SUMIFS($N$8:$N$38,$B$8:$B$38,B11,$H$8:$H$38,"Serviço"),IF(H11="ETAPA",SUMIFS($N$8:$N$38,$B$8:$B$38,B11,$C$8:$C$38,C11,$H$8:$H$38,"Serviço"),IF(H11="SUBETAPA",SUMIFS($N$8:$N$38,$B$8:$B$38,B11,$C$8:$C$38,C11,$D$8:$D$38,D11,$H$8:$H$38,"Serviço"),0)))) -> 47630.55 | O11: Interfonia e controle de acesso | P11: Finalizado
A12: =IF($H12="UNIDADE CONSTRUTIVA",OFFSET(A12,-1,0)+1,LARGE(A$3:A11,1)) -> 0 | B12: =IF(H12="UNIDADE CONSTRUTIVA",0,IF(H12="CÉLULA CONSTRUTIVA",OFFSET(B12,-1,0)+1,OFFSET(B12,-1,0))) -> 1 | C12: =IF(H12="CÉLULA CONSTRUTIVA",0,IF(H12="ETAPA",OFFSET(C12,-1,0)+1,OFFSET(C12,-1,0))) -> 1 | D12: =IF(H12="ETAPA",0,IF(H12="SUBETAPA",OFFSET(D12,-1,0)+1,OFFSET(D12,-1,0))) -> 2 | E12: =IF(H12="Subetapa",0,IF(H12="serviço",OFFSET(E12,-1,0)+1,OFFSET(E12,-1,0))) -> 0 | H12: SUBETAPA | I12: =IF(H12="Unidade Construtiva",TEXT(A12,"00"),IF(H12="Célula Construtiva",TEXT(B12,"00"),IF(H12="Etapa",CONCATENATE(TEXT(B12,"00"),".",TEXT(C12,"000")),IF(H12="Subetapa",CONCATENATE(TEXT(B12,"00"),".",TEXT(C12,"000"),".",TEXT(D12,"000")),IF(H12="Serviço",CONCATENATE(TEXT(B12,"00"),".",TEXT(C12,"000"),".",TEXT(D12,"000"),".",TEXT(E12,"000")),""))))) -> 01.001.002 | J12: LÂMPADAS E LUMINÁRIAS | N12: =IF(H12="Serviço",M12*L12,IF(H12="CÉLULA CONSTRUTIVA",SUMIFS($N$8:$N$38,$B$8:$B$38,B12,$H$8:$H$38,"Serviço"),IF(H12="ETAPA",SUMIFS($N$8:$N$38,$B$8:$B$38,B12,$C$8:$C$38,C12,$H$8:$H$38,"Serviço"),IF(H12="SUBETAPA",SUMIFS($N$8:$N$38,$B$8:$B$38,B12,$C$8:$C$38,C12,$D$8:$D$38,D12,$H$8:$H$38,"Serviço"),0)))) -> 48200
A13: =IF($H13="UNIDADE CONSTRUTIVA",OFFSET(A13,-1,0)+1,LARGE(A$3:A12,1)) -> 0 | B13: =IF(H13="UNIDADE CONSTRUTIVA",0,IF(H13="CÉLULA CONSTRUTIVA",OFFSET(B13,-1,0)+1,OFFSET(B13,-1,0))) -> 1 | C13: =IF(H13="CÉLULA CONSTRUTIVA",0,IF(H13="ETAPA",OFFSET(C13,-1,0)+1,OFFSET(C13,-1,0))) -> 1 | D13: =IF(H13="ETAPA",0,IF(H13="SUBETAPA",OFFSET(D13,-1,0)+1,OFFSET(D13,-1,0))) -> 2 | E13: =IF(H13="Subetapa",0,IF(H13="serviço",OFFSET(E13,-1,0)+1,OFFSET(E13,-1,0))) -> 1 | H13: SERVIÇO | I13: =IF(H13="Unidade Construtiva",TEXT(A13,"00"),IF(H13="Célula Construtiva",TEXT(B13,"00"),IF(H13="Etapa",CONCATENATE(TEXT(B13,"00"),".",TEXT(C13,"000")),IF(H13="Subetapa",CONCATENATE(TEXT(B13,"00"),".",TEXT(C13,"000"),".",TEXT(D13,"000")),IF(H13="Serviço",CONCATENATE(TEXT(B13,"00"),".",TEXT(C13,"000"),".",TEXT(D13,"000"),".",TEXT(E13,"000")),""))))) -> 01.001.002.001 | J13: Lâmpadas e Luminárias | K13: vb | L13: 1 | M13: ='Mobiliário'!C223 -> 48200 | N13: =IF(H13="Serviço",M13*L13,IF(H13="CÉLULA CONSTRUTIVA",SUMIFS($N$8:$N$38,$B$8:$B$38,B13,$H$8:$H$38,"Serviço"),IF(H13="ETAPA",SUMIFS($N$8:$N$38,$B$8:$B$38,B13,$C$8:$C$38,C13,$H$8:$H$38,"Serviço"),IF(H13="SUBETAPA",SUMIFS($N$8:$N$38,$B$8:$B$38,B13,$C$8:$C$38,C13,$D$8:$D$38,D13,$H$8:$H$38,"Serviço"),0)))) -> 48200 | P13: Finalizado
A14: =IF($H14="UNIDADE CONSTRUTIVA",OFFSET(A14,-1,0)+1,LARGE(A$3:A13,1)) -> 0 | B14: =IF(H14="UNIDADE CONSTRUTIVA",0,IF(H14="CÉLULA CONSTRUTIVA",OFFSET(B14,-1,0)+1,OFFSET(B14,-1,0))) -> 1 | C14: =IF(H14="CÉLULA CONSTRUTIVA",0,IF(H14="ETAPA",OFFSET(C14,-1,0)+1,OFFSET(C14,-1,0))) -> 2 | D14: =IF(H14="ETAPA",0,IF(H14="SUBETAPA",OFFSET(D14,-1,0)+1,OFFSET(D14,-1,0))) -> 0 | E14: =IF(H14="Subetapa",0,IF(H14="serviço",OFFSET(E14,-1,0)+1,OFFSET(E14,-1,0))) -> 1 | H14: ETAPA | I14: =IF(H14="Unidade Construtiva",TEXT(A14,"00"),IF(H14="Célula Construtiva",TEXT(B14,"00"),IF(H14="Etapa",CONCATENATE(TEXT(B14,"00"),".",TEXT(C14,"000")),IF(H14="Subetapa",CONCATENATE(TEXT(B14,"00"),".",TEXT(C14,"000"),".",TEXT(D14,"000")),IF(H14="Serviço",CONCATENATE(TEXT(B14,"00"),".",TEXT(C14,"000"),".",TEXT(D14,"000"),".",TEXT(E14,"000")),""))))) -> 01.002 | J14: MOBÍLIA E COMUNICAÇÃO VISUAL | N14: =IF(H14="Serviço",M14*L14,IF(H14="CÉLULA CONSTRUTIVA",SUMIFS($N$8:$N$38,$B$8:$B$38,B14,$H$8:$H$38,"Serviço"),IF(H14="ETAPA",SUMIFS($N$8:$N$38,$B$8:$B$38,B14,$C$8:$C$38,C14,$H$8:$H$38,"Serviço"),IF(H14="SUBETAPA",SUMIFS($N$8:$N$38,$B$8:$B$38,B14,$C$8:$C$38,C14,$D$8:$D$38,D14,$H$8:$H$38,"Serviço"),0)))) -> 10248544
A15: =IF($H15="UNIDADE CONSTRUTIVA",OFFSET(A15,-1,0)+1,LARGE(A$3:A14,1)) -> 0 | B15: =IF(H15="UNIDADE CONSTRUTIVA",0,IF(H15="CÉLULA CONSTRUTIVA",OFFSET(B15,-1,0)+1,OFFSET(B15,-1,0))) -> 1 | C15: =IF(H15="CÉLULA CONSTRUTIVA",0,IF(H15="ETAPA",OFFSET(C15,-1,0)+1,OFFSET(C15,-1,0))) -> 2 | D15: =IF(H15="ETAPA",0,IF(H15="SUBETAPA",OFFSET(D15,-1,0)+1,OFFSET(D15,-1,0))) -> 1 | E15: =IF(H15="Subetapa",0,IF(H15="serviço",OFFSET(E15,-1,0)+1,OFFSET(E15,-1,0))) -> 0 | H15: SUBETAPA | I15: =IF(H15="Unidade Construtiva",TEXT(A15,"00"),IF(H15="Célula Construtiva",TEXT(B15,"00"),IF(H15="Etapa",CONCATENATE(TEXT(B15,"00"),".",TEXT(C15,"000")),IF(H15="Subetapa",CONCATENATE(TEXT(B15,"00"),".",TEXT(C15,"000"),".",TEXT(D15,"000")),IF(H15="Serviço",CONCATENATE(TEXT(B15,"00"),".",TEXT(C15,"000"),".",TEXT(D15,"000"),".",TEXT(E15,"000")),""))))) -> 01.002.001 | J15: MARCENARIA | N15: =IF(H15="Serviço",M15*L15,IF(H15="CÉLULA CONSTRUTIVA",SUMIFS($N$8:$N$38,$B$8:$B$38,B15,$H$8:$H$38,"Serviço"),IF(H15="ETAPA",SUMIFS($N$8:$N$38,$B$8:$B$38,B15,$C$8:$C$38,C15,$H$8:$H$38,"Serviço"),IF(H15="SUBETAPA",SUMIFS($N$8:$N$38,$B$8:$B$38,B15,$C$8:$C$38,C15,$D$8:$D$38,D15,$H$8:$H$38,"Serviço"),0)))) -> 3871758.9
A16: =IF($H16="UNIDADE CONSTRUTIVA",OFFSET(A16,-1,0)+1,LARGE(A$3:A15,1)) -> 0 | B16: =IF(H16="UNIDADE CONSTRUTIVA",0,IF(H16="CÉLULA CONSTRUTIVA",OFFSET(B16,-1,0)+1,OFFSET(B16,-1,0))) -> 1 | C16: =IF(H16="CÉLULA CONSTRUTIVA",0,IF(H16="ETAPA",OFFSET(C16,-1,0)+1,OFFSET(C16,-1,0))) -> 2 | D16: =IF(H16="ETAPA",0,IF(H16="SUBETAPA",OFFSET(D16,-1,0)+1,OFFSET(D16,-1,0))) -> 1 | E16: =IF(H16="Subetapa",0,IF(H16="serviço",OFFSET(E16,-1,0)+1,OFFSET(E16,-1,0))) -> 1 | H16: SERVIÇO | I16: =IF(H16="Unidade Construtiva",TEXT(A16,"00"),IF(H16="Célula Construtiva",TEXT(B16,"00"),IF(H16="Etapa",CONCATENATE(TEXT(B16,"00"),".",TEXT(C16,"000")),IF(H16="Subetapa",CONCATENATE(TEXT(B16,"00"),".",TEXT(C16,"000"),".",TEXT(D16,"000")),IF(H16="Serviço",CONCATENATE(TEXT(B16,"00"),".",TEXT(C16,"000"),".",TEXT(D16,"000"),".",TEXT(E16,"000")),""))))) -> 01.002.001.001 | J16: Marcenaria | K16: vb | L16: 1 | M16: ='Mobiliário'!C224 -> 3871758.9 | N16: =IF(H16="Serviço",M16*L16,IF(H16="CÉLULA CONSTRUTIVA",SUMIFS($N$8:$N$38,$B$8:$B$38,B16,$H$8:$H$38,"Serviço"),IF(H16="ETAPA",SUMIFS($N$8:$N$38,$B$8:$B$38,B16,$C$8:$C$38,C16,$H$8:$H$38,"Serviço"),IF(H16="SUBETAPA",SUMIFS($N$8:$N$38,$B$8:$B$38,B16,$C$8:$C$38,C16,$D$8:$D$38,D16,$H$8:$H$38,"Serviço"),0)))) -> 3871758.9 | P16: Finalizado
A17: =IF($H17="UNIDADE CONSTRUTIVA",OFFSET(A17,-1,0)+1,LARGE(A$3:A16,1)) -> 0 | B17: =IF(H17="UNIDADE CONSTRUTIVA",0,IF(H17="CÉLULA CONSTRUTIVA",OFFSET(B17,-1,0)+1,OFFSET(B17,-1,0))) -> 1 | C17: =IF(H17="CÉLULA CONSTRUTIVA",0,IF(H17="ETAPA",OFFSET(C17,-1,0)+1,OFFSET(C17,-1,0))) -> 2 | D17: =IF(H17="ETAPA",0,IF(H17="SUBETAPA",OFFSET(D17,-1,0)+1,OFFSET(D17,-1,0))) -> 2 | E17: =IF(H17="Subetapa",0,IF(H17="serviço",OFFSET(E17,-1,0)+1,OFFSET(E17,-1,0))) -> 0 | H17: SUBETAPA | I17: =IF(H17="Unidade Construtiva",TEXT(A17,"00"),IF(H17="Célula Construtiva",TEXT(B17,"00"),IF(H17="Etapa",CONCATENATE(TEXT(B17,"00"),".",TEXT(C17,"000")),IF(H17="Subetapa",CONCATENATE(TEXT(B17,"00"),".",TEXT(C17,"000"),".",TEXT(D17,"000")),IF(H17="Serviço",CONCATENATE(TEXT(B17,"00"),".",TEXT(C17,"000"),".",TEXT(D17,"000"),".",TEXT(E17,"000")),""))))) -> 01.002.002 | J17: MARMORARIA | N17: =IF(H17="Serviço",M17*L17,IF(H17="CÉLULA CONSTRUTIVA",SUMIFS($N$8:$N$38,$B$8:$B$38,B17,$H$8:$H$38,"Serviço"),IF(H17="ETAPA",SUMIFS($N$8:$N$38,$B$8:$B$38,B17,$C$8:$C$38,C17,$H$8:$H$38,"Serviço"),IF(H17="SUBETAPA",SUMIFS($N$8:$N$38,$B$8:$B$38,B17,$C$8:$C$38,C17,$D$8:$D$38,D17,$H$8:$H$38,"Serviço"),0)))) -> 176689.5
A18: =IF($H18="UNIDADE CONSTRUTIVA",OFFSET(A18,-1,0)+1,LARGE(A$3:A17,1)) -> 0 | B18: =IF(H18="UNIDADE CONSTRUTIVA",0,IF(H18="CÉLULA CONSTRUTIVA",OFFSET(B18,-1,0)+1,OFFSET(B18,-1,0))) -> 1 | C18: =IF(H18="CÉLULA CONSTRUTIVA",0,IF(H18="ETAPA",OFFSET(C18,-1,0)+1,OFFSET(C18,-1,0))) -> 2 | D18: =IF(H18="ETAPA",0,IF(H18="SUBETAPA",OFFSET(D18,-1,0)+1,OFFSET(D18,-1,0))) -> 2 | E18: =IF(H18="Subetapa",0,IF(H18="serviço",OFFSET(E18,-1,0)+1,OFFSET(E18,-1,0))) -> 1 | H18: SERVIÇO | I18: =IF(H18="Unidade Construtiva",TEXT(A18,"00"),IF(H18="Célula Construtiva",TEXT(B18,"00"),IF(H18="Etapa",CONCATENATE(TEXT(B18,"00"),".",TEXT(C18,"000")),IF(H18="Subetapa",CONCATENATE(TEXT(B18,"00"),".",TEXT(C18,"000"),".",TEXT(D18,"000")),IF(H18="Serviço",CONCATENATE(TEXT(B18,"00"),".",TEXT(C18,"000"),".",TEXT(D18,"000"),".",TEXT(E18,"000")),""))))) -> 01.002.002.001 | J18: Bancada de Granito | K18: vb | L18: 1 | M18: ='Mobiliário'!C225 -> 176689.5 | N18: =IF(H18="Serviço",M18*L18,IF(H18="CÉLULA CONSTRUTIVA",SUMIFS($N$8:$N$38,$B$8:$B$38,B18,$H$8:$H$38,"Serviço"),IF(H18="ETAPA",SUMIFS($N$8:$N$38,$B$8:$B$38,B18,$C$8:$C$38,C18,$H$8:$H$38,"Serviço"),IF(H18="SUBETAPA",SUMIFS($N$8:$N$38,$B$8:$B$38,B18,$C$8:$C$38,C18,$D$8:$D$38,D18,$H$8:$H$38,"Serviço"),0)))) -> 176689.5 | P18: Finalizado
A19: =IF($H19="UNIDADE CONSTRUTIVA",OFFSET(A19,-1,0)+1,LARGE(A$3:A18,1)) -> 0 | B19: =IF(H19="UNIDADE CONSTRUTIVA",0,IF(H19="CÉLULA CONSTRUTIVA",OFFSET(B19,-1,0)+1,OFFSET(B19,-1,0))) -> 1 | C19: =IF(H19="CÉLULA CONSTRUTIVA",0,IF(H19="ETAPA",OFFSET(C19,-1,0)+1,OFFSET(C19,-1,0))) -> 2 | D19: =IF(H19="ETAPA",0,IF(H19="SUBETAPA",OFFSET(D19,-1,0)+1,OFFSET(D19,-1,0))) -> 3 | E19: =IF(H19="Subetapa",0,IF(H19="serviço",OFFSET(E19,-1,0)+1,OFFSET(E19,-1,0))) -> 0 | H19: SUBETAPA | I19: =IF(H19="Unidade Construtiva",TEXT(A19,"00"),IF(H19="Célula Construtiva",TEXT(B19,"00"),IF(H19="Etapa",CONCATENATE(TEXT(B19,"00"),".",TEXT(C19,"000")),IF(H19="Subetapa",CONCATENATE(TEXT(B19,"00"),".",TEXT(C19,"000"),".",TEXT(D19,"000")),IF(H19="Serviço",CONCATENATE(TEXT(B19,"00"),".",TEXT(C19,"000"),".",TEXT(D19,"000"),".",TEXT(E19,"000")),""))))) -> 01.002.003 | J19: BOX DE VIDRO | N19: =IF(H19="Serviço",M19*L19,IF(H19="CÉLULA CONSTRUTIVA",SUMIFS($N$8:$N$38,$B$8:$B$38,B19,$H$8:$H$38,"Serviço"),IF(H19="ETAPA",SUMIFS($N$8:$N$38,$B$8:$B$38,B19,$C$8:$C$38,C19,$H$8:$H$38,"Serviço"),IF(H19="SUBETAPA",SUMIFS($N$8:$N$38,$B$8:$B$38,B19,$C$8:$C$38,C19,$D$8:$D$38,D19,$H$8:$H$38,"Serviço"),0)))) -> 213858
A20: =IF($H20="UNIDADE CONSTRUTIVA",OFFSET(A20,-1,0)+1,LARGE(A$3:A19,1)) -> 0 | B20: =IF(H20="UNIDADE CONSTRUTIVA",0,IF(H20="CÉLULA CONSTRUTIVA",OFFSET(B20,-1,0)+1,OFFSET(B20,-1,0))) -> 1 | C20: =IF(H20="CÉLULA CONSTRUTIVA",0,IF(H20="ETAPA",OFFSET(C20,-1,0)+1,OFFSET(C20,-1,0))) -> 2 | D20: =IF(H20="ETAPA",0,IF(H20="SUBETAPA",OFFSET(D20,-1,0)+1,OFFSET(D20,-1,0))) -> 3 | E20: =IF(H20="Subetapa",0,IF(H20="serviço",OFFSET(E20,-1,0)+1,OFFSET(E20,-1,0))) -> 1 | H20: SERVIÇO | I20: =IF(H20="Unidade Construtiva",TEXT(A20,"00"),IF(H20="Célula Construtiva",TEXT(B20,"00"),IF(H20="Etapa",CONCATENATE(TEXT(B20,"00"),".",TEXT(C20,"000")),IF(H20="Subetapa",CONCATENATE(TEXT(B20,"00"),".",TEXT(C20,"000"),".",TEXT(D20,"000")),IF(H20="Serviço",CONCATENATE(TEXT(B20,"00"),".",TEXT(C20,"000"),".",TEXT(D20,"000"),".",TEXT(E20,"000")),""))))) -> 01.002.003.001 | J20: Box de Vidro | K20: vb | L20: 1 | M20: ='Mobiliário'!C226 -> 213858 | N20: =IF(H20="Serviço",M20*L20,IF(H20="CÉLULA CONSTRUTIVA",SUMIFS($N$8:$N$38,$B$8:$B$38,B20,$H$8:$H$38,"Serviço"),IF(H20="ETAPA",SUMIFS($N$8:$N$38,$B$8:$B$38,B20,$C$8:$C$38,C20,$H$8:$H$38,"Serviço"),IF(H20="SUBETAPA",SUMIFS($N$8:$N$38,$B$8:$B$38,B20,$C$8:$C$38,C20,$D$8:$D$38,D20,$H$8:$H$38,"Serviço"),0)))) -> 213858 | P20: Finalizado
A21: =IF($H21="UNIDADE CONSTRUTIVA",OFFSET(A21,-1,0)+1,LARGE(A$3:A20,1)) -> 0 | B21: =IF(H21="UNIDADE CONSTRUTIVA",0,IF(H21="CÉLULA CONSTRUTIVA",OFFSET(B21,-1,0)+1,OFFSET(B21,-1,0))) -> 1 | C21: =IF(H21="CÉLULA CONSTRUTIVA",0,IF(H21="ETAPA",OFFSET(C21,-1,0)+1,OFFSET(C21,-1,0))) -> 2 | D21: =IF(H21="ETAPA",0,IF(H21="SUBETAPA",OFFSET(D21,-1,0)+1,OFFSET(D21,-1,0))) -> 4 | E21: =IF(H21="Subetapa",0,IF(H21="serviço",OFFSET(E21,-1,0)+1,OFFSET(E21,-1,0))) -> 0 | H21: SUBETAPA | I21: =IF(H21="Unidade Construtiva",TEXT(A21,"00"),IF(H21="Célula Construtiva",TEXT(B21,"00"),IF(H21="Etapa",CONCATENATE(TEXT(B21,"00"),".",TEXT(C21,"000")),IF(H21="Subetapa",CONCATENATE(TEXT(B21,"00"),".",TEXT(C21,"000"),".",TEXT(D21,"000")),IF(H21="Serviço",CONCATENATE(TEXT(B21,"00"),".",TEXT(C21,"000"),".",TEXT(D21,"000"),".",TEXT(E21,"000")),""))))) -> 01.002.004 | J21: MÓVEIS SOLTOS | N21: =IF(H21="Serviço",M21*L21,IF(H21="CÉLULA CONSTRUTIVA",SUMIFS($N$8:$N$38,$B$8:$B$38,B21,$H$8:$H$38,"Serviço"),IF(H21="ETAPA",SUMIFS($N$8:$N$38,$B$8:$B$38,B21,$C$8:$C$38,C21,$H$8:$H$38,"Serviço"),IF(H21="SUBETAPA",SUMIFS($N$8:$N$38,$B$8:$B$38,B21,$C$8:$C$38,C21,$D$8:$D$38,D21,$H$8:$H$38,"Serviço"),0)))) -> 787360.56
A22: =IF($H22="UNIDADE CONSTRUTIVA",OFFSET(A22,-1,0)+1,LARGE(A$3:A21,1)) -> 0 | B22: =IF(H22="UNIDADE CONSTRUTIVA",0,IF(H22="CÉLULA CONSTRUTIVA",OFFSET(B22,-1,0)+1,OFFSET(B22,-1,0))) -> 1 | C22: =IF(H22="CÉLULA CONSTRUTIVA",0,IF(H22="ETAPA",OFFSET(C22,-1,0)+1,OFFSET(C22,-1,0))) -> 2 | D22: =IF(H22="ETAPA",0,IF(H22="SUBETAPA",OFFSET(D22,-1,0)+1,OFFSET(D22,-1,0))) -> 4 | E22: =IF(H22="Subetapa",0,IF(H22="serviço",OFFSET(E22,-1,0)+1,OFFSET(E22,-1,0))) -> 1 | H22: SERVIÇO | I22: =IF(H22="Unidade Construtiva",TEXT(A22,"00"),IF(H22="Célula Construtiva",TEXT(B22,"00"),IF(H22="Etapa",CONCATENATE(TEXT(B22,"00"),".",TEXT(C22,"000")),IF(H22="Subetapa",CONCATENATE(TEXT(B22,"00"),".",TEXT(C22,"000"),".",TEXT(D22,"000")),IF(H22="Serviço",CONCATENATE(TEXT(B22,"00"),".",TEXT(C22,"000"),".",TEXT(D22,"000"),".",TEXT(E22,"000")),""))))) -> 01.002.004.001 | J22: Móveis Soltos | K22: vb | L22: 1 | M22: ='Mobiliário'!C227 -> 787360.56 | N22: =IF(H22="Serviço",M22*L22,IF(H22="CÉLULA CONSTRUTIVA",SUMIFS($N$8:$N$38,$B$8:$B$38,B22,$H$8:$H$38,"Serviço"),IF(H22="ETAPA",SUMIFS($N$8:$N$38,$B$8:$B$38,B22,$C$8:$C$38,C22,$H$8:$H$38,"Serviço"),IF(H22="SUBETAPA",SUMIFS($N$8:$N$38,$B$8:$B$38,B22,$C$8:$C$38,C22,$D$8:$D$38,D22,$H$8:$H$38,"Serviço"),0)))) -> 787360.56 | P22: Finalizado
A23: =IF($H23="UNIDADE CONSTRUTIVA",OFFSET(A23,-1,0)+1,LARGE(A$3:A22,1)) -> 0 | B23: =IF(H23="UNIDADE CONSTRUTIVA",0,IF(H23="CÉLULA CONSTRUTIVA",OFFSET(B23,-1,0)+1,OFFSET(B23,-1,0))) -> 1 | C23: =IF(H23="CÉLULA CONSTRUTIVA",0,IF(H23="ETAPA",OFFSET(C23,-1,0)+1,OFFSET(C23,-1,0))) -> 2 | D23: =IF(H23="ETAPA",0,IF(H23="SUBETAPA",OFFSET(D23,-1,0)+1,OFFSET(D23,-1,0))) -> 5 | E23: =IF(H23="Subetapa",0,IF(H23="serviço",OFFSET(E23,-1,0)+1,OFFSET(E23,-1,0))) -> 0 | H23: SUBETAPA | I23: =IF(H23="Unidade Construtiva",TEXT(A23,"00"),IF(H23="Célula Construtiva",TEXT(B23,"00"),IF(H23="Etapa",CONCATENATE(TEXT(B23,"00"),".",TEXT(C23,"000")),IF(H23="Subetapa",CONCATENATE(TEXT(B23,"00"),".",TEXT(C23,"000"),".",TEXT(D23,"000")),IF(H23="Serviço",CONCATENATE(TEXT(B23,"00"),".",TEXT(C23,"000"),".",TEXT(D23,"000"),".",TEXT(E23,"000")),""))))) -> 01.002.005 | J23: COMPLEMENTOS | N23: =IF(H23="Serviço",M23*L23,IF(H23="CÉLULA CONSTRUTIVA",SUMIFS($N$8:$N$38,$B$8:$B$38,B23,$H$8:$H$38,"Serviço"),IF(H23="ETAPA",SUMIFS($N$8:$N$38,$B$8:$B$38,B23,$C$8:$C$38,C23,$H$8:$H$38,"Serviço"),IF(H23="SUBETAPA",SUMIFS($N$8:$N$38,$B$8:$B$38,B23,$C$8:$C$38,C23,$D$8:$D$38,D23,$H$8:$H$38,"Serviço"),0)))) -> 2794304.5
A24: =IF($H24="UNIDADE CONSTRUTIVA",OFFSET(A24,-1,0)+1,LARGE(A$3:A23,1)) -> 0 | B24: =IF(H24="UNIDADE CONSTRUTIVA",0,IF(H24="CÉLULA CONSTRUTIVA",OFFSET(B24,-1,0)+1,OFFSET(B24,-1,0))) -> 1 | C24: =IF(H24="CÉLULA CONSTRUTIVA",0,IF(H24="ETAPA",OFFSET(C24,-1,0)+1,OFFSET(C24,-1,0))) -> 2 | D24: =IF(H24="ETAPA",0,IF(H24="SUBETAPA",OFFSET(D24,-1,0)+1,OFFSET(D24,-1,0))) -> 5 | E24: =IF(H24="Subetapa",0,IF(H24="serviço",OFFSET(E24,-1,0)+1,OFFSET(E24,-1,0))) -> 1 | H24: SERVIÇO | I24: =IF(H24="Unidade Construtiva",TEXT(A24,"00"),IF(H24="Célula Construtiva",TEXT(B24,"00"),IF(H24="Etapa",CONCATENATE(TEXT(B24,"00"),".",TEXT(C24,"000")),IF(H24="Subetapa",CONCATENATE(TEXT(B24,"00"),".",TEXT(C24,"000"),".",TEXT(D24,"000")),IF(H24="Serviço",CONCATENATE(TEXT(B24,"00"),".",TEXT(C24,"000"),".",TEXT(D24,"000"),".",TEXT(E24,"000")),""))))) -> 01.002.005.001 | J24: Complementos | K24: vb | L24: 1 | M24: ='Mobiliário'!C228 -> 2794304.5 | N24: =IF(H24="Serviço",M24*L24,IF(H24="CÉLULA CONSTRUTIVA",SUMIFS($N$8:$N$38,$B$8:$B$38,B24,$H$8:$H$38,"Serviço"),IF(H24="ETAPA",SUMIFS($N$8:$N$38,$B$8:$B$38,B24,$C$8:$C$38,C24,$H$8:$H$38,"Serviço"),IF(H24="SUBETAPA",SUMIFS($N$8:$N$38,$B$8:$B$38,B24,$C$8:$C$38,C24,$D$8:$D$38,D24,$H$8:$H$38,"Serviço"),0)))) -> 2794304.5 | P24: Finalizado
A25: =IF($H25="UNIDADE CONSTRUTIVA",OFFSET(A25,-1,0)+1,LARGE(A$3:A24,1)) -> 0 | B25: =IF(H25="UNIDADE CONSTRUTIVA",0,IF(H25="CÉLULA CONSTRUTIVA",OFFSET(B25,-1,0)+1,OFFSET(B25,-1,0))) -> 1 | C25: =IF(H25="CÉLULA CONSTRUTIVA",0,IF(H25="ETAPA",OFFSET(C25,-1,0)+1,OFFSET(C25,-1,0))) -> 2 | D25: =IF(H25="ETAPA",0,IF(H25="SUBETAPA",OFFSET(D25,-1,0)+1,OFFSET(D25,-1,0))) -> 6 | E25: =IF(H25="Subetapa",0,IF(H25="serviço",OFFSET(E25,-1,0)+1,OFFSET(E25,-1,0))) -> 0 | H25: SUBETAPA | I25: =IF(H25="Unidade Construtiva",TEXT(A25,"00"),IF(H25="Célula Construtiva",TEXT(B25,"00"),IF(H25="Etapa",CONCATENATE(TEXT(B25,"00"),".",TEXT(C25,"000")),IF(H25="Subetapa",CONCATENATE(TEXT(B25,"00"),".",TEXT(C25,"000"),".",TEXT(D25,"000")),IF(H25="Serviço",CONCATENATE(TEXT(B25,"00"),".",TEXT(C25,"000"),".",TEXT(D25,"000"),".",TEXT(E25,"000")),""))))) -> 01.002.006 | J25: ELETROS E EQUIPAMENTOS | N25: =IF(H25="Serviço",M25*L25,IF(H25="CÉLULA CONSTRUTIVA",SUMIFS($N$8:$N$38,$B$8:$B$38,B25,$H$8:$H$38,"Serviço"),IF(H25="ETAPA",SUMIFS($N$8:$N$38,$B$8:$B$38,B25,$C$8:$C$38,C25,$H$8:$H$38,"Serviço"),IF(H25="SUBETAPA",SUMIFS($N$8:$N$38,$B$8:$B$38,B25,$C$8:$C$38,C25,$D$8:$D$38,D25,$H$8:$H$38,"Serviço"),0)))) -> 1330098.2
A26: =IF($H26="UNIDADE CONSTRUTIVA",OFFSET(A26,-1,0)+1,LARGE(A$3:A25,1)) -> 0 | B26: =IF(H26="UNIDADE CONSTRUTIVA",0,IF(H26="CÉLULA CONSTRUTIVA",OFFSET(B26,-1,0)+1,OFFSET(B26,-1,0))) -> 1 | C26: =IF(H26="CÉLULA CONSTRUTIVA",0,IF(H26="ETAPA",OFFSET(C26,-1,0)+1,OFFSET(C26,-1,0))) -> 2 | D26: =IF(H26="ETAPA",0,IF(H26="SUBETAPA",OFFSET(D26,-1,0)+1,OFFSET(D26,-1,0))) -> 6 | E26: =IF(H26="Subetapa",0,IF(H26="serviço",OFFSET(E26,-1,0)+1,OFFSET(E26,-1,0))) -> 1 | H26: SERVIÇO | I26: =IF(H26="Unidade Construtiva",TEXT(A26,"00"),IF(H26="Célula Construtiva",TEXT(B26,"00"),IF(H26="Etapa",CONCATENATE(TEXT(B26,"00"),".",TEXT(C26,"000")),IF(H26="Subetapa",CONCATENATE(TEXT(B26,"00"),".",TEXT(C26,"000"),".",TEXT(D26,"000")),IF(H26="Serviço",CONCATENATE(TEXT(B26,"00"),".",TEXT(C26,"000"),".",TEXT(D26,"000"),".",TEXT(E26,"000")),""))))) -> 01.002.006.001 | J26: Eletrodomésticos e Equipamentos | K26: vb | L26: 1 | M26: ='Mobiliário'!C229 -> 1330098.2 | N26: =IF(H26="Serviço",M26*L26,IF(H26="CÉLULA CONSTRUTIVA",SUMIFS($N$8:$N$38,$B$8:$B$38,B26,$H$8:$H$38,"Serviço"),IF(H26="ETAPA",SUMIFS($N$8:$N$38,$B$8:$B$38,B26,$C$8:$C$38,C26,$H$8:$H$38,"Serviço"),IF(H26="SUBETAPA",SUMIFS($N$8:$N$38,$B$8:$B$38,B26,$C$8:$C$38,C26,$D$8:$D$38,D26,$H$8:$H$38,"Serviço"),0)))) -> 1330098.2 | P26: Finalizado
A27: =IF($H27="UNIDADE CONSTRUTIVA",OFFSET(A27,-1,0)+1,LARGE(A$3:A26,1)) -> 0 | B27: =IF(H27="UNIDADE CONSTRUTIVA",0,IF(H27="CÉLULA CONSTRUTIVA",OFFSET(B27,-1,0)+1,OFFSET(B27,-1,0))) -> 1 | C27: =IF(H27="CÉLULA CONSTRUTIVA",0,IF(H27="ETAPA",OFFSET(C27,-1,0)+1,OFFSET(C27,-1,0))) -> 2 | D27: =IF(H27="ETAPA",0,IF(H27="SUBETAPA",OFFSET(D27,-1,0)+1,OFFSET(D27,-1,0))) -> 7 | E27: =IF(H27="Subetapa",0,IF(H27="serviço",OFFSET(E27,-1,0)+1,OFFSET(E27,-1,0))) -> 0 | H27: SUBETAPA | I27: =IF(H27="Unidade Construtiva",TEXT(A27,"00"),IF(H27="Célula Construtiva",TEXT(B27,"00"),IF(H27="Etapa",CONCATENATE(TEXT(B27,"00"),".",TEXT(C27,"000")),IF(H27="Subetapa",CONCATENATE(TEXT(B27,"00"),".",TEXT(C27,"000"),".",TEXT(D27,"000")),IF(H27="Serviço",CONCATENATE(TEXT(B27,"00"),".",TEXT(C27,"000"),".",TEXT(D27,"000"),".",TEXT(E27,"000")),""))))) -> 01.002.007 | J27: ENXOVAL | N27: =IF(H27="Serviço",M27*L27,IF(H27="CÉLULA CONSTRUTIVA",SUMIFS($N$8:$N$38,$B$8:$B$38,B27,$H$8:$H$38,"Serviço"),IF(H27="ETAPA",SUMIFS($N$8:$N$38,$B$8:$B$38,B27,$C$8:$C$38,C27,$H$8:$H$38,"Serviço"),IF(H27="SUBETAPA",SUMIFS($N$8:$N$38,$B$8:$B$38,B27,$C$8:$C$38,C27,$D$8:$D$38,D27,$H$8:$H$38,"Serviço"),0)))) -> 320073.6
A28: =IF($H28="UNIDADE CONSTRUTIVA",OFFSET(A28,-1,0)+1,LARGE(A$3:A27,1)) -> 0 | B28: =IF(H28="UNIDADE CONSTRUTIVA",0,IF(H28="CÉLULA CONSTRUTIVA",OFFSET(B28,-1,0)+1,OFFSET(B28,-1,0))) -> 1 | C28: =IF(H28="CÉLULA CONSTRUTIVA",0,IF(H28="ETAPA",OFFSET(C28,-1,0)+1,OFFSET(C28,-1,0))) -> 2 | D28: =IF(H28="ETAPA",0,IF(H28="SUBETAPA",OFFSET(D28,-1,0)+1,OFFSET(D28,-1,0))) -> 7 | E28: =IF(H28="Subetapa",0,IF(H28="serviço",OFFSET(E28,-1,0)+1,OFFSET(E28,-1,0))) -> 1 | H28: SERVIÇO | I28: =IF(H28="Unidade Construtiva",TEXT(A28,"00"),IF(H28="Célula Construtiva",TEXT(B28,"00"),IF(H28="Etapa",CONCATENATE(TEXT(B28,"00"),".",TEXT(C28,"000")),IF(H28="Subetapa",CONCATENATE(TEXT(B28,"00"),".",TEXT(C28,"000"),".",TEXT(D28,"000")),IF(H28="Serviço",CONCATENATE(TEXT(B28,"00"),".",TEXT(C28,"000"),".",TEXT(D28,"000"),".",TEXT(E28,"000")),""))))) -> 01.002.007.001 | J28: Enxoval | K28: vb | L28: 1 | M28: ='Mobiliário'!C230 -> 320073.6 | N28: =IF(H28="Serviço",M28*L28,IF(H28="CÉLULA CONSTRUTIVA",SUMIFS($N$8:$N$38,$B$8:$B$38,B28,$H$8:$H$38,"Serviço"),IF(H28="ETAPA",SUMIFS($N$8:$N$38,$B$8:$B$38,B28,$C$8:$C$38,C28,$H$8:$H$38,"Serviço"),IF(H28="SUBETAPA",SUMIFS($N$8:$N$38,$B$8:$B$38,B28,$C$8:$C$38,C28,$D$8:$D$38,D28,$H$8:$H$38,"Serviço"),0)))) -> 320073.6 | P28: Finalizado
A29: =IF($H29="UNIDADE CONSTRUTIVA",OFFSET(A29,-1,0)+1,LARGE(A$3:A28,1)) -> 0 | B29: =IF(H29="UNIDADE CONSTRUTIVA",0,IF(H29="CÉLULA CONSTRUTIVA",OFFSET(B29,-1,0)+1,OFFSET(B29,-1,0))) -> 1 | C29: =IF(H29="CÉLULA CONSTRUTIVA",0,IF(H29="ETAPA",OFFSET(C29,-1,0)+1,OFFSET(C29,-1,0))) -> 2 | D29: =IF(H29="ETAPA",0,IF(H29="SUBETAPA",OFFSET(D29,-1,0)+1,OFFSET(D29,-1,0))) -> 8 | E29: =IF(H29="Subetapa",0,IF(H29="serviço",OFFSET(E29,-1,0)+1,OFFSET(E29,-1,0))) -> 0 | H29: SUBETAPA | I29: =IF(H29="Unidade Construtiva",TEXT(A29,"00"),IF(H29="Célula Construtiva",TEXT(B29,"00"),IF(H29="Etapa",CONCATENATE(TEXT(B29,"00"),".",TEXT(C29,"000")),IF(H29="Subetapa",CONCATENATE(TEXT(B29,"00"),".",TEXT(C29,"000"),".",TEXT(D29,"000")),IF(H29="Serviço",CONCATENATE(TEXT(B29,"00"),".",TEXT(C29,"000"),".",TEXT(D29,"000"),".",TEXT(E29,"000")),""))))) -> 01.002.008 | J29: MÁQUINAS DE AR CONDICIONADO | N29: =IF(H29="Serviço",M29*L29,IF(H29="CÉLULA CONSTRUTIVA",SUMIFS($N$8:$N$38,$B$8:$B$38,B29,$H$8:$H$38,"Serviço"),IF(H29="ETAPA",SUMIFS($N$8:$N$38,$B$8:$B$38,B29,$C$8:$C$38,C29,$H$8:$H$38,"Serviço"),IF(H29="SUBETAPA",SUMIFS($N$8:$N$38,$B$8:$B$38,B29,$C$8:$C$38,C29,$D$8:$D$38,D29,$H$8:$H$38,"Serviço"),0)))) -> 667800
A30: =IF($H30="UNIDADE CONSTRUTIVA",OFFSET(A30,-1,0)+1,LARGE(A$3:A28,1)) -> 0 | B30: =IF(H30="UNIDADE CONSTRUTIVA",0,IF(H30="CÉLULA CONSTRUTIVA",OFFSET(B30,-1,0)+1,OFFSET(B30,-1,0))) -> 1 | C30: =IF(H30="CÉLULA CONSTRUTIVA",0,IF(H30="ETAPA",OFFSET(C30,-1,0)+1,OFFSET(C30,-1,0))) -> 2 | D30: =IF(H30="ETAPA",0,IF(H30="SUBETAPA",OFFSET(D30,-1,0)+1,OFFSET(D30,-1,0))) -> 8 | E30: =IF(H30="Subetapa",0,IF(H30="serviço",OFFSET(E30,-1,0)+1,OFFSET(E30,-1,0))) -> 1 | H30: SERVIÇO | I30: =IF(H30="Unidade Construtiva",TEXT(A30,"00"),IF(H30="Célula Construtiva",TEXT(B30,"00"),IF(H30="Etapa",CONCATENATE(TEXT(B30,"00"),".",TEXT(C30,"000")),IF(H30="Subetapa",CONCATENATE(TEXT(B30,"00"),".",TEXT(C30,"000"),".",TEXT(D30,"000")),IF(H30="Serviço",CONCATENATE(TEXT(B30,"00"),".",TEXT(C30,"000"),".",TEXT(D30,"000"),".",TEXT(E30,"000")),""))))) -> 01.002.008.001 | J30: Máquina de Ar Condicionado | 12.000 BTUs | K30: un | L30: =Ger_Executivo!F173-'Custos Enxoval'!L31 -> 249 | M30: 2650 | N30: =IF(H30="Serviço",M30*L30,IF(H30="CÉLULA CONSTRUTIVA",SUMIFS($N$8:$N$38,$B$8:$B$38,B30,$H$8:$H$38,"Serviço"),IF(H30="ETAPA",SUMIFS($N$8:$N$38,$B$8:$B$38,B30,$C$8:$C$38,C30,$H$8:$H$38,"Serviço"),IF(H30="SUBETAPA",SUMIFS($N$8:$N$38,$B$8:$B$38,B30,$C$8:$C$38,C30,$D$8:$D$38,D30,$H$8:$H$38,"Serviço"),0)))) -> 659850 | P30: Finalizado
A31: =IF($H31="UNIDADE CONSTRUTIVA",OFFSET(A31,-1,0)+1,LARGE(A$3:A29,1)) -> 0 | B31: =IF(H31="UNIDADE CONSTRUTIVA",0,IF(H31="CÉLULA CONSTRUTIVA",OFFSET(B31,-1,0)+1,OFFSET(B31,-1,0))) -> 1 | C31: =IF(H31="CÉLULA CONSTRUTIVA",0,IF(H31="ETAPA",OFFSET(C31,-1,0)+1,OFFSET(C31,-1,0))) -> 2 | D31: =IF(H31="ETAPA",0,IF(H31="SUBETAPA",OFFSET(D31,-1,0)+1,OFFSET(D31,-1,0))) -> 8 | E31: =IF(H31="Subetapa",0,IF(H31="serviço",OFFSET(E31,-1,0)+1,OFFSET(E31,-1,0))) -> 2 | H31: SERVIÇO | I31: =IF(H31="Unidade Construtiva",TEXT(A31,"00"),IF(H31="Célula Construtiva",TEXT(B31,"00"),IF(H31="Etapa",CONCATENATE(TEXT(B31,"00"),".",TEXT(C31,"000")),IF(H31="Subetapa",CONCATENATE(TEXT(B31,"00"),".",TEXT(C31,"000"),".",TEXT(D31,"000")),IF(H31="Serviço",CONCATENATE(TEXT(B31,"00"),".",TEXT(C31,"000"),".",TEXT(D31,"000"),".",TEXT(E31,"000")),""))))) -> 01.002.008.002 | J31: Máquina de Ar Condicionado | 32.000 BTUs | K31: un | L31: 3 | M31: 2650 | N31: =IF(H31="Serviço",M31*L31,IF(H31="CÉLULA CONSTRUTIVA",SUMIFS($N$8:$N$38,$B$8:$B$38,B31,$H$8:$H$38,"Serviço"),IF(H31="ETAPA",SUMIFS($N$8:$N$38,$B$8:$B$38,B31,$C$8:$C$38,C31,$H$8:$H$38,"Serviço"),IF(H31="SUBETAPA",SUMIFS($N$8:$N$38,$B$8:$B$38,B31,$C$8:$C$38,C31,$D$8:$D$38,D31,$H$8:$H$38,"Serviço"),0)))) -> 7950 | P31: Finalizado
A32: =IF($H32="UNIDADE CONSTRUTIVA",OFFSET(A32,-1,0)+1,LARGE(A$3:A31,1)) -> 0 | B32: =IF(H32="UNIDADE CONSTRUTIVA",0,IF(H32="CÉLULA CONSTRUTIVA",OFFSET(B32,-1,0)+1,OFFSET(B32,-1,0))) -> 1 | C32: =IF(H32="CÉLULA CONSTRUTIVA",0,IF(H32="ETAPA",OFFSET(C32,-1,0)+1,OFFSET(C32,-1,0))) -> 2 | D32: =IF(H32="ETAPA",0,IF(H32="SUBETAPA",OFFSET(D32,-1,0)+1,OFFSET(D32,-1,0))) -> 9 | E32: =IF(H32="Subetapa",0,IF(H32="serviço",OFFSET(E32,-1,0)+1,OFFSET(E32,-1,0))) -> 0 | H32: SUBETAPA | I32: =IF(H32="Unidade Construtiva",TEXT(A32,"00"),IF(H32="Célula Construtiva",TEXT(B32,"00"),IF(H32="Etapa",CONCATENATE(TEXT(B32,"00"),".",TEXT(C32,"000")),IF(H32="Subetapa",CONCATENATE(TEXT(B32,"00"),".",TEXT(C32,"000"),".",TEXT(D32,"000")),IF(H32="Serviço",CONCATENATE(TEXT(B32,"00"),".",TEXT(C32,"000"),".",TEXT(D32,"000"),".",TEXT(E32,"000")),""))))) -> 01.002.009 | J32: COMUNICAÇÃO VISUAL | N32: =IF(H32="Serviço",M32*L32,IF(H32="CÉLULA CONSTRUTIVA",SUMIFS($N$8:$N$38,$B$8:$B$38,B32,$H$8:$H$38,"Serviço"),IF(H32="ETAPA",SUMIFS($N$8:$N$38,$B$8:$B$38,B32,$C$8:$C$38,C32,$H$8:$H$38,"Serviço"),IF(H32="SUBETAPA",SUMIFS($N$8:$N$38,$B$8:$B$38,B32,$C$8:$C$38,C32,$D$8:$D$38,D32,$H$8:$H$38,"Serviço"),0)))) -> 86601
A33: =IF($H33="UNIDADE CONSTRUTIVA",OFFSET(A33,-1,0)+1,LARGE(A$3:A32,1)) -> 0 | B33: =IF(H33="UNIDADE CONSTRUTIVA",0,IF(H33="CÉLULA CONSTRUTIVA",OFFSET(B33,-1,0)+1,OFFSET(B33,-1,0))) -> 1 | C33: =IF(H33="CÉLULA CONSTRUTIVA",0,IF(H33="ETAPA",OFFSET(C33,-1,0)+1,OFFSET(C33,-1,0))) -> 2 | D33: =IF(H33="ETAPA",0,IF(H33="SUBETAPA",OFFSET(D33,-1,0)+1,OFFSET(D33,-1,0))) -> 9 | E33: =IF(H33="Subetapa",0,IF(H33="serviço",OFFSET(E33,-1,0)+1,OFFSET(E33,-1,0))) -> 1 | H33: SERVIÇO | I33: =IF(H33="Unidade Construtiva",TEXT(A33,"00"),IF(H33="Célula Construtiva",TEXT(B33,"00"),IF(H33="Etapa",CONCATENATE(TEXT(B33,"00"),".",TEXT(C33,"000")),IF(H33="Subetapa",CONCATENATE(TEXT(B33,"00"),".",TEXT(C33,"000"),".",TEXT(D33,"000")),IF(H33="Serviço",CONCATENATE(TEXT(B33,"00"),".",TEXT(C33,"000"),".",TEXT(D33,"000"),".",TEXT(E33,"000")),""))))) -> 01.002.009.001 | J33: Comunicação Visual Externa | K33: vb | L33: 1 | M33: =10*'Obra '!E9 -> 86601 | N33: =IF(H33="Serviço",M33*L33,IF(H33="CÉLULA CONSTRUTIVA",SUMIFS($N$8:$N$38,$B$8:$B$38,B33,$H$8:$H$38,"Serviço"),IF(H33="ETAPA",SUMIFS($N$8:$N$38,$B$8:$B$38,B33,$C$8:$C$38,C33,$H$8:$H$38,"Serviço"),IF(H33="SUBETAPA",SUMIFS($N$8:$N$38,$B$8:$B$38,B33,$C$8:$C$38,C33,$D$8:$D$38,D33,$H$8:$H$38,"Serviço"),0)))) -> 86601 | P33: Finalizado
A34: =IF($H34="UNIDADE CONSTRUTIVA",OFFSET(A34,-1,0)+1,LARGE(A$3:A33,1)) -> 0 | B34: =IF(H34="UNIDADE CONSTRUTIVA",0,IF(H34="CÉLULA CONSTRUTIVA",OFFSET(B34,-1,0)+1,OFFSET(B34,-1,0))) -> 1 | C34: =IF(H34="CÉLULA CONSTRUTIVA",0,IF(H34="ETAPA",OFFSET(C34,-1,0)+1,OFFSET(C34,-1,0))) -> 2 | D34: =IF(H34="ETAPA",0,IF(H34="SUBETAPA",OFFSET(D34,-1,0)+1,OFFSET(D34,-1,0))) -> 9 | E34: =IF(H34="Subetapa",0,IF(H34="serviço",OFFSET(E34,-1,0)+1,OFFSET(E34,-1,0))) -> 1 | M34: =SUMIFS($N$7:$N$33,$H$7:$H$33,N34) -> 10344375 | N34: CÉLULA CONSTRUTIVA
A35: =IF($H35="UNIDADE CONSTRUTIVA",OFFSET(A35,-1,0)+1,LARGE(A$3:A34,1)) -> 0 | B35: =IF(H35="UNIDADE CONSTRUTIVA",0,IF(H35="CÉLULA CONSTRUTIVA",OFFSET(B35,-1,0)+1,OFFSET(B35,-1,0))) -> 1 | C35: =IF(H35="CÉLULA CONSTRUTIVA",0,IF(H35="ETAPA",OFFSET(C35,-1,0)+1,OFFSET(C35,-1,0))) -> 2 | D35: =IF(H35="ETAPA",0,IF(H35="SUBETAPA",OFFSET(D35,-1,0)+1,OFFSET(D35,-1,0))) -> 9 | E35: =IF(H35="Subetapa",0,IF(H35="serviço",OFFSET(E35,-1,0)+1,OFFSET(E35,-1,0))) -> 1 | M35: =SUMIFS($N$7:$N$33,$H$7:$H$33,N35) -> 10344375 | N35: ETAPA
A36: =IF($H36="UNIDADE CONSTRUTIVA",OFFSET(A36,-1,0)+1,LARGE(A$3:A35,1)) -> 0 | B36: =IF(H36="UNIDADE CONSTRUTIVA",0,IF(H36="CÉLULA CONSTRUTIVA",OFFSET(B36,-1,0)+1,OFFSET(B36,-1,0))) -> 1 | C36: =IF(H36="CÉLULA CONSTRUTIVA",0,IF(H36="ETAPA",OFFSET(C36,-1,0)+1,OFFSET(C36,-1,0))) -> 2 | D36: =IF(H36="ETAPA",0,IF(H36="SUBETAPA",OFFSET(D36,-1,0)+1,OFFSET(D36,-1,0))) -> 9 | E36: =IF(H36="Subetapa",0,IF(H36="serviço",OFFSET(E36,-1,0)+1,OFFSET(E36,-1,0))) -> 1 | M36: =SUMIFS($N$7:$N$33,$H$7:$H$33,N36) -> 10344375 | N36: SUBETAPA
A37: =IF($H37="UNIDADE CONSTRUTIVA",OFFSET(A37,-1,0)+1,LARGE(A$3:A36,1)) -> 0 | B37: =IF(H37="UNIDADE CONSTRUTIVA",0,IF(H37="CÉLULA CONSTRUTIVA",OFFSET(B37,-1,0)+1,OFFSET(B37,-1,0))) -> 1 | C37: =IF(H37="CÉLULA CONSTRUTIVA",0,IF(H37="ETAPA",OFFSET(C37,-1,0)+1,OFFSET(C37,-1,0))) -> 2 | D37: =IF(H37="ETAPA",0,IF(H37="SUBETAPA",OFFSET(D37,-1,0)+1,OFFSET(D37,-1,0))) -> 9 | E37: =IF(H37="Subetapa",0,IF(H37="serviço",OFFSET(E37,-1,0)+1,OFFSET(E37,-1,0))) -> 1 | M37: =SUMIFS($N$7:$N$33,$H$7:$H$33,N37) -> 10344375 | N37: SERVIÇO
A38: =IF($H38="UNIDADE CONSTRUTIVA",OFFSET(A38,-1,0)+1,LARGE(A$3:A37,1)) -> 0 | B38: =IF(H38="UNIDADE CONSTRUTIVA",0,IF(H38="CÉLULA CONSTRUTIVA",OFFSET(B38,-1,0)+1,OFFSET(B38,-1,0))) -> 1 | C38: =IF(H38="CÉLULA CONSTRUTIVA",0,IF(H38="ETAPA",OFFSET(C38,-1,0)+1,OFFSET(C38,-1,0))) -> 2 | D38: =IF(H38="ETAPA",0,IF(H38="SUBETAPA",OFFSET(D38,-1,0)+1,OFFSET(D38,-1,0))) -> 9 | E38: =IF(H38="Subetapa",0,IF(H38="serviço",OFFSET(E38,-1,0)+1,OFFSET(E38,-1,0))) -> 1
A39: =IF($H39="UNIDADE CONSTRUTIVA",OFFSET(A39,-1,0)+1,LARGE(A$3:A36,1)) -> 0 | B39: =IF(H39="UNIDADE CONSTRUTIVA",0,IF(H39="CÉLULA CONSTRUTIVA",OFFSET(B39,-1,0)+1,OFFSET(B39,-1,0))) -> 1 | C39: =IF(H39="CÉLULA CONSTRUTIVA",0,IF(H39="ETAPA",OFFSET(C39,-1,0)+1,OFFSET(C39,-1,0))) -> 2 | D39: =IF(H39="ETAPA",0,IF(H39="SUBETAPA",OFFSET(D39,-1,0)+1,OFFSET(D39,-1,0))) -> 9 | E39: =IF(H39="Subetapa",0,IF(H39="serviço",OFFSET(E39,-1,0)+1,OFFSET(E39,-1,0))) -> 1
A40: =IF($H40="UNIDADE CONSTRUTIVA",OFFSET(A40,-1,0)+1,LARGE(A$3:A37,1)) -> 0 | B40: =IF(H40="UNIDADE CONSTRUTIVA",0,IF(H40="CÉLULA CONSTRUTIVA",OFFSET(B40,-1,0)+1,OFFSET(B40,-1,0))) -> 1 | C40: =IF(H40="CÉLULA CONSTRUTIVA",0,IF(H40="ETAPA",OFFSET(C40,-1,0)+1,OFFSET(C40,-1,0))) -> 2 | D40: =IF(H40="ETAPA",0,IF(H40="SUBETAPA",OFFSET(D40,-1,0)+1,OFFSET(D40,-1,0))) -> 9 | E40: =IF(H40="Subetapa",0,IF(H40="serviço",OFFSET(E40,-1,0)+1,OFFSET(E40,-1,0))) -> 1
A41: =IF($H41="UNIDADE CONSTRUTIVA",OFFSET(A41,-1,0)+1,LARGE(A$3:A38,1)) -> 0 | B41: =IF(H41="UNIDADE CONSTRUTIVA",0,IF(H41="CÉLULA CONSTRUTIVA",OFFSET(B41,-1,0)+1,OFFSET(B41,-1,0))) -> 1 | C41: =IF(H41="CÉLULA CONSTRUTIVA",0,IF(H41="ETAPA",OFFSET(C41,-1,0)+1,OFFSET(C41,-1,0))) -> 2 | D41: =IF(H41="ETAPA",0,IF(H41="SUBETAPA",OFFSET(D41,-1,0)+1,OFFSET(D41,-1,0))) -> 9 | E41: =IF(H41="Subetapa",0,IF(H41="serviço",OFFSET(E41,-1,0)+1,OFFSET(E41,-1,0))) -> 1
A42: =IF($H42="UNIDADE CONSTRUTIVA",OFFSET(A42,-1,0)+1,LARGE(A$3:A39,1)) -> 0 | B42: =IF(H42="UNIDADE CONSTRUTIVA",0,IF(H42="CÉLULA CONSTRUTIVA",OFFSET(B42,-1,0)+1,OFFSET(B42,-1,0))) -> 1 | C42: =IF(H42="CÉLULA CONSTRUTIVA",0,IF(H42="ETAPA",OFFSET(C42,-1,0)+1,OFFSET(C42,-1,0))) -> 2 | D42: =IF(H42="ETAPA",0,IF(H42="SUBETAPA",OFFSET(D42,-1,0)+1,OFFSET(D42,-1,0))) -> 9 | E42: =IF(H42="Subetapa",0,IF(H42="serviço",OFFSET(E42,-1,0)+1,OFFSET(E42,-1,0))) -> 1
A43: =IF($H43="UNIDADE CONSTRUTIVA",OFFSET(A43,-1,0)+1,LARGE(A$3:A40,1)) -> 0 | B43: =IF(H43="UNIDADE CONSTRUTIVA",0,IF(H43="CÉLULA CONSTRUTIVA",OFFSET(B43,-1,0)+1,OFFSET(B43,-1,0))) -> 1 | C43: =IF(H43="CÉLULA CONSTRUTIVA",0,IF(H43="ETAPA",OFFSET(C43,-1,0)+1,OFFSET(C43,-1,0))) -> 2 | D43: =IF(H43="ETAPA",0,IF(H43="SUBETAPA",OFFSET(D43,-1,0)+1,OFFSET(D43,-1,0))) -> 9 | E43: =IF(H43="Subetapa",0,IF(H43="serviço",OFFSET(E43,-1,0)+1,OFFSET(E43,-1,0))) -> 1
A44: =IF($H44="UNIDADE CONSTRUTIVA",OFFSET(A44,-1,0)+1,LARGE(A$3:A41,1)) -> 0 | B44: =IF(H44="UNIDADE CONSTRUTIVA",0,IF(H44="CÉLULA CONSTRUTIVA",OFFSET(B44,-1,0)+1,OFFSET(B44,-1,0))) -> 1 | C44: =IF(H44="CÉLULA CONSTRUTIVA",0,IF(H44="ETAPA",OFFSET(C44,-1,0)+1,OFFSET(C44,-1,0))) -> 2 | D44: =IF(H44="ETAPA",0,IF(H44="SUBETAPA",OFFSET(D44,-1,0)+1,OFFSET(D44,-1,0))) -> 9 | E44: =IF(H44="Subetapa",0,IF(H44="serviço",OFFSET(E44,-1,0)+1,OFFSET(E44,-1,0))) -> 1
A45: =IF($H45="UNIDADE CONSTRUTIVA",OFFSET(A45,-1,0)+1,LARGE(A$3:A42,1)) -> 0 | B45: =IF(H45="UNIDADE CONSTRUTIVA",0,IF(H45="CÉLULA CONSTRUTIVA",OFFSET(B45,-1,0)+1,OFFSET(B45,-1,0))) -> 1 | C45: =IF(H45="CÉLULA CONSTRUTIVA",0,IF(H45="ETAPA",OFFSET(C45,-1,0)+1,OFFSET(C45,-1,0))) -> 2 | D45: =IF(H45="ETAPA",0,IF(H45="SUBETAPA",OFFSET(D45,-1,0)+1,OFFSET(D45,-1,0))) -> 9 | E45: =IF(H45="Subetapa",0,IF(H45="serviço",OFFSET(E45,-1,0)+1,OFFSET(E45,-1,0))) -> 1
A46: =IF($H46="UNIDADE CONSTRUTIVA",OFFSET(A46,-1,0)+1,LARGE(A$3:A43,1)) -> 0 | B46: =IF(H46="UNIDADE CONSTRUTIVA",0,IF(H46="CÉLULA CONSTRUTIVA",OFFSET(B46,-1,0)+1,OFFSET(B46,-1,0))) -> 1 | C46: =IF(H46="CÉLULA CONSTRUTIVA",0,IF(H46="ETAPA",OFFSET(C46,-1,0)+1,OFFSET(C46,-1,0))) -> 2 | D46: =IF(H46="ETAPA",0,IF(H46="SUBETAPA",OFFSET(D46,-1,0)+1,OFFSET(D46,-1,0))) -> 9 | E46: =IF(H46="Subetapa",0,IF(H46="serviço",OFFSET(E46,-1,0)+1,OFFSET(E46,-1,0))) -> 1
A47: =IF($H47="UNIDADE CONSTRUTIVA",OFFSET(A47,-1,0)+1,LARGE(A$3:A44,1)) -> 0 | B47: =IF(H47="UNIDADE CONSTRUTIVA",0,IF(H47="CÉLULA CONSTRUTIVA",OFFSET(B47,-1,0)+1,OFFSET(B47,-1,0))) -> 1 | C47: =IF(H47="CÉLULA CONSTRUTIVA",0,IF(H47="ETAPA",OFFSET(C47,-1,0)+1,OFFSET(C47,-1,0))) -> 2 | D47: =IF(H47="ETAPA",0,IF(H47="SUBETAPA",OFFSET(D47,-1,0)+1,OFFSET(D47,-1,0))) -> 9 | E47: =IF(H47="Subetapa",0,IF(H47="serviço",OFFSET(E47,-1,0)+1,OFFSET(E47,-1,0))) -> 1
A48: =IF($H48="UNIDADE CONSTRUTIVA",OFFSET(A48,-1,0)+1,LARGE(A$3:A45,1)) -> 0 | B48: =IF(H48="UNIDADE CONSTRUTIVA",0,IF(H48="CÉLULA CONSTRUTIVA",OFFSET(B48,-1,0)+1,OFFSET(B48,-1,0))) -> 1 | C48: =IF(H48="CÉLULA CONSTRUTIVA",0,IF(H48="ETAPA",OFFSET(C48,-1,0)+1,OFFSET(C48,-1,0))) -> 2 | D48: =IF(H48="ETAPA",0,IF(H48="SUBETAPA",OFFSET(D48,-1,0)+1,OFFSET(D48,-1,0))) -> 9 | E48: =IF(H48="Subetapa",0,IF(H48="serviço",OFFSET(E48,-1,0)+1,OFFSET(E48,-1,0))) -> 1
A49: =IF($H49="UNIDADE CONSTRUTIVA",OFFSET(A49,-1,0)+1,LARGE(A$3:A46,1)) -> 0 | B49: =IF(H49="UNIDADE CONSTRUTIVA",0,IF(H49="CÉLULA CONSTRUTIVA",OFFSET(B49,-1,0)+1,OFFSET(B49,-1,0))) -> 1 | C49: =IF(H49="CÉLULA CONSTRUTIVA",0,IF(H49="ETAPA",OFFSET(C49,-1,0)+1,OFFSET(C49,-1,0))) -> 2 | D49: =IF(H49="ETAPA",0,IF(H49="SUBETAPA",OFFSET(D49,-1,0)+1,OFFSET(D49,-1,0))) -> 9 | E49: =IF(H49="Subetapa",0,IF(H49="serviço",OFFSET(E49,-1,0)+1,OFFSET(E49,-1,0))) -> 1
A50: =IF($H50="UNIDADE CONSTRUTIVA",OFFSET(A50,-1,0)+1,LARGE(A$3:A47,1)) -> 0 | B50: =IF(H50="UNIDADE CONSTRUTIVA",0,IF(H50="CÉLULA CONSTRUTIVA",OFFSET(B50,-1,0)+1,OFFSET(B50,-1,0))) -> 1 | C50: =IF(H50="CÉLULA CONSTRUTIVA",0,IF(H50="ETAPA",OFFSET(C50,-1,0)+1,OFFSET(C50,-1,0))) -> 2 | D50: =IF(H50="ETAPA",0,IF(H50="SUBETAPA",OFFSET(D50,-1,0)+1,OFFSET(D50,-1,0))) -> 9 | E50: =IF(H50="Subetapa",0,IF(H50="serviço",OFFSET(E50,-1,0)+1,OFFSET(E50,-1,0))) -> 1
... A671: =IF($H671="UNIDADE CONSTRUTIVA",OFFSET(A671,-1,0)+1,LARGE(A$3:A668,1)) -> 0 | B671: =IF(H671="UNIDADE CONSTRUTIVA",0,IF(H671="CÉLULA CONSTRUTIVA",OFFSET(B671,-1,0)+1,OFFSET(B671,-1,0))) -> 1 | C671: =IF(H671="CÉLULA CONSTRUTIVA",0,IF(H671="ETAPA",OFFSET(C671,-1,0)+1,OFFSET(C671,-1,0))) -> 2 | D671: =IF(H671="ETAPA",0,IF(H671="SUBETAPA",OFFSET(D671,-1,0)+1,OFFSET(D671,-1,0))) -> 9 | E671: =IF(H671="Subetapa",0,IF(H671="serviço",OFFSET(E671,-1,0)+1,OFFSET(E671,-1,0))) -> 1

Sheet EPCs
A1: Obra | B1: ='Obra '!D1 -> PARKSIDE RIO BRANCO
A2: Empresa | B2: ='Obra '!D2 -> PARKSIDE
A3: Revisão | B3: ='Obra '!D3 -> R00 - | K3: Guia pavimentos
A4: Equipamentos de proteção coletiva | K4: Pavimento | L4: Área | M4: Perímetro | N4: Pé Direito
A5: Bandejas de proteção | K5: Subsolo 02 | L5: 700.82 | M5: =4.91+26.37+(1.2*6)+15+5.47+4.8+2.72+0.6+0.2+7.2+0.57+2.4+0.41+5.13+(4*2.4)+2.6+0.3+0.7+1.09+2.78 -> 100.05 | N5: 2.92
K6: Subsolo 01 | L6: 613.5 | M6: =22.53+4.15+7.53+1.77+7.53+3+3.05+3.13+22.08+4.9+7.33+6.11+1.06+2.98 -> 97.15 | N6: 2.92
B7: Descrição | C7: Unidade | D7: Quantidade | F7: Imagem formulário | K7: Terreo | L7: 560.05 | M7: =24.03+16.83+22.08+16.83 -> 79.77 | N7: 3.1 | O7: =M7*N7 -> 247.287
B8: Perímetro de projeção embasamento | C8: m | D8: =M6 -> 97.15 | K8: PAV 02 | L8: 403.28 | M8: =24.03+16.83+22.08+16.83 -> 79.77 | N8: 3.1 | O8: =M8*N8 -> 247.287
B9: Perímetro de projeção torre tipo 1 | C9: m | D9: =M9 -> 79.77 | K9: PAV 03 | L9: 488.63 | M9: =24.03+16.83+22.08+16.83 -> 79.77 | N9: 3.1 | O9: =M9*N9 -> 247.287
B10: Bandeja de proteção primária | C10: m | D10: =D8 -> 97.15 | K10: Tipo | L10: =365.41*15 -> 5481.15 | M10: =24.03+16.83+22.08+16.83 -> 79.77 | N10: 3.1 | O10: =M10*N10*15 -> 3709.305
B11: Bandeja de proteção secundária | C11: m | D11: =D9 -> 79.77 | K11: Cobertura | L11: 322.67 | M11: =22.08+16.43+16.83+22.08+2.5 -> 79.92 | N11: 2.91 | O11: =M11*N11 -> 232.5672
B12: * Considerado as informações do Projeto de Segurança | K12: Barrilete | L12: 45 | M12: =2.55+2.55+6.43+6.43 -> 17.96 | N12: 7.68 | O12: =M12*N12 -> 137.9328
A13: Guarda - corpo de vãos | K13: Reservatório | L13: 45 | M13: =2.55+2.55+6.43+6.43 -> 17.96 | O13: =M13*N13 -> 0
O14: =SUM(O5:O13) -> 4821.666
B15: Descrição | C15: Unidade | D15: Quantidade | F15: Imagem formulário
B16: Perímetro de vãos | C16: m | D16: =(1.65*10*5)+M11 -> 162.42
B17: Guarda - corpo de vãos | C17: m | D17: =D16 -> 162.42
A19: Guarda - corpo de desforma
B21: Descrição | C21: Unidade | D21: Quantidade | F21: Imagem formulário
B22: Perímetro de projeção da torre | C22: m | D22: =M7 -> 79.77
B23: Repetições de pavimentos** | C23: un | D23: 4
B24: Proteção de periferia pós desforma torre | C24: m | D24: =(D22*D23) -> 319.08
A26: Fechamento removível de vãos em madeira
B28: Descrição | C28: Unidade | D28: Quantidade | F28: Imagem formulário
B29: Área das portas de elevadores | C29: m2 | D29: 3.24
B30: Quantidade de elevadores | C30: un | D30: 1
B31: Quantidade de portas de elevadores | C31: un | D31: 8
B32: Fechamento removível de vãos em madeira | C32: m2 | D32: =D29*D31 -> 25.92
B33: Área das portas de aptos | C33: m2
B34: Quantidade de aptos | C34: un
B35: =A26 -> Fechamento removível de vãos em madeira | C35: m2 | D35: =D33*D34 -> 0
A37: Tela fachadeira
B39: Descrição | C39: Unidade | D39: Quantidade | F39: Imagem formulário
B40: Area da fachada | C40: m² | D40: =SUMPRODUCT($M$6:$M$13,$N$6:$N$13) -> 1643.326
B41: =A37 -> Tela fachadeira | C41: m2 | D41: =D40 -> 1643.326
A43: SLQA
B45: Descrição | C45: Unidade | D45: Quantidade | F45: Imagem formulário
B46: Perímetro de projeção da torre 1 | C46: m | D46: =M7 -> 79.77
B47: Altura de cobrimento da tela | C47: un | D47: 1
B48: =A43 -> SLQA | C48: m | D48: =D46*D47 -> 79.77
A51: Tapume
B53: Descrição | C53: Unidade | D53: Quantidade | F53: Imagem formulário
B54: Perímetro de encontro com pavimentação | C54: m | D54: =11.02+11.9+29.83 -> 52.75
B55: Altura do tapume | C55: m | D55: 2.4
B56: =A51 -> Tapume | C56: m2 | D56: =D55*D54 -> 126.6
A58: Linha de Vida
B60: Descrição | C60: Unidade | D60: Quantidade | F60: Imagem formulário
B61: Perímetro de Pavimentos | C61: m | D61: =$D$24 -> 319.08
B62: =A58 -> Linha de Vida | C62: m | D62: =D61 -> 319.08
A64: Cobertura para Proteção de Pedestres
B66: Descrição | C66: Unidade | D66: Quantidade | F66: Imagem formulário
B67: Perímetro de projeção torre | C67: m
B68: Altura de cobrimento da tela | C68: m
B69: Cobertura para Proteção de Pedestres | C69: m2 | D69: =D67*D68 -> 0
A73: COMPOSIÇÃO
A74: Bandeja de proteção primária | C74: m | D74: =D10 -> 97.15 | E74: 284.8 | F74: =D74*E74 -> 27668.32
A75: Bandeja de proteção secundária | C75: m | D75: =D11 -> 79.77 | E75: 270.94 | F75: =D75*E75 -> 21612.884
A76: Guarda - corpo de vãos | C76: m2 | D76: =D17 -> 162.42 | E76: 38.65 | F76: =D76*E76 -> 6277.533
A77: Proteção de periferia pós desforma torre | C77: m | D77: =D24 -> 319.08 | E77: 41.04 | F77: =D77*E77 -> 13095.043
A78: Fechamento removível de vãos em madeira | C78: m2 | D78: =D32 -> 25.92 | E78: 47.35 | F78: =D78*E78 -> 1227.312
A79: Linha de Vida | C79: m | D79: =D62 -> 319.08 | E79: 87.21 | F79: =D79*E79 -> 27826.967
A80: SLQA | C80: m | D80: =D11 -> 79.77 | E80: 88 | F80: =D80*E80 -> 7019.76
E81: Total | F81: =SUM(F74:F80) -> 104727.82

Sheet PISO E TETO
A1: Obra | B1: Estreito
A2: Empresa | B2: D'Lohn Empreendimentos
A3: Revisão | B3: R00
A4: Data | B4: 45726
A5: LEVANTAMENTO QUANTITATIVO
A7: REVESTIMENTOS E ACABAMENTOS DE PISO E TETO
B9: LEVANTAMENTO DE PROJETO | L9: CONTRAPISO
B10: Pavimento | C10: Ambiente | D10: Área (m²) | E10: Material | F10: Contrapiso (Sim/Não) | G10: Forro | H10: Repetição | I10: Total | L10: Revestimento | M10: Área total
B11: SUBSOLO 2 | C11: GARAGEM | D11: 673.78 | E11: POLIDO | F11: Não | G11: Estucamento | H11: 1 | I11: =H11*'PISO E TETO'!$D11 -> 673.78 | L11: Contrapiso | M11: =SUMIF(F:F,"Sim",I:I) -> 7621.262
B12: SUBSOLO 2 | C12: ESCADA | D12: =27.11+1.2*17*0.18 -> 30.782 | E12: CIMENTADO | F12: Sim | G12: Estucamento | H12: 21 | I12: =H12*'PISO E TETO'!$D12 -> 646.422 | L12: Manta acústica | M12: =SUM(I34:I57) -> 6416.83
B13: SUBSOLO 1 | C13: GARAGEM | D13: 586.38 | E13: POLIDO | F13: Não | G13: Estucamento | H13: 1 | I13: =H13*'PISO E TETO'!$D13 -> 586.38 | L13: FORRO
B14: SUBSOLO 1 | E14: POLIDO | F14: Não | G14: Estucamento | H14: 1 | I14: =H14*'PISO E TETO'!$D14 -> 0 | L14: Revestimento | M14: Área total
B15: TERREO / 1 PAV | C15: GARAGEM | D15: 199.21 | E15: POLIDO | F15: Não | G15: Estucamento | H15: 1 | I15: =H15*'PISO E TETO'!$D15 -> 199.21 | L15: Estucamento | M15: =SUMIF(G:G,L15,I:I) -> 2404.962
B16: TERREO / 1 PAV | C16: CIRCULAÇÃO | D16: 49.39 | E16: PORCELANATO | F16: Sim | G16: Gesso | H16: 1 | I16: =H16*'PISO E TETO'!$D16 -> 49.39 | L16: Gesso | M16: =SUMIF(G:G,L16,I:I) -> 6338.53
B17: TERREO / 1 PAV | C17: HALL | D17: 55.57 | E17: PORCELANATO | F17: Sim | G17: Gesso | H17: 1 | I17: =H17*'PISO E TETO'!$D17 -> 55.57 | L17: Madeira | M17: =SUMIF(G:G,L17,I:I) -> 0
B18: TERREO / 1 PAV | C18: COWORKING | D18: 43.63 | E18: PORCELANATO | F18: Sim | G18: Gesso | H18: 1 | I18: =H18*'PISO E TETO'!$D18 -> 43.63 | L18: - | M18: =SUMIF(G:G,L18,I:I) -> 656.05
B19: TERREO / 1 PAV | C19: COPA | D19: 5.39 | E19: PORCELANATO | F19: Sim | G19: Gesso | H19: 1 | I19: =H19*'PISO E TETO'!$D19 -> 5.39 | J19: parte descoberta
B20: TERREO / 1 PAV | C20: WC | D20: 2.88 | E20: PORCELANATO | F20: Sim | G20: Gesso | H20: 1 | I20: =H20*'PISO E TETO'!$D20 -> 2.88 | J20: parte descoberta
B21: TERREO / 1 PAV | C21: ALMOX | D21: 14.25 | E21: PORCELANATO | F21: Sim | G21: Gesso | H21: 1 | I21: =H21*'PISO E TETO'!$D21 -> 14.25 | L21: ACABAMENTOS
B22: TERREO / 1 PAV | C22: MINIMARKET | D22: 8.02 | E22: PORCELANATO | F22: Sim | G22: Gesso | H22: 1 | I22: =H22*'PISO E TETO'!$D22 -> 8.02 | L22: Material | M22: Área total
B23: TERREO / 1 PAV | C23: WC/VEST | D23: 5.98 | E23: PORCELANATO | F23: Sim | G23: Gesso | H23: 1 | I23: =H23*'PISO E TETO'!$D23 -> 5.98 | L23: POLIDO | M23: =SUMIF(E:E,L23,I:I) -> 1758.54
B24: TERREO / 1 PAV | C24: RECEP | D24: 3.82 | E24: PORCELANATO | F24: Sim | G24: Gesso | H24: 1 | I24: =H24*'PISO E TETO'!$D24 -> 3.82 | L24: CIMENTADO | M24: =SUMIF(E:E,L24,I:I) -> 646.422
B25: TERREO / 1 PAV | C25: BICICLETARIO | D25: =5.27+7.06 -> 12.33 | E25: PORCELANATO | F25: Sim | G25: Gesso | H25: 1 | I25: =H25*'PISO E TETO'!$D25 -> 12.33 | L25: PORCELANATO | M25: =SUMIF(E:E,L25,I:I) -> 2228.42
B26: TERREO / 1 PAV | C26: AT | D26: 19.52 | E26: PORCELANATO | F26: Sim | G26: Gesso | H26: 1 | I26: =H26*'PISO E TETO'!$D26 -> 19.52 | L26: VINILICO | M26: =SUMIF(E:E,L26,I:I) -> 4706.56
B27: TERREO / 1 PAV | C27: GAS/LIXO | D27: 12.77 | E27: PORCELANATO | F27: Sim | G27: Gesso | H27: 1 | I27: =H27*'PISO E TETO'!$D27 -> 12.77 | L27: MADEIRA | M27: =SUMIF(E:E,L27,I:I) -> 6.6
B28: TERREO / 1 PAV | C28: LAVANDERIA | D28: 17.33 | E28: PORCELANATO | F28: Sim | G28: Gesso | H28: 1 | I28: =H28*'PISO E TETO'!$D28 -> 17.33 | L28: PASTILHA | M28: =SUMIF(E:E,L28,I:I) -> 33.26
B29: TERREO / 1 PAV | C29: COMERCIAL | D29: 49.33 | E29: PORCELANATO | F29: Sim | G29: Gesso | H29: 1 | I29: =H29*'PISO E TETO'!$D29 -> 49.33 | L29: DECK | M29: =SUMIF(E:E,L29,I:I) -> 19.74
B30: TERREO / 1 PAV | C30: AREA EXXTERNA | D30: =60.47+20.83 -> 81.3 | E30: PORCELANATO | F30: Sim | G30: - | H30: 1 | I30: =H30*'PISO E TETO'!$D30 -> 81.3 | L30: - | M30: =SUMIF(E:E,L30,I:I) -> 0
B31: PAV 02 | C31: GARAGEM | D31: 299.17 | E31: POLIDO | F31: Não | G31: Estucamento | H31: 1 | I31: =H31*'PISO E TETO'!$D31 -> 299.17
B32: PAV 02 | C32: CIRCULAÇÃO | D32: 47.19 | E32: PORCELANATO | F32: Sim | G32: Gesso | H32: 1 | I32: =H32*'PISO E TETO'!$D32 -> 47.19
B33: PAV 02 | C33: COMERCAL | D33: =57.46+35.58+56.01 -> 149.05 | E33: PORCELANATO | F33: Sim | G33: Gesso | H33: 1 | I33: =H33*'PISO E TETO'!$D33 -> 149.05
B34: GARDENS | C34: 1D | D34: =35.58+26.56+32.64 -> 94.78 | E34: VINILICO | F34: Sim | G34: Gesso | H34: 1 | I34: =H34*'PISO E TETO'!$D34 -> 94.78
B35: GARDENS | C35: 1D GARDEN | D35: =29.6+11.6+18.36 -> 59.56 | E35: PORCELANATO | F35: Sim | G35: - | H35: 1 | I35: =H35*'PISO E TETO'!$D35 -> 59.56
B36: GARDENS | C36: 2D | D36: 52.23 | E36: VINILICO | F36: Sim | G36: Gesso | H36: 1 | I36: =H36*'PISO E TETO'!$D36 -> 52.23
B37: GARDENS | C37: 2D GARDEN | D37: 34.16 | E37: PORCELANATO | F37: Sim | G37: - | H37: 1 | I37: =H37*'PISO E TETO'!$D37 -> 34.16
B38: GARDENS | C38: STUDIO | D38: =29.27+22.7+17.08+26.67+25.85+25.58 -> 147.15 | E38: VINILICO | F38: Sim | G38: Gesso | H38: 1 | I38: =H38*'PISO E TETO'!$D38 -> 147.15
B39: GARDENS | C39: STUDIO GARDEN | D39: =25.67+25.58+14.65 -> 65.9 | E39: PORCELANATO | F39: Sim | G39: - | H39: 1 | I39: =H39*'PISO E TETO'!$D39 -> 65.9
B40: GARDENS | C40: CIRCULAÇÃO | D40: 54.06 | E40: PORCELANATO | F40: Sim | G40: Gesso | H40: 1 | I40: =H40*'PISO E TETO'!$D40 -> 54.06
B41: GARDENS | C41: DML | D41: 2.96 | E41: PORCELANATO | F41: Sim | G41: Gesso | H41: 1 | I41: =H41*'PISO E TETO'!$D41 -> 2.96
B42: TIPO (X15) | C42: 1D | D42: =35.58+26.56+32.64 -> 94.78 | E42: VINILICO | F42: Sim | G42: Gesso | H42: 15 | I42: =H42*'PISO E TETO'!$D42 -> 1421.7
B43: TIPO (X15) | C43: 2D | D43: 52.23 | E43: VINILICO | F43: Sim | G43: Gesso | H43: 15 | I43: =H43*'PISO E TETO'!$D43 -> 783.45
B44: TIPO (X15) | C44: STUDIO | D44: =29.27+22.7+17.08+26.67+25.85+25.58 -> 147.15 | E44: VINILICO | F44: Sim | G44: Gesso | H44: 15 | I44: =H44*'PISO E TETO'!$D44 -> 2207.25
B45: TIPO (X15) | C45: AT | D45: =2.4*4+1.81*3 -> 15.03 | E45: PORCELANATO | F45: Sim | G45: - | H45: 15 | I45: =H45*'PISO E TETO'!$D45 -> 225.45
B46: TIPO (X15) | C46: CIRCULAÇÃO | D46: 54.06 | E46: PORCELANATO | F46: Sim | G46: Gesso | H46: 15 | I46: =H46*'PISO E TETO'!$D46 -> 810.9
B47: TIPO (X15) | C47: DML | D47: 2.96 | E47: PORCELANATO | F47: Sim | G47: Gesso | H47: 15 | I47: =H47*'PISO E TETO'!$D47 -> 44.4
B48: COBERTURA | C48: CIRCULAÇÃO | D48: 17.96 | E48: PORCELANATO | F48: Sim | G48: Gesso | H48: 1 | I48: =H48*'PISO E TETO'!$D48 -> 17.96
B49: COBERTURA | C49: ACADEMIA | D49: 31.37 | E49: PORCELANATO | F49: Sim | G49: Gesso | H49: 1 | I49: =H49*'PISO E TETO'!$D49 -> 31.37
B50: COBERTURA | C50: BWC | D50: 3.36 | E50: PORCELANATO | F50: Sim | G50: Gesso | H50: 1 | I50: =H50*'PISO E TETO'!$D50 -> 3.36
B51: COBERTURA | C51: SAUNA | D51: 6.6 | E51: MADEIRA | F51: Sim | G51: Gesso | H51: 1 | I51: =H51*'PISO E TETO'!$D51 -> 6.6
B52: COBERTURA | C52: GOUMET | D52: 148.67 | E52: PORCELANATO | F52: Sim | G52: Gesso | H52: 1 | I52: =H52*'PISO E TETO'!$D52 -> 148.67
B53: COBERTURA | C53: YOGA | D53: 12.19 | E53: PORCELANATO | F53: Sim | G53: Gesso | H53: 1 | I53: =H53*'PISO E TETO'!$D53 -> 12.19
B54: COBERTURA | C54: WC | D54: 3.05 | E54: PORCELANATO | F54: Sim | G54: Gesso | H54: 1 | I54: =H54*'PISO E TETO'!$D54 -> 3.05
B55: COBERTURA | C55: PISCINA | D55: =12.2+(2*2+6.1*2)*1.3 -> 33.26 | E55: PASTILHA | F55: Sim | G55: - | H55: 1 | I55: =H55*'PISO E TETO'!$D55 -> 33.26
B56: COBERTURA | C56: AREA EXTERNA | D56: =34.71+76.11+25.86 -> 136.68 | E56: PORCELANATO | F56: Sim | G56: - | H56: 1 | I56: =H56*'PISO E TETO'!$D56 -> 136.68
B57: COBERTURA | C57: DECK | D57: =6.1+Arquitetura!G411 -> 19.74 | E57: DECK | F57: Não | G57: - | H57: 1 | I57: =H57*'PISO E TETO'!$D57 -> 19.74

Sheet CANTEIRO
A1: Obra | B1: ='Obra '!D1 -> PARKSIDE RIO BRANCO
A2: Empresa | B2: ='Obra '!D2 -> PARKSIDE
A3: Revisão | B3: ='Obra '!D3 -> R00 - | O3: Número de funcionários | S3: Produtividade média (h/m2)
A4: Instalações de canteiro | O4: Área construída | P4: 6601.277 | S4: A.C/prazo | T4: =P4/P5 -> 235.75989
A5: Instalações de canteiro | O5: Prazo da obra | P5: 28 | Q5: meses | S5: Pm | T5: 49 | U5: h/m2
O6: NF | P6: =ROUNDUP((P4*T5)/P5/180,) -> 65 | Q6: funcionários
B7: Descrição | C7: Unidade | D7: Quantidade | O7: Pavimentos | P7: 10
B8: Produtividade média | C8: m2 / mês | D8: ='Obra '!$E$9/'Obra '!$E$7 -> 262.42727 | O8: Equipe administrativa | P8: 5 | Q8: funcionários
B9: Pm | C9: h/m2 | D9: 49
B10: Numero de funcionários | C10: un | D10: =ROUNDUP((D9*'Obra '!$E$9)/'Obra '!$E$7/180,) -> 72
B11: Equipe administrativa | C11: un | D11: 5 | O11: Barracão interno | P11: =450+(P4-13000)/1000*16 -> 347.62043
B12: Pontos de água e esgoto | C12: un | D12: =ROUNDUP($D$10/20,0) -> 4 | E12: 20 funcionários/ponto | O12: Externo | P12: =P11*0.4 -> 139.04817
B13: Bebedouro | C13: un | D13: =ROUNDUP('Obra '!$E$13/5,0) -> 5 | E13: 1 / 5 pav.
B14: Ferramentas | C14: R$ | D14: =800*D10 -> 57600 | E14: 800,00/func. | P14: =SUM(P11:P13) -> 486.6686
B15: EPI | C15: R$ | D15: =500*(D10+D11) -> 38500 | E15: 500,00/func.
B16: Banheiro | C16: un | D16: =ROUNDUP($D$10/20,0) -> 4 | E16: 1/20 func | O16: Área refeitório | P16: 1 | Q16: m²/funcionários
P17: =P16*P6 -> 65 | Q17: m²
A18: Mobiliário de canteiro
O19: Área de vestiário | P19: 1.5 | Q19: m²/funcionários
B20: Descrição | C20: Unidade | D20: Quantidade | E20: Custo unitário | F20: Custo total | P20: =P19*P6 -> 97.5 | Q20: m²
B21: Cadeira | C21: un | D21: =ROUNDUP(D11*1.5,) -> 8 | E21: 200 | F21: =D21*E21 -> 1600
B22: Mesa | C22: un | D22: 1 | E22: 1000 | F22: =E22*D22 -> 1000
B23: Ar condicionado | C23: un | D23: 2 | E23: 5000 | F23: =E23*D23 -> 10000
B24: Armário | C24: m | D24: 4 | E24: 900 | F24: =E24*D24 -> 3600
B25: Escrivaninha | C25: un | D25: =D11 -> 5 | E25: 800 | F25: =E25*D25 -> 4000
B26: TOTAL | F26: =F23+F24+F25+F22+F21 -> 20200
B27: Descrição | C27: Unidade | D27: Quantidade | E27: Custo unitário | F27: Custo total
B28: Computador pessoal | C28: un | D28: =D11 -> 5 | E28: 6500 | F28: =D28*E28 -> 32500
B29: Impressora | C29: un | D29: 1 | E29: 2000 | F29: =E29*D29 -> 2000
B30: Roteador | C30: un | D30: 2 | E30: 500 | F30: =E30*D30 -> 1000
B31: TOTAL | F31: =+F28+F29+F30 -> 35500 | O31: Área sanitários | P31: =1*ROUNDUP(P6/20,) -> 4 | Q31: m²
A33: Instalações Provisórias (central de aço, formas, argamassa, almoxarifado geral, construções temporárias) | O33: área lavatório | P33: =0.6*ROUNDUP(P6/20,) -> 2.4 | Q33: m²
O34: Área de chuveiros | P34: =0.8*ROUNDUP(P6/10,) -> 5.6 | Q34: m²
B35: Descrição | C35: Unidade | D35: Será utilizado | E35: Quantidade | F35: Custo unitário | G35: Custo total
B36: Central de aço | C36: m2 | D36: Sim | E36: =IF(D36="Sim",15,0) -> 15 | F36: 115.4849 | G36: =IF(D36="sim",E36*F36,0) -> 1732.2735
B37: Central de fôrmas | C37: m2 | D37: Sim | E37: =IF(D37="Sim",15,0) -> 15 | F37: 115.4849 | G37: =IF(D37="sim",E37*F37,0) -> 1732.2735
B38: Central de Argamassa | C38: m2 | D38: Sim | E38: =IF(D38="Sim",15,0) -> 15 | F38: 115.4849 | G38: =IF(D38="sim",E38*F38,0) -> 1732.2735
B39: Armazenamento de cerâmicas* | C39: m2 | D39: Sim | E39: =IF(D39="não",0,ROUNDUP(3*'Obra '!$E$10/COUNTIFS($D$39:$D$47,"Sim"),)) -> 69 | F39: 201.22489 | G39: =IF(D39="sim",E39*F39,0) -> 13884.517
B40: Armazenamento de placas degesso* | C40: m2 | D40: Não | E40: =IF(D40="não",0,ROUNDUP(3*'Obra '!$E$10/COUNTIFS($D$39:$D$47,"Sim"),)) -> 0 | F40: 201.22489 | G40: =IF(D40="sim",E40*F40,0) -> 0
B41: Armazenamento de blocos* | C41: m2 | D41: Sim | E41: =IF(D41="não",0,ROUNDUP(3*'Obra '!$E$10/COUNTIFS($D$39:$D$47,"Sim"),)) -> 69 | F41: 201.22489 | G41: =IF(D41="sim",E41*F41,0) -> 13884.517
B42: Armazenamento de contramarcos* | C42: m2 | D42: Sim | E42: =IF(D42="não",0,ROUNDUP(3*'Obra '!$E$10/COUNTIFS($D$39:$D$47,"Sim"),)) -> 69 | F42: 201.22489 | G42: =IF(D42="sim",E42*F42,0) -> 13884.517
B43: Armazenamento de portas e rodapés* | C43: m2 | D43: Sim | E43: =IF(D43="não",0,ROUNDUP(3*'Obra '!$E$10/COUNTIFS($D$39:$D$47,"Sim"),)) -> 69 | F43: 201.22489 | G43: =IF(D43="sim",E43*F43,0) -> 13884.517
B44: Armazenamento de esquadrias* | C44: m2 | D44: Não | E44: =IF(D44="não",0,ROUNDUP(3*'Obra '!$E$10/COUNTIFS($D$39:$D$47,"Sim"),)) -> 0 | F44: 201.22489 | G44: =IF(D44="sim",E44*F44,0) -> 0
B45: Armazenamento de instalações complementares* | C45: m2 | D45: Sim | E45: =IF(D45="não",0,ROUNDUP(3*'Obra '!$E$10/COUNTIFS($D$39:$D$47,"Sim"),)) -> 69 | F45: 201.22489 | G45: =IF(D45="sim",E45*F45,0) -> 13884.517
B46: Armazenamento para estoque geral* | C46: m2 | D46: Sim | E46: =IF(D46="não",0,ROUNDUP(3*'Obra '!$E$10/COUNTIFS($D$39:$D$47,"Sim"),)) -> 69 | F46: 201.22489 | G46: =IF(D46="sim",E46*F46,0) -> 13884.517
B47: Construções temporárias | C47: m2 | D47: Sim | E47: =IF(D47="não",0,ROUNDUP(3*'Obra '!$E$10/COUNTIFS($D$39:$D$47,"Sim"),)) -> 69 | F47: 272.8753 | G47: =IF(D47="sim",E47*F47,0) -> 18828.396
B48: Almoxarifado geral | C48: m2 | D48: Não | E48: =IF(D48="Sim",10*15,0) -> 0 | F48: 272.8753 | G48: =IF(D48="sim",E48*F48,0) -> 0
B49: Guarita | C49: m2 | D49: Sim | E49: =IF(D49="Sim",ROUNDUP(25,),0) -> 25 | F49: 272.88 | G49: =IF(D49="sim",E49*F49,0) -> 6822
B50: Lava Rodas | C50: m2 | D50: Sim | E50: =IF(D50="Sim",ROUNDUP(25,),0) -> 25 | F50: 0 | G50: =IF(D50="sim",E50*F50,0) -> 0
B51: TOTAL | G51: =SUM(G36:G50) -> 114154.32
O52: área lavatório | P52: =0.6*ROUNDUP(P21/20,) -> 0 | Q52: m²
B53: * Central de armazenamento entre pavimentos
O54: Área de chuveiros | P54: =0.8*ROUNDUP(P21/10,) -> 0 | Q54: m²
A55: Sinalização
B57: Descrição | C57: Unidade | D57: Será utilizado | E57: Quantidade | F57: Custo unitário | G57: Custo total
B58: Placa indicativa fixada na estrutura por pregos | C58: VB | D58: Sim | E58: 1 | F58: 7891.02 | G58: =IF(D58="sim",E58*F58,0) -> 7891.02 | O58: Escritório | P58: 8 | Q58: m²/pessoa
B59: Placa indicativa fixada em totem | C59: m2 | D59: Não | G59: =IF(D59="sim",E59*F59,0) -> 0 | P59: =P58*P8 -> 40 | Q59: m²
B60: Instalação de sinalizador noturno | C60: m2 | D60: Não | G60: =IF(D60="sim",E60*F60,0) -> 0
B61: Sinalização com fita fixada em cone | C61: m2 | D61: Não | G61: =IF(D61="sim",E61*F61,0) -> 0 | O61: Almoxarifado | P61: =IF(P4<20000,100,100+((P4-20000)/1000)*5) -> 100 | Q61: m2
B62: Sinalização com fita fixada na estrutura amarrada | C62: m2 | D62: Não | G62: =IF(D62="sim",E62*F62,0) -> 0
B63: #REF! | C63: VB | D63: Sim | G63: =IF(D63="sim",E63*F63,0) -> 0
B64: TOTAL | G64: =SUM(G58:G63) -> 7891.02 | O64: Ferramentas | P64: =P6*800 -> 52000 | Q64: 800 por funcionário
O66: EPI | P66: =P6*500 -> 32500 | Q66: 500,00 por funcionário | R66: Considerando entrega de 2 uniformes, capacete, bota, óculos e cinto
O69: Banheiro | P69: 1 | Q69: para cada | R69: 20 | S69: pessoas
P70: =ROUNDUP(P6/R69,) -> 4

Sheet Quadro resumo estrutural
A10: Quadro de Resumo
A11: 0
A15: Aço (Kg) - Perda = 0% | U15: Forma | V15: Concreto | W15: ENCHIMENTO
A16: Nivel | B16: CA-60 | C16: CA-50A | J16: Total | K16: fbk | L16: BLOCO CERÂMICO 14cm | Q16: CANALETAS | S16: ARGAMASSA | T16: GRAUTE | V16: fck=30MPa | W16: 0 | X16: 0 | Y16: 0 | Z16: 0
B17: 5,0mm | C17: 6,3mm | D17: 8,0mm | E17: 10,0mm | F17: 12,5mm | G17: 16,0mm | H17: 20,0mm | I17: 25,0mm | J17: Pvto. | K17: (Mpa) | L17: 14x19x04 | M17: 14x19x09 | N17: 14x19x14 | O17: 14x19x29 | P17: 14x19x44 | Q17: 14x19x29 | R17: 14x19x14 | U17: (m2) | V17: (m3) | W17: 0 | X17: 0 | Y17: 0 | Z17: 0
A18: 0 | B18: 0 | C18: 0 | D18: 0 | E18: 0 | F18: 0 | G18: 0 | H18: 0 | J18: =SUM(B18:H18) -> 0 | U18: 0 | V18: 0 | W18: 0 | X18: 0 | Y18: 0 | Z18: 0
A19: 0 | B19: 0 | C19: 0 | D19: 0 | E19: 0 | F19: 0 | G19: 0 | H19: 0 | I19: 0 | J19: =SUM(B19:I19) -> 0 | U19: 0 | V19: 0 | W19: 0 | X19: 0 | Y19: 0 | Z19: 0
A20: 0 | B20: 0 | C20: 0 | D20: 0 | E20: 0 | F20: 0 | G20: 0 | H20: 0 | I20: 0 | J20: =SUM(B20:I20) -> 0 | U20: 0 | V20: 0 | W20: 0 | X20: 0 | Y20: 0 | Z20: 0
A21: 0 | B21: 0 | C21: 0 | D21: 0 | E21: 0 | F21: 0 | G21: 0 | H21: 0 | I21: 0 | J21: =SUM(B21:I21) -> 0 | W21: 0 | X21: 0 | Y21: 0 | Z21: 0
A22: 0 | B22: 0 | C22: 0 | D22: 0 | E22: 0 | F22: 0 | G22: 0 | H22: 0 | I22: 0 | J22: =SUM(B22:I22) -> 0 | K22: 0 | L22: 0 | M22: 0 | N22: 0 | O22: 0 | P22: 0 | Q22: 0 | R22: 0 | S22: 0 | T22: 0 | U22: 0 | V22: 0 | W22: 0 | X22: 0 | Y22: 0 | Z22: 0
A23: 0 | B23: 0 | C23: 0 | D23: 0 | E23: 0 | F23: 0 | G23: 0 | H23: 0 | I23: 0 | J23: =SUM(B23:I23) -> 0 | K23: 0 | L23: 0 | M23: 0 | N23: 0 | O23: 0 | P23: 0 | Q23: 0 | R23: 0 | S23: 0 | T23: 0 | U23: 0 | V23: 0 | W23: 0 | X23: 0 | Y23: 0 | Z23: 0
A24: 0 | B24: 0 | C24: 0 | D24: 0 | E24: 0 | F24: 0 | G24: 0 | H24: 0 | I24: 0 | J24: =SUM(B24:I24) -> 0 | K24: 0 | L24: 0 | M24: 0 | N24: 0 | O24: 0 | P24: 0 | Q24: 0 | R24: 0 | S24: 0 | T24: 0 | U24: 0 | V24: 0 | W24: 0 | X24: 0 | Y24: 0 | Z24: 0
A25: 0 | B25: 0 | C25: 0 | D25: 0 | E25: 0 | F25: 0 | G25: 0 | H25: 0 | I25: 0 | J25: =SUM(B25:I25) -> 0 | K25: 0 | L25: 0 | M25: 0 | N25: 0 | O25: 0 | P25: 0 | Q25: 0 | R25: 0 | S25: 0 | T25: 0 | U25: 0 | V25: 0 | W25: 0 | X25: 0 | Y25: 0 | Z25: 0
A26: 0 | B26: 0 | C26: 0 | D26: 0 | E26: 0 | F26: 0 | G26: 0 | H26: 0 | I26: 0 | J26: =SUM(B26:I26) -> 0 | K26: 0 | L26: 0 | M26: 0 | N26: 0 | O26: 0 | P26: 0 | Q26: 0 | R26: 0 | S26: 0 | T26: 0 | U26: 0 | V26: 0 | W26: 0 | X26: 0 | Y26: 0 | Z26: 0
A27: 0 | B27: 0 | C27: 0 | D27: 0 | E27: 0 | F27: 0 | G27: 0 | H27: 0 | I27: 0 | J27: =SUM(B27:I27) -> 0 | K27: 0 | L27: 0 | M27: 0 | N27: 0 | O27: 0 | P27: 0 | Q27: 0 | R27: 0 | S27: 0 | T27: 0 | U27: 0 | V27: 0 | W27: 0 | X27: 0 | Y27: 0 | Z27: 0
A28: 0 | B28: 0 | C28: 0 | D28: 0 | E28: 0 | F28: 0 | G28: 0 | H28: 0 | I28: 0 | J28: =SUM(B28:I28) -> 0 | K28: 0 | L28: 0 | M28: 0 | N28: 0 | O28: 0 | P28: 0 | Q28: 0 | R28: 0 | S28: 0 | T28: 0 | U28: 0 | V28: 0 | W28: 0 | X28: 0 | Y28: 0 | Z28: 0
K29: Total 6 | L29: =SUM(L25:L28) -> 0 | M29: =SUM(M25:M28) -> 0 | N29: =SUM(N25:N28) -> 0 | O29: =SUM(O25:O28) -> 0 | P29: =SUM(P25:P28) -> 0 | Q29: =SUM(Q25:Q28) -> 0 | R29: =SUM(R25:R28) -> 0
A30: 0 | B30: 0 | C30: 0 | D30: 0 | E30: 0 | F30: 0 | G30: 0 | H30: 0 | I30: 0 | J30: =SUM(B30:I30) -> 0 | K30: 0 | L30: 0 | M30: 0 | N30: 0 | O30: 0 | P30: 0 | Q30: 0 | R30: 0 | S30: 0 | T30: 0 | U30: 0 | V30: 0 | W30: 0 | X30: 0 | Y30: 0 | Z30: 0
A31: 0 | B31: 0 | C31: 0 | D31: 0 | E31: 0 | F31: 0 | G31: 0 | H31: 0 | I31: 0 | J31: =SUM(B31:I31) -> 0 | K31: 0 | L31: 0 | M31: 0 | N31: 0 | O31: 0 | P31: 0 | Q31: 0 | R31: 0 | S31: 0 | T31: 0 | U31: 0 | V31: 0 | W31: 0 | X31: 0 | Y31: 0 | Z31: 0
A32: 0 | B32: 0 | C32: 0 | D32: 0 | E32: 0 | F32: 0 | G32: 0 | H32: 0 | I32: 0 | J32: =SUM(B32:I32) -> 0 | K32: 0 | L32: 0 | M32: 0 | N32: 0 | O32: 0 | P32: 0 | Q32: 0 | R32: 0 | S32: 0 | T32: 0 | U32: 0 | V32: 0 | W32: 0 | X32: 0 | Y32: 0 | Z32: 0
A33: 0 | B33: 0 | C33: 0 | D33: 0 | E33: 0 | F33: 0 | G33: 0 | H33: 0 | I33: 0 | J33: =SUM(B33:I33) -> 0 | K33: 0 | L33: 0 | M33: 0 | N33: 0 | O33: 0 | P33: 0 | Q33: 0 | R33: 0 | S33: 0 | T33: 0 | U33: 0 | V33: 0 | W33: 0 | X33: 0 | Y33: 0 | Z33: 0
A34: 0 | B34: 0 | C34: 0 | D34: 0 | E34: 0 | F34: 0 | G34: 0 | H34: 0 | I34: 0 | J34: =SUM(B34:I34) -> 0 | U34: 0 | V34: 0 | W34: 0 | X34: 0 | Y34: 0 | Z34: 0
A35: 0 | B35: 0 | C35: 0 | D35: 0 | E35: 0 | F35: 0 | G35: 0 | H35: 0 | I35: 0 | J35: =SUM(B35:I35) -> 0 | U35: 0 | V35: 0 | W35: 0 | X35: 0 | Y35: 0 | Z35: 0
A36: 0 | B36: 0 | C36: 0 | D36: 0 | E36: 0 | F36: 0 | G36: 0 | H36: 0 | I36: 0 | J36: =SUM(B36:I36) -> 0 | U36: 0 | V36: 0 | W36: 0 | X36: 0 | Y36: 0 | Z36: 0
A37: 0 | B37: 0 | C37: 0 | D37: 0 | E37: 0 | F37: 0 | G37: 0 | H37: 0 | I37: 0 | J37: =SUM(B37:I37) -> 0 | U37: 0 | V37: 0 | W37: 0 | X37: 0 | Y37: 0 | Z37: 0
A38: 0 | B38: 0 | C38: 0 | D38: 0 | E38: 0 | F38: 0 | G38: 0 | H38: 0 | I38: 0 | J38: =SUM(B38:I38) -> 0 | U38: 0 | V38: 0 | W38: 0 | X38: 0 | Y38: 0 | Z38: 0
A39: 0 | B39: 0 | C39: 0 | D39: 0 | E39: 0 | F39: 0 | G39: 0 | H39: 0 | I39: 0 | J39: =SUM(B39:I39) -> 0 | U39: 0 | V39: 0 | W39: 0 | X39: 0 | Y39: 0 | Z39: 0
A40: 0 | B40: 0 | C40: 0 | D40: 0 | E40: 0 | F40: 0 | G40: 0 | H40: 0 | I40: 0 | J40: =SUM(B40:I40) -> 0 | U40: 0 | V40: 0 | W40: 0 | X40: 0 | Y40: 0 | Z40: 0
A41: 0 | B41: 0 | C41: 0 | D41: 0 | E41: 0 | F41: 0 | G41: 0 | H41: 0 | I41: 0 | J41: =SUM(B41:I41) -> 0 | U41: 0 | V41: 0 | W41: 0 | X41: 0 | Y41: 0 | Z41: 0
A42: 0 | B42: 0 | C42: 0 | D42: 0 | E42: 0 | F42: 0 | G42: 0 | H42: 0 | I42: 0 | J42: =SUM(B42:I42) -> 0 | U42: 0 | V42: 0 | W42: 0 | X42: 0 | Y42: 0 | Z42: 0
A43: 0 | B43: 0 | C43: 0 | D43: 0 | E43: 0 | F43: 0 | G43: 0 | H43: 0 | I43: 0 | J43: =SUM(B43:I43) -> 0 | U43: 0 | V43: 0 | W43: 0 | X43: 0 | Y43: 0 | Z43: 0
A44: 0 | B44: 0 | C44: 0 | D44: 0 | E44: 0 | F44: 0 | G44: 0 | H44: 0 | I44: 0 | J44: =SUM(B44:I44) -> 0 | U44: 0 | V44: 0 | W44: 0 | X44: 0 | Y44: 0 | Z44: 0
A45: 0 | B45: 0 | C45: 0 | D45: 0 | E45: 0 | F45: 0 | G45: 0 | H45: 0 | I45: 0 | J45: =SUM(B45:I45) -> 0 | U45: 0 | V45: 0 | W45: 0 | X45: 0 | Y45: 0 | Z45: 0
... A52: 0 | B52: 0 | C52: 0 | D52: 0 | E52: 0 | F52: 0 | G52: 0 | H52: 0 | I52: 0 | J52: =SUM(B52:I52) -> 0 | U52: 0 | V52: 0 | W52: 0 | X52: 0 | Y52: 0 | Z52: 0
A53: 0 | I53: 0 | J53: =SUM(B53:I53) -> 0 | W53: 0 | X53: 0 | Y53: 0 | Z53: 0
A54: 0 | I54: 0 | J54: =SUM(B54:I54) -> 0 | W54: 0 | X54: 0 | Y54: 0 | Z54: 0
A55: Subtotal (kg) | B55: =SUM(B18:B54) -> 0 | C55: =SUM(C18:C54) -> 0 | D55: =SUM(D18:D54) -> 0 | E55: =SUM(E18:E54) -> 0 | F55: =SUM(F18:F54) -> 0 | G55: =SUM(G18:G54) -> 0 | H55: =SUM(H18:H54) -> 0 | I55: =SUM(I18:I54) -> 0
A56: Barras (12m) | B56: =(B55/0.157)/12+1 -> 1 | C56: =(C55/0.245)/12+1 -> 1 | D56: =(D55/0.395)/12+1 -> 1 | E56: =(E55/0.62)/12+1 -> 1 | F56: =(F55/0.98)/12+1 -> 1 | G56: =(G55/1.578)/12+1 -> 1 | H56: =(H55/2.47)/12+1 -> 1 | I56: =(I55/3.853)/12+1 -> 1
A57: Total | J57: =SUM(J18:J54) -> 0 | L57: =SUM(L30:L32) -> 0 | M57: =SUM(M30:M32) -> 0 | N57: =SUM(N30:N32) -> 0 | O57: =SUM(O30:O32) -> 0 | P57: =SUM(P30:P32) -> 0 | Q57: =SUM(Q30:Q32) -> 0 | R57: =SUM(R30:R32) -> 0 | U57: =SUM(U18:U54) -> 0 | V57: =SUM(V18:V54) -> 0 | W57: =SUM(W18:W55) -> 0 | X57: =SUM(X18:X55) -> 0 | Y57: =SUM(Y18:Y55) -> 0 | Z57: =SUM(Z18:Z55) -> 0

Sheet Arquitetura
A1: DADOS
A2: Titulo | B2: QUANTITATIVO
A3: Obra
A4: Cliente
A5: Cidade
A6: Endereço
A7: Descrição
A9: QUANTITATIVOS
A10: Item | B10: Descrição | C10: Unid. | D10: Quantidade
A12: 1. | B12: GERAL COBERTURA
A13: 1.1. | B13: 03.PAV 03
A14: 1.1.1 | C14: m²
A15: 1.1.2 | B15: Basic Roof:_DTR_CB_TELHA METALICA | C15: m² | D15: 104.18
A16: 1.2. | B16: 19.PAV DE COBERTURA
A17: 1.2.1 | C17: m²
A18: 1.2.2 | B18: Basic Roof:_DTR_CB_TELHA METALICA | C18: m² | D18: 25.81
A19: 2. | B19: GERAL CORRIMAO
A20: 2.1. | B20: 01.PAV 01 TERREO | F20: DESCRIÇÃO | G20: TOTAL
A21: 2.1.1 | B21: Railing:GENÉRICO | C21: m | D21: 11.34 | F21: Railing:GENÉRICO | G21: =SUMIF($B$20:$B$77,F21,$D$20:$D$77) -> 128.14
A22: 2.1.2 | B22: Railing:PARACICLO | C22: m | D22: 2.31 | F22: Railing:PARACICLO | G22: =SUMIF($B$20:$B$77,F22,$D$20:$D$77) -> 2.31
A23: 2.2. | B23: -01.SUBSOLO 01 | F23: Railing:_DTR_GC_GUARDA CORPO_TELA | G23: =SUMIF($B$20:$B$77,F23,$D$20:$D$77) -> 578.55
A24: 2.2.1 | B24: Railing:GENÉRICO | C24: m | D24: 5.84
A25: 2.3. | B25: 02.PAV 02
A26: 2.3.1 | B26: Railing:GENÉRICO | C26: m | D26: 5.84
A27: 2.4. | B27: -02.SUBSOLO 02
A28: 2.4.1 | B28: Railing:GENÉRICO | C28: m | D28: 5.84
A29: 2.5. | B29: 03.PAV 03
A30: 2.5.1 | B30: Railing:GENÉRICO | C30: m | D30: 5.84
A31: 2.6. | B31: 04.PAV 04
A32: 2.6.1 | B32: Railing:_DTR_GC_GUARDA CORPO_TELA | C32: m | D32: 38.57
A33: 2.6.2 | B33: Railing:GENÉRICO | C33: m | D33: 5.84
A34: 2.7. | B34: 05.PAV 05
A35: 2.7.1 | B35: Railing:_DTR_GC_GUARDA CORPO_TELA | C35: m | D35: 38.57
A36: 2.7.2 | B36: Railing:GENÉRICO | C36: m | D36: 5.84
A37: 2.8. | B37: 06.PAV 06
A38: 2.8.1 | B38: Railing:_DTR_GC_GUARDA CORPO_TELA | C38: m | D38: 38.57
A39: 2.8.2 | B39: Railing:GENÉRICO | C39: m | D39: 5.84
A40: 2.9. | B40: 07.PAV 07
A41: 2.9.1 | B41: Railing:_DTR_GC_GUARDA CORPO_TELA | C41: m | D41: 38.57
A42: 2.9.2 | B42: Railing:GENÉRICO | C42: m | D42: 5.84
A43: 2.10. | B43: 08.PAV 08
A44: 2.10.1 | B44: Railing:_DTR_GC_GUARDA CORPO_TELA | C44: m | D44: 38.57
A45: 2.10.2 | B45: Railing:GENÉRICO | C45: m | D45: 5.84
A46: 2.11. | B46: 09.PAV 09
A47: 2.11.1 | B47: Railing:_DTR_GC_GUARDA CORPO_TELA | C47: m | D47: 38.57
A48: 2.11.2 | B48: Railing:GENÉRICO | C48: m | D48: 5.84
A49: 2.12. | B49: 10.PAV 10
A50: 2.12.1 | B50: Railing:_DTR_GC_GUARDA CORPO_TELA | C50: m | D50: 38.57
A51: 2.12.2 | B51: Railing:GENÉRICO | C51: m | D51: 5.84
A52: 2.13. | B52: 11.PAV 11
A53: 2.13.1 | B53: Railing:_DTR_GC_GUARDA CORPO_TELA | C53: m | D53: 38.57
A54: 2.13.2 | B54: Railing:GENÉRICO | C54: m | D54: 5.84
A55: 2.14. | B55: 12.PAV 12
A56: 2.14.1 | B56: Railing:_DTR_GC_GUARDA CORPO_TELA | C56: m | D56: 38.57
A57: 2.14.2 | B57: Railing:GENÉRICO | C57: m | D57: 5.84
A58: 2.15. | B58: 13.PAV 13 (U.M.)
A59: 2.15.1 | B59: Railing:_DTR_GC_GUARDA CORPO_TELA | C59: m | D59: 38.57
A60: 2.15.2 | B60: Railing:GENÉRICO | C60: m | D60: 5.84
A61: 2.16. | B61: 14.PAV 14 (ADI)
A62: 2.16.1 | B62: Railing:_DTR_GC_GUARDA CORPO_TELA | C62: m | D62: 38.57
A63: 2.16.2 | B63: Railing:GENÉRICO | C63: m | D63: 5.84
A64: 2.17. | B64: 15.PAV 15 (ADI)
A65: 2.17.1 | B65: Railing:_DTR_GC_GUARDA CORPO_TELA | C65: m | D65: 38.57
A66: 2.17.2 | B66: Railing:GENÉRICO | C66: m | D66: 5.84
A67: 2.18. | B67: 16.PAV 16 (ADI)
A68: 2.18.1 | B68: Railing:_DTR_GC_GUARDA CORPO_TELA | C68: m | D68: 38.57
A69: 2.18.2 | B69: Railing:GENÉRICO | C69: m | D69: 5.84
A70: 2.19. | B70: 17.PAV 17 (HBR)
A71: 2.19.1 | B71: Railing:_DTR_GC_GUARDA CORPO_TELA | C71: m | D71: 38.57
A72: 2.19.2 | B72: Railing:GENÉRICO | C72: m | D72: 5.84
A73: 2.20. | B73: 18.PAV 18 (HBR)
A74: 2.20.1 | B74: Railing:_DTR_GC_GUARDA CORPO_TELA | C74: m | D74: 38.57
A75: 2.20.2 | B75: Railing:GENÉRICO | C75: m | D75: 5.84
A76: 2.21. | B76: 19.PAV DE COBERTURA
A77: 2.21.1 | B77: Railing:GENÉRICO | C77: m | D77: 5.84
A78: 3. | B78: GERAL ESCADAS
A79: 3.1. | B79: 01.PAV 01 TERREO
A80: 3.1.1 | B80: Cast-In-Place Stair:_DTR_EC_MACICA | C80: m²
A81: 3.2. | B81: -01.SUBSOLO 01
A82: 3.2.1 | B82: Cast-In-Place Stair:_DTR_EC_MACICA | C82: m²
A83: 3.3. | B83: 02.PAV 02
A84: 3.3.1 | B84: Cast-In-Place Stair:_DTR_EC_MACICA | C84: m²
A85: 3.4. | B85: -02.SUBSOLO 02
A86: 3.4.1 | B86: Cast-In-Place Stair:_DTR_EC_MACICA | C86: m²
A87: 3.5. | B87: 03.PAV 03
A88: 3.5.1 | B88: Cast-In-Place Stair:_DTR_EC_MACICA | C88: m²
A89: 3.6. | B89: 04.PAV 04
A90: 3.6.1 | B90: Cast-In-Place Stair:_DTR_EC_MACICA | C90: m²
A91: 3.7. | B91: 05.PAV 05
A92: 3.7.1 | B92: Cast-In-Place Stair:_DTR_EC_MACICA | C92: m²
A93: 3.8. | B93: 06.PAV 06
A94: 3.8.1 | B94: Cast-In-Place Stair:_DTR_EC_MACICA | C94: m²
A95: 3.9. | B95: 07.PAV 07
A96: 3.9.1 | B96: Cast-In-Place Stair:_DTR_EC_MACICA | C96: m²
A97: 3.10. | B97: 08.PAV 08
A98: 3.10.1 | B98: Cast-In-Place Stair:_DTR_EC_MACICA | C98: m²
A99: 3.11. | B99: 09.PAV 09
A100: 3.11.1 | B100: Cast-In-Place Stair:_DTR_EC_MACICA | C100: m²
A101: 3.12. | B101: 10.PAV 10
A102: 3.12.1 | B102: Cast-In-Place Stair:_DTR_EC_MACICA | C102: m²
...

Sheet Louças e metais
C1: Projeto | D1: ='Obra '!D1 -> PARKSIDE RIO BRANCO
C2: Empresa | D2: ='Obra '!D2 -> PARKSIDE
C3: Origem
C4: Revisão
A5: LOUÇAS E METAIS
A6: AMBIENTE | B6: DESCRIÇÃO | C6: UNIDADE | D6: QUANTIDADE | E6: REPETIÇÃO | F6: TOTAL
A7: SUBSOLOS
A8: Garagem | B8: Torneira de Jardim | C8: un | D8: 1 | E8: 2 | F8: =E8*D8 -> 2
A9: TERREO
A10: Lavabo PCD - Sala comercial | B10: Vaso sanitário deca branco PNE | C10: un | D10: 1 | E10: 1 | F10: =E10*D10 -> 1
A11: Lavabo PCD - Sala comercial | B11: Lavatório PNE de canto | C11: un | D11: 1 | E11: 1 | F11: =E11*D11 -> 1
A12: Lavabo PCD - Sala comercial | B12: Torneira banheiro PNE | C12: un | D12: 1 | E12: 1 | F12: =E12*D12 -> 1
A13: Lavabo PCD - Sala comercial | B13: Acabamento metálico para registro de gaveta | C13: un | D13: 1 | E13: 1 | F13: =E13*D13 -> 1
A14: Lavabo PCD - Sala comercial | B14: Barra de apoio PNE | C14: un | D14: 2 | E14: 1 | F14: =E14*D14 -> 2
A15: Lavabo PCD - Sala comercial | B15: Engate/ rabicho flexível inóx 1/2"x40mm | C15: un | D15: 2 | E15: 1 | F15: =E15*D15 -> 2
A16: Lavabo PCD - Sala comercial | B16: Sifão ajustável multiuso | C16: un | D16: 1 | E16: 1 | F16: =E16*D16 -> 1
A17: WC | B17: Vaso sanitário deca branco PNE | C17: un | D17: 1 | E17: 1 | F17: =E17*D17 -> 1
A18: WC | B18: Lavatório PNE de canto | C18: un | D18: 1 | E18: 1 | F18: =E18*D18 -> 1
A19: WC | B19: Torneira banheiro PNE | C19: un | D19: 1 | E19: 1 | F19: =E19*D19 -> 1
A20: WC | B20: Acabamento metálico para registro de gaveta | C20: un | D20: 1 | E20: 1 | F20: =E20*D20 -> 1
A21: WC | B21: Barra de apoio PNE | C21: un | D21: 3 | E21: 1 | F21: =E21*D21 -> 3
... A42: Garagem | B42: Torneira de Jardim | C42: un | D42: 1 | E42: 1 | F42: =E42*D42 -> 1
A43: PAV 02
A44: Lavabo PCD - Sala comercial | B44: Vaso sanitário deca branco PNE | C44: un | D44: 1 | E44: 3 | F44: =E44*D44 -> 3
A45: Lavabo PCD - Sala comercial | B45: Lavatório PNE de canto | C45: un | D45: 1 | E45: 3 | F45: =E45*D45 -> 3
A46: Lavabo PCD - Sala comercial | B46: Torneira banheiro PNE | C46: un | D46: 1 | E46: 3 | F46: =E46*D46 -> 3
A47: Lavabo PCD - Sala comercial | B47: Acabamento metálico para registro de gaveta | C47: un | D47: 1 | E47: 3 | F47: =E47*D47 -> 3
A48: Lavabo PCD - Sala comercial | B48: Barra de apoio PNE | C48: un | D48: 2 | E48: 3 | F48: =E48*D48 -> 6
A49: Lavabo PCD - Sala comercial | B49: Engate/ rabicho flexível inóx 1/2"x40mm | C49: un | D49: 2 | E49: 3 | F49: =E49*D49 -> 6
A50: Lavabo PCD - Sala comercial | B50: Sifão ajustável multiuso | C50: un | D50: 1 | E50: 3 | F50: =E50*D50 -> 3
A51: GARDENS
A52: BWC | B52: Vaso sanitário deca branco | C52: un | D52: 1 | E52: =11 -> 11 | F52: =E52*D52 -> 11
A53: BWC | B53: Engate/ rabicho flexível inóx 1/2"x40mm | C53: un | D53: 2 | E53: =11 -> 11 | F53: =E53*D53 -> 22
A54: BWC | B54: Acabamento metálico para registro de gaveta | C54: un | D54: 2 | E54: =11 -> 11 | F54: =E54*D54 -> 22
A55: BWC | B55: Cuba de embutir banheiro | C55: un | D55: 1 | E55: =11 -> 11 | F55: =E55*D55 -> 11
A56: BWC | B56: Ducha | C56: un | D56: 1 | E56: =11 -> 11 | F56: =E56*D56 -> 11
A57: BWC | B57: Torneira banheiro | C57: un | D57: 1 | E57: =11 -> 11 | F57: =E57*D57 -> 11
A58: BWC | B58: Monocomando | C58: un | D58: 1 | E58: =11 -> 11 | F58: =E58*D58 -> 11
A59: BWC | B59: Acessórios para banheiro | C59: un | D59: 1 | E59: =11 -> 11 | F59: =E59*D59 -> 11
A60: BWC | B60: Sifão ajustável multiuso | C60: un | D60: 1 | E60: =11 -> 11 | F60: =E60*D60 -> 11
A61: COZINHA | B61: Acabamento metálico para registro de gaveta | C61: un | D61: 1 | E61: 10 | F61: =E61*D61 -> 10
A62: COZINHA | B62: Engate/ rabicho flexível inóx 1/2"x40mm | C62: un | D62: 1 | E62: 10 | F62: =E62*D62 -> 10
A63: COZINHA | B63: Sifão ajustável multiuso | C63: un | D63: 1 | E63: 10 | F63: =E63*D63 -> 10
A64: COZINHA | B64: Torneira de cozinha | C64: un | D64: 1 | E64: 10 | F64: =E64*D64 -> 10
A65: COZINHA | B65: Cuba de emutir cozinha | C65: un | D65: 1 | E65: 10 | F65: =E65*D65 -> 10
A66: TIPO (x15)
A67: BWC | B67: Vaso sanitário deca branco | C67: un | D67: 1 | E67: =11*15 -> 165 | F67: =E67*D67 -> 165
A68: BWC | B68: Engate/ rabicho flexível inóx 1/2"x40mm | C68: un | D68: 2 | E68: =11*15 -> 165 | F68: =E68*D68 -> 330
A69: BWC | B69: Acabamento metálico para registro de gaveta | C69: un | D69: 2 | E69: =11*15 -> 165 | F69: =E69*D69 -> 330
A70: BWC | B70: Cuba de embutir banheiro | C70: un | D70: 1 | E70: =11*15 -> 165 | F70: =E70*D70 -> 165
A71: BWC | B71: Ducha | C71: un | D71: 1 | E71: =11*15 -> 165 | F71: =E71*D71 -> 165
A72: BWC | B72: Torneira banheiro | C72: un | D72: 1 | E72: =11*15 -> 165 | F72: =E72*D72 -> 165
A73: BWC | B73: Monocomando | C73: un | D73: 1 | E73: =11*15 -> 165 | F73: =E73*D73 -> 165
A74: BWC | B74: Acessórios para banheiro | C74: un | D74: 1 | E74: =11*15 -> 165 | F74: =E74*D74 -> 165
A75: BWC | B75: Sifão ajustável multiuso | C75: un | D75: 1 | E75: =11*15 -> 165 | F75: =E75*D75 -> 165
A76: COZINHA | B76: Acabamento metálico para registro de gaveta | C76: un | D76: 1 | E76: =10*15 -> 150 | F76: =E76*D76 -> 150
A77: COZINHA | B77: Engate/ rabicho flexível inóx 1/2"x40mm | C77: un | D77: 1 | E77: =10*15 -> 150 | F77: =E77*D77 -> 150
A78: COZINHA | B78: Sifão ajustável multiuso | C78: un | D78: 1 | E78: =10*15 -> 150 | F78: =E78*D78 -> 150
A79: COZINHA | B79: Torneira de cozinha | C79: un | D79: 1 | E79: =10*15 -> 150 | F79: =E79*D79 -> 150
A80: COZINHA | B80: Cuba de emutir cozinha | C80: un | D80: 1 | E80: =10*15 -> 150 | F80: =E80*D80 -> 150
A81: COBERTURA
A82: Lavabo | B82: Acabamento metálico para registro de gaveta | C82: un | D82: 1 | E82: 1 | F82: =E82*D82 -> 1
A83: Lavabo | B83: Cuba de embutir | C83: un | D83: 1 | E83: 1 | F83: =E83*D83 -> 1
A84: Lavabo | B84: Engate/ rabicho flexível inóx 1/2"x40mm | C84: un | D84: 2 | E84: 1 | F84: =E84*D84 -> 2
A85: Lavabo | B85: Sifão ajustável multiuso | C85: un | D85: 1 | E85: 1 | F85: =E85*D85 -> 1
A86: Lavabo | B86: Vaso sanitário deca branco | C86: un | D86: 1 | E86: 1 | F86: =E86*D86 -> 1
A87: Lavabo | B87: Torneira de banheiro | C87: un | D87: 1 | E87: 1 | F87: =E87*D87 -> 1
A88: BWC Sauna | B88: Vaso sanitário deca branco | C88: un | D88: 1 | E88: 1 | F88: =E88*D88 -> 1
A89: BWC Sauna | B89: Engate/ rabicho flexível inóx 1/2"x40mm | C89: un | D89: 2 | E89: 1 | F89: =E89*D89 -> 2
A90: BWC Sauna | B90: Acabamento metálico para registro de gaveta | C90: un | D90: 2 | E90: 1 | F90: =E90*D90 -> 2
A91: BWC Sauna | B91: Cuba de embutir banheiro | C91: un | D91: 1 | E91: 1 | F91: =E91*D91 -> 1
A92: BWC Sauna | B92: Ducha | C92: un | D92: 1 | E92: 1 | F92: =E92*D92 -> 1
A93: BWC Sauna | B93: Torneira banheiro | C93: un | D93: 1 | E93: 1 | F93: =E93*D93 -> 1
... A102: áre externa | B102: Torneira de Jardim | C102: un | D102: 1 | E102: 1 | F102: =E102*D102 -> 1
B103: TOTAL | F103: =SUM(F8:F102) -> 2832
A106: TIPO | B106: DESCRIÇÃO | C106: UNIDADE | D106: QUANTIDADE | E106: CUSTO UNITÁRIO | F106: CUSTO TOTAL
A107: LOUÇAS | B107: Cuba de cozinha | C107: un | D107: =SUMIF($B$8:$B$102,B107,$F$8:$F$102) -> 0 | F107: =E107*D107 -> 0
B108: Cuba de embutir | C108: un | D108: =SUMIF($B$8:$B$102,B108,$F$8:$F$102) -> 1 | F108: =E108*D108 -> 0
B109: Cuba de embutir banheiro | C109: un | D109: =SUMIF($B$8:$B$102,B109,$F$8:$F$102) -> 178 | F109: =E109*D109 -> 0
B110: Lavatório PNE de canto | C110: un | D110: =SUMIF($B$8:$B$102,B110,$F$8:$F$102) -> 5 | F110: =E110*D110 -> 0
B111: Vaso sanitário deca branco | C111: un | D111: =SUMIF($B$8:$B$102,B111,$F$8:$F$102) -> 179 | F111: =E111*D111 -> 0
B112: Vaso sanitário deca branco PNE | C112: un | D112: =SUMIF($B$8:$B$102,B112,$F$8:$F$102) -> 5 | F112: =E112*D112 -> 0
B113: Cuba de emutir cozinha | C113: un | D113: =SUMIF($B$8:$B$102,B113,$F$8:$F$102) -> 162 | F113: =E113*D113 -> 0
B114: Tanque inox | C114: un | D114: =SUMIF($B$8:$B$102,B114,$F$8:$F$102) -> 2 | F114: =E114*D114 -> 0
B115: TOTAL | F115: =SUM(F107:F112) -> 0
A116: METAIS | B116: Acabamento metálico para registro de gaveta | C116: un | D116: =SUMIF($B$8:$B$102,B116,$F$8:$F$102) -> 525 | F116: =E116*D116 -> 0
B117: Barra de apoio PNE | C117: un | D117: =SUMIF($B$8:$B$102,B117,$F$8:$F$102) -> 11 | F117: =E117*D117 -> 0
B118: Engate/ rabicho flexível inóx 1/2"x40mm | C118: un | D118: =SUMIF($B$8:$B$102,B118,$F$8:$F$102) -> 530 | F118: =E118*D118 -> 0
B119: Sifão ajustável multiuso | C119: un | D119: =SUMIF($B$8:$B$102,B119,$F$8:$F$102) -> 348 | F119: =E119*D119 -> 0
B120: Torneira de banheiro | C120: un | D120: =SUMIF($B$8:$B$102,B120,$F$8:$F$102) -> 1 | F120: =E120*D120 -> 0
B121: Torneira de Jardim | C121: un | D121: =SUMIF($B$8:$B$102,B121,$F$8:$F$102) -> 4 | F121: =E121*D121 -> 0
B122: Torneira de tanque | C122: un | D122: =SUMIF($B$8:$B$102,B122,$F$8:$F$102) -> 2 | F122: =E122*D122 -> 0
B123: Torneira banheiro PNE | C123: un | D123: =SUMIF($B$8:$B$102,B123,$F$8:$F$102) -> 5 | F123: =E123*D123 -> 0
B124: Ducha | C124: un | D124: =SUMIF($B$8:$B$102,B124,$F$8:$F$102) -> 178 | F124: =E124*D124 -> 0
B125: Monocomando | C125: un | D125: =SUMIF($B$8:$B$102,B125,$F$8:$F$102) -> 178 | F125: =E125*D125 -> 0
B126: Acessórios para banheiro | C126: un | D126: =SUMIF($B$8:$B$102,B126,$F$8:$F$102) -> 178 | F126: =E126*D126 -> 0
B127: Torneira de cozinha | C127: un | D127: =SUMIF($B$8:$B$102,B127,$F$8:$F$102) -> 162 | F127: =E127*D127 -> 0
B128: Torneira banheiro | C128: un | D128: =SUMIF($B$8:$B$102,B128,$F$8:$F$102) -> 178 | F128: =E128*D128 -> 0
B129: TOTAL | F129: =SUM(F116:F124) -> 0
A130: BANCADA | B130: Bancada em granito | C130: m2 | D130: =SUMIF($B$10:$B$102,B130,$F$10:$F$102) -> 0 | E130: 835 | F130: =E130*D130 -> 0
...

Sheet Mobiliário
B1: Obra | C1: ='Obra '!D1 -> PARKSIDE RIO BRANCO
B2: Empresa | C2: ='Obra '!D2 -> PARKSIDE
B3: Revisão | C3: ='Obra '!D3 -> R00 -
B4: LEVANTAMENTO MOBILIÁRIOS E EQUIPAMENTOS DE LAZER
B6: TOTAL COMUNS: | C6: =SUMPRODUCT($E$14:$E$161,$G$14:$G$161) -> 885352.93
B7: TOTAL PRiVATIVAS: | C7: =SUMPRODUCT($E$162:$E$220,$G$162:$G$220,F162:F220) -> 8882190.4
B8: ÁREA COMUM: | C8: =SUMIFS($E$13:$E$161,$D$13:$D$161,"Área: ") -> 691.65
B9: ÁREA PRIVATIVA: | C9: 5303.81
B10: CUSTO COMUM/ M2 | C10: =C6/C8 -> 1280.0592
B11: CUSTO PRIVATIVA/ M2 | C11: =C7/C9 -> 1674.6811
B13: Pavimento | C13: Ambiente | D13: Descrição | E13: Quantidade (un) | F13: Repetição | G13: Preço Unitário | H13: Preço Total | I13: Observações
B14: Subsolos | H14: =SUM(H15:H21)/2 -> 14276
B15: =B14 -> Subsolos | C15: Bicicletario | D15: Área: | E15: =27*3 -> 81 | H15: =SUM(H16:H17) -> 8460
B16: =B15 -> Subsolos | C16: =C15 -> Bicicletario | D16: Acabamentos Especiais | E16: =E15 -> 81 | F16: 1 | G16: 60 | H16: =E16*G16 -> 4860 | I16: COMPLEMENTOS
B17: =B13 -> Pavimento | C17: =C16 -> Bicicletario | D17: Iluminação | E17: =ROUNDUP(E15/10,0) -> 9 | F17: 1 | G17: 400 | H17: =E17*G17 -> 3600 | I17: LÂMPADAS E LUMINÁRIAS
B18: =B16 -> Subsolos | C18: Circulação | D18: Área: | E18: =12*2 -> 24 | H18: =SUM(H19:H21) -> 5816
B19: =B15 -> Subsolos | C19: =C18 -> Circulação | D19: Iluminação | E19: =ROUNDUP(E18/10,0) -> 3 | F19: 1 | G19: 400 | H19: =E19*G19 -> 1200 | I19: LÂMPADAS E LUMINÁRIAS
B20: =B16 -> Subsolos | C20: =C19 -> Circulação | D20: Capa de elevador | E20: 2 | F20: 1 | G20: 980 | H20: =E20*G20 -> 1960 | I20: COMPLEMENTOS
B21: =B18 -> Subsolos | C21: =C20 -> Circulação | D21: Carrinhos de super mercado | E21: 4 | F21: 1 | G21: 664 | H21: =E21*G21 -> 2656 | I21: COMPLEMENTOS
B22: Térreo | H22: =SUM(H23:H91)/2 -> 306496.91
B23: =B22 -> Térreo | C23: Bicicletario | D23: Área: | E23: =5.27+27.4+7.06 -> 39.73 | H23: =SUM(H24:H25) -> 3983.8
B24: =B23 -> Térreo | C24: =C23 -> Bicicletario | D24: Acabamentos Especiais | E24: =E23 -> 39.73 | F24: 1 | G24: 60 | H24: =E24*G24 -> 2383.8 | I24: COMPLEMENTOS
B25: =B21 -> Subsolos | C25: =C24 -> Bicicletario | D25: Iluminação | E25: =ROUNDUP(E23/10,0) -> 4 | F25: 1 | G25: 400 | H25: =E25*G25 -> 1600 | I25: LÂMPADAS E LUMINÁRIAS
B26: =B20 -> Subsolos | C26: Lixeira | D26: Área: | E26: ='PISO E TETO'!D27 -> 12.77 | H26: =SUM(H27:H28) -> 4130.88
B27: =B19 -> Subsolos | C27: =C26 -> Lixeira | D27: Contêiner de Lixo Gruplast em Plástico 240 Litros Preto Com Pedal | E27: 2 | F27: 1 | G27: 399.89 | H27: =E27*G27 -> 799.78 | I27: COMPLEMENTOS
B28: =B20 -> Subsolos | C28: =C27 -> Lixeira | D28: Carro Coletor 120 Litros Cinza com Pedal | E28: 10 | F28: 1 | G28: 333.11 | H28: =E28*G28 -> 3331.1 | I28: COMPLEMENTOS
B29: =B24 -> Térreo | C29: Circulação | D29: Área: | E29: =12*2 -> 24 | H29: =H30 -> 1200
B30: =B23 -> Térreo | C30: =C29 -> Circulação | D30: Iluminação | E30: =ROUNDUP(E29/10,0) -> 3 | F30: 1 | G30: 400 | H30: =E30*G30 -> 1200 | I30: LÂMPADAS E LUMINÁRIAS
B31: =B22 -> Térreo | C31: Hall de Entrada | D31: Área: | E31: 55.57 | H31: =SUM(H32:H38) -> 64812.77
B32: =B31 -> Térreo | C32: =C31 -> Hall de Entrada | D32: Acabamentos Especiais | E32: =E31 -> 55.57 | F32: 1 | G32: 450 | H32: =E32*G32 -> 25006.5 | I32: COMPLEMENTOS
B33: =B32 -> Térreo | C33: =C32 -> Hall de Entrada | D33: Cortina Bali Off White 2,80x2,30m 2 Folhas Inspire | E33: 2 | F33: 1 | G33: 644.9 | H33: =E33*G33*F33 -> 1289.8 | I33: COMPLEMENTOS
B34: =B32 -> Térreo | C34: =C32 -> Hall de Entrada | D34: Marcenaria | E34: 1 | F34: 1 | G34: =E31*1100*0.2 -> 12225.4 | H34: =E34*G34 -> 12225.4 | I34: MARCENARIA
B35: =B34 -> Térreo | C35: =C34 -> Hall de Entrada | D35: Sofá Curvo Heart | E35: 1 | F35: 1 | G35: 4595.62 | H35: =E35*G35 -> 4595.62 | I35: COMPLEMENTOS
B36: =B35 -> Térreo | C36: =C35 -> Hall de Entrada | D36: Tapete Estonado TNG02 2,40X3,00 Grafite | E36: 1 | F36: 1 | G36: 2202.95 | H36: =E36*G36 -> 2202.95 | I36: COMPLEMENTOS
