Workbook

Sheet CAPA
A1: Obra | B1: ACÁCIAS FLOWE'S HOSP.
A2: Empresa | B2: Construtora ALL Empreendimentos
A3: Revisão | B3: R00
A4: Data | B4: 45463
A5: ORÇAMENTO EXECUTIVO
A26: ="ORÇAMENTO EXECUTIVO - "&UPPER(B1) -> ORÇAMENTO EXECUTIVO - ACÁCIAS FLOWE'S HOSP.
A28: =B2 -> Construtora ALL Empreendimentos
A55: ="Itajaí, "&TEXT(B4,"mmmm")&" de "&TEXT(B4,"aaa") -> Itajaí, junho de 2024

Sheet Resumo_Parede
G1: Parede | H1: Massa | I1: =E8+E18+E19+E23+E33+E34+E38+E48+E49+E53+E64+E65+E69+E77+E78 -> 274173.64 | J1: Massa | K1: =I1+I3 -> 399462.75
G2: Parede | H2: Acabamento | I2: =E6-I1 -> 123061.53 | J2: Acabamento | K2: =I2+I4 -> 444162.31
G3: Piso | H3: Massa | I3: =E82+E94+E95+E101+E117+E125+E139+E146+E161+E168+E174 -> 125289.1
G4: Piso | H4: Acabamento | I4: =E80-I3 -> 321100.77
A5: Descrição | B5: Un. | C5: Quant. Serviço | D5: Preço Comp. | E5: Preço total / Verba
A6: =Orçamento!$S$1210 -> REVESTIMENTOS INTERNOS DE PAREDE | B6: =Orçamento!$T$1210 | C6: =Orçamento!$U$1210 | D6: =Orçamento!$Y$1210 | E6: =Orçamento!$Z$1210 -> 397235.17
A7: =Orçamento!$S$1211 -> REVESTIMENTOS INTERNOS DE PAREDE - 1º PAVIMENTO - SUBSOLO | B7: =Orçamento!$T$1211 | C7: =Orçamento!$U$1211 | D7: =Orçamento!$Y$1211 | E7: =Orçamento!$Z$1211 -> 36323.973
A8: =Orçamento!$S$1212 -> Reboco | B8: =Orçamento!$T$1212 | C8: =Orçamento!$U$1212 | D8: =Orçamento!$Y$1212 | E8: =Orçamento!$Z$1212 -> 11199.67
A9: =Orçamento!$S$1213 -> Chapisco aplicado em estruturas de concreto, com desempenadeira dentada, de argamassa industrializada | B9: =Orçamento!$T$1213 -> M2 | C9: =Orçamento!$U$1213 -> 223.73 | D9: =Orçamento!$Y$1213 -> 5.502 | E9: =Orçamento!$Z$1213 -> 1230.9625
A10: =Orçamento!$S$1215 -> Chapisco aplicado em alvenarias internas, com colher de pedreiro, de argamassa estabilizada | B10: =Orçamento!$T$1215 -> M2 | C10: =Orçamento!$U$1215 -> 203.57 | D10: =Orçamento!$Y$1215 -> 7.93 | E10: =Orçamento!$Z$1215 -> 1614.3101
A11: =Orçamento!$S$1217 -> Massa unica para reboco interno em argamassa estabilizada, espessura de 20mm, com execucao de taliscas | B11: =Orçamento!$T$1217 -> M2 | C11: =Orçamento!$U$1217 -> 427.3 | D11: =Orçamento!$Y$1217 -> 19.008 | E11: =Orçamento!$Z$1217 -> 8122.1184
A12: =Orçamento!$S$1219 -> Estucamento de estrutura de concreto em pilares e vigas | B12: =Orçamento!$T$1219 -> M2 | C12: =Orçamento!$U$1219 -> 57.36 | D12: =Orçamento!$Y$1219 -> 4.0495 | E12: =Orçamento!$Z$1219 -> 232.27932
A13: =Orçamento!$S$1224 -> Acabamentos Cerâmicos e Porcelanatos | B13: =Orçamento!$T$1224 | C13: =Orçamento!$U$1224 | D13: =Orçamento!$Y$1224 | E13: =Orçamento!$Z$1224 -> 2161.6075
A14: =Orçamento!$S$1225 -> Revestimento em Cerâmica 60x60cm interno | B14: =Orçamento!$T$1225 -> M2 | C14: =Orçamento!$U$1225 -> 32.5 | D14: =Orçamento!$Y$1225 -> 66.511 | E14: =Orçamento!$Z$1225 -> 2161.6075
A15: =Orçamento!$S$1230 -> Peitoris | B15: =Orçamento!$T$1230 | C15: =Orçamento!$U$1230 | D15: =Orçamento!$Y$1230 | E15: =Orçamento!$Z$1230 -> 261.61178
A16: =Orçamento!$S$1231 -> Peitoril em granito, acabamento polido, espessura 2cm | B16: =Orçamento!$T$1231 -> M | C16: =Orçamento!$U$1231 -> 2.7 | D16: =Orçamento!$Y$1231 -> 96.89325 | E16: =Orçamento!$Z$1231 -> 261.61178
A17: =Orçamento!$S$1234 -> Mão de Obra | B17: =Orçamento!$T$1234 | C17: =Orçamento!$U$1234 | D17: =Orçamento!$Y$1234 | E17: =Orçamento!$Z$1234 -> 22701.083
A18: =Orçamento!$S$1235 -> Mao de obra para reboco interno, incluindo chapisco | B18: =Orçamento!$T$1235 -> M2 | C18: =Orçamento!$U$1235 -> 427.3 | D18: =Orçamento!$Y$1235 -> 40.637259 | E18: =Orçamento!$Z$1235 -> 17364.301
A19: =Orçamento!$S$1237 -> Mao de obra para estucamento de estrutura em concreto | B19: =Orçamento!$T$1237 -> M2 | C19: =Orçamento!$U$1237 -> 57.36 | D19: =Orçamento!$Y$1237 -> 50.894747 | E19: =Orçamento!$Z$1237 -> 2919.3227
A20: =Orçamento!$S$1239 -> Mao de obra para colocacao e rejuntamento de Azulejo Cerâmico | B20: =Orçamento!$T$1239 -> M2 | C20: =Orçamento!$U$1239 -> 32.5 | D20: =Orçamento!$Y$1239 -> 73.51107 | E20: =Orçamento!$Z$1239 -> 2389.1098
A21: =Orçamento!$S$1241 -> Mao de obra para colocacao de peitoril | B21: =Orçamento!$T$1241 -> M | C21: =Orçamento!$U$1241 -> 2.7 | D21: =Orçamento!$Y$1241 -> 10.5 | E21: =Orçamento!$Z$1241 -> 28.35
A22: =Orçamento!$S$1243 -> REVESTIMENTOS INTERNOS DE PAREDE - 2º PAVIMENTO - TÉRREO | B22: =Orçamento!$T$1243 | C22: =Orçamento!$U$1243 | D22: =Orçamento!$Y$1243 | E22: =Orçamento!$Z$1243 -> 39428.127
A23: =Orçamento!$S$1244 -> Reboco | B23: =Orçamento!$T$1244 | C23: =Orçamento!$U$1244 | D23: =Orçamento!$Y$1244 | E23: =Orçamento!$Z$1244 -> 9707.3525
A24: =Orçamento!$S$1245 -> Chapisco aplicado em estruturas de concreto, com desempenadeira dentada, de argamassa industrializada | B24: =Orçamento!$T$1245 -> M2 | C24: =Orçamento!$U$1245 -> 67.914 | D24: =Orçamento!$Y$1245 -> 5.502 | E24: =Orçamento!$Z$1245 -> 373.66283
A25: =Orçamento!$S$1247 -> Chapisco aplicado em alvenarias internas, com colher de pedreiro, de argamassa estabilizada | B25: =Orçamento!$T$1247 -> M2 | C25: =Orçamento!$U$1247 -> 203.57 | D25: =Orçamento!$Y$1247 -> 7.93 | E25: =Orçamento!$Z$1247 -> 1614.3101
A26: =Orçamento!$S$1249 -> Massa unica para reboco interno em argamassa estabilizada, espessura de 20mm, com execucao de taliscas | B26: =Orçamento!$T$1249 -> M2 | C26: =Orçamento!$U$1249 -> 401.634 | D26: =Orçamento!$Y$1249 -> 19.008 | E26: =Orçamento!$Z$1249 -> 7634.2591
A27: =Orçamento!$S$1251 -> Estucamento de estrutura de concreto em pilares e vigas | B27: =Orçamento!$T$1251 -> M2 | C27: =Orçamento!$U$1251 -> 21.02 | D27: =Orçamento!$Y$1251 -> 4.0495 | E27: =Orçamento!$Z$1251 -> 85.12049
A28: =Orçamento!$S$1256 -> Acabamentos Cerâmicos e Porcelanatos | B28: =Orçamento!$T$1256 | C28: =Orçamento!$U$1256 | D28: =Orçamento!$Y$1256 | E28: =Orçamento!$Z$1256 -> 4616.5285
A29: =Orçamento!$S$1257 -> Revestimento em Cerâmica 60x60cm interno | B29: =Orçamento!$T$1257 -> M2 | C29: =Orçamento!$U$1257 -> 69.41 | D29: =Orçamento!$Y$1257 -> 66.511 | E29: =Orçamento!$Z$1257 -> 4616.5285
A30: =Orçamento!$S$1262 -> Peitoris | B30: =Orçamento!$T$1262 | C30: =Orçamento!$U$1262 | D30: =Orçamento!$Y$1262 | E30: =Orçamento!$Z$1262 -> 2355.4749
A31: =Orçamento!$S$1263 -> Peitoril em granito, acabamento polido, espessura 2cm | B31: =Orçamento!$T$1263 -> M | C31: =Orçamento!$U$1263 -> 24.31 | D31: =Orçamento!$Y$1263 -> 96.89325 | E31: =Orçamento!$Z$1263 -> 2355.4749
A32: =Orçamento!$S$1266 -> Mão de Obra | B32: =Orçamento!$T$1266 | C32: =Orçamento!$U$1266 | D32: =Orçamento!$Y$1266 | E32: =Orçamento!$Z$1266 -> 22748.771
A33: =Orçamento!$S$1267 -> Mao de obra para reboco interno, incluindo chapisco | B33: =Orçamento!$T$1267 -> M2 | C33: =Orçamento!$U$1267 -> 401.634 | D33: =Orçamento!$Y$1267 -> 40.637259 | E33: =Orçamento!$Z$1267 -> 16321.305
A34: =Orçamento!$S$1269 -> Mao de obra para estucamento de estrutura em concreto | B34: =Orçamento!$T$1269 -> M2 | C34: =Orçamento!$U$1269 -> 21.02 | D34: =Orçamento!$Y$1269 -> 50.894747 | E34: =Orçamento!$Z$1269 -> 1069.8076
A35: =Orçamento!$S$1271 -> Mao de obra para colocacao e rejuntamento de Azulejo Cerâmico | B35: =Orçamento!$T$1271 -> M2 | C35: =Orçamento!$U$1271 -> 69.41 | D35: =Orçamento!$Y$1271 -> 73.51107 | E35: =Orçamento!$Z$1271 -> 5102.4033
A36: =Orçamento!$S$1273 -> Mao de obra para colocacao de peitoril | B36: =Orçamento!$T$1273 -> M | C36: =Orçamento!$U$1273 -> 24.31 | D36: =Orçamento!$Y$1273 -> 10.5 | E36: =Orçamento!$Z$1273 -> 255.255
A37: =Orçamento!$S$1275 -> REVESTIMENTOS INTERNOS DE PAREDE - 3º ao 7º PAVIMENTO - TIPO | B37: =Orçamento!$T$1275 | C37: =Orçamento!$U$1275 | D37: =Orçamento!$Y$1275 | E37: =Orçamento!$Z$1275 -> 266698.24
A38: =Orçamento!$S$1276 -> Reboco | B38: =Orçamento!$T$1276 | C38: =Orçamento!$U$1276 | D38: =Orçamento!$Y$1276 | E38: =Orçamento!$Z$1276 -> 67943.162
A39: =Orçamento!$S$1277 -> Chapisco aplicado em estruturas de concreto, com desempenadeira dentada, de argamassa industrializada | B39: =Orçamento!$T$1277 -> M2 | C39: =Orçamento!$U$1277 -> 388.91 | D39: =Orçamento!$Y$1277 -> 5.502 | E39: =Orçamento!$Z$1277 -> 2139.7828
A40: =Orçamento!$S$1279 -> Chapisco aplicado em alvenarias internas, com colher de pedreiro, de argamassa estabilizada | B40: =Orçamento!$T$1279 -> M2 | C40: =Orçamento!$U$1279 -> 2144.56 | D40: =Orçamento!$Y$1279 -> 7.93 | E40: =Orçamento!$Z$1279 -> 17006.361
A41: =Orçamento!$S$1281 -> Massa unica para reboco interno em argamassa estabilizada, espessura de 20mm, com execucao de taliscas | B41: =Orçamento!$T$1281 -> M2 | C41: =Orçamento!$U$1281 -> 2533.48 | D41: =Orçamento!$Y$1281 -> 19.008 | E41: =Orçamento!$Z$1281 -> 48156.388
A42: =Orçamento!$S$1283 -> Estucamento de estrutura de concreto em pilares e vigas | B42: =Orçamento!$T$1283 -> M2 | C42: =Orçamento!$U$1283 -> 158.2 | D42: =Orçamento!$Y$1283 -> 4.0495 | E42: =Orçamento!$Z$1283 -> 640.6309
A43: =Orçamento!$S$1288 -> Acabamentos Cerâmicos e Porcelanatos | B43: =Orçamento!$T$1288 | C43: =Orçamento!$U$1288 | D43: =Orçamento!$Y$1288 | E43: =Orçamento!$Z$1288 -> 39222.202
A44: =Orçamento!$S$1289 -> Revestimento em Cerâmica 60x60cm interno | B44: =Orçamento!$T$1289 -> M2 | C44: =Orçamento!$U$1289 -> 589.71 | D44: =Orçamento!$Y$1289 -> 66.511 | E44: =Orçamento!$Z$1289 -> 39222.202
A45: =Orçamento!$S$1294 -> Peitoris | B45: =Orçamento!$T$1294 | C45: =Orçamento!$U$1294 | D45: =Orçamento!$Y$1294 | E45: =Orçamento!$Z$1294 -> 4671.2236
A46: =Orçamento!$S$1295 -> Peitoril em granito, acabamento polido, espessura 2cm | B46: =Orçamento!$T$1295 -> M | C46: =Orçamento!$U$1295 -> 48.21 | D46: =Orçamento!$Y$1295 -> 96.89325 | E46: =Orçamento!$Z$1295 -> 4671.2236
A47: =Orçamento!$S$1298 -> Mão de Obra | B47: =Orçamento!$T$1298 | C47: =Orçamento!$U$1298 | D47: =Orçamento!$Y$1298 | E47: =Orçamento!$Z$1298 -> 154861.65
A48: =Orçamento!$S$1299 -> Mao de obra para reboco interno, incluindo chapisco | B48: =Orçamento!$T$1299 -> M2 | C48: =Orçamento!$U$1299 -> 2533.48 | D48: =Orçamento!$Y$1299 -> 40.637259 | E48: =Orçamento!$Z$1299 -> 102953.68
A49: =Orçamento!$S$1301 -> Mao de obra para estucamento de estrutura em concreto | B49: =Orçamento!$T$1301 -> M2 | C49: =Orçamento!$U$1301 -> 158.2 | D49: =Orçamento!$Y$1301 -> 50.894747 | E49: =Orçamento!$Z$1301 -> 8051.549
A50: =Orçamento!$S$1303 -> Mao de obra para colocacao e rejuntamento de Azulejo Cerâmico | B50: =Orçamento!$T$1303 -> M2 | C50: =Orçamento!$U$1303 -> 589.71 | D50: =Orçamento!$Y$1303 -> 73.51107 | E50: =Orçamento!$Z$1303 -> 43350.213
A51: =Orçamento!$S$1305 -> Mao de obra para colocacao de peitoril | B51: =Orçamento!$T$1305 -> M | C51: =Orçamento!$U$1305 -> 48.21 | D51: =Orçamento!$Y$1305 -> 10.5 | E51: =Orçamento!$Z$1305 -> 506.205
A52: =Orçamento!$S$1307 -> REVESTIMENTOS INTERNOS DE PAREDE - 8º PAVIMENTO - COBERTURA | B52: =Orçamento!$T$1307 | C52: =Orçamento!$U$1307 | D52: =Orçamento!$Y$1307 | E52: =Orçamento!$Z$1307 -> 34603.336
A53: =Orçamento!$S$1308 -> Reboco | B53: =Orçamento!$T$1308 | C53: =Orçamento!$U$1308 | D53: =Orçamento!$Y$1308 | E53: =Orçamento!$Z$1308 -> 7740.9269
A54: =Orçamento!$S$1309 -> Chapisco aplicado em estruturas de concreto, com desempenadeira dentada, de argamassa industrializada | B54: =Orçamento!$T$1309 -> M2 | C54: =Orçamento!$U$1309 -> 108.031 | D54: =Orçamento!$Y$1309 -> 5.502 | E54: =Orçamento!$Z$1309 -> 594.38656
A55: =Orçamento!$S$1311 -> Chapisco aplicado em alvenarias internas, com colher de pedreiro, de argamassa estabilizada | B55: =Orçamento!$T$1311 -> M2 | C55: =Orçamento!$U$1311 -> 203.57 | D55: =Orçamento!$Y$1311 -> 7.93 | E55: =Orçamento!$Z$1311 -> 1614.3101
A56: =Orçamento!$S$1313 -> Massa unica para reboco interno em argamassa estabilizada, espessura de 20mm, com execucao de taliscas | B56: =Orçamento!$T$1313 -> M2 | C56: =Orçamento!$U$1313 -> 283.591 | D56: =Orçamento!$Y$1313 -> 19.008 | E56: =Orçamento!$Z$1313 -> 5390.4977
A57: =Orçamento!$S$1315 -> Estucamento de estrutura de concreto em pilares e vigas | B57: =Orçamento!$T$1315 -> M2 | C57: =Orçamento!$U$1315 -> 35 | D57: =Orçamento!$Y$1315 -> 4.0495 | E57: =Orçamento!$Z$1315 -> 141.7325
A58: =Orçamento!$S$1320 -> Acabamentos Cerâmicos e Porcelanatos | B58: =Orçamento!$T$1320 | C58: =Orçamento!$U$1320 | D58: =Orçamento!$Y$1320 | E58: =Orçamento!$Z$1320 -> 7271.5742
A59: =Orçamento!$S$1321 -> Revestimento em Pastilhas para Piscina | B59: =Orçamento!$T$1321 -> M2 | C59: =Orçamento!$U$1321 -> 45.99 | D59: =Orçamento!$Y$1321 -> 134.1475 | E59: =Orçamento!$Z$1321 -> 6169.4435
A60: =Orçamento!$S$1327 -> Revestimento em Porcelanato 80x80cm interno | B60: =Orçamento!$T$1327 -> M | C60: =Orçamento!$U$1327 -> 13.14 | D60: =Orçamento!$Y$1327 -> 83.876 | E60: =Orçamento!$Z$1327 -> 1102.1306
A61: =Orçamento!$S$1332 -> Peitoris | B61: =Orçamento!$T$1332 | C61: =Orçamento!$U$1332 | D61: =Orçamento!$Y$1332 | E61: =Orçamento!$Z$1332 -> 1748.9232
A62: =Orçamento!$S$1333 -> Peitoril em granito, acabamento polido, espessura 2cm | B62: =Orçamento!$T$1333 -> M | C62: =Orçamento!$U$1333 -> 18.05 | D62: =Orçamento!$Y$1333 -> 96.89325 | E62: =Orçamento!$Z$1333 -> 1748.9232
A63: =Orçamento!$S$1336 -> Mão de Obra | B63: =Orçamento!$T$1336 | C63: =Orçamento!$U$1336 | D63: =Orçamento!$Y$1336 | E63: =Orçamento!$Z$1336 -> 17841.912
A64: =Orçamento!$S$1337 -> Mao de obra para reboco interno, incluindo chapisco | B64: =Orçamento!$T$1337 -> M2 | C64: =Orçamento!$U$1337 -> 283.591 | D64: =Orçamento!$Y$1337 -> 40.637259 | E64: =Orçamento!$Z$1337 -> 11524.361
A65: =Orçamento!$S$1339 -> Mao de obra para estucamento de estrutura em concreto | B65: =Orçamento!$T$1339 -> M2 | C65: =Orçamento!$U$1339 -> 35 | D65: =Orçamento!$Y$1339 -> 50.894747 | E65: =Orçamento!$Z$1339 -> 1781.3161
A66: =Orçamento!$S$1341 -> Mao de obra para colocacao e rejuntamento de Azulejo Cerâmico e Porcelanato | B66: =Orçamento!$T$1341 -> M2 | C66: =Orçamento!$U$1341 -> 59.13 | D66: =Orçamento!$Y$1341 -> 73.51107 | E66: =Orçamento!$Z$1341 -> 4346.7095
A67: =Orçamento!$S$1343 -> Mao de obra para colocacao de peitoril | B67: =Orçamento!$T$1343 -> M | C67: =Orçamento!$U$1343 -> 18.05 | D67: =Orçamento!$Y$1343 -> 10.5 | E67: =Orçamento!$Z$1343 -> 189.525
A68: =Orçamento!$S$1345 -> REVESTIMENTOS INTERNOS DE PAREDE - BARRILETE / CAIXA DÁGUA / CASA DE MÁQUINAS | B68: =Orçamento!$T$1345 | C68: =Orçamento!$U$1345 | D68: =Orçamento!$Y$1345 | E68: =Orçamento!$Z$1345 -> 20181.501
A69: =Orçamento!$S$1346 -> Reboco | B69: =Orçamento!$T$1346 | C69: =Orçamento!$U$1346 | D69: =Orçamento!$Y$1346 | E69: =Orçamento!$Z$1346 -> 5657.5292
A70: =Orçamento!$S$1347 -> Chapisco aplicado em estruturas de concreto, com desempenadeira dentada, de argamassa industrializada | B70: =Orçamento!$T$1347 -> M2 | C70: =Orçamento!$U$1347 -> 34.37 | D70: =Orçamento!$Y$1347 -> 5.502 | E70: =Orçamento!$Z$1347 -> 189.10374
A71: =Orçamento!$S$1349 -> Chapisco aplicado em alvenarias internas, com colher de pedreiro, de argamassa estabilizada | B71: =Orçamento!$T$1349 -> M2 | C71: =Orçamento!$U$1349 -> 203.57 | D71: =Orçamento!$Y$1349 -> 7.93 | E71: =Orçamento!$Z$1349 -> 1614.3101
A72: =Orçamento!$S$1351 -> Massa unica para reboco interno em argamassa estabilizada, espessura de 20mm, com execucao de taliscas | B72: =Orçamento!$T$1351 -> M2 | C72: =Orçamento!$U$1351 -> 194.19 | D72: =Orçamento!$Y$1351 -> 19.008 | E72: =Orçamento!$Z$1351 -> 3691.1635
A73: =Orçamento!$S$1353 -> Estucamento de estrutura de concreto em pilares e vigas | B73: =Orçamento!$T$1353 -> M2 | C73: =Orçamento!$U$1353 -> 40.24 | D73: =Orçamento!$Y$1353 -> 4.0495 | E73: =Orçamento!$Z$1353 -> 162.95188
A74: =Orçamento!$S$1358 -> Peitoris | B74: =Orçamento!$T$1358 | C74: =Orçamento!$U$1358 | D74: =Orçamento!$Y$1358 | E74: =Orçamento!$Z$1358 -> 4136.3728
A75: =Orçamento!$S$1359 -> Peitoril em granito, acabamento polido, espessura 2cm | B75: =Orçamento!$T$1359 -> M | C75: =Orçamento!$U$1359 -> 42.69 | D75: =Orçamento!$Y$1359 -> 96.89325 | E75: =Orçamento!$Z$1359 -> 4136.3728
A76: =Orçamento!$S$1362 -> Mão de Obra | B76: =Orçamento!$T$1362 | C76: =Orçamento!$U$1362 | D76: =Orçamento!$Y$1362 | E76: =Orçamento!$Z$1362 -> 10387.599
A77: =Orçamento!$S$1363 -> Mao de obra para reboco interno, incluindo chapisco | B77: =Orçamento!$T$1363 -> M2 | C77: =Orçamento!$U$1363 -> 194.19 | D77: =Orçamento!$Y$1363 -> 40.637259 | E77: =Orçamento!$Z$1363 -> 7891.3494
A78: =Orçamento!$S$1365 -> Mao de obra para estucamento de estrutura em concreto | B78: =Orçamento!$T$1365 -> M2 | C78: =Orçamento!$U$1365 -> 40.24 | D78: =Orçamento!$Y$1365 -> 50.894747 | E78: =Orçamento!$Z$1365 -> 2048.0046
A79: =Orçamento!$S$1367 -> Mao de obra para colocacao de peitoril | B79: =Orçamento!$T$1367 -> M | C79: =Orçamento!$U$1367 -> 42.69 | D79: =Orçamento!$Y$1367 -> 10.5 | E79: =Orçamento!$Z$1367 -> 448.245
A80: =Orçamento!$S$1456 -> PISOS E PAVIMENTAÇÕES | B80: =Orçamento!$T$1456 | C80: =Orçamento!$U$1456 | D80: =Orçamento!$Y$1456 | E80: =Orçamento!$Z$1456 -> 446389.88
A81: =Orçamento!$S$1457 -> PISOS E PAVIMENTAÇÕES - 1º PAVIMENTO - SUBSOLO | B81: =Orçamento!$T$1457 | C81: =Orçamento!$U$1457 | D81: =Orçamento!$Y$1457 | E81: =Orçamento!$Z$1457 -> 70005.62
A82: =Orçamento!$S$1458 -> Contrapiso | B82: =Orçamento!$T$1458 | C82: =Orçamento!$U$1458 | D82: =Orçamento!$Y$1458 | E82: =Orçamento!$Z$1458 -> 16491.192
A83: =Orçamento!$S$1459 -> Contrapiso comum em argamassa estabilizada, nao aderido, espessura 8cm | B83: =Orçamento!$T$1459 -> M2 | C83: =Orçamento!$U$1459 -> 342.74 | D83: =Orçamento!$Y$1459 -> 47.55 | E83: =Orçamento!$Z$1459 -> 16297.287
A84: =Orçamento!$S$1462 -> Piso cimentado com argamassa de cimento e areia traço 1:3, espessura 1,5cm | B84: =Orçamento!$T$1462 -> M2 | C84: =Orçamento!$U$1462 -> 30.24 | D84: =Orçamento!$Y$1462 -> 6.4122 | E84: =Orçamento!$Z$1462 -> 193.90493
A85: =Orçamento!$S$1465 -> Acabamentos em Piso | B85: =Orçamento!$T$1465 | C85: =Orçamento!$U$1465 | D85: =Orçamento!$Y$1465 | E85: =Orçamento!$Z$1465 -> 18261.932
A86: =Orçamento!$S$1466 -> Revestimento interno de piso Cerâmico placa 60x60cm - áreas Internos | B86: =Orçamento!$T$1466 -> M2 | C86: =Orçamento!$U$1466 -> 301.73 | D86: =Orçamento!$Y$1466 -> 58.695 | E86: =Orçamento!$Z$1466 -> 17710.042
A87: =Orçamento!$S$1471 -> Revestimento interno de piso porcelanato placa 80x80cm - áreas externas | B87: =Orçamento!$T$1471 -> M2 | C87: =Orçamento!$U$1471 -> 7.29 | D87: =Orçamento!$Y$1471 -> 75.705 | E87: =Orçamento!$Z$1471 -> 551.88945
A88: =Orçamento!$S$1477 -> Rodapés | B88: =Orçamento!$T$1477 | C88: =Orçamento!$U$1477 | D88: =Orçamento!$Y$1477 | E88: =Orçamento!$Z$1477 -> 1836.4198
A89: =Orçamento!$S$1478 -> Revestimento interno de Rodapé Cerâmico h=0,30cm | B89: =Orçamento!$T$1478 -> M | C89: =Orçamento!$U$1478 -> 100.43 | D89: =Orçamento!$Y$1478 -> 17.6085 | E89: =Orçamento!$Z$1478 -> 1768.4217
A90: =Orçamento!$S$1483 -> Revestimento interno de Rodapé Cerâmico h=0,07cm | B90: =Orçamento!$T$1483 -> M | C90: =Orçamento!$U$1483 -> 16.55 | D90: =Orçamento!$Y$1483 -> 4.10865 | E90: =Orçamento!$Z$1483 -> 67.998158
A91: =Orçamento!$S$1488 -> Soleiras | B91: =Orçamento!$T$1488 | C91: =Orçamento!$U$1488 | D91: =Orçamento!$Y$1488 | E91: =Orçamento!$Z$1488 -> 71.4285
A92: =Orçamento!$S$1489 -> Soleira em granito, acabamento polido, espessura 2cm | B92: =Orçamento!$T$1489 -> M2 | C92: =Orçamento!$U$1489 -> 0.11 | D92: =Orçamento!$Y$1489 -> 649.35 | E92: =Orçamento!$Z$1489 -> 71.4285
A93: =Orçamento!$S$1493 -> Mão de Obra | B93: =Orçamento!$T$1493 | C93: =Orçamento!$U$1493 | D93: =Orçamento!$Y$1493 | E93: =Orçamento!$Z$1493 -> 33344.648
A94: =Orçamento!$S$1494 -> Mao de obra para execucao de contrapiso comum e acústico | B94: =Orçamento!$T$1494 -> M2 | C94: =Orçamento!$U$1494 -> 342.74 | D94: =Orçamento!$Y$1494 -> 21.975618 | E94: =Orçamento!$Z$1494 -> 7531.9232
A95: =Orçamento!$S$1496 -> Mao de obra para execucao em piso cimentado | B95: =Orçamento!$T$1496 -> M2 | C95: =Orçamento!$U$1496 -> 30.24 | D95: =Orçamento!$Y$1496 -> 21.975618 | E95: =Orçamento!$Z$1496 -> 664.54268
A96: =Orçamento!$S$1498 -> Mao de obra para colocacao e rejuntamento de piso Cerâmico | B96: =Orçamento!$T$1498 -> M2 | C96: =Orçamento!$U$1498 -> 301.73 | D96: =Orçamento!$Y$1498 -> 73.51107 | E96: =Orçamento!$Z$1498 -> 22180.495
A97: =Orçamento!$S$1500 -> Mao de obra para colocacao e rejuntamento de piso porcelanato | B97: =Orçamento!$T$1500 -> M2 | C97: =Orçamento!$U$1500 -> 7.29 | D97: =Orçamento!$Y$1500 -> 73.51107 | E97: =Orçamento!$Z$1500 -> 535.8957
A98: =Orçamento!$S$1502 -> Mao de obra para colocacao de rodape cerâmico e porcelanato | B98: =Orçamento!$T$1502 -> M | C98: =Orçamento!$U$1502 -> 116.98 | D98: =Orçamento!$Y$1502 -> 20.778317 | E98: =Orçamento!$Z$1502 -> 2430.6475
A99: =Orçamento!$S$1504 -> Mao de obra para colocacao de soleiras em granito | B99: =Orçamento!$T$1504 -> M | C99: =Orçamento!$U$1504 -> 0.11 | D99: =Orçamento!$Y$1504 -> 10.4 | E99: =Orçamento!$Z$1504 -> 1.144
A100: =Orçamento!$S$1506 -> PISOS E PAVIMENTAÇÕES - TÉRREO - 2º PAVIMENTO - TÉRREO | B100: =Orçamento!$T$1506 | C100: =Orçamento!$U$1506 | D100: =Orçamento!$Y$1506 | E100: =Orçamento!$Z$1506 -> 80743.998
...

Sheet OBRA
A1: Obra | B1: =CAPA!B1 -> ACÁCIAS FLOWE'S HOSP.
A2: Empresa | B2: =CAPA!B2 -> Construtora ALL Empreendimentos
A3: Revisão | B3: =CAPA!B3 -> R00
A4: DADOS OBRA
A6: ARQUITETURA
B8: Descrição | C8: Unidade | D8: Quantidade
B9: ÁREA DO TERRENO | C9: M2 | D9: 460.03
B10: ÁREA CONSTRUÍDA | C10: M2 | D10: 1943.23
B11: NÚMERO DE APTOS | C11: UN | D11: =3+5*7 -> 38
B12: MESES DE OBRA | C12: MÊS | D12: 22
B13: NÚMERO DE PAVIMENTOS | C13: UN | D13: 8

Sheet Quadro de Áreas
B2: Empreendimento - Total | E2: R00 | G2: R01 | I2: R02 | K2: R03 | M2: R04
B3: Residencial | D3: Total | E3: 7433075.1 | G3: 7152374.4 | I3: =Resumo!E73 -> 6936553.5 | K3: 6954920.9 | M3: ='ABC Insumos'!$I$6 -> 6970627
D4: R$/und | E4: =E3/E23 -> 195607.24 | G4: 184693.28 | I4: =I3/I23 -> 182540.88 | K4: =K3/K23 -> 183024.23 | M4: =M3/M23 -> 183437.55
D5: R$/m2 - Total | E5: =E3/F13 -> 3963.4618 | G5: 3742.32 | I5: =I3/J13 -> 3698.7067 | K5: =K3/L13 -> 3708.5006 | M5: =M3/N13 -> 3716.8754
D6: R$/m2 - Privativo | E6: =E3/F9 -> 7816.9333 | G6: 7380.79 | I6: =I3/J9 -> 7294.7704 | K6: =K3/L9 -> 7314.0862 | M6: =M3/N9 -> 7330.6035
E7: 0 | F7: 0
B8: Áreas | E8: Real | F8: Equivalente | G8: Real | H8: Equivalente | I8: Real | J8: Equivalente | K8: Real | L8: Equivalente | M8: Real | N8: Equivalente
D9: (R1) - Total Privativa | E9: 1023.7465 | F9: 950.89402 | G9: 1023.7465 | H9: 950.89402 | I9: 1023.7465 | J9: 950.89402 | K9: 1023.7465 | L9: 950.89402 | M9: 1023.7465 | N9: 950.89402
D10: (R2) - Total Torre | E10: 1375.9826 | F10: 1226.6523 | G10: 1375.9826 | H10: 1226.6523 | I10: 1375.9826 | J10: 1226.6523 | K10: 1375.9826 | L10: 1226.6523 | M10: 1375.9826 | N10: 1226.6523
D11: (R6) - Total Residencial | E11: 2185.7979 | F11: 1875.3997 | G11: 2185.7979 | H11: 1875.3997 | I11: 0 | J11: 0 | K11: #REF! | L11: #REF! | M11: #REF! | N11: #REF!
D12: (C5) - Total Comercial | E12: 0 | F12: 0 | G12: 0 | H12: 0 | I12: 0 | J12: 0 | K12: #REF! | L12: #REF! | M12: #REF! | N12: #REF!
D13: (E1) - Total Empreendimento | E13: 2185.7979 | F13: 1875.3997 | G13: 2185.7979 | H13: 1875.3997 | I13: 2185.7979 | J13: 1875.3997 | K13: 2185.7979 | L13: 1875.3997 | M13: 2185.7979 | N13: 1875.3997
D14: Área Equivalente Torre - Média | E14: 32.280325 | G14: 32.280325 | I14: 32.280325 | K14: 32.280325 | M14: 32.280325
D15: Área Equivalente Residencial - Média | E15: 1875.3997 | G15: 49.352624 | I15: 0 | K15: #REF! | M15: #REF!
D16: Área Equivalente Comerciall - Média | E16: 0 | G16: 0 | I16: 0 | K16: #REF! | M16: #REF!
D17: Área Equivalente Total - Média | E17: 49.352624 | G17: 49.352624 | I17: 49.352624 | K17: 49.352624 | M17: 49.352624
D18: Área Privativa Unidades - Média | E18: 25.023527 | G18: 25.023527 | I18: 25.023527 | K18: 25.023527 | M18: 25.023527
B19: 0 | C19: 0 | D19: 0 | E19: 0 | F19: 0
B20: Unidades
D21: Nº Unidades Residencial | E21: 38 | G21: 38 | I21: 0 | K21: #REF! | M21: #REF!
D22: Nº Unidades Comercial | E22: 0 | G22: 0 | I22: 0 | K22: #REF! | M22: #REF!
D23: Total de Unidades | E23: 38 | G23: 38 | I23: 38 | K23: 38 | M23: 38
B24: 0 | C24: 0 | D24: 0 | E24: 0 | F24: 0 | G24: 0 | H24: 0 | I24: 0 | J24: 0
B25: Grau de Eficiência
D26: GE Emprendimento: ( E1 ÷ R1 ) | E26: 1.9722489 | G26: 1.9722489 | I26: 1.9722489 | K26: 1.9722489 | M26: 1.9722489
D27: GE Torre: ( R2 ÷ R1 ) | E27: 1.289999 | G27: 1.289999 | I27: 1.289999 | K27: 1.289999 | M27: 1.289999
D28: Total Construída ÷ Privativa Construída: ( R1 ÷ E1 ) | E28: 0.50703539 | G28: 0.50703539 | I28: 0.50703539 | K28: 0.50703539 | M28: 0.50703539
B29: 0 | C29: 0 | D29: 0 | I29: 0 | J29: 0

Sheet Resumo
A1: item | B1: ETAPA | C1: VALOR ORÇADO | D1: % | E1: VALOR / m²
A2: 01 | B2: GERENCIAMENTO TÉCNICO E ADMINISTRATIVO | C2: =Orçamento!$Z$12 -> 728402.37 | D2: =C2/C$19 -> 0.10449596 | E2: =C2/$G$2 -> 374.84105 | G2: 1943.23 | H2: m²
A3: 02 | B3: MOVIMENTAÇÃO DE TERRA | C3: =Orçamento!$Z$172 -> 145568.65 | D3: =C3/C$19 -> 0.020883149 | E3: =C3/$G$2 -> 74.910662
A4: 03 | B4: INFRAESTRUTURA | C4: =Orçamento!$Z$185+Orçamento!$Z$199 -> 502193.32 | D4: =C4/C$19 -> 0.072044211 | E4: =C4/$G$2 -> 258.43226
A5: 04 | B5: SUPRAESTRUTURA | C5: =Orçamento!$Z$234 -> 1352591 | D5: =C5/C$19 -> 0.1940415 | E5: =C5/$G$2 -> 696.05294
A6: 04 | B6: ALVENARIA | C6: =Orçamento!$Z$662 -> 261393.66 | D6: =C6/C$19 -> 0.037499304 | E6: =C6/$G$2 -> 134.51504
A7: 06 | B7: INSTALAÇÕES ELÉTRICAS, HIDRÁULICAS, GLP E PREVENTIVAS | C7: =Orçamento!$Z$973+Orçamento!$Z$1069+Orçamento!$Z$1135+Orçamento!$Z$1957 -> 641270.51 | D7: =C7/C$19 -> 0.091996102 | E7: =C7/$G$2 -> 330.00237
A8: 07 | B8: EQUIPAMENTOS E SISTEMAS ESPECIAIS | C8: =Orçamento!$Z$1160+Orçamento!$Z$1171+Orçamento!$Z$1191 -> 323614.15 | D8: =C8/C$19 -> 0.0464254 | E8: =C8/$G$2 -> 166.53415
A9: 08 | B9: IMPERMEABILIZAÇÃO | C9: =Orçamento!$Z$806 -> 175140.61 | D9: =C9/C$19 -> 0.025125517 | E9: =C9/$G$2 -> 90.128606
A10: 09 | B10: REVESTIMENTOS INTERNOS EM PAREDE | C10: =(Orçamento!$Z$1210) -> 397235.17 | D10: =C10/C$19 -> 0.056987008 | E10: =C10/$G$2 -> 204.42005
A11: 10 | B11: REVESTIMENTOS E ACABAMENTOS INTERNOS EM TETO | C11: =Orçamento!$Z$1369 -> 128940.66 | D11: =C11/C$19 -> 0.018497713 | E11: =C11/$G$2 -> 66.353781
A12: 11 | B12: PISOS E PAVIMENTAÇÕES | C12: =Orçamento!$Z$1456 -> 446389.88 | D12: =C12/C$19 -> 0.064038698 | E12: =C12/$G$2 -> 229.71541
A13: 12 | B13: PINTURA INTERNA | C13: =Orçamento!$Z$1726 -> 303208.12 | D13: =C13/C$19 -> 0.04349797 | E13: =C13/$G$2 -> 156.03306
A14: 13 | B14: ESQUADRIAS, VIDROS E FERRAGENS | C14: =Orçamento!$Z$1837 -> 578274.83 | D14: =C14/C$19 -> 0.082958796 | E14: =C14/$G$2 -> 297.58435
A15: 14 | B15: COBERTURA | C15: =Orçamento!$Z$2061 -> 38853.541 | D15: =C15/C$19 -> 0.0055738947 | E15: =C15/$G$2 -> 19.994309
A16: 15 | B16: REVESTIMENTOS E ACABAMENTOS DE FACHADA | C16: =Orçamento!$Z$2089 -> 365385.57 | D16: =C16/C$19 -> 0.052417891 | E16: =C16/$G$2 -> 188.03002
A17: 16 | B17: SERVIÇOS COMPLEMENTARES | C17: =Orçamento!$Z$2121 -> 442752.49 | D17: =C17/C$19 -> 0.063516881 | E17: =C17/$G$2 -> 227.84358
A18: 17 | B18: IMPREVISTOS E CONTINGENCIAS | C18: =Orçamento!$Z$2143 -> 139412.54 | D18: =C18/C$19 -> 0.02 | E18: =C18/$G$2 -> 71.742686
B19: TOTAL | C19: =SUM(C2:C18) -> 6970627 | D19: =SUM(D2:D18) -> 1 | E19: =SUM(E2:E18) -> 3587.1343
B20: CUB/ESTADO | C20: 2758.46 | D20: DATA BASE | E20: =+E19/C20 -> 1.3004119
A23: item | B23: ETAPA | C23: VALOR ORÇADO | D23: % | E23: VALOR / m²
A24: 01 | B24: GERENCIAMENTO TÉCNICO E ADMINISTRATIVO | C24: =Orçamento!$Z$12 -> 728402.37 | D24: =C24/C$42 -> 0.10449596 | E24: =C24/$G$2 -> 374.84105 | F24: SUPRAESTRUTURA | G24: =D27 -> 0.1940415
A25: 02 | B25: MOVIMENTAÇÃO DE TERRA | C25: =Orçamento!$Z$172 -> 145568.65 | D25: =C25/C$42 -> 0.020883149 | E25: =C25/$G$2 -> 74.910662 | F25: GERENCIAMENTO TÉCNICO E ADMINISTRATIVO | G25: =D24 -> 0.10449596
A26: 03 | B26: INFRAESTRUTURA | C26: =Orçamento!$Z$185+Orçamento!$Z$199 -> 502193.32 | D26: =C26/C$42 -> 0.072044211 | E26: =C26/$G$2 -> 258.43226 | F26: ESQUADRIAS, VIDROS E FERRAGENS | G26: =D36 -> 0.082958796
A27: 04 | B27: SUPRAESTRUTURA | C27: =Orçamento!$Z$234 -> 1352591 | D27: =C27/C$42 -> 0.1940415 | E27: =C27/$G$2 -> 696.05294 | F27: INSTALAÇÕES ELÉTRICAS, HIDRÁULICAS, GLP E PREVENTIVAS | G27: =D29 -> 0.079680478
A28: 04 | B28: ALVENARIA | C28: =Orçamento!$Z$662 -> 261393.66 | D28: =C28/C$42 -> 0.037499304 | E28: =C28/$G$2 -> 134.51504 | F28: INFRAESTRUTURA | G28: =D26 -> 0.072044211
A29: 06 | B29: INSTALAÇÕES ELÉTRICAS, HIDRÁULICAS, GLP E PREVENTIVAS | C29: =Orçamento!$Z$973+Orçamento!$Z$1069+Orçamento!$Z$1135 -> 555422.9 | D29: =C29/C$42 -> 0.079680478 | E29: =C29/$G$2 -> 285.82458 | F29: PISOS E PAVIMENTAÇÕES | G29: =D34 -> 0.064038698
A30: 07 | B30: EQUIPAMENTOS E SISTEMAS ESPECIAIS | C30: =Orçamento!$Z$1160+Orçamento!$Z$1171+Orçamento!$Z$1191 -> 323614.15 | D30: =C30/C$42 -> 0.0464254 | E30: =C30/$G$2 -> 166.53415
A31: 08 | B31: IMPERMEABILIZAÇÃO | C31: =Orçamento!$Z$806 -> 175140.61 | D31: =C31/C$42 -> 0.025125517 | E31: =C31/$G$2 -> 90.128606
A32: 09 | B32: REVESTIMENTOS INTERNOS EM PAREDE | C32: =(Orçamento!$Z$1210) -> 397235.17 | D32: =C32/C$42 -> 0.056987008 | E32: =C32/$G$2 -> 204.42005
A33: 10 | B33: REVESTIMENTOS E ACABAMENTOS INTERNOS EM TETO | C33: =Orçamento!$Z$1369 -> 128940.66 | D33: =C33/C$42 -> 0.018497713 | E33: =C33/$G$2 -> 66.353781
A34: 11 | B34: PISOS E PAVIMENTAÇÕES | C34: =Orçamento!$Z$1456 -> 446389.88 | D34: =C34/C$42 -> 0.064038698 | E34: =C34/$G$2 -> 229.71541
A35: 12 | B35: PINTURA INTERNA | C35: =Orçamento!$Z$1726 -> 303208.12 | D35: =C35/C$42 -> 0.04349797 | E35: =C35/$G$2 -> 156.03306
A36: 13 | B36: ESQUADRIAS, VIDROS E FERRAGENS | C36: =Orçamento!$Z$1837 -> 578274.83 | D36: =C36/C$42 -> 0.082958796 | E36: =C36/$G$2 -> 297.58435
A37: 14 | B37: LOUÇAS E METAIS | C37: =+Orçamento!$Z$1957 -> 85847.616 | D37: =C37/C$42 -> 0.012315623 | E37: =C37/$G$2 -> 44.177795
A38: 15 | B38: COBERTURA | C38: =Orçamento!$Z$2061 -> 38853.541 | D38: =C38/C$42 -> 0.0055738947 | E38: =C38/$G$2 -> 19.994309
A39: 16 | B39: REVESTIMENTOS E ACABAMENTOS DE FACHADA | C39: =Orçamento!$Z$2089 -> 365385.57 | D39: =C39/C$42 -> 0.052417891 | E39: =C39/$G$2 -> 188.03002
A40: 17 | B40: SERVIÇOS COMPLEMENTARES | C40: =Orçamento!$Z$2121 -> 442752.49 | D40: =C40/C$42 -> 0.063516881 | E40: =C40/$G$2 -> 227.84358
A41: 18 | B41: IMPREVISTOS E CONTINGENCIAS | C41: =Orçamento!$Z$2143 -> 139412.54 | D41: =C41/C$42 -> 0.02 | E41: =C41/$G$2 -> 71.742686
B42: TOTAL | C42: =SUM(C24:C41) -> 6970627 | D42: =SUM(D24:D41) -> 1 | E42: =SUM(E24:E41) -> 3587.1343
B43: CUB/SC | C43: 2758.46 | D43: DATA BASE | E43: =+E42/C43 -> 1.3004119
B46: Descrição | C46: R00 | D46: R01 | E46: R02 | F46: R03 | G46: R04 | H46: Difereça | I46: Observações
B47: =Orçamento!$S$12 -> GERENCIAMENTO TÉCNICO E ADMINISTRATIVO | C47: 1269673.5 | D47: 710402.37 | E47: 710402.37 | F47: 728402.37 | G47: =Orçamento!$Z$12 -> 728402.37 | H47: =G47-F47 -> 0
B48: =Orçamento!$S$13 -> GERENCIAMENTO TÉCNICO | C48: 452085.71 | D48: 206833.89 | E48: 206833.89 | F48: 206833.89 | G48: =Orçamento!$Z$13 -> 206833.89 | H48: =G48-F48 -> 0 | K48: =G48/$G$2 -> 106.43819
B49: =Orçamento!$S$73 -> GERENCIAMENTO ADMINISTRATIVO | C49: 817587.81 | D49: 503568.48 | E49: 503568.48 | F49: 521568.48 | G49: =Orçamento!$Z$73 -> 521568.48 | H49: =G49-F49 -> 0 | K49: =G49/$G$2 -> 268.40285
B50: =Orçamento!$S$171 -> GERENCIAMENTO EXECUTIVO | C50: 6163401.6 | D50: 6441972.1 | E50: 6226151.1 | F50: 6226518.5 | G50: =Orçamento!$Z$171 -> 6242224.7 | H50: =G50-F50 -> 15706.174
B51: =Orçamento!$S$172 -> MOVIMENTAÇÃO DE TERRA | C51: 40912.878 | D51: 145568.65 | E51: 145568.65 | F51: 145568.65 | G51: =Orçamento!$Z$172 -> 145568.65 | H51: =G51-F51 -> 0 | K51: =G51/$G$2 -> 74.910662
B52: =Orçamento!$S$185 -> INFRAESTRUTURA | C52: 235826.98 | D52: 348459.09 | E52: 348459.09 | F52: 348459.09 | G52: =Orçamento!$Z$185 -> 348459.09 | H52: =G52-F52 -> 0 | K52: =G52/$G$2 -> 179.31953
B53: =Orçamento!$S$199 -> CONTENÇÕES | C53: 120929.91 | D53: 156045.96 | E53: 153734.23 | F53: 153734.23 | G53: =Orçamento!$Z$199 -> 153734.23 | H53: =G53-F53 -> 0 | K53: =G53/$G$2 -> 79.11273
B54: =Orçamento!$S$234 -> SUPRAESTRUTURA | C54: 1486970.7 | D54: 1395555.6 | E54: 1352591 | F54: 1352591 | G54: =Orçamento!$Z$234 -> 1352591 | H54: =G54-F54 -> 0 | K54: =G54/$G$2 -> 696.05294
B55: =Orçamento!$S$662 -> ALVENARIA | VEDAÇÕES | DIVISÓRIAS | C55: 260075.2 | D55: 261393.66 | E55: 261393.66 | F55: 261393.66 | G55: =Orçamento!$Z$662 -> 261393.66 | H55: =G55-F55 -> 0 | K55: =G55/$G$2 -> 134.51504
B56: =Orçamento!$S$806 -> IMPERMEABILIZAÇÃO E TRATAMENTOS | C56: 132506.86 | D56: 175140.61 | E56: 175140.61 | F56: 175140.61 | G56: =Orçamento!$Z$806 -> 175140.61 | H56: =G56-F56 -> 0 | K56: =G56/$G$2 -> 90.128606
B57: =Orçamento!$S$973 -> SISTEMAS E INSTALAÇÕES ELÉTRICAS | C57: 340562.95 | D57: 340562.95 | E57: 340562.95 | F57: 340562.95 | G57: =Orçamento!$Z$973 -> 340562.95 | H57: =G57-F57 -> 0 | K57: =G57/$G$2 -> 175.25612
B58: =Orçamento!$S$1069 -> SISTEMAS E INSTALAÇÕES HIDROSSANITÁRIAS | DRENAGEM | C58: 175995.35 | D58: 175995.35 | E58: 175995.35 | F58: 175995.35 | G58: =Orçamento!$Z$1069 -> 175995.35 | H58: =G58-F58 -> 0 | K58: =G58/$G$2 -> 90.568461
B59: =Orçamento!$S$1135 -> INSTALAÇÕES PREVENTIVAS | C59: 38864.6 | D59: 38864.6 | E59: 38864.6 | F59: 38864.6 | G59: =Orçamento!$Z$1135 -> 38864.6 | H59: =G59-F59 -> 0 | K59: =G59/$G$2 -> 20
B60: =Orçamento!$S$1160 -> INSTALAÇÕES DE COMUNICAÇÕES | C60: 24852.07 | D60: 17079.15 | E60: 17079.15 | F60: 17079.15 | G60: =Orçamento!$Z$1160 -> 17079.15 | H60: =G60-F60 -> 0 | K60: =G60/$G$2 -> 8.7890522
B61: =Orçamento!$S$1171 -> EQUIPAMENTOS E SISTEMAS ESPECIAIS | C61: 253095 | D61: 253095 | E61: 253095 | F61: 253095 | G61: =Orçamento!$Z$1171 -> 253095 | H61: =G61-F61 -> 0 | K61: =G61/$G$2 -> 130.24449
B62: =Orçamento!$S$1191 -> CLIMATIZAÇÃO | C62: 53440 | D62: 53440 | E62: 53440 | F62: 53440 | G62: =Orçamento!$Z$1191 -> 53440 | H62: =G62-F62 -> 0 | K62: =G62/$G$2 -> 27.500605
B63: =Orçamento!$S$1210 -> REVESTIMENTOS INTERNOS DE PAREDE | C63: 377413.3 | D63: 381843.12 | E63: 381843.12 | F63: 381843.12 | G63: =Orçamento!$Z$1210 -> 397235.17 | H63: =G63-F63 -> 15392.051 | I63: Ajustes Quantitativos Chapisco | K63: =G63/$G$2 -> 204.42005
B64: =Orçamento!$S$1369 -> REVESTIMENTOS E ACABAMENTOS INTERNOS EM TETO | C64: 103795.89 | D64: 128940.66 | E64: 128940.66 | F64: 128940.66 | G64: =Orçamento!$Z$1369 -> 128940.66 | H64: =G64-F64 -> 0 | K64: =G64/$G$2 -> 66.353781
B65: =Orçamento!$S$1456 -> PISOS E PAVIMENTAÇÕES | C65: 436046.39 | D65: 446389.88 | E65: 446389.88 | F65: 446389.88 | G65: =Orçamento!$Z$1456 -> 446389.88 | H65: =G65-F65 -> 0 | K65: =G65/$G$2 -> 229.71541
B66: =Orçamento!$S$1726 -> SISTEMAS DE PINTURA INTERNA | C66: 268226.5 | D66: 303208.12 | E66: 303208.12 | F66: 303208.12 | G66: =Orçamento!$Z$1726 -> 303208.12 | H66: =G66-F66 -> 0 | K66: =G66/$G$2 -> 156.03306
B67: =Orçamento!$S$1837 -> ESQUADRIAS - VIDROS E FERRAGENS | C67: 782141.66 | D67: 744502.92 | E67: 578274.83 | F67: 578274.83 | G67: =Orçamento!$Z$1837 -> 578274.83 | H67: =G67-F67 -> 0 | K67: =G67/$G$2 -> 297.58435
B68: =Orçamento!$S$1957 -> LOUÇAS E METAIS | C68: 79571.616 | D68: 85847.616 | E68: 85847.616 | F68: 85847.616 | G68: =Orçamento!$Z$1957 -> 85847.616 | H68: =G68-F68 -> 0 | K68: =G68/$G$2 -> 44.177795
B69: =Orçamento!$S$2061 -> COBERTURA | C69: 37703.541 | D69: 38853.541 | E69: 38853.541 | F69: 38853.541 | G69: =Orçamento!$Z$2061 -> 38853.541 | H69: =G69-F69 -> 0 | K69: =G69/$G$2 -> 19.994309
B70: =Orçamento!$S$2089 -> REVESTIMENTOS E ACABAMENTOS DE FACHADA | C70: 346056.22 | D70: 365385.57 | E70: 365385.57 | F70: 365385.57 | G70: =Orçamento!$Z$2089 -> 365385.57 | H70: =G70-F70 -> 0 | K70: =G70/$G$2 -> 188.03002
B71: =Orçamento!$S$2121 -> SERVIÇOS COMPLEMENTARES E FINAIS | C71: 419752.49 | D71: 442752.49 | E71: 442752.49 | F71: 442752.49 | G71: =Orçamento!$Z$2121 -> 442752.49 | H71: =G71-F71 -> 0 | K71: =G71/$G$2 -> 227.84358
B72: =Orçamento!$S$2143 -> IMPREVISTOS E CONTINGÊNCIAS | C72: 148661.5 | D72: 143047.49 | E72: 138731.07 | F72: 139098.42 | G72: =Orçamento!$Z$2143 -> 139412.54 | H72: =G72-F72 -> 314.12348 | K72: =G72/$G$2 -> 71.742686
B73: TOTAL | C73: 7433075.1 | D73: =SUM(D47:D72)/2 -> 7152374.4 | E73: 6936553.5 | F73: 6954920.9 | G73: =SUM(G47:G72)/2 -> 6970627 | H73: =SUM(H47:H72)/2 -> 15706.174
H75: =H73/F73 -> 0.0022582822

Sheet Orçamento
A2: ="ORÇAMENTO EXECUTIVO - "&UPPER(S5) -> ORÇAMENTO EXECUTIVO - ACÁCIAS FLOWE'S HOSP.
A4: Empresa: | S4: =CAPA!B2 -> Construtora ALL Empreendimentos | AE4: Cliente | AF4: =S4 -> Construtora ALL Empreendimentos
A5: Obra: | S5: =CAPA!B1 -> ACÁCIAS FLOWE'S HOSP. | AE5: Prazo | AF5: =OBRA!D12 -> 22
A6: Revisão | S6: =CAPA!B3 -> R00 | AE6: Área Construída | AF6: =OBRA!D10 -> 1943.23
A7: Data: | S7: =CAPA!B4 -> 45463 | AE7: Apto | AF7: =OBRA!D11 -> 38
A9: ORÇAMENTO DETALHADO | AE9: =UPPER(AF4) -> CONSTRUTORA ALL EMPREENDIMENTOS
B10: Nivel | C10: Repetições | D10: Código | E10: Coluna1 | F10: Nº Unidade Construtiva | G10: Unidade Construtiva | H10: Nº Célula Construtiva | I10: Célula Construtiva | J10: Nº Etapa | K10: Etapa | L10: Nº Subetapa | M10: Subetapa | N10: Nº Serviço | O10: Serviço | P10: Insumo Apoio | Q10: Serviço Apoio | R10: Base Quant. Serviço | S10: Descrição | T10: Un. | U10: Quant. Serviço | V10: Coef. | W10: Preço Unit. Insumo | X10: Quant. orçada | Y10: Preço Comp. | Z10: Preço total / Verba | AA10: Considerações Quant. | AB10: Ref. Preço | AC10: Perc. (%) | AE10: Índice | AF10: Parâmetro
F11: 0 | H11: 0 | J11: 0 | L11: 0 | N11: 0
B12: Unidade Construtiva | C12: =IF(B12="INSUMO",COUNTIFS(B:B,"INSUMO",S:S,S12),IF(B12="SERVIÇO",COUNTIFS(B:B,"SERVIÇO",S:S,S12),"")) | D12: =IF(B12="Unidade Construtiva",TEXT(F12,"00"),IF(B12="Célula Construtiva",TEXT(H12,"00"),IF(B12="Etapa",CONCATENATE(TEXT(H12,"00"),".",TEXT(J12,"000")),IF(B12="Subetapa",CONCATENATE(TEXT(H12,"00"),".",TEXT(J12,"000"),".",TEXT(L12,"000")),IF(B12="Serviço",CONCATENATE(TEXT(H12,"00"),".",TEXT(J12,"000"),".",TEXT(L12,"000"),".",TEXT(N12,"000")),""))))) -> 01 | E12: =IF(B12="*","",IFERROR(IF(B12="SERVIÇO",D12,OFFSET(E12,-1,0)),"")) -> 0 | F12: =IF($B12="UNIDADE CONSTRUTIVA",OFFSET(F12,-1,0)+1,LARGE(F$10:F11,1)) -> 1 | G12: =IF(B12="*","",IF(B12="UNIDADE CONSTRUTIVA",S12,OFFSET(G12,-1,0))) -> GERENCIAMENTO TÉCNICO E ADMINISTRATIVO | H12: =IF(B12="UNIDADE CONSTRUTIVA",0,IF(B12="CÉLULA CONSTRUTIVA",OFFSET(H12,-1,0)+1,OFFSET(H12,-1,0))) -> 0 | I12: =IF(B12="*","",IF(B12="CÉLULA CONSTRUTIVA",S12,OFFSET(I12,-1,0))) -> 0 | J12: =IF(B12="CÉLULA CONSTRUTIVA",0,IF(B12="ETAPA",OFFSET(J12,-1,0)+1,OFFSET(J12,-1,0))) -> 0 | K12: =IF(B12="*","",IF(B12="ETAPA",S12,OFFSET(K12,-1,0))) -> 0 | L12: =IF(B12="ETAPA",0,IF(B12="SUBETAPA",OFFSET(L12,-1,0)+1,OFFSET(L12,-1,0))) -> 0 | M12: =IF(B12="*","",IF(B12="SUBETAPA",S12,OFFSET(M12,-1,0))) -> 0 | N12: =IF(B12="Subetapa",0,IF(B12="serviço",OFFSET(N12,-1,0)+1,OFFSET(N12,-1,0))) -> 0 | O12: =IF(B12="*","",IF(B12="SERVIÇO",S12,OFFSET(O12,-1,0))) -> 0 | P12: =IF(S12="","",IF(Orçamento!$B12="INSUMO",S12,"")) | Q12: =IF(S12="","",IF(Orçamento!$B12="Serviço",S12,"")) | R12: =IF(B12="serviço",U12,OFFSET(R12,-1,0)) -> 0 | S12: GERENCIAMENTO TÉCNICO E ADMINISTRATIVO | U12: =IF($B12="insumo",R12,"") | W12: =IFERROR(IF(B12="INSUMO",_xlfn.XLOOKUP(S12,Insumos!A:A,Insumos!C:C),""),"Inserir Preço") | X12: =IF(B12="Complemento do insumo",V12,IF(R12="","",IF(B12="serviço",R12,IF(OR(B12="insumo"),V12*R12,"")))) | Y12: =IF(B12="insumo",W12*V12,IF(B12="serviço",SUMIFS(Y:Y,B:B,"insumo",E:E,E12,I:I,I12),"")) | Z12: =IFERROR(IF(B12="Unidade Construtiva",SUMIFS(Z:Z,B:B,"Célula Construtiva",G:G,G12),IF(B12="célula construtiva",SUMIFS(Z:Z,B:B,"Insumo",I:I,I12,G:G,G12),IF(B12="ETAPA",SUMIFS(Z:Z,B:B,"Insumo",K:K,K12,I:I,I12,G:G,G12),IF(B12="subetapa",SUMIFS(Z:Z,M:M,M12,B:B,"insumo",K:K,K12,I:I,I12,G:G,G12),IF(B12="complemento do insumo",V12*W12,IF(B12="INSUMO",R12*V12*W12,X12*Y12)))))),"") -> 728402.37 | AB12: =IF(B12="insumo",_xlfn.XLOOKUP(S12,Insumos!A:A,Insumos!D:D),"") | AC12: =IFERROR(IF(B12="","",Z12/SUMIF(B:B,"INSUMO",Z:Z)),0) -> 0.10449596 | AE12: =IFERROR(IF(OR(Z12="",Z12=0),"",IF(AF12="","",IF(AF12="R$/mês",Z12/OBRA!$D$12,IF(AF12="R$/m²",Z12/OBRA!$D$10,IF(AF12="R$/apto",Orçamento!Z12/OBRA!$D$11,""))))),"") -> 374.84105 | AF12: R$/m²
B13: Célula Construtiva | C13: =IF(B13="INSUMO",COUNTIFS(B:B,"INSUMO",S:S,S13),IF(B13="SERVIÇO",COUNTIFS(B:B,"SERVIÇO",S:S,S13),"")) | D13: =IF(B13="Unidade Construtiva",TEXT(F13,"00"),IF(B13="Célula Construtiva",TEXT(H13,"00"),IF(B13="Etapa",CONCATENATE(TEXT(H13,"00"),".",TEXT(J13,"000")),IF(B13="Subetapa",CONCATENATE(TEXT(H13,"00"),".",TEXT(J13,"000"),".",TEXT(L13,"000")),IF(B13="Serviço",CONCATENATE(TEXT(H13,"00"),".",TEXT(J13,"000"),".",TEXT(L13,"000"),".",TEXT(N13,"000")),""))))) -> 01 | E13: =IF(B13="*","",IFERROR(IF(B13="SERVIÇO",D13,OFFSET(E13,-1,0)),"")) -> 0 | F13: =IF($B13="UNIDADE CONSTRUTIVA",OFFSET(F13,-1,0)+1,LARGE(F$10:F12,1)) -> 1 | G13: =IF(B13="*","",IF(B13="UNIDADE CONSTRUTIVA",S13,OFFSET(G13,-1,0))) -> GERENCIAMENTO TÉCNICO E ADMINISTRATIVO | H13: =IF(B13="UNIDADE CONSTRUTIVA",0,IF(B13="CÉLULA CONSTRUTIVA",OFFSET(H13,-1,0)+1,OFFSET(H13,-1,0))) -> 1 | I13: =IF(B13="*","",IF(B13="CÉLULA CONSTRUTIVA",S13,OFFSET(I13,-1,0))) -> GERENCIAMENTO TÉCNICO | J13: =IF(B13="CÉLULA CONSTRUTIVA",0,IF(B13="ETAPA",OFFSET(J13,-1,0)+1,OFFSET(J13,-1,0))) -> 0 | K13: =IF(B13="*","",IF(B13="ETAPA",S13,OFFSET(K13,-1,0))) -> 0 | L13: =IF(B13="ETAPA",0,IF(B13="SUBETAPA",OFFSET(L13,-1,0)+1,OFFSET(L13,-1,0))) -> 0 | M13: =IF(B13="*","",IF(B13="SUBETAPA",S13,OFFSET(M13,-1,0))) -> 0 | N13: =IF(B13="Subetapa",0,IF(B13="serviço",OFFSET(N13,-1,0)+1,OFFSET(N13,-1,0))) -> 0 | O13: =IF(B13="*","",IF(B13="SERVIÇO",S13,OFFSET(O13,-1,0))) -> 0 | P13: =IF(S13="","",IF(Orçamento!$B13="INSUMO",S13,"")) | Q13: =IF(S13="","",IF(Orçamento!$B13="Serviço",S13,"")) | R13: =IF(B13="serviço",U13,OFFSET(R13,-1,0)) -> 0 | S13: GERENCIAMENTO TÉCNICO | U13: =IF($B13="insumo",R13,"") | W13: =IFERROR(IF(B13="INSUMO",_xlfn.XLOOKUP(S13,Insumos!A:A,Insumos!C:C),""),"Inserir Preço") | X13: =IF(B13="Complemento do insumo",V13,IF(R13="","",IF(B13="serviço",R13,IF(OR(B13="insumo"),V13*R13,"")))) | Y13: =IF(B13="insumo",W13*V13,IF(B13="serviço",SUMIFS(Y:Y,B:B,"insumo",E:E,E13,I:I,I13),"")) | Z13: =IFERROR(IF(B13="Unidade Construtiva",SUMIFS(Z:Z,B:B,"Célula Construtiva",G:G,G13),IF(B13="célula construtiva",SUMIFS(Z:Z,B:B,"Insumo",I:I,I13,G:G,G13),IF(B13="ETAPA",SUMIFS(Z:Z,B:B,"Insumo",K:K,K13,I:I,I13,G:G,G13),IF(B13="subetapa",SUMIFS(Z:Z,M:M,M13,B:B,"insumo",K:K,K13,I:I,I13,G:G,G13),IF(B13="complemento do insumo",V13*W13,IF(B13="INSUMO",R13*V13*W13,X13*Y13)))))),"") -> 206833.89 | AB13: =IF(B13="insumo",_xlfn.XLOOKUP(S13,Insumos!A:A,Insumos!D:D),"") | AC13: =IFERROR(IF(B13="","",Z13/SUMIF(B:B,"INSUMO",Z:Z)),0) -> 0.029672207 | AE13: =IFERROR(IF(OR(Z13="",Z13=0),"",IF(AF13="","",IF(AF13="R$/mês",Z13/OBRA!$D$12,IF(AF13="R$/m²",Z13/OBRA!$D$10,IF(AF13="R$/apto",Orçamento!Z13/OBRA!$D$11,""))))),"") -> 106.43819 | AF13: R$/m²
B14: Etapa | C14: =IF(B14="INSUMO",COUNTIFS(B:B,"INSUMO",S:S,S14),IF(B14="SERVIÇO",COUNTIFS(B:B,"SERVIÇO",S:S,S14),"")) | D14: =IF(B14="Unidade Construtiva",TEXT(F14,"00"),IF(B14="Célula Construtiva",TEXT(H14,"00"),IF(B14="Etapa",CONCATENATE(TEXT(H14,"00"),".",TEXT(J14,"000")),IF(B14="Subetapa",CONCATENATE(TEXT(H14,"00"),".",TEXT(J14,"000"),".",TEXT(L14,"000")),IF(B14="Serviço",CONCATENATE(TEXT(H14,"00"),".",TEXT(J14,"000"),".",TEXT(L14,"000"),".",TEXT(N14,"000")),""))))) -> 01.001 | E14: =IF(B14="*","",IFERROR(IF(B14="SERVIÇO",D14,OFFSET(E14,-1,0)),"")) -> 0 | F14: =IF($B14="UNIDADE CONSTRUTIVA",OFFSET(F14,-1,0)+1,LARGE(F$10:F13,1)) -> 1 | G14: =IF(B14="*","",IF(B14="UNIDADE CONSTRUTIVA",S14,OFFSET(G14,-1,0))) -> GERENCIAMENTO TÉCNICO E ADMINISTRATIVO | H14: =IF(B14="UNIDADE CONSTRUTIVA",0,IF(B14="CÉLULA CONSTRUTIVA",OFFSET(H14,-1,0)+1,OFFSET(H14,-1,0))) -> 1 | I14: =IF(B14="*","",IF(B14="CÉLULA CONSTRUTIVA",S14,OFFSET(I14,-1,0))) -> GERENCIAMENTO TÉCNICO | J14: =IF(B14="CÉLULA CONSTRUTIVA",0,IF(B14="ETAPA",OFFSET(J14,-1,0)+1,OFFSET(J14,-1,0))) -> 1 | K14: =IF(B14="*","",IF(B14="ETAPA",S14,OFFSET(K14,-1,0))) -> ESTUDOS | PROJETOS | CONSULTORIAS | L14: =IF(B14="ETAPA",0,IF(B14="SUBETAPA",OFFSET(L14,-1,0)+1,OFFSET(L14,-1,0))) -> 0 | M14: =IF(B14="*","",IF(B14="SUBETAPA",S14,OFFSET(M14,-1,0))) -> 0 | N14: =IF(B14="Subetapa",0,IF(B14="serviço",OFFSET(N14,-1,0)+1,OFFSET(N14,-1,0))) -> 0 | O14: =IF(B14="*","",IF(B14="SERVIÇO",S14,OFFSET(O14,-1,0))) -> 0 | P14: =IF(S14="","",IF(Orçamento!$B14="INSUMO",S14,"")) | Q14: =IF(S14="","",IF(Orçamento!$B14="Serviço",S14,"")) | R14: =IF(B14="serviço",U14,OFFSET(R14,-1,0)) -> 0 | S14: ESTUDOS | PROJETOS | CONSULTORIAS | U14: =IF($B14="insumo",R14,"") | W14: =IFERROR(IF(B14="INSUMO",_xlfn.XLOOKUP(S14,Insumos!A:A,Insumos!C:C),""),"Inserir Preço") | X14: =IF(B14="Complemento do insumo",V14,IF(R14="","",IF(B14="serviço",R14,IF(OR(B14="insumo"),V14*R14,"")))) | Y14: =IF(B14="insumo",W14*V14,IF(B14="serviço",SUMIFS(Y:Y,B:B,"insumo",E:E,E14,I:I,I14),"")) | Z14: =IFERROR(IF(B14="Unidade Construtiva",SUMIFS(Z:Z,B:B,"Célula Construtiva",G:G,G14),IF(B14="célula construtiva",SUMIFS(Z:Z,B:B,"Insumo",I:I,I14,G:G,G14),IF(B14="ETAPA",SUMIFS(Z:Z,B:B,"Insumo",K:K,K14,I:I,I14,G:G,G14),IF(B14="subetapa",SUMIFS(Z:Z,M:M,M14,B:B,"insumo",K:K,K14,I:I,I14,G:G,G14),IF(B14="complemento do insumo",V14*W14,IF(B14="INSUMO",R14*V14*W14,X14*Y14)))))),"") -> 161015.62 | AB14: =IF(B14="insumo",_xlfn.XLOOKUP(S14,Insumos!A:A,Insumos!D:D),"") | AC14: =IFERROR(IF(B14="","",Z14/SUMIF(B:B,"INSUMO",Z:Z)),0) -> 0.023099159 | AE14: =IFERROR(IF(OR(Z14="",Z14=0),"",IF(AF14="","",IF(AF14="R$/mês",Z14/OBRA!$D$12,IF(AF14="R$/m²",Z14/OBRA!$D$10,IF(AF14="R$/apto",Orçamento!Z14/OBRA!$D$11,""))))),"") -> 82.859785 | AF14: R$/m²
B15: Subetapa | C15: =IF(B15="INSUMO",COUNTIFS(B:B,"INSUMO",S:S,S15),IF(B15="SERVIÇO",COUNTIFS(B:B,"SERVIÇO",S:S,S15),"")) | D15: =IF(B15="Unidade Construtiva",TEXT(F15,"00"),IF(B15="Célula Construtiva",TEXT(H15,"00"),IF(B15="Etapa",CONCATENATE(TEXT(H15,"00"),".",TEXT(J15,"000")),IF(B15="Subetapa",CONCATENATE(TEXT(H15,"00"),".",TEXT(J15,"000"),".",TEXT(L15,"000")),IF(B15="Serviço",CONCATENATE(TEXT(H15,"00"),".",TEXT(J15,"000"),".",TEXT(L15,"000"),".",TEXT(N15,"000")),""))))) -> 01.001.001 | E15: =IF(B15="*","",IFERROR(IF(B15="SERVIÇO",D15,OFFSET(E15,-1,0)),"")) -> 0 | F15: =IF($B15="UNIDADE CONSTRUTIVA",OFFSET(F15,-1,0)+1,LARGE(F$10:F14,1)) -> 1 | G15: =IF(B15="*","",IF(B15="UNIDADE CONSTRUTIVA",S15,OFFSET(G15,-1,0))) -> GERENCIAMENTO TÉCNICO E ADMINISTRATIVO | H15: =IF(B15="UNIDADE CONSTRUTIVA",0,IF(B15="CÉLULA CONSTRUTIVA",OFFSET(H15,-1,0)+1,OFFSET(H15,-1,0))) -> 1 | I15: =IF(B15="*","",IF(B15="CÉLULA CONSTRUTIVA",S15,OFFSET(I15,-1,0))) -> GERENCIAMENTO TÉCNICO | J15: =IF(B15="CÉLULA CONSTRUTIVA",0,IF(B15="ETAPA",OFFSET(J15,-1,0)+1,OFFSET(J15,-1,0))) -> 1 | K15: =IF(B15="*","",IF(B15="ETAPA",S15,OFFSET(K15,-1,0))) -> ESTUDOS | PROJETOS | CONSULTORIAS | L15: =IF(B15="ETAPA",0,IF(B15="SUBETAPA",OFFSET(L15,-1,0)+1,OFFSET(L15,-1,0))) -> 1 | M15: =IF(B15="*","",IF(B15="SUBETAPA",S15,OFFSET(M15,-1,0))) -> Estudos | N15: =IF(B15="Subetapa",0,IF(B15="serviço",OFFSET(N15,-1,0)+1,OFFSET(N15,-1,0))) -> 0 | O15: =IF(B15="*","",IF(B15="SERVIÇO",S15,OFFSET(O15,-1,0))) -> 0 | P15: =IF(S15="","",IF(Orçamento!$B15="INSUMO",S15,"")) | Q15: =IF(S15="","",IF(Orçamento!$B15="Serviço",S15,"")) | R15: =IF(B15="serviço",U15,OFFSET(R15,-1,0)) -> 0 | S15: Estudos | U15: =IF($B15="insumo",R15,"") | W15: =IFERROR(IF(B15="INSUMO",_xlfn.XLOOKUP(S15,Insumos!A:A,Insumos!C:C),""),"Inserir Preço") | X15: =IF(B15="Complemento do insumo",V15,IF(R15="","",IF(B15="serviço",R15,IF(OR(B15="insumo"),V15*R15,"")))) | Y15: =IF(B15="insumo",W15*V15,IF(B15="serviço",SUMIFS(Y:Y,B:B,"insumo",E:E,E15,I:I,I15),"")) | Z15: =IFERROR(IF(B15="Unidade Construtiva",SUMIFS(Z:Z,B:B,"Célula Construtiva",G:G,G15),IF(B15="célula construtiva",SUMIFS(Z:Z,B:B,"Insumo",I:I,I15,G:G,G15),IF(B15="ETAPA",SUMIFS(Z:Z,B:B,"Insumo",K:K,K15,I:I,I15,G:G,G15),IF(B15="subetapa",SUMIFS(Z:Z,M:M,M15,B:B,"insumo",K:K,K15,I:I,I15,G:G,G15),IF(B15="complemento do insumo",V15*W15,IF(B15="INSUMO",R15*V15*W15,X15*Y15)))))),"") -> 16700 | AB15: =IF(B15="insumo",_xlfn.XLOOKUP(S15,Insumos!A:A,Insumos!D:D),"") | AC15: =IFERROR(IF(B15="","",Z15/SUMIF(B:B,"INSUMO",Z:Z)),0) -> 0.0023957673 | AE15: =IFERROR(IF(OR(Z15="",Z15=0),"",IF(AF15="","",IF(AF15="R$/mês",Z15/OBRA!$D$12,IF(AF15="R$/m²",Z15/OBRA!$D$10,IF(AF15="R$/apto",Orçamento!Z15/OBRA!$D$11,""))))),"") -> 8.593939 | AF15: R$/m²
B16: Serviço | C16: =IF(B16="INSUMO",COUNTIFS(B:B,"INSUMO",S:S,S16),IF(B16="SERVIÇO",COUNTIFS(B:B,"SERVIÇO",S:S,S16),"")) -> 1 | D16: =IF(B16="Unidade Construtiva",TEXT(F16,"00"),IF(B16="Célula Construtiva",TEXT(H16,"00"),IF(B16="Etapa",CONCATENATE(TEXT(H16,"00"),".",TEXT(J16,"000")),IF(B16="Subetapa",CONCATENATE(TEXT(H16,"00"),".",TEXT(J16,"000"),".",TEXT(L16,"000")),IF(B16="Serviço",CONCATENATE(TEXT(H16,"00"),".",TEXT(J16,"000"),".",TEXT(L16,"000"),".",TEXT(N16,"000")),""))))) -> 01.001.001.001 | E16: =IF(B16="*","",IFERROR(IF(B16="SERVIÇO",D16,OFFSET(E16,-1,0)),"")) -> 01.001.001.001 | F16: =IF($B16="UNIDADE CONSTRUTIVA",OFFSET(F16,-1,0)+1,LARGE(F$10:F15,1)) -> 1 | G16: =IF(B16="*","",IF(B16="UNIDADE CONSTRUTIVA",S16,OFFSET(G16,-1,0))) -> GERENCIAMENTO TÉCNICO E ADMINISTRATIVO | H16: =IF(B16="UNIDADE CONSTRUTIVA",0,IF(B16="CÉLULA CONSTRUTIVA",OFFSET(H16,-1,0)+1,OFFSET(H16,-1,0))) -> 1 | I16: =IF(B16="*","",IF(B16="CÉLULA CONSTRUTIVA",S16,OFFSET(I16,-1,0))) -> GERENCIAMENTO TÉCNICO | J16: =IF(B16="CÉLULA CONSTRUTIVA",0,IF(B16="ETAPA",OFFSET(J16,-1,0)+1,OFFSET(J16,-1,0))) -> 1 | K16: =IF(B16="*","",IF(B16="ETAPA",S16,OFFSET(K16,-1,0))) -> ESTUDOS | PROJETOS | CONSULTORIAS | L16: =IF(B16="ETAPA",0,IF(B16="SUBETAPA",OFFSET(L16,-1,0)+1,OFFSET(L16,-1,0))) -> 1 | M16: =IF(B16="*","",IF(B16="SUBETAPA",S16,OFFSET(M16,-1,0))) -> Estudos | N16: =IF(B16="Subetapa",0,IF(B16="serviço",OFFSET(N16,-1,0)+1,OFFSET(N16,-1,0))) -> 1 | O16: =IF(B16="*","",IF(B16="SERVIÇO",S16,OFFSET(O16,-1,0))) -> Serviço Levantamento Topografico | P16: =IF(S16="","",IF(Orçamento!$B16="INSUMO",S16,"")) | Q16: =IF(B16="","",IF(B16="Serviço",S16,"")) -> Serviço Levantamento Topografico | R16: =IF(B16="serviço",U16,OFFSET(R16,-1,0)) -> 1 | S16: Serviço Levantamento Topografico | T16: VB | U16: 1 | W16: =IFERROR(IF(B16="INSUMO",_xlfn.XLOOKUP(S16,Insumos!A:A,Insumos!C:C),""),"Inserir Preço") | X16: =IF(B16="Complemento do insumo",V16,IF(R16="","",IF(B16="serviço",R16,IF(OR(B16="insumo"),V16*R16,"")))) -> 1 | Y16: =IF(B16="insumo",W16*V16,IF(B16="serviço",SUMIFS(Y:Y,B:B,"insumo",E:E,E16,I:I,I16),"")) -> 7800 | Z16: =IFERROR(IF(B16="Unidade Construtiva",SUMIFS(Z:Z,B:B,"Célula Construtiva",G:G,G16),IF(B16="célula construtiva",SUMIFS(Z:Z,B:B,"Insumo",I:I,I16,G:G,G16),IF(B16="ETAPA",SUMIFS(Z:Z,B:B,"Insumo",K:K,K16,I:I,I16,G:G,G16),IF(B16="subetapa",SUMIFS(Z:Z,M:M,M16,B:B,"insumo",K:K,K16,I:I,I16,G:G,G16),IF(B16="complemento do insumo",V16*W16,IF(B16="INSUMO",R16*V16*W16,X16*Y16)))))),"") -> 7800 | AB16: =IF(B16="insumo",_xlfn.XLOOKUP(S16,Insumos!A:A,Insumos!D:D),"") | AC16: =IFERROR(IF(B16="","",Z16/SUMIF(B:B,"INSUMO",Z:Z)),0) -> 0.0011189811 | AE16: =IFERROR(IF(OR(Z16="",Z16=0),"",IF(AF16="","",IF(AF16="R$/mês",Z16/OBRA!$D$12,IF(AF16="R$/m²",Z16/OBRA!$D$10,IF(AF16="R$/apto",Orçamento!Z16/OBRA!$D$11,""))))),"") -> 4.0139356 | AF16: R$/m²
B17: Insumo | C17: =IF(B17="INSUMO",COUNTIFS(B:B,"INSUMO",S:S,S17),IF(B17="SERVIÇO",COUNTIFS(B:B,"SERVIÇO",S:S,S17),"")) -> 1 | D17: =IF(B17="Unidade Construtiva",TEXT(F17,"00"),IF(B17="Célula Construtiva",TEXT(H17,"00"),IF(B17="Etapa",CONCATENATE(TEXT(H17,"00"),".",TEXT(J17,"000")),IF(B17="Subetapa",CONCATENATE(TEXT(H17,"00"),".",TEXT(J17,"000"),".",TEXT(L17,"000")),IF(B17="Serviço",CONCATENATE(TEXT(H17,"00"),".",TEXT(J17,"000"),".",TEXT(L17,"000"),".",TEXT(N17,"000")),""))))) | E17: =IF(B17="*","",IFERROR(IF(B17="SERVIÇO",D17,OFFSET(E17,-1,0)),"")) -> 01.001.001.001 | F17: =IF($B17="UNIDADE CONSTRUTIVA",OFFSET(F17,-1,0)+1,LARGE(F$10:F16,1)) -> 1 | G17: =IF(B17="*","",IF(B17="UNIDADE CONSTRUTIVA",S17,OFFSET(G17,-1,0))) -> GERENCIAMENTO TÉCNICO E ADMINISTRATIVO | H17: =IF(B17="UNIDADE CONSTRUTIVA",0,IF(B17="CÉLULA CONSTRUTIVA",OFFSET(H17,-1,0)+1,OFFSET(H17,-1,0))) -> 1 | I17: =IF(B17="*","",IF(B17="CÉLULA CONSTRUTIVA",S17,OFFSET(I17,-1,0))) -> GERENCIAMENTO TÉCNICO | J17: =IF(B17="CÉLULA CONSTRUTIVA",0,IF(B17="ETAPA",OFFSET(J17,-1,0)+1,OFFSET(J17,-1,0))) -> 1 | K17: =IF(B17="*","",IF(B17="ETAPA",S17,OFFSET(K17,-1,0))) -> ESTUDOS | PROJETOS | CONSULTORIAS | L17: =IF(B17="ETAPA",0,IF(B17="SUBETAPA",OFFSET(L17,-1,0)+1,OFFSET(L17,-1,0))) -> 1 | M17: =IF(B17="*","",IF(B17="SUBETAPA",S17,OFFSET(M17,-1,0))) -> Estudos | N17: =IF(B17="Subetapa",0,IF(B17="serviço",OFFSET(N17,-1,0)+1,OFFSET(N17,-1,0))) -> 1 | O17: =IF(B17="*","",IF(B17="SERVIÇO",S17,OFFSET(O17,-1,0))) -> Serviço Levantamento Topografico | P17: =IF(S17="","",IF(Orçamento!$B17="INSUMO",S17,"")) -> LEVANTAMENTO TOPOGRAFICO | Q17: =IF(B17="","",IF(B17="Serviço",S17,"")) | R17: =IF(B17="serviço",U17,OFFSET(R17,-1,0)) -> 1 | S17: LEVANTAMENTO TOPOGRAFICO | T17: =_xlfn.XLOOKUP(S17,Insumos!$A$3:$A$371,Insumos!$B$3:$B$371) -> M3 | U17: =IF($B17="insumo",R17,"") -> 1 | V17: 1 | W17: =IFERROR(IF(B17="INSUMO",_xlfn.XLOOKUP(S17,Insumos!A:A,Insumos!C:C),""),"Inserir Preço") -> 7800 | X17: =IF(B17="Complemento do insumo",V17,IF(R17="","",IF(B17="serviço",R17,IF(OR(B17="insumo"),V17*R17,"")))) -> 1 | Y17: =IF(B17="insumo",W17*V17,IF(B17="serviço",SUMIFS(Y:Y,B:B,"insumo",E:E,E17,I:I,I17),"")) -> 7800 | Z17: =IFERROR(IF(B17="Unidade Construtiva",SUMIFS(Z:Z,B:B,"Célula Construtiva",G:G,G17),IF(B17="célula construtiva",SUMIFS(Z:Z,B:B,"Insumo",I:I,I17,G:G,G17),IF(B17="ETAPA",SUMIFS(Z:Z,B:B,"Insumo",K:K,K17,I:I,I17,G:G,G17),IF(B17="subetapa",SUMIFS(Z:Z,M:M,M17,B:B,"insumo",K:K,K17,I:I,I17,G:G,G17),IF(B17="complemento do insumo",V17*W17,IF(B17="INSUMO",R17*V17*W17,X17*Y17)))))),"") -> 7800 | AB17: =IF(B17="insumo",_xlfn.XLOOKUP(S17,Insumos!A:A,Insumos!D:D),"") -> Balancete | AC17: =IFERROR(IF(B17="","",Z17/SUMIF(B:B,"INSUMO",Z:Z)),0) -> 0.0011189811 | AE17: =IFERROR(IF(OR(Z17="",Z17=0),"",IF(AF17="","",IF(AF17="R$/mês",Z17/OBRA!$D$12,IF(AF17="R$/m²",Z17/OBRA!$D$10,IF(AF17="R$/apto",Orçamento!Z17/OBRA!$D$11,""))))),"") -> 4.0139356 | AF17: R$/m²
B18: Serviço | C18: =IF(B18="INSUMO",COUNTIFS(B:B,"INSUMO",S:S,S18),IF(B18="SERVIÇO",COUNTIFS(B:B,"SERVIÇO",S:S,S18),"")) -> 1 | D18: =IF(B18="Unidade Construtiva",TEXT(F18,"00"),IF(B18="Célula Construtiva",TEXT(H18,"00"),IF(B18="Etapa",CONCATENATE(TEXT(H18,"00"),".",TEXT(J18,"000")),IF(B18="Subetapa",CONCATENATE(TEXT(H18,"00"),".",TEXT(J18,"000"),".",TEXT(L18,"000")),IF(B18="Serviço",CONCATENATE(TEXT(H18,"00"),".",TEXT(J18,"000"),".",TEXT(L18,"000"),".",TEXT(N18,"000")),""))))) -> 01.001.001.002 | E18: =IF(B18="*","",IFERROR(IF(B18="SERVIÇO",D18,OFFSET(E18,-1,0)),"")) -> 01.001.001.002 | F18: =IF($B18="UNIDADE CONSTRUTIVA",OFFSET(F18,-1,0)+1,LARGE(F$10:F17,1)) -> 1 | G18: =IF(B18="*","",IF(B18="UNIDADE CONSTRUTIVA",S18,OFFSET(G18,-1,0))) -> GERENCIAMENTO TÉCNICO E ADMINISTRATIVO | H18: =IF(B18="UNIDADE CONSTRUTIVA",0,IF(B18="CÉLULA CONSTRUTIVA",OFFSET(H18,-1,0)+1,OFFSET(H18,-1,0))) -> 1 | I18: =IF(B18="*","",IF(B18="CÉLULA CONSTRUTIVA",S18,OFFSET(I18,-1,0))) -> GERENCIAMENTO TÉCNICO | J18: =IF(B18="CÉLULA CONSTRUTIVA",0,IF(B18="ETAPA",OFFSET(J18,-1,0)+1,OFFSET(J18,-1,0))) -> 1 | K18: =IF(B18="*","",IF(B18="ETAPA",S18,OFFSET(K18,-1,0))) -> ESTUDOS | PROJETOS | CONSULTORIAS | L18: =IF(B18="ETAPA",0,IF(B18="SUBETAPA",OFFSET(L18,-1,0)+1,OFFSET(L18,-1,0))) -> 1 | M18: =IF(B18="*","",IF(B18="SUBETAPA",S18,OFFSET(M18,-1,0))) -> Estudos | N18: =IF(B18="Subetapa",0,IF(B18="serviço",OFFSET(N18,-1,0)+1,OFFSET(N18,-1,0))) -> 2 | O18: =IF(B18="*","",IF(B18="SERVIÇO",S18,OFFSET(O18,-1,0))) -> Sondagem do terreno | P18: =IF(S18="","",IF(Orçamento!$B18="INSUMO",S18,"")) | Q18: =IF(B18="","",IF(B18="Serviço",S18,"")) -> Sondagem do terreno | R18: =IF(B18="serviço",U18,OFFSET(R18,-1,0)) -> 1 | S18: Sondagem do terreno | T18: VB | U18: 1 | W18: =IFERROR(IF(B18="INSUMO",_xlfn.XLOOKUP(S18,Insumos!A:A,Insumos!C:C),""),"Inserir Preço") | X18: =IF(B18="Complemento do insumo",V18,IF(R18="","",IF(B18="serviço",R18,IF(OR(B18="insumo"),V18*R18,"")))) -> 1 | Y18: =IF(B18="insumo",W18*V18,IF(B18="serviço",SUMIFS(Y:Y,B:B,"insumo",E:E,E18,I:I,I18),"")) -> 8900 | Z18: =IFERROR(IF(B18="Unidade Construtiva",SUMIFS(Z:Z,B:B,"Célula Construtiva",G:G,G18),IF(B18="célula construtiva",SUMIFS(Z:Z,B:B,"Insumo",I:I,I18,G:G,G18),IF(B18="ETAPA",SUMIFS(Z:Z,B:B,"Insumo",K:K,K18,I:I,I18,G:G,G18),IF(B18="subetapa",SUMIFS(Z:Z,M:M,M18,B:B,"insumo",K:K,K18,I:I,I18,G:G,G18),IF(B18="complemento do insumo",V18*W18,IF(B18="INSUMO",R18*V18*W18,X18*Y18)))))),"") -> 8900 | AB18: =IF(B18="insumo",_xlfn.XLOOKUP(S18,Insumos!A:A,Insumos!D:D),"") | AC18: =IFERROR(IF(B18="","",Z18/SUMIF(B:B,"INSUMO",Z:Z)),0) -> 0.0012767861 | AE18: =IFERROR(IF(OR(Z18="",Z18=0),"",IF(AF18="","",IF(AF18="R$/mês",Z18/OBRA!$D$12,IF(AF18="R$/m²",Z18/OBRA!$D$10,IF(AF18="R$/apto",Orçamento!Z18/OBRA!$D$11,""))))),"") -> 4.5800034 | AF18: R$/m²
B19: Insumo | C19: =IF(B19="INSUMO",COUNTIFS(B:B,"INSUMO",S:S,S19),IF(B19="SERVIÇO",COUNTIFS(B:B,"SERVIÇO",S:S,S19),"")) -> 1 | D19: =IF(B19="Unidade Construtiva",TEXT(F19,"00"),IF(B19="Célula Construtiva",TEXT(H19,"00"),IF(B19="Etapa",CONCATENATE(TEXT(H19,"00"),".",TEXT(J19,"000")),IF(B19="Subetapa",CONCATENATE(TEXT(H19,"00"),".",TEXT(J19,"000"),".",TEXT(L19,"000")),IF(B19="Serviço",CONCATENATE(TEXT(H19,"00"),".",TEXT(J19,"000"),".",TEXT(L19,"000"),".",TEXT(N19,"000")),""))))) | E19: =IF(B19="*","",IFERROR(IF(B19="SERVIÇO",D19,OFFSET(E19,-1,0)),"")) -> 01.001.001.002 | F19: =IF($B19="UNIDADE CONSTRUTIVA",OFFSET(F19,-1,0)+1,LARGE(F$10:F18,1)) -> 1 | G19: =IF(B19="*","",IF(B19="UNIDADE CONSTRUTIVA",S19,OFFSET(G19,-1,0))) -> GERENCIAMENTO TÉCNICO E ADMINISTRATIVO | H19: =IF(B19="UNIDADE CONSTRUTIVA",0,IF(B19="CÉLULA CONSTRUTIVA",OFFSET(H19,-1,0)+1,OFFSET(H19,-1,0))) -> 1 | I19: =IF(B19="*","",IF(B19="CÉLULA CONSTRUTIVA",S19,OFFSET(I19,-1,0))) -> GERENCIAMENTO TÉCNICO | J19: =IF(B19="CÉLULA CONSTRUTIVA",0,IF(B19="ETAPA",OFFSET(J19,-1,0)+1,OFFSET(J19,-1,0))) -> 1 | K19: =IF(B19="*","",IF(B19="ETAPA",S19,OFFSET(K19,-1,0))) -> ESTUDOS | PROJETOS | CONSULTORIAS | L19: =IF(B19="ETAPA",0,IF(B19="SUBETAPA",OFFSET(L19,-1,0)+1,OFFSET(L19,-1,0))) -> 1 | M19: =IF(B19="*","",IF(B19="SUBETAPA",S19,OFFSET(M19,-1,0))) -> Estudos | N19: =IF(B19="Subetapa",0,IF(B19="serviço",OFFSET(N19,-1,0)+1,OFFSET(N19,-1,0))) -> 2 | O19: =IF(B19="*","",IF(B19="SERVIÇO",S19,OFFSET(O19,-1,0))) -> Sondagem do terreno | P19: =IF(S19="","",IF(Orçamento!$B19="INSUMO",S19,"")) -> SONDAGEM | Q19: =IF(B19="","",IF(B19="Serviço",S19,"")) | R19: =IF(B19="serviço",U19,OFFSET(R19,-1,0)) -> 1 | S19: SONDAGEM | T19: =_xlfn.XLOOKUP(S19,Insumos!$A$3:$A$371,Insumos!$B$3:$B$371) -> VB | U19: =IF($B19="insumo",R19,"") -> 1 | V19: 1 | W19: =IFERROR(IF(B19="INSUMO",_xlfn.XLOOKUP(S19,Insumos!A:A,Insumos!C:C),""),"Inserir Preço") -> 8900 | X19: =IF(B19="Complemento do insumo",V19,IF(R19="","",IF(B19="serviço",R19,IF(OR(B19="insumo"),V19*R19,"")))) -> 1 | Y19: =IF(B19="insumo",W19*V19,IF(B19="serviço",SUMIFS(Y:Y,B:B,"insumo",E:E,E19,I:I,I19),"")) -> 8900 | Z19: =IFERROR(IF(B19="Unidade Construtiva",SUMIFS(Z:Z,B:B,"Célula Construtiva",G:G,G19),IF(B19="célula construtiva",SUMIFS(Z:Z,B:B,"Insumo",I:I,I19,G:G,G19),IF(B19="ETAPA",SUMIFS(Z:Z,B:B,"Insumo",K:K,K19,I:I,I19,G:G,G19),IF(B19="subetapa",SUMIFS(Z:Z,M:M,M19,B:B,"insumo",K:K,K19,I:I,I19,G:G,G19),IF(B19="complemento do insumo",V19*W19,IF(B19="INSUMO",R19*V19*W19,X19*Y19)))))),"") -> 8900 | AB19: =IF(B19="insumo",_xlfn.XLOOKUP(S19,Insumos!A:A,Insumos!D:D),"") -> Balancete | AC19: =IFERROR(IF(B19="","",Z19/SUMIF(B:B,"INSUMO",Z:Z)),0) -> 0.0012767861 | AE19: =IFERROR(IF(OR(Z19="",Z19=0),"",IF(AF19="","",IF(AF19="R$/mês",Z19/OBRA!$D$12,IF(AF19="R$/m²",Z19/OBRA!$D$10,IF(AF19="R$/apto",Orçamento!Z19/OBRA!$D$11,""))))),"") -> 4.5800034 | AF19: R$/m²
B20: Subetapa | C20: =IF(B20="INSUMO",COUNTIFS(B:B,"INSUMO",S:S,S20),IF(B20="SERVIÇO",COUNTIFS(B:B,"SERVIÇO",S:S,S20),"")) | D20: =IF(B20="Unidade Construtiva",TEXT(F20,"00"),IF(B20="Célula Construtiva",TEXT(H20,"00"),IF(B20="Etapa",CONCATENATE(TEXT(H20,"00"),".",TEXT(J20,"000")),IF(B20="Subetapa",CONCATENATE(TEXT(H20,"00"),".",TEXT(J20,"000"),".",TEXT(L20,"000")),IF(B20="Serviço",CONCATENATE(TEXT(H20,"00"),".",TEXT(J20,"000"),".",TEXT(L20,"000"),".",TEXT(N20,"000")),""))))) -> 01.001.002 | E20: =IF(B20="*","",IFERROR(IF(B20="SERVIÇO",D20,OFFSET(E20,-1,0)),"")) -> 01.001.001.002 | F20: =IF($B20="UNIDADE CONSTRUTIVA",OFFSET(F20,-1,0)+1,LARGE(F$10:F19,1)) -> 1 | G20: =IF(B20="*","",IF(B20="UNIDADE CONSTRUTIVA",S20,OFFSET(G20,-1,0))) -> GERENCIAMENTO TÉCNICO E ADMINISTRATIVO | H20: =IF(B20="UNIDADE CONSTRUTIVA",0,IF(B20="CÉLULA CONSTRUTIVA",OFFSET(H20,-1,0)+1,OFFSET(H20,-1,0))) -> 1 | I20: =IF(B20="*","",IF(B20="CÉLULA CONSTRUTIVA",S20,OFFSET(I20,-1,0))) -> GERENCIAMENTO TÉCNICO | J20: =IF(B20="CÉLULA CONSTRUTIVA",0,IF(B20="ETAPA",OFFSET(J20,-1,0)+1,OFFSET(J20,-1,0))) -> 1 | K20: =IF(B20="*","",IF(B20="ETAPA",S20,OFFSET(K20,-1,0))) -> ESTUDOS | PROJETOS | CONSULTORIAS | L20: =IF(B20="ETAPA",0,IF(B20="SUBETAPA",OFFSET(L20,-1,0)+1,OFFSET(L20,-1,0))) -> 2 | M20: =IF(B20="*","",IF(B20="SUBETAPA",S20,OFFSET(M20,-1,0))) -> Projetos | N20: =IF(B20="Subetapa",0,IF(B20="serviço",OFFSET(N20,-1,0)+1,OFFSET(N20,-1,0))) -> 0 | O20: =IF(B20="*","",IF(B20="SERVIÇO",S20,OFFSET(O20,-1,0))) -> Sondagem do terreno | P20: =IF(S20="","",IF(Orçamento!$B20="INSUMO",S20,"")) | Q20: =IF(B20="","",IF(B20="Serviço",S20,"")) | R20: =IF(B20="serviço",U20,OFFSET(R20,-1,0)) -> 1 | S20: Projetos | U20: =IF($B20="insumo",R20,"") | W20: =IFERROR(IF(B20="INSUMO",_xlfn.XLOOKUP(S20,Insumos!A:A,Insumos!C:C),""),"Inserir Preço") | X20: =IF(B20="Complemento do insumo",V20,IF(R20="","",IF(B20="serviço",R20,IF(OR(B20="insumo"),V20*R20,"")))) | Y20: =IF(B20="insumo",W20*V20,IF(B20="serviço",SUMIFS(Y:Y,B:B,"insumo",E:E,E20,I:I,I20),"")) | Z20: =IFERROR(IF(B20="Unidade Construtiva",SUMIFS(Z:Z,B:B,"Célula Construtiva",G:G,G20),IF(B20="célula construtiva",SUMIFS(Z:Z,B:B,"Insumo",I:I,I20,G:G,G20),IF(B20="ETAPA",SUMIFS(Z:Z,B:B,"Insumo",K:K,K20,I:I,I20,G:G,G20),IF(B20="subetapa",SUMIFS(Z:Z,M:M,M20,B:B,"insumo",K:K,K20,I:I,I20,G:G,G20),IF(B20="complemento do insumo",V20*W20,IF(B20="INSUMO",R20*V20*W20,X20*Y20)))))),"") -> 106486 | AB20: =IF(B20="insumo",_xlfn.XLOOKUP(S20,Insumos!A:A,Insumos!D:D),"") | AC20: =IFERROR(IF(B20="","",Z20/SUMIF(B:B,"INSUMO",Z:Z)),0) -> 0.015276388 | AE20: =IFERROR(IF(OR(Z20="",Z20=0),"",IF(AF20="","",IF(AF20="R$/mês",Z20/OBRA!$D$12,IF(AF20="R$/m²",Z20/OBRA!$D$10,IF(AF20="R$/apto",Orçamento!Z20/OBRA!$D$11,""))))),"") -> 54.798454 | AF20: R$/m²
B21: Serviço | C21: =IF(B21="INSUMO",COUNTIFS(B:B,"INSUMO",S:S,S21),IF(B21="SERVIÇO",COUNTIFS(B:B,"SERVIÇO",S:S,S21),"")) -> 1 | D21: =IF(B21="Unidade Construtiva",TEXT(F21,"00"),IF(B21="Célula Construtiva",TEXT(H21,"00"),IF(B21="Etapa",CONCATENATE(TEXT(H21,"00"),".",TEXT(J21,"000")),IF(B21="Subetapa",CONCATENATE(TEXT(H21,"00"),".",TEXT(J21,"000"),".",TEXT(L21,"000")),IF(B21="Serviço",CONCATENATE(TEXT(H21,"00"),".",TEXT(J21,"000"),".",TEXT(L21,"000"),".",TEXT(N21,"000")),""))))) -> 01.001.002.001 | E21: =IF(B21="*","",IFERROR(IF(B21="SERVIÇO",D21,OFFSET(E21,-1,0)),"")) -> 01.001.002.001 | F21: =IF($B21="UNIDADE CONSTRUTIVA",OFFSET(F21,-1,0)+1,LARGE(F$10:F20,1)) -> 1 | G21: =IF(B21="*","",IF(B21="UNIDADE CONSTRUTIVA",S21,OFFSET(G21,-1,0))) -> GERENCIAMENTO TÉCNICO E ADMINISTRATIVO | H21: =IF(B21="UNIDADE CONSTRUTIVA",0,IF(B21="CÉLULA CONSTRUTIVA",OFFSET(H21,-1,0)+1,OFFSET(H21,-1,0))) -> 1 | I21: =IF(B21="*","",IF(B21="CÉLULA CONSTRUTIVA",S21,OFFSET(I21,-1,0))) -> GERENCIAMENTO TÉCNICO | J21: =IF(B21="CÉLULA CONSTRUTIVA",0,IF(B21="ETAPA",OFFSET(J21,-1,0)+1,OFFSET(J21,-1,0))) -> 1 | K21: =IF(B21="*","",IF(B21="ETAPA",S21,OFFSET(K21,-1,0))) -> ESTUDOS | PROJETOS | CONSULTORIAS | L21: =IF(B21="ETAPA",0,IF(B21="SUBETAPA",OFFSET(L21,-1,0)+1,OFFSET(L21,-1,0))) -> 2 | M21: =IF(B21="*","",IF(B21="SUBETAPA",S21,OFFSET(M21,-1,0))) -> Projetos | N21: =IF(B21="Subetapa",0,IF(B21="serviço",OFFSET(N21,-1,0)+1,OFFSET(N21,-1,0))) -> 1 | O21: =IF(B21="*","",IF(B21="SERVIÇO",S21,OFFSET(O21,-1,0))) -> Projeto Arquitetônico | P21: =IF(S21="","",IF(Orçamento!$B21="INSUMO",S21,"")) | Q21: =IF(B21="","",IF(B21="Serviço",S21,"")) -> Projeto Arquitetônico | R21: =IF(B21="serviço",U21,OFFSET(R21,-1,0)) -> 1 | S21: Projeto Arquitetônico | T21: VB | U21: 1 | W21: =IFERROR(IF(B21="INSUMO",_xlfn.XLOOKUP(S21,Insumos!A:A,Insumos!C:C),""),"Inserir Preço") | X21: =IF(B21="Complemento do insumo",V21,IF(R21="","",IF(B21="serviço",R21,IF(OR(B21="insumo"),V21*R21,"")))) -> 1 | Y21: =IF(B21="insumo",W21*V21,IF(B21="serviço",SUMIFS(Y:Y,B:B,"insumo",E:E,E21,I:I,I21),"")) -> 40816 | Z21: =IFERROR(IF(B21="Unidade Construtiva",SUMIFS(Z:Z,B:B,"Célula Construtiva",G:G,G21),IF(B21="célula construtiva",SUMIFS(Z:Z,B:B,"Insumo",I:I,I21,G:G,G21),IF(B21="ETAPA",SUMIFS(Z:Z,B:B,"Insumo",K:K,K21,I:I,I21,G:G,G21),IF(B21="subetapa",SUMIFS(Z:Z,M:M,M21,B:B,"insumo",K:K,K21,I:I,I21,G:G,G21),IF(B21="complemento do insumo",V21*W21,IF(B21="INSUMO",R21*V21*W21,X21*Y21)))))),"") -> 40816 | AB21: =IF(B21="insumo",_xlfn.XLOOKUP(S21,Insumos!A:A,Insumos!D:D),"") | AC21: =IFERROR(IF(B21="","",Z21/SUMIF(B:B,"INSUMO",Z:Z)),0) -> 0.0058554273 | AE21: =IFERROR(IF(OR(Z21="",Z21=0),"",IF(AF21="","",IF(AF21="R$/mês",Z21/OBRA!$D$12,IF(AF21="R$/m²",Z21/OBRA!$D$10,IF(AF21="R$/apto",Orçamento!Z21/OBRA!$D$11,""))))),"") -> 21.004204 | AF21: R$/m²
B22: Insumo | C22: =IF(B22="INSUMO",COUNTIFS(B:B,"INSUMO",S:S,S22),IF(B22="SERVIÇO",COUNTIFS(B:B,"SERVIÇO",S:S,S22),"")) -> 1 | D22: =IF(B22="Unidade Construtiva",TEXT(F22,"00"),IF(B22="Célula Construtiva",TEXT(H22,"00"),IF(B22="Etapa",CONCATENATE(TEXT(H22,"00"),".",TEXT(J22,"000")),IF(B22="Subetapa",CONCATENATE(TEXT(H22,"00"),".",TEXT(J22,"000"),".",TEXT(L22,"000")),IF(B22="Serviço",CONCATENATE(TEXT(H22,"00"),".",TEXT(J22,"000"),".",TEXT(L22,"000"),".",TEXT(N22,"000")),""))))) | E22: =IF(B22="*","",IFERROR(IF(B22="SERVIÇO",D22,OFFSET(E22,-1,0)),"")) -> 01.001.002.001 | F22: =IF($B22="UNIDADE CONSTRUTIVA",OFFSET(F22,-1,0)+1,LARGE(F$10:F21,1)) -> 1 | G22: =IF(B22="*","",IF(B22="UNIDADE CONSTRUTIVA",S22,OFFSET(G22,-1,0))) -> GERENCIAMENTO TÉCNICO E ADMINISTRATIVO | H22: =IF(B22="UNIDADE CONSTRUTIVA",0,IF(B22="CÉLULA CONSTRUTIVA",OFFSET(H22,-1,0)+1,OFFSET(H22,-1,0))) -> 1 | I22: =IF(B22="*","",IF(B22="CÉLULA CONSTRUTIVA",S22,OFFSET(I22,-1,0))) -> GERENCIAMENTO TÉCNICO | J22: =IF(B22="CÉLULA CONSTRUTIVA",0,IF(B22="ETAPA",OFFSET(J22,-1,0)+1,OFFSET(J22,-1,0))) -> 1 | K22: =IF(B22="*","",IF(B22="ETAPA",S22,OFFSET(K22,-1,0))) -> ESTUDOS | PROJETOS | CONSULTORIAS | L22: =IF(B22="ETAPA",0,IF(B22="SUBETAPA",OFFSET(L22,-1,0)+1,OFFSET(L22,-1,0))) -> 2 | M22: =IF(B22="*","",IF(B22="SUBETAPA",S22,OFFSET(M22,-1,0))) -> Projetos | N22: =IF(B22="Subetapa",0,IF(B22="serviço",OFFSET(N22,-1,0)+1,OFFSET(N22,-1,0))) -> 1 | O22: =IF(B22="*","",IF(B22="SERVIÇO",S22,OFFSET(O22,-1,0))) -> Projeto Arquitetônico | P22: =IF(S22="","",IF(Orçamento!$B22="INSUMO",S22,"")) -> PROJETO ARQUITETONICO | Q22: =IF(B22="","",IF(B22="Serviço",S22,"")) | R22: =IF(B22="serviço",U22,OFFSET(R22,-1,0)) -> 1 | S22: PROJETO ARQUITETONICO | T22: =_xlfn.XLOOKUP(S22,Insumos!$A$3:$A$371,Insumos!$B$3:$B$371) -> VB | U22: =IF($B22="insumo",R22,"") -> 1 | V22: 1 | W22: =IFERROR(IF(B22="INSUMO",_xlfn.XLOOKUP(S22,Insumos!A:A,Insumos!C:C),""),"Inserir Preço") -> 40816 | X22: =IF(B22="Complemento do insumo",V22,IF(R22="","",IF(B22="serviço",R22,IF(OR(B22="insumo"),V22*R22,"")))) -> 1 | Y22: =IF(B22="insumo",W22*V22,IF(B22="serviço",SUMIFS(Y:Y,B:B,"insumo",E:E,E22,I:I,I22),"")) -> 40816 | Z22: =IFERROR(IF(B22="Unidade Construtiva",SUMIFS(Z:Z,B:B,"Célula Construtiva",G:G,G22),IF(B22="célula construtiva",SUMIFS(Z:Z,B:B,"Insumo",I:I,I22,G:G,G22),IF(B22="ETAPA",SUMIFS(Z:Z,B:B,"Insumo",K:K,K22,I:I,I22,G:G,G22),IF(B22="subetapa",SUMIFS(Z:Z,M:M,M22,B:B,"insumo",K:K,K22,I:I,I22,G:G,G22),IF(B22="complemento do insumo",V22*W22,IF(B22="INSUMO",R22*V22*W22,X22*Y22)))))),"") -> 40816 | AB22: =IF(B22="insumo",_xlfn.XLOOKUP(S22,Insumos!A:A,Insumos!D:D),"") -> Recebido Cliente | AC22: =IFERROR(IF(B22="","",Z22/SUMIF(B:B,"INSUMO",Z:Z)),0) -> 0.0058554273 | AE22: =IFERROR(IF(OR(Z22="",Z22=0),"",IF(AF22="","",IF(AF22="R$/mês",Z22/OBRA!$D$12,IF(AF22="R$/m²",Z22/OBRA!$D$10,IF(AF22="R$/apto",Orçamento!Z22/OBRA!$D$11,""))))),"") -> 21.004204 | AF22: R$/m²
B23: Serviço | C23: =IF(B23="INSUMO",COUNTIFS(B:B,"INSUMO",S:S,S23),IF(B23="SERVIÇO",COUNTIFS(B:B,"SERVIÇO",S:S,S23),"")) -> 1 | D23: =IF(B23="Unidade Construtiva",TEXT(F23,"00"),IF(B23="Célula Construtiva",TEXT(H23,"00"),IF(B23="Etapa",CONCATENATE(TEXT(H23,"00"),".",TEXT(J23,"000")),IF(B23="Subetapa",CONCATENATE(TEXT(H23,"00"),".",TEXT(J23,"000"),".",TEXT(L23,"000")),IF(B23="Serviço",CONCATENATE(TEXT(H23,"00"),".",TEXT(J23,"000"),".",TEXT(L23,"000"),".",TEXT(N23,"000")),""))))) -> 01.001.002.002 | E23: =IF(B23="*","",IFERROR(IF(B23="SERVIÇO",D23,OFFSET(E23,-1,0)),"")) -> 01.001.002.002 | F23: =IF($B23="UNIDADE CONSTRUTIVA",OFFSET(F23,-1,0)+1,LARGE(F$10:F22,1)) -> 1 | G23: =IF(B23="*","",IF(B23="UNIDADE CONSTRUTIVA",S23,OFFSET(G23,-1,0))) -> GERENCIAMENTO TÉCNICO E ADMINISTRATIVO | H23: =IF(B23="UNIDADE CONSTRUTIVA",0,IF(B23="CÉLULA CONSTRUTIVA",OFFSET(H23,-1,0)+1,OFFSET(H23,-1,0))) -> 1 | I23: =IF(B23="*","",IF(B23="CÉLULA CONSTRUTIVA",S23,OFFSET(I23,-1,0))) -> GERENCIAMENTO TÉCNICO | J23: =IF(B23="CÉLULA CONSTRUTIVA",0,IF(B23="ETAPA",OFFSET(J23,-1,0)+1,OFFSET(J23,-1,0))) -> 1 | K23: =IF(B23="*","",IF(B23="ETAPA",S23,OFFSET(K23,-1,0))) -> ESTUDOS | PROJETOS | CONSULTORIAS | L23: =IF(B23="ETAPA",0,IF(B23="SUBETAPA",OFFSET(L23,-1,0)+1,OFFSET(L23,-1,0))) -> 2 | M23: =IF(B23="*","",IF(B23="SUBETAPA",S23,OFFSET(M23,-1,0))) -> Projetos | N23: =IF(B23="Subetapa",0,IF(B23="serviço",OFFSET(N23,-1,0)+1,OFFSET(N23,-1,0))) -> 2 | O23: =IF(B23="*","",IF(B23="SERVIÇO",S23,OFFSET(O23,-1,0))) -> Projeto Estrutural | P23: =IF(S23="","",IF(Orçamento!$B23="INSUMO",S23,"")) | Q23: =IF(B23="","",IF(B23="Serviço",S23,"")) -> Projeto Estrutural | R23: =IF(B23="serviço",U23,OFFSET(R23,-1,0)) -> 1 | S23: Projeto Estrutural | T23: VB | U23: 1 | W23: =IFERROR(IF(B23="INSUMO",_xlfn.XLOOKUP(S23,Insumos!A:A,Insumos!C:C),""),"Inserir Preço") | X23: =IF(B23="Complemento do insumo",V23,IF(R23="","",IF(B23="serviço",R23,IF(OR(B23="insumo"),V23*R23,"")))) -> 1 | Y23: =IF(B23="insumo",W23*V23,IF(B23="serviço",SUMIFS(Y:Y,B:B,"insumo",E:E,E23,I:I,I23),"")) -> 29900 | Z23: =IFERROR(IF(B23="Unidade Construtiva",SUMIFS(Z:Z,B:B,"Célula Construtiva",G:G,G23),IF(B23="célula construtiva",SUMIFS(Z:Z,B:B,"Insumo",I:I,I23,G:G,G23),IF(B23="ETAPA",SUMIFS(Z:Z,B:B,"Insumo",K:K,K23,I:I,I23,G:G,G23),IF(B23="subetapa",SUMIFS(Z:Z,M:M,M23,B:B,"insumo",K:K,K23,I:I,I23,G:G,G23),IF(B23="complemento do insumo",V23*W23,IF(B23="INSUMO",R23*V23*W23,X23*Y23)))))),"") -> 29900 | AB23: =IF(B23="insumo",_xlfn.XLOOKUP(S23,Insumos!A:A,Insumos!D:D),"") | AC23: =IFERROR(IF(B23="","",Z23/SUMIF(B:B,"INSUMO",Z:Z)),0) -> 0.0042894276 | AE23: =IFERROR(IF(OR(Z23="",Z23=0),"",IF(AF23="","",IF(AF23="R$/mês",Z23/OBRA!$D$12,IF(AF23="R$/m²",Z23/OBRA!$D$10,IF(AF23="R$/apto",Orçamento!Z23/OBRA!$D$11,""))))),"") -> 15.386753 | AF23: R$/m²
B24: Insumo | C24: =IF(B24="INSUMO",COUNTIFS(B:B,"INSUMO",S:S,S24),IF(B24="SERVIÇO",COUNTIFS(B:B,"SERVIÇO",S:S,S24),"")) -> 1 | D24: =IF(B24="Unidade Construtiva",TEXT(F24,"00"),IF(B24="Célula Construtiva",TEXT(H24,"00"),IF(B24="Etapa",CONCATENATE(TEXT(H24,"00"),".",TEXT(J24,"000")),IF(B24="Subetapa",CONCATENATE(TEXT(H24,"00"),".",TEXT(J24,"000"),".",TEXT(L24,"000")),IF(B24="Serviço",CONCATENATE(TEXT(H24,"00"),".",TEXT(J24,"000"),".",TEXT(L24,"000"),".",TEXT(N24,"000")),""))))) | E24: =IF(B24="*","",IFERROR(IF(B24="SERVIÇO",D24,OFFSET(E24,-1,0)),"")) -> 01.001.002.002 | F24: =IF($B24="UNIDADE CONSTRUTIVA",OFFSET(F24,-1,0)+1,LARGE(F$10:F23,1)) -> 1 | G24: =IF(B24="*","",IF(B24="UNIDADE CONSTRUTIVA",S24,OFFSET(G24,-1,0))) -> GERENCIAMENTO TÉCNICO E ADMINISTRATIVO | H24: =IF(B24="UNIDADE CONSTRUTIVA",0,IF(B24="CÉLULA CONSTRUTIVA",OFFSET(H24,-1,0)+1,OFFSET(H24,-1,0))) -> 1 | I24: =IF(B24="*","",IF(B24="CÉLULA CONSTRUTIVA",S24,OFFSET(I24,-1,0))) -> GERENCIAMENTO TÉCNICO | J24: =IF(B24="CÉLULA CONSTRUTIVA",0,IF(B24="ETAPA",OFFSET(J24,-1,0)+1,OFFSET(J24,-1,0))) -> 1 | K24: =IF(B24="*","",IF(B24="ETAPA",S24,OFFSET(K24,-1,0))) -> ESTUDOS | PROJETOS | CONSULTORIAS | L24: =IF(B24="ETAPA",0,IF(B24="SUBETAPA",OFFSET(L24,-1,0)+1,OFFSET(L24,-1,0))) -> 2 | M24: =IF(B24="*","",IF(B24="SUBETAPA",S24,OFFSET(M24,-1,0))) -> Projetos | N24: =IF(B24="Subetapa",0,IF(B24="serviço",OFFSET(N24,-1,0)+1,OFFSET(N24,-1,0))) -> 2 | O24: =IF(B24="*","",IF(B24="SERVIÇO",S24,OFFSET(O24,-1,0))) -> Projeto Estrutural | P24: =IF(S24="","",IF(Orçamento!$B24="INSUMO",S24,"")) -> PROJETO ESTRUTURAL | Q24: =IF(B24="","",IF(B24="Serviço",S24,"")) | R24: =IF(B24="serviço",U24,OFFSET(R24,-1,0)) -> 1 | S24: PROJETO ESTRUTURAL | T24: =_xlfn.XLOOKUP(S24,Insumos!$A$3:$A$371,Insumos!$B$3:$B$371) -> VB | U24: =IF($B24="insumo",R24,"") -> 1 | V24: 1 | W24: =IFERROR(IF(B24="INSUMO",_xlfn.XLOOKUP(S24,Insumos!A:A,Insumos!C:C),""),"Inserir Preço") -> 29900 | X24: =IF(B24="Complemento do insumo",V24,IF(R24="","",IF(B24="serviço",R24,IF(OR(B24="insumo"),V24*R24,"")))) -> 1 | Y24: =IF(B24="insumo",W24*V24,IF(B24="serviço",SUMIFS(Y:Y,B:B,"insumo",E:E,E24,I:I,I24),"")) -> 29900 | Z24: =IFERROR(IF(B24="Unidade Construtiva",SUMIFS(Z:Z,B:B,"Célula Construtiva",G:G,G24),IF(B24="célula construtiva",SUMIFS(Z:Z,B:B,"Insumo",I:I,I24,G:G,G24),IF(B24="ETAPA",SUMIFS(Z:Z,B:B,"Insumo",K:K,K24,I:I,I24,G:G,G24),IF(B24="subetapa",SUMIFS(Z:Z,M:M,M24,B:B,"insumo",K:K,K24,I:I,I24,G:G,G24),IF(B24="complemento do insumo",V24*W24,IF(B24="INSUMO",R24*V24*W24,X24*Y24)))))),"") -> 29900 | AB24: =IF(B24="insumo",_xlfn.XLOOKUP(S24,Insumos!A:A,Insumos!D:D),"") -> Recebido Cliente | AC24: =IFERROR(IF(B24="","",Z24/SUMIF(B:B,"INSUMO",Z:Z)),0) -> 0.0042894276 | AE24: =IFERROR(IF(OR(Z24="",Z24=0),"",IF(AF24="","",IF(AF24="R$/mês",Z24/OBRA!$D$12,IF(AF24="R$/m²",Z24/OBRA!$D$10,IF(AF24="R$/apto",Orçamento!Z24/OBRA!$D$11,""))))),"") -> 15.386753 | AF24: R$/m²
B25: Serviço | C25: =IF(B25="INSUMO",COUNTIFS(B:B,"INSUMO",S:S,S25),IF(B25="SERVIÇO",COUNTIFS(B:B,"SERVIÇO",S:S,S25),"")) -> 1 | D25: =IF(B25="Unidade Construtiva",TEXT(F25,"00"),IF(B25="Célula Construtiva",TEXT(H25,"00"),IF(B25="Etapa",CONCATENATE(TEXT(H25,"00"),".",TEXT(J25,"000")),IF(B25="Subetapa",CONCATENATE(TEXT(H25,"00"),".",TEXT(J25,"000"),".",TEXT(L25,"000")),IF(B25="Serviço",CONCATENATE(TEXT(H25,"00"),".",TEXT(J25,"000"),".",TEXT(L25,"000"),".",TEXT(N25,"000")),""))))) -> 01.001.002.003 | E25: =IF(B25="*","",IFERROR(IF(B25="SERVIÇO",D25,OFFSET(E25,-1,0)),"")) -> 01.001.002.003 | F25: =IF($B25="UNIDADE CONSTRUTIVA",OFFSET(F25,-1,0)+1,LARGE(F$10:F24,1)) -> 1 | G25: =IF(B25="*","",IF(B25="UNIDADE CONSTRUTIVA",S25,OFFSET(G25,-1,0))) -> GERENCIAMENTO TÉCNICO E ADMINISTRATIVO | H25: =IF(B25="UNIDADE CONSTRUTIVA",0,IF(B25="CÉLULA CONSTRUTIVA",OFFSET(H25,-1,0)+1,OFFSET(H25,-1,0))) -> 1 | I25: =IF(B25="*","",IF(B25="CÉLULA CONSTRUTIVA",S25,OFFSET(I25,-1,0))) -> GERENCIAMENTO TÉCNICO | J25: =IF(B25="CÉLULA CONSTRUTIVA",0,IF(B25="ETAPA",OFFSET(J25,-1,0)+1,OFFSET(J25,-1,0))) -> 1 | K25: =IF(B25="*","",IF(B25="ETAPA",S25,OFFSET(K25,-1,0))) -> ESTUDOS | PROJETOS | CONSULTORIAS | L25: =IF(B25="ETAPA",0,IF(B25="SUBETAPA",OFFSET(L25,-1,0)+1,OFFSET(L25,-1,0))) -> 2 | M25: =IF(B25="*","",IF(B25="SUBETAPA",S25,OFFSET(M25,-1,0))) -> Projetos | N25: =IF(B25="Subetapa",0,IF(B25="serviço",OFFSET(N25,-1,0)+1,OFFSET(N25,-1,0))) -> 3 | O25: =IF(B25="*","",IF(B25="SERVIÇO",S25,OFFSET(O25,-1,0))) -> Projeto eletrico | P25: =IF(S25="","",IF(Orçamento!$B25="INSUMO",S25,"")) | Q25: =IF(B25="","",IF(B25="Serviço",S25,"")) -> Projeto eletrico | R25: =IF(B25="serviço",U25,OFFSET(R25,-1,0)) -> 1 | S25: Projeto eletrico | T25: VB | U25: 1 | W25: =IFERROR(IF(B25="INSUMO",_xlfn.XLOOKUP(S25,Insumos!A:A,Insumos!C:C),""),"Inserir Preço") | X25: =IF(B25="Complemento do insumo",V25,IF(R25="","",IF(B25="serviço",R25,IF(OR(B25="insumo"),V25*R25,"")))) -> 1 | Y25: =IF(B25="insumo",W25*V25,IF(B25="serviço",SUMIFS(Y:Y,B:B,"insumo",E:E,E25,I:I,I25),"")) -> 5936 | Z25: =IFERROR(IF(B25="Unidade Construtiva",SUMIFS(Z:Z,B:B,"Célula Construtiva",G:G,G25),IF(B25="célula construtiva",SUMIFS(Z:Z,B:B,"Insumo",I:I,I25,G:G,G25),IF(B25="ETAPA",SUMIFS(Z:Z,B:B,"Insumo",K:K,K25,I:I,I25,G:G,G25),IF(B25="subetapa",SUMIFS(Z:Z,M:M,M25,B:B,"insumo",K:K,K25,I:I,I25,G:G,G25),IF(B25="complemento do insumo",V25*W25,IF(B25="INSUMO",R25*V25*W25,X25*Y25)))))),"") -> 5936 | AB25: =IF(B25="insumo",_xlfn.XLOOKUP(S25,Insumos!A:A,Insumos!D:D),"") | AC25: =IFERROR(IF(B25="","",Z25/SUMIF(B:B,"INSUMO",Z:Z)),0) -> 0.00085157332 | AE25: =IFERROR(IF(OR(Z25="",Z25=0),"",IF(AF25="","",IF(AF25="R$/mês",Z25/OBRA!$D$12,IF(AF25="R$/m²",Z25/OBRA!$D$10,IF(AF25="R$/apto",Orçamento!Z25/OBRA!$D$11,""))))),"") -> 3.0547079 | AF25: R$/m²
B26: Insumo | C26: =IF(B26="INSUMO",COUNTIFS(B:B,"INSUMO",S:S,S26),IF(B26="SERVIÇO",COUNTIFS(B:B,"SERVIÇO",S:S,S26),"")) -> 1 | D26: =IF(B26="Unidade Construtiva",TEXT(F26,"00"),IF(B26="Célula Construtiva",TEXT(H26,"00"),IF(B26="Etapa",CONCATENATE(TEXT(H26,"00"),".",TEXT(J26,"000")),IF(B26="Subetapa",CONCATENATE(TEXT(H26,"00"),".",TEXT(J26,"000"),".",TEXT(L26,"000")),IF(B26="Serviço",CONCATENATE(TEXT(H26,"00"),".",TEXT(J26,"000"),".",TEXT(L26,"000"),".",TEXT(N26,"000")),""))))) | E26: =IF(B26="*","",IFERROR(IF(B26="SERVIÇO",D26,OFFSET(E26,-1,0)),"")) -> 01.001.002.003 | F26: =IF($B26="UNIDADE CONSTRUTIVA",OFFSET(F26,-1,0)+1,LARGE(F$10:F25,1)) -> 1 | G26: =IF(B26="*","",IF(B26="UNIDADE CONSTRUTIVA",S26,OFFSET(G26,-1,0))) -> GERENCIAMENTO TÉCNICO E ADMINISTRATIVO | H26: =IF(B26="UNIDADE CONSTRUTIVA",0,IF(B26="CÉLULA CONSTRUTIVA",OFFSET(H26,-1,0)+1,OFFSET(H26,-1,0))) -> 1 | I26: =IF(B26="*","",IF(B26="CÉLULA CONSTRUTIVA",S26,OFFSET(I26,-1,0))) -> GERENCIAMENTO TÉCNICO | J26: =IF(B26="CÉLULA CONSTRUTIVA",0,IF(B26="ETAPA",OFFSET(J26,-1,0)+1,OFFSET(J26,-1,0))) -> 1 | K26: =IF(B26="*","",IF(B26="ETAPA",S26,OFFSET(K26,-1,0))) -> ESTUDOS | PROJETOS | CONSULTORIAS | L26: =IF(B26="ETAPA",0,IF(B26="SUBETAPA",OFFSET(L26,-1,0)+1,OFFSET(L26,-1,0))) -> 2 | M26: =IF(B26="*","",IF(B26="SUBETAPA",S26,OFFSET(M26,-1,0))) -> Projetos | N26: =IF(B26="Subetapa",0,IF(B26="serviço",OFFSET(N26,-1,0)+1,OFFSET(N26,-1,0))) -> 3 | O26: =IF(B26="*","",IF(B26="SERVIÇO",S26,OFFSET(O26,-1,0))) -> Projeto eletrico | P26: =IF(S26="","",IF(Orçamento!$B26="INSUMO",S26,"")) -> PROJETO ELETRICO | Q26: =IF(B26="","",IF(B26="Serviço",S26,"")) | R26: =IF(B26="serviço",U26,OFFSET(R26,-1,0)) -> 1 | S26: PROJETO ELETRICO | T26: =_xlfn.XLOOKUP(S26,Insumos!$A$3:$A$371,Insumos!$B$3:$B$371) -> VB | U26: =IF($B26="insumo",R26,"") -> 1 | V26: 1 | W26: =IFERROR(IF(B26="INSUMO",_xlfn.XLOOKUP(S26,Insumos!A:A,Insumos!C:C),""),"Inserir Preço") -> 5936 | X26: =IF(B26="Complemento do insumo",V26,IF(R26="","",IF(B26="serviço",R26,IF(OR(B26="insumo"),V26*R26,"")))) -> 1 | Y26: =IF(B26="insumo",W26*V26,IF(B26="serviço",SUMIFS(Y:Y,B:B,"insumo",E:E,E26,I:I,I26),"")) -> 5936 | Z26: =IFERROR(IF(B26="Unidade Construtiva",SUMIFS(Z:Z,B:B,"Célula Construtiva",G:G,G26),IF(B26="célula construtiva",SUMIFS(Z:Z,B:B,"Insumo",I:I,I26,G:G,G26),IF(B26="ETAPA",SUMIFS(Z:Z,B:B,"Insumo",K:K,K26,I:I,I26,G:G,G26),IF(B26="subetapa",SUMIFS(Z:Z,M:M,M26,B:B,"insumo",K:K,K26,I:I,I26,G:G,G26),IF(B26="complemento do insumo",V26*W26,IF(B26="INSUMO",R26*V26*W26,X26*Y26)))))),"") -> 5936 | AB26: =IF(B26="insumo",_xlfn.XLOOKUP(S26,Insumos!A:A,Insumos!D:D),"") -> Recebido Cliente | AC26: =IFERROR(IF(B26="","",Z26/SUMIF(B:B,"INSUMO",Z:Z)),0) -> 0.00085157332 | AE26: =IFERROR(IF(OR(Z26="",Z26=0),"",IF(AF26="","",IF(AF26="R$/mês",Z26/OBRA!$D$12,IF(AF26="R$/m²",Z26/OBRA!$D$10,IF(AF26="R$/apto",Orçamento!Z26/OBRA!$D$11,""))))),"") -> 3.0547079 | AF26: R$/m²
B27: Serviço | C27: =IF(B27="INSUMO",COUNTIFS(B:B,"INSUMO",S:S,S27),IF(B27="SERVIÇO",COUNTIFS(B:B,"SERVIÇO",S:S,S27),"")) -> 1 | D27: =IF(B27="Unidade Construtiva",TEXT(F27,"00"),IF(B27="Célula Construtiva",TEXT(H27,"00"),IF(B27="Etapa",CONCATENATE(TEXT(H27,"00"),".",TEXT(J27,"000")),IF(B27="Subetapa",CONCATENATE(TEXT(H27,"00"),".",TEXT(J27,"000"),".",TEXT(L27,"000")),IF(B27="Serviço",CONCATENATE(TEXT(H27,"00"),".",TEXT(J27,"000"),".",TEXT(L27,"000"),".",TEXT(N27,"000")),""))))) -> 01.001.002.004 | E27: =IF(B27="*","",IFERROR(IF(B27="SERVIÇO",D27,OFFSET(E27,-1,0)),"")) -> 01.001.002.004 | F27: =IF($B27="UNIDADE CONSTRUTIVA",OFFSET(F27,-1,0)+1,LARGE(F$10:F26,1)) -> 1 | G27: =IF(B27="*","",IF(B27="UNIDADE CONSTRUTIVA",S27,OFFSET(G27,-1,0))) -> GERENCIAMENTO TÉCNICO E ADMINISTRATIVO | H27: =IF(B27="UNIDADE CONSTRUTIVA",0,IF(B27="CÉLULA CONSTRUTIVA",OFFSET(H27,-1,0)+1,OFFSET(H27,-1,0))) -> 1 | I27: =IF(B27="*","",IF(B27="CÉLULA CONSTRUTIVA",S27,OFFSET(I27,-1,0))) -> GERENCIAMENTO TÉCNICO | J27: =IF(B27="CÉLULA CONSTRUTIVA",0,IF(B27="ETAPA",OFFSET(J27,-1,0)+1,OFFSET(J27,-1,0))) -> 1 | K27: =IF(B27="*","",IF(B27="ETAPA",S27,OFFSET(K27,-1,0))) -> ESTUDOS | PROJETOS | CONSULTORIAS | L27: =IF(B27="ETAPA",0,IF(B27="SUBETAPA",OFFSET(L27,-1,0)+1,OFFSET(L27,-1,0))) -> 2 | M27: =IF(B27="*","",IF(B27="SUBETAPA",S27,OFFSET(M27,-1,0))) -> Projetos | N27: =IF(B27="Subetapa",0,IF(B27="serviço",OFFSET(N27,-1,0)+1,OFFSET(N27,-1,0))) -> 4 | O27: =IF(B27="*","",IF(B27="SERVIÇO",S27,OFFSET(O27,-1,0))) -> Projeto hidrossanitário | P27: =IF(S27="","",IF(Orçamento!$B27="INSUMO",S27,"")) | Q27: =IF(B27="","",IF(B27="Serviço",S27,"")) -> Projeto hidrossanitário | R27: =IF(B27="serviço",U27,OFFSET(R27,-1,0)) -> 1 | S27: Projeto hidrossanitário | T27: VB | U27: 1 | W27: =IFERROR(IF(B27="INSUMO",_xlfn.XLOOKUP(S27,Insumos!A:A,Insumos!C:C),""),"Inserir Preço") | X27: =IF(B27="Complemento do insumo",V27,IF(R27="","",IF(B27="serviço",R27,IF(OR(B27="insumo"),V27*R27,"")))) -> 1 | Y27: =IF(B27="insumo",W27*V27,IF(B27="serviço",SUMIFS(Y:Y,B:B,"insumo",E:E,E27,I:I,I27),"")) -> 9500 | Z27: =IFERROR(IF(B27="Unidade Construtiva",SUMIFS(Z:Z,B:B,"Célula Construtiva",G:G,G27),IF(B27="célula construtiva",SUMIFS(Z:Z,B:B,"Insumo",I:I,I27,G:G,G27),IF(B27="ETAPA",SUMIFS(Z:Z,B:B,"Insumo",K:K,K27,I:I,I27,G:G,G27),IF(B27="subetapa",SUMIFS(Z:Z,M:M,M27,B:B,"insumo",K:K,K27,I:I,I27,G:G,G27),IF(B27="complemento do insumo",V27*W27,IF(B27="INSUMO",R27*V27*W27,X27*Y27)))))),"") -> 9500 | AB27: =IF(B27="insumo",_xlfn.XLOOKUP(S27,Insumos!A:A,Insumos!D:D),"") | AC27: =IFERROR(IF(B27="","",Z27/SUMIF(B:B,"INSUMO",Z:Z)),0) -> 0.0013628616 | AE27: =IFERROR(IF(OR(Z27="",Z27=0),"",IF(AF27="","",IF(AF27="R$/mês",Z27/OBRA!$D$12,IF(AF27="R$/m²",Z27/OBRA!$D$10,IF(AF27="R$/apto",Orçamento!Z27/OBRA!$D$11,""))))),"") -> 4.8887677 | AF27: R$/m²
B28: Insumo | C28: =IF(B28="INSUMO",COUNTIFS(B:B,"INSUMO",S:S,S28),IF(B28="SERVIÇO",COUNTIFS(B:B,"SERVIÇO",S:S,S28),"")) -> 1 | D28: =IF(B28="Unidade Construtiva",TEXT(F28,"00"),IF(B28="Célula Construtiva",TEXT(H28,"00"),IF(B28="Etapa",CONCATENATE(TEXT(H28,"00"),".",TEXT(J28,"000")),IF(B28="Subetapa",CONCATENATE(TEXT(H28,"00"),".",TEXT(J28,"000"),".",TEXT(L28,"000")),IF(B28="Serviço",CONCATENATE(TEXT(H28,"00"),".",TEXT(J28,"000"),".",TEXT(L28,"000"),".",TEXT(N28,"000")),""))))) | E28: =IF(B28="*","",IFERROR(IF(B28="SERVIÇO",D28,OFFSET(E28,-1,0)),"")) -> 01.001.002.004 | F28: =IF($B28="UNIDADE CONSTRUTIVA",OFFSET(F28,-1,0)+1,LARGE(F$10:F27,1)) -> 1 | G28: =IF(B28="*","",IF(B28="UNIDADE CONSTRUTIVA",S28,OFFSET(G28,-1,0))) -> GERENCIAMENTO TÉCNICO E ADMINISTRATIVO | H28: =IF(B28="UNIDADE CONSTRUTIVA",0,IF(B28="CÉLULA CONSTRUTIVA",OFFSET(H28,-1,0)+1,OFFSET(H28,-1,0))) -> 1 | I28: =IF(B28="*","",IF(B28="CÉLULA CONSTRUTIVA",S28,OFFSET(I28,-1,0))) -> GERENCIAMENTO TÉCNICO | J28: =IF(B28="CÉLULA CONSTRUTIVA",0,IF(B28="ETAPA",OFFSET(J28,-1,0)+1,OFFSET(J28,-1,0))) -> 1 | K28: =IF(B28="*","",IF(B28="ETAPA",S28,OFFSET(K28,-1,0))) -> ESTUDOS | PROJETOS | CONSULTORIAS | L28: =IF(B28="ETAPA",0,IF(B28="SUBETAPA",OFFSET(L28,-1,0)+1,OFFSET(L28,-1,0))) -> 2 | M28: =IF(B28="*","",IF(B28="SUBETAPA",S28,OFFSET(M28,-1,0))) -> Projetos | N28: =IF(B28="Subetapa",0,IF(B28="serviço",OFFSET(N28,-1,0)+1,OFFSET(N28,-1,0))) -> 4 | O28: =IF(B28="*","",IF(B28="SERVIÇO",S28,OFFSET(O28,-1,0))) -> Projeto hidrossanitário | P28: =IF(S28="","",IF(Orçamento!$B28="INSUMO",S28,"")) -> PROJETO HIDROSSANITARIO | Q28: =IF(B28="","",IF(B28="Serviço",S28,"")) | R28: =IF(B28="serviço",U28,OFFSET(R28,-1,0)) -> 1 | S28: PROJETO HIDROSSANITARIO | T28: =_xlfn.XLOOKUP(S28,Insumos!$A$3:$A$371,Insumos!$B$3:$B$371) -> VB | U28: =IF($B28="insumo",R28,"") -> 1 | V28: 1 | W28: =IFERROR(IF(B28="INSUMO",_xlfn.XLOOKUP(S28,Insumos!A:A,Insumos!C:C),""),"Inserir Preço") -> 9500 | X28: =IF(B28="Complemento do insumo",V28,IF(R28="","",IF(B28="serviço",R28,IF(OR(B28="insumo"),V28*R28,"")))) -> 1 | Y28: =IF(B28="insumo",W28*V28,IF(B28="serviço",SUMIFS(Y:Y,B:B,"insumo",E:E,E28,I:I,I28),"")) -> 9500 | Z28: =IFERROR(IF(B28="Unidade Construtiva",SUMIFS(Z:Z,B:B,"Célula Construtiva",G:G,G28),IF(B28="célula construtiva",SUMIFS(Z:Z,B:B,"Insumo",I:I,I28,G:G,G28),IF(B28="ETAPA",SUMIFS(Z:Z,B:B,"Insumo",K:K,K28,I:I,I28,G:G,G28),IF(B28="subetapa",SUMIFS(Z:Z,M:M,M28,B:B,"insumo",K:K,K28,I:I,I28,G:G,G28),IF(B28="complemento do insumo",V28*W28,IF(B28="INSUMO",R28*V28*W28,X28*Y28)))))),"") -> 9500 | AB28: =IF(B28="insumo",_xlfn.XLOOKUP(S28,Insumos!A:A,Insumos!D:D),"") -> Recebido Cliente | AC28: =IFERROR(IF(B28="","",Z28/SUMIF(B:B,"INSUMO",Z:Z)),0) -> 0.0013628616 | AE28: =IFERROR(IF(OR(Z28="",Z28=0),"",IF(AF28="","",IF(AF28="R$/mês",Z28/OBRA!$D$12,IF(AF28="R$/m²",Z28/OBRA!$D$10,IF(AF28="R$/apto",Orçamento!Z28/OBRA!$D$11,""))))),"") -> 4.8887677 | AF28: R$/m²
B29: Serviço | C29: =IF(B29="INSUMO",COUNTIFS(B:B,"INSUMO",S:S,S29),IF(B29="SERVIÇO",COUNTIFS(B:B,"SERVIÇO",S:S,S29),"")) -> 1 | D29: =IF(B29="Unidade Construtiva",TEXT(F29,"00"),IF(B29="Célula Construtiva",TEXT(H29,"00"),IF(B29="Etapa",CONCATENATE(TEXT(H29,"00"),".",TEXT(J29,"000")),IF(B29="Subetapa",CONCATENATE(TEXT(H29,"00"),".",TEXT(J29,"000"),".",TEXT(L29,"000")),IF(B29="Serviço",CONCATENATE(TEXT(H29,"00"),".",TEXT(J29,"000"),".",TEXT(L29,"000"),".",TEXT(N29,"000")),""))))) -> 01.001.002.005 | E29: =IF(B29="*","",IFERROR(IF(B29="SERVIÇO",D29,OFFSET(E29,-1,0)),"")) -> 01.001.002.005 | F29: =IF($B29="UNIDADE CONSTRUTIVA",OFFSET(F29,-1,0)+1,LARGE(F$10:F28,1)) -> 1 | G29: =IF(B29="*","",IF(B29="UNIDADE CONSTRUTIVA",S29,OFFSET(G29,-1,0))) -> GERENCIAMENTO TÉCNICO E ADMINISTRATIVO | H29: =IF(B29="UNIDADE CONSTRUTIVA",0,IF(B29="CÉLULA CONSTRUTIVA",OFFSET(H29,-1,0)+1,OFFSET(H29,-1,0))) -> 1 | I29: =IF(B29="*","",IF(B29="CÉLULA CONSTRUTIVA",S29,OFFSET(I29,-1,0))) -> GERENCIAMENTO TÉCNICO | J29: =IF(B29="CÉLULA CONSTRUTIVA",0,IF(B29="ETAPA",OFFSET(J29,-1,0)+1,OFFSET(J29,-1,0))) -> 1 | K29: =IF(B29="*","",IF(B29="ETAPA",S29,OFFSET(K29,-1,0))) -> ESTUDOS | PROJETOS | CONSULTORIAS | L29: =IF(B29="ETAPA",0,IF(B29="SUBETAPA",OFFSET(L29,-1,0)+1,OFFSET(L29,-1,0))) -> 2 | M29: =IF(B29="*","",IF(B29="SUBETAPA",S29,OFFSET(M29,-1,0))) -> Projetos | N29: =IF(B29="Subetapa",0,IF(B29="serviço",OFFSET(N29,-1,0)+1,OFFSET(N29,-1,0))) -> 5 | O29: =IF(B29="*","",IF(B29="SERVIÇO",S29,OFFSET(O29,-1,0))) -> Projeto Comunicação e Dados | P29: =IF(S29="","",IF(Orçamento!$B29="INSUMO",S29,"")) | Q29: =IF(B29="","",IF(B29="Serviço",S29,"")) -> Projeto Comunicação e Dados | R29: =IF(B29="serviço",U29,OFFSET(R29,-1,0)) -> 1 | S29: Projeto Comunicação e Dados | T29: VB | U29: 1 | W29: =IFERROR(IF(B29="INSUMO",_xlfn.XLOOKUP(S29,Insumos!A:A,Insumos!C:C),""),"Inserir Preço") | X29: =IF(B29="Complemento do insumo",V29,IF(R29="","",IF(B29="serviço",R29,IF(OR(B29="insumo"),V29*R29,"")))) -> 1 | Y29: =IF(B29="insumo",W29*V29,IF(B29="serviço",SUMIFS(Y:Y,B:B,"insumo",E:E,E29,I:I,I29),"")) -> 2967 | Z29: =IFERROR(IF(B29="Unidade Construtiva",SUMIFS(Z:Z,B:B,"Célula Construtiva",G:G,G29),IF(B29="célula construtiva",SUMIFS(Z:Z,B:B,"Insumo",I:I,I29,G:G,G29),IF(B29="ETAPA",SUMIFS(Z:Z,B:B,"Insumo",K:K,K29,I:I,I29,G:G,G29),IF(B29="subetapa",SUMIFS(Z:Z,M:M,M29,B:B,"insumo",K:K,K29,I:I,I29,G:G,G29),IF(B29="complemento do insumo",V29*W29,IF(B29="INSUMO",R29*V29*W29,X29*Y29)))))),"") -> 2967 | AB29: =IF(B29="insumo",_xlfn.XLOOKUP(S29,Insumos!A:A,Insumos!D:D),"") | AC29: =IFERROR(IF(B29="","",Z29/SUMIF(B:B,"INSUMO",Z:Z)),0) -> 0.0004256432 | AE29: =IFERROR(IF(OR(Z29="",Z29=0),"",IF(AF29="","",IF(AF29="R$/mês",Z29/OBRA!$D$12,IF(AF29="R$/m²",Z29/OBRA!$D$10,IF(AF29="R$/apto",Orçamento!Z29/OBRA!$D$11,""))))),"") -> 1.5268393 | AF29: R$/m²
B30: Insumo | C30: =IF(B30="INSUMO",COUNTIFS(B:B,"INSUMO",S:S,S30),IF(B30="SERVIÇO",COUNTIFS(B:B,"SERVIÇO",S:S,S30),"")) -> 1 | D30: =IF(B30="Unidade Construtiva",TEXT(F30,"00"),IF(B30="Célula Construtiva",TEXT(H30,"00"),IF(B30="Etapa",CONCATENATE(TEXT(H30,"00"),".",TEXT(J30,"000")),IF(B30="Subetapa",CONCATENATE(TEXT(H30,"00"),".",TEXT(J30,"000"),".",TEXT(L30,"000")),IF(B30="Serviço",CONCATENATE(TEXT(H30,"00"),".",TEXT(J30,"000"),".",TEXT(L30,"000"),".",TEXT(N30,"000")),""))))) | E30: =IF(B30="*","",IFERROR(IF(B30="SERVIÇO",D30,OFFSET(E30,-1,0)),"")) -> 01.001.002.005 | F30: =IF($B30="UNIDADE CONSTRUTIVA",OFFSET(F30,-1,0)+1,LARGE(F$10:F29,1)) -> 1 | G30: =IF(B30="*","",IF(B30="UNIDADE CONSTRUTIVA",S30,OFFSET(G30,-1,0))) -> GERENCIAMENTO TÉCNICO E ADMINISTRATIVO | H30: =IF(B30="UNIDADE CONSTRUTIVA",0,IF(B30="CÉLULA CONSTRUTIVA",OFFSET(H30,-1,0)+1,OFFSET(H30,-1,0))) -> 1 | I30: =IF(B30="*","",IF(B30="CÉLULA CONSTRUTIVA",S30,OFFSET(I30,-1,0))) -> GERENCIAMENTO TÉCNICO | J30: =IF(B30="CÉLULA CONSTRUTIVA",0,IF(B30="ETAPA",OFFSET(J30,-1,0)+1,OFFSET(J30,-1,0))) -> 1 | K30: =IF(B30="*","",IF(B30="ETAPA",S30,OFFSET(K30,-1,0))) -> ESTUDOS | PROJETOS | CONSULTORIAS | L30: =IF(B30="ETAPA",0,IF(B30="SUBETAPA",OFFSET(L30,-1,0)+1,OFFSET(L30,-1,0))) -> 2 | M30: =IF(B30="*","",IF(B30="SUBETAPA",S30,OFFSET(M30,-1,0))) -> Projetos | N30: =IF(B30="Subetapa",0,IF(B30="serviço",OFFSET(N30,-1,0)+1,OFFSET(N30,-1,0))) -> 5 | O30: =IF(B30="*","",IF(B30="SERVIÇO",S30,OFFSET(O30,-1,0))) -> Projeto Comunicação e Dados | P30: =IF(S30="","",IF(Orçamento!$B30="INSUMO",S30,"")) -> Projeto Comunicação e Dados | Q30: =IF(B30="","",IF(B30="Serviço",S30,"")) | R30: =IF(B30="serviço",U30,OFFSET(R30,-1,0)) -> 1 | S30: Projeto Comunicação e Dados | T30: =_xlfn.XLOOKUP(S30,Insumos!$A$3:$A$371,Insumos!$B$3:$B$371) -> VB | U30: =IF($B30="insumo",R30,"") -> 1 | V30: 1 | W30: =IFERROR(IF(B30="INSUMO",_xlfn.XLOOKUP(S30,Insumos!A:A,Insumos!C:C),""),"Inserir Preço") -> 2967 | X30: =IF(B30="Complemento do insumo",V30,IF(R30="","",IF(B30="serviço",R30,IF(OR(B30="insumo"),V30*R30,"")))) -> 1 | Y30: =IF(B30="insumo",W30*V30,IF(B30="serviço",SUMIFS(Y:Y,B:B,"insumo",E:E,E30,I:I,I30),"")) -> 2967 | Z30: =IFERROR(IF(B30="Unidade Construtiva",SUMIFS(Z:Z,B:B,"Célula Construtiva",G:G,G30),IF(B30="célula construtiva",SUMIFS(Z:Z,B:B,"Insumo",I:I,I30,G:G,G30),IF(B30="ETAPA",SUMIFS(Z:Z,B:B,"Insumo",K:K,K30,I:I,I30,G:G,G30),IF(B30="subetapa",SUMIFS(Z:Z,M:M,M30,B:B,"insumo",K:K,K30,I:I,I30,G:G,G30),IF(B30="complemento do insumo",V30*W30,IF(B30="INSUMO",R30*V30*W30,X30*Y30)))))),"") -> 2967 | AB30: =IF(B30="insumo",_xlfn.XLOOKUP(S30,Insumos!A:A,Insumos!D:D),"") -> Recebido Cliente | AC30: =IFERROR(IF(B30="","",Z30/SUMIF(B:B,"INSUMO",Z:Z)),0) -> 0.0004256432 | AE30: =IFERROR(IF(OR(Z30="",Z30=0),"",IF(AF30="","",IF(AF30="R$/mês",Z30/OBRA!$D$12,IF(AF30="R$/m²",Z30/OBRA!$D$10,IF(AF30="R$/apto",Orçamento!Z30/OBRA!$D$11,""))))),"") -> 1.5268393 | AF30: R$/m²
B31: Serviço | C31: =IF(B31="INSUMO",COUNTIFS(B:B,"INSUMO",S:S,S31),IF(B31="SERVIÇO",COUNTIFS(B:B,"SERVIÇO",S:S,S31),"")) -> 1 | D31: =IF(B31="Unidade Construtiva",TEXT(F31,"00"),IF(B31="Célula Construtiva",TEXT(H31,"00"),IF(B31="Etapa",CONCATENATE(TEXT(H31,"00"),".",TEXT(J31,"000")),IF(B31="Subetapa",CONCATENATE(TEXT(H31,"00"),".",TEXT(J31,"000"),".",TEXT(L31,"000")),IF(B31="Serviço",CONCATENATE(TEXT(H31,"00"),".",TEXT(J31,"000"),".",TEXT(L31,"000"),".",TEXT(N31,"000")),""))))) -> 01.001.002.006 | E31: =IF(B31="*","",IFERROR(IF(B31="SERVIÇO",D31,OFFSET(E31,-1,0)),"")) -> 01.001.002.006 | F31: =IF($B31="UNIDADE CONSTRUTIVA",OFFSET(F31,-1,0)+1,LARGE(F$10:F30,1)) -> 1 | G31: =IF(B31="*","",IF(B31="UNIDADE CONSTRUTIVA",S31,OFFSET(G31,-1,0))) -> GERENCIAMENTO TÉCNICO E ADMINISTRATIVO | H31: =IF(B31="UNIDADE CONSTRUTIVA",0,IF(B31="CÉLULA CONSTRUTIVA",OFFSET(H31,-1,0)+1,OFFSET(H31,-1,0))) -> 1 | I31: =IF(B31="*","",IF(B31="CÉLULA CONSTRUTIVA",S31,OFFSET(I31,-1,0))) -> GERENCIAMENTO TÉCNICO | J31: =IF(B31="CÉLULA CONSTRUTIVA",0,IF(B31="ETAPA",OFFSET(J31,-1,0)+1,OFFSET(J31,-1,0))) -> 1 | K31: =IF(B31="*","",IF(B31="ETAPA",S31,OFFSET(K31,-1,0))) -> ESTUDOS | PROJETOS | CONSULTORIAS | L31: =IF(B31="ETAPA",0,IF(B31="SUBETAPA",OFFSET(L31,-1,0)+1,OFFSET(L31,-1,0))) -> 2 | M31: =IF(B31="*","",IF(B31="SUBETAPA",S31,OFFSET(M31,-1,0))) -> Projetos | N31: =IF(B31="Subetapa",0,IF(B31="serviço",OFFSET(N31,-1,0)+1,OFFSET(N31,-1,0))) -> 6 | O31: =IF(B31="*","",IF(B31="SERVIÇO",S31,OFFSET(O31,-1,0))) -> Projeto de Telefonia | P31: =IF(S31="","",IF(Orçamento!$B31="INSUMO",S31,"")) | Q31: =IF(B31="","",IF(B31="Serviço",S31,"")) -> Projeto de Telefonia | R31: =IF(B31="serviço",U31,OFFSET(R31,-1,0)) -> 1 | S31: Projeto de Telefonia | T31: VB | U31: 1 | W31: =IFERROR(IF(B31="INSUMO",_xlfn.XLOOKUP(S31,Insumos!A:A,Insumos!C:C),""),"Inserir Preço") | X31: =IF(B31="Complemento do insumo",V31,IF(R31="","",IF(B31="serviço",R31,IF(OR(B31="insumo"),V31*R31,"")))) -> 1 | Y31: =IF(B31="insumo",W31*V31,IF(B31="serviço",SUMIFS(Y:Y,B:B,"insumo",E:E,E31,I:I,I31),"")) -> 2967 | Z31: =IFERROR(IF(B31="Unidade Construtiva",SUMIFS(Z:Z,B:B,"Célula Construtiva",G:G,G31),IF(B31="célula construtiva",SUMIFS(Z:Z,B:B,"Insumo",I:I,I31,G:G,G31),IF(B31="ETAPA",SUMIFS(Z:Z,B:B,"Insumo",K:K,K31,I:I,I31,G:G,G31),IF(B31="subetapa",SUMIFS(Z:Z,M:M,M31,B:B,"insumo",K:K,K31,I:I,I31,G:G,G31),IF(B31="complemento do insumo",V31*W31,IF(B31="INSUMO",R31*V31*W31,X31*Y31)))))),"") -> 2967 | AB31: =IF(B31="insumo",_xlfn.XLOOKUP(S31,Insumos!A:A,Insumos!D:D),"") | AC31: =IFERROR(IF(B31="","",Z31/SUMIF(B:B,"INSUMO",Z:Z)),0) -> 0.0004256432 | AE31: =IFERROR(IF(OR(Z31="",Z31=0),"",IF(AF31="","",IF(AF31="R$/mês",Z31/OBRA!$D$12,IF(AF31="R$/m²",Z31/OBRA!$D$10,IF(AF31="R$/apto",Orçamento!Z31/OBRA!$D$11,""))))),"") -> 1.5268393 | AF31: R$/m²
B32: Insumo | C32: =IF(B32="INSUMO",COUNTIFS(B:B,"INSUMO",S:S,S32),IF(B32="SERVIÇO",COUNTIFS(B:B,"SERVIÇO",S:S,S32),"")) -> 1 | D32: =IF(B32="Unidade Construtiva",TEXT(F32,"00"),IF(B32="Célula Construtiva",TEXT(H32,"00"),IF(B32="Etapa",CONCATENATE(TEXT(H32,"00"),".",TEXT(J32,"000")),IF(B32="Subetapa",CONCATENATE(TEXT(H32,"00"),".",TEXT(J32,"000"),".",TEXT(L32,"000")),IF(B32="Serviço",CONCATENATE(TEXT(H32,"00"),".",TEXT(J32,"000"),".",TEXT(L32,"000"),".",TEXT(N32,"000")),""))))) | E32: =IF(B32="*","",IFERROR(IF(B32="SERVIÇO",D32,OFFSET(E32,-1,0)),"")) -> 01.001.002.006 | F32: =IF($B32="UNIDADE CONSTRUTIVA",OFFSET(F32,-1,0)+1,LARGE(F$10:F31,1)) -> 1 | G32: =IF(B32="*","",IF(B32="UNIDADE CONSTRUTIVA",S32,OFFSET(G32,-1,0))) -> GERENCIAMENTO TÉCNICO E ADMINISTRATIVO | H32: =IF(B32="UNIDADE CONSTRUTIVA",0,IF(B32="CÉLULA CONSTRUTIVA",OFFSET(H32,-1,0)+1,OFFSET(H32,-1,0))) -> 1 | I32: =IF(B32="*","",IF(B32="CÉLULA CONSTRUTIVA",S32,OFFSET(I32,-1,0))) -> GERENCIAMENTO TÉCNICO | J32: =IF(B32="CÉLULA CONSTRUTIVA",0,IF(B32="ETAPA",OFFSET(J32,-1,0)+1,OFFSET(J32,-1,0))) -> 1 | K32: =IF(B32="*","",IF(B32="ETAPA",S32,OFFSET(K32,-1,0))) -> ESTUDOS | PROJETOS | CONSULTORIAS | L32: =IF(B32="ETAPA",0,IF(B32="SUBETAPA",OFFSET(L32,-1,0)+1,OFFSET(L32,-1,0))) -> 2 | M32: =IF(B32="*","",IF(B32="SUBETAPA",S32,OFFSET(M32,-1,0))) -> Projetos | N32: =IF(B32="Subetapa",0,IF(B32="serviço",OFFSET(N32,-1,0)+1,OFFSET(N32,-1,0))) -> 6 | O32: =IF(B32="*","",IF(B32="SERVIÇO",S32,OFFSET(O32,-1,0))) -> Projeto de Telefonia | P32: =IF(S32="","",IF(Orçamento!$B32="INSUMO",S32,"")) -> Projeto Telefonia | Q32: =IF(B32="","",IF(B32="Serviço",S32,"")) | R32: =IF(B32="serviço",U32,OFFSET(R32,-1,0)) -> 1 | S32: Projeto Telefonia | T32: =_xlfn.XLOOKUP(S32,Insumos!$A$3:$A$371,Insumos!$B$3:$B$371) -> VB | U32: =IF($B32="insumo",R32,"") -> 1 | V32: 1 | W32: =IFERROR(IF(B32="INSUMO",_xlfn.XLOOKUP(S32,Insumos!A:A,Insumos!C:C),""),"Inserir Preço") -> 2967 | X32: =IF(B32="Complemento do insumo",V32,IF(R32="","",IF(B32="serviço",R32,IF(OR(B32="insumo"),V32*R32,"")))) -> 1 | Y32: =IF(B32="insumo",W32*V32,IF(B32="serviço",SUMIFS(Y:Y,B:B,"insumo",E:E,E32,I:I,I32),"")) -> 2967 | Z32: =IFERROR(IF(B32="Unidade Construtiva",SUMIFS(Z:Z,B:B,"Célula Construtiva",G:G,G32),IF(B32="célula construtiva",SUMIFS(Z:Z,B:B,"Insumo",I:I,I32,G:G,G32),IF(B32="ETAPA",SUMIFS(Z:Z,B:B,"Insumo",K:K,K32,I:I,I32,G:G,G32),IF(B32="subetapa",SUMIFS(Z:Z,M:M,M32,B:B,"insumo",K:K,K32,I:I,I32,G:G,G32),IF(B32="complemento do insumo",V32*W32,IF(B32="INSUMO",R32*V32*W32,X32*Y32)))))),"") -> 2967 | AB32: =IF(B32="insumo",_xlfn.XLOOKUP(S32,Insumos!A:A,Insumos!D:D),"") -> Recebido Cliente | AC32: =IFERROR(IF(B32="","",Z32/SUMIF(B:B,"INSUMO",Z:Z)),0) -> 0.0004256432 | AE32: =IFERROR(IF(OR(Z32="",Z32=0),"",IF(AF32="","",IF(AF32="R$/mês",Z32/OBRA!$D$12,IF(AF32="R$/m²",Z32/OBRA!$D$10,IF(AF32="R$/apto",Orçamento!Z32/OBRA!$D$11,""))))),"") -> 1.5268393 | AF32: R$/m²
B33: Serviço | C33: =IF(B33="INSUMO",COUNTIFS(B:B,"INSUMO",S:S,S33),IF(B33="SERVIÇO",COUNTIFS(B:B,"SERVIÇO",S:S,S33),"")) -> 1 | D33: =IF(B33="Unidade Construtiva",TEXT(F33,"00"),IF(B33="Célula Construtiva",TEXT(H33,"00"),IF(B33="Etapa",CONCATENATE(TEXT(H33,"00"),".",TEXT(J33,"000")),IF(B33="Subetapa",CONCATENATE(TEXT(H33,"00"),".",TEXT(J33,"000"),".",TEXT(L33,"000")),IF(B33="Serviço",CONCATENATE(TEXT(H33,"00"),".",TEXT(J33,"000"),".",TEXT(L33,"000"),".",TEXT(N33,"000")),""))))) -> 01.001.002.007 | E33: =IF(B33="*","",IFERROR(IF(B33="SERVIÇO",D33,OFFSET(E33,-1,0)),"")) -> 01.001.002.007 | F33: =IF($B33="UNIDADE CONSTRUTIVA",OFFSET(F33,-1,0)+1,LARGE(F$10:F32,1)) -> 1 | G33: =IF(B33="*","",IF(B33="UNIDADE CONSTRUTIVA",S33,OFFSET(G33,-1,0))) -> GERENCIAMENTO TÉCNICO E ADMINISTRATIVO | H33: =IF(B33="UNIDADE CONSTRUTIVA",0,IF(B33="CÉLULA CONSTRUTIVA",OFFSET(H33,-1,0)+1,OFFSET(H33,-1,0))) -> 1 | I33: =IF(B33="*","",IF(B33="CÉLULA CONSTRUTIVA",S33,OFFSET(I33,-1,0))) -> GERENCIAMENTO TÉCNICO | J33: =IF(B33="CÉLULA CONSTRUTIVA",0,IF(B33="ETAPA",OFFSET(J33,-1,0)+1,OFFSET(J33,-1,0))) -> 1 | K33: =IF(B33="*","",IF(B33="ETAPA",S33,OFFSET(K33,-1,0))) -> ESTUDOS | PROJETOS | CONSULTORIAS | L33: =IF(B33="ETAPA",0,IF(B33="SUBETAPA",OFFSET(L33,-1,0)+1,OFFSET(L33,-1,0))) -> 2 | M33: =IF(B33="*","",IF(B33="SUBETAPA",S33,OFFSET(M33,-1,0))) -> Projetos | N33: =IF(B33="Subetapa",0,IF(B33="serviço",OFFSET(N33,-1,0)+1,OFFSET(N33,-1,0))) -> 7 | O33: =IF(B33="*","",IF(B33="SERVIÇO",S33,OFFSET(O33,-1,0))) -> Projeto de Prevenção Combate a Incêndio | P33: =IF(S33="","",IF(Orçamento!$B33="INSUMO",S33,"")) | Q33: =IF(B33="","",IF(B33="Serviço",S33,"")) -> Projeto de Prevenção Combate a Incêndio | R33: =IF(B33="serviço",U33,OFFSET(R33,-1,0)) -> 1 | S33: Projeto de Prevenção Combate a Incêndio | T33: VB | U33: 1 | W33: =IFERROR(IF(B33="INSUMO",_xlfn.XLOOKUP(S33,Insumos!A:A,Insumos!C:C),""),"Inserir Preço") | X33: =IF(B33="Complemento do insumo",V33,IF(R33="","",IF(B33="serviço",R33,IF(OR(B33="insumo"),V33*R33,"")))) -> 1 | Y33: =IF(B33="insumo",W33*V33,IF(B33="serviço",SUMIFS(Y:Y,B:B,"insumo",E:E,E33,I:I,I33),"")) -> 9500 | Z33: =IFERROR(IF(B33="Unidade Construtiva",SUMIFS(Z:Z,B:B,"Célula Construtiva",G:G,G33),IF(B33="célula construtiva",SUMIFS(Z:Z,B:B,"Insumo",I:I,I33,G:G,G33),IF(B33="ETAPA",SUMIFS(Z:Z,B:B,"Insumo",K:K,K33,I:I,I33,G:G,G33),IF(B33="subetapa",SUMIFS(Z:Z,M:M,M33,B:B,"insumo",K:K,K33,I:I,I33,G:G,G33),IF(B33="complemento do insumo",V33*W33,IF(B33="INSUMO",R33*V33*W33,X33*Y33)))))),"") -> 9500 | AB33: =IF(B33="insumo",_xlfn.XLOOKUP(S33,Insumos!A:A,Insumos!D:D),"") | AC33: =IFERROR(IF(B33="","",Z33/SUMIF(B:B,"INSUMO",Z:Z)),0) -> 0.0013628616 | AE33: =IFERROR(IF(OR(Z33="",Z33=0),"",IF(AF33="","",IF(AF33="R$/mês",Z33/OBRA!$D$12,IF(AF33="R$/m²",Z33/OBRA!$D$10,IF(AF33="R$/apto",Orçamento!Z33/OBRA!$D$11,""))))),"") -> 4.8887677 | AF33: R$/m²
B34: Insumo | C34: =IF(B34="INSUMO",COUNTIFS(B:B,"INSUMO",S:S,S34),IF(B34="SERVIÇO",COUNTIFS(B:B,"SERVIÇO",S:S,S34),"")) -> 1 | D34: =IF(B34="Unidade Construtiva",TEXT(F34,"00"),IF(B34="Célula Construtiva",TEXT(H34,"00"),IF(B34="Etapa",CONCATENATE(TEXT(H34,"00"),".",TEXT(J34,"000")),IF(B34="Subetapa",CONCATENATE(TEXT(H34,"00"),".",TEXT(J34,"000"),".",TEXT(L34,"000")),IF(B34="Serviço",CONCATENATE(TEXT(H34,"00"),".",TEXT(J34,"000"),".",TEXT(L34,"000"),".",TEXT(N34,"000")),""))))) | E34: =IF(B34="*","",IFERROR(IF(B34="SERVIÇO",D34,OFFSET(E34,-1,0)),"")) -> 01.001.002.007 | F34: =IF($B34="UNIDADE CONSTRUTIVA",OFFSET(F34,-1,0)+1,LARGE(F$10:F33,1)) -> 1 | G34: =IF(B34="*","",IF(B34="UNIDADE CONSTRUTIVA",S34,OFFSET(G34,-1,0))) -> GERENCIAMENTO TÉCNICO E ADMINISTRATIVO | H34: =IF(B34="UNIDADE CONSTRUTIVA",0,IF(B34="CÉLULA CONSTRUTIVA",OFFSET(H34,-1,0)+1,OFFSET(H34,-1,0))) -> 1 | I34: =IF(B34="*","",IF(B34="CÉLULA CONSTRUTIVA",S34,OFFSET(I34,-1,0))) -> GERENCIAMENTO TÉCNICO | J34: =IF(B34="CÉLULA CONSTRUTIVA",0,IF(B34="ETAPA",OFFSET(J34,-1,0)+1,OFFSET(J34,-1,0))) -> 1 | K34: =IF(B34="*","",IF(B34="ETAPA",S34,OFFSET(K34,-1,0))) -> ESTUDOS | PROJETOS | CONSULTORIAS | L34: =IF(B34="ETAPA",0,IF(B34="SUBETAPA",OFFSET(L34,-1,0)+1,OFFSET(L34,-1,0))) -> 2 | M34: =IF(B34="*","",IF(B34="SUBETAPA",S34,OFFSET(M34,-1,0))) -> Projetos | N34: =IF(B34="Subetapa",0,IF(B34="serviço",OFFSET(N34,-1,0)+1,OFFSET(N34,-1,0))) -> 7 | O34: =IF(B34="*","",IF(B34="SERVIÇO",S34,OFFSET(O34,-1,0))) -> Projeto de Prevenção Combate a Incêndio | P34: =IF(S34="","",IF(Orçamento!$B34="INSUMO",S34,"")) -> Projeto PCI (Prevenção e combate a Incêndios) | Q34: =IF(B34="","",IF(B34="Serviço",S34,"")) | R34: =IF(B34="serviço",U34,OFFSET(R34,-1,0)) -> 1 | S34: Projeto PCI (Prevenção e combate a Incêndios) | T34: =_xlfn.XLOOKUP(S34,Insumos!$A$3:$A$371,Insumos!$B$3:$B$371) -> VB | U34: =IF($B34="insumo",R34,"") -> 1 | V34: 1 | W34: =IFERROR(IF(B34="INSUMO",_xlfn.XLOOKUP(S34,Insumos!A:A,Insumos!C:C),""),"Inserir Preço") -> 9500 | X34: =IF(B34="Complemento do insumo",V34,IF(R34="","",IF(B34="serviço",R34,IF(OR(B34="insumo"),V34*R34,"")))) -> 1 | Y34: =IF(B34="insumo",W34*V34,IF(B34="serviço",SUMIFS(Y:Y,B:B,"insumo",E:E,E34,I:I,I34),"")) -> 9500 | Z34: =IFERROR(IF(B34="Unidade Construtiva",SUMIFS(Z:Z,B:B,"Célula Construtiva",G:G,G34),IF(B34="célula construtiva",SUMIFS(Z:Z,B:B,"Insumo",I:I,I34,G:G,G34),IF(B34="ETAPA",SUMIFS(Z:Z,B:B,"Insumo",K:K,K34,I:I,I34,G:G,G34),IF(B34="subetapa",SUMIFS(Z:Z,M:M,M34,B:B,"insumo",K:K,K34,I:I,I34,G:G,G34),IF(B34="complemento do insumo",V34*W34,IF(B34="INSUMO",R34*V34*W34,X34*Y34)))))),"") -> 9500 | AB34: =IF(B34="insumo",_xlfn.XLOOKUP(S34,Insumos!A:A,Insumos!D:D),"") -> Recebido Cliente | AC34: =IFERROR(IF(B34="","",Z34/SUMIF(B:B,"INSUMO",Z:Z)),0) -> 0.0013628616 | AE34: =IFERROR(IF(OR(Z34="",Z34=0),"",IF(AF34="","",IF(AF34="R$/mês",Z34/OBRA!$D$12,IF(AF34="R$/m²",Z34/OBRA!$D$10,IF(AF34="R$/apto",Orçamento!Z34/OBRA!$D$11,""))))),"") -> 4.8887677 | AF34: R$/m²
B35: Serviço | C35: =IF(B35="INSUMO",COUNTIFS(B:B,"INSUMO",S:S,S35),IF(B35="SERVIÇO",COUNTIFS(B:B,"SERVIÇO",S:S,S35),"")) -> 1 | D35: =IF(B35="Unidade Construtiva",TEXT(F35,"00"),IF(B35="Célula Construtiva",TEXT(H35,"00"),IF(B35="Etapa",CONCATENATE(TEXT(H35,"00"),".",TEXT(J35,"000")),IF(B35="Subetapa",CONCATENATE(TEXT(H35,"00"),".",TEXT(J35,"000"),".",TEXT(L35,"000")),IF(B35="Serviço",CONCATENATE(TEXT(H35,"00"),".",TEXT(J35,"000"),".",TEXT(L35,"000"),".",TEXT(N35,"000")),""))))) -> 01.001.002.008 | E35: =IF(B35="*","",IFERROR(IF(B35="SERVIÇO",D35,OFFSET(E35,-1,0)),"")) -> 01.001.002.008 | F35: =IF($B35="UNIDADE CONSTRUTIVA",OFFSET(F35,-1,0)+1,LARGE(F$10:F34,1)) -> 1 | G35: =IF(B35="*","",IF(B35="UNIDADE CONSTRUTIVA",S35,OFFSET(G35,-1,0))) -> GERENCIAMENTO TÉCNICO E ADMINISTRATIVO | H35: =IF(B35="UNIDADE CONSTRUTIVA",0,IF(B35="CÉLULA CONSTRUTIVA",OFFSET(H35,-1,0)+1,OFFSET(H35,-1,0))) -> 1 | I35: =IF(B35="*","",IF(B35="CÉLULA CONSTRUTIVA",S35,OFFSET(I35,-1,0))) -> GERENCIAMENTO TÉCNICO | J35: =IF(B35="CÉLULA CONSTRUTIVA",0,IF(B35="ETAPA",OFFSET(J35,-1,0)+1,OFFSET(J35,-1,0))) -> 1 | K35: =IF(B35="*","",IF(B35="ETAPA",S35,OFFSET(K35,-1,0))) -> ESTUDOS | PROJETOS | CONSULTORIAS | L35: =IF(B35="ETAPA",0,IF(B35="SUBETAPA",OFFSET(L35,-1,0)+1,OFFSET(L35,-1,0))) -> 2 | M35: =IF(B35="*","",IF(B35="SUBETAPA",S35,OFFSET(M35,-1,0))) -> Projetos | N35: =IF(B35="Subetapa",0,IF(B35="serviço",OFFSET(N35,-1,0)+1,OFFSET(N35,-1,0))) -> 8 | O35: =IF(B35="*","",IF(B35="SERVIÇO",S35,OFFSET(O35,-1,0))) -> Projeto de Segurança do Trabalho | P35: =IF(S35="","",IF(Orçamento!$B35="INSUMO",S35,"")) | Q35: =IF(B35="","",IF(B35="Serviço",S35,"")) -> Projeto de Segurança do Trabalho | R35: =IF(B35="serviço",U35,OFFSET(R35,-1,0)) -> 1 | S35: Projeto de Segurança do Trabalho | T35: VB | U35: 1 | W35: =IFERROR(IF(B35="INSUMO",_xlfn.XLOOKUP(S35,Insumos!A:A,Insumos!C:C),""),"Inserir Preço") | X35: =IF(B35="Complemento do insumo",V35,IF(R35="","",IF(B35="serviço",R35,IF(OR(B35="insumo"),V35*R35,"")))) -> 1 | Y35: =IF(B35="insumo",W35*V35,IF(B35="serviço",SUMIFS(Y:Y,B:B,"insumo",E:E,E35,I:I,I35),"")) -> 3500 | Z35: =IFERROR(IF(B35="Unidade Construtiva",SUMIFS(Z:Z,B:B,"Célula Construtiva",G:G,G35),IF(B35="célula construtiva",SUMIFS(Z:Z,B:B,"Insumo",I:I,I35,G:G,G35),IF(B35="ETAPA",SUMIFS(Z:Z,B:B,"Insumo",K:K,K35,I:I,I35,G:G,G35),IF(B35="subetapa",SUMIFS(Z:Z,M:M,M35,B:B,"insumo",K:K,K35,I:I,I35,G:G,G35),IF(B35="complemento do insumo",V35*W35,IF(B35="INSUMO",R35*V35*W35,X35*Y35)))))),"") -> 3500 | AB35: =IF(B35="insumo",_xlfn.XLOOKUP(S35,Insumos!A:A,Insumos!D:D),"") | AC35: =IFERROR(IF(B35="","",Z35/SUMIF(B:B,"INSUMO",Z:Z)),0) -> 0.00050210691 | AE35: =IFERROR(IF(OR(Z35="",Z35=0),"",IF(AF35="","",IF(AF35="R$/mês",Z35/OBRA!$D$12,IF(AF35="R$/m²",Z35/OBRA!$D$10,IF(AF35="R$/apto",Orçamento!Z35/OBRA!$D$11,""))))),"") -> 1.8011249 | AF35: R$/m²
B36: Insumo | C36: =IF(B36="INSUMO",COUNTIFS(B:B,"INSUMO",S:S,S36),IF(B36="SERVIÇO",COUNTIFS(B:B,"SERVIÇO",S:S,S36),"")) -> 1 | D36: =IF(B36="Unidade Construtiva",TEXT(F36,"00"),IF(B36="Célula Construtiva",TEXT(H36,"00"),IF(B36="Etapa",CONCATENATE(TEXT(H36,"00"),".",TEXT(J36,"000")),IF(B36="Subetapa",CONCATENATE(TEXT(H36,"00"),".",TEXT(J36,"000"),".",TEXT(L36,"000")),IF(B36="Serviço",CONCATENATE(TEXT(H36,"00"),".",TEXT(J36,"000"),".",TEXT(L36,"000"),".",TEXT(N36,"000")),""))))) | E36: =IF(B36="*","",IFERROR(IF(B36="SERVIÇO",D36,OFFSET(E36,-1,0)),"")) -> 01.001.002.008 | F36: =IF($B36="UNIDADE CONSTRUTIVA",OFFSET(F36,-1,0)+1,LARGE(F$10:F35,1)) -> 1 | G36: =IF(B36="*","",IF(B36="UNIDADE CONSTRUTIVA",S36,OFFSET(G36,-1,0))) -> GERENCIAMENTO TÉCNICO E ADMINISTRATIVO | H36: =IF(B36="UNIDADE CONSTRUTIVA",0,IF(B36="CÉLULA CONSTRUTIVA",OFFSET(H36,-1,0)+1,OFFSET(H36,-1,0))) -> 1 | I36: =IF(B36="*","",IF(B36="CÉLULA CONSTRUTIVA",S36,OFFSET(I36,-1,0))) -> GERENCIAMENTO TÉCNICO | J36: =IF(B36="CÉLULA CONSTRUTIVA",0,IF(B36="ETAPA",OFFSET(J36,-1,0)+1,OFFSET(J36,-1,0))) -> 1 | K36: =IF(B36="*","",IF(B36="ETAPA",S36,OFFSET(K36,-1,0))) -> ESTUDOS | PROJETOS | CONSULTORIAS | L36: =IF(B36="ETAPA",0,IF(B36="SUBETAPA",OFFSET(L36,-1,0)+1,OFFSET(L36,-1,0))) -> 2 | M36: =IF(B36="*","",IF(B36="SUBETAPA",S36,OFFSET(M36,-1,0))) -> Projetos | N36: =IF(B36="Subetapa",0,IF(B36="serviço",OFFSET(N36,-1,0)+1,OFFSET(N36,-1,0))) -> 8 | O36: =IF(B36="*","",IF(B36="SERVIÇO",S36,OFFSET(O36,-1,0))) -> Projeto de Segurança do Trabalho | P36: =IF(S36="","",IF(Orçamento!$B36="INSUMO",S36,"")) -> PROJETO DE SEGURANCA DO TRABALHO | Q36: =IF(B36="","",IF(B36="Serviço",S36,"")) | R36: =IF(B36="serviço",U36,OFFSET(R36,-1,0)) -> 1 | S36: PROJETO DE SEGURANCA DO TRABALHO | T36: =_xlfn.XLOOKUP(S36,Insumos!$A$3:$A$371,Insumos!$B$3:$B$371) -> VB | U36: =IF($B36="insumo",R36,"") -> 1 | V36: 1 | W36: =IFERROR(IF(B36="INSUMO",_xlfn.XLOOKUP(S36,Insumos!A:A,Insumos!C:C),""),"Inserir Preço") -> 3500 | X36: =IF(B36="Complemento do insumo",V36,IF(R36="","",IF(B36="serviço",R36,IF(OR(B36="insumo"),V36*R36,"")))) -> 1 | Y36: =IF(B36="insumo",W36*V36,IF(B36="serviço",SUMIFS(Y:Y,B:B,"insumo",E:E,E36,I:I,I36),"")) -> 3500 | Z36: =IFERROR(IF(B36="Unidade Construtiva",SUMIFS(Z:Z,B:B,"Célula Construtiva",G:G,G36),IF(B36="célula construtiva",SUMIFS(Z:Z,B:B,"Insumo",I:I,I36,G:G,G36),IF(B36="ETAPA",SUMIFS(Z:Z,B:B,"Insumo",K:K,K36,I:I,I36,G:G,G36),IF(B36="subetapa",SUMIFS(Z:Z,M:M,M36,B:B,"insumo",K:K,K36,I:I,I36,G:G,G36),IF(B36="complemento do insumo",V36*W36,IF(B36="INSUMO",R36*V36*W36,X36*Y36)))))),"") -> 3500 | AB36: =IF(B36="insumo",_xlfn.XLOOKUP(S36,Insumos!A:A,Insumos!D:D),"") -> Recebido Cliente | AC36: =IFERROR(IF(B36="","",Z36/SUMIF(B:B,"INSUMO",Z:Z)),0) -> 0.00050210691 | AE36: =IFERROR(IF(OR(Z36="",Z36=0),"",IF(AF36="","",IF(AF36="R$/mês",Z36/OBRA!$D$12,IF(AF36="R$/m²",Z36/OBRA!$D$10,IF(AF36="R$/apto",Orçamento!Z36/OBRA!$D$11,""))))),"") -> 1.8011249 | AF36: R$/m²
B37: Serviço | C37: =IF(B37="INSUMO",COUNTIFS(B:B,"INSUMO",S:S,S37),IF(B37="SERVIÇO",COUNTIFS(B:B,"SERVIÇO",S:S,S37),"")) -> 1 | D37: =IF(B37="Unidade Construtiva",TEXT(F37,"00"),IF(B37="Célula Construtiva",TEXT(H37,"00"),IF(B37="Etapa",CONCATENATE(TEXT(H37,"00"),".",TEXT(J37,"000")),IF(B37="Subetapa",CONCATENATE(TEXT(H37,"00"),".",TEXT(J37,"000"),".",TEXT(L37,"000")),IF(B37="Serviço",CONCATENATE(TEXT(H37,"00"),".",TEXT(J37,"000"),".",TEXT(L37,"000"),".",TEXT(N37,"000")),""))))) -> 01.001.002.009 | E37: =IF(B37="*","",IFERROR(IF(B37="SERVIÇO",D37,OFFSET(E37,-1,0)),"")) -> 01.001.002.009 | F37: =IF($B37="UNIDADE CONSTRUTIVA",OFFSET(F37,-1,0)+1,LARGE(F$10:F36,1)) -> 1 | G37: =IF(B37="*","",IF(B37="UNIDADE CONSTRUTIVA",S37,OFFSET(G37,-1,0))) -> GERENCIAMENTO TÉCNICO E ADMINISTRATIVO | H37: =IF(B37="UNIDADE CONSTRUTIVA",0,IF(B37="CÉLULA CONSTRUTIVA",OFFSET(H37,-1,0)+1,OFFSET(H37,-1,0))) -> 1 | I37: =IF(B37="*","",IF(B37="CÉLULA CONSTRUTIVA",S37,OFFSET(I37,-1,0))) -> GERENCIAMENTO TÉCNICO | J37: =IF(B37="CÉLULA CONSTRUTIVA",0,IF(B37="ETAPA",OFFSET(J37,-1,0)+1,OFFSET(J37,-1,0))) -> 1 | K37: =IF(B37="*","",IF(B37="ETAPA",S37,OFFSET(K37,-1,0))) -> ESTUDOS | PROJETOS | CONSULTORIAS | L37: =IF(B37="ETAPA",0,IF(B37="SUBETAPA",OFFSET(L37,-1,0)+1,OFFSET(L37,-1,0))) -> 2 | M37: =IF(B37="*","",IF(B37="SUBETAPA",S37,OFFSET(M37,-1,0))) -> Projetos | N37: =IF(B37="Subetapa",0,IF(B37="serviço",OFFSET(N37,-1,0)+1,OFFSET(N37,-1,0))) -> 9 | O37: =IF(B37="*","",IF(B37="SERVIÇO",S37,OFFSET(O37,-1,0))) -> Projeto de climatização | P37: =IF(S37="","",IF(Orçamento!$B37="INSUMO",S37,"")) | Q37: =IF(B37="","",IF(B37="Serviço",S37,"")) -> Projeto de climatização | R37: =IF(B37="serviço",U37,OFFSET(R37,-1,0)) -> 1 | S37: Projeto de climatização | T37: VB | U37: 1 | W37: =IFERROR(IF(B37="INSUMO",_xlfn.XLOOKUP(S37,Insumos!A:A,Insumos!C:C),""),"Inserir Preço") | X37: =IF(B37="Complemento do insumo",V37,IF(R37="","",IF(B37="serviço",R37,IF(OR(B37="insumo"),V37*R37,"")))) -> 1 | Y37: =IF(B37="insumo",W37*V37,IF(B37="serviço",SUMIFS(Y:Y,B:B,"insumo",E:E,E37,I:I,I37),"")) -> 1400 | Z37: =IFERROR(IF(B37="Unidade Construtiva",SUMIFS(Z:Z,B:B,"Célula Construtiva",G:G,G37),IF(B37="célula construtiva",SUMIFS(Z:Z,B:B,"Insumo",I:I,I37,G:G,G37),IF(B37="ETAPA",SUMIFS(Z:Z,B:B,"Insumo",K:K,K37,I:I,I37,G:G,G37),IF(B37="subetapa",SUMIFS(Z:Z,M:M,M37,B:B,"insumo",K:K,K37,I:I,I37,G:G,G37),IF(B37="complemento do insumo",V37*W37,IF(B37="INSUMO",R37*V37*W37,X37*Y37)))))),"") -> 1400 | AB37: =IF(B37="insumo",_xlfn.XLOOKUP(S37,Insumos!A:A,Insumos!D:D),"") | AC37: =IFERROR(IF(B37="","",Z37/SUMIF(B:B,"INSUMO",Z:Z)),0) -> 0.00020084276 | AE37: =IFERROR(IF(OR(Z37="",Z37=0),"",IF(AF37="","",IF(AF37="R$/mês",Z37/OBRA!$D$12,IF(AF37="R$/m²",Z37/OBRA!$D$10,IF(AF37="R$/apto",Orçamento!Z37/OBRA!$D$11,""))))),"") -> 0.72044997 | AF37: R$/m²
B38: Insumo | C38: =IF(B38="INSUMO",COUNTIFS(B:B,"INSUMO",S:S,S38),IF(B38="SERVIÇO",COUNTIFS(B:B,"SERVIÇO",S:S,S38),"")) -> 1 | D38: =IF(B38="Unidade Construtiva",TEXT(F38,"00"),IF(B38="Célula Construtiva",TEXT(H38,"00"),IF(B38="Etapa",CONCATENATE(TEXT(H38,"00"),".",TEXT(J38,"000")),IF(B38="Subetapa",CONCATENATE(TEXT(H38,"00"),".",TEXT(J38,"000"),".",TEXT(L38,"000")),IF(B38="Serviço",CONCATENATE(TEXT(H38,"00"),".",TEXT(J38,"000"),".",TEXT(L38,"000"),".",TEXT(N38,"000")),""))))) | E38: =IF(B38="*","",IFERROR(IF(B38="SERVIÇO",D38,OFFSET(E38,-1,0)),"")) -> 01.001.002.009 | F38: =IF($B38="UNIDADE CONSTRUTIVA",OFFSET(F38,-1,0)+1,LARGE(F$10:F37,1)) -> 1 | G38: =IF(B38="*","",IF(B38="UNIDADE CONSTRUTIVA",S38,OFFSET(G38,-1,0))) -> GERENCIAMENTO TÉCNICO E ADMINISTRATIVO | H38: =IF(B38="UNIDADE CONSTRUTIVA",0,IF(B38="CÉLULA CONSTRUTIVA",OFFSET(H38,-1,0)+1,OFFSET(H38,-1,0))) -> 1 | I38: =IF(B38="*","",IF(B38="CÉLULA CONSTRUTIVA",S38,OFFSET(I38,-1,0))) -> GERENCIAMENTO TÉCNICO | J38: =IF(B38="CÉLULA CONSTRUTIVA",0,IF(B38="ETAPA",OFFSET(J38,-1,0)+1,OFFSET(J38,-1,0))) -> 1 | K38: =IF(B38="*","",IF(B38="ETAPA",S38,OFFSET(K38,-1,0))) -> ESTUDOS | PROJETOS | CONSULTORIAS | L38: =IF(B38="ETAPA",0,IF(B38="SUBETAPA",OFFSET(L38,-1,0)+1,OFFSET(L38,-1,0))) -> 2 | M38: =IF(B38="*","",IF(B38="SUBETAPA",S38,OFFSET(M38,-1,0))) -> Projetos | N38: =IF(B38="Subetapa",0,IF(B38="serviço",OFFSET(N38,-1,0)+1,OFFSET(N38,-1,0))) -> 9 | O38: =IF(B38="*","",IF(B38="SERVIÇO",S38,OFFSET(O38,-1,0))) -> Projeto de climatização | P38: =IF(S38="","",IF(Orçamento!$B38="INSUMO",S38,"")) -> Projeto De Climatização | Q38: =IF(B38="","",IF(B38="Serviço",S38,"")) | R38: =IF(B38="serviço",U38,OFFSET(R38,-1,0)) -> 1 | S38: Projeto De Climatização | T38: =_xlfn.XLOOKUP(S38,Insumos!$A$3:$A$371,Insumos!$B$3:$B$371) -> VB | U38: =IF($B38="insumo",R38,"") -> 1 | V38: 1 | W38: =IFERROR(IF(B38="INSUMO",_xlfn.XLOOKUP(S38,Insumos!A:A,Insumos!C:C),""),"Inserir Preço") -> 1400 | X38: =IF(B38="Complemento do insumo",V38,IF(R38="","",IF(B38="serviço",R38,IF(OR(B38="insumo"),V38*R38,"")))) -> 1 | Y38: =IF(B38="insumo",W38*V38,IF(B38="serviço",SUMIFS(Y:Y,B:B,"insumo",E:E,E38,I:I,I38),"")) -> 1400 | Z38: =IFERROR(IF(B38="Unidade Construtiva",SUMIFS(Z:Z,B:B,"Célula Construtiva",G:G,G38),IF(B38="célula construtiva",SUMIFS(Z:Z,B:B,"Insumo",I:I,I38,G:G,G38),IF(B38="ETAPA",SUMIFS(Z:Z,B:B,"Insumo",K:K,K38,I:I,I38,G:G,G38),IF(B38="subetapa",SUMIFS(Z:Z,M:M,M38,B:B,"insumo",K:K,K38,I:I,I38,G:G,G38),IF(B38="complemento do insumo",V38*W38,IF(B38="INSUMO",R38*V38*W38,X38*Y38)))))),"") -> 1400 | AB38: =IF(B38="insumo",_xlfn.XLOOKUP(S38,Insumos!A:A,Insumos!D:D),"") -> Recebido Cliente | AC38: =IFERROR(IF(B38="","",Z38/SUMIF(B:B,"INSUMO",Z:Z)),0) -> 0.00020084276 | AE38: =IFERROR(IF(OR(Z38="",Z38=0),"",IF(AF38="","",IF(AF38="R$/mês",Z38/OBRA!$D$12,IF(AF38="R$/m²",Z38/OBRA!$D$10,IF(AF38="R$/apto",Orçamento!Z38/OBRA!$D$11,""))))),"") -> 0.72044997 | AF38: R$/m²
B39: Subetapa | C39: =IF(B39="INSUMO",COUNTIFS(B:B,"INSUMO",S:S,S39),IF(B39="SERVIÇO",COUNTIFS(B:B,"SERVIÇO",S:S,S39),"")) | D39: =IF(B39="Unidade Construtiva",TEXT(F39,"00"),IF(B39="Célula Construtiva",TEXT(H39,"00"),IF(B39="Etapa",CONCATENATE(TEXT(H39,"00"),".",TEXT(J39,"000")),IF(B39="Subetapa",CONCATENATE(TEXT(H39,"00"),".",TEXT(J39,"000"),".",TEXT(L39,"000")),IF(B39="Serviço",CONCATENATE(TEXT(H39,"00"),".",TEXT(J39,"000"),".",TEXT(L39,"000"),".",TEXT(N39,"000")),""))))) -> 01.001.003 | E39: =IF(B39="*","",IFERROR(IF(B39="SERVIÇO",D39,OFFSET(E39,-1,0)),"")) -> 01.001.002.009 | F39: =IF($B39="UNIDADE CONSTRUTIVA",OFFSET(F39,-1,0)+1,LARGE(F$10:F38,1)) -> 1 | G39: =IF(B39="*","",IF(B39="UNIDADE CONSTRUTIVA",S39,OFFSET(G39,-1,0))) -> GERENCIAMENTO TÉCNICO E ADMINISTRATIVO | H39: =IF(B39="UNIDADE CONSTRUTIVA",0,IF(B39="CÉLULA CONSTRUTIVA",OFFSET(H39,-1,0)+1,OFFSET(H39,-1,0))) -> 1 | I39: =IF(B39="*","",IF(B39="CÉLULA CONSTRUTIVA",S39,OFFSET(I39,-1,0))) -> GERENCIAMENTO TÉCNICO | J39: =IF(B39="CÉLULA CONSTRUTIVA",0,IF(B39="ETAPA",OFFSET(J39,-1,0)+1,OFFSET(J39,-1,0))) -> 1 | K39: =IF(B39="*","",IF(B39="ETAPA",S39,OFFSET(K39,-1,0))) -> ESTUDOS | PROJETOS | CONSULTORIAS | L39: =IF(B39="ETAPA",0,IF(B39="SUBETAPA",OFFSET(L39,-1,0)+1,OFFSET(L39,-1,0))) -> 3 | M39: =IF(B39="*","",IF(B39="SUBETAPA",S39,OFFSET(M39,-1,0))) -> Consultorias | N39: =IF(B39="Subetapa",0,IF(B39="serviço",OFFSET(N39,-1,0)+1,OFFSET(N39,-1,0))) -> 0 | O39: =IF(B39="*","",IF(B39="SERVIÇO",S39,OFFSET(O39,-1,0))) -> Projeto de climatização | P39: =IF(S39="","",IF(Orçamento!$B39="INSUMO",S39,"")) | Q39: =IF(B39="","",IF(B39="Serviço",S39,"")) | R39: =IF(B39="serviço",U39,OFFSET(R39,-1,0)) -> 1 | S39: Consultorias | U39: =IF($B39="insumo",R39,"") | W39: =IFERROR(IF(B39="INSUMO",_xlfn.XLOOKUP(S39,Insumos!A:A,Insumos!C:C),""),"Inserir Preço") | X39: =IF(B39="Complemento do insumo",V39,IF(R39="","",IF(B39="serviço",R39,IF(OR(B39="insumo"),V39*R39,"")))) | Y39: =IF(B39="insumo",W39*V39,IF(B39="serviço",SUMIFS(Y:Y,B:B,"insumo",E:E,E39,I:I,I39),"")) | Z39: =IFERROR(IF(B39="Unidade Construtiva",SUMIFS(Z:Z,B:B,"Célula Construtiva",G:G,G39),IF(B39="célula construtiva",SUMIFS(Z:Z,B:B,"Insumo",I:I,I39,G:G,G39),IF(B39="ETAPA",SUMIFS(Z:Z,B:B,"Insumo",K:K,K39,I:I,I39,G:G,G39),IF(B39="subetapa",SUMIFS(Z:Z,M:M,M39,B:B,"insumo",K:K,K39,I:I,I39,G:G,G39),IF(B39="complemento do insumo",V39*W39,IF(B39="INSUMO",R39*V39*W39,X39*Y39)))))),"") -> 21000 | AB39: =IF(B39="insumo",_xlfn.XLOOKUP(S39,Insumos!A:A,Insumos!D:D),"") | AC39: =IFERROR(IF(B39="","",Z39/SUMIF(B:B,"INSUMO",Z:Z)),0) -> 0.0030126415 | AE39: =IFERROR(IF(OR(Z39="",Z39=0),"",IF(AF39="","",IF(AF39="R$/mês",Z39/OBRA!$D$12,IF(AF39="R$/m²",Z39/OBRA!$D$10,IF(AF39="R$/apto",Orçamento!Z39/OBRA!$D$11,""))))),"") -> 10.80675 | AF39: R$/m²
B40: Serviço | C40: =IF(B40="INSUMO",COUNTIFS(B:B,"INSUMO",S:S,S40),IF(B40="SERVIÇO",COUNTIFS(B:B,"SERVIÇO",S:S,S40),"")) -> 1 | D40: =IF(B40="Unidade Construtiva",TEXT(F40,"00"),IF(B40="Célula Construtiva",TEXT(H40,"00"),IF(B40="Etapa",CONCATENATE(TEXT(H40,"00"),".",TEXT(J40,"000")),IF(B40="Subetapa",CONCATENATE(TEXT(H40,"00"),".",TEXT(J40,"000"),".",TEXT(L40,"000")),IF(B40="Serviço",CONCATENATE(TEXT(H40,"00"),".",TEXT(J40,"000"),".",TEXT(L40,"000"),".",TEXT(N40,"000")),""))))) -> 01.001.003.001 | E40: =IF(B40="*","",IFERROR(IF(B40="SERVIÇO",D40,OFFSET(E40,-1,0)),"")) -> 01.001.003.001 | F40: =IF($B40="UNIDADE CONSTRUTIVA",OFFSET(F40,-1,0)+1,LARGE(F$10:F39,1)) -> 1 | G40: =IF(B40="*","",IF(B40="UNIDADE CONSTRUTIVA",S40,OFFSET(G40,-1,0))) -> GERENCIAMENTO TÉCNICO E ADMINISTRATIVO | H40: =IF(B40="UNIDADE CONSTRUTIVA",0,IF(B40="CÉLULA CONSTRUTIVA",OFFSET(H40,-1,0)+1,OFFSET(H40,-1,0))) -> 1 | I40: =IF(B40="*","",IF(B40="CÉLULA CONSTRUTIVA",S40,OFFSET(I40,-1,0))) -> GERENCIAMENTO TÉCNICO | J40: =IF(B40="CÉLULA CONSTRUTIVA",0,IF(B40="ETAPA",OFFSET(J40,-1,0)+1,OFFSET(J40,-1,0))) -> 1 | K40: =IF(B40="*","",IF(B40="ETAPA",S40,OFFSET(K40,-1,0))) -> ESTUDOS | PROJETOS | CONSULTORIAS | L40: =IF(B40="ETAPA",0,IF(B40="SUBETAPA",OFFSET(L40,-1,0)+1,OFFSET(L40,-1,0))) -> 3 | M40: =IF(B40="*","",IF(B40="SUBETAPA",S40,OFFSET(M40,-1,0))) -> Consultorias | N40: =IF(B40="Subetapa",0,IF(B40="serviço",OFFSET(N40,-1,0)+1,OFFSET(N40,-1,0))) -> 1 | O40: =IF(B40="*","",IF(B40="SERVIÇO",S40,OFFSET(O40,-1,0))) -> Consultoria de Orçamento e Planejamento | P40: =IF(S40="","",IF(Orçamento!$B40="INSUMO",S40,"")) | Q40: =IF(B40="","",IF(B40="Serviço",S40,"")) -> Consultoria de Orçamento e Planejamento | R40: =IF(B40="serviço",U40,OFFSET(R40,-1,0)) -> 1 | S40: Consultoria de Orçamento e Planejamento | T40: VB | U40: 1 | W40: =IFERROR(IF(B40="INSUMO",_xlfn.XLOOKUP(S40,Insumos!A:A,Insumos!C:C),""),"Inserir Preço") | X40: =IF(B40="Complemento do insumo",V40,IF(R40="","",IF(B40="serviço",R40,IF(OR(B40="insumo"),V40*R40,"")))) -> 1 | Y40: =IF(B40="insumo",W40*V40,IF(B40="serviço",SUMIFS(Y:Y,B:B,"insumo",E:E,E40,I:I,I40),"")) -> 21000 | Z40: =IFERROR(IF(B40="Unidade Construtiva",SUMIFS(Z:Z,B:B,"Célula Construtiva",G:G,G40),IF(B40="célula construtiva",SUMIFS(Z:Z,B:B,"Insumo",I:I,I40,G:G,G40),IF(B40="ETAPA",SUMIFS(Z:Z,B:B,"Insumo",K:K,K40,I:I,I40,G:G,G40),IF(B40="subetapa",SUMIFS(Z:Z,M:M,M40,B:B,"insumo",K:K,K40,I:I,I40,G:G,G40),IF(B40="complemento do insumo",V40*W40,IF(B40="INSUMO",R40*V40*W40,X40*Y40)))))),"") -> 21000 | AB40: =IF(B40="insumo",_xlfn.XLOOKUP(S40,Insumos!A:A,Insumos!D:D),"") | AC40: =IFERROR(IF(B40="","",Z40/SUMIF(B:B,"INSUMO",Z:Z)),0) -> 0.0030126415 | AE40: =IFERROR(IF(OR(Z40="",Z40=0),"",IF(AF40="","",IF(AF40="R$/mês",Z40/OBRA!$D$12,IF(AF40="R$/m²",Z40/OBRA!$D$10,IF(AF40="R$/apto",Orçamento!Z40/OBRA!$D$11,""))))),"") -> 10.80675 | AF40: R$/m²
B41: Insumo | C41: =IF(B41="INSUMO",COUNTIFS(B:B,"INSUMO",S:S,S41),IF(B41="SERVIÇO",COUNTIFS(B:B,"SERVIÇO",S:S,S41),"")) -> 1 | D41: =IF(B41="Unidade Construtiva",TEXT(F41,"00"),IF(B41="Célula Construtiva",TEXT(H41,"00"),IF(B41="Etapa",CONCATENATE(TEXT(H41,"00"),".",TEXT(J41,"000")),IF(B41="Subetapa",CONCATENATE(TEXT(H41,"00"),".",TEXT(J41,"000"),".",TEXT(L41,"000")),IF(B41="Serviço",CONCATENATE(TEXT(H41,"00"),".",TEXT(J41,"000"),".",TEXT(L41,"000"),".",TEXT(N41,"000")),""))))) | E41: =IF(B41="*","",IFERROR(IF(B41="SERVIÇO",D41,OFFSET(E41,-1,0)),"")) -> 01.001.003.001 | F41: =IF($B41="UNIDADE CONSTRUTIVA",OFFSET(F41,-1,0)+1,LARGE(F$10:F40,1)) -> 1 | G41: =IF(B41="*","",IF(B41="UNIDADE CONSTRUTIVA",S41,OFFSET(G41,-1,0))) -> GERENCIAMENTO TÉCNICO E ADMINISTRATIVO | H41: =IF(B41="UNIDADE CONSTRUTIVA",0,IF(B41="CÉLULA CONSTRUTIVA",OFFSET(H41,-1,0)+1,OFFSET(H41,-1,0))) -> 1 | I41: =IF(B41="*","",IF(B41="CÉLULA CONSTRUTIVA",S41,OFFSET(I41,-1,0))) -> GERENCIAMENTO TÉCNICO | J41: =IF(B41="CÉLULA CONSTRUTIVA",0,IF(B41="ETAPA",OFFSET(J41,-1,0)+1,OFFSET(J41,-1,0))) -> 1 | K41: =IF(B41="*","",IF(B41="ETAPA",S41,OFFSET(K41,-1,0))) -> ESTUDOS | PROJETOS | CONSULTORIAS | L41: =IF(B41="ETAPA",0,IF(B41="SUBETAPA",OFFSET(L41,-1,0)+1,OFFSET(L41,-1,0))) -> 3 | M41: =IF(B41="*","",IF(B41="SUBETAPA",S41,OFFSET(M41,-1,0))) -> Consultorias | N41: =IF(B41="Subetapa",0,IF(B41="serviço",OFFSET(N41,-1,0)+1,OFFSET(N41,-1,0))) -> 1 | O41: =IF(B41="*","",IF(B41="SERVIÇO",S41,OFFSET(O41,-1,0))) -> Consultoria de Orçamento e Planejamento | P41: =IF(S41="","",IF(Orçamento!$B41="INSUMO",S41,"")) -> ORCAMENTO E PLANEJAMENTO | Q41: =IF(B41="","",IF(B41="Serviço",S41,"")) | R41: =IF(B41="serviço",U41,OFFSET(R41,-1,0)) -> 1 | S41: ORCAMENTO E PLANEJAMENTO | T41: =_xlfn.XLOOKUP(S41,Insumos!$A$3:$A$371,Insumos!$B$3:$B$371) -> VB | U41: =IF($B41="insumo",R41,"") -> 1 | V41: 1 | W41: =IFERROR(IF(B41="INSUMO",_xlfn.XLOOKUP(S41,Insumos!A:A,Insumos!C:C),""),"Inserir Preço") -> 21000 | X41: =IF(B41="Complemento do insumo",V41,IF(R41="","",IF(B41="serviço",R41,IF(OR(B41="insumo"),V41*R41,"")))) -> 1 | Y41: =IF(B41="insumo",W41*V41,IF(B41="serviço",SUMIFS(Y:Y,B:B,"insumo",E:E,E41,I:I,I41),"")) -> 21000 | Z41: =IFERROR(IF(B41="Unidade Construtiva",SUMIFS(Z:Z,B:B,"Célula Construtiva",G:G,G41),IF(B41="célula construtiva",SUMIFS(Z:Z,B:B,"Insumo",I:I,I41,G:G,G41),IF(B41="ETAPA",SUMIFS(Z:Z,B:B,"Insumo",K:K,K41,I:I,I41,G:G,G41),IF(B41="subetapa",SUMIFS(Z:Z,M:M,M41,B:B,"insumo",K:K,K41,I:I,I41,G:G,G41),IF(B41="complemento do insumo",V41*W41,IF(B41="INSUMO",R41*V41*W41,X41*Y41)))))),"") -> 21000 | AB41: =IF(B41="insumo",_xlfn.XLOOKUP(S41,Insumos!A:A,Insumos!D:D),"") -> Recebido Cliente | AC41: =IFERROR(IF(B41="","",Z41/SUMIF(B:B,"INSUMO",Z:Z)),0) -> 0.0030126415 | AE41: =IFERROR(IF(OR(Z41="",Z41=0),"",IF(AF41="","",IF(AF41="R$/mês",Z41/OBRA!$D$12,IF(AF41="R$/m²",Z41/OBRA!$D$10,IF(AF41="R$/apto",Orçamento!Z41/OBRA!$D$11,""))))),"") -> 10.80675 | AF41: R$/m²
B42: Subetapa | C42: =IF(B42="INSUMO",COUNTIFS(B:B,"INSUMO",S:S,S42),IF(B42="SERVIÇO",COUNTIFS(B:B,"SERVIÇO",S:S,S42),"")) | D42: =IF(B42="Unidade Construtiva",TEXT(F42,"00"),IF(B42="Célula Construtiva",TEXT(H42,"00"),IF(B42="Etapa",CONCATENATE(TEXT(H42,"00"),".",TEXT(J42,"000")),IF(B42="Subetapa",CONCATENATE(TEXT(H42,"00"),".",TEXT(J42,"000"),".",TEXT(L42,"000")),IF(B42="Serviço",CONCATENATE(TEXT(H42,"00"),".",TEXT(J42,"000"),".",TEXT(L42,"000"),".",TEXT(N42,"000")),""))))) -> 01.001.004 | E42: =IF(B42="*","",IFERROR(IF(B42="SERVIÇO",D42,OFFSET(E42,-1,0)),"")) -> 01.001.003.001 | F42: =IF($B42="UNIDADE CONSTRUTIVA",OFFSET(F42,-1,0)+1,LARGE(F$10:F41,1)) -> 1 | G42: =IF(B42="*","",IF(B42="UNIDADE CONSTRUTIVA",S42,OFFSET(G42,-1,0))) -> GERENCIAMENTO TÉCNICO E ADMINISTRATIVO | H42: =IF(B42="UNIDADE CONSTRUTIVA",0,IF(B42="CÉLULA CONSTRUTIVA",OFFSET(H42,-1,0)+1,OFFSET(H42,-1,0))) -> 1 | I42: =IF(B42="*","",IF(B42="CÉLULA CONSTRUTIVA",S42,OFFSET(I42,-1,0))) -> GERENCIAMENTO TÉCNICO | J42: =IF(B42="CÉLULA CONSTRUTIVA",0,IF(B42="ETAPA",OFFSET(J42,-1,0)+1,OFFSET(J42,-1,0))) -> 1 | K42: =IF(B42="*","",IF(B42="ETAPA",S42,OFFSET(K42,-1,0))) -> ESTUDOS | PROJETOS | CONSULTORIAS | L42: =IF(B42="ETAPA",0,IF(B42="SUBETAPA",OFFSET(L42,-1,0)+1,OFFSET(L42,-1,0))) -> 4 | M42: =IF(B42="*","",IF(B42="SUBETAPA",S42,OFFSET(M42,-1,0))) -> Controle Tecnológico de Concreto | N42: =IF(B42="Subetapa",0,IF(B42="serviço",OFFSET(N42,-1,0)+1,OFFSET(N42,-1,0))) -> 0 | O42: =IF(B42="*","",IF(B42="SERVIÇO",S42,OFFSET(O42,-1,0))) -> Consultoria de Orçamento e Planejamento | P42: =IF(S42="","",IF(Orçamento!$B42="INSUMO",S42,"")) | Q42: =IF(B42="","",IF(B42="Serviço",S42,"")) | R42: =IF(B42="serviço",U42,OFFSET(R42,-1,0)) -> 1 | S42: Controle Tecnológico de Concreto | U42: =IF($B42="insumo",R42,"") | W42: =IFERROR(IF(B42="INSUMO",_xlfn.XLOOKUP(S42,Insumos!A:A,Insumos!C:C),""),"Inserir Preço") | X42: =IF(B42="Complemento do insumo",V42,IF(R42="","",IF(B42="serviço",R42,IF(OR(B42="insumo"),V42*R42,"")))) | Y42: =IF(B42="insumo",W42*V42,IF(B42="serviço",SUMIFS(Y:Y,B:B,"insumo",E:E,E42,I:I,I42),"")) | Z42: =IFERROR(IF(B42="Unidade Construtiva",SUMIFS(Z:Z,B:B,"Célula Construtiva",G:G,G42),IF(B42="célula construtiva",SUMIFS(Z:Z,B:B,"Insumo",I:I,I42,G:G,G42),IF(B42="ETAPA",SUMIFS(Z:Z,B:B,"Insumo",K:K,K42,I:I,I42,G:G,G42),IF(B42="subetapa",SUMIFS(Z:Z,M:M,M42,B:B,"insumo",K:K,K42,I:I,I42,G:G,G42),IF(B42="complemento do insumo",V42*W42,IF(B42="INSUMO",R42*V42*W42,X42*Y42)))))),"") -> 16829.62 | AB42: =IF(B42="insumo",_xlfn.XLOOKUP(S42,Insumos!A:A,Insumos!D:D),"") | AC42: =IFERROR(IF(B42="","",Z42/SUMIF(B:B,"INSUMO",Z:Z)),0) -> 0.0024143624 | AE42: =IFERROR(IF(OR(Z42="",Z42=0),"",IF(AF42="","",IF(AF42="R$/mês",Z42/OBRA!$D$12,IF(AF42="R$/m²",Z42/OBRA!$D$10,IF(AF42="R$/apto",Orçamento!Z42/OBRA!$D$11,""))))),"") -> 8.6606423 | AF42: R$/m²
B43: Serviço | C43: =IF(B43="INSUMO",COUNTIFS(B:B,"INSUMO",S:S,S43),IF(B43="SERVIÇO",COUNTIFS(B:B,"SERVIÇO",S:S,S43),"")) -> 1 | D43: =IF(B43="Unidade Construtiva",TEXT(F43,"00"),IF(B43="Célula Construtiva",TEXT(H43,"00"),IF(B43="Etapa",CONCATENATE(TEXT(H43,"00"),".",TEXT(J43,"000")),IF(B43="Subetapa",CONCATENATE(TEXT(H43,"00"),".",TEXT(J43,"000"),".",TEXT(L43,"000")),IF(B43="Serviço",CONCATENATE(TEXT(H43,"00"),".",TEXT(J43,"000"),".",TEXT(L43,"000"),".",TEXT(N43,"000")),""))))) -> 01.001.004.001 | E43: =IF(B43="*","",IFERROR(IF(B43="SERVIÇO",D43,OFFSET(E43,-1,0)),"")) -> 01.001.004.001 | F43: =IF($B43="UNIDADE CONSTRUTIVA",OFFSET(F43,-1,0)+1,LARGE(F$10:F42,1)) -> 1 | G43: =IF(B43="*","",IF(B43="UNIDADE CONSTRUTIVA",S43,OFFSET(G43,-1,0))) -> GERENCIAMENTO TÉCNICO E ADMINISTRATIVO | H43: =IF(B43="UNIDADE CONSTRUTIVA",0,IF(B43="CÉLULA CONSTRUTIVA",OFFSET(H43,-1,0)+1,OFFSET(H43,-1,0))) -> 1 | I43: =IF(B43="*","",IF(B43="CÉLULA CONSTRUTIVA",S43,OFFSET(I43,-1,0))) -> GERENCIAMENTO TÉCNICO | J43: =IF(B43="CÉLULA CONSTRUTIVA",0,IF(B43="ETAPA",OFFSET(J43,-1,0)+1,OFFSET(J43,-1,0))) -> 1 | K43: =IF(B43="*","",IF(B43="ETAPA",S43,OFFSET(K43,-1,0))) -> ESTUDOS | PROJETOS | CONSULTORIAS | L43: =IF(B43="ETAPA",0,IF(B43="SUBETAPA",OFFSET(L43,-1,0)+1,OFFSET(L43,-1,0))) -> 4 | M43: =IF(B43="*","",IF(B43="SUBETAPA",S43,OFFSET(M43,-1,0))) -> Controle Tecnológico de Concreto | N43: =IF(B43="Subetapa",0,IF(B43="serviço",OFFSET(N43,-1,0)+1,OFFSET(N43,-1,0))) -> 1 | O43: =IF(B43="*","",IF(B43="SERVIÇO",S43,OFFSET(O43,-1,0))) -> Controle Tecnológico de Concreto - Infraestrura e Contenção | P43: =IF(S43="","",IF(Orçamento!$B43="INSUMO",S43,"")) | Q43: =IF(B43="","",IF(B43="Serviço",S43,"")) -> Controle Tecnológico de Concreto - Infraestrura e Contenção | R43: =IF(B43="serviço",U43,OFFSET(R43,-1,0)) -> 1 | S43: Controle Tecnológico de Concreto - Infraestrura e Contenção | T43: VB | U43: 1 | W43: =IFERROR(IF(B43="INSUMO",_xlfn.XLOOKUP(S43,Insumos!A:A,Insumos!C:C),""),"Inserir Preço") | X43: =IF(B43="Complemento do insumo",V43,IF(R43="","",IF(B43="serviço",R43,IF(OR(B43="insumo"),V43*R43,"")))) -> 1 | Y43: =IF(B43="insumo",W43*V43,IF(B43="serviço",SUMIFS(Y:Y,B:B,"insumo",E:E,E43,I:I,I43),"")) -> 3772 | Z43: =IFERROR(IF(B43="Unidade Construtiva",SUMIFS(Z:Z,B:B,"Célula Construtiva",G:G,G43),IF(B43="célula construtiva",SUMIFS(Z:Z,B:B,"Insumo",I:I,I43,G:G,G43),IF(B43="ETAPA",SUMIFS(Z:Z,B:B,"Insumo",K:K,K43,I:I,I43,G:G,G43),IF(B43="subetapa",SUMIFS(Z:Z,M:M,M43,B:B,"insumo",K:K,K43,I:I,I43,G:G,G43),IF(B43="complemento do insumo",V43*W43,IF(B43="INSUMO",R43*V43*W43,X43*Y43)))))),"") -> 3772 | AB43: =IF(B43="insumo",_xlfn.XLOOKUP(S43,Insumos!A:A,Insumos!D:D),"") | AC43: =IFERROR(IF(B43="","",Z43/SUMIF(B:B,"INSUMO",Z:Z)),0) -> 0.00054112779 | AE43: =IFERROR(IF(OR(Z43="",Z43=0),"",IF(AF43="","",IF(AF43="R$/mês",Z43/OBRA!$D$12,IF(AF43="R$/m²",Z43/OBRA!$D$10,IF(AF43="R$/apto",Orçamento!Z43/OBRA!$D$11,""))))),"") -> 1.9410981 | AF43: R$/m²
B44: Insumo | C44: =IF(B44="INSUMO",COUNTIFS(B:B,"INSUMO",S:S,S44),IF(B44="SERVIÇO",COUNTIFS(B:B,"SERVIÇO",S:S,S44),"")) -> 1 | D44: =IF(B44="Unidade Construtiva",TEXT(F44,"00"),IF(B44="Célula Construtiva",TEXT(H44,"00"),IF(B44="Etapa",CONCATENATE(TEXT(H44,"00"),".",TEXT(J44,"000")),IF(B44="Subetapa",CONCATENATE(TEXT(H44,"00"),".",TEXT(J44,"000"),".",TEXT(L44,"000")),IF(B44="Serviço",CONCATENATE(TEXT(H44,"00"),".",TEXT(J44,"000"),".",TEXT(L44,"000"),".",TEXT(N44,"000")),""))))) | E44: =IF(B44="*","",IFERROR(IF(B44="SERVIÇO",D44,OFFSET(E44,-1,0)),"")) -> 01.001.004.001 | F44: =IF($B44="UNIDADE CONSTRUTIVA",OFFSET(F44,-1,0)+1,LARGE(F$10:F43,1)) -> 1 | G44: =IF(B44="*","",IF(B44="UNIDADE CONSTRUTIVA",S44,OFFSET(G44,-1,0))) -> GERENCIAMENTO TÉCNICO E ADMINISTRATIVO | H44: =IF(B44="UNIDADE CONSTRUTIVA",0,IF(B44="CÉLULA CONSTRUTIVA",OFFSET(H44,-1,0)+1,OFFSET(H44,-1,0))) -> 1 | I44: =IF(B44="*","",IF(B44="CÉLULA CONSTRUTIVA",S44,OFFSET(I44,-1,0))) -> GERENCIAMENTO TÉCNICO | J44: =IF(B44="CÉLULA CONSTRUTIVA",0,IF(B44="ETAPA",OFFSET(J44,-1,0)+1,OFFSET(J44,-1,0))) -> 1 | K44: =IF(B44="*","",IF(B44="ETAPA",S44,OFFSET(K44,-1,0))) -> ESTUDOS | PROJETOS | CONSULTORIAS | L44: =IF(B44="ETAPA",0,IF(B44="SUBETAPA",OFFSET(L44,-1,0)+1,OFFSET(L44,-1,0))) -> 4 | M44: =IF(B44="*","",IF(B44="SUBETAPA",S44,OFFSET(M44,-1,0))) -> Controle Tecnológico de Concreto | N44: =IF(B44="Subetapa",0,IF(B44="serviço",OFFSET(N44,-1,0)+1,OFFSET(N44,-1,0))) -> 1 | O44: =IF(B44="*","",IF(B44="SERVIÇO",S44,OFFSET(O44,-1,0))) -> Controle Tecnológico de Concreto - Infraestrura e Contenção | P44: =IF(S44="","",IF(Orçamento!$B44="INSUMO",S44,"")) -> CONTROLE TECNOLOGICO DO CONCRETO - FUNDAÇÃO | Q44: =IF(B44="","",IF(B44="Serviço",S44,"")) | R44: =IF(B44="serviço",U44,OFFSET(R44,-1,0)) -> 1 | S44: CONTROLE TECNOLOGICO DO CONCRETO - FUNDAÇÃO | T44: =_xlfn.XLOOKUP(S44,Insumos!$A$3:$A$371,Insumos!$B$3:$B$371) -> VB | U44: =IF($B44="insumo",R44,"") -> 1 | V44: 1 | W44: =IFERROR(IF(B44="INSUMO",_xlfn.XLOOKUP(S44,Insumos!A:A,Insumos!C:C),""),"Inserir Preço") -> 3772 | X44: =IF(B44="Complemento do insumo",V44,IF(R44="","",IF(B44="serviço",R44,IF(OR(B44="insumo"),V44*R44,"")))) -> 1 | Y44: =IF(B44="insumo",W44*V44,IF(B44="serviço",SUMIFS(Y:Y,B:B,"insumo",E:E,E44,I:I,I44),"")) -> 3772 | Z44: =IFERROR(IF(B44="Unidade Construtiva",SUMIFS(Z:Z,B:B,"Célula Construtiva",G:G,G44),IF(B44="célula construtiva",SUMIFS(Z:Z,B:B,"Insumo",I:I,I44,G:G,G44),IF(B44="ETAPA",SUMIFS(Z:Z,B:B,"Insumo",K:K,K44,I:I,I44,G:G,G44),IF(B44="subetapa",SUMIFS(Z:Z,M:M,M44,B:B,"insumo",K:K,K44,I:I,I44,G:G,G44),IF(B44="complemento do insumo",V44*W44,IF(B44="INSUMO",R44*V44*W44,X44*Y44)))))),"") -> 3772 | AB44: =IF(B44="insumo",_xlfn.XLOOKUP(S44,Insumos!A:A,Insumos!D:D),"") -> Balancete | AC44: =IFERROR(IF(B44="","",Z44/SUMIF(B:B,"INSUMO",Z:Z)),0) -> 0.00054112779 | AE44: =IFERROR(IF(OR(Z44="",Z44=0),"",IF(AF44="","",IF(AF44="R$/mês",Z44/OBRA!$D$12,IF(AF44="R$/m²",Z44/OBRA!$D$10,IF(AF44="R$/apto",Orçamento!Z44/OBRA!$D$11,""))))),"") -> 1.9410981 | AF44: R$/m²
B45: Serviço | C45: =IF(B45="INSUMO",COUNTIFS(B:B,"INSUMO",S:S,S45),IF(B45="SERVIÇO",COUNTIFS(B:B,"SERVIÇO",S:S,S45),"")) -> 1 | D45: =IF(B45="Unidade Construtiva",TEXT(F45,"00"),IF(B45="Célula Construtiva",TEXT(H45,"00"),IF(B45="Etapa",CONCATENATE(TEXT(H45,"00"),".",TEXT(J45,"000")),IF(B45="Subetapa",CONCATENATE(TEXT(H45,"00"),".",TEXT(J45,"000"),".",TEXT(L45,"000")),IF(B45="Serviço",CONCATENATE(TEXT(H45,"00"),".",TEXT(J45,"000"),".",TEXT(L45,"000"),".",TEXT(N45,"000")),""))))) -> 01.001.004.002 | E45: =IF(B45="*","",IFERROR(IF(B45="SERVIÇO",D45,OFFSET(E45,-1,0)),"")) -> 01.001.004.002 | F45: =IF($B45="UNIDADE CONSTRUTIVA",OFFSET(F45,-1,0)+1,LARGE(F$10:F44,1)) -> 1 | G45: =IF(B45="*","",IF(B45="UNIDADE CONSTRUTIVA",S45,OFFSET(G45,-1,0))) -> GERENCIAMENTO TÉCNICO E ADMINISTRATIVO | H45: =IF(B45="UNIDADE CONSTRUTIVA",0,IF(B45="CÉLULA CONSTRUTIVA",OFFSET(H45,-1,0)+1,OFFSET(H45,-1,0))) -> 1 | I45: =IF(B45="*","",IF(B45="CÉLULA CONSTRUTIVA",S45,OFFSET(I45,-1,0))) -> GERENCIAMENTO TÉCNICO | J45: =IF(B45="CÉLULA CONSTRUTIVA",0,IF(B45="ETAPA",OFFSET(J45,-1,0)+1,OFFSET(J45,-1,0))) -> 1 | K45: =IF(B45="*","",IF(B45="ETAPA",S45,OFFSET(K45,-1,0))) -> ESTUDOS | PROJETOS | CONSULTORIAS | L45: =IF(B45="ETAPA",0,IF(B45="SUBETAPA",OFFSET(L45,-1,0)+1,OFFSET(L45,-1,0))) -> 4 | M45: =IF(B45="*","",IF(B45="SUBETAPA",S45,OFFSET(M45,-1,0))) -> Controle Tecnológico de Concreto | N45: =IF(B45="Subetapa",0,IF(B45="serviço",OFFSET(N45,-1,0)+1,OFFSET(N45,-1,0))) -> 2 | O45: =IF(B45="*","",IF(B45="SERVIÇO",S45,OFFSET(O45,-1,0))) -> Controle Tecnológico de Concreto - Supraestrutura | P45: =IF(S45="","",IF(Orçamento!$B45="INSUMO",S45,"")) | Q45: =IF(B45="","",IF(B45="Serviço",S45,"")) -> Controle Tecnológico de Concreto - Supraestrutura | R45: =IF(B45="serviço",U45,OFFSET(R45,-1,0)) -> 566 | S45: Controle Tecnológico de Concreto - Supraestrutura | T45: UN | U45: =ROUNDUP((U301+U400+U491+U582+U655)/5*6,) -> 566 | W45: =IFERROR(IF(B45="INSUMO",_xlfn.XLOOKUP(S45,Insumos!A:A,Insumos!C:C),""),"Inserir Preço") | X45: =IF(B45="Complemento do insumo",V45,IF(R45="","",IF(B45="serviço",R45,IF(OR(B45="insumo"),V45*R45,"")))) -> 566 | Y45: =IF(B45="insumo",W45*V45,IF(B45="serviço",SUMIFS(Y:Y,B:B,"insumo",E:E,E45,I:I,I45),"")) -> 23.07 | Z45: =IFERROR(IF(B45="Unidade Construtiva",SUMIFS(Z:Z,B:B,"Célula Construtiva",G:G,G45),IF(B45="célula construtiva",SUMIFS(Z:Z,B:B,"Insumo",I:I,I45,G:G,G45),IF(B45="ETAPA",SUMIFS(Z:Z,B:B,"Insumo",K:K,K45,I:I,I45,G:G,G45),IF(B45="subetapa",SUMIFS(Z:Z,M:M,M45,B:B,"insumo",K:K,K45,I:I,I45,G:G,G45),IF(B45="complemento do insumo",V45*W45,IF(B45="INSUMO",R45*V45*W45,X45*Y45)))))),"") -> 13057.62 | AB45: =IF(B45="insumo",_xlfn.XLOOKUP(S45,Insumos!A:A,Insumos!D:D),"") | AC45: =IFERROR(IF(B45="","",Z45/SUMIF(B:B,"INSUMO",Z:Z)),0) -> 0.0018732346 | AE45: =IFERROR(IF(OR(Z45="",Z45=0),"",IF(AF45="","",IF(AF45="R$/mês",Z45/OBRA!$D$12,IF(AF45="R$/m²",Z45/OBRA!$D$10,IF(AF45="R$/apto",Orçamento!Z45/OBRA!$D$11,""))))),"") -> 6.7195443 | AF45: R$/m²
B46: Insumo | C46: =IF(B46="INSUMO",COUNTIFS(B:B,"INSUMO",S:S,S46),IF(B46="SERVIÇO",COUNTIFS(B:B,"SERVIÇO",S:S,S46),"")) -> 1 | D46: =IF(B46="Unidade Construtiva",TEXT(F46,"00"),IF(B46="Célula Construtiva",TEXT(H46,"00"),IF(B46="Etapa",CONCATENATE(TEXT(H46,"00"),".",TEXT(J46,"000")),IF(B46="Subetapa",CONCATENATE(TEXT(H46,"00"),".",TEXT(J46,"000"),".",TEXT(L46,"000")),IF(B46="Serviço",CONCATENATE(TEXT(H46,"00"),".",TEXT(J46,"000"),".",TEXT(L46,"000"),".",TEXT(N46,"000")),""))))) | E46: =IF(B46="*","",IFERROR(IF(B46="SERVIÇO",D46,OFFSET(E46,-1,0)),"")) -> 01.001.004.002 | F46: =IF($B46="UNIDADE CONSTRUTIVA",OFFSET(F46,-1,0)+1,LARGE(F$10:F45,1)) -> 1 | G46: =IF(B46="*","",IF(B46="UNIDADE CONSTRUTIVA",S46,OFFSET(G46,-1,0))) -> GERENCIAMENTO TÉCNICO E ADMINISTRATIVO | H46: =IF(B46="UNIDADE CONSTRUTIVA",0,IF(B46="CÉLULA CONSTRUTIVA",OFFSET(H46,-1,0)+1,OFFSET(H46,-1,0))) -> 1 | I46: =IF(B46="*","",IF(B46="CÉLULA CONSTRUTIVA",S46,OFFSET(I46,-1,0))) -> GERENCIAMENTO TÉCNICO | J46: =IF(B46="CÉLULA CONSTRUTIVA",0,IF(B46="ETAPA",OFFSET(J46,-1,0)+1,OFFSET(J46,-1,0))) -> 1 | K46: =IF(B46="*","",IF(B46="ETAPA",S46,OFFSET(K46,-1,0))) -> ESTUDOS | PROJETOS | CONSULTORIAS | L46: =IF(B46="ETAPA",0,IF(B46="SUBETAPA",OFFSET(L46,-1,0)+1,OFFSET(L46,-1,0))) -> 4 | M46: =IF(B46="*","",IF(B46="SUBETAPA",S46,OFFSET(M46,-1,0))) -> Controle Tecnológico de Concreto | N46: =IF(B46="Subetapa",0,IF(B46="serviço",OFFSET(N46,-1,0)+1,OFFSET(N46,-1,0))) -> 2 | O46: =IF(B46="*","",IF(B46="SERVIÇO",S46,OFFSET(O46,-1,0))) -> Controle Tecnológico de Concreto - Supraestrutura | P46: =IF(S46="","",IF(Orçamento!$B46="INSUMO",S46,"")) -> CONTROLE TECNOLOGICO DO CONCRETO | Q46: =IF(B46="","",IF(B46="Serviço",S46,"")) | R46: =IF(B46="serviço",U46,OFFSET(R46,-1,0)) -> 566 | S46: CONTROLE TECNOLOGICO DO CONCRETO | T46: =_xlfn.XLOOKUP(S46,Insumos!$A$3:$A$371,Insumos!$B$3:$B$371) -> VB | U46: =IF($B46="insumo",R46,"") -> 566 | V46: 1 | W46: =IFERROR(IF(B46="INSUMO",_xlfn.XLOOKUP(S46,Insumos!A:A,Insumos!C:C),""),"Inserir Preço") -> 23.07 | X46: =IF(B46="Complemento do insumo",V46,IF(R46="","",IF(B46="serviço",R46,IF(OR(B46="insumo"),V46*R46,"")))) -> 566 | Y46: =IF(B46="insumo",W46*V46,IF(B46="serviço",SUMIFS(Y:Y,B:B,"insumo",E:E,E46,I:I,I46),"")) -> 23.07 | Z46: =IFERROR(IF(B46="Unidade Construtiva",SUMIFS(Z:Z,B:B,"Célula Construtiva",G:G,G46),IF(B46="célula construtiva",SUMIFS(Z:Z,B:B,"Insumo",I:I,I46,G:G,G46),IF(B46="ETAPA",SUMIFS(Z:Z,B:B,"Insumo",K:K,K46,I:I,I46,G:G,G46),IF(B46="subetapa",SUMIFS(Z:Z,M:M,M46,B:B,"insumo",K:K,K46,I:I,I46,G:G,G46),IF(B46="complemento do insumo",V46*W46,IF(B46="INSUMO",R46*V46*W46,X46*Y46)))))),"") -> 13057.62 | AB46: =IF(B46="insumo",_xlfn.XLOOKUP(S46,Insumos!A:A,Insumos!D:D),"") | AC46: =IFERROR(IF(B46="","",Z46/SUMIF(B:B,"INSUMO",Z:Z)),0) -> 0.0018732346 | AE46: =IFERROR(IF(OR(Z46="",Z46=0),"",IF(AF46="","",IF(AF46="R$/mês",Z46/OBRA!$D$12,IF(AF46="R$/m²",Z46/OBRA!$D$10,IF(AF46="R$/apto",Orçamento!Z46/OBRA!$D$11,""))))),"") -> 6.7195443 | AF46: R$/m²
B47: Etapa | C47: =IF(B47="INSUMO",COUNTIFS(B:B,"INSUMO",S:S,S47),IF(B47="SERVIÇO",COUNTIFS(B:B,"SERVIÇO",S:S,S47),"")) | D47: =IF(B47="Unidade Construtiva",TEXT(F47,"00"),IF(B47="Célula Construtiva",TEXT(H47,"00"),IF(B47="Etapa",CONCATENATE(TEXT(H47,"00"),".",TEXT(J47,"000")),IF(B47="Subetapa",CONCATENATE(TEXT(H47,"00"),".",TEXT(J47,"000"),".",TEXT(L47,"000")),IF(B47="Serviço",CONCATENATE(TEXT(H47,"00"),".",TEXT(J47,"000"),".",TEXT(L47,"000"),".",TEXT(N47,"000")),""))))) -> 01.002 | E47: =IF(B47="*","",IFERROR(IF(B47="SERVIÇO",D47,OFFSET(E47,-1,0)),"")) -> 01.001.004.002 | F47: =IF($B47="UNIDADE CONSTRUTIVA",OFFSET(F47,-1,0)+1,LARGE(F$10:F46,1)) -> 1 | G47: =IF(B47="*","",IF(B47="UNIDADE CONSTRUTIVA",S47,OFFSET(G47,-1,0))) -> GERENCIAMENTO TÉCNICO E ADMINISTRATIVO | H47: =IF(B47="UNIDADE CONSTRUTIVA",0,IF(B47="CÉLULA CONSTRUTIVA",OFFSET(H47,-1,0)+1,OFFSET(H47,-1,0))) -> 1 | I47: =IF(B47="*","",IF(B47="CÉLULA CONSTRUTIVA",S47,OFFSET(I47,-1,0))) -> GERENCIAMENTO TÉCNICO | J47: =IF(B47="CÉLULA CONSTRUTIVA",0,IF(B47="ETAPA",OFFSET(J47,-1,0)+1,OFFSET(J47,-1,0))) -> 2 | K47: =IF(B47="*","",IF(B47="ETAPA",S47,OFFSET(K47,-1,0))) -> TAXAS | DOCUMENTOS | L47: =IF(B47="ETAPA",0,IF(B47="SUBETAPA",OFFSET(L47,-1,0)+1,OFFSET(L47,-1,0))) -> 0 | M47: =IF(B47="*","",IF(B47="SUBETAPA",S47,OFFSET(M47,-1,0))) -> Controle Tecnológico de Concreto | N47: =IF(B47="Subetapa",0,IF(B47="serviço",OFFSET(N47,-1,0)+1,OFFSET(N47,-1,0))) -> 2 | O47: =IF(B47="*","",IF(B47="SERVIÇO",S47,OFFSET(O47,-1,0))) -> Controle Tecnológico de Concreto - Supraestrutura | P47: =IF(S47="","",IF(Orçamento!$B47="INSUMO",S47,"")) | Q47: =IF(B47="","",IF(B47="Serviço",S47,"")) | R47: =IF(B47="serviço",U47,OFFSET(R47,-1,0)) -> 566 | S47: TAXAS | DOCUMENTOS | U47: =IF($B47="insumo",R47,"") | W47: =IFERROR(IF(B47="INSUMO",_xlfn.XLOOKUP(S47,Insumos!A:A,Insumos!C:C),""),"Inserir Preço") | X47: =IF(B47="Complemento do insumo",V47,IF(R47="","",IF(B47="serviço",R47,IF(OR(B47="insumo"),V47*R47,"")))) | Y47: =IF(B47="insumo",W47*V47,IF(B47="serviço",SUMIFS(Y:Y,B:B,"insumo",E:E,E47,I:I,I47),"")) | Z47: =IFERROR(IF(B47="Unidade Construtiva",SUMIFS(Z:Z,B:B,"Célula Construtiva",G:G,G47),IF(B47="célula construtiva",SUMIFS(Z:Z,B:B,"Insumo",I:I,I47,G:G,G47),IF(B47="ETAPA",SUMIFS(Z:Z,B:B,"Insumo",K:K,K47,I:I,I47,G:G,G47),IF(B47="subetapa",SUMIFS(Z:Z,M:M,M47,B:B,"insumo",K:K,K47,I:I,I47,G:G,G47),IF(B47="complemento do insumo",V47*W47,IF(B47="INSUMO",R47*V47*W47,X47*Y47)))))),"") -> 45818.269 | AB47: =IF(B47="insumo",_xlfn.XLOOKUP(S47,Insumos!A:A,Insumos!D:D),"") | AC47: =IFERROR(IF(B47="","",Z47/SUMIF(B:B,"INSUMO",Z:Z)),0) -> 0.0065730485 | AE47: =IFERROR(IF(OR(Z47="",Z47=0),"",IF(AF47="","",IF(AF47="R$/mês",Z47/OBRA!$D$12,IF(AF47="R$/m²",Z47/OBRA!$D$10,IF(AF47="R$/apto",Orçamento!Z47/OBRA!$D$11,""))))),"") -> 23.578408 | AF47: R$/m²
B48: Subetapa | C48: =IF(B48="INSUMO",COUNTIFS(B:B,"INSUMO",S:S,S48),IF(B48="SERVIÇO",COUNTIFS(B:B,"SERVIÇO",S:S,S48),"")) | D48: =IF(B48="Unidade Construtiva",TEXT(F48,"00"),IF(B48="Célula Construtiva",TEXT(H48,"00"),IF(B48="Etapa",CONCATENATE(TEXT(H48,"00"),".",TEXT(J48,"000")),IF(B48="Subetapa",CONCATENATE(TEXT(H48,"00"),".",TEXT(J48,"000"),".",TEXT(L48,"000")),IF(B48="Serviço",CONCATENATE(TEXT(H48,"00"),".",TEXT(J48,"000"),".",TEXT(L48,"000"),".",TEXT(N48,"000")),""))))) -> 01.002.001 | E48: =IF(B48="*","",IFERROR(IF(B48="SERVIÇO",D48,OFFSET(E48,-1,0)),"")) -> 01.001.004.002 | F48: =IF($B48="UNIDADE CONSTRUTIVA",OFFSET(F48,-1,0)+1,LARGE(F$10:F47,1)) -> 1 | G48: =IF(B48="*","",IF(B48="UNIDADE CONSTRUTIVA",S48,OFFSET(G48,-1,0))) -> GERENCIAMENTO TÉCNICO E ADMINISTRATIVO | H48: =IF(B48="UNIDADE CONSTRUTIVA",0,IF(B48="CÉLULA CONSTRUTIVA",OFFSET(H48,-1,0)+1,OFFSET(H48,-1,0))) -> 1 | I48: =IF(B48="*","",IF(B48="CÉLULA CONSTRUTIVA",S48,OFFSET(I48,-1,0))) -> GERENCIAMENTO TÉCNICO | J48: =IF(B48="CÉLULA CONSTRUTIVA",0,IF(B48="ETAPA",OFFSET(J48,-1,0)+1,OFFSET(J48,-1,0))) -> 2 | K48: =IF(B48="*","",IF(B48="ETAPA",S48,OFFSET(K48,-1,0))) -> TAXAS | DOCUMENTOS | L48: =IF(B48="ETAPA",0,IF(B48="SUBETAPA",OFFSET(L48,-1,0)+1,OFFSET(L48,-1,0))) -> 1 | M48: =IF(B48="*","",IF(B48="SUBETAPA",S48,OFFSET(M48,-1,0))) -> Licenciamento - Taxas - Impostos | N48: =IF(B48="Subetapa",0,IF(B48="serviço",OFFSET(N48,-1,0)+1,OFFSET(N48,-1,0))) -> 0 | O48: =IF(B48="*","",IF(B48="SERVIÇO",S48,OFFSET(O48,-1,0))) -> Controle Tecnológico de Concreto - Supraestrutura | P48: =IF(S48="","",IF(Orçamento!$B48="INSUMO",S48,"")) | Q48: =IF(B48="","",IF(B48="Serviço",S48,"")) | R48: =IF(B48="serviço",U48,OFFSET(R48,-1,0)) -> 566 | S48: Licenciamento - Taxas - Impostos | U48: =IF($B48="insumo",R48,"") | W48: =IFERROR(IF(B48="INSUMO",_xlfn.XLOOKUP(S48,Insumos!A:A,Insumos!C:C),""),"Inserir Preço") | X48: =IF(B48="Complemento do insumo",V48,IF(R48="","",IF(B48="serviço",R48,IF(OR(B48="insumo"),V48*R48,"")))) | Y48: =IF(B48="insumo",W48*V48,IF(B48="serviço",SUMIFS(Y:Y,B:B,"insumo",E:E,E48,I:I,I48),"")) | Z48: =IFERROR(IF(B48="Unidade Construtiva",SUMIFS(Z:Z,B:B,"Célula Construtiva",G:G,G48),IF(B48="célula construtiva",SUMIFS(Z:Z,B:B,"Insumo",I:I,I48,G:G,G48),IF(B48="ETAPA",SUMIFS(Z:Z,B:B,"Insumo",K:K,K48,I:I,I48,G:G,G48),IF(B48="subetapa",SUMIFS(Z:Z,M:M,M48,B:B,"insumo",K:K,K48,I:I,I48,G:G,G48),IF(B48="complemento do insumo",V48*W48,IF(B48="INSUMO",R48*V48*W48,X48*Y48)))))),"") -> 45818.269 | AB48: =IF(B48="insumo",_xlfn.XLOOKUP(S48,Insumos!A:A,Insumos!D:D),"") | AC48: =IFERROR(IF(B48="","",Z48/SUMIF(B:B,"INSUMO",Z:Z)),0) -> 0.0065730485 | AE48: =IFERROR(IF(OR(Z48="",Z48=0),"",IF(AF48="","",IF(AF48="R$/mês",Z48/OBRA!$D$12,IF(AF48="R$/m²",Z48/OBRA!$D$10,IF(AF48="R$/apto",Orçamento!Z48/OBRA!$D$11,""))))),"") -> 23.578408 | AF48: R$/m²
B49: Serviço | C49: =IF(B49="INSUMO",COUNTIFS(B:B,"INSUMO",S:S,S49),IF(B49="SERVIÇO",COUNTIFS(B:B,"SERVIÇO",S:S,S49),"")) -> 1 | D49: =IF(B49="Unidade Construtiva",TEXT(F49,"00"),IF(B49="Célula Construtiva",TEXT(H49,"00"),IF(B49="Etapa",CONCATENATE(TEXT(H49,"00"),".",TEXT(J49,"000")),IF(B49="Subetapa",CONCATENATE(TEXT(H49,"00"),".",TEXT(J49,"000"),".",TEXT(L49,"000")),IF(B49="Serviço",CONCATENATE(TEXT(H49,"00"),".",TEXT(J49,"000"),".",TEXT(L49,"000"),".",TEXT(N49,"000")),""))))) -> 01.002.001.001 | E49: =IF(B49="*","",IFERROR(IF(B49="SERVIÇO",D49,OFFSET(E49,-1,0)),"")) -> 01.002.001.001 | F49: =IF($B49="UNIDADE CONSTRUTIVA",OFFSET(F49,-1,0)+1,LARGE(F$10:F48,1)) -> 1 | G49: =IF(B49="*","",IF(B49="UNIDADE CONSTRUTIVA",S49,OFFSET(G49,-1,0))) -> GERENCIAMENTO TÉCNICO E ADMINISTRATIVO | H49: =IF(B49="UNIDADE CONSTRUTIVA",0,IF(B49="CÉLULA CONSTRUTIVA",OFFSET(H49,-1,0)+1,OFFSET(H49,-1,0))) -> 1 | I49: =IF(B49="*","",IF(B49="CÉLULA CONSTRUTIVA",S49,OFFSET(I49,-1,0))) -> GERENCIAMENTO TÉCNICO | J49: =IF(B49="CÉLULA CONSTRUTIVA",0,IF(B49="ETAPA",OFFSET(J49,-1,0)+1,OFFSET(J49,-1,0))) -> 2 | K49: =IF(B49="*","",IF(B49="ETAPA",S49,OFFSET(K49,-1,0))) -> TAXAS | DOCUMENTOS | L49: =IF(B49="ETAPA",0,IF(B49="SUBETAPA",OFFSET(L49,-1,0)+1,OFFSET(L49,-1,0))) -> 1 | M49: =IF(B49="*","",IF(B49="SUBETAPA",S49,OFFSET(M49,-1,0))) -> Licenciamento - Taxas - Impostos | N49: =IF(B49="Subetapa",0,IF(B49="serviço",OFFSET(N49,-1,0)+1,OFFSET(N49,-1,0))) -> 1 | O49: =IF(B49="*","",IF(B49="SERVIÇO",S49,OFFSET(O49,-1,0))) -> Despesas certidão INSS | P49: =IF(S49="","",IF(Orçamento!$B49="INSUMO",S49,"")) | Q49: =IF(B49="","",IF(B49="Serviço",S49,"")) -> Despesas certidão INSS | R49: =IF(B49="serviço",U49,OFFSET(R49,-1,0)) -> 1 | S49: Despesas certidão INSS | T49: VB | U49: 1 | W49: =IFERROR(IF(B49="INSUMO",_xlfn.XLOOKUP(S49,Insumos!A:A,Insumos!C:C),""),"Inserir Preço") | X49: =IF(B49="Complemento do insumo",V49,IF(R49="","",IF(B49="serviço",R49,IF(OR(B49="insumo"),V49*R49,"")))) -> 1 | Y49: =IF(B49="insumo",W49*V49,IF(B49="serviço",SUMIFS(Y:Y,B:B,"insumo",E:E,E49,I:I,I49),"")) -> 2111.2724 | Z49: =IFERROR(IF(B49="Unidade Construtiva",SUMIFS(Z:Z,B:B,"Célula Construtiva",G:G,G49),IF(B49="célula construtiva",SUMIFS(Z:Z,B:B,"Insumo",I:I,I49,G:G,G49),IF(B49="ETAPA",SUMIFS(Z:Z,B:B,"Insumo",K:K,K49,I:I,I49,G:G,G49),IF(B49="subetapa",SUMIFS(Z:Z,M:M,M49,B:B,"insumo",K:K,K49,I:I,I49,G:G,G49),IF(B49="complemento do insumo",V49*W49,IF(B49="INSUMO",R49*V49*W49,X49*Y49)))))),"") -> 2111.2724 | AB49: =IF(B49="insumo",_xlfn.XLOOKUP(S49,Insumos!A:A,Insumos!D:D),"") | AC49: =IFERROR(IF(B49="","",Z49/SUMIF(B:B,"INSUMO",Z:Z)),0) -> 0.00030288128 | AE49: =IFERROR(IF(OR(Z49="",Z49=0),"",IF(AF49="","",IF(AF49="R$/mês",Z49/OBRA!$D$12,IF(AF49="R$/m²",Z49/OBRA!$D$10,IF(AF49="R$/apto",Orçamento!Z49/OBRA!$D$11,""))))),"") -> 1.0864758 | AF49: R$/m²
B50: Insumo | C50: =IF(B50="INSUMO",COUNTIFS(B:B,"INSUMO",S:S,S50),IF(B50="SERVIÇO",COUNTIFS(B:B,"SERVIÇO",S:S,S50),"")) -> 1 | D50: =IF(B50="Unidade Construtiva",TEXT(F50,"00"),IF(B50="Célula Construtiva",TEXT(H50,"00"),IF(B50="Etapa",CONCATENATE(TEXT(H50,"00"),".",TEXT(J50,"000")),IF(B50="Subetapa",CONCATENATE(TEXT(H50,"00"),".",TEXT(J50,"000"),".",TEXT(L50,"000")),IF(B50="Serviço",CONCATENATE(TEXT(H50,"00"),".",TEXT(J50,"000"),".",TEXT(L50,"000"),".",TEXT(N50,"000")),""))))) | E50: =IF(B50="*","",IFERROR(IF(B50="SERVIÇO",D50,OFFSET(E50,-1,0)),"")) -> 01.002.001.001 | F50: =IF($B50="UNIDADE CONSTRUTIVA",OFFSET(F50,-1,0)+1,LARGE(F$10:F49,1)) -> 1 | G50: =IF(B50="*","",IF(B50="UNIDADE CONSTRUTIVA",S50,OFFSET(G50,-1,0))) -> GERENCIAMENTO TÉCNICO E ADMINISTRATIVO | H50: =IF(B50="UNIDADE CONSTRUTIVA",0,IF(B50="CÉLULA CONSTRUTIVA",OFFSET(H50,-1,0)+1,OFFSET(H50,-1,0))) -> 1 | I50: =IF(B50="*","",IF(B50="CÉLULA CONSTRUTIVA",S50,OFFSET(I50,-1,0))) -> GERENCIAMENTO TÉCNICO | J50: =IF(B50="CÉLULA CONSTRUTIVA",0,IF(B50="ETAPA",OFFSET(J50,-1,0)+1,OFFSET(J50,-1,0))) -> 2 | K50: =IF(B50="*","",IF(B50="ETAPA",S50,OFFSET(K50,-1,0))) -> TAXAS | DOCUMENTOS | L50: =IF(B50="ETAPA",0,IF(B50="SUBETAPA",OFFSET(L50,-1,0)+1,OFFSET(L50,-1,0))) -> 1 | M50: =IF(B50="*","",IF(B50="SUBETAPA",S50,OFFSET(M50,-1,0))) -> Licenciamento - Taxas - Impostos | N50: =IF(B50="Subetapa",0,IF(B50="serviço",OFFSET(N50,-1,0)+1,OFFSET(N50,-1,0))) -> 1 | O50: =IF(B50="*","",IF(B50="SERVIÇO",S50,OFFSET(O50,-1,0))) -> Despesas certidão INSS | P50: =IF(S50="","",IF(Orçamento!$B50="INSUMO",S50,"")) -> Certidão INSS | Q50: =IF(B50="","",IF(B50="Serviço",S50,"")) | R50: =IF(B50="serviço",U50,OFFSET(R50,-1,0)) -> 1 | S50: Certidão INSS | T50: =_xlfn.XLOOKUP(S50,Insumos!$A$3:$A$371,Insumos!$B$3:$B$371) -> VB | U50: =IF($B50="insumo",R50,"") -> 1 | V50: 1 | W50: =IFERROR(IF(B50="INSUMO",_xlfn.XLOOKUP(S50,Insumos!A:A,Insumos!C:C),""),"Inserir Preço") -> 2111.2724 | X50: =IF(B50="Complemento do insumo",V50,IF(R50="","",IF(B50="serviço",R50,IF(OR(B50="insumo"),V50*R50,"")))) -> 1 | Y50: =IF(B50="insumo",W50*V50,IF(B50="serviço",SUMIFS(Y:Y,B:B,"insumo",E:E,E50,I:I,I50),"")) -> 2111.2724 | Z50: =IFERROR(IF(B50="Unidade Construtiva",SUMIFS(Z:Z,B:B,"Célula Construtiva",G:G,G50),IF(B50="célula construtiva",SUMIFS(Z:Z,B:B,"Insumo",I:I,I50,G:G,G50),IF(B50="ETAPA",SUMIFS(Z:Z,B:B,"Insumo",K:K,K50,I:I,I50,G:G,G50),IF(B50="subetapa",SUMIFS(Z:Z,M:M,M50,B:B,"insumo",K:K,K50,I:I,I50,G:G,G50),IF(B50="complemento do insumo",V50*W50,IF(B50="INSUMO",R50*V50*W50,X50*Y50)))))),"") -> 2111.2724 | AB50: =IF(B50="insumo",_xlfn.XLOOKUP(S50,Insumos!A:A,Insumos!D:D),"") -> Base de dados | AC50: =IFERROR(IF(B50="","",Z50/SUMIF(B:B,"INSUMO",Z:Z)),0) -> 0.00030288128 | AE50: =IFERROR(IF(OR(Z50="",Z50=0),"",IF(AF50="","",IF(AF50="R$/mês",Z50/OBRA!$D$12,IF(AF50="R$/m²",Z50/OBRA!$D$10,IF(AF50="R$/apto",Orçamento!Z50/OBRA!$D$11,""))))),"") -> 1.0864758 | AF50: R$/m²
B51: Serviço | C51: =IF(B51="INSUMO",COUNTIFS(B:B,"INSUMO",S:S,S51),IF(B51="SERVIÇO",COUNTIFS(B:B,"SERVIÇO",S:S,S51),"")) -> 1 | D51: =IF(B51="Unidade Construtiva",TEXT(F51,"00"),IF(B51="Célula Construtiva",TEXT(H51,"00"),IF(B51="Etapa",CONCATENATE(TEXT(H51,"00"),".",TEXT(J51,"000")),IF(B51="Subetapa",CONCATENATE(TEXT(H51,"00"),".",TEXT(J51,"000"),".",TEXT(L51,"000")),IF(B51="Serviço",CONCATENATE(TEXT(H51,"00"),".",TEXT(J51,"000"),".",TEXT(L51,"000"),".",TEXT(N51,"000")),""))))) -> 01.002.001.002 | E51: =IF(B51="*","",IFERROR(IF(B51="SERVIÇO",D51,OFFSET(E51,-1,0)),"")) -> 01.002.001.002 | F51: =IF($B51="UNIDADE CONSTRUTIVA",OFFSET(F51,-1,0)+1,LARGE(F$10:F50,1)) -> 1 | G51: =IF(B51="*","",IF(B51="UNIDADE CONSTRUTIVA",S51,OFFSET(G51,-1,0))) -> GERENCIAMENTO TÉCNICO E ADMINISTRATIVO | H51: =IF(B51="UNIDADE CONSTRUTIVA",0,IF(B51="CÉLULA CONSTRUTIVA",OFFSET(H51,-1,0)+1,OFFSET(H51,-1,0))) -> 1 | I51: =IF(B51="*","",IF(B51="CÉLULA CONSTRUTIVA",S51,OFFSET(I51,-1,0))) -> GERENCIAMENTO TÉCNICO | J51: =IF(B51="CÉLULA CONSTRUTIVA",0,IF(B51="ETAPA",OFFSET(J51,-1,0)+1,OFFSET(J51,-1,0))) -> 2 | K51: =IF(B51="*","",IF(B51="ETAPA",S51,OFFSET(K51,-1,0))) -> TAXAS | DOCUMENTOS | L51: =IF(B51="ETAPA",0,IF(B51="SUBETAPA",OFFSET(L51,-1,0)+1,OFFSET(L51,-1,0))) -> 1 | M51: =IF(B51="*","",IF(B51="SUBETAPA",S51,OFFSET(M51,-1,0))) -> Licenciamento - Taxas - Impostos | N51: =IF(B51="Subetapa",0,IF(B51="serviço",OFFSET(N51,-1,0)+1,OFFSET(N51,-1,0))) -> 2 | O51: =IF(B51="*","",IF(B51="SERVIÇO",S51,OFFSET(O51,-1,0))) -> Despesas cartorio e juridicas | P51: =IF(S51="","",IF(Orçamento!$B51="INSUMO",S51,"")) | Q51: =IF(B51="","",IF(B51="Serviço",S51,"")) -> Despesas cartorio e juridicas | R51: =IF(B51="serviço",U51,OFFSET(R51,-1,0)) -> 1 | S51: Despesas cartorio e juridicas | T51: VB | U51: 1 | W51: =IFERROR(IF(B51="INSUMO",_xlfn.XLOOKUP(S51,Insumos!A:A,Insumos!C:C),""),"Inserir Preço") | X51: =IF(B51="Complemento do insumo",V51,IF(R51="","",IF(B51="serviço",R51,IF(OR(B51="insumo"),V51*R51,"")))) -> 1 | Y51: =IF(B51="insumo",W51*V51,IF(B51="serviço",SUMIFS(Y:Y,B:B,"insumo",E:E,E51,I:I,I51),"")) -> 6916.85 | Z51: =IFERROR(IF(B51="Unidade Construtiva",SUMIFS(Z:Z,B:B,"Célula Construtiva",G:G,G51),IF(B51="célula construtiva",SUMIFS(Z:Z,B:B,"Insumo",I:I,I51,G:G,G51),IF(B51="ETAPA",SUMIFS(Z:Z,B:B,"Insumo",K:K,K51,I:I,I51,G:G,G51),IF(B51="subetapa",SUMIFS(Z:Z,M:M,M51,B:B,"insumo",K:K,K51,I:I,I51,G:G,G51),IF(B51="complemento do insumo",V51*W51,IF(B51="INSUMO",R51*V51*W51,X51*Y51)))))),"") -> 6916.85 | AB51: =IF(B51="insumo",_xlfn.XLOOKUP(S51,Insumos!A:A,Insumos!D:D),"") | AC51: =IFERROR(IF(B51="","",Z51/SUMIF(B:B,"INSUMO",Z:Z)),0) -> 0.00099228519 | AE51: =IFERROR(IF(OR(Z51="",Z51=0),"",IF(AF51="","",IF(AF51="R$/mês",Z51/OBRA!$D$12,IF(AF51="R$/m²",Z51/OBRA!$D$10,IF(AF51="R$/apto",Orçamento!Z51/OBRA!$D$11,""))))),"") -> 3.5594603 | AF51: R$/m²
B52: Insumo | C52: =IF(B52="INSUMO",COUNTIFS(B:B,"INSUMO",S:S,S52),IF(B52="SERVIÇO",COUNTIFS(B:B,"SERVIÇO",S:S,S52),"")) -> 1 | D52: =IF(B52="Unidade Construtiva",TEXT(F52,"00"),IF(B52="Célula Construtiva",TEXT(H52,"00"),IF(B52="Etapa",CONCATENATE(TEXT(H52,"00"),".",TEXT(J52,"000")),IF(B52="Subetapa",CONCATENATE(TEXT(H52,"00"),".",TEXT(J52,"000"),".",TEXT(L52,"000")),IF(B52="Serviço",CONCATENATE(TEXT(H52,"00"),".",TEXT(J52,"000"),".",TEXT(L52,"000"),".",TEXT(N52,"000")),""))))) | E52: =IF(B52="*","",IFERROR(IF(B52="SERVIÇO",D52,OFFSET(E52,-1,0)),"")) -> 01.002.001.002 | F52: =IF($B52="UNIDADE CONSTRUTIVA",OFFSET(F52,-1,0)+1,LARGE(F$10:F51,1)) -> 1 | G52: =IF(B52="*","",IF(B52="UNIDADE CONSTRUTIVA",S52,OFFSET(G52,-1,0))) -> GERENCIAMENTO TÉCNICO E ADMINISTRATIVO | H52: =IF(B52="UNIDADE CONSTRUTIVA",0,IF(B52="CÉLULA CONSTRUTIVA",OFFSET(H52,-1,0)+1,OFFSET(H52,-1,0))) -> 1 | I52: =IF(B52="*","",IF(B52="CÉLULA CONSTRUTIVA",S52,OFFSET(I52,-1,0))) -> GERENCIAMENTO TÉCNICO | J52: =IF(B52="CÉLULA CONSTRUTIVA",0,IF(B52="ETAPA",OFFSET(J52,-1,0)+1,OFFSET(J52,-1,0))) -> 2 | K52: =IF(B52="*","",IF(B52="ETAPA",S52,OFFSET(K52,-1,0))) -> TAXAS | DOCUMENTOS | L52: =IF(B52="ETAPA",0,IF(B52="SUBETAPA",OFFSET(L52,-1,0)+1,OFFSET(L52,-1,0))) -> 1 | M52: =IF(B52="*","",IF(B52="SUBETAPA",S52,OFFSET(M52,-1,0))) -> Licenciamento - Taxas - Impostos | N52: =IF(B52="Subetapa",0,IF(B52="serviço",OFFSET(N52,-1,0)+1,OFFSET(N52,-1,0))) -> 2 | O52: =IF(B52="*","",IF(B52="SERVIÇO",S52,OFFSET(O52,-1,0))) -> Despesas cartorio e juridicas | P52: =IF(S52="","",IF(Orçamento!$B52="INSUMO",S52,"")) -> Despesas de cartório, licenças, certidões e jurídicas | Q52: =IF(B52="","",IF(B52="Serviço",S52,"")) | R52: =IF(B52="serviço",U52,OFFSET(R52,-1,0)) -> 1 | S52: Despesas de cartório, licenças, certidões e jurídicas | T52: =_xlfn.XLOOKUP(S52,Insumos!$A$3:$A$371,Insumos!$B$3:$B$371) -> VB | U52: =IF($B52="insumo",R52,"") -> 1 | V52: 1 | W52: =IFERROR(IF(B52="INSUMO",_xlfn.XLOOKUP(S52,Insumos!A:A,Insumos!C:C),""),"Inserir Preço") -> 6916.85 | X52: =IF(B52="Complemento do insumo",V52,IF(R52="","",IF(B52="serviço",R52,IF(OR(B52="insumo"),V52*R52,"")))) -> 1 | Y52: =IF(B52="insumo",W52*V52,IF(B52="serviço",SUMIFS(Y:Y,B:B,"insumo",E:E,E52,I:I,I52),"")) -> 6916.85 | Z52: =IFERROR(IF(B52="Unidade Construtiva",SUMIFS(Z:Z,B:B,"Célula Construtiva",G:G,G52),IF(B52="célula construtiva",SUMIFS(Z:Z,B:B,"Insumo",I:I,I52,G:G,G52),IF(B52="ETAPA",SUMIFS(Z:Z,B:B,"Insumo",K:K,K52,I:I,I52,G:G,G52),IF(B52="subetapa",SUMIFS(Z:Z,M:M,M52,B:B,"insumo",K:K,K52,I:I,I52,G:G,G52),IF(B52="complemento do insumo",V52*W52,IF(B52="INSUMO",R52*V52*W52,X52*Y52)))))),"") -> 6916.85 | AB52: =IF(B52="insumo",_xlfn.XLOOKUP(S52,Insumos!A:A,Insumos!D:D),"") -> Recebido Cliente | AC52: =IFERROR(IF(B52="","",Z52/SUMIF(B:B,"INSUMO",Z:Z)),0) -> 0.00099228519 | AE52: =IFERROR(IF(OR(Z52="",Z52=0),"",IF(AF52="","",IF(AF52="R$/mês",Z52/OBRA!$D$12,IF(AF52="R$/m²",Z52/OBRA!$D$10,IF(AF52="R$/apto",Orçamento!Z52/OBRA!$D$11,""))))),"") -> 3.5594603 | AF52: R$/m²
B53: Serviço | C53: =IF(B53="INSUMO",COUNTIFS(B:B,"INSUMO",S:S,S53),IF(B53="SERVIÇO",COUNTIFS(B:B,"SERVIÇO",S:S,S53),"")) -> 1 | D53: =IF(B53="Unidade Construtiva",TEXT(F53,"00"),IF(B53="Célula Construtiva",TEXT(H53,"00"),IF(B53="Etapa",CONCATENATE(TEXT(H53,"00"),".",TEXT(J53,"000")),IF(B53="Subetapa",CONCATENATE(TEXT(H53,"00"),".",TEXT(J53,"000"),".",TEXT(L53,"000")),IF(B53="Serviço",CONCATENATE(TEXT(H53,"00"),".",TEXT(J53,"000"),".",TEXT(L53,"000"),".",TEXT(N53,"000")),""))))) -> 01.002.001.003 | E53: =IF(B53="*","",IFERROR(IF(B53="SERVIÇO",D53,OFFSET(E53,-1,0)),"")) -> 01.002.001.003 | F53: =IF($B53="UNIDADE CONSTRUTIVA",OFFSET(F53,-1,0)+1,LARGE(F$10:F52,1)) -> 1 | G53: =IF(B53="*","",IF(B53="UNIDADE CONSTRUTIVA",S53,OFFSET(G53,-1,0))) -> GERENCIAMENTO TÉCNICO E ADMINISTRATIVO | H53: =IF(B53="UNIDADE CONSTRUTIVA",0,IF(B53="CÉLULA CONSTRUTIVA",OFFSET(H53,-1,0)+1,OFFSET(H53,-1,0))) -> 1 | I53: =IF(B53="*","",IF(B53="CÉLULA CONSTRUTIVA",S53,OFFSET(I53,-1,0))) -> GERENCIAMENTO TÉCNICO | J53: =IF(B53="CÉLULA CONSTRUTIVA",0,IF(B53="ETAPA",OFFSET(J53,-1,0)+1,OFFSET(J53,-1,0))) -> 2 | K53: =IF(B53="*","",IF(B53="ETAPA",S53,OFFSET(K53,-1,0))) -> TAXAS | DOCUMENTOS | L53: =IF(B53="ETAPA",0,IF(B53="SUBETAPA",OFFSET(L53,-1,0)+1,OFFSET(L53,-1,0))) -> 1 | M53: =IF(B53="*","",IF(B53="SUBETAPA",S53,OFFSET(M53,-1,0))) -> Licenciamento - Taxas - Impostos | N53: =IF(B53="Subetapa",0,IF(B53="serviço",OFFSET(N53,-1,0)+1,OFFSET(N53,-1,0))) -> 3 | O53: =IF(B53="*","",IF(B53="SERVIÇO",S53,OFFSET(O53,-1,0))) -> Taxas de ART e RRT | P53: =IF(S53="","",IF(Orçamento!$B53="INSUMO",S53,"")) | Q53: =IF(B53="","",IF(B53="Serviço",S53,"")) -> Taxas de ART e RRT | R53: =IF(B53="serviço",U53,OFFSET(R53,-1,0)) -> 1 | S53: Taxas de ART e RRT | T53: VB | U53: 1 | W53: =IFERROR(IF(B53="INSUMO",_xlfn.XLOOKUP(S53,Insumos!A:A,Insumos!C:C),""),"Inserir Preço") | X53: =IF(B53="Complemento do insumo",V53,IF(R53="","",IF(B53="serviço",R53,IF(OR(B53="insumo"),V53*R53,"")))) -> 1 | Y53: =IF(B53="insumo",W53*V53,IF(B53="serviço",SUMIFS(Y:Y,B:B,"insumo",E:E,E53,I:I,I53),"")) -> 2250 | Z53: =IFERROR(IF(B53="Unidade Construtiva",SUMIFS(Z:Z,B:B,"Célula Construtiva",G:G,G53),IF(B53="célula construtiva",SUMIFS(Z:Z,B:B,"Insumo",I:I,I53,G:G,G53),IF(B53="ETAPA",SUMIFS(Z:Z,B:B,"Insumo",K:K,K53,I:I,I53,G:G,G53),IF(B53="subetapa",SUMIFS(Z:Z,M:M,M53,B:B,"insumo",K:K,K53,I:I,I53,G:G,G53),IF(B53="complemento do insumo",V53*W53,IF(B53="INSUMO",R53*V53*W53,X53*Y53)))))),"") -> 2250 | AB53: =IF(B53="insumo",_xlfn.XLOOKUP(S53,Insumos!A:A,Insumos!D:D),"") | AC53: =IFERROR(IF(B53="","",Z53/SUMIF(B:B,"INSUMO",Z:Z)),0) -> 0.00032278301 | AE53: =IFERROR(IF(OR(Z53="",Z53=0),"",IF(AF53="","",IF(AF53="R$/mês",Z53/OBRA!$D$12,IF(AF53="R$/m²",Z53/OBRA!$D$10,IF(AF53="R$/apto",Orçamento!Z53/OBRA!$D$11,""))))),"") -> 1.157866 | AF53: R$/m²
B54: Insumo | C54: =IF(B54="INSUMO",COUNTIFS(B:B,"INSUMO",S:S,S54),IF(B54="SERVIÇO",COUNTIFS(B:B,"SERVIÇO",S:S,S54),"")) -> 1 | D54: =IF(B54="Unidade Construtiva",TEXT(F54,"00"),IF(B54="Célula Construtiva",TEXT(H54,"00"),IF(B54="Etapa",CONCATENATE(TEXT(H54,"00"),".",TEXT(J54,"000")),IF(B54="Subetapa",CONCATENATE(TEXT(H54,"00"),".",TEXT(J54,"000"),".",TEXT(L54,"000")),IF(B54="Serviço",CONCATENATE(TEXT(H54,"00"),".",TEXT(J54,"000"),".",TEXT(L54,"000"),".",TEXT(N54,"000")),""))))) | E54: =IF(B54="*","",IFERROR(IF(B54="SERVIÇO",D54,OFFSET(E54,-1,0)),"")) -> 01.002.001.003 | F54: =IF($B54="UNIDADE CONSTRUTIVA",OFFSET(F54,-1,0)+1,LARGE(F$10:F53,1)) -> 1 | G54: =IF(B54="*","",IF(B54="UNIDADE CONSTRUTIVA",S54,OFFSET(G54,-1,0))) -> GERENCIAMENTO TÉCNICO E ADMINISTRATIVO | H54: =IF(B54="UNIDADE CONSTRUTIVA",0,IF(B54="CÉLULA CONSTRUTIVA",OFFSET(H54,-1,0)+1,OFFSET(H54,-1,0))) -> 1 | I54: =IF(B54="*","",IF(B54="CÉLULA CONSTRUTIVA",S54,OFFSET(I54,-1,0))) -> GERENCIAMENTO TÉCNICO | J54: =IF(B54="CÉLULA CONSTRUTIVA",0,IF(B54="ETAPA",OFFSET(J54,-1,0)+1,OFFSET(J54,-1,0))) -> 2 | K54: =IF(B54="*","",IF(B54="ETAPA",S54,OFFSET(K54,-1,0))) -> TAXAS | DOCUMENTOS | L54: =IF(B54="ETAPA",0,IF(B54="SUBETAPA",OFFSET(L54,-1,0)+1,OFFSET(L54,-1,0))) -> 1 | M54: =IF(B54="*","",IF(B54="SUBETAPA",S54,OFFSET(M54,-1,0))) -> Licenciamento - Taxas - Impostos | N54: =IF(B54="Subetapa",0,IF(B54="serviço",OFFSET(N54,-1,0)+1,OFFSET(N54,-1,0))) -> 3 | O54: =IF(B54="*","",IF(B54="SERVIÇO",S54,OFFSET(O54,-1,0))) -> Taxas de ART e RRT | P54: =IF(S54="","",IF(Orçamento!$B54="INSUMO",S54,"")) -> Taxas de ART e RRT | Q54: =IF(B54="","",IF(B54="Serviço",S54,"")) | R54: =IF(B54="serviço",U54,OFFSET(R54,-1,0)) -> 1 | S54: Taxas de ART e RRT | T54: =_xlfn.XLOOKUP(S54,Insumos!$A$3:$A$371,Insumos!$B$3:$B$371) -> VB | U54: =IF($B54="insumo",R54,"") -> 1 | V54: 1 | W54: =IFERROR(IF(B54="INSUMO",_xlfn.XLOOKUP(S54,Insumos!A:A,Insumos!C:C),""),"Inserir Preço") -> 2250 | X54: =IF(B54="Complemento do insumo",V54,IF(R54="","",IF(B54="serviço",R54,IF(OR(B54="insumo"),V54*R54,"")))) -> 1 | Y54: =IF(B54="insumo",W54*V54,IF(B54="serviço",SUMIFS(Y:Y,B:B,"insumo",E:E,E54,I:I,I54),"")) -> 2250 | Z54: =IFERROR(IF(B54="Unidade Construtiva",SUMIFS(Z:Z,B:B,"Célula Construtiva",G:G,G54),IF(B54="célula construtiva",SUMIFS(Z:Z,B:B,"Insumo",I:I,I54,G:G,G54),IF(B54="ETAPA",SUMIFS(Z:Z,B:B,"Insumo",K:K,K54,I:I,I54,G:G,G54),IF(B54="subetapa",SUMIFS(Z:Z,M:M,M54,B:B,"insumo",K:K,K54,I:I,I54,G:G,G54),IF(B54="complemento do insumo",V54*W54,IF(B54="INSUMO",R54*V54*W54,X54*Y54)))))),"") -> 2250 | AB54: =IF(B54="insumo",_xlfn.XLOOKUP(S54,Insumos!A:A,Insumos!D:D),"") -> Recebido Cliente | AC54: =IFERROR(IF(B54="","",Z54/SUMIF(B:B,"INSUMO",Z:Z)),0) -> 0.00032278301 | AE54: =IFERROR(IF(OR(Z54="",Z54=0),"",IF(AF54="","",IF(AF54="R$/mês",Z54/OBRA!$D$12,IF(AF54="R$/m²",Z54/OBRA!$D$10,IF(AF54="R$/apto",Orçamento!Z54/OBRA!$D$11,""))))),"") -> 1.157866 | AF54: R$/m²
B55: Serviço | C55: =IF(B55="INSUMO",COUNTIFS(B:B,"INSUMO",S:S,S55),IF(B55="SERVIÇO",COUNTIFS(B:B,"SERVIÇO",S:S,S55),"")) -> 1 | D55: =IF(B55="Unidade Construtiva",TEXT(F55,"00"),IF(B55="Célula Construtiva",TEXT(H55,"00"),IF(B55="Etapa",CONCATENATE(TEXT(H55,"00"),".",TEXT(J55,"000")),IF(B55="Subetapa",CONCATENATE(TEXT(H55,"00"),".",TEXT(J55,"000"),".",TEXT(L55,"000")),IF(B55="Serviço",CONCATENATE(TEXT(H55,"00"),".",TEXT(J55,"000"),".",TEXT(L55,"000"),".",TEXT(N55,"000")),""))))) -> 01.002.001.004 | E55: =IF(B55="*","",IFERROR(IF(B55="SERVIÇO",D55,OFFSET(E55,-1,0)),"")) -> 01.002.001.004 | F55: =IF($B55="UNIDADE CONSTRUTIVA",OFFSET(F55,-1,0)+1,LARGE(F$10:F54,1)) -> 1 | G55: =IF(B55="*","",IF(B55="UNIDADE CONSTRUTIVA",S55,OFFSET(G55,-1,0))) -> GERENCIAMENTO TÉCNICO E ADMINISTRATIVO | H55: =IF(B55="UNIDADE CONSTRUTIVA",0,IF(B55="CÉLULA CONSTRUTIVA",OFFSET(H55,-1,0)+1,OFFSET(H55,-1,0))) -> 1 | I55: =IF(B55="*","",IF(B55="CÉLULA CONSTRUTIVA",S55,OFFSET(I55,-1,0))) -> GERENCIAMENTO TÉCNICO | J55: =IF(B55="CÉLULA CONSTRUTIVA",0,IF(B55="ETAPA",OFFSET(J55,-1,0)+1,OFFSET(J55,-1,0))) -> 2 | K55: =IF(B55="*","",IF(B55="ETAPA",S55,OFFSET(K55,-1,0))) -> TAXAS | DOCUMENTOS | L55: =IF(B55="ETAPA",0,IF(B55="SUBETAPA",OFFSET(L55,-1,0)+1,OFFSET(L55,-1,0))) -> 1 | M55: =IF(B55="*","",IF(B55="SUBETAPA",S55,OFFSET(M55,-1,0))) -> Licenciamento - Taxas - Impostos | N55: =IF(B55="Subetapa",0,IF(B55="serviço",OFFSET(N55,-1,0)+1,OFFSET(N55,-1,0))) -> 4 | O55: =IF(B55="*","",IF(B55="SERVIÇO",S55,OFFSET(O55,-1,0))) -> IPTU | P55: =IF(S55="","",IF(Orçamento!$B55="INSUMO",S55,"")) | Q55: =IF(B55="","",IF(B55="Serviço",S55,"")) -> IPTU | R55: =IF(B55="serviço",U55,OFFSET(R55,-1,0)) -> 1 | S55: IPTU | T55: VB | U55: 1 | W55: =IFERROR(IF(B55="INSUMO",_xlfn.XLOOKUP(S55,Insumos!A:A,Insumos!C:C),""),"Inserir Preço") | X55: =IF(B55="Complemento do insumo",V55,IF(R55="","",IF(B55="serviço",R55,IF(OR(B55="insumo"),V55*R55,"")))) -> 1 | Y55: =IF(B55="insumo",W55*V55,IF(B55="serviço",SUMIFS(Y:Y,B:B,"insumo",E:E,E55,I:I,I55),"")) -> 7000 | Z55: =IFERROR(IF(B55="Unidade Construtiva",SUMIFS(Z:Z,B:B,"Célula Construtiva",G:G,G55),IF(B55="célula construtiva",SUMIFS(Z:Z,B:B,"Insumo",I:I,I55,G:G,G55),IF(B55="ETAPA",SUMIFS(Z:Z,B:B,"Insumo",K:K,K55,I:I,I55,G:G,G55),IF(B55="subetapa",SUMIFS(Z:Z,M:M,M55,B:B,"insumo",K:K,K55,I:I,I55,G:G,G55),IF(B55="complemento do insumo",V55*W55,IF(B55="INSUMO",R55*V55*W55,X55*Y55)))))),"") -> 7000 | AB55: =IF(B55="insumo",_xlfn.XLOOKUP(S55,Insumos!A:A,Insumos!D:D),"") | AC55: =IFERROR(IF(B55="","",Z55/SUMIF(B:B,"INSUMO",Z:Z)),0) -> 0.0010042138 | AE55: =IFERROR(IF(OR(Z55="",Z55=0),"",IF(AF55="","",IF(AF55="R$/mês",Z55/OBRA!$D$12,IF(AF55="R$/m²",Z55/OBRA!$D$10,IF(AF55="R$/apto",Orçamento!Z55/OBRA!$D$11,""))))),"") -> 3.6022499 | AF55: R$/m²
B56: Insumo | C56: =IF(B56="INSUMO",COUNTIFS(B:B,"INSUMO",S:S,S56),IF(B56="SERVIÇO",COUNTIFS(B:B,"SERVIÇO",S:S,S56),"")) -> 1 | D56: =IF(B56="Unidade Construtiva",TEXT(F56,"00"),IF(B56="Célula Construtiva",TEXT(H56,"00"),IF(B56="Etapa",CONCATENATE(TEXT(H56,"00"),".",TEXT(J56,"000")),IF(B56="Subetapa",CONCATENATE(TEXT(H56,"00"),".",TEXT(J56,"000"),".",TEXT(L56,"000")),IF(B56="Serviço",CONCATENATE(TEXT(H56,"00"),".",TEXT(J56,"000"),".",TEXT(L56,"000"),".",TEXT(N56,"000")),""))))) | E56: =IF(B56="*","",IFERROR(IF(B56="SERVIÇO",D56,OFFSET(E56,-1,0)),"")) -> 01.002.001.004 | F56: =IF($B56="UNIDADE CONSTRUTIVA",OFFSET(F56,-1,0)+1,LARGE(F$10:F55,1)) -> 1 | G56: =IF(B56="*","",IF(B56="UNIDADE CONSTRUTIVA",S56,OFFSET(G56,-1,0))) -> GERENCIAMENTO TÉCNICO E ADMINISTRATIVO | H56: =IF(B56="UNIDADE CONSTRUTIVA",0,IF(B56="CÉLULA CONSTRUTIVA",OFFSET(H56,-1,0)+1,OFFSET(H56,-1,0))) -> 1 | I56: =IF(B56="*","",IF(B56="CÉLULA CONSTRUTIVA",S56,OFFSET(I56,-1,0))) -> GERENCIAMENTO TÉCNICO | J56: =IF(B56="CÉLULA CONSTRUTIVA",0,IF(B56="ETAPA",OFFSET(J56,-1,0)+1,OFFSET(J56,-1,0))) -> 2 | K56: =IF(B56="*","",IF(B56="ETAPA",S56,OFFSET(K56,-1,0))) -> TAXAS | DOCUMENTOS | L56: =IF(B56="ETAPA",0,IF(B56="SUBETAPA",OFFSET(L56,-1,0)+1,OFFSET(L56,-1,0))) -> 1 | M56: =IF(B56="*","",IF(B56="SUBETAPA",S56,OFFSET(M56,-1,0))) -> Licenciamento - Taxas - Impostos | N56: =IF(B56="Subetapa",0,IF(B56="serviço",OFFSET(N56,-1,0)+1,OFFSET(N56,-1,0))) -> 4 | O56: =IF(B56="*","",IF(B56="SERVIÇO",S56,OFFSET(O56,-1,0))) -> IPTU | P56: =IF(S56="","",IF(Orçamento!$B56="INSUMO",S56,"")) -> IPTU - IMPOSTO PREDIAL E TERRITORIAL URBANO | Q56: =IF(B56="","",IF(B56="Serviço",S56,"")) | R56: =IF(B56="serviço",U56,OFFSET(R56,-1,0)) -> 1 | S56: IPTU - IMPOSTO PREDIAL E TERRITORIAL URBANO | T56: =_xlfn.XLOOKUP(S56,Insumos!$A$3:$A$371,Insumos!$B$3:$B$371) -> VB | U56: =IF($B56="insumo",R56,"") -> 1 | V56: 1 | W56: =IFERROR(IF(B56="INSUMO",_xlfn.XLOOKUP(S56,Insumos!A:A,Insumos!C:C),""),"Inserir Preço") -> 7000 | X56: =IF(B56="Complemento do insumo",V56,IF(R56="","",IF(B56="serviço",R56,IF(OR(B56="insumo"),V56*R56,"")))) -> 1 | Y56: =IF(B56="insumo",W56*V56,IF(B56="serviço",SUMIFS(Y:Y,B:B,"insumo",E:E,E56,I:I,I56),"")) -> 7000 | Z56: =IFERROR(IF(B56="Unidade Construtiva",SUMIFS(Z:Z,B:B,"Célula Construtiva",G:G,G56),IF(B56="célula construtiva",SUMIFS(Z:Z,B:B,"Insumo",I:I,I56,G:G,G56),IF(B56="ETAPA",SUMIFS(Z:Z,B:B,"Insumo",K:K,K56,I:I,I56,G:G,G56),IF(B56="subetapa",SUMIFS(Z:Z,M:M,M56,B:B,"insumo",K:K,K56,I:I,I56,G:G,G56),IF(B56="complemento do insumo",V56*W56,IF(B56="INSUMO",R56*V56*W56,X56*Y56)))))),"") -> 7000 | AB56: =IF(B56="insumo",_xlfn.XLOOKUP(S56,Insumos!A:A,Insumos!D:D),"") -> Recebido Cliente | AC56: =IFERROR(IF(B56="","",Z56/SUMIF(B:B,"INSUMO",Z:Z)),0) -> 0.0010042138 | AE56: =IFERROR(IF(OR(Z56="",Z56=0),"",IF(AF56="","",IF(AF56="R$/mês",Z56/OBRA!$D$12,IF(AF56="R$/m²",Z56/OBRA!$D$10,IF(AF56="R$/apto",Orçamento!Z56/OBRA!$D$11,""))))),"") -> 3.6022499 | AF56: R$/m²
B57: Serviço | C57: =IF(B57="INSUMO",COUNTIFS(B:B,"INSUMO",S:S,S57),IF(B57="SERVIÇO",COUNTIFS(B:B,"SERVIÇO",S:S,S57),"")) -> 1 | D57: =IF(B57="Unidade Construtiva",TEXT(F57,"00"),IF(B57="Célula Construtiva",TEXT(H57,"00"),IF(B57="Etapa",CONCATENATE(TEXT(H57,"00"),".",TEXT(J57,"000")),IF(B57="Subetapa",CONCATENATE(TEXT(H57,"00"),".",TEXT(J57,"000"),".",TEXT(L57,"000")),IF(B57="Serviço",CONCATENATE(TEXT(H57,"00"),".",TEXT(J57,"000"),".",TEXT(L57,"000"),".",TEXT(N57,"000")),""))))) -> 01.002.001.005 | E57: =IF(B57="*","",IFERROR(IF(B57="SERVIÇO",D57,OFFSET(E57,-1,0)),"")) -> 01.002.001.005 | F57: =IF($B57="UNIDADE CONSTRUTIVA",OFFSET(F57,-1,0)+1,LARGE(F$10:F56,1)) -> 1 | G57: =IF(B57="*","",IF(B57="UNIDADE CONSTRUTIVA",S57,OFFSET(G57,-1,0))) -> GERENCIAMENTO TÉCNICO E ADMINISTRATIVO | H57: =IF(B57="UNIDADE CONSTRUTIVA",0,IF(B57="CÉLULA CONSTRUTIVA",OFFSET(H57,-1,0)+1,OFFSET(H57,-1,0))) -> 1 | I57: =IF(B57="*","",IF(B57="CÉLULA CONSTRUTIVA",S57,OFFSET(I57,-1,0))) -> GERENCIAMENTO TÉCNICO | J57: =IF(B57="CÉLULA CONSTRUTIVA",0,IF(B57="ETAPA",OFFSET(J57,-1,0)+1,OFFSET(J57,-1,0))) -> 2 | K57: =IF(B57="*","",IF(B57="ETAPA",S57,OFFSET(K57,-1,0))) -> TAXAS | DOCUMENTOS | L57: =IF(B57="ETAPA",0,IF(B57="SUBETAPA",OFFSET(L57,-1,0)+1,OFFSET(L57,-1,0))) -> 1 | M57: =IF(B57="*","",IF(B57="SUBETAPA",S57,OFFSET(M57,-1,0))) -> Licenciamento - Taxas - Impostos | N57: =IF(B57="Subetapa",0,IF(B57="serviço",OFFSET(N57,-1,0)+1,OFFSET(N57,-1,0))) -> 5 | O57: =IF(B57="*","",IF(B57="SERVIÇO",S57,OFFSET(O57,-1,0))) -> Taxas de Aprovação de Projetos e Alvarás (Prefeituras/Bombeiro) | P57: =IF(S57="","",IF(Orçamento!$B57="INSUMO",S57,"")) | Q57: =IF(B57="","",IF(B57="Serviço",S57,"")) -> Taxas de Aprovação de Projetos e Alvarás (Prefeituras/Bombeiro) | R57: =IF(B57="serviço",U57,OFFSET(R57,-1,0)) -> 1 | S57: Taxas de Aprovação de Projetos e Alvarás (Prefeituras/Bombeiro) | T57: VB | U57: 1 | W57: =IFERROR(IF(B57="INSUMO",_xlfn.XLOOKUP(S57,Insumos!A:A,Insumos!C:C),""),"Inserir Preço") | X57: =IF(B57="Complemento do insumo",V57,IF(R57="","",IF(B57="serviço",R57,IF(OR(B57="insumo"),V57*R57,"")))) -> 1 | Y57: =IF(B57="insumo",W57*V57,IF(B57="serviço",SUMIFS(Y:Y,B:B,"insumo",E:E,E57,I:I,I57),"")) -> 5923.64 | Z57: =IFERROR(IF(B57="Unidade Construtiva",SUMIFS(Z:Z,B:B,"Célula Construtiva",G:G,G57),IF(B57="célula construtiva",SUMIFS(Z:Z,B:B,"Insumo",I:I,I57,G:G,G57),IF(B57="ETAPA",SUMIFS(Z:Z,B:B,"Insumo",K:K,K57,I:I,I57,G:G,G57),IF(B57="subetapa",SUMIFS(Z:Z,M:M,M57,B:B,"insumo",K:K,K57,I:I,I57,G:G,G57),IF(B57="complemento do insumo",V57*W57,IF(B57="INSUMO",R57*V57*W57,X57*Y57)))))),"") -> 5923.64 | AB57: =IF(B57="insumo",_xlfn.XLOOKUP(S57,Insumos!A:A,Insumos!D:D),"") | AC57: =IFERROR(IF(B57="","",Z57/SUMIF(B:B,"INSUMO",Z:Z)),0) -> 0.00084980017 | AE57: =IFERROR(IF(OR(Z57="",Z57=0),"",IF(AF57="","",IF(AF57="R$/mês",Z57/OBRA!$D$12,IF(AF57="R$/m²",Z57/OBRA!$D$10,IF(AF57="R$/apto",Orçamento!Z57/OBRA!$D$11,""))))),"") -> 3.0483473 | AF57: R$/m²
B58: Insumo | C58: =IF(B58="INSUMO",COUNTIFS(B:B,"INSUMO",S:S,S58),IF(B58="SERVIÇO",COUNTIFS(B:B,"SERVIÇO",S:S,S58),"")) -> 1 | D58: =IF(B58="Unidade Construtiva",TEXT(F58,"00"),IF(B58="Célula Construtiva",TEXT(H58,"00"),IF(B58="Etapa",CONCATENATE(TEXT(H58,"00"),".",TEXT(J58,"000")),IF(B58="Subetapa",CONCATENATE(TEXT(H58,"00"),".",TEXT(J58,"000"),".",TEXT(L58,"000")),IF(B58="Serviço",CONCATENATE(TEXT(H58,"00"),".",TEXT(J58,"000"),".",TEXT(L58,"000"),".",TEXT(N58,"000")),""))))) | E58: =IF(B58="*","",IFERROR(IF(B58="SERVIÇO",D58,OFFSET(E58,-1,0)),"")) -> 01.002.001.005 | F58: =IF($B58="UNIDADE CONSTRUTIVA",OFFSET(F58,-1,0)+1,LARGE(F$10:F57,1)) -> 1 | G58: =IF(B58="*","",IF(B58="UNIDADE CONSTRUTIVA",S58,OFFSET(G58,-1,0))) -> GERENCIAMENTO TÉCNICO E ADMINISTRATIVO | H58: =IF(B58="UNIDADE CONSTRUTIVA",0,IF(B58="CÉLULA CONSTRUTIVA",OFFSET(H58,-1,0)+1,OFFSET(H58,-1,0))) -> 1 | I58: =IF(B58="*","",IF(B58="CÉLULA CONSTRUTIVA",S58,OFFSET(I58,-1,0))) -> GERENCIAMENTO TÉCNICO | J58: =IF(B58="CÉLULA CONSTRUTIVA",0,IF(B58="ETAPA",OFFSET(J58,-1,0)+1,OFFSET(J58,-1,0))) -> 2 | K58: =IF(B58="*","",IF(B58="ETAPA",S58,OFFSET(K58,-1,0))) -> TAXAS | DOCUMENTOS | L58: =IF(B58="ETAPA",0,IF(B58="SUBETAPA",OFFSET(L58,-1,0)+1,OFFSET(L58,-1,0))) -> 1 | M58: =IF(B58="*","",IF(B58="SUBETAPA",S58,OFFSET(M58,-1,0))) -> Licenciamento - Taxas - Impostos | N58: =IF(B58="Subetapa",0,IF(B58="serviço",OFFSET(N58,-1,0)+1,OFFSET(N58,-1,0))) -> 5 | O58: =IF(B58="*","",IF(B58="SERVIÇO",S58,OFFSET(O58,-1,0))) -> Taxas de Aprovação de Projetos e Alvarás (Prefeituras/Bombeiro) | P58: =IF(S58="","",IF(Orçamento!$B58="INSUMO",S58,"")) -> Taxas de Aprovação de Projetos e Alvarás (Prefeituras/Bombeiro) | Q58: =IF(B58="","",IF(B58="Serviço",S58,"")) | R58: =IF(B58="serviço",U58,OFFSET(R58,-1,0)) -> 1 | S58: Taxas de Aprovação de Projetos e Alvarás (Prefeituras/Bombeiro) | T58: =_xlfn.XLOOKUP(S58,Insumos!$A$3:$A$371,Insumos!$B$3:$B$371) -> VB | U58: =IF($B58="insumo",R58,"") -> 1 | V58: 1 | W58: =IFERROR(IF(B58="INSUMO",_xlfn.XLOOKUP(S58,Insumos!A:A,Insumos!C:C),""),"Inserir Preço") -> 5923.64 | X58: =IF(B58="Complemento do insumo",V58,IF(R58="","",IF(B58="serviço",R58,IF(OR(B58="insumo"),V58*R58,"")))) -> 1 | Y58: =IF(B58="insumo",W58*V58,IF(B58="serviço",SUMIFS(Y:Y,B:B,"insumo",E:E,E58,I:I,I58),"")) -> 5923.64 | Z58: =IFERROR(IF(B58="Unidade Construtiva",SUMIFS(Z:Z,B:B,"Célula Construtiva",G:G,G58),IF(B58="célula construtiva",SUMIFS(Z:Z,B:B,"Insumo",I:I,I58,G:G,G58),IF(B58="ETAPA",SUMIFS(Z:Z,B:B,"Insumo",K:K,K58,I:I,I58,G:G,G58),IF(B58="subetapa",SUMIFS(Z:Z,M:M,M58,B:B,"insumo",K:K,K58,I:I,I58,G:G,G58),IF(B58="complemento do insumo",V58*W58,IF(B58="INSUMO",R58*V58*W58,X58*Y58)))))),"") -> 5923.64 | AB58: =IF(B58="insumo",_xlfn.XLOOKUP(S58,Insumos!A:A,Insumos!D:D),"") -> Recebido Cliente + Média base de dados para Bembeiros | AC58: =IFERROR(IF(B58="","",Z58/SUMIF(B:B,"INSUMO",Z:Z)),0) -> 0.00084980017 | AE58: =IFERROR(IF(OR(Z58="",Z58=0),"",IF(AF58="","",IF(AF58="R$/mês",Z58/OBRA!$D$12,IF(AF58="R$/m²",Z58/OBRA!$D$10,IF(AF58="R$/apto",Orçamento!Z58/OBRA!$D$11,""))))),"") -> 3.0483473 | AF58: R$/m²
B59: Serviço | C59: =IF(B59="INSUMO",COUNTIFS(B:B,"INSUMO",S:S,S59),IF(B59="SERVIÇO",COUNTIFS(B:B,"SERVIÇO",S:S,S59),"")) -> 1 | D59: =IF(B59="Unidade Construtiva",TEXT(F59,"00"),IF(B59="Célula Construtiva",TEXT(H59,"00"),IF(B59="Etapa",CONCATENATE(TEXT(H59,"00"),".",TEXT(J59,"000")),IF(B59="Subetapa",CONCATENATE(TEXT(H59,"00"),".",TEXT(J59,"000"),".",TEXT(L59,"000")),IF(B59="Serviço",CONCATENATE(TEXT(H59,"00"),".",TEXT(J59,"000"),".",TEXT(L59,"000"),".",TEXT(N59,"000")),""))))) -> 01.002.001.006 | E59: =IF(B59="*","",IFERROR(IF(B59="SERVIÇO",D59,OFFSET(E59,-1,0)),"")) -> 01.002.001.006 | F59: =IF($B59="UNIDADE CONSTRUTIVA",OFFSET(F59,-1,0)+1,LARGE(F$10:F58,1)) -> 1 | G59: =IF(B59="*","",IF(B59="UNIDADE CONSTRUTIVA",S59,OFFSET(G59,-1,0))) -> GERENCIAMENTO TÉCNICO E ADMINISTRATIVO | H59: =IF(B59="UNIDADE CONSTRUTIVA",0,IF(B59="CÉLULA CONSTRUTIVA",OFFSET(H59,-1,0)+1,OFFSET(H59,-1,0))) -> 1 | I59: =IF(B59="*","",IF(B59="CÉLULA CONSTRUTIVA",S59,OFFSET(I59,-1,0))) -> GERENCIAMENTO TÉCNICO | J59: =IF(B59="CÉLULA CONSTRUTIVA",0,IF(B59="ETAPA",OFFSET(J59,-1,0)+1,OFFSET(J59,-1,0))) -> 2 | K59: =IF(B59="*","",IF(B59="ETAPA",S59,OFFSET(K59,-1,0))) -> TAXAS | DOCUMENTOS | L59: =IF(B59="ETAPA",0,IF(B59="SUBETAPA",OFFSET(L59,-1,0)+1,OFFSET(L59,-1,0))) -> 1 | M59: =IF(B59="*","",IF(B59="SUBETAPA",S59,OFFSET(M59,-1,0))) -> Licenciamento - Taxas - Impostos | N59: =IF(B59="Subetapa",0,IF(B59="serviço",OFFSET(N59,-1,0)+1,OFFSET(N59,-1,0))) -> 6 | O59: =IF(B59="*","",IF(B59="SERVIÇO",S59,OFFSET(O59,-1,0))) -> Taxa de Aprovação Ambiental | P59: =IF(S59="","",IF(Orçamento!$B59="INSUMO",S59,"")) | Q59: =IF(B59="","",IF(B59="Serviço",S59,"")) -> Taxa de Aprovação Ambiental | R59: =IF(B59="serviço",U59,OFFSET(R59,-1,0)) -> 1 | S59: Taxa de Aprovação Ambiental | T59: VB | U59: 1 | W59: =IFERROR(IF(B59="INSUMO",_xlfn.XLOOKUP(S59,Insumos!A:A,Insumos!C:C),""),"Inserir Preço") | X59: =IF(B59="Complemento do insumo",V59,IF(R59="","",IF(B59="serviço",R59,IF(OR(B59="insumo"),V59*R59,"")))) -> 1 | Y59: =IF(B59="insumo",W59*V59,IF(B59="serviço",SUMIFS(Y:Y,B:B,"insumo",E:E,E59,I:I,I59),"")) -> 905.81 | Z59: =IFERROR(IF(B59="Unidade Construtiva",SUMIFS(Z:Z,B:B,"Célula Construtiva",G:G,G59),IF(B59="célula construtiva",SUMIFS(Z:Z,B:B,"Insumo",I:I,I59,G:G,G59),IF(B59="ETAPA",SUMIFS(Z:Z,B:B,"Insumo",K:K,K59,I:I,I59,G:G,G59),IF(B59="subetapa",SUMIFS(Z:Z,M:M,M59,B:B,"insumo",K:K,K59,I:I,I59,G:G,G59),IF(B59="complemento do insumo",V59*W59,IF(B59="INSUMO",R59*V59*W59,X59*Y59)))))),"") -> 905.81 | AB59: =IF(B59="insumo",_xlfn.XLOOKUP(S59,Insumos!A:A,Insumos!D:D),"") | AC59: =IFERROR(IF(B59="","",Z59/SUMIF(B:B,"INSUMO",Z:Z)),0) -> 0.0001299467 | AE59: =IFERROR(IF(OR(Z59="",Z59=0),"",IF(AF59="","",IF(AF59="R$/mês",Z59/OBRA!$D$12,IF(AF59="R$/m²",Z59/OBRA!$D$10,IF(AF59="R$/apto",Orçamento!Z59/OBRA!$D$11,""))))),"") -> 0.46613628 | AF59: R$/m²
B60: Insumo | C60: =IF(B60="INSUMO",COUNTIFS(B:B,"INSUMO",S:S,S60),IF(B60="SERVIÇO",COUNTIFS(B:B,"SERVIÇO",S:S,S60),"")) -> 1 | D60: =IF(B60="Unidade Construtiva",TEXT(F60,"00"),IF(B60="Célula Construtiva",TEXT(H60,"00"),IF(B60="Etapa",CONCATENATE(TEXT(H60,"00"),".",TEXT(J60,"000")),IF(B60="Subetapa",CONCATENATE(TEXT(H60,"00"),".",TEXT(J60,"000"),".",TEXT(L60,"000")),IF(B60="Serviço",CONCATENATE(TEXT(H60,"00"),".",TEXT(J60,"000"),".",TEXT(L60,"000"),".",TEXT(N60,"000")),""))))) | E60: =IF(B60="*","",IFERROR(IF(B60="SERVIÇO",D60,OFFSET(E60,-1,0)),"")) -> 01.002.001.006 | F60: =IF($B60="UNIDADE CONSTRUTIVA",OFFSET(F60,-1,0)+1,LARGE(F$10:F59,1)) -> 1 | G60: =IF(B60="*","",IF(B60="UNIDADE CONSTRUTIVA",S60,OFFSET(G60,-1,0))) -> GERENCIAMENTO TÉCNICO E ADMINISTRATIVO | H60: =IF(B60="UNIDADE CONSTRUTIVA",0,IF(B60="CÉLULA CONSTRUTIVA",OFFSET(H60,-1,0)+1,OFFSET(H60,-1,0))) -> 1 | I60: =IF(B60="*","",IF(B60="CÉLULA CONSTRUTIVA",S60,OFFSET(I60,-1,0))) -> GERENCIAMENTO TÉCNICO | J60: =IF(B60="CÉLULA CONSTRUTIVA",0,IF(B60="ETAPA",OFFSET(J60,-1,0)+1,OFFSET(J60,-1,0))) -> 2 | K60: =IF(B60="*","",IF(B60="ETAPA",S60,OFFSET(K60,-1,0))) -> TAXAS | DOCUMENTOS | L60: =IF(B60="ETAPA",0,IF(B60="SUBETAPA",OFFSET(L60,-1,0)+1,OFFSET(L60,-1,0))) -> 1 | M60: =IF(B60="*","",IF(B60="SUBETAPA",S60,OFFSET(M60,-1,0))) -> Licenciamento - Taxas - Impostos | N60: =IF(B60="Subetapa",0,IF(B60="serviço",OFFSET(N60,-1,0)+1,OFFSET(N60,-1,0))) -> 6 | O60: =IF(B60="*","",IF(B60="SERVIÇO",S60,OFFSET(O60,-1,0))) -> Taxa de Aprovação Ambiental | P60: =IF(S60="","",IF(Orçamento!$B60="INSUMO",S60,"")) -> Taxa Aprovação Ambiental (Lap/Lai/Auc)/Compensatória) | Q60: =IF(B60="","",IF(B60="Serviço",S60,"")) | R60: =IF(B60="serviço",U60,OFFSET(R60,-1,0)) -> 1 | S60: Taxa Aprovação Ambiental (Lap/Lai/Auc)/Compensatória) | T60: =_xlfn.XLOOKUP(S60,Insumos!$A$3:$A$371,Insumos!$B$3:$B$371) -> VB | U60: =IF($B60="insumo",R60,"") -> 1 | V60: 1 | W60: =IFERROR(IF(B60="INSUMO",_xlfn.XLOOKUP(S60,Insumos!A:A,Insumos!C:C),""),"Inserir Preço") -> 905.81 | X60: =IF(B60="Complemento do insumo",V60,IF(R60="","",IF(B60="serviço",R60,IF(OR(B60="insumo"),V60*R60,"")))) -> 1 | Y60: =IF(B60="insumo",W60*V60,IF(B60="serviço",SUMIFS(Y:Y,B:B,"insumo",E:E,E60,I:I,I60),"")) -> 905.81 | Z60: =IFERROR(IF(B60="Unidade Construtiva",SUMIFS(Z:Z,B:B,"Célula Construtiva",G:G,G60),IF(B60="célula construtiva",SUMIFS(Z:Z,B:B,"Insumo",I:I,I60,G:G,G60),IF(B60="ETAPA",SUMIFS(Z:Z,B:B,"Insumo",K:K,K60,I:I,I60,G:G,G60),IF(B60="subetapa",SUMIFS(Z:Z,M:M,M60,B:B,"insumo",K:K,K60,I:I,I60,G:G,G60),IF(B60="complemento do insumo",V60*W60,IF(B60="INSUMO",R60*V60*W60,X60*Y60)))))),"") -> 905.81 | AB60: =IF(B60="insumo",_xlfn.XLOOKUP(S60,Insumos!A:A,Insumos!D:D),"") -> Recebido Cliente | AC60: =IFERROR(IF(B60="","",Z60/SUMIF(B:B,"INSUMO",Z:Z)),0) -> 0.0001299467 | AE60: =IFERROR(IF(OR(Z60="",Z60=0),"",IF(AF60="","",IF(AF60="R$/mês",Z60/OBRA!$D$12,IF(AF60="R$/m²",Z60/OBRA!$D$10,IF(AF60="R$/apto",Orçamento!Z60/OBRA!$D$11,""))))),"") -> 0.46613628 | AF60: R$/m²
B61: Serviço | C61: =IF(B61="INSUMO",COUNTIFS(B:B,"INSUMO",S:S,S61),IF(B61="SERVIÇO",COUNTIFS(B:B,"SERVIÇO",S:S,S61),"")) -> 1 | D61: =IF(B61="Unidade Construtiva",TEXT(F61,"00"),IF(B61="Célula Construtiva",TEXT(H61,"00"),IF(B61="Etapa",CONCATENATE(TEXT(H61,"00"),".",TEXT(J61,"000")),IF(B61="Subetapa",CONCATENATE(TEXT(H61,"00"),".",TEXT(J61,"000"),".",TEXT(L61,"000")),IF(B61="Serviço",CONCATENATE(TEXT(H61,"00"),".",TEXT(J61,"000"),".",TEXT(L61,"000"),".",TEXT(N61,"000")),""))))) -> 01.002.001.007 | E61: =IF(B61="*","",IFERROR(IF(B61="SERVIÇO",D61,OFFSET(E61,-1,0)),"")) -> 01.002.001.007 | F61: =IF($B61="UNIDADE CONSTRUTIVA",OFFSET(F61,-1,0)+1,LARGE(F$10:F60,1)) -> 1 | G61: =IF(B61="*","",IF(B61="UNIDADE CONSTRUTIVA",S61,OFFSET(G61,-1,0))) -> GERENCIAMENTO TÉCNICO E ADMINISTRATIVO | H61: =IF(B61="UNIDADE CONSTRUTIVA",0,IF(B61="CÉLULA CONSTRUTIVA",OFFSET(H61,-1,0)+1,OFFSET(H61,-1,0))) -> 1 | I61: =IF(B61="*","",IF(B61="CÉLULA CONSTRUTIVA",S61,OFFSET(I61,-1,0))) -> GERENCIAMENTO TÉCNICO | J61: =IF(B61="CÉLULA CONSTRUTIVA",0,IF(B61="ETAPA",OFFSET(J61,-1,0)+1,OFFSET(J61,-1,0))) -> 2 | K61: =IF(B61="*","",IF(B61="ETAPA",S61,OFFSET(K61,-1,0))) -> TAXAS | DOCUMENTOS | L61: =IF(B61="ETAPA",0,IF(B61="SUBETAPA",OFFSET(L61,-1,0)+1,OFFSET(L61,-1,0))) -> 1 | M61: =IF(B61="*","",IF(B61="SUBETAPA",S61,OFFSET(M61,-1,0))) -> Licenciamento - Taxas - Impostos | N61: =IF(B61="Subetapa",0,IF(B61="serviço",OFFSET(N61,-1,0)+1,OFFSET(N61,-1,0))) -> 7 | O61: =IF(B61="*","",IF(B61="SERVIÇO",S61,OFFSET(O61,-1,0))) -> Taxas de Aprovação de Projetos (Hidrossanitário) | P61: =IF(S61="","",IF(Orçamento!$B61="INSUMO",S61,"")) | Q61: =IF(B61="","",IF(B61="Serviço",S61,"")) -> Taxas de Aprovação de Projetos (Hidrossanitário) | R61: =IF(B61="serviço",U61,OFFSET(R61,-1,0)) -> 1 | S61: Taxas de Aprovação de Projetos (Hidrossanitário) | T61: VB | U61: 1 | W61: =IFERROR(IF(B61="INSUMO",_xlfn.XLOOKUP(S61,Insumos!A:A,Insumos!C:C),""),"Inserir Preço") | X61: =IF(B61="Complemento do insumo",V61,IF(R61="","",IF(B61="serviço",R61,IF(OR(B61="insumo"),V61*R61,"")))) -> 1 | Y61: =IF(B61="insumo",W61*V61,IF(B61="serviço",SUMIFS(Y:Y,B:B,"insumo",E:E,E61,I:I,I61),"")) -> 293.89 | Z61: =IFERROR(IF(B61="Unidade Construtiva",SUMIFS(Z:Z,B:B,"Célula Construtiva",G:G,G61),IF(B61="célula construtiva",SUMIFS(Z:Z,B:B,"Insumo",I:I,I61,G:G,G61),IF(B61="ETAPA",SUMIFS(Z:Z,B:B,"Insumo",K:K,K61,I:I,I61,G:G,G61),IF(B61="subetapa",SUMIFS(Z:Z,M:M,M61,B:B,"insumo",K:K,K61,I:I,I61,G:G,G61),IF(B61="complemento do insumo",V61*W61,IF(B61="INSUMO",R61*V61*W61,X61*Y61)))))),"") -> 293.89 | AB61: =IF(B61="insumo",_xlfn.XLOOKUP(S61,Insumos!A:A,Insumos!D:D),"") | AC61: =IFERROR(IF(B61="","",Z61/SUMIF(B:B,"INSUMO",Z:Z)),0) -> 4.21612e-05 | AE61: =IFERROR(IF(OR(Z61="",Z61=0),"",IF(AF61="","",IF(AF61="R$/mês",Z61/OBRA!$D$12,IF(AF61="R$/m²",Z61/OBRA!$D$10,IF(AF61="R$/apto",Orçamento!Z61/OBRA!$D$11,""))))),"") -> 0.15123789 | AF61: R$/m²
B62: Insumo | C62: =IF(B62="INSUMO",COUNTIFS(B:B,"INSUMO",S:S,S62),IF(B62="SERVIÇO",COUNTIFS(B:B,"SERVIÇO",S:S,S62),"")) -> 1 | D62: =IF(B62="Unidade Construtiva",TEXT(F62,"00"),IF(B62="Célula Construtiva",TEXT(H62,"00"),IF(B62="Etapa",CONCATENATE(TEXT(H62,"00"),".",TEXT(J62,"000")),IF(B62="Subetapa",CONCATENATE(TEXT(H62,"00"),".",TEXT(J62,"000"),".",TEXT(L62,"000")),IF(B62="Serviço",CONCATENATE(TEXT(H62,"00"),".",TEXT(J62,"000"),".",TEXT(L62,"000"),".",TEXT(N62,"000")),""))))) | E62: =IF(B62="*","",IFERROR(IF(B62="SERVIÇO",D62,OFFSET(E62,-1,0)),"")) -> 01.002.001.007 | F62: =IF($B62="UNIDADE CONSTRUTIVA",OFFSET(F62,-1,0)+1,LARGE(F$10:F61,1)) -> 1 | G62: =IF(B62="*","",IF(B62="UNIDADE CONSTRUTIVA",S62,OFFSET(G62,-1,0))) -> GERENCIAMENTO TÉCNICO E ADMINISTRATIVO | H62: =IF(B62="UNIDADE CONSTRUTIVA",0,IF(B62="CÉLULA CONSTRUTIVA",OFFSET(H62,-1,0)+1,OFFSET(H62,-1,0))) -> 1 | I62: =IF(B62="*","",IF(B62="CÉLULA CONSTRUTIVA",S62,OFFSET(I62,-1,0))) -> GERENCIAMENTO TÉCNICO | J62: =IF(B62="CÉLULA CONSTRUTIVA",0,IF(B62="ETAPA",OFFSET(J62,-1,0)+1,OFFSET(J62,-1,0))) -> 2 | K62: =IF(B62="*","",IF(B62="ETAPA",S62,OFFSET(K62,-1,0))) -> TAXAS | DOCUMENTOS | L62: =IF(B62="ETAPA",0,IF(B62="SUBETAPA",OFFSET(L62,-1,0)+1,OFFSET(L62,-1,0))) -> 1 | M62: =IF(B62="*","",IF(B62="SUBETAPA",S62,OFFSET(M62,-1,0))) -> Licenciamento - Taxas - Impostos | N62: =IF(B62="Subetapa",0,IF(B62="serviço",OFFSET(N62,-1,0)+1,OFFSET(N62,-1,0))) -> 7 | O62: =IF(B62="*","",IF(B62="SERVIÇO",S62,OFFSET(O62,-1,0))) -> Taxas de Aprovação de Projetos (Hidrossanitário) | P62: =IF(S62="","",IF(Orçamento!$B62="INSUMO",S62,"")) -> Taxa Aprovação e legalização água e esgoto | Q62: =IF(B62="","",IF(B62="Serviço",S62,"")) | R62: =IF(B62="serviço",U62,OFFSET(R62,-1,0)) -> 1 | S62: Taxa Aprovação e legalização água e esgoto | T62: =_xlfn.XLOOKUP(S62,Insumos!$A$3:$A$371,Insumos!$B$3:$B$371) -> VB | U62: =IF($B62="insumo",R62,"") -> 1 | V62: 1 | W62: =IFERROR(IF(B62="INSUMO",_xlfn.XLOOKUP(S62,Insumos!A:A,Insumos!C:C),""),"Inserir Preço") -> 293.89 | X62: =IF(B62="Complemento do insumo",V62,IF(R62="","",IF(B62="serviço",R62,IF(OR(B62="insumo"),V62*R62,"")))) -> 1 | Y62: =IF(B62="insumo",W62*V62,IF(B62="serviço",SUMIFS(Y:Y,B:B,"insumo",E:E,E62,I:I,I62),"")) -> 293.89 | Z62: =IFERROR(IF(B62="Unidade Construtiva",SUMIFS(Z:Z,B:B,"Célula Construtiva",G:G,G62),IF(B62="célula construtiva",SUMIFS(Z:Z,B:B,"Insumo",I:I,I62,G:G,G62),IF(B62="ETAPA",SUMIFS(Z:Z,B:B,"Insumo",K:K,K62,I:I,I62,G:G,G62),IF(B62="subetapa",SUMIFS(Z:Z,M:M,M62,B:B,"insumo",K:K,K62,I:I,I62,G:G,G62),IF(B62="complemento do insumo",V62*W62,IF(B62="INSUMO",R62*V62*W62,X62*Y62)))))),"") -> 293.89 | AB62: =IF(B62="insumo",_xlfn.XLOOKUP(S62,Insumos!A:A,Insumos!D:D),"") -> Recebido Cliente | AC62: =IFERROR(IF(B62="","",Z62/SUMIF(B:B,"INSUMO",Z:Z)),0) -> 4.21612e-05 | AE62: =IFERROR(IF(OR(Z62="",Z62=0),"",IF(AF62="","",IF(AF62="R$/mês",Z62/OBRA!$D$12,IF(AF62="R$/m²",Z62/OBRA!$D$10,IF(AF62="R$/apto",Orçamento!Z62/OBRA!$D$11,""))))),"") -> 0.15123789 | AF62: R$/m²
B63: Serviço | C63: =IF(B63="INSUMO",COUNTIFS(B:B,"INSUMO",S:S,S63),IF(B63="SERVIÇO",COUNTIFS(B:B,"SERVIÇO",S:S,S63),"")) -> 1 | D63: =IF(B63="Unidade Construtiva",TEXT(F63,"00"),IF(B63="Célula Construtiva",TEXT(H63,"00"),IF(B63="Etapa",CONCATENATE(TEXT(H63,"00"),".",TEXT(J63,"000")),IF(B63="Subetapa",CONCATENATE(TEXT(H63,"00"),".",TEXT(J63,"000"),".",TEXT(L63,"000")),IF(B63="Serviço",CONCATENATE(TEXT(H63,"00"),".",TEXT(J63,"000"),".",TEXT(L63,"000"),".",TEXT(N63,"000")),""))))) -> 01.002.001.008 | E63: =IF(B63="*","",IFERROR(IF(B63="SERVIÇO",D63,OFFSET(E63,-1,0)),"")) -> 01.002.001.008 | F63: =IF($B63="UNIDADE CONSTRUTIVA",OFFSET(F63,-1,0)+1,LARGE(F$10:F62,1)) -> 1 | G63: =IF(B63="*","",IF(B63="UNIDADE CONSTRUTIVA",S63,OFFSET(G63,-1,0))) -> GERENCIAMENTO TÉCNICO E ADMINISTRATIVO | H63: =IF(B63="UNIDADE CONSTRUTIVA",0,IF(B63="CÉLULA CONSTRUTIVA",OFFSET(H63,-1,0)+1,OFFSET(H63,-1,0))) -> 1 | I63: =IF(B63="*","",IF(B63="CÉLULA CONSTRUTIVA",S63,OFFSET(I63,-1,0))) -> GERENCIAMENTO TÉCNICO | J63: =IF(B63="CÉLULA CONSTRUTIVA",0,IF(B63="ETAPA",OFFSET(J63,-1,0)+1,OFFSET(J63,-1,0))) -> 2 | K63: =IF(B63="*","",IF(B63="ETAPA",S63,OFFSET(K63,-1,0))) -> TAXAS | DOCUMENTOS | L63: =IF(B63="ETAPA",0,IF(B63="SUBETAPA",OFFSET(L63,-1,0)+1,OFFSET(L63,-1,0))) -> 1 | M63: =IF(B63="*","",IF(B63="SUBETAPA",S63,OFFSET(M63,-1,0))) -> Licenciamento - Taxas - Impostos | N63: =IF(B63="Subetapa",0,IF(B63="serviço",OFFSET(N63,-1,0)+1,OFFSET(N63,-1,0))) -> 8 | O63: =IF(B63="*","",IF(B63="SERVIÇO",S63,OFFSET(O63,-1,0))) -> Taxa de Aprovação de Projetos (Elétrico) | P63: =IF(S63="","",IF(Orçamento!$B63="INSUMO",S63,"")) | Q63: =IF(B63="","",IF(B63="Serviço",S63,"")) -> Taxa de Aprovação de Projetos (Elétrico) | R63: =IF(B63="serviço",U63,OFFSET(R63,-1,0)) -> 1 | S63: Taxa de Aprovação de Projetos (Elétrico) | T63: VB | U63: 1 | W63: =IFERROR(IF(B63="INSUMO",_xlfn.XLOOKUP(S63,Insumos!A:A,Insumos!C:C),""),"Inserir Preço") | X63: =IF(B63="Complemento do insumo",V63,IF(R63="","",IF(B63="serviço",R63,IF(OR(B63="insumo"),V63*R63,"")))) -> 1 | Y63: =IF(B63="insumo",W63*V63,IF(B63="serviço",SUMIFS(Y:Y,B:B,"insumo",E:E,E63,I:I,I63),"")) -> 2588.5733 | Z63: =IFERROR(IF(B63="Unidade Construtiva",SUMIFS(Z:Z,B:B,"Célula Construtiva",G:G,G63),IF(B63="célula construtiva",SUMIFS(Z:Z,B:B,"Insumo",I:I,I63,G:G,G63),IF(B63="ETAPA",SUMIFS(Z:Z,B:B,"Insumo",K:K,K63,I:I,I63,G:G,G63),IF(B63="subetapa",SUMIFS(Z:Z,M:M,M63,B:B,"insumo",K:K,K63,I:I,I63,G:G,G63),IF(B63="complemento do insumo",V63*W63,IF(B63="INSUMO",R63*V63*W63,X63*Y63)))))),"") -> 2588.5733 | AB63: =IF(B63="insumo",_xlfn.XLOOKUP(S63,Insumos!A:A,Insumos!D:D),"") | AC63: =IFERROR(IF(B63="","",Z63/SUMIF(B:B,"INSUMO",Z:Z)),0) -> 0.00037135444 | AE63: =IFERROR(IF(OR(Z63="",Z63=0),"",IF(AF63="","",IF(AF63="R$/mês",Z63/OBRA!$D$12,IF(AF63="R$/m²",Z63/OBRA!$D$10,IF(AF63="R$/apto",Orçamento!Z63/OBRA!$D$11,""))))),"") -> 1.3320982 | AF63: R$/m²
B64: Insumo | C64: =IF(B64="INSUMO",COUNTIFS(B:B,"INSUMO",S:S,S64),IF(B64="SERVIÇO",COUNTIFS(B:B,"SERVIÇO",S:S,S64),"")) -> 1 | D64: =IF(B64="Unidade Construtiva",TEXT(F64,"00"),IF(B64="Célula Construtiva",TEXT(H64,"00"),IF(B64="Etapa",CONCATENATE(TEXT(H64,"00"),".",TEXT(J64,"000")),IF(B64="Subetapa",CONCATENATE(TEXT(H64,"00"),".",TEXT(J64,"000"),".",TEXT(L64,"000")),IF(B64="Serviço",CONCATENATE(TEXT(H64,"00"),".",TEXT(J64,"000"),".",TEXT(L64,"000"),".",TEXT(N64,"000")),""))))) | E64: =IF(B64="*","",IFERROR(IF(B64="SERVIÇO",D64,OFFSET(E64,-1,0)),"")) -> 01.002.001.008 | F64: =IF($B64="UNIDADE CONSTRUTIVA",OFFSET(F64,-1,0)+1,LARGE(F$10:F63,1)) -> 1 | G64: =IF(B64="*","",IF(B64="UNIDADE CONSTRUTIVA",S64,OFFSET(G64,-1,0))) -> GERENCIAMENTO TÉCNICO E ADMINISTRATIVO | H64: =IF(B64="UNIDADE CONSTRUTIVA",0,IF(B64="CÉLULA CONSTRUTIVA",OFFSET(H64,-1,0)+1,OFFSET(H64,-1,0))) -> 1 | I64: =IF(B64="*","",IF(B64="CÉLULA CONSTRUTIVA",S64,OFFSET(I64,-1,0))) -> GERENCIAMENTO TÉCNICO | J64: =IF(B64="CÉLULA CONSTRUTIVA",0,IF(B64="ETAPA",OFFSET(J64,-1,0)+1,OFFSET(J64,-1,0))) -> 2 | K64: =IF(B64="*","",IF(B64="ETAPA",S64,OFFSET(K64,-1,0))) -> TAXAS | DOCUMENTOS | L64: =IF(B64="ETAPA",0,IF(B64="SUBETAPA",OFFSET(L64,-1,0)+1,OFFSET(L64,-1,0))) -> 1 | M64: =IF(B64="*","",IF(B64="SUBETAPA",S64,OFFSET(M64,-1,0))) -> Licenciamento - Taxas - Impostos | N64: =IF(B64="Subetapa",0,IF(B64="serviço",OFFSET(N64,-1,0)+1,OFFSET(N64,-1,0))) -> 8 | O64: =IF(B64="*","",IF(B64="SERVIÇO",S64,OFFSET(O64,-1,0))) -> Taxa de Aprovação de Projetos (Elétrico) | P64: =IF(S64="","",IF(Orçamento!$B64="INSUMO",S64,"")) -> Taxa Aprovação e legalização elétrico | Q64: =IF(B64="","",IF(B64="Serviço",S64,"")) | R64: =IF(B64="serviço",U64,OFFSET(R64,-1,0)) -> 1 | S64: Taxa Aprovação e legalização elétrico | T64: =_xlfn.XLOOKUP(S64,Insumos!$A$3:$A$371,Insumos!$B$3:$B$371) -> VB | U64: =IF($B64="insumo",R64,"") -> 1 | V64: 1 | W64: =IFERROR(IF(B64="INSUMO",_xlfn.XLOOKUP(S64,Insumos!A:A,Insumos!C:C),""),"Inserir Preço") -> 2588.5733 | X64: =IF(B64="Complemento do insumo",V64,IF(R64="","",IF(B64="serviço",R64,IF(OR(B64="insumo"),V64*R64,"")))) -> 1 | Y64: =IF(B64="insumo",W64*V64,IF(B64="serviço",SUMIFS(Y:Y,B:B,"insumo",E:E,E64,I:I,I64),"")) -> 2588.5733 | Z64: =IFERROR(IF(B64="Unidade Construtiva",SUMIFS(Z:Z,B:B,"Célula Construtiva",G:G,G64),IF(B64="célula construtiva",SUMIFS(Z:Z,B:B,"Insumo",I:I,I64,G:G,G64),IF(B64="ETAPA",SUMIFS(Z:Z,B:B,"Insumo",K:K,K64,I:I,I64,G:G,G64),IF(B64="subetapa",SUMIFS(Z:Z,M:M,M64,B:B,"insumo",K:K,K64,I:I,I64,G:G,G64),IF(B64="complemento do insumo",V64*W64,IF(B64="INSUMO",R64*V64*W64,X64*Y64)))))),"") -> 2588.5733 | AB64: =IF(B64="insumo",_xlfn.XLOOKUP(S64,Insumos!A:A,Insumos!D:D),"") -> Base de dados | AC64: =IFERROR(IF(B64="","",Z64/SUMIF(B:B,"INSUMO",Z:Z)),0) -> 0.00037135444 | AE64: =IFERROR(IF(OR(Z64="",Z64=0),"",IF(AF64="","",IF(AF64="R$/mês",Z64/OBRA!$D$12,IF(AF64="R$/m²",Z64/OBRA!$D$10,IF(AF64="R$/apto",Orçamento!Z64/OBRA!$D$11,""))))),"") -> 1.3320982 | AF64: R$/m²
B65: Serviço | C65: =IF(B65="INSUMO",COUNTIFS(B:B,"INSUMO",S:S,S65),IF(B65="SERVIÇO",COUNTIFS(B:B,"SERVIÇO",S:S,S65),"")) -> 1 | D65: =IF(B65="Unidade Construtiva",TEXT(F65,"00"),IF(B65="Célula Construtiva",TEXT(H65,"00"),IF(B65="Etapa",CONCATENATE(TEXT(H65,"00"),".",TEXT(J65,"000")),IF(B65="Subetapa",CONCATENATE(TEXT(H65,"00"),".",TEXT(J65,"000"),".",TEXT(L65,"000")),IF(B65="Serviço",CONCATENATE(TEXT(H65,"00"),".",TEXT(J65,"000"),".",TEXT(L65,"000"),".",TEXT(N65,"000")),""))))) -> 01.002.001.009 | E65: =IF(B65="*","",IFERROR(IF(B65="SERVIÇO",D65,OFFSET(E65,-1,0)),"")) -> 01.002.001.009 | F65: =IF($B65="UNIDADE CONSTRUTIVA",OFFSET(F65,-1,0)+1,LARGE(F$10:F64,1)) -> 1 | G65: =IF(B65="*","",IF(B65="UNIDADE CONSTRUTIVA",S65,OFFSET(G65,-1,0))) -> GERENCIAMENTO TÉCNICO E ADMINISTRATIVO | H65: =IF(B65="UNIDADE CONSTRUTIVA",0,IF(B65="CÉLULA CONSTRUTIVA",OFFSET(H65,-1,0)+1,OFFSET(H65,-1,0))) -> 1 | I65: =IF(B65="*","",IF(B65="CÉLULA CONSTRUTIVA",S65,OFFSET(I65,-1,0))) -> GERENCIAMENTO TÉCNICO | J65: =IF(B65="CÉLULA CONSTRUTIVA",0,IF(B65="ETAPA",OFFSET(J65,-1,0)+1,OFFSET(J65,-1,0))) -> 2 | K65: =IF(B65="*","",IF(B65="ETAPA",S65,OFFSET(K65,-1,0))) -> TAXAS | DOCUMENTOS | L65: =IF(B65="ETAPA",0,IF(B65="SUBETAPA",OFFSET(L65,-1,0)+1,OFFSET(L65,-1,0))) -> 1 | M65: =IF(B65="*","",IF(B65="SUBETAPA",S65,OFFSET(M65,-1,0))) -> Licenciamento - Taxas - Impostos | N65: =IF(B65="Subetapa",0,IF(B65="serviço",OFFSET(N65,-1,0)+1,OFFSET(N65,-1,0))) -> 9 | O65: =IF(B65="*","",IF(B65="SERVIÇO",S65,OFFSET(O65,-1,0))) -> Taxa de As Built | P65: =IF(S65="","",IF(Orçamento!$B65="INSUMO",S65,"")) | Q65: =IF(B65="","",IF(B65="Serviço",S65,"")) -> Taxa de As Built | R65: =IF(B65="serviço",U65,OFFSET(R65,-1,0)) -> 1 | S65: Taxa de As Built | T65: VB | U65: 1 | W65: =IFERROR(IF(B65="INSUMO",_xlfn.XLOOKUP(S65,Insumos!A:A,Insumos!C:C),""),"Inserir Preço") | X65: =IF(B65="Complemento do insumo",V65,IF(R65="","",IF(B65="serviço",R65,IF(OR(B65="insumo"),V65*R65,"")))) -> 1 | Y65: =IF(B65="insumo",W65*V65,IF(B65="serviço",SUMIFS(Y:Y,B:B,"insumo",E:E,E65,I:I,I65),"")) -> 7600 | Z65: =IFERROR(IF(B65="Unidade Construtiva",SUMIFS(Z:Z,B:B,"Célula Construtiva",G:G,G65),IF(B65="célula construtiva",SUMIFS(Z:Z,B:B,"Insumo",I:I,I65,G:G,G65),IF(B65="ETAPA",SUMIFS(Z:Z,B:B,"Insumo",K:K,K65,I:I,I65,G:G,G65),IF(B65="subetapa",SUMIFS(Z:Z,M:M,M65,B:B,"insumo",K:K,K65,I:I,I65,G:G,G65),IF(B65="complemento do insumo",V65*W65,IF(B65="INSUMO",R65*V65*W65,X65*Y65)))))),"") -> 7600 | AB65: =IF(B65="insumo",_xlfn.XLOOKUP(S65,Insumos!A:A,Insumos!D:D),"") | AC65: =IFERROR(IF(B65="","",Z65/SUMIF(B:B,"INSUMO",Z:Z)),0) -> 0.0010902893 | AE65: =IFERROR(IF(OR(Z65="",Z65=0),"",IF(AF65="","",IF(AF65="R$/mês",Z65/OBRA!$D$12,IF(AF65="R$/m²",Z65/OBRA!$D$10,IF(AF65="R$/apto",Orçamento!Z65/OBRA!$D$11,""))))),"") -> 3.9110141 | AF65: R$/m²
B66: Insumo | C66: =IF(B66="INSUMO",COUNTIFS(B:B,"INSUMO",S:S,S66),IF(B66="SERVIÇO",COUNTIFS(B:B,"SERVIÇO",S:S,S66),"")) -> 1 | D66: =IF(B66="Unidade Construtiva",TEXT(F66,"00"),IF(B66="Célula Construtiva",TEXT(H66,"00"),IF(B66="Etapa",CONCATENATE(TEXT(H66,"00"),".",TEXT(J66,"000")),IF(B66="Subetapa",CONCATENATE(TEXT(H66,"00"),".",TEXT(J66,"000"),".",TEXT(L66,"000")),IF(B66="Serviço",CONCATENATE(TEXT(H66,"00"),".",TEXT(J66,"000"),".",TEXT(L66,"000"),".",TEXT(N66,"000")),""))))) | E66: =IF(B66="*","",IFERROR(IF(B66="SERVIÇO",D66,OFFSET(E66,-1,0)),"")) -> 01.002.001.009 | F66: =IF($B66="UNIDADE CONSTRUTIVA",OFFSET(F66,-1,0)+1,LARGE(F$10:F65,1)) -> 1 | G66: =IF(B66="*","",IF(B66="UNIDADE CONSTRUTIVA",S66,OFFSET(G66,-1,0))) -> GERENCIAMENTO TÉCNICO E ADMINISTRATIVO | H66: =IF(B66="UNIDADE CONSTRUTIVA",0,IF(B66="CÉLULA CONSTRUTIVA",OFFSET(H66,-1,0)+1,OFFSET(H66,-1,0))) -> 1 | I66: =IF(B66="*","",IF(B66="CÉLULA CONSTRUTIVA",S66,OFFSET(I66,-1,0))) -> GERENCIAMENTO TÉCNICO | J66: =IF(B66="CÉLULA CONSTRUTIVA",0,IF(B66="ETAPA",OFFSET(J66,-1,0)+1,OFFSET(J66,-1,0))) -> 2 | K66: =IF(B66="*","",IF(B66="ETAPA",S66,OFFSET(K66,-1,0))) -> TAXAS | DOCUMENTOS | L66: =IF(B66="ETAPA",0,IF(B66="SUBETAPA",OFFSET(L66,-1,0)+1,OFFSET(L66,-1,0))) -> 1 | M66: =IF(B66="*","",IF(B66="SUBETAPA",S66,OFFSET(M66,-1,0))) -> Licenciamento - Taxas - Impostos | N66: =IF(B66="Subetapa",0,IF(B66="serviço",OFFSET(N66,-1,0)+1,OFFSET(N66,-1,0))) -> 9 | O66: =IF(B66="*","",IF(B66="SERVIÇO",S66,OFFSET(O66,-1,0))) -> Taxa de As Built | P66: =IF(S66="","",IF(Orçamento!$B66="INSUMO",S66,"")) -> Taxas de As Built | Q66: =IF(B66="","",IF(B66="Serviço",S66,"")) | R66: =IF(B66="serviço",U66,OFFSET(R66,-1,0)) -> 1 | S66: Taxas de As Built | T66: =_xlfn.XLOOKUP(S66,Insumos!$A$3:$A$371,Insumos!$B$3:$B$371) -> VB | U66: =IF($B66="insumo",R66,"") -> 1 | V66: 1 | W66: =IFERROR(IF(B66="INSUMO",_xlfn.XLOOKUP(S66,Insumos!A:A,Insumos!C:C),""),"Inserir Preço") -> 7600 | X66: =IF(B66="Complemento do insumo",V66,IF(R66="","",IF(B66="serviço",R66,IF(OR(B66="insumo"),V66*R66,"")))) -> 1 | Y66: =IF(B66="insumo",W66*V66,IF(B66="serviço",SUMIFS(Y:Y,B:B,"insumo",E:E,E66,I:I,I66),"")) -> 7600 | Z66: =IFERROR(IF(B66="Unidade Construtiva",SUMIFS(Z:Z,B:B,"Célula Construtiva",G:G,G66),IF(B66="célula construtiva",SUMIFS(Z:Z,B:B,"Insumo",I:I,I66,G:G,G66),IF(B66="ETAPA",SUMIFS(Z:Z,B:B,"Insumo",K:K,K66,I:I,I66,G:G,G66),IF(B66="subetapa",SUMIFS(Z:Z,M:M,M66,B:B,"insumo",K:K,K66,I:I,I66,G:G,G66),IF(B66="complemento do insumo",V66*W66,IF(B66="INSUMO",R66*V66*W66,X66*Y66)))))),"") -> 7600 | AB66: =IF(B66="insumo",_xlfn.XLOOKUP(S66,Insumos!A:A,Insumos!D:D),"") -> Base de dados | AC66: =IFERROR(IF(B66="","",Z66/SUMIF(B:B,"INSUMO",Z:Z)),0) -> 0.0010902893 | AE66: =IFERROR(IF(OR(Z66="",Z66=0),"",IF(AF66="","",IF(AF66="R$/mês",Z66/OBRA!$D$12,IF(AF66="R$/m²",Z66/OBRA!$D$10,IF(AF66="R$/apto",Orçamento!Z66/OBRA!$D$11,""))))),"") -> 3.9110141 | AF66: R$/m²
B67: Serviço | C67: =IF(B67="INSUMO",COUNTIFS(B:B,"INSUMO",S:S,S67),IF(B67="SERVIÇO",COUNTIFS(B:B,"SERVIÇO",S:S,S67),"")) -> 1 | D67: =IF(B67="Unidade Construtiva",TEXT(F67,"00"),IF(B67="Célula Construtiva",TEXT(H67,"00"),IF(B67="Etapa",CONCATENATE(TEXT(H67,"00"),".",TEXT(J67,"000")),IF(B67="Subetapa",CONCATENATE(TEXT(H67,"00"),".",TEXT(J67,"000"),".",TEXT(L67,"000")),IF(B67="Serviço",CONCATENATE(TEXT(H67,"00"),".",TEXT(J67,"000"),".",TEXT(L67,"000"),".",TEXT(N67,"000")),""))))) -> 01.002.001.010 | E67: =IF(B67="*","",IFERROR(IF(B67="SERVIÇO",D67,OFFSET(E67,-1,0)),"")) -> 01.002.001.010 | F67: =IF($B67="UNIDADE CONSTRUTIVA",OFFSET(F67,-1,0)+1,LARGE(F$10:F66,1)) -> 1 | G67: =IF(B67="*","",IF(B67="UNIDADE CONSTRUTIVA",S67,OFFSET(G67,-1,0))) -> GERENCIAMENTO TÉCNICO E ADMINISTRATIVO | H67: =IF(B67="UNIDADE CONSTRUTIVA",0,IF(B67="CÉLULA CONSTRUTIVA",OFFSET(H67,-1,0)+1,OFFSET(H67,-1,0))) -> 1 | I67: =IF(B67="*","",IF(B67="CÉLULA CONSTRUTIVA",S67,OFFSET(I67,-1,0))) -> GERENCIAMENTO TÉCNICO | J67: =IF(B67="CÉLULA CONSTRUTIVA",0,IF(B67="ETAPA",OFFSET(J67,-1,0)+1,OFFSET(J67,-1,0))) -> 2 | K67: =IF(B67="*","",IF(B67="ETAPA",S67,OFFSET(K67,-1,0))) -> TAXAS | DOCUMENTOS | L67: =IF(B67="ETAPA",0,IF(B67="SUBETAPA",OFFSET(L67,-1,0)+1,OFFSET(L67,-1,0))) -> 1 | M67: =IF(B67="*","",IF(B67="SUBETAPA",S67,OFFSET(M67,-1,0))) -> Licenciamento - Taxas - Impostos | N67: =IF(B67="Subetapa",0,IF(B67="serviço",OFFSET(N67,-1,0)+1,OFFSET(N67,-1,0))) -> 10 | O67: =IF(B67="*","",IF(B67="SERVIÇO",S67,OFFSET(O67,-1,0))) -> Taxa de Habite-se | P67: =IF(S67="","",IF(Orçamento!$B67="INSUMO",S67,"")) | Q67: =IF(B67="","",IF(B67="Serviço",S67,"")) -> Taxa de Habite-se | R67: =IF(B67="serviço",U67,OFFSET(R67,-1,0)) -> 1 | S67: Taxa de Habite-se | T67: VB | U67: 1 | W67: =IFERROR(IF(B67="INSUMO",_xlfn.XLOOKUP(S67,Insumos!A:A,Insumos!C:C),""),"Inserir Preço") | X67: =IF(B67="Complemento do insumo",V67,IF(R67="","",IF(B67="serviço",R67,IF(OR(B67="insumo"),V67*R67,"")))) -> 1 | Y67: =IF(B67="insumo",W67*V67,IF(B67="serviço",SUMIFS(Y:Y,B:B,"insumo",E:E,E67,I:I,I67),"")) -> 2528.2336 | Z67: =IFERROR(IF(B67="Unidade Construtiva",SUMIFS(Z:Z,B:B,"Célula Construtiva",G:G,G67),IF(B67="célula construtiva",SUMIFS(Z:Z,B:B,"Insumo",I:I,I67,G:G,G67),IF(B67="ETAPA",SUMIFS(Z:Z,B:B,"Insumo",K:K,K67,I:I,I67,G:G,G67),IF(B67="subetapa",SUMIFS(Z:Z,M:M,M67,B:B,"insumo",K:K,K67,I:I,I67,G:G,G67),IF(B67="complemento do insumo",V67*W67,IF(B67="INSUMO",R67*V67*W67,X67*Y67)))))),"") -> 2528.2336 | AB67: =IF(B67="insumo",_xlfn.XLOOKUP(S67,Insumos!A:A,Insumos!D:D),"") | AC67: =IFERROR(IF(B67="","",Z67/SUMIF(B:B,"INSUMO",Z:Z)),0) -> 0.00036269816 | AE67: =IFERROR(IF(OR(Z67="",Z67=0),"",IF(AF67="","",IF(AF67="R$/mês",Z67/OBRA!$D$12,IF(AF67="R$/m²",Z67/OBRA!$D$10,IF(AF67="R$/apto",Orçamento!Z67/OBRA!$D$11,""))))),"") -> 1.301047 | AF67: R$/m²
