Workbook
Name \0: #REF!
Name \a: #REF!
Name \m: #REF!
Name aa: #REF!
Name aaaa: '[1]M.O.'!#REF!
Name angelo: [2]Geral!#REF!
Name aux: #REF!
Name BDA: #REF!
Name BDI: #REF!
Name ca: #REF!
Name Capa: #REF!
Name cronograma: #REF!
Name D: #REF!
Name direto: #REF!
Name DRE: #REF!
Name ea: #REF!
Name eee: {#N/A,#N/A,FALSE,"ET-CAPA";#N/A,#N/A,FALSE,"ET-PAG1";#N/A,#N/A,FALSE,"ET-PAG2";#N/A,#N/A,FALSE,"ET-PAG3";#N/A,#N/A,FALSE,"ET-PAG4";#N/A,#N/A,FALSE,"ET-PAG5"}
Name FFFFFFF: #REF!
Name item_1: #REF!
Name LS: '[1]M.O.'!#REF!
Name MENU: #REF!
Name MENU1: #REF!
Name MENU2: #REF!
Name MENU3: #REF!
Name MENU4: #REF!
Name MENU5: #REF!
Name MENU6: #REF!
Name mo: #REF!
Name OAE: #REF!
Name ParamValues1: [3]ParamValues!$A$1:$A$39
Name PAV: #REF!
Name pr: #REF!
Name PRE: #REF!
Name Print_Area_MI: #REF!
Name qe: #REF!
Name qee: #REF!
Name reforsu: #REF!
Name ren: #REF!
Name REV: #REF!
Name sa: #REF!
Name SEG: #REF!
Name SIH: #REF!
Name SIV: #REF!
Name ss: #REF!
Name susref: #REF!
Name tania: #REF!
Name tc: #REF!
Name TOT: #REF!
Name Total: #REF!
Name TRP: #REF!
Name u: {#N/A,#N/A,FALSE,"ET-CAPA";#N/A,#N/A,FALSE,"ET-PAG1";#N/A,#N/A,FALSE,"ET-PAG2";#N/A,#N/A,FALSE,"ET-PAG3";#N/A,#N/A,FALSE,"ET-PAG4";#N/A,#N/A,FALSE,"ET-PAG5"}
Name wrn.GERAL.: {#N/A,#N/A,FALSE,"ET-CAPA";#N/A,#N/A,FALSE,"ET-PAG1";#N/A,#N/A,FALSE,"ET-PAG2";#N/A,#N/A,FALSE,"ET-PAG3";#N/A,#N/A,FALSE,"ET-PAG4";#N/A,#N/A,FALSE,"ET-PAG5"}
Name xxxx: #REF!

Sheet ORÇAMENTO_PARCIAL
A1: ETAPA | B1: VALOR ORÇADO | C1: % | D1: VALOR / m²
A2: GERENCIAMENTO TÉCNICO E ADMINISTRATIVO | B2: =[4]Obra!$C$32 -> 9723475.2 | C2: =B2/B$19 -> 0.40635298 | D2: =B2/ORÇAMENTO_PARCIAL!G$2 -> 1223.0279 | F2: ÁREA CONSTRUÍDA | G2: 7950.33 | H2: m²
A3: MOVIMENTAÇÃO DE TERRA | B3: =[4]Obra!$C$33 -> 0 | C3: =B3/B$19 -> 0 | D3: =B3/ORÇAMENTO_PARCIAL!G$2 -> 0
A4: INFRAESTRUTURA | B4: =[4]Obra!$C$34 -> 0 | C4: =B4/B$19 -> 0 | D4: =B4/ORÇAMENTO_PARCIAL!G$2 -> 0
A5: SUPRAESTRUTURA | B5: =[4]Obra!$C$35 -> 0 | C5: =B5/B$19 -> 0 | D5: =B5/ORÇAMENTO_PARCIAL!G$2 -> 0
A6: ALVENARIA | B6: =[4]Obra!$C$36 -> 1179684.5 | C6: =B6/B$19 -> 0.049300102 | D6: =B6/ORÇAMENTO_PARCIAL!G$2 -> 148.38183
A7: INSTALAÇÕES ELÉTRICAS, HIDRÁULICAS, GLP E PREVENTIVAS | B7: =[4]Obra!$C$37+[4]Obra!$C$48 -> 0 | C7: =B7/B$19 -> 0 | D7: =B7/ORÇAMENTO_PARCIAL!G$2 -> 0
A8: EQUIPAMENTOS E SISTEMAS ESPECIAIS | B8: =[4]Obra!$C$38+[4]Obra!$C$50 -> 0 | C8: =B8/B$19 -> 0 | D8: =B8/ORÇAMENTO_PARCIAL!G$2 -> 0
A9: IMPERMEABILIZAÇÃO | B9: =[4]Obra!$C$41 -> 898539.9 | C9: =B9/B$19 -> 0.037550809 | D9: =B9/ORÇAMENTO_PARCIAL!G$2 -> 113.0192
A10: REVESTIMENTOS INTERNOS EM PISO E PAREDE | B10: =[4]Obra!$C$39 -> 1286111.5 | C10: =B10/B$19 -> 0.053747783 | D10: =B10/ORÇAMENTO_PARCIAL!G$2 -> 161.76832
A11: REVESTIMENTOS E ACABAMENTOS INTERNOS EM TETO | B11: =[4]Obra!$C$40+[4]Obra!$C$44 -> 524454.36 | C11: =B11/B$19 -> 0.021917431 | D11: =B11/ORÇAMENTO_PARCIAL!G$2 -> 65.966364
A12: ACABAMENTOS EM PISO E PAREDE | B12: =[4]Obra!$C$42+[4]Obra!$C$43 -> 1848757.8 | C12: =B12/B$19 -> 0.077261289 | D12: =B12/ORÇAMENTO_PARCIAL!G$2 -> 232.5385
A13: PINTURA INTERNA | B13: =[4]Obra!$C$45 -> 1671037.3 | C13: =B13/B$19 -> 0.069834186 | D13: =B13/ORÇAMENTO_PARCIAL!G$2 -> 210.18464
A14: ESQUADRIAS, VIDROS E FERRAGENS | B14: =[4]Obra!$C$47 -> 4781116.5 | C14: =B14/B$19 -> 0.19980726 | D14: =B14/ORÇAMENTO_PARCIAL!G$2 -> 601.37334
A15: COBERTURA | B15: =[4]Obra!$C$49 -> 90917.911 | C15: =B15/B$19 -> 0.0037995432 | D15: =B15/ORÇAMENTO_PARCIAL!G$2 -> 11.435741
A16: REVESTIMENTOS E ACABAMENTOS DE FACHADA | B16: =[4]Obra!$C$46 -> 1914963.7 | C16: =B16/B$19 -> 0.080028095 | D16: =B16/ORÇAMENTO_PARCIAL!G$2 -> 240.86594
A17: SERVIÇOS COMPLEMENTARES | B17: =[4]Obra!$C$51 -> 9583.9923 | C17: =B17/B$19 -> 0.00040052386 | D17: =B17/ORÇAMENTO_PARCIAL!G$2 -> 1.2054836
A18: IMPREVISTOS E CONTINGENCIAS | B18: =[4]Obra!$C$52 -> 0 | C18: =B18/B$19 -> 0 | D18: =B18/ORÇAMENTO_PARCIAL!G$2 -> 0
A19: TOTAL | B19: =SUM(B2:B18) -> 23928643 | C19: =SUM(C2:C18) -> 1 | D19: =SUM(D2:D18) -> 3009.7672
A20: CUB/SP | B20: 2613.67 | C20: 45689 | D20: =+D19/B20 -> 1.1515483

Sheet EAP
A1: ITEM | B1: DESCRIÇÃO
A2: 1 | B2: GERENCIAMENTO TÉCNICO E ADMINISTRATIVO
A3: 2 | B3: MOVIMENTAÇÃO DE TERRA
A4: 3 | B4: INFRAESTRUTURA
A5: 4 | B5: CONTENÇÃO
A6: 5 | B6: SUPRAESTRUTURA
A7: 6 | B7: ALVENARIA
A8: 7 | B8: INSTALAÇÕES ELÉTRICAS, HIDRÁULICAS, GLP E PREVENTIVAS
A9: 8 | B9: CLIMATIZAÇÃO, EXAUSTÃO MECÂNICA E PRESSURIZAÇÃO
A10: 9 | B10: REVESTIMENTOS ARGAMASSADOS PISO E PAREDE
A11: 10 | B11: REVESTIMENTOS ARGAMASSADOS TETO
A12: 11 | B12: IMPERMEABILIZAÇÃO
A13: 12 | B13: ACABAMENTOS INTERNOS EM PAREDE
... A23: 22 | B23: IMPREVISTOS

Sheet ORÇAMENTO_EXECUTIVO
A1: ETAPA | B1: VALOR ORÇADO | C1: % | D1: VALOR / m²
A2: GERENCIAMENTO TÉCNICO E ADMINISTRATIVO | B2: =[10]Obra!$C32 -> 9723475.2 | C2: =B2/B$24 -> 0.22909635 | D2: =B2/$G$2 -> 1234.166 | F2: ÁREA CONSTRUÍDA | G2: 7878.58 | H2: m²
A3: MOVIMENTAÇÃO DE TERRA | B3: =[10]Obra!$C33 -> 1029319.8 | C3: =B3/B$24 -> 0.024251967 | D3: =B3/$G$2 -> 130.64788 | F3: ÁREA TOTAL ATUALIZADA DO PARCIAL
A4: INFRAESTRUTURA | B4: =[10]Obra!$C34 -> 2461562.8 | C4: =B4/B$24 -> 0.057997273 | D4: =B4/$G$2 -> 312.43736
A5: CONTENÇÃO | B5: =[10]Obra!$C35 -> 767406.84 | C5: =B5/B$24 -> 0.018080995 | D5: =B5/$G$2 -> 97.404207
A6: SUPRAESTRUTURA | B6: =[10]Obra!$C36 -> 6377074.6 | C6: =B6/B$24 -> 0.15025127 | D6: =B6/$G$2 -> 809.41928
A7: ALVENARIA | B7: =[10]Obra!$C37 -> 1138900.3 | C7: =B7/B$24 -> 0.026833811 | D7: =B7/$G$2 -> 144.55654
A8: INSTALAÇÕES ELÉTRICAS, HIDRÁULICAS, GLP E PREVENTIVAS | B8: =[10]Obra!$C38 -> 3970610.7 | C8: =B8/B$24 -> 0.093552192 | D8: =B8/$G$2 -> 503.97542
A9: CLIMATIZAÇÃO, EXAUSTÃO MECÂNICA E PRESSURIZAÇÃO | B9: =[10]Obra!$C39 -> 964750.27 | C9: =B9/B$24 -> 0.022730635 | D9: =B9/$G$2 -> 122.4523
A10: REVESTIMENTOS ARGAMASSADOS PISO E PAREDE | B10: =[10]Obra!$C40 -> 1235828.4 | C10: =B10/B$24 -> 0.029117551 | D10: =B10/$G$2 -> 156.85929
A11: REVESTIMENTOS ARGAMASSADOS TETO | B11: =[10]Obra!$C41 -> 142358.31 | C11: =B11/B$24 -> 0.0033541269 | D11: =B11/$G$2 -> 18.069032
A12: IMPERMEABILIZAÇÃO | B12: =[10]Obra!$C42 -> 893128.61 | C12: =B12/B$24 -> 0.021043146 | D12: =B12/$G$2 -> 113.36162
A13: ACABAMENTOS INTERNOS EM PAREDE | B13: =[10]Obra!$C43 -> 371650.43 | C13: =B13/B$24 -> 0.0087565151 | D13: =B13/$G$2 -> 47.17226
A14: ACABAMENTOS EM PISOS E PAVIMENTAÇÕES | B14: =[10]Obra!$C44 -> 1398785.3 | C14: =B14/B$24 -> 0.032957003 | D14: =B14/$G$2 -> 177.54281
A15: ACABAMENTOS INTERNOS EM TETO | B15: =[10]Obra!$C45 -> 329970.54 | C15: =B15/B$24 -> 0.0077744885 | D15: =B15/$G$2 -> 41.881981
... A23: IMPREVISTOS | B23: =[10]Obra!$C53 -> 449715.04 | C23: =B23/B$24 -> 0.010595808 | D23: =B23/$G$2 -> 57.080723
A24: TOTAL | B24: =SUM(B2:B23) -> 42442733 | C24: =SUM(C2:C23) -> 1 | D24: =SUM(D2:D23) -> 5387.1044
A25: CUB/SP | B25: 2053.66 | C25: 45748 | D25: =ROUNDUP(+D24/B25,2)&" CUB" -> 2,63 CUB
B27: =SUM(B2:B22) -> 41993018

Sheet ANÁLISE_CUSTOS PARCIAL
A1: ETAPA | B1: OBRA | D1: OBRA SIMILAR
B2: VALOR | C2: VALOR / m² | D2: VALOR / m² | G2: Justificativas
A3: =ORÇAMENTO_PARCIAL!A2 -> GERENCIAMENTO TÉCNICO E ADMINISTRATIVO | B3: =ORÇAMENTO_PARCIAL!B2*0 -> 0 | C3: =ORÇAMENTO_PARCIAL!D2*0 -> 0 | D3: =FIXED(CÁLCULO_MÉDIAS!AH8,2,FALSE)&" "&"-"&FIXED(CÁLCULO_MÉDIAS!AI8,2,FALSE) -> 200,00 -550,00 | E3: 9723475.3 | F3: =(1223.03-700) -> 523.03 | G3: Extremamente caro, porém 88% do custo foi informado pela propria empresa
A4: =ORÇAMENTO_PARCIAL!A3 -> MOVIMENTAÇÃO DE TERRA | B4: =ORÇAMENTO_PARCIAL!B3 -> 0 | C4: =ORÇAMENTO_PARCIAL!D3 -> 0 | D4: =FIXED(CÁLCULO_MÉDIAS!AH9,2,FALSE)&" "&"-"&FIXED(CÁLCULO_MÉDIAS!AI9,2,FALSE) -> 65,00 -75,00 | E4: 445700.74 | F4: =56.06-27 -> 29.06 | G4: Ficou bem acima da média, mas temos dois Sub Solo que o volume de de corte do terreno representa 84% do volume dos pavimentos | N4: =5872.21/(1118.43*6.2) -> 0.84683945
A5: =ORÇAMENTO_PARCIAL!A4 -> INFRAESTRUTURA | B5: =ORÇAMENTO_PARCIAL!B4 -> 0 | C5: =ORÇAMENTO_PARCIAL!D4 -> 0 | D5: =FIXED(CÁLCULO_MÉDIAS!AH10,2,FALSE)&" "&"-"&FIXED(CÁLCULO_MÉDIAS!AI10,2,FALSE) -> 130,00 -210,00 | E5: 3966312.3 | F5: =498.89-260 -> 238.89 | G5: Certamente o impacto do aumento se dá pelo uso da estaca estrela, pois enquanto estimado para estaca estrela é de aproximadamente 34% mais caro em relação a estaca pre-moldada circular, isso considerando os mesmos blocos de coroamento.
A6: =ORÇAMENTO_PARCIAL!A5 -> SUPRAESTRUTURA | B6: =ORÇAMENTO_PARCIAL!B5 -> 0 | C6: =ORÇAMENTO_PARCIAL!D5 -> 0 | D6: =FIXED(CÁLCULO_MÉDIAS!AH12,2,FALSE)&" "&"-"&FIXED(CÁLCULO_MÉDIAS!AI12,2,FALSE) -> 680,00 -750,00
A7: =ORÇAMENTO_PARCIAL!A6 -> ALVENARIA | B7: =ORÇAMENTO_PARCIAL!B6 -> 1179684.5 | C7: =ORÇAMENTO_PARCIAL!D6 -> 148.38183 | D7: =FIXED(CÁLCULO_MÉDIAS!AH13,2,FALSE)&" "&"-"&FIXED(CÁLCULO_MÉDIAS!AI13,2,FALSE) -> 120,00 -180,00
A8: =ORÇAMENTO_PARCIAL!A7 -> INSTALAÇÕES ELÉTRICAS, HIDRÁULICAS, GLP E PREVENTIVAS | B8: =ORÇAMENTO_PARCIAL!B7 -> 0 | C8: =ORÇAMENTO_PARCIAL!D7 -> 0 | D8: =FIXED(CÁLCULO_MÉDIAS!AH14,2,FALSE)&" "&"-"&FIXED(CÁLCULO_MÉDIAS!AI14,2,FALSE) -> 270,00 -360,00
A9: =ORÇAMENTO_PARCIAL!A8 -> EQUIPAMENTOS E SISTEMAS ESPECIAIS | B9: =ORÇAMENTO_PARCIAL!B8 -> 0 | C9: =ORÇAMENTO_PARCIAL!D8 -> 0 | D9: =FIXED(CÁLCULO_MÉDIAS!AH15,2,FALSE)&" "&"-"&FIXED(CÁLCULO_MÉDIAS!AI15,2,FALSE) -> 180,00 -270,00
A10: =ORÇAMENTO_PARCIAL!A9 -> IMPERMEABILIZAÇÃO | B10: =ORÇAMENTO_PARCIAL!B9 -> 898539.9 | C10: =ORÇAMENTO_PARCIAL!D9 -> 113.0192 | D10: =FIXED(CÁLCULO_MÉDIAS!AH16,2,FALSE)&" "&"-"&FIXED(CÁLCULO_MÉDIAS!AI16,2,FALSE) -> 60,00 -80,00 | E10: *Muitas áreas descobertas com manta e alguns locais está utilizando manta dupla elevando o custo e ficando fora das médias
A11: =ORÇAMENTO_PARCIAL!A10 -> REVESTIMENTOS INTERNOS EM PISO E PAREDE | B11: =ORÇAMENTO_PARCIAL!B10 -> 1286111.5 | C11: =ORÇAMENTO_PARCIAL!D10 -> 161.76832 | D11: =FIXED(CÁLCULO_MÉDIAS!AH17,2,FALSE)&" "&"-"&FIXED(CÁLCULO_MÉDIAS!AI17,2,FALSE) -> 120,00 -170,00
A12: =ORÇAMENTO_PARCIAL!A11 -> REVESTIMENTOS E ACABAMENTOS INTERNOS EM TETO | B12: =ORÇAMENTO_PARCIAL!B11 -> 524454.36 | C12: =ORÇAMENTO_PARCIAL!D11 -> 65.966364 | D12: =FIXED(CÁLCULO_MÉDIAS!AH18,2,FALSE)&" "&"-"&FIXED(CÁLCULO_MÉDIAS!AI18,2,FALSE) -> 55,00 -80,00
A13: =ORÇAMENTO_PARCIAL!A12 -> ACABAMENTOS EM PISO E PAREDE | B13: =ORÇAMENTO_PARCIAL!B12 -> 1848757.8 | C13: =ORÇAMENTO_PARCIAL!D12 -> 232.5385 | D13: =FIXED(CÁLCULO_MÉDIAS!AH19,2,FALSE)&" "&"-"&FIXED(CÁLCULO_MÉDIAS!AI19,2,FALSE) -> 150,00 -200,00 | G13: =F13*ORÇAMENTO_PARCIAL!G2 -> 0
A14: =ORÇAMENTO_PARCIAL!A13 -> PINTURA INTERNA | B14: =ORÇAMENTO_PARCIAL!B13 -> 1671037.3 | C14: =ORÇAMENTO_PARCIAL!D13 -> 210.18464 | D14: =FIXED(CÁLCULO_MÉDIAS!AH20,2,FALSE)&" "&"-"&FIXED(CÁLCULO_MÉDIAS!AI20,2,FALSE) -> 120,00 -140,00 | E14: * Consideração de Pintura e Textura pas algumas ficaram acima da média dos empreendimentos similares
A15: =ORÇAMENTO_PARCIAL!A14 -> ESQUADRIAS, VIDROS E FERRAGENS | B15: =ORÇAMENTO_PARCIAL!B14 -> 4781116.5 | C15: =ORÇAMENTO_PARCIAL!D14 -> 601.37334 | D15: =FIXED(CÁLCULO_MÉDIAS!AH21,2,FALSE)&" "&"-"&FIXED(CÁLCULO_MÉDIAS!AI21,2,FALSE) -> 250,00 -360,00 | E15: *Cotações que conseguimos para região elevaram o custo
A16: =ORÇAMENTO_PARCIAL!A15 -> COBERTURA | B16: =ORÇAMENTO_PARCIAL!B15 -> 90917.911 | C16: =ORÇAMENTO_PARCIAL!D15 -> 11.435741 | D16: =FIXED(CÁLCULO_MÉDIAS!AH22,2,FALSE)&" "&"-"&FIXED(CÁLCULO_MÉDIAS!AI22,2,FALSE) -> 10,00 -15,00
A17: =ORÇAMENTO_PARCIAL!A16 -> REVESTIMENTOS E ACABAMENTOS DE FACHADA | B17: =ORÇAMENTO_PARCIAL!B16 -> 1914963.7 | C17: =ORÇAMENTO_PARCIAL!D16 -> 240.86594 | D17: =FIXED(CÁLCULO_MÉDIAS!AH23,2,FALSE)&" "&"-"&FIXED(CÁLCULO_MÉDIAS!AI23,2,FALSE) -> 110,00 -140,00 | E17: *Temos uma fachada bem imponente com pedras textura e pintura, onde eleva o custo das médias que temos
A18: =ORÇAMENTO_PARCIAL!A17 -> SERVIÇOS COMPLEMENTARES | B18: =ORÇAMENTO_PARCIAL!B17 -> 9583.9923 | C18: =ORÇAMENTO_PARCIAL!D17 -> 1.2054836 | D18: =FIXED(CÁLCULO_MÉDIAS!AH24,2,FALSE)&" "&"-"&FIXED(CÁLCULO_MÉDIAS!AI24,2,FALSE) -> 130,00 -200,00
A19: TOTAL | B19: =SUM(B3:B18) -> 14205167 | C19: =SUM(C3:C18) -> 1786.7393 | D19: =FIXED(CÁLCULO_MÉDIAS!AH25,2,FALSE)&" "&"-"&FIXED(CÁLCULO_MÉDIAS!AI25,2,FALSE) -> 2.700,00 -3.870,00
B23: 2007.57
B24: 2461.35
B25: =B24/B23 -> 1.2260345
C28: 1.1023
A30: 900,00 - 1100 | B30: 900
A31: 25,00 - 30,00 | B31: 25
A32: 15,00 - 22,00 | B32: 15
A33: 150,00 - 200,00 | B33: 150
A34: 440,00 - 510,00 | B34: 440
A35: -
A36: 55,00 - 70,00 | B36: 55
A37: 170,00 - 200,00 | B37: 170
A38: 165,00 - 230,00 | B38: 165
A39: 40,00 - 70,00 | B39: 40
A40: 55,00 - 77,00 | B40: 55
A41: 35,00 - 50,00 | B41: 35
A42: 130,00 - 175,00 | B42: 130
A43: 35,00 - 65,00 | B43: 35
A44: 35,00 - 55,00 | B44: 35
A45: 430,00 - 550,00 | B45: 430
A46: 35,00 - 50,00 | B46: 35
A47: 150,00 - 220,00 | B47: 150

Sheet ANÁLISE_CUSTOS EXECUTIVO
B2: ETAPA | C2: OBRA | E2: OBRA SIMILAR | F2: Justificativas | G2: MÉDIAS | J2: MÉDIAS
C3: VALOR | D3: VALOR / m² | E3: VALOR / m² | G3: MÍNIMA | H3: MÁXIMA | K3: Justificativas
B4: =ORÇAMENTO_PARCIAL!A2 -> GERENCIAMENTO TÉCNICO E ADMINISTRATIVO | C4: =_xlfn.XLOOKUP(B4,ORÇAMENTO_EXECUTIVO!A$2:A$23,ORÇAMENTO_EXECUTIVO!B$2:B$23) -> 9723475.2 | D4: =C4/C$24 -> 1234.166 | E4: =FIXED(CÁLCULO_MÉDIAS!AH8,2,FALSE)&" "&"-"&FIXED(CÁLCULO_MÉDIAS!AI8,2,FALSE) -> 200,00 -550,00 | F4: Extremamente caro, porém 88% do custo foi informado pela propria empresa | G4: =CÁLCULO_MÉDIAS!AH8 -> 200 | H4: =CÁLCULO_MÉDIAS!AI8 -> 550 | J4: {=_xlfn.IFS(D4>=H4,"FORA",D4>=G4,"DENTRO")} -> FORA | K4: Extremamente caro, porém 88% do custo foi informado pela propria empresa
B5: =ORÇAMENTO_PARCIAL!A3 -> MOVIMENTAÇÃO DE TERRA | C5: =_xlfn.XLOOKUP(B5,ORÇAMENTO_EXECUTIVO!A$2:A$23,ORÇAMENTO_EXECUTIVO!B$2:B$23) -> 1029319.8 | D5: =C5/C$24 -> 130.64788 | E5: =FIXED(CÁLCULO_MÉDIAS!AH9,2,FALSE)&" "&"-"&FIXED(CÁLCULO_MÉDIAS!AI9,2,FALSE) -> 65,00 -75,00 | F5: Dois Subsolos cujo volume de escavação do terreno e blocos são maiores do que as das obras analisadas, possuindo + bota-fora e - reaterro | G5: =CÁLCULO_MÉDIAS!AH9 -> 65 | H5: =CÁLCULO_MÉDIAS!AI9 -> 75 | J5: {=_xlfn.IFS(D5>=H5,"FORA",D5>=G5,"DENTRO")} -> FORA | K5: Ficou bem acima da média, mas temos dois Sub Solo que o volume de de corte do terreno representa 84% do volume dos pavimentos e a escavação de blocos e estacas são maiores do que as das obras analisadas
B6: =ORÇAMENTO_PARCIAL!A4 -> INFRAESTRUTURA | C6: =_xlfn.XLOOKUP(B6,ORÇAMENTO_EXECUTIVO!A$2:A$23,ORÇAMENTO_EXECUTIVO!B$2:B$23) -> 2461562.8 | D6: =C6/C$24 -> 312.43736 | E6: =FIXED(CÁLCULO_MÉDIAS!AH10,2,FALSE)&" "&"-"&FIXED(CÁLCULO_MÉDIAS!AI10,2,FALSE) -> 130,00 -210,00 | F6: Temos um maior numero de estacas de 100 e de 90 cm, o que causa o aumento na etapa de fundação profunda; assim como temos blocos extremamentes grandes sendo usados nesse empreenimento, aumentando o consumo de concreto, formas e aço; e temos o serviço de concreto armado nessa etapa | G6: =CÁLCULO_MÉDIAS!AH10 -> 130 | H6: =CÁLCULO_MÉDIAS!AI10 -> 210 | J6: {=_xlfn.IFS(D6>=H6,"FORA",D6>=G6,"DENTRO")} -> FORA | K6: Temos um maior numero de estacas de 100 e de 90 cm, o que causa o aumento na etapa de fundação profunda + o contrapiso armado esta sendo incluso nessa etapa (subsolo 2), assim como temos blocos extremamentes grandes sendo usados nesse empreenimento, aumentando o consumo de concreto, formas e aço + Valores de corte e dobra em indutria são mais caros do que considerado nas demais obras (corte e dobra em obra)
B7: CONTENÇÃO | C7: =_xlfn.XLOOKUP(B7,ORÇAMENTO_EXECUTIVO!A$2:A$23,ORÇAMENTO_EXECUTIVO!B$2:B$23) -> 767406.84 | D7: =C7/C$24 -> 97.404207 | E7: =FIXED(CÁLCULO_MÉDIAS!AH11,2,FALSE)&" "&"-"&FIXED(CÁLCULO_MÉDIAS!AI11,2,FALSE) -> 50,00 -90,00 | F7: Perimetro de maior de contenção e estacas; e tem adição de valor de estroncas, e as obras de referencia não tem parede de fechamento | G7: =CÁLCULO_MÉDIAS!AH11 -> 50 | H7: =CÁLCULO_MÉDIAS!AI11 -> 90 | J7: {=_xlfn.IFS(D7>=H7,"FORA",D7>=G7,"DENTRO")} -> FORA | K7: Valor proximo de execução de muretas guias com tirantes, porem, como essa obra tem o custo extra das 118 estacas, acaba elevando o m²Contenção de estacas
B8: =ORÇAMENTO_PARCIAL!A5 -> SUPRAESTRUTURA | C8: =_xlfn.XLOOKUP(B8,ORÇAMENTO_EXECUTIVO!A$2:A$23,ORÇAMENTO_EXECUTIVO!B$2:B$23) -> 6377074.6 | D8: =C8/C$24 -> 809.41928 | E8: =FIXED(CÁLCULO_MÉDIAS!AH12,2,FALSE)&" "&"-"&FIXED(CÁLCULO_MÉDIAS!AI12,2,FALSE) -> 680,00 -750,00 | G8: =CÁLCULO_MÉDIAS!AH12 -> 680 | H8: =CÁLCULO_MÉDIAS!AI12 -> 750 | J8: {=_xlfn.IFS(D8>=H8,"FORA",D8>=G8,"DENTRO")} -> FORA | K8: Valores de corte e dobra em indutria são mais caros do que considerado nas demais obras (corte e dobra em obra)
B9: =ORÇAMENTO_PARCIAL!A6 -> ALVENARIA | C9: =_xlfn.XLOOKUP(B9,ORÇAMENTO_EXECUTIVO!A$2:A$23,ORÇAMENTO_EXECUTIVO!B$2:B$23) -> 1138900.3 | D9: =C9/C$24 -> 144.55654 | E9: =FIXED(CÁLCULO_MÉDIAS!AH13,2,FALSE)&" "&"-"&FIXED(CÁLCULO_MÉDIAS!AI13,2,FALSE) -> 120,00 -180,00 | G9: =CÁLCULO_MÉDIAS!AH13 -> 120 | H9: =CÁLCULO_MÉDIAS!AI13 -> 180 | J9: {=_xlfn.IFS(D9>=H9,"FORA",D9>=G9,"DENTRO")} -> DENTRO
B10: =ORÇAMENTO_PARCIAL!A7 -> INSTALAÇÕES ELÉTRICAS, HIDRÁULICAS, GLP E PREVENTIVAS | C10: =ORÇAMENTO_EXECUTIVO!B8+ORÇAMENTO_EXECUTIVO!B19 -> 4519485.8 | D10: =C10/C$24 -> 573.64217 | E10: =FIXED(CÁLCULO_MÉDIAS!AH14,2,FALSE)&" "&"-"&FIXED(CÁLCULO_MÉDIAS!AI14,2,FALSE) -> 270,00 -360,00 | F10: A mão de obra, informada pelo cliente, esta com o preço mais elevado do que é praticado nas obras similares | G10: =CÁLCULO_MÉDIAS!AH14 -> 270 | H10: =CÁLCULO_MÉDIAS!AI14 -> 360 | J10: {=_xlfn.IFS(D10>=H10,"FORA",D10>=G10,"DENTRO")} -> FORA | K10: O preço esta muito fora devido a mão de obra informada pelo cliente esta superfaturada e mais cara do que a média
B11: =ORÇAMENTO_PARCIAL!A8 -> EQUIPAMENTOS E SISTEMAS ESPECIAIS | C11: =ORÇAMENTO_EXECUTIVO!B21+ORÇAMENTO_EXECUTIVO!B9 -> 2369873.7 | D11: =C11/C$24 -> 300.79959 | E11: =FIXED(CÁLCULO_MÉDIAS!AH15,2,FALSE)&" "&"-"&FIXED(CÁLCULO_MÉDIAS!AI15,2,FALSE) -> 180,00 -270,00 | F11: A mão de obra, informada pelo cliente, esta com o preço mais elevado do que é praticado nas obras similares; temos serviços diferenciados,como: escada pressurizada, equipamentos de exaustão em churrasqueiras e coifas, | G11: =CÁLCULO_MÉDIAS!AH15 -> 180 | H11: =CÁLCULO_MÉDIAS!AI15 -> 270 | J11: {=_xlfn.IFS(D11>=H11,"FORA",D11>=G11,"DENTRO")} -> FORA | K11: O preço esta muito fora devido a mão de obra informada pelo cliente esta superfaturada e mais cara do que a média e temos serviços adicionados que geralmente não tem em outras obras, como escada pressurizada, equipamentos de exaustão em churrasqueiras, assim como os spas, espelhos de agua e sistema de geradores, assim como nesse são 3 elevadore
B12: =ORÇAMENTO_PARCIAL!A9 -> IMPERMEABILIZAÇÃO | C12: =_xlfn.XLOOKUP(B12,ORÇAMENTO_EXECUTIVO!A$2:A$23,ORÇAMENTO_EXECUTIVO!B$2:B$23) -> 893128.61 | D12: =C12/C$24 -> 113.36162 | E12: =FIXED(CÁLCULO_MÉDIAS!AH16,2,FALSE)&" "&"-"&FIXED(CÁLCULO_MÉDIAS!AI16,2,FALSE) -> 60,00 -80,00 | F12: Muitas áreas descobertas com manta e alguns locais está utilizando manta dupla elevando o custo ficando fora das médias | G12: =CÁLCULO_MÉDIAS!AH16 -> 60 | H12: =CÁLCULO_MÉDIAS!AI16 -> 80 | J12: {=_xlfn.IFS(D12>=H12,"FORA",D12>=G12,"DENTRO")} -> FORA | K12: *Muitas áreas descobertas com manta e alguns locais está utilizando manta dupla elevando o custo ficando fora das médias
B13: REVESTIMENTOS ARGAMASSADOS PISO E PAREDE | C13: =_xlfn.XLOOKUP(B13,ORÇAMENTO_EXECUTIVO!A$2:A$23,ORÇAMENTO_EXECUTIVO!B$2:B$23) -> 1235828.4 | D13: =C13/C$24 -> 156.85929 | E13: =FIXED(CÁLCULO_MÉDIAS!AH17,2,FALSE)&" "&"-"&FIXED(CÁLCULO_MÉDIAS!AI17,2,FALSE) -> 120,00 -170,00 | G13: =CÁLCULO_MÉDIAS!AH17 -> 120 | H13: =CÁLCULO_MÉDIAS!AI17 -> 170 | J13: {=_xlfn.IFS(D13>=H13,"FORA",D13>=G13,"DENTRO")} -> DENTRO
B14: =ORÇAMENTO_PARCIAL!A11 -> REVESTIMENTOS E ACABAMENTOS INTERNOS EM TETO | C14: =ORÇAMENTO_EXECUTIVO!B15+ORÇAMENTO_EXECUTIVO!B11 -> 472328.85 | D14: =C14/C$24 -> 59.951013 | E14: =FIXED(CÁLCULO_MÉDIAS!AH18,2,FALSE)&" "&"-"&FIXED(CÁLCULO_MÉDIAS!AI18,2,FALSE) -> 55,00 -80,00 | G14: =CÁLCULO_MÉDIAS!AH18 -> 55 | H14: =CÁLCULO_MÉDIAS!AI18 -> 80 | J14: {=_xlfn.IFS(D14>=H14,"FORA",D14>=G14,"DENTRO")} -> DENTRO
B15: =ORÇAMENTO_PARCIAL!A12 -> ACABAMENTOS EM PISO E PAREDE | C15: =ORÇAMENTO_EXECUTIVO!B14+ORÇAMENTO_EXECUTIVO!B13 -> 1770435.7 | D15: =C15/C$24 -> 224.71507 | E15: =FIXED(CÁLCULO_MÉDIAS!AH19,2,FALSE)&" "&"-"&FIXED(CÁLCULO_MÉDIAS!AI19,2,FALSE) -> 150,00 -200,00 | F15: Os acabamentos que normalmente compõe o custo da fachada foram movidos para esta etapa devido ao momento de execução | G15: =CÁLCULO_MÉDIAS!AH19 -> 150 | H15: =CÁLCULO_MÉDIAS!AI19 -> 200 | J15: {=_xlfn.IFS(D15>=H15,"FORA",D15>=G15,"DENTRO")} -> FORA
B16: =ORÇAMENTO_PARCIAL!A13 -> PINTURA INTERNA | C16: =_xlfn.XLOOKUP(B16,ORÇAMENTO_EXECUTIVO!A$2:A$23,ORÇAMENTO_EXECUTIVO!B$2:B$23) -> 1291940.1 | D16: =C16/C$24 -> 163.98134 | E16: =FIXED(CÁLCULO_MÉDIAS!AH20,2,FALSE)&" "&"-"&FIXED(CÁLCULO_MÉDIAS!AI20,2,FALSE) -> 120,00 -140,00 | F16: Em obras similares, areas técnicas e escadas são consideradas texturas, nessa obra esta considerado pintura completa | G16: =CÁLCULO_MÉDIAS!AH20 -> 120 | H16: =CÁLCULO_MÉDIAS!AI20 -> 140 | J16: {=_xlfn.IFS(D16>=H16,"FORA",D16>=G16,"DENTRO")} -> FORA
B17: =ORÇAMENTO_PARCIAL!A14 -> ESQUADRIAS, VIDROS E FERRAGENS | C17: =_xlfn.XLOOKUP(B17,ORÇAMENTO_EXECUTIVO!A$2:A$23,ORÇAMENTO_EXECUTIVO!B$2:B$23) -> 3788741.8 | D17: =C17/C$24 -> 480.89145 | E17: =FIXED(CÁLCULO_MÉDIAS!AH21,2,FALSE)&" "&"-"&FIXED(CÁLCULO_MÉDIAS!AI21,2,FALSE) -> 250,00 -360,00 | F17: Persiana motorizada como extra; linha gold 32; Gradil no Térreo; Escadaria em aço no duplex; Brises da fachada | G17: =CÁLCULO_MÉDIAS!AH21 -> 250 | H17: =CÁLCULO_MÉDIAS!AI21 -> 360 | J17: {=_xlfn.IFS(D17>=H17,"FORA",D17>=G17,"DENTRO")} -> FORA | K17: *Cotações que conseguimos para região elevaram o custo
B18: =ORÇAMENTO_PARCIAL!A15 -> COBERTURA | C18: =_xlfn.XLOOKUP(B18,ORÇAMENTO_EXECUTIVO!A$2:A$23,ORÇAMENTO_EXECUTIVO!B$2:B$23) -> 107939.06 | D18: =C18/C$24 -> 13.700319 | E18: =FIXED(CÁLCULO_MÉDIAS!AH22,2,FALSE)&" "&"-"&FIXED(CÁLCULO_MÉDIAS!AI22,2,FALSE) -> 10,00 -15,00 | G18: =CÁLCULO_MÉDIAS!AH22 -> 10 | H18: =CÁLCULO_MÉDIAS!AI22 -> 15 | J18: {=_xlfn.IFS(D18>=H18,"FORA",D18>=G18,"DENTRO")} -> DENTRO
B19: =ORÇAMENTO_PARCIAL!A16 -> REVESTIMENTOS E ACABAMENTOS DE FACHADA | C19: =_xlfn.XLOOKUP(B19,ORÇAMENTO_EXECUTIVO!A$2:A$23,ORÇAMENTO_EXECUTIVO!B$2:B$23) -> 1739136.8 | D19: =C19/C$24 -> 220.74242 | E19: =FIXED(CÁLCULO_MÉDIAS!AH23,2,FALSE)&" "&"-"&FIXED(CÁLCULO_MÉDIAS!AI23,2,FALSE) -> 110,00 -140,00 | F19: Temos uma fachada bem imponente com pedras, diversificados porcelanatos, molduras em EPS, textura e pintura, onde eleva o custo das médias que temos | G19: =CÁLCULO_MÉDIAS!AH23 -> 110 | H19: =CÁLCULO_MÉDIAS!AI23 -> 140 | J19: {=_xlfn.IFS(D19>=H19,"FORA",D19>=G19,"DENTRO")} -> FORA | K19: *Temos uma fachada bem imponente com pedras, diversificados porcelanatos, molduras em EPS (muito detalhamento em moldura), textura e pintura, onde eleva o custo das médias que temos
B20: =ORÇAMENTO_PARCIAL!A17 -> SERVIÇOS COMPLEMENTARES | C20: =_xlfn.XLOOKUP(B20,ORÇAMENTO_EXECUTIVO!A$2:A$23,ORÇAMENTO_EXECUTIVO!B$2:B$23) -> 2306439.5 | D20: =C20/C$24 -> 292.74812 | E20: =FIXED(CÁLCULO_MÉDIAS!AH24,2,FALSE)&" "&"-"&FIXED(CÁLCULO_MÉDIAS!AI24,2,FALSE) -> 130,00 -200,00 | F20: Temos mais áreas com mobiliário que os demais empreendimentos, e o paisagismo é mais caro devido a area do pomar e outras areas verdes com arvores frutiferas e demais itens de jardinagem | G20: =CÁLCULO_MÉDIAS!AH24 -> 130 | H20: =CÁLCULO_MÉDIAS!AI24 -> 200 | J20: {=_xlfn.IFS(D20>=H20,"FORA",D20>=G20,"DENTRO")} -> FORA | K20: Temos mais áreas com mobiliário que os demais empreendimentos, e o paisagismo é mais caro devido a area do pomar e outras areas verdes com arvores frutiferas e demais itens de jardinagem
B21: TOTAL | C21: =SUM(C4:C20) -> 41993018 | D21: =SUM(D4:D20) -> 5330.0236 | E21: =FIXED(CÁLCULO_MÉDIAS!AH25,2,FALSE)&" "&"-"&FIXED(CÁLCULO_MÉDIAS!AI25,2,FALSE) -> 2.700,00 -3.870,00 | G21: =SUM(G4:G20) -> 2700 | H21: =SUM(H4:H20) -> 3870
C22: =IF(C21=ORÇAMENTO_EXECUTIVO!B27,"OKAY","REVER") -> OKAY
B24: ÁREA CONSTRUÍDA | C24: 7878.58 | D24: m²
B25: ÁREA TOTAL ATUALIZADA DO PARCIAL
D30: 1.1023
B32: 900,00 - 1100 | C32: 900
B33: 25,00 - 30,00 | C33: 25
B34: 15,00 - 22,00 | C34: 15
B35: 150,00 - 200,00 | C35: 150
B36: 440,00 - 510,00 | C36: 440
B37: -
B38: 55,00 - 70,00 | C38: 55
B39: 170,00 - 200,00 | C39: 170
B40: 165,00 - 230,00 | C40: 165
B41: 40,00 - 70,00 | C41: 40
B42: 55,00 - 77,00 | C42: 55
B43: 35,00 - 50,00 | C43: 35
B44: 130,00 - 175,00 | C44: 130
B45: 35,00 - 65,00 | C45: 35
B46: 35,00 - 55,00 | C46: 35
B47: 430,00 - 550,00 | C47: 430
B48: 35,00 - 50,00 | C48: 35
B49: 150,00 - 220,00 | C49: 150

Sheet CÁLCULO_MÉDIAS
C1: ÁREA CONST. | D1: 8366.5 | E1: ÁREA CONST. | F1: 7956.14 | G1: ÁREA CONST. | H1: 11653.22 | I1: ÁREA CONST. | J1: 11653.22 | K1: ÁREA CONST. | L1: 11653.22 | M1: ÁREA CONST. | N1: 6003.01 | O1: ÁREA CONST. | P1: 10520.39 | Q1: ÁREA CONST. | R1: 10661.12 | S1: ÁREA CONST. | T1: 18361.19 | U1: ÁREA CONST. | V1: 10661.12 | W1: ÁREA CONST. | X1: 6998.39 | Z1: 12953.8 | AA1: ÁREA CONST. | AB1: 16651.4 | AC1: ÁREA CONST. | AD1: 87048.41 | AE1: ÁREA CONST. | AF1: 13147.78
C2: CIDADE ESTADO | D2: Santa Catarina | E2: CIDADE ESTADO | F2: Santa Catarina | G2: CIDADE ESTADO | H2: ITAJAÍ - SC | I2: CIDADE ESTADO | J2: ITAJAÍ - SC | K2: CIDADE ESTADO | L2: ITAJAÍ - SC | M2: CIDADE ESTADO | O2: CIDADE ESTADO | Q2: CIDADE ESTADO | S2: CIDADE ESTADO | U2: CIDADE ESTADO | W2: CIDADE ESTADO | X2: CUB/SP R8-A | Y2: CIDADE ESTADO | AA2: CIDADE ESTADO | AC2: CIDADE ESTADO | AD2: MARINGA PR | AE2: CIDADE ESTADO
C3: DATA BASE | D3: 45108 | E3: DATA BASE | F3: 45047 | G3: DATA BASE | H3: 44652 | I3: DATA BASE | J3: 44652 | K3: DATA BASE | L3: 44652 | M3: DATA BASE | N3: 44958 | O3: DATA BASE | P3: 45047 | Q3: DATA BASE | R3: 45047 | S3: DATA BASE | T3: 44805 | U3: DATA BASE | V3: 45047 | W3: DATA BASE | X3: 45474 | Y3: DATA BASE | Z3: 45108 | AA3: DATA BASE | AB3: 45778 | AC3: DATA BASE | AD3: 45078 | AE3: DATA BASE | AF3: 45689
C4: CUB | D4: 2747.9 | E4: CUB | F4: 2680.84 | G4: CUB | H4: 2461.35 | I4: CUB | J4: 2461.35 | K4: CUB | L4: 2461.35 | M4: CUB | N4: 2662.47 | O4: CUB | P4: 2688.94 | Q4: CUB | R4: 2688.94 | S4: CUB | T4: 1850.46 | U4: CUB | V4: 2688.94 | W4: CUB | X4: 2362.18 | Y4: CUB | Z4: 2725.79 | AA4: CUB | AB4: 2923.52 | AC4: CUB | AD4: 2233.93 | AE4: CUB | AF4: 2907.85
X5: 36 MESES
C6: =UPPER("Amalfi - Maiori") -> AMALFI - MAIORI | E6: =UPPER("Passe - Celebretion") -> PASSE - CELEBRETION | G6: BARÃO DE ALBUQUERQUE | I6: BARÃO DE ALBUQUERQUE | K6: ONE PALACE | M6: DOM | O6: LIBERATO | Q6: CARRARO - VERTICE | S6: CARRARO - VERTICE | U6: INDEPY - STELLA MARINA | W6: CAIO PRADO - PARAMETRICO | Y6: COTA 365 | AA6: SÃO FRANCISCO | AC6: SPOTCO - 54 SQUARE PARAMETRICO | AE6: DLHON - ESTREITO | AH6: MÉDIAS
C7: VALOR / M2 | D7: INDEXADO | E7: VALOR / M2 | F7: INDEXADO | G7: VALOR / M2 | H7: INDEXADO | I7: VALOR / M2 | J7: INDEXADO | K7: VALOR / M2 | L7: INDEXADO | M7: VALOR / M2 | N7: INDEXADO | O7: VALOR / M2 | P7: INDEXADO | Q7: VALOR / M2 | R7: INDEXADO | S7: VALOR / M2 | T7: INDEXADO | U7: VALOR / M2 | V7: INDEXADO | W7: VALOR / M2 | X7: INDEXADO | Y7: VALOR / M2 | Z7: INDEXADO | AA7: VALOR / M2 | AB7: INDEXADO | AC7: VALOR / M2 | AD7: INDEXADO | AE7: VALOR / M2 | AF7: INDEXADO | AH7: MÍNIMA | AI7: MÁXIMA
B8: GERENCIAMENTO TECNICO E ADMINISTRATIVO | C8: 396.6908 | D8: =ORÇAMENTO_PARCIAL!$B$20/CÁLCULO_MÉDIAS!D$4*C8 -> 377.31316 | E8: 411.20643 | F8: =ORÇAMENTO_PARCIAL!$B$20/CÁLCULO_MÉDIAS!F$4*E8 -> 400.90342 | G8: 320.9214 | H8: =ORÇAMENTO_PARCIAL!$B$20/CÁLCULO_MÉDIAS!H$4*G8 -> 340.78154 | I8: 320.9214 | J8: =ORÇAMENTO_EXECUTIVO!$B$25/CÁLCULO_MÉDIAS!J$4*I8 -> 267.76503 | K8: 281.42632 | L8: =ORÇAMENTO_EXECUTIVO!$B$25/CÁLCULO_MÉDIAS!L$4*K8 -> 234.81178 | M8: 425.96974 | N8: =ORÇAMENTO_EXECUTIVO!$B$25/CÁLCULO_MÉDIAS!N$4*M8 -> 328.56596 | O8: 283.33076 | P8: =ORÇAMENTO_EXECUTIVO!$B$25/CÁLCULO_MÉDIAS!P$4*O8 -> 216.39198 | Q8: 474.82755 | R8: =ORÇAMENTO_EXECUTIVO!$B$25/CÁLCULO_MÉDIAS!R$4*Q8 -> 362.64637 | S8: 185.02756 | T8: =ORÇAMENTO_PARCIAL!$B$20/CÁLCULO_MÉDIAS!T$4*S8 -> 261.34095 | U8: 642.60182 | V8: =ORÇAMENTO_EXECUTIVO!$B$25/CÁLCULO_MÉDIAS!V$4*U8 -> 490.78285 | W8: 710.53791 | X8: =ORÇAMENTO_EXECUTIVO!$B$25/CÁLCULO_MÉDIAS!X$4*W8 -> 617.73586 | Y8: 247.43142 | Z8: =ORÇAMENTO_EXECUTIVO!$B$25/CÁLCULO_MÉDIAS!Z$4*Y8 -> 186.41936 | AA8: ='[5]Obra '!$E$33 -> 201.31099 | AB8: =ORÇAMENTO_EXECUTIVO!$B$25/CÁLCULO_MÉDIAS!AB$4*AA8 -> 141.4132 | AC8: ='[6]Orçamento Resumo TOTAL'!$F$15/AD1 -> 359.74533 | AD8: =ORÇAMENTO_EXECUTIVO!$B$25/CÁLCULO_MÉDIAS!AD$4*AC8 -> 330.71519 | AE8: 291.25537 | AF8: =ORÇAMENTO_EXECUTIVO!$B$25/CÁLCULO_MÉDIAS!AF$4*AE8 -> 205.6982 | AH8: 200 | AI8: 550
B9: MOVIMENTAÇÃO DE TERRA | C9: 7.3706615 | D9: =ORÇAMENTO_PARCIAL!$B$20/CÁLCULO_MÉDIAS!D$4*C9 -> 7.0106179 | E9: 12.392262 | F9: =ORÇAMENTO_PARCIAL!$B$20/CÁLCULO_MÉDIAS!F$4*E9 -> 12.081767 | G9: 5.6355099 | H9: =ORÇAMENTO_PARCIAL!$B$20/CÁLCULO_MÉDIAS!H$4*G9 -> 5.984262 | I9: 5.6355099 | J9: =ORÇAMENTO_EXECUTIVO!$B$25/CÁLCULO_MÉDIAS!J$4*I9 -> 4.7020624 | K9: 6.2112129 | L9: =ORÇAMENTO_EXECUTIVO!$B$25/CÁLCULO_MÉDIAS!L$4*K9 -> 5.1824078 | M9: 19.58779 | N9: =ORÇAMENTO_EXECUTIVO!$B$25/CÁLCULO_MÉDIAS!N$4*M9 -> 15.108775 | P9: =ORÇAMENTO_EXECUTIVO!$B$25/CÁLCULO_MÉDIAS!P$4*O9 -> 0 | Q9: 17.922887 | R9: =ORÇAMENTO_EXECUTIVO!$B$25/CÁLCULO_MÉDIAS!R$4*Q9 -> 13.688486 | S9: 38.035008 | T9: =ORÇAMENTO_PARCIAL!$B$20/CÁLCULO_MÉDIAS!T$4*S9 -> 53.722295 | U9: 25.933991 | V9: =ORÇAMENTO_EXECUTIVO!$B$25/CÁLCULO_MÉDIAS!V$4*U9 -> 19.806913 | W9: 73.76612 | X9: =ORÇAMENTO_EXECUTIVO!$B$25/CÁLCULO_MÉDIAS!X$4*W9 -> 64.131662 | Y9: 51.128998 | Z9: =ORÇAMENTO_EXECUTIVO!$B$25/CÁLCULO_MÉDIAS!Z$4*Y9 -> 38.521521 | AA9: ='[5]Obra '!$E$34 -> 87.687827 | AB9: =ORÇAMENTO_EXECUTIVO!$B$25/CÁLCULO_MÉDIAS!AB$4*AA9 -> 61.597315 | AC9: ='[6]Orçamento Resumo TOTAL'!$F$18/AD1 -> 51.853028 | AD9: =ORÇAMENTO_EXECUTIVO!$B$25/CÁLCULO_MÉDIAS!AD$4*AC9 -> 47.668678 | AE9: 61.282508 | AF9: =ORÇAMENTO_EXECUTIVO!$B$25/CÁLCULO_MÉDIAS!AF$4*AE9 -> 43.28058 | AH9: 65 | AI9: 75
B10: INFRAESTRUTURA | C10: 176.61774 | D10: =ORÇAMENTO_PARCIAL!$B$20/CÁLCULO_MÉDIAS!D$4*C10 -> 167.99028 | E10: 236.7796 | F10: =ORÇAMENTO_PARCIAL!$B$20/CÁLCULO_MÉDIAS!F$4*E10 -> 230.84695 | G10: 124.41721 | H10: =ORÇAMENTO_PARCIAL!$B$20/CÁLCULO_MÉDIAS!H$4*G10 -> 132.11674 | I10: 124.41721 | J10: =ORÇAMENTO_EXECUTIVO!$B$25/CÁLCULO_MÉDIAS!J$4*I10 -> 103.80915 | K10: 113.54018 | L10: =ORÇAMENTO_EXECUTIVO!$B$25/CÁLCULO_MÉDIAS!L$4*K10 -> 94.733752 | M10: 195.5904 | N10: =ORÇAMENTO_EXECUTIVO!$B$25/CÁLCULO_MÉDIAS!N$4*M10 -> 150.86599 | O10: 171.5507 | P10: =ORÇAMENTO_EXECUTIVO!$B$25/CÁLCULO_MÉDIAS!P$4*O10 -> 131.0207 | Q10: 249.26683 | R10: =ORÇAMENTO_EXECUTIVO!$B$25/CÁLCULO_MÉDIAS!R$4*Q10 -> 190.37588 | S10: =115.924826223137+222.621707525493 -> 338.54653 | T10: =ORÇAMENTO_PARCIAL!$B$20/CÁLCULO_MÉDIAS!T$4*S10 -> 478.17781 | U10: 259.10279 | V10: =ORÇAMENTO_EXECUTIVO!$B$25/CÁLCULO_MÉDIAS!V$4*U10 -> 197.88803 | W10: 720.52059 | X10: =ORÇAMENTO_EXECUTIVO!$B$25/CÁLCULO_MÉDIAS!X$4*W10 -> 626.41471 | Y10: 136.27317 | Z10: =ORÇAMENTO_EXECUTIVO!$B$25/CÁLCULO_MÉDIAS!Z$4*Y10 -> 102.6707 | AA10: 123.88195 | AB10: =ORÇAMENTO_EXECUTIVO!$B$25/CÁLCULO_MÉDIAS!AB$4*AA10 -> 87.022289 | AC10: ='[6]Orçamento Resumo TOTAL'!$F$25/AD1 -> 196.55047 | AD10: =ORÇAMENTO_EXECUTIVO!$B$25/CÁLCULO_MÉDIAS!AD$4*AC10 -> 180.68957 | AE10: 269.65361 | AF10: =ORÇAMENTO_EXECUTIVO!$B$25/CÁLCULO_MÉDIAS!AF$4*AE10 -> 190.44202 | AH10: 130 | AI10: 210
B11: CONTENÇÃO | C11: 581.74946 | G11: 617.18899 | I11: 617.18899 | W11: 40.372428 | X11: =ORÇAMENTO_EXECUTIVO!$B$25/CÁLCULO_MÉDIAS!X$4*W11 -> 35.099459 | Y11: 201.1607 | Z11: =ORÇAMENTO_EXECUTIVO!$B$25/CÁLCULO_MÉDIAS!Z$4*Y11 -> 151.55815 | AA11: ='[5]Obra '!$E$36 -> 125.72357 | AB11: =ORÇAMENTO_EXECUTIVO!$B$25/CÁLCULO_MÉDIAS!AB$4*AA11 -> 88.315957 | AC11: ='[6]Orçamento Resumo TOTAL'!$F$37/AD1 -> 46.785711 | AD11: =ORÇAMENTO_EXECUTIVO!$B$25/CÁLCULO_MÉDIAS!AD$4*AC11 -> 43.010275 | AE11: 95.264377 | AF11: =ORÇAMENTO_EXECUTIVO!$B$25/CÁLCULO_MÉDIAS!AF$4*AE11 -> 67.280169 | AH11: 50 | AI11: 90
B12: SUPRAESTRUTURA | C12: 581.74946 | D12: =ORÇAMENTO_PARCIAL!$B$20/CÁLCULO_MÉDIAS!D$4*C12 -> 553.33204 | E12: 761.96986 | F12: =ORÇAMENTO_PARCIAL!$B$20/CÁLCULO_MÉDIAS!F$4*E12 -> 742.87826 | G12: 617.18899 | H12: =ORÇAMENTO_PARCIAL!$B$20/CÁLCULO_MÉDIAS!H$4*G12 -> 655.38356 | I12: 617.18899 | J12: =ORÇAMENTO_EXECUTIVO!$B$25/CÁLCULO_MÉDIAS!J$4*I12 -> 514.95981 | K12: 640.53849 | L12: =ORÇAMENTO_EXECUTIVO!$B$25/CÁLCULO_MÉDIAS!L$4*K12 -> 534.44178 | M12: 730.88829 | N12: =ORÇAMENTO_EXECUTIVO!$B$25/CÁLCULO_MÉDIAS!N$4*M12 -> 563.76074 | O12: 648.94588 | P12: =ORÇAMENTO_EXECUTIVO!$B$25/CÁLCULO_MÉDIAS!P$4*O12 -> 495.62809 | Q12: 802.98214 | R12: =ORÇAMENTO_EXECUTIVO!$B$25/CÁLCULO_MÉDIAS!R$4*Q12 -> 613.27226 | S12: 697.81371 | T12: =ORÇAMENTO_PARCIAL!$B$20/CÁLCULO_MÉDIAS!T$4*S12 -> 985.62236 | U12: 697.55082 | V12: =ORÇAMENTO_EXECUTIVO!$B$25/CÁLCULO_MÉDIAS!V$4*U12 -> 532.74979 | W12: 792.42091 | X12: =ORÇAMENTO_EXECUTIVO!$B$25/CÁLCULO_MÉDIAS!X$4*W12 -> 688.92426 | Y12: 540.46493 | Z12: =ORÇAMENTO_EXECUTIVO!$B$25/CÁLCULO_MÉDIAS!Z$4*Y12 -> 407.19616 | AA12: ='[5]Obra '!$E$37 -> 317.78492 | AB12: =ORÇAMENTO_EXECUTIVO!$B$25/CÁLCULO_MÉDIAS!AB$4*AA12 -> 223.23165 | AC12: ='[6]Orçamento Resumo TOTAL'!$F$52/AD1 -> 616.6117 | AD12: =ORÇAMENTO_EXECUTIVO!$B$25/CÁLCULO_MÉDIAS!AD$4*AC12 -> 566.85338 | AE12: 717.95947 | AF12: =ORÇAMENTO_EXECUTIVO!$B$25/CÁLCULO_MÉDIAS!AF$4*AE12 -> 507.05664 | AH12: 680 | AI12: 750
B13: ALVENARIA | C13: 114.48087 | D13: =ORÇAMENTO_PARCIAL!$B$20/CÁLCULO_MÉDIAS!D$4*C13 -> 108.88869 | E13: 161.08825 | F13: =ORÇAMENTO_PARCIAL!$B$20/CÁLCULO_MÉDIAS!F$4*E13 -> 157.05209 | G13: 108.56391 | H13: =ORÇAMENTO_PARCIAL!$B$20/CÁLCULO_MÉDIAS!H$4*G13 -> 115.28236 | I13: 108.56391 | J13: =ORÇAMENTO_EXECUTIVO!$B$25/CÁLCULO_MÉDIAS!J$4*I13 -> 90.581735 | K13: 124.50957 | L13: =ORÇAMENTO_EXECUTIVO!$B$25/CÁLCULO_MÉDIAS!L$4*K13 -> 103.88621 | M13: 119.11837 | N13: =ORÇAMENTO_EXECUTIVO!$B$25/CÁLCULO_MÉDIAS!N$4*M13 -> 91.880337 | O13: 146.27237 | P13: =ORÇAMENTO_EXECUTIVO!$B$25/CÁLCULO_MÉDIAS!P$4*O13 -> 111.71455 | Q13: 134.55317 | R13: =ORÇAMENTO_EXECUTIVO!$B$25/CÁLCULO_MÉDIAS!R$4*Q13 -> 102.76409 | S13: 233.94566 | T13: =ORÇAMENTO_PARCIAL!$B$20/CÁLCULO_MÉDIAS!T$4*S13 -> 330.435 | U13: 137.77401 | V13: =ORÇAMENTO_EXECUTIVO!$B$25/CÁLCULO_MÉDIAS!V$4*U13 -> 105.22398 | W13: 197.6051 | X13: =ORÇAMENTO_EXECUTIVO!$B$25/CÁLCULO_MÉDIAS!X$4*W13 -> 171.79626 | Y13: 140.34965 | Z13: =ORÇAMENTO_EXECUTIVO!$B$25/CÁLCULO_MÉDIAS!Z$4*Y13 -> 105.74199 | AA13: ='[5]Obra '!$E$38 -> 205.78126 | AB13: =ORÇAMENTO_EXECUTIVO!$B$25/CÁLCULO_MÉDIAS!AB$4*AA13 -> 144.5534 | AC13: ='[6]Orçamento Resumo TOTAL'!$F$68/AD1 -> 116.06025 | AD13: =ORÇAMENTO_EXECUTIVO!$B$25/CÁLCULO_MÉDIAS!AD$4*AC13 -> 106.69462 | AE13: 153.02854 | AF13: =ORÇAMENTO_EXECUTIVO!$B$25/CÁLCULO_MÉDIAS!AF$4*AE13 -> 108.07593 | AH13: 120 | AI13: 180
B14: INSTALAÇÕES ELÉTRICAS, HIDRÁULICAS, GLP E PREVENTIVAS | C14: 295.45929 | D14: =ORÇAMENTO_PARCIAL!$B$20/CÁLCULO_MÉDIAS!D$4*C14 -> 281.02663 | E14: 310.24178 | F14: =ORÇAMENTO_PARCIAL!$B$20/CÁLCULO_MÉDIAS!F$4*E14 -> 302.46849 | G14: 266.66808 | H14: =ORÇAMENTO_PARCIAL!$B$20/CÁLCULO_MÉDIAS!H$4*G14 -> 283.17076 | I14: 266.66808 | J14: =ORÇAMENTO_EXECUTIVO!$B$25/CÁLCULO_MÉDIAS!J$4*I14 -> 222.49805 | K14: 333.98698 | L14: =ORÇAMENTO_EXECUTIVO!$B$25/CÁLCULO_MÉDIAS!L$4*K14 -> 278.66646 | M14: 311.09537 | N14: =ORÇAMENTO_EXECUTIVO!$B$25/CÁLCULO_MÉDIAS!N$4*M14 -> 239.95918 | O14: 273.47993 | P14: =ORÇAMENTO_EXECUTIVO!$B$25/CÁLCULO_MÉDIAS!P$4*O14 -> 208.86847 | Q14: 303.34022 | R14: =ORÇAMENTO_EXECUTIVO!$B$25/CÁLCULO_MÉDIAS!R$4*Q14 -> 231.67407 | S14: 787.21827 | T14: =ORÇAMENTO_PARCIAL!$B$20/CÁLCULO_MÉDIAS!T$4*S14 -> 1111.9012 | U14: 432.96627 | V14: =ORÇAMENTO_EXECUTIVO!$B$25/CÁLCULO_MÉDIAS!V$4*U14 -> 330.6751 | W14: 367.95 | X14: =ORÇAMENTO_EXECUTIVO!$B$25/CÁLCULO_MÉDIAS!X$4*W14 -> 319.89272 | Y14: 371.77074 | Z14: =ORÇAMENTO_EXECUTIVO!$B$25/CÁLCULO_MÉDIAS!Z$4*Y14 -> 280.09887 | AA14: ='[5]Obra '!$E$39+'[5]Obra '!$E$48 -> 293.56516 | AB14: =ORÇAMENTO_EXECUTIVO!$B$25/CÁLCULO_MÉDIAS!AB$4*AA14 -> 206.2182 | AC14: ='[6]Orçamento Resumo TOTAL'!$F$76/AD1 -> 321.21228 | AD14: =ORÇAMENTO_EXECUTIVO!$B$25/CÁLCULO_MÉDIAS!AD$4*AC14 -> 295.29162 | AE14: 408.65 | AF14: =ORÇAMENTO_EXECUTIVO!$B$25/CÁLCULO_MÉDIAS!AF$4*AE14 -> 288.60779 | AH14: 270 | AI14: 360
B15: EQUIPAMENTOS E SISTEMAS ESPECIAIS | C15: 159.28357 | D15: =ORÇAMENTO_PARCIAL!$B$20/CÁLCULO_MÉDIAS!D$4*C15 -> 151.50285 | E15: 254.66366 | F15: =ORÇAMENTO_PARCIAL!$B$20/CÁLCULO_MÉDIAS!F$4*E15 -> 248.28292 | G15: 192.58192 | H15: =ORÇAMENTO_PARCIAL!$B$20/CÁLCULO_MÉDIAS!H$4*G15 -> 204.49981 | I15: 192.58192 | J15: =ORÇAMENTO_EXECUTIVO!$B$25/CÁLCULO_MÉDIAS!J$4*I15 -> 160.68328 | K15: 187.87175 | L15: =ORÇAMENTO_EXECUTIVO!$B$25/CÁLCULO_MÉDIAS!L$4*K15 -> 156.75329 | M15: 234.95757 | N15: =ORÇAMENTO_EXECUTIVO!$B$25/CÁLCULO_MÉDIAS!N$4*M15 -> 181.23132 | O15: 153.14326 | P15: =ORÇAMENTO_EXECUTIVO!$B$25/CÁLCULO_MÉDIAS!P$4*O15 -> 116.96214 | Q15: 194.75231 | R15: =ORÇAMENTO_EXECUTIVO!$B$25/CÁLCULO_MÉDIAS!R$4*Q15 -> 148.74078 | S15: 126.32497 | T15: =ORÇAMENTO_PARCIAL!$B$20/CÁLCULO_MÉDIAS!T$4*S15 -> 178.42687 | U15: 246.70509 | V15: =ORÇAMENTO_EXECUTIVO!$B$25/CÁLCULO_MÉDIAS!V$4*U15 -> 188.41937 | W15: 349.34294 | X15: =ORÇAMENTO_EXECUTIVO!$B$25/CÁLCULO_MÉDIAS!X$4*W15 -> 303.7159 | Y15: 92.011847 | Z15: =ORÇAMENTO_EXECUTIVO!$B$25/CÁLCULO_MÉDIAS!Z$4*Y15 -> 69.323407 | AA15: ='[5]Obra '!$E$40+'[5]Obra '!$E$49 -> 189.62771 | AB15: =ORÇAMENTO_EXECUTIVO!$B$25/CÁLCULO_MÉDIAS!AB$4*AA15 -> 133.20615 | AC15: ='[6]Orçamento Resumo TOTAL'!$F$98/AD1 -> 305.01235 | AD15: =ORÇAMENTO_EXECUTIVO!$B$25/CÁLCULO_MÉDIAS!AD$4*AC15 -> 280.39896 | AE15: 167.82665 | AF15: =ORÇAMENTO_EXECUTIVO!$B$25/CÁLCULO_MÉDIAS!AF$4*AE15 -> 118.52705 | AH15: 180 | AI15: 270 | AJ15: Em SP é mais caro
B16: IMPERMEABILIZAÇÃO | C16: 64.527967 | D16: =ORÇAMENTO_PARCIAL!$B$20/CÁLCULO_MÉDIAS!D$4*C16 -> 61.375891 | E16: 48.175292 | F16: =ORÇAMENTO_PARCIAL!$B$20/CÁLCULO_MÉDIAS!F$4*E16 -> 46.968232 | G16: 25.029614 | H16: =ORÇAMENTO_PARCIAL!$B$20/CÁLCULO_MÉDIAS!H$4*G16 -> 26.578565 | I16: 25.029614 | J16: =ORÇAMENTO_EXECUTIVO!$B$25/CÁLCULO_MÉDIAS!J$4*I16 -> 20.88379 | K16: 16.045568 | L16: =ORÇAMENTO_EXECUTIVO!$B$25/CÁLCULO_MÉDIAS!L$4*K16 -> 13.387832 | M16: 40.38554 | N16: =ORÇAMENTO_EXECUTIVO!$B$25/CÁLCULO_MÉDIAS!N$4*M16 -> 31.150837 | O16: 69.707842 | P16: =ORÇAMENTO_EXECUTIVO!$B$25/CÁLCULO_MÉDIAS!P$4*O16 -> 53.2389 | Q16: 41.405575 | R16: =ORÇAMENTO_EXECUTIVO!$B$25/CÁLCULO_MÉDIAS!R$4*Q16 -> 31.623232 | S16: 91.988918 | T16: =ORÇAMENTO_PARCIAL!$B$20/CÁLCULO_MÉDIAS!T$4*S16 -> 129.92914 | U16: 66.311564 | V16: =ORÇAMENTO_EXECUTIVO!$B$25/CÁLCULO_MÉDIAS!V$4*U16 -> 50.645015 | W16: 70.028598 | X16: =ORÇAMENTO_EXECUTIVO!$B$25/CÁLCULO_MÉDIAS!X$4*W16 -> 60.882291 | Y16: 27.458809 | Z16: =ORÇAMENTO_EXECUTIVO!$B$25/CÁLCULO_MÉDIAS!Z$4*Y16 -> 20.687969 | AA16: ='[5]Obra '!$E$43 -> 39.802467 | AB16: =ORÇAMENTO_EXECUTIVO!$B$25/CÁLCULO_MÉDIAS!AB$4*AA16 -> 27.959697 | AC16: ='[6]Orçamento Resumo TOTAL'!$F$119/AD1 -> 107.88859 | AD16: =ORÇAMENTO_EXECUTIVO!$B$25/CÁLCULO_MÉDIAS!AD$4*AC16 -> 99.182372 | AE16: 89.458184 | AF16: =ORÇAMENTO_EXECUTIVO!$B$25/CÁLCULO_MÉDIAS!AF$4*AE16 -> 63.179564 | AH16: 60 | AI16: 80
B17: REVESTIMENTOS INTERNOS EM PISO E PAREDE | C17: 196.03001 | D17: =ORÇAMENTO_PARCIAL!$B$20/CÁLCULO_MÉDIAS!D$4*C17 -> 186.45429 | E17: 120.22823 | F17: =ORÇAMENTO_PARCIAL!$B$20/CÁLCULO_MÉDIAS!F$4*E17 -> 117.21584 | G17: 93.008633 | H17: =ORÇAMENTO_PARCIAL!$B$20/CÁLCULO_MÉDIAS!H$4*G17 -> 98.764448 | I17: 93.008633 | J17: =ORÇAMENTO_EXECUTIVO!$B$25/CÁLCULO_MÉDIAS!J$4*I17 -> 77.602986 | K17: 115.30953 | L17: =ORÇAMENTO_EXECUTIVO!$B$25/CÁLCULO_MÉDIAS!L$4*K17 -> 96.210032 | M17: 171.46501 | N17: =ORÇAMENTO_EXECUTIVO!$B$25/CÁLCULO_MÉDIAS!N$4*M17 -> 132.2572 | O17: 152.31227 | P17: =ORÇAMENTO_EXECUTIVO!$B$25/CÁLCULO_MÉDIAS!P$4*O17 -> 116.32748 | Q17: 201.48799 | R17: =ORÇAMENTO_EXECUTIVO!$B$25/CÁLCULO_MÉDIAS!R$4*Q17 -> 153.88511 | S17: 103.79828 | T17: =ORÇAMENTO_PARCIAL!$B$20/CÁLCULO_MÉDIAS!T$4*S17 -> 146.6092 | U17: 175.27527 | V17: =ORÇAMENTO_EXECUTIVO!$B$25/CÁLCULO_MÉDIAS!V$4*U17 -> 133.86532 | W17: 283.26464 | X17: =ORÇAMENTO_EXECUTIVO!$B$25/CÁLCULO_MÉDIAS!X$4*W17 -> 246.26796 | Y17: 135.75045 | Z17: =ORÇAMENTO_EXECUTIVO!$B$25/CÁLCULO_MÉDIAS!Z$4*Y17 -> 102.27687 | AA17: =([5]Ger_Executivo!$N$196+[5]Ger_Executivo!$N$203+[5]Ger_Executivo!$N$173+[5]Ger_Executivo!$N$175)/AB1 -> 70.550745 | AB17: =ORÇAMENTO_EXECUTIVO!$B$25/CÁLCULO_MÉDIAS!AB$4*AA17 -> 49.559176 | AC17: ='[6]Orçamento Resumo TOTAL'!$F$130/AD1 -> 152.7249 | AD17: =ORÇAMENTO_EXECUTIVO!$B$25/CÁLCULO_MÉDIAS!AD$4*AC17 -> 140.40056 | AE17: 240.39218 | AF17: =ORÇAMENTO_EXECUTIVO!$B$25/CÁLCULO_MÉDIAS!AF$4*AE17 -> 169.77622 | AH17: 120 | AI17: 170
B18: REVESTIMENTOS E ACABAMENTOS INTERNOS EM TETO | C18: 57.701689 | D18: =ORÇAMENTO_PARCIAL!$B$20/CÁLCULO_MÉDIAS!D$4*C18 -> 54.883065 | E18: 60.615435 | F18: =ORÇAMENTO_PARCIAL!$B$20/CÁLCULO_MÉDIAS!F$4*E18 -> 59.096681 | G18: 68.03556 | H18: =ORÇAMENTO_PARCIAL!$B$20/CÁLCULO_MÉDIAS!H$4*G18 -> 72.245923 | I18: 68.03556 | J18: =ORÇAMENTO_EXECUTIVO!$B$25/CÁLCULO_MÉDIAS!J$4*I18 -> 56.766372 | K18: 56.158883 | L18: =ORÇAMENTO_EXECUTIVO!$B$25/CÁLCULO_MÉDIAS!L$4*K18 -> 46.856909 | M18: 82.252956 | N18: =ORÇAMENTO_EXECUTIVO!$B$25/CÁLCULO_MÉDIAS!N$4*M18 -> 63.444699 | O18: 54.81864 | P18: =ORÇAMENTO_EXECUTIVO!$B$25/CÁLCULO_MÉDIAS!P$4*O18 -> 41.867371 | Q18: 48.025603 | R18: =ORÇAMENTO_EXECUTIVO!$B$25/CÁLCULO_MÉDIAS!R$4*Q18 -> 36.679234 | S18: 74.689276 | T18: =ORÇAMENTO_PARCIAL!$B$20/CÁLCULO_MÉDIAS!T$4*S18 -> 105.49437 | U18: 49.583491 | V18: =ORÇAMENTO_EXECUTIVO!$B$25/CÁLCULO_MÉDIAS!V$4*U18 -> 37.869061 | W18: 53.645363 | X18: =ORÇAMENTO_EXECUTIVO!$B$25/CÁLCULO_MÉDIAS!X$4*W18 -> 46.638841 | Y18: 48.843612 | Z18: =ORÇAMENTO_EXECUTIVO!$B$25/CÁLCULO_MÉDIAS!Z$4*Y18 -> 36.79967 | AA18: ='[5]Obra '!$E$42 -> 47.851283 | AB18: =ORÇAMENTO_EXECUTIVO!$B$25/CÁLCULO_MÉDIAS!AB$4*AA18 -> 33.61368 | AC18: ='[6]Orçamento Resumo TOTAL'!$F$159/AD1 -> 68.2687 | AD18: =ORÇAMENTO_EXECUTIVO!$B$25/CÁLCULO_MÉDIAS!AD$4*AC18 -> 62.759665 | AE18: 69.739222 | AF18: =ORÇAMENTO_EXECUTIVO!$B$25/CÁLCULO_MÉDIAS!AF$4*AE18 -> 49.253108 | AH18: 55 | AI18: 80
B19: ACABAMENTOS EM PISO E PAREDE | C19: 133.46558 | D19: =ORÇAMENTO_PARCIAL!$B$20/CÁLCULO_MÉDIAS!D$4*C19 -> 126.94603 | E19: 180.49982 | F19: =ORÇAMENTO_PARCIAL!$B$20/CÁLCULO_MÉDIAS!F$4*E19 -> 175.97729 | G19: 149.11808 | H19: =ORÇAMENTO_PARCIAL!$B$20/CÁLCULO_MÉDIAS!H$4*G19 -> 158.34621 | I19: 149.11808 | J19: =ORÇAMENTO_EXECUTIVO!$B$25/CÁLCULO_MÉDIAS!J$4*I19 -> 124.41864 | K19: 173.07743 | L19: =ORÇAMENTO_EXECUTIVO!$B$25/CÁLCULO_MÉDIAS!L$4*K19 -> 144.40945 | M19: 171.08275 | N19: =ORÇAMENTO_EXECUTIVO!$B$25/CÁLCULO_MÉDIAS!N$4*M19 -> 131.96235 | O19: 210.03147 | P19: =ORÇAMENTO_EXECUTIVO!$B$25/CÁLCULO_MÉDIAS!P$4*O19 -> 160.41014 | Q19: 148.92818 | R19: =ORÇAMENTO_EXECUTIVO!$B$25/CÁLCULO_MÉDIAS!R$4*Q19 -> 113.7429 | S19: 162.73194 | T19: =ORÇAMENTO_PARCIAL!$B$20/CÁLCULO_MÉDIAS!T$4*S19 -> 229.84965 | U19: 187.31479 | V19: =ORÇAMENTO_EXECUTIVO!$B$25/CÁLCULO_MÉDIAS!V$4*U19 -> 143.06042 | W19: 85.206158 | X19: =ORÇAMENTO_EXECUTIVO!$B$25/CÁLCULO_MÉDIAS!X$4*W19 -> 74.077538 | Y19: 232.61725 | Z19: =ORÇAMENTO_EXECUTIVO!$B$25/CÁLCULO_MÉDIAS!Z$4*Y19 -> 175.25809 | AA19: ='[5]Obra '!$E$45+'[5]Obra '!$E$41-AA17 -> 13.54089 | AB19: =ORÇAMENTO_EXECUTIVO!$B$25/CÁLCULO_MÉDIAS!AB$4*AA19 -> 9.5119525 | AC19: ='[6]Orçamento Resumo TOTAL'!$F$140/AD1 -> 211.54995 | AD19: =ORÇAMENTO_EXECUTIVO!$B$25/CÁLCULO_MÉDIAS!AD$4*AC19 -> 194.47864 | AE19: 180.83378 | AF19: =ORÇAMENTO_EXECUTIVO!$B$25/CÁLCULO_MÉDIAS!AF$4*AE19 -> 127.71329 | AH19: 150 | AI19: 200
B20: PINTURA INTERNA | C20: 136.67845 | D20: =ORÇAMENTO_PARCIAL!$B$20/CÁLCULO_MÉDIAS!D$4*C20 -> 130.00195 | E20: 114.52019 | F20: =ORÇAMENTO_PARCIAL!$B$20/CÁLCULO_MÉDIAS!F$4*E20 -> 111.65082 | G20: 105.18524 | H20: =ORÇAMENTO_PARCIAL!$B$20/CÁLCULO_MÉDIAS!H$4*G20 -> 111.6946 | I20: 105.18524 | J20: =ORÇAMENTO_EXECUTIVO!$B$25/CÁLCULO_MÉDIAS!J$4*I20 -> 87.762702 | K20: 88.941826 | L20: =ORÇAMENTO_EXECUTIVO!$B$25/CÁLCULO_MÉDIAS!L$4*K20 -> 74.209791 | M20: 131.71985 | N20: =ORÇAMENTO_EXECUTIVO!$B$25/CÁLCULO_MÉDIAS!N$4*M20 -> 101.60031 | O20: 125.38088 | P20: =ORÇAMENTO_EXECUTIVO!$B$25/CÁLCULO_MÉDIAS!P$4*O20 -> 95.758815 | Q20: 177.37605 | R20: =ORÇAMENTO_EXECUTIVO!$B$25/CÁLCULO_MÉDIAS!R$4*Q20 -> 135.46977 | S20: 79.382525 | T20: =ORÇAMENTO_PARCIAL!$B$20/CÁLCULO_MÉDIAS!T$4*S20 -> 112.12332 | U20: 119.98279 | V20: =ORÇAMENTO_EXECUTIVO!$B$25/CÁLCULO_MÉDIAS!V$4*U20 -> 91.636052 | W20: 158.76784 | X20: =ORÇAMENTO_EXECUTIVO!$B$25/CÁLCULO_MÉDIAS!X$4*W20 -> 138.03146 | Y20: 58.704825 | Z20: =ORÇAMENTO_EXECUTIVO!$B$25/CÁLCULO_MÉDIAS!Z$4*Y20 -> 44.229288 | AA20: ='[5]Obra '!$E$45 -> 38.489501 | AB20: =ORÇAMENTO_EXECUTIVO!$B$25/CÁLCULO_MÉDIAS!AB$4*AA20 -> 27.03739 | AC20: ='[6]Orçamento Resumo TOTAL'!$F$165/AD1 -> 115.81815 | AD20: =ORÇAMENTO_EXECUTIVO!$B$25/CÁLCULO_MÉDIAS!AD$4*AC20 -> 106.47205 | AE20: 189.67808 | AF20: =ORÇAMENTO_EXECUTIVO!$B$25/CÁLCULO_MÉDIAS!AF$4*AE20 -> 133.95955 | AH20: 120 | AI20: 140
B21: ESQUADRIAS, VIDROS E FERRAGENS | C21: 334.09739 | D21: =ORÇAMENTO_PARCIAL!$B$20/CÁLCULO_MÉDIAS!D$4*C21 -> 317.77733 | E21: 245.72947 | F21: =ORÇAMENTO_PARCIAL!$B$20/CÁLCULO_MÉDIAS!F$4*E21 -> 239.57258 | G21: 236.04487 | H21: =ORÇAMENTO_PARCIAL!$B$20/CÁLCULO_MÉDIAS!H$4*G21 -> 250.65245 | I21: 236.04487 | J21: =ORÇAMENTO_EXECUTIVO!$B$25/CÁLCULO_MÉDIAS!J$4*I21 -> 196.94717 | K21: 227.17269 | L21: =ORÇAMENTO_EXECUTIVO!$B$25/CÁLCULO_MÉDIAS!L$4*K21 -> 189.54454 | M21: 323.47432 | N21: =ORÇAMENTO_EXECUTIVO!$B$25/CÁLCULO_MÉDIAS!N$4*M21 -> 249.50751 | O21: 243.33429 | P21: =ORÇAMENTO_EXECUTIVO!$B$25/CÁLCULO_MÉDIAS!P$4*O21 -> 185.84495 | Q21: 208.12266 | R21: =ORÇAMENTO_EXECUTIVO!$B$25/CÁLCULO_MÉDIAS!R$4*Q21 -> 158.95229 | S21: 195.99041 | T21: =ORÇAMENTO_PARCIAL!$B$20/CÁLCULO_MÉDIAS!T$4*S21 -> 276.82537 | U21: 451.21593 | V21: =ORÇAMENTO_EXECUTIVO!$B$25/CÁLCULO_MÉDIAS!V$4*U21 -> 344.61316 | W21: 417.17082 | X21: =ORÇAMENTO_EXECUTIVO!$B$25/CÁLCULO_MÉDIAS!X$4*W21 -> 362.68491 | Y21: 298.16274 | Z21: =ORÇAMENTO_EXECUTIVO!$B$25/CÁLCULO_MÉDIAS!Z$4*Y21 -> 224.64126 | AA21: ='[5]Obra '!$E$47 -> 360.94373 | AB21: =ORÇAMENTO_EXECUTIVO!$B$25/CÁLCULO_MÉDIAS!AB$4*AA21 -> 253.54904 | AC21: ='[6]Orçamento Resumo TOTAL'!$F$171/AD1 -> 360.83269 | AD21: =ORÇAMENTO_EXECUTIVO!$B$25/CÁLCULO_MÉDIAS!AD$4*AC21 -> 331.71481 | AE21: 510.68355 | AF21: =ORÇAMENTO_EXECUTIVO!$B$25/CÁLCULO_MÉDIAS!AF$4*AE21 -> 360.66867 | AH21: 250 | AI21: 360
B22: COBERTURA | C22: 14.756748 | D22: =ORÇAMENTO_PARCIAL!$B$20/CÁLCULO_MÉDIAS!D$4*C22 -> 14.035907 | E22: 15.647632 | F22: =ORÇAMENTO_PARCIAL!$B$20/CÁLCULO_MÉDIAS!F$4*E22 -> 15.255571 | G22: 4.7387028 | H22: =ORÇAMENTO_PARCIAL!$B$20/CÁLCULO_MÉDIAS!H$4*G22 -> 5.0319561 | I22: 4.7387028 | J22: =ORÇAMENTO_EXECUTIVO!$B$25/CÁLCULO_MÉDIAS!J$4*I22 -> 3.9537995 | K22: 1.815167 | L22: =ORÇAMENTO_EXECUTIVO!$B$25/CÁLCULO_MÉDIAS!L$4*K22 -> 1.5145086 | M22: 5.0049675 | N22: =ORÇAMENTO_EXECUTIVO!$B$25/CÁLCULO_MÉDIAS!N$4*M22 -> 3.8605136 | O22: 12.639948 | P22: =ORÇAMENTO_EXECUTIVO!$B$25/CÁLCULO_MÉDIAS!P$4*O22 -> 9.6536758 | Q22: 13.493334 | R22: =ORÇAMENTO_EXECUTIVO!$B$25/CÁLCULO_MÉDIAS!R$4*Q22 -> 10.305444 | S22: 20.013602 | T22: =ORÇAMENTO_PARCIAL!$B$20/CÁLCULO_MÉDIAS!T$4*S22 -> 28.268079 | U22: 0 | V22: =ORÇAMENTO_EXECUTIVO!$B$25/CÁLCULO_MÉDIAS!V$4*U22 -> 0 | X22: =ORÇAMENTO_EXECUTIVO!$B$25/CÁLCULO_MÉDIAS!X$4*W22 -> 0 | Y22: 164.44615 | Z22: =ORÇAMENTO_EXECUTIVO!$B$25/CÁLCULO_MÉDIAS!Z$4*Y22 -> 123.89673 | AB22: =ORÇAMENTO_EXECUTIVO!$B$25/CÁLCULO_MÉDIAS!AB$4*AA22 -> 0 | AC22: ='[6]Orçamento Resumo TOTAL'!$F$183/AD1 -> 15.013321 | AD22: =ORÇAMENTO_EXECUTIVO!$B$25/CÁLCULO_MÉDIAS!AD$4*AC22 -> 13.801801 | AE22: 0 | AF22: =ORÇAMENTO_EXECUTIVO!$B$25/CÁLCULO_MÉDIAS!AF$4*AE22 -> 0 | AH22: 10 | AI22: 15
B23: REVESTIMENTOS E ACABAMENTOS DE FACHADA | C23: 149.25162 | D23: =ORÇAMENTO_PARCIAL!$B$20/CÁLCULO_MÉDIAS!D$4*C23 -> 141.96094 | E23: 109.63024 | F23: =ORÇAMENTO_PARCIAL!$B$20/CÁLCULO_MÉDIAS!F$4*E23 -> 106.88339 | G23: 85.43767 | H23: =ORÇAMENTO_PARCIAL!$B$20/CÁLCULO_MÉDIAS!H$4*G23 -> 90.724957 | I23: 85.43767 | J23: =ORÇAMENTO_EXECUTIVO!$B$25/CÁLCULO_MÉDIAS!J$4*I23 -> 71.286052 | K23: 112.90382 | L23: =ORÇAMENTO_EXECUTIVO!$B$25/CÁLCULO_MÉDIAS!L$4*K23 -> 94.202801 | M23: 165.68145 | N23: =ORÇAMENTO_EXECUTIVO!$B$25/CÁLCULO_MÉDIAS!N$4*M23 -> 127.79613 | O23: 102.99303 | P23: =ORÇAMENTO_EXECUTIVO!$B$25/CÁLCULO_MÉDIAS!P$4*O23 -> 78.660243 | Q23: 148.79451 | R23: =ORÇAMENTO_EXECUTIVO!$B$25/CÁLCULO_MÉDIAS!R$4*Q23 -> 113.64082 | S23: 78.015825 | T23: =ORÇAMENTO_PARCIAL!$B$20/CÁLCULO_MÉDIAS!T$4*S23 -> 110.19294 | U23: 60.487349 | V23: =ORÇAMENTO_EXECUTIVO!$B$25/CÁLCULO_MÉDIAS!V$4*U23 -> 46.196809 | W23: 132.27883 | X23: =ORÇAMENTO_EXECUTIVO!$B$25/CÁLCULO_MÉDIAS!X$4*W23 -> 115.00213 | Y23: 18.249467 | Z23: =ORÇAMENTO_EXECUTIVO!$B$25/CÁLCULO_MÉDIAS!Z$4*Y23 -> 13.749482 | AA23: ='[5]Obra '!$E$46 -> 22.828585 | AB23: =ORÇAMENTO_EXECUTIVO!$B$25/CÁLCULO_MÉDIAS!AB$4*AA23 -> 16.0362 | AC23: ='[6]Orçamento Resumo TOTAL'!$F$187/AD1 -> 154.43957 | AD23: =ORÇAMENTO_EXECUTIVO!$B$25/CÁLCULO_MÉDIAS!AD$4*AC23 -> 141.97686 | AE23: 57.088485 | AF23: =ORÇAMENTO_EXECUTIVO!$B$25/CÁLCULO_MÉDIAS!AF$4*AE23 -> 40.318564 | AH23: 110 | AI23: 140
B24: SERVIÇOS COMPLEMENTARES | C24: 181.89468 | D24: =ORÇAMENTO_PARCIAL!$B$20/CÁLCULO_MÉDIAS!D$4*C24 -> 173.00945 | E24: 104.62153 | F24: =ORÇAMENTO_PARCIAL!$B$20/CÁLCULO_MÉDIAS!F$4*E24 -> 102.00017 | G24: 189.05137 | H24: =ORÇAMENTO_PARCIAL!$B$20/CÁLCULO_MÉDIAS!H$4*G24 -> 200.75077 | I24: 189.05137 | J24: =ORÇAMENTO_EXECUTIVO!$B$25/CÁLCULO_MÉDIAS!J$4*I24 -> 157.73752 | K24: 122.2838 | L24: =ORÇAMENTO_EXECUTIVO!$B$25/CÁLCULO_MÉDIAS!L$4*K24 -> 102.02911 | M24: 142.84172 | N24: =ORÇAMENTO_EXECUTIVO!$B$25/CÁLCULO_MÉDIAS!N$4*M24 -> 110.17901 | O24: 116.34736 | P24: =ORÇAMENTO_EXECUTIVO!$B$25/CÁLCULO_MÉDIAS!P$4*O24 -> 88.859523 | Q24: 120.65762 | R24: =ORÇAMENTO_EXECUTIVO!$B$25/CÁLCULO_MÉDIAS!R$4*Q24 -> 92.151454 | S24: 201.17157 | T24: =ORÇAMENTO_PARCIAL!$B$20/CÁLCULO_MÉDIAS!T$4*S24 -> 284.14345 | U24: 151.23034 | V24: =ORÇAMENTO_EXECUTIVO!$B$25/CÁLCULO_MÉDIAS!V$4*U24 -> 115.50116 | W24: 178.89281 | X24: =ORÇAMENTO_EXECUTIVO!$B$25/CÁLCULO_MÉDIAS!X$4*W24 -> 155.52795 | Y24: 167.95411 | Z24: =ORÇAMENTO_EXECUTIVO!$B$25/CÁLCULO_MÉDIAS!Z$4*Y24 -> 126.5397 | AA24: ='[5]Obra '!$E$50 -> 512.71741 | AB24: =ORÇAMENTO_EXECUTIVO!$B$25/CÁLCULO_MÉDIAS!AB$4*AA24 -> 360.1642 | AC24: ='[6]Orçamento Resumo TOTAL'!$F$193/AD1 -> 218.89457 | AD24: =ORÇAMENTO_EXECUTIVO!$B$25/CÁLCULO_MÉDIAS!AD$4*AC24 -> 201.23058 | AE24: 194.06946 | AF24: =ORÇAMENTO_EXECUTIVO!$B$25/CÁLCULO_MÉDIAS!AF$4*AE24 -> 137.06095 | AH24: 130 | AI24: 200
B25: TOTAL | C25: =SUM(C8:C24) -> 3581.806 | D25: =SUM(D8:D24) -> 2853.5091 | E25: =SUM(E8:E24) -> 3148.0097 | F25: =SUM(F8:F24) -> 3069.1345 | G25: =SUM(G8:G24) -> 3208.8157 | H25: =SUM(H8:H24) -> 2752.0089 | I25: =SUM(I8:I24) -> 3208.8157 | J25: =SUM(J8:J24) -> 2162.3581 | ... AF25: =SUM(AF8:AF24) -> 2610.8983 | AH25: =SUM(AH8:AH24) -> 2700 | AI25: =SUM(AI8:AI24) -> 3870
F26: VALORES DE SUPRA SIMILARES | H26: SUPRA MACIÇA | X26: MURETA GUIA NA CONTENÇÃO | Z26: CONTENÇÃO E MOV. TERRA | AD26: CONTENÇÃO
F27: FORMA DA SUPRA BARATA | H27: POUCO BLOCO E INFRA + POUCO MOVI TERRA | X27: ESTACA BARRETE | AD27: TEXTURA EMBORRACHADA E STO MOLDURAS NA FACHADA
B28: Cota Afoso Pena | F28: CONSIDERADO CONTRAPISO ARMADO NA SUPRA (Q92) | H28: DRYWALL 90 MAIS BARATO (130) | X28: SUPRA EXTREMAMENTE PARECIDA
B29: Indepe Estala Marina | F29: SUPRA COM CUBETAS | X29: TEM PERFURAÇÃO DE VIGAS
B30: Carrara | P30: BRAVA MUNDO MENDES | X30: TEM MENOS FORMA, E ERA LOCAÇÃO DE FORMA PRONTA
N31: MOVIMENTAÇÃO DE TERRA | P31: 93 | R31: {=ORÇAMENTO_EXECUTIVO!$B$25/CÁLCULO_MÉDIAS!R$4*P31:Q31} -> 71.02813 | S31: 0 | X31: TEM MENOS AÇO
X32: MENOS CONCRETO
X33: ESCORAMENTO BEM MAIS BARATO
X34: PRESSURIZADOR DE ESCADAS
C35: Cotação Tubo | E35: Cotação Manta | X35: PREÇO ELEVADOR FINAL SIMILAR
C38: https://www.gupar.com.br/construcao/dreno-corrugado/tubo-dreno-corrugado-4-50-metros?parceiro=9038&gad_source=1&gclid=Cj0KCQjw28W2BhC7ARIsAPerrcJrgK4xjmLsYnxsmQIlnQXNwuJ20b0LvQ6DvUG-g_gYSRO5Aocx8B8aApuEEALw_wcB

Sheet COMPARAÇÃO
A1: ETAPA | B1: Orçamento R00 | C1: Orçamento R01 | D1: Diferença | E1: % Diferença
A2: GERENCIAMENTO TÉCNICO E ADMINISTRATIVO | B2: 9723475.3 | C2: ='ANÁLISE_CUSTOS PARCIAL'!B3 -> 0 | D2: =C2-B2 -> -9723475.3 | E2: =D2/C2 -> #DIV/0! | G2: ÁREA CONSTRUÍDA | H2: 7950.33 | I2: m²
A3: MOVIMENTAÇÃO DE TERRA | B3: 445700.74 | C3: ='ANÁLISE_CUSTOS PARCIAL'!B4 -> 0 | D3: =C3-B3 -> -445700.74 | E3: =D3/C3 -> #DIV/0!
A4: INFRAESTRUTURA | B4: 3966312.3 | C4: ='ANÁLISE_CUSTOS PARCIAL'!B5 -> 0 | D4: =C4-B4 -> -3966312.3 | E4: =D4/C4 -> #DIV/0!
A5: SUPRAESTRUTURA | C5: ='ANÁLISE_CUSTOS PARCIAL'!B6 -> 0 | E5: =D5/C5 -> #DIV/0!
A6: ALVENARIA
A7: INSTALAÇÕES ELÉTRICAS, HIDRÁULICAS, GLP E PREVENTIVAS
A8: EQUIPAMENTOS E SISTEMAS ESPECIAIS
A9: IMPERMEABILIZAÇÃO
A10: REVESTIMENTOS INTERNOS EM PISO E PAREDE
A11: REVESTIMENTOS E ACABAMENTOS INTERNOS EM TETO
A12: ACABAMENTOS EM PISO E PAREDE
A13: PINTURA INTERNA
A14: ESQUADRIAS, VIDROS E FERRAGENS
A15: COBERTURA
A16: REVESTIMENTOS E ACABAMENTOS DE FACHADA
A17: SERVIÇOS COMPLEMENTARES
A18: IMPREVISTOS E CONTINGENCIAS
A19: TOTAL | B19: =SUM(B2:B18) -> 14135488 | D19: =SUM(D2:D18) -> -14135488 | E19: =SUM(E2:E18) -> #DIV/0!

Sheet BARÃO
A5: Obra
A6: Unidade construtiva
A7: Tipo de obra
A8: Endereço da obra
A9: Versão do orçamento
A10: BDI
A11: Preços expressos em
A13: Código | B13: Descrição | C13: Un. | D13: Quantidade orçada | E13: Preço unitário | F13: Preço total
A14: 01 | B14: ESTUDOS, PROJETOS E CONSULTORIAS | F14: 475922.4
A15: 01.001 | B15: ESTUDOS, PROJETOS E CONSULTORIAS | F15: 475922.4
A16: 01.001.001 | B16: Estudos | F16: 19700
A17: 01.001.001.001 | B17: Levantamento topográfico | C17: vb | D17: 1 | E17: 1500 | F17: 1500
A18: 01.001.001.002 | B18: Sondagem do terreno | C18: vb | D18: 1 | E18: 13500 | F18: 13500
A19: 01.001.001.003 | B19: Estudo ambiental | C19: vb | D19: 1 | E19: 4700 | F19: 4700
A20: 01.001.002 | B20: Projetos | F20: 353442.91
A21: 01.001.002.001 | B21: Legalização de incorporação | C21: vb | D21: 1 | E21: 15000 | F21: 15000
A22: 01.001.002.002 | B22: Projeto arquitetônico executivo | C22: vb | D22: 1 | E22: 220000 | F22: 220000
A23: 01.001.002.003 | B23: Projeto arquitetônico interiores/ambientação | C23: vb | D23: 1 | E23: 31942.91 | F23: 31942.91
A24: 01.001.002.004 | B24: Projeto técnico de fachada | C24: vb | D24: 1 | E24: 3500 | F24: 3500
A25: 01.001.002.005 | B25: Projeto arquitetônico de fachada | C25: vb | D25: 1 | E25: 500 | F25: 500
A26: 01.001.002.006 | B26: Projeto de fundação | C26: vb | D26: 1 | E26: 10500 | F26: 10500
A27: 01.001.002.007 | B27: Projeto estrutural em concreto armado | C27: vb | D27: 1 | E27: 32000 | F27: 32000
A28: 01.001.002.008 | B28: Projeto elétrico | C28: vb | D28: 1 | E28: 12000 | F28: 12000
A29: 01.001.002.009 | B29: Projeto hidrossanitário | C29: vb | D29: 1 | E29: 12000 | F29: 12000
A30: 01.001.002.010 | B30: Projeto preventivo | C30: vb | D30: 1 | E30: 16000 | F30: 16000
A31: 01.001.003 | B31: Consultorias | F31: 60850
A32: 01.001.003.001 | B32: Orçamento e planejamento | C32: vb | D32: 1 | E32: 28250 | F32: 28250
A33: 01.001.003.002 | B33: Auditoria de qualidade | C33: vb | D33: 1 | E33: 12600 | F33: 12600
A34: 01.001.003.003 | B34: Consultorias técnicas diversas | C34: vb | D34: 1 | E34: 20000 | F34: 20000
A35: 01.001.004 | B35: Ensaios e Laudos | F35: 41929.49
A36: 01.001.004.001 | B36: Controle tecnológico de concreto | C36: m3 | D36: 4030.5987 | E36: 7.5 | F36: 30229.49
A37: 01.001.004.002 | B37: Laudo de vistoria técnica | C37: vb | D37: 1 | E37: 5500 | F37: 5500
A38: 01.001.004.003 | B38: Laudo preventivo de danos à vizinhança | C38: vb | D38: 1 | E38: 6200 | F38: 6200
A39: 02 | B39: TAXAS, DOCUMENTOS | F39: 115650.01
A40: 02.001 | B40: TAXAS, DOCUMENTOS | F40: 115650.01
A41: 02.001.001 | B41: Taxas e Documentos | F41: 115650.01
A42: 02.001.001.001 | B42: Despesas de seguro* | C42: vb | D42: 1 | E42: 17356 | F42: 17356
A43: 02.001.001.002 | B43: Aprovação e legalização prefeitura | C43: vb | D43: 1 | E43: 35415.72 | F43: 35415.72
A44: 02.001.001.003 | B44: Aprovação e legalização bombeiros | C44: vb | D44: 1 | E44: 5889.56 | F44: 5889.56
A45: 02.001.001.004 | B45: Aprovação e legalização ambiental | C45: vb | D45: 1 | E45: 6061.05 | F45: 6061.05
A46: 02.001.001.005 | B46: Taxas de ART | C46: vb | D46: 1 | E46: 752.56 | F46: 752.56
A47: 02.001.001.006 | B47: Taxas de alvará* | C47: vb | D47: 1 | E47: 16247 | F47: 16247
A48: 02.001.001.007 | B48: Despesas cartório, licenças, certidões e jurídicas | C48: vb | D48: 1 | E48: 4366.12 | F48: 4366.12
A49: 02.001.001.008 | B49: Incorporação | C49: vb | D49: 1 | E49: 15000 | F49: 15000
A50: 02.001.001.009 | B50: IPTU* | C50: vb | D50: 1 | E50: 4472 | F50: 4472
A51: 02.001.001.010 | B51: Habite-se* | C51: vb | D51: 1 | E51: 10090 | F51: 10090
A52: Total da unidade construtiva | F52: 591572.41
A54: Obra
A55: Unidade construtiva
A56: Tipo de obra
A57: Endereço da obra
A58: Versão do orçamento
A59: BDI
A60: Preços expressos em
A62: Código | B62: Descrição | C62: Un. | D62: Quantidade orçada | E62: Preço unitário | F62: Preço total
A63: 01 | B63: SEGURANÇA, MEIO AMBIENTE E SAÚDE | F63: 288286.66
A64: 01.001 | B64: SEGURANÇA, MEIO AMBIENTE E SAÚDE | F64: 288286.66
A65: 01.001.001 | B65: Segurança do trabalho | F65: 13200
A66: 01.001.001.001 | B66: Serviço terceirizado de segurança do trabalho | C66: mes | D66: 44 | E66: 300 | F66: 13200
A67: 01.001.002 | B67: Equipamentos de proteção | F67: 267636.66
A68: 01.001.002.001 | B68: Equipamentos de proteção individual* | C68: vb | D68: 1 | E68: 23500 | F68: 23500
A69: 01.001.002.002 | B69: Bandeja de proteção primária | C69: m | D69: 75.08 | E69: 1891.3854 | F69: 142005.22
A70: 01.001.002.003 | B70: Rede de proteção tipo SLQA | C70: m2 | D70: 795 | E70: 47.25 | F70: 37563.75
A71: 01.001.002.004 | B71: Guarda-corpo de vãos, fixado em forma de madeira, em trama de madeira com tela de polipropileno* | C71: vb | D71: 1 | E71: 45000 | F71: 45000
A72: 01.001.002.005 | B72: Guarda-corpo de laje após desforma | C72: m | D72: 182.66 | E72: 23.8021 | F72: 4347.69
A73: 01.001.002.006 | B73: Varal de segurança com cabo de aço* | C73: vb | D73: 1 | E73: 5000 | F73: 5000
A74: 01.001.002.007 | B74: Fechamento removível de vãos de porta de elevador em madeira* | C74: un | D74: 58 | E74: 90 | F74: 5220
A75: 01.001.002.008 | B75: Cobertura para proteção de pedestres* | C75: vb | D75: 1 | E75: 5000 | F75: 5000
A76: 01.001.003 | B76: Meio ambiente | F76: 6100
A77: 01.001.003.001 | B77: Elaboração de programa de prevenção dos riscos ambientais (PPRA)* | C77: vb | D77: 1 | E77: 1350 | F77: 1350
A78: 01.001.003.002 | B78: Elaboração do programa de condições e meio ambiente de trabalho na indústria de construção (PCMAT)* | C78: vb | D78: 1 | E78: 4750 | F78: 4750
A79: 01.001.004 | B79: Saúde ocupacional | F79: 1350
A80: 01.001.004.001 | B80: Elaboração do programa de controle médico de saúde ocupacional (PCMSO)* | C80: vb | D80: 1 | E80: 1350 | F80: 1350
A81: 02 | B81: ADMINISTRAÇÃO E CANTEIRO DE OBRA | F81: 1936039.7
A82: 02.001 | B82: ADMINISTRAÇÃO E CANTEIRO DE OBRA | F82: 1936039.7
A83: 02.001.001 | B83: Equipe de gestão e apoio | F83: 1445400
A84: 02.001.001.001 | B84: Engenheiro civil | C84: mes | D84: 44 | E84: 8000 | F84: 352000
A85: 02.001.001.002 | B85: Almoxarife | C85: mes | D85: 44 | E85: 5000 | F85: 220000
A86: 02.001.001.003 | B86: Auxiliar de engenharia | C86: mes | D86: 44 | E86: 4000 | F86: 176000
A87: 02.001.001.004 | B87: Assistente administrativo | C87: mes | D87: 44 | E87: 4000 | F87: 176000
A88: 02.001.001.005 | B88: Estagiário | C88: mes | D88: 44 | E88: 1350 | F88: 59400
A89: 02.001.001.006 | B89: Vigilância e portaria | C89: mes | D89: 44 | E89: 3000 | F89: 132000
A90: 02.001.001.007 | B90: Equipe de T.I* | C90: mes | D90: 44 | E90: 3000 | F90: 132000
A91: 02.001.001.008 | B91: Mão de obra para apoio civil* | C91: mes | D91: 44 | E91: 4500 | F91: 198000
A92: 02.001.002 | B92: Canteiro de obras | F92: 148999.74
A93: 02.001.002.001 | B93: Limpeza de terreno | C93: vb | D93: 1 | E93: 6500 | F93: 6500
A94: 02.001.002.002 | B94: Instalações provisórias | C94: vb | D94: 1 | E94: 35000 | F94: 35000
A95: 02.001.002.003 | B95: Locação de banheiro químico* | C95: un | D95: 4 | E95: 600 | F95: 2400
A96: 02.001.002.004 | B96: Tapume com telha metálica* | C96: m2 | D96: 115.82 | E96: 60.4364 | F96: 6999.74
A97: 02.001.002.005 | B97: Serviço topográfico* | C97: vb | D97: 1 | E97: 65000 | F97: 65000
A98: 02.001.002.006 | B98: Sinalização de obra* | C98: vb | D98: 1 | E98: 5000 | F98: 5000
A99: 02.001.002.007 | B99: Equipamento de Escritório* | C99: vb | D99: 1 | E99: 10100 | F99: 10100
A100: 02.001.002.008 | B100: Mobiliário de apoio a obra* | C100: vb | D100: 1 | E100: 10500 | F100: 10500
A101: 02.001.002.009 | B101: Catraca de controle de acesso* | C101: vb | D101: 1 | E101: 7500 | F101: 7500
A102: 02.001.003 | B102: Despesas de consumo e manutenção | F102: 341640
A103: 02.001.003.001 | B103: Despesas de consumo - água* | C103: mes | D103: 44 | E103: 1050 | F103: 46200
A104: 02.001.003.002 | B104: Despesas de consumo - luz* | C104: mes | D104: 44 | E104: 1365 | F104: 60060
A105: 02.001.003.003 | B105: Despesas de consumo - internet* | C105: mes | D105: 44 | E105: 250 | F105: 11000
A106: 02.001.003.004 | B106: Despesas de consumo - coleta de lixo* | C106: mes | D106: 44 | E106: 45 | F106: 1980
A107: 02.001.003.005 | B107: Despesas de consumo - material de limpeza* | C107: mes | D107: 44 | E107: 400 | F107: 17600
...

Sheet CAIO PRADO
A1: ORÇAMENTO PARAMÉTRICO
A4: Cliente | B4: =[7]OBRA!B1 -> Caio Prado
A5: Obra | B5: =[7]OBRA!B2 -> Indepy
A6: Data | B6: 45748
A7: Versão | B7: R01
A9: CÓDIGO | B9: ITEM | C9: Quantidade | D9: Unidade | E9: Valor Unitário | F9: Valor Orçado | G9: Considerações
A10: 1 | B10: GERENCIAMENTO TÉCNICO E ADMINISTRATIVO | F10: =F11 -> 4972621.4
A11: 1.1 | B11: GERENCIAMENTO TÉCNICO E ADMINISTRATIVO | F11: =F12 -> 4972621.4
A12: 1.1.1 | B12: Gerenciamento técnico e administrativo | C12: 1 | D12: vb | E12: =F12/C12 -> 4972621.4 | F12: =[7]CUSTOS_INDIRETOS!F74 -> 4972621.4 | G12: Conforme discretização nas abas anteriores
A13: 2 | B13: MOVIMENTAÇÃO DE TERRA | F13: =F14+F16 -> 516244.08
A14: 2.1 | B14: ESCAVAÇÃO DE SUBSOLO | F14: =SUM(F15:F15) -> 69873.884
A15: 2.1.1 | B15: Escavação e bota-fora de subsolo | C15: 1028.775 | D15: m³ | E15: =F15/C15 -> 67.9195 | F15: 69873.884
A16: 2.2 | B16: MOVIMENTAÇÃO DE VALAS | F16: =SUM(F17:F21) -> 446370.19
A17: 2.2.1 | B17: Escavação mecanizada para blocos e baldrames | C17: 1105.7319 | D17: m³ | E17: =F17/C17 -> 39.996 | F17: 44224.853
A18: 2.2.2 | B18: Reaterro para blocos e baldrames | C18: 546.5439 | D18: m³ | E18: =F18/C18 -> 16.005 | F18: 8747.4351
A19: 2.2.3 | B19: Movimentação de bota-fora | C19: 726.9444 | D19: m³ | E19: =F19/C19 -> 49.995 | F19: 36343.585
A20: 2.2.4 | B20: Movimentação de terra das estacas | C20: 4627 | D20: m³ | E20: =F20/C20 -> 74.998 | F20: 347015.75
A21: 2.2.5 | B21: Lastro de brita e= 10cm - Blocos e baldrames | C21: 493.296 | D21: m² | E21: =F21/C21 -> 20.35 | F21: 10038.574
A22: 3 | B22: INFRAESTRUTURA | F22: =F23+F37 -> 5042484.1
A23: 3.1 | B23: FUNDAÇÃO PROFUNDA | F23: =SUM(F24:F36) -> 4020877.6 | G23: Custos levantados através do projeto e levantados com base nas porpostas encaminhadas
A24: 3.1.1 | B24: Serviço especializado para estaca barrete | C24: =[8]INFRAESTRUTURA!$D$21+[8]INFRAESTRUTURA!$D$11 -> 288 | D24: m | E24: =F24/C24 -> 2113.8262 | F24: =SUM([8]INFRAESTRUTURA!$G$11:$G$25) -> 608781.94
A25: 3.1.2 | B25: Serviço especializado para estaca hélice | C25: =[8]INFRAESTRUTURA!$D$27+[8]INFRAESTRUTURA!$D$29+[8]INFRAESTRUTURA!$D$31 -> 1068 | D25: m | E25: =F25/C25 -> 107.12547 | F25: =SUM([8]INFRAESTRUTURA!$G$26:$G$32) -> 114410
A26: 3.1.2 | B26: Concreto (40 Mpa) | C26: 4627 | D26: m³ | E26: =F26/C26 -> 546.002 | F26: =[8]INFRAESTRUTURA!$G$33 -> 2526351.3 | G26: Custo 498,63/m³ repassado pela indepy + perda + bombeamento
A27: 3.1.3 | B27: Armação 6,3mm | C27: 123.17 | D27: kg | E27: =F27/C27 -> 8.35 | F27: 1028.4695 | G27: Custo 7,4/kg repassado pela indepy + arame e espaçados (quantitativo já contem perda)
A28: 3.1.4 | B28: Armação 8mm | C28: 4844.19 | D28: kg | E28: =F28/C28 -> 7.88 | F28: 38172.217 | G28: Custo 7,4/kg repassado pela indepy + arame e espaçados (quantitativo já contem perda)
A29: 3.1.5 | B29: Armação 12,5mm | C29: 1300 | D29: kg | E29: =F29/C29 -> 7.41 | F29: 9633 | G29: Custo 7,4/kg repassado pela indepy + arame e espaçados (quantitativo já contem perda)
A30: 3.1.6 | B30: Armação 16mm | C30: 3630 | D30: kg | E30: =F30/C30 -> 7.35 | F30: 26680.5 | G30: Custo 7,4/kg repassado pela indepy + arame e espaçados (quantitativo já contem perda)
A31: 3.1.6 | B31: Armação 20mm | C31: 39000 | D31: kg | E31: =F31/C31 -> 8.27 | F31: 322530 | G31: Custo 7,4/kg repassado pela indepy + arame e espaçados (quantitativo já contem perda)
A32: 3.1.8 | B32: Forma mureta guia | C32: 607.2 | D32: m² | E32: =F32/C32 -> 68 | F32: 41289.6
A33: 3.1.9 | B33: Concreto mureta guia | C33: 30.36 | D33: m³ | E33: =F33/C33 -> 573.3021 | F33: 17405.452 | G33: Custo 498,63/m³ repassado pela indepy + perda + bombeamento
A34: 3.1.10 | B34: Armação mureta guia 6,3mm | C34: 1450 | D34: kg | E34: =F34/C34 -> 8.35 | F34: 12107.5 | G34: Custo 7,4/kg repassado pela indepy + arame e espaçados (quantitativo já contem perda)
A35: 3.1.11 | B35: Armação mureta guia 10mm | C35: 3906 | D35: kg | E35: =F35/C35 -> 8.44 | F35: 32966.64 | G35: Custo 7,4/kg repassado pela indepy + arame e espaçados (quantitativo já contem perda)
A36: 3.1.12 | B36: Mão de obra execuão | C36: 1 | D36: vb | E36: =F36/C36 -> 269520.99 | F36: 269520.99
A37: 3.2 | B37: FUNDAÇÃO RASA | F37: =SUM(F38:F41) -> 1021606.5
A38: 3.2.1 | B38: Fabricação, montagem e desmontagem de forma para blocos e baldrames resinado | C38: 770.93 | D38: m² | E38: =F38/C38 -> 74.8 | F38: 57665.564
A39: 3.2.2 | B39: Concreto (40 Mpa) | C39: 559.188 | D39: m³ | E39: =F39/C39 -> 630.63231 | F39: 352642.02
A40: 3.2.3 | B40: Armação | C40: 42407 | D40: kg | E40: =F40/C40 -> 8.657 | F40: 367117.4 | G40: Custo 7,4/kg repassado pela indepy + arame e espaçados (quantitativo já contem perda)
A41: 3.2.4 | B41: Mão de obra | C41: 616.62 | D41: m² | E41: =F41/C41 -> 396 | F41: 244181.52 | G41: Valor estimado por área de projeção do embasamento
A42: 4 | B42: CONTENÇÃO | F42: =F43 -> 282541.99
A43: 4.1 | B43: CONTENÇÃO | F43: =SUM(F44:F48) -> 282541.99 | G43: Custos levantados através do projeto
A44: 4.1.1 | B44: Fabricação, montagem e desmontagem de forma para parede de concreto | C44: 582.75 | D44: m² | E44: =F44/C44 -> 173.76249 | F44: 101260.09
A45: 4.1.2 | B45: Concreto (40 Mpa) - com cristalizante | C45: 58.275 | D45: m³ | E45: =F45/C45 -> 746.13231 | F45: 43480.86 | G45: Custo 498,63/m² repassado pela indepy + perda + bombeamento + cristalizante
A46: 4.1.3 | B46: Armação | C46: 5827.5 | D46: kg | E46: =F46/C46 -> 8.657 | F46: 50448.668
A47: 4.1.4 | B47: Drenagem | C47: 92.5 | D47: m | E47: =F47/C47 -> 286 | F47: 26455
A48: 4.1.5 | B48: Mão de obra contenção | C48: 291.375 | D48: m² | E48: =F48/C48 -> 209 | F48: 60897.375
A49: 5 | B49: SUPRAESTRUTURA | F49: =F50+F53+F55+F60+F57 -> 5545670.6
A50: 5.1 | B50: FORMA | F50: =SUM(F51:F52) -> 368213.57
A51: 5.1.1 | B51: Locação de Forma pronta | C51: 1559.346 | D51: m² | E51: =F51/C51 -> 217.8 | F51: 339625.56 | G51: Locação de forma pronta - custo estimado para o porte da obra (3 jogos)
A52: 5.1.2 | B52: Montagem de forma | C52: 10395.64 | D52: m² | E52: =F52/C52 -> 2.75 | F52: 28588.01
A53: 5.2 | B53: ARMADURA | F53: =F54 -> 1503224
A54: 5.2.1 | B54: Armadura Convencional para Estrutura | C54: 174085 | D54: kg | E54: =F54/C54 -> 8.635 | F54: 1503224 | G54: Custo 7,4/kg repassado pela indepy + arame e espaçados (quantitativo já contem perda)
A55: 5.3 | B55: CONCRETO | F55: =F56 -> 1260395.3
A56: 5.3.1 | B56: Concreto | C56: 2007.342 | D56: m³ | E56: =F56/C56 -> 627.89265 | F56: 1260395.3 | G56: Custo 498,63/m³ repassado pela indepy + perda + bombeamento
A57: 5.4 | B57: COMPLEMENTARES | F57: =SUM(F58:F59) -> 258333.6
A58: 5.4.1 | B58: Locação escoramento | C58: 1 | D58: vb | E58: =F58/C58 -> 141733.6 | F58: 141733.6 | G58: Verba repassada para locação de escoramento
A59: 5.4.3 | B59: Perfuração de vigas e lajes | C59: 1 | D59: vb | E59: =F59/C59 -> 116600 | F59: 116600
A60: 5.5 | B60: MÃO DE OBRA | F60: =F61 -> 2155504.1
A61: 5.5.1 | B61: Mão de obra supraestrutura | C61: 6938.39 | D61: m² | E61: =F61/C61 -> 310.66344 | F61: 2155504.1 | G61: Valor estimado com base na área construida
A62: 6 | B62: ALVENARIA | F62: =F63 -> 1382917.5
A63: 6.1 | B63: ALVENARIA | F63: =SUM(F64:F67) -> 1382917.5
A64: 6.1.1 | B64: Alvenaria | C64: 11548.623 | D64: m² | E64: =F64/C64 -> 38.5 | F64: 444621.99 | G64: Blcos de concreto 19x19x39
A65: 6.1.2 | B65: Alvenaria acústica | C65: 2099.517 | D65: m² | E65: =F65/C65 -> 71.5 | F65: 150115.47 | G65: Blocos acústicos 19x19x39, custo repassado pela Indepy
A66: 6.1.3 | B66: Serviços complementares | C66: 13648.14 | D66: m² | E66: =F66/C66 -> 13.75 | F66: 187661.93 | G66: Previsão de amarração com tela, vergas, contravergas e encunahmento;
A67: 6.1.4 | B67: Mão de obra | C67: 13648.14 | D67: m² | E67: =F67/C67 -> 44 | F67: 600518.16 | G67: Fechamento com bloco sical e assentamento com argamassa usinada
A68: 7 | B68: INSTALAÇÕES ELÉTRICAS, HIDRÁULICAS E GLP | F68: =F69+F77+F84 -> 2575057.6 | G68: Valores estimados com base em índices históricos por área construida
A69: 7.1 | B69: INSTALAÇÕES ELÉTRICAS | F69: =SUM(F70:F76) -> 1089299.4
A70: 7.1.1 | B70: Entrada de Energia | C70: 1 | D70: vb | E70: =F70/C70 -> 42340.26 | F70: 42340.26
A71: 7.1.2 | B71: Eletrodutos e Eletrocalhas | C71: 1 | D71: vb | E71: =F71/C71 -> 76982.29 | F71: 76982.29
A72: 7.1.3 | B72: Cabos e Fiações | C72: 1 | D72: vb | E72: =F72/C72 -> 230946.87 | F72: 230946.87
A73: 7.1.4 | B73: Quadros e Disjuntores | C73: 1 | D73: vb | E73: =F73/C73 -> 123171.66 | F73: 123171.66
A74: 7.1.5 | B74: Acabamentos Elétricos | C74: 1 | D74: vb | E74: =F74/C74 -> 76982.29 | F74: 76982.29
A75: 7.1.6 | B75: Equipamentos e Iluminação | C75: 1 | D75: vb | E75: =F75/C75 -> 76982.29 | F75: 76982.29
A76: 7.1.7 | B76: Mão de Obra para Instalações Elétricas | C76: 1 | D76: vb | E76: =F76/C76 -> 461893.74 | F76: 461893.74
A77: 7.2 | B77: INSTALAÇÕES HIDRÁULICAS | F77: =SUM(F78:F83) -> 1324095.4
A78: 7.2.1 | B78: Instalações de Água Fria | C78: 1 | D78: vb | E78: =F78/C78 -> 169361.04 | F78: 169361.04
A79: 7.2.2 | B79: Instalações de Água Quente | C79: 1 | D79: vb | E79: =F79/C79 -> 138568.12 | F79: 138568.12
A80: 7.2.3 | B80: Instalações de Águas Pluviais | C80: 1 | D80: vb | E80: =F80/C80 -> 92378.748 | F80: 92378.748
A81: 7.2.4 | B81: Instalações Sanitárias | C81: 1 | D81: vb | E81: =F81/C81 -> 115473.44 | F81: 115473.44
A82: 7.2.5 | B82: Louças e Metais | C82: 1 | D82: vb | E82: =F82/C82 -> 384911.45 | F82: 384911.45 | G82: Entrega total em áreas comuns e louças e metais em áreas privativas;
A83: 7.2.6 | B83: Mão de Obra para Instalações Hidráulicas | C83: 1 | D83: vb | E83: =F83/C83 -> 423402.6 | F83: 423402.6
A84: 7.3 | B84: INSTALAÇÕES PREVENTIVAS E GLP | F84: =SUM(F85:F87) -> 161662.81
A85: 7.3.1 | B85: Instalações Preventivas | C85: 1 | D85: vb | E85: =F85/C85 -> 76982.29 | F85: 76982.29
A86: 7.3.2 | B86: Instalações de GLP | C86: 1 | D86: vb | E86: =F86/C86 -> 38491.145 | F86: 38491.145
A87: 7.3.3 | B87: Instalações de Proteção e Aterramento - SPDA | C87: 1 | D87: vb | E87: =F87/C87 -> 46189.374 | F87: 46189.374
A88: 8 | B88: SISTEMAS ESPECIAIS | F88: =F89+F93+F98 -> 2444838.2
A89: 8.1 | B89: CLIMATIZAÇÃO, EXAUSTÃO MECÂNICA E PRESSURIZAÇÃO | F89: =SUM(F90:F92) -> 532620
A90: 8.1.1 | B90: Infraestrutura para Instalação de Ar Condicionado | C90: 285 | D90: un | E90: =F90/C90 -> 1210 | F90: 344850 | G90: Infraestrutura para ar-condicionado em areas privativas e comuns
A91: 8.1.2 | B91: Instalação de Ar Condicionado | C91: 10 | D91: un | E91: =F91/C91 -> 6600 | F91: 66000 | G91: Instalação de ar-codicionado em áreas comuns
A92: 8.1.3 | B92: Ventokit | C92: 123 | D92: un | E92: =F92/C92 -> 990 | F92: 121770 | G92: Ventilação mecânica em banheiros enclausurados
A93: 8.2 | B93: COMUNICAÇÃO | F93: =SUM(F94:F97) -> 115473.44
A94: 8.2.1 | B94: CFTV | C94: 1 | D94: vb | E94: =F94/C94 -> 15396.458 | F94: 15396.458
A95: 8.2.2 | B95: Interfone | C95: 1 | D95: vb | E95: =F95/C95 -> 38491.145 | F95: 38491.145
A96: 8.2.3 | B96: TV e internet | C96: 1 | D96: vb | E96: =F96/C96 -> 23094.687 | F96: 23094.687
A97: 8.2.4 | B97: Automação, telecomunicação e sistemas de segurança | C97: 1 | D97: vb | E97: =F97/C97 -> 38491.145 | F97: 38491.145 | G97: Previsão de infraestrutura
A98: 8.3 | B98: EQUIPAMENTOS | F98: =SUM(F99:F107) -> 1796744.7
A99: 8.3.1 | B99: Elevadores | C99: 2 | D99: un | E99: =F99/C99 -> 534941 | F99: 1069882
A100: 8.3.2 | B100: Plataforma elevatória | C100: 2 | D100: un | E100: =F100/C100 -> 47025 | F100: 94050
A101: 8.3.3 | B101: Cadeira de transferência pcd | C101: 1 | D101: un | E101: =F101/C101 -> 23980 | F101: 23980
A102: 8.3.4 | B102: Grupo de geradores | C102: 1 | D102: un | E102: =F102/C102 -> 49500 | F102: 49500
A103: 8.3.5 | B103: Subestação | C103: 1 | D103: un | E103: =F103/C103 -> 198000 | F103: 198000
...

Sheet 54S - SPOT
A1: ORÇAMENTO PARAMÉTRICO - ORÇAMENTO PARAMÉTRICO
A7: Cliente | B7: Spotco
A8: Obra | B8: 54 Park Square
A9: Data | B9: 45275
A10: Versão | B10: TOTAL - R07
A11: CUB/PR - JUN/23 | B11: 2774.87
A12: CUB/PR - atual | B12: ='[9]Orçamento Resumo FASE 1'!B12 -> 2836.93
A14: CÓDIGO | B14: ITEM | C14: Quantidade | D14: Unidade | E14: Valor unitário | F14: Valor Orçado | G14: Valor indexado | H14: Considerações | I14: Observações/Duvidas | J14: RETORNO CARTESIAN
A15: 1 | B15: GERENCIAMENTO TÉCNICO E ADMINISTRATIVO | F15: =F16 -> 31315259 | G15: =G16 -> 31866647
A16: 1.1 | B16: GERENCIAMENTO TÉCNICO E ADMINISTRATIVO | F16: =F17 -> 31315259 | G16: =G17 -> 31866647
A17: 1.1.1 | B17: Gerenciamento técnico e administrativo | C17: 1 | D17: vb | E17: =F17/C17 -> 31315259 | F17: ='[9]CUSTOS_INDIRETOS-FASE 1'!F139+'[9]CUSTOS_INDIRETOS-FASE 2'!F94 -> 31315259 | G17: ='[9]CUSTOS_INDIRETOS-FASE 1'!I139+'[9]CUSTOS_INDIRETOS-FASE 2'!I94 -> 31866647
A18: 2 | B18: MOVIMENTAÇÃO DE TERRA | F18: =F19 -> 4513723.6 | G18: =G19 -> 4614673.1
A19: 2.1 | B19: MOVIMENTAÇÃO DE TERRA | F19: =SUM(F20:F24) -> 4513723.6 | G19: =SUM(G20:G24) -> 4614673.1
A20: 2.1.1 | B20: Escavação subsolo | C20: 94932 | D20: m3 | E20: =F20/C20 -> 30 | F20: 2847960 | G20: =F20*($B$12/$B$11) -> 2911654.7 | H20: Volume previsto no projeto de terraplanagem
A21: 2.1.2 | B21: Escavação mecanizada para blocos e baldrames | C21: 5998.175 | D21: m3 | E21: =F21/C21 -> 70.000125 | F21: 419873 | G21: =F21*($B$12/$B$11) -> 429263.46
A22: 2.1.3 | B22: Reaterro para blocos e baldrames | C22: 1199.635 | D22: m3 | E22: =F22/C22 -> 25.000104 | F22: 29991 | G22: =F22*($B$12/$B$11) -> 30661.749
A23: 2.1.4 | B23: Movimentação de terra (30% de empolamento) | C23: 12976.818 | D23: m3 | E23: =F23/C23 -> 90 | F23: 1167913.6 | G23: =F23*($B$12/$B$11) -> 1194034 | H23: =G24/H24 -> 81.790224
A24: 2.1.5 | B24: Lastro de concreto magro e= 10cm - Blocos | C24: 5998.175 | D24: m2 | E24: =F24/C24 -> 8.0001 | F24: 47986 | G24: =F24*($B$12/$B$11) -> 49059.207 | H24: =C24*0.1 -> 599.8175 | I24: O lastro de concreto sendo um custo de 480/m³, sendo 10 cm de espessura de 10 cm daria 48/m² | J24: A consideração aqui é um lastro de brita 2 na verdade, considerando 80/m³ -> 8/m² (houve um equivoco no nome do serviço)
A25: 3 | B25: INFRAESTRUTURA | F25: =F26+F32 -> 17109406 | G25: =G26+G32 -> 17492058
A26: 3.1 | B26: FUNDAÇÃO PROFUNDA | F26: =SUM(F27:F31) -> 7785843 | G26: =SUM(G27:G31) -> 7959973.5
A27: 3.1.1 | B27: Estaca escavada, diâmetro 100cm | C27: 6600 | D27: m | E27: =F27/C27 -> 75 | F27: 495000 | G27: =F27*($B$12/$B$11) -> 506070.68 | H27: 330 estacas - duas por pilar de embasamento
A28: 3.1.2 | B28: Estaca escavada em rocha, diâmetro 100cm | C28: 5600 | D28: m | E28: =F28/C28 -> 120 | F28: 672000 | G28: =F28*($B$12/$B$11) -> 687029.29 | H28: 280 estacas - 3,5 por pilar da torre
A29: 3.1.3 | B29: Armação | C29: 362853.95 | D29: kg | E29: =F29/C29 -> 7.3000004 | F29: 2648834 | G29: =F29*($B$12/$B$11) -> 2708075.2 | H29: Consideração de R$ 7,30/kg com 7% de perda | I29: Só material?
A30: 3.1.4 | B30: Concreto | C30: 5183.6279 | D30: m3 | E30: =F30/C30 -> 708.00009 | F30: 3670009 | G30: =F30*($B$12/$B$11) -> 3752088.8 | H30: Consideração de R$ 590,00/m³ com 20% de perda | I30: Com o lançamento?
A31: 3.1.5 | B31: Mobilização | C31: 1 | D31: vb | E31: =F31/C31 -> 300000 | F31: 300000 | G31: =F31*($B$12/$B$11) -> 306709.5 | H31: Previsão de mobilização de maquinários | I31: A mão de obra da fundação profunda está também no item 3.2.5? | J31: Sim, os itens da fundação profunda se referem apenas a material, estando a mão de obra inclusa no item 3.2.5
A32: 3.2 | B32: FUNDAÇÃO RASA | F32: =SUM(F33:F36) -> 9323563.2 | G32: =SUM(G33:G36) -> 9532084.8
A33: 3.2.1 | B33: Fabricação, montagem e desmontagem de forma para blocos e baldrames | C33: 5998.175 | D33: m² | E33: =F33/C33 -> 50 | F33: 299908.75 | G33: =F33*($B$12/$B$11) -> 306616.21 | H33: Forma de compensado resinado com 2 reutilizações
A34: 3.2.2 | B34: Armação | C34: 335897.8 | D34: kg | E34: =F34/C34 -> 7.3 | F34: 2452053.9 | G34: =F34*($B$12/$B$11) -> 2506894.2 | H34: Consideração de R$ 7,30/kg com 7% de perda | I34: Só material?
A35: 3.2.3 | B35: Concreto | C35: 4798.54 | D35: m³ | E35: =F35/C35 -> 619.5 | F35: 2972695.5 | G35: =F35*($B$12/$B$11) -> 3039179.9 | H35: Consideração de R$ 590,00/m³ com 5% de perda | I35: Com o lançamento?
A36: 3.2.5 | B36: Mão de obra infraestrutura | C36: 17994.525 | D36: vb | E36: =F36/C36 -> 200 | F36: 3598905 | G36: =F36*($B$12/$B$11) -> 3679394.6 | H36: Valor estimado por área de projeção do embasamento x 1,5 | I36: É para mão de obra de forma, armação e concretagem?
A37: 4 | B37: CONTENÇÃO | F37: =F38 -> 4072621.7 | G37: =G38 -> 4163706
A38: 4.1 | B38: CONTENÇÃO | F38: =SUM(F39:F51) -> 4072621.7 | G38: =SUM(G39:G51) -> 4163706
A39: 4.1.1 | B39: Estaca hélice contínua, diâmetro 50cm | C39: 2628 | D39: m | E39: =F39/C39 -> 80 | F39: 210240 | G39: =F39*($B$12/$B$11) -> 214942.02 | H39: Previsão de 1,25 estacas de 50cm por metro de contenção
A40: 4.1.2 | B40: Armação | C40: 183960 | D40: kg | E40: =F40/C40 -> 7.3 | F40: 1342908 | G40: =F40*($B$12/$B$11) -> 1372942.2 | H40: Consideração de R$ 7,30/kg com 7% de perda
A41: 4.1.3 | B41: Concreto | C41: 516.00659 | D41: m³ | E41: =F41/C41 -> 708 | F41: 365332.67 | G41: =F41*($B$12/$B$11) -> 373503.34 | H41: Consideração de R$ 590,00/m³ com 20% de perda
A42: 4.1.4 | B42: Tirantes | C42: 175.18 | D42: m | E42: =F42/C42 -> 6163.26 | F42: 1079679.9 | G42: =F42*($B$12/$B$11) -> 1103826.9 | H42: Previsão de duas linhas de tirantes
A43: 4.1.5 | B43: Drenagem de contenção | C43: 175.18 | D43: m | E43: =F43/C43 -> 400 | F43: 70072 | G43: =F43*($B$12/$B$11) -> 71639.161 | H43: Verba estimada para estrutura de drenagem
A44: 4.1.6 | B44: Mão de obra armação | C44: 183960 | D44: kg | E44: =F44/C44 -> 2.5 | F44: 459900 | G44: =F44*($B$12/$B$11) -> 470185.67
A45: 4.1.7 | B45: Mão de obra concretagem | C45: 516.00659 | D45: m³ | E45: =F45/C45 -> 600 | F45: 309603.96 | G45: =F45*($B$12/$B$11) -> 316528.25
A46: 4.1.8 | B46: Mão de obra drenagem | C46: 175.18 | D46: m | E46: =F46/C46 -> 100 | F46: 17518 | G46: =F46*($B$12/$B$11) -> 17909.79
A47: 4.1.9 | B47: Mobilização | C47: 1 | D47: vb | E47: =F47/C47 -> 150000 | F47: 150000 | G47: =F47*($B$12/$B$11) -> 153354.75 | H47: Previsão de mobilização de maquinários
A48: 4.1.10 | B48: Forma para viga de coroamento - 40x40 | C48: 140.144 | D48: m2 | E48: =F48/C48 -> 50 | F48: 7007.2 | G48: =F48*($B$12/$B$11) -> 7163.9161 | H48: Forma de compensado resinado com 2 reutilizações
A49: 4.1.11 | B49: Concreto para viga de coroamento | C49: 28.0288 | D49: m3 | E49: =F49/C49 -> 619.5 | F49: 17363.842 | G49: =F49*($B$12/$B$11) -> 17752.184 | H49: Consideração de R$ 590,00/m³ com 5% de perda
A50: 4.1.12 | B50: Armação para viga de coroamento | C50: 2242.304 | D50: vb | E50: =F50/C50 -> 7.3 | F50: 16368.819 | G50: =F50*($B$12/$B$11) -> 16734.908 | H50: Consideração de R$ 7,30/kg com 7% de perda
A51: 4.1.13 | B51: Mão de obra para viga de coroamento | C51: 28.0288 | D51: m³ | E51: =F51/C51 -> 950 | F51: 26627.36 | G51: =F51*($B$12/$B$11) -> 27222.881
A52: 5 | B52: SUPRAESTRUTURA | F52: =F53+F56+F59+F61+F66+F63 -> 53675068 | G52: =G53+G56+G59+G61+G66+G63 -> 54875511
A53: 5.1 | B53: FORMA | F53: =SUM(F54:F55) -> 3543821 | G53: =SUM(G54:G55) -> 3623078.6
A54: 5.1.1 | B54: Fabricação forma | C54: ='[9]Orçamento Resumo FASE 1'!C54+'[9]Orçamento Resumo FASE 2'!C20 -> 27052.069 | D54: m² | E54: =F54/C54 -> 95 | F54: ='[9]Orçamento Resumo FASE 1'!F54+'[9]Orçamento Resumo FASE 2'!F20 -> 2569946.5 | G54: =F54*($B$12/$B$11) -> 2627423.4 | H54: Forma com compensado plastificado - 8 reutilizações
A55: 5.1.2 | B55: Montagem de forma | C55: ='[9]Orçamento Resumo FASE 1'!C55+'[9]Orçamento Resumo FASE 2'!C21 -> 216416.55 | D55: m² | E55: =F55/C55 -> 4.5 | F55: ='[9]Orçamento Resumo FASE 1'!F55+'[9]Orçamento Resumo FASE 2'!F21 -> 973874.48 | G55: =F55*($B$12/$B$11) -> 995655.19
A56: 5.2 | B56: ESCORAMENTO | F56: =SUM(F57:F58) -> 3945644.1 | G56: =SUM(G57:G58) -> 4033888.5
A57: 5.2.1 | B57: Escoramento - Torre | C57: ='[9]Orçamento Resumo FASE 1'!C57+'[9]Orçamento Resumo FASE 2'!C23 -> 51981.6 | D57: m² | E57: =F57/C57 -> 45 | F57: ='[9]Orçamento Resumo FASE 1'!F57+'[9]Orçamento Resumo FASE 2'!F23 -> 2339172 | G57: =F57*($B$12/$B$11) -> 2391487.6 | H57: Locação de escoramento metálico
A58: 5.2.2 | B58: Escoramento - Embasamento | C58: ='[9]Orçamento Resumo FASE 1'!C58+'[9]Orçamento Resumo FASE 2'!C24 -> 35699.38 | D58: m² | E58: =F58/C58 -> 45 | F58: ='[9]Orçamento Resumo FASE 1'!F58+'[9]Orçamento Resumo FASE 2'!F24 -> 1606472.1 | G58: =F58*($B$12/$B$11) -> 1642400.9 | H58: Locação de escoramento metálico
A59: 5.3 | B59: ARMADURA | F59: =F60 -> 14218567 | G59: =G60 -> 14536566
A60: 5.3.1 | B60: Armadura Convencional para Estrutura | C60: ='[9]Orçamento Resumo FASE 1'!C60+'[9]Orçamento Resumo FASE 2'!C26 -> 1947749 | D60: kg | E60: =F60/C60 -> 7.3 | F60: ='[9]Orçamento Resumo FASE 1'!F60+'[9]Orçamento Resumo FASE 2'!F26 -> 14218567 | G60: =F60*($B$12/$B$11) -> 14536566 | H60: Consideração de R$ 7,00/kg
A61: 5.4 | B61: CONCRETO | F61: =F62 -> 14088717 | G61: =G62 -> 14403812
A62: 5.4.1 | B62: Concreto | C62: ='[9]Orçamento Resumo FASE 1'!C62+'[9]Orçamento Resumo FASE 2'!C28 -> 21641.655 | D62: m³ | E62: =F62/C62 -> 651 | F62: ='[9]Orçamento Resumo FASE 1'!F62+'[9]Orçamento Resumo FASE 2'!F28 -> 14088717 | G62: =F62*($B$12/$B$11) -> 14403812 | H62: Consideração de 620,00/m³ com 5% de perda
A63: 5.5 | B63: COMPLEMENTARES | F63: =F65+F64 -> 564993.9 | G63: =G65+G64 -> 577630
A64: 5.5.1 | B64: Junta de dilatação | C64: ='[9]Orçamento Resumo FASE 1'!C64+'[9]Orçamento Resumo FASE 2'!C30 -> 748.59 | D64: m | E64: =F64/C64 -> 80 | F64: ='[9]Orçamento Resumo FASE 1'!F64+'[9]Orçamento Resumo FASE 2'!F30 -> 59887.2 | G64: =F64*($B$12/$B$11) -> 61226.578 | H64: Perímetro de projeção torre
A65: 5.5.1 | B65: Estrutura metálica lazer | C65: ='[9]Orçamento Resumo FASE 1'!C65+'[9]Orçamento Resumo FASE 2'!C31 -> 687.22 | D65: m² | E65: =F65/C65 -> 735 | F65: ='[9]Orçamento Resumo FASE 1'!F65+'[9]Orçamento Resumo FASE 2'!F31 -> 505106.7 | G65: =F65*($B$12/$B$11) -> 516403.42 | H65: Valor estimado com base na área do detalhe
A66: 5.6 | B66: MÃO DE OBRA | F66: =F67 -> 17313324 | G66: =G67 -> 17700537
A67: 5.6.1 | B67: Mão de obra supraestrutura | C67: ='[9]Orçamento Resumo FASE 1'!C67+'[9]Orçamento Resumo FASE 2'!C33 -> 86566.62 | D67: m² | E67: =F67/C67 -> 200 | F67: ='[9]Orçamento Resumo FASE 1'!F67+'[9]Orçamento Resumo FASE 2'!F33 -> 17313324 | G67: =F67*($B$12/$B$11) -> 17700537 | H67: Valor estimado com base na área construida | I67: É para mão de obra de armação e para a concretagem? | J67: Mão de obra para fabricação e montagem de forma, armação, concretagem, transporte e todos demias itens previstos para execução da estrutura
A68: 6 | B68: ALVENARIA | F68: =F69 -> 10102861 | G68: =G69 -> 10328811 | H68: Quantitativos extraídos do modelo preliminar .rvt
A69: 6.1 | B69: ALVENARIA | F69: =SUM(F70:F75) -> 10102861 | G69: =SUM(G70:G75) -> 10328811
A70: 6.1.1 | B70: Alvenaria externa | C70: ='[9]Orçamento Resumo FASE 1'!C70+'[9]Orçamento Resumo FASE 2'!C36 -> 36045.94 | D70: m² | E70: =F70/C70 -> 41 | F70: ='[9]Orçamento Resumo FASE 1'!F70+'[9]Orçamento Resumo FASE 2'!F36 -> 1477883.5 | G70: =F70*($B$12/$B$11) -> 1510936.4 | H70: Fechamento com bloco 19cm e assentamento com argamassa usinada
A71: 6.1.2 | B71: Alvenaria interna | C71: ='[9]Orçamento Resumo FASE 1'!C71+'[9]Orçamento Resumo FASE 2'!C37 -> 53117.56 | D71: m² | E71: =F71/C71 -> 30 | F71: ='[9]Orçamento Resumo FASE 1'!F71+'[9]Orçamento Resumo FASE 2'!F37 -> 1593526.8 | G71: =F71*($B$12/$B$11) -> 1629166 | H71: Fechamento com bloco 11.5cm e assentamento com argamassa usinada
A72: 6.1.3 | B72: Tijolo refratário | C72: ='[9]Orçamento Resumo FASE 1'!C72+'[9]Orçamento Resumo FASE 2'!C38 -> 2860.42 | D72: m² | E72: =F72/C72 -> 320 | F72: ='[9]Orçamento Resumo FASE 1'!F72+'[9]Orçamento Resumo FASE 2'!F38 -> 915334.4 | G72: =F72*($B$12/$B$11) -> 935805.86 | H72: Em churrasqueiras
A73: 6.1.4 | B73: Serviços complementares | C73: ='[9]Orçamento Resumo FASE 1'!C73+'[9]Orçamento Resumo FASE 2'!C39 -> 89163.5 | D73: m² | E73: =F73/C73 -> 8.2 | F73: ='[9]Orçamento Resumo FASE 1'!F73+'[9]Orçamento Resumo FASE 2'!F39 -> 731140.7 | G73: =F73*($B$12/$B$11) -> 747492.67
A74: 6.1.5 | B74: Fechamento parede contenção | C74: 2102.16 | D74: m² | E74: =F74/C74 -> 635.5 | F74: 1335922.7 | G74: =F74*($B$12/$B$11) -> 1365800.6 | H74: Concreto com tela e manta geotextil
A75: 6.1.6 | B75: Mão de obra | C75: ='[9]Orçamento Resumo FASE 1'!C74+'[9]Orçamento Resumo FASE 2'!C40 -> 48823.795 | D75: m² | E75: =F75/C75 -> 82.931949 | F75: ='[9]Orçamento Resumo FASE 1'!F75+'[9]Orçamento Resumo FASE 2'!F40 -> 4049052.5 | G75: =F75*($B$12/$B$11) -> 4139609.6
A76: 7 | B76: INSTALAÇÕES ELÉTRICAS, HIDRÁULICAS E GLP | F76: =F77+F86+F93 -> 27961018 | G76: =G77+G86+G93 -> 28586367 | H76: Valores estimados com base em índices históricos por área construida
A77: 7.1 | B77: INSTALAÇÕES ELÉTRICAS | F77: =SUM(F78:F85) -> 13461109 | G77: =SUM(G78:G85) -> 13762167
A78: 7.1.1 | B78: Entrada de Energia | C78: 1 | D78: vb | E78: =F78/C78 -> 476116.41 | F78: ='[9]Orçamento Resumo FASE 1'!F78+'[9]Orçamento Resumo FASE 2'!F43 -> 476116.41 | G78: =F78*($B$12/$B$11) -> 486764.76
A79: 7.1.2 | B79: Eletrodutos e Eletrocalhas | C79: 1 | D79: vb | E79: =F79/C79 -> 865666.2 | F79: ='[9]Orçamento Resumo FASE 1'!F79+'[9]Orçamento Resumo FASE 2'!F44 -> 865666.2 | G79: =F79*($B$12/$B$11) -> 885026.83
A80: 7.1.3 | B80: Instalações Embutidas e Aparentes | C80: 1 | D80: vb | E80: =F80/C80 -> 1298499.3 | F80: ='[9]Orçamento Resumo FASE 1'!F80+'[9]Orçamento Resumo FASE 2'!F45 -> 1298499.3 | G80: =F80*($B$12/$B$11) -> 1327540.3
A81: 7.1.4 | B81: Cabos e Fiações | C81: 1 | D81: vb | E81: =F81/C81 -> 2596998.6 | F81: ='[9]Orçamento Resumo FASE 1'!F81+'[9]Orçamento Resumo FASE 2'!F46 -> 2596998.6 | G81: =F81*($B$12/$B$11) -> 2655080.5
A82: 7.1.5 | B82: Quadros e Disjuntores | C82: 1 | D82: vb | E82: =F82/C82 -> 1298499.3 | F82: ='[9]Orçamento Resumo FASE 1'!F82+'[9]Orçamento Resumo FASE 2'!F47 -> 1298499.3 | G82: =F82*($B$12/$B$11) -> 1327540.3
A83: 7.1.6 | B83: Acabamentos Elétricos | C83: 1 | D83: vb | E83: =F83/C83 -> 1298499.3 | F83: ='[9]Orçamento Resumo FASE 1'!F83+'[9]Orçamento Resumo FASE 2'!F48 -> 1298499.3 | G83: =F83*($B$12/$B$11) -> 1327540.3
A84: 7.1.7 | B84: Equipamentos e Iluminação | C84: 1 | D84: vb | E84: =F84/C84 -> 1298499.3 | F84: ='[9]Orçamento Resumo FASE 1'!F84+'[9]Orçamento Resumo FASE 2'!F49 -> 1298499.3 | G84: =F84*($B$12/$B$11) -> 1327540.3
A85: 7.1.8 | B85: Mão de Obra para Instalações Elétricas | C85: 1 | D85: vb | E85: =F85/C85 -> 4328331 | F85: ='[9]Orçamento Resumo FASE 1'!F85+'[9]Orçamento Resumo FASE 2'!F50 -> 4328331 | G85: =F85*($B$12/$B$11) -> 4425134.2 | H85: =G85/CÁLCULO_MÉDIAS!$AD$1 -> 50.835325
A86: 7.2 | B86: INSTALAÇÕES HIDRÁULICAS | F86: =SUM(F87:F92) -> 11946194 | G86: =SUM(G87:G92) -> 12213370
A87: 7.2.1 | B87: Instalações de Água Fria | C87: 1 | D87: vb | E87: =F87/C87 -> 1731332.4 | F87: ='[9]Orçamento Resumo FASE 1'!F87+'[9]Orçamento Resumo FASE 2'!F52 -> 1731332.4 | G87: =F87*($B$12/$B$11) -> 1770053.7
A88: 7.2.2 | B88: Instalações de Água Quente | C88: 1 | D88: vb | E88: =F88/C88 -> 1558199.2 | F88: ='[9]Orçamento Resumo FASE 1'!F88+'[9]Orçamento Resumo FASE 2'!F53 -> 1558199.2 | G88: =F88*($B$12/$B$11) -> 1593048.3
A89: 7.2.3 | B89: Instalações de Águas Pluviais | C89: 1 | D89: vb | E89: =F89/C89 -> 865666.2 | F89: ='[9]Orçamento Resumo FASE 1'!F89+'[9]Orçamento Resumo FASE 2'!F54 -> 865666.2 | G89: =F89*($B$12/$B$11) -> 885026.83
A90: 7.2.4 | B90: Instalações Sanitárias | C90: 1 | D90: vb | E90: =F90/C90 -> 1298499.3 | F90: ='[9]Orçamento Resumo FASE 1'!F90+'[9]Orçamento Resumo FASE 2'!F55 -> 1298499.3 | G90: =F90*($B$12/$B$11) -> 1327540.3
A91: 7.2.5 | B91: Louças e Metais | C91: 1 | D91: vb | E91: =F91/C91 -> 2596998.6 | F91: ='[9]Orçamento Resumo FASE 1'!F91+'[9]Orçamento Resumo FASE 2'!F56 -> 2596998.6 | G91: =F91*($B$12/$B$11) -> 2655080.5 | I91: Lançado em verba, já tem quantitativo? | J91: Todos os itens de instalações (etapa 7) foram estimados com base em índices por ainda não termos previsão de quantitativo
A92: 7.2.6 | B92: Mão de Obra para Instalações Hidráulicas | C92: 1 | D92: vb | E92: =F92/C92 -> 3895497.9 | F92: ='[9]Orçamento Resumo FASE 1'!F92+'[9]Orçamento Resumo FASE 2'!F57 -> 3895497.9 | G92: =F92*($B$12/$B$11) -> 3982620.8 | H92: =G92/CÁLCULO_MÉDIAS!$AD$1 -> 45.751792
A93: 7.3 | B93: INSTALAÇÕES PREVENTIVAS E GLP | F93: =SUM(F94:F97) -> 2553715.3 | G93: =SUM(G94:G97) -> 2610829.2
A94: 7.3.1 | B94: Instalações Preventivas | C94: 1 | D94: vb | E94: =F94/C94 -> 822382.89 | F94: ='[9]Orçamento Resumo FASE 1'!F94+'[9]Orçamento Resumo FASE 2'!F59 -> 822382.89 | G94: =F94*($B$12/$B$11) -> 840775.49 | H94: =G94/CÁLCULO_MÉDIAS!$AD$1 -> 9.6587117
A95: 7.3.2 | B95: Instalações de GLP | C95: 1 | D95: vb | E95: =F95/C95 -> 432833.1 | F95: ='[9]Orçamento Resumo FASE 1'!F95+'[9]Orçamento Resumo FASE 2'!F60 -> 432833.1 | G95: =F95*($B$12/$B$11) -> 442513.42 | H95: =G95/CÁLCULO_MÉDIAS!$AD$1 -> 5.0835325
A96: 7.3.3 | B96: Instalações de Proteção e Aterramento - SPDA | C96: 1 | D96: vb | E96: =F96/C96 -> 259699.86 | F96: ='[9]Orçamento Resumo FASE 1'!F96+'[9]Orçamento Resumo FASE 2'!F61 -> 259699.86 | G96: =F96*($B$12/$B$11) -> 265508.05 | H96: =G96/CÁLCULO_MÉDIAS!$AD$1 -> 3.0501195
A97: 7.3.4 | B97: Mão de Obra | C97: 1 | D97: vb | E97: =F97/C97 -> 1038799.4 | F97: ='[9]Orçamento Resumo FASE 1'!F97+'[9]Orçamento Resumo FASE 2'!F62 -> 1038799.4 | G97: =F97*($B$12/$B$11) -> 1062032.2 | H97: =G97/CÁLCULO_MÉDIAS!$AD$1 -> 12.200478
A98: 8 | B98: SISTEMAS ESPECIAIS | F98: =F99+F104+F108+F110 -> 26550840 | G98: =G99+G104+G108+G110 -> 27144650
A99: 8.1 | B99: CLIMATIZAÇÃO, EXAUSTÃO MECÂNICA E PRESSURIZAÇÃO | F99: =SUM(F100:F103) -> 10604665 | G99: =SUM(G100:G103) -> 10841838
A100: 8.1.1 | B100: Infraestrutura para Instalação de Ar Condicionado | C100: ='[9]Orçamento Resumo FASE 1'!C100+'[9]Orçamento Resumo FASE 2'!C65 -> 63963.1 | D100: m² | E100: =F100/C100 -> 150 | F100: ='[9]Orçamento Resumo FASE 1'!F100+'[9]Orçamento Resumo FASE 2'!F65 -> 9594465 | G100: =F100*($B$12/$B$11) -> 9809045.3 | H100: Infraestrutura para ar-condicionado tipo K7 em quartos, escritórios, livings e áreas comuns
A101: 8.1.2 | B101: Instalação de Ar Condicionado | C101: ='[9]Orçamento Resumo FASE 1'!C101+'[9]Orçamento Resumo FASE 2'!C66 -> 29 | D101: un | E101: =F101/C101 -> 6000 | F101: ='[9]Orçamento Resumo FASE 1'!F101+'[9]Orçamento Resumo FASE 2'!F66 -> 174000 | G101: =F101*($B$12/$B$11) -> 177891.51 | H101: Instalação de ar-codicionado tipo K7 em áreas comuns
A102: 8.1.3 | B102: Ventokit | C102: ='[9]Orçamento Resumo FASE 1'!C102+'[9]Orçamento Resumo FASE 2'!C67 -> 378 | D102: un | E102: =F102/C102 -> 900 | F102: ='[9]Orçamento Resumo FASE 1'!F102+'[9]Orçamento Resumo FASE 2'!F67 -> 340200 | G102: =F102*($B$12/$B$11) -> 347808.58 | H102: Ventilação mecânica em banheiros enclausurados;
A103: 8.1.4 | B103: Churrasqueiras | C103: ='[9]Orçamento Resumo FASE 1'!C103+'[9]Orçamento Resumo FASE 2'!C68 -> 248 | D103: un | E103: =F103/C103 -> 2000 | F103: ='[9]Orçamento Resumo FASE 1'!F103+'[9]Orçamento Resumo FASE 2'!F68 -> 496000 | G103: =F103*($B$12/$B$11) -> 507093.05 | H103: Exaustão de churrasqueiras;
A104: 8.2 | B104: COMUNICAÇÃO | F104: =SUM(F105:F107) -> 1471632.5 | G104: =SUM(G105:G107) -> 1504545.6
A105: 8.2.1 | B105: CFTV | C105: 1 | D105: vb | E105: =F105/C105 -> 173133.24 | F105: ='[9]Orçamento Resumo FASE 1'!F105+'[9]Orçamento Resumo FASE 2'!F70 -> 173133.24 | G105: =F105*($B$12/$B$11) -> 177005.37
A106: 8.2.2 | B106: Interfone | C106: 1 | D106: vb | E106: =F106/C106 -> 605966.34 | F106: ='[9]Orçamento Resumo FASE 1'!F106+'[9]Orçamento Resumo FASE 2'!F71 -> 605966.34 | G106: =F106*($B$12/$B$11) -> 619518.78
...
