Workbook
Name \0: #REF!
Name \0: #REF!
Name \0: #REF!
Name \0: #REF!
Name \0: #REF!
Name \1: #REF!
Name \1: #REF!
Name \a: #REF!
Name \a: #REF!
Name \a: #REF!
Name \a: #REF!
Name \b: #REF!
Name \b: #REF!
Name \c: #REF!
Name \c: #REF!
Name \d: #REF!
Name \d: #REF!
Name \e: #REF!
Name \e: #REF!
Name \i: #REF!
Name \i: #REF!
Name \J: #REF!
Name \J: #REF!
Name \k: #REF!
Name \k: #REF!
Name \l: #N/A
Name \m: #REF!
Name \m: #REF!
Name \m: #REF!
Name \m: #REF!
Name \o: #REF!
Name \o: #REF!
Name \p: #REF!
Name \p: #REF!
Name \r: #REF!
Name \r: #REF!
Name \T: #REF!
Name \T: #REF!
Name \z: #REF!
Name \z: #REF!
Name \z: #REF!
Name \z: #REF!
Name _: #REF!
Name _: #REF!
Name _: #REF!
Name _: #REF!
Name _: #REF!
Name _: #REF!
Name _\0: #REF!
Name _\0: #REF!
Name _\0: #REF!
Name _\0: #REF!
Name _\1: #REF!
Name _\1: #REF!
Name _\a: #REF!
Name _\a: #REF!
Name _\b: #REF!
Name _\b: #REF!
Name _\c: #REF!
Name _\c: #REF!

Sheet Obra 
C1: Projeto | D1: Colin Schroeder
C2: Empresa | D2: Grupo DUO
C3: Revisão | D3: R00
A4: QUADRO DE ÁREAS
B6: Descrição | C6: Unidade | E6: Quantidade | G6: Imagens
B7: MESES DE OBRA | C7: MÊS | E7: 42
B8: ÁREA DO TERRENO | C8: M² | E8: 1410.3
B9: ÁREA CONSTRUÍDA | C9: M² | E9: =SUM($E$15:$E$25) -> 6918.78
B10: NÚMERO DE UNIDADES HABITACIONAIS | C10: UN | E10: =1*2*15 -> 30
B11: NÚMERO DE UNIDADES COMERCIAIS | C11: UN
B12: ÁREA PRIVATIVA | C12: M²
B13: NÚMERO DE PAVIMENTOS | C13: UN | E13: 23
B15: 3º Subsolo | C15: M² | E15: 563.09
B16: 2º Subsolo | C16: M² | E16: 563.09
B17: 1º Subsolo | C17: M² | E17: 492.75
B18: Térreo | C18: M² | E18: 461.09
B19: 2º Pavimento | C19: M² | E19: 297.7
B20: Pavimentos Tipos (x15) | C20: M² | E20: =274.77*15 -> 4121.55 | G20: =E20/15 -> 274.77
B21: Cobertura | C21: M² | E21: 283.92
B22: Barrilete | C22: M² | E22: 39.73
B23: Reservatórios | C23: M² | E23: 39.73
B24: Urbanização | C24: M² | E24: 56.13
C25: M²
B31: ETAPA | C31: VALOR ORÇADO | D31: % | E31: VALOR / m²
B32: GERENCIAMENTO TÉCNICO E ADMINISTRATIVO | C32: ='Ger_Tec e Adm'!N122 -> 4773890.6 | D32: =C32/C$50 -> 0.16771847 | E32: =C32/$E$9 -> 689.99023
B33: MOVIMENTAÇÃO DE TERRA | C33: =Ger_Executivo!N8 -> 495334.16 | D33: =C33/C$50 -> 0.017402302 | E33: =C33/$E$9 -> 71.592703
B34: INFRAESTRUTURA | C34: =Ger_Executivo!N24 -> 1269914.5 | D34: =C34/C$50 -> 0.044615206 | E34: =C34/$E$9 -> 183.54601
B35: CONTENÇÃO | C35: =Ger_Executivo!N52 -> 1540547.1 | D35: =C35/C$50 -> 0.054123192 | E35: =C35/$E$9 -> 222.66167
B36: SUPRAESTRUTURA | C36: =Ger_Executivo!N71 -> 4631663.2 | D36: =C36/C$50 -> 0.16272167 | E36: =C36/$E$9 -> 669.43352
B37: ALVENARIA | C37: =Ger_Executivo!N85 -> 995637.47 | D37: =C37/C$50 -> 0.034979183 | E37: =C37/$E$9 -> 143.90362
B38: IMPERMEABILIZAÇÃO E TRATAMENTOS | C38: =Ger_Executivo!N102 -> 578916.37 | D38: =C38/C$50 -> 0.02033875 | E38: =C38/$E$9 -> 83.673187
B39: INSTALAÇÕES ELÉTRICAS, HIDRÁULICAS, GLP E PREVENTIVAS | C39: =Ger_Executivo!N127+Ger_Executivo!N139+Ger_Executivo!N155+Ger_Executivo!N167 -> 2103665.3 | D39: =C39/C$50 -> 0.073906913 | E39: =C39/$E$9 -> 304.05147
B40: EQUIPAMENTOS E SISTEMAS ESPECIAIS | C40: =Ger_Executivo!N173+Ger_Executivo!N180+Ger_Executivo!N187 -> 1243883.4 | D40: =C40/C$50 -> 0.04370067 | E40: =C40/$E$9 -> 179.78363
B41: REVESTIMENTOS INTERNOS DE PAREDE | C41: =Ger_Executivo!N196 -> 1432824 | D41: =C41/C$50 -> 0.050338616 | E41: =C41/$E$9 -> 207.092
B42: REVESTIMENTOS INTERNOS DE TETO | C42: =Ger_Executivo!N217 -> 674623.17 | D42: =C42/C$50 -> 0.023701164 | E42: =C42/$E$9 -> 97.506087
B43: PISOS E PAVIMENTAÇÕES | C43: =Ger_Executivo!N227 -> 1873726.3 | D43: =C43/C$50 -> 0.065828593 | E43: =C43/$E$9 -> 270.81744
B44: PINTURA INTERNA | C44: =Ger_Executivo!N256 -> 1176215 | D44: =C44/C$50 -> 0.041323312 | E44: =C44/$E$9 -> 170.00323
B45: ESQUADRIAS, VIDROS E FERRAGENS | C45: =Ger_Executivo!N278 -> 3144968.2 | D45: =C45/C$50 -> 0.11049043 | E45: =C45/$E$9 -> 454.55531
B46: LOUÇAS E METAIS | C46: =Ger_Executivo!N318 -> 197104.8 | D46: =C46/C$50 -> 0.0069247742 | E46: =C46/$E$9 -> 28.488375
B47: REVESTIMENTOS E ACABAMENTOS EM FACHADA | C47: =Ger_Executivo!N328 -> 1075313.7 | D47: =C47/C$50 -> 0.037778404 | E47: =C47/$E$9 -> 155.41956
B48: SERVIÇOS COMPLEMENTARES | C48: =Ger_Executivo!N352 -> 905391.4 | D48: =C48/C$50 -> 0.031808617 | E48: =C48/$E$9 -> 130.85998
B49: IMPREVISTOS | C49: =Ger_Executivo!N369 -> 350095.92 | D49: =C49/C$50 -> 0.012299727 | E49: =C49/$E$9 -> 50.600817
B50: TOTAL | C50: =SUM(C32:C49) -> 28463714 | D50: =SUM(D32:D49) -> 1 | E50: =SUM(E32:E49) -> 4113.9788
B51: CUB/SC | C51: 3012.64 | D51: 46023 | E51: =ROUNDUP(+E50/C51,2)&" CUB" -> 1,37 CUB

Sheet EPCs
A1: Obra | B1: ='Obra '!D1 -> Colin Schroeder
A2: Empresa | B2: ='Obra '!D2 -> Grupo DUO
A3: Revisão | B3: ='Obra '!D3 -> R00 | K3: Guia pavimentos
A4: Equipamentos de proteção coletiva | K4: Pavimento | L4: Área | M4: Perímetro | N4: Pé Direito
A5: Bandejas de proteção
K6: 3º Subsolo | L6: ='Obra '!E15 -> 563.09 | M6: =27.51+26.97+17.98+24.77 -> 97.23 | N6: 2.82
B7: Descrição | C7: Unidade | D7: Quantidade | F7: Imagem formulário | K7: 2º Subsolo | L7: ='Obra '!E16 -> 563.09 | M7: =27.51+26.97+17.98+24.77 -> 97.23 | N7: 2.82
B8: Perímetro de projeção embasamento | C8: m | D8: =M9 -> 97.23 | K8: 1º Subsolo | L8: ='Obra '!E17 -> 492.75 | M8: =27.51+26.97+17.98+24.77 -> 97.23 | N8: 2.82
B9: Perímetro de projeção Primária tipo 1 | C9: m | K9: Térreo | L9: ='Obra '!E18 -> 461.09 | M9: =27.51+26.97+17.98+24.77 -> 97.23 | N9: 3.3
B10: Perímetro de projeção torre tipo 1 | C10: m | D10: =M10 -> 71.85 | K10: 2º Pavimento | L10: ='Obra '!E19 -> 297.7 | M10: =20.05+11.8+19.46+17.06+1.8+1.68 -> 71.85 | N10: 2.68 | O10: 43.856
B11: Bandeja de proteção primária | C11: m | D11: =D8+D9 -> 97.23 | K11: 3º Pavimento - Tipo | L11: ='Obra '!$E$20/15 -> 274.77 | M11: =20.05+11.8+19.46+17.06+1.8+1.68 -> 71.85 | N11: 2.68 | O11: 53.717
B12: Bandeja de proteção secundária | C12: m | D12: =D10 -> 71.85 | K12: 4º Pavimento - Tipo | L12: ='Obra '!$E$20/15 -> 274.77 | M12: =20.05+11.8+19.46+17.06+1.8+1.68 -> 71.85 | N12: 2.68
B13: * Considerado as informações do Projeto de Segurança | K13: 5º Pavimento - Tipo | L13: ='Obra '!$E$20/15 -> 274.77 | M13: =20.05+11.8+19.46+17.06+1.8+1.68 -> 71.85 | N13: 2.68
A14: Guarda - corpo de vãos | K14: 6º Pavimento - Tipo | L14: ='Obra '!$E$20/15 -> 274.77 | M14: =20.05+11.8+19.46+17.06+1.8+1.68 -> 71.85 | N14: 2.68
K15: 7º Pavimento - Tipo | L15: ='Obra '!$E$20/15 -> 274.77 | M15: =20.05+11.8+19.46+17.06+1.8+1.68 -> 71.85 | N15: 2.68
B16: Descrição | C16: Unidade | D16: Quantidade | F16: Imagem formulário | K16: 8º Pavimento - Tipo | L16: ='Obra '!$E$20/15 -> 274.77 | M16: =20.05+11.8+19.46+17.06+1.8+1.68 -> 71.85 | N16: 2.68
B17: Perímetro de vãos | C17: m | D17: =43.86+53.72*15+74.65 -> 924.31 | K17: 9º Pavimento - Tipo | L17: ='Obra '!$E$20/15 -> 274.77 | M17: =20.05+11.8+19.46+17.06+1.8+1.68 -> 71.85 | N17: 2.68
B18: Guarda - corpo de vãos | C18: m | D18: =D17 -> 924.31 | K18: 10º Pavimento - Tipo | L18: ='Obra '!$E$20/15 -> 274.77 | M18: =20.05+11.8+19.46+17.06+1.8+1.68 -> 71.85 | N18: 2.68
K19: 11º Pavimento - Tipo | L19: ='Obra '!$E$20/15 -> 274.77 | M19: =20.05+11.8+19.46+17.06+1.8+1.68 -> 71.85 | N19: 2.68
A20: Guarda - corpo de desforma | K20: 12º Pavimento - Tipo | L20: ='Obra '!$E$20/15 -> 274.77 | M20: =20.05+11.8+19.46+17.06+1.8+1.68 -> 71.85 | N20: 2.68
K21: 13º Pavimento - Tipo | L21: ='Obra '!$E$20/15 -> 274.77 | M21: =20.05+11.8+19.46+17.06+1.8+1.68 -> 71.85 | N21: 2.68
B22: Descrição | C22: Unidade | D22: Quantidade | F22: Imagem formulário | K22: 14º Pavimento - Tipo | L22: ='Obra '!$E$20/15 -> 274.77 | M22: =20.05+11.8+19.46+17.06+1.8+1.68 -> 71.85 | N22: 2.68
B23: Perímetro de projeção da torre | C23: m | D23: =M10 -> 71.85 | K23: 15º Pavimento - Tipo | L23: ='Obra '!$E$20/15 -> 274.77 | M23: =20.05+11.8+19.46+17.06+1.8+1.68 -> 71.85 | N23: 2.68
B24: Repetições de pavimentos** | C24: un | D24: 4 | K24: 16º Pavimento - Tipo | L24: ='Obra '!$E$20/15 -> 274.77 | M24: =20.05+11.8+19.46+17.06+1.8+1.68 -> 71.85 | N24: 2.68
B25: Proteção de periferia pós desforma torre | C25: m | D25: =(D23*D24) -> 287.4 | K25: 17º Pavimento - Tipo | L25: ='Obra '!$E$20/15 -> 274.77 | M25: =20.05+11.8+19.46+17.06+1.8+1.68 -> 71.85 | N25: 2.68
K26: Nível técnico | L26: =L25 -> 274.77 | N26: 1.44 | O26: NÃO CONSIDERADO ÁREA CONSTRUÍDA
A27: Fechamento removível de vãos em madeira | K27: Plano de cobertura | L27: ='Obra '!E21 -> 283.92 | N27: 3.1 | O27: 74.65
K28: Reservatórios | L28: ='Obra '!E22 -> 39.73 | N28: 3.95
B29: Descrição | C29: Unidade | D29: Quantidade | F29: Imagem formulário | K29: Cob. Reservatório | L29: =L28 -> 39.73 | N29: 1.7
B30: Área das portas de elevadores | C30: m2 | D30: =0.9*2.1 -> 1.89
B31: Quantidade de elevadores | C31: un | D31: 2
B32: Quantidade de portas de elevadores | C32: un | D32: 22
B33: Fechamento removível de vãos em madeira | C33: m2 | D33: =D30*D32 -> 41.58
B34: Área das portas de aptos | C34: m2
B35: Quantidade de aptos | C35: un
B36: =A27 -> Fechamento removível de vãos em madeira | C36: m2 | D36: =D34*D35 -> 0
A38: Fechamento removível de vãos de portas de entrada de apto em madeira
B40: Descrição | C40: Unidade | D40: Quantidade | F40: Imagem formulário
B41: Área das portas de entrada | C41: m2 | D41: =0.9*2.1 -> 1.89
B42: Quantidade de portas de entrada | C42: un | D42: =1+2*15 -> 31
B43: Fechamento removível de vãos em madeira | C43: m2 | D43: =D41*D42 -> 58.59
B44: Área das portas de aptos | C44: m2
B45: Quantidade de aptos | C45: un
B46: =A38 -> Fechamento removível de vãos de portas de entrada de apto em madeira | C46: m2 | D46: =D44*D45 -> 0
A48: Tela fachadeira
B50: Descrição | C50: Unidade | D50: Quantidade | F50: Imagem formulário
B51: Area da fachada | C51: m² | D51: =SUMPRODUCT($M$9:$M$29,$N$9:$N$29) -> 3401.787
B52: =A48 -> Tela fachadeira | C52: m2 | D52: =D51 -> 3401.787
A54: SLQA
B56: Descrição | C56: Unidade | D56: Quantidade | F56: Imagem formulário
B57: Perímetro de projeção da torre 1 | C57: m | D57: =$M$22 -> 71.85
B58: Altura de cobrimento da tela | C58: un | D58: =N27+N26 -> 4.54
B59: =A54 -> SLQA | C59: m2 | D59: =D57*D58 -> 326.199
A62: Tapume
B64: Descrição | C64: Unidade | D64: Quantidade | F64: Imagem formulário
B65: Perímetro de encontro com pavimentação | C65: m | D65: =27.86+27.42 -> 55.28
B66: Altura do tapume | C66: m | D66: 2.4
B67: =A62 -> Tapume | C67: m2 | D67: =D66*D65 -> 132.672
A69: Linha de Vida
B71: Descrição | C71: Unidade | D71: Quantidade | F71: Imagem formulário
B72: Perímetro de Pavimentos | C72: m | D72: =$D$25 -> 287.4
B73: =A69 -> Linha de Vida | C73: m | D73: =D72 -> 287.4
A75: Cobertura para Proteção de Pedestres
B77: Descrição | C77: Unidade | D77: Quantidade | F77: Imagem formulário
B78: Perímetro de projeção torre | C78: m
B79: Altura de cobrimento da tela | C79: m
B80: Cobertura para Proteção de Pedestres | C80: m2 | D80: =D78*D79 -> 0

Sheet CANTEIRO
A1: Obra | B1: ='Obra '!D1 -> Colin Schroeder
A2: Empresa | B2: ='Obra '!D2 -> Grupo DUO
A3: Revisão | B3: ='Obra '!D3 -> R00 | O3: Número de funcionários | S3: Produtividade média (h/m2)
A4: Instalações de canteiro | O4: Área construída | P4: 6601.277 | S4: A.C/prazo | T4: =P4/P5 -> 235.75989
A5: Instalações de canteiro | O5: Prazo da obra | P5: 28 | Q5: meses | S5: Pm | T5: 49 | U5: h/m2
O6: NF | P6: =ROUNDUP((P4*T5)/P5/180,) -> 65 | Q6: funcionários
B7: Descrição | C7: Unidade | D7: Quantidade | O7: Pavimentos | P7: 10
B8: Produtividade média | C8: m2 / mês | D8: ='Obra '!$E$9/'Obra '!$E$7 -> 164.73286 | O8: Equipe administrativa | P8: 5 | Q8: funcionários
B9: Pm | C9: h/m2 | D9: 49
B10: Numero de funcionários | C10: un | D10: =ROUNDUP((D9*'Obra '!$E$9)/'Obra '!$E$7/180,) -> 45
B11: Equipe administrativa | C11: un | D11: 5 | O11: Barracão interno | P11: =450+(P4-13000)/1000*16 -> 347.62043
B12: Pontos de água e esgoto | C12: un | D12: =ROUNDUP($D$10/20,0) -> 3 | E12: 20 funcionários/ponto | O12: Externo | P12: =P11*0.4 -> 139.04817
B13: Bebedouro | C13: un | D13: =ROUNDUP('Obra '!$E$13/5,0) -> 5 | E13: 1 / 5 pav.
B14: Ferramentas | C14: R$ | D14: =800*D10 -> 36000 | E14: 800,00/func. | P14: =SUM(P11:P13) -> 486.6686
B15: EPI | C15: R$ | D15: =500*(D10+D11)*ROUND('Obra '!E7/12,0) -> 100000 | E15: 500,00/func./ano
B16: Banheiro | C16: un | D16: =ROUNDUP($D$10/20,0) -> 3 | E16: 1/20 func | O16: Área refeitório | P16: 1 | Q16: m²/funcionários
P17: =P16*P6 -> 65 | Q17: m²
A18: Mobiliário de canteiro
O19: Área de vestiário | P19: 1.5 | Q19: m²/funcionários
B20: Descrição | C20: Unidade | D20: Quantidade | E20: Custo unitário | F20: Custo total | P20: =P19*P6 -> 97.5 | Q20: m²
B21: Cadeira | C21: un | D21: =ROUNDUP(D11*1.5,) -> 8 | E21: 200 | F21: =D21*E21 -> 1600
B22: Mesa | C22: un | D22: 1 | E22: 1000 | F22: =E22*D22 -> 1000
B23: Ar condicionado | C23: un | D23: 2 | E23: 5000 | F23: =E23*D23 -> 10000
B24: Armário | C24: m | D24: 4 | E24: 900 | F24: =E24*D24 -> 3600
B25: Escrivaninha | C25: un | D25: =D11 -> 5 | E25: 800 | F25: =E25*D25 -> 4000
B26: TOTAL | F26: =F23+F24+F25+F22+F21 -> 20200
B27: Descrição | C27: Unidade | D27: Quantidade | E27: Custo unitário | F27: Custo total
B28: Computador pessoal | C28: un | D28: =D11 -> 5 | E28: 6500 | F28: =D28*E28 -> 32500
B29: Impressora | C29: un | D29: 1 | E29: 2000 | F29: =E29*D29 -> 2000
B30: Roteador | C30: un | D30: 2 | E30: 500 | F30: =E30*D30 -> 1000
B31: TOTAL | F31: =+F28+F29+F30 -> 35500 | O31: Área sanitários | P31: =1*ROUNDUP(P6/20,) -> 4 | Q31: m²
A33: Instalações Provisórias (central de aço, formas, argamassa, almoxarifado geral, construções temporárias) | O33: área lavatório | P33: =0.6*ROUNDUP(P6/20,) -> 2.4 | Q33: m²
O34: Área de chuveiros | P34: =0.8*ROUNDUP(P6/10,) -> 5.6 | Q34: m²
B35: Descrição | C35: Unidade | D35: Será utilizado | E35: Quantidade | F35: Custo unitário | G35: Custo total
B36: Central de aço | C36: m2 | D36: Sim | E36: =IF(D36="Sim",15,0) -> 15 | F36: 115.4849 | G36: =IF(D36="sim",E36*F36,0) -> 1732.2735
B37: Central de fôrmas | C37: m2 | D37: Sim | E37: =IF(D37="Sim",15,0) -> 15 | F37: 115.4849 | G37: =IF(D37="sim",E37*F37,0) -> 1732.2735
B38: Central de Argamassa | C38: m2 | D38: Sim | E38: =IF(D38="Sim",15,0) -> 15 | F38: 115.4849 | G38: =IF(D38="sim",E38*F38,0) -> 1732.2735
B39: Armazenamento de cerâmicas* | C39: m2 | D39: Sim | E39: =IF(D39="não",0,ROUNDUP(3*'Obra '!$E$10/COUNTIFS($D$39:$D$47,"Sim"),)) -> 13 | F39: 201.22489 | G39: =IF(D39="sim",E39*F39,0) -> 2615.9236
B40: Armazenamento de placas degesso* | C40: m2 | D40: Não | E40: =IF(D40="não",0,ROUNDUP(3*'Obra '!$E$10/COUNTIFS($D$39:$D$47,"Sim"),)) -> 0 | F40: 201.22489 | G40: =IF(D40="sim",E40*F40,0) -> 0
B41: Armazenamento de blocos* | C41: m2 | D41: Sim | E41: =IF(D41="não",0,ROUNDUP(3*'Obra '!$E$10/COUNTIFS($D$39:$D$47,"Sim"),)) -> 13 | F41: 201.22489 | G41: =IF(D41="sim",E41*F41,0) -> 2615.9236
B42: Armazenamento de contramarcos* | C42: m2 | D42: Sim | E42: =IF(D42="não",0,ROUNDUP(3*'Obra '!$E$10/COUNTIFS($D$39:$D$47,"Sim"),)) -> 13 | F42: 201.22489 | G42: =IF(D42="sim",E42*F42,0) -> 2615.9236
B43: Armazenamento de portas e rodapés* | C43: m2 | D43: Sim | E43: =IF(D43="não",0,ROUNDUP(3*'Obra '!$E$10/COUNTIFS($D$39:$D$47,"Sim"),)) -> 13 | F43: 201.22489 | G43: =IF(D43="sim",E43*F43,0) -> 2615.9236
B44: Armazenamento de esquadrias* | C44: m2 | D44: Não | E44: =IF(D44="não",0,ROUNDUP(3*'Obra '!$E$10/COUNTIFS($D$39:$D$47,"Sim"),)) -> 0 | F44: 201.22489 | G44: =IF(D44="sim",E44*F44,0) -> 0
B45: Armazenamento de instalações complementares* | C45: m2 | D45: Sim | E45: =IF(D45="não",0,ROUNDUP(3*'Obra '!$E$10/COUNTIFS($D$39:$D$47,"Sim"),)) -> 13 | F45: 201.22489 | G45: =IF(D45="sim",E45*F45,0) -> 2615.9236
B46: Armazenamento para estoque geral* | C46: m2 | D46: Sim | E46: =IF(D46="não",0,ROUNDUP(3*'Obra '!$E$10/COUNTIFS($D$39:$D$47,"Sim"),)) -> 13 | F46: 201.22489 | G46: =IF(D46="sim",E46*F46,0) -> 2615.9236
B47: Construções temporárias | C47: m2 | D47: Sim | E47: =IF(D47="não",0,ROUNDUP(3*'Obra '!$E$10/COUNTIFS($D$39:$D$47,"Sim"),)) -> 13 | F47: 272.8753 | G47: =IF(D47="sim",E47*F47,0) -> 3547.3789
B48: Almoxarifado geral | C48: m2 | D48: Sim | E48: =IF(D48="Sim",10*15,0) -> 150 | F48: 272.8753 | G48: =IF(D48="sim",E48*F48,0) -> 40931.295
B49: Guarita | C49: m2 | D49: Não | E49: =IF(D49="Sim",ROUNDUP(25,),0) -> 0 | F49: 0 | G49: =IF(D49="sim",E49*F49,0) -> 0
B50: Lava Rodas | C50: m2 | D50: Sim | E50: =IF(D50="Sim",ROUNDUP(25,),0) -> 25 | F50: 0 | G50: =IF(D50="sim",E50*F50,0) -> 0
B51: TOTAL | G51: =SUM(G36:G50) -> 65371.036
O52: área lavatório | P52: =0.6*ROUNDUP(P21/20,) -> 0 | Q52: m²
B53: * Central de armazenamento entre pavimentos
O54: Área de chuveiros | P54: =0.8*ROUNDUP(P21/10,) -> 0 | Q54: m²
A55: Sinalização
B57: Descrição | C57: Unidade | D57: Será utilizado | E57: Quantidade | F57: Custo unitário | G57: Custo total
B58: Placa indicativa fixada na estrutura por pregos | C58: VB | D58: Sim | E58: 1 | F58: 7891.02 | G58: =IF(D58="sim",E58*F58,0) -> 7891.02 | O58: Escritório | P58: 8 | Q58: m²/pessoa
B59: Placa indicativa fixada em totem | C59: VB | D59: Sim | E59: 1 | F59: =F58*0.2 -> 1578.204 | G59: =IF(D59="sim",E59*F59,0) -> 1578.204 | P59: =P58*P8 -> 40 | Q59: m²
B60: Instalação de sinalizador noturno | C60: m2 | D60: Não | G60: =IF(D60="sim",E60*F60,0) -> 0
B61: Sinalização com fita fixada em cone | C61: m2 | D61: Não | G61: =IF(D61="sim",E61*F61,0) -> 0 | O61: Almoxarifado | P61: =IF(P4<20000,100,100+((P4-20000)/1000)*5) -> 100 | Q61: m2
B62: Sinalização com fita fixada na estrutura amarrada | C62: m2 | D62: Não | G62: =IF(D62="sim",E62*F62,0) -> 0
B63: TOTAL | G63: =SUM(G58:G62) -> 9469.224
O64: Ferramentas | P64: =P6*800 -> 52000 | Q64: 800 por funcionário
O66: EPI | P66: =P6*500 -> 32500 | Q66: 500,00 por funcionário | R66: Considerando entrega de 2 uniformes, capacete, bota, óculos e cinto
O69: Banheiro | P69: 1 | Q69: para cada | R69: 20 | S69: pessoas
P70: =ROUNDUP(P6/R69,) -> 4

Sheet Ensaios 
C1: Projeto | D1: ='Obra '!D1 -> Colin Schroeder
C2: Empresa | D2: ='Obra '!D2 -> Grupo DUO
C3: Revisão | D3: ='Obra '!D3 -> R00
A4: ENSAIOS
A5: Item | B5: Descrição/Especificação | C5: Unid. | D5: V. Unit. (R$) | E5: Qtde. | F5: V. Total (R$) | G5: Observações
B6: CONTROLE TECNOLÓGICO - CONCRETO | F6: =SUM(F7:F12) -> 50780
A7: 1 | B7: Laudo e ART | C7: vb | D7: 1450 | E7: 1 | F7: =$D7*E7 -> 1450
A8: =A7+1 -> 2 | B8: Controle Tecnologico Infraestrutura - Coleta materiais da obra | C8: unid. | D8: 20 | E8: =ROUNDUP((Ger_Executivo!L34+Ger_Executivo!L48+Ger_Executivo!L49)/8,0)*4 -> 388 | F8: =$D8*E8 -> 7760 | G8: 4 CPs por caminhão betoneira de 8m³
A9: =A8+1 -> 3 | B9: Controle Tecnologico Contenção - Coleta materiais da obra | C9: unid. | D9: 20 | E9: =ROUNDUP((Ger_Executivo!L57+Ger_Executivo!L68)/8,0)*4 -> 292 | F9: =$D9*E9 -> 5840 | G9: 4 CPs por caminhão betoneira de 8m³
A10: =A9+1 -> 4 | B10: Controle Tecnologico Supraestrutura - Coleta materiais da obra | C10: unid. | D10: 20 | E10: =ROUNDUP((Ger_Executivo!L79)/8,0)*4 -> 764 | F10: =$D10*E10 -> 15280 | G10: 4 CPs por caminhão betoneira de 8m³
A11: =A8+1 -> 3 | B11: Controle Tecnológico - Ensaio de concreto endurecido/grouth - compressão simples / Detalhe: Concreto | C11: cps | D11: 12.5 | E11: =E8+E9+E10 -> 1444 | F11: =$D11*E11 -> 18050
A12: =A11+1 -> 4 | B12: Determinação do módulo de deformação tangente inicial (Eci) (módulo de elasticidade), Incluindo Avaliação Estática dos Resultados (NBR 8522 e NBR 12655) | C12: ensaio | D12: 480 | E12: =ROUNDUP('Obra '!E13/5,0) -> 5 | F12: =$D12*E12 -> 2400 | G12: A cada 5 pav. (e quando houver troca de fornecedor)
B13: ENSAIO PARA GUARDA-CORPO | F13: =F14 -> 4210
A14: 1 | B14: Ensaio de guarda-corpo Determinação do esforço horizontal, esforço vertical e Resistencia a impactos | C14: ensaios | D14: 4210 | E14: 1 | F14: =$D14*E14 -> 4210 | G14: 1 prototipo por projeto
B15: ENSAIOS PARA ARGAMASSA DE REVESTIMENTO (FACHADA) | F15: =F16 -> 1260
A16: 1 | B16: Ensaio de arrancamento de argamassa de revestimento Determinação da aderencia a tração | C16: ensaios | D16: 1260 | E16: 1 | F16: =$D16*E16 -> 1260 | G16: 1 ensaio por torre
B17: ENSAIO ARRANCAMENTO DE REBOCO | F17: =F18 -> 1260
A18: 1 | B18: Ensaio de arrancamento de argamassa de reboco Determinação da aderencia a tração | C18: ensaios | D18: 1260 | E18: 1 | F18: =$D18*E18 -> 1260 | G18: 1 ensaio por torre
B19: ENSAIO PARA REVESTIMENTOS CERÂMICOS | F19: =F20 -> 664.44444
A20: 1 | B20: Aderência em Revestimento Cerâmico Determinação da aderência a tração (NBR 13754) | C20: ensaios | D20: 664.44444 | E20: 1 | F20: =$D20*E20 -> 664.44444 | G20: Torre Alta: 1 ensaio por torre, por referência de produto
B21: ENSAIO PARA ANCORAGEM (GANHOS DA COBERTURA) | F21: =SUM(F22) -> 1680
A22: 1 | B22: Arrancamento de ganchos da cobertura Ensaio de Arrancamento | C22: ensaios | D22: 1680 | E22: 1 | F22: =$D22*E22 -> 1680 | G22: 1 ensaio por torre
C23: SUBTOTAL: | F23: =F6+F13+F15+F17+F19+F21 -> 59854.444

Sheet BASES
A1: Estimativas Custos Indiretos
A2: Empresa | B2: ='Obra '!$D$2 -> Grupo DUO
A3: Obra | B3: ='Obra '!$D$1 -> Colin Schroeder
A4: Prazo de Obra | B4: ='Obra '!$E$7 -> 42 | H4: 30 | J4: 42 | N4: 42 | P4: 36
A5: Cidade/Estado | B5: Porto Belo - SC | H5: Navegantes - SC | J5: Itajaí - SC | L5: Porto Belo - SC | N5: Florianópolis | P5: Florianópolis
A6: R$/m² | B6: =$E$11/$B$8 -> #REF! | H6: 591.53 | J6: 419.37 | L6: 442.78 | N6: 1179.5 | P6: 1188.19
A7: Área de Terreno | B7: ='Obra '!$E$8 -> 1410.3 | H7: 463.3 | J7: 463.3 | L7: 675 | N7: 1817.53 | P7: 2498.8
A8: Área Construída | B8: ='Obra '!$E$9 -> 6918.78 | H8: 4498.66 | J8: 8366.5 | L8: 7055.73 | N8: 7013.06 | P8: 5579.63
A9: N° pavimentos | B9: ='Obra '!$E$13 -> 23 | H9: 12 | J9: 17 | L9: 19 | N9: 5 | P9: 6
A10: Cub | B10: ='Obra '!C51 -> 3012.64 | H10: 2750.52 | J10: 2747.9 | L10: 2846.12 | N10: 2907.85 | P10: 2907.85
A11: Data Cub | B11: 45616 | D11: Total | E11: =SUMPRODUCT($D$12:$D$342,$E$12:$E$342) -> #REF! | H11: 45139 | J11: 45108 | L11: 45566 | N11: 45717 | P11: 45717
A12: Descrição | C12: Unidade | D12: Quantidade | E12: Valor (R$) | F12: Status do Custo | G12: Indice Médio | H12: Valor | I12: Referência | J12: Valor | K12: Referência | L12: Valor | M12: Referência | N12: Valor | O12: Referência | P12: Valor | Q12: Referência
A13: TEC 01 – ESTUDOS, PROJETOS, CONSULTORIAS, ENSAIOS E LAUDOS
A14: ESTUDOS | E14: =SUMPRODUCT(D15:D23,E15:E23) -> 10300
A15: Memorial descritivo | C15: vb | D15: 1 | F15: Não Solicitado | G15: =IFERROR(AVERAGEIFS($H15:$Q15,H$12:Q$12,"Referência"),"") | I15: =IF(H15=0,"",($B$10/H$10)*H15/H$8) | J15: 0 | K15: =IF(J15=0,"",($B$10/J$10)*J15/J$8) | L15: 0 | M15: =IF(L15=0,"",($B$10/L$10)*L15/L$8) | O15: =IF(N15=0,"",($B$10/N$10)*N15/N$8) | Q15: =IF(P15=0,"",($B$10/P$10)*P15/P$8)
A16: Levantamento topográfico | C16: vb | D16: 1 | E16: 1800 | F16: Recebido | G16: =IFERROR(AVERAGEIFS($H16:$Q16,H$12:Q$12,"Referência"),"") -> 2.2254635 | H16: 27500 | I16: =IF(H16=0,"",($B$10/H$10)*H16/H$8) -> 6.6954836 | J16: 3500 | K16: =IF(J16=0,"",($B$10/J$10)*J16/J$8) -> 0.45863854 | L16: 5000 | M16: =IF(L16=0,"",($B$10/L$10)*L16/L$8) -> 0.75010504 | O16: =IF(N16=0,"",($B$10/N$10)*N16/N$8) | P16: 5372.77 | Q16: =IF(P16=0,"",($B$10/P$10)*P16/P$8) -> 0.99762675
A17: Estudo geológico | C17: vb | D17: 1 | F17: Não Solicitado | G17: =IFERROR(AVERAGEIFS($H17:$Q17,H$12:Q$12,"Referência"),"") | H17: 0 | I17: =IF(H17=0,"",($B$10/H$10)*H17/H$8) | J17: 0 | K17: =IF(J17=0,"",($B$10/J$10)*J17/J$8) | L17: 0 | M17: =IF(L17=0,"",($B$10/L$10)*L17/L$8) | O17: =IF(N17=0,"",($B$10/N$10)*N17/N$8) | Q17: =IF(P17=0,"",($B$10/P$10)*P17/P$8)
A18: Estudo ambiental | C18: vb | D18: 1 | F18: Não Solicitado | G18: =IFERROR(AVERAGEIFS($H18:$Q18,H$12:Q$12,"Referência"),"") -> 1.477808 | H18: 0 | I18: =IF(H18=0,"",($B$10/H$10)*H18/H$8) | J18: 11964.095 | K18: =IF(J18=0,"",($B$10/J$10)*J18/J$8) -> 1.56777 | L18: 4000 | M18: =IF(L18=0,"",($B$10/L$10)*L18/L$8) -> 0.60008403 | N18: 15000 | O18: =IF(N18=0,"",($B$10/N$10)*N18/N$8) -> 2.2159448 | P18: 8226.07 | Q18: =IF(P18=0,"",($B$10/P$10)*P18/P$8) -> 1.5274332
A19: Sondagem do terreno | C19: vb | D19: 1 | E19: 8500 | F19: Recebido | G19: =IFERROR(AVERAGEIFS($H19:$Q19,H$12:Q$12,"Referência"),"") -> 2.1530271 | H19: 12933 | I19: =IF(H19=0,"",($B$10/H$10)*H19/H$8) -> 3.1488251 | J19: 5500 | K19: =IF(J19=0,"",($B$10/J$10)*J19/J$8) -> 0.7207177 | L19: 4800 | M19: =IF(L19=0,"",($B$10/L$10)*L19/L$8) -> 0.72010084 | N19: 24620.6 | O19: =IF(N19=0,"",($B$10/N$10)*N19/N$8) -> 3.6371927 | P19: 13670.14 | Q19: =IF(P19=0,"",($B$10/P$10)*P19/P$8) -> 2.5382991
A20: Projeto de canteiro | C20: vb | D20: 1 | F20: Não Solicitado | G20: =IFERROR(AVERAGEIFS($H20:$Q20,H$12:Q$12,"Referência"),"") -> 0.58236585 | H20: 0 | I20: =IF(H20=0,"",($B$10/H$10)*H20/H$8) | J20: 0 | K20: =IF(J20=0,"",($B$10/J$10)*J20/J$8) | L20: 5000 | M20: =IF(L20=0,"",($B$10/L$10)*L20/L$8) -> 0.75010504 | N20: 2709.3 | O20: =IF(N20=0,"",($B$10/N$10)*N20/N$8) -> 0.40024395 | P20: 3213.82 | Q20: =IF(P20=0,"",($B$10/P$10)*P20/P$8) -> 0.59674857
A21: Estudo de Análise Técnica de Projeto | C21: vb | D21: 1 | F21: Não Solicitado | G21: =IFERROR(AVERAGEIFS($H21:$Q21,H$12:Q$12,"Referência"),"") | H21: 0 | I21: =IF(H21=0,"",($B$10/H$10)*H21/H$8) | J21: 0 | K21: =IF(J21=0,"",($B$10/J$10)*J21/J$8) | L21: 0 | M21: =IF(L21=0,"",($B$10/L$10)*L21/L$8) | O21: =IF(N21=0,"",($B$10/N$10)*N21/N$8) | Q21: =IF(P21=0,"",($B$10/P$10)*P21/P$8)
A22: Estudo Rebaixamento de Lençol Freático | C22: vb | D22: 1 | F22: Não Solicitado | G22: =IFERROR(AVERAGEIFS($H22:$Q22,H$12:Q$12,"Referência"),"") | H22: 0 | I22: =IF(H22=0,"",($B$10/H$10)*H22/H$8) | J22: 0 | K22: =IF(J22=0,"",($B$10/J$10)*J22/J$8) | L22: 0 | M22: =IF(L22=0,"",($B$10/L$10)*L22/L$8) | O22: =IF(N22=0,"",($B$10/N$10)*N22/N$8) | Q22: =IF(P22=0,"",($B$10/P$10)*P22/P$8)
A23: Informações complementares de Estudos | C23: vb | D23: 1 | F23: Não Solicitado | G23: =IFERROR(AVERAGEIFS($H23:$Q23,H$12:Q$12,"Referência"),"") | H23: 0 | I23: =IF(H23=0,"",($B$10/H$10)*H23/H$8) | J23: 0 | K23: =IF(J23=0,"",($B$10/J$10)*J23/J$8) | L23: 0 | M23: =IF(L23=0,"",($B$10/L$10)*L23/L$8) | O23: =IF(N23=0,"",($B$10/N$10)*N23/N$8) | Q23: =IF(P23=0,"",($B$10/P$10)*P23/P$8)
A24: Projetos - Arquitetonico | E24: =SUMPRODUCT(D25:D31,E25:E31) -> 329231.36 | I24: =IF(H24=0,"",($B$10/H$10)*H24/H$8) | K24: =IF(J24=0,"",($B$10/J$10)*J24/J$8) | M24: =IF(L24=0,"",($B$10/L$10)*L24/L$8) | O24: =IF(N24=0,"",($B$10/N$10)*N24/N$8) | Q24: =IF(P24=0,"",($B$10/P$10)*P24/P$8)
A25: Legalização de incorporação | C25: vb | D25: 1 | F25: Não Solicitado | G25: =IFERROR(AVERAGEIFS($H25:$Q25,H$12:Q$12,"Referência"),"") -> 2.890017 | H25: 15500 | I25: =IF(H25=0,"",($B$10/H$10)*H25/H$8) -> 3.7738181 | J25: 15310 | K25: =IF(J25=0,"",($B$10/J$10)*J25/J$8) -> 2.006216 | L25: 0 | M25: =IF(L25=0,"",($B$10/L$10)*L25/L$8) | O25: =IF(N25=0,"",($B$10/N$10)*N25/N$8) | Q25: =IF(P25=0,"",($B$10/P$10)*P25/P$8)
A26: Projeto Arquitetônico | C26: vb | D26: 1 | F26: Não Solicitado | G26: =IFERROR(AVERAGEIFS($H26:$Q26,H$12:Q$12,"Referência"),"") -> 10.210643 | H26: 67500 | I26: =IF(H26=0,"",($B$10/H$10)*H26/H$8) -> 16.434369 | J26: 74000 | K26: =IF(J26=0,"",($B$10/J$10)*J26/J$8) -> 9.6969291 | L26: 30000 | M26: =IF(L26=0,"",($B$10/L$10)*L26/L$8) -> 4.5006302 | O26: =IF(N26=0,"",($B$10/N$10)*N26/N$8) | Q26: =IF(P26=0,"",($B$10/P$10)*P26/P$8)
A27: Projeto Arquitetônico legal - incluindo: executivo + interiores + fachada | C27: vb | D27: 1 | E27: 320000 | F27: Recebido | G27: =IFERROR(AVERAGEIFS($H27:$Q27,H$12:Q$12,"Referência"),"") -> 4.7594165 | H27: 0 | I27: =IF(H27=0,"",($B$10/H$10)*H27/H$8) | J27: 0 | K27: =IF(J27=0,"",($B$10/J$10)*J27/J$8) | L27: 31725 | M27: =IF(L27=0,"",($B$10/L$10)*L27/L$8) -> 4.7594165 | O27: =IF(N27=0,"",($B$10/N$10)*N27/N$8) | Q27: =IF(P27=0,"",($B$10/P$10)*P27/P$8)
A28: Projeto Arquitetônico Executivo | C28: vb | D28: 1 | F28: Não Solicitado | G28: =IFERROR(AVERAGEIFS($H28:$Q28,H$12:Q$12,"Referência"),"") -> 21.584563 | H28: 0 | I28: =IF(H28=0,"",($B$10/H$10)*H28/H$8) | J28: 0 | K28: =IF(J28=0,"",($B$10/J$10)*J28/J$8) | L28: 31725 | M28: =IF(L28=0,"",($B$10/L$10)*L28/L$8) -> 4.7594165 | N28: 260000 | O28: =IF(N28=0,"",($B$10/N$10)*N28/N$8) -> 38.40971 | Q28: =IF(P28=0,"",($B$10/P$10)*P28/P$8)
A29: Projeto Arquitetônico interiores | C29: vb | D29: 1 | F29: Não Solicitado | G29: =IFERROR(AVERAGEIFS($H29:$Q29,H$12:Q$12,"Referência"),"") -> 6.9367285 | H29: 34500 | I29: =IF(H29=0,"",($B$10/H$10)*H29/H$8) -> 8.3997886 | J29: 65550 | K29: =IF(J29=0,"",($B$10/J$10)*J29/J$8) -> 8.5896446 | L29: 14100 | M29: =IF(L29=0,"",($B$10/L$10)*L29/L$8) -> 2.1152962 | N29: 58500 | O29: =IF(N29=0,"",($B$10/N$10)*N29/N$8) -> 8.6421848 | Q29: =IF(P29=0,"",($B$10/P$10)*P29/P$8)
A30: Projeto arquitetônico de fachada | C30: vb | D30: 1 | F30: Não Solicitado | G30: =IFERROR(AVERAGEIFS($H30:$Q30,H$12:Q$12,"Referência"),"") -> 1.3342472 | H30: 6200 | I30: =IF(H30=0,"",($B$10/H$10)*H30/H$8) -> 1.5095272 | J30: 2884 | K30: =IF(J30=0,"",($B$10/J$10)*J30/J$8) -> 0.37791815 | L30: 14100 | M30: =IF(L30=0,"",($B$10/L$10)*L30/L$8) -> 2.1152962 | O30: =IF(N30=0,"",($B$10/N$10)*N30/N$8) | Q30: =IF(P30=0,"",($B$10/P$10)*P30/P$8)
A31: Projeto técnico de fachada | C31: vb | D31: 1 | E31: =G31*$B$8 -> 9231.3628 | F31: Estimado | G31: =IFERROR(AVERAGEIFS($H31:$Q31,H$12:Q$12,"Referência"),"") -> 1.3342472 | H31: 6200 | I31: =IF(H31=0,"",($B$10/H$10)*H31/H$8) -> 1.5095272 | J31: 2884 | K31: =IF(J31=0,"",($B$10/J$10)*J31/J$8) -> 0.37791815 | L31: 14100 | M31: =IF(L31=0,"",($B$10/L$10)*L31/L$8) -> 2.1152962 | O31: =IF(N31=0,"",($B$10/N$10)*N31/N$8) | Q31: =IF(P31=0,"",($B$10/P$10)*P31/P$8)
A32: Projetos - Estrutural | E32: =SUMPRODUCT(D33:D37,E33:E37) -> 70469.17 | I32: =IF(H32=0,"",($B$10/H$10)*H32/H$8) | K32: =IF(J32=0,"",($B$10/J$10)*J32/J$8) | M32: =IF(L32=0,"",($B$10/L$10)*L32/L$8) | O32: =IF(N32=0,"",($B$10/N$10)*N32/N$8) | Q32: =IF(P32=0,"",($B$10/P$10)*P32/P$8)
A33: Projeto de terraplanagem | C33: vb | F33: Não Solicitado | G33: =IFERROR(AVERAGEIFS($H33:$Q33,H$12:Q$12,"Referência"),"") -> 0.19655937 | I33: =IF(H33=0,"",($B$10/H$10)*H33/H$8) | J33: 1500 | K33: =IF(J33=0,"",($B$10/J$10)*J33/J$8) -> 0.19655937 | L33: 0 | M33: =IF(L33=0,"",($B$10/L$10)*L33/L$8) | O33: =IF(N33=0,"",($B$10/N$10)*N33/N$8) | Q33: =IF(P33=0,"",($B$10/P$10)*P33/P$8)
A34: Projeto de Fundações | B34: à atualizar | C34: vb | D34: 1 | E34: =G34*$B$8 -> 20568.443 | F34: Estimado | G34: =IFERROR(AVERAGEIFS($H34:$Q34,H$12:Q$12,"Referência"),"") -> 2.9728425 | H34: 0 | I34: =IF(H34=0,"",($B$10/H$10)*H34/H$8) | J34: 7635 | K34: =IF(J34=0,"",($B$10/J$10)*J34/J$8) -> 1.0004872 | L34: 8000 | M34: =IF(L34=0,"",($B$10/L$10)*L34/L$8) -> 1.2001681 | N34: 50000 | O34: =IF(N34=0,"",($B$10/N$10)*N34/N$8) -> 7.3864828 | P34: 12409.56 | Q34: =IF(P34=0,"",($B$10/P$10)*P34/P$8) -> 2.3042321
A35: Projeto estrutural | B35: à atualizar | C35: vb | D35: 1 | E35: =G35*$B$8 -> 49900.727 | F35: Estimado | G35: =IFERROR(AVERAGEIFS($H35:$Q35,H$12:Q$12,"Referência"),"") -> 7.2123592 | H35: 29341.44 | I35: =IF(H35=0,"",($B$10/H$10)*H35/H$8) -> 7.143823 | J35: 41100 | K35: =IF(J35=0,"",($B$10/J$10)*J35/J$8) -> 5.3857268 | L35: 58000 | M35: =IF(L35=0,"",($B$10/L$10)*L35/L$8) -> 8.7012184 | O35: =IF(N35=0,"",($B$10/N$10)*N35/N$8) | P35: 41030.73 | Q35: =IF(P35=0,"",($B$10/P$10)*P35/P$8) -> 7.6186686
A36: Projeto de estrutura metálica | C36: vb | F36: Não Solicitado | G36: =IFERROR(AVERAGEIFS($H36:$Q36,H$12:Q$12,"Referência"),"") | H36: 0 | I36: =IF(H36=0,"",($B$10/H$10)*H36/H$8) | J36: 0 | K36: =IF(J36=0,"",($B$10/J$10)*J36/J$8) | L36: 0 | M36: =IF(L36=0,"",($B$10/L$10)*L36/L$8) | O36: =IF(N36=0,"",($B$10/N$10)*N36/N$8) | Q36: =IF(P36=0,"",($B$10/P$10)*P36/P$8)
A37: Projeto de alvenaria estrutural | C37: vb | F37: Não Solicitado | G37: =IFERROR(AVERAGEIFS($H37:$Q37,H$12:Q$12,"Referência"),"") | H37: 0 | I37: =IF(H37=0,"",($B$10/H$10)*H37/H$8) | J37: 0 | K37: =IF(J37=0,"",($B$10/J$10)*J37/J$8) | L37: 0 | M37: =IF(L37=0,"",($B$10/L$10)*L37/L$8) | O37: =IF(N37=0,"",($B$10/N$10)*N37/N$8) | Q37: =IF(P37=0,"",($B$10/P$10)*P37/P$8)
A38: Projetos - Complementares | E38: =SUMPRODUCT(D39:D56,E39:E56) -> 114402.62 | I38: =IF(H38=0,"",($B$10/H$10)*H38/H$8) | K38: =IF(J38=0,"",($B$10/J$10)*J38/J$8) | M38: =IF(L38=0,"",($B$10/L$10)*L38/L$8) | O38: =IF(N38=0,"",($B$10/N$10)*N38/N$8) | Q38: =IF(P38=0,"",($B$10/P$10)*P38/P$8)
A39: Projeto elétrico/comunicação/telefonia/luminotécnico | C39: vb | D39: 1 | E39: 32200 | F39: Recebido | G39: =IFERROR(AVERAGEIFS($H39:$Q39,H$12:Q$12,"Referência"),"") -> 2.0501437 | H39: 9000 | I39: =IF(H39=0,"",($B$10/H$10)*H39/H$8) -> 2.1912492 | J39: 6000 | K39: =IF(J39=0,"",($B$10/J$10)*J39/J$8) -> 0.78623749 | L39: 21150 | M39: =IF(L39=0,"",($B$10/L$10)*L39/L$8) -> 3.1729443 | O39: =IF(N39=0,"",($B$10/N$10)*N39/N$8) | Q39: =IF(P39=0,"",($B$10/P$10)*P39/P$8)
A40: Projeto elétrico | C40: vb | D40: 1 | F40: Não Solicitado | G40: =IFERROR(AVERAGEIFS($H40:$Q40,H$12:Q$12,"Referência"),"") | H40: 0 | I40: =IF(H40=0,"",($B$10/H$10)*H40/H$8) | J40: 0 | K40: =IF(J40=0,"",($B$10/J$10)*J40/J$8) | L40: 0 | M40: =IF(L40=0,"",($B$10/L$10)*L40/L$8) | O40: =IF(N40=0,"",($B$10/N$10)*N40/N$8) | Q40: =IF(P40=0,"",($B$10/P$10)*P40/P$8)
A41: Projeto comunicação e dados | C41: vb | D41: 1 | F41: Não Solicitado | G41: =IFERROR(AVERAGEIFS($H41:$Q41,H$12:Q$12,"Referência"),"") -> 0.26207916 | H41: 0 | I41: =IF(H41=0,"",($B$10/H$10)*H41/H$8) | J41: 2000 | K41: =IF(J41=0,"",($B$10/J$10)*J41/J$8) -> 0.26207916 | L41: 0 | M41: =IF(L41=0,"",($B$10/L$10)*L41/L$8) | O41: =IF(N41=0,"",($B$10/N$10)*N41/N$8) | Q41: =IF(P41=0,"",($B$10/P$10)*P41/P$8)
A42: Projeto de telefonia | C42: vb | D42: 1 | F42: Não Solicitado | G42: =IFERROR(AVERAGEIFS($H42:$Q42,H$12:Q$12,"Referência"),"") -> 0.13103958 | H42: 0 | I42: =IF(H42=0,"",($B$10/H$10)*H42/H$8) | J42: 1000 | K42: =IF(J42=0,"",($B$10/J$10)*J42/J$8) -> 0.13103958 | L42: 0 | M42: =IF(L42=0,"",($B$10/L$10)*L42/L$8) | O42: =IF(N42=0,"",($B$10/N$10)*N42/N$8) | Q42: =IF(P42=0,"",($B$10/P$10)*P42/P$8)
A43: Projeto luminotécnico | C43: vb | D43: 1 | F43: Não Solicitado | G43: =IFERROR(AVERAGEIFS($H43:$Q43,H$12:Q$12,"Referência"),"") -> 0.13103958 | H43: 0 | I43: =IF(H43=0,"",($B$10/H$10)*H43/H$8) | J43: 1000 | K43: =IF(J43=0,"",($B$10/J$10)*J43/J$8) -> 0.13103958 | L43: 0 | M43: =IF(L43=0,"",($B$10/L$10)*L43/L$8) | O43: =IF(N43=0,"",($B$10/N$10)*N43/N$8) | Q43: =IF(P43=0,"",($B$10/P$10)*P43/P$8)
A44: Projeto de automação | C44: vb | D44: 1 | F44: Não Solicitado | G44: =IFERROR(AVERAGEIFS($H44:$Q44,H$12:Q$12,"Referência"),"") | H44: 0 | I44: =IF(H44=0,"",($B$10/H$10)*H44/H$8) | J44: 0 | K44: =IF(J44=0,"",($B$10/J$10)*J44/J$8) | L44: 0 | M44: =IF(L44=0,"",($B$10/L$10)*L44/L$8) | O44: =IF(N44=0,"",($B$10/N$10)*N44/N$8) | Q44: =IF(P44=0,"",($B$10/P$10)*P44/P$8)
A45: Projeto hidrossanitário | C45: vb | D45: 1 | F45: Não Solicitado | G45: =IFERROR(AVERAGEIFS($H45:$Q45,H$12:Q$12,"Referência"),"") | H45: 0 | I45: =IF(H45=0,"",($B$10/H$10)*H45/H$8) | K45: =IF(J45=0,"",($B$10/J$10)*J45/J$8) | L45: 0 | M45: =IF(L45=0,"",($B$10/L$10)*L45/L$8) | O45: =IF(N45=0,"",($B$10/N$10)*N45/N$8) | Q45: =IF(P45=0,"",($B$10/P$10)*P45/P$8)
A46: Projeto hidrossanitário/drenagem/pluvial | C46: vb | D46: 1 | E46: 22970 | F46: Recebido | G46: =IFERROR(AVERAGEIFS($H46:$Q46,H$12:Q$12,"Referência"),"") -> 2.2416701 | H46: 0 | I46: =IF(H46=0,"",($B$10/H$10)*H46/H$8) | J46: 10000 | K46: =IF(J46=0,"",($B$10/J$10)*J46/J$8) -> 1.3103958 | L46: 21150 | M46: =IF(L46=0,"",($B$10/L$10)*L46/L$8) -> 3.1729443 | O46: =IF(N46=0,"",($B$10/N$10)*N46/N$8) | Q46: =IF(P46=0,"",($B$10/P$10)*P46/P$8)
A47: Projeto de drenagem | C47: vb | D47: 1 | F47: Não Solicitado | G47: =IFERROR(AVERAGEIFS($H47:$Q47,H$12:Q$12,"Referência"),"") | H47: 0 | I47: =IF(H47=0,"",($B$10/H$10)*H47/H$8) | J47: 0 | K47: =IF(J47=0,"",($B$10/J$10)*J47/J$8) | L47: 0 | M47: =IF(L47=0,"",($B$10/L$10)*L47/L$8) | O47: =IF(N47=0,"",($B$10/N$10)*N47/N$8) | Q47: =IF(P47=0,"",($B$10/P$10)*P47/P$8)
A48: Projeto pluvial | C48: vb | D48: 1 | F48: Não Solicitado | G48: =IFERROR(AVERAGEIFS($H48:$Q48,H$12:Q$12,"Referência"),"") | H48: 0 | I48: =IF(H48=0,"",($B$10/H$10)*H48/H$8) | J48: 0 | K48: =IF(J48=0,"",($B$10/J$10)*J48/J$8) | L48: 0 | M48: =IF(L48=0,"",($B$10/L$10)*L48/L$8) | O48: =IF(N48=0,"",($B$10/N$10)*N48/N$8) | Q48: =IF(P48=0,"",($B$10/P$10)*P48/P$8)
A49: Projeto de irrigação | C49: vb | D49: 1 | E49: =0.71*B8 -> 4912.3338 | F49: Estimado | G49: =IFERROR(AVERAGEIFS($H49:$Q49,H$12:Q$12,"Referência"),"") | H49: 0 | I49: =IF(H49=0,"",($B$10/H$10)*H49/H$8) | J49: 0 | K49: =IF(J49=0,"",($B$10/J$10)*J49/J$8) | L49: 0 | M49: =IF(L49=0,"",($B$10/L$10)*L49/L$8) | O49: =IF(N49=0,"",($B$10/N$10)*N49/N$8) | Q49: =IF(P49=0,"",($B$10/P$10)*P49/P$8)
A50: Projeto preventivo (PPCI - Plano de Prevenção e Proteção Contra Incêndios) e Gás | C50: vb | D50: 1 | E50: 20675 | F50: Recebido | G50: =IFERROR(AVERAGEIFS($H50:$Q50,H$12:Q$12,"Referência"),"") -> 2.569269 | I50: =IF(H50=0,"",($B$10/H$10)*H50/H$8) | J50: 15000 | K50: =IF(J50=0,"",($B$10/J$10)*J50/J$8) -> 1.9655937 | L50: 21150 | M50: =IF(L50=0,"",($B$10/L$10)*L50/L$8) -> 3.1729443 | O50: =IF(N50=0,"",($B$10/N$10)*N50/N$8) | Q50: =IF(P50=0,"",($B$10/P$10)*P50/P$8)
A51: Projeto de climatização/exaustão | C51: vb | D51: 1 | E51: 29000 | F51: Recebido | G51: =IFERROR(AVERAGEIFS($H51:$Q51,H$12:Q$12,"Referência"),"") | H51: 0 | I51: =IF(H51=0,"",($B$10/H$10)*H51/H$8) | J51: 0 | K51: =IF(J51=0,"",($B$10/J$10)*J51/J$8) | L51: 0 | M51: =IF(L51=0,"",($B$10/L$10)*L51/L$8) | O51: =IF(N51=0,"",($B$10/N$10)*N51/N$8) | Q51: =IF(P51=0,"",($B$10/P$10)*P51/P$8)
A52: Projeto de climatização | C52: vb | D52: 1 | F52: Não Solicitado | G52: =IFERROR(AVERAGEIFS($H52:$Q52,H$12:Q$12,"Referência"),"") -> 0.13103958 | H52: 0 | I52: =IF(H52=0,"",($B$10/H$10)*H52/H$8) | J52: 1000 | K52: =IF(J52=0,"",($B$10/J$10)*J52/J$8) -> 0.13103958 | L52: 0 | M52: =IF(L52=0,"",($B$10/L$10)*L52/L$8) | O52: =IF(N52=0,"",($B$10/N$10)*N52/N$8) | Q52: =IF(P52=0,"",($B$10/P$10)*P52/P$8)
A53: Projeto de exautão | C53: vb | D53: 1 | F53: Não Solicitado | G53: =IFERROR(AVERAGEIFS($H53:$Q53,H$12:Q$12,"Referência"),"") | H53: 0 | I53: =IF(H53=0,"",($B$10/H$10)*H53/H$8) | J53: 0 | K53: =IF(J53=0,"",($B$10/J$10)*J53/J$8) | L53: 0 | M53: =IF(L53=0,"",($B$10/L$10)*L53/L$8) | O53: =IF(N53=0,"",($B$10/N$10)*N53/N$8) | Q53: =IF(P53=0,"",($B$10/P$10)*P53/P$8)
A54: Projeto de gás | C54: vb | D54: 1 | F54: Não Solicitado | G54: =IFERROR(AVERAGEIFS($H54:$Q54,H$12:Q$12,"Referência"),"") | H54: 0 | I54: =IF(H54=0,"",($B$10/H$10)*H54/H$8) | J54: 0 | K54: =IF(J54=0,"",($B$10/J$10)*J54/J$8) | L54: 0 | M54: =IF(L54=0,"",($B$10/L$10)*L54/L$8) | O54: =IF(N54=0,"",($B$10/N$10)*N54/N$8) | Q54: =IF(P54=0,"",($B$10/P$10)*P54/P$8)
A55: Projeto de Segurança | C55: vb | D55: 1 | E55: =G55*$B$8 -> 4645.2833 | F55: Estimado | G55: =IFERROR(AVERAGEIFS($H55:$Q55,H$12:Q$12,"Referência"),"") -> 0.67140208 | H55: 4000 | I55: =IF(H55=0,"",($B$10/H$10)*H55/H$8) -> 0.97388853 | J55: 850 | K55: =IF(J55=0,"",($B$10/J$10)*J55/J$8) -> 0.11138364 | L55: 0 | M55: =IF(L55=0,"",($B$10/L$10)*L55/L$8) | N55: 5374.99 | O55: =IF(N55=0,"",($B$10/N$10)*N55/N$8) -> 0.79404542 | P55: 4342.32 | Q55: =IF(P55=0,"",($B$10/P$10)*P55/P$8) -> 0.80629072
A56: Projeto pressurização | C56: vb | D56: 1 | F56: Não Solicitado | G56: =IFERROR(AVERAGEIFS($H56:$Q56,H$12:Q$12,"Referência"),"") | H56: 0 | I56: =IF(H56=0,"",($B$10/H$10)*H56/H$8) | J56: 0 | K56: =IF(J56=0,"",($B$10/J$10)*J56/J$8) | L56: 0 | M56: =IF(L56=0,"",($B$10/L$10)*L56/L$8) | O56: =IF(N56=0,"",($B$10/N$10)*N56/N$8) | Q56: =IF(P56=0,"",($B$10/P$10)*P56/P$8)
A57: Projetos - Complementares | E57: =SUMPRODUCT(D58:D66,E58:E66) -> 38049.203 | I57: =IF(H57=0,"",($B$10/H$10)*H57/H$8) | K57: =IF(J57=0,"",($B$10/J$10)*J57/J$8) | M57: =IF(L57=0,"",($B$10/L$10)*L57/L$8) | O57: =IF(N57=0,"",($B$10/N$10)*N57/N$8) | Q57: =IF(P57=0,"",($B$10/P$10)*P57/P$8)
A58: Projeto de Impermeabilização | C58: vb | D58: 1 | E58: =G58*$B$8 -> 16004.243 | F58: Estimado | G58: =IFERROR(AVERAGEIFS($H58:$Q58,H$12:Q$12,"Referência"),"") -> 2.3131597 | H58: 0 | I58: =IF(H58=0,"",($B$10/H$10)*H58/H$8) | J58: 0 | K58: =IF(J58=0,"",($B$10/J$10)*J58/J$8) | L58: 0 | M58: =IF(L58=0,"",($B$10/L$10)*L58/L$8) | N58: 16000 | O58: =IF(N58=0,"",($B$10/N$10)*N58/N$8) -> 2.3636745 | P58: 12185.59 | Q58: =IF(P58=0,"",($B$10/P$10)*P58/P$8) -> 2.2626449
A59: Projeto de esquadrias | C59: vb | F59: Não Solicitado | G59: =IFERROR(AVERAGEIFS($H59:$Q59,H$12:Q$12,"Referência"),"") | I59: =IF(H59=0,"",($B$10/H$10)*H59/H$8) | K59: =IF(J59=0,"",($B$10/J$10)*J59/J$8) | L59: 0 | M59: =IF(L59=0,"",($B$10/L$10)*L59/L$8) | O59: =IF(N59=0,"",($B$10/N$10)*N59/N$8) | Q59: =IF(P59=0,"",($B$10/P$10)*P59/P$8)
A60: Projeto de forro | C60: vb | F60: Não Solicitado | G60: =IFERROR(AVERAGEIFS($H60:$Q60,H$12:Q$12,"Referência"),"") | H60: 0 | I60: =IF(H60=0,"",($B$10/H$10)*H60/H$8) | J60: 0 | K60: =IF(J60=0,"",($B$10/J$10)*J60/J$8) | L60: 0 | M60: =IF(L60=0,"",($B$10/L$10)*L60/L$8) | O60: =IF(N60=0,"",($B$10/N$10)*N60/N$8) | Q60: =IF(P60=0,"",($B$10/P$10)*P60/P$8)
A61: Projeto acústico | C61: vb | F61: Não Solicitado | G61: =IFERROR(AVERAGEIFS($H61:$Q61,H$12:Q$12,"Referência"),"") | H61: 0 | I61: =IF(H61=0,"",($B$10/H$10)*H61/H$8) | J61: 0 | K61: =IF(J61=0,"",($B$10/J$10)*J61/J$8) | L61: 0 | M61: =IF(L61=0,"",($B$10/L$10)*L61/L$8) | O61: =IF(N61=0,"",($B$10/N$10)*N61/N$8) | Q61: =IF(P61=0,"",($B$10/P$10)*P61/P$8)
A62: Protjeto de Sonorização | C62: vb | F62: Não Solicitado | G62: =IFERROR(AVERAGEIFS($H62:$Q62,H$12:Q$12,"Referência"),"") | H62: 0 | I62: =IF(H62=0,"",($B$10/H$10)*H62/H$8) | J62: 0 | K62: =IF(J62=0,"",($B$10/J$10)*J62/J$8) | L62: 0 | M62: =IF(L62=0,"",($B$10/L$10)*L62/L$8) | O62: =IF(N62=0,"",($B$10/N$10)*N62/N$8) | Q62: =IF(P62=0,"",($B$10/P$10)*P62/P$8)
A63: Projeto de Piscina | C63: vb | D63: 1 | E63: =G63*$B$8 -> 5300.5705 | F63: Estimado | G63: =IFERROR(AVERAGEIFS($H63:$Q63,H$12:Q$12,"Referência"),"") -> 0.76611346 | H63: 0 | I63: =IF(H63=0,"",($B$10/H$10)*H63/H$8) | K63: =IF(J63=0,"",($B$10/J$10)*J63/J$8) | L63: 0 | M63: =IF(L63=0,"",($B$10/L$10)*L63/L$8) | N63: 6500 | O63: =IF(N63=0,"",($B$10/N$10)*N63/N$8) -> 0.96024276 | P63: 3080.45 | Q63: =IF(P63=0,"",($B$10/P$10)*P63/P$8) -> 0.57198416
A64: Projeto de comunicação visual | C64: vb | F64: Não Solicitado | G64: =IFERROR(AVERAGEIFS($H64:$Q64,H$12:Q$12,"Referência"),"") | H64: 0 | I64: =IF(H64=0,"",($B$10/H$10)*H64/H$8) | K64: =IF(J64=0,"",($B$10/J$10)*J64/J$8) | L64: 0 | M64: =IF(L64=0,"",($B$10/L$10)*L64/L$8) | O64: =IF(N64=0,"",($B$10/N$10)*N64/N$8) | Q64: =IF(P64=0,"",($B$10/P$10)*P64/P$8)
A65: Projeto de Paisagismo | C65: vb | D65: 1 | E65: =G65*$B$8 -> 16744.39 | F65: Estimado | G65: =IFERROR(AVERAGEIFS($H65:$Q65,H$12:Q$12,"Referência"),"") -> 2.4201362 | H65: 0 | I65: =IF(H65=0,"",($B$10/H$10)*H65/H$8) | K65: =IF(J65=0,"",($B$10/J$10)*J65/J$8) | L65: 0 | M65: =IF(L65=0,"",($B$10/L$10)*L65/L$8) | N65: 24000 | O65: =IF(N65=0,"",($B$10/N$10)*N65/N$8) -> 3.5455117 | P65: 6973 | Q65: =IF(P65=0,"",($B$10/P$10)*P65/P$8) -> 1.2947607
A66: Projeto de pavimentação | C66: vb | F66: Não Solicitado | G66: =IFERROR(AVERAGEIFS($H66:$Q66,H$12:Q$12,"Referência"),"") | H66: 0 | I66: =IF(H66=0,"",($B$10/H$10)*H66/H$8) | J66: 0 | K66: =IF(J66=0,"",($B$10/J$10)*J66/J$8) | L66: 0 | M66: =IF(L66=0,"",($B$10/L$10)*L66/L$8) | O66: =IF(N66=0,"",($B$10/N$10)*N66/N$8) | Q66: =IF(P66=0,"",($B$10/P$10)*P66/P$8)
A67: Projetos - BIM | E67: =SUMPRODUCT(D68:D71,E68:E71) -> 68700 | I67: =IF(H67=0,"",($B$10/H$10)*H67/H$8) | K67: =IF(J67=0,"",($B$10/J$10)*J67/J$8) | M67: =IF(L67=0,"",($B$10/L$10)*L67/L$8) | O67: =IF(N67=0,"",($B$10/N$10)*N67/N$8) | Q67: =IF(P67=0,"",($B$10/P$10)*P67/P$8)
A68: Modelagem BIM arquitetônica | C68: vb | F68: Não Solicitado | G68: =IFERROR(AVERAGEIFS($H68:$Q68,H$12:Q$12,"Referência"),"") | H68: 0 | I68: =IF(H68=0,"",($B$10/H$10)*H68/H$8) | J68: 0 | K68: =IF(J68=0,"",($B$10/J$10)*J68/J$8) | L68: 0 | M68: =IF(L68=0,"",($B$10/L$10)*L68/L$8) | O68: =IF(N68=0,"",($B$10/N$10)*N68/N$8) | Q68: =IF(P68=0,"",($B$10/P$10)*P68/P$8)
A69: Modelagem BIM Complementares | C69: vb | F69: Não Solicitado | G69: =IFERROR(AVERAGEIFS($H69:$Q69,H$12:Q$12,"Referência"),"") | I69: =IF(H69=0,"",($B$10/H$10)*H69/H$8) | K69: =IF(J69=0,"",($B$10/J$10)*J69/J$8) | L69: 0 | M69: =IF(L69=0,"",($B$10/L$10)*L69/L$8) | O69: =IF(N69=0,"",($B$10/N$10)*N69/N$8) | Q69: =IF(P69=0,"",($B$10/P$10)*P69/P$8)
A70: Compatibilização de Projetos BIM | C70: vb | D70: 1 | E70: 68700 | F70: Recebido | G70: =IFERROR(AVERAGEIFS($H70:$Q70,H$12:Q$12,"Referência"),"") -> 1.4381594 | I70: =IF(H70=0,"",($B$10/H$10)*H70/H$8) | J70: 10975 | K70: =IF(J70=0,"",($B$10/J$10)*J70/J$8) -> 1.4381594 | L70: 0 | M70: =IF(L70=0,"",($B$10/L$10)*L70/L$8) | O70: =IF(N70=0,"",($B$10/N$10)*N70/N$8) | Q70: =IF(P70=0,"",($B$10/P$10)*P70/P$8)
A71: Informações complementares de projetos | C71: vb | F71: Não Solicitado | G71: =IFERROR(AVERAGEIFS($H71:$Q71,H$12:Q$12,"Referência"),"") | H71: 0 | I71: =IF(H71=0,"",($B$10/H$10)*H71/H$8) | J71: 0 | K71: =IF(J71=0,"",($B$10/J$10)*J71/J$8) | L71: 0 | M71: =IF(L71=0,"",($B$10/L$10)*L71/L$8) | O71: =IF(N71=0,"",($B$10/N$10)*N71/N$8) | Q71: =IF(P71=0,"",($B$10/P$10)*P71/P$8)
A72: CONSULTORIAS | E72: =SUMPRODUCT(D73:D79,E73:E79) -> 81564.963 | I72: =IF(H72=0,"",($B$10/H$10)*H72/H$8) | K72: =IF(J72=0,"",($B$10/J$10)*J72/J$8) | M72: =IF(L72=0,"",($B$10/L$10)*L72/L$8) | O72: =IF(N72=0,"",($B$10/N$10)*N72/N$8) | Q72: =IF(P72=0,"",($B$10/P$10)*P72/P$8)
A73: Consultorias Técnicas de esquadrias | C73: vb | F73: Não Solicitado | G73: =IFERROR(AVERAGEIFS($H73:$Q73,H$12:Q$12,"Referência"),"") | H73: 0 | I73: =IF(H73=0,"",($B$10/H$10)*H73/H$8) | J73: 0 | K73: =IF(J73=0,"",($B$10/J$10)*J73/J$8) | L73: 0 | M73: =IF(L73=0,"",($B$10/L$10)*L73/L$8) | O73: =IF(N73=0,"",($B$10/N$10)*N73/N$8) | Q73: =IF(P73=0,"",($B$10/P$10)*P73/P$8)
A74: Consultoria técnica de fachada | C74: vb | D74: 1 | E74: =G74*$B$8 -> 27596.943 | F74: Estimado | G74: =IFERROR(AVERAGEIFS($H74:$Q74,H$12:Q$12,"Referência"),"") -> 3.9887007 | H74: 0 | I74: =IF(H74=0,"",($B$10/H$10)*H74/H$8) | J74: 0 | K74: =IF(J74=0,"",($B$10/J$10)*J74/J$8) | L74: 0 | M74: =IF(L74=0,"",($B$10/L$10)*L74/L$8) | N74: 27000 | O74: =IF(N74=0,"",($B$10/N$10)*N74/N$8) -> 3.9887007 | Q74: =IF(P74=0,"",($B$10/P$10)*P74/P$8)
A75: consultoria técnica de legalização | C75: vb | D75: 1 | E75: 15000 | F75: Recebido | G75: =IFERROR(AVERAGEIFS($H75:$Q75,H$12:Q$12,"Referência"),"") | H75: 0 | I75: =IF(H75=0,"",($B$10/H$10)*H75/H$8) | J75: 0 | K75: =IF(J75=0,"",($B$10/J$10)*J75/J$8) | L75: 0 | M75: =IF(L75=0,"",($B$10/L$10)*L75/L$8) | O75: =IF(N75=0,"",($B$10/N$10)*N75/N$8) | Q75: =IF(P75=0,"",($B$10/P$10)*P75/P$8)
A76: Orçamento e planejamento | C76: vb | D76: 1 | E76: 38968.02 | F76: Recebido | G76: =IFERROR(AVERAGEIFS($H76:$Q76,H$12:Q$12,"Referência"),"") -> 5.7347071 | H76: 0 | I76: =IF(H76=0,"",($B$10/H$10)*H76/H$8) | J76: 50891.05 | K76: =IF(J76=0,"",($B$10/J$10)*J76/J$8) -> 6.6687419 | L76: 32000 | M76: =IF(L76=0,"",($B$10/L$10)*L76/L$8) -> 4.8006722 | O76: =IF(N76=0,"",($B$10/N$10)*N76/N$8) | Q76: =IF(P76=0,"",($B$10/P$10)*P76/P$8)
A77: Consultoria técnica de qualidade | C77: vb | F77: Não Solicitado | G77: =IFERROR(AVERAGEIFS($H77:$Q77,H$12:Q$12,"Referência"),"") -> 5.3976501 | H77: 28825 | I77: =IF(H77=0,"",($B$10/H$10)*H77/H$8) -> 7.0180842 | J77: 28825 | K77: =IF(J77=0,"",($B$10/J$10)*J77/J$8) -> 3.7772159 | L77: 0 | M77: =IF(L77=0,"",($B$10/L$10)*L77/L$8) | O77: =IF(N77=0,"",($B$10/N$10)*N77/N$8) | Q77: =IF(P77=0,"",($B$10/P$10)*P77/P$8)
A78: Auditoria de qualidade | C78: vb | F78: Não Solicitado | G78: =IFERROR(AVERAGEIFS($H78:$Q78,H$12:Q$12,"Referência"),"") | H78: 0 | I78: =IF(H78=0,"",($B$10/H$10)*H78/H$8) | J78: 0 | K78: =IF(J78=0,"",($B$10/J$10)*J78/J$8) | L78: 0 | M78: =IF(L78=0,"",($B$10/L$10)*L78/L$8) | O78: =IF(N78=0,"",($B$10/N$10)*N78/N$8) | Q78: =IF(P78=0,"",($B$10/P$10)*P78/P$8)
A79: Prevision | C79: vb | F79: Não Solicitado | G79: =IFERROR(AVERAGEIFS($H79:$Q79,H$12:Q$12,"Referência"),"") | H79: 0 | I79: =IF(H79=0,"",($B$10/H$10)*H79/H$8) | J79: 0 | K79: =IF(J79=0,"",($B$10/J$10)*J79/J$8) | L79: 0 | M79: =IF(L79=0,"",($B$10/L$10)*L79/L$8) | O79: =IF(N79=0,"",($B$10/N$10)*N79/N$8) | Q79: =IF(P79=0,"",($B$10/P$10)*P79/P$8)
A80: SERVIÇOS TÉCNICOS | E80: =SUMPRODUCT(D81:D109,E81:E109) -> #REF! | I80: =IF(H80=0,"",($B$10/H$10)*H80/H$8) | K80: =IF(J80=0,"",($B$10/J$10)*J80/J$8) | M80: =IF(L80=0,"",($B$10/L$10)*L80/L$8) | O80: =IF(N80=0,"",($B$10/N$10)*N80/N$8) | Q80: =IF(P80=0,"",($B$10/P$10)*P80/P$8)
A81: Controle Tecnologico de Concreto | C81: vb | D81: 1 | E81: ='Ensaios '!F6 -> 50780 | F81: Estimado | G81: =IFERROR(AVERAGEIFS($H81:$Q81,H$12:Q$12,"Referência"),"") -> 4.842291 | H81: 18999.95 | I81: =IF(H81=0,"",($B$10/H$10)*H81/H$8) -> 4.6259583 | J81: 14520 | K81: =IF(J81=0,"",($B$10/J$10)*J81/J$8) -> 1.9026947 | L81: 53314 | M81: =IF(L81=0,"",($B$10/L$10)*L81/L$8) -> 7.99822 | O81: =IF(N81=0,"",($B$10/N$10)*N81/N$8) | Q81: =IF(P81=0,"",($B$10/P$10)*P81/P$8)
A82: Ensaio de graute | C82: vb | F82: Não Solicitado | G82: =IFERROR(AVERAGEIFS($H82:$Q82,H$12:Q$12,"Referência"),"") | H82: 0 | I82: =IF(H82=0,"",($B$10/H$10)*H82/H$8) | J82: 0 | K82: =IF(J82=0,"",($B$10/J$10)*J82/J$8) | L82: 0 | M82: =IF(L82=0,"",($B$10/L$10)*L82/L$8) | O82: =IF(N82=0,"",($B$10/N$10)*N82/N$8) | Q82: =IF(P82=0,"",($B$10/P$10)*P82/P$8)
A83: Ensaio de argamassa | C83: vb | D83: 1 | E83: ='Ensaios '!#REF! -> #REF! | F83: Estimado | G83: =IFERROR(AVERAGEIFS($H83:$Q83,H$12:Q$12,"Referência"),"") | H83: 0 | I83: =IF(H83=0,"",($B$10/H$10)*H83/H$8) | J83: 0 | K83: =IF(J83=0,"",($B$10/J$10)*J83/J$8) | L83: 0 | M83: =IF(L83=0,"",($B$10/L$10)*L83/L$8) | O83: =IF(N83=0,"",($B$10/N$10)*N83/N$8) | Q83: =IF(P83=0,"",($B$10/P$10)*P83/P$8)
A84: Prova de carga | C84: vb | F84: Não Solicitado | G84: =IFERROR(AVERAGEIFS($H84:$Q84,H$12:Q$12,"Referência"),"") | H84: 0 | I84: =IF(H84=0,"",($B$10/H$10)*H84/H$8) | J84: 0 | K84: =IF(J84=0,"",($B$10/J$10)*J84/J$8) | L84: 0 | M84: =IF(L84=0,"",($B$10/L$10)*L84/L$8) | O84: =IF(N84=0,"",($B$10/N$10)*N84/N$8) | Q84: =IF(P84=0,"",($B$10/P$10)*P84/P$8)
A85: Tese de Esquadrias | C85: vb | F85: Não Solicitado | G85: =IFERROR(AVERAGEIFS($H85:$Q85,H$12:Q$12,"Referência"),"") | H85: 0 | I85: =IF(H85=0,"",($B$10/H$10)*H85/H$8) | J85: 0 | K85: =IF(J85=0,"",($B$10/J$10)*J85/J$8) | L85: 0 | M85: =IF(L85=0,"",($B$10/L$10)*L85/L$8) | O85: =IF(N85=0,"",($B$10/N$10)*N85/N$8) | Q85: =IF(P85=0,"",($B$10/P$10)*P85/P$8)
A86: Ensiao de caixilho | C86: vb | F86: Não Solicitado | G86: =IFERROR(AVERAGEIFS($H86:$Q86,H$12:Q$12,"Referência"),"") | H86: 0 | I86: =IF(H86=0,"",($B$10/H$10)*H86/H$8) | J86: 0 | K86: =IF(J86=0,"",($B$10/J$10)*J86/J$8) | L86: 0 | M86: =IF(L86=0,"",($B$10/L$10)*L86/L$8) | O86: =IF(N86=0,"",($B$10/N$10)*N86/N$8) | Q86: =IF(P86=0,"",($B$10/P$10)*P86/P$8)
A87: Ensaio de guarda-corpo | C87: vb | D87: 1 | E87: ='Ensaios '!F13 -> 4210 | F87: Estimado | G87: =IFERROR(AVERAGEIFS($H87:$Q87,H$12:Q$12,"Referência"),"") | H87: 0 | I87: =IF(H87=0,"",($B$10/H$10)*H87/H$8) | J87: 0 | K87: =IF(J87=0,"",($B$10/J$10)*J87/J$8) | L87: 0 | M87: =IF(L87=0,"",($B$10/L$10)*L87/L$8) | O87: =IF(N87=0,"",($B$10/N$10)*N87/N$8) | Q87: =IF(P87=0,"",($B$10/P$10)*P87/P$8)
A88: Ensaio de arrancamento de reboco | C88: vb | D88: 1 | E88: ='Ensaios '!F17 -> 1260 | F88: Estimado | G88: =IFERROR(AVERAGEIFS($H88:$Q88,H$12:Q$12,"Referência"),"") -> 0.37346281 | H88: 0 | I88: =IF(H88=0,"",($B$10/H$10)*H88/H$8) | J88: 2850 | K88: =IF(J88=0,"",($B$10/J$10)*J88/J$8) -> 0.37346281 | L88: 0 | M88: =IF(L88=0,"",($B$10/L$10)*L88/L$8) | O88: =IF(N88=0,"",($B$10/N$10)*N88/N$8) | Q88: =IF(P88=0,"",($B$10/P$10)*P88/P$8)
A89: Ensaio de arrancamento revestimento cerâmico | C89: vb | D89: 1 | E89: ='Ensaios '!F19 -> 664.44444 | F89: Estimado | G89: =IFERROR(AVERAGEIFS($H89:$Q89,H$12:Q$12,"Referência"),"") | H89: 0 | I89: =IF(H89=0,"",($B$10/H$10)*H89/H$8) | J89: 0 | K89: =IF(J89=0,"",($B$10/J$10)*J89/J$8) | L89: 0 | M89: =IF(L89=0,"",($B$10/L$10)*L89/L$8) | O89: =IF(N89=0,"",($B$10/N$10)*N89/N$8) | Q89: =IF(P89=0,"",($B$10/P$10)*P89/P$8)
A90: Ensaio de arrancamento fachada | C90: vb | D90: 1 | E90: ='Ensaios '!F15 -> 1260 | F90: Estimado | G90: =IFERROR(AVERAGEIFS($H90:$Q90,H$12:Q$12,"Referência"),"") | H90: 0 | I90: =IF(H90=0,"",($B$10/H$10)*H90/H$8) | J90: 0 | K90: =IF(J90=0,"",($B$10/J$10)*J90/J$8) | L90: 0 | M90: =IF(L90=0,"",($B$10/L$10)*L90/L$8) | O90: =IF(N90=0,"",($B$10/N$10)*N90/N$8) | Q90: =IF(P90=0,"",($B$10/P$10)*P90/P$8)
A91: Ensaio de arrancamento de gancho da cobertura | C91: vb | D91: 1 | E91: ='Ensaios '!F21 -> 1680 | F91: Estimado | G91: =IFERROR(AVERAGEIFS($H91:$Q91,H$12:Q$12,"Referência"),"") | H91: 0 | I91: =IF(H91=0,"",($B$10/H$10)*H91/H$8) | J91: 0 | K91: =IF(J91=0,"",($B$10/J$10)*J91/J$8) | L91: 0 | M91: =IF(L91=0,"",($B$10/L$10)*L91/L$8) | O91: =IF(N91=0,"",($B$10/N$10)*N91/N$8) | Q91: =IF(P91=0,"",($B$10/P$10)*P91/P$8)
A92: Ensaio de prisma (oco e cheio) | C92: vb | F92: Não Solicitado | G92: =IFERROR(AVERAGEIFS($H92:$Q92,H$12:Q$12,"Referência"),"") | H92: 0 | I92: =IF(H92=0,"",($B$10/H$10)*H92/H$8) | J92: 0 | K92: =IF(J92=0,"",($B$10/J$10)*J92/J$8) | L92: 0 | M92: =IF(L92=0,"",($B$10/L$10)*L92/L$8) | O92: =IF(N92=0,"",($B$10/N$10)*N92/N$8) | Q92: =IF(P92=0,"",($B$10/P$10)*P92/P$8)
A93: Ensaio de bloco estrutual | C93: vb | F93: Não Solicitado | G93: =IFERROR(AVERAGEIFS($H93:$Q93,H$12:Q$12,"Referência"),"") | H93: 0 | I93: =IF(H93=0,"",($B$10/H$10)*H93/H$8) | J93: 0 | K93: =IF(J93=0,"",($B$10/J$10)*J93/J$8) | L93: 0 | M93: =IF(L93=0,"",($B$10/L$10)*L93/L$8) | O93: =IF(N93=0,"",($B$10/N$10)*N93/N$8) | Q93: =IF(P93=0,"",($B$10/P$10)*P93/P$8)
A94: Laudo de Vizinhança | C94: vb | D94: 1 | E94: 3900 | F94: Recebido | G94: =IFERROR(AVERAGEIFS($H94:$Q94,H$12:Q$12,"Referência"),"") | H94: 0 | I94: =IF(H94=0,"",($B$10/H$10)*H94/H$8) | J94: 0 | K94: =IF(J94=0,"",($B$10/J$10)*J94/J$8) | L94: 0 | M94: =IF(L94=0,"",($B$10/L$10)*L94/L$8) | O94: =IF(N94=0,"",($B$10/N$10)*N94/N$8) | Q94: =IF(P94=0,"",($B$10/P$10)*P94/P$8)
A95: Laudo de avaliação de desempenho | C95: vb | F95: Não Solicitado | G95: =IFERROR(AVERAGEIFS($H95:$Q95,H$12:Q$12,"Referência"),"") | H95: 0 | I95: =IF(H95=0,"",($B$10/H$10)*H95/H$8) | J95: 0 | K95: =IF(J95=0,"",($B$10/J$10)*J95/J$8) | L95: 0 | M95: =IF(L95=0,"",($B$10/L$10)*L95/L$8) | O95: =IF(N95=0,"",($B$10/N$10)*N95/N$8) | Q95: =IF(P95=0,"",($B$10/P$10)*P95/P$8)
A96: Laudo de avaliação de desempenho - Luminico | C96: vb | F96: Não Solicitado | G96: =IFERROR(AVERAGEIFS($H96:$Q96,H$12:Q$12,"Referência"),"") -> 1.0585077 | H96: 0 | I96: =IF(H96=0,"",($B$10/H$10)*H96/H$8) | J96: 0 | K96: =IF(J96=0,"",($B$10/J$10)*J96/J$8) | L96: 7055.73 | M96: =IF(L96=0,"",($B$10/L$10)*L96/L$8) -> 1.0585077 | O96: =IF(N96=0,"",($B$10/N$10)*N96/N$8) | Q96: =IF(P96=0,"",($B$10/P$10)*P96/P$8)
A97: Laudo de avaliação de desempenho - Acústico | C97: vb | F97: Não Solicitado | G97: =IFERROR(AVERAGEIFS($H97:$Q97,H$12:Q$12,"Referência"),"") -> 1.0585077 | H97: 0 | I97: =IF(H97=0,"",($B$10/H$10)*H97/H$8) | J97: 0 | K97: =IF(J97=0,"",($B$10/J$10)*J97/J$8) | L97: 7055.73 | M97: =IF(L97=0,"",($B$10/L$10)*L97/L$8) -> 1.0585077 | O97: =IF(N97=0,"",($B$10/N$10)*N97/N$8) | Q97: =IF(P97=0,"",($B$10/P$10)*P97/P$8)
A98: Laudo de avaliação de desempenho - Térmico | C98: vb | F98: Não Solicitado | G98: =IFERROR(AVERAGEIFS($H98:$Q98,H$12:Q$12,"Referência"),"") -> 1.0585077 | H98: 0 | I98: =IF(H98=0,"",($B$10/H$10)*H98/H$8) | J98: 0 | K98: =IF(J98=0,"",($B$10/J$10)*J98/J$8) | L98: 7055.73 | M98: =IF(L98=0,"",($B$10/L$10)*L98/L$8) -> 1.0585077 | O98: =IF(N98=0,"",($B$10/N$10)*N98/N$8) | Q98: =IF(P98=0,"",($B$10/P$10)*P98/P$8)
A99: Laudo de Vistória de Fim e Obra | C99: vb | F99: Não Solicitado | G99: =IFERROR(AVERAGEIFS($H99:$Q99,H$12:Q$12,"Referência"),"") -> 0.76002063 | H99: 3121.5919 | I99: =IF(H99=0,"",($B$10/H$10)*H99/H$8) -> 0.76002063 | J99: 0 | K99: =IF(J99=0,"",($B$10/J$10)*J99/J$8) | L99: 0 | M99: =IF(L99=0,"",($B$10/L$10)*L99/L$8) | O99: =IF(N99=0,"",($B$10/N$10)*N99/N$8) | Q99: =IF(P99=0,"",($B$10/P$10)*P99/P$8)
A100: Laudo de Potabilidade de água | C100: vb | F100: Não Solicitado | G100: =IFERROR(AVERAGEIFS($H100:$Q100,H$12:Q$12,"Referência"),"") | H100: 0 | I100: =IF(H100=0,"",($B$10/H$10)*H100/H$8) | J100: 0 | K100: =IF(J100=0,"",($B$10/J$10)*J100/J$8) | L100: 0 | M100: =IF(L100=0,"",($B$10/L$10)*L100/L$8) | O100: =IF(N100=0,"",($B$10/N$10)*N100/N$8) | Q100: =IF(P100=0,"",($B$10/P$10)*P100/P$8)
...

Sheet Ger_Tec e Adm
G4: PROJETO: | I4: ='Obra '!D1 -> Colin Schroeder | O4: REVISÃO: | P4: DATA
G5: EMPRESA: | I5: ='Obra '!D2 -> Grupo DUO | O5: ='Obra '!D3 -> R00 | P5: 45551
A6: Unidade Construtiva | B6: Célula Construtiva | C6: Etapa | D6: Subetapa | E6: Serviço | G6: GERENCIAMENTO EXECUTIVO
A7: 0 | B7: 0 | C7: 0 | D7: 0 | E7: 0 | G7: Atalho | H7: NIVEL | I7: Item | J7: Descrição | K7: Unidade | L7: Quant. | M7: Preço un | N7: Total | O7: Considerações | P7: Situação
A8: =IF($H8="UNIDADE CONSTRUTIVA",OFFSET(A8,-1,0)+1,LARGE(A$3:A7,1)) -> 0 | B8: =IF(H8="UNIDADE CONSTRUTIVA",0,IF(H8="CÉLULA CONSTRUTIVA",OFFSET(B8,-1,0)+1,OFFSET(B8,-1,0))) -> 1 | C8: =IF(H8="CÉLULA CONSTRUTIVA",0,IF(H8="ETAPA",OFFSET(C8,-1,0)+1,OFFSET(C8,-1,0))) -> 0 | D8: =IF(H8="ETAPA",0,IF(H8="SUBETAPA",OFFSET(D8,-1,0)+1,OFFSET(D8,-1,0))) -> 0 | E8: =IF(H8="Subetapa",0,IF(H8="serviço",OFFSET(E8,-1,0)+1,OFFSET(E8,-1,0))) -> 0 | H8: CÉLULA CONSTRUTIVA | I8: =IF(H8="Unidade Construtiva",TEXT(A8,"00"),IF(H8="Célula Construtiva",TEXT(B8,"00"),IF(H8="Etapa",CONCATENATE(TEXT(B8,"00"),".",TEXT(C8,"000")),IF(H8="Subetapa",CONCATENATE(TEXT(B8,"00"),".",TEXT(C8,"000"),".",TEXT(D8,"000")),IF(H8="Serviço",CONCATENATE(TEXT(B8,"00"),".",TEXT(C8,"000"),".",TEXT(D8,"000"),".",TEXT(E8,"000")),""))))) -> 01 | J8: SERVIÇOS TÉCNICOS | N8: =IF(H8="Serviço",M8*L8,IF(H8="CÉLULA CONSTRUTIVA",SUMIFS($N$8:$N$419,$B$8:$B$419,B8,$H$8:$H$419,"Serviço"),IF(H8="ETAPA",SUMIFS($N$8:$N$419,$B$8:$B$419,B8,$C$8:$C$419,C8,$H$8:$H$419,"Serviço"),IF(H8="SUBETAPA",SUMIFS($N$8:$N$419,$B$8:$B$419,B8,$C$8:$C$419,C8,$D$8:$D$419,D8,$H$8:$H$419,"Serviço"),0)))) -> 2405432.1 | Q8: =N8/'Obra '!$C$32 -> 0.50387247
A9: =IF($H9="UNIDADE CONSTRUTIVA",OFFSET(A9,-1,0)+1,LARGE(A$3:A8,1)) -> 0 | B9: =IF(H9="UNIDADE CONSTRUTIVA",0,IF(H9="CÉLULA CONSTRUTIVA",OFFSET(B9,-1,0)+1,OFFSET(B9,-1,0))) -> 1 | C9: =IF(H9="CÉLULA CONSTRUTIVA",0,IF(H9="ETAPA",OFFSET(C9,-1,0)+1,OFFSET(C9,-1,0))) -> 1 | D9: =IF(H9="ETAPA",0,IF(H9="SUBETAPA",OFFSET(D9,-1,0)+1,OFFSET(D9,-1,0))) -> 0 | E9: =IF(H9="Subetapa",0,IF(H9="serviço",OFFSET(E9,-1,0)+1,OFFSET(E9,-1,0))) -> 0 | H9: ETAPA | I9: =IF(H9="Unidade Construtiva",TEXT(A9,"00"),IF(H9="Célula Construtiva",TEXT(B9,"00"),IF(H9="Etapa",CONCATENATE(TEXT(B9,"00"),".",TEXT(C9,"000")),IF(H9="Subetapa",CONCATENATE(TEXT(B9,"00"),".",TEXT(C9,"000"),".",TEXT(D9,"000")),IF(H9="Serviço",CONCATENATE(TEXT(B9,"00"),".",TEXT(C9,"000"),".",TEXT(D9,"000"),".",TEXT(E9,"000")),""))))) -> 01.001 | J9: ESTUDOS, PROJETOS, CONSULTORIA E ENSAIOS | N9: =IF(H9="Serviço",M9*L9,IF(H9="CÉLULA CONSTRUTIVA",SUMIFS($N$8:$N$419,$B$8:$B$419,B9,$H$8:$H$419,"Serviço"),IF(H9="ETAPA",SUMIFS($N$8:$N$419,$B$8:$B$419,B9,$C$8:$C$419,C9,$H$8:$H$419,"Serviço"),IF(H9="SUBETAPA",SUMIFS($N$8:$N$419,$B$8:$B$419,B9,$C$8:$C$419,C9,$D$8:$D$419,D9,$H$8:$H$419,"Serviço"),0)))) -> 772571.76 | Q9: =N9/'Obra '!$C$32 -> 0.16183273
A10: =IF($H10="UNIDADE CONSTRUTIVA",OFFSET(A10,-1,0)+1,LARGE(A$3:A9,1)) -> 0 | B10: =IF(H10="UNIDADE CONSTRUTIVA",0,IF(H10="CÉLULA CONSTRUTIVA",OFFSET(B10,-1,0)+1,OFFSET(B10,-1,0))) -> 1 | C10: =IF(H10="CÉLULA CONSTRUTIVA",0,IF(H10="ETAPA",OFFSET(C10,-1,0)+1,OFFSET(C10,-1,0))) -> 1 | D10: =IF(H10="ETAPA",0,IF(H10="SUBETAPA",OFFSET(D10,-1,0)+1,OFFSET(D10,-1,0))) -> 1 | E10: =IF(H10="Subetapa",0,IF(H10="serviço",OFFSET(E10,-1,0)+1,OFFSET(E10,-1,0))) -> 0 | H10: SUBETAPA | I10: =IF(H10="Unidade Construtiva",TEXT(A10,"00"),IF(H10="Célula Construtiva",TEXT(B10,"00"),IF(H10="Etapa",CONCATENATE(TEXT(B10,"00"),".",TEXT(C10,"000")),IF(H10="Subetapa",CONCATENATE(TEXT(B10,"00"),".",TEXT(C10,"000"),".",TEXT(D10,"000")),IF(H10="Serviço",CONCATENATE(TEXT(B10,"00"),".",TEXT(C10,"000"),".",TEXT(D10,"000"),".",TEXT(E10,"000")),""))))) -> 01.001.001 | J10: Estudos | N10: =IF(H10="Serviço",M10*L10,IF(H10="CÉLULA CONSTRUTIVA",SUMIFS($N$8:$N$419,$B$8:$B$419,B10,$H$8:$H$419,"Serviço"),IF(H10="ETAPA",SUMIFS($N$8:$N$419,$B$8:$B$419,B10,$C$8:$C$419,C10,$H$8:$H$419,"Serviço"),IF(H10="SUBETAPA",SUMIFS($N$8:$N$419,$B$8:$B$419,B10,$C$8:$C$419,C10,$D$8:$D$419,D10,$H$8:$H$419,"Serviço"),0)))) -> 10300 | Q10: =N10/'Obra '!$C$32 -> 0.0021575693
A11: =IF($H11="UNIDADE CONSTRUTIVA",OFFSET(A11,-1,0)+1,LARGE(A$3:A10,1)) -> 0 | B11: =IF(H11="UNIDADE CONSTRUTIVA",0,IF(H11="CÉLULA CONSTRUTIVA",OFFSET(B11,-1,0)+1,OFFSET(B11,-1,0))) -> 1 | C11: =IF(H11="CÉLULA CONSTRUTIVA",0,IF(H11="ETAPA",OFFSET(C11,-1,0)+1,OFFSET(C11,-1,0))) -> 1 | D11: =IF(H11="ETAPA",0,IF(H11="SUBETAPA",OFFSET(D11,-1,0)+1,OFFSET(D11,-1,0))) -> 1 | E11: =IF(H11="Subetapa",0,IF(H11="serviço",OFFSET(E11,-1,0)+1,OFFSET(E11,-1,0))) -> 1 | H11: SERVIÇO | I11: =IF(H11="Unidade Construtiva",TEXT(A11,"00"),IF(H11="Célula Construtiva",TEXT(B11,"00"),IF(H11="Etapa",CONCATENATE(TEXT(B11,"00"),".",TEXT(C11,"000")),IF(H11="Subetapa",CONCATENATE(TEXT(B11,"00"),".",TEXT(C11,"000"),".",TEXT(D11,"000")),IF(H11="Serviço",CONCATENATE(TEXT(B11,"00"),".",TEXT(C11,"000"),".",TEXT(D11,"000"),".",TEXT(E11,"000")),""))))) -> 01.001.001.001 | J11: Levantamento Topográfico | K11: =IFERROR(VLOOKUP(J11,BASES!$A$13:$E$342,3,FALSE),0) -> vb | L11: =IFERROR(VLOOKUP(J11,BASES!$A$13:$E$342,4,FALSE),0) -> 1 | M11: =IFERROR(VLOOKUP(J11,BASES!$A$13:$E$342,5,FALSE),0) -> 1800 | N11: =IF(H11="Serviço",M11*L11,IF(H11="CÉLULA CONSTRUTIVA",SUMIFS($N$8:$N$419,$B$8:$B$419,B11,$H$8:$H$419,"Serviço"),IF(H11="ETAPA",SUMIFS($N$8:$N$419,$B$8:$B$419,B11,$C$8:$C$419,C11,$H$8:$H$419,"Serviço"),IF(H11="SUBETAPA",SUMIFS($N$8:$N$419,$B$8:$B$419,B11,$C$8:$C$419,C11,$D$8:$D$419,D11,$H$8:$H$419,"Serviço"),0)))) -> 1800 | O11: =IF(VLOOKUP(J11,BASES!$A$13:$F$342,6,FALSE)="Recebido","Valor informado em formulário",IF(VLOOKUP(J11,BASES!$A$13:$F$342,6,FALSE)="Estimado","Estimado com base em índices históricos","Não solicitado")) -> Valor informado em formulário | P11: Lançado ERP
A12: =IF($H12="UNIDADE CONSTRUTIVA",OFFSET(A12,-1,0)+1,LARGE(A$3:A11,1)) -> 0 | B12: =IF(H12="UNIDADE CONSTRUTIVA",0,IF(H12="CÉLULA CONSTRUTIVA",OFFSET(B12,-1,0)+1,OFFSET(B12,-1,0))) -> 1 | C12: =IF(H12="CÉLULA CONSTRUTIVA",0,IF(H12="ETAPA",OFFSET(C12,-1,0)+1,OFFSET(C12,-1,0))) -> 1 | D12: =IF(H12="ETAPA",0,IF(H12="SUBETAPA",OFFSET(D12,-1,0)+1,OFFSET(D12,-1,0))) -> 1 | E12: =IF(H12="Subetapa",0,IF(H12="serviço",OFFSET(E12,-1,0)+1,OFFSET(E12,-1,0))) -> 2 | H12: SERVIÇO | I12: =IF(H12="Unidade Construtiva",TEXT(A12,"00"),IF(H12="Célula Construtiva",TEXT(B12,"00"),IF(H12="Etapa",CONCATENATE(TEXT(B12,"00"),".",TEXT(C12,"000")),IF(H12="Subetapa",CONCATENATE(TEXT(B12,"00"),".",TEXT(C12,"000"),".",TEXT(D12,"000")),IF(H12="Serviço",CONCATENATE(TEXT(B12,"00"),".",TEXT(C12,"000"),".",TEXT(D12,"000"),".",TEXT(E12,"000")),""))))) -> 01.001.001.002 | J12: Sondagem do terreno | K12: =IFERROR(VLOOKUP(J12,BASES!$A$13:$E$342,3,FALSE),0) -> vb | L12: =IFERROR(VLOOKUP(J12,BASES!$A$13:$E$342,4,FALSE),0) -> 1 | M12: =IFERROR(VLOOKUP(J12,BASES!$A$13:$E$342,5,FALSE),0) -> 8500 | N12: =IF(H12="Serviço",M12*L12,IF(H12="CÉLULA CONSTRUTIVA",SUMIFS($N$8:$N$419,$B$8:$B$419,B12,$H$8:$H$419,"Serviço"),IF(H12="ETAPA",SUMIFS($N$8:$N$419,$B$8:$B$419,B12,$C$8:$C$419,C12,$H$8:$H$419,"Serviço"),IF(H12="SUBETAPA",SUMIFS($N$8:$N$419,$B$8:$B$419,B12,$C$8:$C$419,C12,$D$8:$D$419,D12,$H$8:$H$419,"Serviço"),0)))) -> 8500 | O12: =IF(VLOOKUP(J12,BASES!$A$13:$F$342,6,FALSE)="Recebido","Valor informado em formulário",IF(VLOOKUP(J12,BASES!$A$13:$F$342,6,FALSE)="Estimado","Estimado com base em índices históricos","Não solicitado")) -> Valor informado em formulário | P12: Lançado ERP
A13: =IF($H13="UNIDADE CONSTRUTIVA",OFFSET(A13,-1,0)+1,LARGE(A$3:A12,1)) -> 0 | B13: =IF(H13="UNIDADE CONSTRUTIVA",0,IF(H13="CÉLULA CONSTRUTIVA",OFFSET(B13,-1,0)+1,OFFSET(B13,-1,0))) -> 1 | C13: =IF(H13="CÉLULA CONSTRUTIVA",0,IF(H13="ETAPA",OFFSET(C13,-1,0)+1,OFFSET(C13,-1,0))) -> 1 | D13: =IF(H13="ETAPA",0,IF(H13="SUBETAPA",OFFSET(D13,-1,0)+1,OFFSET(D13,-1,0))) -> 2 | E13: =IF(H13="Subetapa",0,IF(H13="serviço",OFFSET(E13,-1,0)+1,OFFSET(E13,-1,0))) -> 0 | H13: SUBETAPA | I13: =IF(H13="Unidade Construtiva",TEXT(A13,"00"),IF(H13="Célula Construtiva",TEXT(B13,"00"),IF(H13="Etapa",CONCATENATE(TEXT(B13,"00"),".",TEXT(C13,"000")),IF(H13="Subetapa",CONCATENATE(TEXT(B13,"00"),".",TEXT(C13,"000"),".",TEXT(D13,"000")),IF(H13="Serviço",CONCATENATE(TEXT(B13,"00"),".",TEXT(C13,"000"),".",TEXT(D13,"000"),".",TEXT(E13,"000")),""))))) -> 01.001.002 | J13: Projetos | N13: =IF(H13="Serviço",M13*L13,IF(H13="CÉLULA CONSTRUTIVA",SUMIFS($N$8:$N$419,$B$8:$B$419,B13,$H$8:$H$419,"Serviço"),IF(H13="ETAPA",SUMIFS($N$8:$N$419,$B$8:$B$419,B13,$C$8:$C$419,C13,$H$8:$H$419,"Serviço"),IF(H13="SUBETAPA",SUMIFS($N$8:$N$419,$B$8:$B$419,B13,$C$8:$C$419,C13,$D$8:$D$419,D13,$H$8:$H$419,"Serviço"),0)))) -> 552152.35 | Q13: =N13/'Obra '!$C$32 -> 0.11566087
A14: =IF($H14="UNIDADE CONSTRUTIVA",OFFSET(A14,-1,0)+1,LARGE(A$3:A13,1)) -> 0 | B14: =IF(H14="UNIDADE CONSTRUTIVA",0,IF(H14="CÉLULA CONSTRUTIVA",OFFSET(B14,-1,0)+1,OFFSET(B14,-1,0))) -> 1 | C14: =IF(H14="CÉLULA CONSTRUTIVA",0,IF(H14="ETAPA",OFFSET(C14,-1,0)+1,OFFSET(C14,-1,0))) -> 1 | D14: =IF(H14="ETAPA",0,IF(H14="SUBETAPA",OFFSET(D14,-1,0)+1,OFFSET(D14,-1,0))) -> 2 | E14: =IF(H14="Subetapa",0,IF(H14="serviço",OFFSET(E14,-1,0)+1,OFFSET(E14,-1,0))) -> 1 | H14: SERVIÇO | I14: =IF(H14="Unidade Construtiva",TEXT(A14,"00"),IF(H14="Célula Construtiva",TEXT(B14,"00"),IF(H14="Etapa",CONCATENATE(TEXT(B14,"00"),".",TEXT(C14,"000")),IF(H14="Subetapa",CONCATENATE(TEXT(B14,"00"),".",TEXT(C14,"000"),".",TEXT(D14,"000")),IF(H14="Serviço",CONCATENATE(TEXT(B14,"00"),".",TEXT(C14,"000"),".",TEXT(D14,"000"),".",TEXT(E14,"000")),""))))) -> 01.001.002.001 | J14: Projeto Arquitetônico legal - incluindo: executivo + interiores + fachada | K14: =IFERROR(VLOOKUP(J14,BASES!$A$13:$E$342,3,FALSE),0) -> vb | L14: =IFERROR(VLOOKUP(J14,BASES!$A$13:$E$342,4,FALSE),0) -> 1 | M14: =IFERROR(VLOOKUP(J14,BASES!$A$13:$E$342,5,FALSE),0) -> 320000 | N14: =IF(H14="Serviço",M14*L14,IF(H14="CÉLULA CONSTRUTIVA",SUMIFS($N$8:$N$419,$B$8:$B$419,B14,$H$8:$H$419,"Serviço"),IF(H14="ETAPA",SUMIFS($N$8:$N$419,$B$8:$B$419,B14,$C$8:$C$419,C14,$H$8:$H$419,"Serviço"),IF(H14="SUBETAPA",SUMIFS($N$8:$N$419,$B$8:$B$419,B14,$C$8:$C$419,C14,$D$8:$D$419,D14,$H$8:$H$419,"Serviço"),0)))) -> 320000 | O14: =IF(VLOOKUP(J14,BASES!$A$13:$F$342,6,FALSE)="Recebido","Valor informado em formulário",IF(VLOOKUP(J14,BASES!$A$13:$F$342,6,FALSE)="Estimado","Estimado com base em índices históricos","Não solicitado")) -> Valor informado em formulário | P14: Lançado ERP
A15: =IF($H15="UNIDADE CONSTRUTIVA",OFFSET(A15,-1,0)+1,LARGE(A$3:A14,1)) -> 0 | B15: =IF(H15="UNIDADE CONSTRUTIVA",0,IF(H15="CÉLULA CONSTRUTIVA",OFFSET(B15,-1,0)+1,OFFSET(B15,-1,0))) -> 1 | C15: =IF(H15="CÉLULA CONSTRUTIVA",0,IF(H15="ETAPA",OFFSET(C15,-1,0)+1,OFFSET(C15,-1,0))) -> 1 | D15: =IF(H15="ETAPA",0,IF(H15="SUBETAPA",OFFSET(D15,-1,0)+1,OFFSET(D15,-1,0))) -> 2 | E15: =IF(H15="Subetapa",0,IF(H15="serviço",OFFSET(E15,-1,0)+1,OFFSET(E15,-1,0))) -> 2 | H15: SERVIÇO | I15: =IF(H15="Unidade Construtiva",TEXT(A15,"00"),IF(H15="Célula Construtiva",TEXT(B15,"00"),IF(H15="Etapa",CONCATENATE(TEXT(B15,"00"),".",TEXT(C15,"000")),IF(H15="Subetapa",CONCATENATE(TEXT(B15,"00"),".",TEXT(C15,"000"),".",TEXT(D15,"000")),IF(H15="Serviço",CONCATENATE(TEXT(B15,"00"),".",TEXT(C15,"000"),".",TEXT(D15,"000"),".",TEXT(E15,"000")),""))))) -> 01.001.002.002 | J15: Projeto técnico de fachada | K15: =IFERROR(VLOOKUP(J15,BASES!$A$13:$E$342,3,FALSE),0) -> vb | L15: =IFERROR(VLOOKUP(J15,BASES!$A$13:$E$342,4,FALSE),0) -> 1 | M15: =IFERROR(VLOOKUP(J15,BASES!$A$13:$E$342,5,FALSE),0) -> 9231.3628 | N15: =IF(H15="Serviço",M15*L15,IF(H15="CÉLULA CONSTRUTIVA",SUMIFS($N$8:$N$419,$B$8:$B$419,B15,$H$8:$H$419,"Serviço"),IF(H15="ETAPA",SUMIFS($N$8:$N$419,$B$8:$B$419,B15,$C$8:$C$419,C15,$H$8:$H$419,"Serviço"),IF(H15="SUBETAPA",SUMIFS($N$8:$N$419,$B$8:$B$419,B15,$C$8:$C$419,C15,$D$8:$D$419,D15,$H$8:$H$419,"Serviço"),0)))) -> 9231.3628 | O15: =IF(VLOOKUP(J15,BASES!$A$13:$F$342,6,FALSE)="Recebido","Valor informado em formulário",IF(VLOOKUP(J15,BASES!$A$13:$F$342,6,FALSE)="Estimado","Estimado com base em índices históricos","Não solicitado")) -> Estimado com base em índices históricos | P15: Lançado ERP
A16: =IF($H16="UNIDADE CONSTRUTIVA",OFFSET(A16,-1,0)+1,LARGE(A$3:A15,1)) -> 0 | B16: =IF(H16="UNIDADE CONSTRUTIVA",0,IF(H16="CÉLULA CONSTRUTIVA",OFFSET(B16,-1,0)+1,OFFSET(B16,-1,0))) -> 1 | C16: =IF(H16="CÉLULA CONSTRUTIVA",0,IF(H16="ETAPA",OFFSET(C16,-1,0)+1,OFFSET(C16,-1,0))) -> 1 | D16: =IF(H16="ETAPA",0,IF(H16="SUBETAPA",OFFSET(D16,-1,0)+1,OFFSET(D16,-1,0))) -> 2 | E16: =IF(H16="Subetapa",0,IF(H16="serviço",OFFSET(E16,-1,0)+1,OFFSET(E16,-1,0))) -> 3 | H16: SERVIÇO | I16: =IF(H16="Unidade Construtiva",TEXT(A16,"00"),IF(H16="Célula Construtiva",TEXT(B16,"00"),IF(H16="Etapa",CONCATENATE(TEXT(B16,"00"),".",TEXT(C16,"000")),IF(H16="Subetapa",CONCATENATE(TEXT(B16,"00"),".",TEXT(C16,"000"),".",TEXT(D16,"000")),IF(H16="Serviço",CONCATENATE(TEXT(B16,"00"),".",TEXT(C16,"000"),".",TEXT(D16,"000"),".",TEXT(E16,"000")),""))))) -> 01.001.002.003 | J16: Projeto Estrutural | K16: =IFERROR(VLOOKUP(J16,BASES!$A$13:$E$342,3,FALSE),0) -> vb | L16: =IFERROR(VLOOKUP(J16,BASES!$A$13:$E$342,4,FALSE),0) -> 1 | M16: =IFERROR(VLOOKUP(J16,BASES!$A$13:$E$342,5,FALSE),0) -> 49900.727 | N16: =IF(H16="Serviço",M16*L16,IF(H16="CÉLULA CONSTRUTIVA",SUMIFS($N$8:$N$419,$B$8:$B$419,B16,$H$8:$H$419,"Serviço"),IF(H16="ETAPA",SUMIFS($N$8:$N$419,$B$8:$B$419,B16,$C$8:$C$419,C16,$H$8:$H$419,"Serviço"),IF(H16="SUBETAPA",SUMIFS($N$8:$N$419,$B$8:$B$419,B16,$C$8:$C$419,C16,$D$8:$D$419,D16,$H$8:$H$419,"Serviço"),0)))) -> 49900.727 | O16: =IF(VLOOKUP(J16,BASES!$A$13:$F$342,6,FALSE)="Recebido","Valor informado em formulário",IF(VLOOKUP(J16,BASES!$A$13:$F$342,6,FALSE)="Estimado","Estimado com base em índices históricos","Não solicitado")) -> Estimado com base em índices históricos | P16: Lançado ERP
A17: =IF($H17="UNIDADE CONSTRUTIVA",OFFSET(A17,-1,0)+1,LARGE(A$3:A16,1)) -> 0 | B17: =IF(H17="UNIDADE CONSTRUTIVA",0,IF(H17="CÉLULA CONSTRUTIVA",OFFSET(B17,-1,0)+1,OFFSET(B17,-1,0))) -> 1 | C17: =IF(H17="CÉLULA CONSTRUTIVA",0,IF(H17="ETAPA",OFFSET(C17,-1,0)+1,OFFSET(C17,-1,0))) -> 1 | D17: =IF(H17="ETAPA",0,IF(H17="SUBETAPA",OFFSET(D17,-1,0)+1,OFFSET(D17,-1,0))) -> 2 | E17: =IF(H17="Subetapa",0,IF(H17="serviço",OFFSET(E17,-1,0)+1,OFFSET(E17,-1,0))) -> 4 | H17: SERVIÇO | I17: =IF(H17="Unidade Construtiva",TEXT(A17,"00"),IF(H17="Célula Construtiva",TEXT(B17,"00"),IF(H17="Etapa",CONCATENATE(TEXT(B17,"00"),".",TEXT(C17,"000")),IF(H17="Subetapa",CONCATENATE(TEXT(B17,"00"),".",TEXT(C17,"000"),".",TEXT(D17,"000")),IF(H17="Serviço",CONCATENATE(TEXT(B17,"00"),".",TEXT(C17,"000"),".",TEXT(D17,"000"),".",TEXT(E17,"000")),""))))) -> 01.001.002.004 | J17: Projeto de Fundações | K17: =IFERROR(VLOOKUP(J17,BASES!$A$13:$E$342,3,FALSE),0) -> vb | L17: =IFERROR(VLOOKUP(J17,BASES!$A$13:$E$342,4,FALSE),0) -> 1 | M17: =IFERROR(VLOOKUP(J17,BASES!$A$13:$E$342,5,FALSE),0) -> 20568.443 | N17: =IF(H17="Serviço",M17*L17,IF(H17="CÉLULA CONSTRUTIVA",SUMIFS($N$8:$N$419,$B$8:$B$419,B17,$H$8:$H$419,"Serviço"),IF(H17="ETAPA",SUMIFS($N$8:$N$419,$B$8:$B$419,B17,$C$8:$C$419,C17,$H$8:$H$419,"Serviço"),IF(H17="SUBETAPA",SUMIFS($N$8:$N$419,$B$8:$B$419,B17,$C$8:$C$419,C17,$D$8:$D$419,D17,$H$8:$H$419,"Serviço"),0)))) -> 20568.443 | O17: =IF(VLOOKUP(J17,BASES!$A$13:$F$342,6,FALSE)="Recebido","Valor informado em formulário",IF(VLOOKUP(J17,BASES!$A$13:$F$342,6,FALSE)="Estimado","Estimado com base em índices históricos","Não solicitado")) -> Estimado com base em índices históricos | P17: Lançado ERP
A18: =IF($H18="UNIDADE CONSTRUTIVA",OFFSET(A18,-1,0)+1,LARGE(A$3:A17,1)) -> 0 | B18: =IF(H18="UNIDADE CONSTRUTIVA",0,IF(H18="CÉLULA CONSTRUTIVA",OFFSET(B18,-1,0)+1,OFFSET(B18,-1,0))) -> 1 | C18: =IF(H18="CÉLULA CONSTRUTIVA",0,IF(H18="ETAPA",OFFSET(C18,-1,0)+1,OFFSET(C18,-1,0))) -> 1 | D18: =IF(H18="ETAPA",0,IF(H18="SUBETAPA",OFFSET(D18,-1,0)+1,OFFSET(D18,-1,0))) -> 2 | E18: =IF(H18="Subetapa",0,IF(H18="serviço",OFFSET(E18,-1,0)+1,OFFSET(E18,-1,0))) -> 5 | H18: SERVIÇO | I18: =IF(H18="Unidade Construtiva",TEXT(A18,"00"),IF(H18="Célula Construtiva",TEXT(B18,"00"),IF(H18="Etapa",CONCATENATE(TEXT(B18,"00"),".",TEXT(C18,"000")),IF(H18="Subetapa",CONCATENATE(TEXT(B18,"00"),".",TEXT(C18,"000"),".",TEXT(D18,"000")),IF(H18="Serviço",CONCATENATE(TEXT(B18,"00"),".",TEXT(C18,"000"),".",TEXT(D18,"000"),".",TEXT(E18,"000")),""))))) -> 01.001.002.005 | J18: Projeto elétrico/comunicação/telefonia/luminotécnico | K18: =IFERROR(VLOOKUP(J18,BASES!$A$13:$E$342,3,FALSE),0) -> vb | L18: =IFERROR(VLOOKUP(J18,BASES!$A$13:$E$342,4,FALSE),0) -> 1 | M18: =IFERROR(VLOOKUP(J18,BASES!$A$13:$E$342,5,FALSE),0) -> 32200 | N18: =IF(H18="Serviço",M18*L18,IF(H18="CÉLULA CONSTRUTIVA",SUMIFS($N$8:$N$419,$B$8:$B$419,B18,$H$8:$H$419,"Serviço"),IF(H18="ETAPA",SUMIFS($N$8:$N$419,$B$8:$B$419,B18,$C$8:$C$419,C18,$H$8:$H$419,"Serviço"),IF(H18="SUBETAPA",SUMIFS($N$8:$N$419,$B$8:$B$419,B18,$C$8:$C$419,C18,$D$8:$D$419,D18,$H$8:$H$419,"Serviço"),0)))) -> 32200 | O18: =IF(VLOOKUP(J18,BASES!$A$13:$F$342,6,FALSE)="Recebido","Valor informado em formulário",IF(VLOOKUP(J18,BASES!$A$13:$F$342,6,FALSE)="Estimado","Estimado com base em índices históricos","Não solicitado")) -> Valor informado em formulário | P18: Lançado ERP
A19: =IF($H19="UNIDADE CONSTRUTIVA",OFFSET(A19,-1,0)+1,LARGE(A$3:A18,1)) -> 0 | B19: =IF(H19="UNIDADE CONSTRUTIVA",0,IF(H19="CÉLULA CONSTRUTIVA",OFFSET(B19,-1,0)+1,OFFSET(B19,-1,0))) -> 1 | C19: =IF(H19="CÉLULA CONSTRUTIVA",0,IF(H19="ETAPA",OFFSET(C19,-1,0)+1,OFFSET(C19,-1,0))) -> 1 | D19: =IF(H19="ETAPA",0,IF(H19="SUBETAPA",OFFSET(D19,-1,0)+1,OFFSET(D19,-1,0))) -> 2 | E19: =IF(H19="Subetapa",0,IF(H19="serviço",OFFSET(E19,-1,0)+1,OFFSET(E19,-1,0))) -> 6 | H19: SERVIÇO | I19: =IF(H19="Unidade Construtiva",TEXT(A19,"00"),IF(H19="Célula Construtiva",TEXT(B19,"00"),IF(H19="Etapa",CONCATENATE(TEXT(B19,"00"),".",TEXT(C19,"000")),IF(H19="Subetapa",CONCATENATE(TEXT(B19,"00"),".",TEXT(C19,"000"),".",TEXT(D19,"000")),IF(H19="Serviço",CONCATENATE(TEXT(B19,"00"),".",TEXT(C19,"000"),".",TEXT(D19,"000"),".",TEXT(E19,"000")),""))))) -> 01.001.002.006 | J19: Projeto hidrossanitário/drenagem/pluvial | K19: =IFERROR(VLOOKUP(J19,BASES!$A$13:$E$342,3,FALSE),0) -> vb | L19: =IFERROR(VLOOKUP(J19,BASES!$A$13:$E$342,4,FALSE),0) -> 1 | M19: =IFERROR(VLOOKUP(J19,BASES!$A$13:$E$342,5,FALSE),0) -> 22970 | N19: =IF(H19="Serviço",M19*L19,IF(H19="CÉLULA CONSTRUTIVA",SUMIFS($N$8:$N$419,$B$8:$B$419,B19,$H$8:$H$419,"Serviço"),IF(H19="ETAPA",SUMIFS($N$8:$N$419,$B$8:$B$419,B19,$C$8:$C$419,C19,$H$8:$H$419,"Serviço"),IF(H19="SUBETAPA",SUMIFS($N$8:$N$419,$B$8:$B$419,B19,$C$8:$C$419,C19,$D$8:$D$419,D19,$H$8:$H$419,"Serviço"),0)))) -> 22970 | O19: =IF(VLOOKUP(J19,BASES!$A$13:$F$342,6,FALSE)="Recebido","Valor informado em formulário",IF(VLOOKUP(J19,BASES!$A$13:$F$342,6,FALSE)="Estimado","Estimado com base em índices históricos","Não solicitado")) -> Valor informado em formulário | P19: Lançado ERP
A20: =IF($H20="UNIDADE CONSTRUTIVA",OFFSET(A20,-1,0)+1,LARGE(A$3:A19,1)) -> 0 | B20: =IF(H20="UNIDADE CONSTRUTIVA",0,IF(H20="CÉLULA CONSTRUTIVA",OFFSET(B20,-1,0)+1,OFFSET(B20,-1,0))) -> 1 | C20: =IF(H20="CÉLULA CONSTRUTIVA",0,IF(H20="ETAPA",OFFSET(C20,-1,0)+1,OFFSET(C20,-1,0))) -> 1 | D20: =IF(H20="ETAPA",0,IF(H20="SUBETAPA",OFFSET(D20,-1,0)+1,OFFSET(D20,-1,0))) -> 2 | E20: =IF(H20="Subetapa",0,IF(H20="serviço",OFFSET(E20,-1,0)+1,OFFSET(E20,-1,0))) -> 7 | H20: SERVIÇO | I20: =IF(H20="Unidade Construtiva",TEXT(A20,"00"),IF(H20="Célula Construtiva",TEXT(B20,"00"),IF(H20="Etapa",CONCATENATE(TEXT(B20,"00"),".",TEXT(C20,"000")),IF(H20="Subetapa",CONCATENATE(TEXT(B20,"00"),".",TEXT(C20,"000"),".",TEXT(D20,"000")),IF(H20="Serviço",CONCATENATE(TEXT(B20,"00"),".",TEXT(C20,"000"),".",TEXT(D20,"000"),".",TEXT(E20,"000")),""))))) -> 01.001.002.007 | J20: Projeto preventivo (PPCI - Plano de Prevenção e Proteção Contra Incêndios) e Gás | K20: =IFERROR(VLOOKUP(J20,BASES!$A$13:$E$342,3,FALSE),0) -> vb | L20: =IFERROR(VLOOKUP(J20,BASES!$A$13:$E$342,4,FALSE),0) -> 1 | M20: =IFERROR(VLOOKUP(J20,BASES!$A$13:$E$342,5,FALSE),0) -> 20675 | N20: =IF(H20="Serviço",M20*L20,IF(H20="CÉLULA CONSTRUTIVA",SUMIFS($N$8:$N$419,$B$8:$B$419,B20,$H$8:$H$419,"Serviço"),IF(H20="ETAPA",SUMIFS($N$8:$N$419,$B$8:$B$419,B20,$C$8:$C$419,C20,$H$8:$H$419,"Serviço"),IF(H20="SUBETAPA",SUMIFS($N$8:$N$419,$B$8:$B$419,B20,$C$8:$C$419,C20,$D$8:$D$419,D20,$H$8:$H$419,"Serviço"),0)))) -> 20675 | O20: =IF(VLOOKUP(J20,BASES!$A$13:$F$342,6,FALSE)="Recebido","Valor informado em formulário",IF(VLOOKUP(J20,BASES!$A$13:$F$342,6,FALSE)="Estimado","Estimado com base em índices históricos","Não solicitado")) -> Valor informado em formulário | P20: Lançado ERP
A21: =IF($H21="UNIDADE CONSTRUTIVA",OFFSET(A21,-1,0)+1,LARGE(A$3:A20,1)) -> 0 | B21: =IF(H21="UNIDADE CONSTRUTIVA",0,IF(H21="CÉLULA CONSTRUTIVA",OFFSET(B21,-1,0)+1,OFFSET(B21,-1,0))) -> 1 | C21: =IF(H21="CÉLULA CONSTRUTIVA",0,IF(H21="ETAPA",OFFSET(C21,-1,0)+1,OFFSET(C21,-1,0))) -> 1 | D21: =IF(H21="ETAPA",0,IF(H21="SUBETAPA",OFFSET(D21,-1,0)+1,OFFSET(D21,-1,0))) -> 2 | E21: =IF(H21="Subetapa",0,IF(H21="serviço",OFFSET(E21,-1,0)+1,OFFSET(E21,-1,0))) -> 8 | H21: SERVIÇO | I21: =IF(H21="Unidade Construtiva",TEXT(A21,"00"),IF(H21="Célula Construtiva",TEXT(B21,"00"),IF(H21="Etapa",CONCATENATE(TEXT(B21,"00"),".",TEXT(C21,"000")),IF(H21="Subetapa",CONCATENATE(TEXT(B21,"00"),".",TEXT(C21,"000"),".",TEXT(D21,"000")),IF(H21="Serviço",CONCATENATE(TEXT(B21,"00"),".",TEXT(C21,"000"),".",TEXT(D21,"000"),".",TEXT(E21,"000")),""))))) -> 01.001.002.008 | J21: Projeto de Impermeabilização | K21: =IFERROR(VLOOKUP(J21,BASES!$A$13:$E$342,3,FALSE),0) -> vb | L21: =IFERROR(VLOOKUP(J21,BASES!$A$13:$E$342,4,FALSE),0) -> 1 | M21: =IFERROR(VLOOKUP(J21,BASES!$A$13:$E$342,5,FALSE),0) -> 16004.243 | N21: =IF(H21="Serviço",M21*L21,IF(H21="CÉLULA CONSTRUTIVA",SUMIFS($N$8:$N$419,$B$8:$B$419,B21,$H$8:$H$419,"Serviço"),IF(H21="ETAPA",SUMIFS($N$8:$N$419,$B$8:$B$419,B21,$C$8:$C$419,C21,$H$8:$H$419,"Serviço"),IF(H21="SUBETAPA",SUMIFS($N$8:$N$419,$B$8:$B$419,B21,$C$8:$C$419,C21,$D$8:$D$419,D21,$H$8:$H$419,"Serviço"),0)))) -> 16004.243 | O21: =IF(VLOOKUP(J21,BASES!$A$13:$F$342,6,FALSE)="Recebido","Valor informado em formulário",IF(VLOOKUP(J21,BASES!$A$13:$F$342,6,FALSE)="Estimado","Estimado com base em índices históricos","Não solicitado")) -> Estimado com base em índices históricos | P21: Lançado ERP
A22: =IF($H22="UNIDADE CONSTRUTIVA",OFFSET(A22,-1,0)+1,LARGE(A$3:A21,1)) -> 0 | B22: =IF(H22="UNIDADE CONSTRUTIVA",0,IF(H22="CÉLULA CONSTRUTIVA",OFFSET(B22,-1,0)+1,OFFSET(B22,-1,0))) -> 1 | C22: =IF(H22="CÉLULA CONSTRUTIVA",0,IF(H22="ETAPA",OFFSET(C22,-1,0)+1,OFFSET(C22,-1,0))) -> 1 | D22: =IF(H22="ETAPA",0,IF(H22="SUBETAPA",OFFSET(D22,-1,0)+1,OFFSET(D22,-1,0))) -> 2 | E22: =IF(H22="Subetapa",0,IF(H22="serviço",OFFSET(E22,-1,0)+1,OFFSET(E22,-1,0))) -> 9 | H22: SERVIÇO | I22: =IF(H22="Unidade Construtiva",TEXT(A22,"00"),IF(H22="Célula Construtiva",TEXT(B22,"00"),IF(H22="Etapa",CONCATENATE(TEXT(B22,"00"),".",TEXT(C22,"000")),IF(H22="Subetapa",CONCATENATE(TEXT(B22,"00"),".",TEXT(C22,"000"),".",TEXT(D22,"000")),IF(H22="Serviço",CONCATENATE(TEXT(B22,"00"),".",TEXT(C22,"000"),".",TEXT(D22,"000"),".",TEXT(E22,"000")),""))))) -> 01.001.002.009 | J22: Projeto de segurança | K22: =IFERROR(VLOOKUP(J22,BASES!$A$13:$E$342,3,FALSE),0) -> vb | L22: =IFERROR(VLOOKUP(J22,BASES!$A$13:$E$342,4,FALSE),0) -> 1 | M22: =IFERROR(VLOOKUP(J22,BASES!$A$13:$E$342,5,FALSE),0) -> 4645.2833 | N22: =IF(H22="Serviço",M22*L22,IF(H22="CÉLULA CONSTRUTIVA",SUMIFS($N$8:$N$419,$B$8:$B$419,B22,$H$8:$H$419,"Serviço"),IF(H22="ETAPA",SUMIFS($N$8:$N$419,$B$8:$B$419,B22,$C$8:$C$419,C22,$H$8:$H$419,"Serviço"),IF(H22="SUBETAPA",SUMIFS($N$8:$N$419,$B$8:$B$419,B22,$C$8:$C$419,C22,$D$8:$D$419,D22,$H$8:$H$419,"Serviço"),0)))) -> 4645.2833 | O22: =IF(VLOOKUP(J22,BASES!$A$13:$F$342,6,FALSE)="Recebido","Valor informado em formulário",IF(VLOOKUP(J22,BASES!$A$13:$F$342,6,FALSE)="Estimado","Estimado com base em índices históricos","Não solicitado")) -> Estimado com base em índices históricos | P22: Lançado ERP
A23: =IF($H23="UNIDADE CONSTRUTIVA",OFFSET(A23,-1,0)+1,LARGE(A$3:A22,1)) -> 0 | B23: =IF(H23="UNIDADE CONSTRUTIVA",0,IF(H23="CÉLULA CONSTRUTIVA",OFFSET(B23,-1,0)+1,OFFSET(B23,-1,0))) -> 1 | C23: =IF(H23="CÉLULA CONSTRUTIVA",0,IF(H23="ETAPA",OFFSET(C23,-1,0)+1,OFFSET(C23,-1,0))) -> 1 | D23: =IF(H23="ETAPA",0,IF(H23="SUBETAPA",OFFSET(D23,-1,0)+1,OFFSET(D23,-1,0))) -> 2 | E23: =IF(H23="Subetapa",0,IF(H23="serviço",OFFSET(E23,-1,0)+1,OFFSET(E23,-1,0))) -> 10 | H23: SERVIÇO | I23: =IF(H23="Unidade Construtiva",TEXT(A23,"00"),IF(H23="Célula Construtiva",TEXT(B23,"00"),IF(H23="Etapa",CONCATENATE(TEXT(B23,"00"),".",TEXT(C23,"000")),IF(H23="Subetapa",CONCATENATE(TEXT(B23,"00"),".",TEXT(C23,"000"),".",TEXT(D23,"000")),IF(H23="Serviço",CONCATENATE(TEXT(B23,"00"),".",TEXT(C23,"000"),".",TEXT(D23,"000"),".",TEXT(E23,"000")),""))))) -> 01.001.002.010 | J23: Projeto de climatização/exaustão | K23: =IFERROR(VLOOKUP(J23,BASES!$A$13:$E$342,3,FALSE),0) -> vb | L23: =IFERROR(VLOOKUP(J23,BASES!$A$13:$E$342,4,FALSE),0) -> 1 | M23: =IFERROR(VLOOKUP(J23,BASES!$A$13:$E$342,5,FALSE),0) -> 29000 | N23: =IF(H23="Serviço",M23*L23,IF(H23="CÉLULA CONSTRUTIVA",SUMIFS($N$8:$N$419,$B$8:$B$419,B23,$H$8:$H$419,"Serviço"),IF(H23="ETAPA",SUMIFS($N$8:$N$419,$B$8:$B$419,B23,$C$8:$C$419,C23,$H$8:$H$419,"Serviço"),IF(H23="SUBETAPA",SUMIFS($N$8:$N$419,$B$8:$B$419,B23,$C$8:$C$419,C23,$D$8:$D$419,D23,$H$8:$H$419,"Serviço"),0)))) -> 29000 | O23: =IF(VLOOKUP(J23,BASES!$A$13:$F$342,6,FALSE)="Recebido","Valor informado em formulário",IF(VLOOKUP(J23,BASES!$A$13:$F$342,6,FALSE)="Estimado","Estimado com base em índices históricos","Não solicitado")) -> Valor informado em formulário | P23: Lançado ERP
A24: =IF($H24="UNIDADE CONSTRUTIVA",OFFSET(A24,-1,0)+1,LARGE(A$3:A23,1)) -> 0 | B24: =IF(H24="UNIDADE CONSTRUTIVA",0,IF(H24="CÉLULA CONSTRUTIVA",OFFSET(B24,-1,0)+1,OFFSET(B24,-1,0))) -> 1 | C24: =IF(H24="CÉLULA CONSTRUTIVA",0,IF(H24="ETAPA",OFFSET(C24,-1,0)+1,OFFSET(C24,-1,0))) -> 1 | D24: =IF(H24="ETAPA",0,IF(H24="SUBETAPA",OFFSET(D24,-1,0)+1,OFFSET(D24,-1,0))) -> 2 | E24: =IF(H24="Subetapa",0,IF(H24="serviço",OFFSET(E24,-1,0)+1,OFFSET(E24,-1,0))) -> 11 | H24: SERVIÇO | I24: =IF(H24="Unidade Construtiva",TEXT(A24,"00"),IF(H24="Célula Construtiva",TEXT(B24,"00"),IF(H24="Etapa",CONCATENATE(TEXT(B24,"00"),".",TEXT(C24,"000")),IF(H24="Subetapa",CONCATENATE(TEXT(B24,"00"),".",TEXT(C24,"000"),".",TEXT(D24,"000")),IF(H24="Serviço",CONCATENATE(TEXT(B24,"00"),".",TEXT(C24,"000"),".",TEXT(D24,"000"),".",TEXT(E24,"000")),""))))) -> 01.001.002.011 | J24: Projeto de irrigação | K24: =IFERROR(VLOOKUP(J24,BASES!$A$13:$E$342,3,FALSE),0) -> vb | L24: =IFERROR(VLOOKUP(J24,BASES!$A$13:$E$342,4,FALSE),0) -> 1 | M24: =IFERROR(VLOOKUP(J24,BASES!$A$13:$E$342,5,FALSE),0) -> 4912.3338 | N24: =IF(H24="Serviço",M24*L24,IF(H24="CÉLULA CONSTRUTIVA",SUMIFS($N$8:$N$419,$B$8:$B$419,B24,$H$8:$H$419,"Serviço"),IF(H24="ETAPA",SUMIFS($N$8:$N$419,$B$8:$B$419,B24,$C$8:$C$419,C24,$H$8:$H$419,"Serviço"),IF(H24="SUBETAPA",SUMIFS($N$8:$N$419,$B$8:$B$419,B24,$C$8:$C$419,C24,$D$8:$D$419,D24,$H$8:$H$419,"Serviço"),0)))) -> 4912.3338 | O24: =IF(VLOOKUP(J24,BASES!$A$13:$F$342,6,FALSE)="Recebido","Valor informado em formulário",IF(VLOOKUP(J24,BASES!$A$13:$F$342,6,FALSE)="Estimado","Estimado com base em índices históricos","Não solicitado")) -> Estimado com base em índices históricos | P24: Lançado ERP
A25: =IF($H25="UNIDADE CONSTRUTIVA",OFFSET(A25,-1,0)+1,LARGE(A$3:A24,1)) -> 0 | B25: =IF(H25="UNIDADE CONSTRUTIVA",0,IF(H25="CÉLULA CONSTRUTIVA",OFFSET(B25,-1,0)+1,OFFSET(B25,-1,0))) -> 1 | C25: =IF(H25="CÉLULA CONSTRUTIVA",0,IF(H25="ETAPA",OFFSET(C25,-1,0)+1,OFFSET(C25,-1,0))) -> 1 | D25: =IF(H25="ETAPA",0,IF(H25="SUBETAPA",OFFSET(D25,-1,0)+1,OFFSET(D25,-1,0))) -> 2 | E25: =IF(H25="Subetapa",0,IF(H25="serviço",OFFSET(E25,-1,0)+1,OFFSET(E25,-1,0))) -> 12 | H25: SERVIÇO | I25: =IF(H25="Unidade Construtiva",TEXT(A25,"00"),IF(H25="Célula Construtiva",TEXT(B25,"00"),IF(H25="Etapa",CONCATENATE(TEXT(B25,"00"),".",TEXT(C25,"000")),IF(H25="Subetapa",CONCATENATE(TEXT(B25,"00"),".",TEXT(C25,"000"),".",TEXT(D25,"000")),IF(H25="Serviço",CONCATENATE(TEXT(B25,"00"),".",TEXT(C25,"000"),".",TEXT(D25,"000"),".",TEXT(E25,"000")),""))))) -> 01.001.002.012 | J25: Projeto de Piscina | K25: =IFERROR(VLOOKUP(J25,BASES!$A$13:$E$342,3,FALSE),0) -> vb | L25: =IFERROR(VLOOKUP(J25,BASES!$A$13:$E$342,4,FALSE),0) -> 1 | M25: =IFERROR(VLOOKUP(J25,BASES!$A$13:$E$342,5,FALSE),0) -> 5300.5705 | N25: =IF(H25="Serviço",M25*L25,IF(H25="CÉLULA CONSTRUTIVA",SUMIFS($N$8:$N$419,$B$8:$B$419,B25,$H$8:$H$419,"Serviço"),IF(H25="ETAPA",SUMIFS($N$8:$N$419,$B$8:$B$419,B25,$C$8:$C$419,C25,$H$8:$H$419,"Serviço"),IF(H25="SUBETAPA",SUMIFS($N$8:$N$419,$B$8:$B$419,B25,$C$8:$C$419,C25,$D$8:$D$419,D25,$H$8:$H$419,"Serviço"),0)))) -> 5300.5705 | O25: =IF(VLOOKUP(J25,BASES!$A$13:$F$342,6,FALSE)="Recebido","Valor informado em formulário",IF(VLOOKUP(J25,BASES!$A$13:$F$342,6,FALSE)="Estimado","Estimado com base em índices históricos","Não solicitado")) -> Estimado com base em índices históricos | P25: Lançado ERP
A26: =IF($H26="UNIDADE CONSTRUTIVA",OFFSET(A26,-1,0)+1,LARGE(A$3:A25,1)) -> 0 | B26: =IF(H26="UNIDADE CONSTRUTIVA",0,IF(H26="CÉLULA CONSTRUTIVA",OFFSET(B26,-1,0)+1,OFFSET(B26,-1,0))) -> 1 | C26: =IF(H26="CÉLULA CONSTRUTIVA",0,IF(H26="ETAPA",OFFSET(C26,-1,0)+1,OFFSET(C26,-1,0))) -> 1 | D26: =IF(H26="ETAPA",0,IF(H26="SUBETAPA",OFFSET(D26,-1,0)+1,OFFSET(D26,-1,0))) -> 2 | E26: =IF(H26="Subetapa",0,IF(H26="serviço",OFFSET(E26,-1,0)+1,OFFSET(E26,-1,0))) -> 13 | H26: SERVIÇO | I26: =IF(H26="Unidade Construtiva",TEXT(A26,"00"),IF(H26="Célula Construtiva",TEXT(B26,"00"),IF(H26="Etapa",CONCATENATE(TEXT(B26,"00"),".",TEXT(C26,"000")),IF(H26="Subetapa",CONCATENATE(TEXT(B26,"00"),".",TEXT(C26,"000"),".",TEXT(D26,"000")),IF(H26="Serviço",CONCATENATE(TEXT(B26,"00"),".",TEXT(C26,"000"),".",TEXT(D26,"000"),".",TEXT(E26,"000")),""))))) -> 01.001.002.013 | J26: Projeto de Paisagismo | K26: =IFERROR(VLOOKUP(J26,BASES!$A$13:$E$342,3,FALSE),0) -> vb | L26: =IFERROR(VLOOKUP(J26,BASES!$A$13:$E$342,4,FALSE),0) -> 1 | M26: =IFERROR(VLOOKUP(J26,BASES!$A$13:$E$342,5,FALSE),0) -> 16744.39 | N26: =IF(H26="Serviço",M26*L26,IF(H26="CÉLULA CONSTRUTIVA",SUMIFS($N$8:$N$419,$B$8:$B$419,B26,$H$8:$H$419,"Serviço"),IF(H26="ETAPA",SUMIFS($N$8:$N$419,$B$8:$B$419,B26,$C$8:$C$419,C26,$H$8:$H$419,"Serviço"),IF(H26="SUBETAPA",SUMIFS($N$8:$N$419,$B$8:$B$419,B26,$C$8:$C$419,C26,$D$8:$D$419,D26,$H$8:$H$419,"Serviço"),0)))) -> 16744.39 | O26: =IF(VLOOKUP(J26,BASES!$A$13:$F$342,6,FALSE)="Recebido","Valor informado em formulário",IF(VLOOKUP(J26,BASES!$A$13:$F$342,6,FALSE)="Estimado","Estimado com base em índices históricos","Não solicitado")) -> Estimado com base em índices históricos | P26: Lançado ERP
A27: =IF($H27="UNIDADE CONSTRUTIVA",OFFSET(A27,-1,0)+1,LARGE(A$3:A26,1)) -> 0 | B27: =IF(H27="UNIDADE CONSTRUTIVA",0,IF(H27="CÉLULA CONSTRUTIVA",OFFSET(B27,-1,0)+1,OFFSET(B27,-1,0))) -> 1 | C27: =IF(H27="CÉLULA CONSTRUTIVA",0,IF(H27="ETAPA",OFFSET(C27,-1,0)+1,OFFSET(C27,-1,0))) -> 1 | D27: =IF(H27="ETAPA",0,IF(H27="SUBETAPA",OFFSET(D27,-1,0)+1,OFFSET(D27,-1,0))) -> 3 | E27: =IF(H27="Subetapa",0,IF(H27="serviço",OFFSET(E27,-1,0)+1,OFFSET(E27,-1,0))) -> 0 | H27: SUBETAPA | I27: =IF(H27="Unidade Construtiva",TEXT(A27,"00"),IF(H27="Célula Construtiva",TEXT(B27,"00"),IF(H27="Etapa",CONCATENATE(TEXT(B27,"00"),".",TEXT(C27,"000")),IF(H27="Subetapa",CONCATENATE(TEXT(B27,"00"),".",TEXT(C27,"000"),".",TEXT(D27,"000")),IF(H27="Serviço",CONCATENATE(TEXT(B27,"00"),".",TEXT(C27,"000"),".",TEXT(D27,"000"),".",TEXT(E27,"000")),""))))) -> 01.001.003 | J27: Consultorias | N27: =IF(H27="Serviço",M27*L27,IF(H27="CÉLULA CONSTRUTIVA",SUMIFS($N$8:$N$419,$B$8:$B$419,B27,$H$8:$H$419,"Serviço"),IF(H27="ETAPA",SUMIFS($N$8:$N$419,$B$8:$B$419,B27,$C$8:$C$419,C27,$H$8:$H$419,"Serviço"),IF(H27="SUBETAPA",SUMIFS($N$8:$N$419,$B$8:$B$419,B27,$C$8:$C$419,C27,$D$8:$D$419,D27,$H$8:$H$419,"Serviço"),0)))) -> 150264.96 | Q27: =N27/'Obra '!$C$32 -> 0.031476415
A28: =IF($H28="UNIDADE CONSTRUTIVA",OFFSET(A28,-1,0)+1,LARGE(A$3:A27,1)) -> 0 | B28: =IF(H28="UNIDADE CONSTRUTIVA",0,IF(H28="CÉLULA CONSTRUTIVA",OFFSET(B28,-1,0)+1,OFFSET(B28,-1,0))) -> 1 | C28: =IF(H28="CÉLULA CONSTRUTIVA",0,IF(H28="ETAPA",OFFSET(C28,-1,0)+1,OFFSET(C28,-1,0))) -> 1 | D28: =IF(H28="ETAPA",0,IF(H28="SUBETAPA",OFFSET(D28,-1,0)+1,OFFSET(D28,-1,0))) -> 3 | E28: =IF(H28="Subetapa",0,IF(H28="serviço",OFFSET(E28,-1,0)+1,OFFSET(E28,-1,0))) -> 1 | H28: SERVIÇO | I28: =IF(H28="Unidade Construtiva",TEXT(A28,"00"),IF(H28="Célula Construtiva",TEXT(B28,"00"),IF(H28="Etapa",CONCATENATE(TEXT(B28,"00"),".",TEXT(C28,"000")),IF(H28="Subetapa",CONCATENATE(TEXT(B28,"00"),".",TEXT(C28,"000"),".",TEXT(D28,"000")),IF(H28="Serviço",CONCATENATE(TEXT(B28,"00"),".",TEXT(C28,"000"),".",TEXT(D28,"000"),".",TEXT(E28,"000")),""))))) -> 01.001.003.001 | J28: Compatibilização de Projetos BIM | K28: =IFERROR(VLOOKUP(J28,BASES!$A$13:$E$342,3,FALSE),0) -> vb | L28: =IFERROR(VLOOKUP(J28,BASES!$A$13:$E$342,4,FALSE),0) -> 1 | M28: =IFERROR(VLOOKUP(J28,BASES!$A$13:$E$342,5,FALSE),0) -> 68700 | N28: =IF(H28="Serviço",M28*L28,IF(H28="CÉLULA CONSTRUTIVA",SUMIFS($N$8:$N$419,$B$8:$B$419,B28,$H$8:$H$419,"Serviço"),IF(H28="ETAPA",SUMIFS($N$8:$N$419,$B$8:$B$419,B28,$C$8:$C$419,C28,$H$8:$H$419,"Serviço"),IF(H28="SUBETAPA",SUMIFS($N$8:$N$419,$B$8:$B$419,B28,$C$8:$C$419,C28,$D$8:$D$419,D28,$H$8:$H$419,"Serviço"),0)))) -> 68700 | O28: =IF(VLOOKUP(J28,BASES!$A$13:$F$342,6,FALSE)="Recebido","Valor informado em formulário",IF(VLOOKUP(J28,BASES!$A$13:$F$342,6,FALSE)="Estimado","Estimado com base em índices históricos","Não solicitado")) -> Valor informado em formulário | P28: Lançado ERP
A29: =IF($H29="UNIDADE CONSTRUTIVA",OFFSET(A29,-1,0)+1,LARGE(A$3:A28,1)) -> 0 | B29: =IF(H29="UNIDADE CONSTRUTIVA",0,IF(H29="CÉLULA CONSTRUTIVA",OFFSET(B29,-1,0)+1,OFFSET(B29,-1,0))) -> 1 | C29: =IF(H29="CÉLULA CONSTRUTIVA",0,IF(H29="ETAPA",OFFSET(C29,-1,0)+1,OFFSET(C29,-1,0))) -> 1 | D29: =IF(H29="ETAPA",0,IF(H29="SUBETAPA",OFFSET(D29,-1,0)+1,OFFSET(D29,-1,0))) -> 3 | E29: =IF(H29="Subetapa",0,IF(H29="serviço",OFFSET(E29,-1,0)+1,OFFSET(E29,-1,0))) -> 2 | H29: SERVIÇO | I29: =IF(H29="Unidade Construtiva",TEXT(A29,"00"),IF(H29="Célula Construtiva",TEXT(B29,"00"),IF(H29="Etapa",CONCATENATE(TEXT(B29,"00"),".",TEXT(C29,"000")),IF(H29="Subetapa",CONCATENATE(TEXT(B29,"00"),".",TEXT(C29,"000"),".",TEXT(D29,"000")),IF(H29="Serviço",CONCATENATE(TEXT(B29,"00"),".",TEXT(C29,"000"),".",TEXT(D29,"000"),".",TEXT(E29,"000")),""))))) -> 01.001.003.002 | J29: Consultoria técnica de legalização | K29: =IFERROR(VLOOKUP(J29,BASES!$A$13:$E$342,3,FALSE),0) -> vb | L29: =IFERROR(VLOOKUP(J29,BASES!$A$13:$E$342,4,FALSE),0) -> 1 | M29: =IFERROR(VLOOKUP(J29,BASES!$A$13:$E$342,5,FALSE),0) -> 15000 | N29: =IF(H29="Serviço",M29*L29,IF(H29="CÉLULA CONSTRUTIVA",SUMIFS($N$8:$N$419,$B$8:$B$419,B29,$H$8:$H$419,"Serviço"),IF(H29="ETAPA",SUMIFS($N$8:$N$419,$B$8:$B$419,B29,$C$8:$C$419,C29,$H$8:$H$419,"Serviço"),IF(H29="SUBETAPA",SUMIFS($N$8:$N$419,$B$8:$B$419,B29,$C$8:$C$419,C29,$D$8:$D$419,D29,$H$8:$H$419,"Serviço"),0)))) -> 15000 | O29: =IF(VLOOKUP(J29,BASES!$A$13:$F$342,6,FALSE)="Recebido","Valor informado em formulário",IF(VLOOKUP(J29,BASES!$A$13:$F$342,6,FALSE)="Estimado","Estimado com base em índices históricos","Não solicitado")) -> Valor informado em formulário | P29: Lançado ERP
A30: =IF($H30="UNIDADE CONSTRUTIVA",OFFSET(A30,-1,0)+1,LARGE(A$3:A29,1)) -> 0 | B30: =IF(H30="UNIDADE CONSTRUTIVA",0,IF(H30="CÉLULA CONSTRUTIVA",OFFSET(B30,-1,0)+1,OFFSET(B30,-1,0))) -> 1 | C30: =IF(H30="CÉLULA CONSTRUTIVA",0,IF(H30="ETAPA",OFFSET(C30,-1,0)+1,OFFSET(C30,-1,0))) -> 1 | D30: =IF(H30="ETAPA",0,IF(H30="SUBETAPA",OFFSET(D30,-1,0)+1,OFFSET(D30,-1,0))) -> 3 | E30: =IF(H30="Subetapa",0,IF(H30="serviço",OFFSET(E30,-1,0)+1,OFFSET(E30,-1,0))) -> 3 | H30: SERVIÇO | I30: =IF(H30="Unidade Construtiva",TEXT(A30,"00"),IF(H30="Célula Construtiva",TEXT(B30,"00"),IF(H30="Etapa",CONCATENATE(TEXT(B30,"00"),".",TEXT(C30,"000")),IF(H30="Subetapa",CONCATENATE(TEXT(B30,"00"),".",TEXT(C30,"000"),".",TEXT(D30,"000")),IF(H30="Serviço",CONCATENATE(TEXT(B30,"00"),".",TEXT(C30,"000"),".",TEXT(D30,"000"),".",TEXT(E30,"000")),""))))) -> 01.001.003.003 | J30: Orçamento e planejamento | K30: =IFERROR(VLOOKUP(J30,BASES!$A$13:$E$342,3,FALSE),0) -> vb | L30: =IFERROR(VLOOKUP(J30,BASES!$A$13:$E$342,4,FALSE),0) -> 1 | M30: =IFERROR(VLOOKUP(J30,BASES!$A$13:$E$342,5,FALSE),0) -> 38968.02 | N30: =IF(H30="Serviço",M30*L30,IF(H30="CÉLULA CONSTRUTIVA",SUMIFS($N$8:$N$419,$B$8:$B$419,B30,$H$8:$H$419,"Serviço"),IF(H30="ETAPA",SUMIFS($N$8:$N$419,$B$8:$B$419,B30,$C$8:$C$419,C30,$H$8:$H$419,"Serviço"),IF(H30="SUBETAPA",SUMIFS($N$8:$N$419,$B$8:$B$419,B30,$C$8:$C$419,C30,$D$8:$D$419,D30,$H$8:$H$419,"Serviço"),0)))) -> 38968.02 | O30: =IF(VLOOKUP(J30,BASES!$A$13:$F$342,6,FALSE)="Recebido","Valor informado em formulário",IF(VLOOKUP(J30,BASES!$A$13:$F$342,6,FALSE)="Estimado","Estimado com base em índices históricos","Não solicitado")) -> Valor informado em formulário | P30: Lançado ERP
A31: =IF($H31="UNIDADE CONSTRUTIVA",OFFSET(A31,-1,0)+1,LARGE(A$3:A30,1)) -> 0 | B31: =IF(H31="UNIDADE CONSTRUTIVA",0,IF(H31="CÉLULA CONSTRUTIVA",OFFSET(B31,-1,0)+1,OFFSET(B31,-1,0))) -> 1 | C31: =IF(H31="CÉLULA CONSTRUTIVA",0,IF(H31="ETAPA",OFFSET(C31,-1,0)+1,OFFSET(C31,-1,0))) -> 1 | D31: =IF(H31="ETAPA",0,IF(H31="SUBETAPA",OFFSET(D31,-1,0)+1,OFFSET(D31,-1,0))) -> 3 | E31: =IF(H31="Subetapa",0,IF(H31="serviço",OFFSET(E31,-1,0)+1,OFFSET(E31,-1,0))) -> 4 | H31: SERVIÇO | I31: =IF(H31="Unidade Construtiva",TEXT(A31,"00"),IF(H31="Célula Construtiva",TEXT(B31,"00"),IF(H31="Etapa",CONCATENATE(TEXT(B31,"00"),".",TEXT(C31,"000")),IF(H31="Subetapa",CONCATENATE(TEXT(B31,"00"),".",TEXT(C31,"000"),".",TEXT(D31,"000")),IF(H31="Serviço",CONCATENATE(TEXT(B31,"00"),".",TEXT(C31,"000"),".",TEXT(D31,"000"),".",TEXT(E31,"000")),""))))) -> 01.001.003.004 | J31: Consultoria técnica de fachada | K31: =IFERROR(VLOOKUP(J31,BASES!$A$13:$E$342,3,FALSE),0) -> vb | L31: =IFERROR(VLOOKUP(J31,BASES!$A$13:$E$342,4,FALSE),0) -> 1 | M31: =IFERROR(VLOOKUP(J31,BASES!$A$13:$E$342,5,FALSE),0) -> 27596.943 | N31: =IF(H31="Serviço",M31*L31,IF(H31="CÉLULA CONSTRUTIVA",SUMIFS($N$8:$N$419,$B$8:$B$419,B31,$H$8:$H$419,"Serviço"),IF(H31="ETAPA",SUMIFS($N$8:$N$419,$B$8:$B$419,B31,$C$8:$C$419,C31,$H$8:$H$419,"Serviço"),IF(H31="SUBETAPA",SUMIFS($N$8:$N$419,$B$8:$B$419,B31,$C$8:$C$419,C31,$D$8:$D$419,D31,$H$8:$H$419,"Serviço"),0)))) -> 27596.943 | O31: =IF(VLOOKUP(J31,BASES!$A$13:$F$342,6,FALSE)="Recebido","Valor informado em formulário",IF(VLOOKUP(J31,BASES!$A$13:$F$342,6,FALSE)="Estimado","Estimado com base em índices históricos","Não solicitado")) -> Estimado com base em índices históricos | P31: Lançado ERP
A32: =IF($H32="UNIDADE CONSTRUTIVA",OFFSET(A32,-1,0)+1,LARGE(A$3:A31,1)) -> 0 | B32: =IF(H32="UNIDADE CONSTRUTIVA",0,IF(H32="CÉLULA CONSTRUTIVA",OFFSET(B32,-1,0)+1,OFFSET(B32,-1,0))) -> 1 | C32: =IF(H32="CÉLULA CONSTRUTIVA",0,IF(H32="ETAPA",OFFSET(C32,-1,0)+1,OFFSET(C32,-1,0))) -> 1 | D32: =IF(H32="ETAPA",0,IF(H32="SUBETAPA",OFFSET(D32,-1,0)+1,OFFSET(D32,-1,0))) -> 4 | E32: =IF(H32="Subetapa",0,IF(H32="serviço",OFFSET(E32,-1,0)+1,OFFSET(E32,-1,0))) -> 0 | H32: SUBETAPA | I32: =IF(H32="Unidade Construtiva",TEXT(A32,"00"),IF(H32="Célula Construtiva",TEXT(B32,"00"),IF(H32="Etapa",CONCATENATE(TEXT(B32,"00"),".",TEXT(C32,"000")),IF(H32="Subetapa",CONCATENATE(TEXT(B32,"00"),".",TEXT(C32,"000"),".",TEXT(D32,"000")),IF(H32="Serviço",CONCATENATE(TEXT(B32,"00"),".",TEXT(C32,"000"),".",TEXT(D32,"000"),".",TEXT(E32,"000")),""))))) -> 01.001.004 | J32: Ensaios | N32: =IF(H32="Serviço",M32*L32,IF(H32="CÉLULA CONSTRUTIVA",SUMIFS($N$8:$N$419,$B$8:$B$419,B32,$H$8:$H$419,"Serviço"),IF(H32="ETAPA",SUMIFS($N$8:$N$419,$B$8:$B$419,B32,$C$8:$C$419,C32,$H$8:$H$419,"Serviço"),IF(H32="SUBETAPA",SUMIFS($N$8:$N$419,$B$8:$B$419,B32,$C$8:$C$419,C32,$D$8:$D$419,D32,$H$8:$H$419,"Serviço"),0)))) -> 59854.444 | Q32: =N32/'Obra '!$C$32 -> 0.012537875
A33: =IF($H33="UNIDADE CONSTRUTIVA",OFFSET(A33,-1,0)+1,LARGE(A$3:A32,1)) -> 0 | B33: =IF(H33="UNIDADE CONSTRUTIVA",0,IF(H33="CÉLULA CONSTRUTIVA",OFFSET(B33,-1,0)+1,OFFSET(B33,-1,0))) -> 1 | C33: =IF(H33="CÉLULA CONSTRUTIVA",0,IF(H33="ETAPA",OFFSET(C33,-1,0)+1,OFFSET(C33,-1,0))) -> 1 | D33: =IF(H33="ETAPA",0,IF(H33="SUBETAPA",OFFSET(D33,-1,0)+1,OFFSET(D33,-1,0))) -> 4 | E33: =IF(H33="Subetapa",0,IF(H33="serviço",OFFSET(E33,-1,0)+1,OFFSET(E33,-1,0))) -> 1 | H33: SERVIÇO | I33: =IF(H33="Unidade Construtiva",TEXT(A33,"00"),IF(H33="Célula Construtiva",TEXT(B33,"00"),IF(H33="Etapa",CONCATENATE(TEXT(B33,"00"),".",TEXT(C33,"000")),IF(H33="Subetapa",CONCATENATE(TEXT(B33,"00"),".",TEXT(C33,"000"),".",TEXT(D33,"000")),IF(H33="Serviço",CONCATENATE(TEXT(B33,"00"),".",TEXT(C33,"000"),".",TEXT(D33,"000"),".",TEXT(E33,"000")),""))))) -> 01.001.004.001 | J33: Controle Tecnologico de Concreto | K33: =IFERROR(VLOOKUP(J33,BASES!$A$13:$E$342,3,FALSE),0) -> vb | L33: =IFERROR(VLOOKUP(J33,BASES!$A$13:$E$342,4,FALSE),0) -> 1 | M33: =IFERROR(VLOOKUP(J33,BASES!$A$13:$E$342,5,FALSE),0) -> 50780 | N33: =IF(H33="Serviço",M33*L33,IF(H33="CÉLULA CONSTRUTIVA",SUMIFS($N$8:$N$419,$B$8:$B$419,B33,$H$8:$H$419,"Serviço"),IF(H33="ETAPA",SUMIFS($N$8:$N$419,$B$8:$B$419,B33,$C$8:$C$419,C33,$H$8:$H$419,"Serviço"),IF(H33="SUBETAPA",SUMIFS($N$8:$N$419,$B$8:$B$419,B33,$C$8:$C$419,C33,$D$8:$D$419,D33,$H$8:$H$419,"Serviço"),0)))) -> 50780 | O33: Levantando conforme aba "Ensaios" | P33: Pendente
A34: =IF($H34="UNIDADE CONSTRUTIVA",OFFSET(A34,-1,0)+1,LARGE(A$3:A33,1)) -> 0 | B34: =IF(H34="UNIDADE CONSTRUTIVA",0,IF(H34="CÉLULA CONSTRUTIVA",OFFSET(B34,-1,0)+1,OFFSET(B34,-1,0))) -> 1 | C34: =IF(H34="CÉLULA CONSTRUTIVA",0,IF(H34="ETAPA",OFFSET(C34,-1,0)+1,OFFSET(C34,-1,0))) -> 1 | D34: =IF(H34="ETAPA",0,IF(H34="SUBETAPA",OFFSET(D34,-1,0)+1,OFFSET(D34,-1,0))) -> 4 | E34: =IF(H34="Subetapa",0,IF(H34="serviço",OFFSET(E34,-1,0)+1,OFFSET(E34,-1,0))) -> 2 | H34: SERVIÇO | I34: =IF(H34="Unidade Construtiva",TEXT(A34,"00"),IF(H34="Célula Construtiva",TEXT(B34,"00"),IF(H34="Etapa",CONCATENATE(TEXT(B34,"00"),".",TEXT(C34,"000")),IF(H34="Subetapa",CONCATENATE(TEXT(B34,"00"),".",TEXT(C34,"000"),".",TEXT(D34,"000")),IF(H34="Serviço",CONCATENATE(TEXT(B34,"00"),".",TEXT(C34,"000"),".",TEXT(D34,"000"),".",TEXT(E34,"000")),""))))) -> 01.001.004.002 | J34: Ensaio de guarda-corpo | K34: =IFERROR(VLOOKUP(J34,BASES!$A$13:$E$342,3,FALSE),0) -> vb | L34: =IFERROR(VLOOKUP(J34,BASES!$A$13:$E$342,4,FALSE),0) -> 1 | M34: =IFERROR(VLOOKUP(J34,BASES!$A$13:$E$342,5,FALSE),0) -> 4210 | N34: =IF(H34="Serviço",M34*L34,IF(H34="CÉLULA CONSTRUTIVA",SUMIFS($N$8:$N$419,$B$8:$B$419,B34,$H$8:$H$419,"Serviço"),IF(H34="ETAPA",SUMIFS($N$8:$N$419,$B$8:$B$419,B34,$C$8:$C$419,C34,$H$8:$H$419,"Serviço"),IF(H34="SUBETAPA",SUMIFS($N$8:$N$419,$B$8:$B$419,B34,$C$8:$C$419,C34,$D$8:$D$419,D34,$H$8:$H$419,"Serviço"),0)))) -> 4210 | O34: =IF(VLOOKUP(J34,BASES!$A$13:$F$342,6,FALSE)="Recebido","Valor informado em formulário",IF(VLOOKUP(J34,BASES!$A$13:$F$342,6,FALSE)="Estimado","Estimado com base em índices históricos","Não solicitado")) -> Estimado com base em índices históricos | P34: Lançado ERP
A35: =IF($H35="UNIDADE CONSTRUTIVA",OFFSET(A35,-1,0)+1,LARGE(A$3:A34,1)) -> 0 | B35: =IF(H35="UNIDADE CONSTRUTIVA",0,IF(H35="CÉLULA CONSTRUTIVA",OFFSET(B35,-1,0)+1,OFFSET(B35,-1,0))) -> 1 | C35: =IF(H35="CÉLULA CONSTRUTIVA",0,IF(H35="ETAPA",OFFSET(C35,-1,0)+1,OFFSET(C35,-1,0))) -> 1 | D35: =IF(H35="ETAPA",0,IF(H35="SUBETAPA",OFFSET(D35,-1,0)+1,OFFSET(D35,-1,0))) -> 4 | E35: =IF(H35="Subetapa",0,IF(H35="serviço",OFFSET(E35,-1,0)+1,OFFSET(E35,-1,0))) -> 3 | H35: SERVIÇO | I35: =IF(H35="Unidade Construtiva",TEXT(A35,"00"),IF(H35="Célula Construtiva",TEXT(B35,"00"),IF(H35="Etapa",CONCATENATE(TEXT(B35,"00"),".",TEXT(C35,"000")),IF(H35="Subetapa",CONCATENATE(TEXT(B35,"00"),".",TEXT(C35,"000"),".",TEXT(D35,"000")),IF(H35="Serviço",CONCATENATE(TEXT(B35,"00"),".",TEXT(C35,"000"),".",TEXT(D35,"000"),".",TEXT(E35,"000")),""))))) -> 01.001.004.003 | J35: Ensaio de arrancamento de reboco | K35: =IFERROR(VLOOKUP(J35,BASES!$A$13:$E$342,3,FALSE),0) -> vb | L35: =IFERROR(VLOOKUP(J35,BASES!$A$13:$E$342,4,FALSE),0) -> 1 | M35: =IFERROR(VLOOKUP(J35,BASES!$A$13:$E$342,5,FALSE),0) -> 1260 | N35: =IF(H35="Serviço",M35*L35,IF(H35="CÉLULA CONSTRUTIVA",SUMIFS($N$8:$N$419,$B$8:$B$419,B35,$H$8:$H$419,"Serviço"),IF(H35="ETAPA",SUMIFS($N$8:$N$419,$B$8:$B$419,B35,$C$8:$C$419,C35,$H$8:$H$419,"Serviço"),IF(H35="SUBETAPA",SUMIFS($N$8:$N$419,$B$8:$B$419,B35,$C$8:$C$419,C35,$D$8:$D$419,D35,$H$8:$H$419,"Serviço"),0)))) -> 1260 | O35: =IF(VLOOKUP(J35,BASES!$A$13:$F$342,6,FALSE)="Recebido","Valor informado em formulário",IF(VLOOKUP(J35,BASES!$A$13:$F$342,6,FALSE)="Estimado","Estimado com base em índices históricos","Não solicitado")) -> Estimado com base em índices históricos | P35: Lançado ERP
A36: =IF($H36="UNIDADE CONSTRUTIVA",OFFSET(A36,-1,0)+1,LARGE(A$3:A35,1)) -> 0 | B36: =IF(H36="UNIDADE CONSTRUTIVA",0,IF(H36="CÉLULA CONSTRUTIVA",OFFSET(B36,-1,0)+1,OFFSET(B36,-1,0))) -> 1 | C36: =IF(H36="CÉLULA CONSTRUTIVA",0,IF(H36="ETAPA",OFFSET(C36,-1,0)+1,OFFSET(C36,-1,0))) -> 1 | D36: =IF(H36="ETAPA",0,IF(H36="SUBETAPA",OFFSET(D36,-1,0)+1,OFFSET(D36,-1,0))) -> 4 | E36: =IF(H36="Subetapa",0,IF(H36="serviço",OFFSET(E36,-1,0)+1,OFFSET(E36,-1,0))) -> 4 | H36: SERVIÇO | I36: =IF(H36="Unidade Construtiva",TEXT(A36,"00"),IF(H36="Célula Construtiva",TEXT(B36,"00"),IF(H36="Etapa",CONCATENATE(TEXT(B36,"00"),".",TEXT(C36,"000")),IF(H36="Subetapa",CONCATENATE(TEXT(B36,"00"),".",TEXT(C36,"000"),".",TEXT(D36,"000")),IF(H36="Serviço",CONCATENATE(TEXT(B36,"00"),".",TEXT(C36,"000"),".",TEXT(D36,"000"),".",TEXT(E36,"000")),""))))) -> 01.001.004.004 | J36: Ensaio de arrancamento revestimento cerâmico | K36: =IFERROR(VLOOKUP(J36,BASES!$A$13:$E$342,3,FALSE),0) -> vb | L36: =IFERROR(VLOOKUP(J36,BASES!$A$13:$E$342,4,FALSE),0) -> 1 | M36: =IFERROR(VLOOKUP(J36,BASES!$A$13:$E$342,5,FALSE),0) -> 664.44444 | N36: =IF(H36="Serviço",M36*L36,IF(H36="CÉLULA CONSTRUTIVA",SUMIFS($N$8:$N$419,$B$8:$B$419,B36,$H$8:$H$419,"Serviço"),IF(H36="ETAPA",SUMIFS($N$8:$N$419,$B$8:$B$419,B36,$C$8:$C$419,C36,$H$8:$H$419,"Serviço"),IF(H36="SUBETAPA",SUMIFS($N$8:$N$419,$B$8:$B$419,B36,$C$8:$C$419,C36,$D$8:$D$419,D36,$H$8:$H$419,"Serviço"),0)))) -> 664.44444 | O36: =IF(VLOOKUP(J36,BASES!$A$13:$F$342,6,FALSE)="Recebido","Valor informado em formulário",IF(VLOOKUP(J36,BASES!$A$13:$F$342,6,FALSE)="Estimado","Estimado com base em índices históricos","Não solicitado")) -> Estimado com base em índices históricos | P36: Lançado ERP
A37: =IF($H37="UNIDADE CONSTRUTIVA",OFFSET(A37,-1,0)+1,LARGE(A$3:A36,1)) -> 0 | B37: =IF(H37="UNIDADE CONSTRUTIVA",0,IF(H37="CÉLULA CONSTRUTIVA",OFFSET(B37,-1,0)+1,OFFSET(B37,-1,0))) -> 1 | C37: =IF(H37="CÉLULA CONSTRUTIVA",0,IF(H37="ETAPA",OFFSET(C37,-1,0)+1,OFFSET(C37,-1,0))) -> 1 | D37: =IF(H37="ETAPA",0,IF(H37="SUBETAPA",OFFSET(D37,-1,0)+1,OFFSET(D37,-1,0))) -> 4 | E37: =IF(H37="Subetapa",0,IF(H37="serviço",OFFSET(E37,-1,0)+1,OFFSET(E37,-1,0))) -> 5 | H37: SERVIÇO | I37: =IF(H37="Unidade Construtiva",TEXT(A37,"00"),IF(H37="Célula Construtiva",TEXT(B37,"00"),IF(H37="Etapa",CONCATENATE(TEXT(B37,"00"),".",TEXT(C37,"000")),IF(H37="Subetapa",CONCATENATE(TEXT(B37,"00"),".",TEXT(C37,"000"),".",TEXT(D37,"000")),IF(H37="Serviço",CONCATENATE(TEXT(B37,"00"),".",TEXT(C37,"000"),".",TEXT(D37,"000"),".",TEXT(E37,"000")),""))))) -> 01.001.004.005 | J37: Ensaio de arrancamento fachada | K37: =IFERROR(VLOOKUP(J37,BASES!$A$13:$E$342,3,FALSE),0) -> vb | L37: =IFERROR(VLOOKUP(J37,BASES!$A$13:$E$342,4,FALSE),0) -> 1 | M37: =IFERROR(VLOOKUP(J37,BASES!$A$13:$E$342,5,FALSE),0) -> 1260 | N37: =IF(H37="Serviço",M37*L37,IF(H37="CÉLULA CONSTRUTIVA",SUMIFS($N$8:$N$419,$B$8:$B$419,B37,$H$8:$H$419,"Serviço"),IF(H37="ETAPA",SUMIFS($N$8:$N$419,$B$8:$B$419,B37,$C$8:$C$419,C37,$H$8:$H$419,"Serviço"),IF(H37="SUBETAPA",SUMIFS($N$8:$N$419,$B$8:$B$419,B37,$C$8:$C$419,C37,$D$8:$D$419,D37,$H$8:$H$419,"Serviço"),0)))) -> 1260 | O37: =IF(VLOOKUP(J37,BASES!$A$13:$F$342,6,FALSE)="Recebido","Valor informado em formulário",IF(VLOOKUP(J37,BASES!$A$13:$F$342,6,FALSE)="Estimado","Estimado com base em índices históricos","Não solicitado")) -> Estimado com base em índices históricos | P37: Lançado ERP
A38: =IF($H38="UNIDADE CONSTRUTIVA",OFFSET(A38,-1,0)+1,LARGE(A$3:A37,1)) -> 0 | B38: =IF(H38="UNIDADE CONSTRUTIVA",0,IF(H38="CÉLULA CONSTRUTIVA",OFFSET(B38,-1,0)+1,OFFSET(B38,-1,0))) -> 1 | C38: =IF(H38="CÉLULA CONSTRUTIVA",0,IF(H38="ETAPA",OFFSET(C38,-1,0)+1,OFFSET(C38,-1,0))) -> 1 | D38: =IF(H38="ETAPA",0,IF(H38="SUBETAPA",OFFSET(D38,-1,0)+1,OFFSET(D38,-1,0))) -> 4 | E38: =IF(H38="Subetapa",0,IF(H38="serviço",OFFSET(E38,-1,0)+1,OFFSET(E38,-1,0))) -> 6 | H38: SERVIÇO | I38: =IF(H38="Unidade Construtiva",TEXT(A38,"00"),IF(H38="Célula Construtiva",TEXT(B38,"00"),IF(H38="Etapa",CONCATENATE(TEXT(B38,"00"),".",TEXT(C38,"000")),IF(H38="Subetapa",CONCATENATE(TEXT(B38,"00"),".",TEXT(C38,"000"),".",TEXT(D38,"000")),IF(H38="Serviço",CONCATENATE(TEXT(B38,"00"),".",TEXT(C38,"000"),".",TEXT(D38,"000"),".",TEXT(E38,"000")),""))))) -> 01.001.004.006 | J38: Ensaio de arrancamento de gancho da cobertura | K38: =IFERROR(VLOOKUP(J38,BASES!$A$13:$E$342,3,FALSE),0) -> vb | L38: =IFERROR(VLOOKUP(J38,BASES!$A$13:$E$342,4,FALSE),0) -> 1 | M38: =IFERROR(VLOOKUP(J38,BASES!$A$13:$E$342,5,FALSE),0) -> 1680 | N38: =IF(H38="Serviço",M38*L38,IF(H38="CÉLULA CONSTRUTIVA",SUMIFS($N$8:$N$419,$B$8:$B$419,B38,$H$8:$H$419,"Serviço"),IF(H38="ETAPA",SUMIFS($N$8:$N$419,$B$8:$B$419,B38,$C$8:$C$419,C38,$H$8:$H$419,"Serviço"),IF(H38="SUBETAPA",SUMIFS($N$8:$N$419,$B$8:$B$419,B38,$C$8:$C$419,C38,$D$8:$D$419,D38,$H$8:$H$419,"Serviço"),0)))) -> 1680 | O38: =IF(VLOOKUP(J38,BASES!$A$13:$F$342,6,FALSE)="Recebido","Valor informado em formulário",IF(VLOOKUP(J38,BASES!$A$13:$F$342,6,FALSE)="Estimado","Estimado com base em índices históricos","Não solicitado")) -> Estimado com base em índices históricos | P38: Lançado ERP
A39: =IF($H39="UNIDADE CONSTRUTIVA",OFFSET(A39,-1,0)+1,LARGE(A$3:A38,1)) -> 0 | B39: =IF(H39="UNIDADE CONSTRUTIVA",0,IF(H39="CÉLULA CONSTRUTIVA",OFFSET(B39,-1,0)+1,OFFSET(B39,-1,0))) -> 1 | C39: =IF(H39="CÉLULA CONSTRUTIVA",0,IF(H39="ETAPA",OFFSET(C39,-1,0)+1,OFFSET(C39,-1,0))) -> 2 | D39: =IF(H39="ETAPA",0,IF(H39="SUBETAPA",OFFSET(D39,-1,0)+1,OFFSET(D39,-1,0))) -> 0 | E39: =IF(H39="Subetapa",0,IF(H39="serviço",OFFSET(E39,-1,0)+1,OFFSET(E39,-1,0))) -> 6 | H39: ETAPA | I39: =IF(H39="Unidade Construtiva",TEXT(A39,"00"),IF(H39="Célula Construtiva",TEXT(B39,"00"),IF(H39="Etapa",CONCATENATE(TEXT(B39,"00"),".",TEXT(C39,"000")),IF(H39="Subetapa",CONCATENATE(TEXT(B39,"00"),".",TEXT(C39,"000"),".",TEXT(D39,"000")),IF(H39="Serviço",CONCATENATE(TEXT(B39,"00"),".",TEXT(C39,"000"),".",TEXT(D39,"000"),".",TEXT(E39,"000")),""))))) -> 01.002 | J39: CONSUMOS, TAXAS E DOCUMENTOS | N39: =IF(H39="Serviço",M39*L39,IF(H39="CÉLULA CONSTRUTIVA",SUMIFS($N$8:$N$419,$B$8:$B$419,B39,$H$8:$H$419,"Serviço"),IF(H39="ETAPA",SUMIFS($N$8:$N$419,$B$8:$B$419,B39,$C$8:$C$419,C39,$H$8:$H$419,"Serviço"),IF(H39="SUBETAPA",SUMIFS($N$8:$N$419,$B$8:$B$419,B39,$C$8:$C$419,C39,$D$8:$D$419,D39,$H$8:$H$419,"Serviço"),0)))) -> 1632860.3 | P39: - | Q39: =N39/'Obra '!$C$32 -> 0.34203974
A40: =IF($H40="UNIDADE CONSTRUTIVA",OFFSET(A40,-1,0)+1,LARGE(A$3:A39,1)) -> 0 | B40: =IF(H40="UNIDADE CONSTRUTIVA",0,IF(H40="CÉLULA CONSTRUTIVA",OFFSET(B40,-1,0)+1,OFFSET(B40,-1,0))) -> 1 | C40: =IF(H40="CÉLULA CONSTRUTIVA",0,IF(H40="ETAPA",OFFSET(C40,-1,0)+1,OFFSET(C40,-1,0))) -> 2 | D40: =IF(H40="ETAPA",0,IF(H40="SUBETAPA",OFFSET(D40,-1,0)+1,OFFSET(D40,-1,0))) -> 1 | E40: =IF(H40="Subetapa",0,IF(H40="serviço",OFFSET(E40,-1,0)+1,OFFSET(E40,-1,0))) -> 0 | H40: SUBETAPA | I40: =IF(H40="Unidade Construtiva",TEXT(A40,"00"),IF(H40="Célula Construtiva",TEXT(B40,"00"),IF(H40="Etapa",CONCATENATE(TEXT(B40,"00"),".",TEXT(C40,"000")),IF(H40="Subetapa",CONCATENATE(TEXT(B40,"00"),".",TEXT(C40,"000"),".",TEXT(D40,"000")),IF(H40="Serviço",CONCATENATE(TEXT(B40,"00"),".",TEXT(C40,"000"),".",TEXT(D40,"000"),".",TEXT(E40,"000")),""))))) -> 01.002.001 | J40: Licenciamentos, Taxas, Impostos, Aprovações e Seguros | N40: =IF(H40="Serviço",M40*L40,IF(H40="CÉLULA CONSTRUTIVA",SUMIFS($N$8:$N$419,$B$8:$B$419,B40,$H$8:$H$419,"Serviço"),IF(H40="ETAPA",SUMIFS($N$8:$N$419,$B$8:$B$419,B40,$C$8:$C$419,C40,$H$8:$H$419,"Serviço"),IF(H40="SUBETAPA",SUMIFS($N$8:$N$419,$B$8:$B$419,B40,$C$8:$C$419,C40,$D$8:$D$419,D40,$H$8:$H$419,"Serviço"),0)))) -> 1609594.9 | Q40: =N40/'Obra '!$C$32 -> 0.33716628
A41: =IF($H41="UNIDADE CONSTRUTIVA",OFFSET(A41,-1,0)+1,LARGE(A$3:A40,1)) -> 0 | B41: =IF(H41="UNIDADE CONSTRUTIVA",0,IF(H41="CÉLULA CONSTRUTIVA",OFFSET(B41,-1,0)+1,OFFSET(B41,-1,0))) -> 1 | C41: =IF(H41="CÉLULA CONSTRUTIVA",0,IF(H41="ETAPA",OFFSET(C41,-1,0)+1,OFFSET(C41,-1,0))) -> 2 | D41: =IF(H41="ETAPA",0,IF(H41="SUBETAPA",OFFSET(D41,-1,0)+1,OFFSET(D41,-1,0))) -> 1 | E41: =IF(H41="Subetapa",0,IF(H41="serviço",OFFSET(E41,-1,0)+1,OFFSET(E41,-1,0))) -> 1 | H41: SERVIÇO | I41: =IF(H41="Unidade Construtiva",TEXT(A41,"00"),IF(H41="Célula Construtiva",TEXT(B41,"00"),IF(H41="Etapa",CONCATENATE(TEXT(B41,"00"),".",TEXT(C41,"000")),IF(H41="Subetapa",CONCATENATE(TEXT(B41,"00"),".",TEXT(C41,"000"),".",TEXT(D41,"000")),IF(H41="Serviço",CONCATENATE(TEXT(B41,"00"),".",TEXT(C41,"000"),".",TEXT(D41,"000"),".",TEXT(E41,"000")),""))))) -> 01.002.001.001 | J41: Despesas de Seguros | K41: =IFERROR(VLOOKUP(J41,BASES!$A$13:$E$342,3,FALSE),0) -> vb | L41: =IFERROR(VLOOKUP(J41,BASES!$A$13:$E$342,4,FALSE),0) -> 1 | M41: =IFERROR(VLOOKUP(J41,BASES!$A$13:$E$342,5,FALSE),0) -> 23035.606 | N41: =IF(H41="Serviço",M41*L41,IF(H41="CÉLULA CONSTRUTIVA",SUMIFS($N$8:$N$419,$B$8:$B$419,B41,$H$8:$H$419,"Serviço"),IF(H41="ETAPA",SUMIFS($N$8:$N$419,$B$8:$B$419,B41,$C$8:$C$419,C41,$H$8:$H$419,"Serviço"),IF(H41="SUBETAPA",SUMIFS($N$8:$N$419,$B$8:$B$419,B41,$C$8:$C$419,C41,$D$8:$D$419,D41,$H$8:$H$419,"Serviço"),0)))) -> 23035.606 | O41: =IF(VLOOKUP(J41,BASES!$A$13:$F$342,6,FALSE)="Recebido","Valor informado em formulário",IF(VLOOKUP(J41,BASES!$A$13:$F$342,6,FALSE)="Estimado","Estimado com base em índices históricos","Não solicitado")) -> Estimado com base em índices históricos | P41: Lançado ERP
A42: =IF($H42="UNIDADE CONSTRUTIVA",OFFSET(A42,-1,0)+1,LARGE(A$3:A41,1)) -> 0 | B42: =IF(H42="UNIDADE CONSTRUTIVA",0,IF(H42="CÉLULA CONSTRUTIVA",OFFSET(B42,-1,0)+1,OFFSET(B42,-1,0))) -> 1 | C42: =IF(H42="CÉLULA CONSTRUTIVA",0,IF(H42="ETAPA",OFFSET(C42,-1,0)+1,OFFSET(C42,-1,0))) -> 2 | D42: =IF(H42="ETAPA",0,IF(H42="SUBETAPA",OFFSET(D42,-1,0)+1,OFFSET(D42,-1,0))) -> 1 | E42: =IF(H42="Subetapa",0,IF(H42="serviço",OFFSET(E42,-1,0)+1,OFFSET(E42,-1,0))) -> 2 | H42: SERVIÇO | I42: =IF(H42="Unidade Construtiva",TEXT(A42,"00"),IF(H42="Célula Construtiva",TEXT(B42,"00"),IF(H42="Etapa",CONCATENATE(TEXT(B42,"00"),".",TEXT(C42,"000")),IF(H42="Subetapa",CONCATENATE(TEXT(B42,"00"),".",TEXT(C42,"000"),".",TEXT(D42,"000")),IF(H42="Serviço",CONCATENATE(TEXT(B42,"00"),".",TEXT(C42,"000"),".",TEXT(D42,"000"),".",TEXT(E42,"000")),""))))) -> 01.002.001.002 | J42: Outorga, aprovação e demais taxas | K42: =IFERROR(VLOOKUP(J42,BASES!$A$13:$E$342,3,FALSE),0) -> vb | L42: =IFERROR(VLOOKUP(J42,BASES!$A$13:$E$342,4,FALSE),0) -> 1 | M42: =IFERROR(VLOOKUP(J42,BASES!$A$13:$E$342,5,FALSE),0) -> 1500000 | N42: =IF(H42="Serviço",M42*L42,IF(H42="CÉLULA CONSTRUTIVA",SUMIFS($N$8:$N$419,$B$8:$B$419,B42,$H$8:$H$419,"Serviço"),IF(H42="ETAPA",SUMIFS($N$8:$N$419,$B$8:$B$419,B42,$C$8:$C$419,C42,$H$8:$H$419,"Serviço"),IF(H42="SUBETAPA",SUMIFS($N$8:$N$419,$B$8:$B$419,B42,$C$8:$C$419,C42,$D$8:$D$419,D42,$H$8:$H$419,"Serviço"),0)))) -> 1500000 | O42: =IF(VLOOKUP(J42,BASES!$A$13:$F$342,6,FALSE)="Recebido","Valor informado em formulário",IF(VLOOKUP(J42,BASES!$A$13:$F$342,6,FALSE)="Estimado","Estimado com base em índices históricos","Não solicitado")) -> Valor informado em formulário | P42: Lançado ERP
A43: =IF($H43="UNIDADE CONSTRUTIVA",OFFSET(A43,-1,0)+1,LARGE(A$3:A42,1)) -> 0 | B43: =IF(H43="UNIDADE CONSTRUTIVA",0,IF(H43="CÉLULA CONSTRUTIVA",OFFSET(B43,-1,0)+1,OFFSET(B43,-1,0))) -> 1 | C43: =IF(H43="CÉLULA CONSTRUTIVA",0,IF(H43="ETAPA",OFFSET(C43,-1,0)+1,OFFSET(C43,-1,0))) -> 2 | D43: =IF(H43="ETAPA",0,IF(H43="SUBETAPA",OFFSET(D43,-1,0)+1,OFFSET(D43,-1,0))) -> 1 | E43: =IF(H43="Subetapa",0,IF(H43="serviço",OFFSET(E43,-1,0)+1,OFFSET(E43,-1,0))) -> 3 | H43: SERVIÇO | I43: =IF(H43="Unidade Construtiva",TEXT(A43,"00"),IF(H43="Célula Construtiva",TEXT(B43,"00"),IF(H43="Etapa",CONCATENATE(TEXT(B43,"00"),".",TEXT(C43,"000")),IF(H43="Subetapa",CONCATENATE(TEXT(B43,"00"),".",TEXT(C43,"000"),".",TEXT(D43,"000")),IF(H43="Serviço",CONCATENATE(TEXT(B43,"00"),".",TEXT(C43,"000"),".",TEXT(D43,"000"),".",TEXT(E43,"000")),""))))) -> 01.002.001.003 | J43: Aprovação e legalização água e esgoto | K43: =IFERROR(VLOOKUP(J43,BASES!$A$13:$E$342,3,FALSE),0) -> vb | L43: =IFERROR(VLOOKUP(J43,BASES!$A$13:$E$342,4,FALSE),0) -> 1 | M43: =IFERROR(VLOOKUP(J43,BASES!$A$13:$E$342,5,FALSE),0) -> 4721.7931 | N43: =IF(H43="Serviço",M43*L43,IF(H43="CÉLULA CONSTRUTIVA",SUMIFS($N$8:$N$419,$B$8:$B$419,B43,$H$8:$H$419,"Serviço"),IF(H43="ETAPA",SUMIFS($N$8:$N$419,$B$8:$B$419,B43,$C$8:$C$419,C43,$H$8:$H$419,"Serviço"),IF(H43="SUBETAPA",SUMIFS($N$8:$N$419,$B$8:$B$419,B43,$C$8:$C$419,C43,$D$8:$D$419,D43,$H$8:$H$419,"Serviço"),0)))) -> 4721.7931 | O43: =IF(VLOOKUP(J43,BASES!$A$13:$F$342,6,FALSE)="Recebido","Valor informado em formulário",IF(VLOOKUP(J43,BASES!$A$13:$F$342,6,FALSE)="Estimado","Estimado com base em índices históricos","Não solicitado")) -> Estimado com base em índices históricos | P43: Lançado ERP
A44: =IF($H44="UNIDADE CONSTRUTIVA",OFFSET(A44,-1,0)+1,LARGE(A$3:A43,1)) -> 0 | B44: =IF(H44="UNIDADE CONSTRUTIVA",0,IF(H44="CÉLULA CONSTRUTIVA",OFFSET(B44,-1,0)+1,OFFSET(B44,-1,0))) -> 1 | C44: =IF(H44="CÉLULA CONSTRUTIVA",0,IF(H44="ETAPA",OFFSET(C44,-1,0)+1,OFFSET(C44,-1,0))) -> 2 | D44: =IF(H44="ETAPA",0,IF(H44="SUBETAPA",OFFSET(D44,-1,0)+1,OFFSET(D44,-1,0))) -> 1 | E44: =IF(H44="Subetapa",0,IF(H44="serviço",OFFSET(E44,-1,0)+1,OFFSET(E44,-1,0))) -> 4 | H44: SERVIÇO | I44: =IF(H44="Unidade Construtiva",TEXT(A44,"00"),IF(H44="Célula Construtiva",TEXT(B44,"00"),IF(H44="Etapa",CONCATENATE(TEXT(B44,"00"),".",TEXT(C44,"000")),IF(H44="Subetapa",CONCATENATE(TEXT(B44,"00"),".",TEXT(C44,"000"),".",TEXT(D44,"000")),IF(H44="Serviço",CONCATENATE(TEXT(B44,"00"),".",TEXT(C44,"000"),".",TEXT(D44,"000"),".",TEXT(E44,"000")),""))))) -> 01.002.001.004 | J44: Aprovação e legalização elétrico | K44: =IFERROR(VLOOKUP(J44,BASES!$A$13:$E$342,3,FALSE),0) -> vb | L44: =IFERROR(VLOOKUP(J44,BASES!$A$13:$E$342,4,FALSE),0) -> 1 | M44: =IFERROR(VLOOKUP(J44,BASES!$A$13:$E$342,5,FALSE),0) -> 8065.186 | N44: =IF(H44="Serviço",M44*L44,IF(H44="CÉLULA CONSTRUTIVA",SUMIFS($N$8:$N$419,$B$8:$B$419,B44,$H$8:$H$419,"Serviço"),IF(H44="ETAPA",SUMIFS($N$8:$N$419,$B$8:$B$419,B44,$C$8:$C$419,C44,$H$8:$H$419,"Serviço"),IF(H44="SUBETAPA",SUMIFS($N$8:$N$419,$B$8:$B$419,B44,$C$8:$C$419,C44,$D$8:$D$419,D44,$H$8:$H$419,"Serviço"),0)))) -> 8065.186 | O44: =IF(VLOOKUP(J44,BASES!$A$13:$F$342,6,FALSE)="Recebido","Valor informado em formulário",IF(VLOOKUP(J44,BASES!$A$13:$F$342,6,FALSE)="Estimado","Estimado com base em índices históricos","Não solicitado")) -> Estimado com base em índices históricos | P44: Lançado ERP
A45: =IF($H45="UNIDADE CONSTRUTIVA",OFFSET(A45,-1,0)+1,LARGE(A$3:A44,1)) -> 0 | B45: =IF(H45="UNIDADE CONSTRUTIVA",0,IF(H45="CÉLULA CONSTRUTIVA",OFFSET(B45,-1,0)+1,OFFSET(B45,-1,0))) -> 1 | C45: =IF(H45="CÉLULA CONSTRUTIVA",0,IF(H45="ETAPA",OFFSET(C45,-1,0)+1,OFFSET(C45,-1,0))) -> 2 | D45: =IF(H45="ETAPA",0,IF(H45="SUBETAPA",OFFSET(D45,-1,0)+1,OFFSET(D45,-1,0))) -> 1 | E45: =IF(H45="Subetapa",0,IF(H45="serviço",OFFSET(E45,-1,0)+1,OFFSET(E45,-1,0))) -> 5 | H45: SERVIÇO | I45: =IF(H45="Unidade Construtiva",TEXT(A45,"00"),IF(H45="Célula Construtiva",TEXT(B45,"00"),IF(H45="Etapa",CONCATENATE(TEXT(B45,"00"),".",TEXT(C45,"000")),IF(H45="Subetapa",CONCATENATE(TEXT(B45,"00"),".",TEXT(C45,"000"),".",TEXT(D45,"000")),IF(H45="Serviço",CONCATENATE(TEXT(B45,"00"),".",TEXT(C45,"000"),".",TEXT(D45,"000"),".",TEXT(E45,"000")),""))))) -> 01.002.001.005 | J45: Aprovação e legalização bombeiros | K45: =IFERROR(VLOOKUP(J45,BASES!$A$13:$E$342,3,FALSE),0) -> vb | L45: =IFERROR(VLOOKUP(J45,BASES!$A$13:$E$342,4,FALSE),0) -> 1 | M45: =IFERROR(VLOOKUP(J45,BASES!$A$13:$E$342,5,FALSE),0) -> 6584.9251 | N45: =IF(H45="Serviço",M45*L45,IF(H45="CÉLULA CONSTRUTIVA",SUMIFS($N$8:$N$419,$B$8:$B$419,B45,$H$8:$H$419,"Serviço"),IF(H45="ETAPA",SUMIFS($N$8:$N$419,$B$8:$B$419,B45,$C$8:$C$419,C45,$H$8:$H$419,"Serviço"),IF(H45="SUBETAPA",SUMIFS($N$8:$N$419,$B$8:$B$419,B45,$C$8:$C$419,C45,$D$8:$D$419,D45,$H$8:$H$419,"Serviço"),0)))) -> 6584.9251 | O45: =IF(VLOOKUP(J45,BASES!$A$13:$F$342,6,FALSE)="Recebido","Valor informado em formulário",IF(VLOOKUP(J45,BASES!$A$13:$F$342,6,FALSE)="Estimado","Estimado com base em índices históricos","Não solicitado")) -> Estimado com base em índices históricos | P45: Lançado ERP
A46: =IF($H46="UNIDADE CONSTRUTIVA",OFFSET(A46,-1,0)+1,LARGE(A$3:A45,1)) -> 0 | B46: =IF(H46="UNIDADE CONSTRUTIVA",0,IF(H46="CÉLULA CONSTRUTIVA",OFFSET(B46,-1,0)+1,OFFSET(B46,-1,0))) -> 1 | C46: =IF(H46="CÉLULA CONSTRUTIVA",0,IF(H46="ETAPA",OFFSET(C46,-1,0)+1,OFFSET(C46,-1,0))) -> 2 | D46: =IF(H46="ETAPA",0,IF(H46="SUBETAPA",OFFSET(D46,-1,0)+1,OFFSET(D46,-1,0))) -> 1 | E46: =IF(H46="Subetapa",0,IF(H46="serviço",OFFSET(E46,-1,0)+1,OFFSET(E46,-1,0))) -> 6 | H46: SERVIÇO | I46: =IF(H46="Unidade Construtiva",TEXT(A46,"00"),IF(H46="Célula Construtiva",TEXT(B46,"00"),IF(H46="Etapa",CONCATENATE(TEXT(B46,"00"),".",TEXT(C46,"000")),IF(H46="Subetapa",CONCATENATE(TEXT(B46,"00"),".",TEXT(C46,"000"),".",TEXT(D46,"000")),IF(H46="Serviço",CONCATENATE(TEXT(B46,"00"),".",TEXT(C46,"000"),".",TEXT(D46,"000"),".",TEXT(E46,"000")),""))))) -> 01.002.001.006 | J46: Taxas de ART | K46: =IFERROR(VLOOKUP(J46,BASES!$A$13:$E$342,3,FALSE),0) -> vb | L46: =IFERROR(VLOOKUP(J46,BASES!$A$13:$E$342,4,FALSE),0) -> 1 | M46: =IFERROR(VLOOKUP(J46,BASES!$A$13:$E$342,5,FALSE),0) -> 2386.576 | N46: =IF(H46="Serviço",M46*L46,IF(H46="CÉLULA CONSTRUTIVA",SUMIFS($N$8:$N$419,$B$8:$B$419,B46,$H$8:$H$419,"Serviço"),IF(H46="ETAPA",SUMIFS($N$8:$N$419,$B$8:$B$419,B46,$C$8:$C$419,C46,$H$8:$H$419,"Serviço"),IF(H46="SUBETAPA",SUMIFS($N$8:$N$419,$B$8:$B$419,B46,$C$8:$C$419,C46,$D$8:$D$419,D46,$H$8:$H$419,"Serviço"),0)))) -> 2386.576 | O46: =IF(VLOOKUP(J46,BASES!$A$13:$F$342,6,FALSE)="Recebido","Valor informado em formulário",IF(VLOOKUP(J46,BASES!$A$13:$F$342,6,FALSE)="Estimado","Estimado com base em índices históricos","Não solicitado")) -> Estimado com base em índices históricos | P46: Lançado ERP
A47: =IF($H47="UNIDADE CONSTRUTIVA",OFFSET(A47,-1,0)+1,LARGE(A$3:A46,1)) -> 0 | B47: =IF(H47="UNIDADE CONSTRUTIVA",0,IF(H47="CÉLULA CONSTRUTIVA",OFFSET(B47,-1,0)+1,OFFSET(B47,-1,0))) -> 1 | C47: =IF(H47="CÉLULA CONSTRUTIVA",0,IF(H47="ETAPA",OFFSET(C47,-1,0)+1,OFFSET(C47,-1,0))) -> 2 | D47: =IF(H47="ETAPA",0,IF(H47="SUBETAPA",OFFSET(D47,-1,0)+1,OFFSET(D47,-1,0))) -> 1 | E47: =IF(H47="Subetapa",0,IF(H47="serviço",OFFSET(E47,-1,0)+1,OFFSET(E47,-1,0))) -> 7 | H47: SERVIÇO | I47: =IF(H47="Unidade Construtiva",TEXT(A47,"00"),IF(H47="Célula Construtiva",TEXT(B47,"00"),IF(H47="Etapa",CONCATENATE(TEXT(B47,"00"),".",TEXT(C47,"000")),IF(H47="Subetapa",CONCATENATE(TEXT(B47,"00"),".",TEXT(C47,"000"),".",TEXT(D47,"000")),IF(H47="Serviço",CONCATENATE(TEXT(B47,"00"),".",TEXT(C47,"000"),".",TEXT(D47,"000"),".",TEXT(E47,"000")),""))))) -> 01.002.001.007 | J47: Alvará Construção | K47: =IFERROR(VLOOKUP(J47,BASES!$A$13:$E$342,3,FALSE),0) -> vb | L47: =IFERROR(VLOOKUP(J47,BASES!$A$13:$E$342,4,FALSE),0) -> 1 | M47: =IFERROR(VLOOKUP(J47,BASES!$A$13:$E$342,5,FALSE),0) -> 38462.858 | N47: =IF(H47="Serviço",M47*L47,IF(H47="CÉLULA CONSTRUTIVA",SUMIFS($N$8:$N$419,$B$8:$B$419,B47,$H$8:$H$419,"Serviço"),IF(H47="ETAPA",SUMIFS($N$8:$N$419,$B$8:$B$419,B47,$C$8:$C$419,C47,$H$8:$H$419,"Serviço"),IF(H47="SUBETAPA",SUMIFS($N$8:$N$419,$B$8:$B$419,B47,$C$8:$C$419,C47,$D$8:$D$419,D47,$H$8:$H$419,"Serviço"),0)))) -> 38462.858 | O47: =IF(VLOOKUP(J47,BASES!$A$13:$F$342,6,FALSE)="Recebido","Valor informado em formulário",IF(VLOOKUP(J47,BASES!$A$13:$F$342,6,FALSE)="Estimado","Estimado com base em índices históricos","Não solicitado")) -> Estimado com base em índices históricos | P47: Lançado ERP
A48: =IF($H48="UNIDADE CONSTRUTIVA",OFFSET(A48,-1,0)+1,LARGE(A$3:A47,1)) -> 0 | B48: =IF(H48="UNIDADE CONSTRUTIVA",0,IF(H48="CÉLULA CONSTRUTIVA",OFFSET(B48,-1,0)+1,OFFSET(B48,-1,0))) -> 1 | C48: =IF(H48="CÉLULA CONSTRUTIVA",0,IF(H48="ETAPA",OFFSET(C48,-1,0)+1,OFFSET(C48,-1,0))) -> 2 | D48: =IF(H48="ETAPA",0,IF(H48="SUBETAPA",OFFSET(D48,-1,0)+1,OFFSET(D48,-1,0))) -> 1 | E48: =IF(H48="Subetapa",0,IF(H48="serviço",OFFSET(E48,-1,0)+1,OFFSET(E48,-1,0))) -> 8 | H48: SERVIÇO | I48: =IF(H48="Unidade Construtiva",TEXT(A48,"00"),IF(H48="Célula Construtiva",TEXT(B48,"00"),IF(H48="Etapa",CONCATENATE(TEXT(B48,"00"),".",TEXT(C48,"000")),IF(H48="Subetapa",CONCATENATE(TEXT(B48,"00"),".",TEXT(C48,"000"),".",TEXT(D48,"000")),IF(H48="Serviço",CONCATENATE(TEXT(B48,"00"),".",TEXT(C48,"000"),".",TEXT(D48,"000"),".",TEXT(E48,"000")),""))))) -> 01.002.001.008 | J48: Iptu | K48: =IFERROR(VLOOKUP(J48,BASES!$A$13:$E$342,3,FALSE),0) -> vb | L48: =IFERROR(VLOOKUP(J48,BASES!$A$13:$E$342,4,FALSE),0) -> 1 | M48: =IFERROR(VLOOKUP(J48,BASES!$A$13:$E$342,5,FALSE),0) -> 17394.132 | N48: =IF(H48="Serviço",M48*L48,IF(H48="CÉLULA CONSTRUTIVA",SUMIFS($N$8:$N$419,$B$8:$B$419,B48,$H$8:$H$419,"Serviço"),IF(H48="ETAPA",SUMIFS($N$8:$N$419,$B$8:$B$419,B48,$C$8:$C$419,C48,$H$8:$H$419,"Serviço"),IF(H48="SUBETAPA",SUMIFS($N$8:$N$419,$B$8:$B$419,B48,$C$8:$C$419,C48,$D$8:$D$419,D48,$H$8:$H$419,"Serviço"),0)))) -> 17394.132 | O48: =IF(VLOOKUP(J48,BASES!$A$13:$F$342,6,FALSE)="Recebido","Valor informado em formulário",IF(VLOOKUP(J48,BASES!$A$13:$F$342,6,FALSE)="Estimado","Estimado com base em índices históricos","Não solicitado")) -> Estimado com base em índices históricos | P48: Lançado ERP
A49: =IF($H49="UNIDADE CONSTRUTIVA",OFFSET(A49,-1,0)+1,LARGE(A$3:A48,1)) -> 0 | B49: =IF(H49="UNIDADE CONSTRUTIVA",0,IF(H49="CÉLULA CONSTRUTIVA",OFFSET(B49,-1,0)+1,OFFSET(B49,-1,0))) -> 1 | C49: =IF(H49="CÉLULA CONSTRUTIVA",0,IF(H49="ETAPA",OFFSET(C49,-1,0)+1,OFFSET(C49,-1,0))) -> 2 | D49: =IF(H49="ETAPA",0,IF(H49="SUBETAPA",OFFSET(D49,-1,0)+1,OFFSET(D49,-1,0))) -> 1 | E49: =IF(H49="Subetapa",0,IF(H49="serviço",OFFSET(E49,-1,0)+1,OFFSET(E49,-1,0))) -> 9 | H49: SERVIÇO | I49: =IF(H49="Unidade Construtiva",TEXT(A49,"00"),IF(H49="Célula Construtiva",TEXT(B49,"00"),IF(H49="Etapa",CONCATENATE(TEXT(B49,"00"),".",TEXT(C49,"000")),IF(H49="Subetapa",CONCATENATE(TEXT(B49,"00"),".",TEXT(C49,"000"),".",TEXT(D49,"000")),IF(H49="Serviço",CONCATENATE(TEXT(B49,"00"),".",TEXT(C49,"000"),".",TEXT(D49,"000"),".",TEXT(E49,"000")),""))))) -> 01.002.001.009 | J49: Alvará Habite-se | K49: =IFERROR(VLOOKUP(J49,BASES!$A$13:$E$342,3,FALSE),0) -> vb | L49: =IFERROR(VLOOKUP(J49,BASES!$A$13:$E$342,4,FALSE),0) -> 1 | M49: =IFERROR(VLOOKUP(J49,BASES!$A$13:$E$342,5,FALSE),0) -> 8943.8536 | N49: =IF(H49="Serviço",M49*L49,IF(H49="CÉLULA CONSTRUTIVA",SUMIFS($N$8:$N$419,$B$8:$B$419,B49,$H$8:$H$419,"Serviço"),IF(H49="ETAPA",SUMIFS($N$8:$N$419,$B$8:$B$419,B49,$C$8:$C$419,C49,$H$8:$H$419,"Serviço"),IF(H49="SUBETAPA",SUMIFS($N$8:$N$419,$B$8:$B$419,B49,$C$8:$C$419,C49,$D$8:$D$419,D49,$H$8:$H$419,"Serviço"),0)))) -> 8943.8536 | O49: =IF(VLOOKUP(J49,BASES!$A$13:$F$342,6,FALSE)="Recebido","Valor informado em formulário",IF(VLOOKUP(J49,BASES!$A$13:$F$342,6,FALSE)="Estimado","Estimado com base em índices históricos","Não solicitado")) -> Estimado com base em índices históricos | P49: Lançado ERP
A50: =IF($H50="UNIDADE CONSTRUTIVA",OFFSET(A50,-1,0)+1,LARGE(A$3:A49,1)) -> 0 | B50: =IF(H50="UNIDADE CONSTRUTIVA",0,IF(H50="CÉLULA CONSTRUTIVA",OFFSET(B50,-1,0)+1,OFFSET(B50,-1,0))) -> 1 | C50: =IF(H50="CÉLULA CONSTRUTIVA",0,IF(H50="ETAPA",OFFSET(C50,-1,0)+1,OFFSET(C50,-1,0))) -> 2 | D50: =IF(H50="ETAPA",0,IF(H50="SUBETAPA",OFFSET(D50,-1,0)+1,OFFSET(D50,-1,0))) -> 2 | E50: =IF(H50="Subetapa",0,IF(H50="serviço",OFFSET(E50,-1,0)+1,OFFSET(E50,-1,0))) -> 0 | H50: SUBETAPA | I50: =IF(H50="Unidade Construtiva",TEXT(A50,"00"),IF(H50="Célula Construtiva",TEXT(B50,"00"),IF(H50="Etapa",CONCATENATE(TEXT(B50,"00"),".",TEXT(C50,"000")),IF(H50="Subetapa",CONCATENATE(TEXT(B50,"00"),".",TEXT(C50,"000"),".",TEXT(D50,"000")),IF(H50="Serviço",CONCATENATE(TEXT(B50,"00"),".",TEXT(C50,"000"),".",TEXT(D50,"000"),".",TEXT(E50,"000")),""))))) -> 01.002.002 | J50: Documentos | N50: =IF(H50="Serviço",M50*L50,IF(H50="CÉLULA CONSTRUTIVA",SUMIFS($N$8:$N$419,$B$8:$B$419,B50,$H$8:$H$419,"Serviço"),IF(H50="ETAPA",SUMIFS($N$8:$N$419,$B$8:$B$419,B50,$C$8:$C$419,C50,$H$8:$H$419,"Serviço"),IF(H50="SUBETAPA",SUMIFS($N$8:$N$419,$B$8:$B$419,B50,$C$8:$C$419,C50,$D$8:$D$419,D50,$H$8:$H$419,"Serviço"),0)))) -> 23265.361 | Q50: =N50/'Obra '!$C$32 -> 0.0048734592
A51: =IF($H51="UNIDADE CONSTRUTIVA",OFFSET(A51,-1,0)+1,LARGE(A$3:A50,1)) -> 0 | B51: =IF(H51="UNIDADE CONSTRUTIVA",0,IF(H51="CÉLULA CONSTRUTIVA",OFFSET(B51,-1,0)+1,OFFSET(B51,-1,0))) -> 1 | C51: =IF(H51="CÉLULA CONSTRUTIVA",0,IF(H51="ETAPA",OFFSET(C51,-1,0)+1,OFFSET(C51,-1,0))) -> 2 | D51: =IF(H51="ETAPA",0,IF(H51="SUBETAPA",OFFSET(D51,-1,0)+1,OFFSET(D51,-1,0))) -> 2 | E51: =IF(H51="Subetapa",0,IF(H51="serviço",OFFSET(E51,-1,0)+1,OFFSET(E51,-1,0))) -> 1 | H51: SERVIÇO | I51: =IF(H51="Unidade Construtiva",TEXT(A51,"00"),IF(H51="Célula Construtiva",TEXT(B51,"00"),IF(H51="Etapa",CONCATENATE(TEXT(B51,"00"),".",TEXT(C51,"000")),IF(H51="Subetapa",CONCATENATE(TEXT(B51,"00"),".",TEXT(C51,"000"),".",TEXT(D51,"000")),IF(H51="Serviço",CONCATENATE(TEXT(B51,"00"),".",TEXT(C51,"000"),".",TEXT(D51,"000"),".",TEXT(E51,"000")),""))))) -> 01.002.002.001 | J51: As Built | K51: =IFERROR(VLOOKUP(J51,BASES!$A$13:$E$342,3,FALSE),0) -> vb | L51: =IFERROR(VLOOKUP(J51,BASES!$A$13:$E$342,4,FALSE),0) -> 1 | M51: =IFERROR(VLOOKUP(J51,BASES!$A$13:$E$342,5,FALSE),0) -> 8874.0052 | N51: =IF(H51="Serviço",M51*L51,IF(H51="CÉLULA CONSTRUTIVA",SUMIFS($N$8:$N$419,$B$8:$B$419,B51,$H$8:$H$419,"Serviço"),IF(H51="ETAPA",SUMIFS($N$8:$N$419,$B$8:$B$419,B51,$C$8:$C$419,C51,$H$8:$H$419,"Serviço"),IF(H51="SUBETAPA",SUMIFS($N$8:$N$419,$B$8:$B$419,B51,$C$8:$C$419,C51,$D$8:$D$419,D51,$H$8:$H$419,"Serviço"),0)))) -> 8874.0052 | O51: =IF(VLOOKUP(J51,BASES!$A$13:$F$342,6,FALSE)="Recebido","Valor informado em formulário",IF(VLOOKUP(J51,BASES!$A$13:$F$342,6,FALSE)="Estimado","Estimado com base em índices históricos","Não solicitado")) -> Estimado com base em índices históricos | P51: Lançado ERP
A52: =IF($H52="UNIDADE CONSTRUTIVA",OFFSET(A52,-1,0)+1,LARGE(A$3:A51,1)) -> 0 | B52: =IF(H52="UNIDADE CONSTRUTIVA",0,IF(H52="CÉLULA CONSTRUTIVA",OFFSET(B52,-1,0)+1,OFFSET(B52,-1,0))) -> 1 | C52: =IF(H52="CÉLULA CONSTRUTIVA",0,IF(H52="ETAPA",OFFSET(C52,-1,0)+1,OFFSET(C52,-1,0))) -> 2 | D52: =IF(H52="ETAPA",0,IF(H52="SUBETAPA",OFFSET(D52,-1,0)+1,OFFSET(D52,-1,0))) -> 2 | E52: =IF(H52="Subetapa",0,IF(H52="serviço",OFFSET(E52,-1,0)+1,OFFSET(E52,-1,0))) -> 2 | H52: SERVIÇO | I52: =IF(H52="Unidade Construtiva",TEXT(A52,"00"),IF(H52="Célula Construtiva",TEXT(B52,"00"),IF(H52="Etapa",CONCATENATE(TEXT(B52,"00"),".",TEXT(C52,"000")),IF(H52="Subetapa",CONCATENATE(TEXT(B52,"00"),".",TEXT(C52,"000"),".",TEXT(D52,"000")),IF(H52="Serviço",CONCATENATE(TEXT(B52,"00"),".",TEXT(C52,"000"),".",TEXT(D52,"000"),".",TEXT(E52,"000")),""))))) -> 01.002.002.002 | J52: Laudo de Vizinhança | K52: =IFERROR(VLOOKUP(J52,BASES!$A$13:$E$342,3,FALSE),0) -> vb | L52: =IFERROR(VLOOKUP(J52,BASES!$A$13:$E$342,4,FALSE),0) -> 1 | M52: =IFERROR(VLOOKUP(J52,BASES!$A$13:$E$342,5,FALSE),0) -> 3900 | N52: =IF(H52="Serviço",M52*L52,IF(H52="CÉLULA CONSTRUTIVA",SUMIFS($N$8:$N$419,$B$8:$B$419,B52,$H$8:$H$419,"Serviço"),IF(H52="ETAPA",SUMIFS($N$8:$N$419,$B$8:$B$419,B52,$C$8:$C$419,C52,$H$8:$H$419,"Serviço"),IF(H52="SUBETAPA",SUMIFS($N$8:$N$419,$B$8:$B$419,B52,$C$8:$C$419,C52,$D$8:$D$419,D52,$H$8:$H$419,"Serviço"),0)))) -> 3900 | O52: =IF(VLOOKUP(J52,BASES!$A$13:$F$342,6,FALSE)="Recebido","Valor informado em formulário",IF(VLOOKUP(J52,BASES!$A$13:$F$342,6,FALSE)="Estimado","Estimado com base em índices históricos","Não solicitado")) -> Valor informado em formulário | P52: Lançado ERP
A53: =IF($H53="UNIDADE CONSTRUTIVA",OFFSET(A53,-1,0)+1,LARGE(A$3:A52,1)) -> 0 | B53: =IF(H53="UNIDADE CONSTRUTIVA",0,IF(H53="CÉLULA CONSTRUTIVA",OFFSET(B53,-1,0)+1,OFFSET(B53,-1,0))) -> 1 | C53: =IF(H53="CÉLULA CONSTRUTIVA",0,IF(H53="ETAPA",OFFSET(C53,-1,0)+1,OFFSET(C53,-1,0))) -> 2 | D53: =IF(H53="ETAPA",0,IF(H53="SUBETAPA",OFFSET(D53,-1,0)+1,OFFSET(D53,-1,0))) -> 2 | E53: =IF(H53="Subetapa",0,IF(H53="serviço",OFFSET(E53,-1,0)+1,OFFSET(E53,-1,0))) -> 3 | H53: SERVIÇO | I53: =IF(H53="Unidade Construtiva",TEXT(A53,"00"),IF(H53="Célula Construtiva",TEXT(B53,"00"),IF(H53="Etapa",CONCATENATE(TEXT(B53,"00"),".",TEXT(C53,"000")),IF(H53="Subetapa",CONCATENATE(TEXT(B53,"00"),".",TEXT(C53,"000"),".",TEXT(D53,"000")),IF(H53="Serviço",CONCATENATE(TEXT(B53,"00"),".",TEXT(C53,"000"),".",TEXT(D53,"000"),".",TEXT(E53,"000")),""))))) -> 01.002.002.003 | J53: Manuais técnicos condomínio/proprietários | K53: =IFERROR(VLOOKUP(J53,BASES!$A$13:$E$342,3,FALSE),0) -> vb | L53: =IFERROR(VLOOKUP(J53,BASES!$A$13:$E$342,4,FALSE),0) -> 1 | M53: =IFERROR(VLOOKUP(J53,BASES!$A$13:$E$342,5,FALSE),0) -> 10491.356 | N53: =IF(H53="Serviço",M53*L53,IF(H53="CÉLULA CONSTRUTIVA",SUMIFS($N$8:$N$419,$B$8:$B$419,B53,$H$8:$H$419,"Serviço"),IF(H53="ETAPA",SUMIFS($N$8:$N$419,$B$8:$B$419,B53,$C$8:$C$419,C53,$H$8:$H$419,"Serviço"),IF(H53="SUBETAPA",SUMIFS($N$8:$N$419,$B$8:$B$419,B53,$C$8:$C$419,C53,$D$8:$D$419,D53,$H$8:$H$419,"Serviço"),0)))) -> 10491.356 | O53: =IF(VLOOKUP(J53,BASES!$A$13:$F$342,6,FALSE)="Recebido","Valor informado em formulário",IF(VLOOKUP(J53,BASES!$A$13:$F$342,6,FALSE)="Estimado","Estimado com base em índices históricos","Não solicitado")) -> Estimado com base em índices históricos | P53: Lançado ERP
A54: =IF($H54="UNIDADE CONSTRUTIVA",OFFSET(A54,-1,0)+1,LARGE(A$3:A53,1)) -> 0 | B54: =IF(H54="UNIDADE CONSTRUTIVA",0,IF(H54="CÉLULA CONSTRUTIVA",OFFSET(B54,-1,0)+1,OFFSET(B54,-1,0))) -> 2 | C54: =IF(H54="CÉLULA CONSTRUTIVA",0,IF(H54="ETAPA",OFFSET(C54,-1,0)+1,OFFSET(C54,-1,0))) -> 0 | D54: =IF(H54="ETAPA",0,IF(H54="SUBETAPA",OFFSET(D54,-1,0)+1,OFFSET(D54,-1,0))) -> 2 | E54: =IF(H54="Subetapa",0,IF(H54="serviço",OFFSET(E54,-1,0)+1,OFFSET(E54,-1,0))) -> 3 | H54: CÉLULA CONSTRUTIVA | I54: =IF(H54="Unidade Construtiva",TEXT(A54,"00"),IF(H54="Célula Construtiva",TEXT(B54,"00"),IF(H54="Etapa",CONCATENATE(TEXT(B54,"00"),".",TEXT(C54,"000")),IF(H54="Subetapa",CONCATENATE(TEXT(B54,"00"),".",TEXT(C54,"000"),".",TEXT(D54,"000")),IF(H54="Serviço",CONCATENATE(TEXT(B54,"00"),".",TEXT(C54,"000"),".",TEXT(D54,"000"),".",TEXT(E54,"000")),""))))) -> 02 | J54: SERVIÇOS INICIAIS | N54: =IF(H54="Serviço",M54*L54,IF(H54="CÉLULA CONSTRUTIVA",SUMIFS($N$8:$N$419,$B$8:$B$419,B54,$H$8:$H$419,"Serviço"),IF(H54="ETAPA",SUMIFS($N$8:$N$419,$B$8:$B$419,B54,$C$8:$C$419,C54,$H$8:$H$419,"Serviço"),IF(H54="SUBETAPA",SUMIFS($N$8:$N$419,$B$8:$B$419,B54,$C$8:$C$419,C54,$D$8:$D$419,D54,$H$8:$H$419,"Serviço"),0)))) -> 1882298.6 | Q54: =N54/'Obra '!$C$32 -> 0.39429026
A55: =IF($H55="UNIDADE CONSTRUTIVA",OFFSET(A55,-1,0)+1,LARGE(A$3:A54,1)) -> 0 | B55: =IF(H55="UNIDADE CONSTRUTIVA",0,IF(H55="CÉLULA CONSTRUTIVA",OFFSET(B55,-1,0)+1,OFFSET(B55,-1,0))) -> 2 | C55: =IF(H55="CÉLULA CONSTRUTIVA",0,IF(H55="ETAPA",OFFSET(C55,-1,0)+1,OFFSET(C55,-1,0))) -> 1 | D55: =IF(H55="ETAPA",0,IF(H55="SUBETAPA",OFFSET(D55,-1,0)+1,OFFSET(D55,-1,0))) -> 0 | E55: =IF(H55="Subetapa",0,IF(H55="serviço",OFFSET(E55,-1,0)+1,OFFSET(E55,-1,0))) -> 3 | H55: ETAPA | I55: =IF(H55="Unidade Construtiva",TEXT(A55,"00"),IF(H55="Célula Construtiva",TEXT(B55,"00"),IF(H55="Etapa",CONCATENATE(TEXT(B55,"00"),".",TEXT(C55,"000")),IF(H55="Subetapa",CONCATENATE(TEXT(B55,"00"),".",TEXT(C55,"000"),".",TEXT(D55,"000")),IF(H55="Serviço",CONCATENATE(TEXT(B55,"00"),".",TEXT(C55,"000"),".",TEXT(D55,"000"),".",TEXT(E55,"000")),""))))) -> 02.001 | J55: SEGURANÇA, MEIO AMBIENTE E SAÚDE | N55: =IF(H55="Serviço",M55*L55,IF(H55="CÉLULA CONSTRUTIVA",SUMIFS($N$8:$N$419,$B$8:$B$419,B55,$H$8:$H$419,"Serviço"),IF(H55="ETAPA",SUMIFS($N$8:$N$419,$B$8:$B$419,B55,$C$8:$C$419,C55,$H$8:$H$419,"Serviço"),IF(H55="SUBETAPA",SUMIFS($N$8:$N$419,$B$8:$B$419,B55,$C$8:$C$419,C55,$D$8:$D$419,D55,$H$8:$H$419,"Serviço"),0)))) -> 650897.99 | Q55: =N55/'Obra '!$C$32 -> 0.13634539
A56: =IF($H56="UNIDADE CONSTRUTIVA",OFFSET(A56,-1,0)+1,LARGE(A$3:A55,1)) -> 0 | B56: =IF(H56="UNIDADE CONSTRUTIVA",0,IF(H56="CÉLULA CONSTRUTIVA",OFFSET(B56,-1,0)+1,OFFSET(B56,-1,0))) -> 2 | C56: =IF(H56="CÉLULA CONSTRUTIVA",0,IF(H56="ETAPA",OFFSET(C56,-1,0)+1,OFFSET(C56,-1,0))) -> 1 | D56: =IF(H56="ETAPA",0,IF(H56="SUBETAPA",OFFSET(D56,-1,0)+1,OFFSET(D56,-1,0))) -> 1 | E56: =IF(H56="Subetapa",0,IF(H56="serviço",OFFSET(E56,-1,0)+1,OFFSET(E56,-1,0))) -> 0 | H56: SUBETAPA | I56: =IF(H56="Unidade Construtiva",TEXT(A56,"00"),IF(H56="Célula Construtiva",TEXT(B56,"00"),IF(H56="Etapa",CONCATENATE(TEXT(B56,"00"),".",TEXT(C56,"000")),IF(H56="Subetapa",CONCATENATE(TEXT(B56,"00"),".",TEXT(C56,"000"),".",TEXT(D56,"000")),IF(H56="Serviço",CONCATENATE(TEXT(B56,"00"),".",TEXT(C56,"000"),".",TEXT(D56,"000"),".",TEXT(E56,"000")),""))))) -> 02.001.001 | J56: Segurança do Trabalho | N56: =IF(H56="Serviço",M56*L56,IF(H56="CÉLULA CONSTRUTIVA",SUMIFS($N$8:$N$419,$B$8:$B$419,B56,$H$8:$H$419,"Serviço"),IF(H56="ETAPA",SUMIFS($N$8:$N$419,$B$8:$B$419,B56,$C$8:$C$419,C56,$H$8:$H$419,"Serviço"),IF(H56="SUBETAPA",SUMIFS($N$8:$N$419,$B$8:$B$419,B56,$C$8:$C$419,C56,$D$8:$D$419,D56,$H$8:$H$419,"Serviço"),0)))) -> 310000 | Q56: =N56/'Obra '!$C$32 -> 0.064936553
A57: =IF($H57="UNIDADE CONSTRUTIVA",OFFSET(A57,-1,0)+1,LARGE(A$3:A56,1)) -> 0 | B57: =IF(H57="UNIDADE CONSTRUTIVA",0,IF(H57="CÉLULA CONSTRUTIVA",OFFSET(B57,-1,0)+1,OFFSET(B57,-1,0))) -> 2 | C57: =IF(H57="CÉLULA CONSTRUTIVA",0,IF(H57="ETAPA",OFFSET(C57,-1,0)+1,OFFSET(C57,-1,0))) -> 1 | D57: =IF(H57="ETAPA",0,IF(H57="SUBETAPA",OFFSET(D57,-1,0)+1,OFFSET(D57,-1,0))) -> 1 | E57: =IF(H57="Subetapa",0,IF(H57="serviço",OFFSET(E57,-1,0)+1,OFFSET(E57,-1,0))) -> 1 | H57: SERVIÇO | I57: =IF(H57="Unidade Construtiva",TEXT(A57,"00"),IF(H57="Célula Construtiva",TEXT(B57,"00"),IF(H57="Etapa",CONCATENATE(TEXT(B57,"00"),".",TEXT(C57,"000")),IF(H57="Subetapa",CONCATENATE(TEXT(B57,"00"),".",TEXT(C57,"000"),".",TEXT(D57,"000")),IF(H57="Serviço",CONCATENATE(TEXT(B57,"00"),".",TEXT(C57,"000"),".",TEXT(D57,"000"),".",TEXT(E57,"000")),""))))) -> 02.001.001.001 | J57: Técnico de segurança do trabalho | K57: =IFERROR(VLOOKUP(J57,BASES!$A$13:$E$342,3,FALSE),0) -> mês | L57: =IFERROR(VLOOKUP(J57,BASES!$A$13:$E$342,4,FALSE),0) -> 42 | M57: =IFERROR(VLOOKUP(J57,BASES!$A$13:$E$342,5,FALSE),0) -> 5000 | N57: =IF(H57="Serviço",M57*L57,IF(H57="CÉLULA CONSTRUTIVA",SUMIFS($N$8:$N$419,$B$8:$B$419,B57,$H$8:$H$419,"Serviço"),IF(H57="ETAPA",SUMIFS($N$8:$N$419,$B$8:$B$419,B57,$C$8:$C$419,C57,$H$8:$H$419,"Serviço"),IF(H57="SUBETAPA",SUMIFS($N$8:$N$419,$B$8:$B$419,B57,$C$8:$C$419,C57,$D$8:$D$419,D57,$H$8:$H$419,"Serviço"),0)))) -> 210000 | O57: =IF(VLOOKUP(J57,BASES!$A$13:$F$342,6,FALSE)="Recebido","Valor informado em formulário",IF(VLOOKUP(J57,BASES!$A$13:$F$342,6,FALSE)="Estimado","Estimado com base em índices históricos","Não solicitado")) -> Valor informado em formulário | P57: Lançado ERP
A58: =IF($H58="UNIDADE CONSTRUTIVA",OFFSET(A58,-1,0)+1,LARGE(A$3:A57,1)) -> 0 | B58: =IF(H58="UNIDADE CONSTRUTIVA",0,IF(H58="CÉLULA CONSTRUTIVA",OFFSET(B58,-1,0)+1,OFFSET(B58,-1,0))) -> 2 | C58: =IF(H58="CÉLULA CONSTRUTIVA",0,IF(H58="ETAPA",OFFSET(C58,-1,0)+1,OFFSET(C58,-1,0))) -> 1 | D58: =IF(H58="ETAPA",0,IF(H58="SUBETAPA",OFFSET(D58,-1,0)+1,OFFSET(D58,-1,0))) -> 1 | E58: =IF(H58="Subetapa",0,IF(H58="serviço",OFFSET(E58,-1,0)+1,OFFSET(E58,-1,0))) -> 2 | H58: SERVIÇO | I58: =IF(H58="Unidade Construtiva",TEXT(A58,"00"),IF(H58="Célula Construtiva",TEXT(B58,"00"),IF(H58="Etapa",CONCATENATE(TEXT(B58,"00"),".",TEXT(C58,"000")),IF(H58="Subetapa",CONCATENATE(TEXT(B58,"00"),".",TEXT(C58,"000"),".",TEXT(D58,"000")),IF(H58="Serviço",CONCATENATE(TEXT(B58,"00"),".",TEXT(C58,"000"),".",TEXT(D58,"000"),".",TEXT(E58,"000")),""))))) -> 02.001.001.002 | J58: Equipamentos de proteção individual - EPI | K58: =IFERROR(VLOOKUP(J58,BASES!$A$13:$E$342,3,FALSE),0) -> vb | L58: =IFERROR(VLOOKUP(J58,BASES!$A$13:$E$342,4,FALSE),0) -> 1 | M58: =CANTEIRO!D15 -> 100000 | N58: =IF(H58="Serviço",M58*L58,IF(H58="CÉLULA CONSTRUTIVA",SUMIFS($N$8:$N$419,$B$8:$B$419,B58,$H$8:$H$419,"Serviço"),IF(H58="ETAPA",SUMIFS($N$8:$N$419,$B$8:$B$419,B58,$C$8:$C$419,C58,$H$8:$H$419,"Serviço"),IF(H58="SUBETAPA",SUMIFS($N$8:$N$419,$B$8:$B$419,B58,$C$8:$C$419,C58,$D$8:$D$419,D58,$H$8:$H$419,"Serviço"),0)))) -> 100000 | O58: Calculado conforme aba "Canteiro" | P58: Lançado ERP
A59: =IF($H59="UNIDADE CONSTRUTIVA",OFFSET(A59,-1,0)+1,LARGE(A$3:A58,1)) -> 0 | B59: =IF(H59="UNIDADE CONSTRUTIVA",0,IF(H59="CÉLULA CONSTRUTIVA",OFFSET(B59,-1,0)+1,OFFSET(B59,-1,0))) -> 2 | C59: =IF(H59="CÉLULA CONSTRUTIVA",0,IF(H59="ETAPA",OFFSET(C59,-1,0)+1,OFFSET(C59,-1,0))) -> 1 | D59: =IF(H59="ETAPA",0,IF(H59="SUBETAPA",OFFSET(D59,-1,0)+1,OFFSET(D59,-1,0))) -> 2 | E59: =IF(H59="Subetapa",0,IF(H59="serviço",OFFSET(E59,-1,0)+1,OFFSET(E59,-1,0))) -> 0 | H59: SUBETAPA | I59: =IF(H59="Unidade Construtiva",TEXT(A59,"00"),IF(H59="Célula Construtiva",TEXT(B59,"00"),IF(H59="Etapa",CONCATENATE(TEXT(B59,"00"),".",TEXT(C59,"000")),IF(H59="Subetapa",CONCATENATE(TEXT(B59,"00"),".",TEXT(C59,"000"),".",TEXT(D59,"000")),IF(H59="Serviço",CONCATENATE(TEXT(B59,"00"),".",TEXT(C59,"000"),".",TEXT(D59,"000"),".",TEXT(E59,"000")),""))))) -> 02.001.002 | J59: Equipamentos de proteção de canteiro | N59: =IF(H59="Serviço",M59*L59,IF(H59="CÉLULA CONSTRUTIVA",SUMIFS($N$8:$N$419,$B$8:$B$419,B59,$H$8:$H$419,"Serviço"),IF(H59="ETAPA",SUMIFS($N$8:$N$419,$B$8:$B$419,B59,$C$8:$C$419,C59,$H$8:$H$419,"Serviço"),IF(H59="SUBETAPA",SUMIFS($N$8:$N$419,$B$8:$B$419,B59,$C$8:$C$419,C59,$D$8:$D$419,D59,$H$8:$H$419,"Serviço"),0)))) -> 263507.36 | Q59: =N59/'Obra '!$C$32 -> 0.055197612
A60: =IF($H60="UNIDADE CONSTRUTIVA",OFFSET(A60,-1,0)+1,LARGE(A$3:A59,1)) -> 0 | B60: =IF(H60="UNIDADE CONSTRUTIVA",0,IF(H60="CÉLULA CONSTRUTIVA",OFFSET(B60,-1,0)+1,OFFSET(B60,-1,0))) -> 2 | C60: =IF(H60="CÉLULA CONSTRUTIVA",0,IF(H60="ETAPA",OFFSET(C60,-1,0)+1,OFFSET(C60,-1,0))) -> 1 | D60: =IF(H60="ETAPA",0,IF(H60="SUBETAPA",OFFSET(D60,-1,0)+1,OFFSET(D60,-1,0))) -> 2 | E60: =IF(H60="Subetapa",0,IF(H60="serviço",OFFSET(E60,-1,0)+1,OFFSET(E60,-1,0))) -> 1 | H60: SERVIÇO | I60: =IF(H60="Unidade Construtiva",TEXT(A60,"00"),IF(H60="Célula Construtiva",TEXT(B60,"00"),IF(H60="Etapa",CONCATENATE(TEXT(B60,"00"),".",TEXT(C60,"000")),IF(H60="Subetapa",CONCATENATE(TEXT(B60,"00"),".",TEXT(C60,"000"),".",TEXT(D60,"000")),IF(H60="Serviço",CONCATENATE(TEXT(B60,"00"),".",TEXT(C60,"000"),".",TEXT(D60,"000"),".",TEXT(E60,"000")),""))))) -> 02.001.002.001 | J60: Bandeja de Proteção Primária com estrutura metálica e trama de madeira | K60: =IFERROR(VLOOKUP(J60,BASES!$A$13:$E$342,3,FALSE),0) -> m | L60: =IFERROR(VLOOKUP(J60,BASES!$A$13:$E$342,4,FALSE),0) -> 97.23 | M60: =IFERROR(VLOOKUP(J60,CPU!$D$2:$H$1439,5,FALSE),0) -> 284.7986 | N60: =IF(H60="Serviço",M60*L60,IF(H60="CÉLULA CONSTRUTIVA",SUMIFS($N$8:$N$419,$B$8:$B$419,B60,$H$8:$H$419,"Serviço"),IF(H60="ETAPA",SUMIFS($N$8:$N$419,$B$8:$B$419,B60,$C$8:$C$419,C60,$H$8:$H$419,"Serviço"),IF(H60="SUBETAPA",SUMIFS($N$8:$N$419,$B$8:$B$419,B60,$C$8:$C$419,C60,$D$8:$D$419,D60,$H$8:$H$419,"Serviço"),0)))) -> 27690.968 | O60: Previsto confomre NR18 | P60: Lançado ERP
A61: =IF($H61="UNIDADE CONSTRUTIVA",OFFSET(A61,-1,0)+1,LARGE(A$3:A60,1)) -> 0 | B61: =IF(H61="UNIDADE CONSTRUTIVA",0,IF(H61="CÉLULA CONSTRUTIVA",OFFSET(B61,-1,0)+1,OFFSET(B61,-1,0))) -> 2 | C61: =IF(H61="CÉLULA CONSTRUTIVA",0,IF(H61="ETAPA",OFFSET(C61,-1,0)+1,OFFSET(C61,-1,0))) -> 1 | D61: =IF(H61="ETAPA",0,IF(H61="SUBETAPA",OFFSET(D61,-1,0)+1,OFFSET(D61,-1,0))) -> 2 | E61: =IF(H61="Subetapa",0,IF(H61="serviço",OFFSET(E61,-1,0)+1,OFFSET(E61,-1,0))) -> 2 | H61: SERVIÇO | I61: =IF(H61="Unidade Construtiva",TEXT(A61,"00"),IF(H61="Célula Construtiva",TEXT(B61,"00"),IF(H61="Etapa",CONCATENATE(TEXT(B61,"00"),".",TEXT(C61,"000")),IF(H61="Subetapa",CONCATENATE(TEXT(B61,"00"),".",TEXT(C61,"000"),".",TEXT(D61,"000")),IF(H61="Serviço",CONCATENATE(TEXT(B61,"00"),".",TEXT(C61,"000"),".",TEXT(D61,"000"),".",TEXT(E61,"000")),""))))) -> 02.001.002.002 | J61: Bandeja de Proteção Secundária com estrutura metálica e trama de madeira | K61: =IFERROR(VLOOKUP(J61,BASES!$A$13:$E$342,3,FALSE),0) -> m | L61: =IFERROR(VLOOKUP(J61,BASES!$A$13:$E$342,4,FALSE),0) -> 71.85 | M61: =IFERROR(VLOOKUP(J61,CPU!$D$2:$H$1439,5,FALSE),0) -> 270.9386 | N61: =IF(H61="Serviço",M61*L61,IF(H61="CÉLULA CONSTRUTIVA",SUMIFS($N$8:$N$419,$B$8:$B$419,B61,$H$8:$H$419,"Serviço"),IF(H61="ETAPA",SUMIFS($N$8:$N$419,$B$8:$B$419,B61,$C$8:$C$419,C61,$H$8:$H$419,"Serviço"),IF(H61="SUBETAPA",SUMIFS($N$8:$N$419,$B$8:$B$419,B61,$C$8:$C$419,C61,$D$8:$D$419,D61,$H$8:$H$419,"Serviço"),0)))) -> 19466.938 | O61: Previsto confomre NR18 | P61: Lançado ERP
A62: =IF($H62="UNIDADE CONSTRUTIVA",OFFSET(A62,-1,0)+1,LARGE(A$3:A61,1)) -> 0 | B62: =IF(H62="UNIDADE CONSTRUTIVA",0,IF(H62="CÉLULA CONSTRUTIVA",OFFSET(B62,-1,0)+1,OFFSET(B62,-1,0))) -> 2 | C62: =IF(H62="CÉLULA CONSTRUTIVA",0,IF(H62="ETAPA",OFFSET(C62,-1,0)+1,OFFSET(C62,-1,0))) -> 1 | D62: =IF(H62="ETAPA",0,IF(H62="SUBETAPA",OFFSET(D62,-1,0)+1,OFFSET(D62,-1,0))) -> 2 | E62: =IF(H62="Subetapa",0,IF(H62="serviço",OFFSET(E62,-1,0)+1,OFFSET(E62,-1,0))) -> 3 | H62: SERVIÇO | I62: =IF(H62="Unidade Construtiva",TEXT(A62,"00"),IF(H62="Célula Construtiva",TEXT(B62,"00"),IF(H62="Etapa",CONCATENATE(TEXT(B62,"00"),".",TEXT(C62,"000")),IF(H62="Subetapa",CONCATENATE(TEXT(B62,"00"),".",TEXT(C62,"000"),".",TEXT(D62,"000")),IF(H62="Serviço",CONCATENATE(TEXT(B62,"00"),".",TEXT(C62,"000"),".",TEXT(D62,"000"),".",TEXT(E62,"000")),""))))) -> 02.001.002.003 | J62: Guarda-corpo de vãos, fixado em fôrma de madeira, em trama de madeira com tela de polipropileno | K62: =IFERROR(VLOOKUP(J62,BASES!$A$13:$E$342,3,FALSE),0) -> m2 | L62: =Arquitetura!H2446+Arquitetura!H2449 -> 261.58 | M62: =IFERROR(VLOOKUP(J62,CPU!$D$2:$H$1439,5,FALSE),0) -> 26.841827 | N62: =IF(H62="Serviço",M62*L62,IF(H62="CÉLULA CONSTRUTIVA",SUMIFS($N$8:$N$419,$B$8:$B$419,B62,$H$8:$H$419,"Serviço"),IF(H62="ETAPA",SUMIFS($N$8:$N$419,$B$8:$B$419,B62,$C$8:$C$419,C62,$H$8:$H$419,"Serviço"),IF(H62="SUBETAPA",SUMIFS($N$8:$N$419,$B$8:$B$419,B62,$C$8:$C$419,C62,$D$8:$D$419,D62,$H$8:$H$419,"Serviço"),0)))) -> 7021.2851 | O62: Previsto confomre NR18 | P62: Lançado ERP
A63: =IF($H63="UNIDADE CONSTRUTIVA",OFFSET(A63,-1,0)+1,LARGE(A$3:A62,1)) -> 0 | B63: =IF(H63="UNIDADE CONSTRUTIVA",0,IF(H63="CÉLULA CONSTRUTIVA",OFFSET(B63,-1,0)+1,OFFSET(B63,-1,0))) -> 2 | C63: =IF(H63="CÉLULA CONSTRUTIVA",0,IF(H63="ETAPA",OFFSET(C63,-1,0)+1,OFFSET(C63,-1,0))) -> 1 | D63: =IF(H63="ETAPA",0,IF(H63="SUBETAPA",OFFSET(D63,-1,0)+1,OFFSET(D63,-1,0))) -> 2 | E63: =IF(H63="Subetapa",0,IF(H63="serviço",OFFSET(E63,-1,0)+1,OFFSET(E63,-1,0))) -> 4 | H63: SERVIÇO | I63: =IF(H63="Unidade Construtiva",TEXT(A63,"00"),IF(H63="Célula Construtiva",TEXT(B63,"00"),IF(H63="Etapa",CONCATENATE(TEXT(B63,"00"),".",TEXT(C63,"000")),IF(H63="Subetapa",CONCATENATE(TEXT(B63,"00"),".",TEXT(C63,"000"),".",TEXT(D63,"000")),IF(H63="Serviço",CONCATENATE(TEXT(B63,"00"),".",TEXT(C63,"000"),".",TEXT(D63,"000"),".",TEXT(E63,"000")),""))))) -> 02.001.002.004 | J63: Guarda corpo de laje após desforma de pontalete de madeira, travessões e tela | K63: =IFERROR(VLOOKUP(J63,BASES!$A$13:$E$342,3,FALSE),0) -> m | L63: =IFERROR(VLOOKUP(J63,BASES!$A$13:$E$342,4,FALSE),0) -> 287.4 | M63: =IFERROR(VLOOKUP(J63,CPU!$D$2:$H$1439,5,FALSE),0) -> 29.291877 | N63: =IF(H63="Serviço",M63*L63,IF(H63="CÉLULA CONSTRUTIVA",SUMIFS($N$8:$N$419,$B$8:$B$419,B63,$H$8:$H$419,"Serviço"),IF(H63="ETAPA",SUMIFS($N$8:$N$419,$B$8:$B$419,B63,$C$8:$C$419,C63,$H$8:$H$419,"Serviço"),IF(H63="SUBETAPA",SUMIFS($N$8:$N$419,$B$8:$B$419,B63,$C$8:$C$419,C63,$D$8:$D$419,D63,$H$8:$H$419,"Serviço"),0)))) -> 8418.4854 | O63: Previsto confomre NR18 | P63: Lançado ERP
A64: =IF($H64="UNIDADE CONSTRUTIVA",OFFSET(A64,-1,0)+1,LARGE(A$3:A63,1)) -> 0 | B64: =IF(H64="UNIDADE CONSTRUTIVA",0,IF(H64="CÉLULA CONSTRUTIVA",OFFSET(B64,-1,0)+1,OFFSET(B64,-1,0))) -> 2 | C64: =IF(H64="CÉLULA CONSTRUTIVA",0,IF(H64="ETAPA",OFFSET(C64,-1,0)+1,OFFSET(C64,-1,0))) -> 1 | D64: =IF(H64="ETAPA",0,IF(H64="SUBETAPA",OFFSET(D64,-1,0)+1,OFFSET(D64,-1,0))) -> 2 | E64: =IF(H64="Subetapa",0,IF(H64="serviço",OFFSET(E64,-1,0)+1,OFFSET(E64,-1,0))) -> 5 | H64: SERVIÇO | I64: =IF(H64="Unidade Construtiva",TEXT(A64,"00"),IF(H64="Célula Construtiva",TEXT(B64,"00"),IF(H64="Etapa",CONCATENATE(TEXT(B64,"00"),".",TEXT(C64,"000")),IF(H64="Subetapa",CONCATENATE(TEXT(B64,"00"),".",TEXT(C64,"000"),".",TEXT(D64,"000")),IF(H64="Serviço",CONCATENATE(TEXT(B64,"00"),".",TEXT(C64,"000"),".",TEXT(D64,"000"),".",TEXT(E64,"000")),""))))) -> 02.001.002.005 | J64: Fechamento removível de vãos de porta de elevador em madeira | K64: =IFERROR(VLOOKUP(J64,BASES!$A$13:$E$342,3,FALSE),0) -> m2 | L64: =IFERROR(VLOOKUP(J64,BASES!$A$13:$E$342,4,FALSE),0) -> 41.58 | M64: =IFERROR(VLOOKUP(J64,CPU!$D$2:$H$1439,5,FALSE),0) -> 47.353011 | N64: =IF(H64="Serviço",M64*L64,IF(H64="CÉLULA CONSTRUTIVA",SUMIFS($N$8:$N$419,$B$8:$B$419,B64,$H$8:$H$419,"Serviço"),IF(H64="ETAPA",SUMIFS($N$8:$N$419,$B$8:$B$419,B64,$C$8:$C$419,C64,$H$8:$H$419,"Serviço"),IF(H64="SUBETAPA",SUMIFS($N$8:$N$419,$B$8:$B$419,B64,$C$8:$C$419,C64,$D$8:$D$419,D64,$H$8:$H$419,"Serviço"),0)))) -> 1968.9382 | O64: Previsto confomre NR18 | P64: Lançado ERP
A65: =IF($H65="UNIDADE CONSTRUTIVA",OFFSET(A65,-1,0)+1,LARGE(A$3:A64,1)) -> 0 | B65: =IF(H65="UNIDADE CONSTRUTIVA",0,IF(H65="CÉLULA CONSTRUTIVA",OFFSET(B65,-1,0)+1,OFFSET(B65,-1,0))) -> 2 | C65: =IF(H65="CÉLULA CONSTRUTIVA",0,IF(H65="ETAPA",OFFSET(C65,-1,0)+1,OFFSET(C65,-1,0))) -> 1 | D65: =IF(H65="ETAPA",0,IF(H65="SUBETAPA",OFFSET(D65,-1,0)+1,OFFSET(D65,-1,0))) -> 2 | E65: =IF(H65="Subetapa",0,IF(H65="serviço",OFFSET(E65,-1,0)+1,OFFSET(E65,-1,0))) -> 6 | H65: SERVIÇO | I65: =IF(H65="Unidade Construtiva",TEXT(A65,"00"),IF(H65="Célula Construtiva",TEXT(B65,"00"),IF(H65="Etapa",CONCATENATE(TEXT(B65,"00"),".",TEXT(C65,"000")),IF(H65="Subetapa",CONCATENATE(TEXT(B65,"00"),".",TEXT(C65,"000"),".",TEXT(D65,"000")),IF(H65="Serviço",CONCATENATE(TEXT(B65,"00"),".",TEXT(C65,"000"),".",TEXT(D65,"000"),".",TEXT(E65,"000")),""))))) -> 02.001.002.006 | J65: Fechamento removível de vãos de porta de entrada dos aptos. em madeira | K65: =IFERROR(VLOOKUP(J65,BASES!$A$13:$E$342,3,FALSE),0) -> m2 | L65: =IFERROR(VLOOKUP(J65,BASES!$A$13:$E$342,4,FALSE),0) -> 58.59 | M65: =IFERROR(VLOOKUP(J65,CPU!$D$2:$H$1439,5,FALSE),0) -> 47.353011 | N65: =IF(H65="Serviço",M65*L65,IF(H65="CÉLULA CONSTRUTIVA",SUMIFS($N$8:$N$419,$B$8:$B$419,B65,$H$8:$H$419,"Serviço"),IF(H65="ETAPA",SUMIFS($N$8:$N$419,$B$8:$B$419,B65,$C$8:$C$419,C65,$H$8:$H$419,"Serviço"),IF(H65="SUBETAPA",SUMIFS($N$8:$N$419,$B$8:$B$419,B65,$C$8:$C$419,C65,$D$8:$D$419,D65,$H$8:$H$419,"Serviço"),0)))) -> 2774.4129 | O65: Previsto confomre NR18 | P65: Lançado ERP
A66: =IF($H66="UNIDADE CONSTRUTIVA",OFFSET(A66,-1,0)+1,LARGE(A$3:A65,1)) -> 0 | B66: =IF(H66="UNIDADE CONSTRUTIVA",0,IF(H66="CÉLULA CONSTRUTIVA",OFFSET(B66,-1,0)+1,OFFSET(B66,-1,0))) -> 2 | C66: =IF(H66="CÉLULA CONSTRUTIVA",0,IF(H66="ETAPA",OFFSET(C66,-1,0)+1,OFFSET(C66,-1,0))) -> 1 | D66: =IF(H66="ETAPA",0,IF(H66="SUBETAPA",OFFSET(D66,-1,0)+1,OFFSET(D66,-1,0))) -> 2 | E66: =IF(H66="Subetapa",0,IF(H66="serviço",OFFSET(E66,-1,0)+1,OFFSET(E66,-1,0))) -> 7 | H66: SERVIÇO | I66: =IF(H66="Unidade Construtiva",TEXT(A66,"00"),IF(H66="Célula Construtiva",TEXT(B66,"00"),IF(H66="Etapa",CONCATENATE(TEXT(B66,"00"),".",TEXT(C66,"000")),IF(H66="Subetapa",CONCATENATE(TEXT(B66,"00"),".",TEXT(C66,"000"),".",TEXT(D66,"000")),IF(H66="Serviço",CONCATENATE(TEXT(B66,"00"),".",TEXT(C66,"000"),".",TEXT(D66,"000"),".",TEXT(E66,"000")),""))))) -> 02.001.002.007 | J66: Rede de proteção, SLQA, leve | K66: =IFERROR(VLOOKUP(J66,BASES!$A$13:$E$342,3,FALSE),0) -> m2 | L66: =IFERROR(VLOOKUP(J66,BASES!$A$13:$E$342,4,FALSE),0) -> 326.199 | M66: =IFERROR(VLOOKUP(J66,CPU!$D$2:$H$1439,5,FALSE),0) -> 417.439 | N66: =IF(H66="Serviço",M66*L66,IF(H66="CÉLULA CONSTRUTIVA",SUMIFS($N$8:$N$419,$B$8:$B$419,B66,$H$8:$H$419,"Serviço"),IF(H66="ETAPA",SUMIFS($N$8:$N$419,$B$8:$B$419,B66,$C$8:$C$419,C66,$H$8:$H$419,"Serviço"),IF(H66="SUBETAPA",SUMIFS($N$8:$N$419,$B$8:$B$419,B66,$C$8:$C$419,C66,$D$8:$D$419,D66,$H$8:$H$419,"Serviço"),0)))) -> 136168.18 | O66: Previsto confomre NR18 | P66: Lançado ERP
A67: =IF($H67="UNIDADE CONSTRUTIVA",OFFSET(A67,-1,0)+1,LARGE(A$3:A66,1)) -> 0 | B67: =IF(H67="UNIDADE CONSTRUTIVA",0,IF(H67="CÉLULA CONSTRUTIVA",OFFSET(B67,-1,0)+1,OFFSET(B67,-1,0))) -> 2 | C67: =IF(H67="CÉLULA CONSTRUTIVA",0,IF(H67="ETAPA",OFFSET(C67,-1,0)+1,OFFSET(C67,-1,0))) -> 1 | D67: =IF(H67="ETAPA",0,IF(H67="SUBETAPA",OFFSET(D67,-1,0)+1,OFFSET(D67,-1,0))) -> 2 | E67: =IF(H67="Subetapa",0,IF(H67="serviço",OFFSET(E67,-1,0)+1,OFFSET(E67,-1,0))) -> 8 | H67: SERVIÇO | I67: =IF(H67="Unidade Construtiva",TEXT(A67,"00"),IF(H67="Célula Construtiva",TEXT(B67,"00"),IF(H67="Etapa",CONCATENATE(TEXT(B67,"00"),".",TEXT(C67,"000")),IF(H67="Subetapa",CONCATENATE(TEXT(B67,"00"),".",TEXT(C67,"000"),".",TEXT(D67,"000")),IF(H67="Serviço",CONCATENATE(TEXT(B67,"00"),".",TEXT(C67,"000"),".",TEXT(D67,"000"),".",TEXT(E67,"000")),""))))) -> 02.001.002.008 | J67: Tela fachadeira mosqueteiro reforçada simples | K67: =IFERROR(VLOOKUP(J67,BASES!$A$13:$E$342,3,FALSE),0) -> m2 | L67: =IFERROR(VLOOKUP(J67,BASES!$A$13:$E$342,4,FALSE),0) -> 3401.787 | M67: =IFERROR(VLOOKUP(J67,CPU!$D$2:$H$1439,5,FALSE),0) -> 7.9493 | N67: =IF(H67="Serviço",M67*L67,IF(H67="CÉLULA CONSTRUTIVA",SUMIFS($N$8:$N$419,$B$8:$B$419,B67,$H$8:$H$419,"Serviço"),IF(H67="ETAPA",SUMIFS($N$8:$N$419,$B$8:$B$419,B67,$C$8:$C$419,C67,$H$8:$H$419,"Serviço"),IF(H67="SUBETAPA",SUMIFS($N$8:$N$419,$B$8:$B$419,B67,$C$8:$C$419,C67,$D$8:$D$419,D67,$H$8:$H$419,"Serviço"),0)))) -> 27041.825 | O67: Previsto confomre NR18 | P67: Lançado ERP
A68: =IF($H68="UNIDADE CONSTRUTIVA",OFFSET(A68,-1,0)+1,LARGE(A$3:A67,1)) -> 0 | B68: =IF(H68="UNIDADE CONSTRUTIVA",0,IF(H68="CÉLULA CONSTRUTIVA",OFFSET(B68,-1,0)+1,OFFSET(B68,-1,0))) -> 2 | C68: =IF(H68="CÉLULA CONSTRUTIVA",0,IF(H68="ETAPA",OFFSET(C68,-1,0)+1,OFFSET(C68,-1,0))) -> 1 | D68: =IF(H68="ETAPA",0,IF(H68="SUBETAPA",OFFSET(D68,-1,0)+1,OFFSET(D68,-1,0))) -> 2 | E68: =IF(H68="Subetapa",0,IF(H68="serviço",OFFSET(E68,-1,0)+1,OFFSET(E68,-1,0))) -> 9 | H68: SERVIÇO | I68: =IF(H68="Unidade Construtiva",TEXT(A68,"00"),IF(H68="Célula Construtiva",TEXT(B68,"00"),IF(H68="Etapa",CONCATENATE(TEXT(B68,"00"),".",TEXT(C68,"000")),IF(H68="Subetapa",CONCATENATE(TEXT(B68,"00"),".",TEXT(C68,"000"),".",TEXT(D68,"000")),IF(H68="Serviço",CONCATENATE(TEXT(B68,"00"),".",TEXT(C68,"000"),".",TEXT(D68,"000"),".",TEXT(E68,"000")),""))))) -> 02.001.002.009 | J68: Sinalização de obra | K68: =IFERROR(VLOOKUP(J68,BASES!$A$13:$E$342,3,FALSE),0) -> vb | L68: =IFERROR(VLOOKUP(J68,BASES!$A$13:$E$342,4,FALSE),0) -> 1 | M68: =IFERROR(VLOOKUP(J68,BASES!$A$13:$E$342,5,FALSE),0) -> 7891.02 | N68: =IF(H68="Serviço",M68*L68,IF(H68="CÉLULA CONSTRUTIVA",SUMIFS($N$8:$N$419,$B$8:$B$419,B68,$H$8:$H$419,"Serviço"),IF(H68="ETAPA",SUMIFS($N$8:$N$419,$B$8:$B$419,B68,$C$8:$C$419,C68,$H$8:$H$419,"Serviço"),IF(H68="SUBETAPA",SUMIFS($N$8:$N$419,$B$8:$B$419,B68,$C$8:$C$419,C68,$D$8:$D$419,D68,$H$8:$H$419,"Serviço"),0)))) -> 7891.02 | O68: Previsto confomre NR18 | P68: Lançado ERP
A69: =IF($H69="UNIDADE CONSTRUTIVA",OFFSET(A69,-1,0)+1,LARGE(A$3:A68,1)) -> 0 | B69: =IF(H69="UNIDADE CONSTRUTIVA",0,IF(H69="CÉLULA CONSTRUTIVA",OFFSET(B69,-1,0)+1,OFFSET(B69,-1,0))) -> 2 | C69: =IF(H69="CÉLULA CONSTRUTIVA",0,IF(H69="ETAPA",OFFSET(C69,-1,0)+1,OFFSET(C69,-1,0))) -> 1 | D69: =IF(H69="ETAPA",0,IF(H69="SUBETAPA",OFFSET(D69,-1,0)+1,OFFSET(D69,-1,0))) -> 2 | E69: =IF(H69="Subetapa",0,IF(H69="serviço",OFFSET(E69,-1,0)+1,OFFSET(E69,-1,0))) -> 10 | H69: SERVIÇO | I69: =IF(H69="Unidade Construtiva",TEXT(A69,"00"),IF(H69="Célula Construtiva",TEXT(B69,"00"),IF(H69="Etapa",CONCATENATE(TEXT(B69,"00"),".",TEXT(C69,"000")),IF(H69="Subetapa",CONCATENATE(TEXT(B69,"00"),".",TEXT(C69,"000"),".",TEXT(D69,"000")),IF(H69="Serviço",CONCATENATE(TEXT(B69,"00"),".",TEXT(C69,"000"),".",TEXT(D69,"000"),".",TEXT(E69,"000")),""))))) -> 02.001.002.010 | J69: Linha de vida | K69: =IFERROR(VLOOKUP(J69,BASES!$A$13:$E$342,3,FALSE),0) -> m | L69: =IFERROR(VLOOKUP(J69,BASES!$A$13:$E$342,4,FALSE),0) -> 287.4 | M69: =IFERROR(VLOOKUP(J69,CPU!$D$2:$H$1439,5,FALSE),0) -> 87.214 | N69: =IF(H69="Serviço",M69*L69,IF(H69="CÉLULA CONSTRUTIVA",SUMIFS($N$8:$N$419,$B$8:$B$419,B69,$H$8:$H$419,"Serviço"),IF(H69="ETAPA",SUMIFS($N$8:$N$419,$B$8:$B$419,B69,$C$8:$C$419,C69,$H$8:$H$419,"Serviço"),IF(H69="SUBETAPA",SUMIFS($N$8:$N$419,$B$8:$B$419,B69,$C$8:$C$419,C69,$D$8:$D$419,D69,$H$8:$H$419,"Serviço"),0)))) -> 25065.304 | O69: Previsto confomre NR18 | P69: Lançado ERP
A70: =IF($H70="UNIDADE CONSTRUTIVA",OFFSET(A70,-1,0)+1,LARGE(A$3:A69,1)) -> 0 | B70: =IF(H70="UNIDADE CONSTRUTIVA",0,IF(H70="CÉLULA CONSTRUTIVA",OFFSET(B70,-1,0)+1,OFFSET(B70,-1,0))) -> 2 | C70: =IF(H70="CÉLULA CONSTRUTIVA",0,IF(H70="ETAPA",OFFSET(C70,-1,0)+1,OFFSET(C70,-1,0))) -> 1 | D70: =IF(H70="ETAPA",0,IF(H70="SUBETAPA",OFFSET(D70,-1,0)+1,OFFSET(D70,-1,0))) -> 3 | E70: =IF(H70="Subetapa",0,IF(H70="serviço",OFFSET(E70,-1,0)+1,OFFSET(E70,-1,0))) -> 0 | H70: SUBETAPA | I70: =IF(H70="Unidade Construtiva",TEXT(A70,"00"),IF(H70="Célula Construtiva",TEXT(B70,"00"),IF(H70="Etapa",CONCATENATE(TEXT(B70,"00"),".",TEXT(C70,"000")),IF(H70="Subetapa",CONCATENATE(TEXT(B70,"00"),".",TEXT(C70,"000"),".",TEXT(D70,"000")),IF(H70="Serviço",CONCATENATE(TEXT(B70,"00"),".",TEXT(C70,"000"),".",TEXT(D70,"000"),".",TEXT(E70,"000")),""))))) -> 02.001.003 | J70: Meio Ambiente | N70: =IF(H70="Serviço",M70*L70,IF(H70="CÉLULA CONSTRUTIVA",SUMIFS($N$8:$N$419,$B$8:$B$419,B70,$H$8:$H$419,"Serviço"),IF(H70="ETAPA",SUMIFS($N$8:$N$419,$B$8:$B$419,B70,$C$8:$C$419,C70,$H$8:$H$419,"Serviço"),IF(H70="SUBETAPA",SUMIFS($N$8:$N$419,$B$8:$B$419,B70,$C$8:$C$419,C70,$D$8:$D$419,D70,$H$8:$H$419,"Serviço"),0)))) -> 74599.309 | Q70: =N70/'Obra '!$C$32 -> 0.015626522
A71: =IF($H71="UNIDADE CONSTRUTIVA",OFFSET(A71,-1,0)+1,LARGE(A$3:A70,1)) -> 0 | B71: =IF(H71="UNIDADE CONSTRUTIVA",0,IF(H71="CÉLULA CONSTRUTIVA",OFFSET(B71,-1,0)+1,OFFSET(B71,-1,0))) -> 2 | C71: =IF(H71="CÉLULA CONSTRUTIVA",0,IF(H71="ETAPA",OFFSET(C71,-1,0)+1,OFFSET(C71,-1,0))) -> 1 | D71: =IF(H71="ETAPA",0,IF(H71="SUBETAPA",OFFSET(D71,-1,0)+1,OFFSET(D71,-1,0))) -> 3 | E71: =IF(H71="Subetapa",0,IF(H71="serviço",OFFSET(E71,-1,0)+1,OFFSET(E71,-1,0))) -> 1 | H71: SERVIÇO | I71: =IF(H71="Unidade Construtiva",TEXT(A71,"00"),IF(H71="Célula Construtiva",TEXT(B71,"00"),IF(H71="Etapa",CONCATENATE(TEXT(B71,"00"),".",TEXT(C71,"000")),IF(H71="Subetapa",CONCATENATE(TEXT(B71,"00"),".",TEXT(C71,"000"),".",TEXT(D71,"000")),IF(H71="Serviço",CONCATENATE(TEXT(B71,"00"),".",TEXT(C71,"000"),".",TEXT(D71,"000"),".",TEXT(E71,"000")),""))))) -> 02.001.003.001 | J71: Projetos de Segurança do Trabalho | K71: =IFERROR(VLOOKUP(J71,BASES!$A$13:$E$342,3,FALSE),0) -> vb | L71: =IFERROR(VLOOKUP(J71,BASES!$A$13:$E$342,4,FALSE),0) -> 1 | M71: =IFERROR(VLOOKUP(J71,BASES!$A$13:$E$342,5,FALSE),0) -> 4285.858 | N71: =IF(H71="Serviço",M71*L71,IF(H71="CÉLULA CONSTRUTIVA",SUMIFS($N$8:$N$419,$B$8:$B$419,B71,$H$8:$H$419,"Serviço"),IF(H71="ETAPA",SUMIFS($N$8:$N$419,$B$8:$B$419,B71,$C$8:$C$419,C71,$H$8:$H$419,"Serviço"),IF(H71="SUBETAPA",SUMIFS($N$8:$N$419,$B$8:$B$419,B71,$C$8:$C$419,C71,$D$8:$D$419,D71,$H$8:$H$419,"Serviço"),0)))) -> 4285.858 | O71: =IF(VLOOKUP(J71,BASES!$A$13:$F$342,6,FALSE)="Recebido","Valor informado em formulário",IF(VLOOKUP(J71,BASES!$A$13:$F$342,6,FALSE)="Estimado","Estimado com base em índices históricos","Não solicitado")) -> Estimado com base em índices históricos | P71: Lançado ERP
A72: =IF($H72="UNIDADE CONSTRUTIVA",OFFSET(A72,-1,0)+1,LARGE(A$3:A71,1)) -> 0 | B72: =IF(H72="UNIDADE CONSTRUTIVA",0,IF(H72="CÉLULA CONSTRUTIVA",OFFSET(B72,-1,0)+1,OFFSET(B72,-1,0))) -> 2 | C72: =IF(H72="CÉLULA CONSTRUTIVA",0,IF(H72="ETAPA",OFFSET(C72,-1,0)+1,OFFSET(C72,-1,0))) -> 1 | D72: =IF(H72="ETAPA",0,IF(H72="SUBETAPA",OFFSET(D72,-1,0)+1,OFFSET(D72,-1,0))) -> 3 | E72: =IF(H72="Subetapa",0,IF(H72="serviço",OFFSET(E72,-1,0)+1,OFFSET(E72,-1,0))) -> 2 | H72: SERVIÇO | I72: =IF(H72="Unidade Construtiva",TEXT(A72,"00"),IF(H72="Célula Construtiva",TEXT(B72,"00"),IF(H72="Etapa",CONCATENATE(TEXT(B72,"00"),".",TEXT(C72,"000")),IF(H72="Subetapa",CONCATENATE(TEXT(B72,"00"),".",TEXT(C72,"000"),".",TEXT(D72,"000")),IF(H72="Serviço",CONCATENATE(TEXT(B72,"00"),".",TEXT(C72,"000"),".",TEXT(D72,"000"),".",TEXT(E72,"000")),""))))) -> 02.001.003.002 | J72: Elaboração do programa de gerenciamento de riscos (PGR) | K72: =IFERROR(VLOOKUP(J72,BASES!$A$13:$E$342,3,FALSE),0) -> vb | L72: =IFERROR(VLOOKUP(J72,BASES!$A$13:$E$342,4,FALSE),0) -> 1 | M72: =IFERROR(VLOOKUP(J72,BASES!$A$13:$E$342,5,FALSE),0) -> 3113.451 | N72: =IF(H72="Serviço",M72*L72,IF(H72="CÉLULA CONSTRUTIVA",SUMIFS($N$8:$N$419,$B$8:$B$419,B72,$H$8:$H$419,"Serviço"),IF(H72="ETAPA",SUMIFS($N$8:$N$419,$B$8:$B$419,B72,$C$8:$C$419,C72,$H$8:$H$419,"Serviço"),IF(H72="SUBETAPA",SUMIFS($N$8:$N$419,$B$8:$B$419,B72,$C$8:$C$419,C72,$D$8:$D$419,D72,$H$8:$H$419,"Serviço"),0)))) -> 3113.451 | O72: =IF(VLOOKUP(J72,BASES!$A$13:$F$342,6,FALSE)="Recebido","Valor informado em formulário",IF(VLOOKUP(J72,BASES!$A$13:$F$342,6,FALSE)="Estimado","Estimado com base em índices históricos","Não solicitado")) -> Estimado com base em índices históricos | P72: Em Andamento
A73: =IF($H73="UNIDADE CONSTRUTIVA",OFFSET(A73,-1,0)+1,LARGE(A$3:A71,1)) -> 0 | B73: =IF(H73="UNIDADE CONSTRUTIVA",0,IF(H73="CÉLULA CONSTRUTIVA",OFFSET(B73,-1,0)+1,OFFSET(B73,-1,0))) -> 2 | C73: =IF(H73="CÉLULA CONSTRUTIVA",0,IF(H73="ETAPA",OFFSET(C73,-1,0)+1,OFFSET(C73,-1,0))) -> 1 | D73: =IF(H73="ETAPA",0,IF(H73="SUBETAPA",OFFSET(D73,-1,0)+1,OFFSET(D73,-1,0))) -> 3 | E73: =IF(H73="Subetapa",0,IF(H73="serviço",OFFSET(E73,-1,0)+1,OFFSET(E73,-1,0))) -> 3 | H73: SERVIÇO | I73: =IF(H73="Unidade Construtiva",TEXT(A73,"00"),IF(H73="Célula Construtiva",TEXT(B73,"00"),IF(H73="Etapa",CONCATENATE(TEXT(B73,"00"),".",TEXT(C73,"000")),IF(H73="Subetapa",CONCATENATE(TEXT(B73,"00"),".",TEXT(C73,"000"),".",TEXT(D73,"000")),IF(H73="Serviço",CONCATENATE(TEXT(B73,"00"),".",TEXT(C73,"000"),".",TEXT(D73,"000"),".",TEXT(E73,"000")),""))))) -> 02.001.003.003 | J73: Remoção de entulhos e resíduos | K73: mês | L73: ='Obra '!E7 -> 42 | M73: =400*4 -> 1600 | N73: =IF(H73="Serviço",M73*L73,IF(H73="CÉLULA CONSTRUTIVA",SUMIFS($N$8:$N$419,$B$8:$B$419,B73,$H$8:$H$419,"Serviço"),IF(H73="ETAPA",SUMIFS($N$8:$N$419,$B$8:$B$419,B73,$C$8:$C$419,C73,$H$8:$H$419,"Serviço"),IF(H73="SUBETAPA",SUMIFS($N$8:$N$419,$B$8:$B$419,B73,$C$8:$C$419,C73,$D$8:$D$419,D73,$H$8:$H$419,"Serviço"),0)))) -> 67200 | O73: Previsto 4 caçambas por mês, durante o prazo da obra | P73: Em Andamento
A74: =IF($H74="UNIDADE CONSTRUTIVA",OFFSET(A74,-1,0)+1,LARGE(A$3:A73,1)) -> 0 | B74: =IF(H74="UNIDADE CONSTRUTIVA",0,IF(H74="CÉLULA CONSTRUTIVA",OFFSET(B74,-1,0)+1,OFFSET(B74,-1,0))) -> 2 | C74: =IF(H74="CÉLULA CONSTRUTIVA",0,IF(H74="ETAPA",OFFSET(C74,-1,0)+1,OFFSET(C74,-1,0))) -> 1 | D74: =IF(H74="ETAPA",0,IF(H74="SUBETAPA",OFFSET(D74,-1,0)+1,OFFSET(D74,-1,0))) -> 4 | E74: =IF(H74="Subetapa",0,IF(H74="serviço",OFFSET(E74,-1,0)+1,OFFSET(E74,-1,0))) -> 0 | H74: SUBETAPA | I74: =IF(H74="Unidade Construtiva",TEXT(A74,"00"),IF(H74="Célula Construtiva",TEXT(B74,"00"),IF(H74="Etapa",CONCATENATE(TEXT(B74,"00"),".",TEXT(C74,"000")),IF(H74="Subetapa",CONCATENATE(TEXT(B74,"00"),".",TEXT(C74,"000"),".",TEXT(D74,"000")),IF(H74="Serviço",CONCATENATE(TEXT(B74,"00"),".",TEXT(C74,"000"),".",TEXT(D74,"000"),".",TEXT(E74,"000")),""))))) -> 02.001.004 | J74: Saúde Ocupacional | N74: =IF(H74="Serviço",M74*L74,IF(H74="CÉLULA CONSTRUTIVA",SUMIFS($N$8:$N$419,$B$8:$B$419,B74,$H$8:$H$419,"Serviço"),IF(H74="ETAPA",SUMIFS($N$8:$N$419,$B$8:$B$419,B74,$C$8:$C$419,C74,$H$8:$H$419,"Serviço"),IF(H74="SUBETAPA",SUMIFS($N$8:$N$419,$B$8:$B$419,B74,$C$8:$C$419,C74,$D$8:$D$419,D74,$H$8:$H$419,"Serviço"),0)))) -> 2791.32 | Q74: =N74/'Obra '!$C$32 -> 0.00058470548
A75: =IF($H75="UNIDADE CONSTRUTIVA",OFFSET(A75,-1,0)+1,LARGE(A$3:A74,1)) -> 0 | B75: =IF(H75="UNIDADE CONSTRUTIVA",0,IF(H75="CÉLULA CONSTRUTIVA",OFFSET(B75,-1,0)+1,OFFSET(B75,-1,0))) -> 2 | C75: =IF(H75="CÉLULA CONSTRUTIVA",0,IF(H75="ETAPA",OFFSET(C75,-1,0)+1,OFFSET(C75,-1,0))) -> 1 | D75: =IF(H75="ETAPA",0,IF(H75="SUBETAPA",OFFSET(D75,-1,0)+1,OFFSET(D75,-1,0))) -> 4 | E75: =IF(H75="Subetapa",0,IF(H75="serviço",OFFSET(E75,-1,0)+1,OFFSET(E75,-1,0))) -> 1 | H75: SERVIÇO | I75: =IF(H75="Unidade Construtiva",TEXT(A75,"00"),IF(H75="Célula Construtiva",TEXT(B75,"00"),IF(H75="Etapa",CONCATENATE(TEXT(B75,"00"),".",TEXT(C75,"000")),IF(H75="Subetapa",CONCATENATE(TEXT(B75,"00"),".",TEXT(C75,"000"),".",TEXT(D75,"000")),IF(H75="Serviço",CONCATENATE(TEXT(B75,"00"),".",TEXT(C75,"000"),".",TEXT(D75,"000"),".",TEXT(E75,"000")),""))))) -> 02.001.004.001 | J75: Dedetização, desratização e sanitização dos ambientes | K75: =IFERROR(VLOOKUP(J75,BASES!$A$13:$E$342,3,FALSE),0) -> mês | L75: =IFERROR(VLOOKUP(J75,BASES!$A$13:$E$342,4,FALSE),0) -> 42 | M75: =IFERROR(VLOOKUP(J75,BASES!$A$13:$E$342,5,FALSE),0) -> 66.46 | N75: =IF(H75="Serviço",M75*L75,IF(H75="CÉLULA CONSTRUTIVA",SUMIFS($N$8:$N$419,$B$8:$B$419,B75,$H$8:$H$419,"Serviço"),IF(H75="ETAPA",SUMIFS($N$8:$N$419,$B$8:$B$419,B75,$C$8:$C$419,C75,$H$8:$H$419,"Serviço"),IF(H75="SUBETAPA",SUMIFS($N$8:$N$419,$B$8:$B$419,B75,$C$8:$C$419,C75,$D$8:$D$419,D75,$H$8:$H$419,"Serviço"),0)))) -> 2791.32 | O75: =IF(VLOOKUP(J75,BASES!$A$13:$F$342,6,FALSE)="Recebido","Valor informado em formulário",IF(VLOOKUP(J75,BASES!$A$13:$F$342,6,FALSE)="Estimado","Estimado com base em índices históricos","Não solicitado")) -> Estimado com base em índices históricos | P75: Lançado ERP
A76: =IF($H76="UNIDADE CONSTRUTIVA",OFFSET(A76,-1,0)+1,LARGE(A$3:A75,1)) -> 0 | B76: =IF(H76="UNIDADE CONSTRUTIVA",0,IF(H76="CÉLULA CONSTRUTIVA",OFFSET(B76,-1,0)+1,OFFSET(B76,-1,0))) -> 2 | C76: =IF(H76="CÉLULA CONSTRUTIVA",0,IF(H76="ETAPA",OFFSET(C76,-1,0)+1,OFFSET(C76,-1,0))) -> 2 | D76: =IF(H76="ETAPA",0,IF(H76="SUBETAPA",OFFSET(D76,-1,0)+1,OFFSET(D76,-1,0))) -> 0 | E76: =IF(H76="Subetapa",0,IF(H76="serviço",OFFSET(E76,-1,0)+1,OFFSET(E76,-1,0))) -> 1 | H76: ETAPA | I76: =IF(H76="Unidade Construtiva",TEXT(A76,"00"),IF(H76="Célula Construtiva",TEXT(B76,"00"),IF(H76="Etapa",CONCATENATE(TEXT(B76,"00"),".",TEXT(C76,"000")),IF(H76="Subetapa",CONCATENATE(TEXT(B76,"00"),".",TEXT(C76,"000"),".",TEXT(D76,"000")),IF(H76="Serviço",CONCATENATE(TEXT(B76,"00"),".",TEXT(C76,"000"),".",TEXT(D76,"000"),".",TEXT(E76,"000")),""))))) -> 02.002 | J76: ADMINISTRAÇÃO E CANTEIRO DE OBRA | N76: =IF(H76="Serviço",M76*L76,IF(H76="CÉLULA CONSTRUTIVA",SUMIFS($N$8:$N$419,$B$8:$B$419,B76,$H$8:$H$419,"Serviço"),IF(H76="ETAPA",SUMIFS($N$8:$N$419,$B$8:$B$419,B76,$C$8:$C$419,C76,$H$8:$H$419,"Serviço"),IF(H76="SUBETAPA",SUMIFS($N$8:$N$419,$B$8:$B$419,B76,$C$8:$C$419,C76,$D$8:$D$419,D76,$H$8:$H$419,"Serviço"),0)))) -> 1231400.6 | Q76: =N76/'Obra '!$C$32 -> 0.25794487
A77: =IF($H77="UNIDADE CONSTRUTIVA",OFFSET(A77,-1,0)+1,LARGE(A$3:A76,1)) -> 0 | B77: =IF(H77="UNIDADE CONSTRUTIVA",0,IF(H77="CÉLULA CONSTRUTIVA",OFFSET(B77,-1,0)+1,OFFSET(B77,-1,0))) -> 2 | C77: =IF(H77="CÉLULA CONSTRUTIVA",0,IF(H77="ETAPA",OFFSET(C77,-1,0)+1,OFFSET(C77,-1,0))) -> 2 | D77: =IF(H77="ETAPA",0,IF(H77="SUBETAPA",OFFSET(D77,-1,0)+1,OFFSET(D77,-1,0))) -> 1 | E77: =IF(H77="Subetapa",0,IF(H77="serviço",OFFSET(E77,-1,0)+1,OFFSET(E77,-1,0))) -> 0 | H77: SUBETAPA | I77: =IF(H77="Unidade Construtiva",TEXT(A77,"00"),IF(H77="Célula Construtiva",TEXT(B77,"00"),IF(H77="Etapa",CONCATENATE(TEXT(B77,"00"),".",TEXT(C77,"000")),IF(H77="Subetapa",CONCATENATE(TEXT(B77,"00"),".",TEXT(C77,"000"),".",TEXT(D77,"000")),IF(H77="Serviço",CONCATENATE(TEXT(B77,"00"),".",TEXT(C77,"000"),".",TEXT(D77,"000"),".",TEXT(E77,"000")),""))))) -> 02.002.001 | J77: Equipe de Gestão e Apoio | N77: =IF(H77="Serviço",M77*L77,IF(H77="CÉLULA CONSTRUTIVA",SUMIFS($N$8:$N$419,$B$8:$B$419,B77,$H$8:$H$419,"Serviço"),IF(H77="ETAPA",SUMIFS($N$8:$N$419,$B$8:$B$419,B77,$C$8:$C$419,C77,$H$8:$H$419,"Serviço"),IF(H77="SUBETAPA",SUMIFS($N$8:$N$419,$B$8:$B$419,B77,$C$8:$C$419,C77,$D$8:$D$419,D77,$H$8:$H$419,"Serviço"),0)))) -> 908029.37 | Q77: =N77/'Obra '!$C$32 -> 0.19020741
A78: =IF($H78="UNIDADE CONSTRUTIVA",OFFSET(A78,-1,0)+1,LARGE(A$3:A77,1)) -> 0 | B78: =IF(H78="UNIDADE CONSTRUTIVA",0,IF(H78="CÉLULA CONSTRUTIVA",OFFSET(B78,-1,0)+1,OFFSET(B78,-1,0))) -> 2 | C78: =IF(H78="CÉLULA CONSTRUTIVA",0,IF(H78="ETAPA",OFFSET(C78,-1,0)+1,OFFSET(C78,-1,0))) -> 2 | D78: =IF(H78="ETAPA",0,IF(H78="SUBETAPA",OFFSET(D78,-1,0)+1,OFFSET(D78,-1,0))) -> 1 | E78: =IF(H78="Subetapa",0,IF(H78="serviço",OFFSET(E78,-1,0)+1,OFFSET(E78,-1,0))) -> 1 | H78: SERVIÇO | I78: =IF(H78="Unidade Construtiva",TEXT(A78,"00"),IF(H78="Célula Construtiva",TEXT(B78,"00"),IF(H78="Etapa",CONCATENATE(TEXT(B78,"00"),".",TEXT(C78,"000")),IF(H78="Subetapa",CONCATENATE(TEXT(B78,"00"),".",TEXT(C78,"000"),".",TEXT(D78,"000")),IF(H78="Serviço",CONCATENATE(TEXT(B78,"00"),".",TEXT(C78,"000"),".",TEXT(D78,"000"),".",TEXT(E78,"000")),""))))) -> 02.002.001.001 | J78: Engenheiro Civil | K78: =IFERROR(VLOOKUP(J78,BASES!$A$13:$E$342,3,FALSE),0) -> mês | L78: =IFERROR(VLOOKUP(J78,BASES!$A$13:$E$342,4,FALSE),0) -> 42 | M78: =IFERROR(VLOOKUP(J78,BASES!$A$13:$E$342,5,FALSE),0) -> 10000 | N78: =IF(H78="Serviço",M78*L78,IF(H78="CÉLULA CONSTRUTIVA",SUMIFS($N$8:$N$419,$B$8:$B$419,B78,$H$8:$H$419,"Serviço"),IF(H78="ETAPA",SUMIFS($N$8:$N$419,$B$8:$B$419,B78,$C$8:$C$419,C78,$H$8:$H$419,"Serviço"),IF(H78="SUBETAPA",SUMIFS($N$8:$N$419,$B$8:$B$419,B78,$C$8:$C$419,C78,$D$8:$D$419,D78,$H$8:$H$419,"Serviço"),0)))) -> 420000 | O78: =IF(VLOOKUP(J78,BASES!$A$13:$F$342,6,FALSE)="Recebido","Valor informado em formulário",IF(VLOOKUP(J78,BASES!$A$13:$F$342,6,FALSE)="Estimado","Estimado com base em índices históricos","Não solicitado")) -> Valor informado em formulário | P78: Lançado ERP
A79: =IF($H79="UNIDADE CONSTRUTIVA",OFFSET(A79,-1,0)+1,LARGE(A$3:A78,1)) -> 0 | B79: =IF(H79="UNIDADE CONSTRUTIVA",0,IF(H79="CÉLULA CONSTRUTIVA",OFFSET(B79,-1,0)+1,OFFSET(B79,-1,0))) -> 2 | C79: =IF(H79="CÉLULA CONSTRUTIVA",0,IF(H79="ETAPA",OFFSET(C79,-1,0)+1,OFFSET(C79,-1,0))) -> 2 | D79: =IF(H79="ETAPA",0,IF(H79="SUBETAPA",OFFSET(D79,-1,0)+1,OFFSET(D79,-1,0))) -> 1 | E79: =IF(H79="Subetapa",0,IF(H79="serviço",OFFSET(E79,-1,0)+1,OFFSET(E79,-1,0))) -> 2 | H79: SERVIÇO | I79: =IF(H79="Unidade Construtiva",TEXT(A79,"00"),IF(H79="Célula Construtiva",TEXT(B79,"00"),IF(H79="Etapa",CONCATENATE(TEXT(B79,"00"),".",TEXT(C79,"000")),IF(H79="Subetapa",CONCATENATE(TEXT(B79,"00"),".",TEXT(C79,"000"),".",TEXT(D79,"000")),IF(H79="Serviço",CONCATENATE(TEXT(B79,"00"),".",TEXT(C79,"000"),".",TEXT(D79,"000"),".",TEXT(E79,"000")),""))))) -> 02.002.001.002 | J79: Serviço de apoio | K79: =IFERROR(VLOOKUP(J79,BASES!$A$13:$E$342,3,FALSE),0) -> mês | L79: =IFERROR(VLOOKUP(J79,BASES!$A$13:$E$342,4,FALSE),0) -> 42 | M79: =IFERROR(VLOOKUP(J79,BASES!$A$13:$E$342,5,FALSE),0) -> 11619.747 | N79: =IF(H79="Serviço",M79*L79,IF(H79="CÉLULA CONSTRUTIVA",SUMIFS($N$8:$N$419,$B$8:$B$419,B79,$H$8:$H$419,"Serviço"),IF(H79="ETAPA",SUMIFS($N$8:$N$419,$B$8:$B$419,B79,$C$8:$C$419,C79,$H$8:$H$419,"Serviço"),IF(H79="SUBETAPA",SUMIFS($N$8:$N$419,$B$8:$B$419,B79,$C$8:$C$419,C79,$D$8:$D$419,D79,$H$8:$H$419,"Serviço"),0)))) -> 488029.37 | O79: =IF(VLOOKUP(J79,BASES!$A$13:$F$342,6,FALSE)="Recebido","Valor informado em formulário",IF(VLOOKUP(J79,BASES!$A$13:$F$342,6,FALSE)="Estimado","Estimado com base em índices históricos","Não solicitado")) -> Estimado com base em índices históricos | P79: Lançado ERP
A80: =IF($H80="UNIDADE CONSTRUTIVA",OFFSET(A80,-1,0)+1,LARGE(A$3:A79,1)) -> 0 | B80: =IF(H80="UNIDADE CONSTRUTIVA",0,IF(H80="CÉLULA CONSTRUTIVA",OFFSET(B80,-1,0)+1,OFFSET(B80,-1,0))) -> 2 | C80: =IF(H80="CÉLULA CONSTRUTIVA",0,IF(H80="ETAPA",OFFSET(C80,-1,0)+1,OFFSET(C80,-1,0))) -> 2 | D80: =IF(H80="ETAPA",0,IF(H80="SUBETAPA",OFFSET(D80,-1,0)+1,OFFSET(D80,-1,0))) -> 2 | E80: =IF(H80="Subetapa",0,IF(H80="serviço",OFFSET(E80,-1,0)+1,OFFSET(E80,-1,0))) -> 0 | H80: SUBETAPA | I80: =IF(H80="Unidade Construtiva",TEXT(A80,"00"),IF(H80="Célula Construtiva",TEXT(B80,"00"),IF(H80="Etapa",CONCATENATE(TEXT(B80,"00"),".",TEXT(C80,"000")),IF(H80="Subetapa",CONCATENATE(TEXT(B80,"00"),".",TEXT(C80,"000"),".",TEXT(D80,"000")),IF(H80="Serviço",CONCATENATE(TEXT(B80,"00"),".",TEXT(C80,"000"),".",TEXT(D80,"000"),".",TEXT(E80,"000")),""))))) -> 02.002.002 | J80: Despesas de Consumo e Manutenção | N80: =IF(H80="Serviço",M80*L80,IF(H80="CÉLULA CONSTRUTIVA",SUMIFS($N$8:$N$419,$B$8:$B$419,B80,$H$8:$H$419,"Serviço"),IF(H80="ETAPA",SUMIFS($N$8:$N$419,$B$8:$B$419,B80,$C$8:$C$419,C80,$H$8:$H$419,"Serviço"),IF(H80="SUBETAPA",SUMIFS($N$8:$N$419,$B$8:$B$419,B80,$C$8:$C$419,C80,$D$8:$D$419,D80,$H$8:$H$419,"Serviço"),0)))) -> 33769.855 | Q80: =N80/'Obra '!$C$32 -> 0.0070738644
A81: =IF($H81="UNIDADE CONSTRUTIVA",OFFSET(A81,-1,0)+1,LARGE(A$3:A80,1)) -> 0 | B81: =IF(H81="UNIDADE CONSTRUTIVA",0,IF(H81="CÉLULA CONSTRUTIVA",OFFSET(B81,-1,0)+1,OFFSET(B81,-1,0))) -> 2 | C81: =IF(H81="CÉLULA CONSTRUTIVA",0,IF(H81="ETAPA",OFFSET(C81,-1,0)+1,OFFSET(C81,-1,0))) -> 2 | D81: =IF(H81="ETAPA",0,IF(H81="SUBETAPA",OFFSET(D81,-1,0)+1,OFFSET(D81,-1,0))) -> 2 | E81: =IF(H81="Subetapa",0,IF(H81="serviço",OFFSET(E81,-1,0)+1,OFFSET(E81,-1,0))) -> 1 | H81: SERVIÇO | I81: =IF(H81="Unidade Construtiva",TEXT(A81,"00"),IF(H81="Célula Construtiva",TEXT(B81,"00"),IF(H81="Etapa",CONCATENATE(TEXT(B81,"00"),".",TEXT(C81,"000")),IF(H81="Subetapa",CONCATENATE(TEXT(B81,"00"),".",TEXT(C81,"000"),".",TEXT(D81,"000")),IF(H81="Serviço",CONCATENATE(TEXT(B81,"00"),".",TEXT(C81,"000"),".",TEXT(D81,"000"),".",TEXT(E81,"000")),""))))) -> 02.002.002.001 | J81: Demolições | K81: =IFERROR(VLOOKUP(J81,BASES!$A$13:$E$342,3,FALSE),0) -> VB | L81: =IFERROR(VLOOKUP(J81,BASES!$A$13:$E$342,4,FALSE),0) -> 1 | M81: =IFERROR(VLOOKUP(J81,BASES!$A$13:$E$342,5,FALSE),0) -> 31456.963 | N81: =IF(H81="Serviço",M81*L81,IF(H81="CÉLULA CONSTRUTIVA",SUMIFS($N$8:$N$419,$B$8:$B$419,B81,$H$8:$H$419,"Serviço"),IF(H81="ETAPA",SUMIFS($N$8:$N$419,$B$8:$B$419,B81,$C$8:$C$419,C81,$H$8:$H$419,"Serviço"),IF(H81="SUBETAPA",SUMIFS($N$8:$N$419,$B$8:$B$419,B81,$C$8:$C$419,C81,$D$8:$D$419,D81,$H$8:$H$419,"Serviço"),0)))) -> 31456.963 | O81: =IF(VLOOKUP(J81,BASES!$A$13:$F$342,6,FALSE)="Recebido","Valor informado em formulário",IF(VLOOKUP(J81,BASES!$A$13:$F$342,6,FALSE)="Estimado","Estimado com base em índices históricos","Não solicitado")) -> Estimado com base em índices históricos | P81: Lançado ERP
A82: =IF($H82="UNIDADE CONSTRUTIVA",OFFSET(A82,-1,0)+1,LARGE(A$3:A81,1)) -> 0 | B82: =IF(H82="UNIDADE CONSTRUTIVA",0,IF(H82="CÉLULA CONSTRUTIVA",OFFSET(B82,-1,0)+1,OFFSET(B82,-1,0))) -> 2 | C82: =IF(H82="CÉLULA CONSTRUTIVA",0,IF(H82="ETAPA",OFFSET(C82,-1,0)+1,OFFSET(C82,-1,0))) -> 2 | D82: =IF(H82="ETAPA",0,IF(H82="SUBETAPA",OFFSET(D82,-1,0)+1,OFFSET(D82,-1,0))) -> 2 | E82: =IF(H82="Subetapa",0,IF(H82="serviço",OFFSET(E82,-1,0)+1,OFFSET(E82,-1,0))) -> 2 | H82: SERVIÇO | I82: =IF(H82="Unidade Construtiva",TEXT(A82,"00"),IF(H82="Célula Construtiva",TEXT(B82,"00"),IF(H82="Etapa",CONCATENATE(TEXT(B82,"00"),".",TEXT(C82,"000")),IF(H82="Subetapa",CONCATENATE(TEXT(B82,"00"),".",TEXT(C82,"000"),".",TEXT(D82,"000")),IF(H82="Serviço",CONCATENATE(TEXT(B82,"00"),".",TEXT(C82,"000"),".",TEXT(D82,"000"),".",TEXT(E82,"000")),""))))) -> 02.002.002.002 | J82: Limpeza mecânica da camada vegetal | K82: =IFERROR(VLOOKUP(J82,BASES!$A$13:$E$342,3,FALSE),0) -> m2 | L82: =IFERROR(VLOOKUP(J82,BASES!$A$13:$E$342,4,FALSE),0) -> 1410.3 | M82: =IFERROR(VLOOKUP(J82,BASES!$A$13:$E$342,5,FALSE),0) -> 1.64 | N82: =IF(H82="Serviço",M82*L82,IF(H82="CÉLULA CONSTRUTIVA",SUMIFS($N$8:$N$419,$B$8:$B$419,B82,$H$8:$H$419,"Serviço"),IF(H82="ETAPA",SUMIFS($N$8:$N$419,$B$8:$B$419,B82,$C$8:$C$419,C82,$H$8:$H$419,"Serviço"),IF(H82="SUBETAPA",SUMIFS($N$8:$N$419,$B$8:$B$419,B82,$C$8:$C$419,C82,$D$8:$D$419,D82,$H$8:$H$419,"Serviço"),0)))) -> 2312.892 | O82: =IF(VLOOKUP(J82,BASES!$A$13:$F$342,6,FALSE)="Recebido","Valor informado em formulário",IF(VLOOKUP(J82,BASES!$A$13:$F$342,6,FALSE)="Estimado","Estimado com base em índices históricos","Não solicitado")) -> Estimado com base em índices históricos | P82: Lançado ERP
A83: =IF($H83="UNIDADE CONSTRUTIVA",OFFSET(A83,-1,0)+1,LARGE(A$3:A82,1)) -> 0 | B83: =IF(H83="UNIDADE CONSTRUTIVA",0,IF(H83="CÉLULA CONSTRUTIVA",OFFSET(B83,-1,0)+1,OFFSET(B83,-1,0))) -> 2 | C83: =IF(H83="CÉLULA CONSTRUTIVA",0,IF(H83="ETAPA",OFFSET(C83,-1,0)+1,OFFSET(C83,-1,0))) -> 2 | D83: =IF(H83="ETAPA",0,IF(H83="SUBETAPA",OFFSET(D83,-1,0)+1,OFFSET(D83,-1,0))) -> 3 | E83: =IF(H83="Subetapa",0,IF(H83="serviço",OFFSET(E83,-1,0)+1,OFFSET(E83,-1,0))) -> 0 | H83: SUBETAPA | I83: =IF(H83="Unidade Construtiva",TEXT(A83,"00"),IF(H83="Célula Construtiva",TEXT(B83,"00"),IF(H83="Etapa",CONCATENATE(TEXT(B83,"00"),".",TEXT(C83,"000")),IF(H83="Subetapa",CONCATENATE(TEXT(B83,"00"),".",TEXT(C83,"000"),".",TEXT(D83,"000")),IF(H83="Serviço",CONCATENATE(TEXT(B83,"00"),".",TEXT(C83,"000"),".",TEXT(D83,"000"),".",TEXT(E83,"000")),""))))) -> 02.002.003 | J83: Despesas de Consumo e Manutenção | N83: =IF(H83="Serviço",M83*L83,IF(H83="CÉLULA CONSTRUTIVA",SUMIFS($N$8:$N$419,$B$8:$B$419,B83,$H$8:$H$419,"Serviço"),IF(H83="ETAPA",SUMIFS($N$8:$N$419,$B$8:$B$419,B83,$C$8:$C$419,C83,$H$8:$H$419,"Serviço"),IF(H83="SUBETAPA",SUMIFS($N$8:$N$419,$B$8:$B$419,B83,$C$8:$C$419,C83,$D$8:$D$419,D83,$H$8:$H$419,"Serviço"),0)))) -> 190421.52 | Q83: =N83/'Obra '!$C$32 -> 0.039888119
A84: =IF($H84="UNIDADE CONSTRUTIVA",OFFSET(A84,-1,0)+1,LARGE(A$3:A83,1)) -> 0 | B84: =IF(H84="UNIDADE CONSTRUTIVA",0,IF(H84="CÉLULA CONSTRUTIVA",OFFSET(B84,-1,0)+1,OFFSET(B84,-1,0))) -> 2 | C84: =IF(H84="CÉLULA CONSTRUTIVA",0,IF(H84="ETAPA",OFFSET(C84,-1,0)+1,OFFSET(C84,-1,0))) -> 2 | D84: =IF(H84="ETAPA",0,IF(H84="SUBETAPA",OFFSET(D84,-1,0)+1,OFFSET(D84,-1,0))) -> 3 | E84: =IF(H84="Subetapa",0,IF(H84="serviço",OFFSET(E84,-1,0)+1,OFFSET(E84,-1,0))) -> 1 | H84: SERVIÇO | I84: =IF(H84="Unidade Construtiva",TEXT(A84,"00"),IF(H84="Célula Construtiva",TEXT(B84,"00"),IF(H84="Etapa",CONCATENATE(TEXT(B84,"00"),".",TEXT(C84,"000")),IF(H84="Subetapa",CONCATENATE(TEXT(B84,"00"),".",TEXT(C84,"000"),".",TEXT(D84,"000")),IF(H84="Serviço",CONCATENATE(TEXT(B84,"00"),".",TEXT(C84,"000"),".",TEXT(D84,"000"),".",TEXT(E84,"000")),""))))) -> 02.002.003.001 | J84: Consumo de água e esgoto | K84: =IFERROR(VLOOKUP(J84,BASES!$A$13:$E$342,3,FALSE),0) -> mês | L84: =IFERROR(VLOOKUP(J84,BASES!$A$13:$E$342,4,FALSE),0) -> 42 | M84: =IFERROR(VLOOKUP(J84,BASES!$A$13:$E$342,5,FALSE),0) -> 500 | N84: =IF(H84="Serviço",M84*L84,IF(H84="CÉLULA CONSTRUTIVA",SUMIFS($N$8:$N$419,$B$8:$B$419,B84,$H$8:$H$419,"Serviço"),IF(H84="ETAPA",SUMIFS($N$8:$N$419,$B$8:$B$419,B84,$C$8:$C$419,C84,$H$8:$H$419,"Serviço"),IF(H84="SUBETAPA",SUMIFS($N$8:$N$419,$B$8:$B$419,B84,$C$8:$C$419,C84,$D$8:$D$419,D84,$H$8:$H$419,"Serviço"),0)))) -> 21000 | O84: =IF(VLOOKUP(J84,BASES!$A$13:$F$342,6,FALSE)="Recebido","Valor informado em formulário",IF(VLOOKUP(J84,BASES!$A$13:$F$342,6,FALSE)="Estimado","Estimado com base em índices históricos","Não solicitado")) -> Estimado com base em índices históricos | P84: Lançado ERP
A85: =IF($H85="UNIDADE CONSTRUTIVA",OFFSET(A85,-1,0)+1,LARGE(A$3:A84,1)) -> 0 | B85: =IF(H85="UNIDADE CONSTRUTIVA",0,IF(H85="CÉLULA CONSTRUTIVA",OFFSET(B85,-1,0)+1,OFFSET(B85,-1,0))) -> 2 | C85: =IF(H85="CÉLULA CONSTRUTIVA",0,IF(H85="ETAPA",OFFSET(C85,-1,0)+1,OFFSET(C85,-1,0))) -> 2 | D85: =IF(H85="ETAPA",0,IF(H85="SUBETAPA",OFFSET(D85,-1,0)+1,OFFSET(D85,-1,0))) -> 3 | E85: =IF(H85="Subetapa",0,IF(H85="serviço",OFFSET(E85,-1,0)+1,OFFSET(E85,-1,0))) -> 2 | H85: SERVIÇO | I85: =IF(H85="Unidade Construtiva",TEXT(A85,"00"),IF(H85="Célula Construtiva",TEXT(B85,"00"),IF(H85="Etapa",CONCATENATE(TEXT(B85,"00"),".",TEXT(C85,"000")),IF(H85="Subetapa",CONCATENATE(TEXT(B85,"00"),".",TEXT(C85,"000"),".",TEXT(D85,"000")),IF(H85="Serviço",CONCATENATE(TEXT(B85,"00"),".",TEXT(C85,"000"),".",TEXT(D85,"000"),".",TEXT(E85,"000")),""))))) -> 02.002.003.002 | J85: Consumo de luz/energia | K85: =IFERROR(VLOOKUP(J85,BASES!$A$13:$E$342,3,FALSE),0) -> mês | L85: =IFERROR(VLOOKUP(J85,BASES!$A$13:$E$342,4,FALSE),0) -> 42 | M85: =IFERROR(VLOOKUP(J85,BASES!$A$13:$E$342,5,FALSE),0) -> 500 | N85: =IF(H85="Serviço",M85*L85,IF(H85="CÉLULA CONSTRUTIVA",SUMIFS($N$8:$N$419,$B$8:$B$419,B85,$H$8:$H$419,"Serviço"),IF(H85="ETAPA",SUMIFS($N$8:$N$419,$B$8:$B$419,B85,$C$8:$C$419,C85,$H$8:$H$419,"Serviço"),IF(H85="SUBETAPA",SUMIFS($N$8:$N$419,$B$8:$B$419,B85,$C$8:$C$419,C85,$D$8:$D$419,D85,$H$8:$H$419,"Serviço"),0)))) -> 21000 | O85: =IF(VLOOKUP(J85,BASES!$A$13:$F$342,6,FALSE)="Recebido","Valor informado em formulário",IF(VLOOKUP(J85,BASES!$A$13:$F$342,6,FALSE)="Estimado","Estimado com base em índices históricos","Não solicitado")) -> Estimado com base em índices históricos | P85: Lançado ERP
A86: =IF($H86="UNIDADE CONSTRUTIVA",OFFSET(A86,-1,0)+1,LARGE(A$3:A85,1)) -> 0 | B86: =IF(H86="UNIDADE CONSTRUTIVA",0,IF(H86="CÉLULA CONSTRUTIVA",OFFSET(B86,-1,0)+1,OFFSET(B86,-1,0))) -> 2 | C86: =IF(H86="CÉLULA CONSTRUTIVA",0,IF(H86="ETAPA",OFFSET(C86,-1,0)+1,OFFSET(C86,-1,0))) -> 2 | D86: =IF(H86="ETAPA",0,IF(H86="SUBETAPA",OFFSET(D86,-1,0)+1,OFFSET(D86,-1,0))) -> 3 | E86: =IF(H86="Subetapa",0,IF(H86="serviço",OFFSET(E86,-1,0)+1,OFFSET(E86,-1,0))) -> 3 | H86: SERVIÇO | I86: =IF(H86="Unidade Construtiva",TEXT(A86,"00"),IF(H86="Célula Construtiva",TEXT(B86,"00"),IF(H86="Etapa",CONCATENATE(TEXT(B86,"00"),".",TEXT(C86,"000")),IF(H86="Subetapa",CONCATENATE(TEXT(B86,"00"),".",TEXT(C86,"000"),".",TEXT(D86,"000")),IF(H86="Serviço",CONCATENATE(TEXT(B86,"00"),".",TEXT(C86,"000"),".",TEXT(D86,"000"),".",TEXT(E86,"000")),""))))) -> 02.002.003.003 | J86: Consumo internet | K86: =IFERROR(VLOOKUP(J86,BASES!$A$13:$E$342,3,FALSE),0) -> mês | L86: =IFERROR(VLOOKUP(J86,BASES!$A$13:$E$342,4,FALSE),0) -> 42 | M86: =IFERROR(VLOOKUP(J86,BASES!$A$13:$E$342,5,FALSE),0) -> 150 | N86: =IF(H86="Serviço",M86*L86,IF(H86="CÉLULA CONSTRUTIVA",SUMIFS($N$8:$N$419,$B$8:$B$419,B86,$H$8:$H$419,"Serviço"),IF(H86="ETAPA",SUMIFS($N$8:$N$419,$B$8:$B$419,B86,$C$8:$C$419,C86,$H$8:$H$419,"Serviço"),IF(H86="SUBETAPA",SUMIFS($N$8:$N$419,$B$8:$B$419,B86,$C$8:$C$419,C86,$D$8:$D$419,D86,$H$8:$H$419,"Serviço"),0)))) -> 6300 | O86: =IF(VLOOKUP(J86,BASES!$A$13:$F$342,6,FALSE)="Recebido","Valor informado em formulário",IF(VLOOKUP(J86,BASES!$A$13:$F$342,6,FALSE)="Estimado","Estimado com base em índices históricos","Não solicitado")) -> Estimado com base em índices históricos | P86: Lançado ERP
A87: =IF($H87="UNIDADE CONSTRUTIVA",OFFSET(A87,-1,0)+1,LARGE(A$3:A86,1)) -> 0 | B87: =IF(H87="UNIDADE CONSTRUTIVA",0,IF(H87="CÉLULA CONSTRUTIVA",OFFSET(B87,-1,0)+1,OFFSET(B87,-1,0))) -> 2 | C87: =IF(H87="CÉLULA CONSTRUTIVA",0,IF(H87="ETAPA",OFFSET(C87,-1,0)+1,OFFSET(C87,-1,0))) -> 2 | D87: =IF(H87="ETAPA",0,IF(H87="SUBETAPA",OFFSET(D87,-1,0)+1,OFFSET(D87,-1,0))) -> 3 | E87: =IF(H87="Subetapa",0,IF(H87="serviço",OFFSET(E87,-1,0)+1,OFFSET(E87,-1,0))) -> 4 | H87: SERVIÇO | I87: =IF(H87="Unidade Construtiva",TEXT(A87,"00"),IF(H87="Célula Construtiva",TEXT(B87,"00"),IF(H87="Etapa",CONCATENATE(TEXT(B87,"00"),".",TEXT(C87,"000")),IF(H87="Subetapa",CONCATENATE(TEXT(B87,"00"),".",TEXT(C87,"000"),".",TEXT(D87,"000")),IF(H87="Serviço",CONCATENATE(TEXT(B87,"00"),".",TEXT(C87,"000"),".",TEXT(D87,"000"),".",TEXT(E87,"000")),""))))) -> 02.002.003.004 | J87: Coleta de lixo | K87: =IFERROR(VLOOKUP(J87,BASES!$A$13:$E$342,3,FALSE),0) -> mês | L87: =IFERROR(VLOOKUP(J87,BASES!$A$13:$E$342,4,FALSE),0) -> 42 | M87: =IFERROR(VLOOKUP(J87,BASES!$A$13:$E$342,5,FALSE),0) -> 80 | N87: =IF(H87="Serviço",M87*L87,IF(H87="CÉLULA CONSTRUTIVA",SUMIFS($N$8:$N$419,$B$8:$B$419,B87,$H$8:$H$419,"Serviço"),IF(H87="ETAPA",SUMIFS($N$8:$N$419,$B$8:$B$419,B87,$C$8:$C$419,C87,$H$8:$H$419,"Serviço"),IF(H87="SUBETAPA",SUMIFS($N$8:$N$419,$B$8:$B$419,B87,$C$8:$C$419,C87,$D$8:$D$419,D87,$H$8:$H$419,"Serviço"),0)))) -> 3360 | O87: =IF(VLOOKUP(J87,BASES!$A$13:$F$342,6,FALSE)="Recebido","Valor informado em formulário",IF(VLOOKUP(J87,BASES!$A$13:$F$342,6,FALSE)="Estimado","Estimado com base em índices históricos","Não solicitado")) -> Estimado com base em índices históricos | P87: Lançado ERP
A88: =IF($H88="UNIDADE CONSTRUTIVA",OFFSET(A88,-1,0)+1,LARGE(A$3:A87,1)) -> 0 | B88: =IF(H88="UNIDADE CONSTRUTIVA",0,IF(H88="CÉLULA CONSTRUTIVA",OFFSET(B88,-1,0)+1,OFFSET(B88,-1,0))) -> 2 | C88: =IF(H88="CÉLULA CONSTRUTIVA",0,IF(H88="ETAPA",OFFSET(C88,-1,0)+1,OFFSET(C88,-1,0))) -> 2 | D88: =IF(H88="ETAPA",0,IF(H88="SUBETAPA",OFFSET(D88,-1,0)+1,OFFSET(D88,-1,0))) -> 3 | E88: =IF(H88="Subetapa",0,IF(H88="serviço",OFFSET(E88,-1,0)+1,OFFSET(E88,-1,0))) -> 5 | H88: SERVIÇO | I88: =IF(H88="Unidade Construtiva",TEXT(A88,"00"),IF(H88="Célula Construtiva",TEXT(B88,"00"),IF(H88="Etapa",CONCATENATE(TEXT(B88,"00"),".",TEXT(C88,"000")),IF(H88="Subetapa",CONCATENATE(TEXT(B88,"00"),".",TEXT(C88,"000"),".",TEXT(D88,"000")),IF(H88="Serviço",CONCATENATE(TEXT(B88,"00"),".",TEXT(C88,"000"),".",TEXT(D88,"000"),".",TEXT(E88,"000")),""))))) -> 02.002.003.005 | J88: Consumo de material de expediente/escritório | K88: =IFERROR(VLOOKUP(J88,BASES!$A$13:$E$342,3,FALSE),0) -> mês | L88: =IFERROR(VLOOKUP(J88,BASES!$A$13:$E$342,4,FALSE),0) -> 42 | M88: =IFERROR(VLOOKUP(J88,BASES!$A$13:$E$342,5,FALSE),0) -> 200 | N88: =IF(H88="Serviço",M88*L88,IF(H88="CÉLULA CONSTRUTIVA",SUMIFS($N$8:$N$419,$B$8:$B$419,B88,$H$8:$H$419,"Serviço"),IF(H88="ETAPA",SUMIFS($N$8:$N$419,$B$8:$B$419,B88,$C$8:$C$419,C88,$H$8:$H$419,"Serviço"),IF(H88="SUBETAPA",SUMIFS($N$8:$N$419,$B$8:$B$419,B88,$C$8:$C$419,C88,$D$8:$D$419,D88,$H$8:$H$419,"Serviço"),0)))) -> 8400 | O88: =IF(VLOOKUP(J88,BASES!$A$13:$F$342,6,FALSE)="Recebido","Valor informado em formulário",IF(VLOOKUP(J88,BASES!$A$13:$F$342,6,FALSE)="Estimado","Estimado com base em índices históricos","Não solicitado")) -> Estimado com base em índices históricos | P88: Lançado ERP
A89: =IF($H89="UNIDADE CONSTRUTIVA",OFFSET(A89,-1,0)+1,LARGE(A$3:A88,1)) -> 0 | B89: =IF(H89="UNIDADE CONSTRUTIVA",0,IF(H89="CÉLULA CONSTRUTIVA",OFFSET(B89,-1,0)+1,OFFSET(B89,-1,0))) -> 2 | C89: =IF(H89="CÉLULA CONSTRUTIVA",0,IF(H89="ETAPA",OFFSET(C89,-1,0)+1,OFFSET(C89,-1,0))) -> 2 | D89: =IF(H89="ETAPA",0,IF(H89="SUBETAPA",OFFSET(D89,-1,0)+1,OFFSET(D89,-1,0))) -> 3 | E89: =IF(H89="Subetapa",0,IF(H89="serviço",OFFSET(E89,-1,0)+1,OFFSET(E89,-1,0))) -> 6 | H89: SERVIÇO | I89: =IF(H89="Unidade Construtiva",TEXT(A89,"00"),IF(H89="Célula Construtiva",TEXT(B89,"00"),IF(H89="Etapa",CONCATENATE(TEXT(B89,"00"),".",TEXT(C89,"000")),IF(H89="Subetapa",CONCATENATE(TEXT(B89,"00"),".",TEXT(C89,"000"),".",TEXT(D89,"000")),IF(H89="Serviço",CONCATENATE(TEXT(B89,"00"),".",TEXT(C89,"000"),".",TEXT(D89,"000"),".",TEXT(E89,"000")),""))))) -> 02.002.003.006 | J89: Consumo de material de higiene e limpeza | K89: =IFERROR(VLOOKUP(J89,BASES!$A$13:$E$342,3,FALSE),0) -> mês | L89: =IFERROR(VLOOKUP(J89,BASES!$A$13:$E$342,4,FALSE),0) -> 42 | M89: =IFERROR(VLOOKUP(J89,BASES!$A$13:$E$342,5,FALSE),0) -> 500 | N89: =IF(H89="Serviço",M89*L89,IF(H89="CÉLULA CONSTRUTIVA",SUMIFS($N$8:$N$419,$B$8:$B$419,B89,$H$8:$H$419,"Serviço"),IF(H89="ETAPA",SUMIFS($N$8:$N$419,$B$8:$B$419,B89,$C$8:$C$419,C89,$H$8:$H$419,"Serviço"),IF(H89="SUBETAPA",SUMIFS($N$8:$N$419,$B$8:$B$419,B89,$C$8:$C$419,C89,$D$8:$D$419,D89,$H$8:$H$419,"Serviço"),0)))) -> 21000 | O89: =IF(VLOOKUP(J89,BASES!$A$13:$F$342,6,FALSE)="Recebido","Valor informado em formulário",IF(VLOOKUP(J89,BASES!$A$13:$F$342,6,FALSE)="Estimado","Estimado com base em índices históricos","Não solicitado")) -> Estimado com base em índices históricos | P89: Lançado ERP
A90: =IF($H90="UNIDADE CONSTRUTIVA",OFFSET(A90,-1,0)+1,LARGE(A$3:A89,1)) -> 0 | B90: =IF(H90="UNIDADE CONSTRUTIVA",0,IF(H90="CÉLULA CONSTRUTIVA",OFFSET(B90,-1,0)+1,OFFSET(B90,-1,0))) -> 2 | C90: =IF(H90="CÉLULA CONSTRUTIVA",0,IF(H90="ETAPA",OFFSET(C90,-1,0)+1,OFFSET(C90,-1,0))) -> 2 | D90: =IF(H90="ETAPA",0,IF(H90="SUBETAPA",OFFSET(D90,-1,0)+1,OFFSET(D90,-1,0))) -> 3 | E90: =IF(H90="Subetapa",0,IF(H90="serviço",OFFSET(E90,-1,0)+1,OFFSET(E90,-1,0))) -> 7 | H90: SERVIÇO | I90: =IF(H90="Unidade Construtiva",TEXT(A90,"00"),IF(H90="Célula Construtiva",TEXT(B90,"00"),IF(H90="Etapa",CONCATENATE(TEXT(B90,"00"),".",TEXT(C90,"000")),IF(H90="Subetapa",CONCATENATE(TEXT(B90,"00"),".",TEXT(C90,"000"),".",TEXT(D90,"000")),IF(H90="Serviço",CONCATENATE(TEXT(B90,"00"),".",TEXT(C90,"000"),".",TEXT(D90,"000"),".",TEXT(E90,"000")),""))))) -> 02.002.003.007 | J90: Consumo de cópias | K90: =IFERROR(VLOOKUP(J90,BASES!$A$13:$E$342,3,FALSE),0) -> mês | L90: =IFERROR(VLOOKUP(J90,BASES!$A$13:$E$342,4,FALSE),0) -> 42 | M90: =IFERROR(VLOOKUP(J90,BASES!$A$13:$E$342,5,FALSE),0) -> 1362.4024 | N90: =IF(H90="Serviço",M90*L90,IF(H90="CÉLULA CONSTRUTIVA",SUMIFS($N$8:$N$419,$B$8:$B$419,B90,$H$8:$H$419,"Serviço"),IF(H90="ETAPA",SUMIFS($N$8:$N$419,$B$8:$B$419,B90,$C$8:$C$419,C90,$H$8:$H$419,"Serviço"),IF(H90="SUBETAPA",SUMIFS($N$8:$N$419,$B$8:$B$419,B90,$C$8:$C$419,C90,$D$8:$D$419,D90,$H$8:$H$419,"Serviço"),0)))) -> 57220.901 | O90: =IF(VLOOKUP(J90,BASES!$A$13:$F$342,6,FALSE)="Recebido","Valor informado em formulário",IF(VLOOKUP(J90,BASES!$A$13:$F$342,6,FALSE)="Estimado","Estimado com base em índices históricos","Não solicitado")) -> Estimado com base em índices históricos | P90: Lançado ERP
A91: =IF($H91="UNIDADE CONSTRUTIVA",OFFSET(A91,-1,0)+1,LARGE(A$3:A90,1)) -> 0 | B91: =IF(H91="UNIDADE CONSTRUTIVA",0,IF(H91="CÉLULA CONSTRUTIVA",OFFSET(B91,-1,0)+1,OFFSET(B91,-1,0))) -> 2 | C91: =IF(H91="CÉLULA CONSTRUTIVA",0,IF(H91="ETAPA",OFFSET(C91,-1,0)+1,OFFSET(C91,-1,0))) -> 2 | D91: =IF(H91="ETAPA",0,IF(H91="SUBETAPA",OFFSET(D91,-1,0)+1,OFFSET(D91,-1,0))) -> 3 | E91: =IF(H91="Subetapa",0,IF(H91="serviço",OFFSET(E91,-1,0)+1,OFFSET(E91,-1,0))) -> 8 | H91: SERVIÇO | I91: =IF(H91="Unidade Construtiva",TEXT(A91,"00"),IF(H91="Célula Construtiva",TEXT(B91,"00"),IF(H91="Etapa",CONCATENATE(TEXT(B91,"00"),".",TEXT(C91,"000")),IF(H91="Subetapa",CONCATENATE(TEXT(B91,"00"),".",TEXT(C91,"000"),".",TEXT(D91,"000")),IF(H91="Serviço",CONCATENATE(TEXT(B91,"00"),".",TEXT(C91,"000"),".",TEXT(D91,"000"),".",TEXT(E91,"000")),""))))) -> 02.002.003.008 | J91: Despesas com vizinhos | K91: =IFERROR(VLOOKUP(J91,BASES!$A$13:$E$342,3,FALSE),0) -> vb | L91: =IFERROR(VLOOKUP(J91,BASES!$A$13:$E$342,4,FALSE),0) -> 1 | M91: =IFERROR(VLOOKUP(J91,BASES!$A$13:$E$342,5,FALSE),0) -> 15600.618 | N91: =IF(H91="Serviço",M91*L91,IF(H91="CÉLULA CONSTRUTIVA",SUMIFS($N$8:$N$419,$B$8:$B$419,B91,$H$8:$H$419,"Serviço"),IF(H91="ETAPA",SUMIFS($N$8:$N$419,$B$8:$B$419,B91,$C$8:$C$419,C91,$H$8:$H$419,"Serviço"),IF(H91="SUBETAPA",SUMIFS($N$8:$N$419,$B$8:$B$419,B91,$C$8:$C$419,C91,$D$8:$D$419,D91,$H$8:$H$419,"Serviço"),0)))) -> 15600.618 | O91: =IF(VLOOKUP(J91,BASES!$A$13:$F$342,6,FALSE)="Recebido","Valor informado em formulário",IF(VLOOKUP(J91,BASES!$A$13:$F$342,6,FALSE)="Estimado","Estimado com base em índices históricos","Não solicitado")) -> Estimado com base em índices históricos | P91: Lançado ERP
A92: =IF($H92="UNIDADE CONSTRUTIVA",OFFSET(A92,-1,0)+1,LARGE(A$3:A91,1)) -> 0 | B92: =IF(H92="UNIDADE CONSTRUTIVA",0,IF(H92="CÉLULA CONSTRUTIVA",OFFSET(B92,-1,0)+1,OFFSET(B92,-1,0))) -> 2 | C92: =IF(H92="CÉLULA CONSTRUTIVA",0,IF(H92="ETAPA",OFFSET(C92,-1,0)+1,OFFSET(C92,-1,0))) -> 2 | D92: =IF(H92="ETAPA",0,IF(H92="SUBETAPA",OFFSET(D92,-1,0)+1,OFFSET(D92,-1,0))) -> 3 | E92: =IF(H92="Subetapa",0,IF(H92="serviço",OFFSET(E92,-1,0)+1,OFFSET(E92,-1,0))) -> 9 | H92: SERVIÇO | I92: =IF(H92="Unidade Construtiva",TEXT(A92,"00"),IF(H92="Célula Construtiva",TEXT(B92,"00"),IF(H92="Etapa",CONCATENATE(TEXT(B92,"00"),".",TEXT(C92,"000")),IF(H92="Subetapa",CONCATENATE(TEXT(B92,"00"),".",TEXT(C92,"000"),".",TEXT(D92,"000")),IF(H92="Serviço",CONCATENATE(TEXT(B92,"00"),".",TEXT(C92,"000"),".",TEXT(D92,"000"),".",TEXT(E92,"000")),""))))) -> 02.002.003.009 | J92: Manutenção provisória do canteiro | K92: =IFERROR(VLOOKUP(J92,BASES!$A$13:$E$342,3,FALSE),0) -> mês | L92: =IFERROR(VLOOKUP(J92,BASES!$A$13:$E$342,4,FALSE),0) -> 42 | M92: =IFERROR(VLOOKUP(J92,BASES!$A$13:$E$342,5,FALSE),0) -> 350 | N92: =IF(H92="Serviço",M92*L92,IF(H92="CÉLULA CONSTRUTIVA",SUMIFS($N$8:$N$419,$B$8:$B$419,B92,$H$8:$H$419,"Serviço"),IF(H92="ETAPA",SUMIFS($N$8:$N$419,$B$8:$B$419,B92,$C$8:$C$419,C92,$H$8:$H$419,"Serviço"),IF(H92="SUBETAPA",SUMIFS($N$8:$N$419,$B$8:$B$419,B92,$C$8:$C$419,C92,$D$8:$D$419,D92,$H$8:$H$419,"Serviço"),0)))) -> 14700 | O92: =IF(VLOOKUP(J92,BASES!$A$13:$F$342,6,FALSE)="Recebido","Valor informado em formulário",IF(VLOOKUP(J92,BASES!$A$13:$F$342,6,FALSE)="Estimado","Estimado com base em índices históricos","Não solicitado")) -> Estimado com base em índices históricos | P92: Lançado ERP
A93: =IF($H93="UNIDADE CONSTRUTIVA",OFFSET(A93,-1,0)+1,LARGE(A$3:A92,1)) -> 0 | B93: =IF(H93="UNIDADE CONSTRUTIVA",0,IF(H93="CÉLULA CONSTRUTIVA",OFFSET(B93,-1,0)+1,OFFSET(B93,-1,0))) -> 2 | C93: =IF(H93="CÉLULA CONSTRUTIVA",0,IF(H93="ETAPA",OFFSET(C93,-1,0)+1,OFFSET(C93,-1,0))) -> 2 | D93: =IF(H93="ETAPA",0,IF(H93="SUBETAPA",OFFSET(D93,-1,0)+1,OFFSET(D93,-1,0))) -> 3 | E93: =IF(H93="Subetapa",0,IF(H93="serviço",OFFSET(E93,-1,0)+1,OFFSET(E93,-1,0))) -> 10 | H93: SERVIÇO | I93: =IF(H93="Unidade Construtiva",TEXT(A93,"00"),IF(H93="Célula Construtiva",TEXT(B93,"00"),IF(H93="Etapa",CONCATENATE(TEXT(B93,"00"),".",TEXT(C93,"000")),IF(H93="Subetapa",CONCATENATE(TEXT(B93,"00"),".",TEXT(C93,"000"),".",TEXT(D93,"000")),IF(H93="Serviço",CONCATENATE(TEXT(B93,"00"),".",TEXT(C93,"000"),".",TEXT(D93,"000"),".",TEXT(E93,"000")),""))))) -> 02.002.003.010 | J93: Manutenção provisória elétrica | K93: =IFERROR(VLOOKUP(J93,BASES!$A$13:$E$342,3,FALSE),0) -> mês | L93: =IFERROR(VLOOKUP(J93,BASES!$A$13:$E$342,4,FALSE),0) -> 42 | M93: =IFERROR(VLOOKUP(J93,BASES!$A$13:$E$342,5,FALSE),0) -> 250 | N93: =IF(H93="Serviço",M93*L93,IF(H93="CÉLULA CONSTRUTIVA",SUMIFS($N$8:$N$419,$B$8:$B$419,B93,$H$8:$H$419,"Serviço"),IF(H93="ETAPA",SUMIFS($N$8:$N$419,$B$8:$B$419,B93,$C$8:$C$419,C93,$H$8:$H$419,"Serviço"),IF(H93="SUBETAPA",SUMIFS($N$8:$N$419,$B$8:$B$419,B93,$C$8:$C$419,C93,$D$8:$D$419,D93,$H$8:$H$419,"Serviço"),0)))) -> 10500 | O93: =IF(VLOOKUP(J93,BASES!$A$13:$F$342,6,FALSE)="Recebido","Valor informado em formulário",IF(VLOOKUP(J93,BASES!$A$13:$F$342,6,FALSE)="Estimado","Estimado com base em índices históricos","Não solicitado")) -> Estimado com base em índices históricos | P93: Lançado ERP
A94: =IF($H94="UNIDADE CONSTRUTIVA",OFFSET(A94,-1,0)+1,LARGE(A$3:A93,1)) -> 0 | B94: =IF(H94="UNIDADE CONSTRUTIVA",0,IF(H94="CÉLULA CONSTRUTIVA",OFFSET(B94,-1,0)+1,OFFSET(B94,-1,0))) -> 2 | C94: =IF(H94="CÉLULA CONSTRUTIVA",0,IF(H94="ETAPA",OFFSET(C94,-1,0)+1,OFFSET(C94,-1,0))) -> 2 | D94: =IF(H94="ETAPA",0,IF(H94="SUBETAPA",OFFSET(D94,-1,0)+1,OFFSET(D94,-1,0))) -> 3 | E94: =IF(H94="Subetapa",0,IF(H94="serviço",OFFSET(E94,-1,0)+1,OFFSET(E94,-1,0))) -> 11 | H94: SERVIÇO | I94: =IF(H94="Unidade Construtiva",TEXT(A94,"00"),IF(H94="Célula Construtiva",TEXT(B94,"00"),IF(H94="Etapa",CONCATENATE(TEXT(B94,"00"),".",TEXT(C94,"000")),IF(H94="Subetapa",CONCATENATE(TEXT(B94,"00"),".",TEXT(C94,"000"),".",TEXT(D94,"000")),IF(H94="Serviço",CONCATENATE(TEXT(B94,"00"),".",TEXT(C94,"000"),".",TEXT(D94,"000"),".",TEXT(E94,"000")),""))))) -> 02.002.003.011 | J94: Manutenção provisória hidrossanitária | K94: =IFERROR(VLOOKUP(J94,BASES!$A$13:$E$342,3,FALSE),0) -> mês | L94: =IFERROR(VLOOKUP(J94,BASES!$A$13:$E$342,4,FALSE),0) -> 42 | M94: =IFERROR(VLOOKUP(J94,BASES!$A$13:$E$342,5,FALSE),0) -> 120 | N94: =IF(H94="Serviço",M94*L94,IF(H94="CÉLULA CONSTRUTIVA",SUMIFS($N$8:$N$419,$B$8:$B$419,B94,$H$8:$H$419,"Serviço"),IF(H94="ETAPA",SUMIFS($N$8:$N$419,$B$8:$B$419,B94,$C$8:$C$419,C94,$H$8:$H$419,"Serviço"),IF(H94="SUBETAPA",SUMIFS($N$8:$N$419,$B$8:$B$419,B94,$C$8:$C$419,C94,$D$8:$D$419,D94,$H$8:$H$419,"Serviço"),0)))) -> 5040 | O94: =IF(VLOOKUP(J94,BASES!$A$13:$F$342,6,FALSE)="Recebido","Valor informado em formulário",IF(VLOOKUP(J94,BASES!$A$13:$F$342,6,FALSE)="Estimado","Estimado com base em índices históricos","Não solicitado")) -> Estimado com base em índices históricos | P94: Lançado ERP
A95: =IF($H95="UNIDADE CONSTRUTIVA",OFFSET(A95,-1,0)+1,LARGE(A$3:A94,1)) -> 0 | B95: =IF(H95="UNIDADE CONSTRUTIVA",0,IF(H95="CÉLULA CONSTRUTIVA",OFFSET(B95,-1,0)+1,OFFSET(B95,-1,0))) -> 2 | C95: =IF(H95="CÉLULA CONSTRUTIVA",0,IF(H95="ETAPA",OFFSET(C95,-1,0)+1,OFFSET(C95,-1,0))) -> 2 | D95: =IF(H95="ETAPA",0,IF(H95="SUBETAPA",OFFSET(D95,-1,0)+1,OFFSET(D95,-1,0))) -> 3 | E95: =IF(H95="Subetapa",0,IF(H95="serviço",OFFSET(E95,-1,0)+1,OFFSET(E95,-1,0))) -> 12 | H95: SERVIÇO | I95: =IF(H95="Unidade Construtiva",TEXT(A95,"00"),IF(H95="Célula Construtiva",TEXT(B95,"00"),IF(H95="Etapa",CONCATENATE(TEXT(B95,"00"),".",TEXT(C95,"000")),IF(H95="Subetapa",CONCATENATE(TEXT(B95,"00"),".",TEXT(C95,"000"),".",TEXT(D95,"000")),IF(H95="Serviço",CONCATENATE(TEXT(B95,"00"),".",TEXT(C95,"000"),".",TEXT(D95,"000"),".",TEXT(E95,"000")),""))))) -> 02.002.003.012 | J95: Manutenção provisória vigilância e acessos | K95: =IFERROR(VLOOKUP(J95,BASES!$A$13:$E$342,3,FALSE),0) -> mês | L95: =IFERROR(VLOOKUP(J95,BASES!$A$13:$E$342,4,FALSE),0) -> 42 | M95: =IFERROR(VLOOKUP(J95,BASES!$A$13:$E$342,5,FALSE),0) -> 150 | N95: =IF(H95="Serviço",M95*L95,IF(H95="CÉLULA CONSTRUTIVA",SUMIFS($N$8:$N$419,$B$8:$B$419,B95,$H$8:$H$419,"Serviço"),IF(H95="ETAPA",SUMIFS($N$8:$N$419,$B$8:$B$419,B95,$C$8:$C$419,C95,$H$8:$H$419,"Serviço"),IF(H95="SUBETAPA",SUMIFS($N$8:$N$419,$B$8:$B$419,B95,$C$8:$C$419,C95,$D$8:$D$419,D95,$H$8:$H$419,"Serviço"),0)))) -> 6300 | O95: =IF(VLOOKUP(J95,BASES!$A$13:$F$342,6,FALSE)="Recebido","Valor informado em formulário",IF(VLOOKUP(J95,BASES!$A$13:$F$342,6,FALSE)="Estimado","Estimado com base em índices históricos","Não solicitado")) -> Estimado com base em índices históricos | P95: Lançado ERP
A96: =IF($H96="UNIDADE CONSTRUTIVA",OFFSET(A96,-1,0)+1,LARGE(A$3:A95,1)) -> 0 | B96: =IF(H96="UNIDADE CONSTRUTIVA",0,IF(H96="CÉLULA CONSTRUTIVA",OFFSET(B96,-1,0)+1,OFFSET(B96,-1,0))) -> 2 | C96: =IF(H96="CÉLULA CONSTRUTIVA",0,IF(H96="ETAPA",OFFSET(C96,-1,0)+1,OFFSET(C96,-1,0))) -> 2 | D96: =IF(H96="ETAPA",0,IF(H96="SUBETAPA",OFFSET(D96,-1,0)+1,OFFSET(D96,-1,0))) -> 4 | E96: =IF(H96="Subetapa",0,IF(H96="serviço",OFFSET(E96,-1,0)+1,OFFSET(E96,-1,0))) -> 0 | H96: SUBETAPA | I96: =IF(H96="Unidade Construtiva",TEXT(A96,"00"),IF(H96="Célula Construtiva",TEXT(B96,"00"),IF(H96="Etapa",CONCATENATE(TEXT(B96,"00"),".",TEXT(C96,"000")),IF(H96="Subetapa",CONCATENATE(TEXT(B96,"00"),".",TEXT(C96,"000"),".",TEXT(D96,"000")),IF(H96="Serviço",CONCATENATE(TEXT(B96,"00"),".",TEXT(C96,"000"),".",TEXT(D96,"000"),".",TEXT(E96,"000")),""))))) -> 02.002.004 | J96: Instalações Provisórias de Canteiro de Obra | N96: =IF(H96="Serviço",M96*L96,IF(H96="CÉLULA CONSTRUTIVA",SUMIFS($N$8:$N$419,$B$8:$B$419,B96,$H$8:$H$419,"Serviço"),IF(H96="ETAPA",SUMIFS($N$8:$N$419,$B$8:$B$419,B96,$C$8:$C$419,C96,$H$8:$H$419,"Serviço"),IF(H96="SUBETAPA",SUMIFS($N$8:$N$419,$B$8:$B$419,B96,$C$8:$C$419,C96,$D$8:$D$419,D96,$H$8:$H$419,"Serviço"),0)))) -> 84929.091 | Q96: =N96/'Obra '!$C$32 -> 0.01779033
A97: =IF($H97="UNIDADE CONSTRUTIVA",OFFSET(A97,-1,0)+1,LARGE(A$3:A96,1)) -> 0 | B97: =IF(H97="UNIDADE CONSTRUTIVA",0,IF(H97="CÉLULA CONSTRUTIVA",OFFSET(B97,-1,0)+1,OFFSET(B97,-1,0))) -> 2 | C97: =IF(H97="CÉLULA CONSTRUTIVA",0,IF(H97="ETAPA",OFFSET(C97,-1,0)+1,OFFSET(C97,-1,0))) -> 2 | D97: =IF(H97="ETAPA",0,IF(H97="SUBETAPA",OFFSET(D97,-1,0)+1,OFFSET(D97,-1,0))) -> 4 | E97: =IF(H97="Subetapa",0,IF(H97="serviço",OFFSET(E97,-1,0)+1,OFFSET(E97,-1,0))) -> 1 | H97: SERVIÇO | I97: =IF(H97="Unidade Construtiva",TEXT(A97,"00"),IF(H97="Célula Construtiva",TEXT(B97,"00"),IF(H97="Etapa",CONCATENATE(TEXT(B97,"00"),".",TEXT(C97,"000")),IF(H97="Subetapa",CONCATENATE(TEXT(B97,"00"),".",TEXT(C97,"000"),".",TEXT(D97,"000")),IF(H97="Serviço",CONCATENATE(TEXT(B97,"00"),".",TEXT(C97,"000"),".",TEXT(D97,"000"),".",TEXT(E97,"000")),""))))) -> 02.002.004.001 | J97: Instalações Provisórias (central de aço, formas, argamassa, almoxarifado geral, construções temporárias) | K97: =IFERROR(VLOOKUP(J97,BASES!$A$13:$E$342,3,FALSE),0) -> vb | L97: =IFERROR(VLOOKUP(J97,BASES!$A$13:$E$342,4,FALSE),0) -> 1 | M97: =IFERROR(VLOOKUP(J97,BASES!$A$13:$E$342,5,FALSE),0) -> 65371.036 | N97: =IF(H97="Serviço",M97*L97,IF(H97="CÉLULA CONSTRUTIVA",SUMIFS($N$8:$N$419,$B$8:$B$419,B97,$H$8:$H$419,"Serviço"),IF(H97="ETAPA",SUMIFS($N$8:$N$419,$B$8:$B$419,B97,$C$8:$C$419,C97,$H$8:$H$419,"Serviço"),IF(H97="SUBETAPA",SUMIFS($N$8:$N$419,$B$8:$B$419,B97,$C$8:$C$419,C97,$D$8:$D$419,D97,$H$8:$H$419,"Serviço"),0)))) -> 65371.036 | O97: =IF(VLOOKUP(J97,BASES!$A$13:$F$342,6,FALSE)="Recebido","Valor informado em formulário",IF(VLOOKUP(J97,BASES!$A$13:$F$342,6,FALSE)="Estimado","Estimado com base em índices históricos","Não solicitado")) -> Estimado com base em índices históricos | P97: Lançado ERP
A98: =IF($H98="UNIDADE CONSTRUTIVA",OFFSET(A98,-1,0)+1,LARGE(A$3:A97,1)) -> 0 | B98: =IF(H98="UNIDADE CONSTRUTIVA",0,IF(H98="CÉLULA CONSTRUTIVA",OFFSET(B98,-1,0)+1,OFFSET(B98,-1,0))) -> 2 | C98: =IF(H98="CÉLULA CONSTRUTIVA",0,IF(H98="ETAPA",OFFSET(C98,-1,0)+1,OFFSET(C98,-1,0))) -> 2 | D98: =IF(H98="ETAPA",0,IF(H98="SUBETAPA",OFFSET(D98,-1,0)+1,OFFSET(D98,-1,0))) -> 4 | E98: =IF(H98="Subetapa",0,IF(H98="serviço",OFFSET(E98,-1,0)+1,OFFSET(E98,-1,0))) -> 2 | H98: SERVIÇO | I98: =IF(H98="Unidade Construtiva",TEXT(A98,"00"),IF(H98="Célula Construtiva",TEXT(B98,"00"),IF(H98="Etapa",CONCATENATE(TEXT(B98,"00"),".",TEXT(C98,"000")),IF(H98="Subetapa",CONCATENATE(TEXT(B98,"00"),".",TEXT(C98,"000"),".",TEXT(D98,"000")),IF(H98="Serviço",CONCATENATE(TEXT(B98,"00"),".",TEXT(C98,"000"),".",TEXT(D98,"000"),".",TEXT(E98,"000")),""))))) -> 02.002.004.002 | J98: Tapume de telha metálica trapezoidal | K98: =IFERROR(VLOOKUP(J98,BASES!$A$13:$E$342,3,FALSE),0) -> m2 | L98: =IFERROR(VLOOKUP(J98,BASES!$A$13:$E$342,4,FALSE),0) -> 132.672 | M98: =IFERROR(VLOOKUP(J98,CPU!$D$2:$H$1439,5,FALSE),0) -> 147.4166 | N98: =IF(H98="Serviço",M98*L98,IF(H98="CÉLULA CONSTRUTIVA",SUMIFS($N$8:$N$419,$B$8:$B$419,B98,$H$8:$H$419,"Serviço"),IF(H98="ETAPA",SUMIFS($N$8:$N$419,$B$8:$B$419,B98,$C$8:$C$419,C98,$H$8:$H$419,"Serviço"),IF(H98="SUBETAPA",SUMIFS($N$8:$N$419,$B$8:$B$419,B98,$C$8:$C$419,C98,$D$8:$D$419,D98,$H$8:$H$419,"Serviço"),0)))) -> 19558.055 | O98: =IF(VLOOKUP(J98,BASES!$A$13:$F$342,6,FALSE)="Recebido","Valor informado em formulário",IF(VLOOKUP(J98,BASES!$A$13:$F$342,6,FALSE)="Estimado","Estimado com base em índices históricos","Não solicitado")) -> Estimado com base em índices históricos | P98: Lançado ERP
A99: =IF($H99="UNIDADE CONSTRUTIVA",OFFSET(A99,-1,0)+1,LARGE(A$3:A98,1)) -> 0 | B99: =IF(H99="UNIDADE CONSTRUTIVA",0,IF(H99="CÉLULA CONSTRUTIVA",OFFSET(B99,-1,0)+1,OFFSET(B99,-1,0))) -> 2 | C99: =IF(H99="CÉLULA CONSTRUTIVA",0,IF(H99="ETAPA",OFFSET(C99,-1,0)+1,OFFSET(C99,-1,0))) -> 2 | D99: =IF(H99="ETAPA",0,IF(H99="SUBETAPA",OFFSET(D99,-1,0)+1,OFFSET(D99,-1,0))) -> 5 | E99: =IF(H99="Subetapa",0,IF(H99="serviço",OFFSET(E99,-1,0)+1,OFFSET(E99,-1,0))) -> 0 | H99: SUBETAPA | I99: =IF(H99="Unidade Construtiva",TEXT(A99,"00"),IF(H99="Célula Construtiva",TEXT(B99,"00"),IF(H99="Etapa",CONCATENATE(TEXT(B99,"00"),".",TEXT(C99,"000")),IF(H99="Subetapa",CONCATENATE(TEXT(B99,"00"),".",TEXT(C99,"000"),".",TEXT(D99,"000")),IF(H99="Serviço",CONCATENATE(TEXT(B99,"00"),".",TEXT(C99,"000"),".",TEXT(D99,"000"),".",TEXT(E99,"000")),""))))) -> 02.002.005 | J99: Ligações Provisórias | N99: =IF(H99="Serviço",M99*L99,IF(H99="CÉLULA CONSTRUTIVA",SUMIFS($N$8:$N$419,$B$8:$B$419,B99,$H$8:$H$419,"Serviço"),IF(H99="ETAPA",SUMIFS($N$8:$N$419,$B$8:$B$419,B99,$C$8:$C$419,C99,$H$8:$H$419,"Serviço"),IF(H99="SUBETAPA",SUMIFS($N$8:$N$419,$B$8:$B$419,B99,$C$8:$C$419,C99,$D$8:$D$419,D99,$H$8:$H$419,"Serviço"),0)))) -> 14250.749 | Q99: =N99/'Obra '!$C$32 -> 0.0029851437
