Workbook
Name \0: #REF!
Name \0: #REF!
Name \0: #REF!
Name \0: #REF!
Name \0: #REF!
Name \0: #REF!
Name \1: #REF!
Name \1: #REF!
Name \1: #REF!
Name \1: #REF!
Name \1: #REF!
Name \a: #REF!
Name \a: #REF!
Name \a: #REF!
Name \a: #REF!
Name \a: #REF!
Name \a: #REF!
Name \b: #REF!
Name \b: #REF!
Name \b: #REF!
Name \b: #REF!
Name \b: #REF!
Name \c: #REF!
Name \c: #REF!
Name \c: #REF!
Name \c: #REF!
Name \c: #REF!
Name \d: #REF!
Name \d: #REF!
Name \d: #REF!
Name \d: #REF!
Name \d: #REF!
Name \e: #REF!
Name \e: #REF!
Name \e: #REF!
Name \e: #REF!
Name \e: #REF!
Name \i: #REF!
Name \i: #REF!
Name \i: #REF!
Name \i: #REF!
Name \i: #REF!
Name \J: #REF!
Name \J: #REF!
Name \J: #REF!
Name \J: #REF!
Name \J: #REF!
Name \k: #REF!
Name \k: #REF!
Name \k: #REF!
Name \k: #REF!
Name \k: #REF!
Name \l: #N/A
Name \m: #REF!
Name \m: #REF!
Name \m: #REF!
Name \m: #REF!
Name \m: #REF!
Name \m: #REF!
Name \o: #REF!

Sheet PROJETOS
B1: Projeto | C1: ='Obra '!D1 -> Caio Prado
B2: Empresa | C2: ='Obra '!D2 -> Indepy
B3: Revisão | C3: ='Obra '!D3 -> R00 - Larissa
A5: INFRAESTRUTURA
A6: PAVIMENTO | B6: DISCIPLINA
B7: ARQUITETURA | C7: FUNDAÇÕES | D7: OBSERVAÇÃO
A8: Fundação Profunda | C8: BRS_RDT_FUN_EX_001_R03
A20: Caminho: | B20: https://qicloud.com.br/root/caroline.nunes@cartesianengenharia.com#Obras/BRS-MOD_REDENTOR/Estrutura/04%20-%20PROJETO%20EXECUTIVO/PDF
A22: INSTALAÇÕES ELETRICAS
A23: PAVIMENTO | B23: DISCIPLINA
B24: ARQUITETURA | C24: ELETRICA | D24: OBSERVAÇÃO
A25: GERAL
A26: ='Obra '!$B$17 -> Subsolo
A27: ='Obra '!$B$18 -> Térreo
A28: ='Obra '!$B$19 -> 1º Pavimento - HMP
A29: ='Obra '!$B$20 -> 2º Pavimento - HMP
A30: ='Obra '!$B$21 -> 3º Pavimento - R2V / HMP
A31: ='Obra '!$B$22 -> 5º/ 7º/ 9º E 11º Pavimento - R2V
A32: ='Obra '!$B$23 -> 4º/ 6º/ 8º/ 10º E 12º Pavimento - R2V
A33: ='Obra '!$B$24 -> 13º Pavimento - LAZER
A34: ='Obra '!$B$25 -> 14º E 16º Pavimento - R2V
A35: ='Obra '!$B$26 -> 15º E 17º Pavimento - R2V
A36: ='Obra '!$B$27 -> 18º Pavimento - LAZER
A37: Caminho: | B37: 2.Projetos em andamento/Empresa/Obra/Escopo/Extração de quantitativos/Projetos Considerados

Sheet Obra 
C1: Projeto | D1: Caio Prado | E1: ENDEREÇO DA OBRA: | F1: R. Caio Prado, 207 - Consolação, São Paulo - SP, 01303-001
C2: Empresa | D2: Indepy | E2: CNPJ:
C3: Revisão | D3: R00 - Larissa | E3: ARQUIVO:
A4: QUADRO DE ÁREAS
B6: Descrição | C6: Unidade | E6: Quantidade | G6: Imagens
B7: MESES DE OBRA | C7: MÊS | E7: 36
B8: ÁREA DO TERRENO | C8: M² | E8: 981.06
B9: ÁREA CONSTRUÍDA | C9: M² | E9: 6938.39
B10: NÚMERO DE UNIDADES HABITACIONAIS | C10: UN | E10: 135
B11: NÚMERO DE UNIDADES COMERCIAIS | C11: UN | E11: 1
B12: ÁREA PRIVATIVA | C12: M² | E12: =SUM(E66:E115) -> 4392.6
B13: NÚMERO DE PAVIMENTOS | C13: UN | E13: 23
B14: ÁREA DE LAZER | C14: M² | E14: =MOBILIÁRIO!C7 -> 1901.04
B15: TOTAL DORMITÓRIOS | C15: UN | E15: 135
B17: Subsolo | C17: M² | E17: 243.84
B18: Térreo | C18: M² | E18: 615.57
B19: 1º Pavimento - HMP | C19: M² | E19: 380.61
B20: 2º Pavimento - HMP | C20: M² | E20: 478.98
B21: 3º Pavimento - R2V / HMP | C21: M² | E21: 412.99
B22: 5º/ 7º/ 9º E 11º Pavimento - R2V | C22: M² | E22: 1651.96
B23: 4º/ 6º/ 8º/ 10º E 12º Pavimento - R2V | C23: M² | E23: 1806.8
B24: 13º Pavimento - LAZER | C24: M² | E24: 294.68
B25: 14º E 16º Pavimento - R2V | C25: M² | E25: 445.2
B26: 15º E 17º Pavimento - R2V | C26: M² | E26: 389.26
B27: 18º Pavimento - LAZER | C27: M² | E27: 82.25
... B29: CX D'ÁGUA | C29: M² | E29: 69.05
B30: TOPO | C30: M²
B35: CARTESIAN
B36: ETAPA | C36: VALOR ORÇADO | D36: % | E36: VALOR / m²
B37: PAREDES E PAINÉIS | C37: =Ger_Executivo!N8 -> 2008722.2 | D37: =C37/C$48 -> 0.11881186 | E37: =C37/$E$9 -> 289.5084
B38: IMPERMEABILIZAÇÃO E TRATAMENTOS | C38: =Ger_Executivo!N28 -> 703992.08 | D38: =C38/C$48 -> 0.04163971 | E38: =C38/$E$9 -> 101.46332
B39: REVESTIMENTOS INTERNOS DE PAREDE | C39: =Ger_Executivo!N70 -> 1323971.4 | D39: =C39/C$48 -> 0.078310235 | E39: =C39/$E$9 -> 190.81825
B40: REVESTIMENTOS E ACABAMENTOS INTERNOS EM TETO | C40: =Ger_Executivo!N93 -> 695689.43 | D40: =C40/C$48 -> 0.041148625 | E40: =C40/$E$9 -> 100.26669
B41: PISOS E PAVIMENTAÇÕES | C41: =Ger_Executivo!N104 -> 1461780 | D41: =C41/C$48 -> 0.086461336 | E41: =C41/$E$9 -> 210.68
B42: SISTEMAS DE PINTURA INTERNA | C42: =Ger_Executivo!N141 -> 1340430.3 | D42: =C42/C$48 -> 0.079283744 | E42: =C42/$E$9 -> 193.19039
B43: ESQUADRIAS, VIDROS E FERRAGENS | C43: =Ger_Executivo!N163 -> 3691455.8 | D43: =C43/C$48 -> 0.21834215 | E43: =C43/$E$9 -> 532.03348
B44: LOUÇAS E METAIS | C44: =Ger_Executivo!N201 -> 326798.11 | D44: =C44/C$48 -> 0.019329448 | E44: =C44/$E$9 -> 47.099992
B45: REVESTIMENTOS E ACABAMENTOS EM FACHADA | C45: =Ger_Executivo!N211 -> 1898087.7 | D45: =C45/C$48 -> 0.11226805 | E45: =C45/$E$9 -> 273.56313
B46: SERVIÇOS COMPLEMENTARES E FINAIS | C46: =Ger_Executivo!N232 -> 3135402.8 | D46: =C46/C$48 -> 0.18545274 | E46: =C46/$E$9 -> 451.89198
B47: IMPREVISTOS E CONTINGÊNCIAS | C47: =Ger_Executivo!N254 -> 320418.31 | D47: =C47/C$48 -> 0.018952096 | E47: =C47/$E$9 -> 46.180498
B48: TOTAL | C48: =SUM(C37:C47) -> 16906748 | D48: =SUM(D37:D47) -> 1 | E48: =SUM(E37:E47) -> 2436.6961
B49: CUB/SP R8-N | C49: 2481.34 | D49: 45931 | E49: =ROUNDUP(+E48/C49,2)&" CUB" -> 0,99 CUB
B64: Área Privativa
B65: Aptos | C65: Área Útil (m2) | D65: Qnt | E65: Total (m2) | F65: VENT. MEC. | G65: Dormitorios | H65: Banheiros
B66: APTO TIPO "E" - FINAL 06/07 - 1 Pav | C66: 27.14 | D66: 2 | E66: =D66*C66 -> 54.28 | F66: 0 | G66: 2 | H66: 2
B67: APTO TIPO "F" - FINAL 08/09 - 1 Pav | C67: 27.83 | D67: 2 | E67: =D67*C67 -> 55.66 | F67: 0 | G67: 2 | H67: 2
B68: APTO TIPO "G" - FINAL 10 - 1 Pav | C68: 27.58 | D68: 1 | E68: =D68*C68 -> 27.58 | F68: 0 | G68: 1 | H68: 1
B69: APTO TIPO "H" - FINAL 11 - 1 Pav | C69: 27.86 | D69: 1 | E69: =D69*C69 -> 27.86 | F69: 0 | G69: 1 | H69: 1
B70: APTO TIPO "J" - FINAL 01- 2 Pav | C70: 34.75 | D70: 1 | E70: =D70*C70 -> 34.75 | F70: 0 | G70: 1 | H70: 1
B71: APTO TIPO "B" - FINAL 02/03 - 2 Pav | C71: 29.97 | D71: 2 | E71: =D71*C71 -> 59.94 | F71: 0 | G71: 2 | H71: 2
B72: APTO TIPO "C" - FINAL 04 - 2 Pav | C72: 30.41 | D72: 1 | E72: =D72*C72 -> 30.41 | F72: 0 | G72: 1 | H72: 1
B73: APTO TIPO "I" - FINAL 05 - 2 Pav | C73: 29.05 | D73: 1 | E73: =D73*C73 -> 29.05 | F73: 0 | G73: 1 | H73: 1
B74: APTO TIPO "E" - FINAL 06/07- 2 Pav | C74: 27.14 | D74: 2 | E74: =D74*C74 -> 54.28 | F74: 0 | G74: 2 | H74: 2
B75: APTO TIPO "F" - FINAL 08/09 - 2 Pav | C75: 27.83 | D75: 2 | E75: =D75*C75 -> 55.66 | F75: 0 | G75: 2 | H75: 2
B76: APTO TIPO "G" - FINAL 10 - 2 Pav | C76: 27.58 | D76: 1 | E76: =D76*C76 -> 27.58 | F76: 0 | G76: 1 | H76: 1
B77: APTO TIPO "H" - FINAL 11 - 2 Pav | C77: 27.86 | D77: 1 | E77: =D77*C77 -> 27.86 | F77: 0 | G77: 1 | H77: 1
... B115: APTO TIPO "M" - FINAL 05(DUPLEX INFERIOR) - 16 Pav | C115: 37.61 | D115: 1 | E115: =D115*C115 -> 37.61 | F115: 0 | G115: 1 | H115: 1
E116: =SUM(E66:E115) -> 4392.6 | F116: =SUM(F66:F115) -> 0 | G116: =SUM(G66:G115) -> 149 | H116: =SUM(H66:H115) -> 149
H117: =E116/H116 -> 29.480537

Sheet Ger_Executivo
G4: PROJETO: | I4: ='Obra '!D1 -> Caio Prado | O4: REVISÃO: | P4: DATA
G5: EMPRESA: | I5: ='Obra '!D2 -> Indepy | O5: R00 | P5: 45980
A6: Unidade Construtiva | B6: Célula Construtiva | C6: Etapa | D6: Subetapa | E6: Serviço | G6: GERENCIAMENTO EXECUTIVO
A7: 0 | B7: 0 | C7: 0 | D7: 0 | E7: 0 | G7: Atalho | H7: NIVEL | I7: Item | J7: Descrição | K7: Unidade | L7: Quant. | M7: Preço un | N7: Total | O7: Considerações | P7: Situação
A8: =IF($H8="UNIDADE CONSTRUTIVA",OFFSET(A8,-1,0)+1,LARGE(A$3:A7,1)) -> 0 | B8: =IF(H8="UNIDADE CONSTRUTIVA",0,IF(H8="CÉLULA CONSTRUTIVA",OFFSET(B8,-1,0)+1,OFFSET(B8,-1,0))) -> 1 | C8: =IF(H8="CÉLULA CONSTRUTIVA",0,IF(H8="ETAPA",OFFSET(C8,-1,0)+1,OFFSET(C8,-1,0))) -> 0 | D8: =IF(H8="ETAPA",0,IF(H8="SUBETAPA",OFFSET(D8,-1,0)+1,OFFSET(D8,-1,0))) -> 0 | E8: =IF(H8="Subetapa",0,IF(H8="serviço",OFFSET(E8,-1,0)+1,OFFSET(E8,-1,0))) -> 0 | H8: CÉLULA CONSTRUTIVA | I8: =IF(H8="Unidade Construtiva",TEXT(A8,"00"),IF(H8="Célula Construtiva",TEXT(B8,"00"),IF(H8="Etapa",CONCATENATE(TEXT(B8,"00"),".",TEXT(C8,"000")),IF(H8="Subetapa",CONCATENATE(TEXT(B8,"00"),".",TEXT(C8,"000"),".",TEXT(D8,"000")),IF(H8="Serviço",CONCATENATE(TEXT(B8,"00"),".",TEXT(C8,"000"),".",TEXT(D8,"000"),".",TEXT(E8,"000")),""))))) -> 01 | J8: PAREDES E PAINÉIS | N8: =IF(H8="Serviço",M8*L8,IF(H8="CÉLULA CONSTRUTIVA",SUMIFS($N$8:$N$262,$B$8:$B$262,B8,$H$8:$H$262,"Serviço"),IF(H8="ETAPA",SUMIFS($N$8:$N$262,$B$8:$B$262,B8,$C$8:$C$262,C8,$H$8:$H$262,"Serviço"),IF(H8="SUBETAPA",SUMIFS($N$8:$N$262,$B$8:$B$262,B8,$C$8:$C$262,C8,$D$8:$D$262,D8,$H$8:$H$262,"Serviço"),0)))) -> 2008722.2 | O8: =N8/'Obra '!$E$9 -> 289.5084 | Q8: ALVENARIA
A9: =IF($H9="UNIDADE CONSTRUTIVA",OFFSET(A9,-1,0)+1,LARGE(A$3:A8,1)) -> 0 | B9: =IF(H9="UNIDADE CONSTRUTIVA",0,IF(H9="CÉLULA CONSTRUTIVA",OFFSET(B9,-1,0)+1,OFFSET(B9,-1,0))) -> 1 | C9: =IF(H9="CÉLULA CONSTRUTIVA",0,IF(H9="ETAPA",OFFSET(C9,-1,0)+1,OFFSET(C9,-1,0))) -> 1 | D9: =IF(H9="ETAPA",0,IF(H9="SUBETAPA",OFFSET(D9,-1,0)+1,OFFSET(D9,-1,0))) -> 0 | E9: =IF(H9="Subetapa",0,IF(H9="serviço",OFFSET(E9,-1,0)+1,OFFSET(E9,-1,0))) -> 0 | H9: ETAPA | I9: =IF(H9="Unidade Construtiva",TEXT(A9,"00"),IF(H9="Célula Construtiva",TEXT(B9,"00"),IF(H9="Etapa",CONCATENATE(TEXT(B9,"00"),".",TEXT(C9,"000")),IF(H9="Subetapa",CONCATENATE(TEXT(B9,"00"),".",TEXT(C9,"000"),".",TEXT(D9,"000")),IF(H9="Serviço",CONCATENATE(TEXT(B9,"00"),".",TEXT(C9,"000"),".",TEXT(D9,"000"),".",TEXT(E9,"000")),""))))) -> 01.001 | J9: VEDAÇÕES | N9: =IF(H9="Serviço",M9*L9,IF(H9="CÉLULA CONSTRUTIVA",SUMIFS($N$8:$N$262,$B$8:$B$262,B9,$H$8:$H$262,"Serviço"),IF(H9="ETAPA",SUMIFS($N$8:$N$262,$B$8:$B$262,B9,$C$8:$C$262,C9,$H$8:$H$262,"Serviço"),IF(H9="SUBETAPA",SUMIFS($N$8:$N$262,$B$8:$B$262,B9,$C$8:$C$262,C9,$D$8:$D$262,D9,$H$8:$H$262,"Serviço"),0)))) -> 2008722.2 | O9: =N9/'Obra '!$E$9 -> 289.5084
A10: =IF($H10="UNIDADE CONSTRUTIVA",OFFSET(A10,-1,0)+1,LARGE(A$3:A17,1)) -> 0 | B10: =IF(H10="UNIDADE CONSTRUTIVA",0,IF(H10="CÉLULA CONSTRUTIVA",OFFSET(B10,-1,0)+1,OFFSET(B10,-1,0))) -> 1 | C10: =IF(H10="CÉLULA CONSTRUTIVA",0,IF(H10="ETAPA",OFFSET(C10,-1,0)+1,OFFSET(C10,-1,0))) -> 1 | D10: =IF(H10="ETAPA",0,IF(H10="SUBETAPA",OFFSET(D10,-1,0)+1,OFFSET(D10,-1,0))) -> 1 | E10: =IF(H10="Subetapa",0,IF(H10="serviço",OFFSET(E10,-1,0)+1,OFFSET(E10,-1,0))) -> 0 | H10: SUBETAPA | I10: =IF(H10="Unidade Construtiva",TEXT(A10,"00"),IF(H10="Célula Construtiva",TEXT(B10,"00"),IF(H10="Etapa",CONCATENATE(TEXT(B10,"00"),".",TEXT(C10,"000")),IF(H10="Subetapa",CONCATENATE(TEXT(B10,"00"),".",TEXT(C10,"000"),".",TEXT(D10,"000")),IF(H10="Serviço",CONCATENATE(TEXT(B10,"00"),".",TEXT(C10,"000"),".",TEXT(D10,"000"),".",TEXT(E10,"000")),""))))) -> 01.001.001 | J10: Alvenaria de vedação com bocos de concreto | N10: =IF(H10="Serviço",M10*L10,IF(H10="CÉLULA CONSTRUTIVA",SUMIFS($N$8:$N$262,$B$8:$B$262,B10,$H$8:$H$262,"Serviço"),IF(H10="ETAPA",SUMIFS($N$8:$N$262,$B$8:$B$262,B10,$C$8:$C$262,C10,$H$8:$H$262,"Serviço"),IF(H10="SUBETAPA",SUMIFS($N$8:$N$262,$B$8:$B$262,B10,$C$8:$C$262,C10,$D$8:$D$262,D10,$H$8:$H$262,"Serviço"),0)))) -> 703546.68 | O10: =N10/'Obra '!$E$9 -> 101.39913
A11: =IF($H11="UNIDADE CONSTRUTIVA",OFFSET(A11,-1,0)+1,LARGE(A$3:A10,1)) -> 0 | B11: =IF(H11="UNIDADE CONSTRUTIVA",0,IF(H11="CÉLULA CONSTRUTIVA",OFFSET(B11,-1,0)+1,OFFSET(B11,-1,0))) -> 1 | C11: =IF(H11="CÉLULA CONSTRUTIVA",0,IF(H11="ETAPA",OFFSET(C11,-1,0)+1,OFFSET(C11,-1,0))) -> 1 | D11: =IF(H11="ETAPA",0,IF(H11="SUBETAPA",OFFSET(D11,-1,0)+1,OFFSET(D11,-1,0))) -> 1 | E11: =IF(H11="Subetapa",0,IF(H11="serviço",OFFSET(E11,-1,0)+1,OFFSET(E11,-1,0))) -> 1 | H11: SERVIÇO | I11: =IF(H11="Unidade Construtiva",TEXT(A11,"00"),IF(H11="Célula Construtiva",TEXT(B11,"00"),IF(H11="Etapa",CONCATENATE(TEXT(B11,"00"),".",TEXT(C11,"000")),IF(H11="Subetapa",CONCATENATE(TEXT(B11,"00"),".",TEXT(C11,"000"),".",TEXT(D11,"000")),IF(H11="Serviço",CONCATENATE(TEXT(B11,"00"),".",TEXT(C11,"000"),".",TEXT(D11,"000"),".",TEXT(E11,"000")),""))))) -> 01.001.001.001 | J11: Alvenaria de vedação de blocos de concreto de 09x19x39cm, com argamassa estabilizada | K11: m2 | L11: =ARQUITETURA!H13 -> 208.45 | M11: 46.3 | N11: =IF(H11="Serviço",M11*L11,IF(H11="CÉLULA CONSTRUTIVA",SUMIFS($N$8:$N$262,$B$8:$B$262,B11,$H$8:$H$262,"Serviço"),IF(H11="ETAPA",SUMIFS($N$8:$N$262,$B$8:$B$262,B11,$C$8:$C$262,C11,$H$8:$H$262,"Serviço"),IF(H11="SUBETAPA",SUMIFS($N$8:$N$262,$B$8:$B$262,B11,$C$8:$C$262,C11,$D$8:$D$262,D11,$H$8:$H$262,"Serviço"),0)))) -> 9651.235
A12: =IF($H12="UNIDADE CONSTRUTIVA",OFFSET(A12,-1,0)+1,LARGE(A$3:A11,1)) -> 0 | B12: =IF(H12="UNIDADE CONSTRUTIVA",0,IF(H12="CÉLULA CONSTRUTIVA",OFFSET(B12,-1,0)+1,OFFSET(B12,-1,0))) -> 1 | C12: =IF(H12="CÉLULA CONSTRUTIVA",0,IF(H12="ETAPA",OFFSET(C12,-1,0)+1,OFFSET(C12,-1,0))) -> 1 | D12: =IF(H12="ETAPA",0,IF(H12="SUBETAPA",OFFSET(D12,-1,0)+1,OFFSET(D12,-1,0))) -> 1 | E12: =IF(H12="Subetapa",0,IF(H12="serviço",OFFSET(E12,-1,0)+1,OFFSET(E12,-1,0))) -> 2 | H12: SERVIÇO | I12: =IF(H12="Unidade Construtiva",TEXT(A12,"00"),IF(H12="Célula Construtiva",TEXT(B12,"00"),IF(H12="Etapa",CONCATENATE(TEXT(B12,"00"),".",TEXT(C12,"000")),IF(H12="Subetapa",CONCATENATE(TEXT(B12,"00"),".",TEXT(C12,"000"),".",TEXT(D12,"000")),IF(H12="Serviço",CONCATENATE(TEXT(B12,"00"),".",TEXT(C12,"000"),".",TEXT(D12,"000"),".",TEXT(E12,"000")),""))))) -> 01.001.001.002 | J12: Alvenaria de vedação de blocos de concreto de 14x19x39cm, com argamassa estabilizada | K12: m2 | L12: =ARQUITETURA!H14 -> 1643 | M12: 49.1 | N12: =IF(H12="Serviço",M12*L12,IF(H12="CÉLULA CONSTRUTIVA",SUMIFS($N$8:$N$262,$B$8:$B$262,B12,$H$8:$H$262,"Serviço"),IF(H12="ETAPA",SUMIFS($N$8:$N$262,$B$8:$B$262,B12,$C$8:$C$262,C12,$H$8:$H$262,"Serviço"),IF(H12="SUBETAPA",SUMIFS($N$8:$N$262,$B$8:$B$262,B12,$C$8:$C$262,C12,$D$8:$D$262,D12,$H$8:$H$262,"Serviço"),0)))) -> 80671.3
A13: =IF($H13="UNIDADE CONSTRUTIVA",OFFSET(A13,-1,0)+1,LARGE(A$3:A12,1)) -> 0 | B13: =IF(H13="UNIDADE CONSTRUTIVA",0,IF(H13="CÉLULA CONSTRUTIVA",OFFSET(B13,-1,0)+1,OFFSET(B13,-1,0))) -> 1 | C13: =IF(H13="CÉLULA CONSTRUTIVA",0,IF(H13="ETAPA",OFFSET(C13,-1,0)+1,OFFSET(C13,-1,0))) -> 1 | D13: =IF(H13="ETAPA",0,IF(H13="SUBETAPA",OFFSET(D13,-1,0)+1,OFFSET(D13,-1,0))) -> 1 | E13: =IF(H13="Subetapa",0,IF(H13="serviço",OFFSET(E13,-1,0)+1,OFFSET(E13,-1,0))) -> 3 | H13: SERVIÇO | I13: =IF(H13="Unidade Construtiva",TEXT(A13,"00"),IF(H13="Célula Construtiva",TEXT(B13,"00"),IF(H13="Etapa",CONCATENATE(TEXT(B13,"00"),".",TEXT(C13,"000")),IF(H13="Subetapa",CONCATENATE(TEXT(B13,"00"),".",TEXT(C13,"000"),".",TEXT(D13,"000")),IF(H13="Serviço",CONCATENATE(TEXT(B13,"00"),".",TEXT(C13,"000"),".",TEXT(D13,"000"),".",TEXT(E13,"000")),""))))) -> 01.001.001.003 | J13: Alvenaria de vedação de blocos de concreto de 19x19x39cm, com argamassa estabilizada | K13: m2 | L13: =ARQUITETURA!H15 -> 2528.25 | M13: 64.22 | N13: =IF(H13="Serviço",M13*L13,IF(H13="CÉLULA CONSTRUTIVA",SUMIFS($N$8:$N$262,$B$8:$B$262,B13,$H$8:$H$262,"Serviço"),IF(H13="ETAPA",SUMIFS($N$8:$N$262,$B$8:$B$262,B13,$C$8:$C$262,C13,$H$8:$H$262,"Serviço"),IF(H13="SUBETAPA",SUMIFS($N$8:$N$262,$B$8:$B$262,B13,$C$8:$C$262,C13,$D$8:$D$262,D13,$H$8:$H$262,"Serviço"),0)))) -> 162364.21
A14: =IF($H14="UNIDADE CONSTRUTIVA",OFFSET(A14,-1,0)+1,LARGE(A$3:A9,1)) -> 0 | B14: =IF(H14="UNIDADE CONSTRUTIVA",0,IF(H14="CÉLULA CONSTRUTIVA",OFFSET(B14,-1,0)+1,OFFSET(B14,-1,0))) -> 1 | C14: =IF(H14="CÉLULA CONSTRUTIVA",0,IF(H14="ETAPA",OFFSET(C14,-1,0)+1,OFFSET(C14,-1,0))) -> 1 | D14: =IF(H14="ETAPA",0,IF(H14="SUBETAPA",OFFSET(D14,-1,0)+1,OFFSET(D14,-1,0))) -> 1 | E14: =IF(H14="Subetapa",0,IF(H14="serviço",OFFSET(E14,-1,0)+1,OFFSET(E14,-1,0))) -> 4 | H14: SERVIÇO | I14: =IF(H14="Unidade Construtiva",TEXT(A14,"00"),IF(H14="Célula Construtiva",TEXT(B14,"00"),IF(H14="Etapa",CONCATENATE(TEXT(B14,"00"),".",TEXT(C14,"000")),IF(H14="Subetapa",CONCATENATE(TEXT(B14,"00"),".",TEXT(C14,"000"),".",TEXT(D14,"000")),IF(H14="Serviço",CONCATENATE(TEXT(B14,"00"),".",TEXT(C14,"000"),".",TEXT(D14,"000"),".",TEXT(E14,"000")),""))))) -> 01.001.001.004 | J14: Alvenaria de vedação de Bloco concreto corta-fogo de 09x19x39cm, com argamassa estabilizada | K14: m2 | L14: =ARQUITETURA!H99 -> 87.04 | M14: 71.5 | N14: =IF(H14="Serviço",M14*L14,IF(H14="CÉLULA CONSTRUTIVA",SUMIFS($N$8:$N$262,$B$8:$B$262,B14,$H$8:$H$262,"Serviço"),IF(H14="ETAPA",SUMIFS($N$8:$N$262,$B$8:$B$262,B14,$C$8:$C$262,C14,$H$8:$H$262,"Serviço"),IF(H14="SUBETAPA",SUMIFS($N$8:$N$262,$B$8:$B$262,B14,$C$8:$C$262,C14,$D$8:$D$262,D14,$H$8:$H$262,"Serviço"),0)))) -> 6223.36 | O14: Da marca oterprem, conforme projeto acustico r03
A15: =IF($H15="UNIDADE CONSTRUTIVA",OFFSET(A15,-1,0)+1,LARGE(A$3:A14,1)) -> 0 | B15: =IF(H15="UNIDADE CONSTRUTIVA",0,IF(H15="CÉLULA CONSTRUTIVA",OFFSET(B15,-1,0)+1,OFFSET(B15,-1,0))) -> 1 | C15: =IF(H15="CÉLULA CONSTRUTIVA",0,IF(H15="ETAPA",OFFSET(C15,-1,0)+1,OFFSET(C15,-1,0))) -> 1 | D15: =IF(H15="ETAPA",0,IF(H15="SUBETAPA",OFFSET(D15,-1,0)+1,OFFSET(D15,-1,0))) -> 1 | E15: =IF(H15="Subetapa",0,IF(H15="serviço",OFFSET(E15,-1,0)+1,OFFSET(E15,-1,0))) -> 5 | H15: SERVIÇO | I15: =IF(H15="Unidade Construtiva",TEXT(A15,"00"),IF(H15="Célula Construtiva",TEXT(B15,"00"),IF(H15="Etapa",CONCATENATE(TEXT(B15,"00"),".",TEXT(C15,"000")),IF(H15="Subetapa",CONCATENATE(TEXT(B15,"00"),".",TEXT(C15,"000"),".",TEXT(D15,"000")),IF(H15="Serviço",CONCATENATE(TEXT(B15,"00"),".",TEXT(C15,"000"),".",TEXT(D15,"000"),".",TEXT(E15,"000")),""))))) -> 01.001.001.005 | J15: Alvenaria de vedação de Bloco concreto corta-fogo de 14x19x39cm, com argamassa estabilizada | K15: m2 | L15: =ARQUITETURA!H100 -> 1154.05 | M15: 99.5 | N15: =IF(H15="Serviço",M15*L15,IF(H15="CÉLULA CONSTRUTIVA",SUMIFS($N$8:$N$262,$B$8:$B$262,B15,$H$8:$H$262,"Serviço"),IF(H15="ETAPA",SUMIFS($N$8:$N$262,$B$8:$B$262,B15,$C$8:$C$262,C15,$H$8:$H$262,"Serviço"),IF(H15="SUBETAPA",SUMIFS($N$8:$N$262,$B$8:$B$262,B15,$C$8:$C$262,C15,$D$8:$D$262,D15,$H$8:$H$262,"Serviço"),0)))) -> 114827.98 | O15: Da marca oterprem, conforme projeto acustico r03
A16: =IF($H16="UNIDADE CONSTRUTIVA",OFFSET(A16,-1,0)+1,LARGE(A$3:A15,1)) -> 0 | B16: =IF(H16="UNIDADE CONSTRUTIVA",0,IF(H16="CÉLULA CONSTRUTIVA",OFFSET(B16,-1,0)+1,OFFSET(B16,-1,0))) -> 1 | C16: =IF(H16="CÉLULA CONSTRUTIVA",0,IF(H16="ETAPA",OFFSET(C16,-1,0)+1,OFFSET(C16,-1,0))) -> 1 | D16: =IF(H16="ETAPA",0,IF(H16="SUBETAPA",OFFSET(D16,-1,0)+1,OFFSET(D16,-1,0))) -> 1 | E16: =IF(H16="Subetapa",0,IF(H16="serviço",OFFSET(E16,-1,0)+1,OFFSET(E16,-1,0))) -> 6 | H16: SERVIÇO | I16: =IF(H16="Unidade Construtiva",TEXT(A16,"00"),IF(H16="Célula Construtiva",TEXT(B16,"00"),IF(H16="Etapa",CONCATENATE(TEXT(B16,"00"),".",TEXT(C16,"000")),IF(H16="Subetapa",CONCATENATE(TEXT(B16,"00"),".",TEXT(C16,"000"),".",TEXT(D16,"000")),IF(H16="Serviço",CONCATENATE(TEXT(B16,"00"),".",TEXT(C16,"000"),".",TEXT(D16,"000"),".",TEXT(E16,"000")),""))))) -> 01.001.001.006 | J16: Alvenaria de vedação de Bloco concreto corta-fogo com densidade acustica reforçada de 14x19x39cm, com argamassa estabilizada | K16: m2 | L16: =ARQUITETURA!H101 -> 2134.28 | M16: 148.5 | N16: =IF(H16="Serviço",M16*L16,IF(H16="CÉLULA CONSTRUTIVA",SUMIFS($N$8:$N$262,$B$8:$B$262,B16,$H$8:$H$262,"Serviço"),IF(H16="ETAPA",SUMIFS($N$8:$N$262,$B$8:$B$262,B16,$C$8:$C$262,C16,$H$8:$H$262,"Serviço"),IF(H16="SUBETAPA",SUMIFS($N$8:$N$262,$B$8:$B$262,B16,$C$8:$C$262,C16,$D$8:$D$262,D16,$H$8:$H$262,"Serviço"),0)))) -> 316940.58 | O16: Da marca oterprem, conforme projeto acustico r03
A17: =IF($H17="UNIDADE CONSTRUTIVA",OFFSET(A17,-1,0)+1,LARGE(A$3:A16,1)) -> 0 | B17: =IF(H17="UNIDADE CONSTRUTIVA",0,IF(H17="CÉLULA CONSTRUTIVA",OFFSET(B17,-1,0)+1,OFFSET(B17,-1,0))) -> 1 | C17: =IF(H17="CÉLULA CONSTRUTIVA",0,IF(H17="ETAPA",OFFSET(C17,-1,0)+1,OFFSET(C17,-1,0))) -> 1 | D17: =IF(H17="ETAPA",0,IF(H17="SUBETAPA",OFFSET(D17,-1,0)+1,OFFSET(D17,-1,0))) -> 1 | E17: =IF(H17="Subetapa",0,IF(H17="serviço",OFFSET(E17,-1,0)+1,OFFSET(E17,-1,0))) -> 7 | H17: SERVIÇO | I17: =IF(H17="Unidade Construtiva",TEXT(A17,"00"),IF(H17="Célula Construtiva",TEXT(B17,"00"),IF(H17="Etapa",CONCATENATE(TEXT(B17,"00"),".",TEXT(C17,"000")),IF(H17="Subetapa",CONCATENATE(TEXT(B17,"00"),".",TEXT(C17,"000"),".",TEXT(D17,"000")),IF(H17="Serviço",CONCATENATE(TEXT(B17,"00"),".",TEXT(C17,"000"),".",TEXT(D17,"000"),".",TEXT(E17,"000")),""))))) -> 01.001.001.007 | J17: Alvenaria de vedação de Bloco concreto corta-fogo de 19x19x39cm, com argamassa estabilizada | K17: m2 | L17: =ARQUITETURA!H102 -> 90.94 | M17: 141.5 | N17: =IF(H17="Serviço",M17*L17,IF(H17="CÉLULA CONSTRUTIVA",SUMIFS($N$8:$N$262,$B$8:$B$262,B17,$H$8:$H$262,"Serviço"),IF(H17="ETAPA",SUMIFS($N$8:$N$262,$B$8:$B$262,B17,$C$8:$C$262,C17,$H$8:$H$262,"Serviço"),IF(H17="SUBETAPA",SUMIFS($N$8:$N$262,$B$8:$B$262,B17,$C$8:$C$262,C17,$D$8:$D$262,D17,$H$8:$H$262,"Serviço"),0)))) -> 12868.01 | O17: Da marca oterprem, conforme projeto acustico r03
A18: =IF($H18="UNIDADE CONSTRUTIVA",OFFSET(A18,-1,0)+1,LARGE(A$3:A13,1)) -> 0 | B18: =IF(H18="UNIDADE CONSTRUTIVA",0,IF(H18="CÉLULA CONSTRUTIVA",OFFSET(B18,-1,0)+1,OFFSET(B18,-1,0))) -> 1 | C18: =IF(H18="CÉLULA CONSTRUTIVA",0,IF(H18="ETAPA",OFFSET(C18,-1,0)+1,OFFSET(C18,-1,0))) -> 1 | D18: =IF(H18="ETAPA",0,IF(H18="SUBETAPA",OFFSET(D18,-1,0)+1,OFFSET(D18,-1,0))) -> 2 | E18: =IF(H18="Subetapa",0,IF(H18="serviço",OFFSET(E18,-1,0)+1,OFFSET(E18,-1,0))) -> 0 | H18: SUBETAPA | I18: =IF(H18="Unidade Construtiva",TEXT(A18,"00"),IF(H18="Célula Construtiva",TEXT(B18,"00"),IF(H18="Etapa",CONCATENATE(TEXT(B18,"00"),".",TEXT(C18,"000")),IF(H18="Subetapa",CONCATENATE(TEXT(B18,"00"),".",TEXT(C18,"000"),".",TEXT(D18,"000")),IF(H18="Serviço",CONCATENATE(TEXT(B18,"00"),".",TEXT(C18,"000"),".",TEXT(D18,"000"),".",TEXT(E18,"000")),""))))) -> 01.001.002 | J18: Serviços complementares para alvenaria de vedação | N18: =IF(H18="Serviço",M18*L18,IF(H18="CÉLULA CONSTRUTIVA",SUMIFS($N$8:$N$262,$B$8:$B$262,B18,$H$8:$H$262,"Serviço"),IF(H18="ETAPA",SUMIFS($N$8:$N$262,$B$8:$B$262,B18,$C$8:$C$262,C18,$H$8:$H$262,"Serviço"),IF(H18="SUBETAPA",SUMIFS($N$8:$N$262,$B$8:$B$262,B18,$C$8:$C$262,C18,$D$8:$D$262,D18,$H$8:$H$262,"Serviço"),0)))) -> 290203.44
A19: =IF($H19="UNIDADE CONSTRUTIVA",OFFSET(A19,-1,0)+1,LARGE(A$3:A18,1)) -> 0 | B19: =IF(H19="UNIDADE CONSTRUTIVA",0,IF(H19="CÉLULA CONSTRUTIVA",OFFSET(B19,-1,0)+1,OFFSET(B19,-1,0))) -> 1 | C19: =IF(H19="CÉLULA CONSTRUTIVA",0,IF(H19="ETAPA",OFFSET(C19,-1,0)+1,OFFSET(C19,-1,0))) -> 1 | D19: =IF(H19="ETAPA",0,IF(H19="SUBETAPA",OFFSET(D19,-1,0)+1,OFFSET(D19,-1,0))) -> 2 | E19: =IF(H19="Subetapa",0,IF(H19="serviço",OFFSET(E19,-1,0)+1,OFFSET(E19,-1,0))) -> 1 | H19: SERVIÇO | I19: =IF(H19="Unidade Construtiva",TEXT(A19,"00"),IF(H19="Célula Construtiva",TEXT(B19,"00"),IF(H19="Etapa",CONCATENATE(TEXT(B19,"00"),".",TEXT(C19,"000")),IF(H19="Subetapa",CONCATENATE(TEXT(B19,"00"),".",TEXT(C19,"000"),".",TEXT(D19,"000")),IF(H19="Serviço",CONCATENATE(TEXT(B19,"00"),".",TEXT(C19,"000"),".",TEXT(D19,"000"),".",TEXT(E19,"000")),""))))) -> 01.001.002.001 | J19: Encunhamento de alvenaria de vedação com argamassa expansiva | K19: m | L19: =ARQUITETURA!H195 -> 4171.21 | M19: 14.7875 | N19: =IF(H19="Serviço",M19*L19,IF(H19="CÉLULA CONSTRUTIVA",SUMIFS($N$8:$N$262,$B$8:$B$262,B19,$H$8:$H$262,"Serviço"),IF(H19="ETAPA",SUMIFS($N$8:$N$262,$B$8:$B$262,B19,$C$8:$C$262,C19,$H$8:$H$262,"Serviço"),IF(H19="SUBETAPA",SUMIFS($N$8:$N$262,$B$8:$B$262,B19,$C$8:$C$262,C19,$D$8:$D$262,D19,$H$8:$H$262,"Serviço"),0)))) -> 61681.768
A20: =IF($H20="UNIDADE CONSTRUTIVA",OFFSET(A20,-1,0)+1,LARGE(A$3:A19,1)) -> 0 | B20: =IF(H20="UNIDADE CONSTRUTIVA",0,IF(H20="CÉLULA CONSTRUTIVA",OFFSET(B20,-1,0)+1,OFFSET(B20,-1,0))) -> 1 | C20: =IF(H20="CÉLULA CONSTRUTIVA",0,IF(H20="ETAPA",OFFSET(C20,-1,0)+1,OFFSET(C20,-1,0))) -> 1 | D20: =IF(H20="ETAPA",0,IF(H20="SUBETAPA",OFFSET(D20,-1,0)+1,OFFSET(D20,-1,0))) -> 2 | E20: =IF(H20="Subetapa",0,IF(H20="serviço",OFFSET(E20,-1,0)+1,OFFSET(E20,-1,0))) -> 2 | H20: SERVIÇO | I20: =IF(H20="Unidade Construtiva",TEXT(A20,"00"),IF(H20="Célula Construtiva",TEXT(B20,"00"),IF(H20="Etapa",CONCATENATE(TEXT(B20,"00"),".",TEXT(C20,"000")),IF(H20="Subetapa",CONCATENATE(TEXT(B20,"00"),".",TEXT(C20,"000"),".",TEXT(D20,"000")),IF(H20="Serviço",CONCATENATE(TEXT(B20,"00"),".",TEXT(C20,"000"),".",TEXT(D20,"000"),".",TEXT(E20,"000")),""))))) -> 01.001.002.002 | J20: Tela soldada para ligacao alvenaria/estrutura | K20: un | L20: =ROUNDUP(ARQUITETURA!H196,0) -> 3924 | M20: 4.1072 | N20: =IF(H20="Serviço",M20*L20,IF(H20="CÉLULA CONSTRUTIVA",SUMIFS($N$8:$N$262,$B$8:$B$262,B20,$H$8:$H$262,"Serviço"),IF(H20="ETAPA",SUMIFS($N$8:$N$262,$B$8:$B$262,B20,$C$8:$C$262,C20,$H$8:$H$262,"Serviço"),IF(H20="SUBETAPA",SUMIFS($N$8:$N$262,$B$8:$B$262,B20,$C$8:$C$262,C20,$D$8:$D$262,D20,$H$8:$H$262,"Serviço"),0)))) -> 16116.653
A21: =IF($H21="UNIDADE CONSTRUTIVA",OFFSET(A21,-1,0)+1,LARGE(A$3:A20,1)) -> 0 | B21: =IF(H21="UNIDADE CONSTRUTIVA",0,IF(H21="CÉLULA CONSTRUTIVA",OFFSET(B21,-1,0)+1,OFFSET(B21,-1,0))) -> 1 | C21: =IF(H21="CÉLULA CONSTRUTIVA",0,IF(H21="ETAPA",OFFSET(C21,-1,0)+1,OFFSET(C21,-1,0))) -> 1 | D21: =IF(H21="ETAPA",0,IF(H21="SUBETAPA",OFFSET(D21,-1,0)+1,OFFSET(D21,-1,0))) -> 2 | E21: =IF(H21="Subetapa",0,IF(H21="serviço",OFFSET(E21,-1,0)+1,OFFSET(E21,-1,0))) -> 3 | H21: SERVIÇO | I21: =IF(H21="Unidade Construtiva",TEXT(A21,"00"),IF(H21="Célula Construtiva",TEXT(B21,"00"),IF(H21="Etapa",CONCATENATE(TEXT(B21,"00"),".",TEXT(C21,"000")),IF(H21="Subetapa",CONCATENATE(TEXT(B21,"00"),".",TEXT(C21,"000"),".",TEXT(D21,"000")),IF(H21="Serviço",CONCATENATE(TEXT(B21,"00"),".",TEXT(C21,"000"),".",TEXT(D21,"000"),".",TEXT(E21,"000")),""))))) -> 01.001.002.003 | J21: Verga/contraverga de concreto, moldada in loco | K21: m | L21: =ARQUITETURA!H194+ARQUITETURA!H197+ARQUITETURA!H198 -> 2642.46 | M21: 80.381545 | N21: =IF(H21="Serviço",M21*L21,IF(H21="CÉLULA CONSTRUTIVA",SUMIFS($N$8:$N$262,$B$8:$B$262,B21,$H$8:$H$262,"Serviço"),IF(H21="ETAPA",SUMIFS($N$8:$N$262,$B$8:$B$262,B21,$C$8:$C$262,C21,$H$8:$H$262,"Serviço"),IF(H21="SUBETAPA",SUMIFS($N$8:$N$262,$B$8:$B$262,B21,$C$8:$C$262,C21,$D$8:$D$262,D21,$H$8:$H$262,"Serviço"),0)))) -> 212405.02
A22: =IF($H22="UNIDADE CONSTRUTIVA",OFFSET(A22,-1,0)+1,LARGE(A$3:A21,1)) -> 0 | B22: =IF(H22="UNIDADE CONSTRUTIVA",0,IF(H22="CÉLULA CONSTRUTIVA",OFFSET(B22,-1,0)+1,OFFSET(B22,-1,0))) -> 1 | C22: =IF(H22="CÉLULA CONSTRUTIVA",0,IF(H22="ETAPA",OFFSET(C22,-1,0)+1,OFFSET(C22,-1,0))) -> 1 | D22: =IF(H22="ETAPA",0,IF(H22="SUBETAPA",OFFSET(D22,-1,0)+1,OFFSET(D22,-1,0))) -> 3 | E22: =IF(H22="Subetapa",0,IF(H22="serviço",OFFSET(E22,-1,0)+1,OFFSET(E22,-1,0))) -> 0 | H22: SUBETAPA | I22: =IF(H22="Unidade Construtiva",TEXT(A22,"00"),IF(H22="Célula Construtiva",TEXT(B22,"00"),IF(H22="Etapa",CONCATENATE(TEXT(B22,"00"),".",TEXT(C22,"000")),IF(H22="Subetapa",CONCATENATE(TEXT(B22,"00"),".",TEXT(C22,"000"),".",TEXT(D22,"000")),IF(H22="Serviço",CONCATENATE(TEXT(B22,"00"),".",TEXT(C22,"000"),".",TEXT(D22,"000"),".",TEXT(E22,"000")),""))))) -> 01.001.003 | J22: Drywall | N22: =IF(H22="Serviço",M22*L22,IF(H22="CÉLULA CONSTRUTIVA",SUMIFS($N$8:$N$262,$B$8:$B$262,B22,$H$8:$H$262,"Serviço"),IF(H22="ETAPA",SUMIFS($N$8:$N$262,$B$8:$B$262,B22,$C$8:$C$262,C22,$H$8:$H$262,"Serviço"),IF(H22="SUBETAPA",SUMIFS($N$8:$N$262,$B$8:$B$262,B22,$C$8:$C$262,C22,$D$8:$D$262,D22,$H$8:$H$262,"Serviço"),0)))) -> 638363.57
A23: =IF($H23="UNIDADE CONSTRUTIVA",OFFSET(A23,-1,0)+1,LARGE(A$3:A22,1)) -> 0 | B23: =IF(H23="UNIDADE CONSTRUTIVA",0,IF(H23="CÉLULA CONSTRUTIVA",OFFSET(B23,-1,0)+1,OFFSET(B23,-1,0))) -> 1 | C23: =IF(H23="CÉLULA CONSTRUTIVA",0,IF(H23="ETAPA",OFFSET(C23,-1,0)+1,OFFSET(C23,-1,0))) -> 1 | D23: =IF(H23="ETAPA",0,IF(H23="SUBETAPA",OFFSET(D23,-1,0)+1,OFFSET(D23,-1,0))) -> 3 | E23: =IF(H23="Subetapa",0,IF(H23="serviço",OFFSET(E23,-1,0)+1,OFFSET(E23,-1,0))) -> 1 | H23: SERVIÇO | I23: =IF(H23="Unidade Construtiva",TEXT(A23,"00"),IF(H23="Célula Construtiva",TEXT(B23,"00"),IF(H23="Etapa",CONCATENATE(TEXT(B23,"00"),".",TEXT(C23,"000")),IF(H23="Subetapa",CONCATENATE(TEXT(B23,"00"),".",TEXT(C23,"000"),".",TEXT(D23,"000")),IF(H23="Serviço",CONCATENATE(TEXT(B23,"00"),".",TEXT(C23,"000"),".",TEXT(D23,"000"),".",TEXT(E23,"000")),""))))) -> 01.001.003.001 | J23: Parede Com Sistema Em Chapas De Gesso Para Drywall, Uso Interno, Montante 70mm, Com Uma Face Resistente a Umidade(RU/70) | K23: m2 | L23: =ARQUITETURA!H322+ARQUITETURA!H323 -> 3630.03 | M23: 128.62074 | N23: =IF(H23="Serviço",M23*L23,IF(H23="CÉLULA CONSTRUTIVA",SUMIFS($N$8:$N$262,$B$8:$B$262,B23,$H$8:$H$262,"Serviço"),IF(H23="ETAPA",SUMIFS($N$8:$N$262,$B$8:$B$262,B23,$C$8:$C$262,C23,$H$8:$H$262,"Serviço"),IF(H23="SUBETAPA",SUMIFS($N$8:$N$262,$B$8:$B$262,B23,$C$8:$C$262,C23,$D$8:$D$262,D23,$H$8:$H$262,"Serviço"),0)))) -> 466897.16
A24: =IF($H24="UNIDADE CONSTRUTIVA",OFFSET(A24,-1,0)+1,LARGE(A$3:A23,1)) -> 0 | B24: =IF(H24="UNIDADE CONSTRUTIVA",0,IF(H24="CÉLULA CONSTRUTIVA",OFFSET(B24,-1,0)+1,OFFSET(B24,-1,0))) -> 1 | C24: =IF(H24="CÉLULA CONSTRUTIVA",0,IF(H24="ETAPA",OFFSET(C24,-1,0)+1,OFFSET(C24,-1,0))) -> 1 | D24: =IF(H24="ETAPA",0,IF(H24="SUBETAPA",OFFSET(D24,-1,0)+1,OFFSET(D24,-1,0))) -> 3 | E24: =IF(H24="Subetapa",0,IF(H24="serviço",OFFSET(E24,-1,0)+1,OFFSET(E24,-1,0))) -> 2 | H24: SERVIÇO | I24: =IF(H24="Unidade Construtiva",TEXT(A24,"00"),IF(H24="Célula Construtiva",TEXT(B24,"00"),IF(H24="Etapa",CONCATENATE(TEXT(B24,"00"),".",TEXT(C24,"000")),IF(H24="Subetapa",CONCATENATE(TEXT(B24,"00"),".",TEXT(C24,"000"),".",TEXT(D24,"000")),IF(H24="Serviço",CONCATENATE(TEXT(B24,"00"),".",TEXT(C24,"000"),".",TEXT(D24,"000"),".",TEXT(E24,"000")),""))))) -> 01.001.003.002 | J24: Parede Com Sistema Em Chapas De Gesso Para Drywall, Uso Interno, Montante 70mm, Com Uma Face Resistente a Umidade(RU/70) - com tratamento de junta | K24: m2 | L24: =SUM(ARQUITETURA!F380:F459) -> 1305.21 | M24: 131.37074 | N24: =IF(H24="Serviço",M24*L24,IF(H24="CÉLULA CONSTRUTIVA",SUMIFS($N$8:$N$262,$B$8:$B$262,B24,$H$8:$H$262,"Serviço"),IF(H24="ETAPA",SUMIFS($N$8:$N$262,$B$8:$B$262,B24,$C$8:$C$262,C24,$H$8:$H$262,"Serviço"),IF(H24="SUBETAPA",SUMIFS($N$8:$N$262,$B$8:$B$262,B24,$C$8:$C$262,C24,$D$8:$D$262,D24,$H$8:$H$262,"Serviço"),0)))) -> 171466.41
A25: =IF($H25="UNIDADE CONSTRUTIVA",OFFSET(A25,-1,0)+1,LARGE(A$3:A23,1)) -> 0 | B25: =IF(H25="UNIDADE CONSTRUTIVA",0,IF(H25="CÉLULA CONSTRUTIVA",OFFSET(B25,-1,0)+1,OFFSET(B25,-1,0))) -> 1 | C25: =IF(H25="CÉLULA CONSTRUTIVA",0,IF(H25="ETAPA",OFFSET(C25,-1,0)+1,OFFSET(C25,-1,0))) -> 1 | D25: =IF(H25="ETAPA",0,IF(H25="SUBETAPA",OFFSET(D25,-1,0)+1,OFFSET(D25,-1,0))) -> 4 | E25: =IF(H25="Subetapa",0,IF(H25="serviço",OFFSET(E25,-1,0)+1,OFFSET(E25,-1,0))) -> 0 | H25: SUBETAPA | I25: =IF(H25="Unidade Construtiva",TEXT(A25,"00"),IF(H25="Célula Construtiva",TEXT(B25,"00"),IF(H25="Etapa",CONCATENATE(TEXT(B25,"00"),".",TEXT(C25,"000")),IF(H25="Subetapa",CONCATENATE(TEXT(B25,"00"),".",TEXT(C25,"000"),".",TEXT(D25,"000")),IF(H25="Serviço",CONCATENATE(TEXT(B25,"00"),".",TEXT(C25,"000"),".",TEXT(D25,"000"),".",TEXT(E25,"000")),""))))) -> 01.001.004 | J25: Mão de obra | N25: =IF(H25="Serviço",M25*L25,IF(H25="CÉLULA CONSTRUTIVA",SUMIFS($N$8:$N$262,$B$8:$B$262,B25,$H$8:$H$262,"Serviço"),IF(H25="ETAPA",SUMIFS($N$8:$N$262,$B$8:$B$262,B25,$C$8:$C$262,C25,$H$8:$H$262,"Serviço"),IF(H25="SUBETAPA",SUMIFS($N$8:$N$262,$B$8:$B$262,B25,$C$8:$C$262,C25,$D$8:$D$262,D25,$H$8:$H$262,"Serviço"),0)))) -> 376608.48
A26: =IF($H26="UNIDADE CONSTRUTIVA",OFFSET(A26,-1,0)+1,LARGE(A$3:A25,1)) -> 0 | B26: =IF(H26="UNIDADE CONSTRUTIVA",0,IF(H26="CÉLULA CONSTRUTIVA",OFFSET(B26,-1,0)+1,OFFSET(B26,-1,0))) -> 1 | C26: =IF(H26="CÉLULA CONSTRUTIVA",0,IF(H26="ETAPA",OFFSET(C26,-1,0)+1,OFFSET(C26,-1,0))) -> 1 | D26: =IF(H26="ETAPA",0,IF(H26="SUBETAPA",OFFSET(D26,-1,0)+1,OFFSET(D26,-1,0))) -> 4 | E26: =IF(H26="Subetapa",0,IF(H26="serviço",OFFSET(E26,-1,0)+1,OFFSET(E26,-1,0))) -> 1 | H26: SERVIÇO | I26: =IF(H26="Unidade Construtiva",TEXT(A26,"00"),IF(H26="Célula Construtiva",TEXT(B26,"00"),IF(H26="Etapa",CONCATENATE(TEXT(B26,"00"),".",TEXT(C26,"000")),IF(H26="Subetapa",CONCATENATE(TEXT(B26,"00"),".",TEXT(C26,"000"),".",TEXT(D26,"000")),IF(H26="Serviço",CONCATENATE(TEXT(B26,"00"),".",TEXT(C26,"000"),".",TEXT(D26,"000"),".",TEXT(E26,"000")),""))))) -> 01.001.004.001 | J26: Mão de obra para assentamento de blocos cerâmicos | K26: m2 | L26: =SUM(L14:L17) -> 3466.31 | M26: 48 | N26: =IF(H26="Serviço",M26*L26,IF(H26="CÉLULA CONSTRUTIVA",SUMIFS($N$8:$N$262,$B$8:$B$262,B26,$H$8:$H$262,"Serviço"),IF(H26="ETAPA",SUMIFS($N$8:$N$262,$B$8:$B$262,B26,$C$8:$C$262,C26,$H$8:$H$262,"Serviço"),IF(H26="SUBETAPA",SUMIFS($N$8:$N$262,$B$8:$B$262,B26,$C$8:$C$262,C26,$D$8:$D$262,D26,$H$8:$H$262,"Serviço"),0)))) -> 166382.88
A27: =IF($H27="UNIDADE CONSTRUTIVA",OFFSET(A27,-1,0)+1,LARGE(A$3:A26,1)) -> 0 | B27: =IF(H27="UNIDADE CONSTRUTIVA",0,IF(H27="CÉLULA CONSTRUTIVA",OFFSET(B27,-1,0)+1,OFFSET(B27,-1,0))) -> 1 | C27: =IF(H27="CÉLULA CONSTRUTIVA",0,IF(H27="ETAPA",OFFSET(C27,-1,0)+1,OFFSET(C27,-1,0))) -> 1 | D27: =IF(H27="ETAPA",0,IF(H27="SUBETAPA",OFFSET(D27,-1,0)+1,OFFSET(D27,-1,0))) -> 4 | E27: =IF(H27="Subetapa",0,IF(H27="serviço",OFFSET(E27,-1,0)+1,OFFSET(E27,-1,0))) -> 2 | H27: SERVIÇO | I27: =IF(H27="Unidade Construtiva",TEXT(A27,"00"),IF(H27="Célula Construtiva",TEXT(B27,"00"),IF(H27="Etapa",CONCATENATE(TEXT(B27,"00"),".",TEXT(C27,"000")),IF(H27="Subetapa",CONCATENATE(TEXT(B27,"00"),".",TEXT(C27,"000"),".",TEXT(D27,"000")),IF(H27="Serviço",CONCATENATE(TEXT(B27,"00"),".",TEXT(C27,"000"),".",TEXT(D27,"000"),".",TEXT(E27,"000")),""))))) -> 01.001.004.002 | J27: Mão de obra para assentamento de blocos concreto | K27: m2 | L27: =SUM(L11:L13) -> 4379.7 | M27: 48 | N27: =IF(H27="Serviço",M27*L27,IF(H27="CÉLULA CONSTRUTIVA",SUMIFS($N$8:$N$262,$B$8:$B$262,B27,$H$8:$H$262,"Serviço"),IF(H27="ETAPA",SUMIFS($N$8:$N$262,$B$8:$B$262,B27,$C$8:$C$262,C27,$H$8:$H$262,"Serviço"),IF(H27="SUBETAPA",SUMIFS($N$8:$N$262,$B$8:$B$262,B27,$C$8:$C$262,C27,$D$8:$D$262,D27,$H$8:$H$262,"Serviço"),0)))) -> 210225.6
A28: =IF($H28="UNIDADE CONSTRUTIVA",OFFSET(A28,-1,0)+1,LARGE(A$3:A27,1)) -> 0 | B28: =IF(H28="UNIDADE CONSTRUTIVA",0,IF(H28="CÉLULA CONSTRUTIVA",OFFSET(B28,-1,0)+1,OFFSET(B28,-1,0))) -> 2 | C28: =IF(H28="CÉLULA CONSTRUTIVA",0,IF(H28="ETAPA",OFFSET(C28,-1,0)+1,OFFSET(C28,-1,0))) -> 0 | D28: =IF(H28="ETAPA",0,IF(H28="SUBETAPA",OFFSET(D28,-1,0)+1,OFFSET(D28,-1,0))) -> 4 | E28: =IF(H28="Subetapa",0,IF(H28="serviço",OFFSET(E28,-1,0)+1,OFFSET(E28,-1,0))) -> 2 | H28: CÉLULA CONSTRUTIVA | I28: =IF(H28="Unidade Construtiva",TEXT(A28,"00"),IF(H28="Célula Construtiva",TEXT(B28,"00"),IF(H28="Etapa",CONCATENATE(TEXT(B28,"00"),".",TEXT(C28,"000")),IF(H28="Subetapa",CONCATENATE(TEXT(B28,"00"),".",TEXT(C28,"000"),".",TEXT(D28,"000")),IF(H28="Serviço",CONCATENATE(TEXT(B28,"00"),".",TEXT(C28,"000"),".",TEXT(D28,"000"),".",TEXT(E28,"000")),""))))) -> 02 | J28: IMPERMEABILIZAÇÃO E TRATAMENTOS | N28: =IF(H28="Serviço",M28*L28,IF(H28="CÉLULA CONSTRUTIVA",SUMIFS($N$8:$N$262,$B$8:$B$262,B28,$H$8:$H$262,"Serviço"),IF(H28="ETAPA",SUMIFS($N$8:$N$262,$B$8:$B$262,B28,$C$8:$C$262,C28,$H$8:$H$262,"Serviço"),IF(H28="SUBETAPA",SUMIFS($N$8:$N$262,$B$8:$B$262,B28,$C$8:$C$262,C28,$D$8:$D$262,D28,$H$8:$H$262,"Serviço"),0)))) -> 703992.08 | O28: =N28/'Obra '!$E$9 -> 101.46332 | Q28: IMPERMEABILIZAÇÃO
A29: =IF($H29="UNIDADE CONSTRUTIVA",OFFSET(A29,-1,0)+1,LARGE(A$3:A28,1)) -> 0 | B29: =IF(H29="UNIDADE CONSTRUTIVA",0,IF(H29="CÉLULA CONSTRUTIVA",OFFSET(B29,-1,0)+1,OFFSET(B29,-1,0))) -> 2 | C29: =IF(H29="CÉLULA CONSTRUTIVA",0,IF(H29="ETAPA",OFFSET(C29,-1,0)+1,OFFSET(C29,-1,0))) -> 1 | D29: =IF(H29="ETAPA",0,IF(H29="SUBETAPA",OFFSET(D29,-1,0)+1,OFFSET(D29,-1,0))) -> 0 | E29: =IF(H29="Subetapa",0,IF(H29="serviço",OFFSET(E29,-1,0)+1,OFFSET(E29,-1,0))) -> 2 | H29: ETAPA | I29: =IF(H29="Unidade Construtiva",TEXT(A29,"00"),IF(H29="Célula Construtiva",TEXT(B29,"00"),IF(H29="Etapa",CONCATENATE(TEXT(B29,"00"),".",TEXT(C29,"000")),IF(H29="Subetapa",CONCATENATE(TEXT(B29,"00"),".",TEXT(C29,"000"),".",TEXT(D29,"000")),IF(H29="Serviço",CONCATENATE(TEXT(B29,"00"),".",TEXT(C29,"000"),".",TEXT(D29,"000"),".",TEXT(E29,"000")),""))))) -> 02.001 | J29: IMPERMEABILIZAÇÃO E TRATAMENTOS | N29: =IF(H29="Serviço",M29*L29,IF(H29="CÉLULA CONSTRUTIVA",SUMIFS($N$8:$N$262,$B$8:$B$262,B29,$H$8:$H$262,"Serviço"),IF(H29="ETAPA",SUMIFS($N$8:$N$262,$B$8:$B$262,B29,$C$8:$C$262,C29,$H$8:$H$262,"Serviço"),IF(H29="SUBETAPA",SUMIFS($N$8:$N$262,$B$8:$B$262,B29,$C$8:$C$262,C29,$D$8:$D$262,D29,$H$8:$H$262,"Serviço"),0)))) -> 703992.08
A30: =IF($H30="UNIDADE CONSTRUTIVA",OFFSET(A30,-1,0)+1,LARGE(A$3:A29,1)) -> 0 | B30: =IF(H30="UNIDADE CONSTRUTIVA",0,IF(H30="CÉLULA CONSTRUTIVA",OFFSET(B30,-1,0)+1,OFFSET(B30,-1,0))) -> 2 | C30: =IF(H30="CÉLULA CONSTRUTIVA",0,IF(H30="ETAPA",OFFSET(C30,-1,0)+1,OFFSET(C30,-1,0))) -> 1 | D30: =IF(H30="ETAPA",0,IF(H30="SUBETAPA",OFFSET(D30,-1,0)+1,OFFSET(D30,-1,0))) -> 1 | E30: =IF(H30="Subetapa",0,IF(H30="serviço",OFFSET(E30,-1,0)+1,OFFSET(E30,-1,0))) -> 0 | H30: SUBETAPA | I30: =IF(H30="Unidade Construtiva",TEXT(A30,"00"),IF(H30="Célula Construtiva",TEXT(B30,"00"),IF(H30="Etapa",CONCATENATE(TEXT(B30,"00"),".",TEXT(C30,"000")),IF(H30="Subetapa",CONCATENATE(TEXT(B30,"00"),".",TEXT(C30,"000"),".",TEXT(D30,"000")),IF(H30="Serviço",CONCATENATE(TEXT(B30,"00"),".",TEXT(C30,"000"),".",TEXT(D30,"000"),".",TEXT(E30,"000")),""))))) -> 02.001.001 | J30: Regularização e proteção mecânica | N30: =IF(H30="Serviço",M30*L30,IF(H30="CÉLULA CONSTRUTIVA",SUMIFS($N$8:$N$262,$B$8:$B$262,B30,$H$8:$H$262,"Serviço"),IF(H30="ETAPA",SUMIFS($N$8:$N$262,$B$8:$B$262,B30,$C$8:$C$262,C30,$H$8:$H$262,"Serviço"),IF(H30="SUBETAPA",SUMIFS($N$8:$N$262,$B$8:$B$262,B30,$C$8:$C$262,C30,$D$8:$D$262,D30,$H$8:$H$262,"Serviço"),0)))) -> 58243.88
A31: =IF($H31="UNIDADE CONSTRUTIVA",OFFSET(A31,-1,0)+1,LARGE(A$3:A30,1)) -> 0 | B31: =IF(H31="UNIDADE CONSTRUTIVA",0,IF(H31="CÉLULA CONSTRUTIVA",OFFSET(B31,-1,0)+1,OFFSET(B31,-1,0))) -> 2 | C31: =IF(H31="CÉLULA CONSTRUTIVA",0,IF(H31="ETAPA",OFFSET(C31,-1,0)+1,OFFSET(C31,-1,0))) -> 1 | D31: =IF(H31="ETAPA",0,IF(H31="SUBETAPA",OFFSET(D31,-1,0)+1,OFFSET(D31,-1,0))) -> 1 | E31: =IF(H31="Subetapa",0,IF(H31="serviço",OFFSET(E31,-1,0)+1,OFFSET(E31,-1,0))) -> 1 | H31: SERVIÇO | I31: =IF(H31="Unidade Construtiva",TEXT(A31,"00"),IF(H31="Célula Construtiva",TEXT(B31,"00"),IF(H31="Etapa",CONCATENATE(TEXT(B31,"00"),".",TEXT(C31,"000")),IF(H31="Subetapa",CONCATENATE(TEXT(B31,"00"),".",TEXT(C31,"000"),".",TEXT(D31,"000")),IF(H31="Serviço",CONCATENATE(TEXT(B31,"00"),".",TEXT(C31,"000"),".",TEXT(D31,"000"),".",TEXT(E31,"000")),""))))) -> 02.001.001.001 | J31: Regularização de superfície para impermeabilização | K31: m2 | L31: =ARQUITETURA!H742 -> 2847.53 | M31: 7.0659 | N31: =IF(H31="Serviço",M31*L31,IF(H31="CÉLULA CONSTRUTIVA",SUMIFS($N$8:$N$262,$B$8:$B$262,B31,$H$8:$H$262,"Serviço"),IF(H31="ETAPA",SUMIFS($N$8:$N$262,$B$8:$B$262,B31,$C$8:$C$262,C31,$H$8:$H$262,"Serviço"),IF(H31="SUBETAPA",SUMIFS($N$8:$N$262,$B$8:$B$262,B31,$C$8:$C$262,C31,$D$8:$D$262,D31,$H$8:$H$262,"Serviço"),0)))) -> 20120.362 | O31: Considerado somente nos pisos que recebem impermeabilização
A32: =IF($H32="UNIDADE CONSTRUTIVA",OFFSET(A32,-1,0)+1,LARGE(A$3:A31,1)) -> 0 | B32: =IF(H32="UNIDADE CONSTRUTIVA",0,IF(H32="CÉLULA CONSTRUTIVA",OFFSET(B32,-1,0)+1,OFFSET(B32,-1,0))) -> 2 | C32: =IF(H32="CÉLULA CONSTRUTIVA",0,IF(H32="ETAPA",OFFSET(C32,-1,0)+1,OFFSET(C32,-1,0))) -> 1 | D32: =IF(H32="ETAPA",0,IF(H32="SUBETAPA",OFFSET(D32,-1,0)+1,OFFSET(D32,-1,0))) -> 1 | E32: =IF(H32="Subetapa",0,IF(H32="serviço",OFFSET(E32,-1,0)+1,OFFSET(E32,-1,0))) -> 2 | H32: SERVIÇO | I32: =IF(H32="Unidade Construtiva",TEXT(A32,"00"),IF(H32="Célula Construtiva",TEXT(B32,"00"),IF(H32="Etapa",CONCATENATE(TEXT(B32,"00"),".",TEXT(C32,"000")),IF(H32="Subetapa",CONCATENATE(TEXT(B32,"00"),".",TEXT(C32,"000"),".",TEXT(D32,"000")),IF(H32="Serviço",CONCATENATE(TEXT(B32,"00"),".",TEXT(C32,"000"),".",TEXT(D32,"000"),".",TEXT(E32,"000")),""))))) -> 02.001.001.002 | J32: Proteção mecânica de superfície com argamassa de cimento e areia, traço 1:3 E=5cm | K32: m2 | L32: =ARQUITETURA!H741 -> 772.38 | M32: 49.3585 | N32: =IF(H32="Serviço",M32*L32,IF(H32="CÉLULA CONSTRUTIVA",SUMIFS($N$8:$N$262,$B$8:$B$262,B32,$H$8:$H$262,"Serviço"),IF(H32="ETAPA",SUMIFS($N$8:$N$262,$B$8:$B$262,B32,$C$8:$C$262,C32,$H$8:$H$262,"Serviço"),IF(H32="SUBETAPA",SUMIFS($N$8:$N$262,$B$8:$B$262,B32,$C$8:$C$262,C32,$D$8:$D$262,D32,$H$8:$H$262,"Serviço"),0)))) -> 38123.518 | O32: Considerado somente nos pisos que recebem manta asfaltica
A33: =IF($H33="UNIDADE CONSTRUTIVA",OFFSET(A33,-1,0)+1,LARGE(A$3:A32,1)) -> 0 | B33: =IF(H33="UNIDADE CONSTRUTIVA",0,IF(H33="CÉLULA CONSTRUTIVA",OFFSET(B33,-1,0)+1,OFFSET(B33,-1,0))) -> 2 | C33: =IF(H33="CÉLULA CONSTRUTIVA",0,IF(H33="ETAPA",OFFSET(C33,-1,0)+1,OFFSET(C33,-1,0))) -> 1 | D33: =IF(H33="ETAPA",0,IF(H33="SUBETAPA",OFFSET(D33,-1,0)+1,OFFSET(D33,-1,0))) -> 2 | E33: =IF(H33="Subetapa",0,IF(H33="serviço",OFFSET(E33,-1,0)+1,OFFSET(E33,-1,0))) -> 0 | H33: SUBETAPA | I33: =IF(H33="Unidade Construtiva",TEXT(A33,"00"),IF(H33="Célula Construtiva",TEXT(B33,"00"),IF(H33="Etapa",CONCATENATE(TEXT(B33,"00"),".",TEXT(C33,"000")),IF(H33="Subetapa",CONCATENATE(TEXT(B33,"00"),".",TEXT(C33,"000"),".",TEXT(D33,"000")),IF(H33="Serviço",CONCATENATE(TEXT(B33,"00"),".",TEXT(C33,"000"),".",TEXT(D33,"000"),".",TEXT(E33,"000")),""))))) -> 02.001.002 | J33: Impermeabilização de fundação e contenção | N33: =IF(H33="Serviço",M33*L33,IF(H33="CÉLULA CONSTRUTIVA",SUMIFS($N$8:$N$262,$B$8:$B$262,B33,$H$8:$H$262,"Serviço"),IF(H33="ETAPA",SUMIFS($N$8:$N$262,$B$8:$B$262,B33,$C$8:$C$262,C33,$H$8:$H$262,"Serviço"),IF(H33="SUBETAPA",SUMIFS($N$8:$N$262,$B$8:$B$262,B33,$C$8:$C$262,C33,$D$8:$D$262,D33,$H$8:$H$262,"Serviço"),0)))) -> 8300.3378
A34: =IF($H34="UNIDADE CONSTRUTIVA",OFFSET(A34,-1,0)+1,LARGE(A$3:A33,1)) -> 0 | B34: =IF(H34="UNIDADE CONSTRUTIVA",0,IF(H34="CÉLULA CONSTRUTIVA",OFFSET(B34,-1,0)+1,OFFSET(B34,-1,0))) -> 2 | C34: =IF(H34="CÉLULA CONSTRUTIVA",0,IF(H34="ETAPA",OFFSET(C34,-1,0)+1,OFFSET(C34,-1,0))) -> 1 | D34: =IF(H34="ETAPA",0,IF(H34="SUBETAPA",OFFSET(D34,-1,0)+1,OFFSET(D34,-1,0))) -> 2 | E34: =IF(H34="Subetapa",0,IF(H34="serviço",OFFSET(E34,-1,0)+1,OFFSET(E34,-1,0))) -> 1 | H34: SERVIÇO | I34: =IF(H34="Unidade Construtiva",TEXT(A34,"00"),IF(H34="Célula Construtiva",TEXT(B34,"00"),IF(H34="Etapa",CONCATENATE(TEXT(B34,"00"),".",TEXT(C34,"000")),IF(H34="Subetapa",CONCATENATE(TEXT(B34,"00"),".",TEXT(C34,"000"),".",TEXT(D34,"000")),IF(H34="Serviço",CONCATENATE(TEXT(B34,"00"),".",TEXT(C34,"000"),".",TEXT(D34,"000"),".",TEXT(E34,"000")),""))))) -> 02.001.002.001 | J34: C4 - Argamassa polimérica rígida, estruturada com tela de poliéster nos pontos críticos (4,0 kg/m²) | K34: m2 | L34: =IMPERMEABILIZAÇÃO!B139 -> 209.84 | M34: 39.555556 | N34: =IF(H34="Serviço",M34*L34,IF(H34="CÉLULA CONSTRUTIVA",SUMIFS($N$8:$N$262,$B$8:$B$262,B34,$H$8:$H$262,"Serviço"),IF(H34="ETAPA",SUMIFS($N$8:$N$262,$B$8:$B$262,B34,$C$8:$C$262,C34,$H$8:$H$262,"Serviço"),IF(H34="SUBETAPA",SUMIFS($N$8:$N$262,$B$8:$B$262,B34,$C$8:$C$262,C34,$D$8:$D$262,D34,$H$8:$H$262,"Serviço"),0)))) -> 8300.3378
A35: =IF($H35="UNIDADE CONSTRUTIVA",OFFSET(A35,-1,0)+1,LARGE(A$3:A34,1)) -> 0 | B35: =IF(H35="UNIDADE CONSTRUTIVA",0,IF(H35="CÉLULA CONSTRUTIVA",OFFSET(B35,-1,0)+1,OFFSET(B35,-1,0))) -> 2 | C35: =IF(H35="CÉLULA CONSTRUTIVA",0,IF(H35="ETAPA",OFFSET(C35,-1,0)+1,OFFSET(C35,-1,0))) -> 1 | D35: =IF(H35="ETAPA",0,IF(H35="SUBETAPA",OFFSET(D35,-1,0)+1,OFFSET(D35,-1,0))) -> 3 | E35: =IF(H35="Subetapa",0,IF(H35="serviço",OFFSET(E35,-1,0)+1,OFFSET(E35,-1,0))) -> 0 | H35: SUBETAPA | I35: =IF(H35="Unidade Construtiva",TEXT(A35,"00"),IF(H35="Célula Construtiva",TEXT(B35,"00"),IF(H35="Etapa",CONCATENATE(TEXT(B35,"00"),".",TEXT(C35,"000")),IF(H35="Subetapa",CONCATENATE(TEXT(B35,"00"),".",TEXT(C35,"000"),".",TEXT(D35,"000")),IF(H35="Serviço",CONCATENATE(TEXT(B35,"00"),".",TEXT(C35,"000"),".",TEXT(D35,"000"),".",TEXT(E35,"000")),""))))) -> 02.001.003 | J35: Impermeabilização de lajes e terraços | N35: =IF(H35="Serviço",M35*L35,IF(H35="CÉLULA CONSTRUTIVA",SUMIFS($N$8:$N$262,$B$8:$B$262,B35,$H$8:$H$262,"Serviço"),IF(H35="ETAPA",SUMIFS($N$8:$N$262,$B$8:$B$262,B35,$C$8:$C$262,C35,$H$8:$H$262,"Serviço"),IF(H35="SUBETAPA",SUMIFS($N$8:$N$262,$B$8:$B$262,B35,$C$8:$C$262,C35,$D$8:$D$262,D35,$H$8:$H$262,"Serviço"),0)))) -> 144021.66
A36: =IF($H36="UNIDADE CONSTRUTIVA",OFFSET(A36,-1,0)+1,LARGE(A$3:A35,1)) -> 0 | B36: =IF(H36="UNIDADE CONSTRUTIVA",0,IF(H36="CÉLULA CONSTRUTIVA",OFFSET(B36,-1,0)+1,OFFSET(B36,-1,0))) -> 2 | C36: =IF(H36="CÉLULA CONSTRUTIVA",0,IF(H36="ETAPA",OFFSET(C36,-1,0)+1,OFFSET(C36,-1,0))) -> 1 | D36: =IF(H36="ETAPA",0,IF(H36="SUBETAPA",OFFSET(D36,-1,0)+1,OFFSET(D36,-1,0))) -> 3 | E36: =IF(H36="Subetapa",0,IF(H36="serviço",OFFSET(E36,-1,0)+1,OFFSET(E36,-1,0))) -> 1 | H36: SERVIÇO | I36: =IF(H36="Unidade Construtiva",TEXT(A36,"00"),IF(H36="Célula Construtiva",TEXT(B36,"00"),IF(H36="Etapa",CONCATENATE(TEXT(B36,"00"),".",TEXT(C36,"000")),IF(H36="Subetapa",CONCATENATE(TEXT(B36,"00"),".",TEXT(C36,"000"),".",TEXT(D36,"000")),IF(H36="Serviço",CONCATENATE(TEXT(B36,"00"),".",TEXT(C36,"000"),".",TEXT(D36,"000"),".",TEXT(E36,"000")),""))))) -> 02.001.003.001 | J36: C3 - Argamassa polimérica rígida, estruturada com tela de poliéster nos pontos críticos (3,0 kg/m²) | K36: m2 | L36: =SUMIFS(IMPERMEABILIZAÇÃO!B$13:B$145,IMPERMEABILIZAÇÃO!D$13:D$145,IMPERMEABILIZAÇÃO!$U$7,IMPERMEABILIZAÇÃO!E$13:E$145,Ger_Executivo!$I$35) -> 44.84 | M36: 29.666667 | N36: =IF(H36="Serviço",M36*L36,IF(H36="CÉLULA CONSTRUTIVA",SUMIFS($N$8:$N$262,$B$8:$B$262,B36,$H$8:$H$262,"Serviço"),IF(H36="ETAPA",SUMIFS($N$8:$N$262,$B$8:$B$262,B36,$C$8:$C$262,C36,$H$8:$H$262,"Serviço"),IF(H36="SUBETAPA",SUMIFS($N$8:$N$262,$B$8:$B$262,B36,$C$8:$C$262,C36,$D$8:$D$262,D36,$H$8:$H$262,"Serviço"),0)))) -> 1330.2533
A37: =IF($H37="UNIDADE CONSTRUTIVA",OFFSET(A37,-1,0)+1,LARGE(A$3:A36,1)) -> 0 | B37: =IF(H37="UNIDADE CONSTRUTIVA",0,IF(H37="CÉLULA CONSTRUTIVA",OFFSET(B37,-1,0)+1,OFFSET(B37,-1,0))) -> 2 | C37: =IF(H37="CÉLULA CONSTRUTIVA",0,IF(H37="ETAPA",OFFSET(C37,-1,0)+1,OFFSET(C37,-1,0))) -> 1 | D37: =IF(H37="ETAPA",0,IF(H37="SUBETAPA",OFFSET(D37,-1,0)+1,OFFSET(D37,-1,0))) -> 3 | E37: =IF(H37="Subetapa",0,IF(H37="serviço",OFFSET(E37,-1,0)+1,OFFSET(E37,-1,0))) -> 2 | H37: SERVIÇO | I37: =IF(H37="Unidade Construtiva",TEXT(A37,"00"),IF(H37="Célula Construtiva",TEXT(B37,"00"),IF(H37="Etapa",CONCATENATE(TEXT(B37,"00"),".",TEXT(C37,"000")),IF(H37="Subetapa",CONCATENATE(TEXT(B37,"00"),".",TEXT(C37,"000"),".",TEXT(D37,"000")),IF(H37="Serviço",CONCATENATE(TEXT(B37,"00"),".",TEXT(C37,"000"),".",TEXT(D37,"000"),".",TEXT(E37,"000")),""))))) -> 02.001.003.002 | J37: M44A - Manta asfáltica tipo IV, 4 mm A, com acabamento areia/areia aderida com asfalto oxidado (3,0 kg/m²) + banho de asfalto oxidado (2,0 kg/m²) | K37: m2 | L37: =SUMIFS(IMPERMEABILIZAÇÃO!B$13:B$145,IMPERMEABILIZAÇÃO!D$13:D$145,IMPERMEABILIZAÇÃO!$U$6,IMPERMEABILIZAÇÃO!E$13:E$145,Ger_Executivo!$I$35) -> 733.06 | M37: 108 | N37: =IF(H37="Serviço",M37*L37,IF(H37="CÉLULA CONSTRUTIVA",SUMIFS($N$8:$N$262,$B$8:$B$262,B37,$H$8:$H$262,"Serviço"),IF(H37="ETAPA",SUMIFS($N$8:$N$262,$B$8:$B$262,B37,$C$8:$C$262,C37,$H$8:$H$262,"Serviço"),IF(H37="SUBETAPA",SUMIFS($N$8:$N$262,$B$8:$B$262,B37,$C$8:$C$262,C37,$D$8:$D$262,D37,$H$8:$H$262,"Serviço"),0)))) -> 79170.48
A38: =IF($H38="UNIDADE CONSTRUTIVA",OFFSET(A38,-1,0)+1,LARGE(A$3:A37,1)) -> 0 | B38: =IF(H38="UNIDADE CONSTRUTIVA",0,IF(H38="CÉLULA CONSTRUTIVA",OFFSET(B38,-1,0)+1,OFFSET(B38,-1,0))) -> 2 | C38: =IF(H38="CÉLULA CONSTRUTIVA",0,IF(H38="ETAPA",OFFSET(C38,-1,0)+1,OFFSET(C38,-1,0))) -> 1 | D38: =IF(H38="ETAPA",0,IF(H38="SUBETAPA",OFFSET(D38,-1,0)+1,OFFSET(D38,-1,0))) -> 3 | E38: =IF(H38="Subetapa",0,IF(H38="serviço",OFFSET(E38,-1,0)+1,OFFSET(E38,-1,0))) -> 3 | H38: SERVIÇO | I38: =IF(H38="Unidade Construtiva",TEXT(A38,"00"),IF(H38="Célula Construtiva",TEXT(B38,"00"),IF(H38="Etapa",CONCATENATE(TEXT(B38,"00"),".",TEXT(C38,"000")),IF(H38="Subetapa",CONCATENATE(TEXT(B38,"00"),".",TEXT(C38,"000"),".",TEXT(D38,"000")),IF(H38="Serviço",CONCATENATE(TEXT(B38,"00"),".",TEXT(C38,"000"),".",TEXT(D38,"000"),".",TEXT(E38,"000")),""))))) -> 02.001.003.003 | J38: E3 - Membrana de polímero acrílico com cimento e fibras, estruturada com tela de poliéster nos pontos críticos (3,0 kg/m²) | K38: m2 | L38: =SUMIFS(IMPERMEABILIZAÇÃO!B$13:B$145,IMPERMEABILIZAÇÃO!D$13:D$145,IMPERMEABILIZAÇÃO!$U$4,IMPERMEABILIZAÇÃO!E$13:E$145,Ger_Executivo!$I$35) -> 565.63 | M38: 66 | N38: =IF(H38="Serviço",M38*L38,IF(H38="CÉLULA CONSTRUTIVA",SUMIFS($N$8:$N$262,$B$8:$B$262,B38,$H$8:$H$262,"Serviço"),IF(H38="ETAPA",SUMIFS($N$8:$N$262,$B$8:$B$262,B38,$C$8:$C$262,C38,$H$8:$H$262,"Serviço"),IF(H38="SUBETAPA",SUMIFS($N$8:$N$262,$B$8:$B$262,B38,$C$8:$C$262,C38,$D$8:$D$262,D38,$H$8:$H$262,"Serviço"),0)))) -> 37331.58
A39: =IF($H39="UNIDADE CONSTRUTIVA",OFFSET(A39,-1,0)+1,LARGE(A$3:A38,1)) -> 0 | B39: =IF(H39="UNIDADE CONSTRUTIVA",0,IF(H39="CÉLULA CONSTRUTIVA",OFFSET(B39,-1,0)+1,OFFSET(B39,-1,0))) -> 2 | C39: =IF(H39="CÉLULA CONSTRUTIVA",0,IF(H39="ETAPA",OFFSET(C39,-1,0)+1,OFFSET(C39,-1,0))) -> 1 | D39: =IF(H39="ETAPA",0,IF(H39="SUBETAPA",OFFSET(D39,-1,0)+1,OFFSET(D39,-1,0))) -> 3 | E39: =IF(H39="Subetapa",0,IF(H39="serviço",OFFSET(E39,-1,0)+1,OFFSET(E39,-1,0))) -> 4 | H39: SERVIÇO | I39: =IF(H39="Unidade Construtiva",TEXT(A39,"00"),IF(H39="Célula Construtiva",TEXT(B39,"00"),IF(H39="Etapa",CONCATENATE(TEXT(B39,"00"),".",TEXT(C39,"000")),IF(H39="Subetapa",CONCATENATE(TEXT(B39,"00"),".",TEXT(C39,"000"),".",TEXT(D39,"000")),IF(H39="Serviço",CONCATENATE(TEXT(B39,"00"),".",TEXT(C39,"000"),".",TEXT(D39,"000"),".",TEXT(E39,"000")),""))))) -> 02.001.003.004 | J39: M44A + M44AE2 - Manta asfáltica tipo IV, 4 mm + manta asfáltica tipo IV, 4 mm + banho de asfalto oxidado + membrana de polímero acrílico com cimento e fibras para combater eflorescência | K39: m2 | L39: =SUMIFS(IMPERMEABILIZAÇÃO!B$13:B$145,IMPERMEABILIZAÇÃO!D$13:D$145,IMPERMEABILIZAÇÃO!$U$15,IMPERMEABILIZAÇÃO!E$13:E$145,Ger_Executivo!$I$35) -> 3.64 | M39: 246 | N39: =IF(H39="Serviço",M39*L39,IF(H39="CÉLULA CONSTRUTIVA",SUMIFS($N$8:$N$262,$B$8:$B$262,B39,$H$8:$H$262,"Serviço"),IF(H39="ETAPA",SUMIFS($N$8:$N$262,$B$8:$B$262,B39,$C$8:$C$262,C39,$H$8:$H$262,"Serviço"),IF(H39="SUBETAPA",SUMIFS($N$8:$N$262,$B$8:$B$262,B39,$C$8:$C$262,C39,$D$8:$D$262,D39,$H$8:$H$262,"Serviço"),0)))) -> 895.44
A40: =IF($H40="UNIDADE CONSTRUTIVA",OFFSET(A40,-1,0)+1,LARGE(A$3:A39,1)) -> 0 | B40: =IF(H40="UNIDADE CONSTRUTIVA",0,IF(H40="CÉLULA CONSTRUTIVA",OFFSET(B40,-1,0)+1,OFFSET(B40,-1,0))) -> 2 | C40: =IF(H40="CÉLULA CONSTRUTIVA",0,IF(H40="ETAPA",OFFSET(C40,-1,0)+1,OFFSET(C40,-1,0))) -> 1 | D40: =IF(H40="ETAPA",0,IF(H40="SUBETAPA",OFFSET(D40,-1,0)+1,OFFSET(D40,-1,0))) -> 3 | E40: =IF(H40="Subetapa",0,IF(H40="serviço",OFFSET(E40,-1,0)+1,OFFSET(E40,-1,0))) -> 5 | H40: SERVIÇO | I40: =IF(H40="Unidade Construtiva",TEXT(A40,"00"),IF(H40="Célula Construtiva",TEXT(B40,"00"),IF(H40="Etapa",CONCATENATE(TEXT(B40,"00"),".",TEXT(C40,"000")),IF(H40="Subetapa",CONCATENATE(TEXT(B40,"00"),".",TEXT(C40,"000"),".",TEXT(D40,"000")),IF(H40="Serviço",CONCATENATE(TEXT(B40,"00"),".",TEXT(C40,"000"),".",TEXT(D40,"000"),".",TEXT(E40,"000")),""))))) -> 02.001.003.005 | J40: M44AR05 - Manta asfáltica tipo IV, 4 mm A, com acabamento areia/areia aderida com asfalto oxidado (3,0 kg/m²) + banho de asfalto oxidado (2,0 kg/m²) + pintura de proteção antirraiz sobre a proteção mecânica (0,5 L/m²) | K40: m2 | L40: =SUMIFS(IMPERMEABILIZAÇÃO!B$13:B$145,IMPERMEABILIZAÇÃO!D$13:D$145,IMPERMEABILIZAÇÃO!$U$14,IMPERMEABILIZAÇÃO!E$13:E$145,Ger_Executivo!$I$35) -> 11.53 | M40: 138 | N40: =IF(H40="Serviço",M40*L40,IF(H40="CÉLULA CONSTRUTIVA",SUMIFS($N$8:$N$262,$B$8:$B$262,B40,$H$8:$H$262,"Serviço"),IF(H40="ETAPA",SUMIFS($N$8:$N$262,$B$8:$B$262,B40,$C$8:$C$262,C40,$H$8:$H$262,"Serviço"),IF(H40="SUBETAPA",SUMIFS($N$8:$N$262,$B$8:$B$262,B40,$C$8:$C$262,C40,$D$8:$D$262,D40,$H$8:$H$262,"Serviço"),0)))) -> 1591.14
A41: =IF($H41="UNIDADE CONSTRUTIVA",OFFSET(A41,-1,0)+1,LARGE(A$3:A40,1)) -> 0 | B41: =IF(H41="UNIDADE CONSTRUTIVA",0,IF(H41="CÉLULA CONSTRUTIVA",OFFSET(B41,-1,0)+1,OFFSET(B41,-1,0))) -> 2 | C41: =IF(H41="CÉLULA CONSTRUTIVA",0,IF(H41="ETAPA",OFFSET(C41,-1,0)+1,OFFSET(C41,-1,0))) -> 1 | D41: =IF(H41="ETAPA",0,IF(H41="SUBETAPA",OFFSET(D41,-1,0)+1,OFFSET(D41,-1,0))) -> 3 | E41: =IF(H41="Subetapa",0,IF(H41="serviço",OFFSET(E41,-1,0)+1,OFFSET(E41,-1,0))) -> 6 | H41: SERVIÇO | I41: =IF(H41="Unidade Construtiva",TEXT(A41,"00"),IF(H41="Célula Construtiva",TEXT(B41,"00"),IF(H41="Etapa",CONCATENATE(TEXT(B41,"00"),".",TEXT(C41,"000")),IF(H41="Subetapa",CONCATENATE(TEXT(B41,"00"),".",TEXT(C41,"000"),".",TEXT(D41,"000")),IF(H41="Serviço",CONCATENATE(TEXT(B41,"00"),".",TEXT(C41,"000"),".",TEXT(D41,"000"),".",TEXT(E41,"000")),""))))) -> 02.001.003.006 | J41: M44AE2 - Manta asfáltica tipo IV, 4 mm A, com acabamento areia/areia aderida com asfalto oxidado (3,0 kg/m²) + banho de asfalto oxidado (2,0 kg/m²) + membrana de polímero acrílico com cimento e fibras para combater eflorescência (2,0 kg/m²) | K41: m2 | L41: =SUMIFS(IMPERMEABILIZAÇÃO!B$13:B$145,IMPERMEABILIZAÇÃO!D$13:D$145,IMPERMEABILIZAÇÃO!$U$12,IMPERMEABILIZAÇÃO!E$13:E$145,Ger_Executivo!$I$35) -> 59.81 | M41: 156 | N41: =IF(H41="Serviço",M41*L41,IF(H41="CÉLULA CONSTRUTIVA",SUMIFS($N$8:$N$262,$B$8:$B$262,B41,$H$8:$H$262,"Serviço"),IF(H41="ETAPA",SUMIFS($N$8:$N$262,$B$8:$B$262,B41,$C$8:$C$262,C41,$H$8:$H$262,"Serviço"),IF(H41="SUBETAPA",SUMIFS($N$8:$N$262,$B$8:$B$262,B41,$C$8:$C$262,C41,$D$8:$D$262,D41,$H$8:$H$262,"Serviço"),0)))) -> 9330.36
A42: =IF($H42="UNIDADE CONSTRUTIVA",OFFSET(A42,-1,0)+1,LARGE(A$3:A41,1)) -> 0 | B42: =IF(H42="UNIDADE CONSTRUTIVA",0,IF(H42="CÉLULA CONSTRUTIVA",OFFSET(B42,-1,0)+1,OFFSET(B42,-1,0))) -> 2 | C42: =IF(H42="CÉLULA CONSTRUTIVA",0,IF(H42="ETAPA",OFFSET(C42,-1,0)+1,OFFSET(C42,-1,0))) -> 1 | D42: =IF(H42="ETAPA",0,IF(H42="SUBETAPA",OFFSET(D42,-1,0)+1,OFFSET(D42,-1,0))) -> 3 | E42: =IF(H42="Subetapa",0,IF(H42="serviço",OFFSET(E42,-1,0)+1,OFFSET(E42,-1,0))) -> 7 | H42: SERVIÇO | I42: =IF(H42="Unidade Construtiva",TEXT(A42,"00"),IF(H42="Célula Construtiva",TEXT(B42,"00"),IF(H42="Etapa",CONCATENATE(TEXT(B42,"00"),".",TEXT(C42,"000")),IF(H42="Subetapa",CONCATENATE(TEXT(B42,"00"),".",TEXT(C42,"000"),".",TEXT(D42,"000")),IF(H42="Serviço",CONCATENATE(TEXT(B42,"00"),".",TEXT(C42,"000"),".",TEXT(D42,"000"),".",TEXT(E42,"000")),""))))) -> 02.001.003.007 | J42: I30 - Membrana acrílica, estruturada com tela de poliéster, nos pontos críticos (3,0 kg/m²) | K42: m2 | L42: =SUMIFS(IMPERMEABILIZAÇÃO!B$13:B$145,IMPERMEABILIZAÇÃO!D$13:D$145,IMPERMEABILIZAÇÃO!$U$11,IMPERMEABILIZAÇÃO!E$13:E$145,Ger_Executivo!$I$35) -> 1.92 | M42: 72 | N42: =IF(H42="Serviço",M42*L42,IF(H42="CÉLULA CONSTRUTIVA",SUMIFS($N$8:$N$262,$B$8:$B$262,B42,$H$8:$H$262,"Serviço"),IF(H42="ETAPA",SUMIFS($N$8:$N$262,$B$8:$B$262,B42,$C$8:$C$262,C42,$H$8:$H$262,"Serviço"),IF(H42="SUBETAPA",SUMIFS($N$8:$N$262,$B$8:$B$262,B42,$C$8:$C$262,C42,$D$8:$D$262,D42,$H$8:$H$262,"Serviço"),0)))) -> 138.24
A43: =IF($H43="UNIDADE CONSTRUTIVA",OFFSET(A43,-1,0)+1,LARGE(A$3:A42,1)) -> 0 | B43: =IF(H43="UNIDADE CONSTRUTIVA",0,IF(H43="CÉLULA CONSTRUTIVA",OFFSET(B43,-1,0)+1,OFFSET(B43,-1,0))) -> 2 | C43: =IF(H43="CÉLULA CONSTRUTIVA",0,IF(H43="ETAPA",OFFSET(C43,-1,0)+1,OFFSET(C43,-1,0))) -> 1 | D43: =IF(H43="ETAPA",0,IF(H43="SUBETAPA",OFFSET(D43,-1,0)+1,OFFSET(D43,-1,0))) -> 3 | E43: =IF(H43="Subetapa",0,IF(H43="serviço",OFFSET(E43,-1,0)+1,OFFSET(E43,-1,0))) -> 8 | H43: SERVIÇO | I43: =IF(H43="Unidade Construtiva",TEXT(A43,"00"),IF(H43="Célula Construtiva",TEXT(B43,"00"),IF(H43="Etapa",CONCATENATE(TEXT(B43,"00"),".",TEXT(C43,"000")),IF(H43="Subetapa",CONCATENATE(TEXT(B43,"00"),".",TEXT(C43,"000"),".",TEXT(D43,"000")),IF(H43="Serviço",CONCATENATE(TEXT(B43,"00"),".",TEXT(C43,"000"),".",TEXT(D43,"000"),".",TEXT(E43,"000")),""))))) -> 02.001.003.008 | J43: C4RQ - Argamassa polimérica rígida, com alta resistência química, estruturada com tela de poliéster nos pontos críticos (4,0 kg/m²) | K43: m2 | L43: =SUMIFS(IMPERMEABILIZAÇÃO!B$13:B$145,IMPERMEABILIZAÇÃO!D$13:D$145,IMPERMEABILIZAÇÃO!$U$10,IMPERMEABILIZAÇÃO!E$13:E$145,Ger_Executivo!$I$35) -> 47.53 | M43: 39.555556 | N43: =IF(H43="Serviço",M43*L43,IF(H43="CÉLULA CONSTRUTIVA",SUMIFS($N$8:$N$262,$B$8:$B$262,B43,$H$8:$H$262,"Serviço"),IF(H43="ETAPA",SUMIFS($N$8:$N$262,$B$8:$B$262,B43,$C$8:$C$262,C43,$H$8:$H$262,"Serviço"),IF(H43="SUBETAPA",SUMIFS($N$8:$N$262,$B$8:$B$262,B43,$C$8:$C$262,C43,$D$8:$D$262,D43,$H$8:$H$262,"Serviço"),0)))) -> 1880.0756
A44: =IF($H44="UNIDADE CONSTRUTIVA",OFFSET(A44,-1,0)+1,LARGE(A$3:A43,1)) -> 0 | B44: =IF(H44="UNIDADE CONSTRUTIVA",0,IF(H44="CÉLULA CONSTRUTIVA",OFFSET(B44,-1,0)+1,OFFSET(B44,-1,0))) -> 2 | C44: =IF(H44="CÉLULA CONSTRUTIVA",0,IF(H44="ETAPA",OFFSET(C44,-1,0)+1,OFFSET(C44,-1,0))) -> 1 | D44: =IF(H44="ETAPA",0,IF(H44="SUBETAPA",OFFSET(D44,-1,0)+1,OFFSET(D44,-1,0))) -> 3 | E44: =IF(H44="Subetapa",0,IF(H44="serviço",OFFSET(E44,-1,0)+1,OFFSET(E44,-1,0))) -> 9 | H44: SERVIÇO | I44: =IF(H44="Unidade Construtiva",TEXT(A44,"00"),IF(H44="Célula Construtiva",TEXT(B44,"00"),IF(H44="Etapa",CONCATENATE(TEXT(B44,"00"),".",TEXT(C44,"000")),IF(H44="Subetapa",CONCATENATE(TEXT(B44,"00"),".",TEXT(C44,"000"),".",TEXT(D44,"000")),IF(H44="Serviço",CONCATENATE(TEXT(B44,"00"),".",TEXT(C44,"000"),".",TEXT(D44,"000"),".",TEXT(E44,"000")),""))))) -> 02.001.003.009 | J44: C4 - Argamassa polimérica rígida, estruturada com tela de poliéster nos pontos críticos (4,0 kg/m²) | K44: m2 | L44: =SUMIFS(IMPERMEABILIZAÇÃO!B$13:B$145,IMPERMEABILIZAÇÃO!D$13:D$145,IMPERMEABILIZAÇÃO!$U$9,IMPERMEABILIZAÇÃO!E$13:E$145,Ger_Executivo!$I$35) -> 64.26 | M44: 39.555556 | N44: =IF(H44="Serviço",M44*L44,IF(H44="CÉLULA CONSTRUTIVA",SUMIFS($N$8:$N$262,$B$8:$B$262,B44,$H$8:$H$262,"Serviço"),IF(H44="ETAPA",SUMIFS($N$8:$N$262,$B$8:$B$262,B44,$C$8:$C$262,C44,$H$8:$H$262,"Serviço"),IF(H44="SUBETAPA",SUMIFS($N$8:$N$262,$B$8:$B$262,B44,$C$8:$C$262,C44,$D$8:$D$262,D44,$H$8:$H$262,"Serviço"),0)))) -> 2541.84
A45: =IF($H45="UNIDADE CONSTRUTIVA",OFFSET(A45,-1,0)+1,LARGE(A$3:A44,1)) -> 0 | B45: =IF(H45="UNIDADE CONSTRUTIVA",0,IF(H45="CÉLULA CONSTRUTIVA",OFFSET(B45,-1,0)+1,OFFSET(B45,-1,0))) -> 2 | C45: =IF(H45="CÉLULA CONSTRUTIVA",0,IF(H45="ETAPA",OFFSET(C45,-1,0)+1,OFFSET(C45,-1,0))) -> 1 | D45: =IF(H45="ETAPA",0,IF(H45="SUBETAPA",OFFSET(D45,-1,0)+1,OFFSET(D45,-1,0))) -> 3 | E45: =IF(H45="Subetapa",0,IF(H45="serviço",OFFSET(E45,-1,0)+1,OFFSET(E45,-1,0))) -> 10 | H45: SERVIÇO | I45: =IF(H45="Unidade Construtiva",TEXT(A45,"00"),IF(H45="Célula Construtiva",TEXT(B45,"00"),IF(H45="Etapa",CONCATENATE(TEXT(B45,"00"),".",TEXT(C45,"000")),IF(H45="Subetapa",CONCATENATE(TEXT(B45,"00"),".",TEXT(C45,"000"),".",TEXT(D45,"000")),IF(H45="Serviço",CONCATENATE(TEXT(B45,"00"),".",TEXT(C45,"000"),".",TEXT(D45,"000"),".",TEXT(E45,"000")),""))))) -> 02.001.003.010 | J45: I30EL - Membrana de polímero acrílico, sem cimento (3,0 kg/m²), com resistência à alcalinidade, estruturada com tela de poliéster nos pontos críticos – Ref.: Sika Baucryl, MC DF9, Icopor HP, Procryl Imper | K45: m2 | L45: =SUMIFS(IMPERMEABILIZAÇÃO!B$13:B$145,IMPERMEABILIZAÇÃO!D$13:D$145,IMPERMEABILIZAÇÃO!$U$5,IMPERMEABILIZAÇÃO!E$13:E$145,Ger_Executivo!$I$35) -> 130.83 | M45: 75 | N45: =IF(H45="Serviço",M45*L45,IF(H45="CÉLULA CONSTRUTIVA",SUMIFS($N$8:$N$262,$B$8:$B$262,B45,$H$8:$H$262,"Serviço"),IF(H45="ETAPA",SUMIFS($N$8:$N$262,$B$8:$B$262,B45,$C$8:$C$262,C45,$H$8:$H$262,"Serviço"),IF(H45="SUBETAPA",SUMIFS($N$8:$N$262,$B$8:$B$262,B45,$C$8:$C$262,C45,$D$8:$D$262,D45,$H$8:$H$262,"Serviço"),0)))) -> 9812.25
A46: =IF($H46="UNIDADE CONSTRUTIVA",OFFSET(A46,-1,0)+1,LARGE(A$3:A45,1)) -> 0 | B46: =IF(H46="UNIDADE CONSTRUTIVA",0,IF(H46="CÉLULA CONSTRUTIVA",OFFSET(B46,-1,0)+1,OFFSET(B46,-1,0))) -> 2 | C46: =IF(H46="CÉLULA CONSTRUTIVA",0,IF(H46="ETAPA",OFFSET(C46,-1,0)+1,OFFSET(C46,-1,0))) -> 1 | D46: =IF(H46="ETAPA",0,IF(H46="SUBETAPA",OFFSET(D46,-1,0)+1,OFFSET(D46,-1,0))) -> 4 | E46: =IF(H46="Subetapa",0,IF(H46="serviço",OFFSET(E46,-1,0)+1,OFFSET(E46,-1,0))) -> 0 | H46: SUBETAPA | I46: =IF(H46="Unidade Construtiva",TEXT(A46,"00"),IF(H46="Célula Construtiva",TEXT(B46,"00"),IF(H46="Etapa",CONCATENATE(TEXT(B46,"00"),".",TEXT(C46,"000")),IF(H46="Subetapa",CONCATENATE(TEXT(B46,"00"),".",TEXT(C46,"000"),".",TEXT(D46,"000")),IF(H46="Serviço",CONCATENATE(TEXT(B46,"00"),".",TEXT(C46,"000"),".",TEXT(D46,"000"),".",TEXT(E46,"000")),""))))) -> 02.001.004 | J46: Impermeabilização de piscinas, floreiras e espelhos d´água | N46: =IF(H46="Serviço",M46*L46,IF(H46="CÉLULA CONSTRUTIVA",SUMIFS($N$8:$N$262,$B$8:$B$262,B46,$H$8:$H$262,"Serviço"),IF(H46="ETAPA",SUMIFS($N$8:$N$262,$B$8:$B$262,B46,$C$8:$C$262,C46,$H$8:$H$262,"Serviço"),IF(H46="SUBETAPA",SUMIFS($N$8:$N$262,$B$8:$B$262,B46,$C$8:$C$262,C46,$D$8:$D$262,D46,$H$8:$H$262,"Serviço"),0)))) -> 33151.44
A47: =IF($H47="UNIDADE CONSTRUTIVA",OFFSET(A47,-1,0)+1,LARGE(A$3:A46,1)) -> 0 | B47: =IF(H47="UNIDADE CONSTRUTIVA",0,IF(H47="CÉLULA CONSTRUTIVA",OFFSET(B47,-1,0)+1,OFFSET(B47,-1,0))) -> 2 | C47: =IF(H47="CÉLULA CONSTRUTIVA",0,IF(H47="ETAPA",OFFSET(C47,-1,0)+1,OFFSET(C47,-1,0))) -> 1 | D47: =IF(H47="ETAPA",0,IF(H47="SUBETAPA",OFFSET(D47,-1,0)+1,OFFSET(D47,-1,0))) -> 4 | E47: =IF(H47="Subetapa",0,IF(H47="serviço",OFFSET(E47,-1,0)+1,OFFSET(E47,-1,0))) -> 1 | H47: SERVIÇO | I47: =IF(H47="Unidade Construtiva",TEXT(A47,"00"),IF(H47="Célula Construtiva",TEXT(B47,"00"),IF(H47="Etapa",CONCATENATE(TEXT(B47,"00"),".",TEXT(C47,"000")),IF(H47="Subetapa",CONCATENATE(TEXT(B47,"00"),".",TEXT(C47,"000"),".",TEXT(D47,"000")),IF(H47="Serviço",CONCATENATE(TEXT(B47,"00"),".",TEXT(C47,"000"),".",TEXT(D47,"000"),".",TEXT(E47,"000")),""))))) -> 02.001.004.001 | J47: M44A + M44AE2 - Manta asfáltica tipo IV, 4 mm + manta asfáltica tipo IV, 4 mm + banho de asfalto oxidado + membrana de polímero acrílico com cimento e fibras para combater eflorescência | K47: m2 | L47: =SUMIFS(IMPERMEABILIZAÇÃO!B$13:B$145,IMPERMEABILIZAÇÃO!D$13:D$145,IMPERMEABILIZAÇÃO!$U$15,IMPERMEABILIZAÇÃO!E$13:E$145,$I$46) -> 124.84 | M47: 246 | N47: =IF(H47="Serviço",M47*L47,IF(H47="CÉLULA CONSTRUTIVA",SUMIFS($N$8:$N$262,$B$8:$B$262,B47,$H$8:$H$262,"Serviço"),IF(H47="ETAPA",SUMIFS($N$8:$N$262,$B$8:$B$262,B47,$C$8:$C$262,C47,$H$8:$H$262,"Serviço"),IF(H47="SUBETAPA",SUMIFS($N$8:$N$262,$B$8:$B$262,B47,$C$8:$C$262,C47,$D$8:$D$262,D47,$H$8:$H$262,"Serviço"),0)))) -> 30710.64
A48: =IF($H48="UNIDADE CONSTRUTIVA",OFFSET(A48,-1,0)+1,LARGE(A$3:A47,1)) -> 0 | B48: =IF(H48="UNIDADE CONSTRUTIVA",0,IF(H48="CÉLULA CONSTRUTIVA",OFFSET(B48,-1,0)+1,OFFSET(B48,-1,0))) -> 2 | C48: =IF(H48="CÉLULA CONSTRUTIVA",0,IF(H48="ETAPA",OFFSET(C48,-1,0)+1,OFFSET(C48,-1,0))) -> 1 | D48: =IF(H48="ETAPA",0,IF(H48="SUBETAPA",OFFSET(D48,-1,0)+1,OFFSET(D48,-1,0))) -> 4 | E48: =IF(H48="Subetapa",0,IF(H48="serviço",OFFSET(E48,-1,0)+1,OFFSET(E48,-1,0))) -> 2 | H48: SERVIÇO | I48: =IF(H48="Unidade Construtiva",TEXT(A48,"00"),IF(H48="Célula Construtiva",TEXT(B48,"00"),IF(H48="Etapa",CONCATENATE(TEXT(B48,"00"),".",TEXT(C48,"000")),IF(H48="Subetapa",CONCATENATE(TEXT(B48,"00"),".",TEXT(C48,"000"),".",TEXT(D48,"000")),IF(H48="Serviço",CONCATENATE(TEXT(B48,"00"),".",TEXT(C48,"000"),".",TEXT(D48,"000"),".",TEXT(E48,"000")),""))))) -> 02.001.004.002 | J48: M44A - Manta asfáltica tipo IV, 4 mm A, com acabamento areia/areia aderida com asfalto oxidado (3,0 kg/m²) + banho de asfalto oxidado (2,0 kg/m²) | K48: m2 | L48: =SUMIFS(IMPERMEABILIZAÇÃO!B$13:B$145,IMPERMEABILIZAÇÃO!D$13:D$145,IMPERMEABILIZAÇÃO!$U$6,IMPERMEABILIZAÇÃO!E$13:E$145,$I$46) -> 22.6 | M48: 108 | N48: =IF(H48="Serviço",M48*L48,IF(H48="CÉLULA CONSTRUTIVA",SUMIFS($N$8:$N$262,$B$8:$B$262,B48,$H$8:$H$262,"Serviço"),IF(H48="ETAPA",SUMIFS($N$8:$N$262,$B$8:$B$262,B48,$C$8:$C$262,C48,$H$8:$H$262,"Serviço"),IF(H48="SUBETAPA",SUMIFS($N$8:$N$262,$B$8:$B$262,B48,$C$8:$C$262,C48,$D$8:$D$262,D48,$H$8:$H$262,"Serviço"),0)))) -> 2440.8
A49: =IF($H49="UNIDADE CONSTRUTIVA",OFFSET(A49,-1,0)+1,LARGE(A$3:A48,1)) -> 0 | B49: =IF(H49="UNIDADE CONSTRUTIVA",0,IF(H49="CÉLULA CONSTRUTIVA",OFFSET(B49,-1,0)+1,OFFSET(B49,-1,0))) -> 2 | C49: =IF(H49="CÉLULA CONSTRUTIVA",0,IF(H49="ETAPA",OFFSET(C49,-1,0)+1,OFFSET(C49,-1,0))) -> 1 | D49: =IF(H49="ETAPA",0,IF(H49="SUBETAPA",OFFSET(D49,-1,0)+1,OFFSET(D49,-1,0))) -> 5 | E49: =IF(H49="Subetapa",0,IF(H49="serviço",OFFSET(E49,-1,0)+1,OFFSET(E49,-1,0))) -> 0 | H49: SUBETAPA | I49: =IF(H49="Unidade Construtiva",TEXT(A49,"00"),IF(H49="Célula Construtiva",TEXT(B49,"00"),IF(H49="Etapa",CONCATENATE(TEXT(B49,"00"),".",TEXT(C49,"000")),IF(H49="Subetapa",CONCATENATE(TEXT(B49,"00"),".",TEXT(C49,"000"),".",TEXT(D49,"000")),IF(H49="Serviço",CONCATENATE(TEXT(B49,"00"),".",TEXT(C49,"000"),".",TEXT(D49,"000"),".",TEXT(E49,"000")),""))))) -> 02.001.005 | J49: Impermeabilização de banheiro, cozinha, área de serviço, fosso do elevador e sacada | N49: =IF(H49="Serviço",M49*L49,IF(H49="CÉLULA CONSTRUTIVA",SUMIFS($N$8:$N$262,$B$8:$B$262,B49,$H$8:$H$262,"Serviço"),IF(H49="ETAPA",SUMIFS($N$8:$N$262,$B$8:$B$262,B49,$C$8:$C$262,C49,$H$8:$H$262,"Serviço"),IF(H49="SUBETAPA",SUMIFS($N$8:$N$262,$B$8:$B$262,B49,$C$8:$C$262,C49,$D$8:$D$262,D49,$H$8:$H$262,"Serviço"),0)))) -> 162154.31
A50: =IF($H50="UNIDADE CONSTRUTIVA",OFFSET(A50,-1,0)+1,LARGE(A$3:A49,1)) -> 0 | B50: =IF(H50="UNIDADE CONSTRUTIVA",0,IF(H50="CÉLULA CONSTRUTIVA",OFFSET(B50,-1,0)+1,OFFSET(B50,-1,0))) -> 2 | C50: =IF(H50="CÉLULA CONSTRUTIVA",0,IF(H50="ETAPA",OFFSET(C50,-1,0)+1,OFFSET(C50,-1,0))) -> 1 | D50: =IF(H50="ETAPA",0,IF(H50="SUBETAPA",OFFSET(D50,-1,0)+1,OFFSET(D50,-1,0))) -> 5 | E50: =IF(H50="Subetapa",0,IF(H50="serviço",OFFSET(E50,-1,0)+1,OFFSET(E50,-1,0))) -> 1 | H50: SERVIÇO | I50: =IF(H50="Unidade Construtiva",TEXT(A50,"00"),IF(H50="Célula Construtiva",TEXT(B50,"00"),IF(H50="Etapa",CONCATENATE(TEXT(B50,"00"),".",TEXT(C50,"000")),IF(H50="Subetapa",CONCATENATE(TEXT(B50,"00"),".",TEXT(C50,"000"),".",TEXT(D50,"000")),IF(H50="Serviço",CONCATENATE(TEXT(B50,"00"),".",TEXT(C50,"000"),".",TEXT(D50,"000"),".",TEXT(E50,"000")),""))))) -> 02.001.005.001 | J50: C3 - Argamassa polimérica rígida, estruturada com tela de poliéster nos pontos críticos (3,0 kg/m²) | K50: m2 | L50: =SUMIFS(IMPERMEABILIZAÇÃO!B$13:B$145,IMPERMEABILIZAÇÃO!D$13:D$145,IMPERMEABILIZAÇÃO!$U$7,IMPERMEABILIZAÇÃO!E$13:E$145,$I$49) -> 189.46 | M50: 29.666667 | N50: =IF(H50="Serviço",M50*L50,IF(H50="CÉLULA CONSTRUTIVA",SUMIFS($N$8:$N$262,$B$8:$B$262,B50,$H$8:$H$262,"Serviço"),IF(H50="ETAPA",SUMIFS($N$8:$N$262,$B$8:$B$262,B50,$C$8:$C$262,C50,$H$8:$H$262,"Serviço"),IF(H50="SUBETAPA",SUMIFS($N$8:$N$262,$B$8:$B$262,B50,$C$8:$C$262,C50,$D$8:$D$262,D50,$H$8:$H$262,"Serviço"),0)))) -> 5620.6467
A51: =IF($H51="UNIDADE CONSTRUTIVA",OFFSET(A51,-1,0)+1,LARGE(A$3:A50,1)) -> 0 | B51: =IF(H51="UNIDADE CONSTRUTIVA",0,IF(H51="CÉLULA CONSTRUTIVA",OFFSET(B51,-1,0)+1,OFFSET(B51,-1,0))) -> 2 | C51: =IF(H51="CÉLULA CONSTRUTIVA",0,IF(H51="ETAPA",OFFSET(C51,-1,0)+1,OFFSET(C51,-1,0))) -> 1 | D51: =IF(H51="ETAPA",0,IF(H51="SUBETAPA",OFFSET(D51,-1,0)+1,OFFSET(D51,-1,0))) -> 5 | E51: =IF(H51="Subetapa",0,IF(H51="serviço",OFFSET(E51,-1,0)+1,OFFSET(E51,-1,0))) -> 2 | H51: SERVIÇO | I51: =IF(H51="Unidade Construtiva",TEXT(A51,"00"),IF(H51="Célula Construtiva",TEXT(B51,"00"),IF(H51="Etapa",CONCATENATE(TEXT(B51,"00"),".",TEXT(C51,"000")),IF(H51="Subetapa",CONCATENATE(TEXT(B51,"00"),".",TEXT(C51,"000"),".",TEXT(D51,"000")),IF(H51="Serviço",CONCATENATE(TEXT(B51,"00"),".",TEXT(C51,"000"),".",TEXT(D51,"000"),".",TEXT(E51,"000")),""))))) -> 02.001.005.002 | J51: E3 - Membrana de polímero acrílico com cimento e fibras, estruturada com tela de poliéster nos pontos críticos (3,0 kg/m²) | K51: m2 | L51: =SUMIFS(IMPERMEABILIZAÇÃO!B$13:B$145,IMPERMEABILIZAÇÃO!D$13:D$145,IMPERMEABILIZAÇÃO!$U$4,IMPERMEABILIZAÇÃO!E$13:E$145,$I$49) -> 2310.47 | M51: 66 | N51: =IF(H51="Serviço",M51*L51,IF(H51="CÉLULA CONSTRUTIVA",SUMIFS($N$8:$N$262,$B$8:$B$262,B51,$H$8:$H$262,"Serviço"),IF(H51="ETAPA",SUMIFS($N$8:$N$262,$B$8:$B$262,B51,$C$8:$C$262,C51,$H$8:$H$262,"Serviço"),IF(H51="SUBETAPA",SUMIFS($N$8:$N$262,$B$8:$B$262,B51,$C$8:$C$262,C51,$D$8:$D$262,D51,$H$8:$H$262,"Serviço"),0)))) -> 152491.02
A52: =IF($H52="UNIDADE CONSTRUTIVA",OFFSET(A52,-1,0)+1,LARGE(A$3:A51,1)) -> 0 | B52: =IF(H52="UNIDADE CONSTRUTIVA",0,IF(H52="CÉLULA CONSTRUTIVA",OFFSET(B52,-1,0)+1,OFFSET(B52,-1,0))) -> 2 | C52: =IF(H52="CÉLULA CONSTRUTIVA",0,IF(H52="ETAPA",OFFSET(C52,-1,0)+1,OFFSET(C52,-1,0))) -> 1 | D52: =IF(H52="ETAPA",0,IF(H52="SUBETAPA",OFFSET(D52,-1,0)+1,OFFSET(D52,-1,0))) -> 5 | E52: =IF(H52="Subetapa",0,IF(H52="serviço",OFFSET(E52,-1,0)+1,OFFSET(E52,-1,0))) -> 3 | H52: SERVIÇO | I52: =IF(H52="Unidade Construtiva",TEXT(A52,"00"),IF(H52="Célula Construtiva",TEXT(B52,"00"),IF(H52="Etapa",CONCATENATE(TEXT(B52,"00"),".",TEXT(C52,"000")),IF(H52="Subetapa",CONCATENATE(TEXT(B52,"00"),".",TEXT(C52,"000"),".",TEXT(D52,"000")),IF(H52="Serviço",CONCATENATE(TEXT(B52,"00"),".",TEXT(C52,"000"),".",TEXT(D52,"000"),".",TEXT(E52,"000")),""))))) -> 02.001.005.003 | J52: C4 - Argamassa polimérica rígida, estruturada com tela de poliéster nos pontos críticos (4,0 kg/m²) | K52: m2 | L52: =SUMIFS(IMPERMEABILIZAÇÃO!B$13:B$145,IMPERMEABILIZAÇÃO!D$13:D$145,IMPERMEABILIZAÇÃO!$U$9,IMPERMEABILIZAÇÃO!E$13:E$145,$I$49) -> 35.09 | M52: 39.555556 | N52: =IF(H52="Serviço",M52*L52,IF(H52="CÉLULA CONSTRUTIVA",SUMIFS($N$8:$N$262,$B$8:$B$262,B52,$H$8:$H$262,"Serviço"),IF(H52="ETAPA",SUMIFS($N$8:$N$262,$B$8:$B$262,B52,$C$8:$C$262,C52,$H$8:$H$262,"Serviço"),IF(H52="SUBETAPA",SUMIFS($N$8:$N$262,$B$8:$B$262,B52,$C$8:$C$262,C52,$D$8:$D$262,D52,$H$8:$H$262,"Serviço"),0)))) -> 1388.0044
A53: =IF($H53="UNIDADE CONSTRUTIVA",OFFSET(A53,-1,0)+1,LARGE(A$3:A52,1)) -> 0 | B53: =IF(H53="UNIDADE CONSTRUTIVA",0,IF(H53="CÉLULA CONSTRUTIVA",OFFSET(B53,-1,0)+1,OFFSET(B53,-1,0))) -> 2 | C53: =IF(H53="CÉLULA CONSTRUTIVA",0,IF(H53="ETAPA",OFFSET(C53,-1,0)+1,OFFSET(C53,-1,0))) -> 1 | D53: =IF(H53="ETAPA",0,IF(H53="SUBETAPA",OFFSET(D53,-1,0)+1,OFFSET(D53,-1,0))) -> 5 | E53: =IF(H53="Subetapa",0,IF(H53="serviço",OFFSET(E53,-1,0)+1,OFFSET(E53,-1,0))) -> 4 | H53: SERVIÇO | I53: =IF(H53="Unidade Construtiva",TEXT(A53,"00"),IF(H53="Célula Construtiva",TEXT(B53,"00"),IF(H53="Etapa",CONCATENATE(TEXT(B53,"00"),".",TEXT(C53,"000")),IF(H53="Subetapa",CONCATENATE(TEXT(B53,"00"),".",TEXT(C53,"000"),".",TEXT(D53,"000")),IF(H53="Serviço",CONCATENATE(TEXT(B53,"00"),".",TEXT(C53,"000"),".",TEXT(D53,"000"),".",TEXT(E53,"000")),""))))) -> 02.001.005.004 | J53: M44A - Manta asfáltica tipo IV, 4 mm A, com acabamento areia/areia aderida com asfalto oxidado (3,0 kg/m²) + banho de asfalto oxidado (2,0 kg/m²) | K53: m2 | L53: =SUMIFS(IMPERMEABILIZAÇÃO!B$13:B$145,IMPERMEABILIZAÇÃO!D$13:D$145,IMPERMEABILIZAÇÃO!$U$6,IMPERMEABILIZAÇÃO!E$13:E$145,$I$49) -> 24.58 | M53: 108 | N53: =IF(H53="Serviço",M53*L53,IF(H53="CÉLULA CONSTRUTIVA",SUMIFS($N$8:$N$262,$B$8:$B$262,B53,$H$8:$H$262,"Serviço"),IF(H53="ETAPA",SUMIFS($N$8:$N$262,$B$8:$B$262,B53,$C$8:$C$262,C53,$H$8:$H$262,"Serviço"),IF(H53="SUBETAPA",SUMIFS($N$8:$N$262,$B$8:$B$262,B53,$C$8:$C$262,C53,$D$8:$D$262,D53,$H$8:$H$262,"Serviço"),0)))) -> 2654.64
A54: =IF($H54="UNIDADE CONSTRUTIVA",OFFSET(A54,-1,0)+1,LARGE(A$3:A53,1)) -> 0 | B54: =IF(H54="UNIDADE CONSTRUTIVA",0,IF(H54="CÉLULA CONSTRUTIVA",OFFSET(B54,-1,0)+1,OFFSET(B54,-1,0))) -> 2 | C54: =IF(H54="CÉLULA CONSTRUTIVA",0,IF(H54="ETAPA",OFFSET(C54,-1,0)+1,OFFSET(C54,-1,0))) -> 1 | D54: =IF(H54="ETAPA",0,IF(H54="SUBETAPA",OFFSET(D54,-1,0)+1,OFFSET(D54,-1,0))) -> 6 | E54: =IF(H54="Subetapa",0,IF(H54="serviço",OFFSET(E54,-1,0)+1,OFFSET(E54,-1,0))) -> 0 | H54: SUBETAPA | I54: =IF(H54="Unidade Construtiva",TEXT(A54,"00"),IF(H54="Célula Construtiva",TEXT(B54,"00"),IF(H54="Etapa",CONCATENATE(TEXT(B54,"00"),".",TEXT(C54,"000")),IF(H54="Subetapa",CONCATENATE(TEXT(B54,"00"),".",TEXT(C54,"000"),".",TEXT(D54,"000")),IF(H54="Serviço",CONCATENATE(TEXT(B54,"00"),".",TEXT(C54,"000"),".",TEXT(D54,"000"),".",TEXT(E54,"000")),""))))) -> 02.001.006 | J54: Impermeabilização de esquadrias | N54: =IF(H54="Serviço",M54*L54,IF(H54="CÉLULA CONSTRUTIVA",SUMIFS($N$8:$N$262,$B$8:$B$262,B54,$H$8:$H$262,"Serviço"),IF(H54="ETAPA",SUMIFS($N$8:$N$262,$B$8:$B$262,B54,$C$8:$C$262,C54,$H$8:$H$262,"Serviço"),IF(H54="SUBETAPA",SUMIFS($N$8:$N$262,$B$8:$B$262,B54,$C$8:$C$262,C54,$D$8:$D$262,D54,$H$8:$H$262,"Serviço"),0)))) -> 5280.9633
A55: =IF($H55="UNIDADE CONSTRUTIVA",OFFSET(A55,-1,0)+1,LARGE(A$3:A54,1)) -> 0 | B55: =IF(H55="UNIDADE CONSTRUTIVA",0,IF(H55="CÉLULA CONSTRUTIVA",OFFSET(B55,-1,0)+1,OFFSET(B55,-1,0))) -> 2 | C55: =IF(H55="CÉLULA CONSTRUTIVA",0,IF(H55="ETAPA",OFFSET(C55,-1,0)+1,OFFSET(C55,-1,0))) -> 1 | D55: =IF(H55="ETAPA",0,IF(H55="SUBETAPA",OFFSET(D55,-1,0)+1,OFFSET(D55,-1,0))) -> 6 | E55: =IF(H55="Subetapa",0,IF(H55="serviço",OFFSET(E55,-1,0)+1,OFFSET(E55,-1,0))) -> 1 | H55: SERVIÇO | I55: =IF(H55="Unidade Construtiva",TEXT(A55,"00"),IF(H55="Célula Construtiva",TEXT(B55,"00"),IF(H55="Etapa",CONCATENATE(TEXT(B55,"00"),".",TEXT(C55,"000")),IF(H55="Subetapa",CONCATENATE(TEXT(B55,"00"),".",TEXT(C55,"000"),".",TEXT(D55,"000")),IF(H55="Serviço",CONCATENATE(TEXT(B55,"00"),".",TEXT(C55,"000"),".",TEXT(D55,"000"),".",TEXT(E55,"000")),""))))) -> 02.001.006.001 | J55: C3 - Argamassa polimérica rígida, estruturada com tela de poliéster nos pontos críticos (3,0 kg/m²) | K55: m2 | L55: =IMPERMEABILIZAÇÃO!B84+IMPERMEABILIZAÇÃO!B41 -> 178.01 | M55: 29.666667 | N55: =IF(H55="Serviço",M55*L55,IF(H55="CÉLULA CONSTRUTIVA",SUMIFS($N$8:$N$262,$B$8:$B$262,B55,$H$8:$H$262,"Serviço"),IF(H55="ETAPA",SUMIFS($N$8:$N$262,$B$8:$B$262,B55,$C$8:$C$262,C55,$H$8:$H$262,"Serviço"),IF(H55="SUBETAPA",SUMIFS($N$8:$N$262,$B$8:$B$262,B55,$C$8:$C$262,C55,$D$8:$D$262,D55,$H$8:$H$262,"Serviço"),0)))) -> 5280.9633
A56: =IF($H56="UNIDADE CONSTRUTIVA",OFFSET(A56,-1,0)+1,LARGE(A$3:A55,1)) -> 0 | B56: =IF(H56="UNIDADE CONSTRUTIVA",0,IF(H56="CÉLULA CONSTRUTIVA",OFFSET(B56,-1,0)+1,OFFSET(B56,-1,0))) -> 2 | C56: =IF(H56="CÉLULA CONSTRUTIVA",0,IF(H56="ETAPA",OFFSET(C56,-1,0)+1,OFFSET(C56,-1,0))) -> 1 | D56: =IF(H56="ETAPA",0,IF(H56="SUBETAPA",OFFSET(D56,-1,0)+1,OFFSET(D56,-1,0))) -> 7 | E56: =IF(H56="Subetapa",0,IF(H56="serviço",OFFSET(E56,-1,0)+1,OFFSET(E56,-1,0))) -> 0 | H56: SUBETAPA | I56: =IF(H56="Unidade Construtiva",TEXT(A56,"00"),IF(H56="Célula Construtiva",TEXT(B56,"00"),IF(H56="Etapa",CONCATENATE(TEXT(B56,"00"),".",TEXT(C56,"000")),IF(H56="Subetapa",CONCATENATE(TEXT(B56,"00"),".",TEXT(C56,"000"),".",TEXT(D56,"000")),IF(H56="Serviço",CONCATENATE(TEXT(B56,"00"),".",TEXT(C56,"000"),".",TEXT(D56,"000"),".",TEXT(E56,"000")),""))))) -> 02.001.007 | J56: Impermeabilização de ralos | N56: =IF(H56="Serviço",M56*L56,IF(H56="CÉLULA CONSTRUTIVA",SUMIFS($N$8:$N$262,$B$8:$B$262,B56,$H$8:$H$262,"Serviço"),IF(H56="ETAPA",SUMIFS($N$8:$N$262,$B$8:$B$262,B56,$C$8:$C$262,C56,$H$8:$H$262,"Serviço"),IF(H56="SUBETAPA",SUMIFS($N$8:$N$262,$B$8:$B$262,B56,$C$8:$C$262,C56,$D$8:$D$262,D56,$H$8:$H$262,"Serviço"),0)))) -> 3915.7267
A57: =IF($H57="UNIDADE CONSTRUTIVA",OFFSET(A57,-1,0)+1,LARGE(A$3:A56,1)) -> 0 | B57: =IF(H57="UNIDADE CONSTRUTIVA",0,IF(H57="CÉLULA CONSTRUTIVA",OFFSET(B57,-1,0)+1,OFFSET(B57,-1,0))) -> 2 | C57: =IF(H57="CÉLULA CONSTRUTIVA",0,IF(H57="ETAPA",OFFSET(C57,-1,0)+1,OFFSET(C57,-1,0))) -> 1 | D57: =IF(H57="ETAPA",0,IF(H57="SUBETAPA",OFFSET(D57,-1,0)+1,OFFSET(D57,-1,0))) -> 7 | E57: =IF(H57="Subetapa",0,IF(H57="serviço",OFFSET(E57,-1,0)+1,OFFSET(E57,-1,0))) -> 1 | H57: SERVIÇO | I57: =IF(H57="Unidade Construtiva",TEXT(A57,"00"),IF(H57="Célula Construtiva",TEXT(B57,"00"),IF(H57="Etapa",CONCATENATE(TEXT(B57,"00"),".",TEXT(C57,"000")),IF(H57="Subetapa",CONCATENATE(TEXT(B57,"00"),".",TEXT(C57,"000"),".",TEXT(D57,"000")),IF(H57="Serviço",CONCATENATE(TEXT(B57,"00"),".",TEXT(C57,"000"),".",TEXT(D57,"000"),".",TEXT(E57,"000")),""))))) -> 02.001.007.001 | J57: Tratamento de ralo com manta de poliéster | K57: un | L57: ='Obra '!H116*2+'Obra '!G116 -> 447 | M57: 8.760015 | N57: =IF(H57="Serviço",M57*L57,IF(H57="CÉLULA CONSTRUTIVA",SUMIFS($N$8:$N$262,$B$8:$B$262,B57,$H$8:$H$262,"Serviço"),IF(H57="ETAPA",SUMIFS($N$8:$N$262,$B$8:$B$262,B57,$C$8:$C$262,C57,$H$8:$H$262,"Serviço"),IF(H57="SUBETAPA",SUMIFS($N$8:$N$262,$B$8:$B$262,B57,$C$8:$C$262,C57,$D$8:$D$262,D57,$H$8:$H$262,"Serviço"),0)))) -> 3915.7267 | O57: Considerado 1 na cozinha + 2 no banheiro
A58: =IF($H58="UNIDADE CONSTRUTIVA",OFFSET(A58,-1,0)+1,LARGE(A$3:A57,1)) -> 0 | B58: =IF(H58="UNIDADE CONSTRUTIVA",0,IF(H58="CÉLULA CONSTRUTIVA",OFFSET(B58,-1,0)+1,OFFSET(B58,-1,0))) -> 2 | C58: =IF(H58="CÉLULA CONSTRUTIVA",0,IF(H58="ETAPA",OFFSET(C58,-1,0)+1,OFFSET(C58,-1,0))) -> 1 | D58: =IF(H58="ETAPA",0,IF(H58="SUBETAPA",OFFSET(D58,-1,0)+1,OFFSET(D58,-1,0))) -> 8 | E58: =IF(H58="Subetapa",0,IF(H58="serviço",OFFSET(E58,-1,0)+1,OFFSET(E58,-1,0))) -> 0 | H58: SUBETAPA | I58: =IF(H58="Unidade Construtiva",TEXT(A58,"00"),IF(H58="Célula Construtiva",TEXT(B58,"00"),IF(H58="Etapa",CONCATENATE(TEXT(B58,"00"),".",TEXT(C58,"000")),IF(H58="Subetapa",CONCATENATE(TEXT(B58,"00"),".",TEXT(C58,"000"),".",TEXT(D58,"000")),IF(H58="Serviço",CONCATENATE(TEXT(B58,"00"),".",TEXT(C58,"000"),".",TEXT(D58,"000"),".",TEXT(E58,"000")),""))))) -> 02.001.008 | J58: Impermeabilização de reservatórios | N58: =IF(H58="Serviço",M58*L58,IF(H58="CÉLULA CONSTRUTIVA",SUMIFS($N$8:$N$262,$B$8:$B$262,B58,$H$8:$H$262,"Serviço"),IF(H58="ETAPA",SUMIFS($N$8:$N$262,$B$8:$B$262,B58,$C$8:$C$262,C58,$H$8:$H$262,"Serviço"),IF(H58="SUBETAPA",SUMIFS($N$8:$N$262,$B$8:$B$262,B58,$C$8:$C$262,C58,$D$8:$D$262,D58,$H$8:$H$262,"Serviço"),0)))) -> 18309.413
A59: =IF($H59="UNIDADE CONSTRUTIVA",OFFSET(A59,-1,0)+1,LARGE(A$3:A58,1)) -> 0 | B59: =IF(H59="UNIDADE CONSTRUTIVA",0,IF(H59="CÉLULA CONSTRUTIVA",OFFSET(B59,-1,0)+1,OFFSET(B59,-1,0))) -> 2 | C59: =IF(H59="CÉLULA CONSTRUTIVA",0,IF(H59="ETAPA",OFFSET(C59,-1,0)+1,OFFSET(C59,-1,0))) -> 1 | D59: =IF(H59="ETAPA",0,IF(H59="SUBETAPA",OFFSET(D59,-1,0)+1,OFFSET(D59,-1,0))) -> 8 | E59: =IF(H59="Subetapa",0,IF(H59="serviço",OFFSET(E59,-1,0)+1,OFFSET(E59,-1,0))) -> 1 | H59: SERVIÇO | I59: =IF(H59="Unidade Construtiva",TEXT(A59,"00"),IF(H59="Célula Construtiva",TEXT(B59,"00"),IF(H59="Etapa",CONCATENATE(TEXT(B59,"00"),".",TEXT(C59,"000")),IF(H59="Subetapa",CONCATENATE(TEXT(B59,"00"),".",TEXT(C59,"000"),".",TEXT(D59,"000")),IF(H59="Serviço",CONCATENATE(TEXT(B59,"00"),".",TEXT(C59,"000"),".",TEXT(D59,"000"),".",TEXT(E59,"000")),""))))) -> 02.001.008.001 | J59: C3 - Argamassa polimérica rígida, estruturada com tela de poliéster nos pontos críticos (3,0 kg/m²) | K59: m2 | L59: =SUMIFS(IMPERMEABILIZAÇÃO!B$13:B$145,IMPERMEABILIZAÇÃO!D$13:D$145,IMPERMEABILIZAÇÃO!$U$7,IMPERMEABILIZAÇÃO!E$13:E$145,$I$58) -> 32.87 | M59: 29.666667 | N59: =IF(H59="Serviço",M59*L59,IF(H59="CÉLULA CONSTRUTIVA",SUMIFS($N$8:$N$262,$B$8:$B$262,B59,$H$8:$H$262,"Serviço"),IF(H59="ETAPA",SUMIFS($N$8:$N$262,$B$8:$B$262,B59,$C$8:$C$262,C59,$H$8:$H$262,"Serviço"),IF(H59="SUBETAPA",SUMIFS($N$8:$N$262,$B$8:$B$262,B59,$C$8:$C$262,C59,$D$8:$D$262,D59,$H$8:$H$262,"Serviço"),0)))) -> 975.14333
A60: =IF($H60="UNIDADE CONSTRUTIVA",OFFSET(A60,-1,0)+1,LARGE(A$3:A59,1)) -> 0 | B60: =IF(H60="UNIDADE CONSTRUTIVA",0,IF(H60="CÉLULA CONSTRUTIVA",OFFSET(B60,-1,0)+1,OFFSET(B60,-1,0))) -> 2 | C60: =IF(H60="CÉLULA CONSTRUTIVA",0,IF(H60="ETAPA",OFFSET(C60,-1,0)+1,OFFSET(C60,-1,0))) -> 1 | D60: =IF(H60="ETAPA",0,IF(H60="SUBETAPA",OFFSET(D60,-1,0)+1,OFFSET(D60,-1,0))) -> 8 | E60: =IF(H60="Subetapa",0,IF(H60="serviço",OFFSET(E60,-1,0)+1,OFFSET(E60,-1,0))) -> 2 | H60: SERVIÇO | I60: =IF(H60="Unidade Construtiva",TEXT(A60,"00"),IF(H60="Célula Construtiva",TEXT(B60,"00"),IF(H60="Etapa",CONCATENATE(TEXT(B60,"00"),".",TEXT(C60,"000")),IF(H60="Subetapa",CONCATENATE(TEXT(B60,"00"),".",TEXT(C60,"000"),".",TEXT(D60,"000")),IF(H60="Serviço",CONCATENATE(TEXT(B60,"00"),".",TEXT(C60,"000"),".",TEXT(D60,"000"),".",TEXT(E60,"000")),""))))) -> 02.001.008.002 | J60: C3E3 - Argamassa polimérica rígida (3,0 kg/m²) + membrana de polímero acrílico com cimento e fibras, estruturada com tela de poliéster nos pontos críticos (3,0 kg/m²) | K60: m2 | L60: =SUMIFS(IMPERMEABILIZAÇÃO!B$13:B$145,IMPERMEABILIZAÇÃO!D$13:D$145,IMPERMEABILIZAÇÃO!$U$8,IMPERMEABILIZAÇÃO!E$13:E$145,$I$58) -> 163.53 | M60: 95.666667 | N60: =IF(H60="Serviço",M60*L60,IF(H60="CÉLULA CONSTRUTIVA",SUMIFS($N$8:$N$262,$B$8:$B$262,B60,$H$8:$H$262,"Serviço"),IF(H60="ETAPA",SUMIFS($N$8:$N$262,$B$8:$B$262,B60,$C$8:$C$262,C60,$H$8:$H$262,"Serviço"),IF(H60="SUBETAPA",SUMIFS($N$8:$N$262,$B$8:$B$262,B60,$C$8:$C$262,C60,$D$8:$D$262,D60,$H$8:$H$262,"Serviço"),0)))) -> 15644.37
A61: =IF($H61="UNIDADE CONSTRUTIVA",OFFSET(A61,-1,0)+1,LARGE(A$3:A60,1)) -> 0 | B61: =IF(H61="UNIDADE CONSTRUTIVA",0,IF(H61="CÉLULA CONSTRUTIVA",OFFSET(B61,-1,0)+1,OFFSET(B61,-1,0))) -> 2 | C61: =IF(H61="CÉLULA CONSTRUTIVA",0,IF(H61="ETAPA",OFFSET(C61,-1,0)+1,OFFSET(C61,-1,0))) -> 1 | D61: =IF(H61="ETAPA",0,IF(H61="SUBETAPA",OFFSET(D61,-1,0)+1,OFFSET(D61,-1,0))) -> 8 | E61: =IF(H61="Subetapa",0,IF(H61="serviço",OFFSET(E61,-1,0)+1,OFFSET(E61,-1,0))) -> 3 | H61: SERVIÇO | I61: =IF(H61="Unidade Construtiva",TEXT(A61,"00"),IF(H61="Célula Construtiva",TEXT(B61,"00"),IF(H61="Etapa",CONCATENATE(TEXT(B61,"00"),".",TEXT(C61,"000")),IF(H61="Subetapa",CONCATENATE(TEXT(B61,"00"),".",TEXT(C61,"000"),".",TEXT(D61,"000")),IF(H61="Serviço",CONCATENATE(TEXT(B61,"00"),".",TEXT(C61,"000"),".",TEXT(D61,"000"),".",TEXT(E61,"000")),""))))) -> 02.001.008.003 | J61: E2 - Membrana de polímero acrílico, com cimento e com fibras, estruturada com tela de poliéster nos pontos críticos (2,0 kg/m²) | K61: m2 | L61: =SUMIFS(IMPERMEABILIZAÇÃO!B$13:B$145,IMPERMEABILIZAÇÃO!D$13:D$145,IMPERMEABILIZAÇÃO!$U$13,IMPERMEABILIZAÇÃO!E$13:E$145,$I$58) -> 27.76 | M61: 48 | N61: =IF(H61="Serviço",M61*L61,IF(H61="CÉLULA CONSTRUTIVA",SUMIFS($N$8:$N$262,$B$8:$B$262,B61,$H$8:$H$262,"Serviço"),IF(H61="ETAPA",SUMIFS($N$8:$N$262,$B$8:$B$262,B61,$C$8:$C$262,C61,$H$8:$H$262,"Serviço"),IF(H61="SUBETAPA",SUMIFS($N$8:$N$262,$B$8:$B$262,B61,$C$8:$C$262,C61,$D$8:$D$262,D61,$H$8:$H$262,"Serviço"),0)))) -> 1332.48
A62: =IF($H62="UNIDADE CONSTRUTIVA",OFFSET(A62,-1,0)+1,LARGE(A$3:A61,1)) -> 0 | B62: =IF(H62="UNIDADE CONSTRUTIVA",0,IF(H62="CÉLULA CONSTRUTIVA",OFFSET(B62,-1,0)+1,OFFSET(B62,-1,0))) -> 2 | C62: =IF(H62="CÉLULA CONSTRUTIVA",0,IF(H62="ETAPA",OFFSET(C62,-1,0)+1,OFFSET(C62,-1,0))) -> 1 | D62: =IF(H62="ETAPA",0,IF(H62="SUBETAPA",OFFSET(D62,-1,0)+1,OFFSET(D62,-1,0))) -> 8 | E62: =IF(H62="Subetapa",0,IF(H62="serviço",OFFSET(E62,-1,0)+1,OFFSET(E62,-1,0))) -> 4 | H62: SERVIÇO | I62: =IF(H62="Unidade Construtiva",TEXT(A62,"00"),IF(H62="Célula Construtiva",TEXT(B62,"00"),IF(H62="Etapa",CONCATENATE(TEXT(B62,"00"),".",TEXT(C62,"000")),IF(H62="Subetapa",CONCATENATE(TEXT(B62,"00"),".",TEXT(C62,"000"),".",TEXT(D62,"000")),IF(H62="Serviço",CONCATENATE(TEXT(B62,"00"),".",TEXT(C62,"000"),".",TEXT(D62,"000"),".",TEXT(E62,"000")),""))))) -> 02.001.008.004 | J62: M44AR05 - Manta asfáltica tipo IV, 4 mm A, com acabamento areia/areia aderida com asfalto oxidado (3,0 kg/m²) + banho de asfalto oxidado (2,0 kg/m²) + pintura de proteção antirraiz sobre a proteção mecânica (0,5 L/m²) | K62: m2 | L62: =SUMIFS(IMPERMEABILIZAÇÃO!B$13:B$145,IMPERMEABILIZAÇÃO!D$13:D$145,IMPERMEABILIZAÇÃO!$U$14,IMPERMEABILIZAÇÃO!E$13:E$145,$I$58) -> 2.59 | M62: 138 | N62: =IF(H62="Serviço",M62*L62,IF(H62="CÉLULA CONSTRUTIVA",SUMIFS($N$8:$N$262,$B$8:$B$262,B62,$H$8:$H$262,"Serviço"),IF(H62="ETAPA",SUMIFS($N$8:$N$262,$B$8:$B$262,B62,$C$8:$C$262,C62,$H$8:$H$262,"Serviço"),IF(H62="SUBETAPA",SUMIFS($N$8:$N$262,$B$8:$B$262,B62,$C$8:$C$262,C62,$D$8:$D$262,D62,$H$8:$H$262,"Serviço"),0)))) -> 357.42
A63: =IF($H63="UNIDADE CONSTRUTIVA",OFFSET(A63,-1,0)+1,LARGE(A$3:A62,1)) -> 0 | B63: =IF(H63="UNIDADE CONSTRUTIVA",0,IF(H63="CÉLULA CONSTRUTIVA",OFFSET(B63,-1,0)+1,OFFSET(B63,-1,0))) -> 2 | C63: =IF(H63="CÉLULA CONSTRUTIVA",0,IF(H63="ETAPA",OFFSET(C63,-1,0)+1,OFFSET(C63,-1,0))) -> 1 | D63: =IF(H63="ETAPA",0,IF(H63="SUBETAPA",OFFSET(D63,-1,0)+1,OFFSET(D63,-1,0))) -> 9 | E63: =IF(H63="Subetapa",0,IF(H63="serviço",OFFSET(E63,-1,0)+1,OFFSET(E63,-1,0))) -> 0 | H63: SUBETAPA | I63: =IF(H63="Unidade Construtiva",TEXT(A63,"00"),IF(H63="Célula Construtiva",TEXT(B63,"00"),IF(H63="Etapa",CONCATENATE(TEXT(B63,"00"),".",TEXT(C63,"000")),IF(H63="Subetapa",CONCATENATE(TEXT(B63,"00"),".",TEXT(C63,"000"),".",TEXT(D63,"000")),IF(H63="Serviço",CONCATENATE(TEXT(B63,"00"),".",TEXT(C63,"000"),".",TEXT(D63,"000"),".",TEXT(E63,"000")),""))))) -> 02.001.009 | J63: Mão de Obra | N63: =IF(H63="Serviço",M63*L63,IF(H63="CÉLULA CONSTRUTIVA",SUMIFS($N$8:$N$262,$B$8:$B$262,B63,$H$8:$H$262,"Serviço"),IF(H63="ETAPA",SUMIFS($N$8:$N$262,$B$8:$B$262,B63,$C$8:$C$262,C63,$H$8:$H$262,"Serviço"),IF(H63="SUBETAPA",SUMIFS($N$8:$N$262,$B$8:$B$262,B63,$C$8:$C$262,C63,$D$8:$D$262,D63,$H$8:$H$262,"Serviço"),0)))) -> 270614.35
A64: =IF($H64="UNIDADE CONSTRUTIVA",OFFSET(A64,-1,0)+1,LARGE(A$3:A63,1)) -> 0 | B64: =IF(H64="UNIDADE CONSTRUTIVA",0,IF(H64="CÉLULA CONSTRUTIVA",OFFSET(B64,-1,0)+1,OFFSET(B64,-1,0))) -> 2 | C64: =IF(H64="CÉLULA CONSTRUTIVA",0,IF(H64="ETAPA",OFFSET(C64,-1,0)+1,OFFSET(C64,-1,0))) -> 1 | D64: =IF(H64="ETAPA",0,IF(H64="SUBETAPA",OFFSET(D64,-1,0)+1,OFFSET(D64,-1,0))) -> 9 | E64: =IF(H64="Subetapa",0,IF(H64="serviço",OFFSET(E64,-1,0)+1,OFFSET(E64,-1,0))) -> 1 | H64: SERVIÇO | I64: =IF(H64="Unidade Construtiva",TEXT(A64,"00"),IF(H64="Célula Construtiva",TEXT(B64,"00"),IF(H64="Etapa",CONCATENATE(TEXT(B64,"00"),".",TEXT(C64,"000")),IF(H64="Subetapa",CONCATENATE(TEXT(B64,"00"),".",TEXT(C64,"000"),".",TEXT(D64,"000")),IF(H64="Serviço",CONCATENATE(TEXT(B64,"00"),".",TEXT(C64,"000"),".",TEXT(D64,"000"),".",TEXT(E64,"000")),""))))) -> 02.001.009.001 | J64: Mão de obra para regularização de superfície | K64: m2 | L64: =L31 -> 2847.53 | M64: 20 | N64: =IF(H64="Serviço",M64*L64,IF(H64="CÉLULA CONSTRUTIVA",SUMIFS($N$8:$N$262,$B$8:$B$262,B64,$H$8:$H$262,"Serviço"),IF(H64="ETAPA",SUMIFS($N$8:$N$262,$B$8:$B$262,B64,$C$8:$C$262,C64,$H$8:$H$262,"Serviço"),IF(H64="SUBETAPA",SUMIFS($N$8:$N$262,$B$8:$B$262,B64,$C$8:$C$262,C64,$D$8:$D$262,D64,$H$8:$H$262,"Serviço"),0)))) -> 56950.6
A65: =IF($H65="UNIDADE CONSTRUTIVA",OFFSET(A65,-1,0)+1,LARGE(A$3:A64,1)) -> 0 | B65: =IF(H65="UNIDADE CONSTRUTIVA",0,IF(H65="CÉLULA CONSTRUTIVA",OFFSET(B65,-1,0)+1,OFFSET(B65,-1,0))) -> 2 | C65: =IF(H65="CÉLULA CONSTRUTIVA",0,IF(H65="ETAPA",OFFSET(C65,-1,0)+1,OFFSET(C65,-1,0))) -> 1 | D65: =IF(H65="ETAPA",0,IF(H65="SUBETAPA",OFFSET(D65,-1,0)+1,OFFSET(D65,-1,0))) -> 9 | E65: =IF(H65="Subetapa",0,IF(H65="serviço",OFFSET(E65,-1,0)+1,OFFSET(E65,-1,0))) -> 2 | H65: SERVIÇO | I65: =IF(H65="Unidade Construtiva",TEXT(A65,"00"),IF(H65="Célula Construtiva",TEXT(B65,"00"),IF(H65="Etapa",CONCATENATE(TEXT(B65,"00"),".",TEXT(C65,"000")),IF(H65="Subetapa",CONCATENATE(TEXT(B65,"00"),".",TEXT(C65,"000"),".",TEXT(D65,"000")),IF(H65="Serviço",CONCATENATE(TEXT(B65,"00"),".",TEXT(C65,"000"),".",TEXT(D65,"000"),".",TEXT(E65,"000")),""))))) -> 02.001.009.002 | J65: Mão de obra para proteção mecânica | K65: m2 | L65: =L32 -> 772.38 | M65: 35 | N65: =IF(H65="Serviço",M65*L65,IF(H65="CÉLULA CONSTRUTIVA",SUMIFS($N$8:$N$262,$B$8:$B$262,B65,$H$8:$H$262,"Serviço"),IF(H65="ETAPA",SUMIFS($N$8:$N$262,$B$8:$B$262,B65,$C$8:$C$262,C65,$H$8:$H$262,"Serviço"),IF(H65="SUBETAPA",SUMIFS($N$8:$N$262,$B$8:$B$262,B65,$C$8:$C$262,C65,$D$8:$D$262,D65,$H$8:$H$262,"Serviço"),0)))) -> 27033.3
A66: =IF($H66="UNIDADE CONSTRUTIVA",OFFSET(A66,-1,0)+1,LARGE(A$3:A65,1)) -> 0 | B66: =IF(H66="UNIDADE CONSTRUTIVA",0,IF(H66="CÉLULA CONSTRUTIVA",OFFSET(B66,-1,0)+1,OFFSET(B66,-1,0))) -> 2 | C66: =IF(H66="CÉLULA CONSTRUTIVA",0,IF(H66="ETAPA",OFFSET(C66,-1,0)+1,OFFSET(C66,-1,0))) -> 1 | D66: =IF(H66="ETAPA",0,IF(H66="SUBETAPA",OFFSET(D66,-1,0)+1,OFFSET(D66,-1,0))) -> 9 | E66: =IF(H66="Subetapa",0,IF(H66="serviço",OFFSET(E66,-1,0)+1,OFFSET(E66,-1,0))) -> 3 | H66: SERVIÇO | I66: =IF(H66="Unidade Construtiva",TEXT(A66,"00"),IF(H66="Célula Construtiva",TEXT(B66,"00"),IF(H66="Etapa",CONCATENATE(TEXT(B66,"00"),".",TEXT(C66,"000")),IF(H66="Subetapa",CONCATENATE(TEXT(B66,"00"),".",TEXT(C66,"000"),".",TEXT(D66,"000")),IF(H66="Serviço",CONCATENATE(TEXT(B66,"00"),".",TEXT(C66,"000"),".",TEXT(D66,"000"),".",TEXT(E66,"000")),""))))) -> 02.001.009.003 | J66: Mão de obra impermeabilização com membrana de polimero | K66: m2 | L66: =L38+L42+L45+L51+L61 -> 3036.61 | M66: 30 | N66: =IF(H66="Serviço",M66*L66,IF(H66="CÉLULA CONSTRUTIVA",SUMIFS($N$8:$N$262,$B$8:$B$262,B66,$H$8:$H$262,"Serviço"),IF(H66="ETAPA",SUMIFS($N$8:$N$262,$B$8:$B$262,B66,$C$8:$C$262,C66,$H$8:$H$262,"Serviço"),IF(H66="SUBETAPA",SUMIFS($N$8:$N$262,$B$8:$B$262,B66,$C$8:$C$262,C66,$D$8:$D$262,D66,$H$8:$H$262,"Serviço"),0)))) -> 91098.3
A67: =IF($H67="UNIDADE CONSTRUTIVA",OFFSET(A67,-1,0)+1,LARGE(A$3:A66,1)) -> 0 | B67: =IF(H67="UNIDADE CONSTRUTIVA",0,IF(H67="CÉLULA CONSTRUTIVA",OFFSET(B67,-1,0)+1,OFFSET(B67,-1,0))) -> 2 | C67: =IF(H67="CÉLULA CONSTRUTIVA",0,IF(H67="ETAPA",OFFSET(C67,-1,0)+1,OFFSET(C67,-1,0))) -> 1 | D67: =IF(H67="ETAPA",0,IF(H67="SUBETAPA",OFFSET(D67,-1,0)+1,OFFSET(D67,-1,0))) -> 9 | E67: =IF(H67="Subetapa",0,IF(H67="serviço",OFFSET(E67,-1,0)+1,OFFSET(E67,-1,0))) -> 4 | H67: SERVIÇO | I67: =IF(H67="Unidade Construtiva",TEXT(A67,"00"),IF(H67="Célula Construtiva",TEXT(B67,"00"),IF(H67="Etapa",CONCATENATE(TEXT(B67,"00"),".",TEXT(C67,"000")),IF(H67="Subetapa",CONCATENATE(TEXT(B67,"00"),".",TEXT(C67,"000"),".",TEXT(D67,"000")),IF(H67="Serviço",CONCATENATE(TEXT(B67,"00"),".",TEXT(C67,"000"),".",TEXT(D67,"000"),".",TEXT(E67,"000")),""))))) -> 02.001.009.004 | J67: Mão de obra impermeabilização de superfície com manta asfáltica | K67: m2 | L67: =L62+L53+L48+L47+L41+L40+L39+L37 -> 982.65 | M67: 45 | N67: =IF(H67="Serviço",M67*L67,IF(H67="CÉLULA CONSTRUTIVA",SUMIFS($N$8:$N$262,$B$8:$B$262,B67,$H$8:$H$262,"Serviço"),IF(H67="ETAPA",SUMIFS($N$8:$N$262,$B$8:$B$262,B67,$C$8:$C$262,C67,$H$8:$H$262,"Serviço"),IF(H67="SUBETAPA",SUMIFS($N$8:$N$262,$B$8:$B$262,B67,$C$8:$C$262,C67,$D$8:$D$262,D67,$H$8:$H$262,"Serviço"),0)))) -> 44219.25
A68: =IF($H68="UNIDADE CONSTRUTIVA",OFFSET(A68,-1,0)+1,LARGE(A$3:A67,1)) -> 0 | B68: =IF(H68="UNIDADE CONSTRUTIVA",0,IF(H68="CÉLULA CONSTRUTIVA",OFFSET(B68,-1,0)+1,OFFSET(B68,-1,0))) -> 2 | C68: =IF(H68="CÉLULA CONSTRUTIVA",0,IF(H68="ETAPA",OFFSET(C68,-1,0)+1,OFFSET(C68,-1,0))) -> 1 | D68: =IF(H68="ETAPA",0,IF(H68="SUBETAPA",OFFSET(D68,-1,0)+1,OFFSET(D68,-1,0))) -> 9 | E68: =IF(H68="Subetapa",0,IF(H68="serviço",OFFSET(E68,-1,0)+1,OFFSET(E68,-1,0))) -> 5 | H68: SERVIÇO | I68: =IF(H68="Unidade Construtiva",TEXT(A68,"00"),IF(H68="Célula Construtiva",TEXT(B68,"00"),IF(H68="Etapa",CONCATENATE(TEXT(B68,"00"),".",TEXT(C68,"000")),IF(H68="Subetapa",CONCATENATE(TEXT(B68,"00"),".",TEXT(C68,"000"),".",TEXT(D68,"000")),IF(H68="Serviço",CONCATENATE(TEXT(B68,"00"),".",TEXT(C68,"000"),".",TEXT(D68,"000"),".",TEXT(E68,"000")),""))))) -> 02.001.009.005 | J68: Mão de obra impermeabilização de argamassa polimérica | K68: m2 | L68: =L60+L59+L55+L52+L50+L44+L43+L36+L34 -> 965.43 | M68: 30 | N68: =IF(H68="Serviço",M68*L68,IF(H68="CÉLULA CONSTRUTIVA",SUMIFS($N$8:$N$262,$B$8:$B$262,B68,$H$8:$H$262,"Serviço"),IF(H68="ETAPA",SUMIFS($N$8:$N$262,$B$8:$B$262,B68,$C$8:$C$262,C68,$H$8:$H$262,"Serviço"),IF(H68="SUBETAPA",SUMIFS($N$8:$N$262,$B$8:$B$262,B68,$C$8:$C$262,C68,$D$8:$D$262,D68,$H$8:$H$262,"Serviço"),0)))) -> 28962.9
A69: =IF($H69="UNIDADE CONSTRUTIVA",OFFSET(A69,-1,0)+1,LARGE(A$3:A68,1)) -> 0 | B69: =IF(H69="UNIDADE CONSTRUTIVA",0,IF(H69="CÉLULA CONSTRUTIVA",OFFSET(B69,-1,0)+1,OFFSET(B69,-1,0))) -> 2 | C69: =IF(H69="CÉLULA CONSTRUTIVA",0,IF(H69="ETAPA",OFFSET(C69,-1,0)+1,OFFSET(C69,-1,0))) -> 1 | D69: =IF(H69="ETAPA",0,IF(H69="SUBETAPA",OFFSET(D69,-1,0)+1,OFFSET(D69,-1,0))) -> 9 | E69: =IF(H69="Subetapa",0,IF(H69="serviço",OFFSET(E69,-1,0)+1,OFFSET(E69,-1,0))) -> 6 | H69: SERVIÇO | I69: =IF(H69="Unidade Construtiva",TEXT(A69,"00"),IF(H69="Célula Construtiva",TEXT(B69,"00"),IF(H69="Etapa",CONCATENATE(TEXT(B69,"00"),".",TEXT(C69,"000")),IF(H69="Subetapa",CONCATENATE(TEXT(B69,"00"),".",TEXT(C69,"000"),".",TEXT(D69,"000")),IF(H69="Serviço",CONCATENATE(TEXT(B69,"00"),".",TEXT(C69,"000"),".",TEXT(D69,"000"),".",TEXT(E69,"000")),""))))) -> 02.001.009.006 | J69: Mão de obra tratamento de ralo com manta de poliéster | K69: un | L69: =L57 -> 447 | M69: 50 | N69: =IF(H69="Serviço",M69*L69,IF(H69="CÉLULA CONSTRUTIVA",SUMIFS($N$8:$N$262,$B$8:$B$262,B69,$H$8:$H$262,"Serviço"),IF(H69="ETAPA",SUMIFS($N$8:$N$262,$B$8:$B$262,B69,$C$8:$C$262,C69,$H$8:$H$262,"Serviço"),IF(H69="SUBETAPA",SUMIFS($N$8:$N$262,$B$8:$B$262,B69,$C$8:$C$262,C69,$D$8:$D$262,D69,$H$8:$H$262,"Serviço"),0)))) -> 22350
A70: =IF($H70="UNIDADE CONSTRUTIVA",OFFSET(A70,-1,0)+1,LARGE(A$3:A69,1)) -> 0 | B70: =IF(H70="UNIDADE CONSTRUTIVA",0,IF(H70="CÉLULA CONSTRUTIVA",OFFSET(B70,-1,0)+1,OFFSET(B70,-1,0))) -> 3 | C70: =IF(H70="CÉLULA CONSTRUTIVA",0,IF(H70="ETAPA",OFFSET(C70,-1,0)+1,OFFSET(C70,-1,0))) -> 0 | D70: =IF(H70="ETAPA",0,IF(H70="SUBETAPA",OFFSET(D70,-1,0)+1,OFFSET(D70,-1,0))) -> 9 | E70: =IF(H70="Subetapa",0,IF(H70="serviço",OFFSET(E70,-1,0)+1,OFFSET(E70,-1,0))) -> 6 | H70: CÉLULA CONSTRUTIVA | I70: =IF(H70="Unidade Construtiva",TEXT(A70,"00"),IF(H70="Célula Construtiva",TEXT(B70,"00"),IF(H70="Etapa",CONCATENATE(TEXT(B70,"00"),".",TEXT(C70,"000")),IF(H70="Subetapa",CONCATENATE(TEXT(B70,"00"),".",TEXT(C70,"000"),".",TEXT(D70,"000")),IF(H70="Serviço",CONCATENATE(TEXT(B70,"00"),".",TEXT(C70,"000"),".",TEXT(D70,"000"),".",TEXT(E70,"000")),""))))) -> 03 | J70: REVESTIMENTOS INTERNOS DE PAREDE | N70: =IF(H70="Serviço",M70*L70,IF(H70="CÉLULA CONSTRUTIVA",SUMIFS($N$8:$N$262,$B$8:$B$262,B70,$H$8:$H$262,"Serviço"),IF(H70="ETAPA",SUMIFS($N$8:$N$262,$B$8:$B$262,B70,$C$8:$C$262,C70,$H$8:$H$262,"Serviço"),IF(H70="SUBETAPA",SUMIFS($N$8:$N$262,$B$8:$B$262,B70,$C$8:$C$262,C70,$D$8:$D$262,D70,$H$8:$H$262,"Serviço"),0)))) -> 1323971.4 | O70: =N70/'Obra '!$E$9 -> 190.81825
A71: =IF($H71="UNIDADE CONSTRUTIVA",OFFSET(A71,-1,0)+1,LARGE(A$3:A70,1)) -> 0 | B71: =IF(H71="UNIDADE CONSTRUTIVA",0,IF(H71="CÉLULA CONSTRUTIVA",OFFSET(B71,-1,0)+1,OFFSET(B71,-1,0))) -> 3 | C71: =IF(H71="CÉLULA CONSTRUTIVA",0,IF(H71="ETAPA",OFFSET(C71,-1,0)+1,OFFSET(C71,-1,0))) -> 1 | D71: =IF(H71="ETAPA",0,IF(H71="SUBETAPA",OFFSET(D71,-1,0)+1,OFFSET(D71,-1,0))) -> 0 | E71: =IF(H71="Subetapa",0,IF(H71="serviço",OFFSET(E71,-1,0)+1,OFFSET(E71,-1,0))) -> 6 | H71: ETAPA | I71: =IF(H71="Unidade Construtiva",TEXT(A71,"00"),IF(H71="Célula Construtiva",TEXT(B71,"00"),IF(H71="Etapa",CONCATENATE(TEXT(B71,"00"),".",TEXT(C71,"000")),IF(H71="Subetapa",CONCATENATE(TEXT(B71,"00"),".",TEXT(C71,"000"),".",TEXT(D71,"000")),IF(H71="Serviço",CONCATENATE(TEXT(B71,"00"),".",TEXT(C71,"000"),".",TEXT(D71,"000"),".",TEXT(E71,"000")),""))))) -> 03.001 | J71: REVESTIMENTOS INTERNOS DE PAREDE | N71: =IF(H71="Serviço",M71*L71,IF(H71="CÉLULA CONSTRUTIVA",SUMIFS($N$8:$N$262,$B$8:$B$262,B71,$H$8:$H$262,"Serviço"),IF(H71="ETAPA",SUMIFS($N$8:$N$262,$B$8:$B$262,B71,$C$8:$C$262,C71,$H$8:$H$262,"Serviço"),IF(H71="SUBETAPA",SUMIFS($N$8:$N$262,$B$8:$B$262,B71,$C$8:$C$262,C71,$D$8:$D$262,D71,$H$8:$H$262,"Serviço"),0)))) -> 1323971.4
A72: =IF($H72="UNIDADE CONSTRUTIVA",OFFSET(A72,-1,0)+1,LARGE(A$3:A71,1)) -> 0 | B72: =IF(H72="UNIDADE CONSTRUTIVA",0,IF(H72="CÉLULA CONSTRUTIVA",OFFSET(B72,-1,0)+1,OFFSET(B72,-1,0))) -> 3 | C72: =IF(H72="CÉLULA CONSTRUTIVA",0,IF(H72="ETAPA",OFFSET(C72,-1,0)+1,OFFSET(C72,-1,0))) -> 1 | D72: =IF(H72="ETAPA",0,IF(H72="SUBETAPA",OFFSET(D72,-1,0)+1,OFFSET(D72,-1,0))) -> 1 | E72: =IF(H72="Subetapa",0,IF(H72="serviço",OFFSET(E72,-1,0)+1,OFFSET(E72,-1,0))) -> 0 | H72: SUBETAPA | I72: =IF(H72="Unidade Construtiva",TEXT(A72,"00"),IF(H72="Célula Construtiva",TEXT(B72,"00"),IF(H72="Etapa",CONCATENATE(TEXT(B72,"00"),".",TEXT(C72,"000")),IF(H72="Subetapa",CONCATENATE(TEXT(B72,"00"),".",TEXT(C72,"000"),".",TEXT(D72,"000")),IF(H72="Serviço",CONCATENATE(TEXT(B72,"00"),".",TEXT(C72,"000"),".",TEXT(D72,"000"),".",TEXT(E72,"000")),""))))) -> 03.001.001 | J72: Argamassado interno em parede | N72: =IF(H72="Serviço",M72*L72,IF(H72="CÉLULA CONSTRUTIVA",SUMIFS($N$8:$N$262,$B$8:$B$262,B72,$H$8:$H$262,"Serviço"),IF(H72="ETAPA",SUMIFS($N$8:$N$262,$B$8:$B$262,B72,$C$8:$C$262,C72,$H$8:$H$262,"Serviço"),IF(H72="SUBETAPA",SUMIFS($N$8:$N$262,$B$8:$B$262,B72,$C$8:$C$262,C72,$D$8:$D$262,D72,$H$8:$H$262,"Serviço"),0)))) -> 159860.62 | O72: =N72/'Obra '!$E$9 -> 23.040016 | Q72: REVESTIMENTOS ARGAMASSADOS PAREDE
A73: =IF($H73="UNIDADE CONSTRUTIVA",OFFSET(A73,-1,0)+1,LARGE(A$3:A72,1)) -> 0 | B73: =IF(H73="UNIDADE CONSTRUTIVA",0,IF(H73="CÉLULA CONSTRUTIVA",OFFSET(B73,-1,0)+1,OFFSET(B73,-1,0))) -> 3 | C73: =IF(H73="CÉLULA CONSTRUTIVA",0,IF(H73="ETAPA",OFFSET(C73,-1,0)+1,OFFSET(C73,-1,0))) -> 1 | D73: =IF(H73="ETAPA",0,IF(H73="SUBETAPA",OFFSET(D73,-1,0)+1,OFFSET(D73,-1,0))) -> 1 | E73: =IF(H73="Subetapa",0,IF(H73="serviço",OFFSET(E73,-1,0)+1,OFFSET(E73,-1,0))) -> 1 | H73: SERVIÇO | I73: =IF(H73="Unidade Construtiva",TEXT(A73,"00"),IF(H73="Célula Construtiva",TEXT(B73,"00"),IF(H73="Etapa",CONCATENATE(TEXT(B73,"00"),".",TEXT(C73,"000")),IF(H73="Subetapa",CONCATENATE(TEXT(B73,"00"),".",TEXT(C73,"000"),".",TEXT(D73,"000")),IF(H73="Serviço",CONCATENATE(TEXT(B73,"00"),".",TEXT(C73,"000"),".",TEXT(D73,"000"),".",TEXT(E73,"000")),""))))) -> 03.001.001.001 | J73: Massa unica para emboço interno em argamassa estabilizada, espessura de 2,5cm, com execução de taliscas | K73: m2 | L73: =ARQUITETURA!H465 -> 2077.54 | M73: 17.745838 | N73: =IF(H73="Serviço",M73*L73,IF(H73="CÉLULA CONSTRUTIVA",SUMIFS($N$8:$N$262,$B$8:$B$262,B73,$H$8:$H$262,"Serviço"),IF(H73="ETAPA",SUMIFS($N$8:$N$262,$B$8:$B$262,B73,$C$8:$C$262,C73,$H$8:$H$262,"Serviço"),IF(H73="SUBETAPA",SUMIFS($N$8:$N$262,$B$8:$B$262,B73,$C$8:$C$262,C73,$D$8:$D$262,D73,$H$8:$H$262,"Serviço"),0)))) -> 36867.688
A74: =IF($H74="UNIDADE CONSTRUTIVA",OFFSET(A74,-1,0)+1,LARGE(A$3:A73,1)) -> 0 | B74: =IF(H74="UNIDADE CONSTRUTIVA",0,IF(H74="CÉLULA CONSTRUTIVA",OFFSET(B74,-1,0)+1,OFFSET(B74,-1,0))) -> 3 | C74: =IF(H74="CÉLULA CONSTRUTIVA",0,IF(H74="ETAPA",OFFSET(C74,-1,0)+1,OFFSET(C74,-1,0))) -> 1 | D74: =IF(H74="ETAPA",0,IF(H74="SUBETAPA",OFFSET(D74,-1,0)+1,OFFSET(D74,-1,0))) -> 1 | E74: =IF(H74="Subetapa",0,IF(H74="serviço",OFFSET(E74,-1,0)+1,OFFSET(E74,-1,0))) -> 2 | H74: SERVIÇO | I74: =IF(H74="Unidade Construtiva",TEXT(A74,"00"),IF(H74="Célula Construtiva",TEXT(B74,"00"),IF(H74="Etapa",CONCATENATE(TEXT(B74,"00"),".",TEXT(C74,"000")),IF(H74="Subetapa",CONCATENATE(TEXT(B74,"00"),".",TEXT(C74,"000"),".",TEXT(D74,"000")),IF(H74="Serviço",CONCATENATE(TEXT(B74,"00"),".",TEXT(C74,"000"),".",TEXT(D74,"000"),".",TEXT(E74,"000")),""))))) -> 03.001.001.002 | J74: Chapisco aplicado em estruturas de concreto, com argamassa pré-fabricada adesiva de cimento colante, aplicação convencional | K74: m2 | L74: =ARQUITETURA!H528 -> 365.5 | M74: 19.53585 | N74: =IF(H74="Serviço",M74*L74,IF(H74="CÉLULA CONSTRUTIVA",SUMIFS($N$8:$N$262,$B$8:$B$262,B74,$H$8:$H$262,"Serviço"),IF(H74="ETAPA",SUMIFS($N$8:$N$262,$B$8:$B$262,B74,$C$8:$C$262,C74,$H$8:$H$262,"Serviço"),IF(H74="SUBETAPA",SUMIFS($N$8:$N$262,$B$8:$B$262,B74,$C$8:$C$262,C74,$D$8:$D$262,D74,$H$8:$H$262,"Serviço"),0)))) -> 7140.3532
A75: =IF($H75="UNIDADE CONSTRUTIVA",OFFSET(A75,-1,0)+1,LARGE(A$3:A74,1)) -> 0 | B75: =IF(H75="UNIDADE CONSTRUTIVA",0,IF(H75="CÉLULA CONSTRUTIVA",OFFSET(B75,-1,0)+1,OFFSET(B75,-1,0))) -> 3 | C75: =IF(H75="CÉLULA CONSTRUTIVA",0,IF(H75="ETAPA",OFFSET(C75,-1,0)+1,OFFSET(C75,-1,0))) -> 1 | D75: =IF(H75="ETAPA",0,IF(H75="SUBETAPA",OFFSET(D75,-1,0)+1,OFFSET(D75,-1,0))) -> 1 | E75: =IF(H75="Subetapa",0,IF(H75="serviço",OFFSET(E75,-1,0)+1,OFFSET(E75,-1,0))) -> 3 | H75: SERVIÇO | I75: =IF(H75="Unidade Construtiva",TEXT(A75,"00"),IF(H75="Célula Construtiva",TEXT(B75,"00"),IF(H75="Etapa",CONCATENATE(TEXT(B75,"00"),".",TEXT(C75,"000")),IF(H75="Subetapa",CONCATENATE(TEXT(B75,"00"),".",TEXT(C75,"000"),".",TEXT(D75,"000")),IF(H75="Serviço",CONCATENATE(TEXT(B75,"00"),".",TEXT(C75,"000"),".",TEXT(D75,"000"),".",TEXT(E75,"000")),""))))) -> 03.001.001.003 | J75: Chapisco convencional com adesivo sintético de alto desempenho aplicados em alvenaria, aplicação convencional. | K75: m2 | L75: =ARQUITETURA!H527 -> 1712.04 | M75: 7.49985 | N75: =IF(H75="Serviço",M75*L75,IF(H75="CÉLULA CONSTRUTIVA",SUMIFS($N$8:$N$262,$B$8:$B$262,B75,$H$8:$H$262,"Serviço"),IF(H75="ETAPA",SUMIFS($N$8:$N$262,$B$8:$B$262,B75,$C$8:$C$262,C75,$H$8:$H$262,"Serviço"),IF(H75="SUBETAPA",SUMIFS($N$8:$N$262,$B$8:$B$262,B75,$C$8:$C$262,C75,$D$8:$D$262,D75,$H$8:$H$262,"Serviço"),0)))) -> 12840.043
A76: =IF($H76="UNIDADE CONSTRUTIVA",OFFSET(A76,-1,0)+1,LARGE(A$3:A75,1)) -> 0 | B76: =IF(H76="UNIDADE CONSTRUTIVA",0,IF(H76="CÉLULA CONSTRUTIVA",OFFSET(B76,-1,0)+1,OFFSET(B76,-1,0))) -> 3 | C76: =IF(H76="CÉLULA CONSTRUTIVA",0,IF(H76="ETAPA",OFFSET(C76,-1,0)+1,OFFSET(C76,-1,0))) -> 1 | D76: =IF(H76="ETAPA",0,IF(H76="SUBETAPA",OFFSET(D76,-1,0)+1,OFFSET(D76,-1,0))) -> 1 | E76: =IF(H76="Subetapa",0,IF(H76="serviço",OFFSET(E76,-1,0)+1,OFFSET(E76,-1,0))) -> 4 | H76: SERVIÇO | I76: =IF(H76="Unidade Construtiva",TEXT(A76,"00"),IF(H76="Célula Construtiva",TEXT(B76,"00"),IF(H76="Etapa",CONCATENATE(TEXT(B76,"00"),".",TEXT(C76,"000")),IF(H76="Subetapa",CONCATENATE(TEXT(B76,"00"),".",TEXT(C76,"000"),".",TEXT(D76,"000")),IF(H76="Serviço",CONCATENATE(TEXT(B76,"00"),".",TEXT(C76,"000"),".",TEXT(D76,"000"),".",TEXT(E76,"000")),""))))) -> 03.001.001.004 | J76: Massa unica para reboco interno em argamassa estabilizada, espessura de 0,5cm, com execução desempenado fino | K76: m2 | L76: =ARQUITETURA!H588 -> 66.91 | M76: 3.179715 | N76: =IF(H76="Serviço",M76*L76,IF(H76="CÉLULA CONSTRUTIVA",SUMIFS($N$8:$N$262,$B$8:$B$262,B76,$H$8:$H$262,"Serviço"),IF(H76="ETAPA",SUMIFS($N$8:$N$262,$B$8:$B$262,B76,$C$8:$C$262,C76,$H$8:$H$262,"Serviço"),IF(H76="SUBETAPA",SUMIFS($N$8:$N$262,$B$8:$B$262,B76,$C$8:$C$262,C76,$D$8:$D$262,D76,$H$8:$H$262,"Serviço"),0)))) -> 212.75473
A77: =IF($H77="UNIDADE CONSTRUTIVA",OFFSET(A77,-1,0)+1,LARGE(A$3:A76,1)) -> 0 | B77: =IF(H77="UNIDADE CONSTRUTIVA",0,IF(H77="CÉLULA CONSTRUTIVA",OFFSET(B77,-1,0)+1,OFFSET(B77,-1,0))) -> 3 | C77: =IF(H77="CÉLULA CONSTRUTIVA",0,IF(H77="ETAPA",OFFSET(C77,-1,0)+1,OFFSET(C77,-1,0))) -> 1 | D77: =IF(H77="ETAPA",0,IF(H77="SUBETAPA",OFFSET(D77,-1,0)+1,OFFSET(D77,-1,0))) -> 1 | E77: =IF(H77="Subetapa",0,IF(H77="serviço",OFFSET(E77,-1,0)+1,OFFSET(E77,-1,0))) -> 5 | H77: SERVIÇO | I77: =IF(H77="Unidade Construtiva",TEXT(A77,"00"),IF(H77="Célula Construtiva",TEXT(B77,"00"),IF(H77="Etapa",CONCATENATE(TEXT(B77,"00"),".",TEXT(C77,"000")),IF(H77="Subetapa",CONCATENATE(TEXT(B77,"00"),".",TEXT(C77,"000"),".",TEXT(D77,"000")),IF(H77="Serviço",CONCATENATE(TEXT(B77,"00"),".",TEXT(C77,"000"),".",TEXT(D77,"000"),".",TEXT(E77,"000")),""))))) -> 03.001.001.005 | J77: Estucamento de estrutura de concreto em pilares e vigas | K77: m2 | L77: =ARQUITETURA!H593 -> 253.75 | M77: 5.1029167 | N77: =IF(H77="Serviço",M77*L77,IF(H77="CÉLULA CONSTRUTIVA",SUMIFS($N$8:$N$262,$B$8:$B$262,B77,$H$8:$H$262,"Serviço"),IF(H77="ETAPA",SUMIFS($N$8:$N$262,$B$8:$B$262,B77,$C$8:$C$262,C77,$H$8:$H$262,"Serviço"),IF(H77="SUBETAPA",SUMIFS($N$8:$N$262,$B$8:$B$262,B77,$C$8:$C$262,C77,$D$8:$D$262,D77,$H$8:$H$262,"Serviço"),0)))) -> 1294.8651
A78: =IF($H78="UNIDADE CONSTRUTIVA",OFFSET(A78,-1,0)+1,LARGE(A$3:A77,1)) -> 0 | B78: =IF(H78="UNIDADE CONSTRUTIVA",0,IF(H78="CÉLULA CONSTRUTIVA",OFFSET(B78,-1,0)+1,OFFSET(B78,-1,0))) -> 3 | C78: =IF(H78="CÉLULA CONSTRUTIVA",0,IF(H78="ETAPA",OFFSET(C78,-1,0)+1,OFFSET(C78,-1,0))) -> 1 | D78: =IF(H78="ETAPA",0,IF(H78="SUBETAPA",OFFSET(D78,-1,0)+1,OFFSET(D78,-1,0))) -> 1 | E78: =IF(H78="Subetapa",0,IF(H78="serviço",OFFSET(E78,-1,0)+1,OFFSET(E78,-1,0))) -> 6 | H78: SERVIÇO | I78: =IF(H78="Unidade Construtiva",TEXT(A78,"00"),IF(H78="Célula Construtiva",TEXT(B78,"00"),IF(H78="Etapa",CONCATENATE(TEXT(B78,"00"),".",TEXT(C78,"000")),IF(H78="Subetapa",CONCATENATE(TEXT(B78,"00"),".",TEXT(C78,"000"),".",TEXT(D78,"000")),IF(H78="Serviço",CONCATENATE(TEXT(B78,"00"),".",TEXT(C78,"000"),".",TEXT(D78,"000"),".",TEXT(E78,"000")),""))))) -> 03.001.001.006 | J78: Aplicação manual de gesso sarrafeado em paredes, espessura de 0,5cm, com execução de taliscas | K78: m2 | L78: =ARQUITETURA!H379 -> 10093.84 | M78: 6.829516 | N78: =IF(H78="Serviço",M78*L78,IF(H78="CÉLULA CONSTRUTIVA",SUMIFS($N$8:$N$262,$B$8:$B$262,B78,$H$8:$H$262,"Serviço"),IF(H78="ETAPA",SUMIFS($N$8:$N$262,$B$8:$B$262,B78,$C$8:$C$262,C78,$H$8:$H$262,"Serviço"),IF(H78="SUBETAPA",SUMIFS($N$8:$N$262,$B$8:$B$262,B78,$C$8:$C$262,C78,$D$8:$D$262,D78,$H$8:$H$262,"Serviço"),0)))) -> 68936.042
A79: =IF($H79="UNIDADE CONSTRUTIVA",OFFSET(A79,-1,0)+1,LARGE(A$3:A78,1)) -> 0 | B79: =IF(H79="UNIDADE CONSTRUTIVA",0,IF(H79="CÉLULA CONSTRUTIVA",OFFSET(B79,-1,0)+1,OFFSET(B79,-1,0))) -> 3 | C79: =IF(H79="CÉLULA CONSTRUTIVA",0,IF(H79="ETAPA",OFFSET(C79,-1,0)+1,OFFSET(C79,-1,0))) -> 1 | D79: =IF(H79="ETAPA",0,IF(H79="SUBETAPA",OFFSET(D79,-1,0)+1,OFFSET(D79,-1,0))) -> 1 | E79: =IF(H79="Subetapa",0,IF(H79="serviço",OFFSET(E79,-1,0)+1,OFFSET(E79,-1,0))) -> 7 | H79: SERVIÇO | I79: =IF(H79="Unidade Construtiva",TEXT(A79,"00"),IF(H79="Célula Construtiva",TEXT(B79,"00"),IF(H79="Etapa",CONCATENATE(TEXT(B79,"00"),".",TEXT(C79,"000")),IF(H79="Subetapa",CONCATENATE(TEXT(B79,"00"),".",TEXT(C79,"000"),".",TEXT(D79,"000")),IF(H79="Serviço",CONCATENATE(TEXT(B79,"00"),".",TEXT(C79,"000"),".",TEXT(D79,"000"),".",TEXT(E79,"000")),""))))) -> 03.001.001.007 | J79: Aplicação manual de gesso sarrafeado em paredes, espessura de 1,0cm, com execução de taliscas | K79: m2 | L79: =ARQUITETURA!H380 -> 2384.42 | M79: 13.659032 | N79: =IF(H79="Serviço",M79*L79,IF(H79="CÉLULA CONSTRUTIVA",SUMIFS($N$8:$N$262,$B$8:$B$262,B79,$H$8:$H$262,"Serviço"),IF(H79="ETAPA",SUMIFS($N$8:$N$262,$B$8:$B$262,B79,$C$8:$C$262,C79,$H$8:$H$262,"Serviço"),IF(H79="SUBETAPA",SUMIFS($N$8:$N$262,$B$8:$B$262,B79,$C$8:$C$262,C79,$D$8:$D$262,D79,$H$8:$H$262,"Serviço"),0)))) -> 32568.869
A80: =IF($H80="UNIDADE CONSTRUTIVA",OFFSET(A80,-1,0)+1,LARGE(A$3:A79,1)) -> 0 | B80: =IF(H80="UNIDADE CONSTRUTIVA",0,IF(H80="CÉLULA CONSTRUTIVA",OFFSET(B80,-1,0)+1,OFFSET(B80,-1,0))) -> 3 | C80: =IF(H80="CÉLULA CONSTRUTIVA",0,IF(H80="ETAPA",OFFSET(C80,-1,0)+1,OFFSET(C80,-1,0))) -> 1 | D80: =IF(H80="ETAPA",0,IF(H80="SUBETAPA",OFFSET(D80,-1,0)+1,OFFSET(D80,-1,0))) -> 2 | E80: =IF(H80="Subetapa",0,IF(H80="serviço",OFFSET(E80,-1,0)+1,OFFSET(E80,-1,0))) -> 0 | H80: SUBETAPA | I80: =IF(H80="Unidade Construtiva",TEXT(A80,"00"),IF(H80="Célula Construtiva",TEXT(B80,"00"),IF(H80="Etapa",CONCATENATE(TEXT(B80,"00"),".",TEXT(C80,"000")),IF(H80="Subetapa",CONCATENATE(TEXT(B80,"00"),".",TEXT(C80,"000"),".",TEXT(D80,"000")),IF(H80="Serviço",CONCATENATE(TEXT(B80,"00"),".",TEXT(C80,"000"),".",TEXT(D80,"000"),".",TEXT(E80,"000")),""))))) -> 03.001.002 | J80: Acabamentos cerâmicos | N80: =IF(H80="Serviço",M80*L80,IF(H80="CÉLULA CONSTRUTIVA",SUMIFS($N$8:$N$262,$B$8:$B$262,B80,$H$8:$H$262,"Serviço"),IF(H80="ETAPA",SUMIFS($N$8:$N$262,$B$8:$B$262,B80,$C$8:$C$262,C80,$H$8:$H$262,"Serviço"),IF(H80="SUBETAPA",SUMIFS($N$8:$N$262,$B$8:$B$262,B80,$C$8:$C$262,C80,$D$8:$D$262,D80,$H$8:$H$262,"Serviço"),0)))) -> 257234.24 | O80: =N80/'Obra '!$E$9 -> 37.074053 | Q80: ACABAMENTOS INTERNOS EM PAREDE
A81: =IF($H81="UNIDADE CONSTRUTIVA",OFFSET(A81,-1,0)+1,LARGE(A$3:A80,1)) -> 0 | B81: =IF(H81="UNIDADE CONSTRUTIVA",0,IF(H81="CÉLULA CONSTRUTIVA",OFFSET(B81,-1,0)+1,OFFSET(B81,-1,0))) -> 3 | C81: =IF(H81="CÉLULA CONSTRUTIVA",0,IF(H81="ETAPA",OFFSET(C81,-1,0)+1,OFFSET(C81,-1,0))) -> 1 | D81: =IF(H81="ETAPA",0,IF(H81="SUBETAPA",OFFSET(D81,-1,0)+1,OFFSET(D81,-1,0))) -> 2 | E81: =IF(H81="Subetapa",0,IF(H81="serviço",OFFSET(E81,-1,0)+1,OFFSET(E81,-1,0))) -> 1 | H81: SERVIÇO | I81: =IF(H81="Unidade Construtiva",TEXT(A81,"00"),IF(H81="Célula Construtiva",TEXT(B81,"00"),IF(H81="Etapa",CONCATENATE(TEXT(B81,"00"),".",TEXT(C81,"000")),IF(H81="Subetapa",CONCATENATE(TEXT(B81,"00"),".",TEXT(C81,"000"),".",TEXT(D81,"000")),IF(H81="Serviço",CONCATENATE(TEXT(B81,"00"),".",TEXT(C81,"000"),".",TEXT(D81,"000"),".",TEXT(E81,"000")),""))))) -> 03.001.002.001 | J81: Revestimento em paredes, 61x 61cm com Junta de 3mm | K81: m2 | L81: =SUM(ARQUITETURA!H633:H638,ARQUITETURA!H641:H650) -> 3263.4 | M81: 78.824 | N81: =IF(H81="Serviço",M81*L81,IF(H81="CÉLULA CONSTRUTIVA",SUMIFS($N$8:$N$262,$B$8:$B$262,B81,$H$8:$H$262,"Serviço"),IF(H81="ETAPA",SUMIFS($N$8:$N$262,$B$8:$B$262,B81,$C$8:$C$262,C81,$H$8:$H$262,"Serviço"),IF(H81="SUBETAPA",SUMIFS($N$8:$N$262,$B$8:$B$262,B81,$C$8:$C$262,C81,$D$8:$D$262,D81,$H$8:$H$262,"Serviço"),0)))) -> 257234.24
A82: =IF($H82="UNIDADE CONSTRUTIVA",OFFSET(A82,-1,0)+1,LARGE(A$3:A81,1)) -> 0 | B82: =IF(H82="UNIDADE CONSTRUTIVA",0,IF(H82="CÉLULA CONSTRUTIVA",OFFSET(B82,-1,0)+1,OFFSET(B82,-1,0))) -> 3 | C82: =IF(H82="CÉLULA CONSTRUTIVA",0,IF(H82="ETAPA",OFFSET(C82,-1,0)+1,OFFSET(C82,-1,0))) -> 1 | D82: =IF(H82="ETAPA",0,IF(H82="SUBETAPA",OFFSET(D82,-1,0)+1,OFFSET(D82,-1,0))) -> 3 | E82: =IF(H82="Subetapa",0,IF(H82="serviço",OFFSET(E82,-1,0)+1,OFFSET(E82,-1,0))) -> 0 | H82: SUBETAPA | I82: =IF(H82="Unidade Construtiva",TEXT(A82,"00"),IF(H82="Célula Construtiva",TEXT(B82,"00"),IF(H82="Etapa",CONCATENATE(TEXT(B82,"00"),".",TEXT(C82,"000")),IF(H82="Subetapa",CONCATENATE(TEXT(B82,"00"),".",TEXT(C82,"000"),".",TEXT(D82,"000")),IF(H82="Serviço",CONCATENATE(TEXT(B82,"00"),".",TEXT(C82,"000"),".",TEXT(D82,"000"),".",TEXT(E82,"000")),""))))) -> 03.001.003 | J82: Acabamentos especiais | N82: =IF(H82="Serviço",M82*L82,IF(H82="CÉLULA CONSTRUTIVA",SUMIFS($N$8:$N$262,$B$8:$B$262,B82,$H$8:$H$262,"Serviço"),IF(H82="ETAPA",SUMIFS($N$8:$N$262,$B$8:$B$262,B82,$C$8:$C$262,C82,$H$8:$H$262,"Serviço"),IF(H82="SUBETAPA",SUMIFS($N$8:$N$262,$B$8:$B$262,B82,$C$8:$C$262,C82,$D$8:$D$262,D82,$H$8:$H$262,"Serviço"),0)))) -> 21618.957 | O82: =N82/'Obra '!$E$9 -> 3.1158463 | Q82: ACABAMENTOS INTERNOS EM PAREDE
A83: =IF($H83="UNIDADE CONSTRUTIVA",OFFSET(A83,-1,0)+1,LARGE(A$3:A82,1)) -> 0 | B83: =IF(H83="UNIDADE CONSTRUTIVA",0,IF(H83="CÉLULA CONSTRUTIVA",OFFSET(B83,-1,0)+1,OFFSET(B83,-1,0))) -> 3 | C83: =IF(H83="CÉLULA CONSTRUTIVA",0,IF(H83="ETAPA",OFFSET(C83,-1,0)+1,OFFSET(C83,-1,0))) -> 1 | D83: =IF(H83="ETAPA",0,IF(H83="SUBETAPA",OFFSET(D83,-1,0)+1,OFFSET(D83,-1,0))) -> 3 | E83: =IF(H83="Subetapa",0,IF(H83="serviço",OFFSET(E83,-1,0)+1,OFFSET(E83,-1,0))) -> 1 | H83: SERVIÇO | I83: =IF(H83="Unidade Construtiva",TEXT(A83,"00"),IF(H83="Célula Construtiva",TEXT(B83,"00"),IF(H83="Etapa",CONCATENATE(TEXT(B83,"00"),".",TEXT(C83,"000")),IF(H83="Subetapa",CONCATENATE(TEXT(B83,"00"),".",TEXT(C83,"000"),".",TEXT(D83,"000")),IF(H83="Serviço",CONCATENATE(TEXT(B83,"00"),".",TEXT(C83,"000"),".",TEXT(D83,"000"),".",TEXT(E83,"000")),""))))) -> 03.001.003.001 | J83: Requadro de portas dos Elevadores Granito preto são gabriel | K83: m2 | L83: =ARQUITETURA!H702 -> 30.69 | M83: 704.43 | N83: =IF(H83="Serviço",M83*L83,IF(H83="CÉLULA CONSTRUTIVA",SUMIFS($N$8:$N$262,$B$8:$B$262,B83,$H$8:$H$262,"Serviço"),IF(H83="ETAPA",SUMIFS($N$8:$N$262,$B$8:$B$262,B83,$C$8:$C$262,C83,$H$8:$H$262,"Serviço"),IF(H83="SUBETAPA",SUMIFS($N$8:$N$262,$B$8:$B$262,B83,$C$8:$C$262,C83,$D$8:$D$262,D83,$H$8:$H$262,"Serviço"),0)))) -> 21618.957
A84: =IF($H84="UNIDADE CONSTRUTIVA",OFFSET(A84,-1,0)+1,LARGE(A$3:A83,1)) -> 0 | B84: =IF(H84="UNIDADE CONSTRUTIVA",0,IF(H84="CÉLULA CONSTRUTIVA",OFFSET(B84,-1,0)+1,OFFSET(B84,-1,0))) -> 3 | C84: =IF(H84="CÉLULA CONSTRUTIVA",0,IF(H84="ETAPA",OFFSET(C84,-1,0)+1,OFFSET(C84,-1,0))) -> 1 | D84: =IF(H84="ETAPA",0,IF(H84="SUBETAPA",OFFSET(D84,-1,0)+1,OFFSET(D84,-1,0))) -> 4 | E84: =IF(H84="Subetapa",0,IF(H84="serviço",OFFSET(E84,-1,0)+1,OFFSET(E84,-1,0))) -> 0 | H84: SUBETAPA | I84: =IF(H84="Unidade Construtiva",TEXT(A84,"00"),IF(H84="Célula Construtiva",TEXT(B84,"00"),IF(H84="Etapa",CONCATENATE(TEXT(B84,"00"),".",TEXT(C84,"000")),IF(H84="Subetapa",CONCATENATE(TEXT(B84,"00"),".",TEXT(C84,"000"),".",TEXT(D84,"000")),IF(H84="Serviço",CONCATENATE(TEXT(B84,"00"),".",TEXT(C84,"000"),".",TEXT(D84,"000"),".",TEXT(E84,"000")),""))))) -> 03.001.004 | J84: Peitoris | N84: =IF(H84="Serviço",M84*L84,IF(H84="CÉLULA CONSTRUTIVA",SUMIFS($N$8:$N$262,$B$8:$B$262,B84,$H$8:$H$262,"Serviço"),IF(H84="ETAPA",SUMIFS($N$8:$N$262,$B$8:$B$262,B84,$C$8:$C$262,C84,$H$8:$H$262,"Serviço"),IF(H84="SUBETAPA",SUMIFS($N$8:$N$262,$B$8:$B$262,B84,$C$8:$C$262,C84,$D$8:$D$262,D84,$H$8:$H$262,"Serviço"),0)))) -> 346093.5 | O84: =N84/'Obra '!$E$9 -> 49.880953 | Q84: ACABAMENTOS INTERNOS EM PAREDE
A85: =IF($H85="UNIDADE CONSTRUTIVA",OFFSET(A85,-1,0)+1,LARGE(A$3:A84,1)) -> 0 | B85: =IF(H85="UNIDADE CONSTRUTIVA",0,IF(H85="CÉLULA CONSTRUTIVA",OFFSET(B85,-1,0)+1,OFFSET(B85,-1,0))) -> 3 | C85: =IF(H85="CÉLULA CONSTRUTIVA",0,IF(H85="ETAPA",OFFSET(C85,-1,0)+1,OFFSET(C85,-1,0))) -> 1 | D85: =IF(H85="ETAPA",0,IF(H85="SUBETAPA",OFFSET(D85,-1,0)+1,OFFSET(D85,-1,0))) -> 4 | E85: =IF(H85="Subetapa",0,IF(H85="serviço",OFFSET(E85,-1,0)+1,OFFSET(E85,-1,0))) -> 1 | H85: SERVIÇO | I85: =IF(H85="Unidade Construtiva",TEXT(A85,"00"),IF(H85="Célula Construtiva",TEXT(B85,"00"),IF(H85="Etapa",CONCATENATE(TEXT(B85,"00"),".",TEXT(C85,"000")),IF(H85="Subetapa",CONCATENATE(TEXT(B85,"00"),".",TEXT(C85,"000"),".",TEXT(D85,"000")),IF(H85="Serviço",CONCATENATE(TEXT(B85,"00"),".",TEXT(C85,"000"),".",TEXT(D85,"000"),".",TEXT(E85,"000")),""))))) -> 03.001.004.001 | J85: Peitoril em granito preto são gabriel | K85: m2 | L85: =ARQUITETURA!H1740 -> 491.31 | M85: 704.43 | N85: =IF(H85="Serviço",M85*L85,IF(H85="CÉLULA CONSTRUTIVA",SUMIFS($N$8:$N$262,$B$8:$B$262,B85,$H$8:$H$262,"Serviço"),IF(H85="ETAPA",SUMIFS($N$8:$N$262,$B$8:$B$262,B85,$C$8:$C$262,C85,$H$8:$H$262,"Serviço"),IF(H85="SUBETAPA",SUMIFS($N$8:$N$262,$B$8:$B$262,B85,$C$8:$C$262,C85,$D$8:$D$262,D85,$H$8:$H$262,"Serviço"),0)))) -> 346093.5
A86: =IF($H86="UNIDADE CONSTRUTIVA",OFFSET(A86,-1,0)+1,LARGE(A$3:A85,1)) -> 0 | B86: =IF(H86="UNIDADE CONSTRUTIVA",0,IF(H86="CÉLULA CONSTRUTIVA",OFFSET(B86,-1,0)+1,OFFSET(B86,-1,0))) -> 3 | C86: =IF(H86="CÉLULA CONSTRUTIVA",0,IF(H86="ETAPA",OFFSET(C86,-1,0)+1,OFFSET(C86,-1,0))) -> 1 | D86: =IF(H86="ETAPA",0,IF(H86="SUBETAPA",OFFSET(D86,-1,0)+1,OFFSET(D86,-1,0))) -> 5 | E86: =IF(H86="Subetapa",0,IF(H86="serviço",OFFSET(E86,-1,0)+1,OFFSET(E86,-1,0))) -> 0 | H86: SUBETAPA | I86: =IF(H86="Unidade Construtiva",TEXT(A86,"00"),IF(H86="Célula Construtiva",TEXT(B86,"00"),IF(H86="Etapa",CONCATENATE(TEXT(B86,"00"),".",TEXT(C86,"000")),IF(H86="Subetapa",CONCATENATE(TEXT(B86,"00"),".",TEXT(C86,"000"),".",TEXT(D86,"000")),IF(H86="Serviço",CONCATENATE(TEXT(B86,"00"),".",TEXT(C86,"000"),".",TEXT(D86,"000"),".",TEXT(E86,"000")),""))))) -> 03.001.005 | J86: Mão de obra - Revestimentos | N86: =IF(H86="Serviço",M86*L86,IF(H86="CÉLULA CONSTRUTIVA",SUMIFS($N$8:$N$262,$B$8:$B$262,B86,$H$8:$H$262,"Serviço"),IF(H86="ETAPA",SUMIFS($N$8:$N$262,$B$8:$B$262,B86,$C$8:$C$262,C86,$H$8:$H$262,"Serviço"),IF(H86="SUBETAPA",SUMIFS($N$8:$N$262,$B$8:$B$262,B86,$C$8:$C$262,C86,$D$8:$D$262,D86,$H$8:$H$262,"Serviço"),0)))) -> 539164.09 | O86: =N86/'Obra '!$E$9 -> 77.707377
A87: =IF($H87="UNIDADE CONSTRUTIVA",OFFSET(A87,-1,0)+1,LARGE(A$3:A86,1)) -> 0 | B87: =IF(H87="UNIDADE CONSTRUTIVA",0,IF(H87="CÉLULA CONSTRUTIVA",OFFSET(B87,-1,0)+1,OFFSET(B87,-1,0))) -> 3 | C87: =IF(H87="CÉLULA CONSTRUTIVA",0,IF(H87="ETAPA",OFFSET(C87,-1,0)+1,OFFSET(C87,-1,0))) -> 1 | D87: =IF(H87="ETAPA",0,IF(H87="SUBETAPA",OFFSET(D87,-1,0)+1,OFFSET(D87,-1,0))) -> 5 | E87: =IF(H87="Subetapa",0,IF(H87="serviço",OFFSET(E87,-1,0)+1,OFFSET(E87,-1,0))) -> 1 | H87: SERVIÇO | I87: =IF(H87="Unidade Construtiva",TEXT(A87,"00"),IF(H87="Célula Construtiva",TEXT(B87,"00"),IF(H87="Etapa",CONCATENATE(TEXT(B87,"00"),".",TEXT(C87,"000")),IF(H87="Subetapa",CONCATENATE(TEXT(B87,"00"),".",TEXT(C87,"000"),".",TEXT(D87,"000")),IF(H87="Serviço",CONCATENATE(TEXT(B87,"00"),".",TEXT(C87,"000"),".",TEXT(D87,"000"),".",TEXT(E87,"000")),""))))) -> 03.001.005.001 | J87: Mão de obra execução de massa única em paredes interna, incluindo chapisco | K87: m2 | L87: =L73 -> 2077.54 | M87: 36 | N87: =IF(H87="Serviço",M87*L87,IF(H87="CÉLULA CONSTRUTIVA",SUMIFS($N$8:$N$262,$B$8:$B$262,B87,$H$8:$H$262,"Serviço"),IF(H87="ETAPA",SUMIFS($N$8:$N$262,$B$8:$B$262,B87,$C$8:$C$262,C87,$H$8:$H$262,"Serviço"),IF(H87="SUBETAPA",SUMIFS($N$8:$N$262,$B$8:$B$262,B87,$C$8:$C$262,C87,$D$8:$D$262,D87,$H$8:$H$262,"Serviço"),0)))) -> 74791.44 | Q87: REVESTIMENTOS ARGAMASSADOS PAREDE
A88: =IF($H88="UNIDADE CONSTRUTIVA",OFFSET(A88,-1,0)+1,LARGE(A$3:A87,1)) -> 0 | B88: =IF(H88="UNIDADE CONSTRUTIVA",0,IF(H88="CÉLULA CONSTRUTIVA",OFFSET(B88,-1,0)+1,OFFSET(B88,-1,0))) -> 3 | C88: =IF(H88="CÉLULA CONSTRUTIVA",0,IF(H88="ETAPA",OFFSET(C88,-1,0)+1,OFFSET(C88,-1,0))) -> 1 | D88: =IF(H88="ETAPA",0,IF(H88="SUBETAPA",OFFSET(D88,-1,0)+1,OFFSET(D88,-1,0))) -> 5 | E88: =IF(H88="Subetapa",0,IF(H88="serviço",OFFSET(E88,-1,0)+1,OFFSET(E88,-1,0))) -> 2 | H88: SERVIÇO | I88: =IF(H88="Unidade Construtiva",TEXT(A88,"00"),IF(H88="Célula Construtiva",TEXT(B88,"00"),IF(H88="Etapa",CONCATENATE(TEXT(B88,"00"),".",TEXT(C88,"000")),IF(H88="Subetapa",CONCATENATE(TEXT(B88,"00"),".",TEXT(C88,"000"),".",TEXT(D88,"000")),IF(H88="Serviço",CONCATENATE(TEXT(B88,"00"),".",TEXT(C88,"000"),".",TEXT(D88,"000"),".",TEXT(E88,"000")),""))))) -> 03.001.005.002 | J88: Mão de obra para massa de gesso de paredes | K88: m2 | L88: =L78+L79 -> 12478.26 | M88: 15 | N88: =IF(H88="Serviço",M88*L88,IF(H88="CÉLULA CONSTRUTIVA",SUMIFS($N$8:$N$262,$B$8:$B$262,B88,$H$8:$H$262,"Serviço"),IF(H88="ETAPA",SUMIFS($N$8:$N$262,$B$8:$B$262,B88,$C$8:$C$262,C88,$H$8:$H$262,"Serviço"),IF(H88="SUBETAPA",SUMIFS($N$8:$N$262,$B$8:$B$262,B88,$C$8:$C$262,C88,$D$8:$D$262,D88,$H$8:$H$262,"Serviço"),0)))) -> 187173.9 | Q88: REVESTIMENTOS ARGAMASSADOS PAREDE
A89: =IF($H89="UNIDADE CONSTRUTIVA",OFFSET(A89,-1,0)+1,LARGE(A$3:A88,1)) -> 0 | B89: =IF(H89="UNIDADE CONSTRUTIVA",0,IF(H89="CÉLULA CONSTRUTIVA",OFFSET(B89,-1,0)+1,OFFSET(B89,-1,0))) -> 3 | C89: =IF(H89="CÉLULA CONSTRUTIVA",0,IF(H89="ETAPA",OFFSET(C89,-1,0)+1,OFFSET(C89,-1,0))) -> 1 | D89: =IF(H89="ETAPA",0,IF(H89="SUBETAPA",OFFSET(D89,-1,0)+1,OFFSET(D89,-1,0))) -> 5 | E89: =IF(H89="Subetapa",0,IF(H89="serviço",OFFSET(E89,-1,0)+1,OFFSET(E89,-1,0))) -> 3 | H89: SERVIÇO | I89: =IF(H89="Unidade Construtiva",TEXT(A89,"00"),IF(H89="Célula Construtiva",TEXT(B89,"00"),IF(H89="Etapa",CONCATENATE(TEXT(B89,"00"),".",TEXT(C89,"000")),IF(H89="Subetapa",CONCATENATE(TEXT(B89,"00"),".",TEXT(C89,"000"),".",TEXT(D89,"000")),IF(H89="Serviço",CONCATENATE(TEXT(B89,"00"),".",TEXT(C89,"000"),".",TEXT(D89,"000"),".",TEXT(E89,"000")),""))))) -> 03.001.005.003 | J89: Mão de obra estucamento de paredes | K89: m2 | L89: =L77 -> 253.75 | M89: 25 | N89: =IF(H89="Serviço",M89*L89,IF(H89="CÉLULA CONSTRUTIVA",SUMIFS($N$8:$N$262,$B$8:$B$262,B89,$H$8:$H$262,"Serviço"),IF(H89="ETAPA",SUMIFS($N$8:$N$262,$B$8:$B$262,B89,$C$8:$C$262,C89,$H$8:$H$262,"Serviço"),IF(H89="SUBETAPA",SUMIFS($N$8:$N$262,$B$8:$B$262,B89,$C$8:$C$262,C89,$D$8:$D$262,D89,$H$8:$H$262,"Serviço"),0)))) -> 6343.75 | Q89: REVESTIMENTOS ARGAMASSADOS PAREDE
A90: =IF($H90="UNIDADE CONSTRUTIVA",OFFSET(A90,-1,0)+1,LARGE(A$3:A89,1)) -> 0 | B90: =IF(H90="UNIDADE CONSTRUTIVA",0,IF(H90="CÉLULA CONSTRUTIVA",OFFSET(B90,-1,0)+1,OFFSET(B90,-1,0))) -> 3 | C90: =IF(H90="CÉLULA CONSTRUTIVA",0,IF(H90="ETAPA",OFFSET(C90,-1,0)+1,OFFSET(C90,-1,0))) -> 1 | D90: =IF(H90="ETAPA",0,IF(H90="SUBETAPA",OFFSET(D90,-1,0)+1,OFFSET(D90,-1,0))) -> 5 | E90: =IF(H90="Subetapa",0,IF(H90="serviço",OFFSET(E90,-1,0)+1,OFFSET(E90,-1,0))) -> 4 | H90: SERVIÇO | I90: =IF(H90="Unidade Construtiva",TEXT(A90,"00"),IF(H90="Célula Construtiva",TEXT(B90,"00"),IF(H90="Etapa",CONCATENATE(TEXT(B90,"00"),".",TEXT(C90,"000")),IF(H90="Subetapa",CONCATENATE(TEXT(B90,"00"),".",TEXT(C90,"000"),".",TEXT(D90,"000")),IF(H90="Serviço",CONCATENATE(TEXT(B90,"00"),".",TEXT(C90,"000"),".",TEXT(D90,"000"),".",TEXT(E90,"000")),""))))) -> 03.001.005.004 | J90: Mão de obra para assentamento de revestimento cerâmico em parede | K90: m2 | L90: =L81 -> 3263.4 | M90: 75 | N90: =IF(H90="Serviço",M90*L90,IF(H90="CÉLULA CONSTRUTIVA",SUMIFS($N$8:$N$262,$B$8:$B$262,B90,$H$8:$H$262,"Serviço"),IF(H90="ETAPA",SUMIFS($N$8:$N$262,$B$8:$B$262,B90,$C$8:$C$262,C90,$H$8:$H$262,"Serviço"),IF(H90="SUBETAPA",SUMIFS($N$8:$N$262,$B$8:$B$262,B90,$C$8:$C$262,C90,$D$8:$D$262,D90,$H$8:$H$262,"Serviço"),0)))) -> 244755 | O90: =N90/'Obra '!$E$9 -> 35.275475 | Q90: ACABAMENTOS INTERNOS EM PAREDE
A91: =IF($H91="UNIDADE CONSTRUTIVA",OFFSET(A91,-1,0)+1,LARGE(A$3:A90,1)) -> 0 | B91: =IF(H91="UNIDADE CONSTRUTIVA",0,IF(H91="CÉLULA CONSTRUTIVA",OFFSET(B91,-1,0)+1,OFFSET(B91,-1,0))) -> 3 | C91: =IF(H91="CÉLULA CONSTRUTIVA",0,IF(H91="ETAPA",OFFSET(C91,-1,0)+1,OFFSET(C91,-1,0))) -> 1 | D91: =IF(H91="ETAPA",0,IF(H91="SUBETAPA",OFFSET(D91,-1,0)+1,OFFSET(D91,-1,0))) -> 5 | E91: =IF(H91="Subetapa",0,IF(H91="serviço",OFFSET(E91,-1,0)+1,OFFSET(E91,-1,0))) -> 5 | H91: SERVIÇO | I91: =IF(H91="Unidade Construtiva",TEXT(A91,"00"),IF(H91="Célula Construtiva",TEXT(B91,"00"),IF(H91="Etapa",CONCATENATE(TEXT(B91,"00"),".",TEXT(C91,"000")),IF(H91="Subetapa",CONCATENATE(TEXT(B91,"00"),".",TEXT(C91,"000"),".",TEXT(D91,"000")),IF(H91="Serviço",CONCATENATE(TEXT(B91,"00"),".",TEXT(C91,"000"),".",TEXT(D91,"000"),".",TEXT(E91,"000")),""))))) -> 03.001.005.005 | J91: Mão de obra para assentamento de requadros em portas de elevador | K91: m2 | L91: =L83 -> 30.69 | M91: 50 | N91: =IF(H91="Serviço",M91*L91,IF(H91="CÉLULA CONSTRUTIVA",SUMIFS($N$8:$N$262,$B$8:$B$262,B91,$H$8:$H$262,"Serviço"),IF(H91="ETAPA",SUMIFS($N$8:$N$262,$B$8:$B$262,B91,$C$8:$C$262,C91,$H$8:$H$262,"Serviço"),IF(H91="SUBETAPA",SUMIFS($N$8:$N$262,$B$8:$B$262,B91,$C$8:$C$262,C91,$D$8:$D$262,D91,$H$8:$H$262,"Serviço"),0)))) -> 1534.5 | O91: =N91/'Obra '!$E$9 -> 0.22116082 | Q91: ACABAMENTOS INTERNOS EM PAREDE
A92: =IF($H92="UNIDADE CONSTRUTIVA",OFFSET(A92,-1,0)+1,LARGE(A$3:A91,1)) -> 0 | B92: =IF(H92="UNIDADE CONSTRUTIVA",0,IF(H92="CÉLULA CONSTRUTIVA",OFFSET(B92,-1,0)+1,OFFSET(B92,-1,0))) -> 3 | C92: =IF(H92="CÉLULA CONSTRUTIVA",0,IF(H92="ETAPA",OFFSET(C92,-1,0)+1,OFFSET(C92,-1,0))) -> 1 | D92: =IF(H92="ETAPA",0,IF(H92="SUBETAPA",OFFSET(D92,-1,0)+1,OFFSET(D92,-1,0))) -> 5 | E92: =IF(H92="Subetapa",0,IF(H92="serviço",OFFSET(E92,-1,0)+1,OFFSET(E92,-1,0))) -> 6 | H92: SERVIÇO | I92: =IF(H92="Unidade Construtiva",TEXT(A92,"00"),IF(H92="Célula Construtiva",TEXT(B92,"00"),IF(H92="Etapa",CONCATENATE(TEXT(B92,"00"),".",TEXT(C92,"000")),IF(H92="Subetapa",CONCATENATE(TEXT(B92,"00"),".",TEXT(C92,"000"),".",TEXT(D92,"000")),IF(H92="Serviço",CONCATENATE(TEXT(B92,"00"),".",TEXT(C92,"000"),".",TEXT(D92,"000"),".",TEXT(E92,"000")),""))))) -> 03.001.005.006 | J92: Mão de obra para colocação de peitoril e pingadeira | K92: m2 | L92: =L85 -> 491.31 | M92: 50 | N92: =IF(H92="Serviço",M92*L92,IF(H92="CÉLULA CONSTRUTIVA",SUMIFS($N$8:$N$262,$B$8:$B$262,B92,$H$8:$H$262,"Serviço"),IF(H92="ETAPA",SUMIFS($N$8:$N$262,$B$8:$B$262,B92,$C$8:$C$262,C92,$H$8:$H$262,"Serviço"),IF(H92="SUBETAPA",SUMIFS($N$8:$N$262,$B$8:$B$262,B92,$C$8:$C$262,C92,$D$8:$D$262,D92,$H$8:$H$262,"Serviço"),0)))) -> 24565.5 | O92: =N92/'Obra '!$E$9 -> 3.5405188 | Q92: ACABAMENTOS INTERNOS EM PAREDE
A93: =IF($H93="UNIDADE CONSTRUTIVA",OFFSET(A93,-1,0)+1,LARGE(A$3:A92,1)) -> 0 | B93: =IF(H93="UNIDADE CONSTRUTIVA",0,IF(H93="CÉLULA CONSTRUTIVA",OFFSET(B93,-1,0)+1,OFFSET(B93,-1,0))) -> 4 | C93: =IF(H93="CÉLULA CONSTRUTIVA",0,IF(H93="ETAPA",OFFSET(C93,-1,0)+1,OFFSET(C93,-1,0))) -> 0 | D93: =IF(H93="ETAPA",0,IF(H93="SUBETAPA",OFFSET(D93,-1,0)+1,OFFSET(D93,-1,0))) -> 5 | E93: =IF(H93="Subetapa",0,IF(H93="serviço",OFFSET(E93,-1,0)+1,OFFSET(E93,-1,0))) -> 6 | H93: CÉLULA CONSTRUTIVA | I93: =IF(H93="Unidade Construtiva",TEXT(A93,"00"),IF(H93="Célula Construtiva",TEXT(B93,"00"),IF(H93="Etapa",CONCATENATE(TEXT(B93,"00"),".",TEXT(C93,"000")),IF(H93="Subetapa",CONCATENATE(TEXT(B93,"00"),".",TEXT(C93,"000"),".",TEXT(D93,"000")),IF(H93="Serviço",CONCATENATE(TEXT(B93,"00"),".",TEXT(C93,"000"),".",TEXT(D93,"000"),".",TEXT(E93,"000")),""))))) -> 04 | J93: REVESTIMENTOS E ACABAMENTOS INTERNOS EM TETO | N93: =IF(H93="Serviço",M93*L93,IF(H93="CÉLULA CONSTRUTIVA",SUMIFS($N$8:$N$262,$B$8:$B$262,B93,$H$8:$H$262,"Serviço"),IF(H93="ETAPA",SUMIFS($N$8:$N$262,$B$8:$B$262,B93,$C$8:$C$262,C93,$H$8:$H$262,"Serviço"),IF(H93="SUBETAPA",SUMIFS($N$8:$N$262,$B$8:$B$262,B93,$C$8:$C$262,C93,$D$8:$D$262,D93,$H$8:$H$262,"Serviço"),0)))) -> 695689.43 | O93: =N93/'Obra '!$E$9 -> 100.26669
A94: =IF($H94="UNIDADE CONSTRUTIVA",OFFSET(A94,-1,0)+1,LARGE(A$3:A93,1)) -> 0 | B94: =IF(H94="UNIDADE CONSTRUTIVA",0,IF(H94="CÉLULA CONSTRUTIVA",OFFSET(B94,-1,0)+1,OFFSET(B94,-1,0))) -> 4 | C94: =IF(H94="CÉLULA CONSTRUTIVA",0,IF(H94="ETAPA",OFFSET(C94,-1,0)+1,OFFSET(C94,-1,0))) -> 1 | D94: =IF(H94="ETAPA",0,IF(H94="SUBETAPA",OFFSET(D94,-1,0)+1,OFFSET(D94,-1,0))) -> 0 | E94: =IF(H94="Subetapa",0,IF(H94="serviço",OFFSET(E94,-1,0)+1,OFFSET(E94,-1,0))) -> 6 | H94: ETAPA | I94: =IF(H94="Unidade Construtiva",TEXT(A94,"00"),IF(H94="Célula Construtiva",TEXT(B94,"00"),IF(H94="Etapa",CONCATENATE(TEXT(B94,"00"),".",TEXT(C94,"000")),IF(H94="Subetapa",CONCATENATE(TEXT(B94,"00"),".",TEXT(C94,"000"),".",TEXT(D94,"000")),IF(H94="Serviço",CONCATENATE(TEXT(B94,"00"),".",TEXT(C94,"000"),".",TEXT(D94,"000"),".",TEXT(E94,"000")),""))))) -> 04.001 | J94: REVESTIMENTOS E ACABAMENTOS INTERNOS EM TETO | N94: =IF(H94="Serviço",M94*L94,IF(H94="CÉLULA CONSTRUTIVA",SUMIFS($N$8:$N$262,$B$8:$B$262,B94,$H$8:$H$262,"Serviço"),IF(H94="ETAPA",SUMIFS($N$8:$N$262,$B$8:$B$262,B94,$C$8:$C$262,C94,$H$8:$H$262,"Serviço"),IF(H94="SUBETAPA",SUMIFS($N$8:$N$262,$B$8:$B$262,B94,$C$8:$C$262,C94,$D$8:$D$262,D94,$H$8:$H$262,"Serviço"),0)))) -> 695689.43
A95: =IF($H95="UNIDADE CONSTRUTIVA",OFFSET(A95,-1,0)+1,LARGE(A$3:A94,1)) -> 0 | B95: =IF(H95="UNIDADE CONSTRUTIVA",0,IF(H95="CÉLULA CONSTRUTIVA",OFFSET(B95,-1,0)+1,OFFSET(B95,-1,0))) -> 4 | C95: =IF(H95="CÉLULA CONSTRUTIVA",0,IF(H95="ETAPA",OFFSET(C95,-1,0)+1,OFFSET(C95,-1,0))) -> 1 | D95: =IF(H95="ETAPA",0,IF(H95="SUBETAPA",OFFSET(D95,-1,0)+1,OFFSET(D95,-1,0))) -> 1 | E95: =IF(H95="Subetapa",0,IF(H95="serviço",OFFSET(E95,-1,0)+1,OFFSET(E95,-1,0))) -> 0 | H95: SUBETAPA | I95: =IF(H95="Unidade Construtiva",TEXT(A95,"00"),IF(H95="Célula Construtiva",TEXT(B95,"00"),IF(H95="Etapa",CONCATENATE(TEXT(B95,"00"),".",TEXT(C95,"000")),IF(H95="Subetapa",CONCATENATE(TEXT(B95,"00"),".",TEXT(C95,"000"),".",TEXT(D95,"000")),IF(H95="Serviço",CONCATENATE(TEXT(B95,"00"),".",TEXT(C95,"000"),".",TEXT(D95,"000"),".",TEXT(E95,"000")),""))))) -> 04.001.001 | J95: Revestimento interno argamassado em teto | K95: =SUM(L96:L99) -> 5747.02 | L95: =L96/K95 -> 0.065625315 | N95: =IF(H95="Serviço",M95*L95,IF(H95="CÉLULA CONSTRUTIVA",SUMIFS($N$8:$N$262,$B$8:$B$262,B95,$H$8:$H$262,"Serviço"),IF(H95="ETAPA",SUMIFS($N$8:$N$262,$B$8:$B$262,B95,$C$8:$C$262,C95,$H$8:$H$262,"Serviço"),IF(H95="SUBETAPA",SUMIFS($N$8:$N$262,$B$8:$B$262,B95,$C$8:$C$262,C95,$D$8:$D$262,D95,$H$8:$H$262,"Serviço"),0)))) -> 1924.565 | Q95: REVESTIMENTOS ARGAMASSADOS TETO
A96: =IF($H96="UNIDADE CONSTRUTIVA",OFFSET(A96,-1,0)+1,LARGE(A$3:A95,1)) -> 0 | B96: =IF(H96="UNIDADE CONSTRUTIVA",0,IF(H96="CÉLULA CONSTRUTIVA",OFFSET(B96,-1,0)+1,OFFSET(B96,-1,0))) -> 4 | C96: =IF(H96="CÉLULA CONSTRUTIVA",0,IF(H96="ETAPA",OFFSET(C96,-1,0)+1,OFFSET(C96,-1,0))) -> 1 | D96: =IF(H96="ETAPA",0,IF(H96="SUBETAPA",OFFSET(D96,-1,0)+1,OFFSET(D96,-1,0))) -> 1 | E96: =IF(H96="Subetapa",0,IF(H96="serviço",OFFSET(E96,-1,0)+1,OFFSET(E96,-1,0))) -> 1 | H96: SERVIÇO | I96: =IF(H96="Unidade Construtiva",TEXT(A96,"00"),IF(H96="Célula Construtiva",TEXT(B96,"00"),IF(H96="Etapa",CONCATENATE(TEXT(B96,"00"),".",TEXT(C96,"000")),IF(H96="Subetapa",CONCATENATE(TEXT(B96,"00"),".",TEXT(C96,"000"),".",TEXT(D96,"000")),IF(H96="Serviço",CONCATENATE(TEXT(B96,"00"),".",TEXT(C96,"000"),".",TEXT(D96,"000"),".",TEXT(E96,"000")),""))))) -> 04.001.001.001 | J96: Estucamento de teto | K96: m2 | L96: =SUM(ARQUITETURA!H1346:H1346,ARQUITETURA!H1353) -> 377.15 | M96: 5.1029167 | N96: =IF(H96="Serviço",M96*L96,IF(H96="CÉLULA CONSTRUTIVA",SUMIFS($N$8:$N$262,$B$8:$B$262,B96,$H$8:$H$262,"Serviço"),IF(H96="ETAPA",SUMIFS($N$8:$N$262,$B$8:$B$262,B96,$C$8:$C$262,C96,$H$8:$H$262,"Serviço"),IF(H96="SUBETAPA",SUMIFS($N$8:$N$262,$B$8:$B$262,B96,$C$8:$C$262,C96,$D$8:$D$262,D96,$H$8:$H$262,"Serviço"),0)))) -> 1924.565
A97: =IF($H97="UNIDADE CONSTRUTIVA",OFFSET(A97,-1,0)+1,LARGE(A$3:A96,1)) -> 0 | B97: =IF(H97="UNIDADE CONSTRUTIVA",0,IF(H97="CÉLULA CONSTRUTIVA",OFFSET(B97,-1,0)+1,OFFSET(B97,-1,0))) -> 4 | C97: =IF(H97="CÉLULA CONSTRUTIVA",0,IF(H97="ETAPA",OFFSET(C97,-1,0)+1,OFFSET(C97,-1,0))) -> 1 | D97: =IF(H97="ETAPA",0,IF(H97="SUBETAPA",OFFSET(D97,-1,0)+1,OFFSET(D97,-1,0))) -> 2 | E97: =IF(H97="Subetapa",0,IF(H97="serviço",OFFSET(E97,-1,0)+1,OFFSET(E97,-1,0))) -> 0 | H97: SUBETAPA | I97: =IF(H97="Unidade Construtiva",TEXT(A97,"00"),IF(H97="Célula Construtiva",TEXT(B97,"00"),IF(H97="Etapa",CONCATENATE(TEXT(B97,"00"),".",TEXT(C97,"000")),IF(H97="Subetapa",CONCATENATE(TEXT(B97,"00"),".",TEXT(C97,"000"),".",TEXT(D97,"000")),IF(H97="Serviço",CONCATENATE(TEXT(B97,"00"),".",TEXT(C97,"000"),".",TEXT(D97,"000"),".",TEXT(E97,"000")),""))))) -> 04.001.002 | J97: Acabamento de gesso em teto | N97: =IF(H97="Serviço",M97*L97,IF(H97="CÉLULA CONSTRUTIVA",SUMIFS($N$8:$N$262,$B$8:$B$262,B97,$H$8:$H$262,"Serviço"),IF(H97="ETAPA",SUMIFS($N$8:$N$262,$B$8:$B$262,B97,$C$8:$C$262,C97,$H$8:$H$262,"Serviço"),IF(H97="SUBETAPA",SUMIFS($N$8:$N$262,$B$8:$B$262,B97,$C$8:$C$262,C97,$D$8:$D$262,D97,$H$8:$H$262,"Serviço"),0)))) -> 684336.12 | Q97: ACABAMENTOS INTERNOS EM TETO
A98: =IF($H98="UNIDADE CONSTRUTIVA",OFFSET(A98,-1,0)+1,LARGE(A$3:A97,1)) -> 0 | B98: =IF(H98="UNIDADE CONSTRUTIVA",0,IF(H98="CÉLULA CONSTRUTIVA",OFFSET(B98,-1,0)+1,OFFSET(B98,-1,0))) -> 4 | C98: =IF(H98="CÉLULA CONSTRUTIVA",0,IF(H98="ETAPA",OFFSET(C98,-1,0)+1,OFFSET(C98,-1,0))) -> 1 | D98: =IF(H98="ETAPA",0,IF(H98="SUBETAPA",OFFSET(D98,-1,0)+1,OFFSET(D98,-1,0))) -> 2 | E98: =IF(H98="Subetapa",0,IF(H98="serviço",OFFSET(E98,-1,0)+1,OFFSET(E98,-1,0))) -> 1 | H98: SERVIÇO | I98: =IF(H98="Unidade Construtiva",TEXT(A98,"00"),IF(H98="Célula Construtiva",TEXT(B98,"00"),IF(H98="Etapa",CONCATENATE(TEXT(B98,"00"),".",TEXT(C98,"000")),IF(H98="Subetapa",CONCATENATE(TEXT(B98,"00"),".",TEXT(C98,"000"),".",TEXT(D98,"000")),IF(H98="Serviço",CONCATENATE(TEXT(B98,"00"),".",TEXT(C98,"000"),".",TEXT(D98,"000"),".",TEXT(E98,"000")),""))))) -> 04.001.002.001 | J98: Gesso corrido em tetos - Material e Mão de Obra | K98: m2 | L98: =ARQUITETURA!H1354 -> 92.4 | M98: 60 | N98: =IF(H98="Serviço",M98*L98,IF(H98="CÉLULA CONSTRUTIVA",SUMIFS($N$8:$N$262,$B$8:$B$262,B98,$H$8:$H$262,"Serviço"),IF(H98="ETAPA",SUMIFS($N$8:$N$262,$B$8:$B$262,B98,$C$8:$C$262,C98,$H$8:$H$262,"Serviço"),IF(H98="SUBETAPA",SUMIFS($N$8:$N$262,$B$8:$B$262,B98,$C$8:$C$262,C98,$D$8:$D$262,D98,$H$8:$H$262,"Serviço"),0)))) -> 5544 | O98: Forro de gesso liso
A99: =IF($H99="UNIDADE CONSTRUTIVA",OFFSET(A99,-1,0)+1,LARGE(A$3:A98,1)) -> 0 | B99: =IF(H99="UNIDADE CONSTRUTIVA",0,IF(H99="CÉLULA CONSTRUTIVA",OFFSET(B99,-1,0)+1,OFFSET(B99,-1,0))) -> 4 | C99: =IF(H99="CÉLULA CONSTRUTIVA",0,IF(H99="ETAPA",OFFSET(C99,-1,0)+1,OFFSET(C99,-1,0))) -> 1 | D99: =IF(H99="ETAPA",0,IF(H99="SUBETAPA",OFFSET(D99,-1,0)+1,OFFSET(D99,-1,0))) -> 2 | E99: =IF(H99="Subetapa",0,IF(H99="serviço",OFFSET(E99,-1,0)+1,OFFSET(E99,-1,0))) -> 2 | H99: SERVIÇO | I99: =IF(H99="Unidade Construtiva",TEXT(A99,"00"),IF(H99="Célula Construtiva",TEXT(B99,"00"),IF(H99="Etapa",CONCATENATE(TEXT(B99,"00"),".",TEXT(C99,"000")),IF(H99="Subetapa",CONCATENATE(TEXT(B99,"00"),".",TEXT(C99,"000"),".",TEXT(D99,"000")),IF(H99="Serviço",CONCATENATE(TEXT(B99,"00"),".",TEXT(C99,"000"),".",TEXT(D99,"000"),".",TEXT(E99,"000")),""))))) -> 04.001.002.002 | J99: Forro Com Sistema Em Chapas De Gesso Para Drywall, Uso Interno, Montante 48mm, Com Uma Face Resistente a Umidade (RU/48) | K99: m2 | L99: =ARQUITETURA!H1355 -> 5277.47 | M99: 128.62074 | N99: =IF(H99="Serviço",M99*L99,IF(H99="CÉLULA CONSTRUTIVA",SUMIFS($N$8:$N$262,$B$8:$B$262,B99,$H$8:$H$262,"Serviço"),IF(H99="ETAPA",SUMIFS($N$8:$N$262,$B$8:$B$262,B99,$C$8:$C$262,C99,$H$8:$H$262,"Serviço"),IF(H99="SUBETAPA",SUMIFS($N$8:$N$262,$B$8:$B$262,B99,$C$8:$C$262,C99,$D$8:$D$262,D99,$H$8:$H$262,"Serviço"),0)))) -> 678792.12 | O99: Forro demais áreas, dito como placas de drywall ru, sem determinação do montante, adotamos o de 48 e negativo
A100: =IF($H100="UNIDADE CONSTRUTIVA",OFFSET(A100,-1,0)+1,LARGE(A$3:A99,1)) -> 0 | B100: =IF(H100="UNIDADE CONSTRUTIVA",0,IF(H100="CÉLULA CONSTRUTIVA",OFFSET(B100,-1,0)+1,OFFSET(B100,-1,0))) -> 4 | C100: =IF(H100="CÉLULA CONSTRUTIVA",0,IF(H100="ETAPA",OFFSET(C100,-1,0)+1,OFFSET(C100,-1,0))) -> 1 | D100: =IF(H100="ETAPA",0,IF(H100="SUBETAPA",OFFSET(D100,-1,0)+1,OFFSET(D100,-1,0))) -> 2 | E100: =IF(H100="Subetapa",0,IF(H100="serviço",OFFSET(E100,-1,0)+1,OFFSET(E100,-1,0))) -> 3 | H100: SERVIÇO | I100: =IF(H100="Unidade Construtiva",TEXT(A100,"00"),IF(H100="Célula Construtiva",TEXT(B100,"00"),IF(H100="Etapa",CONCATENATE(TEXT(B100,"00"),".",TEXT(C100,"000")),IF(H100="Subetapa",CONCATENATE(TEXT(B100,"00"),".",TEXT(C100,"000"),".",TEXT(D100,"000")),IF(H100="Serviço",CONCATENATE(TEXT(B100,"00"),".",TEXT(C100,"000"),".",TEXT(D100,"000"),".",TEXT(E100,"000")),""))))) -> 04.001.002.003 | J100: Negativo de forro de gesso acartonado - área umida | K100: m | L100: =ARQUITETURA!H1417 -> 8226.33 | N100: =IF(H100="Serviço",M100*L100,IF(H100="CÉLULA CONSTRUTIVA",SUMIFS($N$8:$N$262,$B$8:$B$262,B100,$H$8:$H$262,"Serviço"),IF(H100="ETAPA",SUMIFS($N$8:$N$262,$B$8:$B$262,B100,$C$8:$C$262,C100,$H$8:$H$262,"Serviço"),IF(H100="SUBETAPA",SUMIFS($N$8:$N$262,$B$8:$B$262,B100,$C$8:$C$262,C100,$D$8:$D$262,D100,$H$8:$H$262,"Serviço"),0)))) -> 0 | O100: Custo embutido no custo por m2
A101: =IF($H101="UNIDADE CONSTRUTIVA",OFFSET(A101,-1,0)+1,LARGE(A$3:A100,1)) -> 0 | B101: =IF(H101="UNIDADE CONSTRUTIVA",0,IF(H101="CÉLULA CONSTRUTIVA",OFFSET(B101,-1,0)+1,OFFSET(B101,-1,0))) -> 4 | C101: =IF(H101="CÉLULA CONSTRUTIVA",0,IF(H101="ETAPA",OFFSET(C101,-1,0)+1,OFFSET(C101,-1,0))) -> 1 | D101: =IF(H101="ETAPA",0,IF(H101="SUBETAPA",OFFSET(D101,-1,0)+1,OFFSET(D101,-1,0))) -> 2 | E101: =IF(H101="Subetapa",0,IF(H101="serviço",OFFSET(E101,-1,0)+1,OFFSET(E101,-1,0))) -> 4 | H101: SERVIÇO | I101: =IF(H101="Unidade Construtiva",TEXT(A101,"00"),IF(H101="Célula Construtiva",TEXT(B101,"00"),IF(H101="Etapa",CONCATENATE(TEXT(B101,"00"),".",TEXT(C101,"000")),IF(H101="Subetapa",CONCATENATE(TEXT(B101,"00"),".",TEXT(C101,"000"),".",TEXT(D101,"000")),IF(H101="Serviço",CONCATENATE(TEXT(B101,"00"),".",TEXT(C101,"000"),".",TEXT(D101,"000"),".",TEXT(E101,"000")),""))))) -> 04.001.002.004 | J101: Negativo de forro de gesso corrido | K101: m | L101: =ARQUITETURA!H1418 -> 83.34 | N101: =IF(H101="Serviço",M101*L101,IF(H101="CÉLULA CONSTRUTIVA",SUMIFS($N$8:$N$262,$B$8:$B$262,B101,$H$8:$H$262,"Serviço"),IF(H101="ETAPA",SUMIFS($N$8:$N$262,$B$8:$B$262,B101,$C$8:$C$262,C101,$H$8:$H$262,"Serviço"),IF(H101="SUBETAPA",SUMIFS($N$8:$N$262,$B$8:$B$262,B101,$C$8:$C$262,C101,$D$8:$D$262,D101,$H$8:$H$262,"Serviço"),0)))) -> 0 | O101: Custo embutido no custo por m2
A102: =IF($H102="UNIDADE CONSTRUTIVA",OFFSET(A102,-1,0)+1,LARGE(A$3:A101,1)) -> 0 | B102: =IF(H102="UNIDADE CONSTRUTIVA",0,IF(H102="CÉLULA CONSTRUTIVA",OFFSET(B102,-1,0)+1,OFFSET(B102,-1,0))) -> 4 | C102: =IF(H102="CÉLULA CONSTRUTIVA",0,IF(H102="ETAPA",OFFSET(C102,-1,0)+1,OFFSET(C102,-1,0))) -> 1 | D102: =IF(H102="ETAPA",0,IF(H102="SUBETAPA",OFFSET(D102,-1,0)+1,OFFSET(D102,-1,0))) -> 3 | E102: =IF(H102="Subetapa",0,IF(H102="serviço",OFFSET(E102,-1,0)+1,OFFSET(E102,-1,0))) -> 0 | H102: SUBETAPA | I102: =IF(H102="Unidade Construtiva",TEXT(A102,"00"),IF(H102="Célula Construtiva",TEXT(B102,"00"),IF(H102="Etapa",CONCATENATE(TEXT(B102,"00"),".",TEXT(C102,"000")),IF(H102="Subetapa",CONCATENATE(TEXT(B102,"00"),".",TEXT(C102,"000"),".",TEXT(D102,"000")),IF(H102="Serviço",CONCATENATE(TEXT(B102,"00"),".",TEXT(C102,"000"),".",TEXT(D102,"000"),".",TEXT(E102,"000")),""))))) -> 04.001.003 | J102: Mão de obra | N102: =IF(H102="Serviço",M102*L102,IF(H102="CÉLULA CONSTRUTIVA",SUMIFS($N$8:$N$262,$B$8:$B$262,B102,$H$8:$H$262,"Serviço"),IF(H102="ETAPA",SUMIFS($N$8:$N$262,$B$8:$B$262,B102,$C$8:$C$262,C102,$H$8:$H$262,"Serviço"),IF(H102="SUBETAPA",SUMIFS($N$8:$N$262,$B$8:$B$262,B102,$C$8:$C$262,C102,$D$8:$D$262,D102,$H$8:$H$262,"Serviço"),0)))) -> 9428.75 | Q102: REVESTIMENTOS ARGAMASSADOS TETO
A103: =IF($H103="UNIDADE CONSTRUTIVA",OFFSET(A103,-1,0)+1,LARGE(A$3:A102,1)) -> 0 | B103: =IF(H103="UNIDADE CONSTRUTIVA",0,IF(H103="CÉLULA CONSTRUTIVA",OFFSET(B103,-1,0)+1,OFFSET(B103,-1,0))) -> 4 | C103: =IF(H103="CÉLULA CONSTRUTIVA",0,IF(H103="ETAPA",OFFSET(C103,-1,0)+1,OFFSET(C103,-1,0))) -> 1 | D103: =IF(H103="ETAPA",0,IF(H103="SUBETAPA",OFFSET(D103,-1,0)+1,OFFSET(D103,-1,0))) -> 3 | E103: =IF(H103="Subetapa",0,IF(H103="serviço",OFFSET(E103,-1,0)+1,OFFSET(E103,-1,0))) -> 1 | H103: SERVIÇO | I103: =IF(H103="Unidade Construtiva",TEXT(A103,"00"),IF(H103="Célula Construtiva",TEXT(B103,"00"),IF(H103="Etapa",CONCATENATE(TEXT(B103,"00"),".",TEXT(C103,"000")),IF(H103="Subetapa",CONCATENATE(TEXT(B103,"00"),".",TEXT(C103,"000"),".",TEXT(D103,"000")),IF(H103="Serviço",CONCATENATE(TEXT(B103,"00"),".",TEXT(C103,"000"),".",TEXT(D103,"000"),".",TEXT(E103,"000")),""))))) -> 04.001.003.001 | J103: Mão de obra execução de estucamento em teto | K103: m2 | L103: =L96 -> 377.15 | M103: 25 | N103: =IF(H103="Serviço",M103*L103,IF(H103="CÉLULA CONSTRUTIVA",SUMIFS($N$8:$N$262,$B$8:$B$262,B103,$H$8:$H$262,"Serviço"),IF(H103="ETAPA",SUMIFS($N$8:$N$262,$B$8:$B$262,B103,$C$8:$C$262,C103,$H$8:$H$262,"Serviço"),IF(H103="SUBETAPA",SUMIFS($N$8:$N$262,$B$8:$B$262,B103,$C$8:$C$262,C103,$D$8:$D$262,D103,$H$8:$H$262,"Serviço"),0)))) -> 9428.75
...

Sheet ARQUITETURA
A1: EMBASSAMENTO | B1: DADOS
A2: TORRE | B2: Titulo | C2: QUANTITATIVO
A3: ignorar | B3: Obra
B4: Cliente
B5: Cidade
B6: Endereço
B7: Descrição
B9: QUANTITATIVOS
B10: Item | C10: Descrição | D10: Unid. | E10: Quantidade | F10: OBSERVAÇÕES
B12: 1. | C12: Alvenaria de vedação com bocos de concreto | E12: =SUM(E14:E97) -> 4379.7 | H12: =SUM(H13:H18) -> 4379.7 | I12: =IF(H12=E12,"OKAY","REVER") -> OKAY | L12: =SUM(L13:L14) -> 0
A13: EMBASSAMENTO | B13: 1.1. | C13: 01_1º SUBSOLO 1 | G13: BLOCO DE CONCRETO 09 cm, | H13: =SUMIF($C:$C,G13,$E:$E) -> 208.45
A14: EMBASSAMENTO | B14: 1.1.1 | C14: BLOCO DE CONCRETO 14 cm, | D14: m² | E14: 130.61 | G14: BLOCO DE CONCRETO 14 cm, | H14: =SUMIF($C:$C,G14,$E:$E) -> 1643
A15: EMBASSAMENTO | B15: 1.1.2 | C15: BLOCO DE CONCRETO 19 cm, | D15: m² | E15: 143.39 | G15: BLOCO DE CONCRETO 19 cm, | H15: =SUMIF($C:$C,G15,$E:$E) -> 2528.25
A16: EMBASSAMENTO | B16: 1.2. | C16: 02_TÉRREO | H16: =SUMIF($C:$C,G16,$E:$E) -> 0
A17: EMBASSAMENTO | B17: 1.2.1 | C17: BLOCO DE CONCRETO 09 cm, | D17: m² | E17: 1.71 | H17: =SUMIF($C:$C,G17,$E:$E) -> 0
A18: EMBASSAMENTO | B18: 1.2.2 | C18: BLOCO DE CONCRETO 14 cm, | D18: m² | E18: 197.94 | H18: =SUMIF($C:$C,G18,$E:$E) -> 0
A19: EMBASSAMENTO | B19: 1.2.3 | C19: BLOCO DE CONCRETO 19 cm, | D19: m² | E19: 316.99 | J19: =SUM(J13:J18) -> 0
A20: TORRE | B20: 1.3. | C20: 03_1º PAVTO | G20: conferencia | H20: =H22+H30 -> 4379.7 | I20: =IF(H20=H12,"OKAY","REVER") -> OKAY
A21: TORRE | B21: 1.3.1 | C21: BLOCO DE CONCRETO 09 cm, | D21: m² | E21: 17.06
A22: TORRE | B22: 1.3.2 | C22: BLOCO DE CONCRETO 14 cm, | D22: m² | E22: 110.58 | G22: =$A$1 -> EMBASSAMENTO | H22: =SUM(H23:H28) -> 790.64
A23: TORRE | B23: 1.3.3 | C23: BLOCO DE CONCRETO 19 cm, | D23: m² | E23: 226.9 | G23: BLOCO DE CONCRETO 09 cm, | H23: =SUMIFS($E:$E,$C:$C,G23,$A:$A,$G$22) -> 1.71
A24: TORRE | B24: 1.4. | C24: 04_2º PAVTO | G24: BLOCO DE CONCRETO 14 cm, | H24: =SUMIFS($E:$E,$C:$C,G24,$A:$A,$G$22) -> 328.55
A25: TORRE | B25: 1.4.1 | C25: BLOCO DE CONCRETO 09 cm, | D25: m² | E25: 22.95 | G25: BLOCO DE CONCRETO 19 cm, | H25: =SUMIFS($E:$E,$C:$C,G25,$A:$A,$G$22) -> 460.38
A26: TORRE | B26: 1.4.2 | C26: BLOCO DE CONCRETO 14 cm, | D26: m² | E26: 106.04 | H26: =SUMIFS($E:$E,$C:$C,G26,$A:$A,$G$22) -> 0
A27: TORRE | B27: 1.4.3 | C27: BLOCO DE CONCRETO 19 cm, | D27: m² | E27: 159.89 | H27: =SUMIFS($E:$E,$C:$C,G27,$A:$A,$G$22) -> 0
A28: TORRE | B28: 1.5. | C28: 05_3º PAVTO | H28: =SUMIFS($E:$E,$C:$C,G28,$A:$A,$G$22) -> 0
A29: TORRE | B29: 1.5.1 | C29: BLOCO DE CONCRETO 09 cm, | D29: m² | E29: 13.49
A30: TORRE | B30: 1.5.2 | C30: BLOCO DE CONCRETO 14 cm, | D30: m² | E30: 79.5 | G30: =$A$2 -> TORRE | H30: =SUM(H31:H36) -> 3589.06
A31: TORRE | B31: 1.5.3 | C31: BLOCO DE CONCRETO 19 cm, | D31: m² | E31: 144.83 | G31: BLOCO DE CONCRETO 09 cm, | H31: =SUMIFS($E:$E,$C:$C,G31,$A:$A,$G$30) -> 206.74
A32: TORRE | B32: 1.6. | C32: 06_4º PAVTO | G32: BLOCO DE CONCRETO 14 cm, | H32: =SUMIFS($E:$E,$C:$C,G32,$A:$A,$G$30) -> 1314.45
A33: TORRE | B33: 1.6.1 | C33: BLOCO DE CONCRETO 09 cm, | D33: m² | E33: 5.4 | G33: BLOCO DE CONCRETO 19 cm, | H33: =SUMIFS($E:$E,$C:$C,G33,$A:$A,$G$30) -> 2067.87
A34: TORRE | B34: 1.6.2 | C34: BLOCO DE CONCRETO 14 cm, | D34: m² | E34: 84.52 | H34: =SUMIFS($E:$E,$C:$C,G34,$A:$A,$G$30) -> 0
A35: TORRE | B35: 1.6.3 | C35: BLOCO DE CONCRETO 19 cm, | D35: m² | E35: 88.67 | H35: =SUMIFS($E:$E,$C:$C,G35,$A:$A,$G$30) -> 0
A36: TORRE | B36: 1.7. | C36: 07_5º PAVTO | H36: =SUMIFS($E:$E,$C:$C,G36,$A:$A,$G$30) -> 0
A37: TORRE | B37: 1.7.1 | C37: BLOCO DE CONCRETO 09 cm, | D37: m² | E37: 12.06
A38: TORRE | B38: 1.7.2 | C38: BLOCO DE CONCRETO 14 cm, | D38: m² | E38: 80.25
A39: TORRE | B39: 1.7.3 | C39: BLOCO DE CONCRETO 19 cm, | D39: m² | E39: 91.11
A40: TORRE | B40: 1.8. | C40: 08_6º PAVTO
A41: TORRE | B41: 1.8.1 | C41: BLOCO DE CONCRETO 09 cm, | D41: m² | E41: 5.4
A42: TORRE | B42: 1.8.2 | C42: BLOCO DE CONCRETO 14 cm, | D42: m² | E42: 84.52
A43: TORRE | B43: 1.8.3 | C43: BLOCO DE CONCRETO 19 cm, | D43: m² | E43: 88.67
A44: TORRE | B44: 1.9. | C44: 09_7º PAVTO
A45: TORRE | B45: 1.9.1 | C45: BLOCO DE CONCRETO 09 cm, | D45: m² | E45: 12.06
A46: TORRE | B46: 1.9.2 | C46: BLOCO DE CONCRETO 14 cm, | D46: m² | E46: 80.25
A47: TORRE | B47: 1.9.3 | C47: BLOCO DE CONCRETO 19 cm, | D47: m² | E47: 91.11
A48: TORRE | B48: 1.10. | C48: 10_8º PAVTO
A49: TORRE | B49: 1.10.1 | C49: BLOCO DE CONCRETO 09 cm, | D49: m² | E49: 5.4
A50: TORRE | B50: 1.10.2 | C50: BLOCO DE CONCRETO 14 cm, | D50: m² | E50: 84.52
A51: TORRE | B51: 1.10.3 | C51: BLOCO DE CONCRETO 19 cm, | D51: m² | E51: 88.67
A52: TORRE | B52: 1.11. | C52: 11_9º PAVTO
A53: TORRE | B53: 1.11.1 | C53: BLOCO DE CONCRETO 09 cm, | D53: m² | E53: 12.06
A54: TORRE | B54: 1.11.2 | C54: BLOCO DE CONCRETO 14 cm, | D54: m² | E54: 80.25
A55: TORRE | B55: 1.11.3 | C55: BLOCO DE CONCRETO 19 cm, | D55: m² | E55: 91.11
A56: TORRE | B56: 1.12. | C56: 12_10º PAVTO
A57: TORRE | B57: 1.12.1 | C57: BLOCO DE CONCRETO 09 cm, | D57: m² | E57: 5.4
A58: TORRE | B58: 1.12.2 | C58: BLOCO DE CONCRETO 14 cm, | D58: m² | E58: 84.52
A59: TORRE | B59: 1.12.3 | C59: BLOCO DE CONCRETO 19 cm, | D59: m² | E59: 88.67
A60: TORRE | B60: 1.13. | C60: 13_11º PAVTO
A61: TORRE | B61: 1.13.1 | C61: BLOCO DE CONCRETO 09 cm, | D61: m² | E61: 12.06
A62: TORRE | B62: 1.13.2 | C62: BLOCO DE CONCRETO 14 cm, | D62: m² | E62: 80.25
A63: TORRE | B63: 1.13.3 | C63: BLOCO DE CONCRETO 19 cm, | D63: m² | E63: 91.12
A64: TORRE | B64: 1.14. | C64: 14_12º PAVTO
A65: TORRE | B65: 1.14.1 | C65: BLOCO DE CONCRETO 09 cm, | D65: m² | E65: 6.23
A66: TORRE | B66: 1.14.2 | C66: BLOCO DE CONCRETO 14 cm, | D66: m² | E66: 91.69
A67: TORRE | B67: 1.14.3 | C67: BLOCO DE CONCRETO 19 cm, | D67: m² | E67: 90.78
A68: TORRE | B68: 1.15. | C68: 15_13º PAVTO
A69: TORRE | B69: 1.15.1 | C69: BLOCO DE CONCRETO 09 cm, | D69: m² | E69: 15.8
A70: TORRE | B70: 1.15.2 | C70: BLOCO DE CONCRETO 14 cm, | D70: m² | E70: 77.71
A71: TORRE | B71: 1.15.3 | C71: BLOCO DE CONCRETO 19 cm, | D71: m² | E71: 165.11
A72: TORRE | B72: 1.16. | C72: 16_14º PAVTO
A73: TORRE | B73: 1.16.1 | C73: BLOCO DE CONCRETO 09 cm, | D73: m² | E73: 18.61
A74: TORRE | B74: 1.16.2 | C74: BLOCO DE CONCRETO 14 cm, | D74: m² | E74: 26.49
A75: TORRE | B75: 1.16.3 | C75: BLOCO DE CONCRETO 19 cm, | D75: m² | E75: 92.16
A76: TORRE | B76: 1.17. | C76: 17_15º PAVTO
A77: TORRE | B77: 1.17.1 | C77: BLOCO DE CONCRETO 14 cm, | D77: m² | E77: 26.43
A78: TORRE | B78: 1.17.2 | C78: BLOCO DE CONCRETO 19 cm, | D78: m² | E78: 60.78
A79: TORRE | B79: 1.18. | C79: 18_16º PAVTO
A80: TORRE | B80: 1.18.1 | C80: BLOCO DE CONCRETO 09 cm, | D80: m² | E80: 18.61
A81: TORRE | B81: 1.18.2 | C81: BLOCO DE CONCRETO 14 cm, | D81: m² | E81: 26.64
A82: TORRE | B82: 1.18.3 | C82: BLOCO DE CONCRETO 19 cm, | D82: m² | E82: 59.54
A83: TORRE | B83: 1.19. | C83: 19_17º PAVTO
A84: TORRE | B84: 1.19.1 | C84: BLOCO DE CONCRETO 14 cm, | D84: m² | E84: 29.52
A85: TORRE | B85: 1.19.2 | C85: BLOCO DE CONCRETO 19 cm, | D85: m² | E85: 64.16
A86: TORRE | B86: 1.20. | C86: 20_LAZER
A87: TORRE | B87: 1.20.1 | C87: BLOCO DE CONCRETO 09 cm, | D87: m² | E87: 5.43
A88: TORRE | B88: 1.20.2 | C88: BLOCO DE CONCRETO 14 cm, | D88: m² | E88: 61.55
A89: TORRE | B89: 1.20.3 | C89: BLOCO DE CONCRETO 19 cm, | D89: m² | E89: 136.74
A90: TORRE | B90: 1.21. | C90: 21_BARRILETE
A91: TORRE | B91: 1.21.1 | C91: BLOCO DE CONCRETO 09 cm, | D91: m² | E91: 9.36
A92: TORRE | B92: 1.21.2 | C92: BLOCO DE CONCRETO 14 cm, | D92: m² | E92: 13.79
A93: TORRE | B93: 1.21.3 | C93: BLOCO DE CONCRETO 19 cm, | D93: m² | E93: 55.45
A94: TORRE | B94: 1.22. | C94: 22_CAIXA D'ÁGUA
A95: TORRE | B95: 1.22.1 | C95: BLOCO DE CONCRETO 09 cm, | D95: m² | E95: 9.36
A96: TORRE | B96: 1.22.2 | C96: BLOCO DE CONCRETO 14 cm, | D96: m² | E96: 5.43
A97: TORRE | B97: 1.22.3 | C97: BLOCO DE CONCRETO 19 cm, | D97: m² | E97: 92.4
B98: 2. | C98: Alvenaria de vedação com bocos acf | E98: =SUM(E99:E192) -> 3466.31 | H98: =SUM(H99:H104) -> 3466.31 | I98: =IF(H98=E98,"OKAY","REVER") -> OKAY
A99: EMBASSAMENTO | B99: 2.1. | C99: 01_1º SUBSOLO 1 | G99: BLOCO CORTA-FOGO 09 cm, | H99: =SUMIF($C:$C,G99,$E:$E) -> 87.04
A100: EMBASSAMENTO | B100: 2.1.1 | C100: BLOCO CORTA-FOGO 14 cm, | D100: m² | E100: 58.37 | G100: BLOCO CORTA-FOGO 14 cm, | H100: =SUMIF($C:$C,G100,$E:$E) -> 1154.05
A101: EMBASSAMENTO | B101: 2.1.2 | C101: BLOCO CORTA-FOGO 19 cm, | D101: m² | E101: 25.41 | G101: BLOCO CORTA-FOGO 19 cm, | H101: =SUMIF($C:$C,G101,$E:$E) -> 2134.28
A102: EMBASSAMENTO | B102: 2.2. | C102: 02_TÉRREO | G102: BLOCO CORTA-FOGO ACÚSTICO 14 cm, | H102: =SUMIF($C:$C,G102,$E:$E) -> 90.94
...

Sheet IMPERMEABILIZAÇÃO
B1: Projeto: | C1: ='Obra '!D1 -> Caio Prado
B2: Empresa: | C2: ='Obra '!D2 -> Indepy
B3: Revisão: | C3: ='Obra '!D3 -> R00 - Larissa | T3: EAP | U3: TIPO
A4: IMPERMEABILIZAÇÃO | T4: {=_xlfn.UNIQUE(_xlfn._xlws.FILTER(E13:E145,E13:E145<>""))} -> 02.001.005 | U4: {=_xlfn.UNIQUE(_xlfn._xlws.FILTER(D13:D145,D13:D145<>""))} -> E3 | V4: Membrana de polímero acrílico com cimento e fibras, estruturada com tela de poliéster nos pontos críticos (3,0 kg/m²) | W4: =U4&" - "&V4 -> E3 - Membrana de polímero acrílico com cimento e fibras, estruturada com tela de poliéster nos pontos críticos (3,0 kg/m²)
B5: REGULARIZAÇÃO | C5: PROTEÇÃO | D5: =U4 -> E3 | E5: =U5 -> I30EL | F5: =U6 -> M44A | G5: =U7 -> C3 | H5: =U8 -> C3E3 | I5: =U9 -> C4 | J5: =U10 -> C4RQ | K5: =U11 -> I30 | L5: =U12 -> M44AE2 | M5: =U13 -> E2 | N5: =U14 -> M44AR05 | O5: =U15 -> M44A + M44AE2 | T5: 02.001.003 | U5: I30EL | V5: Membrana de polímero acrílico, sem cimento (3,0 kg/m²), com resistência à alcalinidade, estruturada com tela de poliéster nos pontos críticos – Ref.: Sika Baucryl, MC DF9, Icopor HP, Procryl Imper | W5: =U5&" - "&V5 -> I30EL - Membrana de polímero acrílico, sem cimento (3,0 kg/m²), com resistência à alcalinidade, estruturada com tela de poliéster nos pontos críticos – Ref.: Sika Baucryl, MC DF9, Icopor HP, Procryl Imper
B6: m2 | C6: m2 | D6: m2 | E6: m2 | F6: m2 | G6: m2 | H6: m2 | I6: m2 | J6: m2 | K6: m2 | L6: m2 | M6: m2 | N6: m2 | O6: m2 | T6: 06.001.006 | U6: M44A | V6: Manta asfáltica tipo IV, 4 mm A, com acabamento areia/areia aderida com asfalto oxidado (3,0 kg/m²) + banho de asfalto oxidado (2,0 kg/m²) | W6: =U6&" - "&V6 -> M44A - Manta asfáltica tipo IV, 4 mm A, com acabamento areia/areia aderida com asfalto oxidado (3,0 kg/m²) + banho de asfalto oxidado (2,0 kg/m²)
A7: IMPERMEABILIZAÇÃO | B7: =F146 -> 4984.69 | C7: =G146 -> 14.12 | D7: =SUMIF($D$13:$D$145,D$5,$B$13:$B$145) -> 2876.1 | E7: =SUMIF($D$13:$D$145,E$5,$B$13:$B$145) -> 130.83 | F7: =SUMIF($D$13:$D$145,F$5,$B$13:$B$145) -> 780.24 | G7: =SUMIF($D$13:$D$145,G$5,$B$13:$B$145) -> 445.18 | H7: =SUMIF($D$13:$D$145,H$5,$B$13:$B$145) -> 163.53 | I7: =SUMIF($D$13:$D$145,I$5,$B$13:$B$145) -> 309.19 | J7: =SUMIF($D$13:$D$145,J$5,$B$13:$B$145) -> 47.53 | K7: =SUMIF($D$13:$D$145,K$5,$B$13:$B$145) -> 1.92 | ... O7: =SUMIF($D$13:$D$145,O$5,$B$13:$B$145) -> 128.48 | T7: 02.001.008 | U7: C3 | V7: Argamassa polimérica rígida, estruturada com tela de poliéster nos pontos críticos (3,0 kg/m²) | W7: =U7&" - "&V7 -> C3 - Argamassa polimérica rígida, estruturada com tela de poliéster nos pontos críticos (3,0 kg/m²)
T8: 02.001.004 | U8: C3E3 | V8: Argamassa polimérica rígida (3,0 kg/m²) + membrana de polímero acrílico com cimento e fibras, estruturada com tela de poliéster nos pontos críticos (3,0 kg/m²) | W8: =U8&" - "&V8 -> C3E3 - Argamassa polimérica rígida (3,0 kg/m²) + membrana de polímero acrílico com cimento e fibras, estruturada com tela de poliéster nos pontos críticos (3,0 kg/m²)
A9: IMPERMEABILIZAÇÃO | T9: 06.001.002.001 | U9: C4 | V9: Argamassa polimérica rígida, estruturada com tela de poliéster nos pontos críticos (4,0 kg/m²) | W9: =U9&" - "&V9 -> C4 - Argamassa polimérica rígida, estruturada com tela de poliéster nos pontos críticos (4,0 kg/m²)
A10: ITEM | B10: ÁREA | C10: AMBIENTE | D10: TIPO | E10: NUMERO EAP | F10: REGULARIZAÇÃO | G10: PROTEÇÃO | H10: E3 | I10: I30EL | J10: M44A | K10: C3 | L10: C3E3 | M10: C4 | N10: C4RQ | O10: I30 | P10: M44AE2 | Q10: E2 | R10: M44AR05 | S10: M44A + M44AE2 | U10: C4RQ | V10: Argamassa polimérica rígida, com alta resistência química, estruturada com tela de poliéster nos pontos críticos (4,0 kg/m²) | W10: =U10&" - "&V10 -> C4RQ - Argamassa polimérica rígida, com alta resistência química, estruturada com tela de poliéster nos pontos críticos (4,0 kg/m²)
I11: I30EL | J11: M44A | K11: C3 | L11: C3E3 | M11: C4 | N11: C4RQ | O11: I30 | P11: M44AE2 | Q11: E2 | R11: M44AR05 | S11: M44A + M44AE2 | U11: I30 | V11: Membrana acrílica, estruturada com tela de poliéster, nos pontos críticos (3,0 kg/m²) | W11: =U11&" - "&V11 -> I30 - Membrana acrílica, estruturada com tela de poliéster, nos pontos críticos (3,0 kg/m²)
B12: M² | I12: I30EL | J12: M44A | K12: C3 | L12: C3E3 | M12: C4 | N12: C4RQ | O12: I30 | P12: M44AE2 | Q12: E2 | R12: M44AR05 | S12: M44A + M44AE2 | U12: M44AE2 | V12: Manta asfáltica tipo IV, 4 mm A, com acabamento areia/areia aderida com asfalto oxidado (3,0 kg/m²) + banho de asfalto oxidado (2,0 kg/m²) + membrana de polímero acrílico com cimento e fibras para combater eflorescência (2,0 kg/m²) | W12: =U12&" - "&V12 -> M44AE2 - Manta asfáltica tipo IV, 4 mm A, com acabamento areia/areia aderida com asfalto oxidado (3,0 kg/m²) + banho de asfalto oxidado (2,0 kg/m²) + membrana de polímero acrílico com cimento e fibras para combater eflorescência (2,0 kg/m²)
A13: E3 - Membrana de polímero acrílico com cimento e fibras, estruturada com tela de poliéster nos pontos críticos (3,0 kg/m²) SACADA - IMPER | B13: 26.82 | C13: SACADA | D13: =TRIM(LEFT(A13,FIND("-",A13)-1)) -> E3 | E13: 02.001.005 | F13: =B13 -> 26.82 | H13: =SUMIF($D13,H$10,$B13) -> 26.82 | I13: =SUMIF($D13,I$10,$B13) -> 0 | J13: =SUMIF($D13,J$10,$B13) -> 0 | K13: =SUMIF($D13,K$10,$B13) -> 0 | L13: =SUMIF($D13,L$10,$B13) -> 0 | M13: =SUMIF($D13,M$10,$B13) -> 0 | N13: =SUMIF($D13,N$10,$B13) -> 0 | O13: =SUMIF($D13,O$10,$B13) -> 0 | ... S13: =SUMIF($D13,S$10,$B13) -> 0 | U13: E2 | V13: Membrana de polímero acrílico, com cimento e com fibras, estruturada com tela de poliéster nos pontos críticos (2,0 kg/m²) | W13: =U13&" - "&V13 -> E2 - Membrana de polímero acrílico, com cimento e com fibras, estruturada com tela de poliéster nos pontos críticos (2,0 kg/m²)
A14: I30EL - Membrana de polímero acrílico, sem cimento (3,0 kg/m²), com resistência à alcalinidade, estruturada com tela de poliéster nos pontos críticos – Ref.: Sika Baucryl, MC DF9, Icopor HP, Procryl Imper. - ABA 01 | B14: 54.68 | C14: ABA 01 | D14: =TRIM(LEFT(A14,FIND("-",A14)-1)) -> I30EL | E14: 02.001.003 | F14: =B14 -> 54.68 | H14: =SUMIF($D14,H$10,$B14) -> 0 | I14: =SUMIF($D14,I$10,$B14) -> 54.68 | J14: =SUMIF($D14,J$10,$B14) -> 0 | K14: =SUMIF($D14,K$10,$B14) -> 0 | L14: =SUMIF($D14,L$10,$B14) -> 0 | M14: =SUMIF($D14,M$10,$B14) -> 0 | N14: =SUMIF($D14,N$10,$B14) -> 0 | O14: =SUMIF($D14,O$10,$B14) -> 0 | ... S14: =SUMIF($D14,S$10,$B14) -> 0 | U14: M44AR05 | V14: Manta asfáltica tipo IV, 4 mm A, com acabamento areia/areia aderida com asfalto oxidado (3,0 kg/m²) + banho de asfalto oxidado (2,0 kg/m²) + pintura de proteção antirraiz sobre a proteção mecânica (0,5 L/m²) | W14: =U14&" - "&V14 -> M44AR05 - Manta asfáltica tipo IV, 4 mm A, com acabamento areia/areia aderida com asfalto oxidado (3,0 kg/m²) + banho de asfalto oxidado (2,0 kg/m²) + pintura de proteção antirraiz sobre a proteção mecânica (0,5 L/m²)
A15: I30EL - Membrana de polímero acrílico, sem cimento (3,0 kg/m²), com resistência à alcalinidade, estruturada com tela de poliéster nos pontos críticos – Ref.: Sika Baucryl, MC DF9, Icopor HP, Procryl Imper. - ABA 02 | B15: 36 | C15: ABA 02 | D15: =TRIM(LEFT(A15,FIND("-",A15)-1)) -> I30EL | E15: 02.001.003 | F15: =B15 -> 36 | H15: =SUMIF($D15,H$10,$B15) -> 0 | I15: =SUMIF($D15,I$10,$B15) -> 36 | J15: =SUMIF($D15,J$10,$B15) -> 0 | K15: =SUMIF($D15,K$10,$B15) -> 0 | L15: =SUMIF($D15,L$10,$B15) -> 0 | M15: =SUMIF($D15,M$10,$B15) -> 0 | N15: =SUMIF($D15,N$10,$B15) -> 0 | O15: =SUMIF($D15,O$10,$B15) -> 0 | ... S15: =SUMIF($D15,S$10,$B15) -> 0 | U15: M44A + M44AE2 | V15: Manta asfáltica tipo IV, 4 mm A, com acabamento areia/areia + manta asfáltica tipo IV, 4 mm A, com acabamento areia/areia aderida com asfalto oxidado (3,0 kg/m²) + banho de asfalto oxidado (2,0 kg/m²) + membrana de polímero acrílico com cimento e fibras para combater eflorescência (2,0 kg/m²) | W15: =U15&" - "&V15 -> M44A + M44AE2 - Manta asfáltica tipo IV, 4 mm A, com acabamento areia/areia + manta asfáltica tipo IV, 4 mm A, com acabamento areia/areia aderida com asfalto oxidado (3,0 kg/m²) + banho de asfalto oxidado (2,0 kg/m²) + membrana de polímero acrílico com cimento e fibras para combater eflorescência (2,0 kg/m²)
A16: I30EL - Membrana de polímero acrílico, sem cimento (3,0 kg/m²), com resistência à alcalinidade, estruturada com tela de poliéster nos pontos críticos – Ref.: Sika Baucryl, MC DF9, Icopor HP, Procryl Imper. - ABA 03 | B16: 24.42 | C16: ABA 03 | D16: =TRIM(LEFT(A16,FIND("-",A16)-1)) -> I30EL | E16: 02.001.003 | F16: =B16 -> 24.42 | H16: =SUMIF($D16,H$10,$B16) -> 0 | I16: =SUMIF($D16,I$10,$B16) -> 24.42 | J16: =SUMIF($D16,J$10,$B16) -> 0 | K16: =SUMIF($D16,K$10,$B16) -> 0 | L16: =SUMIF($D16,L$10,$B16) -> 0 | M16: =SUMIF($D16,M$10,$B16) -> 0 | N16: =SUMIF($D16,N$10,$B16) -> 0 | O16: =SUMIF($D16,O$10,$B16) -> 0 | ... S16: =SUMIF($D16,S$10,$B16) -> 0
A17: I30EL - Membrana de polímero acrílico, sem cimento (3,0 kg/m²), com resistência à alcalinidade, estruturada com tela de poliéster nos pontos críticos – Ref.: Sika Baucryl, MC DF9, Icopor HP, Procryl Imper. - ABA 04 | B17: 15.73 | C17: ABA 04 | D17: =TRIM(LEFT(A17,FIND("-",A17)-1)) -> I30EL | E17: 02.001.003 | F17: =B17 -> 15.73 | H17: =SUMIF($D17,H$10,$B17) -> 0 | I17: =SUMIF($D17,I$10,$B17) -> 15.73 | J17: =SUMIF($D17,J$10,$B17) -> 0 | K17: =SUMIF($D17,K$10,$B17) -> 0 | L17: =SUMIF($D17,L$10,$B17) -> 0 | M17: =SUMIF($D17,M$10,$B17) -> 0 | N17: =SUMIF($D17,N$10,$B17) -> 0 | O17: =SUMIF($D17,O$10,$B17) -> 0 | ... S17: =SUMIF($D17,S$10,$B17) -> 0
A18: M44A - Manta asfáltica tipo IV, 4 mm A, com acabamento areia/areia aderida com asfalto oxidado (3,0 kg/m²) + banho de asfalto oxidado (2,0 kg/m²) - ACESSO E ESCADA | B18: 12.48 | C18: =TRIM(RIGHT(A18,LEN(A18)-FIND("@",SUBSTITUTE(A18,"-","@",LEN(A18)-LEN(SUBSTITUTE(A18,"-","")))))) -> ACESSO E ESCADA | D18: =TRIM(LEFT(A18,FIND("-",A18)-1)) -> M44A | E18: 02.001.005 | F18: =B18 -> 12.48 | H18: =SUMIF($D18,H$10,$B18) -> 0 | I18: =SUMIF($D18,I$10,$B18) -> 0 | J18: =SUMIF($D18,J$10,$B18) -> 12.48 | K18: =SUMIF($D18,K$10,$B18) -> 0 | L18: =SUMIF($D18,L$10,$B18) -> 0 | M18: =SUMIF($D18,M$10,$B18) -> 0 | N18: =SUMIF($D18,N$10,$B18) -> 0 | O18: =SUMIF($D18,O$10,$B18) -> 0 | ... S18: =SUMIF($D18,S$10,$B18) -> 0
A19: E3 - Membrana de polímero acrílico com cimento e fibras, estruturada com tela de poliéster nos pontos críticos (3,0 kg/m²) - APA 01 | B19: 121.06 | C19: =TRIM(RIGHT(A19,LEN(A19)-FIND("@",SUBSTITUTE(A19,"-","@",LEN(A19)-LEN(SUBSTITUTE(A19,"-","")))))) -> APA 01 | D19: =TRIM(LEFT(A19,FIND("-",A19)-1)) -> E3 | E19: 02.001.005 | F19: =B19 -> 121.06 | H19: =SUMIF($D19,H$10,$B19) -> 121.06 | I19: =SUMIF($D19,I$10,$B19) -> 0 | J19: =SUMIF($D19,J$10,$B19) -> 0 | K19: =SUMIF($D19,K$10,$B19) -> 0 | L19: =SUMIF($D19,L$10,$B19) -> 0 | M19: =SUMIF($D19,M$10,$B19) -> 0 | N19: =SUMIF($D19,N$10,$B19) -> 0 | O19: =SUMIF($D19,O$10,$B19) -> 0 | ... S19: =SUMIF($D19,S$10,$B19) -> 0
A20: E3 - Membrana de polímero acrílico com cimento e fibras, estruturada com tela de poliéster nos pontos críticos (3,0 kg/m²) - APA 02 | B20: 245.08 | C20: =TRIM(RIGHT(A20,LEN(A20)-FIND("@",SUBSTITUTE(A20,"-","@",LEN(A20)-LEN(SUBSTITUTE(A20,"-","")))))) -> APA 02 | D20: =TRIM(LEFT(A20,FIND("-",A20)-1)) -> E3 | E20: 02.001.005 | F20: =B20 -> 245.08 | H20: =SUMIF($D20,H$10,$B20) -> 245.08 | I20: =SUMIF($D20,I$10,$B20) -> 0 | J20: =SUMIF($D20,J$10,$B20) -> 0 | K20: =SUMIF($D20,K$10,$B20) -> 0 | L20: =SUMIF($D20,L$10,$B20) -> 0 | M20: =SUMIF($D20,M$10,$B20) -> 0 | N20: =SUMIF($D20,N$10,$B20) -> 0 | O20: =SUMIF($D20,O$10,$B20) -> 0 | ... S20: =SUMIF($D20,S$10,$B20) -> 0
A21: E3 - Membrana de polímero acrílico com cimento e fibras, estruturada com tela de poliéster nos pontos críticos (3,0 kg/m²) - APA 03 | B21: 56.82 | C21: =TRIM(RIGHT(A21,LEN(A21)-FIND("@",SUBSTITUTE(A21,"-","@",LEN(A21)-LEN(SUBSTITUTE(A21,"-","")))))) -> APA 03 | D21: =TRIM(LEFT(A21,FIND("-",A21)-1)) -> E3 | E21: 02.001.005 | F21: =B21 -> 56.82 | H21: =SUMIF($D21,H$10,$B21) -> 56.82 | I21: =SUMIF($D21,I$10,$B21) -> 0 | J21: =SUMIF($D21,J$10,$B21) -> 0 | K21: =SUMIF($D21,K$10,$B21) -> 0 | L21: =SUMIF($D21,L$10,$B21) -> 0 | M21: =SUMIF($D21,M$10,$B21) -> 0 | N21: =SUMIF($D21,N$10,$B21) -> 0 | O21: =SUMIF($D21,O$10,$B21) -> 0 | ... S21: =SUMIF($D21,S$10,$B21) -> 0
A22: E3 - Membrana de polímero acrílico com cimento e fibras, estruturada com tela de poliéster nos pontos críticos (3,0 kg/m²) - APA 04 | B22: 87.65 | C22: =TRIM(RIGHT(A22,LEN(A22)-FIND("@",SUBSTITUTE(A22,"-","@",LEN(A22)-LEN(SUBSTITUTE(A22,"-","")))))) -> APA 04 | D22: =TRIM(LEFT(A22,FIND("-",A22)-1)) -> E3 | E22: 02.001.005 | F22: =B22 -> 87.65 | H22: =SUMIF($D22,H$10,$B22) -> 87.65 | I22: =SUMIF($D22,I$10,$B22) -> 0 | J22: =SUMIF($D22,J$10,$B22) -> 0 | K22: =SUMIF($D22,K$10,$B22) -> 0 | L22: =SUMIF($D22,L$10,$B22) -> 0 | M22: =SUMIF($D22,M$10,$B22) -> 0 | N22: =SUMIF($D22,N$10,$B22) -> 0 | O22: =SUMIF($D22,O$10,$B22) -> 0 | ... S22: =SUMIF($D22,S$10,$B22) -> 0
A23: E3 - Membrana de polímero acrílico com cimento e fibras, estruturada com tela de poliéster nos pontos críticos (3,0 kg/m²) - APA 05 | B23: 52.51 | C23: =TRIM(RIGHT(A23,LEN(A23)-FIND("@",SUBSTITUTE(A23,"-","@",LEN(A23)-LEN(SUBSTITUTE(A23,"-","")))))) -> APA 05 | D23: =TRIM(LEFT(A23,FIND("-",A23)-1)) -> E3 | E23: 02.001.005 | F23: =B23 -> 52.51 | H23: =SUMIF($D23,H$10,$B23) -> 52.51 | I23: =SUMIF($D23,I$10,$B23) -> 0 | J23: =SUMIF($D23,J$10,$B23) -> 0 | K23: =SUMIF($D23,K$10,$B23) -> 0 | L23: =SUMIF($D23,L$10,$B23) -> 0 | M23: =SUMIF($D23,M$10,$B23) -> 0 | N23: =SUMIF($D23,N$10,$B23) -> 0 | O23: =SUMIF($D23,O$10,$B23) -> 0 | ... S23: =SUMIF($D23,S$10,$B23) -> 0
A24: E3 - Membrana de polímero acrílico com cimento e fibras, estruturada com tela de poliéster nos pontos críticos (3,0 kg/m²) - APA 06 | B24: 28.62 | C24: =TRIM(RIGHT(A24,LEN(A24)-FIND("@",SUBSTITUTE(A24,"-","@",LEN(A24)-LEN(SUBSTITUTE(A24,"-","")))))) -> APA 06 | D24: =TRIM(LEFT(A24,FIND("-",A24)-1)) -> E3 | E24: 02.001.005 | F24: =B24 -> 28.62 | H24: =SUMIF($D24,H$10,$B24) -> 28.62 | I24: =SUMIF($D24,I$10,$B24) -> 0 | J24: =SUMIF($D24,J$10,$B24) -> 0 | K24: =SUMIF($D24,K$10,$B24) -> 0 | L24: =SUMIF($D24,L$10,$B24) -> 0 | M24: =SUMIF($D24,M$10,$B24) -> 0 | N24: =SUMIF($D24,N$10,$B24) -> 0 | O24: =SUMIF($D24,O$10,$B24) -> 0 | ... S24: =SUMIF($D24,S$10,$B24) -> 0
A25: E3 - Membrana de polímero acrílico com cimento e fibras, estruturada com tela de poliéster nos pontos críticos (3,0 kg/m²) - APA 07 | B25: 9.36 | C25: =TRIM(RIGHT(A25,LEN(A25)-FIND("@",SUBSTITUTE(A25,"-","@",LEN(A25)-LEN(SUBSTITUTE(A25,"-","")))))) -> APA 07 | D25: =TRIM(LEFT(A25,FIND("-",A25)-1)) -> E3 | E25: 02.001.005 | F25: =B25 -> 9.36 | H25: =SUMIF($D25,H$10,$B25) -> 9.36 | I25: =SUMIF($D25,I$10,$B25) -> 0 | J25: =SUMIF($D25,J$10,$B25) -> 0 | K25: =SUMIF($D25,K$10,$B25) -> 0 | L25: =SUMIF($D25,L$10,$B25) -> 0 | M25: =SUMIF($D25,M$10,$B25) -> 0 | N25: =SUMIF($D25,N$10,$B25) -> 0 | O25: =SUMIF($D25,O$10,$B25) -> 0 | ... S25: =SUMIF($D25,S$10,$B25) -> 0
A26: E3 - Membrana de polímero acrílico com cimento e fibras, estruturada com tela de poliéster nos pontos críticos (3,0 kg/m²) - APA 08 | B26: 4.82 | C26: =TRIM(RIGHT(A26,LEN(A26)-FIND("@",SUBSTITUTE(A26,"-","@",LEN(A26)-LEN(SUBSTITUTE(A26,"-","")))))) -> APA 08 | D26: =TRIM(LEFT(A26,FIND("-",A26)-1)) -> E3 | E26: 02.001.005 | F26: =B26 -> 4.82 | H26: =SUMIF($D26,H$10,$B26) -> 4.82 | I26: =SUMIF($D26,I$10,$B26) -> 0 | J26: =SUMIF($D26,J$10,$B26) -> 0 | K26: =SUMIF($D26,K$10,$B26) -> 0 | L26: =SUMIF($D26,L$10,$B26) -> 0 | M26: =SUMIF($D26,M$10,$B26) -> 0 | N26: =SUMIF($D26,N$10,$B26) -> 0 | O26: =SUMIF($D26,O$10,$B26) -> 0 | ... S26: =SUMIF($D26,S$10,$B26) -> 0
A27: C3 - Argamassa polimérica rígida, estruturada com tela de poliéster nos pontos críticos (3,0 kg/m²) - APA FUNC. | B27: 8.51 | C27: =TRIM(RIGHT(A27,LEN(A27)-FIND("@",SUBSTITUTE(A27,"-","@",LEN(A27)-LEN(SUBSTITUTE(A27,"-","")))))) -> APA FUNC. | D27: =TRIM(LEFT(A27,FIND("-",A27)-1)) -> C3 | E27: 02.001.005 | F27: =B27 -> 8.51 | H27: =SUMIF($D27,H$10,$B27) -> 0 | I27: =SUMIF($D27,I$10,$B27) -> 0 | J27: =SUMIF($D27,J$10,$B27) -> 0 | K27: =SUMIF($D27,K$10,$B27) -> 8.51 | L27: =SUMIF($D27,L$10,$B27) -> 0 | M27: =SUMIF($D27,M$10,$B27) -> 0 | N27: =SUMIF($D27,N$10,$B27) -> 0 | O27: =SUMIF($D27,O$10,$B27) -> 0 | ... S27: =SUMIF($D27,S$10,$B27) -> 0
A28: E3 - Membrana de polímero acrílico com cimento e fibras, estruturada com tela de poliéster nos pontos críticos (3,0 kg/m²) - ÁREA TÉCNICA | B28: 133.84 | C28: =TRIM(RIGHT(A28,LEN(A28)-FIND("@",SUBSTITUTE(A28,"-","@",LEN(A28)-LEN(SUBSTITUTE(A28,"-","")))))) -> ÁREA TÉCNICA | D28: =TRIM(LEFT(A28,FIND("-",A28)-1)) -> E3 | E28: 02.001.005 | F28: =B28 -> 133.84 | H28: =SUMIF($D28,H$10,$B28) -> 133.84 | I28: =SUMIF($D28,I$10,$B28) -> 0 | J28: =SUMIF($D28,J$10,$B28) -> 0 | K28: =SUMIF($D28,K$10,$B28) -> 0 | L28: =SUMIF($D28,L$10,$B28) -> 0 | M28: =SUMIF($D28,M$10,$B28) -> 0 | N28: =SUMIF($D28,N$10,$B28) -> 0 | O28: =SUMIF($D28,O$10,$B28) -> 0 | ... S28: =SUMIF($D28,S$10,$B28) -> 0
A29: E3 - Membrana de polímero acrílico com cimento e fibras, estruturada com tela de poliéster nos pontos críticos (3,0 kg/m²) - BANHO 01 | B29: 264.71 | C29: =TRIM(RIGHT(A29,LEN(A29)-FIND("@",SUBSTITUTE(A29,"-","@",LEN(A29)-LEN(SUBSTITUTE(A29,"-","")))))) -> BANHO 01 | D29: =TRIM(LEFT(A29,FIND("-",A29)-1)) -> E3 | E29: 02.001.005 | F29: =B29 -> 264.71 | H29: =SUMIF($D29,H$10,$B29) -> 264.71 | I29: =SUMIF($D29,I$10,$B29) -> 0 | J29: =SUMIF($D29,J$10,$B29) -> 0 | K29: =SUMIF($D29,K$10,$B29) -> 0 | L29: =SUMIF($D29,L$10,$B29) -> 0 | M29: =SUMIF($D29,M$10,$B29) -> 0 | N29: =SUMIF($D29,N$10,$B29) -> 0 | O29: =SUMIF($D29,O$10,$B29) -> 0 | ... S29: =SUMIF($D29,S$10,$B29) -> 0
... A88: C4 - Argamassa polimérica rígida, estruturada com tela de poliéster nos pontos críticos (4,0 kg/m²) - INTERFACE JARDIM | B88: 52.36 | C88: =TRIM(RIGHT(A88,LEN(A88)-FIND("@",SUBSTITUTE(A88,"-","@",LEN(A88)-LEN(SUBSTITUTE(A88,"-","")))))) -> INTERFACE JARDIM | D88: =TRIM(LEFT(A88,FIND("-",A88)-1)) -> C4 | E88: 02.001.003 | F88: =B88 -> 52.36 | H88: =SUMIF($D88,H$10,$B88) -> 0 | I88: =SUMIF($D88,I$10,$B88) -> 0 | J88: =SUMIF($D88,J$10,$B88) -> 0 | K88: =SUMIF($D88,K$10,$B88) -> 0 | L88: =SUMIF($D88,L$10,$B88) -> 0 | M88: =SUMIF($D88,M$10,$B88) -> 52.36 | N88: =SUMIF($D88,N$10,$B88) -> 0 | O88: =SUMIF($D88,O$10,$B88) -> 0 | ... S88: =SUMIF($D88,S$10,$B88) -> 0
A89: M44AR05 - Manta asfáltica tipo IV, 4 mm A, com acabamento areia/areia aderida com asfalto oxidado (3,0 kg/m²) + banho de asfalto oxidado (2,0 kg/m²) + pintura de proteção antirraiz sobre a proteção mecânica (0,5 L/m²) - JARDINS ELEVADOS | B89: 3.22 | C89: =TRIM(RIGHT(A89,LEN(A89)-FIND("@",SUBSTITUTE(A89,"-","@",LEN(A89)-LEN(SUBSTITUTE(A89,"-","")))))) -> JARDINS ELEVADOS | D89: =TRIM(LEFT(A89,FIND("-",A89)-1)) -> M44AR05 | E89: 02.001.003 | F89: =B89 -> 3.22 | G89: =B89 -> 3.22 | H89: =SUMIF($D89,H$10,$B89) -> 0 | I89: =SUMIF($D89,I$10,$B89) -> 0 | J89: =SUMIF($D89,J$10,$B89) -> 0 | K89: =SUMIF($D89,K$10,$B89) -> 0 | L89: =SUMIF($D89,L$10,$B89) -> 0 | M89: =SUMIF($D89,M$10,$B89) -> 0 | N89: =SUMIF($D89,N$10,$B89) -> 0 | O89: =SUMIF($D89,O$10,$B89) -> 0 | ... S89: =SUMIF($D89,S$10,$B89) -> 0
A90: M44A - Manta asfáltica tipo IV, 4 mm A, com acabamento areia/areia aderida com asfalto oxidado (3,0 kg/m²) + banho de asfalto oxidado (2,0 kg/m²) - LAJE IMPERMEABILIZADA | B90: 96.3 | C90: =TRIM(RIGHT(A90,LEN(A90)-FIND("@",SUBSTITUTE(A90,"-","@",LEN(A90)-LEN(SUBSTITUTE(A90,"-","")))))) -> LAJE IMPERMEABILIZADA | D90: =TRIM(LEFT(A90,FIND("-",A90)-1)) -> M44A | E90: 02.001.003 | F90: =B90 -> 96.3 | H90: =SUMIF($D90,H$10,$B90) -> 0 | I90: =SUMIF($D90,I$10,$B90) -> 0 | J90: =SUMIF($D90,J$10,$B90) -> 96.3 | K90: =SUMIF($D90,K$10,$B90) -> 0 | L90: =SUMIF($D90,L$10,$B90) -> 0 | M90: =SUMIF($D90,M$10,$B90) -> 0 | N90: =SUMIF($D90,N$10,$B90) -> 0 | O90: =SUMIF($D90,O$10,$B90) -> 0 | ... S90: =SUMIF($D90,S$10,$B90) -> 0
A91: E3 - Membrana de polímero acrílico com cimento e fibras, estruturada com tela de poliéster nos pontos críticos (3,0 kg/m²) - LAVABO | B91: 4.8 | C91: =TRIM(RIGHT(A91,LEN(A91)-FIND("@",SUBSTITUTE(A91,"-","@",LEN(A91)-LEN(SUBSTITUTE(A91,"-","")))))) -> LAVABO | D91: =TRIM(LEFT(A91,FIND("-",A91)-1)) -> E3 | E91: 02.001.005 | F91: =B91 -> 4.8 | H91: =SUMIF($D91,H$10,$B91) -> 4.8 | I91: =SUMIF($D91,I$10,$B91) -> 0 | J91: =SUMIF($D91,J$10,$B91) -> 0 | K91: =SUMIF($D91,K$10,$B91) -> 0 | L91: =SUMIF($D91,L$10,$B91) -> 0 | M91: =SUMIF($D91,M$10,$B91) -> 0 | N91: =SUMIF($D91,N$10,$B91) -> 0 | O91: =SUMIF($D91,O$10,$B91) -> 0 | ... S91: =SUMIF($D91,S$10,$B91) -> 0
A92: E3 - Membrana de polímero acrílico com cimento e fibras, estruturada com tela de poliéster nos pontos críticos (3,0 kg/m²) - LAVABO 01 | B92: 3.09 | C92: =TRIM(RIGHT(A92,LEN(A92)-FIND("@",SUBSTITUTE(A92,"-","@",LEN(A92)-LEN(SUBSTITUTE(A92,"-","")))))) -> LAVABO 01 | D92: =TRIM(LEFT(A92,FIND("-",A92)-1)) -> E3 | E92: 02.001.005 | F92: =B92 -> 3.09 | H92: =SUMIF($D92,H$10,$B92) -> 3.09 | I92: =SUMIF($D92,I$10,$B92) -> 0 | J92: =SUMIF($D92,J$10,$B92) -> 0 | K92: =SUMIF($D92,K$10,$B92) -> 0 | L92: =SUMIF($D92,L$10,$B92) -> 0 | M92: =SUMIF($D92,M$10,$B92) -> 0 | N92: =SUMIF($D92,N$10,$B92) -> 0 | O92: =SUMIF($D92,O$10,$B92) -> 0 | ... S92: =SUMIF($D92,S$10,$B92) -> 0
A93: E3 - Membrana de polímero acrílico com cimento e fibras, estruturada com tela de poliéster nos pontos críticos (3,0 kg/m²) - LAVABO 02 | B93: 3.7 | C93: =TRIM(RIGHT(A93,LEN(A93)-FIND("@",SUBSTITUTE(A93,"-","@",LEN(A93)-LEN(SUBSTITUTE(A93,"-","")))))) -> LAVABO 02 | D93: =TRIM(LEFT(A93,FIND("-",A93)-1)) -> E3 | E93: 02.001.005 | F93: =B93 -> 3.7 | H93: =SUMIF($D93,H$10,$B93) -> 3.7 | I93: =SUMIF($D93,I$10,$B93) -> 0 | J93: =SUMIF($D93,J$10,$B93) -> 0 | K93: =SUMIF($D93,K$10,$B93) -> 0 | L93: =SUMIF($D93,L$10,$B93) -> 0 | M93: =SUMIF($D93,M$10,$B93) -> 0 | N93: =SUMIF($D93,N$10,$B93) -> 0 | O93: =SUMIF($D93,O$10,$B93) -> 0 | ... S93: =SUMIF($D93,S$10,$B93) -> 0
A94: E3 - Membrana de polímero acrílico com cimento e fibras, estruturada com tela de poliéster nos pontos críticos (3,0 kg/m²) - LAVABO 03 | B94: 1.84 | C94: =TRIM(RIGHT(A94,LEN(A94)-FIND("@",SUBSTITUTE(A94,"-","@",LEN(A94)-LEN(SUBSTITUTE(A94,"-","")))))) -> LAVABO 03 | D94: =TRIM(LEFT(A94,FIND("-",A94)-1)) -> E3 | E94: 02.001.005 | F94: =B94 -> 1.84 | H94: =SUMIF($D94,H$10,$B94) -> 1.84 | I94: =SUMIF($D94,I$10,$B94) -> 0 | J94: =SUMIF($D94,J$10,$B94) -> 0 | K94: =SUMIF($D94,K$10,$B94) -> 0 | L94: =SUMIF($D94,L$10,$B94) -> 0 | M94: =SUMIF($D94,M$10,$B94) -> 0 | N94: =SUMIF($D94,N$10,$B94) -> 0 | O94: =SUMIF($D94,O$10,$B94) -> 0 | ... S94: =SUMIF($D94,S$10,$B94) -> 0
A95: E3 - Membrana de polímero acrílico com cimento e fibras, estruturada com tela de poliéster nos pontos críticos (3,0 kg/m²) - LAVANDERIA | B95: 4.42 | C95: =TRIM(RIGHT(A95,LEN(A95)-FIND("@",SUBSTITUTE(A95,"-","@",LEN(A95)-LEN(SUBSTITUTE(A95,"-","")))))) -> LAVANDERIA | D95: =TRIM(LEFT(A95,FIND("-",A95)-1)) -> E3 | E95: 02.001.005 | F95: =B95 -> 4.42 | H95: =SUMIF($D95,H$10,$B95) -> 4.42 | I95: =SUMIF($D95,I$10,$B95) -> 0 | J95: =SUMIF($D95,J$10,$B95) -> 0 | K95: =SUMIF($D95,K$10,$B95) -> 0 | L95: =SUMIF($D95,L$10,$B95) -> 0 | M95: =SUMIF($D95,M$10,$B95) -> 0 | N95: =SUMIF($D95,N$10,$B95) -> 0 | O95: =SUMIF($D95,O$10,$B95) -> 0 | ... S95: =SUMIF($D95,S$10,$B95) -> 0
A96: M44A + M44AE2 - Manta asfáltica tipo IV, 4 mm A, com acabamento areia/areia + manta asfáltica tipo IV, 4 mm A, com acabamento areia/areia aderida com asfalto oxidado (3,0 kg/m²) + banho de asfalto oxidado (2,0 kg/m²) + membrana de polímero acrílico com cimento e fibras para combater eflorescência (2,0 kg/m²) - PISCINA | B96: 55.15 | C96: =TRIM(RIGHT(A96,LEN(A96)-FIND("@",SUBSTITUTE(A96,"-","@",LEN(A96)-LEN(SUBSTITUTE(A96,"-","")))))) -> PISCINA | D96: =TRIM(LEFT(A96,FIND("-",A96)-1)) -> M44A + M44AE2 | E96: 02.001.004 | F96: =B96 -> 55.15 | H96: =SUMIF($D96,H$10,$B96) -> 0 | I96: =SUMIF($D96,I$10,$B96) -> 0 | J96: =SUMIF($D96,J$10,$B96) -> 0 | K96: =SUMIF($D96,K$10,$B96) -> 0 | L96: =SUMIF($D96,L$10,$B96) -> 0 | M96: =SUMIF($D96,M$10,$B96) -> 0 | N96: =SUMIF($D96,N$10,$B96) -> 0 | O96: =SUMIF($D96,O$10,$B96) -> 0 | ... S96: =SUMIF($D96,S$10,$B96) -> 55.15
A97: M44A + M44AE2 - Manta asfáltica tipo IV, 4 mm A, com acabamento areia/areia + manta asfáltica tipo IV, 4 mm A, com acabamento areia/areia aderida com asfalto oxidado (3,0 kg/m²) + banho de asfalto oxidado (2,0 kg/m²) + membrana de polímero acrílico com cimento e fibras para combater eflorescência (2,0 kg/m²) - PRAINHA | B97: 19.65 | C97: =TRIM(RIGHT(A97,LEN(A97)-FIND("@",SUBSTITUTE(A97,"-","@",LEN(A97)-LEN(SUBSTITUTE(A97,"-","")))))) -> PRAINHA | D97: =TRIM(LEFT(A97,FIND("-",A97)-1)) -> M44A + M44AE2 | E97: 02.001.004 | F97: =B97 -> 19.65 | H97: =SUMIF($D97,H$10,$B97) -> 0 | I97: =SUMIF($D97,I$10,$B97) -> 0 | J97: =SUMIF($D97,J$10,$B97) -> 0 | K97: =SUMIF($D97,K$10,$B97) -> 0 | L97: =SUMIF($D97,L$10,$B97) -> 0 | M97: =SUMIF($D97,M$10,$B97) -> 0 | N97: =SUMIF($D97,N$10,$B97) -> 0 | O97: =SUMIF($D97,O$10,$B97) -> 0 | ... S97: =SUMIF($D97,S$10,$B97) -> 19.65
A98: M44A - Manta asfáltica tipo IV, 4 mm A, com acabamento areia/areia aderida com asfalto oxidado (3,0 kg/m²) + banho de asfalto oxidado (2,0 kg/m²) - PRAÇA | B98: 147.75 | C98: =TRIM(RIGHT(A98,LEN(A98)-FIND("@",SUBSTITUTE(A98,"-","@",LEN(A98)-LEN(SUBSTITUTE(A98,"-","")))))) -> PRAÇA | D98: =TRIM(LEFT(A98,FIND("-",A98)-1)) -> M44A | E98: 02.001.003 | F98: =B98 -> 147.75 | H98: =SUMIF($D98,H$10,$B98) -> 0 | I98: =SUMIF($D98,I$10,$B98) -> 0 | J98: =SUMIF($D98,J$10,$B98) -> 147.75 | K98: =SUMIF($D98,K$10,$B98) -> 0 | L98: =SUMIF($D98,L$10,$B98) -> 0 | M98: =SUMIF($D98,M$10,$B98) -> 0 | N98: =SUMIF($D98,N$10,$B98) -> 0 | O98: =SUMIF($D98,O$10,$B98) -> 0 | ... S98: =SUMIF($D98,S$10,$B98) -> 0
A99: M44A - Manta asfáltica tipo IV, 4 mm A, com acabamento areia/areia aderida com asfalto oxidado (3,0 kg/m²) + banho de asfalto oxidado (2,0 kg/m²) - TAMPA DA CÂMARA | B99: 2.27 | C99: =TRIM(RIGHT(A99,LEN(A99)-FIND("@",SUBSTITUTE(A99,"-","@",LEN(A99)-LEN(SUBSTITUTE(A99,"-","")))))) -> TAMPA DA CÂMARA | D99: =TRIM(LEFT(A99,FIND("-",A99)-1)) -> M44A | E99: 02.001.003 | F99: =B99 -> 2.27 | H99: =SUMIF($D99,H$10,$B99) -> 0 | I99: =SUMIF($D99,I$10,$B99) -> 0 | J99: =SUMIF($D99,J$10,$B99) -> 2.27 | K99: =SUMIF($D99,K$10,$B99) -> 0 | L99: =SUMIF($D99,L$10,$B99) -> 0 | M99: =SUMIF($D99,M$10,$B99) -> 0 | N99: =SUMIF($D99,N$10,$B99) -> 0 | O99: =SUMIF($D99,O$10,$B99) -> 0 | ... S99: =SUMIF($D99,S$10,$B99) -> 0
A100: M44A - Manta asfáltica tipo IV, 4 mm A, com acabamento areia/areia aderida com asfalto oxidado (3,0 kg/m²) + banho de asfalto oxidado (2,0 kg/m²) - TERRAÇO | B100: 9.37 | C100: =TRIM(RIGHT(A100,LEN(A100)-FIND("@",SUBSTITUTE(A100,"-","@",LEN(A100)-LEN(SUBSTITUTE(A100,"-","")))))) -> TERRAÇO | D100: =TRIM(LEFT(A100,FIND("-",A100)-1)) -> M44A | E100: 02.001.003 | F100: =B100 -> 9.37 | H100: =SUMIF($D100,H$10,$B100) -> 0 | I100: =SUMIF($D100,I$10,$B100) -> 0 | J100: =SUMIF($D100,J$10,$B100) -> 9.37 | K100: =SUMIF($D100,K$10,$B100) -> 0 | L100: =SUMIF($D100,L$10,$B100) -> 0 | M100: =SUMIF($D100,M$10,$B100) -> 0 | N100: =SUMIF($D100,N$10,$B100) -> 0 | O100: =SUMIF($D100,O$10,$B100) -> 0 | ... S100: =SUMIF($D100,S$10,$B100) -> 0
A101: M44A - Manta asfáltica tipo IV, 4 mm A, com acabamento areia/areia aderida com asfalto oxidado (3,0 kg/m²) + banho de asfalto oxidado (2,0 kg/m²) - TERRAÇO 01 | B101: 15.49 | C101: =TRIM(RIGHT(A101,LEN(A101)-FIND("@",SUBSTITUTE(A101,"-","@",LEN(A101)-LEN(SUBSTITUTE(A101,"-","")))))) -> TERRAÇO 01 | D101: =TRIM(LEFT(A101,FIND("-",A101)-1)) -> M44A | E101: 02.001.003 | F101: =B101 -> 15.49 | H101: =SUMIF($D101,H$10,$B101) -> 0 | I101: =SUMIF($D101,I$10,$B101) -> 0 | J101: =SUMIF($D101,J$10,$B101) -> 15.49 | K101: =SUMIF($D101,K$10,$B101) -> 0 | L101: =SUMIF($D101,L$10,$B101) -> 0 | M101: =SUMIF($D101,M$10,$B101) -> 0 | N101: =SUMIF($D101,N$10,$B101) -> 0 | O101: =SUMIF($D101,O$10,$B101) -> 0 | ... S101: =SUMIF($D101,S$10,$B101) -> 0
... A109: M44A - Manta asfáltica tipo IV, 4 mm A, com acabamento areia/areia aderida com asfalto oxidado (3,0 kg/m²) + banho de asfalto oxidado (2,0 kg/m²) - TERRAÇO DESCOBERTO | B109: 123.52 | C109: =TRIM(RIGHT(A109,LEN(A109)-FIND("@",SUBSTITUTE(A109,"-","@",LEN(A109)-LEN(SUBSTITUTE(A109,"-","")))))) -> TERRAÇO DESCOBERTO | D109: =TRIM(LEFT(A109,FIND("-",A109)-1)) -> M44A | E109: 02.001.003 | F109: =B109 -> 123.52 | H109: =SUMIF($D109,H$10,$B109) -> 0 | I109: =SUMIF($D109,I$10,$B109) -> 0 | J109: =SUMIF($D109,J$10,$B109) -> 123.52 | K109: =SUMIF($D109,K$10,$B109) -> 0 | L109: =SUMIF($D109,L$10,$B109) -> 0 | M109: =SUMIF($D109,M$10,$B109) -> 0 | N109: =SUMIF($D109,N$10,$B109) -> 0 | O109: =SUMIF($D109,O$10,$B109) -> 0 | ... S109: =SUMIF($D109,S$10,$B109) -> 0
A110: M44AR05 - Manta asfáltica tipo IV, 4 mm A, com acabamento areia/areia aderida com asfalto oxidado (3,0 kg/m²) + banho de asfalto oxidado (2,0 kg/m²) + pintura de proteção antirraiz sobre a proteção mecânica (0,5 L/m²) - TAMPA DE RESERVATÓRIO | B110: 2.59 | C110: =TRIM(RIGHT(A110,LEN(A110)-FIND("@",SUBSTITUTE(A110,"-","@",LEN(A110)-LEN(SUBSTITUTE(A110,"-","")))))) -> TAMPA DE RESERVATÓRIO | D110: =TRIM(LEFT(A110,FIND("-",A110)-1)) -> M44AR05 | E110: 02.001.008 | F110: =B110 -> 2.59 | G110: =B110 -> 2.59 | H110: =SUMIF($D110,H$10,$B110) -> 0 | I110: =SUMIF($D110,I$10,$B110) -> 0 | J110: =SUMIF($D110,J$10,$B110) -> 0 | K110: =SUMIF($D110,K$10,$B110) -> 0 | L110: =SUMIF($D110,L$10,$B110) -> 0 | M110: =SUMIF($D110,M$10,$B110) -> 0 | N110: =SUMIF($D110,N$10,$B110) -> 0 | O110: =SUMIF($D110,O$10,$B110) -> 0 | ... S110: =SUMIF($D110,S$10,$B110) -> 0
A111: M44AR05 - Manta asfáltica tipo IV, 4 mm A, com acabamento areia/areia aderida com asfalto oxidado (3,0 kg/m²) + banho de asfalto oxidado (2,0 kg/m²) + pintura de proteção antirraiz sobre a proteção mecânica (0,5 L/m²) - TAMPA SOB JARDIM | B111: 8.31 | C111: =TRIM(RIGHT(A111,LEN(A111)-FIND("@",SUBSTITUTE(A111,"-","@",LEN(A111)-LEN(SUBSTITUTE(A111,"-","")))))) -> TAMPA SOB JARDIM | D111: =TRIM(LEFT(A111,FIND("-",A111)-1)) -> M44AR05 | E111: 02.001.003 | F111: =B111 -> 8.31 | G111: =B111 -> 8.31 | H111: =SUMIF($D111,H$10,$B111) -> 0 | I111: =SUMIF($D111,I$10,$B111) -> 0 | J111: =SUMIF($D111,J$10,$B111) -> 0 | K111: =SUMIF($D111,K$10,$B111) -> 0 | L111: =SUMIF($D111,L$10,$B111) -> 0 | M111: =SUMIF($D111,M$10,$B111) -> 0 | N111: =SUMIF($D111,N$10,$B111) -> 0 | O111: =SUMIF($D111,O$10,$B111) -> 0 | ... S111: =SUMIF($D111,S$10,$B111) -> 0
A112: M44A + M44AE2 - Manta asfáltica tipo IV, 4 mm A, com acabamento areia/areia + manta asfáltica tipo IV, 4 mm A, com acabamento areia/areia aderida com asfalto oxidado (3,0 kg/m²) + banho de asfalto oxidado (2,0 kg/m²) + membrana de polímero acrílico com cimento e fibras para combater eflorescência (2,0 kg/m²) - PISCINA | B112: 50.04 | C112: =TRIM(RIGHT(A112,LEN(A112)-FIND("@",SUBSTITUTE(A112,"-","@",LEN(A112)-LEN(SUBSTITUTE(A112,"-","")))))) -> PISCINA | D112: =TRIM(LEFT(A112,FIND("-",A112)-1)) -> M44A + M44AE2 | E112: 02.001.004 | F112: =B112 -> 50.04 | H112: =SUMIF($D112,H$10,$B112) -> 0 | I112: =SUMIF($D112,I$10,$B112) -> 0 | J112: =SUMIF($D112,J$10,$B112) -> 0 | K112: =SUMIF($D112,K$10,$B112) -> 0 | L112: =SUMIF($D112,L$10,$B112) -> 0 | M112: =SUMIF($D112,M$10,$B112) -> 0 | N112: =SUMIF($D112,N$10,$B112) -> 0 | O112: =SUMIF($D112,O$10,$B112) -> 0 | ... S112: =SUMIF($D112,S$10,$B112) -> 50.04
A113: M44A - Manta asfáltica tipo IV, 4 mm A, com acabamento areia/areia aderida com asfalto oxidado (3,0 kg/m²) + banho de asfalto oxidado (2,0 kg/m²) - PRAÇA | B113: 22.6 | C113: =TRIM(RIGHT(A113,LEN(A113)-FIND("@",SUBSTITUTE(A113,"-","@",LEN(A113)-LEN(SUBSTITUTE(A113,"-","")))))) -> PRAÇA | D113: =TRIM(LEFT(A113,FIND("-",A113)-1)) -> M44A | E113: 02.001.004 | F113: =B113 -> 22.6 | H113: =SUMIF($D113,H$10,$B113) -> 0 | I113: =SUMIF($D113,I$10,$B113) -> 0 | J113: =SUMIF($D113,J$10,$B113) -> 22.6 | K113: =SUMIF($D113,K$10,$B113) -> 0 | L113: =SUMIF($D113,L$10,$B113) -> 0 | M113: =SUMIF($D113,M$10,$B113) -> 0 | N113: =SUMIF($D113,N$10,$B113) -> 0 | O113: =SUMIF($D113,O$10,$B113) -> 0 | ... S113: =SUMIF($D113,S$10,$B113) -> 0
A114: M44A + M44AE2 - Manta asfáltica tipo IV, 4 mm A, com acabamento areia/areia + manta asfáltica tipo IV, 4 mm A, com acabamento areia/areia aderida com asfalto oxidado (3,0 kg/m²) + banho de asfalto oxidado (2,0 kg/m²) + membrana de polímero acrílico com ci - PRAINHA | B114: 3.64 | C114: =TRIM(RIGHT(A114,LEN(A114)-FIND("@",SUBSTITUTE(A114,"-","@",LEN(A114)-LEN(SUBSTITUTE(A114,"-","")))))) -> PRAINHA | D114: =TRIM(LEFT(A114,FIND("-",A114)-1)) -> M44A + M44AE2 | E114: 02.001.003 | F114: =B114 -> 3.64 | H114: =SUMIF($D114,H$10,$B114) -> 0 | I114: =SUMIF($D114,I$10,$B114) -> 0 | J114: =SUMIF($D114,J$10,$B114) -> 0 | K114: =SUMIF($D114,K$10,$B114) -> 0 | L114: =SUMIF($D114,L$10,$B114) -> 0 | M114: =SUMIF($D114,M$10,$B114) -> 0 | N114: =SUMIF($D114,N$10,$B114) -> 0 | O114: =SUMIF($D114,O$10,$B114) -> 0 | ... S114: =SUMIF($D114,S$10,$B114) -> 3.64
A115: C3E3 - Argamassa polimérica rígida (3,0 kg/m²) + membrana de polímero acrílico com cimento e fibras, estruturada com tela de poliéster nos pontos críticos (3,0 kg/m²) - RESERVATÓRIO ESCOAMENTO | B115: 27.76 | C115: =TRIM(RIGHT(A115,LEN(A115)-FIND("@",SUBSTITUTE(A115,"-","@",LEN(A115)-LEN(SUBSTITUTE(A115,"-","")))))) -> RESERVATÓRIO ESCOAMENTO | D115: =TRIM(LEFT(A115,FIND("-",A115)-1)) -> C3E3 | E115: 02.001.008 | F115: =B115 -> 27.76 | H115: =SUMIF($D115,H$10,$B115) -> 0 | I115: =SUMIF($D115,I$10,$B115) -> 0 | J115: =SUMIF($D115,J$10,$B115) -> 0 | K115: =SUMIF($D115,K$10,$B115) -> 0 | L115: =SUMIF($D115,L$10,$B115) -> 27.76 | M115: =SUMIF($D115,M$10,$B115) -> 0 | N115: =SUMIF($D115,N$10,$B115) -> 0 | O115: =SUMIF($D115,O$10,$B115) -> 0 | ... S115: =SUMIF($D115,S$10,$B115) -> 0
A116: C3E3 - Argamassa polimérica rígida (3,0 kg/m²) + membrana de polímero acrílico com cimento e fibras, estruturada com tela de poliéster nos pontos críticos (3,0 kg/m²) - RESERVATÓRIO INFERIOR 2 | B116: 51.23 | C116: =TRIM(RIGHT(A116,LEN(A116)-FIND("@",SUBSTITUTE(A116,"-","@",LEN(A116)-LEN(SUBSTITUTE(A116,"-","")))))) -> RESERVATÓRIO INFERIOR 2 | D116: =TRIM(LEFT(A116,FIND("-",A116)-1)) -> C3E3 | E116: 02.001.008 | F116: =B116 -> 51.23 | H116: =SUMIF($D116,H$10,$B116) -> 0 | I116: =SUMIF($D116,I$10,$B116) -> 0 | J116: =SUMIF($D116,J$10,$B116) -> 0 | K116: =SUMIF($D116,K$10,$B116) -> 0 | L116: =SUMIF($D116,L$10,$B116) -> 51.23 | M116: =SUMIF($D116,M$10,$B116) -> 0 | N116: =SUMIF($D116,N$10,$B116) -> 0 | O116: =SUMIF($D116,O$10,$B116) -> 0 | ... S116: =SUMIF($D116,S$10,$B116) -> 0
A117: C3E3 - Argamassa polimérica rígida (3,0 kg/m²) + membrana de polímero acrílico com cimento e fibras, estruturada com tela de poliéster nos pontos críticos (3,0 kg/m²) - RESERVATÓRIO REAPROV. PLUVIAL | B117: 27.75 | C117: =TRIM(RIGHT(A117,LEN(A117)-FIND("@",SUBSTITUTE(A117,"-","@",LEN(A117)-LEN(SUBSTITUTE(A117,"-","")))))) -> RESERVATÓRIO REAPROV. PLUVIAL | D117: =TRIM(LEFT(A117,FIND("-",A117)-1)) -> C3E3 | E117: 02.001.008 | F117: =B117 -> 27.75 | H117: =SUMIF($D117,H$10,$B117) -> 0 | I117: =SUMIF($D117,I$10,$B117) -> 0 | J117: =SUMIF($D117,J$10,$B117) -> 0 | K117: =SUMIF($D117,K$10,$B117) -> 0 | L117: =SUMIF($D117,L$10,$B117) -> 27.75 | M117: =SUMIF($D117,M$10,$B117) -> 0 | N117: =SUMIF($D117,N$10,$B117) -> 0 | O117: =SUMIF($D117,O$10,$B117) -> 0 | ... S117: =SUMIF($D117,S$10,$B117) -> 0
A118: C3 - Argamassa polimérica rígida, estruturada com tela de poliéster nos pontos críticos (3,0 kg/m²) - SALA PRESS. | B118: 3.35 | C118: =TRIM(RIGHT(A118,LEN(A118)-FIND("@",SUBSTITUTE(A118,"-","@",LEN(A118)-LEN(SUBSTITUTE(A118,"-","")))))) -> SALA PRESS. | D118: =TRIM(LEFT(A118,FIND("-",A118)-1)) -> C3 | E118: 02.001.005 | F118: =B118 -> 3.35 | H118: =SUMIF($D118,H$10,$B118) -> 0 | I118: =SUMIF($D118,I$10,$B118) -> 0 | J118: =SUMIF($D118,J$10,$B118) -> 0 | K118: =SUMIF($D118,K$10,$B118) -> 3.35 | L118: =SUMIF($D118,L$10,$B118) -> 0 | M118: =SUMIF($D118,M$10,$B118) -> 0 | N118: =SUMIF($D118,N$10,$B118) -> 0 | O118: =SUMIF($D118,O$10,$B118) -> 0 | ... S118: =SUMIF($D118,S$10,$B118) -> 0
A119: M44A - Manta asfáltica tipo IV, 4 mm A, com acabamento areia/areia aderida com asfalto oxidado (3,0 kg/m²) + banho de asfalto oxidado (2,0 kg/m²) - TERRAÇO | B119: 4.54 | C119: =TRIM(RIGHT(A119,LEN(A119)-FIND("@",SUBSTITUTE(A119,"-","@",LEN(A119)-LEN(SUBSTITUTE(A119,"-","")))))) -> TERRAÇO | D119: =TRIM(LEFT(A119,FIND("-",A119)-1)) -> M44A | E119: 02.001.003 | F119: =B119 -> 4.54 | H119: =SUMIF($D119,H$10,$B119) -> 0 | I119: =SUMIF($D119,I$10,$B119) -> 0 | J119: =SUMIF($D119,J$10,$B119) -> 4.54 | K119: =SUMIF($D119,K$10,$B119) -> 0 | L119: =SUMIF($D119,L$10,$B119) -> 0 | M119: =SUMIF($D119,M$10,$B119) -> 0 | N119: =SUMIF($D119,N$10,$B119) -> 0 | O119: =SUMIF($D119,O$10,$B119) -> 0 | ... S119: =SUMIF($D119,S$10,$B119) -> 0
A120: E3 - Membrana de polímero acrílico com cimento e fibras, estruturada com tela de poliéster nos pontos críticos (3,0 kg/m²) - TERRAÇO 01 | B120: 35.56 | C120: =TRIM(RIGHT(A120,LEN(A120)-FIND("@",SUBSTITUTE(A120,"-","@",LEN(A120)-LEN(SUBSTITUTE(A120,"-","")))))) -> TERRAÇO 01 | D120: =TRIM(LEFT(A120,FIND("-",A120)-1)) -> E3 | E120: 02.001.003 | F120: =B120 -> 35.56 | H120: =SUMIF($D120,H$10,$B120) -> 35.56 | I120: =SUMIF($D120,I$10,$B120) -> 0 | J120: =SUMIF($D120,J$10,$B120) -> 0 | K120: =SUMIF($D120,K$10,$B120) -> 0 | L120: =SUMIF($D120,L$10,$B120) -> 0 | M120: =SUMIF($D120,M$10,$B120) -> 0 | N120: =SUMIF($D120,N$10,$B120) -> 0 | O120: =SUMIF($D120,O$10,$B120) -> 0 | ... S120: =SUMIF($D120,S$10,$B120) -> 0
A121: M44A - Manta asfáltica tipo IV, 4 mm A, com acabamento areia/areia aderida com asfalto oxidado (3,0 kg/m²) + banho de asfalto oxidado (2,0 kg/m²) - TERRAÇO 01 | B121: 6.17 | C121: =TRIM(RIGHT(A121,LEN(A121)-FIND("@",SUBSTITUTE(A121,"-","@",LEN(A121)-LEN(SUBSTITUTE(A121,"-","")))))) -> TERRAÇO 01 | D121: =TRIM(LEFT(A121,FIND("-",A121)-1)) -> M44A | E121: 02.001.003 | F121: =B121 -> 6.17 | H121: =SUMIF($D121,H$10,$B121) -> 0 | I121: =SUMIF($D121,I$10,$B121) -> 0 | J121: =SUMIF($D121,J$10,$B121) -> 6.17 | K121: =SUMIF($D121,K$10,$B121) -> 0 | L121: =SUMIF($D121,L$10,$B121) -> 0 | M121: =SUMIF($D121,M$10,$B121) -> 0 | N121: =SUMIF($D121,N$10,$B121) -> 0 | O121: =SUMIF($D121,O$10,$B121) -> 0 | ... S121: =SUMIF($D121,S$10,$B121) -> 0
A122: E3 - Membrana de polímero acrílico com cimento e fibras, estruturada com tela de poliéster nos pontos críticos (3,0 kg/m²) - TERRAÇO 02 | B122: 59.72 | C122: =TRIM(RIGHT(A122,LEN(A122)-FIND("@",SUBSTITUTE(A122,"-","@",LEN(A122)-LEN(SUBSTITUTE(A122,"-","")))))) -> TERRAÇO 02 | D122: =TRIM(LEFT(A122,FIND("-",A122)-1)) -> E3 | E122: 02.001.003 | F122: =B122 -> 59.72 | H122: =SUMIF($D122,H$10,$B122) -> 59.72 | I122: =SUMIF($D122,I$10,$B122) -> 0 | J122: =SUMIF($D122,J$10,$B122) -> 0 | K122: =SUMIF($D122,K$10,$B122) -> 0 | L122: =SUMIF($D122,L$10,$B122) -> 0 | M122: =SUMIF($D122,M$10,$B122) -> 0 | N122: =SUMIF($D122,N$10,$B122) -> 0 | O122: =SUMIF($D122,O$10,$B122) -> 0 | ... S122: =SUMIF($D122,S$10,$B122) -> 0
A123: E3 - Membrana de polímero acrílico com cimento e fibras, estruturada com tela de poliéster nos pontos críticos (3,0 kg/m²)E3 - Membrana de polímero acrílico com cimento e fibras, estruturada com tela de poliéster nos pontos críticos (3,0 kg/m²) - TERRAÇO 02 | B123: 3.23 | C123: =TRIM(RIGHT(A123,LEN(A123)-FIND("@",SUBSTITUTE(A123,"-","@",LEN(A123)-LEN(SUBSTITUTE(A123,"-","")))))) -> TERRAÇO 02 | D123: =TRIM(LEFT(A123,FIND("-",A123)-1)) -> E3 | E123: 02.001.003 | F123: =B123 -> 3.23 | H123: =SUMIF($D123,H$10,$B123) -> 3.23 | I123: =SUMIF($D123,I$10,$B123) -> 0 | J123: =SUMIF($D123,J$10,$B123) -> 0 | K123: =SUMIF($D123,K$10,$B123) -> 0 | L123: =SUMIF($D123,L$10,$B123) -> 0 | M123: =SUMIF($D123,M$10,$B123) -> 0 | N123: =SUMIF($D123,N$10,$B123) -> 0 | O123: =SUMIF($D123,O$10,$B123) -> 0 | ... S123: =SUMIF($D123,S$10,$B123) -> 0
... A145: E3 - Membrana de polímero acrílico com cimento e fibras, estruturada com tela de poliéster nos pontos críticos (3,0 kg/m²) - WC PNE 04 | B145: 1.37 | C145: =TRIM(RIGHT(A145,LEN(A145)-FIND("@",SUBSTITUTE(A145,"-","@",LEN(A145)-LEN(SUBSTITUTE(A145,"-","")))))) -> WC PNE 04 | D145: =TRIM(LEFT(A145,FIND("-",A145)-1)) -> E3 | E145: 02.001.005 | F145: =B145 -> 1.37 | H145: =SUMIF($D145,H$10,$B145) -> 1.37 | I145: =SUMIF($D145,I$10,$B145) -> 0 | J145: =SUMIF($D145,J$10,$B145) -> 0 | K145: =SUMIF($D145,K$10,$B145) -> 0 | L145: =SUMIF($D145,L$10,$B145) -> 0 | M145: =SUMIF($D145,M$10,$B145) -> 0 | N145: =SUMIF($D145,N$10,$B145) -> 0 | O145: =SUMIF($D145,O$10,$B145) -> 0 | ... S145: =SUMIF($D145,S$10,$B145) -> 0
A146: ="TOTAL GERAL - "&A9 -> TOTAL GERAL - IMPERMEABILIZAÇÃO | B146: =SUM(B13:B145) -> 4984.69 | F146: =SUM(F13:F145) -> 4984.69 | G146: =SUM(G13:G145) -> 14.12 | H146: =SUM(H13:H145) -> 2876.1 | I146: =SUM(I13:I145) -> 130.83 | J146: =SUM(J13:J145) -> 780.24 | K146: =SUM(K13:K145) -> 445.18 | L146: =SUM(L13:L145) -> 163.53 | M146: =SUM(M13:M145) -> 309.19 | ... S146: =SUM(S13:S145) -> 128.48
H147: =IF(H146=D7,"okay","rever") -> okay | I147: =IF(I146=E7,"okay","rever") -> okay | J147: =IF(J146=F7,"okay","rever") -> okay | K147: =IF(K146=G7,"okay","rever") -> okay | L147: =IF(L146=H7,"okay","rever") -> okay | M147: =IF(M146=I7,"okay","rever") -> okay | N147: =IF(N146=J7,"okay","rever") -> okay | O147: =IF(O146=K7,"okay","rever") -> okay | ... S147: =IF(S146=O7,"okay","rever") -> okay

Sheet LOUÇAS E METAIS
D1: Projeto | E1: ='Obra '!D1 -> Caio Prado
D2: Empresa | E2: ='Obra '!D2 -> Indepy
D3: Origem
D4: Revisão | E4: ='Obra '!D3 -> R00 - Larissa
C5: LEVANTAMENTO LOUÇAS E METAIS
C6: Aplicação | D6: Descrição do Material | E6: Un. | F6: Total | H6: Qtde/ Pavimento
H7: ='Obra '!$B$17 -> Subsolo | I7: ='Obra '!$B$18 -> Térreo | J7: ='Obra '!$B$19 -> 1º Pavimento - HMP | K7: ='Obra '!$B$20 -> 2º Pavimento - HMP | L7: ='Obra '!$B$21 -> 3º Pavimento - R2V / HMP | M7: ='Obra '!$B$22 -> 5º/ 7º/ 9º E 11º Pavimento - R2V | N7: ='Obra '!$B$23 -> 4º/ 6º/ 8º/ 10º E 12º Pavimento - R2V | O7: ='Obra '!$B$24 -> 13º Pavimento - LAZER | P7: ='Obra '!$B$25 -> 14º E 16º Pavimento - R2V | Q7: ='Obra '!$B$26 -> 15º E 17º Pavimento - R2V | R7: ='Obra '!$B$27 -> 18º Pavimento - LAZER | S7: ='Obra '!$B$28 -> BARRILETE | T7: Custo do Item | U7: Custo Total
H8: 1 | I8: 1 | J8: 1 | K8: 1 | L8: 1 | M8: 4 | N8: 5 | O8: 1 | P8: 2 | Q8: 2 | R8: 1 | S8: 1
C9: louças e aparelhos sanitários | D9: Banheiro - Bacia Sanitária / Caixa Acoplada | E9: un | F9: =SUMPRODUCT($H$8:$Q$8,$H9:$Q9) -> 151 | I9: 1 | J9: 6 | K9: 13 | L9: 11 | M9: 11 | N9: 11 | O9: 1 | P9: 5 | Q9: 5 | T9: 952.5988 | U9: =SUMPRODUCT(H9:S9,$H$8:$S$8)*T9 -> 143842.42
C10: louças e aparelhos sanitários | D10: Banheiro - Bacia Sanitária PNE | E10: un | F10: =SUMPRODUCT($H$8:$Q$8,$H10:$Q10) -> 8 | H10: 2 | I10: 3 | J10: 1 | O10: 2 | R10: 2 | T10: 1166.57 | U10: =SUMPRODUCT(H10:S10,$H$8:$S$8)*T10 -> 11665.7
C11: louças e aparelhos sanitários | D11: Banheiro - Cuba de Sobrepor - PNE | E11: un | F11: =SUMPRODUCT($H$8:$Q$8,$H11:$Q11) -> 0 | T11: 492.89 | U11: =SUMPRODUCT(H11:S11,$H$8:$S$8)*T11 -> 0
C12: louças e aparelhos sanitários | D12: Banheiro - Cuba | E12: un | F12: =SUMPRODUCT($H$8:$Q$8,$H12:$Q12) -> 3 | H12: 2 | O12: 1 | R12: 1 | T12: 492.89 | U12: =SUMPRODUCT(H12:S12,$H$8:$S$8)*T12 -> 1971.56
C13: louças e aparelhos sanitários | D13: Banheiro - Lavatorio / Suspenso | E13: un | F13: =SUMPRODUCT($H$8:$Q$8,$H13:$Q13) -> 1 | I13: 1 | T13: 683.162 | U13: =SUMPRODUCT(H13:S13,$H$8:$S$8)*T13 -> 683.162
C14: louças e aparelhos sanitários | D14: Banheiro - Lavatorio PNE | E14: un | F14: =SUMPRODUCT($H$8:$Q$8,$H14:$Q14) -> 8 | H14: 2 | I14: 3 | J14: 1 | O14: 2 | R14: 2 | T14: 694.262 | U14: =SUMPRODUCT(H14:S14,$H$8:$S$8)*T14 -> 6942.62
C15: louças e aparelhos sanitários | D15: Cuba Pia Cozinha - Lazer | E15: un | F15: =SUMPRODUCT($H$8:$Q$8,$H15:$Q15) -> 0 | T15: 1981.262 | U15: =SUMPRODUCT(H15:S15,$H$8:$S$8)*T15 -> 0
C16: louças e aparelhos sanitários | D16: Cozinha - Cuba / Inox | E16: un | F16: =SUMPRODUCT($H$8:$Q$8,$H16:$Q16) -> 6 | H16: 1 | I16: 2 | O16: 3 | T16: 809.262 | U16: =SUMPRODUCT(H16:S16,$H$8:$S$8)*T16 -> 4855.572
C17: louças e aparelhos sanitários | D17: Cozinha - Cuba Dupla / Inox | E17: un | F17: =SUMPRODUCT($H$8:$Q$8,$H17:$Q17) -> 0 | U17: =SUMPRODUCT(H17:S17,$H$8:$S$8)*T17 -> 0
C18: louças e aparelhos sanitários | D18: Cozinha - Pia Sintetica | E18: un | F18: =SUMPRODUCT($H$8:$Q$8,$H18:$Q18) -> 0 | U18: =SUMPRODUCT(H18:S18,$H$8:$S$8)*T18 -> 0
C19: louças e aparelhos sanitários | D19: Tanque Louça Suspenso | E19: un | F19: =SUMPRODUCT($H$8:$Q$8,$H19:$Q19) -> 0 | T19: 558.362 | U19: =SUMPRODUCT(H19:S19,$H$8:$S$8)*T19 -> 0
C20: louças e aparelhos sanitários | D20: Tanque Louça c/ Coluna | E20: un | F20: =SUMPRODUCT($H$8:$Q$8,$H20:$Q20) -> 0 | U20: =SUMPRODUCT(H20:S20,$H$8:$S$8)*T20 -> 0
C21: louças e aparelhos sanitários | D21: Tanque Fibra | E21: un | F21: =SUMPRODUCT($H$8:$Q$8,$H21:$Q21) -> 0 | U21: =SUMPRODUCT(H21:S21,$H$8:$S$8)*T21 -> 0
C22: louças e aparelhos sanitários | D22: Tanque Inox | E22: un | F22: =SUMPRODUCT($H$8:$Q$8,$H22:$Q22) -> 1 | H22: 1 | T22: 834.262 | U22: =SUMPRODUCT(H22:S22,$H$8:$S$8)*T22 -> 834.262
C23: louças e aparelhos sanitários | D23: Mictório Louça | E23: un | F23: =SUMPRODUCT($H$8:$Q$8,$H23:$Q23) -> 0 | T23: 1063 | U23: =SUMPRODUCT(H23:S23,$H$8:$S$8)*T23 -> 0
C24: louças e aparelhos sanitários | D24: Mictório Inox | E24: un | F24: =SUMPRODUCT($H$8:$Q$8,$H24:$Q24) -> 0 | U24: =SUMPRODUCT(H24:S24,$H$8:$S$8)*T24 -> 0
C25: louças e aparelhos sanitários | D25: Cadeira PNE para ducha | E25: un | F25: =SUMPRODUCT($H$8:$Q$8,$H25:$Q25) -> 2 | H25: 2 | T25: 454 | U25: =SUMPRODUCT(H25:S25,$H$8:$S$8)*T25 -> 908
C26: louças e aparelhos sanitários | D26: Churrasqueiras kit Gourmet Médio Inox 304 | E26: un | F26: =SUMPRODUCT($H$8:$Q$8,$H26:$Q26) -> 1 | O26: 1 | T26: 3889 | U26: =SUMPRODUCT(H26:S26,$H$8:$S$8)*T26 -> 3889
C27: louças e aparelhos sanitários | D27: Churrasqueira Pré Frabricada | E27: un | F27: =SUMPRODUCT($H$8:$Q$8,$H27:$Q27) -> 0 | T27: 1577 | U27: =SUMPRODUCT(H27:S27,$H$8:$S$8)*T27 -> 0
C28: louças e aparelhos sanitários | D28: Banheira de Hidromassagem | E28: un | F28: =SUMPRODUCT($H$8:$Q$8,$H28:$Q28) -> 0 | U28: =SUMPRODUCT(H28:S28,$H$8:$S$8)*T28 -> 0
C29: metais para acabamentos | D29: Considerada somente o registro | E29: un | F29: =SUMPRODUCT($H$8:$Q$8,$H29:$Q29) -> 294 | J29: 12 | K29: 26 | L29: 22 | M29: 22 | N29: 22 | P29: 10 | Q29: 8 | U29: =SUMPRODUCT(H29:S29,$H$8:$S$8)*T29 -> 0 | V29: Considerado junto dos registro comuns
C30: metais para acabamentos | D30: Exastor Mecânico | E30: un | F30: =SUMPRODUCT($H$8:$Q$8,$H30:$Q30) -> 0 | T30: 836 | U30: =SUMPRODUCT(H30:S30,$H$8:$S$8)*T30 -> 0 | V30: Considerado em climatização
C31: metais para acabamentos | D31: Acessórios de Banheiro/Lavabo | E31: un | F31: =SUMPRODUCT($H$8:$Q$8,$H31:$Q31) -> 9 | H31: 2 | I31: 4 | O31: 3 | R31: 3 | T31: 1183.51 | U31: =SUMPRODUCT(H31:S31,$H$8:$S$8)*T31 -> 14202.12
C32: metais para acabamentos | D32: Chuveiro Elétrico | E32: un | F32: =SUMPRODUCT($H$8:$Q$8,$H32:$Q32) -> 2 | H32: 2 | T32: 400 | U32: =SUMPRODUCT(H32:S32,$H$8:$S$8)*T32 -> 800
C33: metais para acabamentos | D33: Ducha | E33: un | F33: =SUMPRODUCT($H$8:$Q$8,$H33:$Q33) -> 0 | R33: 1 | T33: 1196.32 | U33: =SUMPRODUCT(H33:S33,$H$8:$S$8)*T33 -> 1196.32
C34: metais para acabamentos | D34: Torneira de Jardins | E34: un | F34: =SUMPRODUCT($H$8:$Q$8,$H34:$Q34) -> 12 | I34: 5 | L34: 1 | O34: 2 | P34: 2 | R34: 3 | T34: 72 | U34: =SUMPRODUCT(H34:S34,$H$8:$S$8)*T34 -> 1080
C35: metais para acabamentos | D35: Torneira misturador pia cozinha | E35: un | F35: =SUMPRODUCT($H$8:$Q$8,$H35:$Q35) -> 6 | H35: =SUM(H$15:H$18) -> 1 | I35: =SUM(I$15:I$18) -> 2 | J35: =SUM(J$15:J$18) -> 0 | K35: =SUM(K$15:K$18) -> 0 | L35: =SUM(L$15:L$18) -> 0 | M35: =SUM(M$15:M$18) -> 0 | N35: =SUM(N$15:N$18) -> 0 | O35: =SUM(O$15:O$18) -> 3 | ... S35: =SUM(S$15:S$18) -> 0 | T35: 1054.93 | U35: =SUMPRODUCT(H35:S35,$H$8:$S$8)*T35 -> 6329.58
C36: metais para acabamentos | D36: Torneira tanque | E36: un | F36: =SUMPRODUCT($H$8:$Q$8,$H36:$Q36) -> 1 | H36: =SUM(H$19:H$22) -> 1 | I36: =SUM(I$19:I$22) -> 0 | J36: =SUM(J$19:J$22) -> 0 | K36: =SUM(K$19:K$22) -> 0 | L36: =SUM(L$19:L$22) -> 0 | M36: =SUM(M$19:M$22) -> 0 | N36: =SUM(N$19:N$22) -> 0 | O36: =SUM(O$19:O$22) -> 0 | ... S36: =SUM(S$19:S$22) -> 0 | T36: 150 | U36: =SUMPRODUCT(H36:S36,$H$8:$S$8)*T36 -> 150
C37: metais para acabamentos | D37: Torneira Lavatório mesa | E37: un | F37: =SUMPRODUCT($H$8:$Q$8,$H37:$Q37) -> 12 | H37: =SUM(H$11:H$14) -> 4 | I37: =SUM(I$11:I$14) -> 4 | J37: =SUM(J$11:J$14) -> 1 | K37: =SUM(K$11:K$14) -> 0 | L37: =SUM(L$11:L$14) -> 0 | M37: =SUM(M$11:M$14) -> 0 | N37: =SUM(N$11:N$14) -> 0 | O37: =SUM(O$11:O$14) -> 3 | ... S37: =SUM(S$11:S$14) -> 0 | T37: 350 | U37: =SUMPRODUCT(H37:S37,$H$8:$S$8)*T37 -> 5250
C38: metais para acabamentos | D38: Barra de apoio PNE | E38: un | F38: =SUMPRODUCT($H$8:$Q$8,$H38:$Q38) -> 20 | H38: =H$10*2+H$25*2 -> 8 | I38: =I$10*2+I$25*2 -> 6 | J38: =J$10*2+J$25*2 -> 2 | K38: =K$10*2+K$25*2 -> 0 | L38: =L$10*2+L$25*2 -> 0 | M38: =M$10*2+M$25*2 -> 0 | N38: =N$10*2+N$25*2 -> 0 | O38: =O$10*2+O$25*2 -> 4 | ... S38: =S$10*2+S$25*2 -> 0 | T38: 44 | U38: =SUMPRODUCT(H38:S38,$H$8:$S$8)*T38 -> 1056
C39: metais para acabamentos | D39: Acabamento de Registro Comum | E39: un | F39: =SUMPRODUCT($H$8:$Q$8,$H39:$Q39) -> 460 | H39: =SUM(H$16:H$22,H$9:H$10,H29) -> 4 | I39: =SUM(I$16:I$22,I$9:I$10,I29) -> 6 | J39: =SUM(J$16:J$22,J$9:J$10,J29) -> 19 | K39: =SUM(K$16:K$22,K$9:K$10,K29) -> 39 | L39: =SUM(L$16:L$22,L$9:L$10,L29) -> 33 | M39: =SUM(M$16:M$22,M$9:M$10,M29) -> 33 | N39: =SUM(N$16:N$22,N$9:N$10,N29) -> 33 | O39: =SUM(O$16:O$22,O$9:O$10,O29) -> 6 | ... S39: =SUM(S$16:S$22,S$9:S$10,S29) -> 0 | T39: 176 | U39: =SUMPRODUCT(H39:S39,$H$8:$S$8)*T39 -> 81312
C40: metais para acabamentos | D40: Acabamento de Registro Pressão | E40: un | F40: =SUMPRODUCT($H$8:$Q$8,$H40:$Q40) -> 2 | H40: =H32 -> 2 | I40: =I32 -> 0 | J40: =J32 -> 0 | K40: =K32 -> 0 | L40: =L32 -> 0 | M40: =M32 -> 0 | N40: =N32 -> 0 | O40: =O32 -> 0 | ... S40: =S32 -> 0 | T40: 240 | U40: =SUMPRODUCT(H40:S40,$H$8:$S$8)*T40 -> 480
C41: metais para acabamentos | D41: Sifão ajustável multiuso | E41: un | F41: =SUMPRODUCT($H$8:$Q$8,$H41:$Q41) -> 21 | H41: =SUM(H$11:H$25) -> 8 | I41: =SUM(I$11:I$25) -> 6 | J41: =SUM(J$11:J$25) -> 1 | K41: =SUM(K$11:K$25) -> 0 | L41: =SUM(L$11:L$25) -> 0 | M41: =SUM(M$11:M$25) -> 0 | N41: =SUM(N$11:N$25) -> 0 | O41: =SUM(O$11:O$25) -> 6 | ... S41: =SUM(S$11:S$25) -> 0 | U41: =SUMPRODUCT(H41:J41,$H$8:$J$8)*T41 -> 0 | W41: Está nas composições
C42: metais para acabamentos | D42: Anel de vedação, 100 mm, para saíde de bacia sanitária | E42: un | F42: =SUMPRODUCT($H$8:$Q$8,$H42:$Q42) -> 161 | H42: =SUM(H$9:H$10,H$23:H$25) -> 4 | I42: =SUM(I$9:I$10,I$23:I$25) -> 4 | J42: =SUM(J$9:J$10,J$23:J$25) -> 7 | K42: =SUM(K$9:K$10,K$23:K$25) -> 13 | L42: =SUM(L$9:L$10,L$23:L$25) -> 11 | M42: =SUM(M$9:M$10,M$23:M$25) -> 11 | N42: =SUM(N$9:N$10,N$23:N$25) -> 11 | O42: =SUM(O$9:O$10,O$23:O$25) -> 3 | ... S42: =SUM(S$9:S$10,S$23:S$25) -> 0 | U42: =SUMPRODUCT(H42:J42,$H$8:$J$8)*T42 -> 0 | W42: Está nas composições
C43: metais para acabamentos | D43: Engate/ rabicho flexível inóx 1/2"x40mm | E43: un | F43: =SUMPRODUCT($H$8:$Q$8,$H43:$Q43) -> 161 | H43: =SUM(H$9:H$10,H$23:H$25) -> 4 | I43: =SUM(I$9:I$10,I$23:I$25) -> 4 | J43: =SUM(J$9:J$10,J$23:J$25) -> 7 | K43: =SUM(K$9:K$10,K$23:K$25) -> 13 | L43: =SUM(L$9:L$10,L$23:L$25) -> 11 | M43: =SUM(M$9:M$10,M$23:M$25) -> 11 | N43: =SUM(N$9:N$10,N$23:N$25) -> 11 | O43: =SUM(O$9:O$10,O$23:O$25) -> 3 | ... S43: =SUM(S$9:S$10,S$23:S$25) -> 0 | U43: =SUMPRODUCT(H43:J43,$H$8:$J$8)*T43 -> 0 | W43: Está nas composições
C44: metais para acabamentos | D44: Parafuso niquelado para fixação de bacia sanitária - tamanho S-10 | E44: un | F44: =SUMPRODUCT($H$8:$Q$8,$H44:$Q44) -> 636 | H44: =SUM(H$9:H$10)*4 -> 8 | I44: =SUM(I$9:I$10)*4 -> 16 | J44: =SUM(J$9:J$10)*4 -> 28 | K44: =SUM(K$9:K$10)*4 -> 52 | L44: =SUM(L$9:L$10)*4 -> 44 | M44: =SUM(M$9:M$10)*4 -> 44 | N44: =SUM(N$9:N$10)*4 -> 44 | O44: =SUM(O$9:O$10)*4 -> 12 | ... S44: =SUM(S$9:S$10)*4 -> 0 | U44: =SUMPRODUCT(H44:J44,$H$8:$J$8)*T44 -> 0 | W44: Está nas composições
C45: metais para acabamentos | D45: Válvula de escoamento para lavatório | E45: un | F45: =SUMPRODUCT($H$8:$Q$8,$H45:$Q45) -> 12 | H45: =SUM(H$11:H$14) -> 4 | I45: =SUM(I$11:I$14) -> 4 | J45: =SUM(J$11:J$14) -> 1 | K45: =SUM(K$11:K$14) -> 0 | L45: =SUM(L$11:L$14) -> 0 | M45: =SUM(M$11:M$14) -> 0 | N45: =SUM(N$11:N$14) -> 0 | O45: =SUM(O$11:O$14) -> 3 | ... S45: =SUM(S$11:S$14) -> 0 | U45: =SUMPRODUCT(H45:J45,$H$8:$J$8)*T45 -> 0 | W45: Está nas composições
C46: metais para acabamentos | D46: Válvula de escoamento para Pia | E46: un | F46: =SUMPRODUCT($H$8:$Q$8,$H46:$Q46) -> 6 | H46: =SUM(H$16:H$18) -> 1 | I46: =SUM(I$16:I$18) -> 2 | J46: =SUM(J$16:J$18) -> 0 | K46: =SUM(K$16:K$18) -> 0 | L46: =SUM(L$16:L$18) -> 0 | M46: =SUM(M$16:M$18) -> 0 | N46: =SUM(N$16:N$18) -> 0 | O46: =SUM(O$16:O$18) -> 3 | ... S46: =SUM(S$16:S$18) -> 0 | U46: =SUMPRODUCT(H46:J46,$H$8:$J$8)*T46 -> 0 | W46: Está nas composições
C47: metais para acabamentos | D47: Válvula de escoamento para tanque | E47: un | F47: =SUMPRODUCT($H$8:$Q$8,$H47:$Q47) -> 1 | H47: =SUM(H$19:H$22) -> 1 | I47: =SUM(I$19:I$22) -> 0 | J47: =SUM(J$19:J$22) -> 0 | K47: =SUM(K$19:K$22) -> 0 | L47: =SUM(L$19:L$22) -> 0 | M47: =SUM(M$19:M$22) -> 0 | N47: =SUM(N$19:N$22) -> 0 | O47: =SUM(O$19:O$22) -> 0 | ... S47: =SUM(S$19:S$22) -> 0 | U47: =SUMPRODUCT(H47:J47,$H$8:$J$8)*T47 -> 0 | W47: Está nas composições
C48: metais para acabamentos | D48: Ducha higienica | F48: =SUMPRODUCT($H$8:$Q$8,$H48:$Q48) -> 0 | T48: 1196.32 | U48: =SUMPRODUCT(H48:Q48,$H$8:$Q$8)*T48 -> 0
C49: artefatos em pedra | D49: Bancada Cozinha | E49: m2 | F49: =SUMPRODUCT($H$8:$Q$8,$H49:$Q49) -> 0 | T49: 750 | U49: =SUMPRODUCT(H49:S49,$H$8:$S$8)*T49 -> 0
C50: artefatos em pedra | D50: Bancada Banheiros | E50: m2 | F50: =SUMPRODUCT($H$8:$Q$8,$H50:$Q50) -> 0 | T50: 750 | U50: =SUMPRODUCT(H50:S50,$H$8:$S$8)*T50 -> 0
C51: artefatos em pedra | D51: Bancada Tanque | E51: m2 | F51: =SUMPRODUCT($H$8:$Q$8,$H51:$Q51) -> 0 | T51: 750 | U51: =SUMPRODUCT(H51:S51,$H$8:$S$8)*T51 -> 0
F52: =SUMPRODUCT($H$8:$Q$8,$H52:$Q52) -> 0 | U52: =SUMPRODUCT(H52:Q52,$H$8:$Q$8)*T52 -> 0
