Workbook
Name \0: #REF!
Name \1: #REF!
Name \a: #REF!
Name \b: #REF!
Name \c: #REF!
Name \d: #REF!
Name \e: #REF!
Name \i: #REF!
Name \J: #REF!
Name \k: #REF!
Name \l: #N/A
Name \m: #REF!
Name \o: #REF!
Name \p: #REF!
Name \r: #REF!
Name \T: #REF!
Name \z: #REF!
Name _: #REF!
Name _\0: #REF!
Name _\1: #REF!
Name _\a: #REF!
Name _\b: #REF!
Name _\c: #REF!
Name _\d: #REF!
Name _\e: #REF!
Name _\i: #REF!
Name _\J: #REF!
Name _\k: #REF!
Name _\l: #N/A
Name _\m: #REF!
Name _\o: #REF!
Name _\p: #REF!
Name _\r: #REF!
Name _\T: #REF!
Name _\z: #REF!
Name __: #REF!
Name ______ACR10: #REF!
Name ______ACR15: #REF!
Name ______acr20: #REF!
Name ______acr5: #REF!
Name ______ARQ1: #REF!
Name ______QT100: #REF!
Name ______QT2: #REF!
Name ______QT3: #REF!
Name ______QT4: #REF!
Name ______QT50: #REF!
Name ______QT75: #REF!
Name _____ACR10: #REF!
Name _____ACR15: #REF!
Name _____acr20: #REF!
Name _____acr5: #REF!
Name _____ARQ1: #REF!
Name _____key2: #REF!
Name _____QT100: #REF!
Name _____QT2: #REF!
Name _____QT3: #REF!
Name _____QT4: #REF!
Name _____QT50: #REF!
Name _____QT75: #REF!
Name ____key2: #REF!

Sheet CAPA
A1: DADOS DO EMPREENDIMENTO
B2: Projeto: | C2: Electra Towers | E2: ENDEREÇO DA OBRA: | F2: Rua 254, 215, Meia Praia, Itapema/SC
B3: Empresa: | C3: Thozen Empreendimentos | E3: Cidade/ES: | F3: Itapema, SC
B4: Revisão: | C4: R00 | E4: CNPJ: | F4: 43.339.082/0001-06
B6: Pazo de Obra: | C6: 48 | E6: Nº Unid. Residenciais: | F6: 192 | I6: Imagens
B8: Área do Terreno: | C8: 2095.43 | E8: Nº Unid. Comerciais: | F8: 7
B10: Área Construída: | C10: 37893.89 | E10: Nº Pavimentos: | F10: 57
B12: Área Privativa: | C12: 22778.64 | E12: Total de Dormitórios: | F12: 576
B14: Área de Lazer: | C14: 1736.27 | E14: Nº Subsolos: | F14: 0
B16: Área Comercial: | C16: 500.04 | E16: Nº Vagas: | F16: 399
B18: Torre | C18: Pavimento | D18: Área | E18: Área Privativa | F18: Perímetro | G18: Pé direito
B19: Embasamento | C19: Térreo | D19: 1565.91 | E19: 0 | G19: 4.3
B20: Embasamento | C20: Garagem 01 | D20: 1736.27 | E20: 0
B21: Embasamento | C21: Garagem 02 | D21: 1736.27 | E21: 0
B22: Embasamento | C22: Garagem 03 | D22: 1736.27 | E22: 0
B23: Embasamento | C23: Garagem 04 | D23: 1736.27 | E23: 0
B24: Embasamento | C24: Garagem 05 | D24: 1736.27 | E24: 0
B25: Embasamento | C25: Pavimento diferenciado — Lazer | D25: 1736.27 | E25: 0 | G25: 3.6
B26: Torre A | C26: Pavimento tipo — Torre A (×24) | D26: 12720.48 | E26: 11382.72 | G26: 3.24
B27: Torre B | C27: Pavimento tipo — Torre B (×24) | D27: 12892.32 | E27: 11397.12 | G27: 3.24
B28: Cobertura | C28: Casa de Máquinas | D28: 176.26 | E28: 0
B29: Cobertura | C29: Reservatórios | D29: 121.3 | E29: 0
B37: Torre | C37: Pavimento | D37: Descrição | E37: Área | I37: ETAPA
B38: Áreas Comuns | C38: =_xlfn.XLOOKUP(D38,MOBILIÁRIO!C:C,MOBILIÁRIO!B:B) -> TÉRREO | D38: {=_xlfn.UNIQUE(_xlfn._xlws.FILTER(MOBILIÁRIO!C7:C316,MOBILIÁRIO!C7:C316<>""))} -> Hall Externo | E38: =_xlfn.XLOOKUP(D38,MOBILIÁRIO!C:C,MOBILIÁRIO!F:F) -> 12.33 | I38: GERENCIAMENTO TÉCNICO E ADMINISTRATIVO
B39: Áreas Comuns | C39: =_xlfn.XLOOKUP(D39,MOBILIÁRIO!C:C,MOBILIÁRIO!B:B) -> TÉRREO | D39: Hall Térreo | E39: =_xlfn.XLOOKUP(D39,MOBILIÁRIO!C:C,MOBILIÁRIO!F:F) -> 35.27 | I39: MOVIMENTAÇÃO DE TERRA
B40: Áreas Comuns | C40: =_xlfn.XLOOKUP(D40,MOBILIÁRIO!C:C,MOBILIÁRIO!B:B) -> TÉRREO | D40: Guarita | E40: =_xlfn.XLOOKUP(D40,MOBILIÁRIO!C:C,MOBILIÁRIO!F:F) -> 4.72 | I40: CONTENÇÃO
B41: Áreas Comuns | C41: =_xlfn.XLOOKUP(D41,MOBILIÁRIO!C:C,MOBILIÁRIO!B:B) -> TÉRREO | D41: Lavapés | E41: =_xlfn.XLOOKUP(D41,MOBILIÁRIO!C:C,MOBILIÁRIO!F:F) -> 1 | I41: INFRAESTRUTURA
B42: Áreas Comuns | C42: =_xlfn.XLOOKUP(D42,MOBILIÁRIO!C:C,MOBILIÁRIO!B:B) -> TÉRREO | D42: Lavabo Pne - Térreo | E42: =_xlfn.XLOOKUP(D42,MOBILIÁRIO!C:C,MOBILIÁRIO!F:F) -> 3.77 | I42: SUPRAESTRUTURA
B43: Áreas Comuns | C43: =_xlfn.XLOOKUP(D43,MOBILIÁRIO!C:C,MOBILIÁRIO!B:B) -> TÉRREO | D43: Bicicletário/Box | E43: =_xlfn.XLOOKUP(D43,MOBILIÁRIO!C:C,MOBILIÁRIO!F:F) -> 87.33 | I43: ALVENARIAS E VEDAÇÕES
B44: Áreas Comuns | C44: =_xlfn.XLOOKUP(D44,MOBILIÁRIO!C:C,MOBILIÁRIO!B:B) -> TÉRREO | D44: Antecâmara - Térreo | E44: =_xlfn.XLOOKUP(D44,MOBILIÁRIO!C:C,MOBILIÁRIO!F:F) -> 8.07 | I44: SISTEMAS E INSTALAÇÕES ELÉTRICAS
B45: Áreas Comuns | C45: =_xlfn.XLOOKUP(D45,MOBILIÁRIO!C:C,MOBILIÁRIO!B:B) -> 2º AO 5º PAVIMENTO - GARAGENS (X5) | D45: Antecâmara - Garagens (x5) | E45: =_xlfn.XLOOKUP(D45,MOBILIÁRIO!C:C,MOBILIÁRIO!F:F) -> 33.6 | I45: SISTEMAS E INSTALAÇÕES HIDROSSANITÁRIAS E DRENAGEM
B46: Áreas Comuns | C46: =_xlfn.XLOOKUP(D46,MOBILIÁRIO!C:C,MOBILIÁRIO!B:B) -> 4º PAVIMENTO - LAZER/GARAGENS | D46: Sala de massagem | E46: =_xlfn.XLOOKUP(D46,MOBILIÁRIO!C:C,MOBILIÁRIO!F:F) -> 7.47 | I46: INSTALAÇÕES PREVENTIVAS
B47: Áreas Comuns | C47: =_xlfn.XLOOKUP(D47,MOBILIÁRIO!C:C,MOBILIÁRIO!B:B) -> 4º PAVIMENTO - LAZER/GARAGENS | D47: Banheiro - Lazer/Garagem | E47: =_xlfn.XLOOKUP(D47,MOBILIÁRIO!C:C,MOBILIÁRIO!F:F) -> 3.91 | I47: INSTALAÇÕES DE GÁS
B48: Áreas Comuns | C48: =_xlfn.XLOOKUP(D48,MOBILIÁRIO!C:C,MOBILIÁRIO!B:B) -> 4º PAVIMENTO - LAZER/GARAGENS | D48: Lavabo - Lazer/Garagem | E48: =_xlfn.XLOOKUP(D48,MOBILIÁRIO!C:C,MOBILIÁRIO!F:F) -> 2.61 | I48: EQUIPAMENTOS E SISTEMAS ESPECIAIS
B49: Áreas Comuns | C49: =_xlfn.XLOOKUP(D49,MOBILIÁRIO!C:C,MOBILIÁRIO!B:B) -> 4º PAVIMENTO - LAZER/GARAGENS | D49: Lavabo Pne - Lazer/Garagem | E49: =_xlfn.XLOOKUP(D49,MOBILIÁRIO!C:C,MOBILIÁRIO!F:F) -> 4.33 | I49: CLIMATIZAÇÃO, EXAUSTÃO MECÂNICA
B50: Áreas Comuns | C50: =_xlfn.XLOOKUP(D50,MOBILIÁRIO!C:C,MOBILIÁRIO!B:B) -> 4º PAVIMENTO - LAZER/GARAGENS | D50: Circulação - Lazer/garagem | E50: =_xlfn.XLOOKUP(D50,MOBILIÁRIO!C:C,MOBILIÁRIO!F:F) -> 30.85 | I50: INSTALAÇÕES ESPECIAIS
... B63: Áreas Comuns | C63: =_xlfn.XLOOKUP(D63,MOBILIÁRIO!C:C,MOBILIÁRIO!B:B) -> 5º PAVIMENTO - LAZER | D63: Laje Verde | E63: =_xlfn.XLOOKUP(D63,MOBILIÁRIO!C:C,MOBILIÁRIO!F:F) -> 269.95 | I63: CUB/SC
B64: Áreas Comuns | C64: =_xlfn.XLOOKUP(D64,MOBILIÁRIO!C:C,MOBILIÁRIO!B:B) -> 5º PAVIMENTO - LAZER | D64: Brinquedoteca | E64: =_xlfn.XLOOKUP(D64,MOBILIÁRIO!C:C,MOBILIÁRIO!F:F) -> 16.32
B65: Áreas Comuns | C65: =_xlfn.XLOOKUP(D65,MOBILIÁRIO!C:C,MOBILIÁRIO!B:B) -> 5º PAVIMENTO - LAZER | D65: Game Center | E65: =_xlfn.XLOOKUP(D65,MOBILIÁRIO!C:C,MOBILIÁRIO!F:F) -> 13.09 | I65: DESCRIÇÃO
B66: Áreas Comuns | C66: =_xlfn.XLOOKUP(D66,MOBILIÁRIO!C:C,MOBILIÁRIO!B:B) -> 5º PAVIMENTO - LAZER | D66: Sala de Festas | E66: =_xlfn.XLOOKUP(D66,MOBILIÁRIO!C:C,MOBILIÁRIO!F:F) -> 93.46 | I66: VALOR POR ÁREA PRIVATIVA (R$/m²)
B67: Áreas Comuns | C67: =_xlfn.XLOOKUP(D67,MOBILIÁRIO!C:C,MOBILIÁRIO!B:B) -> 5º PAVIMENTO - LAZER | D67: Terraço | E67: =_xlfn.XLOOKUP(D67,MOBILIÁRIO!C:C,MOBILIÁRIO!F:F) -> 88.11 | I67: Tipo diferenciado Apart. 1
B68: Áreas Comuns | C68: =_xlfn.XLOOKUP(D68,MOBILIÁRIO!C:C,MOBILIÁRIO!B:B) -> 5º PAVIMENTO - LAZER | D68: Wine Bar | E68: =_xlfn.XLOOKUP(D68,MOBILIÁRIO!C:C,MOBILIÁRIO!F:F) -> 29.79 | I68: Tipo diferenciado Apart. 2
B69: Áreas Comuns | C69: =_xlfn.XLOOKUP(D69,MOBILIÁRIO!C:C,MOBILIÁRIO!B:B) -> 5º PAVIMENTO - LAZER | D69: Academia | E69: =_xlfn.XLOOKUP(D69,MOBILIÁRIO!C:C,MOBILIÁRIO!F:F) -> 63.68 | I69: Tipo Apart. 01
B70: Áreas Comuns | C70: =_xlfn.XLOOKUP(D70,MOBILIÁRIO!C:C,MOBILIÁRIO!B:B) -> 5º PAVIMENTO - LAZER | D70: Espaço Crossfit | E70: =_xlfn.XLOOKUP(D70,MOBILIÁRIO!C:C,MOBILIÁRIO!F:F) -> 34.41 | I70: Tipo Apart. 02
B71: Áreas Comuns | C71: =_xlfn.XLOOKUP(D71,MOBILIÁRIO!C:C,MOBILIÁRIO!B:B) -> 5º PAVIMENTO - LAZER | D71: Antecâmara - Lazer | E71: =_xlfn.XLOOKUP(D71,MOBILIÁRIO!C:C,MOBILIÁRIO!F:F) -> 4.15 | I71: Penthouse
B72: Áreas Comuns | C72: =_xlfn.XLOOKUP(D72,MOBILIÁRIO!C:C,MOBILIÁRIO!B:B) -> 6º AO 38º PAVIMENTO - PAVIMENTOS (X33) | D72: Antecâmara - Tipos (x33) | E72: =_xlfn.XLOOKUP(D72,MOBILIÁRIO!C:C,MOBILIÁRIO!F:F) -> 221.76 | I72: Penthouse diferenciado
I73: Duplex
B76: Torre | C76: Apartamentos | D76: Área | E76: Quantidade | F76: Total vagas | G76: Total apartamentos | I76: QUADRO DE ÁREAS
B77: Torre 1 | C77: Tipo 1 | D77: 102.67 | E77: 9 | F77: 18 | G77: =E77 -> 9
B78: Torre 1 | C78: Tipo 2 | D78: 108.38 | E78: 9 | F78: 18 | G78: =E78 -> 9
B79: Torre 1 | C79: Tipo 3 penthouse (outorga) | D79: 202.02 | E79: 9 | F79: 18 | G79: =E79 -> 9
B80: Torre 1 | C80: Tipo 3 penthouse | D80: 202.02 | E80: 12 | F80: 36 | G80: =E80 -> 12
B81: Torre 1 | C81: Tipo 4 penthouse | D81: 199.18 | E81: 1 | F81: 3 | G81: =E81 -> 1
B82: Torre 1 | C82: duplex 1 | D82: 329.41 | E82: 1 | F82: 4 | G82: =E82 -> 1
D83: =SUMPRODUCT(D77:E82) -> 1184.68 | E83: =SUM(E77:E82) -> 41 | F83: =SUM(F77:F82) -> 97 | G83: =SUM(G77:G82) -> 41
B86: Torre | C86: Sala comercial | D86: Área | E86: Total vagas | F86: Total banheiros
B87: Torre 1 | C87: Sala comercial 1 | D87: 176.43 | E87: 2 | F87: 1
B88: Torre 1 | C88: Sala comercial 2 | D88: 84.08 | E88: 1 | F88: 1
B89: Torre 1 | C89: Sala comercial 3 | D89: 60.82 | E89: 1 | F89: 1
B90: Torre 1 | C90: Sala comercial 4 | D90: 132.86 | E90: 2 | F90: 1
B91: Torre 1 | C91: Sala comercial 5 | D91: 83.77 | E91: 1 | F91: 1
D92: =SUM(D87:D91) -> 537.96 | E92: =SUM(E87:E91) -> 7 | F92: =SUM(F87:F91) -> 5

Sheet EAP
A1: EAP DE ORÇAMENTO
A3: Contrutora - Obra
A5: UNIDADE CONSTRUTIVA | B5: 1 | C5: GERENCIAMENTO TÉCNICO E ADMINISTRATIVO
A6: CÉLULA CONSTRUTIVA | B6: 1 | C6: SERVIÇOS TÉCNICOS
A7: ETAPA | B7: 1.001 | C7: ESTUDOS, PROJETOS E CONSULTORIAS
A8: Subetapa | B8: 01.001.001 | C8: Estudos
A9: Subetapa | B9: 01.001.002 | C9: Projetos
A10: Subetapa | B10: 01.001.003 | C10: Consultorias
A11: Subetapa | B11: 01.001.004 | C11: Ensaios
A12: ETAPA | B12: 1.002 | C12: TAXAS E DOCUMENTOS
A13: Subetapa | B13: 01.002.001 | C13: Licenciamentos, Taxas, Impostos, Aprovações e Seguros
A14: Subetapa | B14: 01.002.002 | C14: Documentos
A15: CÉLULA CONSTRUTIVA | B15: 2 | C15: SERVIÇOS INICIAIS
A16: ETAPA | B16: 2.001 | C16: SEGURANÇA, MEIO AMBIENTE, SAÚDE
A17: Subetapa | B17: 02.001.001 | C17: Segurança do trabalho
A18: Subetapa | B18: 02.001.002 | C18: Equipamentos de proteção
A19: Subetapa | B19: 02.001.003 | C19: Meio ambiente
A20: Subetapa | B20: 02.001.004 | C20: Saúde ocupacional
A21: ETAPA | B21: 2.002 | C21: ADMINISTRAÇÃO E CANTEIRO DE OBRA
A22: Subetapa | B22: 02.002.001 | C22: Equipe de Gestão e Apoio
A23: Subetapa | B23: 02.002.002 | C23: Operação inicial de canteiro
A24: Subetapa | B24: 02.002.003 | C24: Despesas de consumo e manutenção
A25: Subetapa | B25: 02.002.004 | C25: Instalações provisórias
A26: Subetapa | B26: 02.002.005 | C26: Ligações Provisórias
A27: ETAPA | B27: 2.003 | C27: SERVIÇOS PRELIMINARES
... A29: Subetapa | B29: 02.003.002 | C29: Limpeza de terreno
A30: CÉLULA CONSTRUTIVA | B30: 3 | C30: EQUIPAMENTOS
A31: ETAPA | B31: 3.001 | C31: EQUIPAMENTOS
A32: Subetapa | B32: 03.001.001 | C32: Equipamentos de Carga e Transporte
A33: Subetapa | B33: 03.001.002 | C33: Equipamentos de obra
A34: Subetapa | B34: 03.001.003 | C34: Balancins e Andaimes
A35: UNIDADE CONSTRUTIVA | B35: 2 | C35: GERENCIAMENTO EXECUTIVO
A36: CÉLULA CONSTRUTIVA | B36: 1 | C36: INFRAESTRUTURA
A37: ETAPA | B37: 1.001 | C37: MOVIMENTAÇÃO DE TERRA
A38: Subetapa | B38: 01.001.001 | C38: Corte e aterro
A39: Subetapa | B39: 01.001.002 | C39: Rebaixamento de lençol
A40: Subetapa | B40: 01.001.003 | C40: Escavação e Reaterro de Valas
A41: Subetapa | B41: 01.001.004 | C41: Lastro de estrutura de concreto
A42: Subetapa | B42: 01.001.005 | C42: Movimentação de bota - fora
A43: ETAPA | B43: 1.002 | C43: FUNDAÇÃO PROFUNDA
A44: Subetapa | B44: 01.002.001 | C44: Perfuração
A45: Subetapa | B45: 01.002.002 | C45: Armadura
A46: Subetapa | B46: 01.002.003 | C46: Acessórios
A47: Subetapa | B47: 01.002.004 | C47: Concreto
A48: Subetapa | B48: 01.002.005 | C48: Mão de obra
... A53: Subetapa | B53: 01.003.004 | C53: Mão de obra
A54: CÉLULA CONSTRUTIVA | B54: 2 | C54: SUPRAESTRUTURA
A55: ETAPA | B55: 2.001 | C55: SUPRAESTRUTURA - EMBASAMENTO
A56: Subetapa | B56: 02.001.001 | C56: Forma
A57: Subetapa | B57: 02.001.002 | C57: Armadura
A58: Subetapa | B58: 02.001.003 | C58: Concreto
A59: Subetapa | B59: 02.001.004 | C59: Complementares
A60: Subetapa | B60: 02.001.005 | C60: Mão de obra
A61: ETAPA | B61: 2.002 | C61: SUPRAESTRUTURA - TORRE A
A62: Subetapa | B62: 02.002.001 | C62: Forma
A63: Subetapa | B63: 02.002.002 | C63: Armadura
A64: Subetapa | B64: 02.002.003 | C64: Concreto
A65: Subetapa | B65: 02.002.004 | C65: Complementares
A66: Subetapa | B66: 02.002.005 | C66: Mão de obra
... A72: Subetapa | B72: 02.003.005 | C72: Mão de obra
A73: CÉLULA CONSTRUTIVA | B73: 3 | C73: PAREDES E PAINÉIS
A74: ETAPA | B74: 3.001 | C74: PAREDES E PAINÉIS - EMBASAMENTO
A75: Subetapa | B75: 03.001.001 | C75: Alvenaria de vedação com blocos cerâmicos
A76: Subetapa | B76: 03.001.002 | C76: Alvenaria de vedação com bocos de concreto
A77: Subetapa | B77: 03.001.003 | C77: Serviços complementares para alvenaria de vedação
A78: Subetapa | B78: 03.001.004 | C78: Drywall
A79: Subetapa | B79: 03.001.005 | C79: Mão de obra
A80: ETAPA | B80: 3.002 | C80: PAREDES E PAINÉIS - TORRE A
A81: Subetapa | B81: 03.002.001 | C81: Alvenaria de vedação com blocos cerâmicos
A82: Subetapa | B82: 03.002.002 | C82: Alvenaria de vedação com bocos de concreto
A83: Subetapa | B83: 03.002.003 | C83: Serviços complementares para alvenaria de vedação
A84: Subetapa | B84: 03.002.004 | C84: Drywall
A85: Subetapa | B85: 03.002.005 | C85: Mão de obra
... A91: Subetapa | B91: 03.003.005 | C91: Mão de obra
A92: CÉLULA CONSTRUTIVA | B92: 4 | C92: IMPERMEABILIZAÇÃO E TRATAMENTOS
A93: ETAPA | B93: 4.001 | C93: IMPERMEABILIZAÇÃO E TRATAMENTOS - EMBASAMENTO
A94: Subetapa | B94: 04.001.001 | C94: Regularização e proteção mecânica
A95: Subetapa | B95: 04.001.002 | C95: Impermeabilização de cisternas
A96: Subetapa | B96: 04.001.003 | C96: Impermeabilização de fundação e contenção
A97: Subetapa | B97: 04.001.004 | C97: Impermeabilização de lajes e terraços
A98: Subetapa | B98: 04.001.005 | C98: Impermeabilização de piscinas e espelhos d´água
A99: Subetapa | B99: 04.001.006 | C99: Impermeabilização de banheiro, cozinha e sacada
A100: Subetapa | B100: 04.001.007 | C100: Impermeabilização de esquadrias
A101: Subetapa | B101: 04.001.008 | C101: Impermeabilização de ralos
A102: Subetapa | B102: 04.001.009 | C102: Impermeabilização de floreiras
A103: Subetapa | B103: 04.001.010 | C103: Impermeabilização de reservatórios
A104: Subetapa | B104: 04.001.011 | C104: Mão de obra
... A128: Subetapa | B128: 04.003.011 | C128: Mão de obra
A129: CÉLULA CONSTRUTIVA | B129: 5 | C129: SISTEMAS E INSTALAÇÕES HIDROSSANITÁRIAS E DRENAGEM
A130: ETAPA | B130: 5.001 | C130: SISTEMAS E INSTALAÇÕES HIDROSSANITÁRIAS E DRENAGEM - EMBASAMENTO
A131: Subetapa | B131: 05.001.001 | C131: Instalações de água fria
A132: Subetapa | B132: 05.001.002 | C132: Instalações de água quente
A133: Subetapa | B133: 05.001.003 | C133: Instalações de esgoto e pluviais
A134: Subetapa | B134: 05.001.004 | C134: Cisterna
A135: Subetapa | B135: 05.001.005 | C135: Hidrômetros
A136: Subetapa | B136: 05.001.006 | C136: Reservatórios
A137: Subetapa | B137: 05.001.007 | C137: Sistema de bombas
A138: Subetapa | B138: 05.001.008 | C138: Mão de obra
A139: ETAPA | B139: 5.002 | C139: SISTEMAS E INSTALAÇÕES HIDROSSANITÁRIAS E DRENAGEM - TORRE A
A140: Subetapa | B140: 05.002.001 | C140: Instalações de água fria
...

Sheet Resumo Estrutura
B1: Projeto: | C1: =CAPA!$C$2 -> Elizabeth II Royal Home
B2: Empresa: | C2: =CAPA!$C$3 -> Gessele
B3: Revisão: | C3: R00
A4: Item | B4: Disciplina | C4: EAP - Arquitetura | D4: Pavimento Proj. Estrutural | E4: Etapa | F4: Projetos | G4: Área Pavimento | H4: Mpa | I4: Concreto | J4: Forma Convencional | K4: Forma Convencional Fabricação | L4: Cubeta inteira | M4: Meia Cubeta | N4: Aço | O4: Ø5.0mm 0,154 kg/m | P4: Ø6.3mm 0,245 kg/m | Q4: Ø8.0mm 0,395 kg/m | R4: Ø10.0mm 0,617 kg/m | S4: Ø12.5mm 0,963 kg/m | T4: Ø16.0mm 1,578 kg/m | U4: Ø20.0mm 2,466 kg/m | V4: Ø25.0mm 3,853 kg/m | W4: Ø32.0mm 6,313 kg/m
A5: Torre | Q5: =Q81/SUM($O$81:$W$81) -> 0.069768384 | R5: =R81/SUM($O$81:$W$81) -> 0.079324587 | S5: =S81/SUM($O$81:$W$81) -> 0.089771623 | T5: =T81/SUM($O$81:$W$81) -> 0.030085844 | U5: =U81/SUM($O$81:$W$81) -> 0.11503887 | V5: =V81/SUM($O$81:$W$81) -> 0.54725462 | W5: =W81/SUM($O$81:$W$81) -> 0
A6: =A5 -> Torre | B6: Fundação | C6: Contenções | D6: Contenções | E6: Mureta guia | F6: PR-1248-00-CON-FO-01-R00 | H6: 50 | I6: ='Fund. Rasa | Contenção'!AG84 -> 11.390452 | J6: ='Fund. Rasa | Contenção'!AD84 -> 222.6272 | N6: =SUM(O6:W6) -> 711.9216 | P6: =(30*48+(1.02+1.07+0.07+0.02+0.07+0.17+0.12+0.07+0.02+0.07)*48*2/0.2)*0.245 -> 670.32 | S6: =0.45*48*2*0.963 -> 41.6016
A7: =A5 -> Torre | B7: Fundação | C7: Contenções | D7: Contenções | E7: Parede de Diafragma | H7: 50 | I7: 210 | J7: 1050 | N7: =SUM(O7:W7) -> 18250 | P7: 2282 | Q7: 77 | S7: 3884 | V7: 12007
A8: =A7 -> Torre | B8: Fundação | C8: Contenções | D8: Contenções | E8: Estroncas | F8: PR-1248-00-CON-FO-01-R00 | H8: 50 | I8: 8.4 | J8: 37.2 | N8: =SUM(O8:W8) -> 608.81818 | Q8: =(62+84.7)/1.1 -> 133.36364 | S8: =49.9/1.1 -> 45.363636 | U8: =473.1/1.1 -> 430.09091
A9: =A7 -> Torre | B9: Fundação | C9: Contenções | D9: Contenções | E9: Viga Coroamento | F9: PR-1248-00-CON-VI-01-R01 | H9: 50 | I9: 9.4 | J9: 45.6 | N9: =SUM(O9:W9) -> 2057.2727 | Q9: =858/1.1 -> 780 | T9: =1405/1.1 -> 1277.2727
D10: TOTAL - CONTENÇÃO | I10: =SUM(I7:I9) -> 227.8 | J10: =SUM(J7:J9) -> 1132.8 | K10: =SUM(K7:K9) -> 0 | L10: =SUM(L7:L9) -> 0 | M10: =SUM(M7:M9) -> 0 | N10: =SUM(N7:N9) -> 20916.091 | O10: =SUM(O7:O9) -> 0 | P10: =SUM(P7:P9) -> 2282 | ... W10: =SUM(W7:W9) -> 0
A11: =A5 -> Torre | B11: Fundação | C11: Fundação - Estacas | D11: Fundação | E11: Estacas | H11: 50 | I11: =Estacas!K7 -> 83.448555 | P11: =Estacas!M7 -> 6175 | U11: =Estacas!N7 -> 41456
D12: TOTAL - FUNDAÇÃO ESTACA | I12: =SUM(I11) -> 83.448555 | J12: =SUM(J11) -> 0 | K12: =SUM(K11) -> 0 | L12: =SUM(L11) -> 0 | M12: =SUM(M11) -> 0 | N12: =SUM(N11) -> 0 | O12: =SUM(O11) -> 0 | P12: =SUM(P11) -> 6175 | ... W12: =SUM(W11) -> 0
A13: =A5 -> Torre | B13: Fundação | C13: Fundação - Blocos | D13: Fundação | E13: Blocos | F13: PR-1248-00-FUN-AR-01-R01 | H13: 50 | I13: 658.5 | J13: 524.5 | N13: =SUM(O13:W13) -> 69835.455 | S13: =581/1.1 -> 528.18182 | T13: =8065/1.1 -> 7331.8182 | U13: =1450/1.1 -> 1318.1818 | V13: =66723/1.1 -> 60657.273
D14: TOTAL - FUNDAÇÃO BLOCOS | I14: =SUM(I13) -> 658.5 | J14: =SUM(J13) -> 524.5 | K14: =SUM(K13) -> 0 | L14: =SUM(L13) -> 0 | M14: =SUM(M13) -> 0 | N14: =SUM(N13) -> 69835.455 | O14: =SUM(O13) -> 0 | P14: =SUM(P13) -> 0 | ... W14: =SUM(W13) -> 0
A15: =A5 -> Torre | B15: Fundação | C15: Fundação - Vigas etc. | D15: Fundação | E15: Pilares | F15: PR-1248-00-FUN-AR-01-R01 | H15: 50 | I15: 18.7 | J15: 122.9 | N15: =SUM(O15:W15) -> 44086 | O15: =31 -> 31 | P15: =97+14+12 -> 123 | Q15: =83+15+1 -> 99 | R15: =4397+153+1118 -> 5668 | S15: =4398+60+195 -> 4653 | T15: =484+130 -> 614 | U15: =902 -> 902 | V15: =3332+1348 -> 4680 | W15: =27316 -> 27316
A16: =A5 -> Torre | B16: Fundação | C16: Fundação - Vigas etc. | D16: Fundação | E16: Vigas | H16: 50
A17: =A16 -> Torre | B17: Fundação | C17: Fundação - Vigas etc. | D17: Fundação | E17: Laje p/ equipamentos | F17: PR-1248-00-FUN-LA-01-R01 | H17: 50 | I17: =1.4*(1.19*2.325)+0.3*(4.2*4.2) -> 9.16545 | J17: =4.2*4*0.3+(1.19*2+2.325*2)*1.4 -> 14.882 | N17: =SUM(O17:W17) -> 829.90909 | S17: =(191.8+551.8)/1.1 -> 676 | T17: =169.3/1.1 -> 153.90909
A18: =A5 -> Torre | B18: Fundação | C18: Fundação - Vigas etc. | D18: Fundação | E18: Contrapiso | H18: 50 | N18: =SUM(O18:W18) -> 17 | O18: =11 -> 11 | R18: =6 -> 6
A19: =A5 -> Torre | B19: Fundação | C19: Fundação - Vigas etc. | D19: Fundação | E19: Cisternas | F19: PR-1248-01-CIS-FO-01-R02 | H19: 50 | I19: ='Cálculo de apoio'!D8 -> 23.18176 | J19: ='Cálculo de apoio'!E6 -> 28.95 | N19: =SUM(O19:W19) -> 3419.1818 | O19: ='Cálculo de apoio'!J8 -> 10 | P19: ='Cálculo de apoio'!K8 -> 7.2727273 | Q19: ='Cálculo de apoio'!L8 -> 883.63636 | R19: ='Cálculo de apoio'!M8 -> 1337.6364 | S19: ='Cálculo de apoio'!N8 -> 678.81818 | T19: ='Cálculo de apoio'!O8 -> 501.81818 | U19: ='Cálculo de apoio'!P8 -> 0 | V19: ='Cálculo de apoio'!Q8 -> 0
A20: =A5 -> Torre | B20: Fundação | C20: Fundação - Vigas etc. | D20: Fundação | E20: Dutos | H20: 50 | N20: =SUM(O20:W20) -> 0
C21: TOTAL - VIGAS BALDRAMES/PILARES DE ARRANQUE/CISTERNAS E DUTOS | I21: =SUM(I15:I20) -> 51.04721 | J21: =SUM(J15:J20) -> 166.732 | K21: =SUM(K15:K20) -> 0 | L21: =SUM(L15:L20) -> 0 | M21: =SUM(M15:M20) -> 0 | N21: =SUM(N15:N20) -> 48352.091 | O21: =SUM(O15:O20) -> 52 | P21: =SUM(P15:P20) -> 130.27273 | ... W21: =SUM(W15:W20) -> 27316
A22: =A20 -> Torre | B22: Supraestrutura | C22: Térreo | D22: Térreo | E22: Pilares | H22: 50 | K22: =J28*3 -> 1733.4 | N22: =SUM(O22:W22) -> 0
A23: =A22 -> Torre | B23: Supraestrutura | C23: Térreo | D23: Térreo | E23: Vigas | H23: 50 | I23: 106.6 | J23: 582.1 | K23: =J23*3 -> 1746.3 | N23: =SUM(O23:W23) -> 17598 | P23: 1364 | Q23: 1169 | R23: 2046 | S23: 1225 | T23: 1240 | U23: 3719 | V23: 6835
A24: =A23 -> Torre | B24: Supraestrutura | C24: Térreo | D24: Térreo | E24: Lajes | H24: 50 | I24: 97 | K24: =J30*3 -> 1261.185 | N24: =SUM(O24:W24) -> 4886.3636 | P24: =777.2/1.1+909.4/1.1+1201.9/1.1+1189.3/1.1 -> 3707.0909 | Q24: =673.2/1.1+292.6/1.1+267.4/1.1+64/1.1 -> 1179.2727
A25: =A24 -> Torre | B25: Supraestrutura | C25: Térreo | D25: Térreo | E25: Capiteis | H25: 50 | N25: =SUM(O25:W25) -> 0
A26: =A25 -> Torre | B26: Supraestrutura | C26: Térreo | D26: Térreo | E26: Lajes | H26: 50 | I26: 4.8 | J26: =(0.5816+0.5128+(3.01+2.65)*1.2+3.1+3.2*1.2)/1.6*4.8 -> 44.4792 | K26: =J32*3 -> 133.4376 | N26: =SUM(O26:W26) -> 302.54545 | P26: =10/1.1 -> 9.0909091 | Q26: 9 | R26: =55/1.1+36/1.1+25/1.1 -> 105.45455 | S26: 145 | T26: 34
D27: ="TOTAL - "&UPPER(C26) -> TOTAL - TÉRREO | I27: =SUM(I22:I26) -> 208.4 | J27: =SUM(J22:J26) -> 626.5792 | K27: =SUM(K22:K26) -> 4874.3226 | L27: =SUM(L22:L26) -> 0 | M27: =SUM(M22:M26) -> 0 | N27: =SUM(N22:N26) -> 22786.909 | O27: =SUM(O22:O26) -> 0 | P27: =SUM(P22:P26) -> 5080.1818 | ... W27: =SUM(W22:W26) -> 0
A28: =A5 -> Torre | B28: Supraestrutura | C28: Mezanino G1 | D28: Garagem G1 | E28: Pilares | H28: 50 | I28: 101.9 | J28: 577.8 | N28: =SUM(O28:W28) -> 45075 | P28: 311 | Q28: 278 | R28: 6542 | S28: 8103 | T28: 760 | U28: 629 | V28: 7983 | W28: 20469
A29: =A5 -> Torre | B29: Supraestrutura | C29: Mezanino G1 | D29: Garagem G1 | E29: Vigas | H29: 50 | I29: 37 | J29: 329.6 | N29: =SUM(O29:W29) -> 7215 | O29: 5 | P29: 449 | Q29: 632 | R29: 246 | S29: 964 | T29: 1526 | U29: 1632 | V29: 1761
A30: =A5 -> Torre | B30: Supraestrutura | C30: Mezanino G1 | D30: Garagem G1 | E30: Lajes | H30: 50 | I30: 101.3 | J30: =I30*4.15 -> 420.395 | N30: =SUM(O30:W30) -> 6276 | P30: 275 | Q30: 4210 | R30: 1216 | S30: 247 | T30: 328
A31: =A7 -> Torre | B31: Supraestrutura | C31: Mezanino G1 | D31: Garagem G1 | E31: Capiteis | H31: 50 | N31: =SUM(O31:W31) -> 580.90909 | P31: =7/1.1 -> 6.3636364 | Q31: =8/1.1 -> 7.2727273 | S31: =263/1.1 -> 239.09091 | T31: =361/1.1 -> 328.18182
A32: =A5 -> Torre | B32: Supraestrutura | C32: Mezanino G1 | D32: Garagem G1 | E32: Escadas | H32: 50 | I32: 4.8 | J32: =(0.5816+0.5128+(3.01+2.65)*1.2+3.1+3.2*1.2)/1.6*4.8 -> 44.4792 | N32: =SUM(O32:W32) -> 302.54545 | P32: =10/1.1 -> 9.0909091 | Q32: 9 | R32: =55/1.1+36/1.1+25/1.1 -> 105.45455 | S32: 145 | T32: 34
D33: ="TOTAL - "&UPPER(C32) -> TOTAL - MEZANINO G1 | I33: =SUM(I28:I32) -> 245 | J33: =SUM(J28:J32) -> 1372.2742 | K33: =SUM(K28:K32) -> 0 | L33: =SUM(L28:L32) -> 0 | M33: =SUM(M28:M32) -> 0 | N33: =SUM(N28:N32) -> 59449.455 | O33: =SUM(O28:O32) -> 5 | P33: =SUM(P28:P32) -> 1050.4545 | ... W33: =SUM(W28:W32) -> 20469
A34: =A5 -> Torre | B34: Supraestrutura | C34: G2 | D34: Garagem G2 | E34: Pilares | H34: 50 | I34: 73.8 | J34: 477.3 | N34: =SUM(O34:W34) -> 28668 | P34: 318 | Q34: 265 | R34: 3264 | S34: 4826 | T34: 604 | U34: 353 | V34: 5463 | W34: 13575
A35: =A5 -> Torre | B35: Supraestrutura | C35: G2 | D35: Garagem G2 | E35: Vigas | H35: 50 | I35: 31.8 | J35: 303.1 | N35: =SUM(O35:W35) -> 6621 | O35: 1 | P35: 500 | Q35: 693 | R35: 188 | S35: 866 | T35: 1890 | U35: 1043 | V35: 1440
A36: =A5 -> Torre | B36: Supraestrutura | C36: G2 | D36: Garagem G2 | E36: Lajes | H36: 50 | I36: 174.5 | J36: =I36*4.15 -> 724.175 | N36: =SUM(O36:W36) -> 11527 | P36: 705 | Q36: 7045 | R36: 3087 | S36: 63 | T36: 627
A37: =A7 -> Torre | B37: Supraestrutura | C37: G2 | D37: Garagem G2 | E37: Capiteis | H37: 50 | N37: =SUM(O37:W37) -> 1879.0909 | P37: =31/1.1 -> 28.181818 | Q37: =40/1.1 -> 36.363636 | R37: =333/1.1 -> 302.72727 | S37: =236/1.1 -> 214.54545 | T37: =1427/1.1 -> 1297.2727
A38: =A5 -> Torre | B38: Supraestrutura | C38: G2 | D38: Garagem G2 | E38: Escadas | H38: 50 | I38: 1.6 | J38: =(0.5816+0.5128+(3.01+2.65)*1.2+3.1+3.2*1.2)*1 -> 14.8264 | N38: =SUM(O38:W38) -> 106 | P38: 20 | Q38: 14 | R38: 72
D39: ="TOTAL - "&UPPER(C38) -> TOTAL - G2 | I39: =SUM(I34:I38) -> 281.7 | J39: =SUM(J34:J38) -> 1519.4014 | K39: =SUM(K34:K38) -> 0 | L39: =SUM(L34:L38) -> 0 | M39: =SUM(M34:M38) -> 0 | N39: =SUM(N34:N38) -> 48801.091 | O39: =SUM(O34:O38) -> 1 | P39: =SUM(P34:P38) -> 1571.1818 | ... W39: =SUM(W34:W38) -> 13575
A40: =A5 -> Torre | B40: Supraestrutura | C40: Mezanino G2 | D40: Garagem G3 | E40: Pilares | H40: 50 | I40: 79 | J40: 506.1 | N40: =SUM(O40:W40) -> 15968.154 | O40: =O$5*$N40 -> 89.875825 | P40: =P$5*$N40 -> 1008.0317 | Q40: =Q$5*$N40 -> 1114.0723 | R40: =R$5*$N40 -> 1266.6672 | S40: =S$5*$N40 -> 1433.4871 | T40: =T$5*$N40 -> 480.41538 | U40: =U$5*$N40 -> 1836.9584 | V40: =V$5*$N40 -> 8738.6458 | W40: =W$5*$N40 -> 0
A41: =A5 -> Torre | B41: Supraestrutura | C41: Mezanino G2 | D41: Garagem G3 | E41: Vigas | H41: 50 | I41: 27.5 | J41: 263.7 | N41: =SUM(O41:W41) -> 5840.1524 | O41: =O$5*$N41 -> 32.870958 | P41: =P$5*$N41 -> 368.67499 | Q41: =Q$5*$N41 -> 407.45799 | R41: =R$5*$N41 -> 463.26767 | S41: =S$5*$N41 -> 524.27995 | T41: =T$5*$N41 -> 175.70591 | U41: =U$5*$N41 -> 671.84454 | V41: =V$5*$N41 -> 3196.0503 | W41: =W$5*$N41 -> 0
A42: =A5 -> Torre | B42: Supraestrutura | C42: Mezanino G2 | D42: Garagem G3 | E42: Lajes | H42: 50 | I42: 175.8 | J42: 730.3 | N42: =SUM(O42:W42) -> 14768.805 | O42: =O$5*$N42 -> 83.125359 | P42: =P$5*$N42 -> 932.31967 | Q42: =Q$5*$N42 -> 1030.3956 | R42: =R$5*$N42 -> 1171.5293 | S42: =S$5*$N42 -> 1325.8196 | T42: =T$5*$N42 -> 444.33195 | U42: =U$5*$N42 -> 1698.9866 | V42: =V$5*$N42 -> 8082.2966 | W42: =W$5*$N42 -> 0
A43: =A7 -> Torre | B43: Supraestrutura | C43: Mezanino G2 | D43: Garagem G3 | E43: Capiteis | H43: 50 | N43: =SUM(O43:W43) -> 0 | O43: =O$5*$N43 -> 0 | P43: =P$5*$N43 -> 0 | Q43: =Q$5*$N43 -> 0 | R43: =R$5*$N43 -> 0 | S43: =S$5*$N43 -> 0 | T43: =T$5*$N43 -> 0 | U43: =U$5*$N43 -> 0 | V43: =V$5*$N43 -> 0 | W43: =W$5*$N43 -> 0
A44: =A5 -> Torre | B44: Supraestrutura | C44: Mezanino G2 | D44: Garagem G3 | E44: Escadas | H44: 50 | I44: 1.6 | J44: =(0.5816+0.5128+(3.01+2.65)*1.2+3.1+3.2*1.2)*1 -> 14.8264 | N44: =SUM(O44:W44) -> 105.3892 | O44: =O$5*$N44 -> 0.59317697 | P44: =P$5*$N44 -> 6.6529705 | Q44: =Q$5*$N44 -> 7.352834 | R44: =R$5*$N44 -> 8.3599546 | S44: =S$5*$N44 -> 9.4609593 | T44: =T$5*$N44 -> 3.170723 | U44: =U$5*$N44 -> 12.123855 | V44: =V$5*$N44 -> 57.674725 | W44: =W$5*$N44 -> 0
D45: ="TOTAL - "&UPPER(C44) -> TOTAL - MEZANINO G2 | I45: =SUM(I40:I44) -> 283.9 | J45: =SUM(J40:J44) -> 1514.9264 | K45: =SUM(K40:K44) -> 0 | L45: =SUM(L40:L44) -> 0 | M45: =SUM(M40:M44) -> 0 | N45: =SUM(N40:N44) -> 36682.5 | O45: =SUM(O40:O44) -> 206.46532 | P45: =SUM(P40:P44) -> 2315.6794 | ... W45: =SUM(W40:W44) -> 0
A46: =A5 -> Torre | B46: Supraestrutura | C46: G3 | D46: Garagem G4 | E46: Pilares | H46: 50 | I46: 79 | J46: 506.1 | N46: =SUM(O46:W46) -> 15968.154 | O46: =O$5*$N46 -> 89.875825 | P46: =P$5*$N46 -> 1008.0317 | Q46: =Q$5*$N46 -> 1114.0723 | R46: =R$5*$N46 -> 1266.6672 | S46: =S$5*$N46 -> 1433.4871 | T46: =T$5*$N46 -> 480.41538 | U46: =U$5*$N46 -> 1836.9584 | V46: =V$5*$N46 -> 8738.6458 | W46: =W$5*$N46 -> 0
A47: =A5 -> Torre | B47: Supraestrutura | C47: G3 | D47: Garagem G4 | E47: Vigas | H47: 50 | I47: 27.5 | J47: 263.7 | N47: =SUM(O47:W47) -> 5840.1524 | O47: =O$5*$N47 -> 32.870958 | P47: =P$5*$N47 -> 368.67499 | Q47: =Q$5*$N47 -> 407.45799 | R47: =R$5*$N47 -> 463.26767 | S47: =S$5*$N47 -> 524.27995 | T47: =T$5*$N47 -> 175.70591 | U47: =U$5*$N47 -> 671.84454 | V47: =V$5*$N47 -> 3196.0503 | W47: =W$5*$N47 -> 0
A48: =A5 -> Torre | B48: Supraestrutura | C48: G3 | D48: Garagem G4 | E48: Lajes | H48: 50 | I48: 176 | J48: 730.9 | N48: =SUM(O48:W48) -> 14768.805 | O48: =O$5*$N48 -> 83.125359 | P48: =P$5*$N48 -> 932.31967 | Q48: =Q$5*$N48 -> 1030.3956 | R48: =R$5*$N48 -> 1171.5293 | S48: =S$5*$N48 -> 1325.8196 | T48: =T$5*$N48 -> 444.33195 | U48: =U$5*$N48 -> 1698.9866 | V48: =V$5*$N48 -> 8082.2966 | W48: =W$5*$N48 -> 0
A49: =A48 -> Torre | B49: Supraestrutura | C49: G3 | D49: Garagem G4 | E49: Capiteis | H49: 50 | N49: =SUM(O49:W49) -> 0 | O49: =O$5*$N49 -> 0 | P49: =P$5*$N49 -> 0 | Q49: =Q$5*$N49 -> 0 | R49: =R$5*$N49 -> 0 | S49: =S$5*$N49 -> 0 | T49: =T$5*$N49 -> 0 | U49: =U$5*$N49 -> 0 | V49: =V$5*$N49 -> 0 | W49: =W$5*$N49 -> 0
A50: =A5 -> Torre | B50: Supraestrutura | C50: G3 | D50: Garagem G4 | E50: Escadas | H50: 50 | I50: =((0.5816+0.5128)*1.2+0.1123*2.48) -> 1.591784 | J50: =(0.5816+0.5128+(3.01+2.65)*1.2+3.1+3.2*1.2)*1 -> 14.8264 | N50: =SUM(O50:W50) -> 105.3892 | O50: =O$5*$N50 -> 0.59317697 | P50: =P$5*$N50 -> 6.6529705 | Q50: =Q$5*$N50 -> 7.352834 | R50: =R$5*$N50 -> 8.3599546 | S50: =S$5*$N50 -> 9.4609593 | T50: =T$5*$N50 -> 3.170723 | U50: =U$5*$N50 -> 12.123855 | V50: =V$5*$N50 -> 57.674725 | W50: =W$5*$N50 -> 0
D51: ="TOTAL - "&UPPER(C50) -> TOTAL - G3 | I51: =SUM(I46:I50) -> 284.09178 | J51: =SUM(J46:J50) -> 1515.5264 | K51: =SUM(K46:K50) -> 0 | L51: =SUM(L46:L50) -> 0 | M51: =SUM(M46:M50) -> 0 | N51: =SUM(N46:N50) -> 36682.5 | O51: =SUM(O46:O50) -> 206.46532 | P51: =SUM(P46:P50) -> 2315.6794 | ... W51: =SUM(W46:W50) -> 0
A52: =A5 -> Torre | B52: Supraestrutura | C52: Mezanino G3 | D52: Garagem G5 | E52: Pilares | H52: 50 | I52: 79 | J52: 506.1 | N52: =SUM(O52:W52) -> 19129.136 | O52: =O$5*$N52 -> 107.66723 | P52: =P$5*$N52 -> 1207.5771 | Q52: =Q$5*$N52 -> 1334.6089 | R52: =R$5*$N52 -> 1517.4108 | S52: =S$5*$N52 -> 1717.2536 | T52: =T$5*$N52 -> 575.51621 | U52: =U$5*$N52 -> 2200.5943 | V52: =V$5*$N52 -> 10468.508 | W52: =W$5*$N52 -> 0
A53: =A5 -> Torre | B53: Supraestrutura | C53: Mezanino G3 | D53: Garagem G5 | E53: Vigas | H53: 50 | I53: 28.6 | J53: 275.8 | N53: =SUM(O53:W53) -> 6996.2422 | O53: =O$5*$N53 -> 39.377942 | P53: =P$5*$N53 -> 441.6562 | Q53: =Q$5*$N53 -> 488.11651 | R53: =R$5*$N53 -> 554.97402 | S53: =S$5*$N53 -> 628.06402 | T53: =T$5*$N53 -> 210.48785 | U53: =U$5*$N53 -> 804.83982 | V53: =V$5*$N53 -> 3828.7258 | W53: =W$5*$N53 -> 0
A54: =A5 -> Torre | B54: Supraestrutura | C54: Mezanino G3 | D54: Garagem G5 | E54: Lajes | H54: 50 | I54: 177.9 | J54: 743.5 | N54: =SUM(O54:W54) -> 17692.37 | O54: =O$5*$N54 -> 99.580475 | P54: =P$5*$N54 -> 1116.8774 | Q54: =Q$5*$N54 -> 1234.368 | R54: =R$5*$N54 -> 1403.4399 | S54: =S$5*$N54 -> 1588.2728 | T54: =T$5*$N54 -> 532.28988 | U54: =U$5*$N54 -> 2035.3103 | V54: =V$5*$N54 -> 9682.2311 | W54: =W$5*$N54 -> 0
A55: =A54 -> Torre | B55: Supraestrutura | C55: Mezanino G3 | D55: Garagem G5 | E55: Capiteis | H55: 50 | N55: =SUM(O55:W55) -> 0 | O55: =O$5*$N55 -> 0 | P55: =P$5*$N55 -> 0 | Q55: =Q$5*$N55 -> 0 | R55: =R$5*$N55 -> 0 | S55: =S$5*$N55 -> 0 | T55: =T$5*$N55 -> 0 | U55: =U$5*$N55 -> 0 | V55: =V$5*$N55 -> 0 | W55: =W$5*$N55 -> 0
A56: =A5 -> Torre | B56: Supraestrutura | C56: Mezanino G3 | D56: Garagem G5 | E56: Escadas | H56: 50 | I56: =((0.5816+0.5128)*1.2+0.1123*2.48) -> 1.591784 | J56: =(0.5816+0.5128+(3.01+2.65)*1.2+3.1+3.2*1.2)*1 -> 14.8264 | N56: =SUM(O56:W56) -> 126.25156 | O56: =O$5*$N56 -> 0.71059957 | P56: =P$5*$N56 -> 7.9699621 | Q56: =Q$5*$N56 -> 8.8083674 | R56: =R$5*$N56 -> 10.014853 | S56: =S$5*$N56 -> 11.333808 | T56: =T$5*$N56 -> 3.7983848 | U56: =U$5*$N56 -> 14.523837 | V56: =V$5*$N56 -> 69.09175 | W56: =W$5*$N56 -> 0
D57: ="TOTAL - "&UPPER(C56) -> TOTAL - MEZANINO G3 | I57: =SUM(I52:I56) -> 287.09178 | J57: =SUM(J52:J56) -> 1540.2264 | K57: =SUM(K52:K56) -> 0 | L57: =SUM(L52:L56) -> 0 | M57: =SUM(M52:M56) -> 0 | N57: =SUM(N52:N56) -> 43944 | O57: =SUM(O52:O56) -> 247.33625 | P57: =SUM(P52:P56) -> 2774.0807 | ... W57: =SUM(W52:W56) -> 0
A58: =A56 -> Torre | B58: Supraestrutura | C58: Garagem/Lazer | D58: Lazer 01 | E58: Pilares | H58: 50 | I58: 79 | J58: 506.1 | N58: =SUM(O58:W58) -> 19129.136 | O58: =O$5*$N58 -> 107.66723 | P58: =P$5*$N58 -> 1207.5771 | Q58: =Q$5*$N58 -> 1334.6089 | R58: =R$5*$N58 -> 1517.4108 | S58: =S$5*$N58 -> 1717.2536 | T58: =T$5*$N58 -> 575.51621 | U58: =U$5*$N58 -> 2200.5943 | V58: =V$5*$N58 -> 10468.508 | W58: =W$5*$N58 -> 0
A59: =A5 -> Torre | B59: Supraestrutura | C59: Garagem/Lazer | D59: Lazer 01 | E59: Vigas | H59: 50 | I59: 59.3 | J59: 531.2 | N59: =SUM(O59:W59) -> 6996.2422 | O59: =O$5*$N59 -> 39.377942 | P59: =P$5*$N59 -> 441.6562 | Q59: =Q$5*$N59 -> 488.11651 | R59: =R$5*$N59 -> 554.97402 | S59: =S$5*$N59 -> 628.06402 | T59: =T$5*$N59 -> 210.48785 | U59: =U$5*$N59 -> 804.83982 | V59: =V$5*$N59 -> 3828.7258 | W59: =W$5*$N59 -> 0
A60: =A5 -> Torre | B60: Supraestrutura | C60: Garagem/Lazer | D60: Lazer 01 | E60: Lajes | H60: 50 | I60: 159.9 | J60: 728.9 | N60: =SUM(O60:W60) -> 17692.37 | O60: =O$5*$N60 -> 99.580475 | P60: =P$5*$N60 -> 1116.8774 | Q60: =Q$5*$N60 -> 1234.368 | R60: =R$5*$N60 -> 1403.4399 | S60: =S$5*$N60 -> 1588.2728 | T60: =T$5*$N60 -> 532.28988 | U60: =U$5*$N60 -> 2035.3103 | V60: =V$5*$N60 -> 9682.2311 | W60: =W$5*$N60 -> 0
A61: =A60 -> Torre | B61: Supraestrutura | C61: Garagem/Lazer | D61: Lazer 01 | E61: Capiteis | H61: 50 | N61: =SUM(O61:W61) -> 0 | O61: =O$5*$N61 -> 0 | P61: =P$5*$N61 -> 0 | Q61: =Q$5*$N61 -> 0 | R61: =R$5*$N61 -> 0 | S61: =S$5*$N61 -> 0 | T61: =T$5*$N61 -> 0 | U61: =U$5*$N61 -> 0 | V61: =V$5*$N61 -> 0 | W61: =W$5*$N61 -> 0
A62: =A11 -> Torre | B62: Supraestrutura | C62: Garagem/Lazer | D62: Lazer 01 | E62: Escadas | H62: 50 | I62: =((0.5816+0.5128)*1.2+0.1123*2.48) -> 1.591784 | J62: =(0.5816+0.5128+(3.01+2.65)*1.2+3.1+3.2*1.2)*1 -> 14.8264 | N62: =SUM(O62:W62) -> 126.25156 | O62: =O$5*$N62 -> 0.71059957 | P62: =P$5*$N62 -> 7.9699621 | Q62: =Q$5*$N62 -> 8.8083674 | R62: =R$5*$N62 -> 10.014853 | S62: =S$5*$N62 -> 11.333808 | T62: =T$5*$N62 -> 3.7983848 | U62: =U$5*$N62 -> 14.523837 | V62: =V$5*$N62 -> 69.09175 | W62: =W$5*$N62 -> 0
D63: ="TOTAL - "&UPPER(C62) -> TOTAL - GARAGEM/LAZER | I63: =SUM(I58:I62) -> 299.79178 | J63: =SUM(J58:J62) -> 1781.0264 | K63: =SUM(K58:K62) -> 0 | L63: =SUM(L58:L62) -> 0 | M63: =SUM(M58:M62) -> 0 | N63: =SUM(N58:N62) -> 43944 | O63: =SUM(O58:O62) -> 247.33625 | P63: =SUM(P58:P62) -> 2774.0807 | ... W63: =SUM(W58:W62) -> 0
A64: =A62 -> Torre | B64: Supraestrutura | C64: Patamar Intermediário | D64: Patamar | E64: Pilares | H64: 50 | I64: 70 | J64: 437.1 | N64: =SUM(O64:W64) -> 11022.629 | O64: =O$5*$N64 -> 62.040229 | P64: =P$5*$N64 -> 695.83249 | Q64: =Q$5*$N64 -> 769.03104 | R64: =R$5*$N64 -> 874.36553 | S64: =S$5*$N64 -> 989.51933 | T64: =T$5*$N64 -> 331.62511 | U64: =U$5*$N64 -> 1268.0309 | V64: =V$5*$N64 -> 6032.1848 | W64: =W$5*$N64 -> 0
A65: =A5 -> Torre | B65: Supraestrutura | C65: Patamar Intermediário | D65: Patamar | E65: Vigas | H65: 50 | I65: 7.9 | J65: 76.8 | N65: =SUM(O65:W65) -> 4031.3887 | O65: =O$5*$N65 -> 22.690437 | P65: =P$5*$N65 -> 254.49203 | Q65: =Q$5*$N65 -> 281.26348 | R65: =R$5*$N65 -> 319.78825 | S65: =S$5*$N65 -> 361.90431 | T65: =T$5*$N65 -> 121.28773 | U65: =U$5*$N65 -> 463.76642 | V65: =V$5*$N65 -> 2206.1961 | W65: =W$5*$N65 -> 0
A66: =A5 -> Torre | B66: Supraestrutura | C66: Patamar Intermediário | D66: Patamar | E66: Lajes | H66: 50 | I66: 1.7 | J66: 38.9 | N66: =SUM(O66:W66) -> 10194.733 | O66: =O$5*$N66 -> 57.380461 | P66: =P$5*$N66 -> 643.56935 | Q66: =Q$5*$N66 -> 711.27003 | R66: =R$5*$N66 -> 808.69298 | S66: =S$5*$N66 -> 915.19772 | T66: =T$5*$N66 -> 306.71714 | U66: =U$5*$N66 -> 1172.7906 | V66: =V$5*$N66 -> 5579.1146 | W66: =W$5*$N66 -> 0
A67: =A6 -> Torre | B67: Supraestrutura | C67: Patamar Intermediário | D67: Patamar | E67: Capiteis | H67: 50 | N67: =SUM(O67:W67) -> 0 | O67: =O$5*$N67 -> 0 | P67: =P$5*$N67 -> 0 | Q67: =Q$5*$N67 -> 0 | R67: =R$5*$N67 -> 0 | S67: =S$5*$N67 -> 0 | T67: =T$5*$N67 -> 0 | U67: =U$5*$N67 -> 0 | V67: =V$5*$N67 -> 0 | W67: =W$5*$N67 -> 0
A68: =A5 -> Torre | B68: Supraestrutura | C68: Patamar Intermediário | D68: Patamar | E68: Escadas | H68: 50 | I68: =((0.5816+0.5128)*1.2+0.1123*2.48) -> 1.591784 | J68: =(0.5816+0.5128+(3.01+2.65)*1.2+3.1+3.2*1.2)*1 -> 14.8264 | N68: =SUM(O68:W68) -> 72.748929 | O68: =O$5*$N68 -> 0.40946312 | P68: =P$5*$N68 -> 4.5924676 | Q68: =Q$5*$N68 -> 5.0755752 | R68: =R$5*$N68 -> 5.7707787 | S68: =S$5*$N68 -> 6.5307894 | T68: =T$5*$N68 -> 2.1887129 | U68: =U$5*$N68 -> 8.3689547 | V68: =V$5*$N68 -> 39.812187 | W68: =W$5*$N68 -> 0
D69: ="TOTAL - "&UPPER(C68) -> TOTAL - PATAMAR INTERMEDIÁRIO | I69: =SUM(I64:I68) -> 81.191784 | J69: =SUM(J64:J68) -> 567.6264 | K69: =SUM(K64:K68) -> 0 | L69: =SUM(L64:L68) -> 0 | M69: =SUM(M64:M68) -> 0 | N69: =SUM(N64:N68) -> 25321.5 | O69: =SUM(O64:O68) -> 142.52059 | P69: =SUM(P64:P68) -> 1598.4863 | ... W69: =SUM(W64:W68) -> 0
A70: =A66 -> Torre | B70: Supraestrutura | C70: Lazer | D70: Lazer 02 | E70: Pilares | H70: 50 | I70: 70 | J70: 437.1 | N70: =SUM(O70:W70) -> 11022.629 | O70: =O$5*$N70 -> 62.040229 | P70: =P$5*$N70 -> 695.83249 | Q70: =Q$5*$N70 -> 769.03104 | R70: =R$5*$N70 -> 874.36553 | S70: =S$5*$N70 -> 989.51933 | T70: =T$5*$N70 -> 331.62511 | U70: =U$5*$N70 -> 1268.0309 | V70: =V$5*$N70 -> 6032.1848 | W70: =W$5*$N70 -> 0
A71: =A5 -> Torre | B71: Supraestrutura | C71: Lazer | D71: Lazer 02 | E71: Vigas | H71: 50 | I71: 56.5 | J71: 478.2 | N71: =SUM(O71:W71) -> 4031.3887 | O71: =O$5*$N71 -> 22.690437 | P71: =P$5*$N71 -> 254.49203 | Q71: =Q$5*$N71 -> 281.26348 | R71: =R$5*$N71 -> 319.78825 | S71: =S$5*$N71 -> 361.90431 | T71: =T$5*$N71 -> 121.28773 | U71: =U$5*$N71 -> 463.76642 | V71: =V$5*$N71 -> 2206.1961 | W71: =W$5*$N71 -> 0
A72: =A5 -> Torre | B72: Supraestrutura | C72: Lazer | D72: Lazer 02 | E72: Lajes | H72: 50 | I72: 90.4 | J72: 406.1 | N72: =SUM(O72:W72) -> 10194.733 | O72: =O$5*$N72 -> 57.380461 | P72: =P$5*$N72 -> 643.56935 | Q72: =Q$5*$N72 -> 711.27003 | R72: =R$5*$N72 -> 808.69298 | S72: =S$5*$N72 -> 915.19772 | T72: =T$5*$N72 -> 306.71714 | U72: =U$5*$N72 -> 1172.7906 | V72: =V$5*$N72 -> 5579.1146 | W72: =W$5*$N72 -> 0
A73: =A6 -> Torre | B73: Supraestrutura | C73: Lazer | D73: Lazer 02 | E73: Capiteis | H73: 50 | N73: =SUM(O73:W73) -> 0 | O73: =O$5*$N73 -> 0 | P73: =P$5*$N73 -> 0 | Q73: =Q$5*$N73 -> 0 | R73: =R$5*$N73 -> 0 | S73: =S$5*$N73 -> 0 | T73: =T$5*$N73 -> 0 | U73: =U$5*$N73 -> 0 | V73: =V$5*$N73 -> 0 | W73: =W$5*$N73 -> 0
A74: =A5 -> Torre | B74: Supraestrutura | C74: Lazer | D74: Lazer 02 | E74: Escadas | H74: 50 | I74: =((0.5816+0.5128)*1.2+0.1123*2.48) -> 1.591784 | J74: =(0.5816+0.5128+(3.01+2.65)*1.2+3.1+3.2*1.2)*1 -> 14.8264 | N74: =SUM(O74:W74) -> 72.748929 | O74: =O$5*$N74 -> 0.40946312 | P74: =P$5*$N74 -> 4.5924676 | Q74: =Q$5*$N74 -> 5.0755752 | R74: =R$5*$N74 -> 5.7707787 | S74: =S$5*$N74 -> 6.5307894 | T74: =T$5*$N74 -> 2.1887129 | U74: =U$5*$N74 -> 8.3689547 | V74: =V$5*$N74 -> 39.812187 | W74: =W$5*$N74 -> 0
D75: ="TOTAL - "&UPPER(C74) -> TOTAL - LAZER | I75: =SUM(I70:I74) -> 218.49178 | J75: =SUM(J70:J74) -> 1336.2264 | K75: =SUM(K70:K74) -> 0 | L75: =SUM(L70:L74) -> 0 | M75: =SUM(M70:M74) -> 0 | N75: =SUM(N70:N74) -> 25321.5 | O75: =SUM(O70:O74) -> 142.52059 | P75: =SUM(P70:P74) -> 1598.4863 | ... W75: =SUM(W70:W74) -> 0
A76: =A44 -> Torre | B76: Supraestrutura | C76: Tipo diferenciado | D76: Tipo 01 - Diferenciado | E76: Pilares | H76: 50 | I76: 76.84 | J76: 442.07 | N76: =SUM(O76:W76) -> 15226.473 | O76: =O$5*$N76 -> 85.701318 | P76: =P$5*$N76 -> 961.21118 | Q76: =Q$5*$N76 -> 1062.3264 | R76: =R$5*$N76 -> 1207.8337 | S76: =S$5*$N76 -> 1366.9052 | T76: =T$5*$N76 -> 458.10129 | U76: =U$5*$N76 -> 1751.6363 | V76: =V$5*$N76 -> 8332.7576 | W76: =W$5*$N76 -> 0
A77: =A76 -> Torre | B77: Supraestrutura | C77: Tipo diferenciado | D77: Tipo 01 - Diferenciado | E77: Vigas | F77: ELZ-EX-EST-5201-TP1-R00 | H77: 50 | I77: 22.75 | J77: 212.09 | N77: =SUM(O77:W77) -> 6172.9239 | O77: =O$5*$N77 -> 34.743943 | P77: =P$5*$N77 -> 389.68207 | Q77: =Q$5*$N77 -> 430.67492 | R77: =R$5*$N77 -> 489.66464 | S77: =S$5*$N77 -> 554.15339 | T77: =T$5*$N77 -> 185.71762 | U77: =U$5*$N77 -> 710.1262 | V77: =V$5*$N77 -> 3378.1611 | W77: =W$5*$N77 -> 0
A78: =A77 -> Torre | B78: Supraestrutura | C78: Tipo diferenciado | D78: Tipo 01 - Diferenciado | E78: Lajes | H78: 50 | I78: 38.63 | J78: 326.78 | N78: =SUM(O78:W78) -> 5381.1603 | O78: =O$5*$N78 -> 30.287548 | P78: =P$5*$N78 -> 339.69991 | Q78: =Q$5*$N78 -> 375.43486 | R78: =R$5*$N78 -> 426.85832 | S78: =S$5*$N78 -> 483.0755 | T78: =T$5*$N78 -> 161.89675 | U78: =U$5*$N78 -> 619.04262 | V78: =V$5*$N78 -> 2944.8648 | W78: =W$5*$N78 -> 0
A79: =A78 -> Torre | B79: Supraestrutura | C79: Tipo diferenciado | D79: Tipo 01 - Diferenciado | E79: Capiteis | H79: 50 | N79: =SUM(O79:W79) -> 0 | O79: =O$5*$N79 -> 0 | P79: =P$5*$N79 -> 0 | Q79: =Q$5*$N79 -> 0 | R79: =R$5*$N79 -> 0 | S79: =S$5*$N79 -> 0 | T79: =T$5*$N79 -> 0 | U79: =U$5*$N79 -> 0 | V79: =V$5*$N79 -> 0 | W79: =W$5*$N79 -> 0
A80: =A78 -> Torre | B80: Supraestrutura | C80: Tipo diferenciado | D80: Tipo 01 - Diferenciado | E80: Escadas | H80: 50 | I80: =((0.5816+0.5128)*1.2+0.1123*2.48) -> 1.591784 | J80: =(0.5816+0.5128+(3.01+2.65)*1.2+3.1+3.2*1.2)*1 -> 14.8264 | N80: =SUM(O80:W80) -> 115.44282 | O80: =O$5*$N80 -> 0.64976323 | P80: =P$5*$N80 -> 7.2876322 | Q80: =Q$5*$N80 -> 8.0542593 | R80: =R$5*$N80 -> 9.1574544 | S80: =S$5*$N80 -> 10.36349 | T80: =T$5*$N80 -> 3.4731948 | U80: =U$5*$N80 -> 13.280412 | V80: =V$5*$N80 -> 63.176619 | W80: =W$5*$N80 -> 0
D81: ="TOTAL - "&UPPER(C80) -> TOTAL - TIPO DIFERENCIADO | I81: =SUM(I76:I80) -> 139.81178 | J81: =SUM(J76:J80) -> 995.7664 | K81: =SUM(K76:K80) -> 0 | L81: =SUM(L76:L80) -> 0 | M81: =SUM(M76:M80) -> 0 | N81: =SUM(N76:N80) -> 26896 | O81: =SUM(O76:O80) -> 151.38257 | P81: =SUM(P76:P80) -> 1697.8808 | ... W81: =SUM(W76:W80) -> 0
A82: =A80 -> Torre | B82: Supraestrutura | C82: Tipo - 8x | D82: Tipo A - 02 | E82: Pilares | H82: 45 | I82: 73.73 | J82: 418.2 | K82: =J82*2 -> 836.4 | N82: =SUM(O82:W82) -> 13690.578 | O82: =O$5*$N82 -> 77.056624 | P82: =P$5*$N82 -> 864.25379 | Q82: =Q$5*$N82 -> 955.16952 | R82: =R$5*$N82 -> 1085.9995 | S82: =S$5*$N82 -> 1229.0254 | T82: =T$5*$N82 -> 411.8926 | U82: =U$5*$N82 -> 1574.9487 | V82: =V$5*$N82 -> 7492.2322 | W82: =W$5*$N82 -> 0
A83: =A82 -> Torre | B83: Supraestrutura | C83: Tipo - 8x | D83: Tipo A - 02 | E83: Vigas | F83: ELZ-EX-EST-5201-TP2-R00 | H83: 45 | I83: 21.475 | J83: 202.025 | K83: =J83*2 -> 404.05 | N83: =SUM(O83:W83) -> 5550.2609 | O83: =O$5*$N83 -> 31.239321 | P83: =P$5*$N83 -> 350.37483 | Q83: =Q$5*$N83 -> 387.23273 | R83: =R$5*$N83 -> 440.27216 | S83: =S$5*$N83 -> 498.25593 | T83: =T$5*$N83 -> 166.98428 | U83: =U$5*$N83 -> 638.49576 | V83: =V$5*$N83 -> 3037.4059 | W83: =W$5*$N83 -> 0
A84: =A83 -> Torre | B84: Supraestrutura | C84: Tipo - 8x | D84: Tipo A - 02 | E84: Lajes | H84: 45 | I84: 30.875 | J84: 266.6375 | K84: =J84*2 -> 533.275 | N84: =SUM(O84:W84) -> 4838.3626 | O84: =O$5*$N84 -> 27.232443 | P84: =P$5*$N84 -> 305.43437 | Q84: =Q$5*$N84 -> 337.56474 | R84: =R$5*$N84 -> 383.80112 | S84: =S$5*$N84 -> 434.34766 | T84: =T$5*$N84 -> 145.56622 | U84: =U$5*$N84 -> 556.59978 | V84: =V$5*$N84 -> 2647.8163 | W84: =W$5*$N84 -> 0
A85: =A84 -> Torre | B85: Supraestrutura | C85: Tipo - 8x | D85: Tipo A - 02 | E85: Abas | H85: 45 | I85: 0 | J85: 0 | K85: =J85*2 -> 0 | N85: =SUM(O85:W85) -> 0 | O85: =O$5*$N85 -> 0 | P85: =P$5*$N85 -> 0 | Q85: =Q$5*$N85 -> 0 | R85: =R$5*$N85 -> 0 | S85: =S$5*$N85 -> 0 | T85: =T$5*$N85 -> 0 | U85: =U$5*$N85 -> 0 | V85: =V$5*$N85 -> 0 | W85: =W$5*$N85 -> 0
A86: =A84 -> Torre | B86: Supraestrutura | C86: Tipo - 8x | D86: Tipo A - 02 | E86: Escadas | H86: 45 | I86: 0.198973 | J86: 1.8533 | K86: =J86*2 -> 3.7066 | N86: =SUM(O86:W86) -> 103.7981 | O86: =O$5*$N86 -> 0.5842216 | P86: =P$5*$N86 -> 6.5525286 | Q86: =Q$5*$N86 -> 7.241826 | R86: =R$5*$N86 -> 8.2337418 | S86: =S$5*$N86 -> 9.3181243 | T86: =T$5*$N86 -> 3.1228536 | U86: =U$5*$N86 -> 11.940817 | V86: =V$5*$N86 -> 56.803992 | W86: =W$5*$N86 -> 0
D87: ="TOTAL - "&UPPER(C86) -> TOTAL - TIPO - 8X | I87: =SUM(I82:I86) -> 126.27897 | J87: =SUM(J82:J86) -> 888.7158 | K87: =SUM(K82:K86) -> 1777.4316 | L87: =SUM(L82:L86) -> 0 | M87: =SUM(M82:M86) -> 0 | N87: =SUM(N82:N86) -> 24183 | O87: =SUM(O82:O86) -> 136.11261 | P87: =SUM(P82:P86) -> 1526.6155 | ... W87: =SUM(W82:W86) -> 0
A88: =A86 -> Torre | B88: Supraestrutura | C88: Tipo - 8x | D88: Tipo A - 03 | E88: Pilares | H88: 45 | I88: 73.73 | J88: 418.2 | N88: 12908.195 | O88: =O$5*$N88 -> 0 | P88: =P$5*$N88 -> 0 | Q88: =Q$5*$N88 -> 900.58389 | R88: =R$5*$N88 -> 1023.9372 | S88: =S$5*$N88 -> 1158.7896 | T88: =T$5*$N88 -> 388.35394 | U88: =U$5*$N88 -> 1484.9442 | V88: =V$5*$N88 -> 7064.0692 | W88: =W$5*$N88 -> 0 | X88: 0.56612407
A89: =A88 -> Torre | B89: Supraestrutura | C89: Tipo - 8x | D89: Tipo A - 03 | E89: Vigas | F89: ELZ-EX-EST-5201-TP2-R00 | H89: 45 | I89: 21.475 | J89: 202.025 | N89: 5233.0769 | O89: =O$5*$N89 -> 0 | P89: =P$5*$N89 -> 0 | Q89: =Q$5*$N89 -> 365.10332 | R89: =R$5*$N89 -> 415.11167 | S89: =S$5*$N89 -> 469.78181 | T89: =T$5*$N89 -> 157.44154 | U89: =U$5*$N89 -> 602.00727 | V89: =V$5*$N89 -> 2863.8255 | W89: =W$5*$N89 -> 0 | X89: 0.22951085
A90: =A89 -> Torre | B90: Supraestrutura | C90: Tipo - 8x | D90: Tipo A - 03 | E90: Lajes | H90: 45 | I90: 30.875 | J90: 266.6375 | N90: 4561.8619 | O90: =O$5*$N90 -> 0 | P90: =P$5*$N90 -> 0 | Q90: =Q$5*$N90 -> 318.27373 | R90: =R$5*$N90 -> 361.86781 | S90: =S$5*$N90 -> 409.52574 | T90: =T$5*$N90 -> 137.24746 | U90: =U$5*$N90 -> 524.79145 | V90: =V$5*$N90 -> 2496.5 | W90: =W$5*$N90 -> 0 | X90: 0.20007289
A91: =A90 -> Torre | B91: Supraestrutura | C91: Tipo - 8x | D91: Tipo A - 03 | E91: Abas | H91: 45 | I91: 0 | J91: 0 | N91: 0 | O91: =O$5*$N91 -> 0 | P91: =P$5*$N91 -> 0 | Q91: =Q$5*$N91 -> 0 | R91: =R$5*$N91 -> 0 | S91: =S$5*$N91 -> 0 | T91: =T$5*$N91 -> 0 | U91: =U$5*$N91 -> 0 | V91: =V$5*$N91 -> 0 | W91: =W$5*$N91 -> 0 | X91: 0
A92: =A90 -> Torre | B92: Supraestrutura | C92: Tipo - 8x | D92: Tipo A - 03 | E92: Escadas | H92: 45 | I92: 0.198973 | J92: 1.8533 | N92: 97.866294 | O92: =O$5*$N92 -> 0 | P92: =P$5*$N92 -> 0 | Q92: =Q$5*$N92 -> 6.8279731 | R92: =R$5*$N92 -> 7.7632034 | S92: =S$5*$N92 -> 8.7856161 | T92: =T$5*$N92 -> 2.94439 | U92: =U$5*$N92 -> 11.258428 | V92: =V$5*$N92 -> 53.557781 | W92: =W$5*$N92 -> 0 | X92: 0.0042921931
D93: ="TOTAL - "&UPPER(C92) -> TOTAL - TIPO - 8X | I93: =SUM(I88:I92) -> 126.27897 | J93: =SUM(J88:J92) -> 888.7158 | K93: =SUM(K88:K92) -> 0 | L93: =SUM(L88:L92) -> 0 | M93: =SUM(M88:M92) -> 0 | N93: =SUM(N88:N92) -> 22801 | O93: =SUM(O88:O92) -> 0 | P93: =SUM(P88:P92) -> 0 | ... W93: =SUM(W88:W92) -> 0
A94: =A92 -> Torre | B94: Supraestrutura | C94: Tipo - 8x | D94: Tipo A - 04 | E94: Pilares | H94: 45 | I94: 73.73 | J94: 418.2 | N94: 12296.215 | O94: =O$5*$N94 -> 0 | P94: =P$5*$N94 -> 0 | Q94: =Q$5*$N94 -> 857.88703 | R94: =R$5*$N94 -> 975.39216 | S94: =S$5*$N94 -> 1103.8512 | T94: =T$5*$N94 -> 369.942 | U94: =U$5*$N94 -> 1414.5427 | V94: =V$5*$N94 -> 6729.1603 | W94: =W$5*$N94 -> 0 | X94: 0.56612407
A95: =A94 -> Torre | B95: Supraestrutura | C95: Tipo - 8x | D95: Tipo A - 04 | E95: Vigas | F95: ELZ-EX-EST-5201-TP2-R00 | H95: 45 | I95: 21.475 | J95: 202.025 | N95: 4984.9757 | O95: =O$5*$N95 -> 0 | P95: =P$5*$N95 -> 0 | Q95: =Q$5*$N95 -> 347.7937 | R95: =R$5*$N95 -> 395.43114 | S95: =S$5*$N95 -> 447.50936 | T95: =T$5*$N95 -> 149.9772 | U95: =U$5*$N95 -> 573.46599 | V95: =V$5*$N95 -> 2728.051 | W95: =W$5*$N95 -> 0 | X95: 0.22951085
A96: =A95 -> Torre | B96: Supraestrutura | C96: Tipo - 8x | D96: Tipo A - 04 | E96: Lajes | H96: 45 | I96: 30.875 | J96: 266.6375 | N96: 4345.5831 | O96: =O$5*$N96 -> 0 | P96: =P$5*$N96 -> 0 | Q96: =Q$5*$N96 -> 303.18431 | R96: =R$5*$N96 -> 344.71158 | S96: =S$5*$N96 -> 390.11005 | T96: =T$5*$N96 -> 130.74053 | U96: =U$5*$N96 -> 499.91098 | V96: =V$5*$N96 -> 2378.1404 | W96: =W$5*$N96 -> 0 | X96: 0.20007289
A97: =A96 -> Torre | B97: Supraestrutura | C97: Tipo - 8x | D97: Tipo A - 04 | E97: Abas | H97: 45 | I97: 0 | J97: 0 | N97: 0 | O97: =O$5*$N97 -> 0 | P97: =P$5*$N97 -> 0 | Q97: =Q$5*$N97 -> 0 | R97: =R$5*$N97 -> 0 | S97: =S$5*$N97 -> 0 | T97: =T$5*$N97 -> 0 | U97: =U$5*$N97 -> 0 | V97: =V$5*$N97 -> 0 | W97: =W$5*$N97 -> 0 | X97: 0
A98: =A96 -> Torre | B98: Supraestrutura | C98: Tipo - 8x | D98: Tipo A - 04 | E98: Escadas | H98: 45 | I98: 0.198973 | J98: 1.8533 | N98: 93.226433 | O98: =O$5*$N98 -> 0 | P98: =P$5*$N98 -> 0 | Q98: =Q$5*$N98 -> 6.5042576 | R98: =R$5*$N98 -> 7.3951483 | S98: =S$5*$N98 -> 8.3690882 | T98: =T$5*$N98 -> 2.8047959 | U98: =U$5*$N98 -> 10.724664 | V98: =V$5*$N98 -> 51.018596 | W98: =W$5*$N98 -> 0 | X98: 0.0042921931
D99: ="TOTAL - "&UPPER(C98) -> TOTAL - TIPO - 8X | I99: =SUM(I94:I98) -> 126.27897 | J99: =SUM(J94:J98) -> 888.7158 | K99: =SUM(K94:K98) -> 0 | L99: =SUM(L94:L98) -> 0 | M99: =SUM(M94:M98) -> 0 | N99: =SUM(N94:N98) -> 21720 | O99: =SUM(O94:O98) -> 0 | P99: =SUM(P94:P98) -> 0 | ... W99: =SUM(W94:W98) -> 0
A100: =A98 -> Torre | B100: Supraestrutura | C100: Tipo - 8x | D100: Tipo A - 05 | E100: Pilares | H100: 45 | I100: 73.73 | J100: 418.2 | N100: 11293.043 | O100: =O$5*$N100 -> 0 | P100: =P$5*$N100 -> 0 | Q100: =Q$5*$N100 -> 787.89735 | R100: =R$5*$N100 -> 895.81597 | S100: =S$5*$N100 -> 1013.7948 | T100: =T$5*$N100 -> 339.76073 | U100: =U$5*$N100 -> 1299.1389 | V100: =V$5*$N100 -> 6180.1699 | W100: =W$5*$N100 -> 0 | X100: 0.56612407
...

Sheet Cálculo de apoio
E1: FUNDAÇÃO
A2: Pavimento | B2: Etapa | C2: Projeto | D2: Concreto | E2: Forma Convencional | F2: Forma Nervurada | G2: Cubeta inteira | H2: Meia Cubeta | I2: Total Aço kg | J2: Ø5.0mm 0,154 kg/m | K2: Ø6.3mm 0,245 kg/m | L2: Ø8.0mm 0,395 kg/m | M2: Ø10.0mm 0,617 kg/m | N2: Ø12.5mm 0,963 kg/m | O2: Ø16.0mm 1,578 kg/m | P2: Ø20.0mm 2,466 kg/m | Q2: Ø25.0mm 3,853 kg/m
A3: Fundação | B3: Vigas | C3: PR-1248-01-CIS-VI-01-R01 | D3: 12.7 | E3: 138.9 | I3: =SUM(J3:Q3) -> 2452.7273 | L3: =459/1.1 -> 417.27273 | M3: =1217/1.1 -> 1106.3636 | N3: =470/1.1 -> 427.27273 | O3: =552/1.1 -> 501.81818
A4: Fundação | B4: Pilares | C4: PR-1248-01-CIS-PI-01-R00 | D4: 0.7 | E4: 8.3 | I4: =SUM(J4:Q4) -> 177.27273 | K4: =8/1.1 -> 7.2727273 | L4: =49/1.1 -> 44.545455 | M4: =138/1.1 -> 125.45455
A5: Fundação | B5: Laje de fundo | C5: PR-1248-01-CIS-LA-01-R01 | D5: ='Fund. Rasa | Contenção'!AG75 -> 4.7376 | E5: ='Fund. Rasa | Contenção'!AD75 -> 0 | I5: =SUM(J5:Q5) -> 393.45455 | L5: =(93.6+73.8+78.1)/1.1 -> 223.18182 | M5: =49.9/1.1 -> 45.363636 | N5: =137.4/1.1 -> 124.90909
A6: Fundação | B6: Laje de cobertura | C6: PR-1248-01-CIS-LA-02-R01 | D6: ='Fund. Rasa | Contenção'!AG76 -> 4.632 | E6: ='Fund. Rasa | Contenção'!AD76 -> 28.95 | I6: =SUM(J6:Q6) -> 380.27273 | L6: =(71.2+1.8+68.3+77.2)/1.1 -> 198.63636 | M6: =60.5/1.1 -> 55 | N6: =139.3/1.1 -> 126.63636
A7: Fundação | B7: Pescoço Alçapão | C7: PR-1248-01-CIS-FO-01-R02 | D7: ='Fund. Rasa | Contenção'!AG73+'Fund. Rasa | Contenção'!AG74 -> 0.41216 | E7: ='Fund. Rasa | Contenção'!AD73+'Fund. Rasa | Contenção'!AD74 -> 5.152 | I7: =SUM(J7:Q7) -> 15.454545 | J7: =11/1.1 -> 10 | M7: =6/1.1 -> 5.4545455
A8: TÉRREO | B8: CISTERNA | C8: SOMATÓRIO | D8: =SUM(D3:D7) -> 23.18176 | E8: =SUM(E3:E7) -> 181.302 | F8: =SUM(F3:F7) -> 0 | G8: =SUM(G3:G7) -> 0 | H8: =SUM(H3:H7) -> 0 | I8: =SUM(I3:I7) -> 3419.1818 | J8: =SUM(J3:J7) -> 10 | K8: =SUM(K3:K7) -> 7.2727273 | ... Q8: =SUM(Q3:Q7) -> 0

Sheet Escoramento
A1: CLIENTE | B1: =CAPA!C2 -> Elizabeth II Royal Home
A2: OBRA | B2: =CAPA!C3 -> Gessele
A3: REVISÃO | B3: =CAPA!C4 -> R00
A4: PLANILHA DE ESCORAMENTO
A5: PAVIMENTO | B5: ÁREA | C5: R$ | D5: R$ | F5: ESCORAMENTO (PARA 1 MÊS)
C6: ESCOR. / m2 | D6: DIA / m2 | E6: DIAS CORRIDOS | F6: 1 | G6: 0.75 | H6: 0.5 | I6: 0.25 | J6: TRAV/MÊS / M2 | K6: TRAV.
A7: 1º PAVTO. TÉRREO | B7: 784.58 | C7: 12.606307 | D7: =C7/30 -> 0.42021022 | E7: 40 | F7: =(E7+7)*B7*D7 -> 15495.361 | G7: 0 | J7: 13.716359 | K7: =(J7*($E7)*B7)/30 -> 14348.775
A8: MEZANINO 1º PAVTO - GARAGEM. | B8: 801.15 | C8: 12.606307 | D8: =C8/30 -> 0.42021022 | E8: 50 | F8: =(E8+7)*B8*D8 -> 19189.131 | G8: =(B7*D7*0.75)*7 -> 1730.8648 | H8: =(B7*D7*0.5)*7 -> 1153.9099 | I8: =(B7*D7*0.25)*7 -> 576.95493 | J8: 19.6 | K8: =(J8*($E8)*B8)/30 -> 26170.9
A9: 2º PAVTO. - GARAGEM | B9: 878.5 | C9: 11.665145 | D9: =C9/30 -> 0.38883816 | E9: 50 | F9: =(E9+7)*B9*D9 -> 19470.876 | G9: =(B8*D8*0.75)*7 -> 1767.4199 | H9: =(B8*D8*0.5)*7 -> 1178.28 | I9: =(B8*D8*0.25)*7 -> 589.13998 | J9: 19.6 | K9: =(J9*($E9)*B9)/30 -> 28697.667
A10: MEZANINO 2º PAVTO - GARAGEM. | B10: 878.5 | C10: 11.665145 | D10: =C10/30 -> 0.38883816 | E10: 50 | F10: =(E10+7)*B10*D10 -> 19470.876 | G10: =(B9*D9*0.75)*7 -> 1793.3702 | H10: =(B9*D9*0.5)*7 -> 1195.5801 | I10: =(B9*D9*0.25)*7 -> 597.79006 | J10: 19.6 | K10: =(J10*($E10)*B10)/30 -> 28697.667
A11: 3º PAVTO. - GARAGEM | B11: 878.5 | C11: 11.665145 | D11: =C11/30 -> 0.38883816 | E11: 50 | F11: =(E11+7)*B11*D11 -> 19470.876 | G11: =(B10*D10*0.75)*7 -> 1793.3702 | H11: =(B10*D10*0.5)*7 -> 1195.5801 | I11: =(B10*D10*0.25)*7 -> 597.79006 | J11: 19.6 | K11: =(J11*($E11)*B11)/30 -> 28697.667
A12: MEZANINO 3º PAVTO - GARAGEM. | B12: 892.45 | C12: 11.665145 | D12: =C12/30 -> 0.38883816 | E12: 50 | F12: =(E12+7)*B12*D12 -> 19780.061 | G12: =(B11*D11*0.75)*7 -> 1793.3702 | H12: =(B11*D11*0.5)*7 -> 1195.5801 | I12: =(B11*D11*0.25)*7 -> 597.79006 | J12: 19.6 | K12: =(J12*($E12)*B12)/30 -> 29153.367
A13: 4º PAVTO. - GARAGEM/LAZER | B13: 892.45 | C13: 12.423854 | D13: =C13/30 -> 0.41412846 | E13: 45 | F13: =(E13+7)*B13*D13 -> 19218.625 | G13: =(B12*D12*0.75)*7 -> 1821.8477 | H13: =(B12*D12*0.5)*7 -> 1214.5652 | I13: =(B12*D12*0.25)*7 -> 607.28258 | J13: 15.057641 | K13: =(J13*($E13)*B13)/30 -> 20157.287
A14: 5º PAVTO. - LAZER | B14: 499.27 | C14: 12.423854 | D14: =C14/30 -> 0.41412846 | E14: 45 | F14: =(E14+7)*B14*D14 -> 10751.62 | G14: =(B13*D13*0.75)*7 -> 1940.3419 | H14: =(B13*D13*0.5)*7 -> 1293.5613 | I14: =(B13*D13*0.25)*7 -> 646.78065 | J14: 15.057641 | K14: =(J14*($E14)*B14)/30 -> 11276.742
A15: 6º PAVTO. - TIPO DIFERENCIADO | B15: 345.53 | C15: 17.010506 | D15: =C15/30 -> 0.56701686 | E15: 18 | F15: =(E15+7)*B15*D15 -> 4898.0334 | G15: =(B14*D14*0.75)*7 -> 1085.5001 | H15: =(B14*D14*0.5)*7 -> 723.6667 | I15: =(B14*D14*0.25)*7 -> 361.83335 | J15: 15.057641 | K15: =(J15*($E15)*B15)/30 -> 3121.7199
A16: 7º AO 14º PAVTO. - TIPO 8X | B16: 303.41 | C16: 17.010506 | D16: =C16/30 -> 0.56701686 | E16: 17 | F16: =(E16+7)*B16*D16 -> 4128.926 | G16: =(B15*D15*0.75)*7 -> 1028.587 | H16: =(B15*D15*0.5)*7 -> 685.72467 | I16: =(B15*D15*0.25)*7 -> 342.86234 | J16: 15.057641 | K16: =(J16*($E16)*B16)/30 -> 2588.8953
A17: 7º AO 14º PAVTO. - TIPO 8X | B17: 303.41 | C17: 17.010506 | D17: =C17/30 -> 0.56701686 | E17: 17 | F17: =(E17+7)*B17*D17 -> 4128.926 | G17: =(B16*D16*0.75)*7 -> 903.20257 | H17: =(B16*D16*0.5)*7 -> 602.13505 | I17: =(B16*D16*0.25)*7 -> 301.06752 | J17: 15.057641 | K17: =(J17*($E17)*B17)/30 -> 2588.8953
A18: 7º AO 14º PAVTO. - TIPO 8X | B18: 303.41 | C18: 17.010506 | D18: =C18/30 -> 0.56701686 | E18: 17 | F18: =(E18+7)*B18*D18 -> 4128.926 | G18: =(B17*D17*0.75)*7 -> 903.20257 | H18: =(B17*D17*0.5)*7 -> 602.13505 | I18: =(B17*D17*0.25)*7 -> 301.06752 | J18: 15.057641 | K18: =(J18*($E18)*B18)/30 -> 2588.8953
A19: 7º AO 14º PAVTO. - TIPO 8X | B19: 303.41 | C19: 17.010506 | D19: =C19/30 -> 0.56701686 | E19: 17 | F19: =(E19+7)*B19*D19 -> 4128.926 | G19: =(B18*D18*0.75)*7 -> 903.20257 | H19: =(B18*D18*0.5)*7 -> 602.13505 | I19: =(B18*D18*0.25)*7 -> 301.06752 | J19: 15.057641 | K19: =(J19*($E19)*B19)/30 -> 2588.8953
... A23: 7º AO 14º PAVTO. - TIPO 8X | B23: 303.41 | C23: 17.010506 | D23: =C23/30 -> 0.56701686 | E23: 17 | F23: =(E23+7)*B23*D23 -> 4128.926 | G23: =(B22*D22*0.75)*7 -> 903.20257 | H23: =(B22*D22*0.5)*7 -> 602.13505 | I23: =(B22*D22*0.25)*7 -> 301.06752 | J23: 15.057641 | K23: =(J23*($E23)*B23)/30 -> 2588.8953
A24: 15º AO 36º PAVTO. - PENTHOUSE | B24: 289.77136 | C24: 11.466294 | D24: =C24/30 -> 0.3822098 | E24: 17 | F24: =(E24+7)*B24*D24 -> 2658.0829 | G24: =(B16*D16*0.75)*7 -> 903.20257 | H24: =(B16*D16*0.5)*7 -> 602.13505 | I24: =(B16*D16*0.25)*7 -> 301.06752 | J24: 15.057641 | K24: =(J24*($E24)*B24)/30 -> 2472.5214
A25: 15º AO 36º PAVTO. - PENTHOUSE | B25: 289.77136 | C25: 11.466294 | D25: =C25/30 -> 0.3822098 | E25: 17 | F25: =(E25+7)*B25*D25 -> 2658.0829 | G25: =(B24*D24*0.75)*7 -> 581.45564 | H25: =(B24*D24*0.5)*7 -> 387.63709 | I25: =(B24*D24*0.25)*7 -> 193.81855 | J25: 15.057641 | K25: =(J25*($E25)*B25)/30 -> 2472.5214
A26: 15º AO 36º PAVTO. - PENTHOUSE | B26: 289.77136 | C26: 11.466294 | D26: =C26/30 -> 0.3822098 | E26: 17 | F26: =(E26+7)*B26*D26 -> 2658.0829 | G26: =(B25*D25*0.75)*7 -> 581.45564 | H26: =(B25*D25*0.5)*7 -> 387.63709 | I26: =(B25*D25*0.25)*7 -> 193.81855 | J26: 15.057641 | K26: =(J26*($E26)*B26)/30 -> 2472.5214
A27: 15º AO 36º PAVTO. - PENTHOUSE | B27: 289.77136 | C27: 11.466294 | D27: =C27/30 -> 0.3822098 | E27: 17 | F27: =(E27+7)*B27*D27 -> 2658.0829 | G27: =(B26*D26*0.75)*7 -> 581.45564 | H27: =(B26*D26*0.5)*7 -> 387.63709 | I27: =(B26*D26*0.25)*7 -> 193.81855 | J27: 15.057641 | K27: =(J27*($E27)*B27)/30 -> 2472.5214
A28: 15º AO 36º PAVTO. - PENTHOUSE | B28: 289.77136 | C28: 11.466294 | D28: =C28/30 -> 0.3822098 | E28: 17 | F28: =(E28+7)*B28*D28 -> 2658.0829 | G28: =(B27*D27*0.75)*7 -> 581.45564 | H28: =(B27*D27*0.5)*7 -> 387.63709 | I28: =(B27*D27*0.25)*7 -> 193.81855 | J28: 15.057641 | K28: =(J28*($E28)*B28)/30 -> 2472.5214
A29: 15º AO 36º PAVTO. - PENTHOUSE | B29: 289.77136 | C29: 11.466294 | D29: =C29/30 -> 0.3822098 | E29: 17 | F29: =(E29+7)*B29*D29 -> 2658.0829 | G29: =(B28*D28*0.75)*7 -> 581.45564 | H29: =(B28*D28*0.5)*7 -> 387.63709 | I29: =(B28*D28*0.25)*7 -> 193.81855 | J29: 15.057641 | K29: =(J29*($E29)*B29)/30 -> 2472.5214
A30: 15º AO 36º PAVTO. - PENTHOUSE | B30: 289.77136 | C30: 11.466294 | D30: =C30/30 -> 0.3822098 | E30: 17 | F30: =(E30+7)*B30*D30 -> 2658.0829 | G30: =(B29*D29*0.75)*7 -> 581.45564 | H30: =(B29*D29*0.5)*7 -> 387.63709 | I30: =(B29*D29*0.25)*7 -> 193.81855 | J30: 15.057641 | K30: =(J30*($E30)*B30)/30 -> 2472.5214
A31: 15º AO 36º PAVTO. - PENTHOUSE | B31: 289.77136 | C31: 11.466294 | D31: =C31/30 -> 0.3822098 | E31: 17 | F31: =(E31+7)*B31*D31 -> 2658.0829 | G31: =(B30*D30*0.75)*7 -> 581.45564 | H31: =(B30*D30*0.5)*7 -> 387.63709 | I31: =(B30*D30*0.25)*7 -> 193.81855 | J31: 15.057641 | K31: =(J31*($E31)*B31)/30 -> 2472.5214
A32: 15º AO 36º PAVTO. - PENTHOUSE | B32: 289.77136 | C32: 11.466294 | D32: =C32/30 -> 0.3822098 | E32: 17 | F32: =(E32+7)*B32*D32 -> 2658.0829 | G32: =(B31*D31*0.75)*7 -> 581.45564 | H32: =(B31*D31*0.5)*7 -> 387.63709 | I32: =(B31*D31*0.25)*7 -> 193.81855 | J32: 15.057641 | K32: =(J32*($E32)*B32)/30 -> 2472.5214
A33: 15º AO 36º PAVTO. - PENTHOUSE | B33: 289.77136 | C33: 11.466294 | D33: =C33/30 -> 0.3822098 | E33: 17 | F33: =(E33+7)*B33*D33 -> 2658.0829 | G33: =(B32*D32*0.75)*7 -> 581.45564 | H33: =(B32*D32*0.5)*7 -> 387.63709 | I33: =(B32*D32*0.25)*7 -> 193.81855 | J33: 15.057641 | K33: =(J33*($E33)*B33)/30 -> 2472.5214
A34: 15º AO 36º PAVTO. - PENTHOUSE | B34: 289.77136 | C34: 11.466294 | D34: =C34/30 -> 0.3822098 | E34: 17 | F34: =(E34+7)*B34*D34 -> 2658.0829 | G34: =(B33*D33*0.75)*7 -> 581.45564 | H34: =(B33*D33*0.5)*7 -> 387.63709 | I34: =(B33*D33*0.25)*7 -> 193.81855 | J34: 15.057641 | K34: =(J34*($E34)*B34)/30 -> 2472.5214
A35: 15º AO 36º PAVTO. - PENTHOUSE | B35: 289.77136 | C35: 11.466294 | D35: =C35/30 -> 0.3822098 | E35: 17 | F35: =(E35+7)*B35*D35 -> 2658.0829 | G35: =(B34*D34*0.75)*7 -> 581.45564 | H35: =(B34*D34*0.5)*7 -> 387.63709 | I35: =(B34*D34*0.25)*7 -> 193.81855 | J35: 15.057641 | K35: =(J35*($E35)*B35)/30 -> 2472.5214
A36: 15º AO 36º PAVTO. - PENTHOUSE | B36: 289.77136 | C36: 11.466294 | D36: =C36/30 -> 0.3822098 | E36: 17 | F36: =(E36+7)*B36*D36 -> 2658.0829 | G36: =(B35*D35*0.75)*7 -> 581.45564 | H36: =(B35*D35*0.5)*7 -> 387.63709 | I36: =(B35*D35*0.25)*7 -> 193.81855 | J36: 15.057641 | K36: =(J36*($E36)*B36)/30 -> 2472.5214
... A49: 40º PAVTO - BARRILETE | B49: 73.72 | C49: 17.010506 | D49: =C49/30 -> 0.56701686 | E49: 14 | F49: =(E49+7)*B49*D49 -> 877.81014 | G49: =(B48*D48*0.75)*7 -> 559.44048 | H49: =(B48*D48*0.5)*7 -> 372.96032 | I49: =(B48*D48*0.25)*7 -> 186.48016 | J49: 8.7500862 | K49: =(J49*($E49)*B49)/30 -> 301.0263
A50: 41º AO 42º PAVTO - COBERTURA/BARRILETE | B50: 73.72 | C50: 11.466551 | D50: =C50/30 -> 0.38221836 | E50: 14 | F50: =(E50+7)*B50*D50 -> 591.71989 | G50: =(B49*D49*0.75)*7 -> 219.45254 | H50: =(B49*D49*0.5)*7 -> 146.30169 | J50: 15.057978 | K50: =(J50*($E50)*B50)/30 -> 518.03459
A51: 43º PAVTO - RESERVATÓRIO | B51: 73.72 | C51: 78.097189 | D51: =C51/30 -> 2.6032396 | E51: 14 | F51: =(E51+7)*B51*D51 -> 4030.1274 | G51: =(B50*D50*0.75)*7 -> 147.92997 | H51: =(B50*D50*0.5)*7 -> 98.619981 | J51: 119.68702 | K51: =(J51*($E51)*B51)/30 -> 4117.5528
F52: =(E52+7)*B52*D52 -> 0 | G52: =(B51*D51*0.75)*7 -> 1007.5318 | H52: =(B51*D51*0.5)*7 -> 671.68789 | K52: =(J52*($E52)*B52)/30 -> 0
A54: ÍNDICE | G54: PREÇO DO CIMBRAMENTO POR M2 | K54: =SUM(F6:I52,K6:K52)/SUM(B5:B52) -> 36.16532
A55: Descrição | B55: R$ ESCOR. / m2 | C55: TRAV/MÊS / M2 | D55: DIAS CORRIDOS | G55: ART | K55: 1250
A56: Térreo | B56: 12.61 | C56: 13.72 | D56: 40 | G56: FRETE DE IDA | K56: =1100+450 -> 1550
A57: Garagem | B57: 11.67 | C57: 19.6 | D57: 50 | G57: FRETE DE VOLTA | K57: =1100+450 -> 1550
A58: Lazer | B58: 17.01 | C58: 15.057641 | D58: 45 | G58: FRETE / M2 | K58: =SUM(K55:K57)/SUM(B5:B52) -> 0.25970661
A59: Tipo Dif | B59: 17.01 | C59: 15.057641 | D59: 18 | G59: TOTAL / M2 | K59: =K58+K54 -> 36.425027
A60: Tipo | B60: 11.47 | C60: 15.057641 | D60: 17
A61: Casa de máquinas | B61: 11.47 | C61: 8.75 | D61: 14
A62: Barrilete e Reservatórios | B62: 78.1 | C62: 119.68702 | D62: 14

Sheet Ger_Executivo_Manual
H4: PROJETO: | I4: Electra Towers | O4: REVISÃO: | P4: DATA
H5: EMPRESA: | I5: Thozen | O5: R00
A6: Unidade Construtiva | B6: Célula Construtiva | C6: Etapa | D6: Subetapa | E6: Serviço | G6: GERENCIAMENTO EXECUTIVO
A7: 0 | B7: 0 | C7: 0 | D7: 0 | E7: 0 | G7: EAP | H7: NIVEL | I7: Item | J7: Descrição | K7: Unidade | L7: Quant. | M7: Preço un | N7: Total | O7: Considerações | P7: Situação
A8: 0 | B8: 1 | C8: 0 | D8: 0 | E8: 0 | H8: CÉLULA CONSTRUTIVA | I8: 01 | J8: MOVIMENTAÇÃO DE TERRA
A9: 0 | B9: 1 | C9: 1 | D9: 0 | E9: 0 | H9: ETAPA | I9: 01.001 | J9: DEMOLIÇÕES, LIMPEZA DE TERRENO E LOCAÇÃO DE OBRA | N9: 26235.314 | O9: 1.5663183
A10: 0 | B10: 1 | C10: 1 | D10: 1 | E10: 0 | H10: SUBETAPA | I10: 01.001.001 | J10: Locação e gabarito de obra | N10: 26235.314 | O10: 1.5663183
A11: 0 | B11: 1 | C11: 1 | D11: 1 | E11: 1 | G11: MOVIMENTAÇÃO DE TERRA | H11: SERVIÇO | I11: 01.001.001.001 | J11: Locação da obra | K11: m2 | N11: 26235.314 | P11: Pendente
A12: 0 | B12: 1 | C12: 2 | D12: 0 | E12: 1 | H12: ETAPA | I12: 01.002 | J12: SERVIÇOS PRELIMINARES
A13: 0 | B13: 1 | C13: 2 | D13: 1 | E13: 0 | H13: SUBETAPA | I13: 01.002.001 | J13: Limpeza Permanente e Remoção entulho
A14: 0 | B14: 1 | C14: 2 | D14: 1 | E14: 1 | G14: MOVIMENTAÇÃO DE TERRA | H14: SERVIÇO | I14: 01.002.001.001 | J14: Limpeza da camada vegetal | K14: m2 | P14: Pendente
A15: 0 | B15: 1 | C15: 2 | D15: 1 | E15: 2 | G15: MOVIMENTAÇÃO DE TERRA | H15: SERVIÇO | I15: 01.002.001.002 | J15: Remoção de entulhos e resíduos | P15: Pendente
A16: 0 | B16: 1 | C16: 2 | D16: 2 | E16: 0 | H16: SUBETAPA | I16: 01.002.002 | J16: Mão de Obra de Canteiro
A17: 0 | B17: 1 | C17: 2 | D17: 2 | E17: 1 | G17: MOVIMENTAÇÃO DE TERRA | H17: SERVIÇO | I17: 01.002.002.001 | J17: Mão de Obra de Canteiro | K17: vb | P17: Pendente
A18: 0 | B18: 1 | C18: 3 | D18: 0 | E18: 1 | H18: ETAPA | I18: 01.003 | J18: SERVIÇOS DE TERRAPLANAGEM | N18: 271126.19 | O18: 16.186957
A19: 0 | B19: 1 | C19: 3 | D19: 1 | E19: 0 | H19: SUBETAPA | I19: 01.003.001 | J19: Mao de obra - movimentações de terra | N19: 271126.19 | O19: 16.186957
A20: 0 | B20: 1 | C20: 3 | D20: 1 | E20: 1 | G20: MOVIMENTAÇÃO DE TERRA | H20: SERVIÇO | I20: 01.003.001.001 | J20: Mão de obra movimentação de terra | K20: vb | N20: 233000 | P20: Pendente
A21: 0 | B21: 1 | C21: 4 | D21: 0 | E21: 2 | H21: ETAPA | I21: 01.004 | J21: SERVIÇO DE DRENAGEM | N21: 80000 | O21: 4.7762135
A22: 0 | B22: 1 | C22: 4 | D22: 1 | E22: 0 | H22: SUBETAPA | I22: 01.004.001 | J22: Drenagem | N22: 80000 | O22: 4.7762135
A23: 0 | B23: 1 | C23: 4 | D23: 1 | E23: 1 | G23: MOVIMENTAÇÃO DE TERRA | H23: SERVIÇO | I23: 01.004.001.001 | J23: Rebaixamento de Lençol freático | K23: vb | N23: 80000 | P23: Pendente
A24: 0 | B24: 2 | C24: 0 | D24: 1 | E24: 1 | H24: CÉLULA CONSTRUTIVA | I24: 02 | J24: CONTENÇÃO | N24: 772006.63 | O24: 46.090856
A25: 0 | B25: 2 | C25: 1 | D25: 0 | E25: 1 | H25: ETAPA | I25: 02.001 | J25: MURETA GUIA | N25: 18739.389 | O25: 1.1187915
A26: 0 | B26: 2 | C26: 1 | D26: 1 | E26: 0 | H26: SUBETAPA | I26: 02.001.001 | J26: Forma | N26: 6673.9436 | O26: 0.39845225
A27: 0 | B27: 2 | C27: 1 | D27: 1 | E27: 1 | G27: CONTENÇÃO | H27: SERVIÇO | I27: 02.001.001.001 | J27: Forma para infraestrutura em Tábuas de Madeira Serrada 2x reaproveitamento | K27: m2 | L27: 111.3136 | M27: 59.956229 | N27: 6673.9436 | P27: Pendente
A28: 0 | B28: 2 | C28: 1 | D28: 2 | E28: 0 | H28: SUBETAPA | I28: 02.001.002 | J28: Armadura | N28: 4318.7306 | O28: 0.25783974
A29: 0 | B29: 2 | C29: 1 | D29: 2 | E29: 1 | G29: CONTENÇÃO | H29: SERVIÇO | I29: 02.001.002.001 | J29: Armação aço CA-50 ø 6,3mm para Contenções (corte e dobra em obra) | K29: un | L29: 670.32 | M29: 6.0795674 | N29: 4075.2556 | P29: Pendente
A30: 0 | B30: 2 | C30: 1 | D30: 2 | E30: 2 | G30: CONTENÇÃO | H30: SERVIÇO | I30: 02.001.002.002 | J30: Armação aço CA-50 ø 12,5mm para Contenções (corte e dobra em obra) | K30: un | L30: 41.6016 | M30: 5.8525391 | N30: 243.47499 | P30: Pendente
A31: 0 | B31: 2 | C31: 1 | D31: 3 | E31: 0 | H31: SUBETAPA | I31: 02.001.003 | J31: Concreto | N31: 7746.7147 | O31: 0.46249954
A32: 0 | B32: 2 | C32: 1 | D32: 3 | E32: 1 | G32: CONTENÇÃO | H32: SERVIÇO | I32: 02.001.003.001 | J32: Concreto Usinado bombeável 50MPa para infraestrutura- incluindo serviço de bombeamento | K32: m3 | L32: 11.390452 | M32: 680.106 | N32: 7746.7147 | P32: Pendente
A33: 0 | B33: 2 | C33: 2 | D33: 0 | E33: 1 | H33: ETAPA | I33: 02.002 | J33: LAMELAS | PAREDE DIAFRAGMA | N33: 331865.23 | O33: 19.81324
A34: 0 | B34: 2 | C34: 2 | D34: 1 | E34: 0 | H34: SUBETAPA | I34: 02.002.001 | J34: Armadura | N34: 155967.97 | O34: 9.3117038
A35: 0 | B35: 2 | C35: 2 | D35: 1 | E35: 1 | G35: CONTENÇÃO | H35: SERVIÇO | I35: 02.002.001.001 | J35: Armação aço CA-50 ø 6,3mm para Contenções (corte e dobra em Indústria) | K35: un | L35: 2282 | M35: 8.964145 | N35: 20456.179 | P35: Pendente
A36: 0 | B36: 2 | C36: 2 | D36: 1 | E36: 2 | G36: CONTENÇÃO | H36: SERVIÇO | I36: 02.002.001.002 | J36: Armação aço CA-50 ø 8,0mm para Contenções (corte e dobra em Indústria) | K36: un | L36: 77 | M36: 8.964145 | N36: 690.23916 | P36: Pendente
A37: 0 | B37: 2 | C37: 2 | D37: 1 | E37: 3 | G37: CONTENÇÃO | H37: SERVIÇO | I37: 02.002.001.003 | J37: Armação aço CA-50 ø 12,5mm para Contenções (corte e dobra em Indústria) | K37: un | L37: 3884 | M37: 8.484145 | N37: 32952.419 | P37: Pendente
A38: 0 | B38: 2 | C38: 2 | D38: 1 | E38: 4 | G38: CONTENÇÃO | H38: SERVIÇO | I38: 02.002.001.004 | J38: Armação aço CA-50 ø 25,0mm para Contenções (corte e dobra em Indústria) | K38: un | L38: 12007 | M38: 8.484145 | N38: 101869.13 | P38: Pendente
A39: 0 | B39: 2 | C39: 2 | D39: 2 | E39: 0 | H39: SUBETAPA | I39: 02.002.002 | J39: Concreto | N39: 175897.26 | O39: 10.501536
A40: 0 | B40: 2 | C40: 2 | D40: 2 | E40: 1 | G40: CONTENÇÃO | H40: SERVIÇO | I40: 02.002.002.001 | J40: Concreto Usinado bombeável 50MPa com Penetron para infraestrutura- incluindo serviço de bombeamento | K40: m3 | L40: 210 | M40: 837.606 | N40: 175897.26 | P40: Pendente
A41: 0 | B41: 2 | C41: 3 | D41: 0 | E41: 1 | H41: ETAPA | I41: 02.003 | J41: VIGAS COROAMENTO | N41: 37645.991 | O41: 2.2475661
A42: 0 | B42: 2 | C42: 3 | D42: 1 | E42: 0 | H42: SUBETAPA | I42: 02.003.001 | J42: Forma | N42: 2482.1879 | O42: 0.14819324
A43: 0 | B43: 2 | C43: 3 | D43: 1 | E43: 1 | G43: CONTENÇÃO | H43: SERVIÇO | I43: 02.003.001.001 | J43: Forma para infraestrutura em Tábuas de Madeira Serrada 2x reaproveitamento | K43: m2 | L43: 41.4 | M43: 59.956229 | N43: 2482.1879 | P43: Pendente
A44: 0 | B44: 2 | C44: 3 | D44: 2 | E44: 0 | H44: SUBETAPA | I44: 02.003.002 | J44: Armadura | N44: 23057.916 | O44: 1.3766191
A45: 0 | B45: 2 | C45: 3 | D45: 2 | E45: 1 | G45: CONTENÇÃO | H45: SERVIÇO | I45: 02.003.002.001 | J45: Armação aço CA-50 ø 8,0mm para Contenções (corte e dobra em Indústria) | K45: kg | L45: 913.36364 | M45: 8.964145 | N45: 8187.5241 | P45: Pendente
A46: 0 | B46: 2 | C46: 3 | D46: 2 | E46: 2 | G46: CONTENÇÃO | H46: SERVIÇO | I46: 02.003.002.002 | J46: Armação aço CA-50 ø 12,5mm para Contenções (corte e dobra em Indústria) | K46: kg | L46: 45.363636 | M46: 8.484145 | N46: 384.87167 | P46: Pendente
A47: 0 | B47: 2 | C47: 3 | D47: 2 | E47: 3 | G47: CONTENÇÃO | H47: SERVIÇO | I47: 02.003.002.003 | J47: Armação aço CA-50 ø 16,0mm para Contenções (corte e dobra em Indústria) | K47: kg | L47: 1277.2727 | M47: 8.484145 | N47: 10836.567 | P47: Pendente
A48: 0 | B48: 2 | C48: 3 | D48: 2 | E48: 4 | G48: CONTENÇÃO | H48: SERVIÇO | I48: 02.003.002.004 | J48: Armação aço CA-50 ø 20,0mm para Contenções (corte e dobra em Indústria) | K48: kg | L48: 430.09091 | M48: 8.484145 | N48: 3648.9536 | P48: Pendente
A49: 0 | B49: 2 | C49: 3 | D49: 3 | E49: 0 | H49: SUBETAPA | I49: 02.003.003 | J49: Concreto | N49: 12105.887
A50: 0 | B50: 2 | C50: 3 | D50: 3 | E50: 1 | G50: CONTENÇÃO | H50: SERVIÇO | I50: 02.003.003.001 | J50: Concreto Usinado bombeável 50MPa para infraestrutura- incluindo serviço de bombeamento | K50: m3 | L50: 17.8 | M50: 680.106 | N50: 12105.887 | P50: Pendente
A51: 0 | B51: 2 | C51: 4 | D51: 0 | E51: 1 | H51: ETAPA | I51: 02.004 | J51: ESTACAS PRANCHA METÁLICA | N51: 243756 | O51: 14.552884
A52: 0 | B52: 2 | C52: 4 | D52: 1 | E52: 0 | H52: SUBETAPA | I52: 02.004.001 | J52: Estacas prancha metálica | N52: 243756 | O52: 14.552884
A53: 0 | B53: 2 | C53: 4 | D53: 1 | E53: 1 | G53: CONTENÇÃO | H53: SERVIÇO | I53: 02.004.001.001 | J53: Locação e cravação de estacas prancha EP400 para contenção | K53: m2 | L53: 492.8 | M53: 470.28409 | N53: 231756 | O53: Cotação, considerado 6 meses de locação | P53: Pendente
A54: 0 | B54: 2 | C54: 4 | D54: 1 | E54: 2 | G54: CONTENÇÃO | H54: SERVIÇO | I54: 02.004.001.002 | J54: Mobilização e Desmobilização de equipamento e máquinas considerando serviço de carga e descarga | K54: vb | L54: 1 | M54: 12000 | N54: 12000 | P54: Pendente
A55: 0 | B55: 2 | C55: 5 | D55: 0 | E55: 2 | H55: ETAPA | I55: 02.005 | J55: MÃO DE OBRA CONTENÇÕES | N55: 140000.02 | O55: 8.3583748
A56: 0 | B56: 2 | C56: 5 | D56: 1 | E56: 0 | H56: SUBETAPA | I56: 02.005.001 | J56: Mão de Obra | N56: 140000.02 | O56: 8.3583748
A57: 0 | B57: 2 | C57: 5 | D57: 1 | E57: 1 | G57: CONTENÇÃO | H57: SERVIÇO | I57: 02.005.001.001 | J57: Mão de obra para execução de contenção | K57: m2 | L57: 525 | M57: 266.6667 | N57: 140000.02 | O57: Prosposta Gessele | P57: Pendente
A58: 0 | B58: 3 | C58: 0 | D58: 1 | E58: 1 | H58: CÉLULA CONSTRUTIVA | I58: 03 | J58: INFRAESTRUTURA | N58: 4572490 | O58: 272.98986
A59: 0 | B59: 3 | C59: 1 | D59: 0 | E59: 1 | H59: ETAPA | I59: 03.001 | J59: ESTACA HÉLICE CONTÍNUA | N59: 3041540.5 | O59: 181.58809
A60: 0 | B60: 3 | C60: 1 | D60: 1 | E60: 0 | H60: SUBETAPA | I60: 03.001.001 | J60: Perfuração | N60: 950000 | O60: 56.717535
A61: 0 | B61: 3 | C61: 1 | D61: 1 | E61: 1 | G61: INFRAESTRUTURA | H61: SERVIÇO | I61: 03.001.001.001 | J61: Perfuração de estaca hélice contínua Ø 60cm | K61: m | L61: 6732 | M61: 137.48633 | N61: 925557.99 | O61: Repessado pela Gessele na reunião do dia 05/03/2026 - 950k efeg | P61: Pendente
A62: 0 | B62: 3 | C62: 1 | D62: 1 | E62: 2 | G62: INFRAESTRUTURA | H62: SERVIÇO | I62: 03.001.001.002 | J62: Mobilização e desmobilização de equipamentos - Para execução de estaca hélice monitorada | K62: vb | L62: 1 | M62: 24442.015 | N62: 24442.015 | O62: Repessado pela Gessele na reunião do dia 05/03/2026 - 950k efeg | P62: Pendente
A63: 0 | B63: 3 | C63: 1 | D63: 2 | E63: 0 | H63: SUBETAPA | I63: 03.001.002 | J63: Armadura | N63: 298834.78 | O63: 17.841234
A64: 0 | B64: 3 | C64: 1 | D64: 2 | E64: 1 | G64: INFRAESTRUTURA | H64: SERVIÇO | I64: 03.001.002.001 | J64: Armação aço CA-50 ø 6,3mm para estaca (corte e dobra em indústria) | K64: un | L64: 3495 | M64: 8.964145 | N64: 31329.687 | P64: Pendente
A65: 0 | B65: 3 | C65: 1 | D65: 2 | E65: 2 | G65: INFRAESTRUTURA | H65: SERVIÇO | I65: 03.001.002.002 | J65: Armação aço CA-50 ø 20,0mm para estaca (corte e dobra em indústria) | K65: un | L65: 31530 | M65: 8.484145 | N65: 267505.09 | P65: Pendente
A66: 0 | B66: 3 | C66: 1 | D66: 3 | E66: 0 | H66: SUBETAPA | I66: 03.001.003 | J66: Concreto | N66: 1792705.7 | O66: 107.02932
A67: 0 | B67: 3 | C67: 1 | D67: 3 | E67: 1 | G67: INFRAESTRUTURA | H67: SERVIÇO | I67: 03.001.003.001 | J67: Concreto Usinado bombeável para estacas 50MPa - incluindo serviço de bombeamento | K67: m3 | L67: 1903.4282 | M67: 941.83 | N67: 1792705.7 | P67: Pendente
A68: 0 | B68: 3 | C68: 1 | D68: 4 | E68: 0 | H68: SUBETAPA | I68: 03.001.004 | J68: Mão de Obra | N68: 0 | O68: 0
A69: 0 | B69: 3 | C69: 2 | D69: 0 | E69: 0 | H69: ETAPA | I69: 03.002 | J69: BLOCOS | N69: 1056067.4 | O69: 63.050045
A70: 0 | B70: 3 | C70: 2 | D70: 1 | E70: 0 | H70: SUBETAPA | I70: 03.002.001 | J70: Forma | N70: 15723.521 | O70: 0.93873616
A71: 0 | B71: 3 | C71: 2 | D71: 1 | E71: 1 | G71: INFRAESTRUTURA | H71: SERVIÇO | I71: 03.002.001.001 | J71: Forma para infraestrutura em Tábuas de Madeira Serrada 2x reaproveitamento | K71: m2 | L71: 262.25 | M71: 59.956229 | N71: 15723.521 | O71: Apenas blocos, 2x reaproveitamento | P71: Pendente
A72: 0 | B72: 3 | C72: 2 | D72: 2 | E72: 0 | H72: SUBETAPA | I72: 03.002.002 | J72: Armadura | N72: 592494.12 | O72: 35.37348
A73: 0 | B73: 3 | C73: 2 | D73: 2 | E73: 1 | G73: INFRAESTRUTURA | H73: SERVIÇO | I73: 03.002.002.001 | J73: Armação aço CA-50 ø 12,5mm para infraestrutura (corte e dobra em Indústria) | K73: kg | L73: 528.18182 | M73: 8.484145 | N73: 4481.1711 | P73: Pendente
A74: 0 | B74: 3 | C74: 2 | D74: 2 | E74: 2 | G74: INFRAESTRUTURA | H74: SERVIÇO | I74: 03.002.002.002 | J74: Armação aço CA-50 ø 16,0mm para infraestrutura (corte e dobra em Indústria) | K74: kg | L74: 7331.8182 | M74: 8.484145 | N74: 62204.209 | P74: Pendente
A75: 0 | B75: 3 | C75: 2 | D75: 2 | E75: 3 | G75: INFRAESTRUTURA | H75: SERVIÇO | I75: 03.002.002.003 | J75: Armação aço CA-50 ø 20,0mm para infraestrutura (corte e dobra em Indústria) | K75: kg | L75: 1318.1818 | M75: 8.484145 | N75: 11183.646 | P75: Pendente
A76: 0 | B76: 3 | C76: 2 | D76: 2 | E76: 4 | G76: INFRAESTRUTURA | H76: SERVIÇO | I76: 03.002.002.004 | J76: Armação aço CA-50 ø 25,0mm para infraestrutura (corte e dobra em Indústria) | K76: kg | L76: 60657.273 | M76: 8.484145 | N76: 514625.1 | P76: Pendente
A77: 0 | B77: 3 | C77: 2 | D77: 3 | E77: 0 | H77: SUBETAPA | I77: 03.002.003 | J77: Concreto | N77: 447849.8 | O77: 26.737828
A78: 0 | B78: 3 | C78: 2 | D78: 3 | E78: 1 | G78: INFRAESTRUTURA | H78: SERVIÇO | I78: 03.002.003.001 | J78: Concreto Usinado bombeável 50MPa para infraestrutura- incluindo serviço de bombeamento | K78: m3 | L78: 658.5 | M78: 680.106 | N78: 447849.8 | O78: 5% de perda, fck = 50Mpa | P78: Pendente
A79: 0 | B79: 3 | C79: 2 | D79: 4 | E79: 0 | H79: SUBETAPA | I79: 03.002.004 | J79: Mão de Obra | N79: 0 | O79: 0
A80: 0 | B80: 3 | C80: 3 | D80: 0 | E80: 0 | H80: ETAPA | I80: 03.003 | J80: VIGAS BALDRAMES | PILARES DE ARRANQUE | CISTERNAS E DUTOS | N80: 474882.06 | O80: 28.351727
A81: 0 | B81: 3 | C81: 3 | D81: 1 | E81: 0 | H81: SUBETAPA | I81: 03.003.001 | J81: Forma | N81: 9996.6219 | O81: 0.59682501
A82: 0 | B82: 3 | C82: 3 | D82: 1 | E82: 1 | G82: INFRAESTRUTURA | H82: SERVIÇO | I82: 03.003.001.001 | J82: Forma para infraestrutura em Tábuas de Madeira Serrada 2x reaproveitamento | K82: m2 | L82: 166.732 | M82: 59.956229 | N82: 9996.6219 | O82: Considerado blocos, vigas de fundação, duto, cisterna, lajes e pilares de arranque | P82: Pendente
A83: 0 | B83: 3 | C83: 3 | D83: 2 | E83: 0 | H83: SUBETAPA | I83: 03.003.002 | J83: Armadura | N83: 430167.93 | O83: 25.682173
A84: 0 | B84: 3 | C84: 3 | D84: 2 | E84: 1 | G84: INFRAESTRUTURA | H84: SERVIÇO | I84: 03.003.002.001 | J84: Armação aço CA-50 ø 5,0mm para infraestrutura (corte e dobra em Indústria) | K84: kg | L84: 52 | M84: 8.964145 | N84: 466.13554 | O84: Considerado vigas de fundação, duto, cisterna, lajes e pilares de arranque - 10% de perda | P84: Pendente
A85: 0 | B85: 3 | C85: 3 | D85: 2 | E85: 2 | G85: INFRAESTRUTURA | H85: SERVIÇO | I85: 03.003.002.002 | J85: Armação aço CA-50 ø 6,3mm para infraestrutura (corte e dobra em Indústria) | K85: kg | L85: 130.27273 | M85: 8.964145 | N85: 1167.7836 | O85: Considerado vigas de fundação, duto, cisterna, lajes e pilares de arranque - 10% de perda | P85: Pendente
A86: 0 | B86: 3 | C86: 3 | D86: 2 | E86: 3 | G86: INFRAESTRUTURA | H86: SERVIÇO | I86: 03.003.002.003 | J86: Armação aço CA-50 ø 8,0mm para infraestrutura (corte e dobra em Indústria) | K86: kg | L86: 982.63636 | M86: 8.964145 | N86: 8808.4948 | O86: Considerado vigas de fundação, duto, cisterna, lajes e pilares de arranque - 10% de perda | P86: Pendente
A87: 0 | B87: 3 | C87: 3 | D87: 2 | E87: 4 | G87: INFRAESTRUTURA | H87: SERVIÇO | I87: 03.003.002.004 | J87: Armação aço CA-50 ø 10,0mm para infraestrutura (corte e dobra em Indústria) | K87: kg | L87: 7011.6364 | M87: 8.964145 | N87: 62853.325 | O87: Considerado vigas de fundação, duto, cisterna, lajes e pilares de arranque - 10% de perda | P87: Pendente
A88: 0 | B88: 3 | C88: 3 | D88: 2 | E88: 5 | G88: INFRAESTRUTURA | H88: SERVIÇO | I88: 03.003.002.005 | J88: Armação aço CA-50 ø 12,5mm para infraestrutura (corte e dobra em Indústria) | K88: kg | L88: 6007.8182 | M88: 8.484145 | N88: 50971.201 | O88: Considerado vigas de fundação, duto, cisterna, lajes e pilares de arranque - 10% de perda | P88: Pendente
A89: 0 | B89: 3 | C89: 3 | D89: 2 | E89: 6 | G89: INFRAESTRUTURA | H89: SERVIÇO | I89: 03.003.002.006 | J89: Armação aço CA-50 ø 16,0mm para infraestrutura (corte e dobra em Indústria) | K89: kg | L89: 1269.7273 | M89: 8.484145 | N89: 10772.55 | O89: Considerado vigas de fundação, duto, cisterna, lajes e pilares de arranque - 10% de perda | P89: Pendente
A90: 0 | B90: 3 | C90: 3 | D90: 2 | E90: 7 | G90: INFRAESTRUTURA | H90: SERVIÇO | I90: 03.003.002.007 | J90: Armação aço CA-50 ø 20,0mm para infraestrutura (corte e dobra em Indústria) | K90: kg | L90: 902 | M90: 8.484145 | N90: 7652.6988 | O90: Considerado vigas de fundação, duto, cisterna, lajes e pilares de arranque - 10% de perda | P90: Pendente
A91: 0 | B91: 3 | C91: 3 | D91: 2 | E91: 8 | G91: INFRAESTRUTURA | H91: SERVIÇO | I91: 03.003.002.008 | J91: Armação aço CA-50 ø 25,0mm para infraestrutura (corte e dobra em Indústria) | K91: kg | L91: 4680 | M91: 8.484145 | N91: 39705.799 | O91: Considerado vigas de fundação, duto, cisterna, lajes e pilares de arranque - 10% de perda | P91: Pendente
A92: 0 | B92: 3 | C92: 3 | D92: 2 | E92: 9 | G92: INFRAESTRUTURA | H92: SERVIÇO | I92: 03.003.002.009 | J92: Armação aço CA-50 ø 32,00mm para infraestrutura (corte e dobra em Indústria) | K92: kg | L92: 27316 | M92: 9.0705059 | N92: 247769.94 | O92: Considerado vigas de fundação, duto, cisterna, lajes e pilares de arranque - 10% de perda | P92: Pendente
A93: 0 | B93: 3 | C93: 3 | D93: 3 | E93: 0 | H93: SUBETAPA | I93: 03.003.003 | J93: Concreto | N93: 34717.514 | O93: 2.0727282
A94: 0 | B94: 3 | C94: 3 | D94: 3 | E94: 1 | G94: INFRAESTRUTURA | H94: SERVIÇO | I94: 03.003.003.001 | J94: Concreto Usinado bombeável 50MPa para infraestrutura- incluindo serviço de bombeamento | K94: m3 | L94: 51.04721 | M94: 680.106 | N94: 34717.514 | O94: Cotações recentes do concreto. Considerado vigas de fundação, duto, cisterna, lajes e pilares de arranque - 5% de perda, fck = 50Mpa | P94: Pendente
A95: 0 | B95: 3 | C95: 3 | D95: 4 | E95: 0 | H95: SUBETAPA | I95: 03.003.004 | J95: Mão de Obra | N95: 0 | O95: 0
A96: 0 | B96: 4 | C96: 0 | D96: 4 | E96: 0 | H96: CÉLULA CONSTRUTIVA | I96: 04 | J96: SUPRAESTRUTURA | N96: 20793271 | O96: 1241.4138
A97: 0 | B97: 4 | C97: 1 | D97: 0 | E97: 0 | H97: ETAPA | I97: 04.001 | J97: PISO SOBRE O SOLO - GERAL | N97: 19428.045 | O97: 1.1599061
A98: 0 | B98: 4 | C98: 1 | D98: 1 | E98: 0 | H98: SUBETAPA | I98: 04.001.001 | J98: Piso sobre o solo - Geral | N98: 19428.045 | O98: 1.1599061
A99: 0 | B99: 4 | C99: 1 | D99: 1 | E99: 1 | G99: SUPRAESTRUTURA | H99: SERVIÇO | I99: 04.001.001.001 | J99: Lastro de Concreto Magro, Aplicado em piso sobre solo | K99: m3 | L99: 39.229 | M99: 495.247 | N99: 19428.045 | O99: O concreto e a armadura entraram nos itens referentes ao terreo, conforme lista de materiais do projetista | P99: Pendente
A100: 0 | B100: 4 | C100: 2 | D100: 0 | E100: 1 | H100: ETAPA | I100: 04.002 | J100: FORMA | N100: 1435615 | O100: 85.710046
A101: 0 | B101: 4 | C101: 2 | D101: 1 | E101: 0 | H101: SUBETAPA | I101: 04.002.001 | J101: Forma - Térreo | N101: 529090.67 | O101: 31.588125
A102: 0 | B102: 4 | C102: 2 | D102: 1 | E102: 1 | G102: SUPRAESTRUTURA | H102: SERVIÇO | I102: 04.002.001.001 | J102: Fabricação de Fôrma para Supraestrutura, em Chapa de Madeira Compensada Resinada, E=20mm | K102: m2 | L102: 4874.3226 | M102: 108.03523 | N102: 526598.54 | O102: 8x reaproveitamento - 3 jogos | P102: Pendente
A103: 0 | B103: 4 | C103: 2 | D103: 1 | E103: 2 | G103: SUPRAESTRUTURA | H103: SERVIÇO | I103: 04.002.001.002 | J103: Montagem e Desmontagem de Fôrma de Supraestrutura | K103: m2 | L103: 626.5792 | M103: 3.9773488 | N103: 2492.124 | P103: Pendente
...

Sheet Orçamento
A1: DADOS
A2: Titulo | B2: ORÇAMENTO
A3: Obra | B3: ELECTRA TOWERS
A4: Cliente | B4: THOZEN
A5: Cidade | B5: Porto Belo
A6: Endereço
A7: Descrição
A8: UF | B8: SC
A10: RESUMO
A11: Tipo | C11: Preço | E11: Observação
A12: Total | C12: 21718825 | E12: Geral da edificação
A13: Material | C13: 15467433
A14: Execução | C14: 6251392.4
A16: TABELA DE ORÇAMENTO
A17: Item | B17: Referência | C17: Tipo | D17: Código | E17: Descrição | F17: Unid. | G17: Quantidade | H17: Custo unitário | I17: Preço total | J17: % | K17: Observação
A19: 1. | E19: 03. PAREDES E PAINÉIS | I19: 1964071 | J19: 0.090431735
A20: 1.1. | E20: ARQ_Embasamento | I20: 228660.08 | J20: 0.010528198
A21: 1.1.1. | E21: 03.001. Alvenaria de vedação com blocos cerâmicos | I21: 133087.99 | J21: 0.006127771
A22: 1.1.1.1 | E22: BLOCO CERAMICO, 0,05 (Parede padrão) | F22: m² | G22: 35.77 | H22: 0 | I22: 0
A23: 1.1.1.2 | E23: BLOCO CERAMICO, 0,09 (Parede padrão) | F23: m² | G23: 171.98 | H23: 0 | I23: 0
A24: 1.1.1.3 | B24: Thozen - Electra | C24: COMPOSICAO | D24: 4825 | E24: Alvenaria de vedação de blocos cerâmicos furados na horizontal de 11,5x19x19cm (espessura 11,5cm) com argamassa industrializada de assentamento | F24: m2 | G24: 1262.88 | H24: 25.096 | I24: 31693.236 | J24: 0.0014592519
A25: 1.1.1.4 | B25: Thozen - Electra | C25: COMPOSICAO | D25: 4826 | E25: Alvenaria de vedação de blocos cerâmicos furados na horizontal de 14x19x19cm (espessura 14cm) com argamassa industrializada de assentamento | F25: m2 | G25: 1610.87 | H25: 40.7664 | I25: 65669.371 | J25: 0.0030236152
A26: 1.1.1.5 | B26: Thozen - Electra | C26: COMPOSICAO | D26: 90472 | E26: Alvenaria de vedação de blocos cerâmicos furados na horizontal de 19x19x19cm (espessura 19cm) com argamassa industrializada de assentamento | F26: m2 | G26: 631.36 | H26: 56.5848 | I26: 35725.379 | J26: 0.0016449039
A27: 1.1.2. | E27: 03.002. Alvenaria de vedação com blocos de concreto | I27: 0
A28: 1.1.2.1 | E28: BLOCO CONCRETO, 0,05 (Parede padrão) | F28: m² | G28: 1.49 | H28: 0 | I28: 0
A29: 1.1.2.2 | E29: BLOCO ANTI CHAMAS, 0,125 (Parede padrão) | F29: m² | G29: 252.44 | H29: 0 | I29: 0
A30: 1.1.2.3 | E30: BLOCO ANTI CHAMAS, 0,15 (Parede padrão) | F30: m² | G30: 774.4 | H30: 0 | I30: 0
A31: 1.1.3. | E31: 03.003. Serviços complementares para alvenaria de vedação | I31: 95572.097 | J31: 0.0044004266
A32: 1.1.3.1 | B32: Thozen - Electra | C32: COMPOSICAO | D32: 4831 | E32: Verga/contraverga de concreto, moldada in loco | F32: m | G32: 104.16 | H32: 43.712512 | I32: 4553.0952 | J32: 0.00020963819
A33: 1.1.3.2 | B33: Thozen - Electra | C33: COMPOSICAO | D33: 4828 | E33: Encunhamento de alvenaria de vedação com argamassa expansiva | F33: m | G33: 18470.23 | H33: 3.633798 | I33: 67117.085 | J33: 0.0030902724
A34: 1.1.3.3 | B34: Thozen - Electra | C34: COMPOSICAO | D34: 4829 | E34: Tela soldada para ligação alvenaria/estrutura | F34: m² | G34: 2370.59 | H34: 1.85 | I34: 4385.5915 | J34: 0.00020192582
A35: 1.1.3.4 | B35: Thozen - Electra | C35: COMPOSICAO | D35: 4831 | E35: Verga/contraverga de concreto, moldada in loco | F35: m | G35: 446.47 | H35: 43.712512 | I35: 19516.325 | J35: 0.00089859028
A36: 1.1.4. | E36: 03.005. Mão de obra | I36: 0
A37: 1.1.4.1 | E37: Mão de obra alvenaria cerâmica | F37: m² | G37: 4045.19 | H37: 0 | I37: 0
A38: 1.1.4.2 | E38: Mão de obra blocos sílico calcário (Parede padrão) | F38: m² | G38: 1028.33 | H38: 0 | I38: 0
A39: 1.1.5. | E39: Alvenaria de vedação com tijolo refratário | I39: 0
A40: 1.1.5.1 | E40: TIJOLO REFRATARIO, 0,016 (Parede padrão) | F40: m² | G40: 14.56 | H40: 0 | I40: 0
A41: 1.2. | E41: ARQ_Impermeab | I41: 45754.495 | J41: 0.0021066745
A42: 1.2.1. | E42: 03.003. Serviços complementares para alvenaria de vedação | I42: 45754.495 | J42: 0.0021066745
A43: 1.2.1.1 | B43: Thozen - Electra | C43: COMPOSICAO | D43: 4828 | E43: Encunhamento de alvenaria de vedação com argamassa expansiva | F43: m | G43: 12591.37 | H43: 3.633798 | I43: 45754.495 | J43: 0.0021066745
A44: 1.3. | E44: ARQ_Torre_A | I44: 823378.32 | J44: 0.037910813
A45: 1.3.1. | E45: 03.001. Alvenaria de vedação com blocos cerâmicos | I45: 416102.64 | J45: 0.019158616
A46: 1.3.1.1 | E46: BLOCO CERAMICO, 0,05 (Parede padrão) | F46: m² | G46: 1074.45 | H46: 0 | I46: 0
A47: 1.3.1.2 | E47: BLOCO CERAMICO, 0,09 (Parede padrão) | F47: m² | G47: 1364.5 | H47: 0 | I47: 0
A48: 1.3.1.3 | B48: Thozen - Electra | C48: COMPOSICAO | D48: 4825 | E48: Alvenaria de vedação de blocos cerâmicos furados na horizontal de 11,5x19x19cm (espessura 11,5cm) com argamassa industrializada de assentamento | F48: m2 | G48: 7270.36 | H48: 25.096 | I48: 182456.95 | J48: 0.0084008667
A49: 1.3.1.4 | B49: Thozen - Electra | C49: COMPOSICAO | D49: 4826 | E49: Alvenaria de vedação de blocos cerâmicos furados na horizontal de 14x19x19cm (espessura 14cm) com argamassa industrializada de assentamento | F49: m2 | G49: 4090.42 | H49: 40.7664 | I49: 166751.7 | J49: 0.0076777495
A50: 1.3.1.5 | B50: Thozen - Electra | C50: COMPOSICAO | D50: 90472 | E50: Alvenaria de vedação de blocos cerâmicos furados na horizontal de 19x19x19cm (espessura 19cm) com argamassa industrializada de assentamento | F50: m2 | G50: 1182.19 | H50: 56.5848 | I50: 66893.985 | J50: 0.0030800002
A51: 1.3.2. | E51: 03.002. Alvenaria de vedação com blocos de concreto | I51: 0
A52: 1.3.2.1 | E52: BLOCO CONCRETO, 0,05 (Parede padrão) | F52: m² | G52: 363.8 | H52: 0 | I52: 0
A53: 1.3.2.2 | E53: BLOCO ANTI CHAMAS, 0,125 (Parede padrão) | F53: m² | G53: 128.55 | H53: 0 | I53: 0
A54: 1.3.2.3 | E54: BLOCO ANTI CHAMAS, 0,15 (Parede padrão) | F54: m² | G54: 862.58 | H54: 0 | I54: 0
A55: 1.3.3. | E55: 03.003. Serviços complementares para alvenaria de vedação | I55: 407275.68 | J55: 0.018752197
A56: 1.3.3.1 | B56: Thozen - Electra | C56: COMPOSICAO | D56: 4831 | E56: Verga/contraverga de concreto, moldada in loco | F56: m | G56: 1151.26 | H56: 43.712512 | I56: 50324.467 | J56: 0.0023170897
A57: 1.3.3.2 | B57: Thozen - Electra | C57: COMPOSICAO | D57: 4828 | E57: Encunhamento de alvenaria de vedação com argamassa expansiva | F57: m | G57: 62783.49 | H57: 3.633798 | I57: 228142.52 | J57: 0.010504367
A58: 1.3.3.3 | B58: Thozen - Electra | C58: COMPOSICAO | D58: 4829 | E58: Tela soldada para ligação alvenaria/estrutura | F58: m² | G58: 8168.42 | H58: 1.85 | I58: 15111.577 | J58: 0.00069578243
A59: 1.3.3.4 | B59: Thozen - Electra | C59: COMPOSICAO | D59: 4831 | E59: Verga/contraverga de concreto, moldada in loco | F59: m | G59: 2601.02 | H59: 43.712512 | I59: 113697.12 | J59: 0.0052349571
A60: 1.3.4. | E60: 03.005. Mão de obra | I60: 0
A61: 1.3.4.1 | E61: Mão de obra alvenaria cerâmica | F61: m² | G61: 16873.23 | H61: 0 | I61: 0
A62: 1.3.4.2 | E62: Mão de obra blocos sílico calcário (Parede padrão) | F62: m² | G62: 1354.93 | H62: 0 | I62: 0
A63: 1.3.5. | E63: Alvenaria de vedação com tijolo refratário | I63: 0
A64: 1.3.5.1 | E64: TIJOLO REFRATARIO, 0,016 (Parede padrão) | F64: m² | G64: 287.37 | H64: 0 | I64: 0
A65: 1.4. | E65: ARQ_Torre_B | I65: 866278.14 | J65: 0.03988605
A66: 1.4.1. | E66: 03.001. Alvenaria de vedação com blocos cerâmicos | I66: 489178.45 | J66: 0.022523246
A67: 1.4.1.1 | E67: BLOCO CERAMICO, 0,05 (Parede padrão) | F67: m² | G67: 398.15 | H67: 0 | I67: 0
A68: 1.4.1.2 | E68: BLOCO CERAMICO, 0,09 (Parede padrão) | F68: m² | G68: 3063.66 | H68: 0 | I68: 0
A69: 1.4.1.3 | B69: Thozen - Electra | C69: COMPOSICAO | D69: 4825 | E69: Alvenaria de vedação de blocos cerâmicos furados na horizontal de 11,5x19x19cm (espessura 11,5cm) com argamassa industrializada de assentamento | F69: m2 | G69: 8394.28 | H69: 25.096 | I69: 210662.85 | J69: 0.009699551
A70: 1.4.1.4 | B70: Thozen - Electra | C70: COMPOSICAO | D70: 4826 | E70: Alvenaria de vedação de blocos cerâmicos furados na horizontal de 14x19x19cm (espessura 14cm) com argamassa industrializada de assentamento | F70: m2 | G70: 5416.8 | H70: 40.7664 | I70: 220823.44 | J70: 0.010167375
A71: 1.4.1.5 | B71: Thozen - Electra | C71: COMPOSICAO | D71: 90472 | E71: Alvenaria de vedação de blocos cerâmicos furados na horizontal de 19x19x19cm (espessura 19cm) com argamassa industrializada de assentamento | F71: m2 | G71: 1019.57 | H71: 56.5848 | I71: 57692.165 | J71: 0.0026563207
A72: 1.4.2. | E72: 03.002. Alvenaria de vedação com blocos de concreto | I72: 0
A73: 1.4.2.1 | E73: BLOCO ANTI CHAMAS, 0,125 (Parede padrão) | F73: m² | G73: 245.34 | H73: 0 | I73: 0
A74: 1.4.2.2 | E74: BLOCO ANTI CHAMAS, 0,15 (Parede padrão) | F74: m² | G74: 662.3 | H74: 0 | I74: 0
A75: 1.4.3. | E75: 03.003. Serviços complementares para alvenaria de vedação | I75: 377099.69 | J75: 0.017362803
A76: 1.4.3.1 | B76: Thozen - Electra | C76: COMPOSICAO | D76: 4831 | E76: Verga/contraverga de concreto, moldada in loco | F76: m | G76: 1126.07 | H76: 43.712512 | I76: 49223.348 | J76: 0.0022663909
A77: 1.4.3.2 | B77: Thozen - Electra | C77: COMPOSICAO | D77: 4828 | E77: Encunhamento de alvenaria de vedação com argamassa expansiva | F77: m | G77: 54949.59 | H77: 3.633798 | I77: 199675.71 | J77: 0.00919367
A78: 1.4.3.3 | B78: Thozen - Electra | C78: COMPOSICAO | D78: 4829 | E78: Tela soldada para ligação alvenaria/estrutura | F78: m² | G78: 9600.05 | H78: 1.85 | I78: 17760.092 | J78: 0.00081772805
A79: 1.4.3.4 | B79: Thozen - Electra | C79: COMPOSICAO | D79: 4831 | E79: Verga/contraverga de concreto, moldada in loco | F79: m | G79: 2526.52 | H79: 43.712512 | I79: 110440.54 | J79: 0.0050850143
A80: 1.4.4. | E80: 03.005. Mão de obra | I80: 0
A81: 1.4.4.1 | E81: Mão de obra alvenaria cerâmica | F81: m² | G81: 20189.64 | H81: 0 | I81: 0
A82: 1.4.4.2 | E82: Mão de obra blocos sílico calcário (Parede padrão) | F82: m² | G82: 907.65 | H82: 0 | I82: 0
A83: 1.4.5. | E83: Alvenaria de vedação com tijolo refratário | I83: 0
A84: 1.4.5.1 | E84: TIJOLO REFRATARIO, 0,016 (Parede padrão) | F84: m² | G84: 269.16 | H84: 0 | I84: 0
A85: 2. | E85: 04. IMPERMEABILIZAÇÃO E TRATAMENTOS | I85: 331117.51 | J85: 0.015245646
A86: 2.1. | E86: ARQ_Embasamento | I86: 0
A87: 2.1.1. | E87: 04.007. Impermeabilização de esquadrias | I87: 0
A88: 2.1.1.1 | E88: Peitoril | F88: m² | G88: 84.83 | H88: 0 | I88: 0
A89: 2.2. | E89: ARQ_Impermeab | I89: 331117.51 | J89: 0.015245646
A90: 2.2.1. | E90: 04.004. Impermeabilização de lajes e terraços | I90: 0
A91: 2.2.1.1 | E91: VERIFICAR MATERIAL TERRAÇO (Laje) | F91: m² | G91: 755.42 | H91: 0 | I91: 0
A92: 2.2.1.2 | E92: VERIFICAR MATERIAL - TERRAÇO (Parede padrão) | F92: m² | G92: 55.75 | H92: 0 | I92: 0
A93: 2.2.2. | E93: 04.006. Impermeabilização de banheiro, cozinha e sacada | I93: 331117.51 | J93: 0.015245646
A94: 2.2.2.1 | B94: Thozen - Electra | C94: COMPOSICAO | D94: 4842 | E94: Impermeabilização com argamassa polimérica, 3 demãos | F94: m2 | G94: 9140.58 | H94: 36.225 | I94: 331117.51 | J94: 0.015245646
A95: 2.2.3. | E95: 04.007. Impermeabilização de esquadrias | I95: 0
A96: 2.2.3.1 | E96: Polímero acrílico - janela | F96: m² | G96: 582.79 | H96: 0 | I96: 0
A97: 2.3. | E97: ARQ_Torre_A | I97: 0
A98: 2.3.1. | E98: 04.007. Impermeabilização de esquadrias | I98: 0
A99: 2.3.1.1 | E99: Peitoril | F99: m² | G99: 252.2 | H99: 0 | I99: 0
A100: 2.4. | E100: ARQ_Torre_B | I100: 0
A101: 2.4.1. | E101: 04.007. Impermeabilização de esquadrias | I101: 0
A102: 2.4.1.1 | E102: Peitoril | F102: m² | G102: 234.85 | H102: 0 | I102: 0
A103: 3. | E103: 12. REVESTIMENTOS ARGAMASSADOS INTERNOS DE PAREDE | I103: 4588051.9 | J103: 0.2112477
...

Sheet Composições
A1: DADOS
A2: Titulo | B2: ORÇAMENTO
A3: Obra | B3: ELECTRA TOWERS
A4: Cliente | B4: THOZEN
A5: Cidade | B5: Porto Belo
A6: Endereço
A7: Descrição
A8: UF | B8: SC
A11: TABELA DE COMPOSIÇÕES UTILIZADAS
A12: Código | B12: Referência | C12: Tipo | D12: Tipo | E12: Descrição | F12: Unid. | G12: Multiplicador | H12: Preço | J12: Ref. Tabela | K12: Ref. Código | L12: Justificativa | M12: Grupo de Serviço | N12: Serviço
H13: Unitário | I13: Total
A14: 4825 | B14: Thozen - Electra | D14: Original | E14: Alvenaria de vedação de blocos cerâmicos furados na horizontal de 11,5x19x19cm (espessura 11,5cm) com argamassa industrializada de assentamento | F14: m2 | I14: 25.096 | N14: BLOCOS | O14: =A14&B14&C14 -> 4825Thozen - Electra
A15: 194 | B15: Thozen - Electra | C15: INSUMO | D15: Original | E15: ARGAMASSA ESTABILIZADA PARA ASSENTAMENTO | F15: m3 | G15: 0.0125 | H15: 480 | I15: 6
A16: 228 | B16: Thozen - Electra | C16: INSUMO | D16: Original | E16: BLOCO CERÂMICO 11,5X19X19CM | F16: un | G16: 17.36 | H16: 1.1 | I16: 19.096
A17: 4826 | B17: Thozen - Electra | D17: Original | E17: Alvenaria de vedação de blocos cerâmicos furados na horizontal de 14x19x19cm (espessura 14cm) com argamassa industrializada de assentamento | F17: m2 | I17: 40.7664 | N17: BLOCOS | O17: =A17&B17&C17 -> 4826Thozen - Electra
A18: 194 | B18: Thozen - Electra | C18: INSUMO | D18: Original | E18: ARGAMASSA ESTABILIZADA PARA ASSENTAMENTO | F18: m3 | G18: 0.022 | H18: 480 | I18: 10.56
A19: 232 | B19: Thozen - Electra | C19: INSUMO | D19: Original | E19: BLOCO CERÂMICO 14X19X19CM | F19: un | G19: 17.36 | H19: 1.74 | I19: 30.2064
A20: 90472 | B20: Thozen - Electra | D20: Original | E20: Alvenaria de vedação de blocos cerâmicos furados na horizontal de 19x19x19cm (espessura 19cm) com argamassa industrializada de assentamento | F20: m2 | I20: 56.5848 | N20: BLOCOS | O20: =A20&B20&C20 -> 90472Thozen - Electra
A21: 194 | B21: Thozen - Electra | C21: INSUMO | D21: Original | E21: ARGAMASSA ESTABILIZADA PARA ASSENTAMENTO | F21: m3 | G21: 0.03 | H21: 480 | I21: 14.4
A22: 48433 | B22: Thozen - Electra | C22: INSUMO | D22: Original | E22: BLOCO CERÂMICO 19X19X19CM | F22: un | G22: 17.36 | H22: 2.43 | I22: 42.1848
A23: 4831 | B23: Thozen - Electra | D23: Original | E23: Verga/contraverga de concreto, moldada in loco | F23: m | I23: 43.712512 | O23: =A23&B23&C23 -> 4831Thozen - Electra
A24: 759 | B24: Thozen - Electra | C24: INSUMO | D24: Original | E24: CONCRETO USINADO FCK 20 MPA, SLUMP 14+/-2 | F24: m3 | G24: 0.0264 | H24: 450 | I24: 11.88
A25: 4800 | B25: Thozen - Electra | C25: INSUMO | D25: Original | E25: DESMOLDANTE DE FORMAS PARA CONCRETO | F25: l | G25: 0.007 | H25: 6.45 | I25: 0.04515
A26: 1412 | B26: Thozen - Electra | C26: INSUMO | D26: Original | E26: ESPAÇADOR PLÁSTICO | F26: un | G26: 6 | H26: 0.15 | I26: 0.9
A27: 2324 | B27: Thozen - Electra | C27: INSUMO | D27: Original | E27: PONTALETE 7,5X7,5 CM PINUS | F27: m3 | G27: 0.0012 | H27: 1310 | I27: 1.572
A28: 2362 | B28: Thozen - Electra | C28: INSUMO | D28: Original | E28: PREGO POLIDO COM CABEÇA 17X21 | F28: kg | G28: 0.0512 | H28: 10.91 | I28: 0.558592
A29: 2546 | B29: Thozen - Electra | C29: INSUMO | D29: Original | E29: SARRAFO 2,5X7,5 CM PINUS | F29: m3 | G29: 0.003171 | H29: 1300 | I29: 4.1223
A30: 2611 | B30: Thozen - Electra | C30: INSUMO | D30: Original | E30: TÁBUA 1"X12" 2,5X30CM PINUS | F30: m3 | G30: 0.011676 | H30: 1800 | I30: 21.0168
A31: 32 | B31: Thozen - Electra | C31: INSUMO | D31: Original | E31: AÇO CA-50 DIÂMETRO 6,30 MM | F31: kg | G31: 0.5243 | H31: 6.9 | I31: 3.61767
A32: 4828 | B32: Thozen - Electra | D32: Original | E32: Encunhamento de alvenaria de vedação com argamassa expansiva | F32: m | I32: 3.633798 | N32: ENCUNHAMENTO | O32: =A32&B32&C32 -> 4828Thozen - Electra
A33: 48435 | B33: Thozen - Electra | C33: INSUMO | D33: Original | E33: ARGAMASSA EXPANSIVA PARA ENCUNHAMENTO | F33: Kg | G33: 0.2154 | H33: 16.87 | I33: 3.633798
A34: 4829 | B34: Thozen - Electra | D34: Original | E34: Tela soldada para ligação alvenaria/estrutura | F34: m² | I34: 1.85 | O34: =A34&B34&C34 -> 4829Thozen - Electra
A35: 718 | B35: Thozen - Electra | C35: INSUMO | D35: Original | E35: CARTUCHO 22 - CARGA LEVE PARA FINCA PINO E POLVORA | F35: un | G35: 1 | H35: 0.3 | I35: 0.3
A36: 2260 | B36: Thozen - Electra | C36: INSUMO | D36: Original | E36: PINO LISO EM AÇO GALVANIZADO 1/2 X 22MM COM ARRUELA | F36: un | G36: 1 | H36: 0.3 | I36: 0.3
A37: 2901 | B37: Thozen - Electra | C37: INSUMO | D37: Original | E37: TELA DE ACO SOLDADA, FIO 1,24MM, MALHA 15X15MM | F37: m2 | G37: 0.5 | H37: 2.5 | I37: 1.25
A38: 4842 | B38: Thozen - Electra | D38: Original | E38: Impermeabilização com argamassa polimérica, 3 demãos | F38: m2 | I38: 36.225 | O38: =A38&B38&C38 -> 4842Thozen - Electra
A39: 202 | B39: Thozen - Electra | C39: INSUMO | D39: Original | E39: ARGAMASSA POLIMÉRICA IMPERMEABILIZANTE | F39: kg | G39: 3.15 | H39: 11.5 | I39: 36.225
A40: 90541 | B40: Thozen - Electra | D40: Original | E40: Chapisco adesivo aplicado em concreto, com desempenadeira dentada | F40: m2 | I40: 6.459 | N40: CHAPISCO | O40: =A40&B40&C40 -> 90541Thozen - Electra
A41: 197 | B41: Thozen - Electra | C41: INSUMO | D41: Original | E41: ARGAMASSA ESTABILIZADA PARA REBOCO | F41: m3 | G41: 0.0033 | H41: 480 | I41: 1.584
A42: 48481 | B42: Thozen - Electra | C42: INSUMO | D42: Original | E42: ADITIVO ADESIVO LÍQUIDO PARA ARGAMASSA | F42: L | G42: 0.625 | H42: 7.8 | I42: 4.875
A43: 90507 | B43: Thozen - Electra | D43: Original | E43: Chapisco rolado aplicado em alvenaria, com desempenadeira dentada | F43: m2 | I43: 5.502 | N43: CHAPISCO | O43: =A43&B43&C43 -> 90507Thozen - Electra
A44: 48373 | B44: Thozen - Electra | C44: INSUMO | D44: Original | E44: CHAPISCO COLANTE 20KG | F44: Kg | G44: 4.2 | H44: 1.31 | I44: 5.502
A45: 4861 | B45: Thozen - Electra | D45: Original | E45: Massa única para paredes internas em argamassa estabilizada, aplicação manual, espessura 2cm, com execução de taliscas | F45: m2 | I45: 18.048 | N45: REBOCO | O45: =A45&B45&C45 -> 4861Thozen - Electra
A46: 197 | B46: Thozen - Electra | C46: INSUMO | D46: Original | E46: ARGAMASSA ESTABILIZADA PARA REBOCO | F46: m3 | G46: 0.0376 | H46: 480 | I46: 18.048
A47: 4865 | B47: Thozen - Electra | D47: Original | E47: Mão de obra para reboco interno, incluso chapisco | F47: m2 | I47: 35 | O47: =A47&B47&C47 -> 4865Thozen - Electra
A48: 2154 | B48: Thozen - Electra | C48: INSUMO | D48: Original | E48: MÃO DE OBRA PARA EXECUÇÃO DE CHAPISCO E REBOCO INTERNO EM PAREDES | F48: m2 | G48: 1 | H48: 35 | I48: 35
A49: 4899 | B49: Thozen - Electra | D49: Original | E49: Revestimento interno de parede em porcelanato, placa 30x90cm, aplicação em banheiros e cozinhas | F49: m2 | I49: 97.430075 | O49: =A49&B49&C49 -> 4899Thozen - Electra
A50: 193 | B50: Thozen - Electra | C50: INSUMO | D50: Original | E50: ARGAMASSA COLANTE AC III | F50: kg | G50: 9 | H50: 2.345 | I50: 21.105
A51: 4881 | B51: Thozen - Electra | C51: INSUMO | D51: Original | E51: ESPAÇADOR PARA REVESTIMENTO CERÂMICO TIPO CRUZETA 5 MM | F51: un | G51: 4 | H51: 0.2 | I51: 0.8
A52: 4880 | B52: Thozen - Electra | C52: INSUMO | D52: Original | E52: REJUNTE FLEXÍVEL | F52: m2 | G52: 0.25 | H52: 2.0643 | I52: 0.516075
A53: 48500 | B53: Thozen - Electra | C53: INSUMO | D53: Original | E53: REVESTIMENTO PORCELANATO INTERNO 30X90CM | F53: m2 | G53: 1.1 | H53: 68.19 | I53: 75.009
A54: 90511 | B54: Thozen - Electra | D54: Original | E54: Acabamentos de elevador em granito, acabamento polido, esp. 2cm | F54: m² | I54: 623.4139 | N54: PEITORIL | O54: =A54&B54&C54 -> 90511Thozen - Electra
A55: 193 | B55: Thozen - Electra | C55: INSUMO | D55: Original | E55: ARGAMASSA COLANTE AC III | F55: kg | G55: 8.62 | H55: 2.345 | I55: 20.2139
A56: 1526 | B56: Thozen - Electra | C56: INSUMO | D56: Original | E56: GRANITO POLIDO | F56: m2 | G56: 1.16 | H56: 520 | I56: 603.2
A57: 4902 | B57: Thozen - Electra | D57: Original | E57: Peitoril em granito, acabamento polido, esp. 2cm | F57: m² | I57: 623.4139 | N57: PEITORIL | O57: =A57&B57&C57 -> 4902Thozen - Electra
A58: 193 | B58: Thozen - Electra | C58: INSUMO | D58: Original | E58: ARGAMASSA COLANTE AC III | F58: kg | G58: 8.62 | H58: 2.345 | I58: 20.2139
A59: 1526 | B59: Thozen - Electra | C59: INSUMO | D59: Original | E59: GRANITO POLIDO | F59: m2 | G59: 1.16 | H59: 520 | I59: 603.2
A60: 4872 | B60: Thozen - Electra | D60: Original | E60: Forro de gesso acartonado, aplicação em áreas secas - material e mão de obra | F60: m2 | I60: 126.4 | N60: FORRO EM GESSO | O60: =A60&B60&C60 -> 4872Thozen - Electra
A61: 4874 | B61: Thozen - Electra | C61: INSUMO | D61: Original | E61: FORRO DE GESSO ACARTONADO, APLICAÇÃO EM ÁREAS SECAS - MATERIAL E MÃO DE OBRA | F61: m2 | G61: 1 | H61: 100 | I61: 100
A62: 1514 | B62: Thozen - Electra | C62: INSUMO | D62: Original | E62: GESSO NEGATIVO | F62: m | G62: 1.2 | H62: 22 | I62: 26.4
A63: 4876 | B63: Thozen - Electra | D63: Original | E63: Gesso negativo - material e mão de obra | F63: m | I63: 22 | O63: =A63&B63&C63 -> 4876Thozen - Electra
A64: 1514 | B64: Thozen - Electra | C64: INSUMO | D64: Original | E64: GESSO NEGATIVO | F64: m | G64: 1 | H64: 22 | I64: 22
A65: 1481 | B65: Thozen - Electra | D65: Original | E65: Textura acrilica aplicacao em teto, 1 demão, incluindo aplicação de uma demão de fundo selador látex pva | F65: m2 | I65: 9.171036 | N65: PINTURA TETO | O65: =A65&B65&C65 -> 1481Thozen - Electra
A66: 2940 | B66: Thozen - Electra | C66: INSUMO | D66: Original | E66: TEXTURA ACRÍLICA | F66: kg | G66: 1.1074 | H66: 7.23 | I66: 8.006502
A67: 2553 | B67: Thozen - Electra | C67: INSUMO | D67: Original | E67: SELADOR LÁTEX PVA | F67: l | G67: 0.1666 | H67: 6.99 | I67: 1.164534
A68: 4873 | B68: Thozen - Electra | D68: Original | E68: Forro de gesso acartonado, aplicação em áreas molhadas - material e mão de obra | F68: m2 | I68: 136.4 | N68: FORRO EM GESSO | O68: =A68&B68&C68 -> 4873Thozen - Electra
A69: 4875 | B69: Thozen - Electra | C69: INSUMO | D69: Original | E69: FORRO DE GESSO ACARTONADO, APLICAÇÃO EM ÁREAS ÚMIDAS - MATERIAL E MÃO DE OBRA | F69: m2 | G69: 1 | H69: 110 | I69: 110
A70: 1514 | B70: Thozen - Electra | C70: INSUMO | D70: Original | E70: GESSO NEGATIVO | F70: m | G70: 1.2 | H70: 22 | I70: 26.4
A71: 60 | B71: Thozen - Electra | D71: Original | E71: Contrapiso comum em argamassa estabilizada, nao aderido, espessura 5cm | F71: m2 | I71: 26.4 | N71: CONTRAPISO | O71: =A71&B71&C71 -> 60Thozen - Electra
A72: 458 | B72: Thozen - Electra | C72: INSUMO | D72: Original | E72: ARGAMASSA ESTABILIZADA P/ CONTRAPISO | F72: M3 | G72: 0.055 | H72: 480 | I72: 26.4
A73: 4863 | B73: Thozen - Electra | D73: Original | E73: Mão de obra de execução contrapiso comum | F73: m2 | I73: 32 | O73: =A73&B73&C73 -> 4863Thozen - Electra
A74: 2156 | B74: Thozen - Electra | C74: INSUMO | D74: Original | E74: MÃO DE OBRA PARA EXECUÇÃO DE CONTRAPISO | F74: m2 | G74: 1 | H74: 32 | I74: 32
A75: 4883 | B75: Thozen - Electra | D75: Original | E75: Revestimento interno de piso porcelanato, placa 80x80, aplicação em áreas internas | F75: m2 | I75: 93.8717 | O75: =A75&B75&C75 -> 4883Thozen - Electra
A76: 193 | B76: Thozen - Electra | C76: INSUMO | D76: Original | E76: ARGAMASSA COLANTE AC III | F76: kg | G76: 9 | H76: 2.345 | I76: 21.105
A77: 4881 | B77: Thozen - Electra | C77: INSUMO | D77: Original | E77: ESPAÇADOR PARA REVESTIMENTO CERÂMICO TIPO CRUZETA 5 MM | F77: un | G77: 4 | H77: 0.2 | I77: 0.8
A78: 4884 | B78: Thozen - Electra | C78: INSUMO | D78: Original | E78: PISO PORCELANATO 80X80CM, ACABAMENTO NATURAL, PADRÃO MÉDIO | F78: m2 | G78: 1.1 | H78: 65 | I78: 71.5
A79: 2521 | B79: Thozen - Electra | C79: INSUMO | D79: Original | E79: REJUNTE ACRÍLICO | F79: kg | G79: 0.13 | H79: 3.59 | I79: 0.4667
A80: 90521 | B80: Thozen - Electra | D80: Original | E80: Rodapé em poliestireno, altura 15cm | F80: m | I80: 82.225797 | O80: =A80&B80&C80 -> 90521Thozen - Electra
A81: 417 | B81: Thozen - Electra | C81: INSUMO | D81: Original | E81: BUCHA T PARA RODAPÉ | F81: un | G81: 2.5 | H81: 1.99 | I81: 4.975
A82: 738 | B82: Thozen - Electra | C82: INSUMO | D82: Original | E82: COLA PARA RODAPÉ DE POLIESTIRENO | F82: kg | G82: 0.0694 | H82: 5.0403 | I82: 0.34979682
A83: 48465 | B83: Thozen - Electra | C83: INSUMO | D83: Original | E83: RODAPÉ POLIESTIRENO H=15CM | F83: m | G83: 1.1 | H83: 69.91 | I83: 76.901
A84: 4882 | B84: Thozen - Electra | D84: Original | E84: Rodapé em poliestireno, altura 10cm | F84: m | I84: 17.655797 | O84: =A84&B84&C84 -> 4882Thozen - Electra
A85: 417 | B85: Thozen - Electra | C85: INSUMO | D85: Original | E85: BUCHA T PARA RODAPÉ | F85: un | G85: 2.5 | H85: 1.99 | I85: 4.975
A86: 738 | B86: Thozen - Electra | C86: INSUMO | D86: Original | E86: COLA PARA RODAPÉ DE POLIESTIRENO | F86: kg | G86: 0.0694 | H86: 5.0403 | I86: 0.34979682
A87: 2538 | B87: Thozen - Electra | C87: INSUMO | D87: Original | E87: RODAPÉ POLIESTIRENO H=10CM | F87: m | G87: 1.1 | H87: 11.21 | I87: 12.331
A88: 4891 | B88: Thozen - Electra | D88: Original | E88: Rodapé em porcelanato, altura 10cm, com placa 80x80 | F88: m | I88: 9.7339012 | O88: =A88&B88&C88 -> 4891Thozen - Electra
A89: 193 | B89: Thozen - Electra | C89: INSUMO | D89: Original | E89: ARGAMASSA COLANTE AC III | F89: kg | G89: 0.9 | H89: 2.345 | I89: 2.1105
A90: 1412 | B90: Thozen - Electra | C90: INSUMO | D90: Original | E90: ESPAÇADOR PLÁSTICO | F90: un | G90: 2 | H90: 0.15 | I90: 0.3
A91: 4884 | B91: Thozen - Electra | C91: INSUMO | D91: Original | E91: PISO PORCELANATO 80X80CM, ACABAMENTO NATURAL, PADRÃO MÉDIO | F91: m2 | G91: 0.11 | H91: 65 | I91: 7.15
A92: 4880 | B92: Thozen - Electra | C92: INSUMO | D92: Original | E92: REJUNTE FLEXÍVEL | F92: m2 | G92: 0.084 | H92: 2.0643 | I92: 0.1734012
A93: 4898 | B93: Thozen - Electra | D93: Original | E93: Soleira de granito, acabamento polido, espessura 2cm | F93: m2 | I93: 593.64172 | O93: =A93&B93&C93 -> 4898Thozen - Electra
A94: 193 | B94: Thozen - Electra | C94: INSUMO | D94: Original | E94: ARGAMASSA COLANTE AC III | F94: kg | G94: 9 | H94: 2.345 | I94: 21.105
A95: 1526 | B95: Thozen - Electra | C95: INSUMO | D95: Original | E95: GRANITO POLIDO | F95: m2 | G95: 1.1 | H95: 520 | I95: 572
A96: 4880 | B96: Thozen - Electra | C96: INSUMO | D96: Original | E96: REJUNTE FLEXÍVEL | F96: m2 | G96: 0.26 | H96: 2.0643 | I96: 0.536718
A97: 90559 | B97: Thozen - Electra | D97: Original | E97: Massa latex acrílica em paredes internas 2 demaos | F97: m2 | I97: 11.9703 | N97: MASSA | O97: =A97&B97&C97 -> 90559Thozen - Electra
A98: 1400 | B98: Thozen - Electra | C98: INSUMO | D98: Original | E98: LIXA EM FOLHA PARA PAREDE OU MADEIRA N° 120 | F98: UN | G98: 0.1 | H98: 18.48 | I98: 1.848
A99: 48483 | B99: Thozen - Electra | C99: INSUMO | D99: Original | E99: MASSA ACRÍLICA | F99: kg | G99: 0.8802 | H99: 11.5 | I99: 10.1223
A100: 4926 | B100: Thozen - Electra | D100: Original | E100: Pintura com tinta acrílica em paredes internas, aplicação manual, 3 demãos | F100: m2 | I100: 20.035312 | N100: PINTURA ACRÍLICA | O100: =A100&B100&C100 -> 4926Thozen - Electra
A101: 2944 | B101: Thozen - Electra | C101: INSUMO | D101: Original | E101: TINTA LÁTEX ACRÍLICA | F101: l | G101: 0.34275 | H101: 36.67 | I101: 12.568643
A102: 2186 | B102: Thozen - Electra | C102: INSUMO | D102: Original | E102: MASSA CORRIDA PVA | F102: kg | G102: 1.3389 | H102: 3.6 | I102: 4.82004
...

Sheet Insumos (2)
A1: DADOS
A2: Titulo | B2: Tabela de insumos utilizados no projeto
A3: Obra | B3: ELECTRA TOWERS
A4: Cliente | B4: THOZEN
A5: Cidade | B5: Porto Belo
A6: Endereço
A7: Descrição
A8: UF | B8: SC
A11: INSUMOS UTILIZADOS
A12: Código | B12: Tabela | C12: Tipo | D12: Descrição | E12: Unid. | F12: Preço | G12: Origem custo | H12: Justificativa
A14: 194 | B14: Thozen - Electra | C14: Material | D14: ARGAMASSA ESTABILIZADA PARA ASSENTAMENTO | E14: m3 | F14: 480 | I14: =A14&B14 -> 194Thozen - Electra
A15: 228 | B15: Thozen - Electra | C15: Material | D15: BLOCO CERÂMICO 11,5X19X19CM | E15: un | F15: 1.1 | I15: =A15&B15 -> 228Thozen - Electra
A16: 232 | B16: Thozen - Electra | C16: Material | D16: BLOCO CERÂMICO 14X19X19CM | E16: un | F16: 1.74 | I16: =A16&B16 -> 232Thozen - Electra
A17: 48433 | B17: Thozen - Electra | C17: Material | D17: BLOCO CERÂMICO 19X19X19CM | E17: un | F17: 2.43 | I17: =A17&B17 -> 48433Thozen - Electra
A18: 759 | B18: Thozen - Electra | C18: Material | D18: CONCRETO USINADO FCK 20 MPA, SLUMP 14+/-2 | E18: m3 | F18: 450 | I18: =A18&B18 -> 759Thozen - Electra
A19: 4800 | B19: Thozen - Electra | C19: Material | D19: DESMOLDANTE DE FORMAS PARA CONCRETO | E19: l | F19: 6.45 | I19: =A19&B19 -> 4800Thozen - Electra
A20: 1412 | B20: Thozen - Electra | C20: Material | D20: ESPAÇADOR PLÁSTICO | E20: un | F20: 0.15 | I20: =A20&B20 -> 1412Thozen - Electra
A21: 2324 | B21: Thozen - Electra | C21: Material | D21: PONTALETE 7,5X7,5 CM PINUS | E21: m3 | F21: 1310 | I21: =A21&B21 -> 2324Thozen - Electra
A22: 2362 | B22: Thozen - Electra | C22: Material | D22: PREGO POLIDO COM CABEÇA 17X21 | E22: kg | F22: 10.91 | I22: =A22&B22 -> 2362Thozen - Electra
A23: 2546 | B23: Thozen - Electra | C23: Material | D23: SARRAFO 2,5X7,5 CM PINUS | E23: m3 | F23: 1300 | I23: =A23&B23 -> 2546Thozen - Electra
A24: 2611 | B24: Thozen - Electra | C24: Material | D24: TÁBUA 1"X12" 2,5X30CM PINUS | E24: m3 | F24: 1800 | I24: =A24&B24 -> 2611Thozen - Electra
A25: 32 | B25: Thozen - Electra | C25: Material | D25: AÇO CA-50 DIÂMETRO 6,30 MM | E25: kg | F25: 6.9 | G25: GERDAU | I25: =A25&B25 -> 32Thozen - Electra
A26: 48435 | B26: Thozen - Electra | C26: Material | D26: ARGAMASSA EXPANSIVA PARA ENCUNHAMENTO | E26: Kg | F26: 16.87 | I26: =A26&B26 -> 48435Thozen - Electra
A27: 718 | B27: Thozen - Electra | C27: Material | D27: CARTUCHO 22 - CARGA LEVE PARA FINCA PINO E POLVORA | E27: un | F27: 0.3 | I27: =A27&B27 -> 718Thozen - Electra
A28: 2260 | B28: Thozen - Electra | C28: Material | D28: PINO LISO EM AÇO GALVANIZADO 1/2 X 22MM COM ARRUELA | E28: un | F28: 0.3 | I28: =A28&B28 -> 2260Thozen - Electra
A29: 2901 | B29: Thozen - Electra | C29: Material | D29: TELA DE ACO SOLDADA, FIO 1,24MM, MALHA 15X15MM | E29: m2 | F29: 2.5 | I29: =A29&B29 -> 2901Thozen - Electra
A30: 202 | B30: Thozen - Electra | C30: Material | D30: ARGAMASSA POLIMÉRICA IMPERMEABILIZANTE | E30: kg | F30: 11.5 | I30: =A30&B30 -> 202Thozen - Electra
A31: 197 | B31: Thozen - Electra | C31: Material | D31: ARGAMASSA ESTABILIZADA PARA REBOCO | E31: m3 | F31: 480 | I31: =A31&B31 -> 197Thozen - Electra
A32: 48481 | B32: Thozen - Electra | C32: Material | D32: ADITIVO ADESIVO LÍQUIDO PARA ARGAMASSA | E32: L | F32: 7.8 | I32: =A32&B32 -> 48481Thozen - Electra
A33: 48373 | B33: Thozen - Electra | C33: Material | D33: CHAPISCO COLANTE 20KG | E33: Kg | F33: 1.31 | I33: =A33&B33 -> 48373Thozen - Electra
A34: 2154 | B34: Thozen - Electra | C34: Mao_obra | D34: MÃO DE OBRA PARA EXECUÇÃO DE CHAPISCO E REBOCO INTERNO EM PAREDES | E34: m2 | F34: 35 | I34: =A34&B34 -> 2154Thozen - Electra
A35: 193 | B35: Thozen - Electra | C35: Material | D35: ARGAMASSA COLANTE AC III | E35: kg | F35: 2.345 | I35: =A35&B35 -> 193Thozen - Electra
A36: 4881 | B36: Thozen - Electra | C36: Material | D36: ESPAÇADOR PARA REVESTIMENTO CERÂMICO TIPO CRUZETA 5 MM | E36: un | F36: 0.2 | I36: =A36&B36 -> 4881Thozen - Electra
A37: 4880 | B37: Thozen - Electra | C37: Material | D37: REJUNTE FLEXÍVEL | E37: m2 | F37: 2.0643 | I37: =A37&B37 -> 4880Thozen - Electra
... A61: 2552 | B61: Thozen - Electra | C61: Material | D61: SELADOR ACRÍLICO | E61: l | F61: 9.44 | I61: =A61&B61 -> 2552Thozen - Electra

Sheet PROJETOS
B1: GESTÃO DOS PROJETOS | J1: LEGENDA
A2: Obra | B2: Electra Towers (Rubens Alves) | J2: NÃO SE APLICA
A3: Empresa | B3: Thozen Empreendimentos | J3: PENDENTE
A4: Revisão | B4: R01 | J4: RECEBIDO
B5: PAVIMENTO | C5: DISCIPLINA | D5: PROJETOS | E5: CAMINHO | F5: STATUS | G5: OBSERVAÇÕES | J5: REVISADO
B7: ESTRUTURA
B8: TERRAPLENAGEM | C8: INFRAESTRUTURA | F8: NÃO SE APLICA
B9: MOVIMENTAÇÃO DE TERRA | C9: INFRAESTRUTURA | F9: PENDENTE
B10: FUNDAÇÃO PROFUNDA | C10: INFRAESTRUTURA | D10: 1203 - PREFORMAS - R20.DWG | E10: 01 ESTRUTURA/DWG | F10: RECEBIDO | G10: DWG Pré-formas Rev.20
B11: FUNDAÇÃO RASA | C11: INFRAESTRUTURA | D11: 1203 - THOZEN - RUBENS ALVES - BLOCOS+RAMPAS DE ACESSO - R26.ifc | E11: 01 ESTRUTURA/IFC | F11: RECEBIDO | G11: IFC Blocos + Rampas de Acesso Rev.26
B12: CONTENÇÃO | C12: INFRAESTRUTURA | F12: NÃO SE APLICA
B13: ÁREA – 1º PAVTO. (TÉRREO) | C13: SUPRAESTRUTURA | F13: RECEBIDO | G13: Coberto pelo IFC estrutural completo
B14: ÁREA – MEZANINO DO 1º PAVTO. | C14: SUPRAESTRUTURA | F14: RECEBIDO | G14: Coberto pelo IFC estrutural completo
B15: ÁREA – 2º PAVIMENTO | C15: SUPRAESTRUTURA | F15: RECEBIDO | G15: Coberto pelo IFC estrutural completo
B16: ÁREA – MEZANINO DO 2º PAVTO. | C16: SUPRAESTRUTURA | F16: RECEBIDO | G16: Coberto pelo IFC estrutural completo
B17: ÁREA – 3º PAVIMENTO | C17: SUPRAESTRUTURA | F17: RECEBIDO | G17: Coberto pelo IFC estrutural completo
B18: ÁREA – MEZANINO DO 3º PAVTO. | C18: SUPRAESTRUTURA | F18: RECEBIDO | G18: Coberto pelo IFC estrutural completo
B19: ÁREA – 4º PAVIMENTO GARAGEM/LAZER | C19: SUPRAESTRUTURA | F19: RECEBIDO | G19: Coberto pelo IFC estrutural completo
B20: ÁREA – 5º PAVIMENTO LAZER | C20: SUPRAESTRUTURA | F20: RECEBIDO | G20: Coberto pelo IFC estrutural completo
B21: ÁREA – 6º PAVIMENTO TIPO - DIFERENCIADO | C21: SUPRAESTRUTURA | F21: RECEBIDO | G21: Coberto pelo IFC estrutural completo
B22: ÁREA – 7º AO 14° PAVIMENTO TIPO - X8 | C22: SUPRAESTRUTURA | F22: RECEBIDO | G22: Coberto pelo IFC estrutural completo
B23: ÁREA – 15º AO 35° PAVIMENTO TIPO - X21 | C23: SUPRAESTRUTURA | F23: RECEBIDO | G23: Coberto pelo IFC estrutural completo
B24: ARQUITETURA
B25: TERRAPLENAGEM | C25: ARQUITETURA | F25: NÃO SE APLICA
B26: MOVIMENTAÇÃO DE TERRA | C26: ARQUITETURA | F26: NÃO SE APLICA
B27: FUNDAÇÃO PROFUNDA | C27: ARQUITETURA | F27: NÃO SE APLICA
B28: FUNDAÇÃO RASA | C28: ARQUITETURA | F28: NÃO SE APLICA
B29: CONTENÇÃO | C29: ARQUITETURA | F29: NÃO SE APLICA
B30: TÉRREO 01 | C30: ARQUITETURA | D30: RA_ARQ_EXE_01_TÉRREO_R02.dwg | E30: 02 ARQUITETURA/DWG | F30: RECEBIDO | G30: DWG Executivo Rev.02
B31: TÉRREO 02 | C31: ARQUITETURA | D31: RA_ARQ_EXE_10_CORTE1_R02.dwg + RA_ARQ_EXE_11_CORTE2_R02.dwg | E31: 02 ARQUITETURA/DWG | F31: RECEBIDO | G31: Cortes 1 e 2, Rev.02
B32: GARAGEM 01 | C32: ARQUITETURA | D32: RA_ARQ_EXE_02_G1_R02.dwg | E32: 02 ARQUITETURA/DWG | F32: RECEBIDO | G32: DWG Executivo Rev.02
B33: GARAGEM 02 | C33: ARQUITETURA | D33: RA_ARQ_EXE_03_G2_R02.dwg | E33: 02 ARQUITETURA/DWG | F33: RECEBIDO | G33: DWG Executivo Rev.02
B34: GARAGEM 03 | C34: ARQUITETURA | D34: RA_ARQ_EXE_04_G3_R02.dwg | E34: 02 ARQUITETURA/DWG | F34: RECEBIDO | G34: DWG Executivo Rev.02
B35: GARAGEM 04 | C35: ARQUITETURA | D35: RA_ARQ_EXE_05_G4_R02.dwg | E35: 02 ARQUITETURA/DWG | F35: RECEBIDO | G35: DWG Executivo Rev.02
B36: LAZER 01 | C36: ARQUITETURA | D36: RA_ARQ_EXE_06_G5_R02.dwg | E36: 02 ARQUITETURA/DWG | F36: RECEBIDO | G36: DWG Executivo Rev.02
B37: LAZER 02 | C37: ARQUITETURA | D37: RA_ARQ_EXE_07_LAZER_R02.dwg | E37: 02 ARQUITETURA/DWG | F37: RECEBIDO | G37: DWG Executivo Rev.02
B38: TIPO DIFERENCIADO 01 | C38: ARQUITETURA | D38: RA_ARQ_EXE_MODELAGEM EMBASAMENTO + COBERTURA_R08.ifc | E38: 02 ARQUITETURA/IFC | F38: RECEBIDO | G38: IFC Embasamento + Cobertura Rev.08
B39: TIPO DIFERENCIADO 02 | C39: ARQUITETURA | D39: RA_ARQ_EXE_MODELAGEM TIPO_R07.ifc | E39: 02 ARQUITETURA/IFC | F39: RECEBIDO | G39: IFC Tipo Rev.07
B40: TIPO (30x) | C40: ARQUITETURA | D40: RA_ARQ_EXE_08_TIPOS_R02.dwg | E40: 02 ARQUITETURA/DWG | F40: RECEBIDO | G40: DWG Executivo Rev.02
B41: DUPLEX INFERIOR (3x) | C41: ARQUITETURA | F41: NÃO SE APLICA
B42: DUPLEX SUPERIOR (3x) | C42: ARQUITETURA | F42: NÃO SE APLICA
B43: LAZER 3 | C43: ARQUITETURA | F43: NÃO SE APLICA
B44: CASA DE MÁQUINAS | C44: ARQUITETURA | F44: NÃO SE APLICA
B45: BARRILETE | RESERVATÓRIOS | C45: ARQUITETURA | D45: RA_ARQ_EXE_09_RES E COB_R02.dwg | E45: 02 ARQUITETURA/DWG | F45: RECEBIDO | G45: DWG Executivo Rev.02
B46: COMPLEMENTARES
B47: GERAL | C47: INSTALAÇÕES PLUVIAL | F47: NÃO SE APLICA
B48: GERAL | C48: INSTALAÇÕES ELÉTRICA | D48: 348 - E01 [28] rev.01 - EL_R.Rubens Alves - 01° PAVTO. TÉRREO [T. A].dwg; 348 - E02 [28] rev.01 - EL_R.Rubens Alves - 01° PAVTO. TÉRREO [T. B].dwg; 348 - E03 [28] rev.01 - EL_R.Rubens Alves - 02° PAVTO. G1 [T. A].dwg (+24 mais) | E48: 09 ELÉTRICO | F48: RECEBIDO | G48: DWG 18 pranchas + IFC 9 modelos, Rev.01
B49: GERAL | C49: INSTALAÇÕES TELEFONIA | D49: 348 - T02 [24] rev.01 - EL_R.Rubens Alves - 01° PAVTO. TÉRREO [T. A].dwg; 348 - T03 [24] rev.01 - EL_R.Rubens Alves - 01° PAVTO. TÉRREO [T. B].dwg; 348 - T04 [24] rev.01 - EL_R.Rubens Alves - 02° PAVTO. G1 [T. A].dwg (+24 mais) | E49: 10 TELEFONICO | F49: RECEBIDO | G49: DWG 18 pranchas + IFC 9 modelos, Rev.01
B50: GERAL | C50: INSTALAÇÕES POTÁVEL | D50: 348 - H01 [30] rev.01 - EL_R.Rubens Alves - 01° PAVTO. TÉRREO - PISO [T.A].dwg; 348 - H02 [30] rev.01 - EL_R.Rubens Alves - 01° PAVTO. TÉRREO - PISO [T.B].dwg; 348 - H03 [30] rev.01 - EL_R.Rubens Alves - 01° PAVTO. TÉRREO - TETO [T.A].dwg (+18 mais) | E50: 05 HIDRÁULICO | F50: RECEBIDO | G50: DWG 20 pranchas + IFC completo, Rev.01
B51: GERAL | C51: INSTALAÇÕES ESGOTO | D51: 348 - S01 [22] rev.01 - EL_R.Rubens Alves - 01° PAVTO. TÉRREO [T.A].dwg; 348 - S02 [22] rev.01 - EL_R.Rubens Alves - 01° PAVTO. TÉRREO [T.B].dwg; 348 - S03 [22] rev.01 - EL_R.Rubens Alves - 02° PAVTO. G1 [T.A].dwg (+27 mais) | E51: 06 SANITÁRIO | F51: RECEBIDO | G51: DWG 20 pranchas + IFC 10 modelos, Rev.01
B52: GERAL | C52: INSTALAÇÕES PCI | D52: 348 - IGC 01 [08] rev-00 - 01° PAVTO- TÉRREO (T-A).dwg; 348 - IGC 01 [08] rev.00 - 01° PAVTO. TÉRREO (T.A).dwg; 348 - IGC 02 [08] rev.00 - 01° PAVTO. TÉRREO (T.B).dwg (+13 mais) | E52: 07 PREVENTIVO INCENDIO CIVIL | F52: RECEBIDO | G52: DWG 11 pranchas + IFC 5 modelos (IGC+PCI+Dutos), Rev.00-01
B53: GERAL | C53: INST. PREV. INCÊNDIO ELÉTRICO | D53: 27 arquivos (DWG 18 + IFC 9) | E53: 08 PREVENTIVO INCENDIO ELÉTRICO | F53: RECEBIDO | G53: Prev. Incêndio Elétrico, DWG+IFC, Rev.01
B54: GERAL | C54: SPDA | D54: 10 pranchas DWG (SPDA Rev.00) | E54: 11 SPDA | F54: RECEBIDO | G54: SPDA completo, Rev.00
B55: GERAL | C55: VENTILAÇÃO MECÂNICA ESCADA | D55: RA_EVM_LEGAL_PROJETO_R05.dwg | E55: 12 ESCADA VENTILACAO MECANICA | F55: RECEBIDO | G55: Projeto Legal Rev.05
B56: GERAL | C56: EXAUSTÃO CHURRASQUEIRA | D56: RA_CHU_EXE_PROJETO_R00.dwg | E56: 13 CHURRASQUEIRA EXAUSTAO | F56: RECEBIDO | G56: Exaustão Churrasqueiras Rev.00
B57: GERAL | C57: AR-CONDICIONADO | D57: RA_ARC_EXE_00_TODAS CAD_R05.dwg | E57: 14 AR-CONDICIONADO | F57: RECEBIDO | G57: Ar-condicionado completo Rev.05
B58: GERAL | C58: ALVENARIA | D58: 18 pranchas DWG (Alvenaria + Locação, Pré-Executivo Rev.01) | E58: 03 ALVENARIA | F58: RECEBIDO | G58: Alvenaria 9 pavimentos + 9 locações, Rev.01
B59: GERAL | C59: ESQUADRIAS | D59: 4 pranchas DWG (Portas, Janelas, Peles Vidro, Vidro Fixo) | E59: 04 ESQUADRIA | F59: RECEBIDO | G59: Esquadrias Pré-Executivo Rev.01
B60: GERAL | C60: EQUIPAMENTOS HIDROMASSAGEM | F60: NÃO SE APLICA
B61: GERAL | C61: EQUIPAMENTOS PISCINA | F61: NÃO SE APLICA
B62: GERAL | C62: LOUÇAS/ METAIS/ BANCADAS | F62: NÃO SE APLICA
B63: GERAL | C63: MOBILIÁRIO | F63: NÃO SE APLICA
B64: GERAL | C64: INTERIORES | F64: NÃO SE APLICA

Sheet Ger_Tec e Adm
A4: PROJETO: | C4: Electra Towers | I4: REVISÃO: | J4: DATA
A5: EMPRESA: | C5: Thozen | I5: R00
A6: GERENCIAMENTO EXECUTIVO
A7: Atalho | B7: NIVEL | C7: Item | D7: Descrição | E7: Unidade | F7: Quant. | G7: Preço un | H7: Total | I7: Considerações | J7: Situação
B8: CÉLULA CONSTRUTIVA | C8: 01 | D8: SERVIÇOS TÉCNICOS | H8: =H9+H57 -> 3668982.5
B9: ETAPA | C9: 01.001 | D9: ESTUDOS, PROJETOS E CONSULTORIAS | H9: =H10+H20+H41+H46 -> 2273047.4 | J9: -
B10: SUBETAPA | C10: 01.001.001 | D10: Estudos | H10: =H11+H12+H13+H14+H15+H16+H17+H18+H19 -> 260925.31
B11: SERVIÇO | C11: 01.001.001.001 | D11: Memorial descritivo | E11: vb | F11: 1 | G11: 18386.35 | H11: =G11*F11 -> 18386.35 | I11: Estimado | J11: Lançado ERP
B12: SERVIÇO | C12: 01.001.001.002 | D12: Levantamento topográfico | E12: vb | F12: 1 | G12: 3000 | H12: =G12*F12 -> 3000 | I12: Recebido | J12: Lançado ERP
B13: SERVIÇO | C13: 01.001.001.003 | D13: Estudo geológico | E13: vb | F13: 1 | G13: 26930.408 | H13: =G13*F13 -> 26930.408 | I13: Estimado | J13: Lançado ERP
B14: SERVIÇO | C14: 01.001.001.004 | D14: Estudo ambiental | E14: vb | F14: 1 | G14: 4500 | H14: =G14*F14 -> 4500 | I14: Recebido | J14: Lançado ERP
B15: SERVIÇO | C15: 01.001.001.005 | D15: Sondagem do terreno | E15: vb | F15: 1 | G15: 7947.99 | H15: =G15*F15 -> 7947.99 | I15: Recebido | J15: Lançado ERP
B16: SERVIÇO | C16: 01.001.001.006 | D16: Projeto de canteiro | E16: vb | F16: 1 | G16: 11160.563 | H16: =G16*F16 -> 11160.563 | I16: Estimado | J16: Lançado ERP
B17: SERVIÇO | C17: 01.001.001.007 | D17: EFEG - Teste de Carga | E17: vb | F17: 1 | G17: 29000 | H17: =G17*F17 -> 29000 | I17: Recebido | J17: Lançado ERP
B18: SERVIÇO | C18: 01.001.001.008 | D18: Solugeot - Teste de Carga | E18: vb | F18: 1 | G18: 140000 | H18: =G18*F18 -> 140000 | I18: Recebido | J18: Lançado ERP
B19: SERVIÇO | C19: 01.001.001.009 | D19: Concreto - Teste de Carga | E19: vb | F19: 1 | G19: 20000 | H19: =G19*F19 -> 20000 | I19: Recebido | J19: Lançado ERP
B20: SUBETAPA | C20: 01.001.002 | D20: Projetos | H20: =H21+H22+H23+H24+H25+H26+H27+H28+H29+H30+H31+H32+H33+H34+H35+H36+H37+H38+H39+H40 -> 1205079.2
B21: SERVIÇO | C21: 01.001.002.001 | D21: Legalização de incorporação | E21: vb | F21: 1 | G21: 67351.993 | H21: =G21*F21 -> 67351.993 | I21: Estimado | J21: Lançado ERP
B22: SERVIÇO | C22: 01.001.002.002 | D22: Projeto arquitetônico legal | E22: vb | F22: 1 | G22: 237000 | H22: =G22*F22 -> 237000 | I22: Recebido - Considerado junto desse projeto os valores de projeto arquitetônico legal + hidráulico + preventivo + elétrico + arquitetônico | J22: Lançado ERP
B23: SERVIÇO | C23: 01.001.002.003 | D23: Projeto Arquitetônico interiores | E23: vb | F23: 1 | G23: 86773.378 | H23: =G23*F23 -> 86773.378 | I23: Estimado | J23: Lançado ERP
B24: SERVIÇO | C24: 01.001.002.004 | D24: Projeto arquitetônico de fachada | E24: vb | F24: 1 | G24: 58250 | H24: =G24*F24 -> 58250 | I24: Recebido | J24: Lançado ERP
B25: SERVIÇO | C25: 01.001.002.005 | D25: Projeto técnico de fachada | E25: vb | F25: 1 | G25: 75145.12 | H25: =G25*F25 -> 75145.12 | I25: Estimado | J25: Lançado ERP
B26: SERVIÇO | C26: 01.001.002.006 | D26: Projeto de terraplanagem | E26: vb | F26: 1 | G26: 6962.4358 | H26: =G26*F26 -> 6962.4358 | I26: Estimado | J26: Lançado ERP
B27: SERVIÇO | C27: 01.001.002.007 | D27: Projeto estrutural | E27: vb | F27: 1 | G27: 70000 | H27: =G27*F27 -> 70000 | I27: Recebido - Considerado junto desse projeto os valores de projeto estrutural e fundação | J27: Lançado ERP
B28: SERVIÇO | C28: 01.001.002.008 | D28: Projeto de automação | E28: vb | F28: 1 | G28: 96720.281 | H28: =G28*F28 -> 96720.281 | I28: Estimado | J28: Lançado ERP
B29: SERVIÇO | C29: 01.001.002.009 | D29: Projeto de irrigação | E29: vb | F29: 1 | G29: 39550.22 | H29: =G29*F29 -> 39550.22 | I29: Estimado | J29: Lançado ERP
B30: SERVIÇO | C30: 01.001.002.010 | D30: Projeto preventivo (PPCI - Plano de Prevenção e Proteção Contra Incêndios) e Gás | E30: vb | F30: 1 | G30: 27354.018 | H30: =G30*F30 -> 27354.018 | I30: Estimado - Considerado somente o projeto de gás, pois o ppci, conforme informado no formulario, esta nicluso no arquitetônico | J30: Lançado ERP
B31: SERVIÇO | C31: 01.001.002.011 | D31: Projeto de climatização/exaustão | E31: vb | F31: 1 | G31: 91124.893 | H31: =G31*F31 -> 91124.893 | I31: Estimado | J31: Lançado ERP
B32: SERVIÇO | C32: 01.001.002.012 | D32: Projeto de Segurança | E32: vb | F32: 1 | G32: 24827.001 | H32: =G32*F32 -> 24827.001 | I32: Estimado | J32: Lançado ERP
... B40: SERVIÇO | C40: 01.001.002.020 | D40: Projeto de Paisagismo | E40: vb | F40: 1 | G40: 36770.652 | H40: =G40*F40 -> 36770.652 | I40: Estimado | J40: Lançado ERP
B41: SUBETAPA | C41: 01.001.003 | D41: Consultorias | H41: =H42+H43+H44+H45 -> 206589.87
B42: SERVIÇO | C42: 01.001.003.001 | D42: Compatibilização de Projetos BIM | E42: vb | F42: 1 | G42: 144789.87 | H42: =G42*F42 -> 144789.87 | I42: Estimado | J42: Lançado ERP
B43: SERVIÇO | C43: 01.001.003.002 | D43: Tour Virtual | E43: vb | F43: 1 | G43: 11300 | H43: =G43*F43 -> 11300 | I43: Recebido | J43: Lançado ERP
B44: SERVIÇO | C44: 01.001.003.003 | D44: Consultoria técnica de legalização | E44: vb | F44: 1 | G44: 16000 | H44: =G44*F44 -> 16000 | I44: Recebido | J44: Lançado ERP
B45: SERVIÇO | C45: 01.001.003.004 | D45: Orçamento e planejamento | E45: vb | F45: 1 | G45: 34500 | H45: =G45*F45 -> 34500 | I45: Recebido | J45: Lançado ERP
B46: SUBETAPA | C46: 01.001.004 | D46: Ensaios | H46: =H47+H48+H49+H50+H51+H52+H53+H54+H55+H56 -> 600453
B47: SERVIÇO | C47: 01.001.004.001 | D47: Controle tecnológico do concreto | E47: vb | F47: 1 | G47: 238185 | H47: =G47*F47 -> 238185 | I47: Estimado | J47: Lançado ERP
B48: SERVIÇO | C48: 01.001.004.002 | D48: Ensaio de argamassa | E48: vb | F48: 1 | G48: 11200 | H48: =G48*F48 -> 11200 | I48: Estimado | J48: Lançado ERP
B49: SERVIÇO | C49: 01.001.004.003 | D49: Prova de carga | E49: vb | F49: 1 | G49: 5500 | H49: =G49*F49 -> 5500 | I49: Estimado | J49: Lançado ERP
B50: SERVIÇO | C50: 01.001.004.004 | D50: Ensaio de arrancamento de reboco | E50: vb | F50: 1 | G50: 6300 | H50: =G50*F50 -> 6300 | I50: Estimado | J50: Lançado ERP
B51: SERVIÇO | C51: 01.001.004.005 | D51: Ensaio de arrancamento revestimento cerâmico | E51: vb | F51: 1 | G51: 5360 | H51: =G51*F51 -> 5360 | I51: Estimado | J51: Lançado ERP
B52: SERVIÇO | C52: 01.001.004.006 | D52: Ensaio de arrancamento fachada | E52: vb | F52: 1 | G52: 5360 | H52: =G52*F52 -> 5360 | I52: Estimado | J52: Lançado ERP
B53: SERVIÇO | C53: 01.001.004.007 | D53: Ensaio de arrancamento de gancho da cobertura | E53: vb | F53: 1 | G53: 3840 | H53: =G53*F53 -> 3840 | I53: Estimado | J53: Lançado ERP
B54: SERVIÇO | C54: 01.001.004.008 | D54: Laudo de Vizinhança | E54: vb | F54: 1 | G54: 7500 | H54: =G54*F54 -> 7500 | I54: Recebido | J54: Lançado ERP
B55: SERVIÇO | C55: 01.001.004.009 | D55: Laudo Spda | E55: vb | F55: 1 | G55: 4200 | H55: =G55*F55 -> 4200 | I55: Estimado | J55: Lançado ERP
B56: SERVIÇO | C56: 01.001.004.010 | D56: Softwares | E56: vb | F56: 1 | G56: 313008 | H56: =G56*F56 -> 313008 | I56: Estimado | J56: Lançado ERP
B57: ETAPA | C57: 01.002 | D57: TAXAS E DOCUMENTOS | H57: =H58+H75 -> 1395935.1
B58: SUBETAPA | C58: 01.002.001 | D58: Licenciamentos, Taxas, Impostos, Aprovações e Seguros | H58: =H59+H60+H61+H62+H63+H64+H65+H66+H67+H68+H69+H70+H71+H72+H73+H74 -> 1044668.3
B59: SERVIÇO | C59: 01.002.001.001 | D59: Despesas de Seguros | E59: vb | F59: 1 | G59: 71960.851 | H59: =G59*F59 -> 71960.851 | I59: Estimado | J59: Finalizado
B60: SERVIÇO | C60: 01.002.001.002 | D60: Taxas de consulta de viabilidade | E60: vb | F60: 1 | G60: 412.37 | H60: =G60*F60 -> 412.37 | I60: Estimado | J60: Finalizado
B61: SERVIÇO | C61: 01.002.001.003 | D61: Avaliação e Legalização ambiental | E61: vb | F61: 1 | G61: 11955.032 | H61: =G61*F61 -> 11955.032 | I61: Estimado | J61: Finalizado
B62: SERVIÇO | C62: 01.002.001.004 | D62: Aprovação e legalização prefeitura | E62: vb | F62: 1 | G62: 30000 | H62: =G62*F62 -> 30000 | I62: Recebido | J62: Finalizado
B63: SERVIÇO | C63: 01.002.001.005 | D63: Aprovação e legalização água e esgoto | E63: vb | F63: 1 | G63: 16643.349 | H63: =G63*F63 -> 16643.349 | I63: Estimado | J63: Finalizado
B64: SERVIÇO | C64: 01.002.001.006 | D64: Aprovação e legalização elétrico | E64: vb | F64: 1 | G64: 33097.805 | H64: =G64*F64 -> 33097.805 | I64: Estimado | J64: Finalizado
B65: SERVIÇO | C65: 01.002.001.007 | D65: Taxas ART | E65: vb | F65: 1 | G65: 12228.686 | H65: =G65*F65 -> 12228.686 | I65: Estimado | J65: Finalizado
B66: SERVIÇO | C66: 01.002.001.008 | D66: Taxas alvará | E66: vb | F66: 1 | G66: 146127.51 | H66: =G66*F66 -> 146127.51 | I66: Estimado | J66: Finalizado
B67: SERVIÇO | C67: 01.002.001.009 | D67: Taxa Renovação Alvará de Construção | E67: vb | F67: 1 | G67: 3600 | H67: =G67*F67 -> 3600 | I67: Estimado | J67: Finalizado
B68: SERVIÇO | C68: 01.002.001.010 | D68: Taxas de Alvará de Demolição | E68: vb | F68: 1 | G68: 1000 | H68: =G68*F68 -> 1000 | I68: Recebido | J68: Finalizado
B69: SERVIÇO | C69: 01.002.001.011 | D69: Taxa LAP, AUC, LAI e LAO | E69: vb | F69: 1 | G69: 8800 | H69: =G69*F69 -> 8800 | I69: Estimado | J69: Finalizado
B70: SERVIÇO | C70: 01.002.001.012 | D70: Outorga onerosa, compra de índice e obra de arte | E70: vb | F70: 1 | G70: 453148.83 | H70: =G70*F70 -> 453148.83 | I70: Recebido | J70: Finalizado
... B74: SERVIÇO | C74: 01.002.001.016 | D74: Taxa Habite-se | E74: vb | F74: 1 | G74: 31036.411 | H74: =G74*F74 -> 31036.411 | I74: Estimado | J74: Finalizado
B75: SUBETAPA | C75: 01.002.002 | D75: Documentos | H75: =H76+H77+H78+H79 -> 351266.87
B76: SERVIÇO | C76: 01.002.002.001 | D76: As Built | E76: vb | F76: 1 | G76: 41370.448 | H76: =G76*F76 -> 41370.448 | I76: Estimado | J76: Finalizado
B77: SERVIÇO | C77: 01.002.002.002 | D77: Laudo técnico de vistoria de entrega | E77: vb | F77: 1 | G77: 162829.57 | H77: =G77*F77 -> 162829.57 | I77: Estimado | J77: Finalizado
B78: SERVIÇO | C78: 01.002.002.003 | D78: Manuais técnicos condomínio/proprietários | E78: vb | F78: 1 | G78: 105185.05 | H78: =G78*F78 -> 105185.05 | I78: Estimado | J78: Finalizado
B79: SERVIÇO | C79: 01.002.002.004 | D79: Certidão INSS | E79: vb | F79: 1 | G79: 41881.806 | H79: =G79*F79 -> 41881.806 | I79: Estimado | J79: Finalizado
B80: CÉLULA CONSTRUTIVA | C80: 02 | D80: SERVIÇOS INICIAIS | H80: =H81+H106+H148 -> 4925713.3
B81: ETAPA | C81: 02.001 | D81: SEGURANÇA, MEIO AMBIENTE E SAÚDE | H81: =H82+H86+H98+H102 -> 609504.18 | J81: -
B82: SUBETAPA | C82: 02.001.001 | D82: Segurança do Trabalho | H82: =H83+H84+H85 -> 300750
B83: SERVIÇO | C83: 02.001.001.001 | D83: Serviço terceirizado de segurança do trabalho - Valor/mês (R$) | E83: mês | F83: 36 | G83: 2500 | H83: =G83*F83 -> 90000 | I83: Recebido | J83: Finalizado
B84: SERVIÇO | C84: 02.001.001.002 | D84: Equipamentos de proteção individual - EPI | E84: vb | F84: 1 | G84: 204750 | H84: =G84*F84 -> 204750 | I84: Estimado | J84: Finalizado
B85: SERVIÇO | C85: 02.001.001.003 | D85: Projetos de segurança do trabalho | E85: vb | F85: 1 | G85: 6000 | H85: =G85*F85 -> 6000 | I85: Recebido | J85: Finalizado
B86: SUBETAPA | C86: 02.001.002 | D86: Equipamentos de proteção | H86: =H87+H88+H89+H90+H91+H92+H93+H94+H95+H96+H97 -> 213973.14
B87: SERVIÇO | C87: 02.001.002.001 | D87: Bandeja de proteção primária | E87: m | F87: 0 | G87: 243.95615 | H87: =G87*F87 -> 0 | I87: EPC'S | J87: Lançado ERP
B88: SERVIÇO | C88: 02.001.002.002 | D88: Bandeja de proteção secundária | E88: m | F88: 0 | G88: 230.09615 | H88: =G88*F88 -> 0 | I88: EPC'S | J88: Lançado ERP
B89: SERVIÇO | C89: 02.001.002.003 | D89: Guarda-corpo de vãos, fixado em fôrma de madeira, em trama de madeira com tela de polipropileno | E89: m2 | F89: 649.372 | G89: 38.622647 | H89: =G89*F89 -> 25080.466 | I89: EPC'S | J89: Lançado ERP
B90: SERVIÇO | C90: 02.001.002.004 | D90: Guarda-corpo em laje pós-desforma com Escora metálica, travessões e tela | E90: m | F90: 0 | G90: 42.431057 | H90: =G90*F90 -> 0 | I90: EPC'S | J90: Lançado ERP
B91: SERVIÇO | C91: 02.001.002.005 | D91: Tela fachadeira | E91: m2 | F91: 0 | G91: 8.5113 | H91: =G91*F91 -> 0 | I91: EPC'S | J91: Lançado ERP
B92: SERVIÇO | C92: 02.001.002.006 | D92: Fechamento removível de vãos de porta de elevador em madeira | E92: m2 | F92: 211.68 | G92: 49.519651 | H92: =G92*F92 -> 10482.32 | I92: EPC'S | J92: Lançado ERP
B93: SERVIÇO | C93: 02.001.002.007 | D93: Fechamento removível de vãos de porta de entrada dos aptos. em madeira | E93: m2 | F93: 861.84 | G93: 49.519651 | H93: =G93*F93 -> 42678.016 | I93: EPC'S | J93: Lançado ERP
B94: SERVIÇO | C94: 02.001.002.008 | D94: Fechamento removível de abertura no piso do elevador em madeira | E94: m2 | F94: 304.08 | G94: 49.519651 | H94: =G94*F94 -> 15057.935 | I94: EPC'S | J94: Lançado ERP
B95: SERVIÇO | C95: 02.001.002.009 | D95: Cobertura para Proteção de Pedestres | E95: m2 | F95: 137.13 | G95: 880 | H95: =G95*F95 -> 120674.4 | I95: EPC'S | J95: Lançado ERP
B96: SERVIÇO | C96: 02.001.002.010 | D96: Varal de segurança com cabo de aço (linha de vida) | E96: m | F96: 0 | G96: 87.214 | H96: =G96*F96 -> 0 | I96: EPC'S | J96: Lançado ERP
B97: SERVIÇO | C97: 02.001.002.011 | D97: Tela SLQA | E97: m | F97: 0 | G97: 88 | H97: =G97*F97 -> 0 | I97: EPC'S | J97: Lançado ERP
B98: SUBETAPA | C98: 02.001.003 | D98: Meio Ambiente | H98: =H99+H100+H101 -> 85259.856
B99: SERVIÇO | C99: 02.001.003.001 | D99: Elaboração do Programa de Controle Médico de Saúde Ocupacional (PCMSO) | E99: vb | F99: 1 | G99: 8059.8562 | H99: =G99*F99 -> 8059.8562 | I99: Estimado | J99: Finalizado
B100: SERVIÇO | C100: 02.001.003.002 | D100: Elaboração do programa de gerenciamento de riscos (PGR) | E100: vb | F100: 1 | G100: 5200 | H100: =G100*F100 -> 5200 | I100: Recebido | J100: Finalizado
B101: SERVIÇO | C101: 02.001.003.003 | D101: Remoção de entulhos e resíduos | E101: mês | F101: 36 | G101: 2000 | H101: =G101*F101 -> 72000 | I101: Estimado | J101: Finalizado
B102: SUBETAPA | C102: 02.001.004 | D102: Saúde Ocupacional | H102: =H103+H104+H105 -> 9521.1865
B103: SERVIÇO | C103: 02.001.004.001 | D103: Medicamentos preventivos e de emergência | E103: vb | F103: 1 | G103: 3789.0563 | H103: =G103*F103 -> 3789.0563 | I103: Estimado | J103: Finalizado
B104: SERVIÇO | C104: 02.001.004.002 | D104: Kit socorrista | E104: vb | F104: 1 | G104: 1232.1302 | H104: =G104*F104 -> 1232.1302 | I104: Estimado | J104: Finalizado
B105: SERVIÇO | C105: 02.001.004.003 | D105: Dedetização, desratização e sanitização dos ambientes | E105: mês | F105: 18 | G105: 250 | H105: =G105*F105 -> 4500 | I105: Estimado | J105: Finalizado
B106: ETAPA | C106: 02.002 | D106: ADMINISTRAÇÃO E CANTEIRO DE OBRA | H106: =H107+H114+H133+H138 -> 4271209.1
B107: SUBETAPA | C107: 02.002.001 | D107: Equipe de Gestão e Apoio | H107: =H108+H109+H110+H111+H112+H113 -> 2054400
B108: SERVIÇO | C108: 02.002.001.001 | D108: Engenheiro Civil | E108: mês | F108: 48 | G108: 21000 | H108: =G108*F108 -> 1008000 | I108: Recebido | J108: Finalizado
B109: SERVIÇO | C109: 02.002.001.002 | D109: Almoxarife | E109: mês | F109: 24 | G109: 5000 | H109: =G109*F109 -> 120000 | I109: Recebido | J109: Finalizado
B110: SERVIÇO | C110: 02.002.001.003 | D110: Auxiliar de engenharia | E110: mês | F110: 12 | G110: 6800 | H110: =G110*F110 -> 81600 | I110: Recebido | J110: Finalizado
B111: SERVIÇO | C111: 02.002.001.004 | D111: Assistente administrativo | E111: mês | F111: 48 | G111: 4500 | H111: =G111*F111 -> 216000 | I111: Recebido | J111: Finalizado
B112: SERVIÇO | C112: 02.002.001.005 | D112: Estagiário | E112: mês | F112: 36 | G112: 2000 | H112: =G112*F112 -> 72000 | I112: Recebido | J112: Finalizado
B113: SERVIÇO | C113: 02.002.001.006 | D113: Vigilância / portaria | E113: mês | F113: 48 | G113: 11600 | H113: =G113*F113 -> 556800 | I113: Estimado - Vamos contratar o controle da Inmeta (Sistema) e instalar catraca e facial (prever custo) | J113: Finalizado
...

Sheet Ger_Executivo_Cartesian
H4: PROJETO: | I4: Electra Towers | O4: REVISÃO: | P4: DATA
H5: EMPRESA: | I5: Thozen | O5: R00
A6: Unidade Construtiva | B6: Célula Construtiva | C6: Etapa | D6: Subetapa | E6: Serviço | G6: GERENCIAMENTO EXECUTIVO
A7: 0 | B7: 0 | C7: 0 | D7: 0 | E7: 0 | G7: EAP | H7: NIVEL | I7: Item | J7: Descrição | K7: Unidade | L7: Quant. | M7: Preço un | N7: Total | O7: Considerações | P7: Situação
A8: 0 | B8: 1 | C8: 0 | D8: 0 | E8: 0 | H8: CÉLULA CONSTRUTIVA | I8: 01 | J8: MOVIMENTAÇÃO DE TERRA
A9: 0 | B9: 1 | C9: 1 | D9: 0 | E9: 0 | H9: ETAPA | I9: 01.001 | J9: DEMOLIÇÕES, LIMPEZA DE TERRENO E LOCAÇÃO DE OBRA | N9: 26235.314 | O9: 1.5663183
A10: 0 | B10: 1 | C10: 1 | D10: 1 | E10: 0 | H10: SUBETAPA | I10: 01.001.001 | J10: Locação e gabarito de obra | N10: 26235.314 | O10: 1.5663183
A11: 0 | B11: 1 | C11: 1 | D11: 1 | E11: 1 | G11: MOVIMENTAÇÃO DE TERRA | H11: SERVIÇO | I11: 01.001.001.001 | J11: Locação da obra | K11: m2 | N11: 26235.314 | P11: Pendente
A12: 0 | B12: 1 | C12: 2 | D12: 0 | E12: 1 | H12: ETAPA | I12: 01.002 | J12: SERVIÇOS PRELIMINARES
A13: 0 | B13: 1 | C13: 2 | D13: 1 | E13: 0 | H13: SUBETAPA | I13: 01.002.001 | J13: Limpeza Permanente e Remoção entulho
A14: 0 | B14: 1 | C14: 2 | D14: 1 | E14: 1 | G14: MOVIMENTAÇÃO DE TERRA | H14: SERVIÇO | I14: 01.002.001.001 | J14: Limpeza da camada vegetal | K14: m2 | P14: Pendente
A15: 0 | B15: 1 | C15: 2 | D15: 1 | E15: 2 | G15: MOVIMENTAÇÃO DE TERRA | H15: SERVIÇO | I15: 01.002.001.002 | J15: Remoção de entulhos e resíduos | P15: Pendente
A16: 0 | B16: 1 | C16: 2 | D16: 2 | E16: 0 | H16: SUBETAPA | I16: 01.002.002 | J16: Mão de Obra de Canteiro
A17: 0 | B17: 1 | C17: 2 | D17: 2 | E17: 1 | G17: MOVIMENTAÇÃO DE TERRA | H17: SERVIÇO | I17: 01.002.002.001 | J17: Mão de Obra de Canteiro | K17: vb | P17: Pendente
A18: 0 | B18: 1 | C18: 3 | D18: 0 | E18: 1 | H18: ETAPA | I18: 01.003 | J18: SERVIÇOS DE TERRAPLANAGEM | N18: 271126.19 | O18: 16.186957
A19: 0 | B19: 1 | C19: 3 | D19: 1 | E19: 0 | H19: SUBETAPA | I19: 01.003.001 | J19: Mao de obra - movimentações de terra | N19: 271126.19 | O19: 16.186957
A20: 0 | B20: 1 | C20: 3 | D20: 1 | E20: 1 | G20: MOVIMENTAÇÃO DE TERRA | H20: SERVIÇO | I20: 01.003.001.001 | J20: Mão de obra movimentação de terra | K20: vb | N20: 233000 | P20: Pendente
A21: 0 | B21: 1 | C21: 4 | D21: 0 | E21: 2 | H21: ETAPA | I21: 01.004 | J21: SERVIÇO DE DRENAGEM | N21: 80000 | O21: 4.7762135
A22: 0 | B22: 1 | C22: 4 | D22: 1 | E22: 0 | H22: SUBETAPA | I22: 01.004.001 | J22: Drenagem | N22: 80000 | O22: 4.7762135
A23: 0 | B23: 1 | C23: 4 | D23: 1 | E23: 1 | G23: MOVIMENTAÇÃO DE TERRA | H23: SERVIÇO | I23: 01.004.001.001 | J23: Rebaixamento de Lençol freático | K23: vb | N23: 80000 | P23: Pendente
A24: 0 | B24: 2 | C24: 0 | D24: 1 | E24: 1 | H24: CÉLULA CONSTRUTIVA | I24: 02 | J24: CONTENÇÃO | N24: 772006.63 | O24: 46.090856
A25: 0 | B25: 2 | C25: 1 | D25: 0 | E25: 1 | H25: ETAPA | I25: 02.001 | J25: MURETA GUIA | N25: 18739.389 | O25: 1.1187915
A26: 0 | B26: 2 | C26: 1 | D26: 1 | E26: 0 | H26: SUBETAPA | I26: 02.001.001 | J26: Forma | N26: 6673.9436 | O26: 0.39845225
A27: 0 | B27: 2 | C27: 1 | D27: 1 | E27: 1 | G27: CONTENÇÃO | H27: SERVIÇO | I27: 02.001.001.001 | J27: Forma para infraestrutura em Tábuas de Madeira Serrada 2x reaproveitamento | K27: m2 | L27: 111.3136 | M27: 59.956229 | N27: 6673.9436 | P27: Pendente
A28: 0 | B28: 2 | C28: 1 | D28: 2 | E28: 0 | H28: SUBETAPA | I28: 02.001.002 | J28: Armadura | N28: 4318.7306 | O28: 0.25783974
A29: 0 | B29: 2 | C29: 1 | D29: 2 | E29: 1 | G29: CONTENÇÃO | H29: SERVIÇO | I29: 02.001.002.001 | J29: Armação aço CA-50 ø 6,3mm para Contenções (corte e dobra em obra) | K29: un | L29: 670.32 | M29: 6.0795674 | N29: 4075.2556 | P29: Pendente
A30: 0 | B30: 2 | C30: 1 | D30: 2 | E30: 2 | G30: CONTENÇÃO | H30: SERVIÇO | I30: 02.001.002.002 | J30: Armação aço CA-50 ø 12,5mm para Contenções (corte e dobra em obra) | K30: un | L30: 41.6016 | M30: 5.8525391 | N30: 243.47499 | P30: Pendente
A31: 0 | B31: 2 | C31: 1 | D31: 3 | E31: 0 | H31: SUBETAPA | I31: 02.001.003 | J31: Concreto | N31: 7746.7147 | O31: 0.46249954
A32: 0 | B32: 2 | C32: 1 | D32: 3 | E32: 1 | G32: CONTENÇÃO | H32: SERVIÇO | I32: 02.001.003.001 | J32: Concreto Usinado bombeável 50MPa para infraestrutura- incluindo serviço de bombeamento | K32: m3 | L32: 11.390452 | M32: 680.106 | N32: 7746.7147 | P32: Pendente
A33: 0 | B33: 2 | C33: 2 | D33: 0 | E33: 1 | H33: ETAPA | I33: 02.002 | J33: LAMELAS | PAREDE DIAFRAGMA | N33: 331865.23 | O33: 19.81324
A34: 0 | B34: 2 | C34: 2 | D34: 1 | E34: 0 | H34: SUBETAPA | I34: 02.002.001 | J34: Armadura | N34: 155967.97 | O34: 9.3117038
A35: 0 | B35: 2 | C35: 2 | D35: 1 | E35: 1 | G35: CONTENÇÃO | H35: SERVIÇO | I35: 02.002.001.001 | J35: Armação aço CA-50 ø 6,3mm para Contenções (corte e dobra em Indústria) | K35: un | L35: 2282 | M35: 8.964145 | N35: 20456.179 | P35: Pendente
A36: 0 | B36: 2 | C36: 2 | D36: 1 | E36: 2 | G36: CONTENÇÃO | H36: SERVIÇO | I36: 02.002.001.002 | J36: Armação aço CA-50 ø 8,0mm para Contenções (corte e dobra em Indústria) | K36: un | L36: 77 | M36: 8.964145 | N36: 690.23916 | P36: Pendente
A37: 0 | B37: 2 | C37: 2 | D37: 1 | E37: 3 | G37: CONTENÇÃO | H37: SERVIÇO | I37: 02.002.001.003 | J37: Armação aço CA-50 ø 12,5mm para Contenções (corte e dobra em Indústria) | K37: un | L37: 3884 | M37: 8.484145 | N37: 32952.419 | P37: Pendente
A38: 0 | B38: 2 | C38: 2 | D38: 1 | E38: 4 | G38: CONTENÇÃO | H38: SERVIÇO | I38: 02.002.001.004 | J38: Armação aço CA-50 ø 25,0mm para Contenções (corte e dobra em Indústria) | K38: un | L38: 12007 | M38: 8.484145 | N38: 101869.13 | P38: Pendente
A39: 0 | B39: 2 | C39: 2 | D39: 2 | E39: 0 | H39: SUBETAPA | I39: 02.002.002 | J39: Concreto | N39: 175897.26 | O39: 10.501536
A40: 0 | B40: 2 | C40: 2 | D40: 2 | E40: 1 | G40: CONTENÇÃO | H40: SERVIÇO | I40: 02.002.002.001 | J40: Concreto Usinado bombeável 50MPa com Penetron para infraestrutura- incluindo serviço de bombeamento | K40: m3 | L40: 210 | M40: 837.606 | N40: 175897.26 | P40: Pendente
A41: 0 | B41: 2 | C41: 3 | D41: 0 | E41: 1 | H41: ETAPA | I41: 02.003 | J41: VIGAS COROAMENTO | N41: 37645.991 | O41: 2.2475661
A42: 0 | B42: 2 | C42: 3 | D42: 1 | E42: 0 | H42: SUBETAPA | I42: 02.003.001 | J42: Forma | N42: 2482.1879 | O42: 0.14819324
A43: 0 | B43: 2 | C43: 3 | D43: 1 | E43: 1 | G43: CONTENÇÃO | H43: SERVIÇO | I43: 02.003.001.001 | J43: Forma para infraestrutura em Tábuas de Madeira Serrada 2x reaproveitamento | K43: m2 | L43: 41.4 | M43: 59.956229 | N43: 2482.1879 | P43: Pendente
A44: 0 | B44: 2 | C44: 3 | D44: 2 | E44: 0 | H44: SUBETAPA | I44: 02.003.002 | J44: Armadura | N44: 23057.916 | O44: 1.3766191
A45: 0 | B45: 2 | C45: 3 | D45: 2 | E45: 1 | G45: CONTENÇÃO | H45: SERVIÇO | I45: 02.003.002.001 | J45: Armação aço CA-50 ø 8,0mm para Contenções (corte e dobra em Indústria) | K45: kg | L45: 913.36364 | M45: 8.964145 | N45: 8187.5241 | P45: Pendente
A46: 0 | B46: 2 | C46: 3 | D46: 2 | E46: 2 | G46: CONTENÇÃO | H46: SERVIÇO | I46: 02.003.002.002 | J46: Armação aço CA-50 ø 12,5mm para Contenções (corte e dobra em Indústria) | K46: kg | L46: 45.363636 | M46: 8.484145 | N46: 384.87167 | P46: Pendente
A47: 0 | B47: 2 | C47: 3 | D47: 2 | E47: 3 | G47: CONTENÇÃO | H47: SERVIÇO | I47: 02.003.002.003 | J47: Armação aço CA-50 ø 16,0mm para Contenções (corte e dobra em Indústria) | K47: kg | L47: 1277.2727 | M47: 8.484145 | N47: 10836.567 | P47: Pendente
A48: 0 | B48: 2 | C48: 3 | D48: 2 | E48: 4 | G48: CONTENÇÃO | H48: SERVIÇO | I48: 02.003.002.004 | J48: Armação aço CA-50 ø 20,0mm para Contenções (corte e dobra em Indústria) | K48: kg | L48: 430.09091 | M48: 8.484145 | N48: 3648.9536 | P48: Pendente
A49: 0 | B49: 2 | C49: 3 | D49: 3 | E49: 0 | H49: SUBETAPA | I49: 02.003.003 | J49: Concreto | N49: 12105.887
A50: 0 | B50: 2 | C50: 3 | D50: 3 | E50: 1 | G50: CONTENÇÃO | H50: SERVIÇO | I50: 02.003.003.001 | J50: Concreto Usinado bombeável 50MPa para infraestrutura- incluindo serviço de bombeamento | K50: m3 | L50: 17.8 | M50: 680.106 | N50: 12105.887 | P50: Pendente
A51: 0 | B51: 2 | C51: 4 | D51: 0 | E51: 1 | H51: ETAPA | I51: 02.004 | J51: ESTACAS PRANCHA METÁLICA | N51: 243756 | O51: 14.552884
A52: 0 | B52: 2 | C52: 4 | D52: 1 | E52: 0 | H52: SUBETAPA | I52: 02.004.001 | J52: Estacas prancha metálica | N52: 243756 | O52: 14.552884
A53: 0 | B53: 2 | C53: 4 | D53: 1 | E53: 1 | G53: CONTENÇÃO | H53: SERVIÇO | I53: 02.004.001.001 | J53: Locação e cravação de estacas prancha EP400 para contenção | K53: m2 | L53: 492.8 | M53: 470.28409 | N53: 231756 | O53: Cotação, considerado 6 meses de locação | P53: Pendente
A54: 0 | B54: 2 | C54: 4 | D54: 1 | E54: 2 | G54: CONTENÇÃO | H54: SERVIÇO | I54: 02.004.001.002 | J54: Mobilização e Desmobilização de equipamento e máquinas considerando serviço de carga e descarga | K54: vb | L54: 1 | M54: 12000 | N54: 12000 | P54: Pendente
A55: 0 | B55: 2 | C55: 5 | D55: 0 | E55: 2 | H55: ETAPA | I55: 02.005 | J55: MÃO DE OBRA CONTENÇÕES | N55: 140000.02 | O55: 8.3583748
A56: 0 | B56: 2 | C56: 5 | D56: 1 | E56: 0 | H56: SUBETAPA | I56: 02.005.001 | J56: Mão de Obra | N56: 140000.02 | O56: 8.3583748
A57: 0 | B57: 2 | C57: 5 | D57: 1 | E57: 1 | G57: CONTENÇÃO | H57: SERVIÇO | I57: 02.005.001.001 | J57: Mão de obra para execução de contenção | K57: m2 | L57: 525 | M57: 266.6667 | N57: 140000.02 | O57: Prosposta Gessele | P57: Pendente
A58: 0 | B58: 3 | C58: 0 | D58: 1 | E58: 1 | H58: CÉLULA CONSTRUTIVA | I58: 03 | J58: INFRAESTRUTURA | N58: 4572490 | O58: 272.98986
A59: 0 | B59: 3 | C59: 1 | D59: 0 | E59: 1 | H59: ETAPA | I59: 03.001 | J59: ESTACA HÉLICE CONTÍNUA | N59: 3041540.5 | O59: 181.58809
A60: 0 | B60: 3 | C60: 1 | D60: 1 | E60: 0 | H60: SUBETAPA | I60: 03.001.001 | J60: Perfuração | N60: 950000 | O60: 56.717535
A61: 0 | B61: 3 | C61: 1 | D61: 1 | E61: 1 | G61: INFRAESTRUTURA | H61: SERVIÇO | I61: 03.001.001.001 | J61: Perfuração de estaca hélice contínua Ø 60cm | K61: m | L61: 6732 | M61: 137.48633 | N61: 925557.99 | O61: Repessado pela Gessele na reunião do dia 05/03/2026 - 950k efeg | P61: Pendente
A62: 0 | B62: 3 | C62: 1 | D62: 1 | E62: 2 | G62: INFRAESTRUTURA | H62: SERVIÇO | I62: 03.001.001.002 | J62: Mobilização e desmobilização de equipamentos - Para execução de estaca hélice monitorada | K62: vb | L62: 1 | M62: 24442.015 | N62: 24442.015 | O62: Repessado pela Gessele na reunião do dia 05/03/2026 - 950k efeg | P62: Pendente
A63: 0 | B63: 3 | C63: 1 | D63: 2 | E63: 0 | H63: SUBETAPA | I63: 03.001.002 | J63: Armadura | N63: 298834.78 | O63: 17.841234
A64: 0 | B64: 3 | C64: 1 | D64: 2 | E64: 1 | G64: INFRAESTRUTURA | H64: SERVIÇO | I64: 03.001.002.001 | J64: Armação aço CA-50 ø 6,3mm para estaca (corte e dobra em indústria) | K64: un | L64: 3495 | M64: 8.964145 | N64: 31329.687 | P64: Pendente
A65: 0 | B65: 3 | C65: 1 | D65: 2 | E65: 2 | G65: INFRAESTRUTURA | H65: SERVIÇO | I65: 03.001.002.002 | J65: Armação aço CA-50 ø 20,0mm para estaca (corte e dobra em indústria) | K65: un | L65: 31530 | M65: 8.484145 | N65: 267505.09 | P65: Pendente
A66: 0 | B66: 3 | C66: 1 | D66: 3 | E66: 0 | H66: SUBETAPA | I66: 03.001.003 | J66: Concreto | N66: 1792705.7 | O66: 107.02932
A67: 0 | B67: 3 | C67: 1 | D67: 3 | E67: 1 | G67: INFRAESTRUTURA | H67: SERVIÇO | I67: 03.001.003.001 | J67: Concreto Usinado bombeável para estacas 50MPa - incluindo serviço de bombeamento | K67: m3 | L67: 1903.4282 | M67: 941.83 | N67: 1792705.7 | P67: Pendente
A68: 0 | B68: 3 | C68: 1 | D68: 4 | E68: 0 | H68: SUBETAPA | I68: 03.001.004 | J68: Mão de Obra | N68: 0 | O68: 0
A69: 0 | B69: 3 | C69: 2 | D69: 0 | E69: 0 | H69: ETAPA | I69: 03.002 | J69: BLOCOS | N69: 1056067.4 | O69: 63.050045
A70: 0 | B70: 3 | C70: 2 | D70: 1 | E70: 0 | H70: SUBETAPA | I70: 03.002.001 | J70: Forma | N70: 15723.521 | O70: 0.93873616
A71: 0 | B71: 3 | C71: 2 | D71: 1 | E71: 1 | G71: INFRAESTRUTURA | H71: SERVIÇO | I71: 03.002.001.001 | J71: Forma para infraestrutura em Tábuas de Madeira Serrada 2x reaproveitamento | K71: m2 | L71: 262.25 | M71: 59.956229 | N71: 15723.521 | O71: Apenas blocos, 2x reaproveitamento | P71: Pendente
A72: 0 | B72: 3 | C72: 2 | D72: 2 | E72: 0 | H72: SUBETAPA | I72: 03.002.002 | J72: Armadura | N72: 592494.12 | O72: 35.37348
A73: 0 | B73: 3 | C73: 2 | D73: 2 | E73: 1 | G73: INFRAESTRUTURA | H73: SERVIÇO | I73: 03.002.002.001 | J73: Armação aço CA-50 ø 12,5mm para infraestrutura (corte e dobra em Indústria) | K73: kg | L73: 528.18182 | M73: 8.484145 | N73: 4481.1711 | P73: Pendente
A74: 0 | B74: 3 | C74: 2 | D74: 2 | E74: 2 | G74: INFRAESTRUTURA | H74: SERVIÇO | I74: 03.002.002.002 | J74: Armação aço CA-50 ø 16,0mm para infraestrutura (corte e dobra em Indústria) | K74: kg | L74: 7331.8182 | M74: 8.484145 | N74: 62204.209 | P74: Pendente
A75: 0 | B75: 3 | C75: 2 | D75: 2 | E75: 3 | G75: INFRAESTRUTURA | H75: SERVIÇO | I75: 03.002.002.003 | J75: Armação aço CA-50 ø 20,0mm para infraestrutura (corte e dobra em Indústria) | K75: kg | L75: 1318.1818 | M75: 8.484145 | N75: 11183.646 | P75: Pendente
A76: 0 | B76: 3 | C76: 2 | D76: 2 | E76: 4 | G76: INFRAESTRUTURA | H76: SERVIÇO | I76: 03.002.002.004 | J76: Armação aço CA-50 ø 25,0mm para infraestrutura (corte e dobra em Indústria) | K76: kg | L76: 60657.273 | M76: 8.484145 | N76: 514625.1 | P76: Pendente
A77: 0 | B77: 3 | C77: 2 | D77: 3 | E77: 0 | H77: SUBETAPA | I77: 03.002.003 | J77: Concreto | N77: 447849.8 | O77: 26.737828
A78: 0 | B78: 3 | C78: 2 | D78: 3 | E78: 1 | G78: INFRAESTRUTURA | H78: SERVIÇO | I78: 03.002.003.001 | J78: Concreto Usinado bombeável 50MPa para infraestrutura- incluindo serviço de bombeamento | K78: m3 | L78: 658.5 | M78: 680.106 | N78: 447849.8 | O78: 5% de perda, fck = 50Mpa | P78: Pendente
A79: 0 | B79: 3 | C79: 2 | D79: 4 | E79: 0 | H79: SUBETAPA | I79: 03.002.004 | J79: Mão de Obra | N79: 0 | O79: 0
A80: 0 | B80: 3 | C80: 3 | D80: 0 | E80: 0 | H80: ETAPA | I80: 03.003 | J80: VIGAS BALDRAMES | PILARES DE ARRANQUE | CISTERNAS E DUTOS | N80: 474882.06 | O80: 28.351727
A81: 0 | B81: 3 | C81: 3 | D81: 1 | E81: 0 | H81: SUBETAPA | I81: 03.003.001 | J81: Forma | N81: 9996.6219 | O81: 0.59682501
A82: 0 | B82: 3 | C82: 3 | D82: 1 | E82: 1 | G82: INFRAESTRUTURA | H82: SERVIÇO | I82: 03.003.001.001 | J82: Forma para infraestrutura em Tábuas de Madeira Serrada 2x reaproveitamento | K82: m2 | L82: 166.732 | M82: 59.956229 | N82: 9996.6219 | O82: Considerado blocos, vigas de fundação, duto, cisterna, lajes e pilares de arranque | P82: Pendente
A83: 0 | B83: 3 | C83: 3 | D83: 2 | E83: 0 | H83: SUBETAPA | I83: 03.003.002 | J83: Armadura | N83: 430167.93 | O83: 25.682173
A84: 0 | B84: 3 | C84: 3 | D84: 2 | E84: 1 | G84: INFRAESTRUTURA | H84: SERVIÇO | I84: 03.003.002.001 | J84: Armação aço CA-50 ø 5,0mm para infraestrutura (corte e dobra em Indústria) | K84: kg | L84: 52 | M84: 8.964145 | N84: 466.13554 | O84: Considerado vigas de fundação, duto, cisterna, lajes e pilares de arranque - 10% de perda | P84: Pendente
A85: 0 | B85: 3 | C85: 3 | D85: 2 | E85: 2 | G85: INFRAESTRUTURA | H85: SERVIÇO | I85: 03.003.002.002 | J85: Armação aço CA-50 ø 6,3mm para infraestrutura (corte e dobra em Indústria) | K85: kg | L85: 130.27273 | M85: 8.964145 | N85: 1167.7836 | O85: Considerado vigas de fundação, duto, cisterna, lajes e pilares de arranque - 10% de perda | P85: Pendente
A86: 0 | B86: 3 | C86: 3 | D86: 2 | E86: 3 | G86: INFRAESTRUTURA | H86: SERVIÇO | I86: 03.003.002.003 | J86: Armação aço CA-50 ø 8,0mm para infraestrutura (corte e dobra em Indústria) | K86: kg | L86: 982.63636 | M86: 8.964145 | N86: 8808.4948 | O86: Considerado vigas de fundação, duto, cisterna, lajes e pilares de arranque - 10% de perda | P86: Pendente
A87: 0 | B87: 3 | C87: 3 | D87: 2 | E87: 4 | G87: INFRAESTRUTURA | H87: SERVIÇO | I87: 03.003.002.004 | J87: Armação aço CA-50 ø 10,0mm para infraestrutura (corte e dobra em Indústria) | K87: kg | L87: 7011.6364 | M87: 8.964145 | N87: 62853.325 | O87: Considerado vigas de fundação, duto, cisterna, lajes e pilares de arranque - 10% de perda | P87: Pendente
A88: 0 | B88: 3 | C88: 3 | D88: 2 | E88: 5 | G88: INFRAESTRUTURA | H88: SERVIÇO | I88: 03.003.002.005 | J88: Armação aço CA-50 ø 12,5mm para infraestrutura (corte e dobra em Indústria) | K88: kg | L88: 6007.8182 | M88: 8.484145 | N88: 50971.201 | O88: Considerado vigas de fundação, duto, cisterna, lajes e pilares de arranque - 10% de perda | P88: Pendente
A89: 0 | B89: 3 | C89: 3 | D89: 2 | E89: 6 | G89: INFRAESTRUTURA | H89: SERVIÇO | I89: 03.003.002.006 | J89: Armação aço CA-50 ø 16,0mm para infraestrutura (corte e dobra em Indústria) | K89: kg | L89: 1269.7273 | M89: 8.484145 | N89: 10772.55 | O89: Considerado vigas de fundação, duto, cisterna, lajes e pilares de arranque - 10% de perda | P89: Pendente
A90: 0 | B90: 3 | C90: 3 | D90: 2 | E90: 7 | G90: INFRAESTRUTURA | H90: SERVIÇO | I90: 03.003.002.007 | J90: Armação aço CA-50 ø 20,0mm para infraestrutura (corte e dobra em Indústria) | K90: kg | L90: 902 | M90: 8.484145 | N90: 7652.6988 | O90: Considerado vigas de fundação, duto, cisterna, lajes e pilares de arranque - 10% de perda | P90: Pendente
A91: 0 | B91: 3 | C91: 3 | D91: 2 | E91: 8 | G91: INFRAESTRUTURA | H91: SERVIÇO | I91: 03.003.002.008 | J91: Armação aço CA-50 ø 25,0mm para infraestrutura (corte e dobra em Indústria) | K91: kg | L91: 4680 | M91: 8.484145 | N91: 39705.799 | O91: Considerado vigas de fundação, duto, cisterna, lajes e pilares de arranque - 10% de perda | P91: Pendente
A92: 0 | B92: 3 | C92: 3 | D92: 2 | E92: 9 | G92: INFRAESTRUTURA | H92: SERVIÇO | I92: 03.003.002.009 | J92: Armação aço CA-50 ø 32,00mm para infraestrutura (corte e dobra em Indústria) | K92: kg | L92: 27316 | M92: 9.0705059 | N92: 247769.94 | O92: Considerado vigas de fundação, duto, cisterna, lajes e pilares de arranque - 10% de perda | P92: Pendente
A93: 0 | B93: 3 | C93: 3 | D93: 3 | E93: 0 | H93: SUBETAPA | I93: 03.003.003 | J93: Concreto | N93: 34717.514 | O93: 2.0727282
A94: 0 | B94: 3 | C94: 3 | D94: 3 | E94: 1 | G94: INFRAESTRUTURA | H94: SERVIÇO | I94: 03.003.003.001 | J94: Concreto Usinado bombeável 50MPa para infraestrutura- incluindo serviço de bombeamento | K94: m3 | L94: 51.04721 | M94: 680.106 | N94: 34717.514 | O94: Cotações recentes do concreto. Considerado vigas de fundação, duto, cisterna, lajes e pilares de arranque - 5% de perda, fck = 50Mpa | P94: Pendente
A95: 0 | B95: 3 | C95: 3 | D95: 4 | E95: 0 | H95: SUBETAPA | I95: 03.003.004 | J95: Mão de Obra | N95: 0 | O95: 0
A96: 0 | B96: 4 | C96: 0 | D96: 4 | E96: 0 | H96: CÉLULA CONSTRUTIVA | I96: 04 | J96: SUPRAESTRUTURA | N96: 20793271 | O96: 1241.4138
A97: 0 | B97: 4 | C97: 1 | D97: 0 | E97: 0 | H97: ETAPA | I97: 04.001 | J97: PISO SOBRE O SOLO - GERAL | N97: 19428.045 | O97: 1.1599061
A98: 0 | B98: 4 | C98: 1 | D98: 1 | E98: 0 | H98: SUBETAPA | I98: 04.001.001 | J98: Piso sobre o solo - Geral | N98: 19428.045 | O98: 1.1599061
A99: 0 | B99: 4 | C99: 1 | D99: 1 | E99: 1 | G99: SUPRAESTRUTURA | H99: SERVIÇO | I99: 04.001.001.001 | J99: Lastro de Concreto Magro, Aplicado em piso sobre solo | K99: m3 | L99: 39.229 | M99: 495.247 | N99: 19428.045 | O99: O concreto e a armadura entraram nos itens referentes ao terreo, conforme lista de materiais do projetista | P99: Pendente
A100: 0 | B100: 4 | C100: 2 | D100: 0 | E100: 1 | H100: ETAPA | I100: 04.002 | J100: FORMA | N100: 1435615 | O100: 85.710046
A101: 0 | B101: 4 | C101: 2 | D101: 1 | E101: 0 | H101: SUBETAPA | I101: 04.002.001 | J101: Forma - Térreo | N101: 529090.67 | O101: 31.588125
A102: 0 | B102: 4 | C102: 2 | D102: 1 | E102: 1 | G102: SUPRAESTRUTURA | H102: SERVIÇO | I102: 04.002.001.001 | J102: Fabricação de Fôrma para Supraestrutura, em Chapa de Madeira Compensada Resinada, E=20mm | K102: m2 | L102: 4874.3226 | M102: 108.03523 | N102: 526598.54 | O102: 8x reaproveitamento - 3 jogos | P102: Pendente
A103: 0 | B103: 4 | C103: 2 | D103: 1 | E103: 2 | G103: SUPRAESTRUTURA | H103: SERVIÇO | I103: 04.002.001.002 | J103: Montagem e Desmontagem de Fôrma de Supraestrutura | K103: m2 | L103: 626.5792 | M103: 3.9773488 | N103: 2492.124 | P103: Pendente
...

Sheet CPU
A1: Repetição | B1: Tipo | C1: Descrição | D1: Descrição | E1: Und | F1: Quantidade | G1: Custo unit. | H1: Custo Total. | I1: Quantidade | J1: Cuto Total | K1: Observgações
A2: 1 | B2: Etapa | C2: Descrição | D2: CUSTOS INDIRETOS | G2: {=IF(B2="insumo",_xlfn.XLOOKUP($D2,Insumos!$B$1:$B$996,Insumos!$D$1:$D$996),"")} | H2: 0 | I2: 0 | J2: 0
A3: 1 | B3: Subetapa | C3: Descrição | D3: INSTALAÇÕES PROVISÓRIAS | H3: 0 | I3: 0 | J3: 0
A4: 1 | B4: Serviço | C4: Central de aço | D4: Central de aço | E4: M2 | G4: {=IF(B4="insumo",_xlfn.XLOOKUP($D4,Insumos!$B$1:$B$996,Insumos!$D$1:$D$996),"")} | H4: 118.1045 | I4: 0 | J4: 0
A5: 3 | B5: Insumo | C5: Central de aço | D5: LONA PLASTICA 120 MICRAS 4X100M PRETA | E5: {=_xlfn.XLOOKUP(D5,Insumos!B:B,Insumos!C:$C)} -> M2 | F5: 1 | G5: {=IF(B5="insumo",_xlfn.XLOOKUP($D5,Insumos!$B$1:$B$996,Insumos!$D$1:$D$996),"")} -> 1.25 | H5: 1.25 | I5: 0 | J5: 0
A6: 3 | B6: Insumo | C6: Central de aço | D6: TELHA METALICA GALVANIZADA TRAPEZOIDAL 0,43MM NBR 14514 | E6: {=_xlfn.XLOOKUP(D6,Insumos!B:B,Insumos!C:$C)} -> M2 | F6: 1 | G6: {=IF(B6="insumo",_xlfn.XLOOKUP($D6,Insumos!$B$1:$B$996,Insumos!$D$1:$D$996),"")} -> 31 | H6: 31 | I6: 0 | J6: 0
A7: 9 | B7: Insumo | C7: Central de aço | D7: Concreto Usinado bombeável 20MPa Convencional | E7: {=_xlfn.XLOOKUP(D7,Insumos!B:B,Insumos!C:$C)} -> M3 | F7: 0.074 | G7: {=IF(B7="insumo",_xlfn.XLOOKUP($D7,Insumos!$B$1:$B$996,Insumos!$D$1:$D$996),"")} -> 490 | H7: 36.26 | I7: 0 | J7: 0
A8: 3 | B8: Insumo | C8: Central de aço | D8: PREGO GALVANIZADO LISO S/CABECA 17X21 NBR 6627 | E8: {=_xlfn.XLOOKUP(D8,Insumos!B:B,Insumos!C:$C)} -> KG | F8: 0.15 | G8: {=IF(B8="insumo",_xlfn.XLOOKUP($D8,Insumos!$B$1:$B$996,Insumos!$D$1:$D$996),"")} -> 10.03 | H8: 1.5045 | I8: 0 | J8: 0
A9: 3 | B9: Insumo | C9: Central de aço | D9: BLOCO CONCRETO ESTRUTURAL 03MPA 14X19X39CM NBR 6136 | E9: {=_xlfn.XLOOKUP(D9,Insumos!B:B,Insumos!C:$C)} -> UN | F9: 9 | G9: {=IF(B9="insumo",_xlfn.XLOOKUP($D9,Insumos!$B$1:$B$996,Insumos!$D$1:$D$996),"")} -> 2.95 | H9: 26.55 | I9: 0 | J9: 0
A10: 3 | B10: Insumo | C10: Central de aço | D10: ARGAMASSA ENSACADA P/ASSENTAMENTO BLOCO 04MPA NBR 13281 | E10: {=_xlfn.XLOOKUP(D10,Insumos!B:B,Insumos!C:$C)} -> KG | F10: 24 | G10: {=IF(B10="insumo",_xlfn.XLOOKUP($D10,Insumos!$B$1:$B$996,Insumos!$D$1:$D$996),"")} -> 0.46 | H10: 11.04 | I10: 0 | J10: 0
A11: 3 | B11: Insumo | C11: Central de aço | D11: SERVICO EMP. - INST. PROVISORIA - CONFECCAO BAIA P/MATERIAL | E11: {=_xlfn.XLOOKUP(D11,Insumos!B:B,Insumos!C:$C)} -> M2 | F11: 1 | G11: {=IF(B11="insumo",_xlfn.XLOOKUP($D11,Insumos!$B$1:$B$996,Insumos!$D$1:$D$996),"")} -> 10.5 | H11: 10.5 | I11: 0 | J11: 0
A12: 1 | B12: Serviço | C12: Central de fôrmas | D12: Central de fôrmas | E12: M2 | G12: {=IF(B12="insumo",_xlfn.XLOOKUP($D12,Insumos!$B$1:$B$996,Insumos!$D$1:$D$996),"")} | H12: 118.1045 | I12: 0 | J12: 0
A13: 3 | B13: Insumo | C13: Central de fôrmas | D13: LONA PLASTICA 120 MICRAS 4X100M PRETA | E13: {=_xlfn.XLOOKUP(D13,Insumos!B:B,Insumos!C:$C)} -> M2 | F13: 1 | G13: {=IF(B13="insumo",_xlfn.XLOOKUP($D13,Insumos!$B$1:$B$996,Insumos!$D$1:$D$996),"")} -> 1.25 | H13: 1.25 | I13: 0 | J13: 0
A14: 3 | B14: Insumo | C14: Central de fôrmas | D14: TELHA METALICA GALVANIZADA TRAPEZOIDAL 0,43MM NBR 14514 | E14: {=_xlfn.XLOOKUP(D14,Insumos!B:B,Insumos!C:$C)} -> M2 | F14: 1 | G14: {=IF(B14="insumo",_xlfn.XLOOKUP($D14,Insumos!$B$1:$B$996,Insumos!$D$1:$D$996),"")} -> 31 | H14: 31 | I14: 0 | J14: 0
A15: 9 | B15: Insumo | C15: Central de fôrmas | D15: Concreto Usinado bombeável 20MPa Convencional | E15: {=_xlfn.XLOOKUP(D15,Insumos!B:B,Insumos!C:$C)} -> M3 | F15: 0.074 | G15: {=IF(B15="insumo",_xlfn.XLOOKUP($D15,Insumos!$B$1:$B$996,Insumos!$D$1:$D$996),"")} -> 490 | H15: 36.26 | I15: 0 | J15: 0
A16: 3 | B16: Insumo | C16: Central de fôrmas | D16: PREGO GALVANIZADO LISO S/CABECA 17X21 NBR 6627 | E16: {=_xlfn.XLOOKUP(D16,Insumos!B:B,Insumos!C:$C)} -> KG | F16: 0.15 | G16: {=IF(B16="insumo",_xlfn.XLOOKUP($D16,Insumos!$B$1:$B$996,Insumos!$D$1:$D$996),"")} -> 10.03 | H16: 1.5045 | I16: 0 | J16: 0
A17: 3 | B17: Insumo | C17: Central de fôrmas | D17: BLOCO CONCRETO ESTRUTURAL 03MPA 14X19X39CM NBR 6136 | E17: {=_xlfn.XLOOKUP(D17,Insumos!B:B,Insumos!C:$C)} -> UN | F17: 9 | G17: {=IF(B17="insumo",_xlfn.XLOOKUP($D17,Insumos!$B$1:$B$996,Insumos!$D$1:$D$996),"")} -> 2.95 | H17: 26.55 | I17: 0 | J17: 0
A18: 3 | B18: Insumo | C18: Central de fôrmas | D18: ARGAMASSA ENSACADA P/ASSENTAMENTO BLOCO 04MPA NBR 13281 | E18: {=_xlfn.XLOOKUP(D18,Insumos!B:B,Insumos!C:$C)} -> KG | F18: 24 | G18: {=IF(B18="insumo",_xlfn.XLOOKUP($D18,Insumos!$B$1:$B$996,Insumos!$D$1:$D$996),"")} -> 0.46 | H18: 11.04 | I18: 0 | J18: 0
A19: 3 | B19: Insumo | C19: Central de fôrmas | D19: SERVICO EMP. - INST. PROVISORIA - CONFECCAO BAIA P/MATERIAL | E19: {=_xlfn.XLOOKUP(D19,Insumos!B:B,Insumos!C:$C)} -> M2 | F19: 1 | G19: {=IF(B19="insumo",_xlfn.XLOOKUP($D19,Insumos!$B$1:$B$996,Insumos!$D$1:$D$996),"")} -> 10.5 | H19: 10.5 | I19: 0 | J19: 0
A20: 1 | B20: Serviço | C20: Central de Argamassa | D20: Central de Argamassa | E20: M2 | G20: {=IF(B20="insumo",_xlfn.XLOOKUP($D20,Insumos!$B$1:$B$996,Insumos!$D$1:$D$996),"")} | H20: 118.1045 | I20: 0 | J20: 0
A21: 3 | B21: Insumo | C21: Central de Argamassa | D21: LONA PLASTICA 120 MICRAS 4X100M PRETA | E21: {=_xlfn.XLOOKUP(D21,Insumos!B:B,Insumos!C:$C)} -> M2 | F21: 1 | G21: {=IF(B21="insumo",_xlfn.XLOOKUP($D21,Insumos!$B$1:$B$996,Insumos!$D$1:$D$996),"")} -> 1.25 | H21: 1.25 | I21: 0 | J21: 0
A22: 3 | B22: Insumo | C22: Central de Argamassa | D22: TELHA METALICA GALVANIZADA TRAPEZOIDAL 0,43MM NBR 14514 | E22: {=_xlfn.XLOOKUP(D22,Insumos!B:B,Insumos!C:$C)} -> M2 | F22: 1 | G22: {=IF(B22="insumo",_xlfn.XLOOKUP($D22,Insumos!$B$1:$B$996,Insumos!$D$1:$D$996),"")} -> 31 | H22: 31 | I22: 0 | J22: 0
A23: 9 | B23: Insumo | C23: Central de Argamassa | D23: Concreto Usinado bombeável 20MPa Convencional | E23: {=_xlfn.XLOOKUP(D23,Insumos!B:B,Insumos!C:$C)} -> M3 | F23: 0.074 | G23: {=IF(B23="insumo",_xlfn.XLOOKUP($D23,Insumos!$B$1:$B$996,Insumos!$D$1:$D$996),"")} -> 490 | H23: 36.26 | I23: 0 | J23: 0
A24: 3 | B24: Insumo | C24: Central de Argamassa | D24: PREGO GALVANIZADO LISO S/CABECA 17X21 NBR 6627 | E24: {=_xlfn.XLOOKUP(D24,Insumos!B:B,Insumos!C:$C)} -> KG | F24: 0.15 | G24: {=IF(B24="insumo",_xlfn.XLOOKUP($D24,Insumos!$B$1:$B$996,Insumos!$D$1:$D$996),"")} -> 10.03 | H24: 1.5045 | I24: 0 | J24: 0
A25: 3 | B25: Insumo | C25: Central de Argamassa | D25: BLOCO CONCRETO ESTRUTURAL 03MPA 14X19X39CM NBR 6136 | E25: {=_xlfn.XLOOKUP(D25,Insumos!B:B,Insumos!C:$C)} -> UN | F25: 9 | G25: {=IF(B25="insumo",_xlfn.XLOOKUP($D25,Insumos!$B$1:$B$996,Insumos!$D$1:$D$996),"")} -> 2.95 | H25: 26.55 | I25: 0 | J25: 0
A26: 3 | B26: Insumo | C26: Central de Argamassa | D26: ARGAMASSA ENSACADA P/ASSENTAMENTO BLOCO 04MPA NBR 13281 | E26: {=_xlfn.XLOOKUP(D26,Insumos!B:B,Insumos!C:$C)} -> KG | F26: 24 | G26: {=IF(B26="insumo",_xlfn.XLOOKUP($D26,Insumos!$B$1:$B$996,Insumos!$D$1:$D$996),"")} -> 0.46 | H26: 11.04 | I26: 0 | J26: 0
A27: 3 | B27: Insumo | C27: Central de Argamassa | D27: SERVICO EMP. - INST. PROVISORIA - CONFECCAO BAIA P/MATERIAL | E27: {=_xlfn.XLOOKUP(D27,Insumos!B:B,Insumos!C:$C)} -> M2 | F27: 1 | G27: {=IF(B27="insumo",_xlfn.XLOOKUP($D27,Insumos!$B$1:$B$996,Insumos!$D$1:$D$996),"")} -> 10.5 | H27: 10.5 | I27: 0 | J27: 0
A28: 1 | B28: Serviço | C28: Armazenamento de cerâmicas* | D28: Armazenamento de cerâmicas* | E28: M2 | G28: {=IF(B28="insumo",_xlfn.XLOOKUP($D28,Insumos!$B$1:$B$996,Insumos!$D$1:$D$996),"")} | H28: 382.10489 | I28: 0 | J28: 0
A29: 11 | B29: Insumo | C29: Armazenamento de cerâmicas* | D29: MADEIRA PINUS/SIMILAR - TABUA PINUS 200X20MM NBR 11700 | E29: {=_xlfn.XLOOKUP(D29,Insumos!B:B,Insumos!C:$C)} -> M2 | F29: 0.591 | G29: {=IF(B29="insumo",_xlfn.XLOOKUP($D29,Insumos!$B$1:$B$996,Insumos!$D$1:$D$996),"")} -> 46.5 | H29: 27.4815 | I29: 0 | J29: 0
A30: 10 | B30: Insumo | C30: Armazenamento de cerâmicas* | D30: COMPENSADO MADEIRA TIPO RESINADO COLA FENOLICA 2440X1220X10MM | E30: {=_xlfn.XLOOKUP(D30,Insumos!B:B,Insumos!C:$C)} -> UN | F30: 0.404 | G30: {=IF(B30="insumo",_xlfn.XLOOKUP($D30,Insumos!$B$1:$B$996,Insumos!$D$1:$D$996),"")} -> 58.46 | H30: 23.61784 | I30: 0 | J30: 0
A31: 25 | B31: Insumo | C31: Armazenamento de cerâmicas* | D31: MADEIRA PINUS/SIMILAR - PONTALETE 75X75MM NBR 11700/15696 | E31: {=_xlfn.XLOOKUP(D31,Insumos!B:B,Insumos!C:$C)} -> M | F31: 4.39 | G31: {=IF(B31="insumo",_xlfn.XLOOKUP($D31,Insumos!$B$1:$B$996,Insumos!$D$1:$D$996),"")} -> 7 | H31: 30.73 | I31: 0 | J31: 0
A32: 11 | B32: Insumo | C32: Armazenamento de cerâmicas* | D32: MADEIRA PINUS/SIMILAR - SARRAFO PINUS 50X20MM NBR 11700/15696 | E32: {=_xlfn.XLOOKUP(D32,Insumos!B:B,Insumos!C:$C)} -> M2 | F32: 0.15 | G32: {=IF(B32="insumo",_xlfn.XLOOKUP($D32,Insumos!$B$1:$B$996,Insumos!$D$1:$D$996),"")} -> 46.5 | H32: 6.975 | I32: 0 | J32: 0
A33: 10 | B33: Insumo | C33: Armazenamento de cerâmicas* | D33: MADEIRA PINUS/SIMILAR - SARRAFO PINUS 50X10MM NBR 11700 | E33: {=_xlfn.XLOOKUP(D33,Insumos!B:B,Insumos!C:$C)} -> M | F33: 1 | G33: {=IF(B33="insumo",_xlfn.XLOOKUP($D33,Insumos!$B$1:$B$996,Insumos!$D$1:$D$996),"")} -> 7.39 | H33: 7.39 | I33: 0 | J33: 0
A34: 40 | B34: Insumo | C34: Armazenamento de cerâmicas* | D34: PREGO DE ACO POLIDO COM CABECA 17 X 21 (2 X 11) | E34: {=_xlfn.XLOOKUP(D34,Insumos!B:B,Insumos!C:$C)} -> KG | F34: 1 | G34: {=IF(B34="insumo",_xlfn.XLOOKUP($D34,Insumos!$B$1:$B$996,Insumos!$D$1:$D$996),"")} -> 18.13 | H34: 18.13 | I34: 0 | J34: 0
A35: 10 | B35: Insumo | C35: Armazenamento de cerâmicas* | D35: EXTINTOR INCENDIO PO QUIMICO 06KG CLASSE ABC (COMPLETO) NBR 15808 | E35: {=_xlfn.XLOOKUP(D35,Insumos!B:B,Insumos!C:$C)} -> UN | F35: 0.015 | G35: {=IF(B35="insumo",_xlfn.XLOOKUP($D35,Insumos!$B$1:$B$996,Insumos!$D$1:$D$996),"")} -> 185.37 | H35: 2.78055 | I35: 0 | J35: 0
A36: 10 | B36: Insumo | C36: Armazenamento de cerâmicas* | D36: MATERIAL PARA INSTALAÇÃO ELÉTRICA | E36: {=_xlfn.XLOOKUP(D36,Insumos!B:B,Insumos!C:$C)} -> VB | F36: 1 | G36: {=IF(B36="insumo",_xlfn.XLOOKUP($D36,Insumos!$B$1:$B$996,Insumos!$D$1:$D$996),"")} -> 215 | H36: 215 | I36: 0 | J36: 0
A37: 10 | B37: Insumo | C37: Armazenamento de cerâmicas* | D37: SERVICO INSTALAÇÃO BARRACAO ALMOXARIFADO | E37: {=_xlfn.XLOOKUP(D37,Insumos!B:B,Insumos!C:$C)} -> M2 | F37: 1 | G37: {=IF(B37="insumo",_xlfn.XLOOKUP($D37,Insumos!$B$1:$B$996,Insumos!$D$1:$D$996),"")} -> 50 | H37: 50 | I37: 0 | J37: 0
A38: 1 | B38: Serviço | C38: Armazenamento de placas degesso* | D38: Armazenamento de placas degesso* | E38: M2 | G38: {=IF(B38="insumo",_xlfn.XLOOKUP($D38,Insumos!$B$1:$B$996,Insumos!$D$1:$D$996),"")} | H38: 382.10489 | I38: 0 | J38: 0
A39: 11 | B39: Insumo | C39: Armazenamento de placas degesso* | D39: MADEIRA PINUS/SIMILAR - TABUA PINUS 200X20MM NBR 11700 | E39: {=_xlfn.XLOOKUP(D39,Insumos!B:B,Insumos!C:$C)} -> M2 | F39: 0.591 | G39: {=IF(B39="insumo",_xlfn.XLOOKUP($D39,Insumos!$B$1:$B$996,Insumos!$D$1:$D$996),"")} -> 46.5 | H39: 27.4815 | I39: 0 | J39: 0
A40: 10 | B40: Insumo | C40: Armazenamento de placas degesso* | D40: COMPENSADO MADEIRA TIPO RESINADO COLA FENOLICA 2440X1220X10MM | E40: {=_xlfn.XLOOKUP(D40,Insumos!B:B,Insumos!C:$C)} -> UN | F40: 0.404 | G40: {=IF(B40="insumo",_xlfn.XLOOKUP($D40,Insumos!$B$1:$B$996,Insumos!$D$1:$D$996),"")} -> 58.46 | H40: 23.61784 | I40: 0 | J40: 0
A41: 25 | B41: Insumo | C41: Armazenamento de placas degesso* | D41: MADEIRA PINUS/SIMILAR - PONTALETE 75X75MM NBR 11700/15696 | E41: {=_xlfn.XLOOKUP(D41,Insumos!B:B,Insumos!C:$C)} -> M | F41: 4.39 | G41: {=IF(B41="insumo",_xlfn.XLOOKUP($D41,Insumos!$B$1:$B$996,Insumos!$D$1:$D$996),"")} -> 7 | H41: 30.73 | I41: 0 | J41: 0
A42: 11 | B42: Insumo | C42: Armazenamento de placas degesso* | D42: MADEIRA PINUS/SIMILAR - SARRAFO PINUS 50X20MM NBR 11700/15696 | E42: {=_xlfn.XLOOKUP(D42,Insumos!B:B,Insumos!C:$C)} -> M2 | F42: 0.15 | G42: {=IF(B42="insumo",_xlfn.XLOOKUP($D42,Insumos!$B$1:$B$996,Insumos!$D$1:$D$996),"")} -> 46.5 | H42: 6.975 | I42: 0 | J42: 0
A43: 10 | B43: Insumo | C43: Armazenamento de placas degesso* | D43: MADEIRA PINUS/SIMILAR - SARRAFO PINUS 50X10MM NBR 11700 | E43: {=_xlfn.XLOOKUP(D43,Insumos!B:B,Insumos!C:$C)} -> M | F43: 1 | G43: {=IF(B43="insumo",_xlfn.XLOOKUP($D43,Insumos!$B$1:$B$996,Insumos!$D$1:$D$996),"")} -> 7.39 | H43: 7.39 | I43: 0 | J43: 0
A44: 40 | B44: Insumo | C44: Armazenamento de placas degesso* | D44: PREGO DE ACO POLIDO COM CABECA 17 X 21 (2 X 11) | E44: {=_xlfn.XLOOKUP(D44,Insumos!B:B,Insumos!C:$C)} -> KG | F44: 1 | G44: {=IF(B44="insumo",_xlfn.XLOOKUP($D44,Insumos!$B$1:$B$996,Insumos!$D$1:$D$996),"")} -> 18.13 | H44: 18.13 | I44: 0 | J44: 0
A45: 10 | B45: Insumo | C45: Armazenamento de placas degesso* | D45: EXTINTOR INCENDIO PO QUIMICO 06KG CLASSE ABC (COMPLETO) NBR 15808 | E45: {=_xlfn.XLOOKUP(D45,Insumos!B:B,Insumos!C:$C)} -> UN | F45: 0.015 | G45: {=IF(B45="insumo",_xlfn.XLOOKUP($D45,Insumos!$B$1:$B$996,Insumos!$D$1:$D$996),"")} -> 185.37 | H45: 2.78055 | I45: 0 | J45: 0
A46: 10 | B46: Insumo | C46: Armazenamento de placas degesso* | D46: MATERIAL PARA INSTALAÇÃO ELÉTRICA | E46: {=_xlfn.XLOOKUP(D46,Insumos!B:B,Insumos!C:$C)} -> VB | F46: 1 | G46: {=IF(B46="insumo",_xlfn.XLOOKUP($D46,Insumos!$B$1:$B$996,Insumos!$D$1:$D$996),"")} -> 215 | H46: 215 | I46: 0 | J46: 0
A47: 10 | B47: Insumo | C47: Armazenamento de placas degesso* | D47: SERVICO INSTALAÇÃO BARRACAO ALMOXARIFADO | E47: {=_xlfn.XLOOKUP(D47,Insumos!B:B,Insumos!C:$C)} -> M2 | F47: 1 | G47: {=IF(B47="insumo",_xlfn.XLOOKUP($D47,Insumos!$B$1:$B$996,Insumos!$D$1:$D$996),"")} -> 50 | H47: 50 | I47: 0 | J47: 0
A48: 1 | B48: Serviço | C48: Armazenamento de blocos* | D48: Armazenamento de blocos* | E48: M2 | G48: {=IF(B48="insumo",_xlfn.XLOOKUP($D48,Insumos!$B$1:$B$996,Insumos!$D$1:$D$996),"")} | H48: 382.10489 | I48: 0 | J48: 0
A49: 11 | B49: Insumo | C49: Armazenamento de blocos* | D49: MADEIRA PINUS/SIMILAR - TABUA PINUS 200X20MM NBR 11700 | E49: {=_xlfn.XLOOKUP(D49,Insumos!B:B,Insumos!C:$C)} -> M2 | F49: 0.591 | G49: {=IF(B49="insumo",_xlfn.XLOOKUP($D49,Insumos!$B$1:$B$996,Insumos!$D$1:$D$996),"")} -> 46.5 | H49: 27.4815 | I49: 0 | J49: 0
A50: 10 | B50: Insumo | C50: Armazenamento de blocos* | D50: COMPENSADO MADEIRA TIPO RESINADO COLA FENOLICA 2440X1220X10MM | E50: {=_xlfn.XLOOKUP(D50,Insumos!B:B,Insumos!C:$C)} -> UN | F50: 0.404 | G50: {=IF(B50="insumo",_xlfn.XLOOKUP($D50,Insumos!$B$1:$B$996,Insumos!$D$1:$D$996),"")} -> 58.46 | H50: 23.61784 | I50: 0 | J50: 0
A51: 25 | B51: Insumo | C51: Armazenamento de blocos* | D51: MADEIRA PINUS/SIMILAR - PONTALETE 75X75MM NBR 11700/15696 | E51: {=_xlfn.XLOOKUP(D51,Insumos!B:B,Insumos!C:$C)} -> M | F51: 4.39 | G51: {=IF(B51="insumo",_xlfn.XLOOKUP($D51,Insumos!$B$1:$B$996,Insumos!$D$1:$D$996),"")} -> 7 | H51: 30.73 | I51: 0 | J51: 0
A52: 11 | B52: Insumo | C52: Armazenamento de blocos* | D52: MADEIRA PINUS/SIMILAR - SARRAFO PINUS 50X20MM NBR 11700/15696 | E52: {=_xlfn.XLOOKUP(D52,Insumos!B:B,Insumos!C:$C)} -> M2 | F52: 0.15 | G52: {=IF(B52="insumo",_xlfn.XLOOKUP($D52,Insumos!$B$1:$B$996,Insumos!$D$1:$D$996),"")} -> 46.5 | H52: 6.975 | I52: 0 | J52: 0
A53: 10 | B53: Insumo | C53: Armazenamento de blocos* | D53: MADEIRA PINUS/SIMILAR - SARRAFO PINUS 50X10MM NBR 11700 | E53: {=_xlfn.XLOOKUP(D53,Insumos!B:B,Insumos!C:$C)} -> M | F53: 1 | G53: {=IF(B53="insumo",_xlfn.XLOOKUP($D53,Insumos!$B$1:$B$996,Insumos!$D$1:$D$996),"")} -> 7.39 | H53: 7.39 | I53: 0 | J53: 0
A54: 40 | B54: Insumo | C54: Armazenamento de blocos* | D54: PREGO DE ACO POLIDO COM CABECA 17 X 21 (2 X 11) | E54: {=_xlfn.XLOOKUP(D54,Insumos!B:B,Insumos!C:$C)} -> KG | F54: 1 | G54: {=IF(B54="insumo",_xlfn.XLOOKUP($D54,Insumos!$B$1:$B$996,Insumos!$D$1:$D$996),"")} -> 18.13 | H54: 18.13 | I54: 0 | J54: 0
A55: 10 | B55: Insumo | C55: Armazenamento de blocos* | D55: EXTINTOR INCENDIO PO QUIMICO 06KG CLASSE ABC (COMPLETO) NBR 15808 | E55: {=_xlfn.XLOOKUP(D55,Insumos!B:B,Insumos!C:$C)} -> UN | F55: 0.015 | G55: {=IF(B55="insumo",_xlfn.XLOOKUP($D55,Insumos!$B$1:$B$996,Insumos!$D$1:$D$996),"")} -> 185.37 | H55: 2.78055 | I55: 0 | J55: 0
A56: 10 | B56: Insumo | C56: Armazenamento de blocos* | D56: MATERIAL PARA INSTALAÇÃO ELÉTRICA | E56: {=_xlfn.XLOOKUP(D56,Insumos!B:B,Insumos!C:$C)} -> VB | F56: 1 | G56: {=IF(B56="insumo",_xlfn.XLOOKUP($D56,Insumos!$B$1:$B$996,Insumos!$D$1:$D$996),"")} -> 215 | H56: 215 | I56: 0 | J56: 0
A57: 10 | B57: Insumo | C57: Armazenamento de blocos* | D57: SERVICO INSTALAÇÃO BARRACAO ALMOXARIFADO | E57: {=_xlfn.XLOOKUP(D57,Insumos!B:B,Insumos!C:$C)} -> M2 | F57: 1 | G57: {=IF(B57="insumo",_xlfn.XLOOKUP($D57,Insumos!$B$1:$B$996,Insumos!$D$1:$D$996),"")} -> 50 | H57: 50 | I57: 0 | J57: 0
A58: 1 | B58: Serviço | C58: Armazenamento de contramarcos* | D58: Armazenamento de contramarcos* | E58: M2 | G58: {=IF(B58="insumo",_xlfn.XLOOKUP($D58,Insumos!$B$1:$B$996,Insumos!$D$1:$D$996),"")} | H58: 382.10489 | I58: 0 | J58: 0
A59: 11 | B59: Insumo | C59: Armazenamento de contramarcos* | D59: MADEIRA PINUS/SIMILAR - TABUA PINUS 200X20MM NBR 11700 | E59: {=_xlfn.XLOOKUP(D59,Insumos!B:B,Insumos!C:$C)} -> M2 | F59: 0.591 | G59: {=IF(B59="insumo",_xlfn.XLOOKUP($D59,Insumos!$B$1:$B$996,Insumos!$D$1:$D$996),"")} -> 46.5 | H59: 27.4815 | I59: 0 | J59: 0
A60: 10 | B60: Insumo | C60: Armazenamento de contramarcos* | D60: COMPENSADO MADEIRA TIPO RESINADO COLA FENOLICA 2440X1220X10MM | E60: {=_xlfn.XLOOKUP(D60,Insumos!B:B,Insumos!C:$C)} -> UN | F60: 0.404 | G60: {=IF(B60="insumo",_xlfn.XLOOKUP($D60,Insumos!$B$1:$B$996,Insumos!$D$1:$D$996),"")} -> 58.46 | H60: 23.61784 | I60: 0 | J60: 0
A61: 25 | B61: Insumo | C61: Armazenamento de contramarcos* | D61: MADEIRA PINUS/SIMILAR - PONTALETE 75X75MM NBR 11700/15696 | E61: {=_xlfn.XLOOKUP(D61,Insumos!B:B,Insumos!C:$C)} -> M | F61: 4.39 | G61: {=IF(B61="insumo",_xlfn.XLOOKUP($D61,Insumos!$B$1:$B$996,Insumos!$D$1:$D$996),"")} -> 7 | H61: 30.73 | I61: 0 | J61: 0
A62: 11 | B62: Insumo | C62: Armazenamento de contramarcos* | D62: MADEIRA PINUS/SIMILAR - SARRAFO PINUS 50X20MM NBR 11700/15696 | E62: {=_xlfn.XLOOKUP(D62,Insumos!B:B,Insumos!C:$C)} -> M2 | F62: 0.15 | G62: {=IF(B62="insumo",_xlfn.XLOOKUP($D62,Insumos!$B$1:$B$996,Insumos!$D$1:$D$996),"")} -> 46.5 | H62: 6.975 | I62: 0 | J62: 0
A63: 10 | B63: Insumo | C63: Armazenamento de contramarcos* | D63: MADEIRA PINUS/SIMILAR - SARRAFO PINUS 50X10MM NBR 11700 | E63: {=_xlfn.XLOOKUP(D63,Insumos!B:B,Insumos!C:$C)} -> M | F63: 1 | G63: {=IF(B63="insumo",_xlfn.XLOOKUP($D63,Insumos!$B$1:$B$996,Insumos!$D$1:$D$996),"")} -> 7.39 | H63: 7.39 | I63: 0 | J63: 0
A64: 40 | B64: Insumo | C64: Armazenamento de contramarcos* | D64: PREGO DE ACO POLIDO COM CABECA 17 X 21 (2 X 11) | E64: {=_xlfn.XLOOKUP(D64,Insumos!B:B,Insumos!C:$C)} -> KG | F64: 1 | G64: {=IF(B64="insumo",_xlfn.XLOOKUP($D64,Insumos!$B$1:$B$996,Insumos!$D$1:$D$996),"")} -> 18.13 | H64: 18.13 | I64: 0 | J64: 0
A65: 10 | B65: Insumo | C65: Armazenamento de contramarcos* | D65: EXTINTOR INCENDIO PO QUIMICO 06KG CLASSE ABC (COMPLETO) NBR 15808 | E65: {=_xlfn.XLOOKUP(D65,Insumos!B:B,Insumos!C:$C)} -> UN | F65: 0.015 | G65: {=IF(B65="insumo",_xlfn.XLOOKUP($D65,Insumos!$B$1:$B$996,Insumos!$D$1:$D$996),"")} -> 185.37 | H65: 2.78055 | I65: 0 | J65: 0
A66: 10 | B66: Insumo | C66: Armazenamento de contramarcos* | D66: MATERIAL PARA INSTALAÇÃO ELÉTRICA | E66: {=_xlfn.XLOOKUP(D66,Insumos!B:B,Insumos!C:$C)} -> VB | F66: 1 | G66: {=IF(B66="insumo",_xlfn.XLOOKUP($D66,Insumos!$B$1:$B$996,Insumos!$D$1:$D$996),"")} -> 215 | H66: 215 | I66: 0 | J66: 0
A67: 10 | B67: Insumo | C67: Armazenamento de contramarcos* | D67: SERVICO INSTALAÇÃO BARRACAO ALMOXARIFADO | E67: {=_xlfn.XLOOKUP(D67,Insumos!B:B,Insumos!C:$C)} -> M2 | F67: 1 | G67: {=IF(B67="insumo",_xlfn.XLOOKUP($D67,Insumos!$B$1:$B$996,Insumos!$D$1:$D$996),"")} -> 50 | H67: 50 | I67: 0 | J67: 0
A68: 1 | B68: Serviço | C68: Armazenamento de portas e rodapés* | D68: Armazenamento de portas e rodapés* | E68: M2 | G68: {=IF(B68="insumo",_xlfn.XLOOKUP($D68,Insumos!$B$1:$B$996,Insumos!$D$1:$D$996),"")} | H68: 382.10489 | I68: 0 | J68: 0
A69: 11 | B69: Insumo | C69: Armazenamento de portas e rodapés* | D69: MADEIRA PINUS/SIMILAR - TABUA PINUS 200X20MM NBR 11700 | E69: {=_xlfn.XLOOKUP(D69,Insumos!B:B,Insumos!C:$C)} -> M2 | F69: 0.591 | G69: {=IF(B69="insumo",_xlfn.XLOOKUP($D69,Insumos!$B$1:$B$996,Insumos!$D$1:$D$996),"")} -> 46.5 | H69: 27.4815 | I69: 0 | J69: 0
A70: 10 | B70: Insumo | C70: Armazenamento de portas e rodapés* | D70: COMPENSADO MADEIRA TIPO RESINADO COLA FENOLICA 2440X1220X10MM | E70: {=_xlfn.XLOOKUP(D70,Insumos!B:B,Insumos!C:$C)} -> UN | F70: 0.404 | G70: {=IF(B70="insumo",_xlfn.XLOOKUP($D70,Insumos!$B$1:$B$996,Insumos!$D$1:$D$996),"")} -> 58.46 | H70: 23.61784 | I70: 0 | J70: 0
A71: 25 | B71: Insumo | C71: Armazenamento de portas e rodapés* | D71: MADEIRA PINUS/SIMILAR - PONTALETE 75X75MM NBR 11700/15696 | E71: {=_xlfn.XLOOKUP(D71,Insumos!B:B,Insumos!C:$C)} -> M | F71: 4.39 | G71: {=IF(B71="insumo",_xlfn.XLOOKUP($D71,Insumos!$B$1:$B$996,Insumos!$D$1:$D$996),"")} -> 7 | H71: 30.73 | I71: 0 | J71: 0
A72: 11 | B72: Insumo | C72: Armazenamento de portas e rodapés* | D72: MADEIRA PINUS/SIMILAR - SARRAFO PINUS 50X20MM NBR 11700/15696 | E72: {=_xlfn.XLOOKUP(D72,Insumos!B:B,Insumos!C:$C)} -> M2 | F72: 0.15 | G72: {=IF(B72="insumo",_xlfn.XLOOKUP($D72,Insumos!$B$1:$B$996,Insumos!$D$1:$D$996),"")} -> 46.5 | H72: 6.975 | I72: 0 | J72: 0
A73: 10 | B73: Insumo | C73: Armazenamento de portas e rodapés* | D73: MADEIRA PINUS/SIMILAR - SARRAFO PINUS 50X10MM NBR 11700 | E73: {=_xlfn.XLOOKUP(D73,Insumos!B:B,Insumos!C:$C)} -> M | F73: 1 | G73: {=IF(B73="insumo",_xlfn.XLOOKUP($D73,Insumos!$B$1:$B$996,Insumos!$D$1:$D$996),"")} -> 7.39 | H73: 7.39 | I73: 0 | J73: 0
A74: 40 | B74: Insumo | C74: Armazenamento de portas e rodapés* | D74: PREGO DE ACO POLIDO COM CABECA 17 X 21 (2 X 11) | E74: {=_xlfn.XLOOKUP(D74,Insumos!B:B,Insumos!C:$C)} -> KG | F74: 1 | G74: {=IF(B74="insumo",_xlfn.XLOOKUP($D74,Insumos!$B$1:$B$996,Insumos!$D$1:$D$996),"")} -> 18.13 | H74: 18.13 | I74: 0 | J74: 0
A75: 10 | B75: Insumo | C75: Armazenamento de portas e rodapés* | D75: EXTINTOR INCENDIO PO QUIMICO 06KG CLASSE ABC (COMPLETO) NBR 15808 | E75: {=_xlfn.XLOOKUP(D75,Insumos!B:B,Insumos!C:$C)} -> UN | F75: 0.015 | G75: {=IF(B75="insumo",_xlfn.XLOOKUP($D75,Insumos!$B$1:$B$996,Insumos!$D$1:$D$996),"")} -> 185.37 | H75: 2.78055 | I75: 0 | J75: 0
A76: 10 | B76: Insumo | C76: Armazenamento de portas e rodapés* | D76: MATERIAL PARA INSTALAÇÃO ELÉTRICA | E76: {=_xlfn.XLOOKUP(D76,Insumos!B:B,Insumos!C:$C)} -> VB | F76: 1 | G76: {=IF(B76="insumo",_xlfn.XLOOKUP($D76,Insumos!$B$1:$B$996,Insumos!$D$1:$D$996),"")} -> 215 | H76: 215 | I76: 0 | J76: 0
A77: 10 | B77: Insumo | C77: Armazenamento de portas e rodapés* | D77: SERVICO INSTALAÇÃO BARRACAO ALMOXARIFADO | E77: {=_xlfn.XLOOKUP(D77,Insumos!B:B,Insumos!C:$C)} -> M2 | F77: 1 | G77: {=IF(B77="insumo",_xlfn.XLOOKUP($D77,Insumos!$B$1:$B$996,Insumos!$D$1:$D$996),"")} -> 50 | H77: 50 | I77: 0 | J77: 0
A78: 1 | B78: Serviço | C78: Armazenamento de esquadrias* | D78: Armazenamento de esquadrias* | E78: M2 | G78: {=IF(B78="insumo",_xlfn.XLOOKUP($D78,Insumos!$B$1:$B$996,Insumos!$D$1:$D$996),"")} | H78: 382.10489 | I78: 0 | J78: 0
A79: 11 | B79: Insumo | C79: Armazenamento de esquadrias* | D79: MADEIRA PINUS/SIMILAR - TABUA PINUS 200X20MM NBR 11700 | E79: {=_xlfn.XLOOKUP(D79,Insumos!B:B,Insumos!C:$C)} -> M2 | F79: 0.591 | G79: {=IF(B79="insumo",_xlfn.XLOOKUP($D79,Insumos!$B$1:$B$996,Insumos!$D$1:$D$996),"")} -> 46.5 | H79: 27.4815 | I79: 0 | J79: 0
A80: 10 | B80: Insumo | C80: Armazenamento de esquadrias* | D80: COMPENSADO MADEIRA TIPO RESINADO COLA FENOLICA 2440X1220X10MM | E80: {=_xlfn.XLOOKUP(D80,Insumos!B:B,Insumos!C:$C)} -> UN | F80: 0.404 | G80: {=IF(B80="insumo",_xlfn.XLOOKUP($D80,Insumos!$B$1:$B$996,Insumos!$D$1:$D$996),"")} -> 58.46 | H80: 23.61784 | I80: 0 | J80: 0
A81: 25 | B81: Insumo | C81: Armazenamento de esquadrias* | D81: MADEIRA PINUS/SIMILAR - PONTALETE 75X75MM NBR 11700/15696 | E81: {=_xlfn.XLOOKUP(D81,Insumos!B:B,Insumos!C:$C)} -> M | F81: 4.39 | G81: {=IF(B81="insumo",_xlfn.XLOOKUP($D81,Insumos!$B$1:$B$996,Insumos!$D$1:$D$996),"")} -> 7 | H81: 30.73 | I81: 0 | J81: 0
A82: 11 | B82: Insumo | C82: Armazenamento de esquadrias* | D82: MADEIRA PINUS/SIMILAR - SARRAFO PINUS 50X20MM NBR 11700/15696 | E82: {=_xlfn.XLOOKUP(D82,Insumos!B:B,Insumos!C:$C)} -> M2 | F82: 0.15 | G82: {=IF(B82="insumo",_xlfn.XLOOKUP($D82,Insumos!$B$1:$B$996,Insumos!$D$1:$D$996),"")} -> 46.5 | H82: 6.975 | I82: 0 | J82: 0
A83: 10 | B83: Insumo | C83: Armazenamento de esquadrias* | D83: MADEIRA PINUS/SIMILAR - SARRAFO PINUS 50X10MM NBR 11700 | E83: {=_xlfn.XLOOKUP(D83,Insumos!B:B,Insumos!C:$C)} -> M | F83: 1 | G83: {=IF(B83="insumo",_xlfn.XLOOKUP($D83,Insumos!$B$1:$B$996,Insumos!$D$1:$D$996),"")} -> 7.39 | H83: 7.39 | I83: 0 | J83: 0
A84: 40 | B84: Insumo | C84: Armazenamento de esquadrias* | D84: PREGO DE ACO POLIDO COM CABECA 17 X 21 (2 X 11) | E84: {=_xlfn.XLOOKUP(D84,Insumos!B:B,Insumos!C:$C)} -> KG | F84: 1 | G84: {=IF(B84="insumo",_xlfn.XLOOKUP($D84,Insumos!$B$1:$B$996,Insumos!$D$1:$D$996),"")} -> 18.13 | H84: 18.13 | I84: 0 | J84: 0
A85: 10 | B85: Insumo | C85: Armazenamento de esquadrias* | D85: EXTINTOR INCENDIO PO QUIMICO 06KG CLASSE ABC (COMPLETO) NBR 15808 | E85: {=_xlfn.XLOOKUP(D85,Insumos!B:B,Insumos!C:$C)} -> UN | F85: 0.015 | G85: {=IF(B85="insumo",_xlfn.XLOOKUP($D85,Insumos!$B$1:$B$996,Insumos!$D$1:$D$996),"")} -> 185.37 | H85: 2.78055 | I85: 0 | J85: 0
A86: 10 | B86: Insumo | C86: Armazenamento de esquadrias* | D86: MATERIAL PARA INSTALAÇÃO ELÉTRICA | E86: {=_xlfn.XLOOKUP(D86,Insumos!B:B,Insumos!C:$C)} -> VB | F86: 1 | G86: {=IF(B86="insumo",_xlfn.XLOOKUP($D86,Insumos!$B$1:$B$996,Insumos!$D$1:$D$996),"")} -> 215 | H86: 215 | I86: 0 | J86: 0
A87: 10 | B87: Insumo | C87: Armazenamento de esquadrias* | D87: SERVICO INSTALAÇÃO BARRACAO ALMOXARIFADO | E87: {=_xlfn.XLOOKUP(D87,Insumos!B:B,Insumos!C:$C)} -> M2 | F87: 1 | G87: {=IF(B87="insumo",_xlfn.XLOOKUP($D87,Insumos!$B$1:$B$996,Insumos!$D$1:$D$996),"")} -> 50 | H87: 50 | I87: 0 | J87: 0
A88: 1 | B88: Serviço | C88: Armazenamento de instalações complementares* | D88: Armazenamento de instalações complementares* | E88: M2 | G88: {=IF(B88="insumo",_xlfn.XLOOKUP($D88,Insumos!$B$1:$B$996,Insumos!$D$1:$D$996),"")} | H88: 382.10489 | I88: 0 | J88: 0
A89: 11 | B89: Insumo | C89: Armazenamento de instalações complementares* | D89: MADEIRA PINUS/SIMILAR - TABUA PINUS 200X20MM NBR 11700 | E89: {=_xlfn.XLOOKUP(D89,Insumos!B:B,Insumos!C:$C)} -> M2 | F89: 0.591 | G89: {=IF(B89="insumo",_xlfn.XLOOKUP($D89,Insumos!$B$1:$B$996,Insumos!$D$1:$D$996),"")} -> 46.5 | H89: 27.4815 | I89: 0 | J89: 0
A90: 10 | B90: Insumo | C90: Armazenamento de instalações complementares* | D90: COMPENSADO MADEIRA TIPO RESINADO COLA FENOLICA 2440X1220X10MM | E90: {=_xlfn.XLOOKUP(D90,Insumos!B:B,Insumos!C:$C)} -> UN | F90: 0.404 | G90: {=IF(B90="insumo",_xlfn.XLOOKUP($D90,Insumos!$B$1:$B$996,Insumos!$D$1:$D$996),"")} -> 58.46 | H90: 23.61784 | I90: 0 | J90: 0
A91: 25 | B91: Insumo | C91: Armazenamento de instalações complementares* | D91: MADEIRA PINUS/SIMILAR - PONTALETE 75X75MM NBR 11700/15696 | E91: {=_xlfn.XLOOKUP(D91,Insumos!B:B,Insumos!C:$C)} -> M | F91: 4.39 | G91: {=IF(B91="insumo",_xlfn.XLOOKUP($D91,Insumos!$B$1:$B$996,Insumos!$D$1:$D$996),"")} -> 7 | H91: 30.73 | I91: 0 | J91: 0
A92: 11 | B92: Insumo | C92: Armazenamento de instalações complementares* | D92: MADEIRA PINUS/SIMILAR - SARRAFO PINUS 50X20MM NBR 11700/15696 | E92: {=_xlfn.XLOOKUP(D92,Insumos!B:B,Insumos!C:$C)} -> M2 | F92: 0.15 | G92: {=IF(B92="insumo",_xlfn.XLOOKUP($D92,Insumos!$B$1:$B$996,Insumos!$D$1:$D$996),"")} -> 46.5 | H92: 6.975 | I92: 0 | J92: 0
A93: 10 | B93: Insumo | C93: Armazenamento de instalações complementares* | D93: MADEIRA PINUS/SIMILAR - SARRAFO PINUS 50X10MM NBR 11700 | E93: {=_xlfn.XLOOKUP(D93,Insumos!B:B,Insumos!C:$C)} -> M | F93: 1 | G93: {=IF(B93="insumo",_xlfn.XLOOKUP($D93,Insumos!$B$1:$B$996,Insumos!$D$1:$D$996),"")} -> 7.39 | H93: 7.39 | I93: 0 | J93: 0
A94: 40 | B94: Insumo | C94: Armazenamento de instalações complementares* | D94: PREGO DE ACO POLIDO COM CABECA 17 X 21 (2 X 11) | E94: {=_xlfn.XLOOKUP(D94,Insumos!B:B,Insumos!C:$C)} -> KG | F94: 1 | G94: {=IF(B94="insumo",_xlfn.XLOOKUP($D94,Insumos!$B$1:$B$996,Insumos!$D$1:$D$996),"")} -> 18.13 | H94: 18.13 | I94: 0 | J94: 0
A95: 10 | B95: Insumo | C95: Armazenamento de instalações complementares* | D95: EXTINTOR INCENDIO PO QUIMICO 06KG CLASSE ABC (COMPLETO) NBR 15808 | E95: {=_xlfn.XLOOKUP(D95,Insumos!B:B,Insumos!C:$C)} -> UN | F95: 0.015 | G95: {=IF(B95="insumo",_xlfn.XLOOKUP($D95,Insumos!$B$1:$B$996,Insumos!$D$1:$D$996),"")} -> 185.37 | H95: 2.78055 | I95: 0 | J95: 0
A96: 10 | B96: Insumo | C96: Armazenamento de instalações complementares* | D96: MATERIAL PARA INSTALAÇÃO ELÉTRICA | E96: {=_xlfn.XLOOKUP(D96,Insumos!B:B,Insumos!C:$C)} -> VB | F96: 1 | G96: {=IF(B96="insumo",_xlfn.XLOOKUP($D96,Insumos!$B$1:$B$996,Insumos!$D$1:$D$996),"")} -> 215 | H96: 215 | I96: 0 | J96: 0
A97: 10 | B97: Insumo | C97: Armazenamento de instalações complementares* | D97: SERVICO INSTALAÇÃO BARRACAO ALMOXARIFADO | E97: {=_xlfn.XLOOKUP(D97,Insumos!B:B,Insumos!C:$C)} -> M2 | F97: 1 | G97: {=IF(B97="insumo",_xlfn.XLOOKUP($D97,Insumos!$B$1:$B$996,Insumos!$D$1:$D$996),"")} -> 50 | H97: 50 | I97: 0 | J97: 0
A98: 1 | B98: Serviço | C98: Armazenamento para estoque geral* | D98: Armazenamento para estoque geral* | E98: M2 | G98: {=IF(B98="insumo",_xlfn.XLOOKUP($D98,Insumos!$B$1:$B$996,Insumos!$D$1:$D$996),"")} | H98: 382.10489 | I98: 0 | J98: 0
A99: 11 | B99: Insumo | C99: Armazenamento para estoque geral* | D99: MADEIRA PINUS/SIMILAR - TABUA PINUS 200X20MM NBR 11700 | E99: {=_xlfn.XLOOKUP(D99,Insumos!B:B,Insumos!C:$C)} -> M2 | F99: 0.591 | G99: {=IF(B99="insumo",_xlfn.XLOOKUP($D99,Insumos!$B$1:$B$996,Insumos!$D$1:$D$996),"")} -> 46.5 | H99: 27.4815 | I99: 0 | J99: 0
A100: 10 | B100: Insumo | C100: Armazenamento para estoque geral* | D100: COMPENSADO MADEIRA TIPO RESINADO COLA FENOLICA 2440X1220X10MM | E100: {=_xlfn.XLOOKUP(D100,Insumos!B:B,Insumos!C:$C)} -> UN | F100: 0.404 | G100: {=IF(B100="insumo",_xlfn.XLOOKUP($D100,Insumos!$B$1:$B$996,Insumos!$D$1:$D$996),"")} -> 58.46 | H100: 23.61784 | I100: 0 | J100: 0
...

Sheet Insumos
A1: Repetição | B1: Descrição | C1: Und | D1: 1 | E1: Custo Unitário | F1: Grupo insumo | G1: Sub Grupo | H1: Observações | I1: Grupo Sienge
A2: =COUNTIFS($B$2:$B$996,B2) -> 1 | B2: Arame Galvanizado | C2: KG | D2: =E2*$D$1 -> 13.69 | E2: 13.69 | F2: Aço | G2: Arame | I2: Armadura
A3: =COUNTIFS($B$2:$B$996,B3) -> 1 | B3: Arame Recozido BWG 18 | C3: KG | D3: =E3*$D$1 -> 13.73 | E3: 13.73 | F3: Aço | G3: Arame | H3: Custo Incorrido | I3: Armadura
A4: =COUNTIFS($B$2:$B$996,B4) -> 1 | B4: Barras de transferencia lisa 12,5mm 50 cm | C4: pc | D4: =E4*$D$1 -> 3.82 | E4: 3.82 | F4: Aço | G4: Barra de Aço CA50 / CA60 | I4: Armadura
A5: =COUNTIFS($B$2:$B$996,B5) -> 1 | B5: Monocordoalha engraxada CP - 190 RB (12,7mm) | C5: KG | D5: =E5*$D$1 -> 15.5 | E5: 15.5 | F5: Aço | G5: Barra de Aço CA50 / CA60 | I5: Armadura
A6: =COUNTIFS($B$2:$B$996,B6) -> 1 | B6: Armação aço Média para estaca (Corte e Dobra em Obra) | C6: KG | D6: =E6*$D$1 -> 7.6873385 | E6: 7.6873385 | F6: Aço | G6: Barra de Aço CA50 / CA60 | I6: Armadura
A7: =COUNTIFS($B$2:$B$996,B7) -> 1 | B7: Armação aço Média para estaca (Corte e Dobra em Indústria) | C7: KG | D7: =E7*$D$1 -> 8.2873385 | E7: 8.2873385 | F7: Aço | G7: Barra de Aço CA50 / CA60 | I7: Armadura
A8: =COUNTIFS($B$2:$B$996,B8) -> 1 | B8: CORTE E DOBRA ARMADO ESTACA Ø50CM 5F 16,0 4MTS ESP75 PS20 | C8: KG | D8: =E8*$D$1 -> 302.922 | E8: 302.922 | F8: Aço | G8: Barra de Aço CA50 / CA60 | I8: Armadura
A9: =COUNTIFS($B$2:$B$996,B9) -> 1 | B9: CORTE E DOBRA ARMADO ESTACA Ø60CM 5F 20,0 4MTS ESP75 PS20 | C9: KG | D9: =E9*$D$1 -> 466.337 | E9: 466.337 | F9: Aço | G9: Barra de Aço CA50 / CA60 | I9: Armadura
A10: =COUNTIFS($B$2:$B$996,B10) -> 1 | B10: CORTE E DOBRA ARMADO ESTACA Ø60CM 7F 20,0 6MTS ESP75 PS20 | C10: KG | D10: =E10*$D$1 -> 937.639 | E10: 937.639 | F10: Aço | G10: Barra de Aço CA50 / CA60 | I10: Armadura
A11: =COUNTIFS($B$2:$B$996,B11) -> 1 | B11: CORTE E DOBRA ARMADO ESTACA Ø60CM 9F 20,0 8MTS ESP75 PS20 | C11: KG | D11: =E11*$D$1 -> 1609.666 | E11: 1609.666 | F11: Aço | G11: Barra de Aço CA50 / CA60 | I11: Armadura
A12: =COUNTIFS($B$2:$B$996,B12) -> 1 | B12: Aço CA50 10,0 mm | C12: KG | D12: =E12*$D$1 -> 4.8006843 | E12: 4.8006843 | F12: Aço | G12: Barra de Aço CA50 / CA60 | H12: Scaini ferro e Aço | I12: Armadura
A13: =COUNTIFS($B$2:$B$996,B13) -> 1 | B13: Aço CA50 12,5 mm | C13: KG | D13: =E13*$D$1 -> 5.0530855 | E13: 5.0530855 | F13: Aço | G13: Barra de Aço CA50 / CA60 | H13: Scaini ferro e Aço | I13: Armadura
A14: =COUNTIFS($B$2:$B$996,B14) -> 1 | B14: Aço CA50 16,0mm | C14: KG | D14: =E14*$D$1 -> 4.9405604 | E14: 4.9405604 | F14: Aço | G14: Barra de Aço CA50 / CA60 | H14: Scaini ferro e Aço | I14: Armadura
A15: =COUNTIFS($B$2:$B$996,B15) -> 1 | B15: Aço CA50 20,0mm | C15: KG | D15: =E15*$D$1 -> 5.0344353 | E15: 5.0344353 | F15: Aço | G15: Barra de Aço CA50 / CA60 | H15: Scaini ferro e Aço | I15: Armadura
A16: =COUNTIFS($B$2:$B$996,B16) -> 1 | B16: Aço CA50 25,0mm | C16: KG | D16: =E16*$D$1 -> 5.1608662 | E16: 5.1608662 | F16: Aço | G16: Barra de Aço CA50 / CA60 | H16: Scaini ferro e Aço | I16: Armadura
A17: =COUNTIFS($B$2:$B$996,B17) -> 1 | B17: Aço CA50 6,3 mm | C17: KG | D17: =E17*$D$1 -> 5.2594749 | E17: 5.2594749 | F17: Aço | G17: Barra de Aço CA50 / CA60 | H17: Scaini ferro e Aço | I17: Armadura
A18: =COUNTIFS($B$2:$B$996,B18) -> 1 | B18: Aço CA50 8,0 mm | C18: KG | D18: =E18*$D$1 -> 4.924857 | E18: 4.924857 | F18: Aço | G18: Barra de Aço CA50 / CA60 | H18: Scaini ferro e Aço | I18: Armadura
A19: =COUNTIFS($B$2:$B$996,B19) -> 1 | B19: Aço CA60 5,0mm | C19: KG | D19: =E19*$D$1 -> 6.1446197 | E19: 6.1446197 | F19: Aço | G19: Barra de Aço CA50 / CA60 | H19: Scaini ferro e Aço | I19: Armadura
A20: =COUNTIFS($B$2:$B$996,B20) -> 1 | B20: Aço CA60 32,0mm | C20: KG | D20: =E20*$D$1 -> 6.22 | E20: 6.22 | F20: Aço | G20: Barra de Aço CA50 / CA60 | I20: Armadura
A21: =COUNTIFS($B$2:$B$876,B21) -> 1 | B21: Aço CA50 5,0 mm Corte e Dobra em Indústria | C21: UN | D21: =E21*$D$1 -> 8.67 | E21: 8.67 | F21: Aço | G21: Barra de Aço CA50 / CA60 | H21: Proposta Gessele | I21: Armadura
A22: =COUNTIFS($B$2:$B$876,B22) -> 1 | B22: Aço CA50 6,3 mm Corte e Dobra em Indústria | C22: UN | D22: =E22*$D$1 -> 8.67 | E22: 8.67 | F22: Aço | G22: Barra de Aço CA50 / CA60 | H22: Proposta Gessele | I22: Armadura
A23: =COUNTIFS($B$2:$B$876,B23) -> 1 | B23: Aço CA50 8,0 mm Corte e Dobra em Indústria | C23: UN | D23: =E23*$D$1 -> 8.67 | E23: 8.67 | F23: Aço | G23: Barra de Aço CA50 / CA60 | H23: Proposta Gessele | I23: Armadura
A24: =COUNTIFS($B$2:$B$876,B24) -> 1 | B24: Aço CA50 10,0 mm Corte e Dobra em Indústria | C24: UN | D24: =E24*$D$1 -> 8.67 | E24: 8.67 | F24: Aço | G24: Barra de Aço CA50 / CA60 | H24: Proposta Gessele | I24: Armadura
A25: =COUNTIFS($B$2:$B$876,B25) -> 1 | B25: Aço CA50 12,5 mm Corte e Dobra em Indústria | C25: UN | D25: =E25*$D$1 -> 8.19 | E25: 8.19 | F25: Aço | G25: Barra de Aço CA50 / CA60 | H25: Proposta Gessele | I25: Armadura
A26: =COUNTIFS($B$2:$B$876,B26) -> 1 | B26: Aço CA50 16,0 mm Corte e Dobra em Indústria | C26: UN | D26: =E26*$D$1 -> 8.19 | E26: 8.19 | F26: Aço | G26: Barra de Aço CA50 / CA60 | H26: Proposta Gessele | I26: Armadura
A27: =COUNTIFS($B$2:$B$876,B27) -> 1 | B27: Aço CA50 20,0 mm Corte e Dobra em Indústria | C27: UN | D27: =E27*$D$1 -> 8.19 | E27: 8.19 | F27: Aço | G27: Barra de Aço CA50 / CA60 | H27: Proposta Gessele | I27: Armadura
A28: =COUNTIFS($B$2:$B$876,B28) -> 1 | B28: Aço CA50 25,0mm Corte e Dobra em Indústria | C28: UN | D28: =E28*$D$1 -> 8.19 | E28: 8.19 | F28: Aço | G28: Barra de Aço CA50 / CA60 | H28: Proposta Gessele | I28: Armadura
A29: =COUNTIFS($B$2:$B$876,B29) -> 1 | B29: Aço CA50 32,0mm Corte e Dobra em Indústria | C29: UN | D29: =E29*$D$1 -> 8.7763609 | E29: =(E21*E20)/E19 -> 8.7763609 | F29: Aço | G29: Barra de Aço CA50 / CA60 | I29: Armadura
A30: =COUNTIFS($B$2:$B$996,B30) -> 1 | B30: Sistema e Instalação de Fachada Ventilada. Mecanização das peças, arremate das esquadrias e Fretes | C30: UN | D30: =E30*$D$1 -> 305 | E30: =305 -> 305 | F30: Aço | G30: Diversos | I30: Armadura
A31: =COUNTIFS($B$2:$B$996,B31) -> 1 | B31: ESPACADOR / DISTANCIADOR CIRCULAR COM ENTRADA LATERAL, EM PLASTICO, PARA VERGALHAO *4,2 A 12,5* MM, COBRIMENTO 40 MM | C31: M2 | D31: =E31*$D$1 -> 0.43 | E31: 0.43 | F31: Aço | G31: Diversos | I31: Armadura
A32: =COUNTIFS($B$2:$B$996,B32) -> 1 | B32: TELA ACO CARBONO CA60 M.150X150MM F.03,4MM 245X600CM Q61 (14,26KG/UN) | C32: KG | D32: =E32*$D$1 -> 6.1 | E32: 6.1 | F32: Aço | G32: Tela de Aço CA60 | I32: Armadura
A33: =COUNTIFS($B$2:$B$996,B33) -> 1 | B33: TELA ACO CARBONO CA60 M.150X150MM F.04,2MM 245X600CM Q92 (21,8KG/UN) | C33: KG | D33: =E33*$D$1 -> 4.88 | E33: 4.88 | F33: Aço | G33: Tela de Aço CA60 | I33: Armadura
A34: =COUNTIFS($B$2:$B$996,B34) -> 1 | B34: TELA ACO CARBONO CA60 M.100X100MM F.04,2MM 245X600CM Q113 (26,46KG/UN) | C34: KG | D34: =E34*$D$1 -> 8.537037 | E34: =225.89/26.46 -> 8.537037 | F34: Aço | G34: Tela de Aço CA60 | I34: Armadura
A35: =COUNTIFS($B$2:$B$996,B35) -> 1 | B35: TELA ACO CARBONO CA60 M.100X100MM F.04,2MM 245X600CM Q138 (32,34KG/UN) | C35: KG | D35: =E35*$D$1 -> 9.1447124 | E35: 9.1447124 | F35: Aço | G35: Tela de Aço CA60 | I35: Armadura
A36: =COUNTIFS($B$2:$B$996,B36) -> 1 | B36: TELA DE ACO SOLDADA GALVANIZADA/ZINCADA PARA ALVENARIA, FIO D = *1,20 A 1,70* MM, MALHA 15 X 15 MM, (C X L) *50 X 17,5* CM | C36: UN | D36: =E36*$D$1 -> 2.5 | E36: 2.5 | F36: Aço | G36: Tela de Aço Carbono | I36: Armadura
A37: =COUNTIFS($B$2:$B$996,B37) -> 1 | B37: Tela de arame galvanizada, hexagonal, fio 0,56 mm (24 bwg), malha 1/2", h = 1 m | C37: M2 | D37: =E37*$D$1 -> 14.27 | E37: 14.27 | F37: Aço | G37: Tela de Aço Carbono | I37: Armadura
A38: =COUNTIFS($B$2:$B$996,B38) -> 1 | B38: TIJOLO REFRATÁRIO 5 X 11,5 X 23 CM | C38: UN | D38: =E38*$D$1 -> 7 | E38: 7 | F38: Alvenaria | G38: Alvenaria Refratária | I38: Pintura
A39: =COUNTIFS($B$2:$B$996,B39) -> 1 | B39: TIJOLO REFRATÁRIO 2,5 X 11,5 X 23 CM | C39: UN | D39: =E39*$D$1 -> 5.95 | E39: 5.95 | F39: Alvenaria | G39: Alvenaria Refratária | I39: Pintura
A40: =COUNTIFS($B$2:$B$996,B40) -> 1 | B40: BLOCO CONCRETO ESTRUTURAL 03MPA 14X19X39CM NBR 6136 | C40: UN | D40: =E40*$D$1 -> 2.95 | E40: 2.95 | F40: Alvenaria | G40: Alvenaria Estrutural | I40: Elementos de Vedação (Cerâmica)
A41: =COUNTIFS($B$2:$B$996,B41) -> 1 | B41: BLOCO CONCRETO ESTRUTURAL 04MPA 14X19X04CM NBR 6136 | C41: UN | D41: =E41*$D$1 -> 4.1861538 | E41: 4.1861538 | F41: Alvenaria | G41: Alvenaria Estrutural | I41: Elementos de Vedação (Cerâmica)
A42: =COUNTIFS($B$2:$B$996,B42) -> 1 | B42: BLOCO CONCRETO ESTRUTURAL 04MPA 14X19X09CM NBR 6136 | C42: UN | D42: =E42*$D$1 -> 3.9889744 | E42: 3.9889744 | F42: Alvenaria | G42: Alvenaria Estrutural | I42: Elementos de Vedação (Cerâmica)
A43: =COUNTIFS($B$2:$B$996,B43) -> 1 | B43: BLOCO CONCRETO ESTRUTURAL 04MPA 14X19X14CM NBR 6136 | C43: UN | D43: =E43*$D$1 -> 1.376 | E43: 1.376 | F43: Alvenaria | G43: Alvenaria Estrutural | I43: Elementos de Vedação (Cerâmica)
A44: =COUNTIFS($B$2:$B$996,B44) -> 1 | B44: BLOCO CONCRETO ESTRUTURAL 04MPA 11,5X19X29CM NBR 6136 | C44: UN | D44: =E44*$D$1 -> 1.998 | E44: 1.998 | F44: Alvenaria | G44: Alvenaria Estrutural | I44: Elementos de Vedação (Cerâmica)
A45: =COUNTIFS($B$2:$B$996,B45) -> 1 | B45: BLOCO CONCRETO ESTRUTURAL 04MPA 14X19X29CM NBR 6136 | C45: UN | D45: =E45*$D$1 -> 1.998 | E45: 1.998 | F45: Alvenaria | G45: Alvenaria Estrutural | I45: Elementos de Vedação (Cerâmica)
A46: =COUNTIFS($B$2:$B$996,B46) -> 1 | B46: BLOCO CONCRETO ESTRUTURAL 04MPA 14X19X44CM NBR 6136 | C46: UN | D46: =E46*$D$1 -> 4.02 | E46: 4.02 | F46: Alvenaria | G46: Alvenaria Estrutural | I46: Elementos de Vedação (Cerâmica)
... A67: =COUNTIFS($B$2:$B$996,B67) -> 1 | B67: BLOCO CERÂMICO - 9X19X39cm | C67: UN | D67: =E67*$D$1 -> 0.99 | E67: 0.99 | F67: Alvenaria | G67: Alvenaria vedação | I67: Elementos de Vedação (Cerâmica)
A68: =COUNTIFS($B$2:$B$996,B68) -> 1 | B68: BLOCO CERÂMICO - 11,5X19X39cm | C68: UN | D68: =E68*$D$1 -> 1.15 | E68: =E66*11.5/14 -> 1.15 | F68: Alvenaria | G68: Alvenaria vedação | I68: Elementos de Vedação (Cerâmica)
A69: =COUNTIFS($B$2:$B$996,B69) -> 1 | B69: BLOCO CERÂMICO - 19X19X39cm | C69: UN | D69: =E69*$D$1 -> 1.9 | E69: =E66*19/14 -> 1.9 | F69: Alvenaria | G69: Alvenaria vedação | I69: Elementos de Vedação (Cerâmica)
A70: =COUNTIFS($B$2:$B$996,B70) -> 1 | B70: BLOCO CERÂMICO - 9X19X19cm | C70: UN | D70: =E70*$D$1 -> 0.99 | E70: 0.99 | F70: Alvenaria | G70: Alvenaria vedação | I70: Elementos de Vedação (Cerâmica)
A71: =COUNTIFS($B$2:$B$996,B71) -> 1 | B71: BLOCO CERÂMICO - 11,5X19X19cm | C71: UN | D71: =E71*$D$1 -> 1.24 | E71: 1.24 | F71: Alvenaria | G71: Alvenaria vedação | I71: Elementos de Vedação (Cerâmica)
A72: =COUNTIFS($B$2:$B$996,B72) -> 1 | B72: BLOCO CERÂMICO - 14X19X19cm | C72: UN | D72: =E72*$D$1 -> 2.6 | E72: 2.6 | F72: Alvenaria | G72: Alvenaria vedação | I72: Elementos de Vedação (Cerâmica)
A73: =COUNTIFS($B$2:$B$996,B73) -> 1 | B73: BLOCO CERÂMICO - 19X19X19cm | C73: UN | D73: =E73*$D$1 -> 1.59 | E73: 1.59 | F73: Alvenaria | G73: Alvenaria vedação | I73: Elementos de Vedação (Cerâmica)
A74: =COUNTIFS($B$2:$B$996,B74) -> 1 | B74: BLOCO DE VEDACAO CONCRETO 09X19X39 CM | C74: UN | D74: =E74*$D$1 -> 2.7 | E74: 2.7 | F74: Alvenaria | G74: Alvenaria vedação | I74: Elementos de Vedação (Cerâmica)
A75: =COUNTIFS($B$2:$B$996,B75) -> 1 | B75: BLOCO DE VEDACAO CONCRETO 11,5X19X39 CM | C75: UN | D75: =E75*$D$1 -> 3.45 | E75: =E74/9*11.5 -> 3.45 | F75: Alvenaria | G75: Alvenaria vedação | I75: Elementos de Vedação (Cerâmica)
A76: =COUNTIFS($B$2:$B$996,B76) -> 1 | B76: BLOCO DE VEDACAO CONCRETO 19X19X39 CM | C76: UN | D76: =E76*$D$1 -> 5.7 | E76: =E74/9*19 -> 5.7 | F76: Alvenaria | G76: Alvenaria vedação | I76: Elementos de Vedação (Cerâmica)
A77: =COUNTIFS($B$2:$B$996,B77) -> 1 | B77: ELEMENTO VAZADO CONCRETO QUADRADO | C77: UN | D77: =E77*$D$1 -> 15 | E77: 15 | F77: Alvenaria | G77: Alvenaria vedação | I77: Elementos de Vedação (Cerâmica)
A78: =COUNTIFS($B$2:$B$996,B78) -> 1 | B78: ELEMENTO VAZADO CERAMICO QUADRADO | C78: UN | D78: =E78*$D$1 -> 11.99 | E78: 11.99 | F78: Alvenaria | G78: Alvenaria vedação | I78: Elementos de Vedação (Cerâmica)
A79: =COUNTIFS($B$2:$B$996,B79) -> 1 | B79: BLOCO DE VEDACAO CERAMICO MACIÇO 5,5X11,5X24 CM | C79: UN | D79: =E79*$D$1 -> 1.05 | E79: 1.05 | F79: Alvenaria | G79: Alvenaria vedação | I79: Elementos de Vedação (Cerâmica)
A80: =COUNTIFS($B$2:$B$996,B80) -> 1 | B80: BLOCO DE VEDACAO CERAMICO 09X19X29 CM | C80: UN | D80: =E80*$D$1 -> 1.18 | E80: 1.18 | F80: Alvenaria | G80: Alvenaria vedação | I80: Elementos de Vedação (Cerâmica)
A81: =COUNTIFS($B$2:$B$996,B81) -> 1 | B81: BLOCO DE VEDACAO CERAMICO 11,5X19X29 CM | C81: UN | D81: =E81*$D$1 -> 1.43 | E81: 1.43 | F81: Alvenaria | G81: Alvenaria vedação | I81: Elementos de Vedação (Cerâmica)
A82: =COUNTIFS($B$2:$B$996,B82) -> 1 | B82: BLOCO DE VEDACAO CERAMICO 14X19X29 CM | C82: UN | D82: =E82*$D$1 -> 1.72 | E82: 1.72 | F82: Alvenaria | G82: Alvenaria vedação | I82: Elementos de Vedação (Cerâmica)
