Workbook
Name \0: #REF!
Name \a: #REF!
Name \m: #REF!
Name aa: #REF!
Name aa: #REF!
Name aaaa: '[1]M.O.'!#REF!
Name angelo: [2]Geral!#REF!
Name area: #REF!
Name area: #REF!
Name aux: #REF!
Name aux: #REF!
Name BDA: #REF!
Name BDA: #REF!
Name BDI: #REF!
Name ca: #REF!
Name Capa: #REF!
Name cronograma: #REF!
Name cronograma: #REF!
Name D: #REF!
Name direto: #REF!
Name DRE: #REF!
Name ea: #REF!
Name FFFFFFF: #REF!
Name FFFFFFF: #REF!
Name item_1: #REF!
Name item_1: #REF!
Name LS: '[1]M.O.'!#REF!
Name LS: '[1]M.O.'!#REF!
Name MENU: #REF!
Name MENU: #REF!
Name MENU1: #REF!
Name MENU1: #REF!
Name MENU2: #REF!
Name MENU2: #REF!
Name MENU3: #REF!
Name MENU4: #REF!
Name MENU5: #REF!
Name MENU6: #REF!
Name mo: #REF!
Name OAE: #REF!
Name ParamValues1: [3]ParamValues!$A$1:$A$39
Name PAV: #REF!
Name PAV: #REF!
Name pr: #REF!
Name pr: #REF!
Name PRE: #REF!
Name PRE: #REF!
Name Print_Area_MI: #REF!
Name qe: #REF!
Name qee: #REF!
Name reforsu: #REF!
Name ren: #REF!
Name REV: #REF!
Name sa: #REF!
Name SEG: #REF!
Name SIH: #REF!
Name SIV: #REF!
Name ss: #REF!
Name susref: #REF!
Name tania: #REF!

Sheet Marine
A1: ORÇAMENTO EXECUTIVO
A2: Obra | B2: MARINE
A3: Empresa | B3: AMALFI
A4: Revisão | B4: R00 | F4: AC | G4: 4498.66
A5: Data | B5: 45322 | F5: APE | G5: 479.88
A6: ORÇAMENTO EXECUTIVO MARINE - R00 | G6: OBSERVAÇÕES
A7: Código | B7: Descrição | C7: Un. | D7: Quantidade orçada | E7: Preço unitário | F7: Preço total | G7: Considerações | H7: Quantitativos
A8: 01 | B8: CUSTOS INDIRETOS | F8: =F9+F74+F144 -> 2346985.5 | G8: OS CUSTOS INDIRETOS FORAM LANÇADOS SEGUINDO FORMULÁRIO DE CUSTOS INDIRETOS PREENCHIDO EM 19/06/2023 PELO ENGENHEIRO VINÍCIUS
A9: 01.01 | B9: SERVIÇOS TECNICOS | F9: =F10+F55 -> 387573.05 | G9: =F8-[4]ORÇAMENTO_EXECUTIVO_COMENTADO!$G$8 -> 63318.936
A10: 01.01.001 | B10: ESTUDOS-PROJETOS-CONSULTORIAS | F10: =F11+F17+F42+F51 -> 304289.7
A11: 01.01.001.0001 | B11: Estudos | F11: =SUM(F12:F16) -> 40433.9
A12: 01.01.001.0001.00001 | B12: Levantamento Topográfico | C12: VB | D12: 1 | E12: 27500 | F12: =E12*D12 -> 27500 | G12: Contrato ALFAPLAN TOPOGRAFIA - Incluido medição do terreno. Locação do gabarito e locação dos pilares.
A13: 01.01.001.0001.00002 | B13: Sondagem de Percussão | C13: VB | D13: 1 | E13: 12933.9 | F13: =E13*D13 -> 12933.9 | G13: Contrato com SOLO SONDAGEM.
A14: 01.01.001.0001.00003 | B14: Estudo ambiental | C14: VB | D14: 0 | E14: 1500 | F14: =E14*D14 -> 0 | G14: EXCLUIR
A15: 01.01.001.0001.00004 | B15: Memorial Descritivo | C15: VB | D15: 0 | E15: 2138 | F15: =E15*D15 -> 0 | G15: EXCLUIR
A16: 01.01.001.0001.00005 | B16: Estudo Geológico | C16: VB | D16: 0 | E16: 3122 | F16: =E16*D16 -> 0 | G16: EXCLUIR
A17: 01.01.001.0002 | B17: Projetos | F17: =SUM(F18:F41) -> 166779.75
A18: 01.01.001.0002.00001 | B18: Legalização e incorporação | C18: VB | D18: 1 | E18: 15500 | F18: =E18*D18 -> 15500 | G18: Despachante Marcos contratado pela Amalfi
A19: 01.01.001.0002.00002 | B19: Projetos Arquitetura | C19: VB | D19: 1 | E19: 67500 | F19: =E19*D19 -> 67500 | G19: Estará junto com Projetos de ARQ, HID e PCI no contrato da M&N Arquitetura
A20: 01.01.001.0002.00003 | B20: Projeto De Interiores | C20: VB | D20: 1 | E20: 34500 | F20: =E20*D20 -> 34500
A21: 01.01.001.0002.00004 | B21: Projetos Fachadas | C21: VB | D21: 1 | E21: 6200 | F21: =E21*D21 -> 6200 | G21: Valor de acordo com contrato Aetos
A22: 01.01.001.0002.00005 | B22: Projetos Fundação | C22: VB | D22: 0 | E22: 5000 | F22: =E22*D22 -> 0 | G22: EXCLUIR
A23: 01.01.001.0002.00006 | B23: Projetos Estrutura | C23: VB | D23: 1 | E23: 29341.44 | F23: =E23*D23 -> 29341.44 | G23: Valor de acordo com contrato CFA.
A24: 01.01.001.0002.00007 | B24: Projetos Elétricos | C24: VB | D24: 1 | E24: 9000 | F24: =E24*D24 -> 9000 | G24: Valode acordo com contrato PROCAUTI
A25: 01.01.001.0002.00008 | B25: Projetos de terraplanagem | C25: VB | E25: 980 | F25: =E25*D25 -> 0 | G25: EXCLUIR
A26: 01.01.001.0002.00009 | B26: Projetos comunicação e dados | C26: VB | E26: 1000 | F26: =E26*D26 -> 0 | G26: EXCLUIR
A27: 01.01.001.0002.00010 | B27: Projetos Luminotecnico | C27: VB | E27: 1000 | F27: =E27*D27 -> 0 | G27: EXCLUIR
A28: 01.01.001.0002.00011 | B28: Projetos de telefonia | C28: VB | E28: 1000 | F28: =E28*D28 -> 0 | G28: EXCLUIR
A29: 01.01.001.0002.00012 | B29: Projetos Hidráulicos | C29: VB | E29: 20000 | F29: =E29*D29 -> 0 | G29: EXCLUIR
A30: 01.01.001.0002.00013 | B30: Projetos Incêndio | C30: VB | E30: 21000 | F30: =E30*D30 -> 0 | G30: EXCLUIR
A31: 01.01.001.0002.00014 | B31: Projetos Ar Condicionado | C31: VB | E31: 1000 | F31: =E31*D31 -> 0 | G31: EXCLUIR
A32: 01.01.001.0002.00015 | B32: Projetos Segurança | C32: VB | D32: 1 | E32: 4000 | F32: =E32*D32 -> 4000 | G32: Conforme contratos de PGR e PCMSO e laudos da SPS
A33: 01.01.001.0002.00016 | B33: Projeto Impermeabilização | C33: VB | E33: 5000 | F33: =E33*D33 -> 0 | G33: EXCLUIR
A34: 01.01.001.0002.00017 | B34: Projeto De Esquadrias | C34: VB | E34: 14280 | F34: =E34*D34 -> 0 | G34: EXCLUIR
A35: 01.01.001.0002.00018 | B35: Projetos Isolamento Acústico | C35: VB | E35: 7000 | F35: =E35*D35 -> 0 | G35: EXCLUIR
A36: 01.01.001.0002.00019 | B36: Projetos de sonorização | C36: VB | E36: 7000 | F36: =E36*D36 -> 0 | G36: EXCLUIR
A37: 01.01.001.0002.00020 | B37: Projetos Piscinas | C37: VB | E37: 1000 | F37: =E37*D37 -> 0 | G37: EXCLUIR
A38: 01.01.001.0002.00021 | B38: Projetos Comunicação Visual | C38: VB | E38: 1000 | F38: =E38*D38 -> 0 | G38: EXCLUIR
A39: 01.01.001.0002.00022 | B39: Projetos Paisagismo | C39: VB | E39: 1000 | F39: =E39*D39 -> 0 | G39: EXCLUIR
A40: 01.01.001.0002.00028 | B40: Projetos de Exaustão | C40: VB | E40: 2000 | F40: =E40*D40 -> 0 | G40: EXCLUIR
A41: 01.01.001.0002.00029 | B41: Projeto SPDA | C41: VB | D41: 1 | E41: 738.31 | F41: =E41*D41 -> 738.31 | G41: Item adicionado em revisão
A42: 01.01.001.0003 | B42: Consultorias | F42: =SUM(F43:F50) -> 73726.05
A43: 01.01.001.0003.00001 | B43: Consultoria de Esquadrias | C43: VB | E43: 2688.5 | F43: =E43*D43 -> 0 | G43: EXCLUIR
A44: 01.01.001.0003.00002 | B44: Consultoria/Compatibilização de Projetos | C44: VB | E44: 5900 | F44: =E44*D44 -> 0 | G44: EXCLUIR
A45: 01.01.001.0003.00003 | B45: Consultoria Controle de Qualidade | C45: VB | D45: 1 | E45: 28825 | F45: =E45*D45 -> 28825 | G45: Qualidade é feita por equipe interna. Laudos de qualidade: Acustico, estrutural, entorno, luminico e térmico (Base do Cielo)
A46: 01.01.001.0003.00004 | B46: Modelagem BIM arquitetonico | C46: VB | E46: 4795 | F46: =E46*D46 -> 0 | G46: EXCLUIR
A47: 01.01.001.0003.00005 | B47: Modelagem BIM complementares | C47: VB | E47: 10754 | F47: =E47*D47 -> 0 | G47: EXCLUIR
A48: 01.01.001.0003.00006 | B48: Consultoria de legalização | C48: VB | E48: 4570 | F48: =E48*D48 -> 0 | G48: EXCLUIR
A49: 01.01.001.0003.00008 | B49: Consultoria Diversas | C49: VB | E49: 20000 | F49: =E49*D49 -> 0 | G49: EXCLUIR
A50: 01.01.001.0003.00009 | B50: Orçamento e Planejamento | C50: VB | D50: 1 | E50: 44901.05 | F50: =E50*D50 -> 44901.05 | G50: Conforme contrato com a Cartesian + contrato do sfotware Prevision
A51: 01.01.001.0004 | B51: Ensaios | F51: =F52+F53+F54 -> 23350
A52: 01.01.001.0004.00001 | B52: Controle Tecnológico de Concreto | C52: UN | D52: 828 | E52: 22.94686 | F52: =E52*D52 -> 19000 | G52: Consideração contrato Labotec | H52: Consideração de 4 corpos de prova por caminhão betoneira (8m³) para 2.400,29m³ de concreto levantados em projeto
A53: 01.01.001.0004.00002 | B53: Ensaio de arrancamento | C53: VB | D53: 1 | E53: 2850 | F53: =E53*D53 -> 2850 | G53: Item adicionado em revisão
A54: 01.01.001.0004.00003 | B54: Laudos extras | C54: VB | D54: 1 | E54: 1500 | F54: =E54*D54 -> 1500 | G54: Item adicionado em revisão
A55: 01.01.002 | B55: CONSUMOS-TAXAS-DOCUMENTOS | F55: =F56+F70 -> 83283.35
A56: 01.01.002.0001 | B56: Licenciamentos, Taxas, Impostos, Aprovações e Seguros | F56: =SUM(F57:F69) -> 75033.35
A57: 01.01.002.0001.00001 | B57: Aprovação de Projetos prefeitura | C57: VB | D57: 1 | E57: 108.69 | F57: =E57*D57 -> 108.69 | G57: Boleto RRT arquitetura. Taxa de análise é junto com alvará
A58: 01.01.002.0001.00002 | B58: Aprovação Corpo de Bombeiros | C58: VB | D58: 1 | E58: 3688.92 | F58: =E58*D58 -> 3688.92 | G58: Conforme boleto do PCI no amplidrive
A59: 01.01.002.0001.00003 | B59: Projetos-Licença Ambiental | C59: VB | D59: 1 | E59: 1643.09 | F59: =E59*D59 -> 1643.09 | G59: Boleto LAP LAI 46224 e boleto da ART Carlão (responsável pelo ambiental) no amplidrive
A60: 01.01.002.0001.00004 | B60: Alvará Construção | C60: VB | D60: 1 | E60: 6581.03 | F60: =E60*D60 -> 6581.03 | G60: Valor boleto no amplidrive
A61: 01.01.002.0001.00005 | B61: Despesas com Cartório | C61: VB | D61: 1 | E61: 10000 | F61: =E61*D61 -> 10000
A62: 01.01.002.0001.00006 | B62: Aprovação de Projetos agua e esgoto | C62: VB | D62: 1 | E62: 2512.89 | F62: =E62*D62 -> 2512.89 | G62: custo de viabilidade + aprovação com base no boleto HIDRO 46224 do amplidrive
A63: 01.01.002.0001.00007 | B63: Taxa de Habite-se prefeitura | C63: VB | D63: 1 | E63: 3104.09 | F63: =E63*D63 -> 3104.09 | G63: Prefeitura com base no Cielo. Solicitado média a Juciane
A64: 01.01.002.0001.00014 | B64: Taxa de Habite-se bombeiros | C64: VB | D64: 1 | E64: 0 | F64: =E64*D64 -> 0 | G64: Item adicionado em revisão
A65: 01.01.002.0001.00008 | B65: Seguro da Obra | C65: VB | D65: 1 | E65: 13004.64 | F65: =E65*D65 -> 13004.64 | G65: Apólice do Marine no amplidrive
A66: 01.01.002.0001.00009 | B66: IPTU | C66: VB | D66: 1 | E66: 9000 | F66: =E66*D66 -> 9000 | G66: Com base no IPTU de 2023
A67: 01.01.002.0001.00010 | B67: Taxas ART | C67: VB | D67: 1 | E67: 1000 | F67: =E67*D67 -> 1000
A68: 01.01.002.0001.00012 | B68: INSS | C68: VB | D68: 1 | E68: 4890 | F68: =E68*D68 -> 4890
A69: 01.01.002.0001.00013 | B69: Incorporação | C69: VB | D69: 1 | E69: 19500 | F69: =E69*D69 -> 19500 | G69: Valores do contato da CVB Engenharia e MG Serviços Administrativos
A70: 01.01.002.0002 | B70: Documentos | F70: =SUM(F71:F73) -> 8250
A71: 01.01.002.0002.00005 | B71: Projetos-As Built | C71: VB | D71: 1 | E71: 6750 | F71: =E71*D71 -> 6750 | G71: Valor alterado em Revisão
A72: 01.01.002.0002.00006 | B72: Laudo Técnico de Vistoria de Entrega | C72: VB | E72: 3120 | F72: =E72*D72 -> 0 | G72: EXCLUIR
A73: 01.01.002.0002.00007 | B73: Manuais Técnicos de Condominio | C73: VB | D73: 1 | E73: 1500 | F73: =E73*D73 -> 1500
A74: 01.02 | B74: SERVIÇOS INICIAIS | F74: =F75+F97+F141 -> 1705182.3
A75: 01.02.001 | B75: SEGURANÇA-MEIO AMBIENTE-SAÚDE | F75: =F76+F79+F89+F92 -> 267669.46
A76: 01.02.001.0001 | B76: Segurança do trabalho | F76: =F77+F78 -> 60000
A77: 01.02.001.0001.00001 | B77: Técnico em Segurança | C77: MES | D77: 30 | E77: 1000 | F77: =E77*D77 -> 30000 | G77: Colaborador Interno, valor estimado
A78: 01.02.001.0001.00003 | B78: Serviço de segurança do trabalho terceirizados | C78: MES | D78: 30 | E78: 1000 | F78: =E78*D78 -> 30000
A79: 01.02.001.0002 | B79: Equipamentos de proteção | F79: =SUM(F80:F88) -> 155469.46
A80: 01.02.001.0002.00001 | B80: Equipamento de Segurança Pessoal | C80: VB | D80: 1 | E80: 3500 | F80: =E80*D80 -> 3500
A81: 01.02.001.0002.00002 | B81: Bandeja Salva Vidas-Fixa | C81: M | D81: 147.6 | E81: 483.675 | F81: =E81*D81 -> 71390.43 | H81: EPC''s'
A82: 01.02.001.0002.00003 | B82: Bandeja Salva Vidas-Móvel | C82: M | D82: 73.89 | E82: 169.3175 | F82: =E82*D82 -> 12510.87 | H82: EPC''s'
A83: 01.02.001.0002.00004 | B83: Guarda-corpo de vãos - fixado em forma de madeira - em trama de madeira com tela de polipropileno | C83: M | D83: 192.3 | E83: 18.6718 | F83: =E83*D83 -> 3590.5871 | H83: EPC''s'
A84: 01.02.001.0002.00006 | B84: Guarda-corpo de laje pós desforma com escora metálica - trevesões e tela | C84: M | D84: 221.67 | E84: 18.6718 | F84: =E84*D84 -> 4138.9779 | H84: EPC''s'
A85: 01.02.001.0002.00007 | B85: Fechament removivel de vãos em madeira | C85: M2 | D85: 90.63 | E85: 58.1818 | F85: =E85*D85 -> 5273.0165 | H85: EPC''s'
A86: 01.02.001.0002.00008 | B86: Proteção-Linha de Vida | C86: M | D86: 221.67 | E86: 87.168 | F86: =E86*D86 -> 19322.531 | H86: EPC''s'
A87: 01.02.001.0002.00009 | B87: Tela fachadeira | C87: M2 | D87: 3013.83 | E87: 6.08 | F87: =E87*D87 -> 18324.086 | H87: EPC''s'
A88: 01.02.001.0002.00010 | B88: Tela SLQA | C88: M | D88: 73.89 | E88: 235.7418 | F88: =E88*D88 -> 17418.962 | G88: Item adicionado em revisão
A89: 01.02.001.0003 | B89: Meio ambiente | F89: =F90+F91 -> 4700
A90: 01.02.001.0003.00001 | B90: Elaboracao do Programa de Prevencao dos Riscos Ambientais (PPRA) | C90: VB | D90: 1 | E90: 3100 | F90: =E90*D90 -> 3100
A91: 01.02.001.0003.00002 | B91: Programa de Controle Médico de Saúde Ocupacional (PCMSO) | C91: VB | D91: 1 | E91: 1600 | F91: =E91*D91 -> 1600
A92: 01.02.001.0004 | B92: Saúde ocupacional | F92: =SUM(F93:F96) -> 47500
A93: 01.02.001.0004.00002 | B93: Material de Primeiro Socorro | C93: VB | D93: 1 | E93: 500 | F93: =E93*D93 -> 500
A94: 01.02.001.0004.00003 | B94: Dedetização | C94: VB | D94: 1 | E94: 5000 | F94: =E94*D94 -> 5000
A95: 01.02.001.0004.00004 | B95: Elaboracao do Programa de Condicoes e Meio Ambiente de Trabalho na Industria de Construcao (PCMAT) | C95: VB | D95: 1 | E95: 2000 | F95: =E95*D95 -> 2000
A96: 01.02.001.0004.00005 | B96: Retirada de Entulho | C96: VB | D96: 1 | E96: 40000 | F96: =E96*D96 -> 40000
A97: 01.02.002 | B97: ADMINISTRAÇÃO E CANTEIRO DE OBRA | F97: =F98+F110+F112+F131+F138 -> 1436012.9
A98: 01.02.002.0001 | B98: Equipe de Gestão e Apoio | F98: =SUM(F99:F109) -> 1107599
A99: 01.02.002.0001.00001 | B99: Engenheiro Civil | C99: MES | D99: 30 | E99: 7200 | F99: =E99*D99 -> 216000
A100: 01.02.002.0001.00002 | B100: Mestre geral | C100: MES | D100: 30 | E100: 5000 | F100: =E100*D100 -> 150000
...

Sheet Ravello
A1: ORÇAMENTO EXECUTIVO
A2: Obra | B2: RAVELLO | F2: AT | G2: 1412.41
A3: Empresa | B3: AMALFI | F3: AC | G3: 13434.29
A4: Revisão | B4: R00 | F4: APE | G4: 1023.93
A5: Data | B5: 45351
A6: ORÇAMENTO EXECUTIVO RAVELLO - R00
A7: Código | B7: Descrição | C7: Un. | D7: Quantidade orçada | E7: Preço unitário | F7: Preço total
A8: 02 | B8: CUSTOS DIRETOS | F8: =F9+F15+F36+F62+F86+F110+F126+F146+F158+F164+F174+F185+F196+F217+F234+F276+F306+F355+F367+F387 -> 34082879
A9: 02.01 | B9: MOVIMENTAÇÃO DE TERRA | F9: =F10 -> 91928.48
A10: 02.01.001 | B10: MOVIMENTAÇÃO DE TERRA | F10: =F11+F13 -> 91928.48
A11: 02.01.001.0001 | B11: Movimentação de terra | F11: =F12 -> 88500
A12: 02.01.001.0001.00002 | B12: Escavação Mecânica com Bota Fora de blocos e baldrames | C12: VB | D12: 1 | E12: 88500 | F12: =E12*D12 -> 88500 | G12: =F12/G4 -> 86.43169
A13: 02.01.001.0002 | B13: Lastro de brita | F13: =F14 -> 3428.48
A14: 02.01.001.0002.00001 | B14: Lastro de Brita e=10cm | C14: M2 | D14: 389.6 | E14: 8.8 | F14: =E14*D14 -> 3428.48 | G14: =D14/G4 -> 0.38049476
A15: 02.02 | B15: INFRAESTRUTURA | F15: =F16+F19 -> 2274308.4
A16: 02.02.001 | B16: FUNDAÇÃO PROFUNDA | F16: =F17 -> 949000 | G16: =F16/$G$3 -> 70.640131
A17: 02.02.001.0001 | B17: Fundação profunda | F17: =F18 -> 949000
A18: 02.02.001.0001.00001 | B18: Execução de estacas | C18: VB | D18: 1 | E18: 949000 | F18: =E18*D18 -> 949000
A19: 02.02.002 | B19: FUNDAÇÃO RASA | F19: =F20+F22+F32+F34 -> 1325308.4 | G19: =F19/$G$3 -> 98.651168
A20: 02.02.002.0001 | B20: Forma | F20: =F21 -> 113398.5
A21: 02.02.002.0001.00001 | B21: Fabricacao e montagem de forma para bloco de fundacao - em madeira serrada | C21: M2 | D21: 2128.44 | E21: 53.2778 | F21: 113398.5
A22: 02.02.002.0002 | B22: Armadura | F22: =SUM(F23:F31) -> 451418.81
A23: 02.02.002.0002.00001 | B23: Armacao aco CA-60 ø 5.0mm para infraestrutura corte e dobra em obra | C23: KG | D23: 2937.6 | E23: 8.4179 | F23: 24728.54
A24: 02.02.002.0002.00002 | B24: Armacao aco CA-50 ø 6.3mm para infraestrutura corte e dobra em obra | C24: KG | D24: 798.3 | E24: 0.4869 | F24: 388.7242
A25: 02.02.002.0002.00003 | B25: Armacao aco CA-50 ø 8.0mm para infraestrutura corte e dobra em obra | C25: KG | D25: 1896 | E25: 7.6699 | F25: 14542.206
A26: 02.02.002.0002.00004 | B26: Armacao aco CA-50 ø 10.0mm para infraestrutura corte e dobra em obra | C26: KG | D26: 6541 | E26: 7.3399 | F26: 48010.548
A27: 02.02.002.0002.00005 | B27: Armacao aco CA-50 ø 12.5mm para infraestrutura corte e dobra em obra | C27: KG | D27: 6299 | E27: 7.0099 | F27: 44155.612
A28: 02.02.002.0002.00006 | B28: Armacao aco CA-50 ø 16.0mm para infraestrutura corte e dobra em obra | C28: KG | D28: 10249 | E28: 7.0099 | F28: 71844.875
A29: 02.02.002.0002.00007 | B29: Armacao aco CA-50 ø 20.0mm para infraestrutura corte e dobra em obra | C29: KG | D29: 24674 | E29: 7.1419 | F29: 176220.23
A30: 02.02.002.0002.00008 | B30: Armacao aco CA-50 ø 25.0mm para infraestrutura corte e dobra em obra | C30: KG | D30: 5076 | E30: 7.1419 | F30: 36252.487
A31: 02.02.002.0002.00009 | B31: Armação aco com tela TQ 138 | C31: KG | D31: 2937.6 | E31: 12.0083 | F31: 35275.592
A32: 02.02.002.0003 | B32: Concreto | F32: =F33 -> 304905.83
A33: 02.02.002.0003.00001 | B33: Concreto usinado bombeavel - para infraestrutura - Fck 35MPa - Brita 0 SLUMP = 12 +/- 2 incluindo servico de bombeamento | C33: M3 | D33: 509.45 | E33: 598.5 | F33: =E33*D33 -> 304905.83
A34: 02.02.002.0004 | B34: Mão de obra | F34: =F35 -> 455585.26
A35: 02.02.002.0004.00001 | B35: Mao de obra para execucacao de infraestrutura de concreto armado (inclusindo blocos-baldrames-contenções-cisterna-dutos) | C35: VB | D35: 1 | E35: 455585.26 | F35: 455585.26
A36: 02.03 | B36: SUPRAESTRUTURA | F36: =F37 -> 8742671.4 | G36: =F36/$G$3 -> 650.77287
A37: 02.03.001 | B37: SUPRAESTRUTURA | F37: =F38+F41+F51+F53+F58+F60 -> 8742671.4
A38: 02.03.001.0001 | B38: Forma | F38: =F39+F40 -> 689058.07 | G38: =F38/$G$3 -> 51.290992
A39: 02.03.001.0001.00001 | B39: Fabricação de Fôrma Para Estruturas de Concreto Armado - em Chapa de Madeira Compensada Plastificada - E=18mm | C39: M2 | D39: =2.5*1109.21*2+2.5*(7467/15)*2 -> 8035.05 | E39: 83.977571 | F39: =E39*D39 -> 674763.98
A40: 02.03.001.0001.00005 | B40: Montagem e desmontagem de fôrma para Estruturas de Concreto Armado - em chapa de madeira compensada plastificada | C40: M2 | D40: =2.5*[5]OBRA!D10 -> 33585.725 | E40: 0.4256 | F40: =E40*D40 -> 14294.085
A41: 02.03.001.0002 | B41: Armadura | F41: =SUM(F42:F50) -> 2489883.9 | G41: =F41/$G$3 -> 185.33796
A42: 02.03.001.0002.00001 | B42: Armacao aco CA-60 ø 5.0mm para supraestrutura corte e dobra em obra | C42: KG | D42: 4621.4 | E42: 8.4085 | F42: 38859.273 | G42: =SUM(D42:D50)/D52 -> 99.153389
A43: 02.03.001.0002.00002 | B43: Armacao aco CA-50 ø 6.3mm para supraestrutura corte e dobra em obra | C43: KG | D43: 42423.4 | E43: 7.6308 | F43: 323726.6
A44: 02.03.001.0002.00003 | B44: Armacao aco CA-50 ø 8.0mm para supraestrutura corte e dobra em obra | C44: KG | D44: 17427 | E44: 7.6069 | F44: 132565.62
A45: 02.03.001.0002.00004 | B45: Armacao aco CA-50 ø 10.0mm para supraestrutura corte e dobra em obra | C45: KG | D45: 18751 | E45: 7.2529 | F45: 135999.32
A46: 02.03.001.0002.00005 | B46: Armacao aco CA-50 ø 12.5mm para supraestrutura corte e dobra em obra | C46: KG | D46: 120199.2 | E46: 6.9018 | F46: 829589.64
A47: 02.03.001.0002.00006 | B47: Armacao aco CA-50 ø 16.0mm para supraestrutura corte e dobra em obra | C47: KG | D47: 50324 | E47: 6.8832 | F47: 346389.65
A48: 02.03.001.0002.00007 | B48: Armacao aco CA-50 ø 20.0mm para supraestrutura corte e dobra em obra | C48: KG | D48: 12203 | E48: 7.0033 | F48: 85461.392
A49: 02.03.001.0002.00008 | B49: Armacao aco CA-50 ø 25.0mm para supraestrutura corte e dobra em obra | C49: KG | D49: 28977 | E49: 7.0033 | F49: 202934.91
A50: 02.03.001.0002.00009 | B50: Armação aco com tela TQ 138 | C50: KG | D50: 32840.4 | E50: 12.0083 | F50: 394357.48
A51: 02.03.001.0003 | B51: Concreto | F51: =F52 -> 1972646.6 | G51: =F51/$G$3 -> 146.83669
A52: 02.03.001.0003.00001 | B52: Concreto usinado bombeavel - para supraestrutura - Fck 35MPa - Brita 0 SLUMP = 12 +/- 2 incluindo servico de bombeamento | C52: M3 | D52: 3305.65 | E52: 596.75 | F52: =E52*D52 -> 1972646.6 | G52: =D52/G3 -> 0.24606064
A53: 02.03.001.0004 | B53: Complementares | F53: =SUM(F54:F57) -> 600845.25 | G53: =F53/$G$3 -> 44.724749
A54: 02.03.001.0004.00001 | B54: Locação de cubetas | C54: MES | D54: 5 | E54: 28132.294 | F54: =E54*D54 -> 140661.47 | G54: =(F54+F55)/G3 -> 20.430103
A55: 02.03.001.0004.00002 | B55: Aquisição de cubetas | C55: VB | D55: 1 | E55: 133802.45 | F55: =E55*D55 -> 133802.45
A56: 02.03.001.0004.00003 | B56: Locação de escoramento metálico | C56: MES | D56: 17 | E56: 16621.647 | F56: =E56*D56 -> 282568 | G56: =F56/G3 -> 21.033341
A57: 02.03.001.0004.00004 | B57: Equipamentos de proteção | C57: VB | D57: 1 | E57: 43813.33 | F57: =E57*D57 -> 43813.33
A58: 02.03.001.0005 | B58: Mão de obra | F58: =F59 -> 2830171.1 | G58: =F58/$G$3 -> 210.66771
A59: 02.03.001.0005.00001 | B59: Mao de obra para execucacao de supraestrutura de concreto armado | C59: VB | D59: 1 | E59: 2830171.1 | F59: =E59*D59 -> 2830171.1
A60: 02.03.001.0006 | B60: Imprevistos e contingências | F60: =F61 -> 160066.47
A61: 02.03.001.0006.00001 | B61: Imprevistos e contingências | C61: VB | D61: 1 | E61: 160066.47 | F61: =E61*D61 -> 160066.47
A62: 02.04 | B62: PAREDES E PAINÉIS | F62: =F63 -> 1608711.9
A63: 02.04.001 | B63: PAREDES E PAINÉIS | F63: =F64+F69+F72+F74+F78+F84 -> 1608711.9
A64: 02.04.001.0001 | B64: Alvenaria de vedação com blocos cerâmicos | F64: =SUM(F65:F68) -> 441142.31
A65: 02.04.001.0001.00001 | B65: Alvenaria de vedação de blocos cerâmicos furados na horizontal de 11,5x19x29 cm (espessura 11,5cm) com argamassa industrializada de assentamento | C65: M2 | D65: 8997.45 | E65: 27.795 | F65: =E65*D65 -> 250084.12 | G65: =D65/$G$3 -> 0.66973766
A66: 02.04.001.0001.00002 | B66: Alvenaria de vedação de blocos cerâmicos furados na horizontal de 14x19x29 cm (espessura 14cm) com argamassa industrializada de assentamento | C66: M2 | D66: 4285.18 | E66: 30.17 | F66: =E66*D66 -> 129283.88 | G66: =D66/$G$3 -> 0.31897331
A67: 02.04.001.0001.00003 | B67: Alvenaria de vedação de blocos cerâmicos furados na horizontal de 9x19x29 cm (espessura 9cm) com argamassa industrializada de assentamento | C67: M2 | D67: 1315.83 | E67: 20.65 | F67: =E67*D67 -> 27171.889 | G67: =D67/$G$3 -> 0.09794563
A68: 02.04.001.0001.00004 | B68: Alvenaria de vedação de blocos cerâmicos furados na horizontal de 19x19x29 cm (espessura 19cm) com argamassa industrializada de assentamento | C68: M2 | D68: 965.2 | E68: 35.85 | F68: =E68*D68 -> 34602.42 | G68: =D68/$G$3 -> 0.071846
A69: 02.04.001.0002 | B69: Alvenaria de vedação com bocos resistente ao fogo | F69: =F70+F71 -> 128759.93
A70: 02.04.001.0002.00001 | B70: Alvenaria com bloco silico calcário de 12.5x30x60cm (espessura de 12.5cm) com argamassa industrializada de assentamento | C70: M2 | D70: 68.41 | E70: 60.082 | F70: =E70*D70 -> 4110.2096 | G70: =(D70+D71)/$G$3 -> 0.15952239
A71: 02.04.001.0002.00002 | B71: Alvenaria com bloco silico calcário de 10x30x60cm (espessura de 10cm) com argamassa industrializada de assentamento | C71: M2 | D71: 2074.66 | E71: 60.082 | F71: =E71*D71 -> 124649.72
A72: 02.04.001.0004 | B72: Revestimento em tijolo refratário | F72: =F73 -> 54910.128
A73: 02.04.001.0004.00001 | B73: Assentamento de tijolos refratários de 5.0x11.5x23 cm com argamassa refratária | C73: M2 | D73: 349.19 | E73: 157.25 | F73: =E73*D73 -> 54910.128 | G73: =D73/$G$3 -> 0.025992442
A74: 02.04.001.0006 | B74: Serviços complementares para alvenaria de vedação | F74: =SUM(F75:F77) -> 227615.7
A75: 02.04.001.0006.00001 | B75: Verga/Contraverga de Concreto | C75: M | D75: 2417.8 | E75: 36.8567 | F75: =E75*D75 -> 89112.129 | G75: =F74/(D65+D66+D67+D68+D70+D71) -> 12.854756
A76: 02.04.001.0006.00002 | B76: Encunhamento com Expansor | C76: M | D76: 8324.63 | E76: 14.7875 | F76: =E76*D76 -> 123100.47
A77: 02.04.001.0006.00003 | B77: Tela soldada para ligacao alvenaria/estrutura - para blocos de 9 a 14cm | C77: UN | D77: 4163 | E77: 3.7 | F77: =E77*D77 -> 15403.1
A78: 02.04.001.0007 | B78: Mão de obra | F78: =SUM(F79:F83) -> 726830.49
A79: 02.04.001.0007.00001 | B79: Mao de obra empreitada vedacoes internas e externas - assentamento de blocos silico-calcários | C79: M2 | D79: =D70+D71 -> 2143.07 | E79: 35 | F79: =E79*D79 -> 75007.45
A80: 02.04.001.0007.00002 | B80: Mao de obra empreitada vedacoes internas - assentamento de blocos cerâmicos | C80: M2 | D80: =D66+D67+D68 -> 6566.21 | E80: 34 | F80: =E80*D80 -> 223251.14
A81: 02.04.001.0007.00003 | B81: Mao de obra empreitada vedacoes externas - assentamento de blocos cerâmicos até o pavimento lazer | C81: VB | D81: 1 | E81: 119748.04 | F81: =E81*D81 -> 119748.04
A82: 02.04.001.0007.00004 | B82: Mao de obra empreitada vedacoes externas - assentamento de blocos cerâmicos nos pavimentos tipo | C82: M2 | D82: 6376.69 | E82: 45.6921 | F82: =E82*D82 -> 291364.36
A83: 02.04.001.0007.00005 | B83: Mao de obra empreitada vedacoes internas e externas - assentamento de tijolo refratário em churrasqueira | C83: M2 | D83: =D73 -> 349.19 | E83: 50 | F83: =E83*D83 -> 17459.5
A84: 02.04.001.0008 | B84: Imprevistos e contingências | F84: =F85 -> 29453.34
A85: 02.04.001.0008.00001 | B85: Imprevistos e contingências | C85: VB | D85: 1 | E85: 29453.34 | F85: =E85*D85 -> 29453.34
A86: 02.05 | B86: IMPERMEABILIZAÇÃO E TRATAMENTOS | F86: =F87 -> 818981.42
A87: 02.05.001 | B87: IMPERMEABILIZAÇÃO E TRATAMENTOS | F87: =F88+F91+F94+F96+F98+F100+F102+F108 -> 818981.42
A88: 02.05.001.0001 | B88: Regularização e proteção mecânica | F88: =F89+F90 -> 79243.535
A89: 02.05.001.0001.00001 | B89: Regularizacao de superficie para impermeabilizacao | C89: M2 | D89: =D93+D97 -> 6166.85 | E89: 6.2895 | F89: =E89*D89 -> 38786.403
A90: 02.05.001.0001.00002 | B90: Protecao mecanica de superficie com argamassa de cimento e areia - traço 1:3 E=5cm | C90: M2 | D90: =D97 -> 1656.26 | E90: 24.4268 | F90: =E90*D90 -> 40457.132
A91: 02.05.001.0002 | B91: Impermeabilização com argamassa polimérica | F91: =F92+F93 -> 340454.8
A92: 02.05.001.0002.00001 | B92: Mão de obra para impermeabilização de reservatorios | C92: M2 | D92: 353.05 | E92: 70 | F92: =E92*D92 -> 24713.5 | G92: =(D92+D93)/$G$3 -> 0.36203179
A93: 02.05.001.0002.00002 | B93: Mão de obra para impermeabilização com argamassa polimérica | C93: M2 | D93: 4510.59 | E93: 70 | F93: =E93*D93 -> 315741.3
A94: 02.05.001.0003 | B94: Impermeabilização de fundação e contenção | F94: =F95 -> 28819.202
A95: 02.05.001.0003.00001 | B95: Impermeabilizacao com tinta asfaltica em baldrames | C95: M2 | D95: =D21+32.73 -> 2161.17 | E95: 13.335 | F95: =E95*D95 -> 28819.202
A96: 02.05.001.0004 | B96: Impermeabilização com manta asfáltica | F96: =F97 -> 188813.64
A97: 02.05.001.0004.00001 | B97: Mão de obra para impermeabilização com manta asfáltica | C97: M2 | D97: 1656.26 | E97: 114 | F97: =E97*D97 -> 188813.64 | G97: =(D97)/$G$3 -> 0.12328601
A98: 02.05.001.0007 | B98: Impermeabilização de esquadrias | F98: =F99 -> 4991.68
A99: 02.05.001.0007.00001 | B99: Impermeabilizacao com manta liquida em peitoris | C99: M2 | D99: 164.2 | E99: 30.4 | F99: =E99*D99 -> 4991.68 | G99: =(F99+F106)/$G$3 -> 0.76268117
A100: 02.05.001.0008 | B100: Impermeabilização de ralos | F100: =F101 -> 415.7056
...

Sheet Dados Gerais
A2: ORÇAMENTO PARAMÉTRICO GERENCIAMENTO EXECUTIVO
A7: Cliente | B7: Amalfi
A8: Obra | B8: San Felicce
A9: Data | B9: 45747
A10: Revisão | B10: R00
A12: Descrição | B12: Identificador | C12: Informação
A13: Área do terreno | B13: AT | C13: 953.88 | D13: m² | F13: Pavimento | G13: Area (m²) | H13: Correção Amalfi (m²) | I13: diferença
A14: Área total construída | B14: AC | C14: =H21 -> 7456.95 | D14: m² | F14: TERREO | G14: 1946.79 | H14: 821.97
A15: N° total de pavimentos | B15: NP | C15: 13 | D15: un | F15: G1 | G15: 776.7 | H15: 761.33
A16: N° de pavimentos tipo | B16: NPT | C16: 9 | D16: un | F16: G2+LAZER | G16: 776.7 | H16: 756.19
A17: N° de pavimentos tipo diferenciado | B17: NPD | C17: 0 | D17: un | F17: TIPO (x9) | G17: =558.43 -> 558.43 | H17: 4907.25
A18: N° de pavimentos duplex | B18: ND | C18: 0 | D18: un | F18: COBERTURA | G18: =558.43 -> 558.43 | H18: 72.31
A19: Área Lazer | B19: AL | C19: =44.72+32.53+60.94+13.13+3.07+1.34+1.85+23.07+78.72+5.12+6.38+12.59+1.84+2.05+1.86+10.01+3.51+6.06 -> 308.79 | D19: m² | F19: BARRILETE | G19: 69.87 | H19: 68.95
A20: Locação da obra | B20: LC | C20: 129.29 | D20: m | F20: RESERVATÓRIO + TAMPA | G20: =69.87*2 -> 139.74 | H20: 68.95
A21: Área de projeção da torre | B21: APT | C21: =H17/9 -> 545.25 | D21: m² | G21: =SUM(G14:G16)+G17*9+G18+G19+G20 -> 9294.1 | H21: =SUM(H14:H20) -> 7456.95 | I21: =G21-H21 -> 1837.15
A22: Perímetro de projeção da torre | B22: PPT | C22: 109.27 | D22: m
A23: Área de subsolos | B23: AS | C23: 0 | D23: m²
A24: N° de subsolos | B24: NS | C24: 0 | D24: un
A25: Área do embasamento | B25: AE | C25: =H14+H15+H16 -> 2339.49 | D25: m²
A26: Área de projeção do embasamento | B26: APE | C26: =H15 -> 761.33 | D26: m²
A27: Perímetro de projeção embasamento | B27: PPE | C27: 121.18 | D27: m
A28: N° de pavimentos de embasamento | B28: NPE | C28: 3 | D28: un
A32: TERREO

Sheet Movimentação de Terra
A2: ORÇAMENTO PARAMÉTRICO GERENCIAMENTO EXECUTIVO
A7: Cliente | B7: Amalfi
A8: Obra | B8: San Felicce
A9: Data | B9: 45397
A10: Revisão | B10: R00 | J10: =6*30*200 -> 36000
A12: REBAIXAMENTO DE LENÇOL
A14: Descrição | B14: Quantidade | D14: Parâmetro | F14: Referência | G14: Valor total
A15: Rebaixamento de Lençol | B15: ='Dados Gerais'!C26 -> 761.33 | C15: m² | D15: 30 | E15: R$ / m² | F15: Média | G15: =D15*B15 -> 22839.9 | I15: =G15/'Dados Gerais'!$C$26 -> 30 | J15: 40 dias d erebaixamento
A16: TOTAL | G16: =SUM(G15:G15) -> 22839.9 | J16: 200,00 por dia
J17: =40*200 -> 8000
A19: ESCAVAÇÃO E REATERRO DE VALAS
A21: Descrição | B21: Quantidade | D21: Parâmetro | F21: Referência | G21: Valor total
A22: Escavação mecanizada para blocos e baldrames | B22: =D22*'Dados Gerais'!C26 -> 913.596 | C22: m³ | D22: 1.2 | E22: m³ / APE | F22: Média | G22: =+ROUNDUP((B22*80),0) -> 73088 | J22: =G22/'Dados Gerais'!$C$14 -> 9.8013263
A23: Reaterro para blocos e baldrames | B23: =D23*B22 -> 548.1576 | C23: m³ | D23: 0.6 | E23: m³ | F23: Média | G23: =+ROUNDUP((B23*30),0) -> 16445 | J23: =G23/'Dados Gerais'!$C$14 -> 2.2053252
A24: TOTAL | G24: =SUM(G22:G23) -> 89533 | I24: =G24/'Dados Gerais'!$C$26 -> 117.60078
A27: REGULARIZAÇÃO E APILOAMENTO DE FUNDO DE VALAS
A29: Descrição | B29: Quantidade | D29: Parâmetro | F29: Referência | G29: Valor total
A30: Lastro de BRITA | B30: =D30*'Dados Gerais'!C26 -> 304.532 | C30: m² | D30: 0.4 | E30: m² / APE | F30: Média | G30: =ROUNDUP((B30*8.8),0) -> 2680 | I30: =G30/'Dados Gerais'!$C$26 -> 3.5201555 | J30: =G30/'Dados Gerais'!$C$14 -> 0.35939627
A31: TOTAL | G31: =SUM(G30:G30) -> 2680
A34: TOTAL MOVIMENTAÇÃO DE TERRA | G34: =G16+G24+G31 -> 115052.9 | H34: =G34/'Dados Gerais'!C14 -> 15.428949

Sheet Infraestrutura
A2: ORÇAMENTO PARAMÉTRICO GERENCIAMENTO EXECUTIVO
A7: Cliente | B7: Amalfi
A8: Obra | B8: San Felicce
A9: Data | B9: 45397
A10: Revisão | B10: R00
A12: FUNDAÇÃO PROFUNDA
A14: Descrição | B14: Quantidade | D14: Parâmetro | F14: Referência | G14: Valor total
A15: Número de Estacas | B15: 102 | C15: un | D15: =B15/'Dados Gerais'!C26 -> 0.13397607 | E15: un / APE | F15: Média | G15: 0 | K15: Total estacas
A16: Estaca Hélice Continua Diâmetro 60 | B16: =D16*B15 -> 102 | C16: un | D16: 1 | E16: % | F16: Média | G16: 0 | J16: MARINE | K16: 413.02235 | L16: R$/m | M16: =63/Marine!G5 -> 0.13128282 | N16: =[8]ESTACAS!$D$19/[8]ESTACAS!$F$13 -> 3.3465079 | O16: KG/M
A17: Estaca Hélice Continua Diâmetro 60 | B17: =D17*B16 -> 2142 | C17: m | D17: 21 | E17: m / un | F17: Média | G17: =ROUNDUP((B17*100),0) -> 214200 | J17: RAVELLO | K17: 253.74332 | L17: R$/m
A18: Armação 6,3mm | B18: =D18*B20 -> 1514.0906 | C18: kg | D18: 2.5 | E18: kg / m³ | F18: Média | G18: =+ROUNDUP((B18*7.67),0) -> 11614
A19: Armação 16mm | B19: =D19*B20 -> 6661.9985 | C19: kg | D19: 11 | E19: kg / m³ | F19: Média | G19: =+ROUNDUP((B19*7.34),0) -> 48900
A20: Concreto | B20: =(PI()*0.6^2)/4*B17 -> 605.63623 | C20: m³ | D20: =535+35 -> 570 | E20: R$ / m³ | F20: Média | G20: =+ROUNDUP((B20*D20),0)*1.3 -> 448776.9
A21: Mobilização | B21: 1 | C21: vb | D21: 15000 | E21: vb | F21: Média | G21: =+ROUNDUP((B21*D21),0) -> 15000
A22: TOTAL | G22: =SUM(G15:G21) -> 738490.9 | H22: =G22/B17 -> 344.76699
A25: FUNDAÇÃO RASA
A27: Descrição | B27: Quantidade | D27: Parâmetro | F27: Referência | G27: Valor total
A28: Fabricação, montagem e desmontagem de forma para blocos e baldrames resinado | B28: =D28*'Dados Gerais'!C26 -> 380.665 | C28: m² | D28: 0.5 | E28: m² / APE | F28: Média | G28: =+B28*50 -> 19033.25
A29: Armação | B29: =B30*D29 -> 45679.8 | C29: kg | D29: 100 | E29: kg / m³ | F29: Média | G29: =+ROUNDUP((B29*7.34),0) -> 335290
A30: Concreto | B30: ='Dados Gerais'!C26*Infraestrutura!D30 -> 456.798 | C30: m³ | D30: 0.6 | E30: m³ / APE | F30: Média | G30: =+B30*(535+35)*1.05 -> 273393.6
A31: Mão de obra | B31: ='Dados Gerais'!C26 -> 761.33 | C31: m² | D31: 450 | E31: R$ / APE | F31: Média
A32: TOTAL | G32: =SUM(G28:G31) -> 627716.85
A36: TOTAL INFRAESTRUTURA | G36: =G22+G32 -> 1366207.8 | H36: =G36/'Dados Gerais'!C14 -> 183.21267

Sheet Supraestrutura
A2: ORÇAMENTO PARAMÉTRICO GERENCIAMENTO EXECUTIVO
A7: Cliente | B7: Amalfi
A8: Obra | B8: San Felicce
A9: Data | B9: 45397
A10: Revisão | B10: R00
A12: SUPRAESTRUTURA
A14: Descrição | B14: Quantidade | D14: Parâmetro | F14: Referência | G14: Valor total
A15: Fabricação forma | B15: =B16/D15 -> 1864.2375 | C15: m² | D15: 8 | E15: Reutilizações | F15: Média | G15: =+B15*85 -> 158460.19
A16: Montagem de forma | B16: =D16*'Dados Gerais'!C14 -> 14913.9 | C16: m² | D16: 2 | E16: m² / AC | F16: Média | G16: =+B16*1.5 -> 22370.85
A17: Escoramento - Torre | B17: ='Dados Gerais'!C21*'Dados Gerais'!C16 -> 4907.25 | C17: m² | D17: 45 | E17: R$ / m² | F17: Média | G17: =+B17*D17*0.5 -> 110413.12
A18: Escoramento - Embasamento | B18: =+'Dados Gerais'!C25 -> 2339.49 | C18: m² | D18: 45 | E18: R$ / m² | F18: Média | G18: =+B18*D18 -> 105277.05
A19: Cubetas | B19: =B17+B18 -> 7246.74 | C19: m² | D19: 24 | E19: R$ / m² | F19: Média | G19: =+B19*D19 -> 173921.76
A20: Armadura Convencional para Estrutura | B20: =D20*B21 -> 188660.84 | C20: kg | D20: 110 | E20: kg / m³ | F20: Média | G20: =+B20*7.25 -> 1367791.1
A21: Concreto | B21: =D21*'Dados Gerais'!C14 -> 1715.0985 | C21: m³ | D21: 0.23 | E21: m³ / AC | F21: Média | G21: =+B21*575*1.05 -> 1035490.7
A22: Mão de obra - estrutura em concreto armado | B22: ='Dados Gerais'!C14 -> 7456.95 | C22: m² | D22: 200 | E22: R$ / m² | F22: Média | G22: =+B22*D22 -> 1491390
A23: TOTAL | G23: =SUM(G15:G22) -> 4465114.7
A26: TOTAL SUPRAESTRUTURA | G26: =G23 -> 4465114.7 | H26: =G26/'Dados Gerais'!C14 -> 598.78566
A29: SUPRAESTRUTURA
A31: Descrição | B31: Quantidade | D31: Parâmetro | F31: Referência | G31: Valor total
A32: Fabricação forma | B32: =B33/D32 -> 1957.4494 | C32: m² | D32: 8 | E32: Reutilizações | F32: Média | G32: =+B32*85 -> 166383.2
A33: Montagem de forma | B33: =D33*'Dados Gerais'!C14 -> 15659.595 | C33: m² | D33: 2.1 | E33: m² / AC | F33: Média | G33: =+B33*1.5 -> 23489.393
A34: Escoramento - Torre | B34: ='Dados Gerais'!C21*'Dados Gerais'!C16 -> 4907.25 | C34: m² | D34: 45 | E34: R$ / m² | F34: Média | G34: =+B34*D34*0.5 -> 110413.12
A35: Escoramento - Embasamento | B35: =+'Dados Gerais'!C25 -> 2339.49 | C35: m² | D35: 45 | E35: R$ / m² | F35: Média | G35: =+B35*D35 -> 105277.05
A36: Armadura Convencional para Estrutura | B36: =D36*B37 -> 134225.1 | C36: kg | D36: 90 | E36: kg / m³ | F36: Média | G36: =+B36*7.25 -> 973131.98
A37: Concreto | B37: =D37*'Dados Gerais'!C14 -> 1491.39 | C37: m³ | D37: 0.2 | E37: m³ / AC | F37: Média | G37: =+B37*575*1.05 -> 900426.71
A38: Mão de obra - estrutura em concreto armado | B38: ='Dados Gerais'!C14 -> 7456.95 | C38: m² | D38: 240 | E38: R$ / m² | F38: Média | G38: =+B38*D38 -> 1789668
A39: TOTAL | G39: =SUM(G32:G38) -> 4068789.5

Sheet Alvenaria
A2: ORÇAMENTO PARAMÉTRICO GERENCIAMENTO EXECUTIVO
A7: Cliente | B7: Amalfi
A8: Obra | B8: San Felicce
A9: Data | B9: 45397
A10: Revisão | B10: R00
A12: ALVENARIA
B13: =SUM(B15:B19,B21) -> 9621.8691 | C13: =B13/'Dados Gerais'!C14 -> 1.2903223
A14: Descrição | B14: Quantidade | D14: Parâmetro | F14: Referência | G14: Valor total | J14: alvenaria lazer | K14: 124.1 | L14: m | M14: =K14/K16 -> 0.61323319
A15: Alvenaria embasamento | B15: =D15*('Dados Gerais'!C25-B16) -> 1810.3281 | C15: m² | D15: 0.8 | E15: m² / AE | F15: Média | G15: =+B15*30 -> 54309.842 | J15: drywall lazer | K15: 78.27 | L15: m | M15: =K15/K16 -> 0.38676681
A16: Alvenaria lazer | B16: =D16*'Dados Gerais'!C19*0.62 -> 76.57992 | C16: m² | D16: 0.4 | E16: m² / AL | F16: Média | G16: =+B16*30 -> 2297.3976 | J16: lin | K16: =SUM(K14:K15) -> 202.37
A17: Drywall lazer | B17: =D17*'Dados Gerais'!C19*0.38 -> 46.93608 | C17: m² | D17: 0.4 | E17: m² / AL | F17: Média | G17: =+B17*220 -> 10325.938
A18: Alvenaria tipo | B18: =D18*'Dados Gerais'!C21*'Dados Gerais'!C16*0.56 -> 4122.09 | C18: m² | D18: 1.5 | E18: m² / APT*(NPT+2ND) | F18: Média | G18: =+B18*30 -> 123662.7 | J18: alvenaria tipo | K18: 183.81 | L18: m | M18: =K18/K20 -> 1
A19: Drywall tipo | B19: =D18*'Dados Gerais'!C21*'Dados Gerais'!C16*0.44 -> 3238.785 | C19: m² | D19: 1.5 | E19: m² / APT*(NPT+2ND) | F19: Média | G19: =+B19*220 -> 712532.7
A20: Alvenaria escadas | B20: =D20*'Dados Gerais'!C14 -> 1267.6815 | C20: m² | D20: 0.17 | E20: m² / AC | F20: Média | G20: =+B20*60 -> 76060.89 | K20: =SUM(K18:K18) -> 183.81
A21: Alvenaria cobertura / reservatório | B21: =D21*'Dados Gerais'!C21 -> 327.15 | C21: m² | D21: 0.6 | E21: m² / APT | F21: Média | G21: =+B21*30 -> 9814.5
A22: Alvenaria refratárias | B22: ='Sistemas especiais'!B18 -> 47 | C22: un | D22: 1.75 | E22: m² / un | F22: Média | G22: =+B22*210 -> 9870 | K22: =K20+K16 -> 386.18 | L22: =(K15+#REF!)/K22 -> #REF!
A23: Serviços complementares | B23: =B15+B16+B18+B20+B21 -> 7603.8295 | C23: m² | D23: 7.5 | E23: R$ / m² | F23: Média | G23: =+B23*D23 -> 57028.721
A24: Mão de obra | B24: =B16+B18+B20+B21+B15 -> 7603.8295 | C24: m² | D24: 65 | E24: R$ / m² | F24: Média | G24: =+B24*D24 -> 494248.92
A25: TOTAL | G25: =SUM(G15:G24) -> 1550151.6
A28: TOTAL ALVENARIA | G28: =G25 -> 1550151.6 | H28: =G28/'Dados Gerais'!C14 -> 207.88011
E30: =(B15+B16+B18+B21)/'Dados Gerais'!$C$14 -> 0.84969699

Sheet Instalações
A2: ORÇAMENTO PARAMÉTRICO GERENCIAMENTO EXECUTIVO
A7: Cliente | B7: Amalfi
A8: Obra | B8: San Felicce
A9: Data | B9: 45397
A10: Revisão | B10: R00
A12: INSTALAÇÕES ELÉTRICAS
A14: Descrição | B14: Quantidade | D14: Parâmetro | F14: Referência | G14: Valor total
A15: Entrada de Energia | B15: 1 | C15: vb | D15: 5 | E15: R$ / AC | F15: Média | G15: =+D15*'Dados Gerais'!$C$14 -> 37284.75
A16: Eletrodutos e Eletrocalhas | B16: 1 | C16: vb | D16: 10 | E16: R$ / AC | F16: Média | G16: =+D16*'Dados Gerais'!$C$14 -> 74569.5
A17: Cabos e Fiações | B17: 1 | C17: vb | D17: 30 | E17: R$ / AC | F17: Média | G17: =+D17*'Dados Gerais'!$C$14 -> 223708.5
A18: Quadros e Disjuntores | B18: 1 | C18: vb | D18: 25 | E18: R$ / AC | F18: Média | G18: =+D18*'Dados Gerais'!$C$14 -> 186423.75
A19: Acabamentos Elétricos | B19: 1 | C19: vb | D19: 15 | E19: R$ / AC | F19: Média
A20: Equipamentos e Iluminação | B20: 1 | C20: vb | D20: 2 | E20: R$ / AC | F20: Média | G20: =+D20*'Dados Gerais'!$C$14 -> 14913.9
A21: Mão de Obra para Instalações Elétricas | B21: 1 | C21: vb | D21: 55 | E21: R$ / AC | F21: Média | G21: =+D21*'Dados Gerais'!$C$14 -> 410132.25
A22: TOTAL | G22: =SUM(G15:G21) -> 947032.65
A24: INSTALAÇÕES HIDROSSANITÁRIAS | J24: Esgoto
J25: Caixa de reclaque esgoto | P25: 1 | R25: 1145.2341 | S25: =R25*P25 -> 1145.2341
A26: Descrição | B26: Quantidade | D26: Parâmetro | F26: Referência | G26: Valor total | J26: MOTOBOMBA SHENEIDER BCS-350 (vazão 8,4m³/altura de operação 7 m.c.a.).1CV | N26: un | P26: 2 | R26: 5650.8 | S26: =R26*P26 -> 11301.6
A27: Instalações de Água Fria | B27: 1 | C27: vb | D27: 20 | E27: R$ / AC | F27: Média | G27: =+D27*'Dados Gerais'!$C$14 -> 149139
A28: Instalações de Água Quente | B28: 1 | C28: vb | D28: 10 | E28: R$ / AC | F28: Média | G28: =+D28*'Dados Gerais'!$C$14 -> 74569.5 | J28: Drenagem
A29: Instalações de Águas Pluviais | B29: 1 | C29: vb | D29: 10 | E29: R$ / AC | F29: Média | G29: =+D29*'Dados Gerais'!$C$14 -> 74569.5 | J29: QUADRO COMANDO BOMBA - Quadro Elevatório de Drenagem Pluvial, 2x1CV/380V | N29: un | P29: 4 | R29: 9116 | S29: =R29*P29 -> 36464
A30: Instalações Sanitárias | B30: 1 | C30: vb | D30: 15 | E30: R$ / AC | F30: Média | G30: =+D30*'Dados Gerais'!$C$14 -> 111854.25 | J30: Filtro de água Pluvial - FV1 | N30: un | P30: =2*4 -> 8 | R30: 1430 | S30: =R30*P30 -> 11440
A31: Louças e Metais | B31: 1 | C31: vb | D31: 20 | E31: R$ / AC | F31: Média | G31: =+D31*'Dados Gerais'!$C$14 -> 149139 | J31: MOTOBOMBA BRAVA DV-05 (vazão 5,3m³/altura operação 12 m.c.a.).1,2CV | N31: un | P31: =2*4 -> 8 | R31: 2100 | S31: =R31*P31 -> 16800
A32: Sistema de tratamento de esgoto | B32: 1 | C32: vb | D32: 20.5617 | E32: R$ / AC | F32: Média | G32: =+D32*'Dados Gerais'!$C$14 -> 153327.57
A33: Mão de Obra para Instalações Hidráulicas | B33: 1 | C33: vb | D33: 55 | E33: R$ / AC | F33: Média | G33: =+D33*'Dados Gerais'!$C$14 -> 410132.25 | S33: =SUM(S25:S31) -> 77150.834
A34: TOTAL | G34: =SUM(G27:G33) -> 1122731.1
A37: INSTALAÇÕES PREVENTIVAS E GLP
A39: Descrição | B39: Quantidade | D39: Parâmetro | F39: Referência | G39: Valor total
A40: Instalações Preventivas | B40: 1 | C40: vb | D40: 15 | E40: R$ / AC | F40: Média | G40: =+D40*'Dados Gerais'!$C$14 -> 111854.25
A41: Instalações de GLP | B41: 1 | C41: vb | D41: 10 | E41: R$ / AC | F41: Média | G41: =+D41*'Dados Gerais'!$C$14 -> 74569.5
A42: Instalações de Proteção e Aterramento - SPDA | B42: 1 | C42: vb | D42: 20 | E42: R$ / AC | F42: Média | G42: =+D42*'Dados Gerais'!$C$14 -> 149139
A43: TOTAL | G43: =SUM(G40:G42) -> 335562.75
A46: TOTAL INSTALAÇÕES | G46: =G22+G34+G43 -> 2405326.5 | H46: =G46/'Dados Gerais'!C14 -> 322.5617

Sheet Sistemas especiais
A2: ORÇAMENTO PARAMÉTRICO GERENCIAMENTO EXECUTIVO
A7: Cliente | B7: Amalfi
A8: Obra | B8: San Felicce
A9: Data | B9: 45397
A10: Revisão | B10: R00
A12: CLIMATIZAÇÃO, EXAUSTÃO MECÂNICA E PRESSURIZAÇÃO
A14: Descrição | B14: Quantidade | D14: Parâmetro | F14: Referência | G14: Valor total | J14: PRIVATIVA | K14: AREAS COMUNS
A15: Infraestrutura para Instalação de Ar Condicionado | B15: =(J15+K15) -> 160 | C15: un | D15: 1000 | E15: R$ / un | F15: Média | G15: =D15*B15 -> 160000 | J15: =9*17 -> 153 | K15: =3+4 -> 7 | M15: =8+7+17*15 -> 270
A16: Instalação de Ar Condicionado | B16: =K15 -> 7 | C16: un | D16: 4000 | E16: R$ / un | F16: Média | G16: =D16*B16 -> 28000
A17: Ventokit | B17: =(J17+K17) -> 42 | C17: un | D17: 350 | E17: R$ / un | F17: Média | G17: =+B17*D17 -> 14700 | J17: =4*9 -> 36 | K17: =2+2+2 -> 6
A18: Churrasqueiras | B18: =(J18+K18) -> 47 | C18: un | D18: 4500 | E18: R$ / un | F18: Média | G18: =+B18*D18 -> 211500 | J18: =5*9 -> 45 | K18: =2 -> 2
A19: TOTAL | G19: =SUM(G15:G18) -> 414200 | H19: =G19/'Dados Gerais'!$C$14 -> 55.545498
A21: COMUNICAÇÃO
A23: Descrição | B23: Quantidade | D23: Parâmetro | F23: Referência | G23: Valor total
A24: CFTV | B24: 1 | C24: vb | D24: 1 | E24: R$ / AC | F24: Média | G24: =+D24*'Dados Gerais'!$C$14 -> 7456.95
A25: Interfone | B25: 1 | C25: vb | D25: 2 | E25: R$ / AC | F25: Média | G25: =+D25*'Dados Gerais'!$C$14 -> 14913.9
A26: TV e internet | B26: 1 | C26: vb | D26: 6 | E26: R$ / AC | F26: Média | G26: =+D26*'Dados Gerais'!$C$14 -> 44741.7
A27: Automação, telecomunicação e sistemas de segurança | B27: 1 | C27: vb | D27: 2 | E27: R$ / AC | F27: Média
A28: TOTAL | G28: =SUM(G24:G27) -> 67112.55 | H28: =G28/'Dados Gerais'!$C$14 -> 9
A30: OUTROS SISTEMAS ESPECIAIS
A32: Descrição | B32: Quantidade | D32: Parâmetro | F32: Referência | G32: Valor total
A33: Outros sistemas | B33: 1 | C33: vb | D33: 20 | E33: R$ / AC | F33: Média | G33: =+D33*'Dados Gerais'!C14 -> 149139
A34: TOTAL | G34: =SUM(G33:G33) -> 149139
A37: EQUIPAMENTOS
A39: Descrição | B39: Quantidade | D39: Parâmetro | F39: Referência | G39: Valor total
A40: Elevadores | B40: 2 | C40: un | D40: 226000 | E40: R$ / un | F40: Média | G40: =B40*D40 -> 452000
A41: Grupo de geradores | B41: 1 | C41: un | D41: 80000 | E41: R$ | F41: Média
A42: Subestação | B42: 1 | C42: un | D42: 250000 | E42: R$ | F42: Média
A43: Infra de carro elétrico | B43: =1*5*9 -> 45 | C43: un | D43: 500 | E43: R$ / un | F43: Média
A44: Instalação carro elétrico | B44: 1 | C44: un | D44: 10000 | E44: R$ / un | F44: Média
A45: Sistema de placas fotovoltaicas | B45: =11.63*16.25 -> 188.9875 | C45: m2 | D45: 810 | E45: R$ / m² (telhado) | F45: Média
A46: Equipamentos para Piscina | B46: 1 | C46: un | D46: 50000 | E46: R$ | F46: Média | G46: =+B46*D46 -> 50000
A47: TOTAL | G47: =SUM(G40:G46) -> 502000 | H47: =G47/'Dados Gerais'!$C$14 -> 67.319749
A50: TOTAL SISTEMAS ESPECIAIS | G50: =G19+G34+G47+G28 -> 1132451.6 | H50: =G50/'Dados Gerais'!C14 -> 151.86525

Sheet Impermeabilização
A2: ORÇAMENTO PARAMÉTRICO GERENCIAMENTO EXECUTIVO
A7: Cliente | B7: Amalfi
A8: Obra | B8: San Felicce
A9: Data | B9: 45397
A10: Revisão | B10: R00
A12: IMPERMEABILIZAÇÃO
A14: Descrição | B14: Quantidade | D14: Parâmetro | F14: Referência | G14: Valor total
A15: Regularização de Superfície | B15: =B19+B20 -> 3780 | C15: m² | D15: 25 | E15: R$ / m² | F15: Média | G15: =+B15*D15 -> 94500
A16: Poço do elevador | B16: =3.33*2+7.3*1.8*2 -> 32.94 | C16: m² | D16: 45 | E16: R$ / m² | F16: Média | G16: =+B16*D16 -> 1482.3
A17: Baldrames | B17: =Infraestrutura!B28 -> 380.665 | C17: m² | D17: 30 | E17: R$ / m² | F17: Média | G17: =+B17*D17 -> 11419.95
A18: Ralos | B18: 1 | C18: vb | D18: 0.4 | E18: R$ / AC | F18: Média | G18: =D18*'Dados Gerais'!C14 -> 2982.78
A19: Impermeabilizações cimenticias | B19: =D19*'Dados Gerais'!C14 -> 2982.78 | C19: m² | D19: 0.4 | E19: m² / AC | F19: Média | G19: =+B19*105 -> 313191.9
A20: Impermeabilizações com manta asfaltica | B20: =('Dados Gerais'!G18+60.55+10.1+11.01+12.85+5.06+6.35)*1.2 -> 797.22 | C20: m² | D20: 0.18 | E20: m² / AC | F20: Média | G20: =+B20*120 -> 95666.4
A21: Impermeabilização de peitoril | B21: 1 | C21: vb | D21: 1 | E21: R$ / AC | F21: Média | G21: =+D21*'Dados Gerais'!$C$14 -> 7456.95
A22: Proteção Mecânica | B22: =B20 -> 797.22 | C22: m² | D22: 28 | E22: R$ / m² | F22: Média | G22: =D22*B22 -> 22322.16
A23: TOTAL | G23: =SUM(G15:G22) -> 549022.44
A26: TOTAL IMPERMEABILIZAÇÃO | G26: =G23 -> 549022.44 | H26: =G26/'Dados Gerais'!C14 -> 73.625603

Sheet Rev. Internos Piso e Parede
A2: ORÇAMENTO PARAMÉTRICO GERENCIAMENTO EXECUTIVO
A7: Cliente | B7: Amalfi
A8: Obra | B8: San Felicce
A9: Data | B9: 45397
A10: Revisão | B10: R00
A12: REVESTIMENTOS INTERNOS EM PISO E PAREDE
J13: =SUM(G15:G18) -> 428546.45
A14: Descrição | B14: Quantidade | D14: Parâmetro | F14: Referência | G14: Valor total | J14: =G20+G21 -> 150062.43
A15: Piso de concreto lapidado | B15: ='Acabamentos de Piso e Parede'!H31+'Acabamentos de Piso e Parede'!H32+'Acabamentos de Piso e Parede'!H33+'Acabamentos de Piso e Parede'!H34+'Acabamentos de Piso e Parede'!H35 -> 1581.2 | C15: m² | D15: 157 | E15: R$ / m² | F15: Média | G15: =D15*B15 -> 248248.4
A16: Piso de concreto alisado ranhurado | B16: ='Acabamentos de Piso e Parede'!I31+'Acabamentos de Piso e Parede'!I32+'Acabamentos de Piso e Parede'!I33+'Acabamentos de Piso e Parede'!I34+'Acabamentos de Piso e Parede'!I35 -> 237.7 | C16: m² | D16: 30 | E16: R$ / m² | F16: Média | G16: =D16*B16 -> 7131
A17: Contrapiso | B17: =SUM('Acabamentos de Piso e Parede'!B31:G35)-'Acabamentos de Piso e Parede'!D31+'Acabamentos de Piso e Parede'!M33 -> 4809.72 | C17: m² | D17: =B17/'Dados Gerais'!C14 -> 0.64499829 | E17: m² / AC | F17: Média | G17: =+B17*25 -> 120243
A18: Manta acústica | B18: ='Acabamentos de Piso e Parede'!B34+'Acabamentos de Piso e Parede'!G34 -> 3528.27 | C18: m² | D18: =B18/'Dados Gerais'!C14 -> 0.47315189 | E18: m² / AC | F18: Média | G18: =+B18*15 -> 52924.05
A19: Mão de obra contrapiso | B19: =B17 -> 4809.72 | G19: =B19*24 -> 115433.28
A20: Chapisco | B20: =Alvenaria!B23*2-'Rev. Fachada'!B15 -> 10349.133 | C20: m² | D20: 2.1 | E20: m² / AC | F20: Média | G20: =+B20*2.5 -> 25872.832
A21: Reboco | B21: =B20 -> 10349.133 | C21: m² | D21: 2.1 | E21: m² / AC | F21: Média | G21: =B21*12 -> 124189.59
A22: Mão de obra reboco | B22: =B20 -> 10349.133 | C22: m² | E22: m² / AC | F22: Média | G22: =B22*45 -> 465710.98
A23: TOTAL | G23: =SUM(G15:G21) -> 694042.16
A26: TOTAL REVESTIMENTOS | G26: =G23 -> 694042.16 | H26: =G26/'Dados Gerais'!C14 -> 93.073194
B29: =Alvenaria!B23*2-'Rev. Fachada'!B15 -> 10349.133

Sheet Acabamentos de Teto
A2: ORÇAMENTO PARAMÉTRICO GERENCIAMENTO EXECUTIVO
A7: Cliente | B7: Amalfi
A8: Obra | B8: San Felicce
A9: Data | B9: 45397
A10: Revisão | B10: R00
A12: ACABAMENTOS DE TETO
A14: Descrição | B14: Quantidade | D14: Parâmetro | F14: Referência | G14: Valor total
A15: Forro de gesso acartonado | B15: =+'Dados Gerais'!C14*D15 -> 5219.865 | C15: m² | D15: 0.7 | E15: m² / AC | F15: Média | G15: =+B15*110 -> 574185.15
A16: Negativo | B16: =B15*1.2 -> 6263.838 | C16: m | D16: =B16/'Dados Gerais'!$C$14 -> 0.84 | E16: m / AC | F16: Média | G16: =+B16*22 -> 137804.44
A17: Estucamento | B17: =D17*'Dados Gerais'!$C$14 -> 1491.39 | C17: m² | D17: 0.2 | E17: R$ / AC | F17: Média | G17: =B17*24 -> 35793.36
A18: Chapisco e reboco | B18: =D18*'Dados Gerais'!$C$14 -> 0 | C18: m² | D18: 0 | E18: R$ / AC | F18: Média | G18: =B18*91 -> 0
A19: TOTAL | G19: =SUM(G15:G18) -> 747782.95
A22: TOTAL TETO | G22: =G19 -> 747782.95 | H22: =G22/'Dados Gerais'!C14 -> 100.28

Sheet Acabamentos de Piso e Parede
A2: ORÇAMENTO PARAMÉTRICO GERENCIAMENTO EXECUTIVO
A7: Cliente | B7: Amalfi
A8: Obra | B8: San Felicce
A9: Data | B9: 45397
A10: Revisão | B10: R00
A12: ACABAMENTOS EM PISO E PAREDE
A14: Descrição | B14: Quantidade | D14: Parâmetro | F14: Referência | G14: Valor total
A15: Porcelanato | B15: =SUM(B31:B34)+SUM(F31:F35)+C31 -> 3217.69 | C15: m² | D15: =70+85 -> 155 | E15: R$ / m² | F15: Média | G15: =+D15*B15 -> 498741.95 | I15: =SUM(G15:G20)+G21/2 -> 979686.75 | K15: =I15+'Rev. Internos Piso e Parede'!J13 -> 1408233.2 | L15: PISO
A16: Piso vinilico | B16: =SUM(G31:G35) -> 1285.83 | C16: m² | D16: 130 | E16: R$ / m² | F16: Média | G16: =+D16*B16 -> 167157.9 | I16: =G22 -> 372847.5 | K16: =I16+'Rev. Internos Piso e Parede'!J14 -> 522909.93 | L16: PAREDE
A17: Piscina | B17: =5.12+6.38+12.59+9.35*0.5+10.64*0.2+15.32*1.5 -> 53.873 | C17: m² | D17: 250 | E17: R$ / m² | F17: Média | G17: =+D17*B17 -> 13468.25
A18: Emborrachado | B18: =SUM(E31:E35) -> 45.68 | C18: m² | D18: 310 | E18: R$ / m² | F18: Média | G18: =+D18*B18 -> 14160.8
A19: Paver | B19: =SUM(D31:D35) -> 190.85 | C19: m² | D19: 210 | E19: R$ / m² | F19: Média | G19: =+D19*B19 -> 40078.5
A20: Rodapés | B20: 1 | C20: vb | D20: 18 | E20: R$ / AC | F20: Média | G20: =+D20*'Dados Gerais'!$C$14 -> 134225.1
A21: Soleiras e peitoris | B21: 1 | C21: vb | D21: 30 | E21: R$ / AC | F21: Média | G21: =+D21*'Dados Gerais'!$C$14 -> 223708.5
A22: Revestimentos de Parede | B22: 1 | C22: vb | D22: =30+20 -> 50 | E22: R$ / AC | F22: Média | G22: =+D22*'Dados Gerais'!$C$14 -> 372847.5
A23: =20*40 -> 800 | G23: =SUM(G15:G22) -> 1464388.5
A26: TOTAL ACABAMENTOS | G26: =G23 -> 1464388.5 | H26: =G26/'Dados Gerais'!C14 -> 196.37902 | M26: =93.57+88.12+77.13+107.7+90.62 -> 457.14
L27: QUARTO | M27: =13.61+9.94+11.26+10.54+14+10.65+13.2+14.02+9.35+11.26+14.32+10.72 -> 142.87
L28: BANHEIRO | M28: =3.71+3.81+2+1.91+3.47+3.47+3.76+3.8+1.91+3.66+3.64+1.8+3.66+3.67 -> 44.27
L29: LIVNG E CIRCULAÇÃO | M29: =30.02+1.42+26.1+4.86+16.15+1.72+25.53+1.45+21.62+3.14 -> 132.01
B30: PORCELANATO | C30: CERAMICA | D30: PAVER | E30: EMBORRACHADO | F30: ANTIDERRAPANTE | G30: VINILICO | H30: ALISADO | I30: RANHURARDO | L30: COZINHA E AREA DE SERVIÇO | M30: =7.72+11+9.41+8.95+7.19+2.99 -> 47.26
A31: TERREO | B31: =0.89+51.22+12.62+27.48 -> 92.21 | C31: =9.17+16.31+2.96+2+2 -> 32.44 | D31: =113.16+77.69 -> 190.85 | H31: =4.31+336.97+201.17 -> 542.45 | I31: =30.44 -> 30.44 | L31: SACADA E AREA TECNICA | M31: =5.76+8.95+7.62+10.94+1.41+9.64+3.02+8.04+2.69+2.44+6.01 -> 66.52
A32: G1 | B32: =6.24 -> 6.24 | H32: =623.54 -> 623.54 | I32: =88.41 -> 88.41
A33: G2+LAZER | B33: =23.07+6.64+44.72+3.07+1.34+1.85+60.94 -> 141.63 | E33: =32.53+13.15 -> 45.68 | F33: =78.72+1.84+2.05+1.86+10.01+6.06+3.51 -> 104.05 | H33: =323.2+9.09 -> 332.29 | I33: =30.44+88.41 -> 118.85 | L33: ESCADA | M33: =(5.31+12.35+1.25*0.18*18)*12 -> 260.52
A34: TIPO | B34: =(25.62+M28+M29+M30)*9 -> 2242.44 | F34: =M31*9 -> 598.68 | G34: =M27*9 -> 1285.83 | I34: =0 -> 0
A35: COBERTURA | H35: =20.1+62.82 -> 82.92 | I35: =0 -> 0

Sheet Pintura Interna
A2: ORÇAMENTO PARAMÉTRICO GERENCIAMENTO EXECUTIVO
A7: Cliente | B7: Amalfi
A8: Obra | B8: Tramonti
A9: Data | B9: 45352
A10: Revisão | B10: R00
A12: PINTURA INTERNA - OPÇÃO 1
A14: Descrição | B14: Quantidade | D14: Parâmetro | F14: Referência | G14: Valor total
A15: Pintura piso epoxi | B15: =('Acabamentos de Piso e Parede'!H31+'Acabamentos de Piso e Parede'!H32+'Acabamentos de Piso e Parede'!H33)*0.02 -> 29.9656 | C15: m2 | D15: 90 | E15: R$ / m² | F15: Média | G15: =+D15*B15 -> 2696.904 | H15: apenas vagas
A16: Pintura acrílica antiderrapante | B16: ='Acabamentos de Piso e Parede'!M33+'Acabamentos de Piso e Parede'!H35 -> 343.44 | C16: m2 | D16: 65 | E16: R$ / m² | F16: Média | G16: =+D16*B16 -> 22323.6
A17: Textura escadas | B17: 1 | C17: vb | D17: 8 | E17: R$ / AC | F17: Média | G17: =+D17*'Dados Gerais'!$C$14 -> 59655.6
A18: Pintura Interna | B18: 1 | C18: vb | D18: 24 | E18: R$ / AC | F18: Média | G18: =+D18*'Dados Gerais'!$C$14 -> 178966.8
A19: Mão deo obra pintura e textura | B19: 1 | C19: vb | D19: 105 | E19: R$ / AC | F19: Média | G19: =+D19*'Dados Gerais'!$C$14 -> 782979.75
A20: TOTAL | G20: =SUM(G15:G18) -> 263642.9
A23: TOTAL PINTURA | G23: =G20 -> 263642.9 | H23: =G23/'Dados Gerais'!C14 -> 35.355327

Sheet Esquadrias
A2: ORÇAMENTO PARAMÉTRICO GERENCIAMENTO EXECUTIVO
A7: Cliente | B7: Amalfi
A8: Obra | B8: Tramonti
A9: Data | B9: 45352
A10: Revisão | B10: R00
A12: ESQUADRIAS
A14: Descrição | B14: Quantidade | D14: Parâmetro | F14: Referência | G14: Valor total
A15: Esquadrias de Alumínio | B15: =0.18*'Dados Gerais'!$C$14 -> 1342.251 | C15: m² | D15: 741.32624 | E15: R$ / m² | F15: Média | G15: =D15*B15 -> 995045.89
A16: PCF | B16: =12*2 -> 24 | C16: un | D16: 1150 | E16: R$ / un | F16: Média | G16: =D16*B16 -> 27600
A17: Serralherias | B17: 1 | C17: vb | D17: 3 | E17: R$ / AC | F17: Média | G17: =D17*B17*'Dados Gerais'!C14 -> 22370.85
A18: Guarda-corpo - vidro | B18: =B34 -> 391.14 | C18: m² | D18: 727.37 | E18: R$ / m² | F18: Média | G18: =+D18*B18 -> 284503.5
A19: Gradil | B19: =B31*9*1.1 -> 229.482 | C19: m | D19: 671.38 | E19: R$ / m² | F19: Média | G19: =+D19*B19 -> 154069.63
A20: Corrimão madeira | B20: =(4.64+13.3)*1.1*12 -> 236.808 | C20: m | D20: =60.5*3 -> 181.5 | E20: R$ / m² | F20: Média | G20: =+D20*B20 -> 42980.652
A21: Portão de alumínio | B21: 2 | C21: un | D21: 18000 | E21: R$ / un | F21: Média | G21: =+D21*B21 -> 36000
A22: Esquadrias de Madeira | B22: =3+6+(7+6+5+7+6)*9 -> 288 | C22: un | D22: 900 | E22: R$ / un | F22: Média | G22: =D22*B22 -> 259200
A23: TOTAL | G23: =SUM(G15:G22) -> 1821770.5
A26: TOTAL ESQUADRIAS | G26: =G23 -> 1821770.5 | H26: =G26/'Dados Gerais'!C14 -> 244.30505
C29: 626.24
B30: TIPO
A31: GRADIL | B31: =1.28+8.98+4.07+5.11+3.74 -> 23.18
A32: GUARDA COPRO | B32: =3.39+5.26+13.11+9.8 -> 31.56 | C32: 41.91
B34: =(B32*9+C32)*1.2 -> 391.14

Sheet Auxiliar
A2: 2 Portões acesso garagem - Área: 9,2m² x 2 = 18,4m² | B2: 2 | C2: portão | D2: 18.4
A3: 2 portas corta-fogo 1 folha | B3: 2 | C3: pcf
A4: 1 porta de correr alumínio 2 folhas – Área: 3,465m² | B4: 1 | C4: porta alumínio | D4: 3.465
A5: 1 porta de correr alumínio 2 folhas – Área: 1,7325m² | B5: 1 | C5: porta alumínio | D5: 1.7325 | G5: Guarda alumínio | H5: =SUMIF(C:C,G5,D:D) -> 400.5221
A6: 2 portas de abrir alumínio 2 folhas – Área: 2,6376m² x 2 = 5,2752m² | B6: 2 | C6: porta alumínio | D6: 5.2752 | G6: janela | H6: =SUMIF(C:C,G6,D:D) -> 1895.06
A7: 1 porta de abrir alumínio 2 folhas – Área: 4,1916m² | B7: 1 | C7: porta alumínio | D7: 4.1916 | G7: madeira | H7: =SUMIF(C:C,G7,B:B) -> 218
A8: 1 porta pivotante | B8: 1 | C8: pivotante | G8: pcf | H8: =SUMIF(C:C,G8,B:B) -> 60
A9: 19 portas de abrir madeira 1 folha | B9: 19 | C9: madeira | G9: pivotante | H9: =SUMIF(C:C,G9,B:B) -> 1
A10: 3 portas de abrir vidro 1 folha – Área: 2,1m² x 3 = 6,3m² | B10: 3 | C10: porta alumínio | D10: 6.3 | G10: porta alumínio | H10: =SUMIF(C:C,G10,D:D) -> 46.62
A11: 2 portas de abrir vidro 1 folha – Área: 1,89m² x 2 = 3,78m² | B11: 2 | C11: porta alumínio | D11: 3.78 | G11: portão | H11: =SUMIF(C:C,G11,B:B) -> 2
A12: 1 porta de abrir alumínio 1 folha – Área: 2,0076m² | B12: 1 | C12: porta alumínio | D12: 2.0076 | G12: gradil | H12: =SUMIF(C:C,G12,D:D) -> 113.88
A13: Janelas – Área: 3,75 + 4,875 + 2,5 + 1,1 + 1,2 + 5,5402 + 4,4874 = 23,4526m² | C13: janela | D13: 23.4526 | G13: Brise | H13: 109.3146
A14: Muro de vidro – Área: 7,0774 + 5,485 + 3,43 + 4,8138 = 20,8062m² | C14: Guarda alumínio | D14: 20.8062
A15: 8 portas corta-fogo 1 folha | B15: 8 | C15: pcf
A16: Janelas – Area: (1,1 + 1,2 + 28,7391) x 4 = 124,1564m² | C16: janela | D16: 124.1564
A17: 2 portas corta-fogo 1 folha | B17: 2 | C17: pcf
A18: 2 portas de abrir alumínio 1 folha – Área: 1,47m² x 2 = 2,94m² | B18: 2 | C18: porta alumínio | D18: 2.94
A19: 2 portas de abrir vidro 1 folha – Área: 1,89m² x 2 = 3,78m² | B19: 2 | C19: porta alumínio | D19: 3.78
A20: 5 portas de abrir madeira 1 folha | B20: 5 | C20: madeira
A21: 1 janela-porta de correr vidro – Área: 14,7348m² | B21: 1 | C21: janela | D21: 14.7348
A22: Janelas – Área: 1,2894 + 1,2894 + 23,46 + 1,854 + 5,562 + 5,562 + 1,854 + 1,854 + 1,1 + 1,2 = 45,0248m² | C22: janela | D22: 45.0248
A23: Guarda corpo vidro – Área: 7,5299 + 5,7955 + 6,5555 = 19,8809m² | C23: Guarda alumínio | D23: 19.8809
A24: 38 portas corta-fogo 1 folha | B24: 38 | C24: pcf
A25: 171 portas de abrir madeira 1 folha | B25: 171 | C25: madeira
A26: 19 porta de abrir alumínio 1 folha – Área: 1,26m² x 19 = 23,94m² | B26: 19 | C26: porta alumínio | D26: 23.94
A27: 19 janela-porta de correr vidro 5 folhas - Área: 25,4205m² x 19 = 482,9895m² | B27: 19 | C27: janela | D27: 482.9895
A28: 19 janela-porta de correr vidro 5 folhas - Área: 17,8284m² x 19 = 338,7396m² | B28: 19 | C28: janela | D28: 338.7396
A29: Janelas – Área: 1,1 + 1,1 + 1,2 + 1,92 + 0,36 + 2,781 + 2,781 + 1,854 + 1,854 + 5,562 + 5,562 + 1,854 = 27,928m² x 19 = 530,632m² | C29: janela | D29: 530.632
A30: Guarda corpo metálico – Área: 4,745m² x 19 = 90,155m² - Perímetro: 3,65m x 19 = 69,35m | C30: gradil | D30: 90.155
A31: Guarda corpo vidro – Área: 15,645m² x 19 = 297,255m² - Perímetro: 14,9m x 19 = 283,1m | C31: Guarda alumínio | D31: 297.255
A32: 2 portas corta-fogo 1 folha | B32: 2 | C32: pcf
A33: 2 portas de abrir madeira 1 folha | B33: 2 | C33: madeira
A34: 1 porta de abrir alumínio 1 folha – Área: 1,26m² | B34: 1 | C34: porta alumínio | D34: 1.26
A35: 1 janela-porta de correr vidro 3 folhas - Área: 15,21m² | B35: 1 | C35: janela | D35: 15.21
A36: 1 janela-porta de correr vidro 5 folhas - Área: 25,4205m² | B36: 1 | C36: janela | D36: 25.4205
A37: 1 janela-porta de correr vidro 5 folhas - Área: 17,8284m² | B37: 1 | C37: janela | D37: 17.8284
A38: Janelas – Área: 1,1 + 1,2 + 1,1 + 1,92 + 0,36 + 2,781 + 2,781 + 1,854 + 1,854 + 5,562 + 5,562 + 1,854 = 27,928m² | C38: janela | D38: 27.928
A39: Guarda corpo metálico – Área: 4,745m² - Perímetro: 3,65m | C39: gradil | D39: 4.745
A40: Guarda corpo vidro – Área: 15,645m² - Perímetro: 14,9m | C40: Guarda alumínio | D40: 15.645
A41: 2 portas corta-fogo 1 folha | B41: 2 | C41: pcf
A42: 7 portas de abrir madeira 1 folha | B42: 7 | C42: madeira
A43: 2 portas de correr madeira 1 folha | B43: 2 | C43: madeira
A44: 1 janela-porta de correr vidro 5 folhas - Área: 25,4205m² | B44: 1 | C44: janela | D44: 25.4205
A45: 1 janela-porta de correr vidro 5 folhas - Área: 17,8284m² | B45: 1 | C45: janela | D45: 17.8284
A46: Janelas – Área: 1,1 + 1,2 + 1,92 + 0,36 + 2,781 + 2,781 + 1,854 + 1,854 + 5,562 + 5,562 + 1,854 = 26,828m² | C46: janela | D46: 26.828
A47: Guarda corpo metálico – Área: 4,745m² - Perímetro: 3,65m | C47: gradil | D47: 4.745
A48: Guarda corpo vidro – Área: 15,645m² - Perímetro: 14,9m | C48: Guarda alumínio | D48: 15.645
A49: 2 portas corta-fogo 1 folha | B49: 2 | C49: pcf
A50: 4 portas de abrir madeira 1 folha | B50: 4 | C50: madeira
A51: 1 porta de abrir alumínio 1 folha – Área: 1,26m² | B51: 1 | C51: porta alumínio | D51: 1.26
A52: 1 porta de correr madeira 1 folha | B52: 1 | C52: madeira
A53: 1 porta de correr vidro 3 folhas – Área: 10,5m² | B53: 1 | C53: porta alumínio | D53: 10.5
A54: 1 janela-porta de correr vidro 5 folhas - Área: 25,4205m² | B54: 1 | C54: janela | D54: 25.4205
A55: 1 janela-porta de correr vidro 5 folhas - Área: 17,8284m² | B55: 1 | C55: janela | D55: 17.8284
A56: Janelas – Área: 1,1 + 1,2 + 1,1 + 1,92 + 0,36 + 2,781 + 2,781 + 1,854 + 1,854 + 5,562 + 5,562 + 1,854 = 27,928m² | C56: janela | D56: 27.928
A57: Guarda corpo metálico – Área: 4,745m² - Perímetro: 3,65m | C57: gradil | D57: 4.745
A58: Guarda corpo vidro – Área: 15,645m² - Perímetro: 14,9m | C58: Guarda alumínio | D58: 15.645
A59: 2 portas corta-fogo 1 folha | B59: 2 | C59: pcf
A60: 7 portas de abrir madeira 1 folha | B60: 7 | C60: madeira
A61: 1 janela-porta de correr vidro – Área: 5,61m² | B61: 1 | C61: janela | D61: 5.61
A62: Janela – Área: 1,1 + 1,2 + 1,92 + 0,36 + 2,781 + 2,781 + 1,854 + 1,854 + 5,562 + 5,562 + 1,854 + 25,0512 + 17,8284 = 69,7076m² | C62: janela | D62: 69.7076
A63: Guarda corpo metálico – Área: 4,745m² - Perímetro: 3,65m | C63: gradil | D63: 4.745
A64: Guarda corpo vidro – Área: 15,645m² - Perímetro: 14,9m | C64: Guarda alumínio | D64: 15.645
A65: 2 portas corta-fogo 1 folha | B65: 2 | C65: pcf
A66: 2 portas de abrir alumínio 1 folha – Área: 1,47m² x 2 = 2,94m² | B66: 2 | C66: porta alumínio | D66: 2.94
A67: Janelas – Area: 1,1 + 1,2 + 0,84 + 0,84 + 3,549 + 3,549 + 10,647 + 10,647 = 32,372m² | C67: janela | D67: 32.372
A68: Guarda corpo metálico – Área: 4,745m² - Perímetro: 3,65m | C68: gradil | D68: 4.745

Sheet Rev. Fachada
A2: ORÇAMENTO PARAMÉTRICO GERENCIAMENTO EXECUTIVO
A7: Cliente | B7: Amalfi
A8: Obra | B8: Tramonti
A9: Data | B9: 45352
A10: Revisão | B10: R00
A12: REVESTIMENTOS ARGAMASSADOS
A14: Descrição | B14: Quantidade | D14: Parâmetro | F14: Referência | G14: Valor total
A15: Chapisco e reboco | B15: =K19*L19+K20*L20+K21*L21 -> 4858.5261 | C15: m² | D15: 18 | E15: R$ / m² | F15: - | G15: =B15*D15 -> 87453.47
A16: Mão de obra | B16: =B15 -> 4858.5261 | C16: m² | D16: 115 | E16: R$ / m² | F16: - | G16: =B16*D16 -> 558730.5
A17: TOTAL | G17: =SUM(G15:G16) -> 646183.97
A19: PINTURA | J19: EMBASAMENTO | K19: ='Dados Gerais'!C27 -> 121.18 | L19: 9.42
J20: TORRE | K20: ='Dados Gerais'!C22 -> 109.27 | L20: 31.95
A21: Descrição | B21: Quantidade | D21: Parâmetro | F21: Referência | G21: Valor total | J21: RESERV | K21: 33.96 | L21: 6.65
A22: Microtextura | B22: =B15 -> 4858.5261 | C22: m² | D22: =30+42 -> 72 | E22: R$ / m² | F22: - | G22: =+B22*D22 -> 349813.88
A23: TOTAL | G23: =SUM(G22) -> 349813.88
A25: ACABAMENTOS ESPECIAIS
A27: Descrição | B27: Quantidade | D27: Parâmetro | F27: Referência | G27: Valor total
A28: Revestimentos especiais | B28: 1 | C28: vb | D28: 40 | E28: R$ / m² | F28: - | G28: =B28*D28*'Dados Gerais'!C14 -> 298278
G29: =SUM(G28:G28) -> 298278
J30: =25.78*2 -> 51.56
A32: TOTAL FACHADA | G32: =G29+G23+G17 -> 1294275.9 | H32: =G32/'Dados Gerais'!C14 -> 173.56638

Sheet Complementares
A2: ORÇAMENTO PARAMÉTRICO GERENCIAMENTO EXECUTIVO
A7: Cliente | B7: Amalfi
A8: Obra | B8: Tramonti
A9: Data | B9: 45352
A10: Revisão | B10: R00
A12: SERVIÇOS COMPLEMENTARES
A14: Descrição | B14: Quantidade | D14: Parâmetro | F14: Referência | G14: Valor total
A15: Móveis e decoração | B15: 1 | C15: vb | D15: 1750 | E15: R$ / AL | F15: Média | G15: =200*'Dados Gerais'!C14 -> 1491390 | J15: Alinterna | K15: ='Dados Gerais'!C19 -> 308.79
A16: Comunicação visual | B16: 1 | C16: vb | D16: 3 | E16: R$ / AC | F16: Média | G16: =B16*D16*'Dados Gerais'!$C$14 -> 22370.85
A17: Paisagismo | B17: 1 | C17: vb | D17: 5 | E17: R$ / AC | F17: Média | G17: =B17*D17*'Dados Gerais'!$C$14 -> 37284.75 | K17: =K15/'Dados Gerais'!C14 -> 0.041409692
A18: Ligações definitivas | B18: 1 | C18: vb | D18: 10 | E18: R$ / AC | F18: Média | G18: =B18*D18*'Dados Gerais'!$C$14 -> 74569.5
A19: desmobilização | B19: 1 | C19: vb | D19: 1 | E19: R$ / AC | F19: Média | G19: =B19*D19*'Dados Gerais'!$C$14 -> 7456.95
A20: Limpeza | B20: 1 | C20: vb | D20: 15 | E20: R$ / AC | F20: Média | G20: =B20*D20*'Dados Gerais'!$C$14 -> 111854.25
A21: TOTAL4 | G21: =SUM(G15:G20) -> 1744926.3
A24: TOTAL COMPLEMENTARES | G24: =G21 -> 1744926.3 | H24: =G24/'Dados Gerais'!C14 -> 234
