Workbook
Name \0: #REF!
Name \0: #REF!
Name \0: #REF!
Name \1: #REF!
Name \1: #REF!
Name \a: #REF!
Name \a: #REF!
Name \b: #REF!
Name \c: #REF!
Name \d: #REF!
Name \e: #REF!
Name \i: #REF!
Name \J: #REF!
Name \k: #REF!
Name \l: #N/A
Name \m: #REF!
Name \m: #REF!
Name \o: #REF!
Name \p: #REF!
Name \r: #REF!
Name \T: #REF!
Name \z: #REF!
Name ______ACR10: #REF!
Name ______ACR15: #REF!
Name ______acr20: #REF!
Name ______acr5: #REF!
Name ______ARQ1: #REF!
Name ______QT100: #REF!
Name ______QT2: #REF!
Name ______QT3: #REF!
Name ______QT4: #REF!
Name ______QT50: #REF!
Name ______QT75: #REF!
Name _____ACR10: #REF!
Name _____ACR15: #REF!
Name _____acr20: #REF!
Name _____acr5: #REF!
Name _____ARQ1: #REF!
Name _____QT100: #REF!
Name _____QT2: #REF!
Name _____QT3: #REF!
Name _____QT4: #REF!
Name _____QT50: #REF!
Name _____QT75: #REF!
Name ___ACR10: #REF!
Name ___ACR15: #REF!
Name ___acr20: #REF!
Name ___acr5: #REF!
Name ___ARQ1: #REF!
Name ___QT100: #REF!
Name ___QT2: #REF!
Name ___QT3: #REF!
Name ___QT4: #REF!
Name ___QT50: #REF!
Name ___QT75: #REF!
Name __ACR10: #REF!
Name __ACR15: #REF!
Name __acr20: #REF!
Name __acr5: #REF!
Name __ARQ1: #REF!

Sheet OBRA
A1: ESTUDO DE VIABILIDADE
A7: Cliente | B7: HOTEL COLLINE
A8: Obra | B8: HOTEL COLLINE - MIGUEL PEREIRA - RIO DE JANEIRO
A9: Data | B9: 45824
A10: Versão | B10: R01
B13: Descrição | C13: Identificador | D13: Unidade | E13: Hotel | F13: Residencial | G13: Quantidade Total
B14: ÁREA DO TERRENO | C14: AT | D14: M2 | G14: 6049.17
B15: ÁREA TOTAL CONSTRUÍDA | C15: AC | D15: M2 | E15: =SUM(E16:E26) -> 6049.17 | F15: =SUM(F16:F26) -> 21510.28 | G15: =SUM(G16:G26) -> 27559.45
B16: SUBSOLO / TERREO | D16: M2 | E16: 1662.34 | F16: 2365.57 | G16: =F16+E16 -> 4027.91
B17: TÉRREO/ GARAGEM 1 | D17: M2 | E17: =1147.74+527.82 -> 1675.56 | F17: 2339.03 | G17: =F17+E17 -> 4014.59
B18: 1º PAVIMENTO / GARAGEM 2 | D18: M2 | E18: =812.7+31.66 -> 844.36 | F18: 2514.32 | G18: =F18+E18 -> 3358.68
B19: 2º PAVIMENTO / LAZER | D19: M2 | E19: =900.46+243.83 -> 1144.29 | F19: 2513.4 | G19: =F19+E19 -> 3657.69
B20: SUBTELHADO / 5º PAV. DIFERENCIADO TORRE I E II (X1) | D20: M2 | E20: =691.7+30.92 -> 722.62 | F20: 699.84 | G20: =F20+E20 -> 1422.46
B21: 6º AO 18º PAV. DIFERENCIADO TORRE I E II (X13) | D21: M2 | F21: 9097.92 | G21: =F21+E21 -> 9097.92
B22: DUPLEX INFERIOR TORRE I E II | D22: M2 | F22: 699.84 | G22: =F22+E22 -> 699.84
B23: DUPLEX SUPERIOR TORRE I E II | D23: M2 | F23: 693.56 | G23: =F23+E23 -> 693.56
B24: INSPEÇÃO TORRE I E II | D24: M2 | F24: 303.24 | G24: =F24+E24 -> 303.24
B25: CASA DE MÁQUINAS TORRE I E II | D25: M2 | F25: 150.18 | G25: =F25+E25 -> 150.18
B26: CAIXA D'AGUA TORRE I E II | D26: M2 | F26: 133.38 | G26: =F26+E26 -> 133.38
B27: UNIDADES RESIDENCIAIS | C27: UR | D27: UN | E27: 36 | F27: 60 | G27: =F27+E27 -> 96
B28: Dormitórios | C28: dorm | D28: UN | E28: =E27 -> 36 | G28: =F28+E28 -> 36
B29: Banheiros | C29: ban | D29: UN | G29: =F29+E29 -> 0
B30: UNIDADES COMERCIAIS | C30: UC | D30: UN | G30: =F30+E30 -> 0
B31: Churrasqueiras | C31: CHU | D31: UN | F31: 60 | G31: =F31+E31 -> 60
B32: NÚMERO TOTAL DE PAVIMENTOS | C32: NP | D32: UN | E32: 5 | F32: 23 | G32: =F32+E32 -> 28
B33: NÚMERO DE PAVIMENTOS TIPO | C33: NPT | D33: UN | E33: 0 | F33: 13 | G33: =F33+E33 -> 13
B34: NÚMERO DE PAVIMENTOS TIPO DIFERENCIADOS | C34: NPD | D34: UN | E34: 3 | F34: 1 | G34: =F34+E34 -> 4
B35: NÚMERO DE PAVIMENTOS DUPLEX | C35: ND | D35: UN | E35: 0 | F35: 1 | G35: =F35+E35 -> 1
B36: ÁREA DE PROJEÇÃO DA TORRE | C36: APT | D36: M2 | E36: 1021.82 | F36: =369.45*2 -> 738.9 | G36: =F36+E36 -> 1760.72
B37: PERÍMETRO DE PROJEÇÃO DA TORRE | C37: PPT | D37: M | E37: 151.474 | F37: =101.4*2 -> 202.8 | G37: =F37+E37 -> 354.274
B38: ÁREA DE LAZER | C38: AL | D38: M2 | E38: 0 | F38: =F20 -> 699.84 | G38: =F38+E38 -> 699.84
B39: ÁREA DO EMBASAMENTO | C39: AE | D39: M2 | E39: =E17 -> 1675.56 | F39: =F17+F18+F19 -> 7366.75 | G39: =F39+E39 -> 9042.31
B40: ÁREA DE SUBSOLOS | C40: S | D40: M2 | E40: =E16 -> 1662.34 | F40: 0 | G40: =F40+E40 -> 1662.34
B41: NÚMERO DE SUBSOLOS | C41: NS | D41: UN | E41: 1 | F41: 0 | G41: =F41+E41 -> 1
B42: ÁREA DE PROJEÇÃO DO EMBASAMENTO | C42: APE | D42: M2 | E42: 2087.28 | F42: 2365.57 | G42: =F42+E42 -> 4452.85
B43: PERÍMETRO DE PROJEÇÃO DE EMBAMENTO | C43: PE | D43: M | E43: 226.19 | F43: 223.43 | G43: =F43+E43 -> 449.62
B44: NÚMERO DE PAVIMENTOS DE EMBASAMENTO | C44: NE | D44: UN | E44: 1 | F44: 3 | G44: =F44+E44 -> 4
B45: PRAZO HOTEL | C45: PM | D45: mês | E45: 24
B46: PRAZO RESIDENCIAL | C46: P1 | D46: mês | F46: 36
B47: PRAZO DE OBRA TOTAL (INICIO AO FIM) | C47: PR | D47: mês | G47: =F46 -> 36
L131: 1301371.9

Sheet RESUMOS
A1: HOTEL | B1: R00 | E1: R01 | H1: DIFERENÇA
A2: ETAPA | B2: VALOR ORÇADO | C2: % | D2: VALOR / m² | E2: VALOR ORÇADO | F2: % | G2: VALOR / m² | H2: VALOR ORÇADO | I2: % | J2: VALOR / m²
A3: MOVIMENTAÇÃO DE TERRA | B3: =[4]HOTEL!$L$5 -> 137245.95 | C3: =B3/B$18 -> 0.0033071137 | D3: =B3/RESUMOS!M$3 -> 22.688394 | E3: =HOTEL!L5 -> 137245.95 | F3: =E3/E$18 -> 0.0032933654 | G3: =E3/RESUMOS!M$3 -> 22.688394 | H3: =E3-B3 -> 0 | I3: =H3/B3 -> 0 | J3: =H3/RESUMOS!M$3 -> 0 | L3: ÁREA CONSTRUÍDA HOTEL | M3: =[5]OBRA!$E$15 -> 6049.17 | N3: m²
A4: INFRAESTRUTURA | B4: =[4]HOTEL!$L$22 -> 2200957.6 | C4: =B4/B$18 -> 0.053034839 | D4: =B4/RESUMOS!M$3 -> 363.84457 | E4: =HOTEL!L22 -> 2200957.6 | F4: =E4/E$18 -> 0.052814363 | G4: =E4/RESUMOS!M$3 -> 363.84457 | H4: =E4-B4 -> 0 | I4: =H4/B4 -> 0 | J4: =H4/RESUMOS!M$3 -> 0 | L4: ÁREA CONSTRUÍDA RESIDENCIAL | M4: =[5]OBRA!$F$15 -> 21510.28 | N4: m²
A5: SUPRAESTRUTURA | B5: =[4]HOTEL!$L$40 -> 4644536.7 | C5: =B5/B$18 -> 0.11191595 | D5: =B5/RESUMOS!M$3 -> 767.79735 | E5: =HOTEL!L40 -> 4644536.7 | F5: =E5/E$18 -> 0.11145069 | G5: =E5/RESUMOS!M$3 -> 767.79735 | H5: =E5-B5 -> 0 | I5: =H5/B5 -> 0 | J5: =H5/RESUMOS!M$3 -> 0 | M5: =M3+M4 -> 27559.45
A6: PAREDES E PAINÉIS | B6: =[4]HOTEL!$L$54 -> 2943440.9 | C6: =B6/B$18 -> 0.070925907 | D6: =B6/RESUMOS!M$3 -> 486.58591 | E6: =HOTEL!L54 -> 2968837.7 | F6: =E6/E$18 -> 0.071240478 | G6: =E6/RESUMOS!M$3 -> 490.7843 | H6: =E6-B6 -> 25396.8 | I6: =H6/B6 -> 0.0086282691 | J6: =H6/RESUMOS!M$3 -> 4.1983942
A7: INSTALAÇÕES ELÉTRICAS, HIDRÁULICAS, GLP E PREVENTIVAS | B7: =[4]HOTEL!$L$107+[4]HOTEL!$L$130+[4]HOTEL!$L$153+[4]HOTEL!$L$167+[4]HOTEL!$L$366 -> 3789528.2 | C7: =B7/B$18 -> 0.091313444 | D7: =B7/RESUMOS!M$3 -> 626.45424 | E7: =HOTEL!L108+HOTEL!L131+HOTEL!L154+HOTEL!L168+HOTEL!L369 -> 3789528.2 | F7: =E7/E$18 -> 0.090933836 | G7: =E7/RESUMOS!M$3 -> 626.45424 | H7: =E7-B7 -> 0 | I7: =H7/B7 -> 0 | J7: =H7/RESUMOS!M$3 -> 0
A8: EQUIPAMENTOS E SISTEMAS ESPECIAIS | B8: =[4]HOTEL!$L$179+[4]HOTEL!$L$190+[4]HOTEL!$L$209 -> 6534261.9 | C8: =B8/B$18 -> 0.15745125 | D8: =B8/RESUMOS!M$3 -> 1080.1915 | E8: =HOTEL!L180+HOTEL!L191+HOTEL!L210 -> 6534261.9 | F8: =E8/E$18 -> 0.1567967 | G8: =E8/RESUMOS!M$3 -> 1080.1915 | H8: =E8-B8 -> 0 | I8: =H8/B8 -> 0 | J8: =H8/RESUMOS!M$3 -> 0
A9: IMPERMEABILIZAÇÃO | B9: =[4]HOTEL!$L$73 -> 493452.25 | C9: =B9/B$18 -> 0.011890352 | D9: =B9/RESUMOS!M$3 -> 81.573546 | E9: =HOTEL!L74 -> 493452.25 | F9: =E9/E$18 -> 0.011840921 | G9: =E9/RESUMOS!M$3 -> 81.573546 | H9: =E9-B9 -> 0 | I9: =H9/B9 -> 0 | J9: =H9/RESUMOS!M$3 -> 0
A10: REVESTIMENTOS INTERNOS DE PAREDE | B10: =[4]HOTEL!$L$224 -> 2569648.4 | C10: =B10/B$18 -> 0.061918907 | D10: =B10/RESUMOS!M$3 -> 424.79355 | E10: =HOTEL!L225 -> 2569648.4 | F10: =E10/E$18 -> 0.061661498 | G10: =E10/RESUMOS!M$3 -> 424.79355 | H10: =E10-B10 -> 0 | I10: =H10/B10 -> 0 | J10: =H10/RESUMOS!M$3 -> 0
A11: REVESTIMENTOS E ACABAMENTOS INTERNOS EM TETO | B11: =[4]HOTEL!$L$248 -> 855037.86 | C11: =B11/B$18 -> 0.020603212 | D11: =B11/RESUMOS!M$3 -> 141.34796 | E11: =HOTEL!L249 -> 831199.77 | F11: =E11/E$18 -> 0.019945539 | G11: =E11/RESUMOS!M$3 -> 137.40724 | H11: =E11-B11 -> -23838.089 | I11: =H11/B11 -> -0.027879571 | J11: =H11/RESUMOS!M$3 -> -3.9407206
A12: PISOS E PAVIMENTAÇÕES | B12: =[4]HOTEL!$L$261 -> 3227702.4 | C12: =B12/B$18 -> 0.077775544 | D12: =B12/RESUMOS!M$3 -> 533.57773 | E12: =HOTEL!L264 -> 3231121.7 | F12: =E12/E$18 -> 0.077534267 | G12: =E12/RESUMOS!M$3 -> 534.14298 | H12: =E12-B12 -> 3419.3378 | I12: =H12/B12 -> 0.0010593721 | J12: =H12/RESUMOS!M$3 -> 0.56525735
A13: PINTURA INTERNA | B13: =[4]HOTEL!$L$300 -> 890994.12 | C13: =B13/B$18 -> 0.021469623 | D13: =B13/RESUMOS!M$3 -> 147.29196 | E13: =HOTEL!L303 -> 890237.65 | F13: =E13/E$18 -> 0.021362217 | G13: =E13/RESUMOS!M$3 -> 147.16691 | H13: =E13-B13 -> -756.4711 | I13: =H13/B13 -> -0.00084901918 | J13: =H13/RESUMOS!M$3 -> -0.1250537
A14: ESQUADRIAS, VIDROS E FERRAGENS | B14: =[4]HOTEL!$L$319 -> 10001040 | C14: =B14/B$18 -> 0.24098763 | D14: =B14/RESUMOS!M$3 -> 1653.2913 | E14: =HOTEL!L322 -> 10170063 | F14: =E14/E$18 -> 0.24404169 | G14: =E14/RESUMOS!M$3 -> 1681.2328 | H14: =E14-B14 -> 169023.14 | I14: =H14/B14 -> 0.016900556 | J14: =H14/RESUMOS!M$3 -> 27.941543
A15: COBERTURA | B15: =[4]HOTEL!$L$377 -> 1393694.5 | C15: =B15/B$18 -> 0.033582819 | D15: =B15/RESUMOS!M$3 -> 230.39433 | E15: =HOTEL!L380 -> 1393694.5 | F15: =E15/E$18 -> 0.033443209 | G15: =E15/RESUMOS!M$3 -> 230.39433 | H15: =E15-B15 -> 0 | I15: =H15/B15 -> 0 | J15: =H15/RESUMOS!M$3 -> 0
A16: REVESTIMENTOS E ACABAMENTOS DE FACHADA | B16: =[4]HOTEL!$L$395 -> 1254677.7 | C16: =B16/B$18 -> 0.030233035 | D16: =B16/RESUMOS!M$3 -> 207.41319 | E16: =HOTEL!L398 -> 1254677.7 | F16: =E16/E$18 -> 0.03010735 | G16: =E16/RESUMOS!M$3 -> 207.41319 | H16: =E16-B16 -> 0 | I16: =H16/B16 -> 0 | J16: =H16/RESUMOS!M$3 -> 0
A17: SERVIÇOS COMPLEMENTARES | B17: =[4]HOTEL!$L$425 -> 564003.74 | C17: =B17/B$18 -> 0.013590379 | D17: =B17/RESUMOS!M$3 -> 93.23655 | E17: =HOTEL!L428 -> 564003.74 | F17: =E17/E$18 -> 0.013533881 | G17: =E17/RESUMOS!M$3 -> 93.23655 | H17: =E17-B17 -> 0 | I17: =H17/B17 -> 0 | J17: =H17/RESUMOS!M$3 -> 0
A18: TOTAL | B18: =SUM(B3:B17) -> 41500222 | C18: =SUM(C3:C17) -> 1 | D18: =SUM(D3:D17) -> 6860.4821 | E18: =SUM(E3:E17) -> 41673467 | F18: =SUM(F3:F17) -> 1 | G18: =SUM(G3:G17) -> 6889.1215 | H18: =SUM(H3:H17) -> 173244.72 | I18: =SUM(I3:I17) -> -0.0021403928 | J18: =SUM(J3:J17) -> 28.63942
A19: CUB/RJ | B19: 2303.36 | C19: 45717 | D19: =+D18/B19 -> 2.9784671 | E19: 2303.36 | F19: 45717 | G19: =+G18/E19 -> 2.9909009 | H19: =H18/B18 -> 0.0041745492 | J19: =+J18/E19 -> 0.012433758
A21: RESIDENCIAL | B21: R00 | E21: R01 | H21: DIFERENÇA
A22: ETAPA | B22: VALOR ORÇADO | C22: % | D22: VALOR / m² | E22: VALOR ORÇADO | F22: % | G22: VALOR / m² | H22: VALOR ORÇADO | I22: % | J22: VALOR / m²
A23: MOVIMENTAÇÃO DE TERRA | B23: =[4]RESIDENCIAL!$L$5 -> 150402.2 | C23: =B23/B$38 -> 0.00172833 | D23: =B23/RESUMOS!M$4 -> 6.9921082 | E23: =RESIDENCIAL!L5 -> 150402.2 | F23: =E23/E$38 -> 0.0017183605 | G23: =E23/RESUMOS!M$4 -> 6.9921082 | H23: =E23-B23 -> 0 | I23: =H23/B23 -> 0 | J23: =H23/RESUMOS!M$4 -> 0
A24: INFRAESTRUTURA | B24: =[4]RESIDENCIAL!$L$22 -> 4184719.8 | C24: =B24/B$38 -> 0.048088237 | D24: =B24/RESUMOS!M$4 -> 194.54511 | E24: =RESIDENCIAL!L22 -> 4184719.8 | F24: =E24/E$38 -> 0.04781085 | G24: =E24/RESUMOS!M$4 -> 194.54511 | H24: =E24-B24 -> 0 | I24: =H24/B24 -> 0 | J24: =H24/RESUMOS!M$4 -> 0
A25: SUPRAESTRUTURA | B25: =[4]RESIDENCIAL!$L$40 -> 15149858 | C25: =B25/B$38 -> 0.17409288 | D25: =B25/RESUMOS!M$4 -> 704.30778 | E25: =RESIDENCIAL!L40 -> 15149858 | F25: =E25/E$38 -> 0.17308866 | G25: =E25/RESUMOS!M$4 -> 704.30778 | H25: =E25-B25 -> 0 | I25: =H25/B25 -> 0 | J25: =H25/RESUMOS!M$4 -> 0
A26: PAREDES E PAINÉIS | B26: =[4]RESIDENCIAL!$L$54 -> 6993312.5 | C26: =B26/B$38 -> 0.080362864 | D26: =B26/RESUMOS!M$4 -> 325.1149 | E26: =RESIDENCIAL!L54 -> 6993312.5 | F26: =E26/E$38 -> 0.079899307 | G26: =E26/RESUMOS!M$4 -> 325.1149 | H26: =E26-B26 -> 0 | I26: =H26/B26 -> 0 | J26: =H26/RESUMOS!M$4 -> 0
A27: INSTALAÇÕES ELÉTRICAS, HIDRÁULICAS, GLP E PREVENTIVAS | B27: =[4]RESIDENCIAL!$L$108+[4]RESIDENCIAL!$L$132+[4]RESIDENCIAL!$L$155+[4]RESIDENCIAL!$L$169+[4]RESIDENCIAL!$L$379 -> 9279749.7 | C27: =B27/B$38 -> 0.1066372 | D27: =B27/RESUMOS!M$4 -> 431.40999 | E27: =RESIDENCIAL!L108+RESIDENCIAL!L132+RESIDENCIAL!L155+RESIDENCIAL!L169+RESIDENCIAL!L382 -> 9279749.7 | F27: =E27/E$38 -> 0.10602208 | G27: =E27/RESUMOS!M$4 -> 431.40999 | H27: =E27-B27 -> 0 | I27: =H27/B27 -> 0 | J27: =H27/RESUMOS!M$4 -> 0
A28: EQUIPAMENTOS E SISTEMAS ESPECIAIS | B28: =[4]RESIDENCIAL!$L$181+[4]RESIDENCIAL!$L$192+[4]RESIDENCIAL!$L$211 -> 4796558.1 | C28: =B28/B$38 -> 0.055119107 | D28: =B28/RESUMOS!M$4 -> 222.9891 | E28: =RESIDENCIAL!L181+RESIDENCIAL!L192+RESIDENCIAL!L212 -> 5166429.3 | F28: =E28/E$38 -> 0.05902698 | G28: =E28/RESUMOS!M$4 -> 240.1842 | H28: =E28-B28 -> 369871.22 | I28: =H28/B28 -> 0.077111798 | J28: =H28/RESUMOS!M$4 -> 17.195091
A29: IMPERMEABILIZAÇÃO | B29: =[4]RESIDENCIAL!$L$74 -> 1276413.3 | C29: =B29/B$38 -> 0.01466776 | D29: =B29/RESUMOS!M$4 -> 59.33969 | E29: =RESIDENCIAL!L74 -> 1276413.3 | F29: =E29/E$38 -> 0.014583152 | G29: =E29/RESUMOS!M$4 -> 59.33969 | H29: =E29-B29 -> 0 | I29: =H29/B29 -> 0 | J29: =H29/RESUMOS!M$4 -> 0
A30: REVESTIMENTOS INTERNOS DE PAREDE | B30: =[4]RESIDENCIAL!$L$230 -> 2958539.7 | C30: =B30/B$38 -> 0.033997726 | D30: =B30/RESUMOS!M$4 -> 137.54073 | E30: =RESIDENCIAL!L231 -> 2958539.7 | F30: =E30/E$38 -> 0.033801617 | G30: =E30/RESUMOS!M$4 -> 137.54073 | H30: =E30-B30 -> 0 | I30: =H30/B30 -> 0 | J30: =H30/RESUMOS!M$4 -> 0
A31: REVESTIMENTOS E ACABAMENTOS INTERNOS EM TETO | B31: =[4]RESIDENCIAL!$L$254 -> 2340465.1 | C31: =B31/B$38 -> 0.026895191 | D31: =B31/RESUMOS!M$4 -> 108.80682 | E31: =RESIDENCIAL!L255 -> 2442171.8 | F31: =E31/E$38 -> 0.027902061 | G31: =E31/RESUMOS!M$4 -> 113.5351 | H31: =E31-B31 -> 101706.72 | I31: =H31/B31 -> 0.043455774 | J31: =H31/RESUMOS!M$4 -> 4.7282844
A32: PISOS E PAVIMENTAÇÕES | B32: =[4]RESIDENCIAL!$L$272 -> 7298340.6 | C32: =B32/B$38 -> 0.08386806 | D32: =B32/RESUMOS!M$4 -> 339.29547 | E32: =RESIDENCIAL!L275 -> 7331642.3 | F32: =E32/E$38 -> 0.083764759 | G32: =E32/RESUMOS!M$4 -> 340.84365 | H32: =E32-B32 -> 33301.671 | I32: =H32/B32 -> 0.00456291 | J32: =H32/RESUMOS!M$4 -> 1.5481747
A33: PINTURA INTERNA | B33: =[4]RESIDENCIAL!$L$313 -> 3699799.5 | C33: =B33/B$38 -> 0.04251583 | D33: =B33/RESUMOS!M$4 -> 172.00146 | E33: =RESIDENCIAL!L316 -> 3699799.5 | F33: =E33/E$38 -> 0.042270586 | G33: =E33/RESUMOS!M$4 -> 172.00146 | H33: =E33-B33 -> 0 | I33: =H33/B33 -> 0 | J33: =H33/RESUMOS!M$4 -> 0
A34: ESQUADRIAS, VIDROS E FERRAGENS | B34: =[4]RESIDENCIAL!$L$332 -> 17129486 | C34: =B34/B$38 -> 0.19684156 | D34: =B34/RESUMOS!M$4 -> 796.33953 | E34: =RESIDENCIAL!L335 -> 17129486 | F34: =E34/E$38 -> 0.19570612 | G34: =E34/RESUMOS!M$4 -> 796.33953 | H34: =E34-B34 -> 0 | I34: =H34/B34 -> 0 | J34: =H34/RESUMOS!M$4 -> 0
A35: COBERTURA | B35: =[4]RESIDENCIAL!$L$390 -> 1138286.1 | C35: =B35/B$38 -> 0.013080486 | D35: =B35/RESUMOS!M$4 -> 52.918235 | E35: =RESIDENCIAL!L393 -> 1138286.1 | F35: =E35/E$38 -> 0.013005034 | G35: =E35/RESUMOS!M$4 -> 52.918235 | H35: =E35-B35 -> 0 | I35: =H35/B35 -> 0 | J35: =H35/RESUMOS!M$4 -> 0
A36: REVESTIMENTOS E ACABAMENTOS DE FACHADA | B36: =[4]RESIDENCIAL!$L$408 -> 3653145 | C36: =B36/B$38 -> 0.041979705 | D36: =B36/RESUMOS!M$4 -> 169.83252 | E36: =RESIDENCIAL!L411 -> 3653145 | F36: =E36/E$38 -> 0.041737553 | G36: =E36/RESUMOS!M$4 -> 169.83252 | H36: =E36-B36 -> 0 | I36: =H36/B36 -> 0 | J36: =H36/RESUMOS!M$4 -> 0
A37: SERVIÇOS COMPLEMENTARES | B37: =[4]RESIDENCIAL!$L$442 -> 6972618.1 | C37: =B37/B$38 -> 0.080125056 | D37: =B37/RESUMOS!M$4 -> 324.15283 | E37: =RESIDENCIAL!L445 -> 6972618.1 | F37: =E37/E$38 -> 0.079662871 | G37: =E37/RESUMOS!M$4 -> 324.15283 | H37: =E37-B37 -> 0 | I37: =H37/B37 -> 0 | J37: =H37/RESUMOS!M$4 -> 0
A38: TOTAL | B38: =SUM(B23:B37) -> 87021693 | C38: =SUM(C23:C37) -> 1 | D38: =SUM(D23:D37) -> 4045.5863 | E38: =SUM(E23:E37) -> 87526573 | F38: =SUM(F23:F37) -> 1 | G38: =SUM(G23:G37) -> 4069.0578 | H38: =SUM(H23:H37) -> 504879.61 | I38: =SUM(I23:I37) -> 0.12513048 | J38: =SUM(J23:J37) -> 23.47155
A39: CUB/RJ | B39: 2303.36 | C39: 45717 | D39: =+D38/B39 -> 1.7563847 | E39: 2303.36 | F39: 45717 | G39: =+G38/E39 -> 1.7665748 | H39: =H38/B38 -> 0.0058017672 | J39: =+J38/E39 -> 0.010190135
A41: TOTAL | B41: R00 | E41: R01 | H41: DIFERENÇA
A42: ETAPA | B42: VALOR ORÇADO | C42: % | D42: VALOR / m² | E42: VALOR ORÇADO | F42: % | G42: VALOR / m² | H42: VALOR ORÇADO | I42: % | J42: VALOR / m²
A43: GERENCIAMENTO TÉCNICO E ADMINISTRATIVO | B43: =[4]INDIRETOS!$L$4 -> 9773213.3 | C43: =B43/B$59 -> 0.070669252 | D43: =B43/RESUMOS!M$5 -> 354.62295 | E43: =INDIRETOS!L4 -> 13604538 | F43: =E43/E$59 -> 0.09526682 | G43: =E43/RESUMOS!M$5 -> 493.6433 | H43: =E43-B43 -> 3831324.6 | I43: =H43/B43 -> 0.39202302 | J43: =H43/RESUMOS!M$5 -> 139.02036
A44: MOVIMENTAÇÃO DE TERRA | B44: =B23+B3 -> 287648.16 | C44: =B44/B$59 -> 0.0020799587 | D44: =B44/RESUMOS!M$5 -> 10.437369 | E44: =E23+E3 -> 287648.16 | F44: =E44/E$59 -> 0.0020142783 | G44: =E44/RESUMOS!M$5 -> 10.437369 | H44: =E44-B44 -> 0 | I44: =H44/B44 -> 0 | J44: =H44/RESUMOS!M$5 -> 0
A45: INFRAESTRUTURA | B45: =B24+B4 -> 6385677.5 | C45: =B45/B$59 -> 0.046174276 | D45: =B45/RESUMOS!M$5 -> 231.70555 | E45: =E24+E4 -> 6385677.5 | F45: =E45/E$59 -> 0.044716196 | G45: =E45/RESUMOS!M$5 -> 231.70555 | H45: =E45-B45 -> 0 | I45: =H45/B45 -> 0 | J45: =H45/RESUMOS!M$5 -> 0
A46: SUPRAESTRUTURA | B46: =B25+B5 -> 19794394 | C46: =B46/B$59 -> 0.14313154 | D46: =B46/RESUMOS!M$5 -> 718.24344 | E46: =E25+E5 -> 19794394 | F46: =E46/E$59 -> 0.13861176 | G46: =E46/RESUMOS!M$5 -> 718.24344 | H46: =E46-B46 -> 0 | I46: =H46/B46 -> 0 | J46: =H46/RESUMOS!M$5 -> 0
A47: PAREDES E PAINÉIS | B47: =B26+B6 -> 9936753.4 | C47: =B47/B$59 -> 0.071851796 | D47: =B47/RESUMOS!M$5 -> 360.55703 | E47: =E26+E6 -> 9962150.2 | F47: =E47/E$59 -> 0.06976072 | G47: =E47/RESUMOS!M$5 -> 361.47856 | H47: =E47-B47 -> 25396.8 | I47: =H47/B47 -> 0.0025558448 | J47: =H47/RESUMOS!M$5 -> 0.92152782
A48: INSTALAÇÕES ELÉTRICAS, HIDRÁULICAS, GLP E PREVENTIVAS | B48: =B27+B7 -> 13069278 | C48: =B48/B$59 -> 0.094502807 | D48: =B48/RESUMOS!M$5 -> 474.22129 | E48: =E27+E7 -> 13069278 | F48: =E48/E$59 -> 0.09151862 | G48: =E48/RESUMOS!M$5 -> 474.22129 | H48: =E48-B48 -> 0 | I48: =H48/B48 -> 0 | J48: =H48/RESUMOS!M$5 -> 0
A49: EQUIPAMENTOS E SISTEMAS ESPECIAIS | B49: =B28+B8 -> 11330820 | C49: =B49/B$59 -> 0.08193217 | D49: =B49/RESUMOS!M$5 -> 411.14101 | E49: =E28+E8 -> 11700691 | F49: =E49/E$59 -> 0.081934987 | G49: =E49/RESUMOS!M$5 -> 424.56186 | H49: =E49-B49 -> 369871.22 | I49: =H49/B49 -> 0.032642935 | J49: =H49/RESUMOS!M$5 -> 13.420849
A50: IMPERMEABILIZAÇÃO | B50: =B29+B9 -> 1769865.6 | C50: =B50/B$59 -> 0.012797744 | D50: =B50/RESUMOS!M$5 -> 64.219917 | E50: =E29+E9 -> 1769865.6 | F50: =E50/E$59 -> 0.012393619 | G50: =E50/RESUMOS!M$5 -> 64.219917 | H50: =E50-B50 -> 0 | I50: =H50/B50 -> 0 | J50: =H50/RESUMOS!M$5 -> 0
A51: REVESTIMENTOS INTERNOS DE PAREDE | B51: =B30+B10 -> 5528188.1 | C51: =B51/B$59 -> 0.039973845 | D51: =B51/RESUMOS!M$5 -> 200.59138 | E51: =E30+E10 -> 5528188.1 | F51: =E51/E$59 -> 0.038711561 | G51: =E51/RESUMOS!M$5 -> 200.59138 | H51: =E51-B51 -> 0 | I51: =H51/B51 -> 0 | J51: =H51/RESUMOS!M$5 -> 0
A52: REVESTIMENTOS E ACABAMENTOS INTERNOS EM TETO | B52: =B31+B11 -> 3195502.9 | C52: =B52/B$59 -> 0.023106403 | D52: =B52/RESUMOS!M$5 -> 115.94945 | E52: =E31+E11 -> 3273371.6 | F52: =E52/E$59 -> 0.022922035 | G52: =E52/RESUMOS!M$5 -> 118.77492 | H52: =E52-B52 -> 77868.632 | I52: =H52/B52 -> 0.024368193 | J52: =H52/RESUMOS!M$5 -> 2.8254784
A53: PISOS E PAVIMENTAÇÕES | B53: =B32+B12 -> 10526043 | C53: =B53/B$59 -> 0.076112897 | D53: =B53/RESUMOS!M$5 -> 381.93951 | E53: =E32+E12 -> 10562764 | F53: =E53/E$59 -> 0.073966564 | G53: =E53/RESUMOS!M$5 -> 383.27194 | H53: =E53-B53 -> 36721.009 | I53: =H53/B53 -> 0.0034885863 | J53: =H53/RESUMOS!M$5 -> 1.332429
A54: PINTURA INTERNA | B54: =B33+B13 -> 4590793.6 | C54: =B54/B$59 -> 0.033195628 | D54: =B54/RESUMOS!M$5 -> 166.57784 | E54: =E33+E13 -> 4590037.2 | F54: =E54/E$59 -> 0.032142087 | G54: =E54/RESUMOS!M$5 -> 166.55039 | H54: =E54-B54 -> -756.4711 | I54: =H54/B54 -> -0.00016478003 | J54: =H54/RESUMOS!M$5 -> -0.027448701
A55: ESQUADRIAS, VIDROS E FERRAGENS | B55: =B34+B14 -> 27130526 | C55: =B55/B$59 -> 0.19617847 | D55: =B55/RESUMOS!M$5 -> 984.43642 | E55: =E34+E14 -> 27299549 | F55: =E55/E$59 -> 0.19116719 | G55: =E55/RESUMOS!M$5 -> 990.56946 | H55: =E55-B55 -> 169023.14 | I55: =H55/B55 -> 0.0062299986 | J55: =H55/RESUMOS!M$5 -> 6.1330376
... A58: SERVIÇOS COMPLEMENTARES | B58: =B37+B17 -> 7536621.8 | C58: =B58/B$59 -> 0.054496654 | D58: =B58/RESUMOS!M$5 -> 273.46779 | E58: =E37+E17 -> 7536621.8 | F58: =E58/E$59 -> 0.052775772 | G58: =E58/RESUMOS!M$5 -> 273.46779 | H58: =E58-B58 -> 0 | I58: =H58/B58 -> 0 | J58: =H58/RESUMOS!M$5 -> 0
A59: TOTAL | B59: =SUM(B43:B58) -> 1.3829513e+08 | C59: =SUM(C43:C58) -> 1 | D59: =SUM(D43:D58) -> 5018.0656 | E59: =SUM(E43:E58) -> 1.4280458e+08 | F59: =SUM(F43:F58) -> 1 | G59: =SUM(G43:G58) -> 5181.6919 | H59: =SUM(H43:H58) -> 4509449 | I59: =SUM(I43:I58) -> 0.4611438 | J59: =SUM(J43:J58) -> 163.62623
A60: CUB/RJ | B60: 2303.36 | C60: 45717 | D60: =+D59/B60 -> 2.178585 | E60: 2303.36 | F60: 45717 | G60: =+G59/E60 -> 2.2496231 | H60: =H59/B59 -> 0.032607432 | J60: =+J59/E60 -> 0.071038063

Sheet CUB
A1: Relação de custos excluindo etapas não contabilizadas pelo CUB
B2: HOTEL | E2: RESIDENCIAL | H2: TOTAL
A3: ETAPA | B3: VALOR ORÇADO | C3: % | D3: VALOR / m² | E3: VALOR ORÇADO | F3: % | G3: VALOR / m² | H3: VALOR ORÇADO | I3: % | J3: VALOR / m²
A4: MOVIMENTAÇÃO DE TERRA | B4: 137245.95 | C4: =B4/B$19 -> 0.004076226 | D4: =B4/CUB!O$4 -> 22.688394 | E4: 150402.2 | F4: =E4/E$19 -> 0.0020346285 | G4: =E4/CUB!O$5 -> 6.9921082 | H4: =E4+B4 -> 287648.16 | I4: =H4/H$19 -> 0.0026735318 | J4: =H4/CUB!O$6 -> 10.437369 | N4: ÁREA CONSTRUÍDA HOTEL | O4: =[5]OBRA!$E$15 -> 6049.17 | P4: m²
A5: INFRAESTRUTURA | B5: 2200957.6 | C5: =B5/B$19 -> 0.06536878 | D5: =B5/CUB!O$4 -> 363.84457 | E5: 4184719.8 | F5: =E5/E$19 -> 0.05661054 | G5: =E5/CUB!O$5 -> 194.54511 | H5: =E5+B5 -> 6385677.5 | I5: =H5/H$19 -> 0.059351369 | J5: =H5/CUB!O$6 -> 231.70555 | N5: ÁREA CONSTRUÍDA RESIDENCIAL | O5: =[5]OBRA!$F$15 -> 21510.28 | P5: m²
A6: SUPRAESTRUTURA | B6: 4644536.7 | C6: =B6/B$19 -> 0.13794346 | D6: =B6/CUB!O$4 -> 767.79735 | E6: 15149858 | F6: =E6/E$19 -> 0.20494601 | G6: =E6/CUB!O$5 -> 704.30778 | H6: =E6+B6 -> 19794394 | I6: =H6/H$19 -> 0.18397804 | J6: =H6/CUB!O$6 -> 718.24344 | O6: =O4+O5 -> 27559.45
A7: PAREDES E PAINÉIS | B7: 2968837.7 | C7: =B7/B$19 -> 0.088174937 | D7: =B7/CUB!O$4 -> 490.7843 | E7: 6993312.5 | F7: =E7/E$19 -> 0.094604948 | G7: =E7/CUB!O$5 -> 325.1149 | H7: =E7+B7 -> 9962150.2 | I7: =H7/H$19 -> 0.092592722 | J7: =H7/CUB!O$6 -> 361.47856
A8: INSTALAÇÕES ELÉTRICAS, HIDRÁULICAS, GLP E PREVENTIVAS | B8: 2884186 | C8: =B8/B$19 -> 0.085660769 | D8: =B8/CUB!O$4 -> 476.79037 | E8: 7800237.6 | F8: =E8/E$19 -> 0.10552096 | G8: =E8/CUB!O$5 -> 362.62836 | H8: =E8+B8 -> 10684424 | I8: =H8/H$19 -> 0.099305856 | J8: =H8/CUB!O$6 -> 387.68639
A9: EQUIPAMENTOS E SISTEMAS ESPECIAIS | B9: 0 | C9: =B9/B$19 -> 0 | D9: =B9/CUB!O$4 -> 0 | E9: 13200 | F9: =E9/E$19 -> 0.0001785685 | G9: =E9/CUB!O$5 -> 0.61366007 | H9: =E9+B9 -> 13200 | I9: =H9/H$19 -> 0.00012268676 | J9: =H9/CUB!O$6 -> 0.47896457
A10: IMPERMEABILIZAÇÃO | B10: 493452.25 | C10: =B10/B$19 -> 0.014655608 | D10: =B10/CUB!O$4 -> 81.573546 | E10: 1276413.3 | F10: =E10/E$19 -> 0.017267213 | G10: =E10/CUB!O$5 -> 59.33969 | H10: =E10+B10 -> 1769865.6 | I10: =H10/H$19 -> 0.01644993 | J10: =H10/CUB!O$6 -> 64.219917
A11: REVESTIMENTOS INTERNOS DE PAREDE | B11: 2569648.4 | C11: =B11/B$19 -> 0.076318954 | D11: =B11/CUB!O$4 -> 424.79355 | E11: 2958539.7 | F11: =E11/E$19 -> 0.040022877 | G11: =E11/CUB!O$5 -> 137.54073 | H11: =E11+B11 -> 5528188.1 | I11: =H11/H$19 -> 0.051381476 | J11: =H11/CUB!O$6 -> 200.59138
A12: REVESTIMENTOS E ACABAMENTOS INTERNOS EM TETO | B12: 831199.77 | C12: =B12/B$19 -> 0.024686761 | D12: =B12/CUB!O$4 -> 137.40724 | E12: 2442171.8 | F12: =E12/E$19 -> 0.033037496 | G12: =E12/CUB!O$5 -> 113.5351 | H12: =E12+B12 -> 3273371.6 | I12: =H12/H$19 -> 0.030424193 | J12: =H12/CUB!O$6 -> 118.77492
A13: PISOS E PAVIMENTAÇÕES | B13: 3231121.7 | C13: =B13/B$19 -> 0.095964812 | D13: =B13/CUB!O$4 -> 534.14298 | E13: 7331642.3 | F13: =E13/E$19 -> 0.099181844 | G13: =E13/CUB!O$5 -> 340.84365 | H13: =E13+B13 -> 10562764 | I13: =H13/H$19 -> 0.098175097 | J13: =H13/CUB!O$6 -> 383.27194
A14: PINTURA INTERNA | B14: 890237.65 | C14: =B14/B$19 -> 0.026440195 | D14: =B14/CUB!O$4 -> 147.16691 | E14: 3699799.5 | F14: =E14/E$19 -> 0.050050579 | G14: =E14/CUB!O$5 -> 172.00146 | H14: =E14+B14 -> 4590037.2 | I14: =H14/H$19 -> 0.042661878 | J14: =H14/CUB!O$6 -> 166.55039
A15: ESQUADRIAS, VIDROS E FERRAGENS | B15: 10170063 | C15: =B15/B$19 -> 0.30205244 | D15: =B15/CUB!O$4 -> 1681.2328 | E15: 17129486 | F15: =E15/E$19 -> 0.23172626 | G15: =E15/CUB!O$5 -> 796.33953 | H15: =E15+B15 -> 27299549 | I15: =H15/H$19 -> 0.25373434 | J15: =H15/CUB!O$6 -> 990.56946
A16: COBERTURA | B16: 1393694.5 | C16: =B16/B$19 -> 0.04139294 | D16: =B16/CUB!O$4 -> 230.39433 | E16: 1138286.1 | F16: =E16/E$19 -> 0.015398639 | G16: =E16/CUB!O$5 -> 52.918235 | H16: =E16+B16 -> 2531980.5 | I16: =H16/H$19 -> 0.02353337 | J16: =H16/CUB!O$6 -> 91.873405
A17: REVESTIMENTOS E ACABAMENTOS DE FACHADA | B17: 1254677.7 | C17: =B17/B$19 -> 0.03726412 | D17: =B17/CUB!O$4 -> 207.41319 | E17: 3653145 | F17: =E17/E$19 -> 0.04941944 | G17: =E17/CUB!O$5 -> 169.83252 | H17: =E17+B17 -> 4907822.7 | I17: =H17/H$19 -> 0.04561552 | J17: =H17/CUB!O$6 -> 178.0813
A18: SERVIÇOS COMPLEMENTARES | B18: 0 | C18: =B18/B$19 -> 0 | D18: =B18/CUB!O$4 -> 0 | E18: 0 | F18: =E18/E$19 -> 0 | G18: =E18/CUB!O$5 -> 0 | H18: =E18+B18 -> 0 | I18: =H18/H$19 -> 0 | J18: =H18/CUB!O$6 -> 0
A19: TOTAL | B19: =SUM(B4:B18) -> 33669859 | C19: =SUM(C4:C18) -> 1 | D19: =SUM(D4:D18) -> 5566.0296 | E19: =SUM(E4:E18) -> 73921214 | F19: =SUM(F4:F18) -> 1 | G19: =SUM(G4:G18) -> 3436.5528 | H19: =SUM(H4:H18) -> 1.0759107e+08 | I19: =SUM(I4:I18) -> 1 | J19: =SUM(J4:J18) -> 3903.963
A20: CUB/RJ | B20: 2303.36 | C20: 45717 | D20: =+D19/B20 -> 2.4164827 | E20: 2303.36 | F20: 45717 | G20: =+G19/E20 -> 1.4919738 | H20: 2303.36 | I20: 45717 | J20: =+J19/H20 -> 1.6948992
D21: =1-D20/RESUMOS!$G$19 -> 0.19205524 | G21: =1-G20/RESUMOS!$G$39 -> 0.15544262 | J21: =1-J20/RESUMOS!$G$60 -> 0.24658527
A22: Equipamentos não contemplados pelo CUB em edifícios residenciais de médio a alto padrão:
A23: Sistemas de Transporte Vertical
A24: Elevadores (social e de serviço)
A25: Plataformas elevatórias (acessibilidade, se houver)
A26: Elevadores de emergência ou gerador-reserva para elevadores
A27: Sistemas Elétricos e de Automação
A28: Gerador de emergência (diesel ou gás)
A29: Quadros elétricos especiais (QGBT, QTA, QTM, etc.)
A30: Sistema de automação predial (BMS)
A31: Medidores individuais de água, gás e energia
A32: Infraestrutura para carregamento de carro elétrico
A33: Sistemas de Segurança Contra Incêndio
... A67: Estação compacta de tratamento de esgoto (ETE)

Sheet INDIRETOS
G1: ORÇAMENTO DE VIABILIDADE - INDIRETOS
J2: GERAL | M2: OBSERVAÇÕES | P2: Clientes possuem opção de fazer 3 suites ou 2 suites + 2 demi-suites - padrão 4 suites
A3: Unidade Construtiva | B3: Célula Construtiva | C3: Etapa | D3: Subetapa | E3: Serviço | G3: Hotel Colline de France - Rio de Janeiro | J3: Quantidade | K3: Unidade | L3: Custo
A4: =IF($G4="UNIDADE CONSTRUTIVA",1,LARGE(A$3:A3,1)) -> 1 | B4: =IF(G4="UNIDADE CONSTRUTIVA",0,IF(G4="CÉLULA CONSTRUTIVA",OFFSET(B4,-1,0)+1,OFFSET(B4,-1,0))) -> 0 | C4: =IF(G4="CÉLULA CONSTRUTIVA",0,IF(G4="ETAPA",OFFSET(C4,-1,0)+1,OFFSET(C4,-1,0))) -> Etapa | D4: =IF(G4="ETAPA",0,IF(G4="SUBETAPA",OFFSET(D4,-1,0)+1,OFFSET(D4,-1,0))) -> Subetapa | E4: =IF(G4="Subetapa",0,IF(G4="serviço",OFFSET(E4,-1,0)+1,OFFSET(E4,-1,0))) -> Serviço | G4: UNIDADE CONSTRUTIVA | H4: =IF(G4="Unidade Construtiva",TEXT(A4,"00"),IF(G4="Célula Construtiva",TEXT(B4,"00"),IF(G4="Etapa",CONCATENATE(TEXT(B4,"00"),".",TEXT(C4,"000")),IF(G4="Subetapa",CONCATENATE(TEXT(B4,"00"),".",TEXT(C4,"000"),".",TEXT(D4,"000")),IF(G4="Serviço",CONCATENATE(TEXT(B4,"00"),".",TEXT(C4,"000"),".",TEXT(D4,"000"),".",TEXT(E4,"000")),""))))) -> 01 | I4: GERENCIAMENTO TÉCNICO E ADMINISTRATIVO | L4: =L5+L14+L68 -> 13604538
A5: =IF($G5="UNIDADE CONSTRUTIVA",OFFSET(A5,0,0)+1,LARGE(A$3:A4,1)) -> 1 | B5: =IF(G5="UNIDADE CONSTRUTIVA",0,IF(G5="CÉLULA CONSTRUTIVA",OFFSET(B5,-1,0)+1,OFFSET(B5,-1,0))) -> 1 | C5: =IF(G5="CÉLULA CONSTRUTIVA",0,IF(G5="ETAPA",OFFSET(C5,-1,0)+1,OFFSET(C5,-1,0))) -> 0 | D5: =IF(G5="ETAPA",0,IF(G5="SUBETAPA",OFFSET(D5,-1,0)+1,OFFSET(D5,-1,0))) -> Subetapa | E5: =IF(G5="Subetapa",0,IF(G5="serviço",OFFSET(E5,-1,0)+1,OFFSET(E5,-1,0))) -> Serviço | G5: CÉLULA CONSTRUTIVA | H5: =IF(G5="Unidade Construtiva",TEXT(A5,"00"),IF(G5="Célula Construtiva",TEXT(B5,"00"),IF(G5="Etapa",CONCATENATE(TEXT(B5,"00"),".",TEXT(C5,"000")),IF(G5="Subetapa",CONCATENATE(TEXT(B5,"00"),".",TEXT(C5,"000"),".",TEXT(D5,"000")),IF(G5="Serviço",CONCATENATE(TEXT(B5,"00"),".",TEXT(C5,"000"),".",TEXT(D5,"000"),".",TEXT(E5,"000")),""))))) -> 01 | I5: SERVIÇOS TÉCNICOS | L5: =L6+L11 -> 4293333.3
A6: =IF($G6="UNIDADE CONSTRUTIVA",OFFSET(A6,0,0)+1,LARGE(A$3:A5,1)) -> 1 | B6: =IF(G6="UNIDADE CONSTRUTIVA",0,IF(G6="CÉLULA CONSTRUTIVA",OFFSET(B6,-1,0)+1,OFFSET(B6,-1,0))) -> 1 | C6: =IF(G6="CÉLULA CONSTRUTIVA",0,IF(G6="ETAPA",OFFSET(C6,-1,0)+1,OFFSET(C6,-1,0))) -> 1 | D6: =IF(G6="ETAPA",0,IF(G6="SUBETAPA",OFFSET(D6,-1,0)+1,OFFSET(D6,-1,0))) -> 0 | E6: =IF(G6="Subetapa",0,IF(G6="serviço",OFFSET(E6,-1,0)+1,OFFSET(E6,-1,0))) -> Serviço | G6: ETAPA | H6: =IF(G6="Unidade Construtiva",TEXT(A6,"00"),IF(G6="Célula Construtiva",TEXT(B6,"00"),IF(G6="Etapa",CONCATENATE(TEXT(B6,"00"),".",TEXT(C6,"000")),IF(G6="Subetapa",CONCATENATE(TEXT(B6,"00"),".",TEXT(C6,"000"),".",TEXT(D6,"000")),IF(G6="Serviço",CONCATENATE(TEXT(B6,"00"),".",TEXT(C6,"000"),".",TEXT(D6,"000"),".",TEXT(E6,"000")),""))))) -> 01.001 | I6: ESTUDOS, PROJETOS E CONSULTORIAS | L6: =SUM(L7:L10) -> 1480076.3
A7: =IF($G7="UNIDADE CONSTRUTIVA",OFFSET(A7,0,0)+1,LARGE(A$3:A6,1)) -> 1 | B7: =IF(G7="UNIDADE CONSTRUTIVA",0,IF(G7="CÉLULA CONSTRUTIVA",OFFSET(B7,-1,0)+1,OFFSET(B7,-1,0))) -> 1 | C7: =IF(G7="CÉLULA CONSTRUTIVA",0,IF(G7="ETAPA",OFFSET(C7,-1,0)+1,OFFSET(C7,-1,0))) -> 1 | D7: =IF(G7="ETAPA",0,IF(G7="SUBETAPA",OFFSET(D7,-1,0)+1,OFFSET(D7,-1,0))) -> 1 | E7: =IF(G7="Subetapa",0,IF(G7="serviço",OFFSET(E7,-1,0)+1,OFFSET(E7,-1,0))) -> 0 | G7: Subetapa | H7: =IF(G7="Unidade Construtiva",TEXT(A7,"00"),IF(G7="Célula Construtiva",TEXT(B7,"00"),IF(G7="Etapa",CONCATENATE(TEXT(B7,"00"),".",TEXT(C7,"000")),IF(G7="Subetapa",CONCATENATE(TEXT(B7,"00"),".",TEXT(C7,"000"),".",TEXT(D7,"000")),IF(G7="Serviço",CONCATENATE(TEXT(B7,"00"),".",TEXT(C7,"000"),".",TEXT(D7,"000"),".",TEXT(E7,"000")),""))))) -> 01.001.001 | I7: Estudos | J7: 1 | K7: vb | L7: 54376.895 | M7: Custo do hotel
A8: =IF($G8="UNIDADE CONSTRUTIVA",OFFSET(A8,0,0)+1,LARGE(A$3:A7,1)) -> 1 | B8: =IF(G8="UNIDADE CONSTRUTIVA",0,IF(G8="CÉLULA CONSTRUTIVA",OFFSET(B8,-1,0)+1,OFFSET(B8,-1,0))) -> 1 | C8: =IF(G8="CÉLULA CONSTRUTIVA",0,IF(G8="ETAPA",OFFSET(C8,-1,0)+1,OFFSET(C8,-1,0))) -> 1 | D8: =IF(G8="ETAPA",0,IF(G8="SUBETAPA",OFFSET(D8,-1,0)+1,OFFSET(D8,-1,0))) -> 2 | E8: =IF(G8="Subetapa",0,IF(G8="serviço",OFFSET(E8,-1,0)+1,OFFSET(E8,-1,0))) -> 0 | G8: Subetapa | H8: =IF(G8="Unidade Construtiva",TEXT(A8,"00"),IF(G8="Célula Construtiva",TEXT(B8,"00"),IF(G8="Etapa",CONCATENATE(TEXT(B8,"00"),".",TEXT(C8,"000")),IF(G8="Subetapa",CONCATENATE(TEXT(B8,"00"),".",TEXT(C8,"000"),".",TEXT(D8,"000")),IF(G8="Serviço",CONCATENATE(TEXT(B8,"00"),".",TEXT(C8,"000"),".",TEXT(D8,"000"),".",TEXT(E8,"000")),""))))) -> 01.001.002 | I8: Projetos | J8: 1 | K8: vb | L8: 1256710.9 | M8: Custo do hotel
A9: =IF($G9="UNIDADE CONSTRUTIVA",OFFSET(A9,0,0)+1,LARGE(A$3:A8,1)) -> 1 | B9: =IF(G9="UNIDADE CONSTRUTIVA",0,IF(G9="CÉLULA CONSTRUTIVA",OFFSET(B9,-1,0)+1,OFFSET(B9,-1,0))) -> 1 | C9: =IF(G9="CÉLULA CONSTRUTIVA",0,IF(G9="ETAPA",OFFSET(C9,-1,0)+1,OFFSET(C9,-1,0))) -> 1 | D9: =IF(G9="ETAPA",0,IF(G9="SUBETAPA",OFFSET(D9,-1,0)+1,OFFSET(D9,-1,0))) -> 3 | E9: =IF(G9="Subetapa",0,IF(G9="serviço",OFFSET(E9,-1,0)+1,OFFSET(E9,-1,0))) -> 0 | G9: Subetapa | H9: =IF(G9="Unidade Construtiva",TEXT(A9,"00"),IF(G9="Célula Construtiva",TEXT(B9,"00"),IF(G9="Etapa",CONCATENATE(TEXT(B9,"00"),".",TEXT(C9,"000")),IF(G9="Subetapa",CONCATENATE(TEXT(B9,"00"),".",TEXT(C9,"000"),".",TEXT(D9,"000")),IF(G9="Serviço",CONCATENATE(TEXT(B9,"00"),".",TEXT(C9,"000"),".",TEXT(D9,"000"),".",TEXT(E9,"000")),""))))) -> 01.001.003 | I9: Consultorias | J9: 1 | K9: vb | L9: 119868.78 | M9: Custo do hotel
A10: =IF($G10="UNIDADE CONSTRUTIVA",OFFSET(A10,0,0)+1,LARGE(A$3:A9,1)) -> 1 | B10: =IF(G10="UNIDADE CONSTRUTIVA",0,IF(G10="CÉLULA CONSTRUTIVA",OFFSET(B10,-1,0)+1,OFFSET(B10,-1,0))) -> 1 | C10: =IF(G10="CÉLULA CONSTRUTIVA",0,IF(G10="ETAPA",OFFSET(C10,-1,0)+1,OFFSET(C10,-1,0))) -> 1 | D10: =IF(G10="ETAPA",0,IF(G10="SUBETAPA",OFFSET(D10,-1,0)+1,OFFSET(D10,-1,0))) -> 4 | E10: =IF(G10="Subetapa",0,IF(G10="serviço",OFFSET(E10,-1,0)+1,OFFSET(E10,-1,0))) -> 0 | G10: Subetapa | H10: =IF(G10="Unidade Construtiva",TEXT(A10,"00"),IF(G10="Célula Construtiva",TEXT(B10,"00"),IF(G10="Etapa",CONCATENATE(TEXT(B10,"00"),".",TEXT(C10,"000")),IF(G10="Subetapa",CONCATENATE(TEXT(B10,"00"),".",TEXT(C10,"000"),".",TEXT(D10,"000")),IF(G10="Serviço",CONCATENATE(TEXT(B10,"00"),".",TEXT(C10,"000"),".",TEXT(D10,"000"),".",TEXT(E10,"000")),""))))) -> 01.001.004 | I10: Ensaios | J10: 1 | K10: vb | L10: 49119.741
A11: =IF($G11="UNIDADE CONSTRUTIVA",OFFSET(A11,0,0)+1,LARGE(A$3:A10,1)) -> 1 | B11: =IF(G11="UNIDADE CONSTRUTIVA",0,IF(G11="CÉLULA CONSTRUTIVA",OFFSET(B11,-1,0)+1,OFFSET(B11,-1,0))) -> 1 | C11: =IF(G11="CÉLULA CONSTRUTIVA",0,IF(G11="ETAPA",OFFSET(C11,-1,0)+1,OFFSET(C11,-1,0))) -> 2 | D11: =IF(G11="ETAPA",0,IF(G11="SUBETAPA",OFFSET(D11,-1,0)+1,OFFSET(D11,-1,0))) -> 0 | E11: =IF(G11="Subetapa",0,IF(G11="serviço",OFFSET(E11,-1,0)+1,OFFSET(E11,-1,0))) -> 0 | G11: ETAPA | H11: =IF(G11="Unidade Construtiva",TEXT(A11,"00"),IF(G11="Célula Construtiva",TEXT(B11,"00"),IF(G11="Etapa",CONCATENATE(TEXT(B11,"00"),".",TEXT(C11,"000")),IF(G11="Subetapa",CONCATENATE(TEXT(B11,"00"),".",TEXT(C11,"000"),".",TEXT(D11,"000")),IF(G11="Serviço",CONCATENATE(TEXT(B11,"00"),".",TEXT(C11,"000"),".",TEXT(D11,"000"),".",TEXT(E11,"000")),""))))) -> 01.002 | I11: TAXAS E DOCUMENTOS | L11: =L12+L13 -> 2813257
A12: =IF($G12="UNIDADE CONSTRUTIVA",OFFSET(A12,0,0)+1,LARGE(A$3:A11,1)) -> 1 | B12: =IF(G12="UNIDADE CONSTRUTIVA",0,IF(G12="CÉLULA CONSTRUTIVA",OFFSET(B12,-1,0)+1,OFFSET(B12,-1,0))) -> 1 | C12: =IF(G12="CÉLULA CONSTRUTIVA",0,IF(G12="ETAPA",OFFSET(C12,-1,0)+1,OFFSET(C12,-1,0))) -> 2 | D12: =IF(G12="ETAPA",0,IF(G12="SUBETAPA",OFFSET(D12,-1,0)+1,OFFSET(D12,-1,0))) -> 1 | E12: =IF(G12="Subetapa",0,IF(G12="serviço",OFFSET(E12,-1,0)+1,OFFSET(E12,-1,0))) -> 0 | G12: Subetapa | H12: =IF(G12="Unidade Construtiva",TEXT(A12,"00"),IF(G12="Célula Construtiva",TEXT(B12,"00"),IF(G12="Etapa",CONCATENATE(TEXT(B12,"00"),".",TEXT(C12,"000")),IF(G12="Subetapa",CONCATENATE(TEXT(B12,"00"),".",TEXT(C12,"000"),".",TEXT(D12,"000")),IF(G12="Serviço",CONCATENATE(TEXT(B12,"00"),".",TEXT(C12,"000"),".",TEXT(D12,"000"),".",TEXT(E12,"000")),""))))) -> 01.002.001 | I12: Licenciamentos, Taxas, Impostos, Aprovações e Seguros | J12: 1 | K12: vb | L12: 2685165.1 | M12: Contemplando taxas de aprovações, alvaras e seguros, incluindo outorga onerosa
A13: =IF($G13="UNIDADE CONSTRUTIVA",OFFSET(A13,0,0)+1,LARGE(A$3:A12,1)) -> 1 | B13: =IF(G13="UNIDADE CONSTRUTIVA",0,IF(G13="CÉLULA CONSTRUTIVA",OFFSET(B13,-1,0)+1,OFFSET(B13,-1,0))) -> 1 | C13: =IF(G13="CÉLULA CONSTRUTIVA",0,IF(G13="ETAPA",OFFSET(C13,-1,0)+1,OFFSET(C13,-1,0))) -> 2 | D13: =IF(G13="ETAPA",0,IF(G13="SUBETAPA",OFFSET(D13,-1,0)+1,OFFSET(D13,-1,0))) -> 2 | E13: =IF(G13="Subetapa",0,IF(G13="serviço",OFFSET(E13,-1,0)+1,OFFSET(E13,-1,0))) -> 0 | G13: Subetapa | H13: =IF(G13="Unidade Construtiva",TEXT(A13,"00"),IF(G13="Célula Construtiva",TEXT(B13,"00"),IF(G13="Etapa",CONCATENATE(TEXT(B13,"00"),".",TEXT(C13,"000")),IF(G13="Subetapa",CONCATENATE(TEXT(B13,"00"),".",TEXT(C13,"000"),".",TEXT(D13,"000")),IF(G13="Serviço",CONCATENATE(TEXT(B13,"00"),".",TEXT(C13,"000"),".",TEXT(D13,"000"),".",TEXT(E13,"000")),""))))) -> 01.002.002 | I13: Documentos | J13: 1 | K13: vb | L13: 128091.91 | M13: Memorias e etc.
A14: =IF($G14="UNIDADE CONSTRUTIVA",OFFSET(A14,0,0)+1,LARGE(A$3:A13,1)) -> 1 | B14: =IF(G14="UNIDADE CONSTRUTIVA",0,IF(G14="CÉLULA CONSTRUTIVA",OFFSET(B14,-1,0)+1,OFFSET(B14,-1,0))) -> 2 | C14: =IF(G14="CÉLULA CONSTRUTIVA",0,IF(G14="ETAPA",OFFSET(C14,-1,0)+1,OFFSET(C14,-1,0))) -> 0 | D14: =IF(G14="ETAPA",0,IF(G14="SUBETAPA",OFFSET(D14,-1,0)+1,OFFSET(D14,-1,0))) -> 2 | E14: =IF(G14="Subetapa",0,IF(G14="serviço",OFFSET(E14,-1,0)+1,OFFSET(E14,-1,0))) -> 0 | G14: CÉLULA CONSTRUTIVA | H14: =IF(G14="Unidade Construtiva",TEXT(A14,"00"),IF(G14="Célula Construtiva",TEXT(B14,"00"),IF(G14="Etapa",CONCATENATE(TEXT(B14,"00"),".",TEXT(C14,"000")),IF(G14="Subetapa",CONCATENATE(TEXT(B14,"00"),".",TEXT(C14,"000"),".",TEXT(D14,"000")),IF(G14="Serviço",CONCATENATE(TEXT(B14,"00"),".",TEXT(C14,"000"),".",TEXT(D14,"000"),".",TEXT(E14,"000")),""))))) -> 02 | I14: SERVIÇOS INICIAIS | L14: =L15+L37+L65 -> 6315344
A15: =IF($G15="UNIDADE CONSTRUTIVA",OFFSET(A15,0,0)+1,LARGE(A$3:A14,1)) -> 1 | B15: =IF(G15="UNIDADE CONSTRUTIVA",0,IF(G15="CÉLULA CONSTRUTIVA",OFFSET(B15,-1,0)+1,OFFSET(B15,-1,0))) -> 2 | C15: =IF(G15="CÉLULA CONSTRUTIVA",0,IF(G15="ETAPA",OFFSET(C15,-1,0)+1,OFFSET(C15,-1,0))) -> 1 | D15: =IF(G15="ETAPA",0,IF(G15="SUBETAPA",OFFSET(D15,-1,0)+1,OFFSET(D15,-1,0))) -> 0 | E15: =IF(G15="Subetapa",0,IF(G15="serviço",OFFSET(E15,-1,0)+1,OFFSET(E15,-1,0))) -> 0 | G15: ETAPA | H15: =IF(G15="Unidade Construtiva",TEXT(A15,"00"),IF(G15="Célula Construtiva",TEXT(B15,"00"),IF(G15="Etapa",CONCATENATE(TEXT(B15,"00"),".",TEXT(C15,"000")),IF(G15="Subetapa",CONCATENATE(TEXT(B15,"00"),".",TEXT(C15,"000"),".",TEXT(D15,"000")),IF(G15="Serviço",CONCATENATE(TEXT(B15,"00"),".",TEXT(C15,"000"),".",TEXT(D15,"000"),".",TEXT(E15,"000")),""))))) -> 02.001 | I15: SEGURANÇA, MEIO AMBIENTE, SAÚDE | L15: =SUM(L16:L36)/2 -> 1572839.3
A16: =IF($G16="UNIDADE CONSTRUTIVA",OFFSET(A16,0,0)+1,LARGE(A$3:A15,1)) -> 1 | B16: =IF(G16="UNIDADE CONSTRUTIVA",0,IF(G16="CÉLULA CONSTRUTIVA",OFFSET(B16,-1,0)+1,OFFSET(B16,-1,0))) -> 2 | C16: =IF(G16="CÉLULA CONSTRUTIVA",0,IF(G16="ETAPA",OFFSET(C16,-1,0)+1,OFFSET(C16,-1,0))) -> 1 | D16: =IF(G16="ETAPA",0,IF(G16="SUBETAPA",OFFSET(D16,-1,0)+1,OFFSET(D16,-1,0))) -> 1 | E16: =IF(G16="Subetapa",0,IF(G16="serviço",OFFSET(E16,-1,0)+1,OFFSET(E16,-1,0))) -> 0 | G16: Subetapa | H16: =IF(G16="Unidade Construtiva",TEXT(A16,"00"),IF(G16="Célula Construtiva",TEXT(B16,"00"),IF(G16="Etapa",CONCATENATE(TEXT(B16,"00"),".",TEXT(C16,"000")),IF(G16="Subetapa",CONCATENATE(TEXT(B16,"00"),".",TEXT(C16,"000"),".",TEXT(D16,"000")),IF(G16="Serviço",CONCATENATE(TEXT(B16,"00"),".",TEXT(C16,"000"),".",TEXT(D16,"000"),".",TEXT(E16,"000")),""))))) -> 02.001.001 | I16: Segurança do trabalho | L16: =L17 -> 252000
A17: =IF($G17="UNIDADE CONSTRUTIVA",OFFSET(A17,0,0)+1,LARGE(A$3:A16,1)) -> 1 | B17: =IF(G17="UNIDADE CONSTRUTIVA",0,IF(G17="CÉLULA CONSTRUTIVA",OFFSET(B17,-1,0)+1,OFFSET(B17,-1,0))) -> 2 | C17: =IF(G17="CÉLULA CONSTRUTIVA",0,IF(G17="ETAPA",OFFSET(C17,-1,0)+1,OFFSET(C17,-1,0))) -> 1 | D17: =IF(G17="ETAPA",0,IF(G17="SUBETAPA",OFFSET(D17,-1,0)+1,OFFSET(D17,-1,0))) -> 1 | E17: =IF(G17="Subetapa",0,IF(G17="serviço",OFFSET(E17,-1,0)+1,OFFSET(E17,-1,0))) -> 1 | G17: Serviço | H17: =IF(G17="Unidade Construtiva",TEXT(A17,"00"),IF(G17="Célula Construtiva",TEXT(B17,"00"),IF(G17="Etapa",CONCATENATE(TEXT(B17,"00"),".",TEXT(C17,"000")),IF(G17="Subetapa",CONCATENATE(TEXT(B17,"00"),".",TEXT(C17,"000"),".",TEXT(D17,"000")),IF(G17="Serviço",CONCATENATE(TEXT(B17,"00"),".",TEXT(C17,"000"),".",TEXT(D17,"000"),".",TEXT(E17,"000")),""))))) -> 02.001.001.001 | I17: Serviço de segurança do trabalho terceirizado | J17: 36 | K17: mes | L17: 252000 | M17: (consideração de dois técnicos com 3.500/mês de cada)
A18: =IF($G18="UNIDADE CONSTRUTIVA",OFFSET(A18,0,0)+1,LARGE(A$3:A16,1)) -> 1 | B18: =IF(G18="UNIDADE CONSTRUTIVA",0,IF(G18="CÉLULA CONSTRUTIVA",OFFSET(B18,-1,0)+1,OFFSET(B18,-1,0))) -> 2 | C18: =IF(G18="CÉLULA CONSTRUTIVA",0,IF(G18="ETAPA",OFFSET(C18,-1,0)+1,OFFSET(C18,-1,0))) -> 1 | D18: =IF(G18="ETAPA",0,IF(G18="SUBETAPA",OFFSET(D18,-1,0)+1,OFFSET(D18,-1,0))) -> 2 | E18: =IF(G18="Subetapa",0,IF(G18="serviço",OFFSET(E18,-1,0)+1,OFFSET(E18,-1,0))) -> 0 | G18: Subetapa | H18: =IF(G18="Unidade Construtiva",TEXT(A18,"00"),IF(G18="Célula Construtiva",TEXT(B18,"00"),IF(G18="Etapa",CONCATENATE(TEXT(B18,"00"),".",TEXT(C18,"000")),IF(G18="Subetapa",CONCATENATE(TEXT(B18,"00"),".",TEXT(C18,"000"),".",TEXT(D18,"000")),IF(G18="Serviço",CONCATENATE(TEXT(B18,"00"),".",TEXT(C18,"000"),".",TEXT(D18,"000"),".",TEXT(E18,"000")),""))))) -> 02.001.002 | I18: Equipamentos de proteção - GERAL | L18: =SUM(L19:L20) -> 118315.4
A19: =IF($G19="UNIDADE CONSTRUTIVA",OFFSET(A19,0,0)+1,LARGE(A$3:A17,1)) -> 1 | B19: =IF(G19="UNIDADE CONSTRUTIVA",0,IF(G19="CÉLULA CONSTRUTIVA",OFFSET(B19,-1,0)+1,OFFSET(B19,-1,0))) -> 2 | C19: =IF(G19="CÉLULA CONSTRUTIVA",0,IF(G19="ETAPA",OFFSET(C19,-1,0)+1,OFFSET(C19,-1,0))) -> 1 | D19: =IF(G19="ETAPA",0,IF(G19="SUBETAPA",OFFSET(D19,-1,0)+1,OFFSET(D19,-1,0))) -> 2 | E19: =IF(G19="Subetapa",0,IF(G19="serviço",OFFSET(E19,-1,0)+1,OFFSET(E19,-1,0))) -> 1 | G19: Serviço | H19: =IF(G19="Unidade Construtiva",TEXT(A19,"00"),IF(G19="Célula Construtiva",TEXT(B19,"00"),IF(G19="Etapa",CONCATENATE(TEXT(B19,"00"),".",TEXT(C19,"000")),IF(G19="Subetapa",CONCATENATE(TEXT(B19,"00"),".",TEXT(C19,"000"),".",TEXT(D19,"000")),IF(G19="Serviço",CONCATENATE(TEXT(B19,"00"),".",TEXT(C19,"000"),".",TEXT(D19,"000"),".",TEXT(E19,"000")),""))))) -> 02.001.002.001 | I19: Sinalização com placa indicativa fixada na estrutura | J19: 1 | K19: vb | L19: 30315.395
A20: =IF($G20="UNIDADE CONSTRUTIVA",OFFSET(A20,0,0)+1,LARGE(A$3:A18,1)) -> 1 | B20: =IF(G20="UNIDADE CONSTRUTIVA",0,IF(G20="CÉLULA CONSTRUTIVA",OFFSET(B20,-1,0)+1,OFFSET(B20,-1,0))) -> 2 | C20: =IF(G20="CÉLULA CONSTRUTIVA",0,IF(G20="ETAPA",OFFSET(C20,-1,0)+1,OFFSET(C20,-1,0))) -> 1 | D20: =IF(G20="ETAPA",0,IF(G20="SUBETAPA",OFFSET(D20,-1,0)+1,OFFSET(D20,-1,0))) -> 2 | E20: =IF(G20="Subetapa",0,IF(G20="serviço",OFFSET(E20,-1,0)+1,OFFSET(E20,-1,0))) -> 2 | G20: Serviço | H20: =IF(G20="Unidade Construtiva",TEXT(A20,"00"),IF(G20="Célula Construtiva",TEXT(B20,"00"),IF(G20="Etapa",CONCATENATE(TEXT(B20,"00"),".",TEXT(C20,"000")),IF(G20="Subetapa",CONCATENATE(TEXT(B20,"00"),".",TEXT(C20,"000"),".",TEXT(D20,"000")),IF(G20="Serviço",CONCATENATE(TEXT(B20,"00"),".",TEXT(C20,"000"),".",TEXT(D20,"000"),".",TEXT(E20,"000")),""))))) -> 02.001.002.002 | I20: Equipamentos de proteção individual | J20: 1 | K20: vb | L20: 88000
A21: =IF($G21="UNIDADE CONSTRUTIVA",OFFSET(A21,0,0)+1,LARGE(A$3:A19,1)) -> 1 | B21: =IF(G21="UNIDADE CONSTRUTIVA",0,IF(G21="CÉLULA CONSTRUTIVA",OFFSET(B21,-1,0)+1,OFFSET(B21,-1,0))) -> 2 | C21: =IF(G21="CÉLULA CONSTRUTIVA",0,IF(G21="ETAPA",OFFSET(C21,-1,0)+1,OFFSET(C21,-1,0))) -> 1 | D21: =IF(G21="ETAPA",0,IF(G21="SUBETAPA",OFFSET(D21,-1,0)+1,OFFSET(D21,-1,0))) -> 3 | E21: =IF(G21="Subetapa",0,IF(G21="serviço",OFFSET(E21,-1,0)+1,OFFSET(E21,-1,0))) -> 0 | G21: Subetapa | H21: =IF(G21="Unidade Construtiva",TEXT(A21,"00"),IF(G21="Célula Construtiva",TEXT(B21,"00"),IF(G21="Etapa",CONCATENATE(TEXT(B21,"00"),".",TEXT(C21,"000")),IF(G21="Subetapa",CONCATENATE(TEXT(B21,"00"),".",TEXT(C21,"000"),".",TEXT(D21,"000")),IF(G21="Serviço",CONCATENATE(TEXT(B21,"00"),".",TEXT(C21,"000"),".",TEXT(D21,"000"),".",TEXT(E21,"000")),""))))) -> 02.001.003 | I21: Equipamentos de proteção - HOTEL | L21: =SUM(L22:L27) -> 420021.29
A22: =IF($G22="UNIDADE CONSTRUTIVA",OFFSET(A22,0,0)+1,LARGE(A$3:A20,1)) -> 1 | B22: =IF(G22="UNIDADE CONSTRUTIVA",0,IF(G22="CÉLULA CONSTRUTIVA",OFFSET(B22,-1,0)+1,OFFSET(B22,-1,0))) -> 2 | C22: =IF(G22="CÉLULA CONSTRUTIVA",0,IF(G22="ETAPA",OFFSET(C22,-1,0)+1,OFFSET(C22,-1,0))) -> 1 | D22: =IF(G22="ETAPA",0,IF(G22="SUBETAPA",OFFSET(D22,-1,0)+1,OFFSET(D22,-1,0))) -> 3 | E22: =IF(G22="Subetapa",0,IF(G22="serviço",OFFSET(E22,-1,0)+1,OFFSET(E22,-1,0))) -> 1 | G22: Serviço | H22: =IF(G22="Unidade Construtiva",TEXT(A22,"00"),IF(G22="Célula Construtiva",TEXT(B22,"00"),IF(G22="Etapa",CONCATENATE(TEXT(B22,"00"),".",TEXT(C22,"000")),IF(G22="Subetapa",CONCATENATE(TEXT(B22,"00"),".",TEXT(C22,"000"),".",TEXT(D22,"000")),IF(G22="Serviço",CONCATENATE(TEXT(B22,"00"),".",TEXT(C22,"000"),".",TEXT(D22,"000"),".",TEXT(E22,"000")),""))))) -> 02.001.003.001 | I22: Bandeja de proteção primária | J22: 226.19 | K22: m | L22: 66574.503
A23: =IF($G23="UNIDADE CONSTRUTIVA",OFFSET(A23,0,0)+1,LARGE(A$3:A21,1)) -> 1 | B23: =IF(G23="UNIDADE CONSTRUTIVA",0,IF(G23="CÉLULA CONSTRUTIVA",OFFSET(B23,-1,0)+1,OFFSET(B23,-1,0))) -> 2 | C23: =IF(G23="CÉLULA CONSTRUTIVA",0,IF(G23="ETAPA",OFFSET(C23,-1,0)+1,OFFSET(C23,-1,0))) -> 1 | D23: =IF(G23="ETAPA",0,IF(G23="SUBETAPA",OFFSET(D23,-1,0)+1,OFFSET(D23,-1,0))) -> 3 | E23: =IF(G23="Subetapa",0,IF(G23="serviço",OFFSET(E23,-1,0)+1,OFFSET(E23,-1,0))) -> 2 | G23: Serviço | H23: =IF(G23="Unidade Construtiva",TEXT(A23,"00"),IF(G23="Célula Construtiva",TEXT(B23,"00"),IF(G23="Etapa",CONCATENATE(TEXT(B23,"00"),".",TEXT(C23,"000")),IF(G23="Subetapa",CONCATENATE(TEXT(B23,"00"),".",TEXT(C23,"000"),".",TEXT(D23,"000")),IF(G23="Serviço",CONCATENATE(TEXT(B23,"00"),".",TEXT(C23,"000"),".",TEXT(D23,"000"),".",TEXT(E23,"000")),""))))) -> 02.001.003.002 | I23: Bandeja de proteção secundária | J23: 226.19 | K23: m | L23: 47513.471
A24: =IF($G24="UNIDADE CONSTRUTIVA",OFFSET(A24,0,0)+1,LARGE(A$3:A19,1)) -> 1 | B24: =IF(G24="UNIDADE CONSTRUTIVA",0,IF(G24="CÉLULA CONSTRUTIVA",OFFSET(B24,-1,0)+1,OFFSET(B24,-1,0))) -> 2 | C24: =IF(G24="CÉLULA CONSTRUTIVA",0,IF(G24="ETAPA",OFFSET(C24,-1,0)+1,OFFSET(C24,-1,0))) -> 1 | D24: =IF(G24="ETAPA",0,IF(G24="SUBETAPA",OFFSET(D24,-1,0)+1,OFFSET(D24,-1,0))) -> 3 | E24: =IF(G24="Subetapa",0,IF(G24="serviço",OFFSET(E24,-1,0)+1,OFFSET(E24,-1,0))) -> 3 | G24: Serviço | H24: =IF(G24="Unidade Construtiva",TEXT(A24,"00"),IF(G24="Célula Construtiva",TEXT(B24,"00"),IF(G24="Etapa",CONCATENATE(TEXT(B24,"00"),".",TEXT(C24,"000")),IF(G24="Subetapa",CONCATENATE(TEXT(B24,"00"),".",TEXT(C24,"000"),".",TEXT(D24,"000")),IF(G24="Serviço",CONCATENATE(TEXT(B24,"00"),".",TEXT(C24,"000"),".",TEXT(D24,"000"),".",TEXT(E24,"000")),""))))) -> 02.001.003.003 | I24: Guarda corpo em laje pós - desforma | J24: 904.76 | K24: m | L24: 44333.24
A25: =IF($G25="UNIDADE CONSTRUTIVA",OFFSET(A25,0,0)+1,LARGE(A$3:A18,1)) -> 1 | B25: =IF(G25="UNIDADE CONSTRUTIVA",0,IF(G25="CÉLULA CONSTRUTIVA",OFFSET(B25,-1,0)+1,OFFSET(B25,-1,0))) -> 2 | C25: =IF(G25="CÉLULA CONSTRUTIVA",0,IF(G25="ETAPA",OFFSET(C25,-1,0)+1,OFFSET(C25,-1,0))) -> 1 | D25: =IF(G25="ETAPA",0,IF(G25="SUBETAPA",OFFSET(D25,-1,0)+1,OFFSET(D25,-1,0))) -> 3 | E25: =IF(G25="Subetapa",0,IF(G25="serviço",OFFSET(E25,-1,0)+1,OFFSET(E25,-1,0))) -> 4 | G25: Serviço | H25: =IF(G25="Unidade Construtiva",TEXT(A25,"00"),IF(G25="Célula Construtiva",TEXT(B25,"00"),IF(G25="Etapa",CONCATENATE(TEXT(B25,"00"),".",TEXT(C25,"000")),IF(G25="Subetapa",CONCATENATE(TEXT(B25,"00"),".",TEXT(C25,"000"),".",TEXT(D25,"000")),IF(G25="Serviço",CONCATENATE(TEXT(B25,"00"),".",TEXT(C25,"000"),".",TEXT(D25,"000"),".",TEXT(E25,"000")),""))))) -> 02.001.003.004 | I25: Fechamento removível de vãos de porta de elevador em madeira | J25: 33 | K25: m2 | L25: 656.37
A26: =IF($G26="UNIDADE CONSTRUTIVA",OFFSET(A26,0,0)+1,LARGE(A$3:A19,1)) -> 1 | B26: =IF(G26="UNIDADE CONSTRUTIVA",0,IF(G26="CÉLULA CONSTRUTIVA",OFFSET(B26,-1,0)+1,OFFSET(B26,-1,0))) -> 2 | C26: =IF(G26="CÉLULA CONSTRUTIVA",0,IF(G26="ETAPA",OFFSET(C26,-1,0)+1,OFFSET(C26,-1,0))) -> 1 | D26: =IF(G26="ETAPA",0,IF(G26="SUBETAPA",OFFSET(D26,-1,0)+1,OFFSET(D26,-1,0))) -> 3 | E26: =IF(G26="Subetapa",0,IF(G26="serviço",OFFSET(E26,-1,0)+1,OFFSET(E26,-1,0))) -> 5 | G26: Serviço | H26: =IF(G26="Unidade Construtiva",TEXT(A26,"00"),IF(G26="Célula Construtiva",TEXT(B26,"00"),IF(G26="Etapa",CONCATENATE(TEXT(B26,"00"),".",TEXT(C26,"000")),IF(G26="Subetapa",CONCATENATE(TEXT(B26,"00"),".",TEXT(C26,"000"),".",TEXT(D26,"000")),IF(G26="Serviço",CONCATENATE(TEXT(B26,"00"),".",TEXT(C26,"000"),".",TEXT(D26,"000"),".",TEXT(E26,"000")),""))))) -> 02.001.003.005 | I26: Varal de segurança com cabo de aço | J26: 904.76 | K26: m | L26: 220761.44
A27: =IF($G27="UNIDADE CONSTRUTIVA",OFFSET(A27,0,0)+1,LARGE(A$3:A20,1)) -> 1 | B27: =IF(G27="UNIDADE CONSTRUTIVA",0,IF(G27="CÉLULA CONSTRUTIVA",OFFSET(B27,-1,0)+1,OFFSET(B27,-1,0))) -> 2 | C27: =IF(G27="CÉLULA CONSTRUTIVA",0,IF(G27="ETAPA",OFFSET(C27,-1,0)+1,OFFSET(C27,-1,0))) -> 1 | D27: =IF(G27="ETAPA",0,IF(G27="SUBETAPA",OFFSET(D27,-1,0)+1,OFFSET(D27,-1,0))) -> 3 | E27: =IF(G27="Subetapa",0,IF(G27="serviço",OFFSET(E27,-1,0)+1,OFFSET(E27,-1,0))) -> 6 | G27: Serviço | H27: =IF(G27="Unidade Construtiva",TEXT(A27,"00"),IF(G27="Célula Construtiva",TEXT(B27,"00"),IF(G27="Etapa",CONCATENATE(TEXT(B27,"00"),".",TEXT(C27,"000")),IF(G27="Subetapa",CONCATENATE(TEXT(B27,"00"),".",TEXT(C27,"000"),".",TEXT(D27,"000")),IF(G27="Serviço",CONCATENATE(TEXT(B27,"00"),".",TEXT(C27,"000"),".",TEXT(D27,"000"),".",TEXT(E27,"000")),""))))) -> 02.001.003.006 | I27: Tela fachadeira reforçada com impressão digital | J27: 2678.8177 | K27: m2 | L27: 40182.265
A28: =IF($G28="UNIDADE CONSTRUTIVA",OFFSET(A28,0,0)+1,LARGE(A$3:A26,1)) -> 1 | B28: =IF(G28="UNIDADE CONSTRUTIVA",0,IF(G28="CÉLULA CONSTRUTIVA",OFFSET(B28,-1,0)+1,OFFSET(B28,-1,0))) -> 2 | C28: =IF(G28="CÉLULA CONSTRUTIVA",0,IF(G28="ETAPA",OFFSET(C28,-1,0)+1,OFFSET(C28,-1,0))) -> 1 | D28: =IF(G28="ETAPA",0,IF(G28="SUBETAPA",OFFSET(D28,-1,0)+1,OFFSET(D28,-1,0))) -> 4 | E28: =IF(G28="Subetapa",0,IF(G28="serviço",OFFSET(E28,-1,0)+1,OFFSET(E28,-1,0))) -> 0 | G28: Subetapa | H28: =IF(G28="Unidade Construtiva",TEXT(A28,"00"),IF(G28="Célula Construtiva",TEXT(B28,"00"),IF(G28="Etapa",CONCATENATE(TEXT(B28,"00"),".",TEXT(C28,"000")),IF(G28="Subetapa",CONCATENATE(TEXT(B28,"00"),".",TEXT(C28,"000"),".",TEXT(D28,"000")),IF(G28="Serviço",CONCATENATE(TEXT(B28,"00"),".",TEXT(C28,"000"),".",TEXT(D28,"000"),".",TEXT(E28,"000")),""))))) -> 02.001.004 | I28: Equipamentos de proteção - RESIDENCIAL | L28: =SUM(L29:L34) -> 613917.5
A29: =IF($G29="UNIDADE CONSTRUTIVA",OFFSET(A29,0,0)+1,LARGE(A$3:A27,1)) -> 1 | B29: =IF(G29="UNIDADE CONSTRUTIVA",0,IF(G29="CÉLULA CONSTRUTIVA",OFFSET(B29,-1,0)+1,OFFSET(B29,-1,0))) -> 2 | C29: =IF(G29="CÉLULA CONSTRUTIVA",0,IF(G29="ETAPA",OFFSET(C29,-1,0)+1,OFFSET(C29,-1,0))) -> 1 | D29: =IF(G29="ETAPA",0,IF(G29="SUBETAPA",OFFSET(D29,-1,0)+1,OFFSET(D29,-1,0))) -> 4 | E29: =IF(G29="Subetapa",0,IF(G29="serviço",OFFSET(E29,-1,0)+1,OFFSET(E29,-1,0))) -> 1 | G29: Serviço | H29: =IF(G29="Unidade Construtiva",TEXT(A29,"00"),IF(G29="Célula Construtiva",TEXT(B29,"00"),IF(G29="Etapa",CONCATENATE(TEXT(B29,"00"),".",TEXT(C29,"000")),IF(G29="Subetapa",CONCATENATE(TEXT(B29,"00"),".",TEXT(C29,"000"),".",TEXT(D29,"000")),IF(G29="Serviço",CONCATENATE(TEXT(B29,"00"),".",TEXT(C29,"000"),".",TEXT(D29,"000"),".",TEXT(E29,"000")),""))))) -> 02.001.004.001 | I29: Bandeja de proteção primária | J29: 426.23 | K29: m | L29: 125452.28
A30: =IF($G30="UNIDADE CONSTRUTIVA",OFFSET(A30,0,0)+1,LARGE(A$3:A28,1)) -> 1 | B30: =IF(G30="UNIDADE CONSTRUTIVA",0,IF(G30="CÉLULA CONSTRUTIVA",OFFSET(B30,-1,0)+1,OFFSET(B30,-1,0))) -> 2 | C30: =IF(G30="CÉLULA CONSTRUTIVA",0,IF(G30="ETAPA",OFFSET(C30,-1,0)+1,OFFSET(C30,-1,0))) -> 1 | D30: =IF(G30="ETAPA",0,IF(G30="SUBETAPA",OFFSET(D30,-1,0)+1,OFFSET(D30,-1,0))) -> 4 | E30: =IF(G30="Subetapa",0,IF(G30="serviço",OFFSET(E30,-1,0)+1,OFFSET(E30,-1,0))) -> 2 | G30: Serviço | H30: =IF(G30="Unidade Construtiva",TEXT(A30,"00"),IF(G30="Célula Construtiva",TEXT(B30,"00"),IF(G30="Etapa",CONCATENATE(TEXT(B30,"00"),".",TEXT(C30,"000")),IF(G30="Subetapa",CONCATENATE(TEXT(B30,"00"),".",TEXT(C30,"000"),".",TEXT(D30,"000")),IF(G30="Serviço",CONCATENATE(TEXT(B30,"00"),".",TEXT(C30,"000"),".",TEXT(D30,"000"),".",TEXT(E30,"000")),""))))) -> 02.001.004.002 | I30: Bandeja de proteção secundária | J30: 202.8 | K30: m | L30: 42600.168
A31: =IF($G31="UNIDADE CONSTRUTIVA",OFFSET(A31,0,0)+1,LARGE(A$3:A26,1)) -> 1 | B31: =IF(G31="UNIDADE CONSTRUTIVA",0,IF(G31="CÉLULA CONSTRUTIVA",OFFSET(B31,-1,0)+1,OFFSET(B31,-1,0))) -> 2 | C31: =IF(G31="CÉLULA CONSTRUTIVA",0,IF(G31="ETAPA",OFFSET(C31,-1,0)+1,OFFSET(C31,-1,0))) -> 1 | D31: =IF(G31="ETAPA",0,IF(G31="SUBETAPA",OFFSET(D31,-1,0)+1,OFFSET(D31,-1,0))) -> 4 | E31: =IF(G31="Subetapa",0,IF(G31="serviço",OFFSET(E31,-1,0)+1,OFFSET(E31,-1,0))) -> 3 | G31: Serviço | H31: =IF(G31="Unidade Construtiva",TEXT(A31,"00"),IF(G31="Célula Construtiva",TEXT(B31,"00"),IF(G31="Etapa",CONCATENATE(TEXT(B31,"00"),".",TEXT(C31,"000")),IF(G31="Subetapa",CONCATENATE(TEXT(B31,"00"),".",TEXT(C31,"000"),".",TEXT(D31,"000")),IF(G31="Serviço",CONCATENATE(TEXT(B31,"00"),".",TEXT(C31,"000"),".",TEXT(D31,"000"),".",TEXT(E31,"000")),""))))) -> 02.001.004.003 | I31: Guarda corpo em laje pós - desforma | J31: 811.2 | K31: m | L31: 39748.8
A32: =IF($G32="UNIDADE CONSTRUTIVA",OFFSET(A32,0,0)+1,LARGE(A$3:A25,1)) -> 1 | B32: =IF(G32="UNIDADE CONSTRUTIVA",0,IF(G32="CÉLULA CONSTRUTIVA",OFFSET(B32,-1,0)+1,OFFSET(B32,-1,0))) -> 2 | C32: =IF(G32="CÉLULA CONSTRUTIVA",0,IF(G32="ETAPA",OFFSET(C32,-1,0)+1,OFFSET(C32,-1,0))) -> 1 | D32: =IF(G32="ETAPA",0,IF(G32="SUBETAPA",OFFSET(D32,-1,0)+1,OFFSET(D32,-1,0))) -> 4 | E32: =IF(G32="Subetapa",0,IF(G32="serviço",OFFSET(E32,-1,0)+1,OFFSET(E32,-1,0))) -> 4 | G32: Serviço | H32: =IF(G32="Unidade Construtiva",TEXT(A32,"00"),IF(G32="Célula Construtiva",TEXT(B32,"00"),IF(G32="Etapa",CONCATENATE(TEXT(B32,"00"),".",TEXT(C32,"000")),IF(G32="Subetapa",CONCATENATE(TEXT(B32,"00"),".",TEXT(C32,"000"),".",TEXT(D32,"000")),IF(G32="Serviço",CONCATENATE(TEXT(B32,"00"),".",TEXT(C32,"000"),".",TEXT(D32,"000"),".",TEXT(E32,"000")),""))))) -> 02.001.004.004 | I32: Fechamento removível de vãos de porta de elevador em madeira | J32: 303.6 | K32: m2 | L32: 6038.604
A33: =IF($G33="UNIDADE CONSTRUTIVA",OFFSET(A33,0,0)+1,LARGE(A$3:A26,1)) -> 1 | B33: =IF(G33="UNIDADE CONSTRUTIVA",0,IF(G33="CÉLULA CONSTRUTIVA",OFFSET(B33,-1,0)+1,OFFSET(B33,-1,0))) -> 2 | C33: =IF(G33="CÉLULA CONSTRUTIVA",0,IF(G33="ETAPA",OFFSET(C33,-1,0)+1,OFFSET(C33,-1,0))) -> 1 | D33: =IF(G33="ETAPA",0,IF(G33="SUBETAPA",OFFSET(D33,-1,0)+1,OFFSET(D33,-1,0))) -> 4 | E33: =IF(G33="Subetapa",0,IF(G33="serviço",OFFSET(E33,-1,0)+1,OFFSET(E33,-1,0))) -> 5 | G33: Serviço | H33: =IF(G33="Unidade Construtiva",TEXT(A33,"00"),IF(G33="Célula Construtiva",TEXT(B33,"00"),IF(G33="Etapa",CONCATENATE(TEXT(B33,"00"),".",TEXT(C33,"000")),IF(G33="Subetapa",CONCATENATE(TEXT(B33,"00"),".",TEXT(C33,"000"),".",TEXT(D33,"000")),IF(G33="Serviço",CONCATENATE(TEXT(B33,"00"),".",TEXT(C33,"000"),".",TEXT(D33,"000"),".",TEXT(E33,"000")),""))))) -> 02.001.004.005 | I33: Varal de segurança com cabo de aço | J33: 811.2 | K33: m | L33: 197932.8
A34: =IF($G34="UNIDADE CONSTRUTIVA",OFFSET(A34,0,0)+1,LARGE(A$3:A27,1)) -> 1 | B34: =IF(G34="UNIDADE CONSTRUTIVA",0,IF(G34="CÉLULA CONSTRUTIVA",OFFSET(B34,-1,0)+1,OFFSET(B34,-1,0))) -> 2 | C34: =IF(G34="CÉLULA CONSTRUTIVA",0,IF(G34="ETAPA",OFFSET(C34,-1,0)+1,OFFSET(C34,-1,0))) -> 1 | D34: =IF(G34="ETAPA",0,IF(G34="SUBETAPA",OFFSET(D34,-1,0)+1,OFFSET(D34,-1,0))) -> 4 | E34: =IF(G34="Subetapa",0,IF(G34="serviço",OFFSET(E34,-1,0)+1,OFFSET(E34,-1,0))) -> 6 | G34: Serviço | H34: =IF(G34="Unidade Construtiva",TEXT(A34,"00"),IF(G34="Célula Construtiva",TEXT(B34,"00"),IF(G34="Etapa",CONCATENATE(TEXT(B34,"00"),".",TEXT(C34,"000")),IF(G34="Subetapa",CONCATENATE(TEXT(B34,"00"),".",TEXT(C34,"000"),".",TEXT(D34,"000")),IF(G34="Serviço",CONCATENATE(TEXT(B34,"00"),".",TEXT(C34,"000"),".",TEXT(D34,"000"),".",TEXT(E34,"000")),""))))) -> 02.001.004.006 | I34: Tela fachadeira reforçada com impressão digital | J34: 13476.324 | K34: m2 | L34: 202144.86
A35: =IF($G35="UNIDADE CONSTRUTIVA",OFFSET(A35,0,0)+1,LARGE(A$3:A18,1)) -> 1 | B35: =IF(G35="UNIDADE CONSTRUTIVA",0,IF(G35="CÉLULA CONSTRUTIVA",OFFSET(B35,-1,0)+1,OFFSET(B35,-1,0))) -> 2 | C35: =IF(G35="CÉLULA CONSTRUTIVA",0,IF(G35="ETAPA",OFFSET(C35,-1,0)+1,OFFSET(C35,-1,0))) -> 1 | D35: =IF(G35="ETAPA",0,IF(G35="SUBETAPA",OFFSET(D35,-1,0)+1,OFFSET(D35,-1,0))) -> 5 | E35: =IF(G35="Subetapa",0,IF(G35="serviço",OFFSET(E35,-1,0)+1,OFFSET(E35,-1,0))) -> 0 | G35: Subetapa | H35: =IF(G35="Unidade Construtiva",TEXT(A35,"00"),IF(G35="Célula Construtiva",TEXT(B35,"00"),IF(G35="Etapa",CONCATENATE(TEXT(B35,"00"),".",TEXT(C35,"000")),IF(G35="Subetapa",CONCATENATE(TEXT(B35,"00"),".",TEXT(C35,"000"),".",TEXT(D35,"000")),IF(G35="Serviço",CONCATENATE(TEXT(B35,"00"),".",TEXT(C35,"000"),".",TEXT(D35,"000"),".",TEXT(E35,"000")),""))))) -> 02.001.005 | I35: Meio ambiente | L35: =L36 -> 168585.11
A36: =IF($G36="UNIDADE CONSTRUTIVA",OFFSET(A36,0,0)+1,LARGE(A$3:A19,1)) -> 1 | B36: =IF(G36="UNIDADE CONSTRUTIVA",0,IF(G36="CÉLULA CONSTRUTIVA",OFFSET(B36,-1,0)+1,OFFSET(B36,-1,0))) -> 2 | C36: =IF(G36="CÉLULA CONSTRUTIVA",0,IF(G36="ETAPA",OFFSET(C36,-1,0)+1,OFFSET(C36,-1,0))) -> 1 | D36: =IF(G36="ETAPA",0,IF(G36="SUBETAPA",OFFSET(D36,-1,0)+1,OFFSET(D36,-1,0))) -> 5 | E36: =IF(G36="Subetapa",0,IF(G36="serviço",OFFSET(E36,-1,0)+1,OFFSET(E36,-1,0))) -> 1 | G36: Serviço | H36: =IF(G36="Unidade Construtiva",TEXT(A36,"00"),IF(G36="Célula Construtiva",TEXT(B36,"00"),IF(G36="Etapa",CONCATENATE(TEXT(B36,"00"),".",TEXT(C36,"000")),IF(G36="Subetapa",CONCATENATE(TEXT(B36,"00"),".",TEXT(C36,"000"),".",TEXT(D36,"000")),IF(G36="Serviço",CONCATENATE(TEXT(B36,"00"),".",TEXT(C36,"000"),".",TEXT(D36,"000"),".",TEXT(E36,"000")),""))))) -> 02.001.005.001 | I36: Meio ambiente | J36: 1 | K36: vb | L36: 168585.11
A37: =IF($G37="UNIDADE CONSTRUTIVA",OFFSET(A37,0,0)+1,LARGE(A$3:A35,1)) -> 1 | B37: =IF(G37="UNIDADE CONSTRUTIVA",0,IF(G37="CÉLULA CONSTRUTIVA",OFFSET(B37,-1,0)+1,OFFSET(B37,-1,0))) -> 2 | C37: =IF(G37="CÉLULA CONSTRUTIVA",0,IF(G37="ETAPA",OFFSET(C37,-1,0)+1,OFFSET(C37,-1,0))) -> 2 | D37: =IF(G37="ETAPA",0,IF(G37="SUBETAPA",OFFSET(D37,-1,0)+1,OFFSET(D37,-1,0))) -> 0 | E37: =IF(G37="Subetapa",0,IF(G37="serviço",OFFSET(E37,-1,0)+1,OFFSET(E37,-1,0))) -> 1 | G37: ETAPA | H37: =IF(G37="Unidade Construtiva",TEXT(A37,"00"),IF(G37="Célula Construtiva",TEXT(B37,"00"),IF(G37="Etapa",CONCATENATE(TEXT(B37,"00"),".",TEXT(C37,"000")),IF(G37="Subetapa",CONCATENATE(TEXT(B37,"00"),".",TEXT(C37,"000"),".",TEXT(D37,"000")),IF(G37="Serviço",CONCATENATE(TEXT(B37,"00"),".",TEXT(C37,"000"),".",TEXT(D37,"000"),".",TEXT(E37,"000")),""))))) -> 02.002 | I37: ADMINISTRAÇÃO E CANTEIRO DE OBRA | L37: =SUM(L38:L64)/2 -> 4742504.7
A38: =IF($G38="UNIDADE CONSTRUTIVA",OFFSET(A38,0,0)+1,LARGE(A$3:A37,1)) -> 1 | B38: =IF(G38="UNIDADE CONSTRUTIVA",0,IF(G38="CÉLULA CONSTRUTIVA",OFFSET(B38,-1,0)+1,OFFSET(B38,-1,0))) -> 2 | C38: =IF(G38="CÉLULA CONSTRUTIVA",0,IF(G38="ETAPA",OFFSET(C38,-1,0)+1,OFFSET(C38,-1,0))) -> 2 | D38: =IF(G38="ETAPA",0,IF(G38="SUBETAPA",OFFSET(D38,-1,0)+1,OFFSET(D38,-1,0))) -> 1 | E38: =IF(G38="Subetapa",0,IF(G38="serviço",OFFSET(E38,-1,0)+1,OFFSET(E38,-1,0))) -> 0 | G38: Subetapa | H38: =IF(G38="Unidade Construtiva",TEXT(A38,"00"),IF(G38="Célula Construtiva",TEXT(B38,"00"),IF(G38="Etapa",CONCATENATE(TEXT(B38,"00"),".",TEXT(C38,"000")),IF(G38="Subetapa",CONCATENATE(TEXT(B38,"00"),".",TEXT(C38,"000"),".",TEXT(D38,"000")),IF(G38="Serviço",CONCATENATE(TEXT(B38,"00"),".",TEXT(C38,"000"),".",TEXT(D38,"000"),".",TEXT(E38,"000")),""))))) -> 02.002.001 | I38: Equipe de Gestão e Apoio - HOTEL | L38: =SUM(L39:L44) -> 1185234.2
A39: =IF($G39="UNIDADE CONSTRUTIVA",OFFSET(A39,0,0)+1,LARGE(A$3:A32,1)) -> 1 | B39: =IF(G39="UNIDADE CONSTRUTIVA",0,IF(G39="CÉLULA CONSTRUTIVA",OFFSET(B39,-1,0)+1,OFFSET(B39,-1,0))) -> 2 | C39: =IF(G39="CÉLULA CONSTRUTIVA",0,IF(G39="ETAPA",OFFSET(C39,-1,0)+1,OFFSET(C39,-1,0))) -> 2 | D39: =IF(G39="ETAPA",0,IF(G39="SUBETAPA",OFFSET(D39,-1,0)+1,OFFSET(D39,-1,0))) -> 1 | E39: =IF(G39="Subetapa",0,IF(G39="serviço",OFFSET(E39,-1,0)+1,OFFSET(E39,-1,0))) -> 1 | G39: Serviço | H39: =IF(G39="Unidade Construtiva",TEXT(A39,"00"),IF(G39="Célula Construtiva",TEXT(B39,"00"),IF(G39="Etapa",CONCATENATE(TEXT(B39,"00"),".",TEXT(C39,"000")),IF(G39="Subetapa",CONCATENATE(TEXT(B39,"00"),".",TEXT(C39,"000"),".",TEXT(D39,"000")),IF(G39="Serviço",CONCATENATE(TEXT(B39,"00"),".",TEXT(C39,"000"),".",TEXT(D39,"000"),".",TEXT(E39,"000")),""))))) -> 02.002.001.001 | I39: Engenheiro civil pleno | J39: 24 | K39: mes | L39: 288000
A40: =IF($G40="UNIDADE CONSTRUTIVA",OFFSET(A40,0,0)+1,LARGE(A$3:A33,1)) -> 1 | B40: =IF(G40="UNIDADE CONSTRUTIVA",0,IF(G40="CÉLULA CONSTRUTIVA",OFFSET(B40,-1,0)+1,OFFSET(B40,-1,0))) -> 2 | C40: =IF(G40="CÉLULA CONSTRUTIVA",0,IF(G40="ETAPA",OFFSET(C40,-1,0)+1,OFFSET(C40,-1,0))) -> 2 | D40: =IF(G40="ETAPA",0,IF(G40="SUBETAPA",OFFSET(D40,-1,0)+1,OFFSET(D40,-1,0))) -> 1 | E40: =IF(G40="Subetapa",0,IF(G40="serviço",OFFSET(E40,-1,0)+1,OFFSET(E40,-1,0))) -> 2 | G40: Serviço | H40: =IF(G40="Unidade Construtiva",TEXT(A40,"00"),IF(G40="Célula Construtiva",TEXT(B40,"00"),IF(G40="Etapa",CONCATENATE(TEXT(B40,"00"),".",TEXT(C40,"000")),IF(G40="Subetapa",CONCATENATE(TEXT(B40,"00"),".",TEXT(C40,"000"),".",TEXT(D40,"000")),IF(G40="Serviço",CONCATENATE(TEXT(B40,"00"),".",TEXT(C40,"000"),".",TEXT(D40,"000"),".",TEXT(E40,"000")),""))))) -> 02.002.001.002 | I40: Almoxarife | J40: 24 | K40: mes | L40: 102106.75
A41: =IF($G41="UNIDADE CONSTRUTIVA",OFFSET(A41,0,0)+1,LARGE(A$3:A34,1)) -> 1 | B41: =IF(G41="UNIDADE CONSTRUTIVA",0,IF(G41="CÉLULA CONSTRUTIVA",OFFSET(B41,-1,0)+1,OFFSET(B41,-1,0))) -> 2 | C41: =IF(G41="CÉLULA CONSTRUTIVA",0,IF(G41="ETAPA",OFFSET(C41,-1,0)+1,OFFSET(C41,-1,0))) -> 2 | D41: =IF(G41="ETAPA",0,IF(G41="SUBETAPA",OFFSET(D41,-1,0)+1,OFFSET(D41,-1,0))) -> 1 | E41: =IF(G41="Subetapa",0,IF(G41="serviço",OFFSET(E41,-1,0)+1,OFFSET(E41,-1,0))) -> 3 | G41: Serviço | H41: =IF(G41="Unidade Construtiva",TEXT(A41,"00"),IF(G41="Célula Construtiva",TEXT(B41,"00"),IF(G41="Etapa",CONCATENATE(TEXT(B41,"00"),".",TEXT(C41,"000")),IF(G41="Subetapa",CONCATENATE(TEXT(B41,"00"),".",TEXT(C41,"000"),".",TEXT(D41,"000")),IF(G41="Serviço",CONCATENATE(TEXT(B41,"00"),".",TEXT(C41,"000"),".",TEXT(D41,"000"),".",TEXT(E41,"000")),""))))) -> 02.002.001.003 | I41: Mestre de obras | J41: 24 | K41: mes | L41: 200875.01
A42: =IF($G42="UNIDADE CONSTRUTIVA",OFFSET(A42,0,0)+1,LARGE(A$3:A35,1)) -> 1 | B42: =IF(G42="UNIDADE CONSTRUTIVA",0,IF(G42="CÉLULA CONSTRUTIVA",OFFSET(B42,-1,0)+1,OFFSET(B42,-1,0))) -> 2 | C42: =IF(G42="CÉLULA CONSTRUTIVA",0,IF(G42="ETAPA",OFFSET(C42,-1,0)+1,OFFSET(C42,-1,0))) -> 2 | D42: =IF(G42="ETAPA",0,IF(G42="SUBETAPA",OFFSET(D42,-1,0)+1,OFFSET(D42,-1,0))) -> 1 | E42: =IF(G42="Subetapa",0,IF(G42="serviço",OFFSET(E42,-1,0)+1,OFFSET(E42,-1,0))) -> 4 | G42: Serviço | H42: =IF(G42="Unidade Construtiva",TEXT(A42,"00"),IF(G42="Célula Construtiva",TEXT(B42,"00"),IF(G42="Etapa",CONCATENATE(TEXT(B42,"00"),".",TEXT(C42,"000")),IF(G42="Subetapa",CONCATENATE(TEXT(B42,"00"),".",TEXT(C42,"000"),".",TEXT(D42,"000")),IF(G42="Serviço",CONCATENATE(TEXT(B42,"00"),".",TEXT(C42,"000"),".",TEXT(D42,"000"),".",TEXT(E42,"000")),""))))) -> 02.002.001.004 | I42: Estagiário | J42: 24 | K42: mes | L42: 72000
A43: =IF($G43="UNIDADE CONSTRUTIVA",OFFSET(A43,0,0)+1,LARGE(A$3:A36,1)) -> 1 | B43: =IF(G43="UNIDADE CONSTRUTIVA",0,IF(G43="CÉLULA CONSTRUTIVA",OFFSET(B43,-1,0)+1,OFFSET(B43,-1,0))) -> 2 | C43: =IF(G43="CÉLULA CONSTRUTIVA",0,IF(G43="ETAPA",OFFSET(C43,-1,0)+1,OFFSET(C43,-1,0))) -> 2 | D43: =IF(G43="ETAPA",0,IF(G43="SUBETAPA",OFFSET(D43,-1,0)+1,OFFSET(D43,-1,0))) -> 1 | E43: =IF(G43="Subetapa",0,IF(G43="serviço",OFFSET(E43,-1,0)+1,OFFSET(E43,-1,0))) -> 5 | G43: Serviço | H43: =IF(G43="Unidade Construtiva",TEXT(A43,"00"),IF(G43="Célula Construtiva",TEXT(B43,"00"),IF(G43="Etapa",CONCATENATE(TEXT(B43,"00"),".",TEXT(C43,"000")),IF(G43="Subetapa",CONCATENATE(TEXT(B43,"00"),".",TEXT(C43,"000"),".",TEXT(D43,"000")),IF(G43="Serviço",CONCATENATE(TEXT(B43,"00"),".",TEXT(C43,"000"),".",TEXT(D43,"000"),".",TEXT(E43,"000")),""))))) -> 02.002.001.005 | I43: Serviço de vigilância 24h | J43: 24 | K43: mes | L43: 366252.48
A44: =IF($G44="UNIDADE CONSTRUTIVA",OFFSET(A44,0,0)+1,LARGE(A$3:A37,1)) -> 1 | B44: =IF(G44="UNIDADE CONSTRUTIVA",0,IF(G44="CÉLULA CONSTRUTIVA",OFFSET(B44,-1,0)+1,OFFSET(B44,-1,0))) -> 2 | C44: =IF(G44="CÉLULA CONSTRUTIVA",0,IF(G44="ETAPA",OFFSET(C44,-1,0)+1,OFFSET(C44,-1,0))) -> 2 | D44: =IF(G44="ETAPA",0,IF(G44="SUBETAPA",OFFSET(D44,-1,0)+1,OFFSET(D44,-1,0))) -> 1 | E44: =IF(G44="Subetapa",0,IF(G44="serviço",OFFSET(E44,-1,0)+1,OFFSET(E44,-1,0))) -> 6 | G44: Serviço | H44: =IF(G44="Unidade Construtiva",TEXT(A44,"00"),IF(G44="Célula Construtiva",TEXT(B44,"00"),IF(G44="Etapa",CONCATENATE(TEXT(B44,"00"),".",TEXT(C44,"000")),IF(G44="Subetapa",CONCATENATE(TEXT(B44,"00"),".",TEXT(C44,"000"),".",TEXT(D44,"000")),IF(G44="Serviço",CONCATENATE(TEXT(B44,"00"),".",TEXT(C44,"000"),".",TEXT(D44,"000"),".",TEXT(E44,"000")),""))))) -> 02.002.001.006 | I44: Operador de grua | J44: 10 | K44: mes | L44: 156000
A45: =IF($G45="UNIDADE CONSTRUTIVA",OFFSET(A45,0,0)+1,LARGE(A$3:A44,1)) -> 1 | B45: =IF(G45="UNIDADE CONSTRUTIVA",0,IF(G45="CÉLULA CONSTRUTIVA",OFFSET(B45,-1,0)+1,OFFSET(B45,-1,0))) -> 2 | C45: =IF(G45="CÉLULA CONSTRUTIVA",0,IF(G45="ETAPA",OFFSET(C45,-1,0)+1,OFFSET(C45,-1,0))) -> 2 | D45: =IF(G45="ETAPA",0,IF(G45="SUBETAPA",OFFSET(D45,-1,0)+1,OFFSET(D45,-1,0))) -> 2 | E45: =IF(G45="Subetapa",0,IF(G45="serviço",OFFSET(E45,-1,0)+1,OFFSET(E45,-1,0))) -> 0 | G45: Subetapa | H45: =IF(G45="Unidade Construtiva",TEXT(A45,"00"),IF(G45="Célula Construtiva",TEXT(B45,"00"),IF(G45="Etapa",CONCATENATE(TEXT(B45,"00"),".",TEXT(C45,"000")),IF(G45="Subetapa",CONCATENATE(TEXT(B45,"00"),".",TEXT(C45,"000"),".",TEXT(D45,"000")),IF(G45="Serviço",CONCATENATE(TEXT(B45,"00"),".",TEXT(C45,"000"),".",TEXT(D45,"000"),".",TEXT(E45,"000")),""))))) -> 02.002.002 | I45: Equipe de Gestão e Apoio - RESIDENCIAL | L45: =SUM(L46:L52) -> 2264911.4
A46: =IF($G46="UNIDADE CONSTRUTIVA",OFFSET(A46,0,0)+1,LARGE(A$3:A39,1)) -> 1 | B46: =IF(G46="UNIDADE CONSTRUTIVA",0,IF(G46="CÉLULA CONSTRUTIVA",OFFSET(B46,-1,0)+1,OFFSET(B46,-1,0))) -> 2 | C46: =IF(G46="CÉLULA CONSTRUTIVA",0,IF(G46="ETAPA",OFFSET(C46,-1,0)+1,OFFSET(C46,-1,0))) -> 2 | D46: =IF(G46="ETAPA",0,IF(G46="SUBETAPA",OFFSET(D46,-1,0)+1,OFFSET(D46,-1,0))) -> 2 | E46: =IF(G46="Subetapa",0,IF(G46="serviço",OFFSET(E46,-1,0)+1,OFFSET(E46,-1,0))) -> 1 | G46: Serviço | H46: =IF(G46="Unidade Construtiva",TEXT(A46,"00"),IF(G46="Célula Construtiva",TEXT(B46,"00"),IF(G46="Etapa",CONCATENATE(TEXT(B46,"00"),".",TEXT(C46,"000")),IF(G46="Subetapa",CONCATENATE(TEXT(B46,"00"),".",TEXT(C46,"000"),".",TEXT(D46,"000")),IF(G46="Serviço",CONCATENATE(TEXT(B46,"00"),".",TEXT(C46,"000"),".",TEXT(D46,"000"),".",TEXT(E46,"000")),""))))) -> 02.002.002.001 | I46: Engenheiro civil senior | J46: 36 | K46: mes | L46: 648000
A47: =IF($G47="UNIDADE CONSTRUTIVA",OFFSET(A47,0,0)+1,LARGE(A$3:A40,1)) -> 1 | B47: =IF(G47="UNIDADE CONSTRUTIVA",0,IF(G47="CÉLULA CONSTRUTIVA",OFFSET(B47,-1,0)+1,OFFSET(B47,-1,0))) -> 2 | C47: =IF(G47="CÉLULA CONSTRUTIVA",0,IF(G47="ETAPA",OFFSET(C47,-1,0)+1,OFFSET(C47,-1,0))) -> 2 | D47: =IF(G47="ETAPA",0,IF(G47="SUBETAPA",OFFSET(D47,-1,0)+1,OFFSET(D47,-1,0))) -> 2 | E47: =IF(G47="Subetapa",0,IF(G47="serviço",OFFSET(E47,-1,0)+1,OFFSET(E47,-1,0))) -> 2 | G47: Serviço | H47: =IF(G47="Unidade Construtiva",TEXT(A47,"00"),IF(G47="Célula Construtiva",TEXT(B47,"00"),IF(G47="Etapa",CONCATENATE(TEXT(B47,"00"),".",TEXT(C47,"000")),IF(G47="Subetapa",CONCATENATE(TEXT(B47,"00"),".",TEXT(C47,"000"),".",TEXT(D47,"000")),IF(G47="Serviço",CONCATENATE(TEXT(B47,"00"),".",TEXT(C47,"000"),".",TEXT(D47,"000"),".",TEXT(E47,"000")),""))))) -> 02.002.002.002 | I47: Auxliar de engenharia | J47: 36 | K47: mes | L47: 180000
A48: =IF($G48="UNIDADE CONSTRUTIVA",OFFSET(A48,0,0)+1,LARGE(A$3:A40,1)) -> 1 | B48: =IF(G48="UNIDADE CONSTRUTIVA",0,IF(G48="CÉLULA CONSTRUTIVA",OFFSET(B48,-1,0)+1,OFFSET(B48,-1,0))) -> 2 | C48: =IF(G48="CÉLULA CONSTRUTIVA",0,IF(G48="ETAPA",OFFSET(C48,-1,0)+1,OFFSET(C48,-1,0))) -> 2 | D48: =IF(G48="ETAPA",0,IF(G48="SUBETAPA",OFFSET(D48,-1,0)+1,OFFSET(D48,-1,0))) -> 2 | E48: =IF(G48="Subetapa",0,IF(G48="serviço",OFFSET(E48,-1,0)+1,OFFSET(E48,-1,0))) -> 3 | G48: Serviço | H48: =IF(G48="Unidade Construtiva",TEXT(A48,"00"),IF(G48="Célula Construtiva",TEXT(B48,"00"),IF(G48="Etapa",CONCATENATE(TEXT(B48,"00"),".",TEXT(C48,"000")),IF(G48="Subetapa",CONCATENATE(TEXT(B48,"00"),".",TEXT(C48,"000"),".",TEXT(D48,"000")),IF(G48="Serviço",CONCATENATE(TEXT(B48,"00"),".",TEXT(C48,"000"),".",TEXT(D48,"000"),".",TEXT(E48,"000")),""))))) -> 02.002.002.003 | I48: Almoxarife | J48: 36 | K48: mes | L48: 153160.13
A49: =IF($G49="UNIDADE CONSTRUTIVA",OFFSET(A49,0,0)+1,LARGE(A$3:A41,1)) -> 1 | B49: =IF(G49="UNIDADE CONSTRUTIVA",0,IF(G49="CÉLULA CONSTRUTIVA",OFFSET(B49,-1,0)+1,OFFSET(B49,-1,0))) -> 2 | C49: =IF(G49="CÉLULA CONSTRUTIVA",0,IF(G49="ETAPA",OFFSET(C49,-1,0)+1,OFFSET(C49,-1,0))) -> 2 | D49: =IF(G49="ETAPA",0,IF(G49="SUBETAPA",OFFSET(D49,-1,0)+1,OFFSET(D49,-1,0))) -> 2 | E49: =IF(G49="Subetapa",0,IF(G49="serviço",OFFSET(E49,-1,0)+1,OFFSET(E49,-1,0))) -> 4 | G49: Serviço | H49: =IF(G49="Unidade Construtiva",TEXT(A49,"00"),IF(G49="Célula Construtiva",TEXT(B49,"00"),IF(G49="Etapa",CONCATENATE(TEXT(B49,"00"),".",TEXT(C49,"000")),IF(G49="Subetapa",CONCATENATE(TEXT(B49,"00"),".",TEXT(C49,"000"),".",TEXT(D49,"000")),IF(G49="Serviço",CONCATENATE(TEXT(B49,"00"),".",TEXT(C49,"000"),".",TEXT(D49,"000"),".",TEXT(E49,"000")),""))))) -> 02.002.002.004 | I49: Mestre de obras | J49: 36 | K49: mes | L49: 602625.02
A50: =IF($G50="UNIDADE CONSTRUTIVA",OFFSET(A50,0,0)+1,LARGE(A$3:A42,1)) -> 1 | B50: =IF(G50="UNIDADE CONSTRUTIVA",0,IF(G50="CÉLULA CONSTRUTIVA",OFFSET(B50,-1,0)+1,OFFSET(B50,-1,0))) -> 2 | C50: =IF(G50="CÉLULA CONSTRUTIVA",0,IF(G50="ETAPA",OFFSET(C50,-1,0)+1,OFFSET(C50,-1,0))) -> 2 | D50: =IF(G50="ETAPA",0,IF(G50="SUBETAPA",OFFSET(D50,-1,0)+1,OFFSET(D50,-1,0))) -> 2 | E50: =IF(G50="Subetapa",0,IF(G50="serviço",OFFSET(E50,-1,0)+1,OFFSET(E50,-1,0))) -> 5 | G50: Serviço | H50: =IF(G50="Unidade Construtiva",TEXT(A50,"00"),IF(G50="Célula Construtiva",TEXT(B50,"00"),IF(G50="Etapa",CONCATENATE(TEXT(B50,"00"),".",TEXT(C50,"000")),IF(G50="Subetapa",CONCATENATE(TEXT(B50,"00"),".",TEXT(C50,"000"),".",TEXT(D50,"000")),IF(G50="Serviço",CONCATENATE(TEXT(B50,"00"),".",TEXT(C50,"000"),".",TEXT(D50,"000"),".",TEXT(E50,"000")),""))))) -> 02.002.002.005 | I50: Estagiário | J50: 36 | K50: mes | L50: 108000
A51: =IF($G51="UNIDADE CONSTRUTIVA",OFFSET(A51,0,0)+1,LARGE(A$3:A43,1)) -> 1 | B51: =IF(G51="UNIDADE CONSTRUTIVA",0,IF(G51="CÉLULA CONSTRUTIVA",OFFSET(B51,-1,0)+1,OFFSET(B51,-1,0))) -> 2 | C51: =IF(G51="CÉLULA CONSTRUTIVA",0,IF(G51="ETAPA",OFFSET(C51,-1,0)+1,OFFSET(C51,-1,0))) -> 2 | D51: =IF(G51="ETAPA",0,IF(G51="SUBETAPA",OFFSET(D51,-1,0)+1,OFFSET(D51,-1,0))) -> 2 | E51: =IF(G51="Subetapa",0,IF(G51="serviço",OFFSET(E51,-1,0)+1,OFFSET(E51,-1,0))) -> 6 | G51: Serviço | H51: =IF(G51="Unidade Construtiva",TEXT(A51,"00"),IF(G51="Célula Construtiva",TEXT(B51,"00"),IF(G51="Etapa",CONCATENATE(TEXT(B51,"00"),".",TEXT(C51,"000")),IF(G51="Subetapa",CONCATENATE(TEXT(B51,"00"),".",TEXT(C51,"000"),".",TEXT(D51,"000")),IF(G51="Serviço",CONCATENATE(TEXT(B51,"00"),".",TEXT(C51,"000"),".",TEXT(D51,"000"),".",TEXT(E51,"000")),""))))) -> 02.002.002.006 | I51: Serviço de vigilância 24h | J51: 12 | K51: mes | L51: 183126.24
A52: =IF($G52="UNIDADE CONSTRUTIVA",OFFSET(A52,0,0)+1,LARGE(A$3:A44,1)) -> 1 | B52: =IF(G52="UNIDADE CONSTRUTIVA",0,IF(G52="CÉLULA CONSTRUTIVA",OFFSET(B52,-1,0)+1,OFFSET(B52,-1,0))) -> 2 | C52: =IF(G52="CÉLULA CONSTRUTIVA",0,IF(G52="ETAPA",OFFSET(C52,-1,0)+1,OFFSET(C52,-1,0))) -> 2 | D52: =IF(G52="ETAPA",0,IF(G52="SUBETAPA",OFFSET(D52,-1,0)+1,OFFSET(D52,-1,0))) -> 2 | E52: =IF(G52="Subetapa",0,IF(G52="serviço",OFFSET(E52,-1,0)+1,OFFSET(E52,-1,0))) -> 7 | G52: Serviço | H52: =IF(G52="Unidade Construtiva",TEXT(A52,"00"),IF(G52="Célula Construtiva",TEXT(B52,"00"),IF(G52="Etapa",CONCATENATE(TEXT(B52,"00"),".",TEXT(C52,"000")),IF(G52="Subetapa",CONCATENATE(TEXT(B52,"00"),".",TEXT(C52,"000"),".",TEXT(D52,"000")),IF(G52="Serviço",CONCATENATE(TEXT(B52,"00"),".",TEXT(C52,"000"),".",TEXT(D52,"000"),".",TEXT(E52,"000")),""))))) -> 02.002.002.007 | I52: Operador de grua | J52: 25 | K52: mes | L52: 390000
A53: =IF($G53="UNIDADE CONSTRUTIVA",OFFSET(A53,0,0)+1,LARGE(A$3:A38,1)) -> 1 | B53: =IF(G53="UNIDADE CONSTRUTIVA",0,IF(G53="CÉLULA CONSTRUTIVA",OFFSET(B53,-1,0)+1,OFFSET(B53,-1,0))) -> 2 | C53: =IF(G53="CÉLULA CONSTRUTIVA",0,IF(G53="ETAPA",OFFSET(C53,-1,0)+1,OFFSET(C53,-1,0))) -> 2 | D53: =IF(G53="ETAPA",0,IF(G53="SUBETAPA",OFFSET(D53,-1,0)+1,OFFSET(D53,-1,0))) -> 3 | E53: =IF(G53="Subetapa",0,IF(G53="serviço",OFFSET(E53,-1,0)+1,OFFSET(E53,-1,0))) -> 0 | G53: Subetapa | H53: =IF(G53="Unidade Construtiva",TEXT(A53,"00"),IF(G53="Célula Construtiva",TEXT(B53,"00"),IF(G53="Etapa",CONCATENATE(TEXT(B53,"00"),".",TEXT(C53,"000")),IF(G53="Subetapa",CONCATENATE(TEXT(B53,"00"),".",TEXT(C53,"000"),".",TEXT(D53,"000")),IF(G53="Serviço",CONCATENATE(TEXT(B53,"00"),".",TEXT(C53,"000"),".",TEXT(D53,"000"),".",TEXT(E53,"000")),""))))) -> 02.002.003 | I53: Operação inicial de canteiro | L53: =L54 -> 81552.254
A54: =IF($G54="UNIDADE CONSTRUTIVA",OFFSET(A54,0,0)+1,LARGE(A$3:A46,1)) -> 1 | B54: =IF(G54="UNIDADE CONSTRUTIVA",0,IF(G54="CÉLULA CONSTRUTIVA",OFFSET(B54,-1,0)+1,OFFSET(B54,-1,0))) -> 2 | C54: =IF(G54="CÉLULA CONSTRUTIVA",0,IF(G54="ETAPA",OFFSET(C54,-1,0)+1,OFFSET(C54,-1,0))) -> 2 | D54: =IF(G54="ETAPA",0,IF(G54="SUBETAPA",OFFSET(D54,-1,0)+1,OFFSET(D54,-1,0))) -> 3 | E54: =IF(G54="Subetapa",0,IF(G54="serviço",OFFSET(E54,-1,0)+1,OFFSET(E54,-1,0))) -> 1 | G54: Serviço | H54: =IF(G54="Unidade Construtiva",TEXT(A54,"00"),IF(G54="Célula Construtiva",TEXT(B54,"00"),IF(G54="Etapa",CONCATENATE(TEXT(B54,"00"),".",TEXT(C54,"000")),IF(G54="Subetapa",CONCATENATE(TEXT(B54,"00"),".",TEXT(C54,"000"),".",TEXT(D54,"000")),IF(G54="Serviço",CONCATENATE(TEXT(B54,"00"),".",TEXT(C54,"000"),".",TEXT(D54,"000"),".",TEXT(E54,"000")),""))))) -> 02.002.003.001 | I54: Locação da obra | J54: 682.96 | K54: m | L54: 81552.254
A55: =IF($G55="UNIDADE CONSTRUTIVA",OFFSET(A55,0,0)+1,LARGE(A$3:A53,1)) -> 1 | B55: =IF(G55="UNIDADE CONSTRUTIVA",0,IF(G55="CÉLULA CONSTRUTIVA",OFFSET(B55,-1,0)+1,OFFSET(B55,-1,0))) -> 2 | C55: =IF(G55="CÉLULA CONSTRUTIVA",0,IF(G55="ETAPA",OFFSET(C55,-1,0)+1,OFFSET(C55,-1,0))) -> 2 | D55: =IF(G55="ETAPA",0,IF(G55="SUBETAPA",OFFSET(D55,-1,0)+1,OFFSET(D55,-1,0))) -> 4 | E55: =IF(G55="Subetapa",0,IF(G55="serviço",OFFSET(E55,-1,0)+1,OFFSET(E55,-1,0))) -> 0 | G55: Subetapa | H55: =IF(G55="Unidade Construtiva",TEXT(A55,"00"),IF(G55="Célula Construtiva",TEXT(B55,"00"),IF(G55="Etapa",CONCATENATE(TEXT(B55,"00"),".",TEXT(C55,"000")),IF(G55="Subetapa",CONCATENATE(TEXT(B55,"00"),".",TEXT(C55,"000"),".",TEXT(D55,"000")),IF(G55="Serviço",CONCATENATE(TEXT(B55,"00"),".",TEXT(C55,"000"),".",TEXT(D55,"000"),".",TEXT(E55,"000")),""))))) -> 02.002.004 | I55: Despesas de consumo e manutenção | L55: =L56 -> 619198.04
A56: =IF($G56="UNIDADE CONSTRUTIVA",OFFSET(A56,0,0)+1,LARGE(A$3:A54,1)) -> 1 | B56: =IF(G56="UNIDADE CONSTRUTIVA",0,IF(G56="CÉLULA CONSTRUTIVA",OFFSET(B56,-1,0)+1,OFFSET(B56,-1,0))) -> 2 | C56: =IF(G56="CÉLULA CONSTRUTIVA",0,IF(G56="ETAPA",OFFSET(C56,-1,0)+1,OFFSET(C56,-1,0))) -> 2 | D56: =IF(G56="ETAPA",0,IF(G56="SUBETAPA",OFFSET(D56,-1,0)+1,OFFSET(D56,-1,0))) -> 4 | E56: =IF(G56="Subetapa",0,IF(G56="serviço",OFFSET(E56,-1,0)+1,OFFSET(E56,-1,0))) -> 1 | G56: Serviço | H56: =IF(G56="Unidade Construtiva",TEXT(A56,"00"),IF(G56="Célula Construtiva",TEXT(B56,"00"),IF(G56="Etapa",CONCATENATE(TEXT(B56,"00"),".",TEXT(C56,"000")),IF(G56="Subetapa",CONCATENATE(TEXT(B56,"00"),".",TEXT(C56,"000"),".",TEXT(D56,"000")),IF(G56="Serviço",CONCATENATE(TEXT(B56,"00"),".",TEXT(C56,"000"),".",TEXT(D56,"000"),".",TEXT(E56,"000")),""))))) -> 02.002.004.001 | I56: Despesas de consumo e manutenção | J56: 1 | K56: vb | L56: 619198.04
A57: =IF($G57="UNIDADE CONSTRUTIVA",OFFSET(A57,0,0)+1,LARGE(A$3:A55,1)) -> 1 | B57: =IF(G57="UNIDADE CONSTRUTIVA",0,IF(G57="CÉLULA CONSTRUTIVA",OFFSET(B57,-1,0)+1,OFFSET(B57,-1,0))) -> 2 | C57: =IF(G57="CÉLULA CONSTRUTIVA",0,IF(G57="ETAPA",OFFSET(C57,-1,0)+1,OFFSET(C57,-1,0))) -> 2 | D57: =IF(G57="ETAPA",0,IF(G57="SUBETAPA",OFFSET(D57,-1,0)+1,OFFSET(D57,-1,0))) -> 5 | E57: =IF(G57="Subetapa",0,IF(G57="serviço",OFFSET(E57,-1,0)+1,OFFSET(E57,-1,0))) -> 0 | G57: Subetapa | H57: =IF(G57="Unidade Construtiva",TEXT(A57,"00"),IF(G57="Célula Construtiva",TEXT(B57,"00"),IF(G57="Etapa",CONCATENATE(TEXT(B57,"00"),".",TEXT(C57,"000")),IF(G57="Subetapa",CONCATENATE(TEXT(B57,"00"),".",TEXT(C57,"000"),".",TEXT(D57,"000")),IF(G57="Serviço",CONCATENATE(TEXT(B57,"00"),".",TEXT(C57,"000"),".",TEXT(D57,"000"),".",TEXT(E57,"000")),""))))) -> 02.002.005 | I57: Instalações provisórias | L57: =SUM(L58:L61) -> 544694.5
A58: =IF($G58="UNIDADE CONSTRUTIVA",OFFSET(A58,0,0)+1,LARGE(A$3:A50,1)) -> 1 | B58: =IF(G58="UNIDADE CONSTRUTIVA",0,IF(G58="CÉLULA CONSTRUTIVA",OFFSET(B58,-1,0)+1,OFFSET(B58,-1,0))) -> 2 | C58: =IF(G58="CÉLULA CONSTRUTIVA",0,IF(G58="ETAPA",OFFSET(C58,-1,0)+1,OFFSET(C58,-1,0))) -> 2 | D58: =IF(G58="ETAPA",0,IF(G58="SUBETAPA",OFFSET(D58,-1,0)+1,OFFSET(D58,-1,0))) -> 5 | E58: =IF(G58="Subetapa",0,IF(G58="serviço",OFFSET(E58,-1,0)+1,OFFSET(E58,-1,0))) -> 1 | G58: Serviço | H58: =IF(G58="Unidade Construtiva",TEXT(A58,"00"),IF(G58="Célula Construtiva",TEXT(B58,"00"),IF(G58="Etapa",CONCATENATE(TEXT(B58,"00"),".",TEXT(C58,"000")),IF(G58="Subetapa",CONCATENATE(TEXT(B58,"00"),".",TEXT(C58,"000"),".",TEXT(D58,"000")),IF(G58="Serviço",CONCATENATE(TEXT(B58,"00"),".",TEXT(C58,"000"),".",TEXT(D58,"000"),".",TEXT(E58,"000")),""))))) -> 02.002.005.001 | I58: Locação de banheiro químico | J58: 10 | K58: mes | L58: 171000
A59: =IF($G59="UNIDADE CONSTRUTIVA",OFFSET(A59,0,0)+1,LARGE(A$3:A51,1)) -> 1 | B59: =IF(G59="UNIDADE CONSTRUTIVA",0,IF(G59="CÉLULA CONSTRUTIVA",OFFSET(B59,-1,0)+1,OFFSET(B59,-1,0))) -> 2 | C59: =IF(G59="CÉLULA CONSTRUTIVA",0,IF(G59="ETAPA",OFFSET(C59,-1,0)+1,OFFSET(C59,-1,0))) -> 2 | D59: =IF(G59="ETAPA",0,IF(G59="SUBETAPA",OFFSET(D59,-1,0)+1,OFFSET(D59,-1,0))) -> 5 | E59: =IF(G59="Subetapa",0,IF(G59="serviço",OFFSET(E59,-1,0)+1,OFFSET(E59,-1,0))) -> 2 | G59: Serviço | H59: =IF(G59="Unidade Construtiva",TEXT(A59,"00"),IF(G59="Célula Construtiva",TEXT(B59,"00"),IF(G59="Etapa",CONCATENATE(TEXT(B59,"00"),".",TEXT(C59,"000")),IF(G59="Subetapa",CONCATENATE(TEXT(B59,"00"),".",TEXT(C59,"000"),".",TEXT(D59,"000")),IF(G59="Serviço",CONCATENATE(TEXT(B59,"00"),".",TEXT(C59,"000"),".",TEXT(D59,"000"),".",TEXT(E59,"000")),""))))) -> 02.002.005.002 | I59: Instalações de canteiro | J59: 1 | K59: vb | L59: 275594.5
A60: =IF($G60="UNIDADE CONSTRUTIVA",OFFSET(A60,0,0)+1,LARGE(A$3:A51,1)) -> 1 | B60: =IF(G60="UNIDADE CONSTRUTIVA",0,IF(G60="CÉLULA CONSTRUTIVA",OFFSET(B60,-1,0)+1,OFFSET(B60,-1,0))) -> 2 | C60: =IF(G60="CÉLULA CONSTRUTIVA",0,IF(G60="ETAPA",OFFSET(C60,-1,0)+1,OFFSET(C60,-1,0))) -> 2 | D60: =IF(G60="ETAPA",0,IF(G60="SUBETAPA",OFFSET(D60,-1,0)+1,OFFSET(D60,-1,0))) -> 5 | E60: =IF(G60="Subetapa",0,IF(G60="serviço",OFFSET(E60,-1,0)+1,OFFSET(E60,-1,0))) -> 3 | G60: Serviço | H60: =IF(G60="Unidade Construtiva",TEXT(A60,"00"),IF(G60="Célula Construtiva",TEXT(B60,"00"),IF(G60="Etapa",CONCATENATE(TEXT(B60,"00"),".",TEXT(C60,"000")),IF(G60="Subetapa",CONCATENATE(TEXT(B60,"00"),".",TEXT(C60,"000"),".",TEXT(D60,"000")),IF(G60="Serviço",CONCATENATE(TEXT(B60,"00"),".",TEXT(C60,"000"),".",TEXT(D60,"000"),".",TEXT(E60,"000")),""))))) -> 02.002.005.003 | I60: Mobiliário de apoio a obra | J60: 1 | K60: vb | L60: 31600
A61: =IF($G61="UNIDADE CONSTRUTIVA",OFFSET(A61,0,0)+1,LARGE(A$3:A52,1)) -> 1 | B61: =IF(G61="UNIDADE CONSTRUTIVA",0,IF(G61="CÉLULA CONSTRUTIVA",OFFSET(B61,-1,0)+1,OFFSET(B61,-1,0))) -> 2 | C61: =IF(G61="CÉLULA CONSTRUTIVA",0,IF(G61="ETAPA",OFFSET(C61,-1,0)+1,OFFSET(C61,-1,0))) -> 2 | D61: =IF(G61="ETAPA",0,IF(G61="SUBETAPA",OFFSET(D61,-1,0)+1,OFFSET(D61,-1,0))) -> 5 | E61: =IF(G61="Subetapa",0,IF(G61="serviço",OFFSET(E61,-1,0)+1,OFFSET(E61,-1,0))) -> 4 | G61: Serviço | H61: =IF(G61="Unidade Construtiva",TEXT(A61,"00"),IF(G61="Célula Construtiva",TEXT(B61,"00"),IF(G61="Etapa",CONCATENATE(TEXT(B61,"00"),".",TEXT(C61,"000")),IF(G61="Subetapa",CONCATENATE(TEXT(B61,"00"),".",TEXT(C61,"000"),".",TEXT(D61,"000")),IF(G61="Serviço",CONCATENATE(TEXT(B61,"00"),".",TEXT(C61,"000"),".",TEXT(D61,"000"),".",TEXT(E61,"000")),""))))) -> 02.002.005.004 | I61: Equipamentos escritório - aquisição | J61: 1 | K61: vb | L61: 66500
A62: =IF($G62="UNIDADE CONSTRUTIVA",OFFSET(A62,0,0)+1,LARGE(A$3:A57,1)) -> 1 | B62: =IF(G62="UNIDADE CONSTRUTIVA",0,IF(G62="CÉLULA CONSTRUTIVA",OFFSET(B62,-1,0)+1,OFFSET(B62,-1,0))) -> 2 | C62: =IF(G62="CÉLULA CONSTRUTIVA",0,IF(G62="ETAPA",OFFSET(C62,-1,0)+1,OFFSET(C62,-1,0))) -> 2 | D62: =IF(G62="ETAPA",0,IF(G62="SUBETAPA",OFFSET(D62,-1,0)+1,OFFSET(D62,-1,0))) -> 6 | E62: =IF(G62="Subetapa",0,IF(G62="serviço",OFFSET(E62,-1,0)+1,OFFSET(E62,-1,0))) -> 0 | G62: Subetapa | H62: =IF(G62="Unidade Construtiva",TEXT(A62,"00"),IF(G62="Célula Construtiva",TEXT(B62,"00"),IF(G62="Etapa",CONCATENATE(TEXT(B62,"00"),".",TEXT(C62,"000")),IF(G62="Subetapa",CONCATENATE(TEXT(B62,"00"),".",TEXT(C62,"000"),".",TEXT(D62,"000")),IF(G62="Serviço",CONCATENATE(TEXT(B62,"00"),".",TEXT(C62,"000"),".",TEXT(D62,"000"),".",TEXT(E62,"000")),""))))) -> 02.002.006 | I62: Ligações Provisórias | L62: =SUM(L63:L64) -> 46914.274
A63: =IF($G63="UNIDADE CONSTRUTIVA",OFFSET(A63,0,0)+1,LARGE(A$3:A54,1)) -> 1 | B63: =IF(G63="UNIDADE CONSTRUTIVA",0,IF(G63="CÉLULA CONSTRUTIVA",OFFSET(B63,-1,0)+1,OFFSET(B63,-1,0))) -> 2 | C63: =IF(G63="CÉLULA CONSTRUTIVA",0,IF(G63="ETAPA",OFFSET(C63,-1,0)+1,OFFSET(C63,-1,0))) -> 2 | D63: =IF(G63="ETAPA",0,IF(G63="SUBETAPA",OFFSET(D63,-1,0)+1,OFFSET(D63,-1,0))) -> 6 | E63: =IF(G63="Subetapa",0,IF(G63="serviço",OFFSET(E63,-1,0)+1,OFFSET(E63,-1,0))) -> 1 | G63: Serviço | H63: =IF(G63="Unidade Construtiva",TEXT(A63,"00"),IF(G63="Célula Construtiva",TEXT(B63,"00"),IF(G63="Etapa",CONCATENATE(TEXT(B63,"00"),".",TEXT(C63,"000")),IF(G63="Subetapa",CONCATENATE(TEXT(B63,"00"),".",TEXT(C63,"000"),".",TEXT(D63,"000")),IF(G63="Serviço",CONCATENATE(TEXT(B63,"00"),".",TEXT(C63,"000"),".",TEXT(D63,"000"),".",TEXT(E63,"000")),""))))) -> 02.002.006.001 | I63: Instalações Provisórias: Redes de Água Fria, Esgoto e Drenagem | J63: 1 | K63: vb | L63: 23457.137
A64: =IF($G64="UNIDADE CONSTRUTIVA",OFFSET(A64,0,0)+1,LARGE(A$3:A55,1)) -> 1 | B64: =IF(G64="UNIDADE CONSTRUTIVA",0,IF(G64="CÉLULA CONSTRUTIVA",OFFSET(B64,-1,0)+1,OFFSET(B64,-1,0))) -> 2 | C64: =IF(G64="CÉLULA CONSTRUTIVA",0,IF(G64="ETAPA",OFFSET(C64,-1,0)+1,OFFSET(C64,-1,0))) -> 2 | D64: =IF(G64="ETAPA",0,IF(G64="SUBETAPA",OFFSET(D64,-1,0)+1,OFFSET(D64,-1,0))) -> 6 | E64: =IF(G64="Subetapa",0,IF(G64="serviço",OFFSET(E64,-1,0)+1,OFFSET(E64,-1,0))) -> 2 | G64: Serviço | H64: =IF(G64="Unidade Construtiva",TEXT(A64,"00"),IF(G64="Célula Construtiva",TEXT(B64,"00"),IF(G64="Etapa",CONCATENATE(TEXT(B64,"00"),".",TEXT(C64,"000")),IF(G64="Subetapa",CONCATENATE(TEXT(B64,"00"),".",TEXT(C64,"000"),".",TEXT(D64,"000")),IF(G64="Serviço",CONCATENATE(TEXT(B64,"00"),".",TEXT(C64,"000"),".",TEXT(D64,"000"),".",TEXT(E64,"000")),""))))) -> 02.002.006.002 | I64: Instalações Provisórias: Redes Elétrica, Comunicação e Dados | J64: 1 | K64: vb | L64: 23457.137
A65: =IF($G65="UNIDADE CONSTRUTIVA",OFFSET(A65,0,0)+1,LARGE(A$3:A62,1)) -> 1 | B65: =IF(G65="UNIDADE CONSTRUTIVA",0,IF(G65="CÉLULA CONSTRUTIVA",OFFSET(B65,-1,0)+1,OFFSET(B65,-1,0))) -> 2 | C65: =IF(G65="CÉLULA CONSTRUTIVA",0,IF(G65="ETAPA",OFFSET(C65,-1,0)+1,OFFSET(C65,-1,0))) -> 3 | D65: =IF(G65="ETAPA",0,IF(G65="SUBETAPA",OFFSET(D65,-1,0)+1,OFFSET(D65,-1,0))) -> 0 | E65: =IF(G65="Subetapa",0,IF(G65="serviço",OFFSET(E65,-1,0)+1,OFFSET(E65,-1,0))) -> 2 | G65: ETAPA | H65: =IF(G65="Unidade Construtiva",TEXT(A65,"00"),IF(G65="Célula Construtiva",TEXT(B65,"00"),IF(G65="Etapa",CONCATENATE(TEXT(B65,"00"),".",TEXT(C65,"000")),IF(G65="Subetapa",CONCATENATE(TEXT(B65,"00"),".",TEXT(C65,"000"),".",TEXT(D65,"000")),IF(G65="Serviço",CONCATENATE(TEXT(B65,"00"),".",TEXT(C65,"000"),".",TEXT(D65,"000"),".",TEXT(E65,"000")),""))))) -> 02.003 | I65: SERVIÇOS PRELIMINARES
A66: =IF($G66="UNIDADE CONSTRUTIVA",OFFSET(A66,0,0)+1,LARGE(A$3:A65,1)) -> 1 | B66: =IF(G66="UNIDADE CONSTRUTIVA",0,IF(G66="CÉLULA CONSTRUTIVA",OFFSET(B66,-1,0)+1,OFFSET(B66,-1,0))) -> 2 | C66: =IF(G66="CÉLULA CONSTRUTIVA",0,IF(G66="ETAPA",OFFSET(C66,-1,0)+1,OFFSET(C66,-1,0))) -> 3 | D66: =IF(G66="ETAPA",0,IF(G66="SUBETAPA",OFFSET(D66,-1,0)+1,OFFSET(D66,-1,0))) -> 1 | E66: =IF(G66="Subetapa",0,IF(G66="serviço",OFFSET(E66,-1,0)+1,OFFSET(E66,-1,0))) -> 0 | G66: Subetapa | H66: =IF(G66="Unidade Construtiva",TEXT(A66,"00"),IF(G66="Célula Construtiva",TEXT(B66,"00"),IF(G66="Etapa",CONCATENATE(TEXT(B66,"00"),".",TEXT(C66,"000")),IF(G66="Subetapa",CONCATENATE(TEXT(B66,"00"),".",TEXT(C66,"000"),".",TEXT(D66,"000")),IF(G66="Serviço",CONCATENATE(TEXT(B66,"00"),".",TEXT(C66,"000"),".",TEXT(D66,"000"),".",TEXT(E66,"000")),""))))) -> 02.003.001 | I66: Demolições | M66: Custos já incorridos
A67: =IF($G67="UNIDADE CONSTRUTIVA",OFFSET(A67,0,0)+1,LARGE(A$3:A66,1)) -> 1 | B67: =IF(G67="UNIDADE CONSTRUTIVA",0,IF(G67="CÉLULA CONSTRUTIVA",OFFSET(B67,-1,0)+1,OFFSET(B67,-1,0))) -> 2 | C67: =IF(G67="CÉLULA CONSTRUTIVA",0,IF(G67="ETAPA",OFFSET(C67,-1,0)+1,OFFSET(C67,-1,0))) -> 3 | D67: =IF(G67="ETAPA",0,IF(G67="SUBETAPA",OFFSET(D67,-1,0)+1,OFFSET(D67,-1,0))) -> 2 | E67: =IF(G67="Subetapa",0,IF(G67="serviço",OFFSET(E67,-1,0)+1,OFFSET(E67,-1,0))) -> 0 | G67: Subetapa | H67: =IF(G67="Unidade Construtiva",TEXT(A67,"00"),IF(G67="Célula Construtiva",TEXT(B67,"00"),IF(G67="Etapa",CONCATENATE(TEXT(B67,"00"),".",TEXT(C67,"000")),IF(G67="Subetapa",CONCATENATE(TEXT(B67,"00"),".",TEXT(C67,"000"),".",TEXT(D67,"000")),IF(G67="Serviço",CONCATENATE(TEXT(B67,"00"),".",TEXT(C67,"000"),".",TEXT(D67,"000"),".",TEXT(E67,"000")),""))))) -> 02.003.002 | I67: Limpeza de terreno | M67: Custos já incorridos
A68: =IF($G68="UNIDADE CONSTRUTIVA",OFFSET(A68,0,0)+1,LARGE(A$3:A67,1)) -> 1 | B68: =IF(G68="UNIDADE CONSTRUTIVA",0,IF(G68="CÉLULA CONSTRUTIVA",OFFSET(B68,-1,0)+1,OFFSET(B68,-1,0))) -> 3 | C68: =IF(G68="CÉLULA CONSTRUTIVA",0,IF(G68="ETAPA",OFFSET(C68,-1,0)+1,OFFSET(C68,-1,0))) -> 0 | D68: =IF(G68="ETAPA",0,IF(G68="SUBETAPA",OFFSET(D68,-1,0)+1,OFFSET(D68,-1,0))) -> 2 | E68: =IF(G68="Subetapa",0,IF(G68="serviço",OFFSET(E68,-1,0)+1,OFFSET(E68,-1,0))) -> 0 | G68: CÉLULA CONSTRUTIVA | H68: =IF(G68="Unidade Construtiva",TEXT(A68,"00"),IF(G68="Célula Construtiva",TEXT(B68,"00"),IF(G68="Etapa",CONCATENATE(TEXT(B68,"00"),".",TEXT(C68,"000")),IF(G68="Subetapa",CONCATENATE(TEXT(B68,"00"),".",TEXT(C68,"000"),".",TEXT(D68,"000")),IF(G68="Serviço",CONCATENATE(TEXT(B68,"00"),".",TEXT(C68,"000"),".",TEXT(D68,"000"),".",TEXT(E68,"000")),""))))) -> 03 | I68: EQUIPAMENTOS | L68: =L69 -> 2995860.6
A69: =IF($G69="UNIDADE CONSTRUTIVA",OFFSET(A69,0,0)+1,LARGE(A$3:A68,1)) -> 1 | B69: =IF(G69="UNIDADE CONSTRUTIVA",0,IF(G69="CÉLULA CONSTRUTIVA",OFFSET(B69,-1,0)+1,OFFSET(B69,-1,0))) -> 3 | C69: =IF(G69="CÉLULA CONSTRUTIVA",0,IF(G69="ETAPA",OFFSET(C69,-1,0)+1,OFFSET(C69,-1,0))) -> 1 | D69: =IF(G69="ETAPA",0,IF(G69="SUBETAPA",OFFSET(D69,-1,0)+1,OFFSET(D69,-1,0))) -> 0 | E69: =IF(G69="Subetapa",0,IF(G69="serviço",OFFSET(E69,-1,0)+1,OFFSET(E69,-1,0))) -> 0 | G69: ETAPA | H69: =IF(G69="Unidade Construtiva",TEXT(A69,"00"),IF(G69="Célula Construtiva",TEXT(B69,"00"),IF(G69="Etapa",CONCATENATE(TEXT(B69,"00"),".",TEXT(C69,"000")),IF(G69="Subetapa",CONCATENATE(TEXT(B69,"00"),".",TEXT(C69,"000"),".",TEXT(D69,"000")),IF(G69="Serviço",CONCATENATE(TEXT(B69,"00"),".",TEXT(C69,"000"),".",TEXT(D69,"000"),".",TEXT(E69,"000")),""))))) -> 03.001 | I69: EQUIPAMENTOS | L69: =SUM(L70:L89)/2 -> 2995860.6
A70: =IF($G70="UNIDADE CONSTRUTIVA",OFFSET(A70,0,0)+1,LARGE(A$3:A69,1)) -> 1 | B70: =IF(G70="UNIDADE CONSTRUTIVA",0,IF(G70="CÉLULA CONSTRUTIVA",OFFSET(B70,-1,0)+1,OFFSET(B70,-1,0))) -> 3 | C70: =IF(G70="CÉLULA CONSTRUTIVA",0,IF(G70="ETAPA",OFFSET(C70,-1,0)+1,OFFSET(C70,-1,0))) -> 1 | D70: =IF(G70="ETAPA",0,IF(G70="SUBETAPA",OFFSET(D70,-1,0)+1,OFFSET(D70,-1,0))) -> 1 | E70: =IF(G70="Subetapa",0,IF(G70="serviço",OFFSET(E70,-1,0)+1,OFFSET(E70,-1,0))) -> 0 | G70: Subetapa | H70: =IF(G70="Unidade Construtiva",TEXT(A70,"00"),IF(G70="Célula Construtiva",TEXT(B70,"00"),IF(G70="Etapa",CONCATENATE(TEXT(B70,"00"),".",TEXT(C70,"000")),IF(G70="Subetapa",CONCATENATE(TEXT(B70,"00"),".",TEXT(C70,"000"),".",TEXT(D70,"000")),IF(G70="Serviço",CONCATENATE(TEXT(B70,"00"),".",TEXT(C70,"000"),".",TEXT(D70,"000"),".",TEXT(E70,"000")),""))))) -> 03.001.001 | I70: Equipamentos de obra | L70: =SUM(L71:L83) -> 2208384
A71: =IF($G71="UNIDADE CONSTRUTIVA",OFFSET(A71,0,0)+1,LARGE(A$3:A70,1)) -> 1 | B71: =IF(G71="UNIDADE CONSTRUTIVA",0,IF(G71="CÉLULA CONSTRUTIVA",OFFSET(B71,-1,0)+1,OFFSET(B71,-1,0))) -> 3 | C71: =IF(G71="CÉLULA CONSTRUTIVA",0,IF(G71="ETAPA",OFFSET(C71,-1,0)+1,OFFSET(C71,-1,0))) -> 1 | D71: =IF(G71="ETAPA",0,IF(G71="SUBETAPA",OFFSET(D71,-1,0)+1,OFFSET(D71,-1,0))) -> 1 | E71: =IF(G71="Subetapa",0,IF(G71="serviço",OFFSET(E71,-1,0)+1,OFFSET(E71,-1,0))) -> 1 | G71: Serviço | H71: =IF(G71="Unidade Construtiva",TEXT(A71,"00"),IF(G71="Célula Construtiva",TEXT(B71,"00"),IF(G71="Etapa",CONCATENATE(TEXT(B71,"00"),".",TEXT(C71,"000")),IF(G71="Subetapa",CONCATENATE(TEXT(B71,"00"),".",TEXT(C71,"000"),".",TEXT(D71,"000")),IF(G71="Serviço",CONCATENATE(TEXT(B71,"00"),".",TEXT(C71,"000"),".",TEXT(D71,"000"),".",TEXT(E71,"000")),""))))) -> 03.001.001.001 | I71: Ferramentas - aquisição/manutenção | J71: 1 | K71: vb | L71: 132800
A72: =IF($G72="UNIDADE CONSTRUTIVA",OFFSET(A72,0,0)+1,LARGE(A$3:A71,1)) -> 1 | B72: =IF(G72="UNIDADE CONSTRUTIVA",0,IF(G72="CÉLULA CONSTRUTIVA",OFFSET(B72,-1,0)+1,OFFSET(B72,-1,0))) -> 3 | C72: =IF(G72="CÉLULA CONSTRUTIVA",0,IF(G72="ETAPA",OFFSET(C72,-1,0)+1,OFFSET(C72,-1,0))) -> 1 | D72: =IF(G72="ETAPA",0,IF(G72="SUBETAPA",OFFSET(D72,-1,0)+1,OFFSET(D72,-1,0))) -> 1 | E72: =IF(G72="Subetapa",0,IF(G72="serviço",OFFSET(E72,-1,0)+1,OFFSET(E72,-1,0))) -> 2 | G72: Serviço | H72: =IF(G72="Unidade Construtiva",TEXT(A72,"00"),IF(G72="Célula Construtiva",TEXT(B72,"00"),IF(G72="Etapa",CONCATENATE(TEXT(B72,"00"),".",TEXT(C72,"000")),IF(G72="Subetapa",CONCATENATE(TEXT(B72,"00"),".",TEXT(C72,"000"),".",TEXT(D72,"000")),IF(G72="Serviço",CONCATENATE(TEXT(B72,"00"),".",TEXT(C72,"000"),".",TEXT(D72,"000"),".",TEXT(E72,"000")),""))))) -> 03.001.001.002 | I72: Mobilização e desmobilização de grua | J72: 1 | K72: Un. | L72: 24000
A73: =IF($G73="UNIDADE CONSTRUTIVA",OFFSET(A73,0,0)+1,LARGE(A$3:A11,1)) -> 1 | B73: =IF(G73="UNIDADE CONSTRUTIVA",0,IF(G73="CÉLULA CONSTRUTIVA",OFFSET(B73,-1,0)+1,OFFSET(B73,-1,0))) -> 3 | C73: =IF(G73="CÉLULA CONSTRUTIVA",0,IF(G73="ETAPA",OFFSET(C73,-1,0)+1,OFFSET(C73,-1,0))) -> 1 | D73: =IF(G73="ETAPA",0,IF(G73="SUBETAPA",OFFSET(D73,-1,0)+1,OFFSET(D73,-1,0))) -> 1 | E73: =IF(G73="Subetapa",0,IF(G73="serviço",OFFSET(E73,-1,0)+1,OFFSET(E73,-1,0))) -> 3 | G73: Serviço | H73: =IF(G73="Unidade Construtiva",TEXT(A73,"00"),IF(G73="Célula Construtiva",TEXT(B73,"00"),IF(G73="Etapa",CONCATENATE(TEXT(B73,"00"),".",TEXT(C73,"000")),IF(G73="Subetapa",CONCATENATE(TEXT(B73,"00"),".",TEXT(C73,"000"),".",TEXT(D73,"000")),IF(G73="Serviço",CONCATENATE(TEXT(B73,"00"),".",TEXT(C73,"000"),".",TEXT(D73,"000"),".",TEXT(E73,"000")),""))))) -> 03.001.001.003 | I73: Locação de gruas - 1 unidades RESIDENCIAL | J73: 19 | K73: mes | L73: 501600
A74: =IF($G74="UNIDADE CONSTRUTIVA",OFFSET(A74,0,0)+1,LARGE(A$3:A12,1)) -> 1 | B74: =IF(G74="UNIDADE CONSTRUTIVA",0,IF(G74="CÉLULA CONSTRUTIVA",OFFSET(B74,-1,0)+1,OFFSET(B74,-1,0))) -> 3 | C74: =IF(G74="CÉLULA CONSTRUTIVA",0,IF(G74="ETAPA",OFFSET(C74,-1,0)+1,OFFSET(C74,-1,0))) -> 1 | D74: =IF(G74="ETAPA",0,IF(G74="SUBETAPA",OFFSET(D74,-1,0)+1,OFFSET(D74,-1,0))) -> 1 | E74: =IF(G74="Subetapa",0,IF(G74="serviço",OFFSET(E74,-1,0)+1,OFFSET(E74,-1,0))) -> 4 | G74: Serviço | H74: =IF(G74="Unidade Construtiva",TEXT(A74,"00"),IF(G74="Célula Construtiva",TEXT(B74,"00"),IF(G74="Etapa",CONCATENATE(TEXT(B74,"00"),".",TEXT(C74,"000")),IF(G74="Subetapa",CONCATENATE(TEXT(B74,"00"),".",TEXT(C74,"000"),".",TEXT(D74,"000")),IF(G74="Serviço",CONCATENATE(TEXT(B74,"00"),".",TEXT(C74,"000"),".",TEXT(D74,"000"),".",TEXT(E74,"000")),""))))) -> 03.001.001.004 | I74: Serviço de montagem de grua RESIDENCIAL | J74: 1 | K74: Un. | L74: 15000
A75: =IF($G75="UNIDADE CONSTRUTIVA",OFFSET(A75,0,0)+1,LARGE(A$3:A13,1)) -> 1 | B75: =IF(G75="UNIDADE CONSTRUTIVA",0,IF(G75="CÉLULA CONSTRUTIVA",OFFSET(B75,-1,0)+1,OFFSET(B75,-1,0))) -> 3 | C75: =IF(G75="CÉLULA CONSTRUTIVA",0,IF(G75="ETAPA",OFFSET(C75,-1,0)+1,OFFSET(C75,-1,0))) -> 1 | D75: =IF(G75="ETAPA",0,IF(G75="SUBETAPA",OFFSET(D75,-1,0)+1,OFFSET(D75,-1,0))) -> 1 | E75: =IF(G75="Subetapa",0,IF(G75="serviço",OFFSET(E75,-1,0)+1,OFFSET(E75,-1,0))) -> 5 | G75: Serviço | H75: =IF(G75="Unidade Construtiva",TEXT(A75,"00"),IF(G75="Célula Construtiva",TEXT(B75,"00"),IF(G75="Etapa",CONCATENATE(TEXT(B75,"00"),".",TEXT(C75,"000")),IF(G75="Subetapa",CONCATENATE(TEXT(B75,"00"),".",TEXT(C75,"000"),".",TEXT(D75,"000")),IF(G75="Serviço",CONCATENATE(TEXT(B75,"00"),".",TEXT(C75,"000"),".",TEXT(D75,"000"),".",TEXT(E75,"000")),""))))) -> 03.001.001.005 | I75: Serviço de desmontagem de grua RESIDENCIAL | J75: 1 | K75: Un. | L75: 40000
A76: =IF($G76="UNIDADE CONSTRUTIVA",OFFSET(A76,0,0)+1,LARGE(A$3:A14,1)) -> 1 | B76: =IF(G76="UNIDADE CONSTRUTIVA",0,IF(G76="CÉLULA CONSTRUTIVA",OFFSET(B76,-1,0)+1,OFFSET(B76,-1,0))) -> 3 | C76: =IF(G76="CÉLULA CONSTRUTIVA",0,IF(G76="ETAPA",OFFSET(C76,-1,0)+1,OFFSET(C76,-1,0))) -> 1 | D76: =IF(G76="ETAPA",0,IF(G76="SUBETAPA",OFFSET(D76,-1,0)+1,OFFSET(D76,-1,0))) -> 1 | E76: =IF(G76="Subetapa",0,IF(G76="serviço",OFFSET(E76,-1,0)+1,OFFSET(E76,-1,0))) -> 6 | G76: Serviço | H76: =IF(G76="Unidade Construtiva",TEXT(A76,"00"),IF(G76="Célula Construtiva",TEXT(B76,"00"),IF(G76="Etapa",CONCATENATE(TEXT(B76,"00"),".",TEXT(C76,"000")),IF(G76="Subetapa",CONCATENATE(TEXT(B76,"00"),".",TEXT(C76,"000"),".",TEXT(D76,"000")),IF(G76="Serviço",CONCATENATE(TEXT(B76,"00"),".",TEXT(C76,"000"),".",TEXT(D76,"000"),".",TEXT(E76,"000")),""))))) -> 03.001.001.006 | I76: Ascensão da grua RESIDENCIAL | J76: 9 | K76: Un. | L76: 81000 | M76: a cada 3 pavimentos
A77: =IF($G77="UNIDADE CONSTRUTIVA",OFFSET(A77,0,0)+1,LARGE(A$3:A15,1)) -> 1 | B77: =IF(G77="UNIDADE CONSTRUTIVA",0,IF(G77="CÉLULA CONSTRUTIVA",OFFSET(B77,-1,0)+1,OFFSET(B77,-1,0))) -> 3 | C77: =IF(G77="CÉLULA CONSTRUTIVA",0,IF(G77="ETAPA",OFFSET(C77,-1,0)+1,OFFSET(C77,-1,0))) -> 1 | D77: =IF(G77="ETAPA",0,IF(G77="SUBETAPA",OFFSET(D77,-1,0)+1,OFFSET(D77,-1,0))) -> 1 | E77: =IF(G77="Subetapa",0,IF(G77="serviço",OFFSET(E77,-1,0)+1,OFFSET(E77,-1,0))) -> 7 | G77: Serviço | H77: =IF(G77="Unidade Construtiva",TEXT(A77,"00"),IF(G77="Célula Construtiva",TEXT(B77,"00"),IF(G77="Etapa",CONCATENATE(TEXT(B77,"00"),".",TEXT(C77,"000")),IF(G77="Subetapa",CONCATENATE(TEXT(B77,"00"),".",TEXT(C77,"000"),".",TEXT(D77,"000")),IF(G77="Serviço",CONCATENATE(TEXT(B77,"00"),".",TEXT(C77,"000"),".",TEXT(D77,"000"),".",TEXT(E77,"000")),""))))) -> 03.001.001.007 | I77: Mobilização e desmobilização de cremalheira | J77: 3 | K77: Un. | L77: 3984
A78: =IF($G78="UNIDADE CONSTRUTIVA",OFFSET(A78,0,0)+1,LARGE(A$3:A16,1)) -> 1 | B78: =IF(G78="UNIDADE CONSTRUTIVA",0,IF(G78="CÉLULA CONSTRUTIVA",OFFSET(B78,-1,0)+1,OFFSET(B78,-1,0))) -> 3 | C78: =IF(G78="CÉLULA CONSTRUTIVA",0,IF(G78="ETAPA",OFFSET(C78,-1,0)+1,OFFSET(C78,-1,0))) -> 1 | D78: =IF(G78="ETAPA",0,IF(G78="SUBETAPA",OFFSET(D78,-1,0)+1,OFFSET(D78,-1,0))) -> 1 | E78: =IF(G78="Subetapa",0,IF(G78="serviço",OFFSET(E78,-1,0)+1,OFFSET(E78,-1,0))) -> 8 | G78: Serviço | H78: =IF(G78="Unidade Construtiva",TEXT(A78,"00"),IF(G78="Célula Construtiva",TEXT(B78,"00"),IF(G78="Etapa",CONCATENATE(TEXT(B78,"00"),".",TEXT(C78,"000")),IF(G78="Subetapa",CONCATENATE(TEXT(B78,"00"),".",TEXT(C78,"000"),".",TEXT(D78,"000")),IF(G78="Serviço",CONCATENATE(TEXT(B78,"00"),".",TEXT(C78,"000"),".",TEXT(D78,"000"),".",TEXT(E78,"000")),""))))) -> 03.001.001.008 | I78: Locação de elevador cremalheira - 2 unidades RESIDENCIAL | J78: 25 | K78: mes | L78: 1000000
A79: =IF($G79="UNIDADE CONSTRUTIVA",OFFSET(A79,0,0)+1,LARGE(A$3:A18,1)) -> 1 | B79: =IF(G79="UNIDADE CONSTRUTIVA",0,IF(G79="CÉLULA CONSTRUTIVA",OFFSET(B79,-1,0)+1,OFFSET(B79,-1,0))) -> 3 | C79: =IF(G79="CÉLULA CONSTRUTIVA",0,IF(G79="ETAPA",OFFSET(C79,-1,0)+1,OFFSET(C79,-1,0))) -> 1 | D79: =IF(G79="ETAPA",0,IF(G79="SUBETAPA",OFFSET(D79,-1,0)+1,OFFSET(D79,-1,0))) -> 1 | E79: =IF(G79="Subetapa",0,IF(G79="serviço",OFFSET(E79,-1,0)+1,OFFSET(E79,-1,0))) -> 9 | G79: Serviço | H79: =IF(G79="Unidade Construtiva",TEXT(A79,"00"),IF(G79="Célula Construtiva",TEXT(B79,"00"),IF(G79="Etapa",CONCATENATE(TEXT(B79,"00"),".",TEXT(C79,"000")),IF(G79="Subetapa",CONCATENATE(TEXT(B79,"00"),".",TEXT(C79,"000"),".",TEXT(D79,"000")),IF(G79="Serviço",CONCATENATE(TEXT(B79,"00"),".",TEXT(C79,"000"),".",TEXT(D79,"000"),".",TEXT(E79,"000")),""))))) -> 03.001.001.009 | I79: Montagem de elevador cremalheira RESIDENCIAL | J79: 2 | K79: Un. | L79: 110000 | M79: Montagem de torres e cancelas por pavimento
A80: =IF($G80="UNIDADE CONSTRUTIVA",OFFSET(A80,0,0)+1,LARGE(A$3:A35,1)) -> 1 | B80: =IF(G80="UNIDADE CONSTRUTIVA",0,IF(G80="CÉLULA CONSTRUTIVA",OFFSET(B80,-1,0)+1,OFFSET(B80,-1,0))) -> 3 | C80: =IF(G80="CÉLULA CONSTRUTIVA",0,IF(G80="ETAPA",OFFSET(C80,-1,0)+1,OFFSET(C80,-1,0))) -> 1 | D80: =IF(G80="ETAPA",0,IF(G80="SUBETAPA",OFFSET(D80,-1,0)+1,OFFSET(D80,-1,0))) -> 1 | E80: =IF(G80="Subetapa",0,IF(G80="serviço",OFFSET(E80,-1,0)+1,OFFSET(E80,-1,0))) -> 10 | G80: Serviço | H80: =IF(G80="Unidade Construtiva",TEXT(A80,"00"),IF(G80="Célula Construtiva",TEXT(B80,"00"),IF(G80="Etapa",CONCATENATE(TEXT(B80,"00"),".",TEXT(C80,"000")),IF(G80="Subetapa",CONCATENATE(TEXT(B80,"00"),".",TEXT(C80,"000"),".",TEXT(D80,"000")),IF(G80="Serviço",CONCATENATE(TEXT(B80,"00"),".",TEXT(C80,"000"),".",TEXT(D80,"000"),".",TEXT(E80,"000")),""))))) -> 03.001.001.010 | I80: Desmontagem de elevador cremalheira RESIDENCIAL | J80: 2 | K80: Un. | L80: 30000 | M80: Confirmar com planejamento
A81: =IF($G81="UNIDADE CONSTRUTIVA",OFFSET(A81,0,0)+1,LARGE(A$3:A32,1)) -> 1 | B81: =IF(G81="UNIDADE CONSTRUTIVA",0,IF(G81="CÉLULA CONSTRUTIVA",OFFSET(B81,-1,0)+1,OFFSET(B81,-1,0))) -> 3 | C81: =IF(G81="CÉLULA CONSTRUTIVA",0,IF(G81="ETAPA",OFFSET(C81,-1,0)+1,OFFSET(C81,-1,0))) -> 1 | D81: =IF(G81="ETAPA",0,IF(G81="SUBETAPA",OFFSET(D81,-1,0)+1,OFFSET(D81,-1,0))) -> 1 | E81: =IF(G81="Subetapa",0,IF(G81="serviço",OFFSET(E81,-1,0)+1,OFFSET(E81,-1,0))) -> 11 | G81: Serviço | H81: =IF(G81="Unidade Construtiva",TEXT(A81,"00"),IF(G81="Célula Construtiva",TEXT(B81,"00"),IF(G81="Etapa",CONCATENATE(TEXT(B81,"00"),".",TEXT(C81,"000")),IF(G81="Subetapa",CONCATENATE(TEXT(B81,"00"),".",TEXT(C81,"000"),".",TEXT(D81,"000")),IF(G81="Serviço",CONCATENATE(TEXT(B81,"00"),".",TEXT(C81,"000"),".",TEXT(D81,"000"),".",TEXT(E81,"000")),""))))) -> 03.001.001.011 | I81: Locação de elevador cremalheira - HOTEL | J81: 10 | K81: mes | L81: 200000
A82: =IF($G82="UNIDADE CONSTRUTIVA",OFFSET(A82,0,0)+1,LARGE(A$3:A33,1)) -> 1 | B82: =IF(G82="UNIDADE CONSTRUTIVA",0,IF(G82="CÉLULA CONSTRUTIVA",OFFSET(B82,-1,0)+1,OFFSET(B82,-1,0))) -> 3 | C82: =IF(G82="CÉLULA CONSTRUTIVA",0,IF(G82="ETAPA",OFFSET(C82,-1,0)+1,OFFSET(C82,-1,0))) -> 1 | D82: =IF(G82="ETAPA",0,IF(G82="SUBETAPA",OFFSET(D82,-1,0)+1,OFFSET(D82,-1,0))) -> 1 | E82: =IF(G82="Subetapa",0,IF(G82="serviço",OFFSET(E82,-1,0)+1,OFFSET(E82,-1,0))) -> 12 | G82: Serviço | H82: =IF(G82="Unidade Construtiva",TEXT(A82,"00"),IF(G82="Célula Construtiva",TEXT(B82,"00"),IF(G82="Etapa",CONCATENATE(TEXT(B82,"00"),".",TEXT(C82,"000")),IF(G82="Subetapa",CONCATENATE(TEXT(B82,"00"),".",TEXT(C82,"000"),".",TEXT(D82,"000")),IF(G82="Serviço",CONCATENATE(TEXT(B82,"00"),".",TEXT(C82,"000"),".",TEXT(D82,"000"),".",TEXT(E82,"000")),""))))) -> 03.001.001.012 | I82: Montagem de elevador cremalheira HOTEL | J82: 1 | K82: Un. | L82: 55000 | M82: Montagem de torres e cancelas por pavimento
A83: =IF($G83="UNIDADE CONSTRUTIVA",OFFSET(A83,0,0)+1,LARGE(A$3:A34,1)) -> 1 | B83: =IF(G83="UNIDADE CONSTRUTIVA",0,IF(G83="CÉLULA CONSTRUTIVA",OFFSET(B83,-1,0)+1,OFFSET(B83,-1,0))) -> 3 | C83: =IF(G83="CÉLULA CONSTRUTIVA",0,IF(G83="ETAPA",OFFSET(C83,-1,0)+1,OFFSET(C83,-1,0))) -> 1 | D83: =IF(G83="ETAPA",0,IF(G83="SUBETAPA",OFFSET(D83,-1,0)+1,OFFSET(D83,-1,0))) -> 1 | E83: =IF(G83="Subetapa",0,IF(G83="serviço",OFFSET(E83,-1,0)+1,OFFSET(E83,-1,0))) -> 13 | G83: Serviço | H83: =IF(G83="Unidade Construtiva",TEXT(A83,"00"),IF(G83="Célula Construtiva",TEXT(B83,"00"),IF(G83="Etapa",CONCATENATE(TEXT(B83,"00"),".",TEXT(C83,"000")),IF(G83="Subetapa",CONCATENATE(TEXT(B83,"00"),".",TEXT(C83,"000"),".",TEXT(D83,"000")),IF(G83="Serviço",CONCATENATE(TEXT(B83,"00"),".",TEXT(C83,"000"),".",TEXT(D83,"000"),".",TEXT(E83,"000")),""))))) -> 03.001.001.013 | I83: Desmontagem de elevador cremalheira HOTEL | J83: 1 | K83: Un. | L83: 15000 | M83: Confirmar com planejamento
A84: =IF($G84="UNIDADE CONSTRUTIVA",OFFSET(A84,0,0)+1,LARGE(A$3:A83,1)) -> 1 | B84: =IF(G84="UNIDADE CONSTRUTIVA",0,IF(G84="CÉLULA CONSTRUTIVA",OFFSET(B84,-1,0)+1,OFFSET(B84,-1,0))) -> 3 | C84: =IF(G84="CÉLULA CONSTRUTIVA",0,IF(G84="ETAPA",OFFSET(C84,-1,0)+1,OFFSET(C84,-1,0))) -> 1 | D84: =IF(G84="ETAPA",0,IF(G84="SUBETAPA",OFFSET(D84,-1,0)+1,OFFSET(D84,-1,0))) -> 2 | E84: =IF(G84="Subetapa",0,IF(G84="serviço",OFFSET(E84,-1,0)+1,OFFSET(E84,-1,0))) -> 0 | G84: Subetapa | H84: =IF(G84="Unidade Construtiva",TEXT(A84,"00"),IF(G84="Célula Construtiva",TEXT(B84,"00"),IF(G84="Etapa",CONCATENATE(TEXT(B84,"00"),".",TEXT(C84,"000")),IF(G84="Subetapa",CONCATENATE(TEXT(B84,"00"),".",TEXT(C84,"000"),".",TEXT(D84,"000")),IF(G84="Serviço",CONCATENATE(TEXT(B84,"00"),".",TEXT(C84,"000"),".",TEXT(D84,"000"),".",TEXT(E84,"000")),""))))) -> 03.001.002 | I84: Balancins e Andaimes | L84: =SUM(L85:L89) -> 787476.63
A85: =IF($G85="UNIDADE CONSTRUTIVA",OFFSET(A85,0,0)+1,LARGE(A$3:A35,1)) -> 1 | B85: =IF(G85="UNIDADE CONSTRUTIVA",0,IF(G85="CÉLULA CONSTRUTIVA",OFFSET(B85,-1,0)+1,OFFSET(B85,-1,0))) -> 3 | C85: =IF(G85="CÉLULA CONSTRUTIVA",0,IF(G85="ETAPA",OFFSET(C85,-1,0)+1,OFFSET(C85,-1,0))) -> 1 | D85: =IF(G85="ETAPA",0,IF(G85="SUBETAPA",OFFSET(D85,-1,0)+1,OFFSET(D85,-1,0))) -> 2 | E85: =IF(G85="Subetapa",0,IF(G85="serviço",OFFSET(E85,-1,0)+1,OFFSET(E85,-1,0))) -> 1 | G85: Serviço | H85: =IF(G85="Unidade Construtiva",TEXT(A85,"00"),IF(G85="Célula Construtiva",TEXT(B85,"00"),IF(G85="Etapa",CONCATENATE(TEXT(B85,"00"),".",TEXT(C85,"000")),IF(G85="Subetapa",CONCATENATE(TEXT(B85,"00"),".",TEXT(C85,"000"),".",TEXT(D85,"000")),IF(G85="Serviço",CONCATENATE(TEXT(B85,"00"),".",TEXT(C85,"000"),".",TEXT(D85,"000"),".",TEXT(E85,"000")),""))))) -> 03.001.002.001 | I85: Locação de balancim - RESIDENCIAL | J85: 13 | K85: mes | L85: 148200
A86: =IF($G86="UNIDADE CONSTRUTIVA",OFFSET(A86,0,0)+1,LARGE(A$3:A37,1)) -> 1 | B86: =IF(G86="UNIDADE CONSTRUTIVA",0,IF(G86="CÉLULA CONSTRUTIVA",OFFSET(B86,-1,0)+1,OFFSET(B86,-1,0))) -> 3 | C86: =IF(G86="CÉLULA CONSTRUTIVA",0,IF(G86="ETAPA",OFFSET(C86,-1,0)+1,OFFSET(C86,-1,0))) -> 1 | D86: =IF(G86="ETAPA",0,IF(G86="SUBETAPA",OFFSET(D86,-1,0)+1,OFFSET(D86,-1,0))) -> 2 | E86: =IF(G86="Subetapa",0,IF(G86="serviço",OFFSET(E86,-1,0)+1,OFFSET(E86,-1,0))) -> 2 | G86: Serviço | H86: =IF(G86="Unidade Construtiva",TEXT(A86,"00"),IF(G86="Célula Construtiva",TEXT(B86,"00"),IF(G86="Etapa",CONCATENATE(TEXT(B86,"00"),".",TEXT(C86,"000")),IF(G86="Subetapa",CONCATENATE(TEXT(B86,"00"),".",TEXT(C86,"000"),".",TEXT(D86,"000")),IF(G86="Serviço",CONCATENATE(TEXT(B86,"00"),".",TEXT(C86,"000"),".",TEXT(D86,"000"),".",TEXT(E86,"000")),""))))) -> 03.001.002.002 | I86: Montagem e desmontagem de balancim RESIDENCIAL | J86: 150 | K86: Un. | L86: 67500
A87: =IF($G87="UNIDADE CONSTRUTIVA",OFFSET(A87,0,0)+1,LARGE(A$3:A41,1)) -> 1 | B87: =IF(G87="UNIDADE CONSTRUTIVA",0,IF(G87="CÉLULA CONSTRUTIVA",OFFSET(B87,-1,0)+1,OFFSET(B87,-1,0))) -> 3 | C87: =IF(G87="CÉLULA CONSTRUTIVA",0,IF(G87="ETAPA",OFFSET(C87,-1,0)+1,OFFSET(C87,-1,0))) -> 1 | D87: =IF(G87="ETAPA",0,IF(G87="SUBETAPA",OFFSET(D87,-1,0)+1,OFFSET(D87,-1,0))) -> 2 | E87: =IF(G87="Subetapa",0,IF(G87="serviço",OFFSET(E87,-1,0)+1,OFFSET(E87,-1,0))) -> 3 | G87: Serviço | H87: =IF(G87="Unidade Construtiva",TEXT(A87,"00"),IF(G87="Célula Construtiva",TEXT(B87,"00"),IF(G87="Etapa",CONCATENATE(TEXT(B87,"00"),".",TEXT(C87,"000")),IF(G87="Subetapa",CONCATENATE(TEXT(B87,"00"),".",TEXT(C87,"000"),".",TEXT(D87,"000")),IF(G87="Serviço",CONCATENATE(TEXT(B87,"00"),".",TEXT(C87,"000"),".",TEXT(D87,"000"),".",TEXT(E87,"000")),""))))) -> 03.001.002.003 | I87: Locação de andaime fachadeiro | J87: 10 | K87: mes | L87: 415216.74
A88: =IF($G88="UNIDADE CONSTRUTIVA",OFFSET(A88,0,0)+1,LARGE(A$3:A42,1)) -> 1 | B88: =IF(G88="UNIDADE CONSTRUTIVA",0,IF(G88="CÉLULA CONSTRUTIVA",OFFSET(B88,-1,0)+1,OFFSET(B88,-1,0))) -> 3 | C88: =IF(G88="CÉLULA CONSTRUTIVA",0,IF(G88="ETAPA",OFFSET(C88,-1,0)+1,OFFSET(C88,-1,0))) -> 1 | D88: =IF(G88="ETAPA",0,IF(G88="SUBETAPA",OFFSET(D88,-1,0)+1,OFFSET(D88,-1,0))) -> 2 | E88: =IF(G88="Subetapa",0,IF(G88="serviço",OFFSET(E88,-1,0)+1,OFFSET(E88,-1,0))) -> 4 | G88: Serviço | H88: =IF(G88="Unidade Construtiva",TEXT(A88,"00"),IF(G88="Célula Construtiva",TEXT(B88,"00"),IF(G88="Etapa",CONCATENATE(TEXT(B88,"00"),".",TEXT(C88,"000")),IF(G88="Subetapa",CONCATENATE(TEXT(B88,"00"),".",TEXT(C88,"000"),".",TEXT(D88,"000")),IF(G88="Serviço",CONCATENATE(TEXT(B88,"00"),".",TEXT(C88,"000"),".",TEXT(D88,"000"),".",TEXT(E88,"000")),""))))) -> 03.001.002.004 | I88: Mão de obra de montagem de andaime fachadeiro | J88: 2678.8177 | K88: m2 | L88: 133940.88
A89: =IF($G89="UNIDADE CONSTRUTIVA",OFFSET(A89,0,0)+1,LARGE(A$3:A53,1)) -> 1 | B89: =IF(G89="UNIDADE CONSTRUTIVA",0,IF(G89="CÉLULA CONSTRUTIVA",OFFSET(B89,-1,0)+1,OFFSET(B89,-1,0))) -> 3 | C89: =IF(G89="CÉLULA CONSTRUTIVA",0,IF(G89="ETAPA",OFFSET(C89,-1,0)+1,OFFSET(C89,-1,0))) -> 1 | D89: =IF(G89="ETAPA",0,IF(G89="SUBETAPA",OFFSET(D89,-1,0)+1,OFFSET(D89,-1,0))) -> 2 | E89: =IF(G89="Subetapa",0,IF(G89="serviço",OFFSET(E89,-1,0)+1,OFFSET(E89,-1,0))) -> 5 | G89: Serviço | H89: =IF(G89="Unidade Construtiva",TEXT(A89,"00"),IF(G89="Célula Construtiva",TEXT(B89,"00"),IF(G89="Etapa",CONCATENATE(TEXT(B89,"00"),".",TEXT(C89,"000")),IF(G89="Subetapa",CONCATENATE(TEXT(B89,"00"),".",TEXT(C89,"000"),".",TEXT(D89,"000")),IF(G89="Serviço",CONCATENATE(TEXT(B89,"00"),".",TEXT(C89,"000"),".",TEXT(D89,"000"),".",TEXT(E89,"000")),""))))) -> 03.001.002.005 | I89: Plataformas de trabalho em madeira para andaime | J89: 904.76 | K89: m | L89: 22619

Sheet HOTEL
G1: ORÇAMENTO DE VIABILIDADE - HOTEL
J2: HOTEL | M2: OBSERVAÇÕES | P2: Clientes possuem opção de fazer 3 suites ou 2 suites + 2 demi-suites - padrão 4 suites
A3: Unidade Construtiva | B3: Célula Construtiva | C3: Etapa | D3: Subetapa | E3: Serviço | G3: Hotel Colline de France - Rio de Janeiro | J3: Quantidade | K3: Unidade | L3: Custo
A4: =IF($G4="UNIDADE CONSTRUTIVA",2,LARGE(A$3:A3,1)) -> 2 | B4: =IF(G4="UNIDADE CONSTRUTIVA",0,IF(G4="CÉLULA CONSTRUTIVA",OFFSET(B4,-1,0)+1,OFFSET(B4,-1,0))) -> 0 | C4: =IF(G4="CÉLULA CONSTRUTIVA",0,IF(G4="ETAPA",OFFSET(C4,-1,0)+1,OFFSET(C4,-1,0))) -> Etapa | D4: =IF(G4="ETAPA",0,IF(G4="SUBETAPA",OFFSET(D4,-1,0)+1,OFFSET(D4,-1,0))) -> Subetapa | E4: =IF(G4="Subetapa",0,IF(G4="serviço",OFFSET(E4,-1,0)+1,OFFSET(E4,-1,0))) -> Serviço | G4: UNIDADE CONSTRUTIVA | H4: =IF(G4="Unidade Construtiva",TEXT(A4,"00"),IF(G4="Célula Construtiva",TEXT(B4,"00"),IF(G4="Etapa",CONCATENATE(TEXT(B4,"00"),".",TEXT(C4,"000")),IF(G4="Subetapa",CONCATENATE(TEXT(B4,"00"),".",TEXT(C4,"000"),".",TEXT(D4,"000")),IF(G4="Serviço",CONCATENATE(TEXT(B4,"00"),".",TEXT(C4,"000"),".",TEXT(D4,"000"),".",TEXT(E4,"000")),""))))) -> 02 | I4: GERENCIAMENTO EXECUTIVO | L4: =L5+L22+L40+L54+L74+L108+L131+L154++L168+L180+L191+L210+L225+L249+L264+L303+L322+L369+L380+L398+L428 -> 41673467
A5: =IF($G5="UNIDADE CONSTRUTIVA",OFFSET(A5,0,0)+1,LARGE(A$3:A4,1)) -> 2 | B5: =IF(G5="UNIDADE CONSTRUTIVA",0,IF(G5="CÉLULA CONSTRUTIVA",OFFSET(B5,-1,0)+1,OFFSET(B5,-1,0))) -> 1 | C5: =IF(G5="CÉLULA CONSTRUTIVA",0,IF(G5="ETAPA",OFFSET(C5,-1,0)+1,OFFSET(C5,-1,0))) -> 0 | D5: =IF(G5="ETAPA",0,IF(G5="SUBETAPA",OFFSET(D5,-1,0)+1,OFFSET(D5,-1,0))) -> Subetapa | E5: =IF(G5="Subetapa",0,IF(G5="serviço",OFFSET(E5,-1,0)+1,OFFSET(E5,-1,0))) -> Serviço | G5: CÉLULA CONSTRUTIVA | H5: =IF(G5="Unidade Construtiva",TEXT(A5,"00"),IF(G5="Célula Construtiva",TEXT(B5,"00"),IF(G5="Etapa",CONCATENATE(TEXT(B5,"00"),".",TEXT(C5,"000")),IF(G5="Subetapa",CONCATENATE(TEXT(B5,"00"),".",TEXT(C5,"000"),".",TEXT(D5,"000")),IF(G5="Serviço",CONCATENATE(TEXT(B5,"00"),".",TEXT(C5,"000"),".",TEXT(D5,"000"),".",TEXT(E5,"000")),""))))) -> 01 | I5: MOVIMENTAÇÃO DE TERRA | L5: =L6 -> 137245.95
A6: =IF($G6="UNIDADE CONSTRUTIVA",OFFSET(A6,0,0)+1,LARGE(A$3:A5,1)) -> 2 | B6: =IF(G6="UNIDADE CONSTRUTIVA",0,IF(G6="CÉLULA CONSTRUTIVA",OFFSET(B6,-1,0)+1,OFFSET(B6,-1,0))) -> 1 | C6: =IF(G6="CÉLULA CONSTRUTIVA",0,IF(G6="ETAPA",OFFSET(C6,-1,0)+1,OFFSET(C6,-1,0))) -> 1 | D6: =IF(G6="ETAPA",0,IF(G6="SUBETAPA",OFFSET(D6,-1,0)+1,OFFSET(D6,-1,0))) -> 0 | E6: =IF(G6="Subetapa",0,IF(G6="serviço",OFFSET(E6,-1,0)+1,OFFSET(E6,-1,0))) -> Serviço | G6: ETAPA | H6: =IF(G6="Unidade Construtiva",TEXT(A6,"00"),IF(G6="Célula Construtiva",TEXT(B6,"00"),IF(G6="Etapa",CONCATENATE(TEXT(B6,"00"),".",TEXT(C6,"000")),IF(G6="Subetapa",CONCATENATE(TEXT(B6,"00"),".",TEXT(C6,"000"),".",TEXT(D6,"000")),IF(G6="Serviço",CONCATENATE(TEXT(B6,"00"),".",TEXT(C6,"000"),".",TEXT(D6,"000"),".",TEXT(E6,"000")),""))))) -> 01.001 | I6: MOVIMENTAÇÃO DE TERRA | L6: =SUM(L7:L20)/2 -> 137245.95
A7: =IF($G7="UNIDADE CONSTRUTIVA",OFFSET(A7,0,0)+1,LARGE(A$3:A6,1)) -> 2 | B7: =IF(G7="UNIDADE CONSTRUTIVA",0,IF(G7="CÉLULA CONSTRUTIVA",OFFSET(B7,-1,0)+1,OFFSET(B7,-1,0))) -> 1 | C7: =IF(G7="CÉLULA CONSTRUTIVA",0,IF(G7="ETAPA",OFFSET(C7,-1,0)+1,OFFSET(C7,-1,0))) -> 1 | D7: =IF(G7="ETAPA",0,IF(G7="SUBETAPA",OFFSET(D7,-1,0)+1,OFFSET(D7,-1,0))) -> 1 | E7: =IF(G7="Subetapa",0,IF(G7="serviço",OFFSET(E7,-1,0)+1,OFFSET(E7,-1,0))) -> 0 | G7: Subetapa | H7: =IF(G7="Unidade Construtiva",TEXT(A7,"00"),IF(G7="Célula Construtiva",TEXT(B7,"00"),IF(G7="Etapa",CONCATENATE(TEXT(B7,"00"),".",TEXT(C7,"000")),IF(G7="Subetapa",CONCATENATE(TEXT(B7,"00"),".",TEXT(C7,"000"),".",TEXT(D7,"000")),IF(G7="Serviço",CONCATENATE(TEXT(B7,"00"),".",TEXT(C7,"000"),".",TEXT(D7,"000"),".",TEXT(E7,"000")),""))))) -> 01.001.001 | I7: Corte e aterro | L7: =SUM(L8:L9) -> 2035.5964
A8: =IF($G8="UNIDADE CONSTRUTIVA",OFFSET(A8,0,0)+1,LARGE(A$3:A7,1)) -> 2 | B8: =IF(G8="UNIDADE CONSTRUTIVA",0,IF(G8="CÉLULA CONSTRUTIVA",OFFSET(B8,-1,0)+1,OFFSET(B8,-1,0))) -> 1 | C8: =IF(G8="CÉLULA CONSTRUTIVA",0,IF(G8="ETAPA",OFFSET(C8,-1,0)+1,OFFSET(C8,-1,0))) -> 1 | D8: =IF(G8="ETAPA",0,IF(G8="SUBETAPA",OFFSET(D8,-1,0)+1,OFFSET(D8,-1,0))) -> 1 | E8: =IF(G8="Subetapa",0,IF(G8="serviço",OFFSET(E8,-1,0)+1,OFFSET(E8,-1,0))) -> 1 | G8: Serviço | H8: =IF(G8="Unidade Construtiva",TEXT(A8,"00"),IF(G8="Célula Construtiva",TEXT(B8,"00"),IF(G8="Etapa",CONCATENATE(TEXT(B8,"00"),".",TEXT(C8,"000")),IF(G8="Subetapa",CONCATENATE(TEXT(B8,"00"),".",TEXT(C8,"000"),".",TEXT(D8,"000")),IF(G8="Serviço",CONCATENATE(TEXT(B8,"00"),".",TEXT(C8,"000"),".",TEXT(D8,"000"),".",TEXT(E8,"000")),""))))) -> 01.001.001.001 | I8: Escavação subsolo
A9: =IF($G9="UNIDADE CONSTRUTIVA",OFFSET(A9,0,0)+1,LARGE(A$3:A8,1)) -> 2 | B9: =IF(G9="UNIDADE CONSTRUTIVA",0,IF(G9="CÉLULA CONSTRUTIVA",OFFSET(B9,-1,0)+1,OFFSET(B9,-1,0))) -> 1 | C9: =IF(G9="CÉLULA CONSTRUTIVA",0,IF(G9="ETAPA",OFFSET(C9,-1,0)+1,OFFSET(C9,-1,0))) -> 1 | D9: =IF(G9="ETAPA",0,IF(G9="SUBETAPA",OFFSET(D9,-1,0)+1,OFFSET(D9,-1,0))) -> 1 | E9: =IF(G9="Subetapa",0,IF(G9="serviço",OFFSET(E9,-1,0)+1,OFFSET(E9,-1,0))) -> 2 | G9: Serviço | H9: =IF(G9="Unidade Construtiva",TEXT(A9,"00"),IF(G9="Célula Construtiva",TEXT(B9,"00"),IF(G9="Etapa",CONCATENATE(TEXT(B9,"00"),".",TEXT(C9,"000")),IF(G9="Subetapa",CONCATENATE(TEXT(B9,"00"),".",TEXT(C9,"000"),".",TEXT(D9,"000")),IF(G9="Serviço",CONCATENATE(TEXT(B9,"00"),".",TEXT(C9,"000"),".",TEXT(D9,"000"),".",TEXT(E9,"000")),""))))) -> 01.001.001.002 | I9: Aterro subsolo | J9: 203.58 | K9: m³ | L9: 2035.5964 | M9: Aterro sob rampas, 30% de empolamento - aproveitamento de terra de escavação
A10: =IF($G10="UNIDADE CONSTRUTIVA",OFFSET(A10,0,0)+1,LARGE(A$3:A9,1)) -> 2 | B10: =IF(G10="UNIDADE CONSTRUTIVA",0,IF(G10="CÉLULA CONSTRUTIVA",OFFSET(B10,-1,0)+1,OFFSET(B10,-1,0))) -> 1 | C10: =IF(G10="CÉLULA CONSTRUTIVA",0,IF(G10="ETAPA",OFFSET(C10,-1,0)+1,OFFSET(C10,-1,0))) -> 1 | D10: =IF(G10="ETAPA",0,IF(G10="SUBETAPA",OFFSET(D10,-1,0)+1,OFFSET(D10,-1,0))) -> 2 | E10: =IF(G10="Subetapa",0,IF(G10="serviço",OFFSET(E10,-1,0)+1,OFFSET(E10,-1,0))) -> 0 | G10: Subetapa | H10: =IF(G10="Unidade Construtiva",TEXT(A10,"00"),IF(G10="Célula Construtiva",TEXT(B10,"00"),IF(G10="Etapa",CONCATENATE(TEXT(B10,"00"),".",TEXT(C10,"000")),IF(G10="Subetapa",CONCATENATE(TEXT(B10,"00"),".",TEXT(C10,"000"),".",TEXT(D10,"000")),IF(G10="Serviço",CONCATENATE(TEXT(B10,"00"),".",TEXT(C10,"000"),".",TEXT(D10,"000"),".",TEXT(E10,"000")),""))))) -> 01.001.002 | I10: Rebaixamento de lençol | L10: =SUM(L11) -> 0
A11: =IF($G11="UNIDADE CONSTRUTIVA",OFFSET(A11,0,0)+1,LARGE(A$3:A10,1)) -> 2 | B11: =IF(G11="UNIDADE CONSTRUTIVA",0,IF(G11="CÉLULA CONSTRUTIVA",OFFSET(B11,-1,0)+1,OFFSET(B11,-1,0))) -> 1 | C11: =IF(G11="CÉLULA CONSTRUTIVA",0,IF(G11="ETAPA",OFFSET(C11,-1,0)+1,OFFSET(C11,-1,0))) -> 1 | D11: =IF(G11="ETAPA",0,IF(G11="SUBETAPA",OFFSET(D11,-1,0)+1,OFFSET(D11,-1,0))) -> 2 | E11: =IF(G11="Subetapa",0,IF(G11="serviço",OFFSET(E11,-1,0)+1,OFFSET(E11,-1,0))) -> 1 | G11: Serviço | H11: =IF(G11="Unidade Construtiva",TEXT(A11,"00"),IF(G11="Célula Construtiva",TEXT(B11,"00"),IF(G11="Etapa",CONCATENATE(TEXT(B11,"00"),".",TEXT(C11,"000")),IF(G11="Subetapa",CONCATENATE(TEXT(B11,"00"),".",TEXT(C11,"000"),".",TEXT(D11,"000")),IF(G11="Serviço",CONCATENATE(TEXT(B11,"00"),".",TEXT(C11,"000"),".",TEXT(D11,"000"),".",TEXT(E11,"000")),""))))) -> 01.001.002.001 | I11: Rebaixamento de lençol
A12: =IF($G12="UNIDADE CONSTRUTIVA",OFFSET(A12,0,0)+1,LARGE(A$3:A10,1)) -> 2 | B12: =IF(G12="UNIDADE CONSTRUTIVA",0,IF(G12="CÉLULA CONSTRUTIVA",OFFSET(B12,-1,0)+1,OFFSET(B12,-1,0))) -> 1 | C12: =IF(G12="CÉLULA CONSTRUTIVA",0,IF(G12="ETAPA",OFFSET(C12,-1,0)+1,OFFSET(C12,-1,0))) -> 1 | D12: =IF(G12="ETAPA",0,IF(G12="SUBETAPA",OFFSET(D12,-1,0)+1,OFFSET(D12,-1,0))) -> 3 | E12: =IF(G12="Subetapa",0,IF(G12="serviço",OFFSET(E12,-1,0)+1,OFFSET(E12,-1,0))) -> 0 | G12: Subetapa | H12: =IF(G12="Unidade Construtiva",TEXT(A12,"00"),IF(G12="Célula Construtiva",TEXT(B12,"00"),IF(G12="Etapa",CONCATENATE(TEXT(B12,"00"),".",TEXT(C12,"000")),IF(G12="Subetapa",CONCATENATE(TEXT(B12,"00"),".",TEXT(C12,"000"),".",TEXT(D12,"000")),IF(G12="Serviço",CONCATENATE(TEXT(B12,"00"),".",TEXT(C12,"000"),".",TEXT(D12,"000"),".",TEXT(E12,"000")),""))))) -> 01.001.003 | I12: Escavação e Reaterro de Valas | L12: =SUM(L13:L14) -> 35418.741
A13: =IF($G13="UNIDADE CONSTRUTIVA",OFFSET(A13,0,0)+1,LARGE(A$3:A11,1)) -> 2 | B13: =IF(G13="UNIDADE CONSTRUTIVA",0,IF(G13="CÉLULA CONSTRUTIVA",OFFSET(B13,-1,0)+1,OFFSET(B13,-1,0))) -> 1 | C13: =IF(G13="CÉLULA CONSTRUTIVA",0,IF(G13="ETAPA",OFFSET(C13,-1,0)+1,OFFSET(C13,-1,0))) -> 1 | D13: =IF(G13="ETAPA",0,IF(G13="SUBETAPA",OFFSET(D13,-1,0)+1,OFFSET(D13,-1,0))) -> 3 | E13: =IF(G13="Subetapa",0,IF(G13="serviço",OFFSET(E13,-1,0)+1,OFFSET(E13,-1,0))) -> 1 | G13: Serviço | H13: =IF(G13="Unidade Construtiva",TEXT(A13,"00"),IF(G13="Célula Construtiva",TEXT(B13,"00"),IF(G13="Etapa",CONCATENATE(TEXT(B13,"00"),".",TEXT(C13,"000")),IF(G13="Subetapa",CONCATENATE(TEXT(B13,"00"),".",TEXT(C13,"000"),".",TEXT(D13,"000")),IF(G13="Serviço",CONCATENATE(TEXT(B13,"00"),".",TEXT(C13,"000"),".",TEXT(D13,"000"),".",TEXT(E13,"000")),""))))) -> 01.001.003.001 | I13: Escavação mecanizada para blocos e baldrames | J13: 810.693 | K13: m³ | L13: 32424.477
A14: =IF($G14="UNIDADE CONSTRUTIVA",OFFSET(A14,0,0)+1,LARGE(A$3:A12,1)) -> 2 | B14: =IF(G14="UNIDADE CONSTRUTIVA",0,IF(G14="CÉLULA CONSTRUTIVA",OFFSET(B14,-1,0)+1,OFFSET(B14,-1,0))) -> 1 | C14: =IF(G14="CÉLULA CONSTRUTIVA",0,IF(G14="ETAPA",OFFSET(C14,-1,0)+1,OFFSET(C14,-1,0))) -> 1 | D14: =IF(G14="ETAPA",0,IF(G14="SUBETAPA",OFFSET(D14,-1,0)+1,OFFSET(D14,-1,0))) -> 3 | E14: =IF(G14="Subetapa",0,IF(G14="serviço",OFFSET(E14,-1,0)+1,OFFSET(E14,-1,0))) -> 2 | G14: Serviço | H14: =IF(G14="Unidade Construtiva",TEXT(A14,"00"),IF(G14="Célula Construtiva",TEXT(B14,"00"),IF(G14="Etapa",CONCATENATE(TEXT(B14,"00"),".",TEXT(C14,"000")),IF(G14="Subetapa",CONCATENATE(TEXT(B14,"00"),".",TEXT(C14,"000"),".",TEXT(D14,"000")),IF(G14="Serviço",CONCATENATE(TEXT(B14,"00"),".",TEXT(C14,"000"),".",TEXT(D14,"000"),".",TEXT(E14,"000")),""))))) -> 01.001.003.002 | I14: Reaterro para blocos e baldrames | J14: 187.083 | K14: m³ | L14: 2994.2634
A15: =IF($G15="UNIDADE CONSTRUTIVA",OFFSET(A15,0,0)+1,LARGE(A$3:A12,1)) -> 2 | B15: =IF(G15="UNIDADE CONSTRUTIVA",0,IF(G15="CÉLULA CONSTRUTIVA",OFFSET(B15,-1,0)+1,OFFSET(B15,-1,0))) -> 1 | C15: =IF(G15="CÉLULA CONSTRUTIVA",0,IF(G15="ETAPA",OFFSET(C15,-1,0)+1,OFFSET(C15,-1,0))) -> 1 | D15: =IF(G15="ETAPA",0,IF(G15="SUBETAPA",OFFSET(D15,-1,0)+1,OFFSET(D15,-1,0))) -> 4 | E15: =IF(G15="Subetapa",0,IF(G15="serviço",OFFSET(E15,-1,0)+1,OFFSET(E15,-1,0))) -> 0 | G15: Subetapa | H15: =IF(G15="Unidade Construtiva",TEXT(A15,"00"),IF(G15="Célula Construtiva",TEXT(B15,"00"),IF(G15="Etapa",CONCATENATE(TEXT(B15,"00"),".",TEXT(C15,"000")),IF(G15="Subetapa",CONCATENATE(TEXT(B15,"00"),".",TEXT(C15,"000"),".",TEXT(D15,"000")),IF(G15="Serviço",CONCATENATE(TEXT(B15,"00"),".",TEXT(C15,"000"),".",TEXT(D15,"000"),".",TEXT(E15,"000")),""))))) -> 01.001.004 | I15: Lastro de estrutura de concreto | L15: =SUM(L16:L17) -> 72492.398
A16: =IF($G16="UNIDADE CONSTRUTIVA",OFFSET(A16,0,0)+1,LARGE(A$3:A13,1)) -> 2 | B16: =IF(G16="UNIDADE CONSTRUTIVA",0,IF(G16="CÉLULA CONSTRUTIVA",OFFSET(B16,-1,0)+1,OFFSET(B16,-1,0))) -> 1 | C16: =IF(G16="CÉLULA CONSTRUTIVA",0,IF(G16="ETAPA",OFFSET(C16,-1,0)+1,OFFSET(C16,-1,0))) -> 1 | D16: =IF(G16="ETAPA",0,IF(G16="SUBETAPA",OFFSET(D16,-1,0)+1,OFFSET(D16,-1,0))) -> 4 | E16: =IF(G16="Subetapa",0,IF(G16="serviço",OFFSET(E16,-1,0)+1,OFFSET(E16,-1,0))) -> 1 | G16: Serviço | H16: =IF(G16="Unidade Construtiva",TEXT(A16,"00"),IF(G16="Célula Construtiva",TEXT(B16,"00"),IF(G16="Etapa",CONCATENATE(TEXT(B16,"00"),".",TEXT(C16,"000")),IF(G16="Subetapa",CONCATENATE(TEXT(B16,"00"),".",TEXT(C16,"000"),".",TEXT(D16,"000")),IF(G16="Serviço",CONCATENATE(TEXT(B16,"00"),".",TEXT(C16,"000"),".",TEXT(D16,"000"),".",TEXT(E16,"000")),""))))) -> 01.001.004.001 | I16: Lastro de concreto magro | J16: 3562.28 | K16: m³ | L16: 72492.398
A17: =IF($G17="UNIDADE CONSTRUTIVA",OFFSET(A17,0,0)+1,LARGE(A$3:A14,1)) -> 2 | B17: =IF(G17="UNIDADE CONSTRUTIVA",0,IF(G17="CÉLULA CONSTRUTIVA",OFFSET(B17,-1,0)+1,OFFSET(B17,-1,0))) -> 1 | C17: =IF(G17="CÉLULA CONSTRUTIVA",0,IF(G17="ETAPA",OFFSET(C17,-1,0)+1,OFFSET(C17,-1,0))) -> 1 | D17: =IF(G17="ETAPA",0,IF(G17="SUBETAPA",OFFSET(D17,-1,0)+1,OFFSET(D17,-1,0))) -> 4 | E17: =IF(G17="Subetapa",0,IF(G17="serviço",OFFSET(E17,-1,0)+1,OFFSET(E17,-1,0))) -> 2 | G17: Serviço | H17: =IF(G17="Unidade Construtiva",TEXT(A17,"00"),IF(G17="Célula Construtiva",TEXT(B17,"00"),IF(G17="Etapa",CONCATENATE(TEXT(B17,"00"),".",TEXT(C17,"000")),IF(G17="Subetapa",CONCATENATE(TEXT(B17,"00"),".",TEXT(C17,"000"),".",TEXT(D17,"000")),IF(G17="Serviço",CONCATENATE(TEXT(B17,"00"),".",TEXT(C17,"000"),".",TEXT(D17,"000"),".",TEXT(E17,"000")),""))))) -> 01.001.004.002 | I17: Lastro de brita
A18: =IF($G18="UNIDADE CONSTRUTIVA",OFFSET(A18,0,0)+1,LARGE(A$3:A15,1)) -> 2 | B18: =IF(G18="UNIDADE CONSTRUTIVA",0,IF(G18="CÉLULA CONSTRUTIVA",OFFSET(B18,-1,0)+1,OFFSET(B18,-1,0))) -> 1 | C18: =IF(G18="CÉLULA CONSTRUTIVA",0,IF(G18="ETAPA",OFFSET(C18,-1,0)+1,OFFSET(C18,-1,0))) -> 1 | D18: =IF(G18="ETAPA",0,IF(G18="SUBETAPA",OFFSET(D18,-1,0)+1,OFFSET(D18,-1,0))) -> 5 | E18: =IF(G18="Subetapa",0,IF(G18="serviço",OFFSET(E18,-1,0)+1,OFFSET(E18,-1,0))) -> 0 | G18: Subetapa | H18: =IF(G18="Unidade Construtiva",TEXT(A18,"00"),IF(G18="Célula Construtiva",TEXT(B18,"00"),IF(G18="Etapa",CONCATENATE(TEXT(B18,"00"),".",TEXT(C18,"000")),IF(G18="Subetapa",CONCATENATE(TEXT(B18,"00"),".",TEXT(C18,"000"),".",TEXT(D18,"000")),IF(G18="Serviço",CONCATENATE(TEXT(B18,"00"),".",TEXT(C18,"000"),".",TEXT(D18,"000"),".",TEXT(E18,"000")),""))))) -> 01.001.005 | I18: Movimentação de bota - fora | L18: =SUM(L19:L21) -> 27299.22
A19: =IF($G19="UNIDADE CONSTRUTIVA",OFFSET(A19,0,0)+1,LARGE(A$3:A16,1)) -> 2 | B19: =IF(G19="UNIDADE CONSTRUTIVA",0,IF(G19="CÉLULA CONSTRUTIVA",OFFSET(B19,-1,0)+1,OFFSET(B19,-1,0))) -> 1 | C19: =IF(G19="CÉLULA CONSTRUTIVA",0,IF(G19="ETAPA",OFFSET(C19,-1,0)+1,OFFSET(C19,-1,0))) -> 1 | D19: =IF(G19="ETAPA",0,IF(G19="SUBETAPA",OFFSET(D19,-1,0)+1,OFFSET(D19,-1,0))) -> 5 | E19: =IF(G19="Subetapa",0,IF(G19="serviço",OFFSET(E19,-1,0)+1,OFFSET(E19,-1,0))) -> 1 | G19: Serviço | H19: =IF(G19="Unidade Construtiva",TEXT(A19,"00"),IF(G19="Célula Construtiva",TEXT(B19,"00"),IF(G19="Etapa",CONCATENATE(TEXT(B19,"00"),".",TEXT(C19,"000")),IF(G19="Subetapa",CONCATENATE(TEXT(B19,"00"),".",TEXT(C19,"000"),".",TEXT(D19,"000")),IF(G19="Serviço",CONCATENATE(TEXT(B19,"00"),".",TEXT(C19,"000"),".",TEXT(D19,"000"),".",TEXT(E19,"000")),""))))) -> 01.001.005.001 | I19: Movimentação de bota - fora para subsolo (30% de empolamento)
A20: =IF($G20="UNIDADE CONSTRUTIVA",OFFSET(A20,0,0)+1,LARGE(A$3:A17,1)) -> 2 | B20: =IF(G20="UNIDADE CONSTRUTIVA",0,IF(G20="CÉLULA CONSTRUTIVA",OFFSET(B20,-1,0)+1,OFFSET(B20,-1,0))) -> 1 | C20: =IF(G20="CÉLULA CONSTRUTIVA",0,IF(G20="ETAPA",OFFSET(C20,-1,0)+1,OFFSET(C20,-1,0))) -> 1 | D20: =IF(G20="ETAPA",0,IF(G20="SUBETAPA",OFFSET(D20,-1,0)+1,OFFSET(D20,-1,0))) -> 5 | E20: =IF(G20="Subetapa",0,IF(G20="serviço",OFFSET(E20,-1,0)+1,OFFSET(E20,-1,0))) -> 2 | G20: Serviço | H20: =IF(G20="Unidade Construtiva",TEXT(A20,"00"),IF(G20="Célula Construtiva",TEXT(B20,"00"),IF(G20="Etapa",CONCATENATE(TEXT(B20,"00"),".",TEXT(C20,"000")),IF(G20="Subetapa",CONCATENATE(TEXT(B20,"00"),".",TEXT(C20,"000"),".",TEXT(D20,"000")),IF(G20="Serviço",CONCATENATE(TEXT(B20,"00"),".",TEXT(C20,"000"),".",TEXT(D20,"000"),".",TEXT(E20,"000")),""))))) -> 01.001.005.002 | I20: Movimentação de bota - fora para valas (30% de empolamento) | J20: 546.039 | K20: m³ | L20: 27299.22 | M20: Diferença de reterro com 30% de empolamento
A21: =IF($G21="UNIDADE CONSTRUTIVA",OFFSET(A21,0,0)+1,LARGE(A$3:A18,1)) -> 2 | B21: =IF(G21="UNIDADE CONSTRUTIVA",0,IF(G21="CÉLULA CONSTRUTIVA",OFFSET(B21,-1,0)+1,OFFSET(B21,-1,0))) -> 1 | C21: =IF(G21="CÉLULA CONSTRUTIVA",0,IF(G21="ETAPA",OFFSET(C21,-1,0)+1,OFFSET(C21,-1,0))) -> 1 | D21: =IF(G21="ETAPA",0,IF(G21="SUBETAPA",OFFSET(D21,-1,0)+1,OFFSET(D21,-1,0))) -> 5 | E21: =IF(G21="Subetapa",0,IF(G21="serviço",OFFSET(E21,-1,0)+1,OFFSET(E21,-1,0))) -> 3 | G21: Serviço | H21: =IF(G21="Unidade Construtiva",TEXT(A21,"00"),IF(G21="Célula Construtiva",TEXT(B21,"00"),IF(G21="Etapa",CONCATENATE(TEXT(B21,"00"),".",TEXT(C21,"000")),IF(G21="Subetapa",CONCATENATE(TEXT(B21,"00"),".",TEXT(C21,"000"),".",TEXT(D21,"000")),IF(G21="Serviço",CONCATENATE(TEXT(B21,"00"),".",TEXT(C21,"000"),".",TEXT(D21,"000"),".",TEXT(E21,"000")),""))))) -> 01.001.005.003 | I21: Movimentação de bota - fora para estacas (30% de empolamento)
A22: =IF($G22="UNIDADE CONSTRUTIVA",OFFSET(A22,0,0)+1,LARGE(A$3:A18,1)) -> 2 | B22: =IF(G22="UNIDADE CONSTRUTIVA",0,IF(G22="CÉLULA CONSTRUTIVA",OFFSET(B22,-1,0)+1,OFFSET(B22,-1,0))) -> 2 | C22: =IF(G22="CÉLULA CONSTRUTIVA",0,IF(G22="ETAPA",OFFSET(C22,-1,0)+1,OFFSET(C22,-1,0))) -> 0 | D22: =IF(G22="ETAPA",0,IF(G22="SUBETAPA",OFFSET(D22,-1,0)+1,OFFSET(D22,-1,0))) -> 5 | E22: =IF(G22="Subetapa",0,IF(G22="serviço",OFFSET(E22,-1,0)+1,OFFSET(E22,-1,0))) -> 3 | G22: CÉLULA CONSTRUTIVA | H22: =IF(G22="Unidade Construtiva",TEXT(A22,"00"),IF(G22="Célula Construtiva",TEXT(B22,"00"),IF(G22="Etapa",CONCATENATE(TEXT(B22,"00"),".",TEXT(C22,"000")),IF(G22="Subetapa",CONCATENATE(TEXT(B22,"00"),".",TEXT(C22,"000"),".",TEXT(D22,"000")),IF(G22="Serviço",CONCATENATE(TEXT(B22,"00"),".",TEXT(C22,"000"),".",TEXT(D22,"000"),".",TEXT(E22,"000")),""))))) -> 02 | I22: INFRAESTRUTURA | L22: =L23+L31 -> 2200957.6
A23: =IF($G23="UNIDADE CONSTRUTIVA",OFFSET(A23,0,0)+1,LARGE(A$3:A22,1)) -> 2 | B23: =IF(G23="UNIDADE CONSTRUTIVA",0,IF(G23="CÉLULA CONSTRUTIVA",OFFSET(B23,-1,0)+1,OFFSET(B23,-1,0))) -> 2 | C23: =IF(G23="CÉLULA CONSTRUTIVA",0,IF(G23="ETAPA",OFFSET(C23,-1,0)+1,OFFSET(C23,-1,0))) -> 1 | D23: =IF(G23="ETAPA",0,IF(G23="SUBETAPA",OFFSET(D23,-1,0)+1,OFFSET(D23,-1,0))) -> 0 | E23: =IF(G23="Subetapa",0,IF(G23="serviço",OFFSET(E23,-1,0)+1,OFFSET(E23,-1,0))) -> 3 | G23: ETAPA | H23: =IF(G23="Unidade Construtiva",TEXT(A23,"00"),IF(G23="Célula Construtiva",TEXT(B23,"00"),IF(G23="Etapa",CONCATENATE(TEXT(B23,"00"),".",TEXT(C23,"000")),IF(G23="Subetapa",CONCATENATE(TEXT(B23,"00"),".",TEXT(C23,"000"),".",TEXT(D23,"000")),IF(G23="Serviço",CONCATENATE(TEXT(B23,"00"),".",TEXT(C23,"000"),".",TEXT(D23,"000"),".",TEXT(E23,"000")),""))))) -> 02.001 | I23: FUNDAÇÃO PROFUNDA | L23: =SUM(L24:L30)/2 -> 749943.13
A24: =IF($G24="UNIDADE CONSTRUTIVA",OFFSET(A24,0,0)+1,LARGE(A$3:A23,1)) -> 2 | B24: =IF(G24="UNIDADE CONSTRUTIVA",0,IF(G24="CÉLULA CONSTRUTIVA",OFFSET(B24,-1,0)+1,OFFSET(B24,-1,0))) -> 2 | C24: =IF(G24="CÉLULA CONSTRUTIVA",0,IF(G24="ETAPA",OFFSET(C24,-1,0)+1,OFFSET(C24,-1,0))) -> 1 | D24: =IF(G24="ETAPA",0,IF(G24="SUBETAPA",OFFSET(D24,-1,0)+1,OFFSET(D24,-1,0))) -> 1 | E24: =IF(G24="Subetapa",0,IF(G24="serviço",OFFSET(E24,-1,0)+1,OFFSET(E24,-1,0))) -> 0 | G24: Subetapa | H24: =IF(G24="Unidade Construtiva",TEXT(A24,"00"),IF(G24="Célula Construtiva",TEXT(B24,"00"),IF(G24="Etapa",CONCATENATE(TEXT(B24,"00"),".",TEXT(C24,"000")),IF(G24="Subetapa",CONCATENATE(TEXT(B24,"00"),".",TEXT(C24,"000"),".",TEXT(D24,"000")),IF(G24="Serviço",CONCATENATE(TEXT(B24,"00"),".",TEXT(C24,"000"),".",TEXT(D24,"000"),".",TEXT(E24,"000")),""))))) -> 02.001.001 | I24: Perfuração | L24: =SUM(L25:L28) -> 733993.13
A25: =IF($G25="UNIDADE CONSTRUTIVA",OFFSET(A25,0,0)+1,LARGE(A$3:A24,1)) -> 2 | B25: =IF(G25="UNIDADE CONSTRUTIVA",0,IF(G25="CÉLULA CONSTRUTIVA",OFFSET(B25,-1,0)+1,OFFSET(B25,-1,0))) -> 2 | C25: =IF(G25="CÉLULA CONSTRUTIVA",0,IF(G25="ETAPA",OFFSET(C25,-1,0)+1,OFFSET(C25,-1,0))) -> 1 | D25: =IF(G25="ETAPA",0,IF(G25="SUBETAPA",OFFSET(D25,-1,0)+1,OFFSET(D25,-1,0))) -> 1 | E25: =IF(G25="Subetapa",0,IF(G25="serviço",OFFSET(E25,-1,0)+1,OFFSET(E25,-1,0))) -> 1 | G25: Serviço | H25: =IF(G25="Unidade Construtiva",TEXT(A25,"00"),IF(G25="Célula Construtiva",TEXT(B25,"00"),IF(G25="Etapa",CONCATENATE(TEXT(B25,"00"),".",TEXT(C25,"000")),IF(G25="Subetapa",CONCATENATE(TEXT(B25,"00"),".",TEXT(C25,"000"),".",TEXT(D25,"000")),IF(G25="Serviço",CONCATENATE(TEXT(B25,"00"),".",TEXT(C25,"000"),".",TEXT(D25,"000"),".",TEXT(E25,"000")),""))))) -> 02.001.001.001 | I25: Cravação de estaca pré-moldada 20x20, incluso fornececimento da estaca | J25: 522 | K25: m | L25: 90809.73
A26: =IF($G26="UNIDADE CONSTRUTIVA",OFFSET(A26,0,0)+1,LARGE(A$3:A25,1)) -> 2 | B26: =IF(G26="UNIDADE CONSTRUTIVA",0,IF(G26="CÉLULA CONSTRUTIVA",OFFSET(B26,-1,0)+1,OFFSET(B26,-1,0))) -> 2 | C26: =IF(G26="CÉLULA CONSTRUTIVA",0,IF(G26="ETAPA",OFFSET(C26,-1,0)+1,OFFSET(C26,-1,0))) -> 1 | D26: =IF(G26="ETAPA",0,IF(G26="SUBETAPA",OFFSET(D26,-1,0)+1,OFFSET(D26,-1,0))) -> 1 | E26: =IF(G26="Subetapa",0,IF(G26="serviço",OFFSET(E26,-1,0)+1,OFFSET(E26,-1,0))) -> 2 | G26: Serviço | H26: =IF(G26="Unidade Construtiva",TEXT(A26,"00"),IF(G26="Célula Construtiva",TEXT(B26,"00"),IF(G26="Etapa",CONCATENATE(TEXT(B26,"00"),".",TEXT(C26,"000")),IF(G26="Subetapa",CONCATENATE(TEXT(B26,"00"),".",TEXT(C26,"000"),".",TEXT(D26,"000")),IF(G26="Serviço",CONCATENATE(TEXT(B26,"00"),".",TEXT(C26,"000"),".",TEXT(D26,"000"),".",TEXT(E26,"000")),""))))) -> 02.001.001.002 | I26: Cravação de estaca pré-moldada 30x30, incluso fornececimento da estaca | J26: 2844 | K26: m | L26: 643183.4
A27: =IF($G27="UNIDADE CONSTRUTIVA",OFFSET(A27,0,0)+1,LARGE(A$3:A26,1)) -> 2 | B27: =IF(G27="UNIDADE CONSTRUTIVA",0,IF(G27="CÉLULA CONSTRUTIVA",OFFSET(B27,-1,0)+1,OFFSET(B27,-1,0))) -> 2 | C27: =IF(G27="CÉLULA CONSTRUTIVA",0,IF(G27="ETAPA",OFFSET(C27,-1,0)+1,OFFSET(C27,-1,0))) -> 1 | D27: =IF(G27="ETAPA",0,IF(G27="SUBETAPA",OFFSET(D27,-1,0)+1,OFFSET(D27,-1,0))) -> 1 | E27: =IF(G27="Subetapa",0,IF(G27="serviço",OFFSET(E27,-1,0)+1,OFFSET(E27,-1,0))) -> 3 | G27: Serviço | H27: =IF(G27="Unidade Construtiva",TEXT(A27,"00"),IF(G27="Célula Construtiva",TEXT(B27,"00"),IF(G27="Etapa",CONCATENATE(TEXT(B27,"00"),".",TEXT(C27,"000")),IF(G27="Subetapa",CONCATENATE(TEXT(B27,"00"),".",TEXT(C27,"000"),".",TEXT(D27,"000")),IF(G27="Serviço",CONCATENATE(TEXT(B27,"00"),".",TEXT(C27,"000"),".",TEXT(D27,"000"),".",TEXT(E27,"000")),""))))) -> 02.001.001.003 | I27: Cravação de estaca centrifugada 50cm, incluso fornececimento da estaca
A28: =IF($G28="UNIDADE CONSTRUTIVA",OFFSET(A28,0,0)+1,LARGE(A$3:A27,1)) -> 2 | B28: =IF(G28="UNIDADE CONSTRUTIVA",0,IF(G28="CÉLULA CONSTRUTIVA",OFFSET(B28,-1,0)+1,OFFSET(B28,-1,0))) -> 2 | C28: =IF(G28="CÉLULA CONSTRUTIVA",0,IF(G28="ETAPA",OFFSET(C28,-1,0)+1,OFFSET(C28,-1,0))) -> 1 | D28: =IF(G28="ETAPA",0,IF(G28="SUBETAPA",OFFSET(D28,-1,0)+1,OFFSET(D28,-1,0))) -> 1 | E28: =IF(G28="Subetapa",0,IF(G28="serviço",OFFSET(E28,-1,0)+1,OFFSET(E28,-1,0))) -> 4 | G28: Serviço | H28: =IF(G28="Unidade Construtiva",TEXT(A28,"00"),IF(G28="Célula Construtiva",TEXT(B28,"00"),IF(G28="Etapa",CONCATENATE(TEXT(B28,"00"),".",TEXT(C28,"000")),IF(G28="Subetapa",CONCATENATE(TEXT(B28,"00"),".",TEXT(C28,"000"),".",TEXT(D28,"000")),IF(G28="Serviço",CONCATENATE(TEXT(B28,"00"),".",TEXT(C28,"000"),".",TEXT(D28,"000"),".",TEXT(E28,"000")),""))))) -> 02.001.001.004 | I28: Cravação de estaca centrifugada 42cm, incluso fornececimento da estaca
A29: =IF($G29="UNIDADE CONSTRUTIVA",OFFSET(A29,0,0)+1,LARGE(A$3:A25,1)) -> 2 | B29: =IF(G29="UNIDADE CONSTRUTIVA",0,IF(G29="CÉLULA CONSTRUTIVA",OFFSET(B29,-1,0)+1,OFFSET(B29,-1,0))) -> 2 | C29: =IF(G29="CÉLULA CONSTRUTIVA",0,IF(G29="ETAPA",OFFSET(C29,-1,0)+1,OFFSET(C29,-1,0))) -> 1 | D29: =IF(G29="ETAPA",0,IF(G29="SUBETAPA",OFFSET(D29,-1,0)+1,OFFSET(D29,-1,0))) -> 2 | E29: =IF(G29="Subetapa",0,IF(G29="serviço",OFFSET(E29,-1,0)+1,OFFSET(E29,-1,0))) -> 0 | G29: Subetapa | H29: =IF(G29="Unidade Construtiva",TEXT(A29,"00"),IF(G29="Célula Construtiva",TEXT(B29,"00"),IF(G29="Etapa",CONCATENATE(TEXT(B29,"00"),".",TEXT(C29,"000")),IF(G29="Subetapa",CONCATENATE(TEXT(B29,"00"),".",TEXT(C29,"000"),".",TEXT(D29,"000")),IF(G29="Serviço",CONCATENATE(TEXT(B29,"00"),".",TEXT(C29,"000"),".",TEXT(D29,"000"),".",TEXT(E29,"000")),""))))) -> 02.001.002 | I29: Mão de obra | L29: =SUM(L30) -> 15950
A30: =IF($G30="UNIDADE CONSTRUTIVA",OFFSET(A30,0,0)+1,LARGE(A$3:A25,1)) -> 2 | B30: =IF(G30="UNIDADE CONSTRUTIVA",0,IF(G30="CÉLULA CONSTRUTIVA",OFFSET(B30,-1,0)+1,OFFSET(B30,-1,0))) -> 2 | C30: =IF(G30="CÉLULA CONSTRUTIVA",0,IF(G30="ETAPA",OFFSET(C30,-1,0)+1,OFFSET(C30,-1,0))) -> 1 | D30: =IF(G30="ETAPA",0,IF(G30="SUBETAPA",OFFSET(D30,-1,0)+1,OFFSET(D30,-1,0))) -> 2 | E30: =IF(G30="Subetapa",0,IF(G30="serviço",OFFSET(E30,-1,0)+1,OFFSET(E30,-1,0))) -> 1 | G30: Serviço | H30: =IF(G30="Unidade Construtiva",TEXT(A30,"00"),IF(G30="Célula Construtiva",TEXT(B30,"00"),IF(G30="Etapa",CONCATENATE(TEXT(B30,"00"),".",TEXT(C30,"000")),IF(G30="Subetapa",CONCATENATE(TEXT(B30,"00"),".",TEXT(C30,"000"),".",TEXT(D30,"000")),IF(G30="Serviço",CONCATENATE(TEXT(B30,"00"),".",TEXT(C30,"000"),".",TEXT(D30,"000"),".",TEXT(E30,"000")),""))))) -> 02.001.002.001 | I30: Mobilização de equipamentos | J30: 1 | K30: un | L30: 15950
A31: =IF($G31="UNIDADE CONSTRUTIVA",OFFSET(A31,0,0)+1,LARGE(A$3:A29,1)) -> 2 | B31: =IF(G31="UNIDADE CONSTRUTIVA",0,IF(G31="CÉLULA CONSTRUTIVA",OFFSET(B31,-1,0)+1,OFFSET(B31,-1,0))) -> 2 | C31: =IF(G31="CÉLULA CONSTRUTIVA",0,IF(G31="ETAPA",OFFSET(C31,-1,0)+1,OFFSET(C31,-1,0))) -> 2 | D31: =IF(G31="ETAPA",0,IF(G31="SUBETAPA",OFFSET(D31,-1,0)+1,OFFSET(D31,-1,0))) -> 0 | E31: =IF(G31="Subetapa",0,IF(G31="serviço",OFFSET(E31,-1,0)+1,OFFSET(E31,-1,0))) -> 1 | G31: ETAPA | H31: =IF(G31="Unidade Construtiva",TEXT(A31,"00"),IF(G31="Célula Construtiva",TEXT(B31,"00"),IF(G31="Etapa",CONCATENATE(TEXT(B31,"00"),".",TEXT(C31,"000")),IF(G31="Subetapa",CONCATENATE(TEXT(B31,"00"),".",TEXT(C31,"000"),".",TEXT(D31,"000")),IF(G31="Serviço",CONCATENATE(TEXT(B31,"00"),".",TEXT(C31,"000"),".",TEXT(D31,"000"),".",TEXT(E31,"000")),""))))) -> 02.002 | I31: FUNDAÇÃO RASA | L31: =SUM(L32:L39)/2 -> 1451014.5
A32: =IF($G32="UNIDADE CONSTRUTIVA",OFFSET(A32,0,0)+1,LARGE(A$3:A31,1)) -> 2 | B32: =IF(G32="UNIDADE CONSTRUTIVA",0,IF(G32="CÉLULA CONSTRUTIVA",OFFSET(B32,-1,0)+1,OFFSET(B32,-1,0))) -> 2 | C32: =IF(G32="CÉLULA CONSTRUTIVA",0,IF(G32="ETAPA",OFFSET(C32,-1,0)+1,OFFSET(C32,-1,0))) -> 2 | D32: =IF(G32="ETAPA",0,IF(G32="SUBETAPA",OFFSET(D32,-1,0)+1,OFFSET(D32,-1,0))) -> 1 | E32: =IF(G32="Subetapa",0,IF(G32="serviço",OFFSET(E32,-1,0)+1,OFFSET(E32,-1,0))) -> 0 | G32: Subetapa | H32: =IF(G32="Unidade Construtiva",TEXT(A32,"00"),IF(G32="Célula Construtiva",TEXT(B32,"00"),IF(G32="Etapa",CONCATENATE(TEXT(B32,"00"),".",TEXT(C32,"000")),IF(G32="Subetapa",CONCATENATE(TEXT(B32,"00"),".",TEXT(C32,"000"),".",TEXT(D32,"000")),IF(G32="Serviço",CONCATENATE(TEXT(B32,"00"),".",TEXT(C32,"000"),".",TEXT(D32,"000"),".",TEXT(E32,"000")),""))))) -> 02.002.001 | I32: Forma | L32: =SUM(L33) -> 159477.34
A33: =IF($G33="UNIDADE CONSTRUTIVA",OFFSET(A33,0,0)+1,LARGE(A$3:A32,1)) -> 2 | B33: =IF(G33="UNIDADE CONSTRUTIVA",0,IF(G33="CÉLULA CONSTRUTIVA",OFFSET(B33,-1,0)+1,OFFSET(B33,-1,0))) -> 2 | C33: =IF(G33="CÉLULA CONSTRUTIVA",0,IF(G33="ETAPA",OFFSET(C33,-1,0)+1,OFFSET(C33,-1,0))) -> 2 | D33: =IF(G33="ETAPA",0,IF(G33="SUBETAPA",OFFSET(D33,-1,0)+1,OFFSET(D33,-1,0))) -> 1 | E33: =IF(G33="Subetapa",0,IF(G33="serviço",OFFSET(E33,-1,0)+1,OFFSET(E33,-1,0))) -> 1 | G33: Serviço | H33: =IF(G33="Unidade Construtiva",TEXT(A33,"00"),IF(G33="Célula Construtiva",TEXT(B33,"00"),IF(G33="Etapa",CONCATENATE(TEXT(B33,"00"),".",TEXT(C33,"000")),IF(G33="Subetapa",CONCATENATE(TEXT(B33,"00"),".",TEXT(C33,"000"),".",TEXT(D33,"000")),IF(G33="Serviço",CONCATENATE(TEXT(B33,"00"),".",TEXT(C33,"000"),".",TEXT(D33,"000"),".",TEXT(E33,"000")),""))))) -> 02.002.001.001 | I33: Fabricação, montagem e desmontagem de forma em madeira serrada para blocos e baldrames | J33: 2132.05 | K33: m² | L33: 159477.34 | M33: Quantitativo de projeto
A34: =IF($G34="UNIDADE CONSTRUTIVA",OFFSET(A34,0,0)+1,LARGE(A$3:A32,1)) -> 2 | B34: =IF(G34="UNIDADE CONSTRUTIVA",0,IF(G34="CÉLULA CONSTRUTIVA",OFFSET(B34,-1,0)+1,OFFSET(B34,-1,0))) -> 2 | C34: =IF(G34="CÉLULA CONSTRUTIVA",0,IF(G34="ETAPA",OFFSET(C34,-1,0)+1,OFFSET(C34,-1,0))) -> 2 | D34: =IF(G34="ETAPA",0,IF(G34="SUBETAPA",OFFSET(D34,-1,0)+1,OFFSET(D34,-1,0))) -> 2 | E34: =IF(G34="Subetapa",0,IF(G34="serviço",OFFSET(E34,-1,0)+1,OFFSET(E34,-1,0))) -> 0 | G34: Subetapa | H34: =IF(G34="Unidade Construtiva",TEXT(A34,"00"),IF(G34="Célula Construtiva",TEXT(B34,"00"),IF(G34="Etapa",CONCATENATE(TEXT(B34,"00"),".",TEXT(C34,"000")),IF(G34="Subetapa",CONCATENATE(TEXT(B34,"00"),".",TEXT(C34,"000"),".",TEXT(D34,"000")),IF(G34="Serviço",CONCATENATE(TEXT(B34,"00"),".",TEXT(C34,"000"),".",TEXT(D34,"000"),".",TEXT(E34,"000")),""))))) -> 02.002.002 | I34: Armadura | L34: =SUM(L35) -> 313625.94
A35: =IF($G35="UNIDADE CONSTRUTIVA",OFFSET(A35,0,0)+1,LARGE(A$3:A33,1)) -> 2 | B35: =IF(G35="UNIDADE CONSTRUTIVA",0,IF(G35="CÉLULA CONSTRUTIVA",OFFSET(B35,-1,0)+1,OFFSET(B35,-1,0))) -> 2 | C35: =IF(G35="CÉLULA CONSTRUTIVA",0,IF(G35="ETAPA",OFFSET(C35,-1,0)+1,OFFSET(C35,-1,0))) -> 2 | D35: =IF(G35="ETAPA",0,IF(G35="SUBETAPA",OFFSET(D35,-1,0)+1,OFFSET(D35,-1,0))) -> 2 | E35: =IF(G35="Subetapa",0,IF(G35="serviço",OFFSET(E35,-1,0)+1,OFFSET(E35,-1,0))) -> 1 | G35: Serviço | H35: =IF(G35="Unidade Construtiva",TEXT(A35,"00"),IF(G35="Célula Construtiva",TEXT(B35,"00"),IF(G35="Etapa",CONCATENATE(TEXT(B35,"00"),".",TEXT(C35,"000")),IF(G35="Subetapa",CONCATENATE(TEXT(B35,"00"),".",TEXT(C35,"000"),".",TEXT(D35,"000")),IF(G35="Serviço",CONCATENATE(TEXT(B35,"00"),".",TEXT(C35,"000"),".",TEXT(D35,"000"),".",TEXT(E35,"000")),""))))) -> 02.002.002.001 | I35: Armadura para blocos e baldrames | J35: 37416.6 | K35: kg | L35: 313625.94 | M35: Adotado taxa de 60 kg/m³
A36: =IF($G36="UNIDADE CONSTRUTIVA",OFFSET(A36,0,0)+1,LARGE(A$3:A34,1)) -> 2 | B36: =IF(G36="UNIDADE CONSTRUTIVA",0,IF(G36="CÉLULA CONSTRUTIVA",OFFSET(B36,-1,0)+1,OFFSET(B36,-1,0))) -> 2 | C36: =IF(G36="CÉLULA CONSTRUTIVA",0,IF(G36="ETAPA",OFFSET(C36,-1,0)+1,OFFSET(C36,-1,0))) -> 2 | D36: =IF(G36="ETAPA",0,IF(G36="SUBETAPA",OFFSET(D36,-1,0)+1,OFFSET(D36,-1,0))) -> 3 | E36: =IF(G36="Subetapa",0,IF(G36="serviço",OFFSET(E36,-1,0)+1,OFFSET(E36,-1,0))) -> 0 | G36: Subetapa | H36: =IF(G36="Unidade Construtiva",TEXT(A36,"00"),IF(G36="Célula Construtiva",TEXT(B36,"00"),IF(G36="Etapa",CONCATENATE(TEXT(B36,"00"),".",TEXT(C36,"000")),IF(G36="Subetapa",CONCATENATE(TEXT(B36,"00"),".",TEXT(C36,"000"),".",TEXT(D36,"000")),IF(G36="Serviço",CONCATENATE(TEXT(B36,"00"),".",TEXT(C36,"000"),".",TEXT(D36,"000"),".",TEXT(E36,"000")),""))))) -> 02.002.003 | I36: Concreto | L36: =SUM(L37) -> 401910.41
A37: =IF($G37="UNIDADE CONSTRUTIVA",OFFSET(A37,0,0)+1,LARGE(A$3:A35,1)) -> 2 | B37: =IF(G37="UNIDADE CONSTRUTIVA",0,IF(G37="CÉLULA CONSTRUTIVA",OFFSET(B37,-1,0)+1,OFFSET(B37,-1,0))) -> 2 | C37: =IF(G37="CÉLULA CONSTRUTIVA",0,IF(G37="ETAPA",OFFSET(C37,-1,0)+1,OFFSET(C37,-1,0))) -> 2 | D37: =IF(G37="ETAPA",0,IF(G37="SUBETAPA",OFFSET(D37,-1,0)+1,OFFSET(D37,-1,0))) -> 3 | E37: =IF(G37="Subetapa",0,IF(G37="serviço",OFFSET(E37,-1,0)+1,OFFSET(E37,-1,0))) -> 1 | G37: Serviço | H37: =IF(G37="Unidade Construtiva",TEXT(A37,"00"),IF(G37="Célula Construtiva",TEXT(B37,"00"),IF(G37="Etapa",CONCATENATE(TEXT(B37,"00"),".",TEXT(C37,"000")),IF(G37="Subetapa",CONCATENATE(TEXT(B37,"00"),".",TEXT(C37,"000"),".",TEXT(D37,"000")),IF(G37="Serviço",CONCATENATE(TEXT(B37,"00"),".",TEXT(C37,"000"),".",TEXT(D37,"000"),".",TEXT(E37,"000")),""))))) -> 02.002.003.001 | I37: Concreto para blocos e baldrames | J37: 623.61 | K37: m³ | L37: 401910.41 | M37: Quantitativo de projeto
A38: =IF($G38="UNIDADE CONSTRUTIVA",OFFSET(A38,0,0)+1,LARGE(A$3:A36,1)) -> 2 | B38: =IF(G38="UNIDADE CONSTRUTIVA",0,IF(G38="CÉLULA CONSTRUTIVA",OFFSET(B38,-1,0)+1,OFFSET(B38,-1,0))) -> 2 | C38: =IF(G38="CÉLULA CONSTRUTIVA",0,IF(G38="ETAPA",OFFSET(C38,-1,0)+1,OFFSET(C38,-1,0))) -> 2 | D38: =IF(G38="ETAPA",0,IF(G38="SUBETAPA",OFFSET(D38,-1,0)+1,OFFSET(D38,-1,0))) -> 4 | E38: =IF(G38="Subetapa",0,IF(G38="serviço",OFFSET(E38,-1,0)+1,OFFSET(E38,-1,0))) -> 0 | G38: Subetapa | H38: =IF(G38="Unidade Construtiva",TEXT(A38,"00"),IF(G38="Célula Construtiva",TEXT(B38,"00"),IF(G38="Etapa",CONCATENATE(TEXT(B38,"00"),".",TEXT(C38,"000")),IF(G38="Subetapa",CONCATENATE(TEXT(B38,"00"),".",TEXT(C38,"000"),".",TEXT(D38,"000")),IF(G38="Serviço",CONCATENATE(TEXT(B38,"00"),".",TEXT(C38,"000"),".",TEXT(D38,"000"),".",TEXT(E38,"000")),""))))) -> 02.002.004 | I38: Mão de obra | L38: =SUM(L39) -> 576000.81
A39: =IF($G39="UNIDADE CONSTRUTIVA",OFFSET(A39,0,0)+1,LARGE(A$3:A37,1)) -> 2 | B39: =IF(G39="UNIDADE CONSTRUTIVA",0,IF(G39="CÉLULA CONSTRUTIVA",OFFSET(B39,-1,0)+1,OFFSET(B39,-1,0))) -> 2 | C39: =IF(G39="CÉLULA CONSTRUTIVA",0,IF(G39="ETAPA",OFFSET(C39,-1,0)+1,OFFSET(C39,-1,0))) -> 2 | D39: =IF(G39="ETAPA",0,IF(G39="SUBETAPA",OFFSET(D39,-1,0)+1,OFFSET(D39,-1,0))) -> 4 | E39: =IF(G39="Subetapa",0,IF(G39="serviço",OFFSET(E39,-1,0)+1,OFFSET(E39,-1,0))) -> 1 | G39: Serviço | H39: =IF(G39="Unidade Construtiva",TEXT(A39,"00"),IF(G39="Célula Construtiva",TEXT(B39,"00"),IF(G39="Etapa",CONCATENATE(TEXT(B39,"00"),".",TEXT(C39,"000")),IF(G39="Subetapa",CONCATENATE(TEXT(B39,"00"),".",TEXT(C39,"000"),".",TEXT(D39,"000")),IF(G39="Serviço",CONCATENATE(TEXT(B39,"00"),".",TEXT(C39,"000"),".",TEXT(D39,"000"),".",TEXT(E39,"000")),""))))) -> 02.002.004.001 | I39: Mão de obra infraestrutura | J39: 1662.34 | K39: m² | L39: 576000.81 | M39: Area de projeção do embasamento
A40: =IF($G40="UNIDADE CONSTRUTIVA",OFFSET(A40,0,0)+1,LARGE(A$3:A38,1)) -> 2 | B40: =IF(G40="UNIDADE CONSTRUTIVA",0,IF(G40="CÉLULA CONSTRUTIVA",OFFSET(B40,-1,0)+1,OFFSET(B40,-1,0))) -> 3 | C40: =IF(G40="CÉLULA CONSTRUTIVA",0,IF(G40="ETAPA",OFFSET(C40,-1,0)+1,OFFSET(C40,-1,0))) -> 0 | D40: =IF(G40="ETAPA",0,IF(G40="SUBETAPA",OFFSET(D40,-1,0)+1,OFFSET(D40,-1,0))) -> 4 | E40: =IF(G40="Subetapa",0,IF(G40="serviço",OFFSET(E40,-1,0)+1,OFFSET(E40,-1,0))) -> 1 | G40: CÉLULA CONSTRUTIVA | H40: =IF(G40="Unidade Construtiva",TEXT(A40,"00"),IF(G40="Célula Construtiva",TEXT(B40,"00"),IF(G40="Etapa",CONCATENATE(TEXT(B40,"00"),".",TEXT(C40,"000")),IF(G40="Subetapa",CONCATENATE(TEXT(B40,"00"),".",TEXT(C40,"000"),".",TEXT(D40,"000")),IF(G40="Serviço",CONCATENATE(TEXT(B40,"00"),".",TEXT(C40,"000"),".",TEXT(D40,"000"),".",TEXT(E40,"000")),""))))) -> 03 | I40: SUPRAESTRUTURA | L40: =L41 -> 4644536.7
A41: =IF($G41="UNIDADE CONSTRUTIVA",OFFSET(A41,0,0)+1,LARGE(A$3:A40,1)) -> 2 | B41: =IF(G41="UNIDADE CONSTRUTIVA",0,IF(G41="CÉLULA CONSTRUTIVA",OFFSET(B41,-1,0)+1,OFFSET(B41,-1,0))) -> 3 | C41: =IF(G41="CÉLULA CONSTRUTIVA",0,IF(G41="ETAPA",OFFSET(C41,-1,0)+1,OFFSET(C41,-1,0))) -> 1 | D41: =IF(G41="ETAPA",0,IF(G41="SUBETAPA",OFFSET(D41,-1,0)+1,OFFSET(D41,-1,0))) -> 0 | E41: =IF(G41="Subetapa",0,IF(G41="serviço",OFFSET(E41,-1,0)+1,OFFSET(E41,-1,0))) -> 1 | G41: ETAPA | H41: =IF(G41="Unidade Construtiva",TEXT(A41,"00"),IF(G41="Célula Construtiva",TEXT(B41,"00"),IF(G41="Etapa",CONCATENATE(TEXT(B41,"00"),".",TEXT(C41,"000")),IF(G41="Subetapa",CONCATENATE(TEXT(B41,"00"),".",TEXT(C41,"000"),".",TEXT(D41,"000")),IF(G41="Serviço",CONCATENATE(TEXT(B41,"00"),".",TEXT(C41,"000"),".",TEXT(D41,"000"),".",TEXT(E41,"000")),""))))) -> 03.001 | I41: SUPRAESTRUTURA | L41: =SUM(L42:L53)/2 -> 4644536.7
A42: =IF($G42="UNIDADE CONSTRUTIVA",OFFSET(A42,0,0)+1,LARGE(A$3:A41,1)) -> 2 | B42: =IF(G42="UNIDADE CONSTRUTIVA",0,IF(G42="CÉLULA CONSTRUTIVA",OFFSET(B42,-1,0)+1,OFFSET(B42,-1,0))) -> 3 | C42: =IF(G42="CÉLULA CONSTRUTIVA",0,IF(G42="ETAPA",OFFSET(C42,-1,0)+1,OFFSET(C42,-1,0))) -> 1 | D42: =IF(G42="ETAPA",0,IF(G42="SUBETAPA",OFFSET(D42,-1,0)+1,OFFSET(D42,-1,0))) -> 1 | E42: =IF(G42="Subetapa",0,IF(G42="serviço",OFFSET(E42,-1,0)+1,OFFSET(E42,-1,0))) -> 0 | G42: Subetapa | H42: =IF(G42="Unidade Construtiva",TEXT(A42,"00"),IF(G42="Célula Construtiva",TEXT(B42,"00"),IF(G42="Etapa",CONCATENATE(TEXT(B42,"00"),".",TEXT(C42,"000")),IF(G42="Subetapa",CONCATENATE(TEXT(B42,"00"),".",TEXT(C42,"000"),".",TEXT(D42,"000")),IF(G42="Serviço",CONCATENATE(TEXT(B42,"00"),".",TEXT(C42,"000"),".",TEXT(D42,"000"),".",TEXT(E42,"000")),""))))) -> 03.001.001 | I42: Forma | L42: =SUM(L43:L44) -> 582026.13
A43: =IF($G43="UNIDADE CONSTRUTIVA",OFFSET(A43,0,0)+1,LARGE(A$3:A42,1)) -> 2 | B43: =IF(G43="UNIDADE CONSTRUTIVA",0,IF(G43="CÉLULA CONSTRUTIVA",OFFSET(B43,-1,0)+1,OFFSET(B43,-1,0))) -> 3 | C43: =IF(G43="CÉLULA CONSTRUTIVA",0,IF(G43="ETAPA",OFFSET(C43,-1,0)+1,OFFSET(C43,-1,0))) -> 1 | D43: =IF(G43="ETAPA",0,IF(G43="SUBETAPA",OFFSET(D43,-1,0)+1,OFFSET(D43,-1,0))) -> 1 | E43: =IF(G43="Subetapa",0,IF(G43="serviço",OFFSET(E43,-1,0)+1,OFFSET(E43,-1,0))) -> 1 | G43: Serviço | H43: =IF(G43="Unidade Construtiva",TEXT(A43,"00"),IF(G43="Célula Construtiva",TEXT(B43,"00"),IF(G43="Etapa",CONCATENATE(TEXT(B43,"00"),".",TEXT(C43,"000")),IF(G43="Subetapa",CONCATENATE(TEXT(B43,"00"),".",TEXT(C43,"000"),".",TEXT(D43,"000")),IF(G43="Serviço",CONCATENATE(TEXT(B43,"00"),".",TEXT(C43,"000"),".",TEXT(D43,"000"),".",TEXT(E43,"000")),""))))) -> 03.001.001.001 | I43: Fabricação de forma para pilares, lajes, vigas, escadas e rampas | J43: 4551.524 | K43: m² | L43: 550734.4 | M43: Adotado fabricação de 2 jogos referentes ao 2º pav
A44: =IF($G44="UNIDADE CONSTRUTIVA",OFFSET(A44,0,0)+1,LARGE(A$3:A43,1)) -> 2 | B44: =IF(G44="UNIDADE CONSTRUTIVA",0,IF(G44="CÉLULA CONSTRUTIVA",OFFSET(B44,-1,0)+1,OFFSET(B44,-1,0))) -> 3 | C44: =IF(G44="CÉLULA CONSTRUTIVA",0,IF(G44="ETAPA",OFFSET(C44,-1,0)+1,OFFSET(C44,-1,0))) -> 1 | D44: =IF(G44="ETAPA",0,IF(G44="SUBETAPA",OFFSET(D44,-1,0)+1,OFFSET(D44,-1,0))) -> 1 | E44: =IF(G44="Subetapa",0,IF(G44="serviço",OFFSET(E44,-1,0)+1,OFFSET(E44,-1,0))) -> 2 | G44: Serviço | H44: =IF(G44="Unidade Construtiva",TEXT(A44,"00"),IF(G44="Célula Construtiva",TEXT(B44,"00"),IF(G44="Etapa",CONCATENATE(TEXT(B44,"00"),".",TEXT(C44,"000")),IF(G44="Subetapa",CONCATENATE(TEXT(B44,"00"),".",TEXT(C44,"000"),".",TEXT(D44,"000")),IF(G44="Serviço",CONCATENATE(TEXT(B44,"00"),".",TEXT(C44,"000"),".",TEXT(D44,"000"),".",TEXT(E44,"000")),""))))) -> 03.001.001.002 | I44: Montagem e desmontagem de forma para pilares, lajes, vigas, escadas e rampas | J44: 11378.81 | K44: m² | L44: 31291.728 | M44: Quantitativo de projeto
A45: =IF($G45="UNIDADE CONSTRUTIVA",OFFSET(A45,0,0)+1,LARGE(A$3:A42,1)) -> 2 | B45: =IF(G45="UNIDADE CONSTRUTIVA",0,IF(G45="CÉLULA CONSTRUTIVA",OFFSET(B45,-1,0)+1,OFFSET(B45,-1,0))) -> 3 | C45: =IF(G45="CÉLULA CONSTRUTIVA",0,IF(G45="ETAPA",OFFSET(C45,-1,0)+1,OFFSET(C45,-1,0))) -> 1 | D45: =IF(G45="ETAPA",0,IF(G45="SUBETAPA",OFFSET(D45,-1,0)+1,OFFSET(D45,-1,0))) -> 2 | E45: =IF(G45="Subetapa",0,IF(G45="serviço",OFFSET(E45,-1,0)+1,OFFSET(E45,-1,0))) -> 0 | G45: Subetapa | H45: =IF(G45="Unidade Construtiva",TEXT(A45,"00"),IF(G45="Célula Construtiva",TEXT(B45,"00"),IF(G45="Etapa",CONCATENATE(TEXT(B45,"00"),".",TEXT(C45,"000")),IF(G45="Subetapa",CONCATENATE(TEXT(B45,"00"),".",TEXT(C45,"000"),".",TEXT(D45,"000")),IF(G45="Serviço",CONCATENATE(TEXT(B45,"00"),".",TEXT(C45,"000"),".",TEXT(D45,"000"),".",TEXT(E45,"000")),""))))) -> 03.001.002 | I45: Armadura | L45: =SUM(L46) -> 1364688.5
A46: =IF($G46="UNIDADE CONSTRUTIVA",OFFSET(A46,0,0)+1,LARGE(A$3:A43,1)) -> 2 | B46: =IF(G46="UNIDADE CONSTRUTIVA",0,IF(G46="CÉLULA CONSTRUTIVA",OFFSET(B46,-1,0)+1,OFFSET(B46,-1,0))) -> 3 | C46: =IF(G46="CÉLULA CONSTRUTIVA",0,IF(G46="ETAPA",OFFSET(C46,-1,0)+1,OFFSET(C46,-1,0))) -> 1 | D46: =IF(G46="ETAPA",0,IF(G46="SUBETAPA",OFFSET(D46,-1,0)+1,OFFSET(D46,-1,0))) -> 2 | E46: =IF(G46="Subetapa",0,IF(G46="serviço",OFFSET(E46,-1,0)+1,OFFSET(E46,-1,0))) -> 1 | G46: Serviço | H46: =IF(G46="Unidade Construtiva",TEXT(A46,"00"),IF(G46="Célula Construtiva",TEXT(B46,"00"),IF(G46="Etapa",CONCATENATE(TEXT(B46,"00"),".",TEXT(C46,"000")),IF(G46="Subetapa",CONCATENATE(TEXT(B46,"00"),".",TEXT(C46,"000"),".",TEXT(D46,"000")),IF(G46="Serviço",CONCATENATE(TEXT(B46,"00"),".",TEXT(C46,"000"),".",TEXT(D46,"000"),".",TEXT(E46,"000")),""))))) -> 03.001.002.001 | I46: Armadura para supraestrutura | J46: 162811.8 | K46: kg | L46: 1364688.5 | M46: Adotado taxa de 90 kg/m³
A47: =IF($G47="UNIDADE CONSTRUTIVA",OFFSET(A47,0,0)+1,LARGE(A$3:A45,1)) -> 2 | B47: =IF(G47="UNIDADE CONSTRUTIVA",0,IF(G47="CÉLULA CONSTRUTIVA",OFFSET(B47,-1,0)+1,OFFSET(B47,-1,0))) -> 3 | C47: =IF(G47="CÉLULA CONSTRUTIVA",0,IF(G47="ETAPA",OFFSET(C47,-1,0)+1,OFFSET(C47,-1,0))) -> 1 | D47: =IF(G47="ETAPA",0,IF(G47="SUBETAPA",OFFSET(D47,-1,0)+1,OFFSET(D47,-1,0))) -> 3 | E47: =IF(G47="Subetapa",0,IF(G47="serviço",OFFSET(E47,-1,0)+1,OFFSET(E47,-1,0))) -> 0 | G47: Subetapa | H47: =IF(G47="Unidade Construtiva",TEXT(A47,"00"),IF(G47="Célula Construtiva",TEXT(B47,"00"),IF(G47="Etapa",CONCATENATE(TEXT(B47,"00"),".",TEXT(C47,"000")),IF(G47="Subetapa",CONCATENATE(TEXT(B47,"00"),".",TEXT(C47,"000"),".",TEXT(D47,"000")),IF(G47="Serviço",CONCATENATE(TEXT(B47,"00"),".",TEXT(C47,"000"),".",TEXT(D47,"000"),".",TEXT(E47,"000")),""))))) -> 03.001.003 | I47: Concreto | L47: =SUM(L48) -> 1165895.3
A48: =IF($G48="UNIDADE CONSTRUTIVA",OFFSET(A48,0,0)+1,LARGE(A$3:A46,1)) -> 2 | B48: =IF(G48="UNIDADE CONSTRUTIVA",0,IF(G48="CÉLULA CONSTRUTIVA",OFFSET(B48,-1,0)+1,OFFSET(B48,-1,0))) -> 3 | C48: =IF(G48="CÉLULA CONSTRUTIVA",0,IF(G48="ETAPA",OFFSET(C48,-1,0)+1,OFFSET(C48,-1,0))) -> 1 | D48: =IF(G48="ETAPA",0,IF(G48="SUBETAPA",OFFSET(D48,-1,0)+1,OFFSET(D48,-1,0))) -> 3 | E48: =IF(G48="Subetapa",0,IF(G48="serviço",OFFSET(E48,-1,0)+1,OFFSET(E48,-1,0))) -> 1 | G48: Serviço | H48: =IF(G48="Unidade Construtiva",TEXT(A48,"00"),IF(G48="Célula Construtiva",TEXT(B48,"00"),IF(G48="Etapa",CONCATENATE(TEXT(B48,"00"),".",TEXT(C48,"000")),IF(G48="Subetapa",CONCATENATE(TEXT(B48,"00"),".",TEXT(C48,"000"),".",TEXT(D48,"000")),IF(G48="Serviço",CONCATENATE(TEXT(B48,"00"),".",TEXT(C48,"000"),".",TEXT(D48,"000"),".",TEXT(E48,"000")),""))))) -> 03.001.003.001 | I48: Concreto para supraestrutura | J48: 1809.02 | K48: m³ | L48: 1165895.3 | M48: Quantitativo de projeto
A49: =IF($G49="UNIDADE CONSTRUTIVA",OFFSET(A49,0,0)+1,LARGE(A$3:A47,1)) -> 2 | B49: =IF(G49="UNIDADE CONSTRUTIVA",0,IF(G49="CÉLULA CONSTRUTIVA",OFFSET(B49,-1,0)+1,OFFSET(B49,-1,0))) -> 3 | C49: =IF(G49="CÉLULA CONSTRUTIVA",0,IF(G49="ETAPA",OFFSET(C49,-1,0)+1,OFFSET(C49,-1,0))) -> 1 | D49: =IF(G49="ETAPA",0,IF(G49="SUBETAPA",OFFSET(D49,-1,0)+1,OFFSET(D49,-1,0))) -> 4 | E49: =IF(G49="Subetapa",0,IF(G49="serviço",OFFSET(E49,-1,0)+1,OFFSET(E49,-1,0))) -> 0 | G49: Subetapa | H49: =IF(G49="Unidade Construtiva",TEXT(A49,"00"),IF(G49="Célula Construtiva",TEXT(B49,"00"),IF(G49="Etapa",CONCATENATE(TEXT(B49,"00"),".",TEXT(C49,"000")),IF(G49="Subetapa",CONCATENATE(TEXT(B49,"00"),".",TEXT(C49,"000"),".",TEXT(D49,"000")),IF(G49="Serviço",CONCATENATE(TEXT(B49,"00"),".",TEXT(C49,"000"),".",TEXT(D49,"000"),".",TEXT(E49,"000")),""))))) -> 03.001.004 | I49: Complementares | L49: =SUM(L50) -> 126318.5
A50: =IF($G50="UNIDADE CONSTRUTIVA",OFFSET(A50,0,0)+1,LARGE(A$3:A48,1)) -> 2 | B50: =IF(G50="UNIDADE CONSTRUTIVA",0,IF(G50="CÉLULA CONSTRUTIVA",OFFSET(B50,-1,0)+1,OFFSET(B50,-1,0))) -> 3 | C50: =IF(G50="CÉLULA CONSTRUTIVA",0,IF(G50="ETAPA",OFFSET(C50,-1,0)+1,OFFSET(C50,-1,0))) -> 1 | D50: =IF(G50="ETAPA",0,IF(G50="SUBETAPA",OFFSET(D50,-1,0)+1,OFFSET(D50,-1,0))) -> 4 | E50: =IF(G50="Subetapa",0,IF(G50="serviço",OFFSET(E50,-1,0)+1,OFFSET(E50,-1,0))) -> 1 | G50: Serviço | H50: =IF(G50="Unidade Construtiva",TEXT(A50,"00"),IF(G50="Célula Construtiva",TEXT(B50,"00"),IF(G50="Etapa",CONCATENATE(TEXT(B50,"00"),".",TEXT(C50,"000")),IF(G50="Subetapa",CONCATENATE(TEXT(B50,"00"),".",TEXT(C50,"000"),".",TEXT(D50,"000")),IF(G50="Serviço",CONCATENATE(TEXT(B50,"00"),".",TEXT(C50,"000"),".",TEXT(D50,"000"),".",TEXT(E50,"000")),""))))) -> 03.001.004.001 | I50: Locação de escoramento metálico | J50: 6755 | K50: un | L50: 126318.5 | M50: Adotado locação de 2 jogos referentes ao 2º pav, com reaproveitamento
A51: =IF($G51="UNIDADE CONSTRUTIVA",OFFSET(A51,0,0)+1,LARGE(A$3:A47,1)) -> 2 | B51: =IF(G51="UNIDADE CONSTRUTIVA",0,IF(G51="CÉLULA CONSTRUTIVA",OFFSET(B51,-1,0)+1,OFFSET(B51,-1,0))) -> 3 | C51: =IF(G51="CÉLULA CONSTRUTIVA",0,IF(G51="ETAPA",OFFSET(C51,-1,0)+1,OFFSET(C51,-1,0))) -> 1 | D51: =IF(G51="ETAPA",0,IF(G51="SUBETAPA",OFFSET(D51,-1,0)+1,OFFSET(D51,-1,0))) -> 5 | E51: =IF(G51="Subetapa",0,IF(G51="serviço",OFFSET(E51,-1,0)+1,OFFSET(E51,-1,0))) -> 0 | G51: Subetapa | H51: =IF(G51="Unidade Construtiva",TEXT(A51,"00"),IF(G51="Célula Construtiva",TEXT(B51,"00"),IF(G51="Etapa",CONCATENATE(TEXT(B51,"00"),".",TEXT(C51,"000")),IF(G51="Subetapa",CONCATENATE(TEXT(B51,"00"),".",TEXT(C51,"000"),".",TEXT(D51,"000")),IF(G51="Serviço",CONCATENATE(TEXT(B51,"00"),".",TEXT(C51,"000"),".",TEXT(D51,"000"),".",TEXT(E51,"000")),""))))) -> 03.001.005 | I51: Mão de obra | L51: =SUM(L52:L53) -> 1405608.3
A52: =IF($G52="UNIDADE CONSTRUTIVA",OFFSET(A52,0,0)+1,LARGE(A$3:A47,1)) -> 2 | B52: =IF(G52="UNIDADE CONSTRUTIVA",0,IF(G52="CÉLULA CONSTRUTIVA",OFFSET(B52,-1,0)+1,OFFSET(B52,-1,0))) -> 3 | C52: =IF(G52="CÉLULA CONSTRUTIVA",0,IF(G52="ETAPA",OFFSET(C52,-1,0)+1,OFFSET(C52,-1,0))) -> 1 | D52: =IF(G52="ETAPA",0,IF(G52="SUBETAPA",OFFSET(D52,-1,0)+1,OFFSET(D52,-1,0))) -> 5 | E52: =IF(G52="Subetapa",0,IF(G52="serviço",OFFSET(E52,-1,0)+1,OFFSET(E52,-1,0))) -> 1 | G52: Serviço | H52: =IF(G52="Unidade Construtiva",TEXT(A52,"00"),IF(G52="Célula Construtiva",TEXT(B52,"00"),IF(G52="Etapa",CONCATENATE(TEXT(B52,"00"),".",TEXT(C52,"000")),IF(G52="Subetapa",CONCATENATE(TEXT(B52,"00"),".",TEXT(C52,"000"),".",TEXT(D52,"000")),IF(G52="Serviço",CONCATENATE(TEXT(B52,"00"),".",TEXT(C52,"000"),".",TEXT(D52,"000"),".",TEXT(E52,"000")),""))))) -> 03.001.005.001 | I52: Mão de obra para supraestrutura | J52: 6049.17 | K52: m² | L52: 1397358.3 | M52: area contruída
A53: =IF($G53="UNIDADE CONSTRUTIVA",OFFSET(A53,0,0)+1,LARGE(A$3:A48,1)) -> 2 | B53: =IF(G53="UNIDADE CONSTRUTIVA",0,IF(G53="CÉLULA CONSTRUTIVA",OFFSET(B53,-1,0)+1,OFFSET(B53,-1,0))) -> 3 | C53: =IF(G53="CÉLULA CONSTRUTIVA",0,IF(G53="ETAPA",OFFSET(C53,-1,0)+1,OFFSET(C53,-1,0))) -> 1 | D53: =IF(G53="ETAPA",0,IF(G53="SUBETAPA",OFFSET(D53,-1,0)+1,OFFSET(D53,-1,0))) -> 5 | E53: =IF(G53="Subetapa",0,IF(G53="serviço",OFFSET(E53,-1,0)+1,OFFSET(E53,-1,0))) -> 2 | G53: Serviço | H53: =IF(G53="Unidade Construtiva",TEXT(A53,"00"),IF(G53="Célula Construtiva",TEXT(B53,"00"),IF(G53="Etapa",CONCATENATE(TEXT(B53,"00"),".",TEXT(C53,"000")),IF(G53="Subetapa",CONCATENATE(TEXT(B53,"00"),".",TEXT(C53,"000"),".",TEXT(D53,"000")),IF(G53="Serviço",CONCATENATE(TEXT(B53,"00"),".",TEXT(C53,"000"),".",TEXT(D53,"000"),".",TEXT(E53,"000")),""))))) -> 03.001.005.002 | I53: Perfuração de vigas | J53: 1 | K53: vb | L53: 8250 | M53: Valor previsto para esperas ou furação posterior
A54: =IF($G54="UNIDADE CONSTRUTIVA",OFFSET(A54,0,0)+1,LARGE(A$3:A53,1)) -> 2 | B54: =IF(G54="UNIDADE CONSTRUTIVA",0,IF(G54="CÉLULA CONSTRUTIVA",OFFSET(B54,-1,0)+1,OFFSET(B54,-1,0))) -> 4 | C54: =IF(G54="CÉLULA CONSTRUTIVA",0,IF(G54="ETAPA",OFFSET(C54,-1,0)+1,OFFSET(C54,-1,0))) -> 0 | D54: =IF(G54="ETAPA",0,IF(G54="SUBETAPA",OFFSET(D54,-1,0)+1,OFFSET(D54,-1,0))) -> 5 | E54: =IF(G54="Subetapa",0,IF(G54="serviço",OFFSET(E54,-1,0)+1,OFFSET(E54,-1,0))) -> 2 | G54: CÉLULA CONSTRUTIVA | H54: =IF(G54="Unidade Construtiva",TEXT(A54,"00"),IF(G54="Célula Construtiva",TEXT(B54,"00"),IF(G54="Etapa",CONCATENATE(TEXT(B54,"00"),".",TEXT(C54,"000")),IF(G54="Subetapa",CONCATENATE(TEXT(B54,"00"),".",TEXT(C54,"000"),".",TEXT(D54,"000")),IF(G54="Serviço",CONCATENATE(TEXT(B54,"00"),".",TEXT(C54,"000"),".",TEXT(D54,"000"),".",TEXT(E54,"000")),""))))) -> 04 | I54: PAREDES E PAINÉIS | L54: =L55 -> 2968837.7
A55: =IF($G55="UNIDADE CONSTRUTIVA",OFFSET(A55,0,0)+1,LARGE(A$3:A54,1)) -> 2 | B55: =IF(G55="UNIDADE CONSTRUTIVA",0,IF(G55="CÉLULA CONSTRUTIVA",OFFSET(B55,-1,0)+1,OFFSET(B55,-1,0))) -> 4 | C55: =IF(G55="CÉLULA CONSTRUTIVA",0,IF(G55="ETAPA",OFFSET(C55,-1,0)+1,OFFSET(C55,-1,0))) -> 1 | D55: =IF(G55="ETAPA",0,IF(G55="SUBETAPA",OFFSET(D55,-1,0)+1,OFFSET(D55,-1,0))) -> 0 | E55: =IF(G55="Subetapa",0,IF(G55="serviço",OFFSET(E55,-1,0)+1,OFFSET(E55,-1,0))) -> 2 | G55: ETAPA | H55: =IF(G55="Unidade Construtiva",TEXT(A55,"00"),IF(G55="Célula Construtiva",TEXT(B55,"00"),IF(G55="Etapa",CONCATENATE(TEXT(B55,"00"),".",TEXT(C55,"000")),IF(G55="Subetapa",CONCATENATE(TEXT(B55,"00"),".",TEXT(C55,"000"),".",TEXT(D55,"000")),IF(G55="Serviço",CONCATENATE(TEXT(B55,"00"),".",TEXT(C55,"000"),".",TEXT(D55,"000"),".",TEXT(E55,"000")),""))))) -> 04.001 | I55: PAREDES E PAINÉIS | L55: =SUM(L56:L73)/2 -> 2968837.7
A56: =IF($G56="UNIDADE CONSTRUTIVA",OFFSET(A56,0,0)+1,LARGE(A$3:A55,1)) -> 2 | B56: =IF(G56="UNIDADE CONSTRUTIVA",0,IF(G56="CÉLULA CONSTRUTIVA",OFFSET(B56,-1,0)+1,OFFSET(B56,-1,0))) -> 4 | C56: =IF(G56="CÉLULA CONSTRUTIVA",0,IF(G56="ETAPA",OFFSET(C56,-1,0)+1,OFFSET(C56,-1,0))) -> 1 | D56: =IF(G56="ETAPA",0,IF(G56="SUBETAPA",OFFSET(D56,-1,0)+1,OFFSET(D56,-1,0))) -> 1 | E56: =IF(G56="Subetapa",0,IF(G56="serviço",OFFSET(E56,-1,0)+1,OFFSET(E56,-1,0))) -> 0 | G56: Subetapa | H56: =IF(G56="Unidade Construtiva",TEXT(A56,"00"),IF(G56="Célula Construtiva",TEXT(B56,"00"),IF(G56="Etapa",CONCATENATE(TEXT(B56,"00"),".",TEXT(C56,"000")),IF(G56="Subetapa",CONCATENATE(TEXT(B56,"00"),".",TEXT(C56,"000"),".",TEXT(D56,"000")),IF(G56="Serviço",CONCATENATE(TEXT(B56,"00"),".",TEXT(C56,"000"),".",TEXT(D56,"000"),".",TEXT(E56,"000")),""))))) -> 04.001.001 | I56: Alvenaria de vedação com blocos cerâmicos | L56: =SUM(L57) -> 0
A57: =IF($G57="UNIDADE CONSTRUTIVA",OFFSET(A57,0,0)+1,LARGE(A$3:A56,1)) -> 2 | B57: =IF(G57="UNIDADE CONSTRUTIVA",0,IF(G57="CÉLULA CONSTRUTIVA",OFFSET(B57,-1,0)+1,OFFSET(B57,-1,0))) -> 4 | C57: =IF(G57="CÉLULA CONSTRUTIVA",0,IF(G57="ETAPA",OFFSET(C57,-1,0)+1,OFFSET(C57,-1,0))) -> 1 | D57: =IF(G57="ETAPA",0,IF(G57="SUBETAPA",OFFSET(D57,-1,0)+1,OFFSET(D57,-1,0))) -> 1 | E57: =IF(G57="Subetapa",0,IF(G57="serviço",OFFSET(E57,-1,0)+1,OFFSET(E57,-1,0))) -> 1 | G57: Serviço | H57: =IF(G57="Unidade Construtiva",TEXT(A57,"00"),IF(G57="Célula Construtiva",TEXT(B57,"00"),IF(G57="Etapa",CONCATENATE(TEXT(B57,"00"),".",TEXT(C57,"000")),IF(G57="Subetapa",CONCATENATE(TEXT(B57,"00"),".",TEXT(C57,"000"),".",TEXT(D57,"000")),IF(G57="Serviço",CONCATENATE(TEXT(B57,"00"),".",TEXT(C57,"000"),".",TEXT(D57,"000"),".",TEXT(E57,"000")),""))))) -> 04.001.001.001 | I57: Alvenaria de vedação com blocos cerâmicos | M57: Fechamento externo do residencial
A58: =IF($G58="UNIDADE CONSTRUTIVA",OFFSET(A58,0,0)+1,LARGE(A$3:A56,1)) -> 2 | B58: =IF(G58="UNIDADE CONSTRUTIVA",0,IF(G58="CÉLULA CONSTRUTIVA",OFFSET(B58,-1,0)+1,OFFSET(B58,-1,0))) -> 4 | C58: =IF(G58="CÉLULA CONSTRUTIVA",0,IF(G58="ETAPA",OFFSET(C58,-1,0)+1,OFFSET(C58,-1,0))) -> 1 | D58: =IF(G58="ETAPA",0,IF(G58="SUBETAPA",OFFSET(D58,-1,0)+1,OFFSET(D58,-1,0))) -> 2 | E58: =IF(G58="Subetapa",0,IF(G58="serviço",OFFSET(E58,-1,0)+1,OFFSET(E58,-1,0))) -> 0 | G58: Subetapa | H58: =IF(G58="Unidade Construtiva",TEXT(A58,"00"),IF(G58="Célula Construtiva",TEXT(B58,"00"),IF(G58="Etapa",CONCATENATE(TEXT(B58,"00"),".",TEXT(C58,"000")),IF(G58="Subetapa",CONCATENATE(TEXT(B58,"00"),".",TEXT(C58,"000"),".",TEXT(D58,"000")),IF(G58="Serviço",CONCATENATE(TEXT(B58,"00"),".",TEXT(C58,"000"),".",TEXT(D58,"000"),".",TEXT(E58,"000")),""))))) -> 04.001.002 | I58: Alvenaria de vedação com bocos de concreto | L58: =SUM(L59:L60) -> 256936.85
A59: =IF($G59="UNIDADE CONSTRUTIVA",OFFSET(A59,0,0)+1,LARGE(A$3:A58,1)) -> 2 | B59: =IF(G59="UNIDADE CONSTRUTIVA",0,IF(G59="CÉLULA CONSTRUTIVA",OFFSET(B59,-1,0)+1,OFFSET(B59,-1,0))) -> 4 | C59: =IF(G59="CÉLULA CONSTRUTIVA",0,IF(G59="ETAPA",OFFSET(C59,-1,0)+1,OFFSET(C59,-1,0))) -> 1 | D59: =IF(G59="ETAPA",0,IF(G59="SUBETAPA",OFFSET(D59,-1,0)+1,OFFSET(D59,-1,0))) -> 2 | E59: =IF(G59="Subetapa",0,IF(G59="serviço",OFFSET(E59,-1,0)+1,OFFSET(E59,-1,0))) -> 1 | G59: Serviço | H59: =IF(G59="Unidade Construtiva",TEXT(A59,"00"),IF(G59="Célula Construtiva",TEXT(B59,"00"),IF(G59="Etapa",CONCATENATE(TEXT(B59,"00"),".",TEXT(C59,"000")),IF(G59="Subetapa",CONCATENATE(TEXT(B59,"00"),".",TEXT(C59,"000"),".",TEXT(D59,"000")),IF(G59="Serviço",CONCATENATE(TEXT(B59,"00"),".",TEXT(C59,"000"),".",TEXT(D59,"000"),".",TEXT(E59,"000")),""))))) -> 04.001.002.001 | I59: Alvenaria de vedação com bocos de concreto | J59: 2678.8177 | K59: m² | L59: 159121.77 | M59: Fechamento externo do hotel
A60: =IF($G60="UNIDADE CONSTRUTIVA",OFFSET(A60,0,0)+1,LARGE(A$3:A59,1)) -> 2 | B60: =IF(G60="UNIDADE CONSTRUTIVA",0,IF(G60="CÉLULA CONSTRUTIVA",OFFSET(B60,-1,0)+1,OFFSET(B60,-1,0))) -> 4 | C60: =IF(G60="CÉLULA CONSTRUTIVA",0,IF(G60="ETAPA",OFFSET(C60,-1,0)+1,OFFSET(C60,-1,0))) -> 1 | D60: =IF(G60="ETAPA",0,IF(G60="SUBETAPA",OFFSET(D60,-1,0)+1,OFFSET(D60,-1,0))) -> 2 | E60: =IF(G60="Subetapa",0,IF(G60="serviço",OFFSET(E60,-1,0)+1,OFFSET(E60,-1,0))) -> 2 | G60: Serviço | H60: =IF(G60="Unidade Construtiva",TEXT(A60,"00"),IF(G60="Célula Construtiva",TEXT(B60,"00"),IF(G60="Etapa",CONCATENATE(TEXT(B60,"00"),".",TEXT(C60,"000")),IF(G60="Subetapa",CONCATENATE(TEXT(B60,"00"),".",TEXT(C60,"000"),".",TEXT(D60,"000")),IF(G60="Serviço",CONCATENATE(TEXT(B60,"00"),".",TEXT(C60,"000"),".",TEXT(D60,"000"),".",TEXT(E60,"000")),""))))) -> 04.001.002.002 | I60: Alvenaria de vedação com bocos de concreto resistente á fogo (sical) | J60: 1209.834 | K60: m² | L60: 97815.079 | M60: Caixa de escadas (rota de fuga)
A61: =IF($G61="UNIDADE CONSTRUTIVA",OFFSET(A61,0,0)+1,LARGE(A$3:A58,1)) -> 2 | B61: =IF(G61="UNIDADE CONSTRUTIVA",0,IF(G61="CÉLULA CONSTRUTIVA",OFFSET(B61,-1,0)+1,OFFSET(B61,-1,0))) -> 4 | C61: =IF(G61="CÉLULA CONSTRUTIVA",0,IF(G61="ETAPA",OFFSET(C61,-1,0)+1,OFFSET(C61,-1,0))) -> 1 | D61: =IF(G61="ETAPA",0,IF(G61="SUBETAPA",OFFSET(D61,-1,0)+1,OFFSET(D61,-1,0))) -> 3 | E61: =IF(G61="Subetapa",0,IF(G61="serviço",OFFSET(E61,-1,0)+1,OFFSET(E61,-1,0))) -> 0 | G61: Subetapa | H61: =IF(G61="Unidade Construtiva",TEXT(A61,"00"),IF(G61="Célula Construtiva",TEXT(B61,"00"),IF(G61="Etapa",CONCATENATE(TEXT(B61,"00"),".",TEXT(C61,"000")),IF(G61="Subetapa",CONCATENATE(TEXT(B61,"00"),".",TEXT(C61,"000"),".",TEXT(D61,"000")),IF(G61="Serviço",CONCATENATE(TEXT(B61,"00"),".",TEXT(C61,"000"),".",TEXT(D61,"000"),".",TEXT(E61,"000")),""))))) -> 04.001.003 | I61: Serviços complementares para alvenaria de vedação | L61: =SUM(L62:L63) -> 78865.761
A62: =IF($G62="UNIDADE CONSTRUTIVA",OFFSET(A62,0,0)+1,LARGE(A$3:A61,1)) -> 2 | B62: =IF(G62="UNIDADE CONSTRUTIVA",0,IF(G62="CÉLULA CONSTRUTIVA",OFFSET(B62,-1,0)+1,OFFSET(B62,-1,0))) -> 4 | C62: =IF(G62="CÉLULA CONSTRUTIVA",0,IF(G62="ETAPA",OFFSET(C62,-1,0)+1,OFFSET(C62,-1,0))) -> 1 | D62: =IF(G62="ETAPA",0,IF(G62="SUBETAPA",OFFSET(D62,-1,0)+1,OFFSET(D62,-1,0))) -> 3 | E62: =IF(G62="Subetapa",0,IF(G62="serviço",OFFSET(E62,-1,0)+1,OFFSET(E62,-1,0))) -> 1 | G62: Serviço | H62: =IF(G62="Unidade Construtiva",TEXT(A62,"00"),IF(G62="Célula Construtiva",TEXT(B62,"00"),IF(G62="Etapa",CONCATENATE(TEXT(B62,"00"),".",TEXT(C62,"000")),IF(G62="Subetapa",CONCATENATE(TEXT(B62,"00"),".",TEXT(C62,"000"),".",TEXT(D62,"000")),IF(G62="Serviço",CONCATENATE(TEXT(B62,"00"),".",TEXT(C62,"000"),".",TEXT(D62,"000"),".",TEXT(E62,"000")),""))))) -> 04.001.003.001 | I62: Serviços complementares para alvenaria de vedação | J62: 3888.6517 | K62: m² | L62: 53468.961 | M62: Considerar serviços de encunhamento, telamento, vergas e contravergas
A63: =IF($G63="UNIDADE CONSTRUTIVA",OFFSET(A63,0,0)+1,LARGE(A$3:A62,1)) -> 2 | B63: =IF(G63="UNIDADE CONSTRUTIVA",0,IF(G63="CÉLULA CONSTRUTIVA",OFFSET(B63,-1,0)+1,OFFSET(B63,-1,0))) -> 4 | C63: =IF(G63="CÉLULA CONSTRUTIVA",0,IF(G63="ETAPA",OFFSET(C63,-1,0)+1,OFFSET(C63,-1,0))) -> 1 | D63: =IF(G63="ETAPA",0,IF(G63="SUBETAPA",OFFSET(D63,-1,0)+1,OFFSET(D63,-1,0))) -> 3 | E63: =IF(G63="Subetapa",0,IF(G63="serviço",OFFSET(E63,-1,0)+1,OFFSET(E63,-1,0))) -> 2 | G63: Serviço | H63: =IF(G63="Unidade Construtiva",TEXT(A63,"00"),IF(G63="Célula Construtiva",TEXT(B63,"00"),IF(G63="Etapa",CONCATENATE(TEXT(B63,"00"),".",TEXT(C63,"000")),IF(G63="Subetapa",CONCATENATE(TEXT(B63,"00"),".",TEXT(C63,"000"),".",TEXT(D63,"000")),IF(G63="Serviço",CONCATENATE(TEXT(B63,"00"),".",TEXT(C63,"000"),".",TEXT(D63,"000"),".",TEXT(E63,"000")),""))))) -> 04.001.003.002 | I63: Elemento pre-moldado - material e mão de obra | J63: 35.52 | K63: m² | L63: 25396.8 | M63: Muretas Box
A64: =IF($G64="UNIDADE CONSTRUTIVA",OFFSET(A64,0,0)+1,LARGE(A$3:A61,1)) -> 2 | B64: =IF(G64="UNIDADE CONSTRUTIVA",0,IF(G64="CÉLULA CONSTRUTIVA",OFFSET(B64,-1,0)+1,OFFSET(B64,-1,0))) -> 4 | C64: =IF(G64="CÉLULA CONSTRUTIVA",0,IF(G64="ETAPA",OFFSET(C64,-1,0)+1,OFFSET(C64,-1,0))) -> 1 | D64: =IF(G64="ETAPA",0,IF(G64="SUBETAPA",OFFSET(D64,-1,0)+1,OFFSET(D64,-1,0))) -> 4 | E64: =IF(G64="Subetapa",0,IF(G64="serviço",OFFSET(E64,-1,0)+1,OFFSET(E64,-1,0))) -> 0 | G64: Subetapa | H64: =IF(G64="Unidade Construtiva",TEXT(A64,"00"),IF(G64="Célula Construtiva",TEXT(B64,"00"),IF(G64="Etapa",CONCATENATE(TEXT(B64,"00"),".",TEXT(C64,"000")),IF(G64="Subetapa",CONCATENATE(TEXT(B64,"00"),".",TEXT(C64,"000"),".",TEXT(D64,"000")),IF(G64="Serviço",CONCATENATE(TEXT(B64,"00"),".",TEXT(C64,"000"),".",TEXT(D64,"000"),".",TEXT(E64,"000")),""))))) -> 04.001.004 | I64: Drywall | L64: =SUM(L65:L70) -> 2152082.9
A65: =IF($G65="UNIDADE CONSTRUTIVA",OFFSET(A65,0,0)+1,LARGE(A$3:A64,1)) -> 2 | B65: =IF(G65="UNIDADE CONSTRUTIVA",0,IF(G65="CÉLULA CONSTRUTIVA",OFFSET(B65,-1,0)+1,OFFSET(B65,-1,0))) -> 4 | C65: =IF(G65="CÉLULA CONSTRUTIVA",0,IF(G65="ETAPA",OFFSET(C65,-1,0)+1,OFFSET(C65,-1,0))) -> 1 | D65: =IF(G65="ETAPA",0,IF(G65="SUBETAPA",OFFSET(D65,-1,0)+1,OFFSET(D65,-1,0))) -> 4 | E65: =IF(G65="Subetapa",0,IF(G65="serviço",OFFSET(E65,-1,0)+1,OFFSET(E65,-1,0))) -> 1 | G65: Serviço | H65: =IF(G65="Unidade Construtiva",TEXT(A65,"00"),IF(G65="Célula Construtiva",TEXT(B65,"00"),IF(G65="Etapa",CONCATENATE(TEXT(B65,"00"),".",TEXT(C65,"000")),IF(G65="Subetapa",CONCATENATE(TEXT(B65,"00"),".",TEXT(C65,"000"),".",TEXT(D65,"000")),IF(G65="Serviço",CONCATENATE(TEXT(B65,"00"),".",TEXT(C65,"000"),".",TEXT(D65,"000"),".",TEXT(E65,"000")),""))))) -> 04.001.004.001 | I65: Divisórias de paredes duplas com isolamento de lã de vidro (5 chapas) | J65: 2661.6348 | K65: m² | L65: 1424738.6 | M65: (2PERF/VID/70/PERF/70/VID/2PERF)
A66: =IF($G66="UNIDADE CONSTRUTIVA",OFFSET(A66,0,0)+1,LARGE(A$3:A65,1)) -> 2 | B66: =IF(G66="UNIDADE CONSTRUTIVA",0,IF(G66="CÉLULA CONSTRUTIVA",OFFSET(B66,-1,0)+1,OFFSET(B66,-1,0))) -> 4 | C66: =IF(G66="CÉLULA CONSTRUTIVA",0,IF(G66="ETAPA",OFFSET(C66,-1,0)+1,OFFSET(C66,-1,0))) -> 1 | D66: =IF(G66="ETAPA",0,IF(G66="SUBETAPA",OFFSET(D66,-1,0)+1,OFFSET(D66,-1,0))) -> 4 | E66: =IF(G66="Subetapa",0,IF(G66="serviço",OFFSET(E66,-1,0)+1,OFFSET(E66,-1,0))) -> 2 | G66: Serviço | H66: =IF(G66="Unidade Construtiva",TEXT(A66,"00"),IF(G66="Célula Construtiva",TEXT(B66,"00"),IF(G66="Etapa",CONCATENATE(TEXT(B66,"00"),".",TEXT(C66,"000")),IF(G66="Subetapa",CONCATENATE(TEXT(B66,"00"),".",TEXT(C66,"000"),".",TEXT(D66,"000")),IF(G66="Serviço",CONCATENATE(TEXT(B66,"00"),".",TEXT(C66,"000"),".",TEXT(D66,"000"),".",TEXT(E66,"000")),""))))) -> 04.001.004.002 | I66: Divisórias de paredes duplas com isolamento de lã de vidro (4 chapas) | J66: 1693.7676 | K66: m² | L66: 356177.31 | M66: 2ST/90/ST+RU
A67: =IF($G67="UNIDADE CONSTRUTIVA",OFFSET(A67,0,0)+1,LARGE(A$3:A65,1)) -> 2 | B67: =IF(G67="UNIDADE CONSTRUTIVA",0,IF(G67="CÉLULA CONSTRUTIVA",OFFSET(B67,-1,0)+1,OFFSET(B67,-1,0))) -> 4 | C67: =IF(G67="CÉLULA CONSTRUTIVA",0,IF(G67="ETAPA",OFFSET(C67,-1,0)+1,OFFSET(C67,-1,0))) -> 1 | D67: =IF(G67="ETAPA",0,IF(G67="SUBETAPA",OFFSET(D67,-1,0)+1,OFFSET(D67,-1,0))) -> 4 | E67: =IF(G67="Subetapa",0,IF(G67="serviço",OFFSET(E67,-1,0)+1,OFFSET(E67,-1,0))) -> 3 | G67: Serviço | H67: =IF(G67="Unidade Construtiva",TEXT(A67,"00"),IF(G67="Célula Construtiva",TEXT(B67,"00"),IF(G67="Etapa",CONCATENATE(TEXT(B67,"00"),".",TEXT(C67,"000")),IF(G67="Subetapa",CONCATENATE(TEXT(B67,"00"),".",TEXT(C67,"000"),".",TEXT(D67,"000")),IF(G67="Serviço",CONCATENATE(TEXT(B67,"00"),".",TEXT(C67,"000"),".",TEXT(D67,"000"),".",TEXT(E67,"000")),""))))) -> 04.001.004.003 | I67: Divisórias de paredes simples com isolamento de lã de vidro (2 chapas)
A68: =IF($G68="UNIDADE CONSTRUTIVA",OFFSET(A68,0,0)+1,LARGE(A$3:A67,1)) -> 2 | B68: =IF(G68="UNIDADE CONSTRUTIVA",0,IF(G68="CÉLULA CONSTRUTIVA",OFFSET(B68,-1,0)+1,OFFSET(B68,-1,0))) -> 4 | C68: =IF(G68="CÉLULA CONSTRUTIVA",0,IF(G68="ETAPA",OFFSET(C68,-1,0)+1,OFFSET(C68,-1,0))) -> 1 | D68: =IF(G68="ETAPA",0,IF(G68="SUBETAPA",OFFSET(D68,-1,0)+1,OFFSET(D68,-1,0))) -> 4 | E68: =IF(G68="Subetapa",0,IF(G68="serviço",OFFSET(E68,-1,0)+1,OFFSET(E68,-1,0))) -> 4 | G68: Serviço | H68: =IF(G68="Unidade Construtiva",TEXT(A68,"00"),IF(G68="Célula Construtiva",TEXT(B68,"00"),IF(G68="Etapa",CONCATENATE(TEXT(B68,"00"),".",TEXT(C68,"000")),IF(G68="Subetapa",CONCATENATE(TEXT(B68,"00"),".",TEXT(C68,"000"),".",TEXT(D68,"000")),IF(G68="Serviço",CONCATENATE(TEXT(B68,"00"),".",TEXT(C68,"000"),".",TEXT(D68,"000"),".",TEXT(E68,"000")),""))))) -> 04.001.004.004 | I68: Divisórias de paredes simples sem isolamento (2 chapas)
A69: =IF($G69="UNIDADE CONSTRUTIVA",OFFSET(A69,0,0)+1,LARGE(A$3:A67,1)) -> 2 | B69: =IF(G69="UNIDADE CONSTRUTIVA",0,IF(G69="CÉLULA CONSTRUTIVA",OFFSET(B69,-1,0)+1,OFFSET(B69,-1,0))) -> 4 | C69: =IF(G69="CÉLULA CONSTRUTIVA",0,IF(G69="ETAPA",OFFSET(C69,-1,0)+1,OFFSET(C69,-1,0))) -> 1 | D69: =IF(G69="ETAPA",0,IF(G69="SUBETAPA",OFFSET(D69,-1,0)+1,OFFSET(D69,-1,0))) -> 4 | E69: =IF(G69="Subetapa",0,IF(G69="serviço",OFFSET(E69,-1,0)+1,OFFSET(E69,-1,0))) -> 5 | G69: Serviço | H69: =IF(G69="Unidade Construtiva",TEXT(A69,"00"),IF(G69="Célula Construtiva",TEXT(B69,"00"),IF(G69="Etapa",CONCATENATE(TEXT(B69,"00"),".",TEXT(C69,"000")),IF(G69="Subetapa",CONCATENATE(TEXT(B69,"00"),".",TEXT(C69,"000"),".",TEXT(D69,"000")),IF(G69="Serviço",CONCATENATE(TEXT(B69,"00"),".",TEXT(C69,"000"),".",TEXT(D69,"000"),".",TEXT(E69,"000")),""))))) -> 04.001.004.005 | I69: Fechamento de paredes de perímetro (1 chapa) | J69: 2678.8177 | K69: m² | L69: 323288.86 | M69: (48/VID/PERF)
A70: =IF($G70="UNIDADE CONSTRUTIVA",OFFSET(A70,0,0)+1,LARGE(A$3:A68,1)) -> 2 | B70: =IF(G70="UNIDADE CONSTRUTIVA",0,IF(G70="CÉLULA CONSTRUTIVA",OFFSET(B70,-1,0)+1,OFFSET(B70,-1,0))) -> 4 | C70: =IF(G70="CÉLULA CONSTRUTIVA",0,IF(G70="ETAPA",OFFSET(C70,-1,0)+1,OFFSET(C70,-1,0))) -> 1 | D70: =IF(G70="ETAPA",0,IF(G70="SUBETAPA",OFFSET(D70,-1,0)+1,OFFSET(D70,-1,0))) -> 4 | E70: =IF(G70="Subetapa",0,IF(G70="serviço",OFFSET(E70,-1,0)+1,OFFSET(E70,-1,0))) -> 6 | G70: Serviço | H70: =IF(G70="Unidade Construtiva",TEXT(A70,"00"),IF(G70="Célula Construtiva",TEXT(B70,"00"),IF(G70="Etapa",CONCATENATE(TEXT(B70,"00"),".",TEXT(C70,"000")),IF(G70="Subetapa",CONCATENATE(TEXT(B70,"00"),".",TEXT(C70,"000"),".",TEXT(D70,"000")),IF(G70="Serviço",CONCATENATE(TEXT(B70,"00"),".",TEXT(C70,"000"),".",TEXT(D70,"000"),".",TEXT(E70,"000")),""))))) -> 04.001.004.006 | I70: Fechamento de shafts e paredes de perímetro (1 chapa) | J70: 396.725 | K70: m² | L70: 47878.126 | M70: (48/VID/PERF)
A71: =IF($G71="UNIDADE CONSTRUTIVA",OFFSET(A71,0,0)+1,LARGE(A$3:A64,1)) -> 2 | B71: =IF(G71="UNIDADE CONSTRUTIVA",0,IF(G71="CÉLULA CONSTRUTIVA",OFFSET(B71,-1,0)+1,OFFSET(B71,-1,0))) -> 4 | C71: =IF(G71="CÉLULA CONSTRUTIVA",0,IF(G71="ETAPA",OFFSET(C71,-1,0)+1,OFFSET(C71,-1,0))) -> 1 | D71: =IF(G71="ETAPA",0,IF(G71="SUBETAPA",OFFSET(D71,-1,0)+1,OFFSET(D71,-1,0))) -> 5 | E71: =IF(G71="Subetapa",0,IF(G71="serviço",OFFSET(E71,-1,0)+1,OFFSET(E71,-1,0))) -> 0 | G71: Subetapa | H71: =IF(G71="Unidade Construtiva",TEXT(A71,"00"),IF(G71="Célula Construtiva",TEXT(B71,"00"),IF(G71="Etapa",CONCATENATE(TEXT(B71,"00"),".",TEXT(C71,"000")),IF(G71="Subetapa",CONCATENATE(TEXT(B71,"00"),".",TEXT(C71,"000"),".",TEXT(D71,"000")),IF(G71="Serviço",CONCATENATE(TEXT(B71,"00"),".",TEXT(C71,"000"),".",TEXT(D71,"000"),".",TEXT(E71,"000")),""))))) -> 04.001.005 | I71: Mão de obra | L71: =SUM(L72:L73) -> 480952.19
A72: =IF($G72="UNIDADE CONSTRUTIVA",OFFSET(A72,0,0)+1,LARGE(A$3:A65,1)) -> 2 | B72: =IF(G72="UNIDADE CONSTRUTIVA",0,IF(G72="CÉLULA CONSTRUTIVA",OFFSET(B72,-1,0)+1,OFFSET(B72,-1,0))) -> 4 | C72: =IF(G72="CÉLULA CONSTRUTIVA",0,IF(G72="ETAPA",OFFSET(C72,-1,0)+1,OFFSET(C72,-1,0))) -> 1 | D72: =IF(G72="ETAPA",0,IF(G72="SUBETAPA",OFFSET(D72,-1,0)+1,OFFSET(D72,-1,0))) -> 5 | E72: =IF(G72="Subetapa",0,IF(G72="serviço",OFFSET(E72,-1,0)+1,OFFSET(E72,-1,0))) -> 1 | G72: Serviço | H72: =IF(G72="Unidade Construtiva",TEXT(A72,"00"),IF(G72="Célula Construtiva",TEXT(B72,"00"),IF(G72="Etapa",CONCATENATE(TEXT(B72,"00"),".",TEXT(C72,"000")),IF(G72="Subetapa",CONCATENATE(TEXT(B72,"00"),".",TEXT(C72,"000"),".",TEXT(D72,"000")),IF(G72="Serviço",CONCATENATE(TEXT(B72,"00"),".",TEXT(C72,"000"),".",TEXT(D72,"000"),".",TEXT(E72,"000")),""))))) -> 04.001.005.001 | I72: Mão de obra para assentamento de blocos cerâmicos e de concreto | J72: 3888.6517 | K72: m² | L72: 153990.61
A73: =IF($G73="UNIDADE CONSTRUTIVA",OFFSET(A73,0,0)+1,LARGE(A$3:A66,1)) -> 2 | B73: =IF(G73="UNIDADE CONSTRUTIVA",0,IF(G73="CÉLULA CONSTRUTIVA",OFFSET(B73,-1,0)+1,OFFSET(B73,-1,0))) -> 4 | C73: =IF(G73="CÉLULA CONSTRUTIVA",0,IF(G73="ETAPA",OFFSET(C73,-1,0)+1,OFFSET(C73,-1,0))) -> 1 | D73: =IF(G73="ETAPA",0,IF(G73="SUBETAPA",OFFSET(D73,-1,0)+1,OFFSET(D73,-1,0))) -> 5 | E73: =IF(G73="Subetapa",0,IF(G73="serviço",OFFSET(E73,-1,0)+1,OFFSET(E73,-1,0))) -> 2 | G73: Serviço | H73: =IF(G73="Unidade Construtiva",TEXT(A73,"00"),IF(G73="Célula Construtiva",TEXT(B73,"00"),IF(G73="Etapa",CONCATENATE(TEXT(B73,"00"),".",TEXT(C73,"000")),IF(G73="Subetapa",CONCATENATE(TEXT(B73,"00"),".",TEXT(C73,"000"),".",TEXT(D73,"000")),IF(G73="Serviço",CONCATENATE(TEXT(B73,"00"),".",TEXT(C73,"000"),".",TEXT(D73,"000"),".",TEXT(E73,"000")),""))))) -> 04.001.005.002 | I73: Mão de obra para execução de parede em drywall | J73: =SUM(J65:J70) -> 7430.9451 | K73: m² | L73: 326961.58
A74: =IF($G74="UNIDADE CONSTRUTIVA",OFFSET(A74,0,0)+1,LARGE(A$3:A71,1)) -> 2 | B74: =IF(G74="UNIDADE CONSTRUTIVA",0,IF(G74="CÉLULA CONSTRUTIVA",OFFSET(B74,-1,0)+1,OFFSET(B74,-1,0))) -> 5 | C74: =IF(G74="CÉLULA CONSTRUTIVA",0,IF(G74="ETAPA",OFFSET(C74,-1,0)+1,OFFSET(C74,-1,0))) -> 0 | D74: =IF(G74="ETAPA",0,IF(G74="SUBETAPA",OFFSET(D74,-1,0)+1,OFFSET(D74,-1,0))) -> 5 | E74: =IF(G74="Subetapa",0,IF(G74="serviço",OFFSET(E74,-1,0)+1,OFFSET(E74,-1,0))) -> 2 | G74: CÉLULA CONSTRUTIVA | H74: =IF(G74="Unidade Construtiva",TEXT(A74,"00"),IF(G74="Célula Construtiva",TEXT(B74,"00"),IF(G74="Etapa",CONCATENATE(TEXT(B74,"00"),".",TEXT(C74,"000")),IF(G74="Subetapa",CONCATENATE(TEXT(B74,"00"),".",TEXT(C74,"000"),".",TEXT(D74,"000")),IF(G74="Serviço",CONCATENATE(TEXT(B74,"00"),".",TEXT(C74,"000"),".",TEXT(D74,"000"),".",TEXT(E74,"000")),""))))) -> 05 | I74: IMPERMEABILIZAÇÃO E TRATAMENTOS | L74: =L75 -> 493452.25
A75: =IF($G75="UNIDADE CONSTRUTIVA",OFFSET(A75,0,0)+1,LARGE(A$3:A74,1)) -> 2 | B75: =IF(G75="UNIDADE CONSTRUTIVA",0,IF(G75="CÉLULA CONSTRUTIVA",OFFSET(B75,-1,0)+1,OFFSET(B75,-1,0))) -> 5 | C75: =IF(G75="CÉLULA CONSTRUTIVA",0,IF(G75="ETAPA",OFFSET(C75,-1,0)+1,OFFSET(C75,-1,0))) -> 1 | D75: =IF(G75="ETAPA",0,IF(G75="SUBETAPA",OFFSET(D75,-1,0)+1,OFFSET(D75,-1,0))) -> 0 | E75: =IF(G75="Subetapa",0,IF(G75="serviço",OFFSET(E75,-1,0)+1,OFFSET(E75,-1,0))) -> 2 | G75: ETAPA | H75: =IF(G75="Unidade Construtiva",TEXT(A75,"00"),IF(G75="Célula Construtiva",TEXT(B75,"00"),IF(G75="Etapa",CONCATENATE(TEXT(B75,"00"),".",TEXT(C75,"000")),IF(G75="Subetapa",CONCATENATE(TEXT(B75,"00"),".",TEXT(C75,"000"),".",TEXT(D75,"000")),IF(G75="Serviço",CONCATENATE(TEXT(B75,"00"),".",TEXT(C75,"000"),".",TEXT(D75,"000"),".",TEXT(E75,"000")),""))))) -> 05.001 | I75: IMPERMEABILIZAÇÃO E TRATAMENTOS | L75: =SUM(L76:L107)/2 -> 493452.25
A76: =IF($G76="UNIDADE CONSTRUTIVA",OFFSET(A76,0,0)+1,LARGE(A$3:A75,1)) -> 2 | B76: =IF(G76="UNIDADE CONSTRUTIVA",0,IF(G76="CÉLULA CONSTRUTIVA",OFFSET(B76,-1,0)+1,OFFSET(B76,-1,0))) -> 5 | C76: =IF(G76="CÉLULA CONSTRUTIVA",0,IF(G76="ETAPA",OFFSET(C76,-1,0)+1,OFFSET(C76,-1,0))) -> 1 | D76: =IF(G76="ETAPA",0,IF(G76="SUBETAPA",OFFSET(D76,-1,0)+1,OFFSET(D76,-1,0))) -> 1 | E76: =IF(G76="Subetapa",0,IF(G76="serviço",OFFSET(E76,-1,0)+1,OFFSET(E76,-1,0))) -> 0 | G76: Subetapa | H76: =IF(G76="Unidade Construtiva",TEXT(A76,"00"),IF(G76="Célula Construtiva",TEXT(B76,"00"),IF(G76="Etapa",CONCATENATE(TEXT(B76,"00"),".",TEXT(C76,"000")),IF(G76="Subetapa",CONCATENATE(TEXT(B76,"00"),".",TEXT(C76,"000"),".",TEXT(D76,"000")),IF(G76="Serviço",CONCATENATE(TEXT(B76,"00"),".",TEXT(C76,"000"),".",TEXT(D76,"000"),".",TEXT(E76,"000")),""))))) -> 05.001.001 | I76: Regularização e proteção mecânica | L76: =SUM(L77:L78) -> 106305.8
A77: =IF($G77="UNIDADE CONSTRUTIVA",OFFSET(A77,0,0)+1,LARGE(A$3:A76,1)) -> 2 | B77: =IF(G77="UNIDADE CONSTRUTIVA",0,IF(G77="CÉLULA CONSTRUTIVA",OFFSET(B77,-1,0)+1,OFFSET(B77,-1,0))) -> 5 | C77: =IF(G77="CÉLULA CONSTRUTIVA",0,IF(G77="ETAPA",OFFSET(C77,-1,0)+1,OFFSET(C77,-1,0))) -> 1 | D77: =IF(G77="ETAPA",0,IF(G77="SUBETAPA",OFFSET(D77,-1,0)+1,OFFSET(D77,-1,0))) -> 1 | E77: =IF(G77="Subetapa",0,IF(G77="serviço",OFFSET(E77,-1,0)+1,OFFSET(E77,-1,0))) -> 1 | G77: Serviço | H77: =IF(G77="Unidade Construtiva",TEXT(A77,"00"),IF(G77="Célula Construtiva",TEXT(B77,"00"),IF(G77="Etapa",CONCATENATE(TEXT(B77,"00"),".",TEXT(C77,"000")),IF(G77="Subetapa",CONCATENATE(TEXT(B77,"00"),".",TEXT(C77,"000"),".",TEXT(D77,"000")),IF(G77="Serviço",CONCATENATE(TEXT(B77,"00"),".",TEXT(C77,"000"),".",TEXT(D77,"000"),".",TEXT(E77,"000")),""))))) -> 05.001.001.001 | I77: Regularização de superfícies a serem impermeabilizadas | J77: 2949.0932 | K77: m² | L77: 71368.055
A78: =IF($G78="UNIDADE CONSTRUTIVA",OFFSET(A78,0,0)+1,LARGE(A$3:A77,1)) -> 2 | B78: =IF(G78="UNIDADE CONSTRUTIVA",0,IF(G78="CÉLULA CONSTRUTIVA",OFFSET(B78,-1,0)+1,OFFSET(B78,-1,0))) -> 5 | C78: =IF(G78="CÉLULA CONSTRUTIVA",0,IF(G78="ETAPA",OFFSET(C78,-1,0)+1,OFFSET(C78,-1,0))) -> 1 | D78: =IF(G78="ETAPA",0,IF(G78="SUBETAPA",OFFSET(D78,-1,0)+1,OFFSET(D78,-1,0))) -> 1 | E78: =IF(G78="Subetapa",0,IF(G78="serviço",OFFSET(E78,-1,0)+1,OFFSET(E78,-1,0))) -> 2 | G78: Serviço | H78: =IF(G78="Unidade Construtiva",TEXT(A78,"00"),IF(G78="Célula Construtiva",TEXT(B78,"00"),IF(G78="Etapa",CONCATENATE(TEXT(B78,"00"),".",TEXT(C78,"000")),IF(G78="Subetapa",CONCATENATE(TEXT(B78,"00"),".",TEXT(C78,"000"),".",TEXT(D78,"000")),IF(G78="Serviço",CONCATENATE(TEXT(B78,"00"),".",TEXT(C78,"000"),".",TEXT(D78,"000"),".",TEXT(E78,"000")),""))))) -> 05.001.001.002 | I78: Proteção mecânica de superfícies que recebem manta | J78: 1134.3422 | K78: m² | L78: 34937.74
A79: =IF($G79="UNIDADE CONSTRUTIVA",OFFSET(A79,0,0)+1,LARGE(A$3:A76,1)) -> 2 | B79: =IF(G79="UNIDADE CONSTRUTIVA",0,IF(G79="CÉLULA CONSTRUTIVA",OFFSET(B79,-1,0)+1,OFFSET(B79,-1,0))) -> 5 | C79: =IF(G79="CÉLULA CONSTRUTIVA",0,IF(G79="ETAPA",OFFSET(C79,-1,0)+1,OFFSET(C79,-1,0))) -> 1 | D79: =IF(G79="ETAPA",0,IF(G79="SUBETAPA",OFFSET(D79,-1,0)+1,OFFSET(D79,-1,0))) -> 2 | E79: =IF(G79="Subetapa",0,IF(G79="serviço",OFFSET(E79,-1,0)+1,OFFSET(E79,-1,0))) -> 0 | G79: Subetapa | H79: =IF(G79="Unidade Construtiva",TEXT(A79,"00"),IF(G79="Célula Construtiva",TEXT(B79,"00"),IF(G79="Etapa",CONCATENATE(TEXT(B79,"00"),".",TEXT(C79,"000")),IF(G79="Subetapa",CONCATENATE(TEXT(B79,"00"),".",TEXT(C79,"000"),".",TEXT(D79,"000")),IF(G79="Serviço",CONCATENATE(TEXT(B79,"00"),".",TEXT(C79,"000"),".",TEXT(D79,"000"),".",TEXT(E79,"000")),""))))) -> 05.001.002 | I79: Impermeabilização de cisternas | L79: =L80 -> 0
A80: =IF($G80="UNIDADE CONSTRUTIVA",OFFSET(A80,0,0)+1,LARGE(A$3:A77,1)) -> 2 | B80: =IF(G80="UNIDADE CONSTRUTIVA",0,IF(G80="CÉLULA CONSTRUTIVA",OFFSET(B80,-1,0)+1,OFFSET(B80,-1,0))) -> 5 | C80: =IF(G80="CÉLULA CONSTRUTIVA",0,IF(G80="ETAPA",OFFSET(C80,-1,0)+1,OFFSET(C80,-1,0))) -> 1 | D80: =IF(G80="ETAPA",0,IF(G80="SUBETAPA",OFFSET(D80,-1,0)+1,OFFSET(D80,-1,0))) -> 2 | E80: =IF(G80="Subetapa",0,IF(G80="serviço",OFFSET(E80,-1,0)+1,OFFSET(E80,-1,0))) -> 1 | G80: Serviço | H80: =IF(G80="Unidade Construtiva",TEXT(A80,"00"),IF(G80="Célula Construtiva",TEXT(B80,"00"),IF(G80="Etapa",CONCATENATE(TEXT(B80,"00"),".",TEXT(C80,"000")),IF(G80="Subetapa",CONCATENATE(TEXT(B80,"00"),".",TEXT(C80,"000"),".",TEXT(D80,"000")),IF(G80="Serviço",CONCATENATE(TEXT(B80,"00"),".",TEXT(C80,"000"),".",TEXT(D80,"000"),".",TEXT(E80,"000")),""))))) -> 05.001.002.001 | I80: Impermeabilização de cisternas
A81: =IF($G81="UNIDADE CONSTRUTIVA",OFFSET(A81,0,0)+1,LARGE(A$3:A79,1)) -> 2 | B81: =IF(G81="UNIDADE CONSTRUTIVA",0,IF(G81="CÉLULA CONSTRUTIVA",OFFSET(B81,-1,0)+1,OFFSET(B81,-1,0))) -> 5 | C81: =IF(G81="CÉLULA CONSTRUTIVA",0,IF(G81="ETAPA",OFFSET(C81,-1,0)+1,OFFSET(C81,-1,0))) -> 1 | D81: =IF(G81="ETAPA",0,IF(G81="SUBETAPA",OFFSET(D81,-1,0)+1,OFFSET(D81,-1,0))) -> 3 | E81: =IF(G81="Subetapa",0,IF(G81="serviço",OFFSET(E81,-1,0)+1,OFFSET(E81,-1,0))) -> 0 | G81: Subetapa | H81: =IF(G81="Unidade Construtiva",TEXT(A81,"00"),IF(G81="Célula Construtiva",TEXT(B81,"00"),IF(G81="Etapa",CONCATENATE(TEXT(B81,"00"),".",TEXT(C81,"000")),IF(G81="Subetapa",CONCATENATE(TEXT(B81,"00"),".",TEXT(C81,"000"),".",TEXT(D81,"000")),IF(G81="Serviço",CONCATENATE(TEXT(B81,"00"),".",TEXT(C81,"000"),".",TEXT(D81,"000"),".",TEXT(E81,"000")),""))))) -> 05.001.003 | I81: Impermeabilização de fundação e contenção | L81: =L82 -> 84803.793
A82: =IF($G82="UNIDADE CONSTRUTIVA",OFFSET(A82,0,0)+1,LARGE(A$3:A80,1)) -> 2 | B82: =IF(G82="UNIDADE CONSTRUTIVA",0,IF(G82="CÉLULA CONSTRUTIVA",OFFSET(B82,-1,0)+1,OFFSET(B82,-1,0))) -> 5 | C82: =IF(G82="CÉLULA CONSTRUTIVA",0,IF(G82="ETAPA",OFFSET(C82,-1,0)+1,OFFSET(C82,-1,0))) -> 1 | D82: =IF(G82="ETAPA",0,IF(G82="SUBETAPA",OFFSET(D82,-1,0)+1,OFFSET(D82,-1,0))) -> 3 | E82: =IF(G82="Subetapa",0,IF(G82="serviço",OFFSET(E82,-1,0)+1,OFFSET(E82,-1,0))) -> 1 | G82: Serviço | H82: =IF(G82="Unidade Construtiva",TEXT(A82,"00"),IF(G82="Célula Construtiva",TEXT(B82,"00"),IF(G82="Etapa",CONCATENATE(TEXT(B82,"00"),".",TEXT(C82,"000")),IF(G82="Subetapa",CONCATENATE(TEXT(B82,"00"),".",TEXT(C82,"000"),".",TEXT(D82,"000")),IF(G82="Serviço",CONCATENATE(TEXT(B82,"00"),".",TEXT(C82,"000"),".",TEXT(D82,"000"),".",TEXT(E82,"000")),""))))) -> 05.001.003.001 | I82: Impermeabilização de fundação e contenção | J82: =[6]IMPERMEABILIZAÇÃO!$D$11+[6]IMPERMEABILIZAÇÃO!$D$12 -> 2192.3575 | K82: m² | L82: =[6]IMPERMEABILIZAÇÃO!$G$11+[6]IMPERMEABILIZAÇÃO!$G$12 -> 84803.793 | M82: Inclui baldrames, contenção e poço do elevador
A83: =IF($G83="UNIDADE CONSTRUTIVA",OFFSET(A83,0,0)+1,LARGE(A$3:A81,1)) -> 2 | B83: =IF(G83="UNIDADE CONSTRUTIVA",0,IF(G83="CÉLULA CONSTRUTIVA",OFFSET(B83,-1,0)+1,OFFSET(B83,-1,0))) -> 5 | C83: =IF(G83="CÉLULA CONSTRUTIVA",0,IF(G83="ETAPA",OFFSET(C83,-1,0)+1,OFFSET(C83,-1,0))) -> 1 | D83: =IF(G83="ETAPA",0,IF(G83="SUBETAPA",OFFSET(D83,-1,0)+1,OFFSET(D83,-1,0))) -> 4 | E83: =IF(G83="Subetapa",0,IF(G83="serviço",OFFSET(E83,-1,0)+1,OFFSET(E83,-1,0))) -> 0 | G83: Subetapa | H83: =IF(G83="Unidade Construtiva",TEXT(A83,"00"),IF(G83="Célula Construtiva",TEXT(B83,"00"),IF(G83="Etapa",CONCATENATE(TEXT(B83,"00"),".",TEXT(C83,"000")),IF(G83="Subetapa",CONCATENATE(TEXT(B83,"00"),".",TEXT(C83,"000"),".",TEXT(D83,"000")),IF(G83="Serviço",CONCATENATE(TEXT(B83,"00"),".",TEXT(C83,"000"),".",TEXT(D83,"000"),".",TEXT(E83,"000")),""))))) -> 05.001.004 | I83: Impermeabilização de lajes e terraços | L83: =L84 -> 187166.46
A84: =IF($G84="UNIDADE CONSTRUTIVA",OFFSET(A84,0,0)+1,LARGE(A$3:A82,1)) -> 2 | B84: =IF(G84="UNIDADE CONSTRUTIVA",0,IF(G84="CÉLULA CONSTRUTIVA",OFFSET(B84,-1,0)+1,OFFSET(B84,-1,0))) -> 5 | C84: =IF(G84="CÉLULA CONSTRUTIVA",0,IF(G84="ETAPA",OFFSET(C84,-1,0)+1,OFFSET(C84,-1,0))) -> 1 | D84: =IF(G84="ETAPA",0,IF(G84="SUBETAPA",OFFSET(D84,-1,0)+1,OFFSET(D84,-1,0))) -> 4 | E84: =IF(G84="Subetapa",0,IF(G84="serviço",OFFSET(E84,-1,0)+1,OFFSET(E84,-1,0))) -> 1 | G84: Serviço | H84: =IF(G84="Unidade Construtiva",TEXT(A84,"00"),IF(G84="Célula Construtiva",TEXT(B84,"00"),IF(G84="Etapa",CONCATENATE(TEXT(B84,"00"),".",TEXT(C84,"000")),IF(G84="Subetapa",CONCATENATE(TEXT(B84,"00"),".",TEXT(C84,"000"),".",TEXT(D84,"000")),IF(G84="Serviço",CONCATENATE(TEXT(B84,"00"),".",TEXT(C84,"000"),".",TEXT(D84,"000"),".",TEXT(E84,"000")),""))))) -> 05.001.004.001 | I84: Impermeabilização de lajes e terraços | J84: 1134.3422 | K84: m² | L84: 187166.46
A85: =IF($G85="UNIDADE CONSTRUTIVA",OFFSET(A85,0,0)+1,LARGE(A$3:A83,1)) -> 2 | B85: =IF(G85="UNIDADE CONSTRUTIVA",0,IF(G85="CÉLULA CONSTRUTIVA",OFFSET(B85,-1,0)+1,OFFSET(B85,-1,0))) -> 5 | C85: =IF(G85="CÉLULA CONSTRUTIVA",0,IF(G85="ETAPA",OFFSET(C85,-1,0)+1,OFFSET(C85,-1,0))) -> 1 | D85: =IF(G85="ETAPA",0,IF(G85="SUBETAPA",OFFSET(D85,-1,0)+1,OFFSET(D85,-1,0))) -> 5 | E85: =IF(G85="Subetapa",0,IF(G85="serviço",OFFSET(E85,-1,0)+1,OFFSET(E85,-1,0))) -> 0 | G85: Subetapa | H85: =IF(G85="Unidade Construtiva",TEXT(A85,"00"),IF(G85="Célula Construtiva",TEXT(B85,"00"),IF(G85="Etapa",CONCATENATE(TEXT(B85,"00"),".",TEXT(C85,"000")),IF(G85="Subetapa",CONCATENATE(TEXT(B85,"00"),".",TEXT(C85,"000"),".",TEXT(D85,"000")),IF(G85="Serviço",CONCATENATE(TEXT(B85,"00"),".",TEXT(C85,"000"),".",TEXT(D85,"000"),".",TEXT(E85,"000")),""))))) -> 05.001.005 | I85: Impermeabilização de piscinas e espelhos d´água | L85: =L86 -> 0
A86: =IF($G86="UNIDADE CONSTRUTIVA",OFFSET(A86,0,0)+1,LARGE(A$3:A84,1)) -> 2 | B86: =IF(G86="UNIDADE CONSTRUTIVA",0,IF(G86="CÉLULA CONSTRUTIVA",OFFSET(B86,-1,0)+1,OFFSET(B86,-1,0))) -> 5 | C86: =IF(G86="CÉLULA CONSTRUTIVA",0,IF(G86="ETAPA",OFFSET(C86,-1,0)+1,OFFSET(C86,-1,0))) -> 1 | D86: =IF(G86="ETAPA",0,IF(G86="SUBETAPA",OFFSET(D86,-1,0)+1,OFFSET(D86,-1,0))) -> 5 | E86: =IF(G86="Subetapa",0,IF(G86="serviço",OFFSET(E86,-1,0)+1,OFFSET(E86,-1,0))) -> 1 | G86: Serviço | H86: =IF(G86="Unidade Construtiva",TEXT(A86,"00"),IF(G86="Célula Construtiva",TEXT(B86,"00"),IF(G86="Etapa",CONCATENATE(TEXT(B86,"00"),".",TEXT(C86,"000")),IF(G86="Subetapa",CONCATENATE(TEXT(B86,"00"),".",TEXT(C86,"000"),".",TEXT(D86,"000")),IF(G86="Serviço",CONCATENATE(TEXT(B86,"00"),".",TEXT(C86,"000"),".",TEXT(D86,"000"),".",TEXT(E86,"000")),""))))) -> 05.001.005.001 | I86: Impermeabilização de piscinas e espelhos d´água
A87: =IF($G87="UNIDADE CONSTRUTIVA",OFFSET(A87,0,0)+1,LARGE(A$3:A85,1)) -> 2 | B87: =IF(G87="UNIDADE CONSTRUTIVA",0,IF(G87="CÉLULA CONSTRUTIVA",OFFSET(B87,-1,0)+1,OFFSET(B87,-1,0))) -> 5 | C87: =IF(G87="CÉLULA CONSTRUTIVA",0,IF(G87="ETAPA",OFFSET(C87,-1,0)+1,OFFSET(C87,-1,0))) -> 1 | D87: =IF(G87="ETAPA",0,IF(G87="SUBETAPA",OFFSET(D87,-1,0)+1,OFFSET(D87,-1,0))) -> 6 | E87: =IF(G87="Subetapa",0,IF(G87="serviço",OFFSET(E87,-1,0)+1,OFFSET(E87,-1,0))) -> 0 | G87: Subetapa | H87: =IF(G87="Unidade Construtiva",TEXT(A87,"00"),IF(G87="Célula Construtiva",TEXT(B87,"00"),IF(G87="Etapa",CONCATENATE(TEXT(B87,"00"),".",TEXT(C87,"000")),IF(G87="Subetapa",CONCATENATE(TEXT(B87,"00"),".",TEXT(C87,"000"),".",TEXT(D87,"000")),IF(G87="Serviço",CONCATENATE(TEXT(B87,"00"),".",TEXT(C87,"000"),".",TEXT(D87,"000"),".",TEXT(E87,"000")),""))))) -> 05.001.006 | I87: Impermeabilização de banheiro, cozinha e sacada | L87: =L88 -> 108885.06
A88: =IF($G88="UNIDADE CONSTRUTIVA",OFFSET(A88,0,0)+1,LARGE(A$3:A86,1)) -> 2 | B88: =IF(G88="UNIDADE CONSTRUTIVA",0,IF(G88="CÉLULA CONSTRUTIVA",OFFSET(B88,-1,0)+1,OFFSET(B88,-1,0))) -> 5 | C88: =IF(G88="CÉLULA CONSTRUTIVA",0,IF(G88="ETAPA",OFFSET(C88,-1,0)+1,OFFSET(C88,-1,0))) -> 1 | D88: =IF(G88="ETAPA",0,IF(G88="SUBETAPA",OFFSET(D88,-1,0)+1,OFFSET(D88,-1,0))) -> 6 | E88: =IF(G88="Subetapa",0,IF(G88="serviço",OFFSET(E88,-1,0)+1,OFFSET(E88,-1,0))) -> 1 | G88: Serviço | H88: =IF(G88="Unidade Construtiva",TEXT(A88,"00"),IF(G88="Célula Construtiva",TEXT(B88,"00"),IF(G88="Etapa",CONCATENATE(TEXT(B88,"00"),".",TEXT(C88,"000")),IF(G88="Subetapa",CONCATENATE(TEXT(B88,"00"),".",TEXT(C88,"000"),".",TEXT(D88,"000")),IF(G88="Serviço",CONCATENATE(TEXT(B88,"00"),".",TEXT(C88,"000"),".",TEXT(D88,"000"),".",TEXT(E88,"000")),""))))) -> 05.001.006.001 | I88: Impermeabilização de banheiro, cozinha e sacada | J88: 1814.751 | K88: m² | L88: 108885.06
A89: =IF($G89="UNIDADE CONSTRUTIVA",OFFSET(A89,0,0)+1,LARGE(A$3:A87,1)) -> 2 | B89: =IF(G89="UNIDADE CONSTRUTIVA",0,IF(G89="CÉLULA CONSTRUTIVA",OFFSET(B89,-1,0)+1,OFFSET(B89,-1,0))) -> 5 | C89: =IF(G89="CÉLULA CONSTRUTIVA",0,IF(G89="ETAPA",OFFSET(C89,-1,0)+1,OFFSET(C89,-1,0))) -> 1 | D89: =IF(G89="ETAPA",0,IF(G89="SUBETAPA",OFFSET(D89,-1,0)+1,OFFSET(D89,-1,0))) -> 7 | E89: =IF(G89="Subetapa",0,IF(G89="serviço",OFFSET(E89,-1,0)+1,OFFSET(E89,-1,0))) -> 0 | G89: Subetapa | H89: =IF(G89="Unidade Construtiva",TEXT(A89,"00"),IF(G89="Célula Construtiva",TEXT(B89,"00"),IF(G89="Etapa",CONCATENATE(TEXT(B89,"00"),".",TEXT(C89,"000")),IF(G89="Subetapa",CONCATENATE(TEXT(B89,"00"),".",TEXT(C89,"000"),".",TEXT(D89,"000")),IF(G89="Serviço",CONCATENATE(TEXT(B89,"00"),".",TEXT(C89,"000"),".",TEXT(D89,"000"),".",TEXT(E89,"000")),""))))) -> 05.001.007 | I89: Impermeabilização de esquadrias | L89: =L90 -> 3629.502
A90: =IF($G90="UNIDADE CONSTRUTIVA",OFFSET(A90,0,0)+1,LARGE(A$3:A88,1)) -> 2 | B90: =IF(G90="UNIDADE CONSTRUTIVA",0,IF(G90="CÉLULA CONSTRUTIVA",OFFSET(B90,-1,0)+1,OFFSET(B90,-1,0))) -> 5 | C90: =IF(G90="CÉLULA CONSTRUTIVA",0,IF(G90="ETAPA",OFFSET(C90,-1,0)+1,OFFSET(C90,-1,0))) -> 1 | D90: =IF(G90="ETAPA",0,IF(G90="SUBETAPA",OFFSET(D90,-1,0)+1,OFFSET(D90,-1,0))) -> 7 | E90: =IF(G90="Subetapa",0,IF(G90="serviço",OFFSET(E90,-1,0)+1,OFFSET(E90,-1,0))) -> 1 | G90: Serviço | H90: =IF(G90="Unidade Construtiva",TEXT(A90,"00"),IF(G90="Célula Construtiva",TEXT(B90,"00"),IF(G90="Etapa",CONCATENATE(TEXT(B90,"00"),".",TEXT(C90,"000")),IF(G90="Subetapa",CONCATENATE(TEXT(B90,"00"),".",TEXT(C90,"000"),".",TEXT(D90,"000")),IF(G90="Serviço",CONCATENATE(TEXT(B90,"00"),".",TEXT(C90,"000"),".",TEXT(D90,"000"),".",TEXT(E90,"000")),""))))) -> 05.001.007.001 | I90: Impermeabilização de esquadrias | J90: 1 | K90: vb | L90: 3629.502
A91: =IF($G91="UNIDADE CONSTRUTIVA",OFFSET(A91,0,0)+1,LARGE(A$3:A89,1)) -> 2 | B91: =IF(G91="UNIDADE CONSTRUTIVA",0,IF(G91="CÉLULA CONSTRUTIVA",OFFSET(B91,-1,0)+1,OFFSET(B91,-1,0))) -> 5 | C91: =IF(G91="CÉLULA CONSTRUTIVA",0,IF(G91="ETAPA",OFFSET(C91,-1,0)+1,OFFSET(C91,-1,0))) -> 1 | D91: =IF(G91="ETAPA",0,IF(G91="SUBETAPA",OFFSET(D91,-1,0)+1,OFFSET(D91,-1,0))) -> 8 | E91: =IF(G91="Subetapa",0,IF(G91="serviço",OFFSET(E91,-1,0)+1,OFFSET(E91,-1,0))) -> 0 | G91: Subetapa | H91: =IF(G91="Unidade Construtiva",TEXT(A91,"00"),IF(G91="Célula Construtiva",TEXT(B91,"00"),IF(G91="Etapa",CONCATENATE(TEXT(B91,"00"),".",TEXT(C91,"000")),IF(G91="Subetapa",CONCATENATE(TEXT(B91,"00"),".",TEXT(C91,"000"),".",TEXT(D91,"000")),IF(G91="Serviço",CONCATENATE(TEXT(B91,"00"),".",TEXT(C91,"000"),".",TEXT(D91,"000"),".",TEXT(E91,"000")),""))))) -> 05.001.008 | I91: Impermeabilização de ralos | L91: =L92 -> 2661.6348
A92: =IF($G92="UNIDADE CONSTRUTIVA",OFFSET(A92,0,0)+1,LARGE(A$3:A90,1)) -> 2 | B92: =IF(G92="UNIDADE CONSTRUTIVA",0,IF(G92="CÉLULA CONSTRUTIVA",OFFSET(B92,-1,0)+1,OFFSET(B92,-1,0))) -> 5 | C92: =IF(G92="CÉLULA CONSTRUTIVA",0,IF(G92="ETAPA",OFFSET(C92,-1,0)+1,OFFSET(C92,-1,0))) -> 1 | D92: =IF(G92="ETAPA",0,IF(G92="SUBETAPA",OFFSET(D92,-1,0)+1,OFFSET(D92,-1,0))) -> 8 | E92: =IF(G92="Subetapa",0,IF(G92="serviço",OFFSET(E92,-1,0)+1,OFFSET(E92,-1,0))) -> 1 | G92: Serviço | H92: =IF(G92="Unidade Construtiva",TEXT(A92,"00"),IF(G92="Célula Construtiva",TEXT(B92,"00"),IF(G92="Etapa",CONCATENATE(TEXT(B92,"00"),".",TEXT(C92,"000")),IF(G92="Subetapa",CONCATENATE(TEXT(B92,"00"),".",TEXT(C92,"000"),".",TEXT(D92,"000")),IF(G92="Serviço",CONCATENATE(TEXT(B92,"00"),".",TEXT(C92,"000"),".",TEXT(D92,"000"),".",TEXT(E92,"000")),""))))) -> 05.001.008.001 | I92: Impermeabilização de ralos | J92: 1 | K92: vb | L92: 2661.6348
A93: =IF($G93="UNIDADE CONSTRUTIVA",OFFSET(A93,0,0)+1,LARGE(A$3:A91,1)) -> 2 | B93: =IF(G93="UNIDADE CONSTRUTIVA",0,IF(G93="CÉLULA CONSTRUTIVA",OFFSET(B93,-1,0)+1,OFFSET(B93,-1,0))) -> 5 | C93: =IF(G93="CÉLULA CONSTRUTIVA",0,IF(G93="ETAPA",OFFSET(C93,-1,0)+1,OFFSET(C93,-1,0))) -> 1 | D93: =IF(G93="ETAPA",0,IF(G93="SUBETAPA",OFFSET(D93,-1,0)+1,OFFSET(D93,-1,0))) -> 9 | E93: =IF(G93="Subetapa",0,IF(G93="serviço",OFFSET(E93,-1,0)+1,OFFSET(E93,-1,0))) -> 0 | G93: Subetapa | H93: =IF(G93="Unidade Construtiva",TEXT(A93,"00"),IF(G93="Célula Construtiva",TEXT(B93,"00"),IF(G93="Etapa",CONCATENATE(TEXT(B93,"00"),".",TEXT(C93,"000")),IF(G93="Subetapa",CONCATENATE(TEXT(B93,"00"),".",TEXT(C93,"000"),".",TEXT(D93,"000")),IF(G93="Serviço",CONCATENATE(TEXT(B93,"00"),".",TEXT(C93,"000"),".",TEXT(D93,"000"),".",TEXT(E93,"000")),""))))) -> 05.001.009 | I93: Impermeabilização de floreiras | L93: =L94 -> 0
A94: =IF($G94="UNIDADE CONSTRUTIVA",OFFSET(A94,0,0)+1,LARGE(A$3:A92,1)) -> 2 | B94: =IF(G94="UNIDADE CONSTRUTIVA",0,IF(G94="CÉLULA CONSTRUTIVA",OFFSET(B94,-1,0)+1,OFFSET(B94,-1,0))) -> 5 | C94: =IF(G94="CÉLULA CONSTRUTIVA",0,IF(G94="ETAPA",OFFSET(C94,-1,0)+1,OFFSET(C94,-1,0))) -> 1 | D94: =IF(G94="ETAPA",0,IF(G94="SUBETAPA",OFFSET(D94,-1,0)+1,OFFSET(D94,-1,0))) -> 9 | E94: =IF(G94="Subetapa",0,IF(G94="serviço",OFFSET(E94,-1,0)+1,OFFSET(E94,-1,0))) -> 1 | G94: Serviço | H94: =IF(G94="Unidade Construtiva",TEXT(A94,"00"),IF(G94="Célula Construtiva",TEXT(B94,"00"),IF(G94="Etapa",CONCATENATE(TEXT(B94,"00"),".",TEXT(C94,"000")),IF(G94="Subetapa",CONCATENATE(TEXT(B94,"00"),".",TEXT(C94,"000"),".",TEXT(D94,"000")),IF(G94="Serviço",CONCATENATE(TEXT(B94,"00"),".",TEXT(C94,"000"),".",TEXT(D94,"000"),".",TEXT(E94,"000")),""))))) -> 05.001.009.001 | I94: Impermeabilização de floreiras
A95: =IF($G95="UNIDADE CONSTRUTIVA",OFFSET(A95,0,0)+1,LARGE(A$3:A93,1)) -> 2 | B95: =IF(G95="UNIDADE CONSTRUTIVA",0,IF(G95="CÉLULA CONSTRUTIVA",OFFSET(B95,-1,0)+1,OFFSET(B95,-1,0))) -> 5 | C95: =IF(G95="CÉLULA CONSTRUTIVA",0,IF(G95="ETAPA",OFFSET(C95,-1,0)+1,OFFSET(C95,-1,0))) -> 1 | D95: =IF(G95="ETAPA",0,IF(G95="SUBETAPA",OFFSET(D95,-1,0)+1,OFFSET(D95,-1,0))) -> 10 | E95: =IF(G95="Subetapa",0,IF(G95="serviço",OFFSET(E95,-1,0)+1,OFFSET(E95,-1,0))) -> 0 | G95: Subetapa | H95: =IF(G95="Unidade Construtiva",TEXT(A95,"00"),IF(G95="Célula Construtiva",TEXT(B95,"00"),IF(G95="Etapa",CONCATENATE(TEXT(B95,"00"),".",TEXT(C95,"000")),IF(G95="Subetapa",CONCATENATE(TEXT(B95,"00"),".",TEXT(C95,"000"),".",TEXT(D95,"000")),IF(G95="Serviço",CONCATENATE(TEXT(B95,"00"),".",TEXT(C95,"000"),".",TEXT(D95,"000"),".",TEXT(E95,"000")),""))))) -> 05.001.010 | I95: Impermeabilização de reservatórios | L95: =L96 -> 0
A96: =IF($G96="UNIDADE CONSTRUTIVA",OFFSET(A96,0,0)+1,LARGE(A$3:A94,1)) -> 2 | B96: =IF(G96="UNIDADE CONSTRUTIVA",0,IF(G96="CÉLULA CONSTRUTIVA",OFFSET(B96,-1,0)+1,OFFSET(B96,-1,0))) -> 5 | C96: =IF(G96="CÉLULA CONSTRUTIVA",0,IF(G96="ETAPA",OFFSET(C96,-1,0)+1,OFFSET(C96,-1,0))) -> 1 | D96: =IF(G96="ETAPA",0,IF(G96="SUBETAPA",OFFSET(D96,-1,0)+1,OFFSET(D96,-1,0))) -> 10 | E96: =IF(G96="Subetapa",0,IF(G96="serviço",OFFSET(E96,-1,0)+1,OFFSET(E96,-1,0))) -> 1 | G96: Serviço | H96: =IF(G96="Unidade Construtiva",TEXT(A96,"00"),IF(G96="Célula Construtiva",TEXT(B96,"00"),IF(G96="Etapa",CONCATENATE(TEXT(B96,"00"),".",TEXT(C96,"000")),IF(G96="Subetapa",CONCATENATE(TEXT(B96,"00"),".",TEXT(C96,"000"),".",TEXT(D96,"000")),IF(G96="Serviço",CONCATENATE(TEXT(B96,"00"),".",TEXT(C96,"000"),".",TEXT(D96,"000"),".",TEXT(E96,"000")),""))))) -> 05.001.010.001 | I96: Impermeabilização de reservatórios
A97: =IF($G97="UNIDADE CONSTRUTIVA",OFFSET(A97,0,0)+1,LARGE(A$3:A95,1)) -> 2 | B97: =IF(G97="UNIDADE CONSTRUTIVA",0,IF(G97="CÉLULA CONSTRUTIVA",OFFSET(B97,-1,0)+1,OFFSET(B97,-1,0))) -> 5 | C97: =IF(G97="CÉLULA CONSTRUTIVA",0,IF(G97="ETAPA",OFFSET(C97,-1,0)+1,OFFSET(C97,-1,0))) -> 1 | D97: =IF(G97="ETAPA",0,IF(G97="SUBETAPA",OFFSET(D97,-1,0)+1,OFFSET(D97,-1,0))) -> 11 | E97: =IF(G97="Subetapa",0,IF(G97="serviço",OFFSET(E97,-1,0)+1,OFFSET(E97,-1,0))) -> 0 | G97: Subetapa | H97: =IF(G97="Unidade Construtiva",TEXT(A97,"00"),IF(G97="Célula Construtiva",TEXT(B97,"00"),IF(G97="Etapa",CONCATENATE(TEXT(B97,"00"),".",TEXT(C97,"000")),IF(G97="Subetapa",CONCATENATE(TEXT(B97,"00"),".",TEXT(C97,"000"),".",TEXT(D97,"000")),IF(G97="Serviço",CONCATENATE(TEXT(B97,"00"),".",TEXT(C97,"000"),".",TEXT(D97,"000"),".",TEXT(E97,"000")),""))))) -> 05.001.011 | I97: Mão de obra
A98: =IF($G98="UNIDADE CONSTRUTIVA",OFFSET(A98,0,0)+1,LARGE(A$3:A96,1)) -> 2 | B98: =IF(G98="UNIDADE CONSTRUTIVA",0,IF(G98="CÉLULA CONSTRUTIVA",OFFSET(B98,-1,0)+1,OFFSET(B98,-1,0))) -> 5 | C98: =IF(G98="CÉLULA CONSTRUTIVA",0,IF(G98="ETAPA",OFFSET(C98,-1,0)+1,OFFSET(C98,-1,0))) -> 1 | D98: =IF(G98="ETAPA",0,IF(G98="SUBETAPA",OFFSET(D98,-1,0)+1,OFFSET(D98,-1,0))) -> 11 | E98: =IF(G98="Subetapa",0,IF(G98="serviço",OFFSET(E98,-1,0)+1,OFFSET(E98,-1,0))) -> 1 | G98: Serviço | H98: =IF(G98="Unidade Construtiva",TEXT(A98,"00"),IF(G98="Célula Construtiva",TEXT(B98,"00"),IF(G98="Etapa",CONCATENATE(TEXT(B98,"00"),".",TEXT(C98,"000")),IF(G98="Subetapa",CONCATENATE(TEXT(B98,"00"),".",TEXT(C98,"000"),".",TEXT(D98,"000")),IF(G98="Serviço",CONCATENATE(TEXT(B98,"00"),".",TEXT(C98,"000"),".",TEXT(D98,"000"),".",TEXT(E98,"000")),""))))) -> 05.001.011.001 | I98: Mão de obra para regularização de superfícies a serem impermeabilizadas | K98: m²
A99: =IF($G99="UNIDADE CONSTRUTIVA",OFFSET(A99,0,0)+1,LARGE(A$3:A97,1)) -> 2 | B99: =IF(G99="UNIDADE CONSTRUTIVA",0,IF(G99="CÉLULA CONSTRUTIVA",OFFSET(B99,-1,0)+1,OFFSET(B99,-1,0))) -> 5 | C99: =IF(G99="CÉLULA CONSTRUTIVA",0,IF(G99="ETAPA",OFFSET(C99,-1,0)+1,OFFSET(C99,-1,0))) -> 1 | D99: =IF(G99="ETAPA",0,IF(G99="SUBETAPA",OFFSET(D99,-1,0)+1,OFFSET(D99,-1,0))) -> 11 | E99: =IF(G99="Subetapa",0,IF(G99="serviço",OFFSET(E99,-1,0)+1,OFFSET(E99,-1,0))) -> 2 | G99: Serviço | H99: =IF(G99="Unidade Construtiva",TEXT(A99,"00"),IF(G99="Célula Construtiva",TEXT(B99,"00"),IF(G99="Etapa",CONCATENATE(TEXT(B99,"00"),".",TEXT(C99,"000")),IF(G99="Subetapa",CONCATENATE(TEXT(B99,"00"),".",TEXT(C99,"000"),".",TEXT(D99,"000")),IF(G99="Serviço",CONCATENATE(TEXT(B99,"00"),".",TEXT(C99,"000"),".",TEXT(D99,"000"),".",TEXT(E99,"000")),""))))) -> 05.001.011.002 | I99: Mão de obra para proteção mecânica de superfícies que recebem manta | K99: m²
A100: =IF($G100="UNIDADE CONSTRUTIVA",OFFSET(A100,0,0)+1,LARGE(A$3:A98,1)) -> 2 | B100: =IF(G100="UNIDADE CONSTRUTIVA",0,IF(G100="CÉLULA CONSTRUTIVA",OFFSET(B100,-1,0)+1,OFFSET(B100,-1,0))) -> 5 | C100: =IF(G100="CÉLULA CONSTRUTIVA",0,IF(G100="ETAPA",OFFSET(C100,-1,0)+1,OFFSET(C100,-1,0))) -> 1 | D100: =IF(G100="ETAPA",0,IF(G100="SUBETAPA",OFFSET(D100,-1,0)+1,OFFSET(D100,-1,0))) -> 11 | E100: =IF(G100="Subetapa",0,IF(G100="serviço",OFFSET(E100,-1,0)+1,OFFSET(E100,-1,0))) -> 3 | G100: Serviço | H100: =IF(G100="Unidade Construtiva",TEXT(A100,"00"),IF(G100="Célula Construtiva",TEXT(B100,"00"),IF(G100="Etapa",CONCATENATE(TEXT(B100,"00"),".",TEXT(C100,"000")),IF(G100="Subetapa",CONCATENATE(TEXT(B100,"00"),".",TEXT(C100,"000"),".",TEXT(D100,"000")),IF(G100="Serviço",CONCATENATE(TEXT(B100,"00"),".",TEXT(C100,"000"),".",TEXT(D100,"000"),".",TEXT(E100,"000")),""))))) -> 05.001.011.003 | I100: Mão de obra para Impermeabilização de cisternas | K100: m²
...

Sheet RESIDENCIAL
G1: ORÇAMENTO DE VIABILIDADE - RESIDENCIAL
J2: RESIDENCIAL | M2: OBSERVAÇÕES | P2: Clientes possuem opção de fazer 3 suites ou 2 suites + 2 demi-suites - padrão 4 suites
A3: Unidade Construtiva | B3: Célula Construtiva | C3: Etapa | D3: Subetapa | E3: Serviço | G3: Hotel Colline de France - Rio de Janeiro | J3: Quantidade | K3: Unidade | L3: Custo
A4: =IF($G4="UNIDADE CONSTRUTIVA",3,LARGE(A$3:A3,1)) -> 3 | B4: =IF(G4="UNIDADE CONSTRUTIVA",0,IF(G4="CÉLULA CONSTRUTIVA",OFFSET(B4,-1,0)+1,OFFSET(B4,-1,0))) -> 0 | C4: =IF(G4="CÉLULA CONSTRUTIVA",0,IF(G4="ETAPA",OFFSET(C4,-1,0)+1,OFFSET(C4,-1,0))) -> Etapa | D4: =IF(G4="ETAPA",0,IF(G4="SUBETAPA",OFFSET(D4,-1,0)+1,OFFSET(D4,-1,0))) -> Subetapa | E4: =IF(G4="Subetapa",0,IF(G4="serviço",OFFSET(E4,-1,0)+1,OFFSET(E4,-1,0))) -> Serviço | G4: UNIDADE CONSTRUTIVA | H4: =IF(G4="Unidade Construtiva",TEXT(A4,"00"),IF(G4="Célula Construtiva",TEXT(B4,"00"),IF(G4="Etapa",CONCATENATE(TEXT(B4,"00"),".",TEXT(C4,"000")),IF(G4="Subetapa",CONCATENATE(TEXT(B4,"00"),".",TEXT(C4,"000"),".",TEXT(D4,"000")),IF(G4="Serviço",CONCATENATE(TEXT(B4,"00"),".",TEXT(C4,"000"),".",TEXT(D4,"000"),".",TEXT(E4,"000")),""))))) -> 03 | I4: GERENCIAMENTO EXECUTIVO | L4: =L5+L22+L40+L54+L74+L108+L132+L155+L169+L181+L192+L212+L231+L255+L275+L316+L335+L382+L393+L411+L445 -> 87526573
A5: =IF($G5="UNIDADE CONSTRUTIVA",OFFSET(A5,0,0)+1,LARGE(A$3:A4,1)) -> 3 | B5: =IF(G5="UNIDADE CONSTRUTIVA",0,IF(G5="CÉLULA CONSTRUTIVA",OFFSET(B5,-1,0)+1,OFFSET(B5,-1,0))) -> 1 | C5: =IF(G5="CÉLULA CONSTRUTIVA",0,IF(G5="ETAPA",OFFSET(C5,-1,0)+1,OFFSET(C5,-1,0))) -> 0 | D5: =IF(G5="ETAPA",0,IF(G5="SUBETAPA",OFFSET(D5,-1,0)+1,OFFSET(D5,-1,0))) -> Subetapa | E5: =IF(G5="Subetapa",0,IF(G5="serviço",OFFSET(E5,-1,0)+1,OFFSET(E5,-1,0))) -> Serviço | G5: CÉLULA CONSTRUTIVA | H5: =IF(G5="Unidade Construtiva",TEXT(A5,"00"),IF(G5="Célula Construtiva",TEXT(B5,"00"),IF(G5="Etapa",CONCATENATE(TEXT(B5,"00"),".",TEXT(C5,"000")),IF(G5="Subetapa",CONCATENATE(TEXT(B5,"00"),".",TEXT(C5,"000"),".",TEXT(D5,"000")),IF(G5="Serviço",CONCATENATE(TEXT(B5,"00"),".",TEXT(C5,"000"),".",TEXT(D5,"000"),".",TEXT(E5,"000")),""))))) -> 01 | I5: MOVIMENTAÇÃO DE TERRA | L5: =L6 -> 150402.2
A6: =IF($G6="UNIDADE CONSTRUTIVA",OFFSET(A6,0,0)+1,LARGE(A$3:A5,1)) -> 3 | B6: =IF(G6="UNIDADE CONSTRUTIVA",0,IF(G6="CÉLULA CONSTRUTIVA",OFFSET(B6,-1,0)+1,OFFSET(B6,-1,0))) -> 1 | C6: =IF(G6="CÉLULA CONSTRUTIVA",0,IF(G6="ETAPA",OFFSET(C6,-1,0)+1,OFFSET(C6,-1,0))) -> 1 | D6: =IF(G6="ETAPA",0,IF(G6="SUBETAPA",OFFSET(D6,-1,0)+1,OFFSET(D6,-1,0))) -> 0 | E6: =IF(G6="Subetapa",0,IF(G6="serviço",OFFSET(E6,-1,0)+1,OFFSET(E6,-1,0))) -> Serviço | G6: ETAPA | H6: =IF(G6="Unidade Construtiva",TEXT(A6,"00"),IF(G6="Célula Construtiva",TEXT(B6,"00"),IF(G6="Etapa",CONCATENATE(TEXT(B6,"00"),".",TEXT(C6,"000")),IF(G6="Subetapa",CONCATENATE(TEXT(B6,"00"),".",TEXT(C6,"000"),".",TEXT(D6,"000")),IF(G6="Serviço",CONCATENATE(TEXT(B6,"00"),".",TEXT(C6,"000"),".",TEXT(D6,"000"),".",TEXT(E6,"000")),""))))) -> 01.001 | I6: MOVIMENTAÇÃO DE TERRA | L6: =SUM(L7:L21)/2 -> 150402.2
