Workbook
Name aa: #REF!
Name aa: #REF!
Name aa: #REF!
Name aa: #REF!
Name aa: #REF!
Name aaaa: '[1]M.O.'!#REF!
Name aaaa: '[1]M.O.'!#REF!
Name aaaa: '[1]M.O.'!#REF!
Name aaaa: '[1]M.O.'!#REF!
Name angelo: [2]Geral!#REF!
Name angelo: [2]Geral!#REF!
Name angelo: [2]Geral!#REF!
Name aux: #REF!
Name aux: #REF!
Name aux: #REF!
Name aux: #REF!
Name BDA: #REF!
Name BDA: #REF!
Name BDA: #REF!
Name BDA: #REF!
Name BDI: #REF!
Name BDI: #REF!
Name BDI: #REF!
Name BDI: #REF!
Name ca: #REF!
Name ca: #REF!
Name ca: #REF!
Name ca: #REF!
Name Capa: #REF!
Name Capa: #REF!
Name Capa: #REF!
Name Capa: #REF!
Name cronograma: #REF!
Name cronograma: #REF!
Name cronograma: #REF!
Name cronograma: #REF!
Name D: #REF!
Name D: #REF!
Name D: #REF!
Name D: #REF!
Name direto: #REF!
Name direto: #REF!
Name direto: #REF!
Name direto: #REF!
Name DRE: #REF!
Name DRE: #REF!
Name DRE: #REF!
Name DRE: #REF!
Name ea: #REF!
Name ea: #REF!
Name ea: #REF!
Name ea: #REF!
Name eee: {#N/A,#N/A,FALSE,"ET-CAPA";#N/A,#N/A,FALSE,"ET-PAG1";#N/A,#N/A,FALSE,"ET-PAG2";#N/A,#N/A,FALSE,"ET-PAG3";#N/A,#N/A,FALSE,"ET-PAG4";#N/A,#N/A,FALSE,"ET-PAG5"}
Name eee: {#N/A,#N/A,FALSE,"ET-CAPA";#N/A,#N/A,FALSE,"ET-PAG1";#N/A,#N/A,FALSE,"ET-PAG2";#N/A,#N/A,FALSE,"ET-PAG3";#N/A,#N/A,FALSE,"ET-PAG4";#N/A,#N/A,FALSE,"ET-PAG5"}
Name eee: {#N/A,#N/A,FALSE,"ET-CAPA";#N/A,#N/A,FALSE,"ET-PAG1";#N/A,#N/A,FALSE,"ET-PAG2";#N/A,#N/A,FALSE,"ET-PAG3";#N/A,#N/A,FALSE,"ET-PAG4";#N/A,#N/A,FALSE,"ET-PAG5"}
Name eee: {#N/A,#N/A,FALSE,"ET-CAPA";#N/A,#N/A,FALSE,"ET-PAG1";#N/A,#N/A,FALSE,"ET-PAG2";#N/A,#N/A,FALSE,"ET-PAG3";#N/A,#N/A,FALSE,"ET-PAG4";#N/A,#N/A,FALSE,"ET-PAG5"}
Name FFFFFFF: #REF!
Name FFFFFFF: #REF!
Name item_1: #REF!
Name item_1: #REF!

Sheet OBRA
A1: Obra | B1: Eternity
A2: Empresa | B2: Meia Praia
A3: Revisão | B3: R01
A4: DADOS OBRA
A6: ARQUITETURA
B8: Descrição | C8: Unidade | D8: Quantidade
B9: ÁREA DO TERRENO | C9: M2 | D9: 304.5
B10: ÁREA CONSTRUÍDA | C10: M2 | D10: 11892.95 | E10: =D10/D12 -> 247.76979
B11: NÚMERO DE UNIDADES HABITACIONAIS | C11: UN | D11: 46
B12: MESES DE OBRA | C12: MÊS | D12: 48
B13: NÚMERO DE PAVIMENTOS | C13: UN | D13: 28

Sheet CANTEIRO
A1: Obra | B1: Eternity
A2: Empresa | B2: Meia Praia
A3: Revisão | B3: =OBRA!B3 -> R01
A4: LEVANTAMENTO QUANTITATIVO
A6: Instalações de canteiro
A8: Instalações de canteiro
B10: Descrição | C10: Unidade | D10: Quantidade
B11: Produtividade média | C11: AC / prazo | D11: =OBRA!D10/OBRA!D12 -> 247.76979
B12: Pm | C12: h/m2 | D12: 49
B13: Numero de funcionários | C13: un | D13: 15
B14: Equipe administrativa | C14: un | D14: 5
B15: Pontos de água e esgoto | C15: un | D15: =ROUNDUP($D$13/20,0) -> 1 | E15: 20 funcionários/ponto
B16: Ferramentas | C16: R$ | D16: =800*D13 -> 12000 | E16: 800,00/func.
B17: EPI | C17: R$ | D17: =500*(D13+D14) -> 10000 | E17: 500,00/func.
B18: Banheiro | C18: un | D18: =ROUNDUP($D$13/20,0) -> 1 | E18: 1/20 func
A20: Mobiliário de canteiro
B22: Descrição | C22: Unidade | D22: Quantidade | E22: Custo unitário | F22: Custo total
B23: Cadeira | C23: un | D23: =ROUNDUP(D14*1.5,0) -> 8 | E23: 200 | F23: =D23*E23 -> 1600
B24: Mesa | C24: un | D24: =D14 -> 5 | E24: 1000 | F24: =E24*D24 -> 5000
B25: Ar condicionado | C25: un | D25: 1 | E25: 5000 | F25: =E25*D25 -> 5000
B26: Armário | C26: m | D26: =7 -> 7 | E26: 900 | F26: =E26*D26 -> 6300
B27: Escrivaninha | C27: un | D27: =D14 -> 5 | E27: 800 | F27: =E27*D27 -> 4000
B28: TOTAL | F28: =F25+F26+F27+F24+F23 -> 21900
B29: Descrição | C29: Unidade | D29: Quantidade | E29: Custo unitário | F29: Custo total
B30: Computador pessoal | C30: un | D30: =D14 -> 5 | E30: 6000 | F30: =D30*E30 -> 30000
B31: Impressora | C31: un | D31: 1 | E31: 2000 | F31: =E31*D31 -> 2000
B32: Roteador | C32: un | D32: 2 | E32: 500 | F32: =E32*D32 -> 1000
B33: TOTAL | F33: =+F30+F31+F32 -> 33000

Sheet EPCs
A1: Obra | B1: Eternity
A2: Empresa | B2: Meia Praia
A3: Revisão | B3: =[3]OBRA!B3 -> R00
A4: LEVANTAMENTO QUANTITATIVO
A6: Equipamentos de proteção coletiva
A8: Bandejas de proteção
B10: Descrição | C10: Unidade | D10: Quantidade
B11: Perímetro de projeção embasamneto | C11: m | D11: 119.84
B12: Perímetro de projeção torre | C12: m | D12: 76.48
B13: Bandeja de proteção primária | C13: m | D13: =D11+D12 -> 196.32
B14: Bandeja de proteção secundária | C14: m | D14: =D12 -> 76.48
A16: Guarda - corpo de desforma
B18: Descrição | C18: Unidade | D18: Quantidade
B19: Perímetro de projeção da torre | C19: m | D19: =D12 -> 76.48
B20: Repetições de pavimentos** | C20: un | D20: 4
B21: Proteção de periferia pós desforma torre | C21: m | D21: =(D19*D20) -> 305.92
A23: Tela fachadeira
B25: Descrição | C25: Unidade | D25: Quantidade
B26: Perimetro da torre | C26: m | D26: =D12 -> 76.48
B27: Altura da torre | C27: m | D27: =3.2*24 -> 76.8
B28: Tela fachadeira | C28: m2 | D28: =D26*D27 -> 5873.664
A30: Tela SLQA
B32: Descrição | C32: Unidade | D32: Quantidade
B33: Perimetro da torre | C33: m | D33: =D19 -> 76.48
B34: Tela SLQA | C34: m | D34: =D33 -> 76.48
A36: Fechamento removível de vãos em madeira
B38: Descrição | C38: Unidade | D38: Quantidade
B39: Área das portas de elevadores | C39: m2 | D39: =0.9*2.4 -> 2.16
B40: Quantidade de elevadores | C40: un | D40: 2
B41: Quantidade de portas de elevadores | C41: un | D41: =D40*[3]OBRA!D13 -> 56
B42: Fechamento removível de vãos em madeira | C42: m2 | D42: =D39*D41 -> 120.96
A44: Tapume
B46: Descrição | C46: Unidade | D46: Quantidade
B47: Perímetro de encontro com pavimentação | C47: m | D47: 31.17
B48: Altura do tapume | C48: m | D48: 2.4
B49: Cobertura para proteção de pedestres | C49: m2 | D49: =D48*D47 -> 74.808

Sheet CUSTOS_INDIRETOS
A1: ORÇAMENTO PARAMÉTRICO - CUSTOS INDIRETOS
A7: Cliente | B7: Meia Praia
A8: Obra | B8: Eternity
A9: Data | B9: 45509
A10: Versão | B10: R01
A12: GERENCIAMENTO TÉCNICO
A13: Código | B13: Descrição | C13: Un. | D13: Quantidade orçada | E13: Preço unitário | F13: Preço total
A14: 01 | B14: GERENCIAMENTO TÉCNICO | F14: =F15+F41 -> 1362498.7
A15: 01.001 | B15: ESTUDOS, PROJETOS E CONSULTORIAS | F15: =SUM(F16:F36) -> 1137556.3
A16: 01.001.001 | B16: Estudos | F16: 18936.713
A17: 02.001.001.001 | B17: Levantamento topográfico
A18: 02.001.001.002 | B18: Estudo geológico
A19: 02.001.001.003 | B19: Estudo ambiental
A20: 02.001.001.004 | B20: Sondagem
A21: 02.001.001.005 | B21: Memorial descritivo
A22: 02.001.001.006 | B22: Projeto de canteiro
A23: 01.001.002 | B23: Projetos | F23: 624115.71
A24: 02.001.002.001 | B24: Projeto arquitetônico | F24: =240000 -> 240000
A25: 02.001.002.002 | B25: Projeto de terraplanagem
A26: 02.001.002.003 | B26: Projeto de fundações
A27: 02.001.002.004 | B27: Projeto hidrossanitário
A28: 02.001.002.005 | B28: Projeto PPCI e GLP
A29: 02.001.002.006 | B29: Projeto estrutural
A30: 02.001.002.007 | B30: Projeto de elétrico
A31: 02.001.002.008 | B31: Projeto de climatização
A32: 02.001.002.009 | B32: Projeto de interiores
A33: 02.001.002.010 | B33: Projeto de impermeabilização
A34: 01.001.003 | B34: Consultorias | F34: 115455.44
A35: 02.001.003.001 | B35: Planejamento e orçamento
A36: 01.001.004 | B36: Ensaios e Laudos | F36: 139048.44
A37: 02.001.004.001 | B37: Controle tecnológico do concreto
A38: 02.001.004.002 | B38: Ensaio com laudo de desempenho
A39: 02.001.004.003 | B39: Prova de cargas estáticas
A40: 02.001.004.004 | B40: Laudo preventivo de danos à vizinhança
A41: 01.002 | B41: TAXAS E DOCUMENTOS | F41: =SUM(F42:F58) -> 224942.38
A42: 01.002.001 | B42: Seguros | F42: 22310.883
A43: 02.002.001.001 | B43: Seguro de obra
A44: 01.002.002 | B44: Licenciamentos, Taxas, Impostos | F44: 141762.55
A45: 02.002.002.001 | B45: Taxas de alvarás
A46: 02.002.002.002 | B46: IPTU
A47: 02.002.002.003 | B47: Aprovação e legalização ambiental
A48: 02.002.002.004 | B48: Aprovação e legalização de água e esgoto
A49: 02.002.002.005 | B49: Aprovação e legalização elétrico
A50: 02.002.002.006 | B50: Aprovação e legalização bombeiros
A51: 02.002.002.007 | B51: Aprovação e legalização prefeitura
A52: 02.002.002.008 | B52: Taxas de ART
A53: 02.002.002.009 | B53: Despesas cartorio, licencas, certidoes e juridicas
A54: 02.002.002.010 | B54: Incorporação
A55: 02.002.002.011 | B55: Habite-se
A56: 02.002.002.012 | B56: Certidão INSS
A57: 02.002.002.013 | B57: Outorga onerosa
A58: 01.002.003 | B58: Documentos | F58: 60868.941
A59: 02.002.003.001 | B59: As built
A60: 02.002.003.002 | B60: Laudo de entrega
A61: 02.002.003.003 | B61: Manual de proprietário
A62: 02 | B62: GERENCIAMENTO ADMINISTRATIVO | F62: =F63+F78+F99 -> 3431505.6
A63: 02.001 | B63: SEGURANÇA, MEIO AMBIENTE E SAÚDE | F63: =F64+F66+F77 -> 497992.64
A64: 02.001.001 | B64: Segurança do Trabalho | F64: =F65 -> 120000
A65: 02.001.001.001 | B65: Serviço de segurança do trabalho terceirizado | C65: mes | D65: =OBRA!D12 -> 48 | E65: =[3]BASES!H19 -> 2500 | F65: =E65*D65 -> 120000
A66: 02.001.002 | B66: Equipamentos de proteção | F66: =SUM(F67:F76) -> 339466.05
A67: 02.001.002.001 | B67: Bandeja de proteção primária | C67: m | D67: =EPCs!D13 -> 196.32 | E67: 294.33 | F67: =E67*D67 -> 57782.866
A68: 02.001.002.002 | B68: Bandeja de proteção secundária | C68: m | D68: =EPCs!D14 -> 76.48 | E68: 210.06 | F68: =E68*D68 -> 16065.389
A69: 02.001.002.003 | B69: Guarda corpo em laje pós - desforma | C69: m | D69: =EPCs!D21 -> 305.92 | E69: =39.19+7.55+0.63+1.63 -> 49 | F69: =E69*D69 -> 14990.08
A70: 02.001.002.004 | B70: Fechamento removível de vãos de porta de elevador em madeira | C70: m2 | D70: =EPCs!D42 -> 120.96 | E70: 19.89 | F70: =E70*D70 -> 2405.8944
A71: 02.001.002.005 | B71: Varal de segurança com cabo de aço | C71: m | D71: =D69 -> 305.92 | E71: 244 | F71: =E71*D71 -> 74644.48
A72: 02.001.002.006 | B72: Tela fachadeira reforçada com impressão digital | C72: m2 | D72: =EPCs!D28 -> 5873.664 | E72: 15 | F72: =E72*D72 -> 88104.96
A73: 02.001.002.007 | B73: Sinalização com placa indicativa fixada na estrutura | C73: vb | D73: 1 | E73: 3270.4385 | F73: =E73*D73 -> 3270.4385
A74: 02.001.002.008 | B74: Equipamentos de proteção individual | C74: vb | D74: 1 | E74: =CANTEIRO!D17 -> 10000 | F74: =E74*D74 -> 10000
A75: 02.001.002.009 | B75: Gurada-corpo de vãos com régua de pinus 2,5x15cm | C75: m | D75: =314.16+83.49/1.1 -> 390.06 | E75: 13.68 | F75: =E75*D75 -> 5336.0208
A76: 02.001.002.011 | B76: Tela SLQA | C76: m | D76: =EPCs!D34 -> 76.48 | E76: =100727.28/(460.84/4) -> 874.29286 | F76: =E76*D76 -> 66865.918
A77: 02.001.003 | B77: Meio Ambiente | F77: 38526.593
A78: 02.002 | B78: ADMINISTRAÇÃO E CANTEIRO DE OBRA | F78: =F79+F88+F90+F98 -> 2632107
A79: 02.002.001 | B79: Equipe de Gestão e Apoio | F79: =SUM(F80:F87) -> 1939200
A80: 02.002.001.001 | B80: Engenheiro Civil | C80: mes | D80: =OBRA!$D$12 -> 48 | E80: 8000 | F80: =E80*D80 -> 384000
A81: 02.002.001.002 | B81: Mestre Geral | C81: mes | D81: =OBRA!$D$12 -> 48 | E81: 6500 | F81: =E81*D81 -> 312000 | G81: rateio do custo do pessoal do escritorio
A82: 02.002.001.003 | B82: Almoxarife | C82: mes | D82: =OBRA!$D$12 -> 48 | E82: 5000 | F82: =E82*D82 -> 240000
A83: 02.002.001.004 | B83: Auxiliar de Engenharia | C83: mes | D83: =OBRA!$D$12 -> 48 | E83: 3000 | F83: =E83*D83 -> 144000
A84: 02.002.001.005 | B84: Estagiário de Engenharia | C84: mes | D84: =OBRA!$D$12 -> 48 | E84: 1400 | F84: =E84*D84 -> 67200
A85: 02.002.001.006 | B85: Operador de Guincho | C85: mes | D85: =OBRA!$D$12 -> 48 | E85: 3500 | F85: =E85*D85 -> 168000
A86: 02.002.001.007 | B86: Equipe de apoio - 1 carpiteiro + 2 serventes | C86: mes | D86: =OBRA!$D$12 -> 48 | E86: 10500 | F86: =E86*D86 -> 504000
A87: 02.002.001.008 | B87: Serviço de vigilância | C87: mes | D87: =OBRA!$D$12 -> 48 | E87: 2500 | F87: =E87*D87 -> 120000
A88: 02.002.002 | B88: Operação Inicial do Canteiro | F88: =SUM(F89:F89) -> 3806.25
A89: 02.002.002.001 | B89: Limpeza mecanizada de camada vegetal | C89: m2 | D89: =OBRA!D9 -> 304.5 | E89: 12.5 | F89: =E89*D89 -> 3806.25
A90: 02.002.003 | B90: Instalações Provisórias | F90: =SUM(F91:F97) -> 377097.15
A91: 02.002.003.001 | B91: Locação de banheiro químico | C91: mes | D91: =OBRA!D12 -> 48 | E91: 2850 | F91: =E91*D91 -> 136800
A92: 02.002.003.002 | B92: Instalações de canteiro | C92: vb | D92: 1 | E92: 66600.524 | F92: =E92*D92 -> 66600.524
A93: 02.002.003.003 | B93: Instalações Provisórias: Redes de Água Fria, Esgoto e Drenagem | C93: vb | D93: 1 | E93: 14272.146 | F93: =E93*D93 -> 14272.146
A94: 02.002.003.004 | B94: Instalações Provisórias: Redes Elétrica, Comunicação e Dados | C94: vb | D94: 1 | E94: 12491.656 | F94: =E94*D94 -> 12491.656
A95: 02.002.003.005 | B95: Mobiliário de apoio a obra | C95: vb | D95: 1 | E95: 87000 | F95: =E95*D95 -> 87000
A96: 02.002.003.006 | B96: Equipamentos escritório - aquisição | C96: vb | D96: 1 | E96: 51000 | F96: =E96*D96 -> 51000
A97: 02.002.003.007 | B97: Tapume com telha metálica | C97: m2 | D97: =EPCs!D49 -> 74.808 | E97: 119.41 | F97: =E97*D97 -> 8932.8233
A98: 02.002.005 | B98: Despesas de Consumo e Manutenção | F98: 312003.61
A99: 02.003 | B99: EQUIPAMENTOS | F99: =F100+F109 -> 301406
A100: 02.003.001 | B100: Equipamentos de Obra | F100: =SUM(F101:F108) -> 200606
A101: 02.003.001.001 | B101: Ferramentas - aquisição/manutenção | C101: vb | D101: 1 | E101: =CANTEIRO!D16 -> 12000 | F101: =E101*D101 -> 12000
A102: 02.003.001.002 | B102: Manutenção incial de elevador cremalheira | C102: Un. | D102: 1 | E102: 70000 | F102: =E102*D102 -> 70000
A103: 02.003.001.003 | B103: Menutenção periódica de elevador cremalheira | C103: mes | D103: 25 | E103: 2000 | F103: =E103*D103 -> 50000
A104: 02.003.001.004 | B104: Montagem e desmontagem de elevador cremalheira | C104: Un. | D104: 1 | E104: 17600 | F104: =E104*D104 -> 17600
A105: 02.003.001.005 | B105: Mobilização e desmobilização de elevador cremalheira | C105: Un. | D105: 1 | E105: 13000 | F105: =E105*D105 -> 13000
A106: 02.003.001.006 | B106: Menutenção periódica de Mini-grua | C106: mes | D106: 25 | E106: 850 | F106: =E106*D106 -> 21250
...

Sheet Gerenciamento Executivo
A1: ORÇAMENTO PARAMÉTRICO
A7: Cliente | B7: Meia Praia
A8: Obra | B8: Eternity
A9: Data | B9: 45509
A10: Versão | B10: R01
A12: CÓDIGO | B12: ITEM | C12: Quantidade | D12: Unidade | E12: Custo unitário | F12: Valor Orçado | G12: Observações
A13: 1 | B13: GERENCIAMENTO TÉCNICO E ADMINISTRATIVO | F13: =F14 -> 4794004.3
A14: 1.1 | B14: GERENCIAMENTO TÉCNICO E ADMINISTRATIVO | F14: =F15 -> 4794004.3
A15: 1.1.1 | B15: Gerenciamento técnico e administrativo | C15: 1 | D15: vb | E15: =F15/C15 -> 4794004.3 | F15: =CUSTOS_INDIRETOS!F113 -> 4794004.3 | G15: Conforme abertura de abas anteriores
A16: 2 | B16: MOVIMENTAÇÃO DE TERRA | F16: =F17 -> 140408.99
A17: 2.1 | B17: MOVIMENTAÇÃO DE VALAS | F17: =SUM(F18:F22) -> 140408.99
A18: 2.1.1 | B18: Escavação mecanizada para blocos e baldrames | C18: 759.2832 | D18: m3 | E18: =F18/C18 -> 66 | F18: 50112.691 | G18: Custo previsto para toda a movimentação com maquinário e apoio
A19: 2.1.2 | B19: Reaterro para blocos e baldrames | C19: 175.2192 | D19: m3 | E19: =F19/C19 -> 22 | F19: 3854.8224
A20: 2.1.3 | B20: Movimentação de bota-fora | C20: 759.2832 | D20: m3 | E20: =F20/C20 -> 44 | F20: 33408.461 | G20: Consideração de 30% como fator de empolamento
A21: 2.1.4 | B21: Movimentação de terra das estacas | C21: 872.82869 | D21: m3 | E21: =F21/C21 -> 44 | F21: 38404.462 | G21: 40,00 R$/m³ de material com empolamento
A22: 2.1.5 | B22: Lastro de concreto magro e=5cm | C22: 718.848 | D22: m2 | E22: =F22/C22 -> 20.35 | F22: 14628.557 | G22: 312,00 R$/m³ de concreto magro + R$ 40,00/m³ para bombeamento
A23: 3 | B23: INFRAESTRUTURA | F23: =F24+F31 -> 2655727.3
A24: 3.1 | B24: FUNDAÇÃO PROFUNDA | F24: =SUM(F25:F30) -> 1265134.7
A25: 3.1.1 | B25: Estaca Hélice Continua Diâmetro 50 | C25: 2268 | D25: m | E25: =F25/C25 -> 99 | F25: 224532 | G25: 90,00 R$/m incluindo todo o serviço, maquinário e apoio
A26: 3.1.2 | B26: Estaca Hélice Continua Diâmetro 60 | C26: 1512 | D26: m | E26: =F26/C26 -> 115.5 | F26: 174636 | G26: 105,00 R$/m incluindo todo o serviço, maquinário e apoio
A27: 3.1.3 | B27: Concreto (40 Mpa) | C27: 872.82869 | D27: m³ | E27: =F27/C27 -> 829.4 | F27: 723924.11 | G27: 535,00 R$/m³ de concreto + R$ 45,00/m³ para bombeamento (30% de perda)
A28: 3.1.4 | B28: Armação | C28: 10473.944 | D28: kg | E28: =F28/C28 -> 8.382 | F28: 87792.601 | G28: Custo médio para a bitola de 10mm (CA-50) de R$ 7,62/kg, incluíndo 10% de perda para corte e dobra em obra
A29: 3.1.5 | B29: Mobilização | C29: 1 | D29: vb | E29: =F29/C29 -> 13750 | F29: 13750 | G29: Custo de mobilização e desmobilização de maquinário para estaca hélice contínua
A30: 3.1.6 | B30: Apoio e arrasamento de estacas | C30: 135 | D30: un | E30: =F30/C30 -> 300 | F30: 40500
A31: 3.2 | B31: FUNDAÇÃO RASA | F31: =SUM(F32:F36) -> 1390592.6
A32: 3.2.1 | B32: Fabricação, montagem e desmontagem de forma para blocos e baldrames resinado | C32: 988.416 | D32: m² | E32: =F32/C32 -> 74.8 | F32: 73933.517 | G32: Consideração de custo de formas de madeira serrada com utilização única
A33: 3.2.3 | B33: Concreto (40 Mpa) | C33: 584.064 | D33: m³ | E33: =F33/C33 -> 669.9 | F33: 391264.47 | G33: 535,00 R$/m³ de concreto + R$ 45,00/m³ para bombeamento (5% de perda)
A34: 3.2.4 | B34: Armação | C34: 46725.12 | D34: kg | E34: =F34/C34 -> 8.382 | F34: 391649.96 | G34: Custo médio para a bitola de 10mm (CA-50) de R$ 7,62/kg, incluíndo 10% de perda para corte e dobra em obra
A35: 3.2.5 | B35: Piso de concreto armado | C35: 898.56 | D35: m² | E35: =F35/C35 -> 198 | F35: 177914.88 | G35: Custo de material para execução de piso sobre solo
A36: 3.2.6 | B36: Mão de obra | C36: 898.56 | D36: m² | E36: =F36/C36 -> 396 | F36: 355829.76 | G36: Mão de obra prevista para formas, armação, concretagem e apoio de todo o sistema de infraestrutura - R$ 396,00/m² de área de projeção do embasamento
A37: 5 | B37: SUPRAESTRUTURA | F37: =F38+F41+F43+F45+F49 -> 8731583.9
A38: 5.1 | B38: FORMA | F38: =SUM(F39:F40) -> 338736.7
A39: 5.1.1 | B39: Fabricação forma | C39: 2123.7411 | D39: m² | E39: =F39/C39 -> 121 | F39: 256972.67 | G39: Fabricação de 3 jogos referentes ao pavimento tipo com compensado plastificado
A40: 5.1.2 | B40: Montagem de forma | C40: 29732.375 | D40: m² | E40: =F40/C40 -> 2.75 | F40: 81764.031 | G40: Montagem contemplando desmoldante e reposição de pregos das formas fabricadas
A41: 5.2 | B41: ARMADURA | F41: =F42 -> 2741384.4
A42: 5.2.1 | B42: Armadura Convencional para Estrutura | C42: 327056.12 | D42: kg | E42: =F42/C42 -> 8.382 | F42: 2741384.4 | G42: Custo médio para a bitola de 10mm (CA-50) de R$ 7,62/kg, incluíndo 10% de perda para corte e dobra em obra | H42: corte e dobra pela mão de obra
A43: 5.3 | B43: CONCRETO | F43: =F44 -> 1991771.8
A44: 5.3.1 | B44: Concreto | C44: 2973.2375 | D44: m³ | E44: =F44/C44 -> 669.9 | F44: 1991771.8 | G44: 535,00 R$/m³ de concreto + R$ 45,00/m³ para bombeamento (5% de perda)
A45: 5.4 | B45: COMPLEMENTARES | F45: =SUM(F46:F48) -> 519952.12
A46: 5.4.1 | B46: Manutenção de escoramento próprio | C46: 5392 | D46: un | E46: =F46/C46 -> 5.5 | F46: 29656 | G46: Previsão de custo para manutenção de escoras próprias durante o período estimado de 24 meses
A47: 5.4.2 | B47: Locação de cubetas | C47: 988 | D47: m² | E47: =F47/C47 -> 331.02847 | F47: 327056.12 | G47: Locação de cubetas a R$0,46/un.dia pelo período estimado de 24 meses
A48: 5.4.3 | B48: Perfuração de vigas | C48: 28 | D48: pavto | E48: =F48/C48 -> 5830 | F48: 163240 | G48: Custo previsto para elementos de espera de furos ou furação posterior para passagem de tubulações
A49: 5.5 | B49: MÃO DE OBRA | F49: =F50 -> 3139738.8
A50: 5.5.1 | B50: Mão de obra supraestrutura | C50: 11892.95 | D50: m² | E50: =F50/C50 -> 264 | F50: 3139738.8 | G50: Mão de obra prevista para formas, armação, concretagem e apoio de todo o sistema de supraestrutura - R$ 264,00/m² de área construída
A51: 6 | B51: ALVENARIA | F51: =F52 -> 1761393.8
A52: 6.1 | B52: ALVENARIA | F52: =SUM(F53:F60) -> 1761393.8
A53: 6.1.1 | B53: Alvenaria embasamento | C53: 4435.2 | D53: m² | E53: =F53/C53 -> 49.5 | F53: 219542.4 | G53: Incluindo bloco e argamassa para assentamento
A54: 6.1.2 | B54: Alvenaria lazer | C54: 358 | D54: m² | E54: =F54/C54 -> 49.5 | F54: 17721 | G54: Incluindo bloco e argamassa para assentamento
A55: 6.1.3 | B55: Alvenaria tipo | C55: 9083.988 | D55: m² | E55: =F55/C55 -> 49.5 | F55: 449657.41 | G55: Incluindo bloco e argamassa para assentamento
A56: 6.1.4 | B56: Alvenaria escadas | C56: 2378.59 | D56: m² | E56: =F56/C56 -> 80.85 | F56: 192309 | G56: Incluindo bloco e argamassa para assentamento
A57: 6.1.5 | B57: Alvenaria cobertura / reservatório | C57: 131.652 | D57: m² | E57: =F57/C57 -> 49.5 | F57: 6516.774 | G57: Incluindo bloco e argamassa para assentamento
A58: 6.1.6 | B58: Alvenaria refratárias | C58: 84 | D58: un | E58: =F58/C58 -> 231 | F58: 19404 | G58: Incluindo bloco e argamassa para assentamento, aplicado no interior de churrasqueiras
A59: 6.1.7 | B59: Serviços complementares | C59: 16387.43 | D59: m² | E59: =F59/C59 -> 13.75 | F59: 225327.16 | G59: Custo previsto para contemplar amarração, encunhamento, vergas e contravergas
A60: 6.1.8 | B60: Mão de obra | C60: 16387.43 | D60: m² | E60: =F60/C60 -> 38.5 | F60: 630916.05 | G60: Mão de obra prevista para assentamento de todos os blocos e serviços complementares R$38,50/m² de parede
A61: 7 | B61: INSTALAÇÕES ELÉTRICAS, HIDRÁULICAS E GLP | F61: =F62+F70+F77 -> 4559162.4 | G61: Custos estimados com base em índices históricos da Cartesian
A62: 7.1 | B62: INSTALAÇÕES ELÉTRICAS | F62: =SUM(F63:F69) -> 1968877.9
A63: 7.1.1 | B63: Entrada de Energia | C63: 1 | D63: vb | E63: =F63/C63 -> 71952.348 | F63: 71952.348
A64: 7.1.2 | B64: Eletrodutos e Eletrocalhas | C64: 1 | D64: vb | E64: =F64/C64 -> 130822.45 | F64: 130822.45
A65: 7.1.3 | B65: Cabos e Fiações | C65: 1 | D65: vb | E65: =F65/C65 -> 392467.35 | F65: 392467.35
A66: 7.1.4 | B66: Quadros e Disjuntores | C66: 1 | D66: vb | E66: =F66/C66 -> 196233.68 | F66: 196233.68
A67: 7.1.5 | B67: Acabamentos Elétricos | C67: 1 | D67: vb | E67: =F67/C67 -> 196233.68 | F67: 196233.68
A68: 7.1.6 | B68: Equipamentos e Iluminação | C68: 1 | D68: vb | E68: =F68/C68 -> 196233.68 | F68: 196233.68
A69: 7.1.7 | B69: Mão de Obra para Instalações Elétricas | C69: 11892.95 | D69: m² | E69: =F69/C69 -> 66 | F69: 784934.7 | G69: Mão de obra prevista para execução de toda a instalação elétrica R$66,00/m² de área construída
A70: 7.2 | B70: INSTALAÇÕES HIDRÁULICAS | F70: =SUM(F71:F76) -> 2053912.5
A71: 7.2.1 | B71: Instalações de Água Fria | C71: 1 | D71: vb | E71: =F71/C71 -> 287809.39 | F71: 287809.39
A72: 7.2.2 | B72: Instalações de Água Quente | C72: 1 | D72: vb | E72: =F72/C72 -> 261644.9 | F72: 261644.9
A73: 7.2.3 | B73: Instalações de Águas Pluviais | C73: 1 | D73: vb | E73: =F73/C73 -> 130822.45 | F73: 130822.45
A74: 7.2.4 | B74: Instalações Sanitárias | C74: 1 | D74: vb | E74: =F74/C74 -> 196233.68 | F74: 196233.68
A75: 7.2.5 | B75: Louças e Metais | C75: 1 | D75: vb | E75: =F75/C75 -> 457878.58 | F75: 457878.58
A76: 7.2.6 | B76: Mão de Obra para Instalações Hidráulicas | C76: 11892.95 | D76: m² | E76: =F76/C76 -> 60.5 | F76: 719523.48 | G76: Mão de obra prevista para execução de toda a instalação hidrossanitária R$60,50/m² de área construída
A77: 7.3 | B77: INSTALAÇÕES PREVENTIVAS E GLP | F77: =SUM(F78:F80) -> 536372.05
A78: 7.3.1 | B78: Instalações Preventivas | C78: 1 | D78: vb | E78: =F78/C78 -> 261644.9 | F78: 261644.9
A79: 7.3.2 | B79: Instalações de GLP | C79: 1 | D79: vb | E79: =F79/C79 -> 170069.19 | F79: 170069.19
A80: 7.3.3 | B80: Instalações de Proteção e Aterramento - SPDA | C80: 1 | D80: vb | E80: =F80/C80 -> 104657.96 | F80: 104657.96
A81: 8 | B81: SISTEMAS ESPECIAIS | F81: =F82+F87+F92+F94 -> 1935684.6
A82: 8.1 | B82: CLIMATIZAÇÃO, EXAUSTÃO MECÂNICA E PRESSURIZAÇÃO | F82: =SUM(F83:F86) -> 477180
A83: 8.1.1 | B83: Infraestrutura para Instalação de Ar Condicionado | C83: 195 | D83: un | E83: =F83/C83 -> 1320 | F83: 257400 | G83: Custo previsto para execução de infraestrutura de ar condicionado em todo o empreendimento incluindo material e mão de obra
A84: 8.1.2 | B84: Instalação de Ar Condicionado (Equipameno) | C84: 6 | D84: un | E84: =F84/C84 -> 5500 | F84: 33000 | G84: Intalação de equipamentos em áreas comuns
A85: 8.1.3 | B85: Sistema de Ventokit | C85: 50 | D85: un | E85: =F85/C85 -> 990 | F85: 49500 | G85: Previsão de estrutura em banheiros enclasurados
A86: 8.1.4 | B86: Sistema de exaustão de Churrasqueiras | C86: 48 | D86: un | E86: =F86/C86 -> 2860 | F86: 137280 | G86: Custo para o sistema completo de exaustão levando por unidade de churrasqueira
A87: 8.2 | B87: COMUNICAÇÃO | F87: =SUM(F88:F91) -> 196233.68
A88: 8.2.1 | B88: CFTV | C88: 1 | D88: vb | E88: =F88/C88 -> 26164.49 | F88: 26164.49 | G88: Sistema estimado com base no porte do empreediemento através de índices
A89: 8.2.2 | B89: Interfone | C89: 1 | D89: vb | E89: =F89/C89 -> 65411.225 | F89: 65411.225 | G89: Sistema estimado com base no porte do empreediemento através de índices
A90: 8.2.3 | B90: TV e internet | C90: 1 | D90: vb | E90: =F90/C90 -> 39246.735 | F90: 39246.735 | G90: Sistema estimado com base no porte do empreediemento através de índices
A91: 8.2.4 | B91: Automação, telecomunicação e sistemas de segurança | C91: 1 | D91: vb | E91: =F91/C91 -> 65411.225 | F91: 65411.225 | G91: Sistema estimado com base no porte do empreediemento através de índices
A92: 8.3 | B92: OUTROS SISTEMAS | F92: =SUM(F93) -> 261644.9
A93: 8.3.1 | B93: Outros sistemas | C93: 1 | D93: vb | E93: =F93/C93 -> 261644.9 | F93: 261644.9 | G93: Verba prevista para equipamentos e instalações especial que podem ser incorporadas com o refinamento do projeto
A94: 8.4 | B94: SISTEMAS ESPECIAIS | F94: =SUM(F95:F101) -> 1000626
A95: 8.4.1 | B95: Elevadores | C95: 2 | D95: un | E95: =F95/C95 -> 422895 | F95: 845790
A96: 8.4.2 | B96: Grupo de geradores | C96: 1 | D96: un | E96: =F96/C96 -> 46200 | F96: 46200
A97: 8.4.3 | B97: Bombas | C97: 1 | D97: un | E97: =F97/C97 -> 11000 | F97: 11000 | G97: Previsão de bombas de pressurização e recalque, complementar ao sistema previsto no item 7.2
A98: 8.4.4 | B98: Infra de carro elétrico | C98: 46 | D98: un | E98: =F98/C98 -> 616 | F98: 28336 | G98: Previsão de espera para equipamento de carregamento de carro elétrico em uma vga por apartameto
A99: 8.4.5 | B99: Equipamento de piscina | C99: 1 | D99: un | E99: =F99/C99 -> 27500 | F99: 27500 | G99: Sistema inclui toda a estrutura de bomba, filtro, skimmer, etc.., incluindo mão de obra
A100: 8.4.6 | B100: Sauna | C100: 1 | D100: un | E100: =F100/C100 -> 8800 | F100: 8800 | G100: Sistema inclui toda estrutura de equipamentos para o funcionamento da sauna
A101: 8.4.7 | B101: Spa | C101: 2 | D101: un | E101: =F101/C101 -> 16500 | F101: 33000 | G101: Custo do equipamento já instalado
A102: 9 | B102: IMPERMEABILIZAÇÃO | F102: =F103+F112 -> 664584.92
A103: 9.1 | B103: IMPERMEABILIZAÇÃO | F103: =SUM(F104:F111) -> 317284.98
A104: 9.1.1 | B104: Regularização de Superfície | C104: 4882.056 | D104: m² | E104: =F104/C104 -> 8.8 | F104: 42962.093 | G104: Apeas material
A105: 9.1.2 | B105: Poço do elevador | C105: 32.4 | D105: m² | E105: =F105/C105 -> 14.3 | F105: 463.32 | G105: Apeas material
A106: 9.1.3 | B106: Baldrames | C106: 988.416 | D106: m² | E106: =F106/C106 -> 7.7 | F106: 7610.8032 | G106: Apeas material
...
