Workbook
Name \0: #REF!
Name \0: #REF!
Name \a: #REF!
Name \a: #REF!
Name \m: #REF!
Name aa: #REF!
Name aa: #REF!
Name aa: #REF!
Name aa: #REF!
Name aaaa: #REF!
Name aaaa: '[1]M.O.'!#REF!
Name aaaa: #REF!
Name aaaa: #REF!
Name aaaa: #REF!
Name angelo: [2]Geral!#REF!
Name angelo: #REF!
Name angelo: #REF!
Name angelo: #REF!
Name area: #REF!
Name area: #REF!
Name aux: #REF!
Name aux: #REF!
Name aux: #REF!
Name BDA: #REF!
Name BDA: #REF!
Name BDA: #REF!
Name BDI: #REF!
Name BDI: #REF!
Name BDI: #REF!
Name ca: #REF!
Name ca: #REF!
Name ca: #REF!
Name Capa: #REF!
Name Capa: #REF!
Name Capa: #REF!
Name cronograma: #REF!
Name cronograma: #REF!
Name cronograma: #REF!
Name D: #REF!
Name D: #REF!
Name D: #REF!
Name direto: #REF!
Name direto: #REF!
Name direto: #REF!
Name DRE: #REF!
Name DRE: #REF!
Name DRE: #REF!
Name ea: #REF!
Name ea: #REF!
Name ea: #REF!
Name eee: {#N/A,#N/A,FALSE,"ET-CAPA";#N/A,#N/A,FALSE,"ET-PAG1";#N/A,#N/A,FALSE,"ET-PAG2";#N/A,#N/A,FALSE,"ET-PAG3";#N/A,#N/A,FALSE,"ET-PAG4";#N/A,#N/A,FALSE,"ET-PAG5"}
Name eee: {#N/A,#N/A,FALSE,"ET-CAPA";#N/A,#N/A,FALSE,"ET-PAG1";#N/A,#N/A,FALSE,"ET-PAG2";#N/A,#N/A,FALSE,"ET-PAG3";#N/A,#N/A,FALSE,"ET-PAG4";#N/A,#N/A,FALSE,"ET-PAG5"}
Name eee: {#N/A,#N/A,FALSE,"ET-CAPA";#N/A,#N/A,FALSE,"ET-PAG1";#N/A,#N/A,FALSE,"ET-PAG2";#N/A,#N/A,FALSE,"ET-PAG3";#N/A,#N/A,FALSE,"ET-PAG4";#N/A,#N/A,FALSE,"ET-PAG5"}
Name eee: {#N/A,#N/A,FALSE,"ET-CAPA";#N/A,#N/A,FALSE,"ET-PAG1";#N/A,#N/A,FALSE,"ET-PAG2";#N/A,#N/A,FALSE,"ET-PAG3";#N/A,#N/A,FALSE,"ET-PAG4";#N/A,#N/A,FALSE,"ET-PAG5"}
Name eee: {#N/A,#N/A,FALSE,"ET-CAPA";#N/A,#N/A,FALSE,"ET-PAG1";#N/A,#N/A,FALSE,"ET-PAG2";#N/A,#N/A,FALSE,"ET-PAG3";#N/A,#N/A,FALSE,"ET-PAG4";#N/A,#N/A,FALSE,"ET-PAG5"}
Name FFFFFFF: #REF!
Name FFFFFFF: #REF!
Name FFFFFFF: #REF!
Name item_1: #REF!
Name item_1: #REF!

Sheet OBRA
A1: Obra | B1: Monolyt
A2: Empresa | B2: Blue Heaven
A3: Revisão | B3: R03
A4: DADOS OBRA
A6: ARQUITETURA
B8: Descrição | C8: Unidade | D8: Quantidade
B9: ÁREA DO TERRENO | C9: M2 | D9: 7541.68
B10: ÁREA CONSTRUÍDA | C10: M2 | D10: 14693.42
B11: NÚMERO DE UNIDADES HABITACIONAIS | C11: UN | D11: 24
B12: MESES DE OBRA | C12: MÊS | D12: 36
B13: NÚMERO DE PAVIMENTOS | C13: UN | D13: 4

Sheet CANTEIRO
A1: Obra | B1: Monolyt
A2: Empresa | B2: Blue Heaven
A3: Revisão | B3: R02
A4: LEVANTAMENTO QUANTITATIVO
A6: Instalações de canteiro
A8: Instalações de canteiro
B10: Descrição | C10: Unidade | D10: Quantidade
B11: Produtividade média | C11: m2 / mês | D11: =OBRA!D10/OBRA!D12 -> 408.15056
B12: Pm | C12: h/m2 | D12: 45
B13: Numero de funcionários | C13: un | D13: =ROUNDUP((D12*OBRA!D10)/OBRA!D12/180,) -> 103
B14: Equipe administrativa | C14: un | D14: 10
B15: Pontos de água e esgoto | C15: un | D15: =ROUNDUP($D$13/20,0) -> 6 | E15: 20 funcionários/ponto
B16: Bebedouro | C16: un | D16: =ROUNDUP(OBRA!$D$13/5,0) -> 1 | E16: 1 / 5 pav.
B17: Ferramentas | C17: R$ | D17: =800*D13 -> 82400 | E17: 800,00/func.
B18: EPI | C18: R$ | D18: =500*D13 -> 51500 | E18: 500,00/func.
B19: Banheiro | C19: un | D19: =ROUNDUP($D$13/20,0) -> 6 | E19: 1/20 func
A21: Mobiliário de canteiro
B23: Descrição | C23: Unidade | D23: Quantidade | E23: Custo unitário | F23: Custo total
B24: Cadeira | C24: un | D24: =D28*1.5 -> 15 | E24: 200 | F24: =D24*E24 -> 3000
B25: Mesa | C25: un | D25: =2 -> 2 | E25: 1000 | F25: =E25*D25 -> 2000
B26: Ar condicionado | C26: un | D26: =2*2 -> 4 | E26: 5000 | F26: =E26*D26 -> 20000
B27: Armário | C27: m | D27: =7*2*2 -> 28 | E27: 900 | F27: =E27*D27 -> 25200
B28: Escrivaninha | C28: un | D28: =D14 -> 10 | E28: 800 | F28: =E28*D28 -> 8000
B29: TOTAL | F29: =F26+F27+F28+F25+F24 -> 58200
B30: Descrição | C30: Unidade | D30: Quantidade | E30: Custo unitário | F30: Custo total
B31: Computador pessoal | C31: un | D31: =D14 -> 10 | E31: 6000 | F31: =D31*E31 -> 60000
B32: Impressora | C32: un | D32: 2 | E32: 2000 | F32: =E32*D32 -> 4000
B33: Roteador | C33: un | D33: =2*2 -> 4 | E33: 500 | F33: =E33*D33 -> 2000
B34: TOTAL | F34: =+F31+F32+F33 -> 66000

Sheet EPCs
A1: Obra | B1: Monolyt
A2: Empresa | B2: Blue Heaven
A3: Revisão | B3: R02
A4: LEVANTAMENTO QUANTITATIVO
A6: Equipamentos de proteção coletiva
A8: Bandejas de proteção
B10: Descrição | C10: Unidade | D10: Quantidade
B11: Perímetro de projeção torre 1 | C11: m | D11: =155.98+66.7 -> 222.68
B12: Perímetro de projeção torre 2 | C12: m | D12: =185.24+54.18 -> 239.42
B13: Número de montagens de bandeja primária | C13: un | D13: 1
B14: Bandeja de proteção primária | C14: m | D14: =D11+D12 -> 462.1
A16: Guarda - corpo de desforma
B18: Descrição | C18: Unidade | D18: Quantidade
B19: Perímetro de projeção da torre | C19: m | D19: =D11+D12 -> 462.1
B20: Repetições de pavimentos** | C20: un | D20: 3
B21: Proteção de periferia pós desforma torre | C21: m | D21: =(D19*D20) -> 1386.3
A23: Guarda-corpo de vãos
B25: Descrição | C25: Unidade | D25: Quantidade
B26: Comprimento de futuros guarda-copro de alumínio | C26: m | D26: 506.635
B27: Tela fachadeira | C27: m | D27: =D26 -> 506.635
A29: Tela fachadeira
B31: Descrição | C31: Unidade | D31: Quantidade
B32: Area da fachada | C32: m² | D32: =(D11+D12)*11.3 -> 5221.73
B33: Tela fachadeira | C33: m2 | D33: =D32 -> 5221.73
A35: Fechamento removível de vãos em madeira
B37: Descrição | C37: Unidade | D37: Quantidade
B38: Área das portas de elevadores | C38: m2 | D38: =1*2.4 -> 2.4
B39: Quantidade de elevadores | C39: un | D39: 6
B40: Quantidade de portas de elevadores | C40: un | D40: =(2+3+3+3+4+3+3+3) -> 24
B41: Fechamento removível de vãos em madeira | C41: m2 | D41: =D38*D40 -> 57.6
A43: Tapume
B45: Descrição | C45: Unidade | D45: Quantidade
B46: Perímetro de encontro com pavimentação | C46: m | D46: =42.1 -> 42.1
B47: Altura do tapume | C47: m | D47: 2.4
B48: Cobertura para proteção de pedestres | C48: m2 | D48: =D47*D46 -> 101.04

Sheet CUSTOS_INDIRETOS
A1: ORÇAMENTO PARAMÉTRICO - CUSTOS INDIRETOS
A7: Cliente | B7: =OBRA!B2 -> Blue Heaven
A8: Obra | B8: =OBRA!B1 -> Monolyt
A9: Data | B9: 45553
A10: Versão | B10: =OBRA!B3 -> R03
A12: GERENCIAMENTO TÉCNICO
A13: Código | B13: Descrição | C13: Un. | D13: Quantidade orçada | E13: Preço unitário | F13: Preço total
A14: 01 | B14: GERENCIAMENTO TÉCNICO | F14: =F15+F35 -> 1959447.4
A15: 01.001 | B15: ESTUDOS, PROJETOS E CONSULTORIAS | F15: =F16+F17+F33+F34 -> 1346038.8
A16: 01.001.001 | B16: Estudos | F16: 56126.829
A17: 01.001.002 | B17: Projetos | F17: =SUM(F18:F32) -> 1058652
A18: 01.001.002.001 | B18: Terraplenagem | C18: vb | D18: 1 | E18: 7400 | F18: =E18*D18 -> 7400
A19: 01.001.002.002 | B19: Topografia | C19: vb | D19: 1 | E19: 6000 | F19: =E19*D19 -> 6000
A20: 01.001.002.003 | B20: Sondagem | C20: vb | D20: 1 | E20: 8820 | F20: =E20*D20 -> 8820
A21: 01.001.002.004 | B21: Imagens 3D Filme | C21: vb | D21: 1 | E21: 49300 | F21: =E21*D21 -> 49300
A22: 01.001.002.005 | B22: Estudo Geofísico | C22: vb | D22: 1 | E22: 21250 | F22: =E22*D22 -> 21250
A23: 01.001.002.006 | B23: Fundações Contenção | C23: vb | D23: 1 | E23: 14000 | F23: =E23*D23 -> 14000
A24: 01.001.002.007 | B24: Estudo Hidrogeológico | C24: vb | D24: 1 | E24: 10682 | F24: =E24*D24 -> 10682
A25: 01.001.002.008 | B25: Luminotécnico | C25: vb | D25: 1 | E25: 70000 | F25: =E25*D25 -> 70000
A26: 01.001.002.009 | B26: Energia Renovável | C26: vb | D26: 1 | E26: 9000 | F26: =E26*D26 -> 9000
A27: 01.001.002.010 | B27: Drywall | C27: vb | D27: 1 | E27: 27000 | F27: =E27*D27 -> 27000
A28: 01.001.002.011 | B28: Paisagismo | C28: vb | D28: 1 | E28: 125000 | F28: =E28*D28 -> 125000
A29: 01.001.002.012 | B29: Aprovativo | C29: vb | D29: 1 | E29: 10200 | F29: =E29*D29 -> 10200
... A32: 01.001.002.014 | B32: Interiores | C32: vb | D32: 1 | E32: 80000 | F32: =E32*D32 -> 80000
A33: 01.001.003 | B33: Consultorias | F33: 59541.37
A34: 01.001.004 | B34: Ensaios e Laudos | F34: 171718.61
A35: 01.002 | B35: TAXAS E DOCUMENTOS | F35: =SUM(F36:F38) -> 613408.59
A36: 01.002.001 | B36: Seguros | F36: 33456.914
A37: 01.002.002 | B37: Licenciamentos, Taxas, Impostos | F37: 447901.92
A38: 01.002.003 | B38: Documentos | F38: 132049.76
A39: 02 | B39: GERENCIAMENTO ADMINISTRATIVO | F39: =F40+F53+F77 -> 12579413
A40: 02.001 | B40: SEGURANÇA, MEIO AMBIENTE E SAÚDE | F40: =F41+F43+F52 -> 878433
A41: 02.001.001 | B41: Segurança do Trabalho | F41: =F42 -> 316800
A42: 02.001.001.001 | B42: Serviço de segurança do trabalho terceirizado | C42: mes | D42: =OBRA!D12 -> 36 | E42: 8000 | F42: =E42*D42*1.1 -> 316800 | G42: Conforme solicitado em 18/07 via whatsapp
A43: 02.001.002 | B43: Equipamentos de proteção | F43: =SUM(F44:F51) -> 387240.15
A44: 02.001.002.001 | B44: Bandeja de proteção primária | C44: m | D44: =EPCs!D14 -> 462.1 | E44: 402.72 | F44: =E44*D44*1.1 -> 204706.6
A45: 02.001.002.002 | B45: Guarda corpo em laje pós - desforma | C45: m | D45: =EPCs!D21 -> 1386.3 | E45: 13.68 | F45: =E45*D45*1.1 -> 20861.042
A46: 02.001.002.003 | B46: Guarda corpo de vãos | C46: m | D46: =EPCs!D27 -> 506.635 | E46: 13.68 | F46: =E46*D46*1.1 -> 7623.8435
A47: 02.001.002.004 | B47: Fechamento removível de vãos de porta de elevador em madeira | C47: m2 | D47: =EPCs!D41 -> 57.6 | E47: 67.76 | F47: =E47*D47*1.1 -> 4293.2736
A48: 02.001.002.005 | B48: Tela fachadeira | C48: m2 | D48: =EPCs!D33 -> 5221.73 | E48: 6.68 | F48: =E48*D48*1.1 -> 38369.272
A49: 02.001.002.006 | B49: Varal de seguranca com cabo de aco | C49: m | D49: =EPCs!D19 -> 462.1 | E49: 90.5 | F49: =E49*D49*1.1 -> 46002.055
A50: 02.001.002.007 | B50: Sinalização com placa indicativa fixada na estrutura | C50: vb | D50: 1 | E50: 7940.0593 | F50: =E50*D50*1.1 -> 8734.0652
A51: 02.001.002.008 | B51: Equipamentos de proteção individual | C51: vb | D51: 1 | E51: =CANTEIRO!D18 -> 51500 | F51: =E51*D51*1.1 -> 56650
A52: 02.001.003 | B52: Meio Ambiente | F52: 174392.85 | G52: Considerado Medicamentos preventivos e de emergência, detetização, desratização e sanitização dos ambientes, PCMAT, PPRA, PCMSO, vistorias e retirada de entulho (caçamba)
A53: 02.002 | B53: ADMINISTRAÇÃO E CANTEIRO DE OBRA | F53: =F54+F66+F68+F76 -> 10636922
A54: 02.002.001 | B54: Equipe de Gestão e Apoio | F54: =SUM(F55:F65) -> 8102532.9
A55: 02.002.001.001 | B55: Engenheiro Civil | C55: mes | E55: =2*12000 -> 24000 | F55: =E55*D55*1.1 -> 0 | G55: Conforme solicitado em 18/07 via whatsapp - tirar custo do Engenheiro
A56: 02.002.001.002 | B56: Mestre Geral | C56: mes | D56: =OBRA!$D$12 -> 36 | E56: =7000*2*1.84 -> 25760 | F56: =E56*D56*1.1 -> 1020096
A57: 02.002.001.003 | B57: Contra Mestre | C57: mes | D57: 18 | E57: =2*5000 -> 10000 | F57: =E57*D57*1.1 -> 198000 | G57: Conforme solicitado em 18/07 via whatsapp: Considerar + 2 contra mestres salário 5mil/mês por 18meses , nos meses finais.
A58: 02.002.001.003 | B58: Almoxarife | C58: mes | D58: =OBRA!$D$12 -> 36 | E58: =2312.2*1.84*2 -> 8508.896 | F58: =E58*D58*1.1 -> 336952.28
A59: 02.002.001.005 | B59: Estagiário de Engenharia | C59: mes | D59: =OBRA!$D$12 -> 36 | E59: =1960*4 -> 7840 | F59: =E59*D59*1.1 -> 310464 | G59: 4 estagiários
A60: 02.002.001.006 | B60: Operador de Grua | C60: mes | D60: 27 | E60: =15600*2 -> 31200 | F60: =E60*D60*1.1 -> 926640 | G60: 2 operadores de grua
A61: 02.002.001.006 | B61: Operador de Bobcat | C61: mes | D61: =36 -> 36 | E61: =5800*2 -> 11600 | F61: =E61*D61*1.1 -> 459360 | G61: Conforme solicitado em 18/07 via whatsapp: Considerar 2 oper. Bobcat
A62: 02.002.001.006 | B62: Operador de Cremalheira | C62: mes | D62: 27 | E62: =7400*2 -> 14800 | F62: =E62*D62*1.1 -> 439560 | G62: Conforme solicitado em 18/07 via whatsapp: 27meses - Considerar 2 oper. cremalheira
A63: 02.002.001.007 | B63: Equipe de apoio | C63: mes | D63: =OBRA!$D$12 -> 36 | E63: =(4*1600+2*4000+2*3250)*2*1.84 -> 76912 | F63: =E63*D63*1.1 -> 3045715.2 | G63: Conforme solicitado em 18/07 via whatsapp: Considerar 4 serventes, 2 pedreiros e 2 carpinteiros por torre - 36meses
A64: 02.002.001.007 | B64: Equipe de apoio | C64: mes | D64: 18 | E64: =(2*1600+1*4000+1*3250)*2*1.84 -> 38456 | F64: =E64*D64*1.1 -> 761428.8 | G64: Conforme solicitado em 18/07 via whatsapp: 18 meses finais+ 2 serv 1 pedr 1 carp por torre
A65: 02.002.001.009 | B65: Serviço de vigilância | C65: mes | D65: =OBRA!$D$12 -> 36 | E65: =2312.2*2.2*3 -> 15260.52 | F65: =E65*D65*1.1 -> 604316.59
A66: 02.002.002 | B66: Operação Inicial do Canteiro | F66: =SUM(F67) -> 51849.05
A67: 02.002.002.001 | B67: Limpeza mecanizada de camada vegetal | C67: m2 | D67: =OBRA!D9/2 -> 3770.84 | E67: 12.5 | F67: =E67*D67*1.1 -> 51849.05 | G67: Ajustado para 50% do terreno
A68: 02.002.003 | B68: Instalações Provisórias | F68: =SUM(F69:F75) -> 682540.23
A69: 02.002.003.001 | B69: Locação de banheiro químico | C69: mes | D69: 6 | E69: =1400*4 -> 5600 | F69: =E69*D69*1.1 -> 36960 | G69: Conforme solicitado em 18/07 via whatsapp: 2 banheiros por torre - 6 meses
A70: 02.002.003.002 | B70: Instalações de canteiro | C70: vb | D70: 1 | E70: 351344.82 | F70: =E70*D70*1.1 -> 386479.3 | G70: Previsão de 2 canteiros - 1/torre
A71: 02.002.003.003 | B71: Instalações Provisórias: Redes de Água Fria, Esgoto e Drenagem | C71: vb | D71: 1 | E71: 14178.677 | F71: =E71*D71*1.1 -> 15596.545
A72: 02.002.003.004 | B72: Instalações Provisórias: Redes Elétrica, Comunicação e Dados | C72: vb | D72: 1 | E72: 25521.619 | F72: =E72*D72*1.1 -> 28073.781
A73: 02.002.003.005 | B73: Mobiliário de apoio a obra | C73: vb | D73: 1 | E73: =CANTEIRO!F29 -> 58200 | F73: =E73*D73*1.1 -> 64020
A74: 02.002.003.006 | B74: Equipamentos escritório - aquisição | C74: vb | D74: 1 | E74: =CANTEIRO!F34 -> 66000 | F74: =E74*D74*1.1 -> 72600
A75: 02.002.003.007 | B75: Tapume com telha metálica | C75: m2 | D75: 200 | E75: =119.41*3 -> 358.23 | F75: =E75*D75*1.1 -> 78810.6 | G75: Conforme solicitado em 18/07 via whatsapp: 200m² de tapume personalizado, triplica valor
A76: 02.002.005 | B76: Despesas de Consumo e Manutenção | F76: =50000*OBRA!D12 -> 1800000 | G76: Consumos: água, energia, internet, coleta de lixo, material de expediente/escritório, material de limpeza, manutenção provisória de canteiro, elétrica, hidrossanitária, vigilância e acesso, equipamentos de escritório, cópias...
A77: 02.003 | B77: EQUIPAMENTOS | F77: =F78+F89 -> 1064057.5
A78: 02.003.001 | B78: Equipamentos de Obra | F78: =SUM(F79:F88) -> 918297.47
A79: 02.003.001.001 | B79: Ferramentas - aquisição/manutenção | C79: vb | D79: 1 | E79: =CANTEIRO!D17 -> 82400 | F79: =E79*D79*1.1 -> 90640 | G79: Kit ferramentas padrão para equipe interna (Exemplo: alicate, balde, colher de pedreiro, martelo, marreta, trena, etc.)
A80: 02.003.001.002 | B80: Ferramentas - locação | C80: mes | D80: =OBRA!$D$12 -> 36 | E80: 4000 | F80: =E80*D80*1.1 -> 158400 | G80: Conforme solicitado em 18/07 via whatsapp: incluir locação
A81: 02.003.001.002 | B81: Manutenção de dois veículos de apoio | C81: mes | D81: =OBRA!$D$12 -> 36 | E81: =166.665*2 -> 333.33 | F81: =E81*D81*1.1 -> 13199.868
A82: 02.003.001.003 | B82: Manutenção inicial de elevador cremalheira | C82: Un. | D82: 2 | E82: 70000 | F82: =E82*D82*1.1 -> 154000 | G82: Reforma do equipamento usado para se adptar a obra atual
A83: 02.003.001.004 | B83: Manutenção periódica de elevador cremalheira | C83: Un. | D83: 18 | E83: 2720 | F83: =E83*D83*1.1 -> 53856 | G83: Conforme solicitado em 18/07 via whatsapp: 18 meses
A84: 02.003.001.005 | B84: Montagem e desmontagem de elevador cremalheira | C84: mes | D84: 2 | E84: 16300 | F84: =E84*D84*1.1 -> 35860 | G84: Conforme solicitado em 18/07 via whatsapp valor revisado
A85: 02.003.001.006 | B85: Mobilização e desmobilização de Cremalheira | C85: Un. | D85: 2 | E85: 1328 | F85: =E85*D85*1.1 -> 2921.6 | G85: Conforme solicitado em 18/07 via whatsapp valor revisado
A86: 02.003.001.007 | B86: Manutenção periódica de de Grua | C86: Un. | D86: 27 | E86: =2300*2 -> 4600 | F86: =E86*D86*1.1 -> 136620 | G86: Conforme solicitado em 18/07 via whatsapp: 27 MESES * 2 TORRES
A87: 02.003.001.008 | B87: Montagem e Desmontagem de Grua | C87: Un. | D87: 2 | E87: 100000 | F87: =E87*D87*1.1 -> 220000 | G87: Conforme solicitado em 18/07 via whatsapp: 100MIL CADA TORRE
A88: 02.003.001.009 | B88: Mobilização e desmobilização de Grua | C88: Un. | D88: 2 | E88: 24000 | F88: =E88*D88*1.1 -> 52800
A89: 02.003.002 | B89: Balancim | F89: =SUM(F90:F92) -> 145760
A90: 02.003.002.001 | B90: Locação de balancim | C90: mes | D90: 6 | E90: =56000/6 -> 9333.3333 | F90: =E90*D90 -> 56000 | G90: Conforme solicitado em 18/07 via whatsapp: 56MIL 6 MESES -
A91: 02.003.002.002 | B91: Montagem e desmontagem de balancim | C91: Un. | D91: 48 | E91: 450 | F91: =E91*D91*1.1 -> 23760 | G91: Conforme solicitado em 18/07 via whatsapp: 48UND
A92: 02.003.002.004 | B92: Locação de andaime | C92: mes | D92: 6 | E92: =5000*2 -> 10000 | F92: =E92*D92*1.1 -> 66000 | G92: Conforme solicitado em 18/07 via whatsapp: 10MILPARA AS 2 TORRES 5+5 / MÊS
A93: Total | F93: =F39+F14 -> 14538860

Sheet GERENCIAMENTO_EXECUTIVO
A1: ORÇAMENTO PARAMÉTRICO - GERENCIAMENTO EXECUTIVO
A7: Cliente | B7: =OBRA!B2 -> Blue Heaven
A8: Obra | B8: =OBRA!B1 -> Monolyt
A9: Data | B9: 45503
A10: Versão | B10: =OBRA!B3 -> R03
A12: GERENCIAMENTO EXECUTIVO
A13: CÓDIGO | B13: ITEM | C13: Quantidade | D13: Unidade | E13: Valor Orçado | F13: Considerações
A14: 1 | B14: GERENCIAMENTO TÉCNICO E ADMINISTRATIVO | E14: =E15 -> 14538860
A15: 1.1 | B15: GERENCIAMENTO TÉCNICO E ADMINISTRATIVO | E15: =E16 -> 14538860
A16: 1.1.1 | B16: Gerenciamento técnico e administrativo | C16: 1 | D16: vb | E16: =CUSTOS_INDIRETOS!F93 -> 14538860 | F16: Conforme aba "custos_indiretos"
A17: 2 | B17: MOVIMENTAÇÃO DE TERRA | E17: =E22+E24+E18 -> 2545063.4
A18: 2.1 | B18: ESCAVAÇÃO VERTICAL DE SUBSOLO | E18: =SUM(E19:E21) -> 1552282
A19: 2.1.1 | B19: Escavação mecanizada | C19: 13424.19 | D19: m³ | E19: 885996.68
A20: 2.1.2 | B20: Reaterro | C20: 248.13756 | D20: m³ | E20: 6823.7829
A21: 2.1.3 | B21: Movimentação de bota-fora | C21: 17128.87 | D21: m² | E21: 659461.53 | F21: 40% empolamento
A22: 2.2 | B22: REBAIXAMENTO DE LENÇOL | E22: =SUM(E23:E23) -> 39600
A23: 2.2.1 | B23: Rebaixamento provisório de lençol | C23: 1 | D23: vb | E23: 39600 | F23: Rebaixameno de lençol provisório considerando período de execução da fundação
A24: 2.3 | B24: MOVIMENTAÇÃO DE VALAS | E24: =SUM(E25:E28) -> 953181.4
A25: 2.3.1 | B25: Escavação mecanizada para blocos e baldrames | C25: 4661.376 | D25: m³ | E25: 257673.24
A26: 2.3.2 | B26: Reaterro para blocos e baldrames | C26: 2796.8256 | D26: m³ | E26: 77301.972
A27: 2.3.3 | B27: Movimentação de bota-fora | C27: 3899.38 | D27: m³ | E27: 171572.57
A28: 2.3.4 | B28: Lastro de concreto magro | C28: 1561.656 | D28: m² | E28: 446633.62
A29: 3 | B29: INFRAESTRUTURA | E29: =E30+E38 -> 5742340
A30: 3.1 | B30: FUNDAÇÃO PROFUNDA | E30: =SUM(E31:E37) -> 2529315.8
A31: 3.1.1 | B31: Estaca Hélice Continua Diâmetro 40 | C31: 820.4 | D31: m | E31: 63170.8
A32: 3.1.2 | B32: Estaca Hélice Continua Diâmetro 50 | C32: 5742.8 | D32: m | E32: 631708
A33: 3.1.3 | B33: Estaca Hélice Continua Diâmetro 60 | C33: 1640.8 | D33: m | E33: 216585.6
A34: 3.1.4 | B34: Armação 6,3mm | C34: 2114.6461 | D34: kg | E34: 18608.886
A35: 3.1.5 | B35: Armação 16mm | C35: 12985.467 | D35: kg | E35: 121414.12
A36: 3.1.6 | B36: Concreto | C36: 1269.2631 | D36: m³ | E36: 1267948.4 | F36: Consideração de concreto com bombeamento + 30% de perda devido a compressão da estaca hélice no solo
A37: 3.1.7 | B37: Mobilização e arrasamento de estacas | C37: 1 | D37: vb | E37: 209880 | F37: Previsão de mobilização de maquinários + arrasamento de estacas
A38: 3.2 | B38: FUNDAÇÃO RASA | E38: =SUM(E39:E42) -> 3213024.3
A39: 3.2.1 | B39: Fabricação, montagem e desmontagem de forma para blocos e baldrames resinado | C39: 2967.1464 | D39: m² | E39: 234997.99 | F39: Forma de madeira serrada sem reutilização
A40: 3.2.2 | B40: Armação | C40: 80815.698 | D40: kg | E40: 711178.14 | F40: Consideração de R$ 8/kg
A41: 3.2.3 | B41: Concreto | C41: 897.9522 | D41: m³ | E41: 720808.68 | F41: Consideração de R$ 729,75/m³ de concreto com bombeamento
A42: 3.2.4 | B42: Mão de obra | C42: 3904.14 | D42: m² | E42: 1546039.4 | F42: Valor estimado por área de projeção do embasamento
A43: 4 | B43: CONTENÇÃO | E43: =E44 -> 1644604.6
A44: 4.2 | B44: PAREDE DE CONCRETO | E44: =SUM(E45:E49) -> 1644604.6
A45: 4.2.1 | B45: Fabricação, montagem e desmontagem de forma - resinado | C45: 2326.96 | D45: m² | E45: 529057.7
A46: 4.2.2 | B46: Concreto | C46: 465.392 | D46: m³ | E46: 373581.79
A47: 4.2.3 | B47: Armação | C47: 46539.2 | D47: kg | E47: 409544.96
A48: 4.2.4 | B48: Estrutura - drenagem | C48: 1 | D48: vb | E48: 89252.8
A49: 4.2.5 | B49: Mão de obra | C49: 1163.48 | D49: m² | E49: 243167.32
A50: 5 | B50: SUPRAESTRUTURA | E50: =E51+E54+E56+E61+E58 -> 16955390
A51: 5.1 | B51: FORMA | E51: =SUM(E52:E53) -> 1558509.6
A52: 5.1.1 | B52: Fabricação forma | C52: 10913.58 | D52: m² | E52: 1380568.4 | F52: Forma de madeira compensada super resinadaa com 8 reutilizações
A53: 5.1.2 | B53: Montagem de forma | C53: 34055.72 | D53: m² | E53: 177941.14
A54: 5.2 | B54: ARMADURA | E54: =E55 -> 3891271
A55: 5.2.1 | B55: Armadura Convencional para Estrutura | C55: 442189.89 | D55: kg | E55: 3891271
A56: 5.3 | B56: CONCRETO | E56: =E57 -> 3234435.3
A57: 5.3.1 | B57: Concreto | C57: 3948.12 | D57: m³ | E57: 3234435.3 | F57: Consideração de R$ 729,75/m³ de concreto com bombeamento / Para concreto das paredes inclinadad R$ 900,38 considerando aditivo
A58: 5.4 | B58: COMPLEMENTARES | E58: =E60+E59 -> 3212648.9
A59: 5.4.1 | B59: Escoramento | C59: 40169.92 | D59: un | E59: 839551.41 | F59: Locação de escoramento metálico
A60: 5.4.2 | B60: Protensão | C60: 61638.897 | D60: kg | E60: 2373097.5
A61: 5.5 | B61: MÃO DE OBRA | E61: =E62 -> 5058525.1
A62: 5.5.1 | B62: Mão de obra supraestrutura | C62: 16217.01 | D62: m² | E62: 5058525.1 | F62: Valor estimado com base na área construida
A63: 6 | B63: ALVENARIA | E63: =E64 -> 3148673.4 | F63: Valores estimados com base em índices históricos por área construida
A64: 6.1 | B64: ALVENARIA | E64: =SUM(E65:E71) -> 3148673.4
A65: 6.1.1 | B65: Alvenaria | C65: 4992.75 | D65: m² | E65: 263617.2
A66: 6.1.2 | B66: Drywall | C66: 7929.2535 | D66: m² | E66: 1918879.3
A67: 6.1.3 | B67: Isolamento lã pet | C67: 7929.2535 | D67: m² | E67: 305276.26
A68: 6.1.4 | B68: Alvenaria escadas | C68: 998.55 | D68: m² | E68: 197712.9
A69: 6.1.5 | B69: Alvenaria refratárias | C69: 24 | D69: m² | E69: 8448 | F69: Churrasqueiras
A70: 6.1.6 | B70: Serviços complementares | C70: 5991.3 | D70: m² | E70: 164760.75 | F70: Previsão de amarração com tela, vergas, contravergas e encunhamento
A71: 6.1.7 | B71: Mão de obra | C71: 5991.3 | D71: un | E71: 289978.92
A72: 7 | B72: INSTALAÇÕES ELÉTRICAS, HIDRÁULICAS E GLP | E72: =E73+E81+E88 -> 6206500.6 | F72: Valores estimados com base em índices históricos por área construida
A73: 7.1 | B73: INSTALAÇÕES ELÉTRICAS | E73: =SUM(E74:E80) -> 3281040.7
A74: 7.1.1 | B74: Entrada de Energia | C74: 1 | D74: vb | E74: 80813.81
A75: 7.1.2 | B75: Eletrodutos e Eletrocalhas | C75: 1 | D75: vb | E75: 371743.53
A76: 7.1.3 | B76: Cabos e Fiações | C76: 1 | D76: vb | E76: 646510.48
A77: 7.1.4 | B77: Quadros e Disjuntores | C77: 1 | D77: vb | E77: 404069.05
A78: 7.1.5 | B78: Acabamentos Elétricos | C78: 1 | D78: vb | E78: 484882.86
A79: 7.1.6 | B79: Equipamentos e Iluminação | C79: 1 | D79: vb | E79: 323255.24
A80: 7.1.7 | B80: Mão de Obra para Instalações Elétricas | C80: 1 | D80: vb | E80: 969765.72
A81: 7.2 | B81: INSTALAÇÕES HIDRÁULICAS | E81: =SUM(E82:E87) -> 2262786.7
A82: 7.2.1 | B82: Instalações de Água Fria | C82: 1 | D82: vb | E82: 404069.05
A83: 7.2.2 | B83: Instalações de Água Quente | C83: 1 | D83: vb | E83: 323255.24
A84: 7.2.3 | B84: Instalações de Águas Pluviais | C84: 1 | D84: vb | E84: 161627.62
A85: 7.2.4 | B85: Instalações Sanitárias | C85: 1 | D85: vb | E85: 242441.43
A86: 7.2.5 | B86: Louças e Metais | C86: 1 | D86: vb | E86: 242441.43 | F86: Entrega total em áreas comuns e nada em áreas privativas
A87: 7.2.6 | B87: Mão de Obra para Instalações Hidráulicas | C87: 1 | D87: vb | E87: 888951.91
A88: 7.3 | B88: INSTALAÇÕES PREVENTIVAS E GLP | E88: =SUM(E89:E91) -> 662673.24
A89: 7.3.1 | B89: Instalações Preventivas | C89: 1 | D89: vb | E89: 290929.72
A90: 7.3.2 | B90: Instalações de GLP | C90: 1 | D90: vb | E90: 242441.43
A91: 7.3.3 | B91: Instalações de Proteção e Aterramento - SPDA | C91: 1 | D91: vb | E91: 129302.1
A92: 8 | B92: SISTEMAS ESPECIAIS | E92: =E93+E98+E104+E106 -> 7227828.5
A93: 8.1 | B93: CLIMATIZAÇÃO, EXAUSTÃO MECÂNICA E PRESSURIZAÇÃO | E93: =SUM(E94:E97) -> 1922186.2
A94: 8.1.1 | B94: Infraestrutura para Instalação de Ar Condicionado | C94: 1 | D94: vb | E94: 1616276.2
A95: 8.1.2 | B95: Instalação de Ar Condicionado | C95: 12 | D95: un | E95: 105600 | F95: Instalação de ar-codicionado em áreas comuns
A96: 8.1.3 | B96: Ventokit | C96: 133 | D96: un | E96: 131670 | F96: Ventilação mecânica em banheiros enclausurados
A97: 8.1.4 | B97: Churrasqueiras | C97: 24 | D97: un | E97: 68640 | F97: Exaustão de churrasqueiras
A98: 8.2 | B98: COMUNICAÇÃO | E98: =SUM(E99:E103) -> 307092.48
A99: 8.2.1 | B99: CFTV | C99: 1 | D99: vb | E99: 32325.524
A100: 8.2.2 | B100: Interfone | C100: 1 | D100: vb | E100: 64651.048
A101: 8.2.2 | B101: Controle de acesso | C101: 1 | D101: vb | E101: 32325.524 | F101: Portaria inteligente
A102: 8.2.3 | B102: TV e internet | C102: 1 | D102: vb | E102: 48488.286
A103: 8.2.4 | B103: Automação, telecomunicação e sistemas de segurança | C103: 1 | D103: vb | E103: 129302.1 | F103: Previsão de infraestrutura
A104: 8.3 | B104: OUTROS SISTEMAS | E104: =SUM(E105) -> 440802.6
A105: 8.3.1 | B105: Outros sistemas | C105: 1 | D105: vb | E105: 440802.6
A106: 8.4 | B106: SISTEMAS ESPECIAIS | E106: =SUM(E107:E115) -> 4557747.3
...

Sheet CREMALHEIRA
