Workbook
Name \0: #REF!
Name \0: #REF!
Name \0: #REF!
Name \0: #REF!
Name \0: #REF!
Name \0: #REF!
Name \0: #REF!
Name \0: #REF!
Name \0: #REF!
Name \1: #REF!
Name \a: #REF!
Name \a: #REF!
Name \a: #REF!
Name \a: #REF!
Name \a: #REF!
Name \b: #REF!
Name \c: #REF!
Name \d: #REF!
Name \e: #REF!
Name \i: #REF!
Name \J: #REF!
Name \k: #REF!
Name \l: #N/A
Name \m: #REF!
Name \m: #REF!
Name \m: #REF!
Name \m: #REF!
Name \m: #REF!
Name \o: #REF!
Name \p: #REF!
Name \r: #REF!
Name \T: #REF!
Name \z: #REF!
Name ______ACR10: #REF!
Name ______ACR15: #REF!
Name ______acr20: #REF!
Name ______acr5: #REF!
Name ______ARQ1: #REF!
Name ______QT100: #REF!
Name ______QT2: #REF!
Name ______QT3: #REF!
Name ______QT4: #REF!
Name ______QT50: #REF!
Name ______QT75: #REF!
Name _____ACR10: #REF!
Name _____ACR15: #REF!
Name _____acr20: #REF!
Name _____acr5: #REF!
Name _____ARQ1: #REF!
Name _____QT100: #REF!
Name _____QT2: #REF!
Name _____QT3: #REF!
Name _____QT4: #REF!
Name _____QT50: #REF!
Name _____QT75: #REF!
Name ___ACR10: #REF!
Name ___ACR15: #REF!
Name ___acr20: #REF!
Name ___acr5: #REF!
Name ___ARQ1: #REF!

Sheet DADOS_INICIAIS
A1: Obra | B1: MONOLYT
A2: Empresa | B2: BLUE HEAVEN
A3: Revisão | B3: R00
A4: DADOS OBRA
A6: ARQUITETURA
B8: Descrição | C8: Identificador | D8: Unidade | E8: Quantidade | G8: Separar por torre
E9: TORRE B | F9: TORRE A
B10: ÁREA DO TERRENO | C10: AT | D10: M2 | E10: 7541.68
B11: ÁREA TOTAL CONSTRUÍDA | C11: AC | D11: M2 | E11: 14693.42
B12: NÚMERO TOTAL DE PAVIMENTOS | C12: NP | D12: UN | E12: 4 | F12: 4 | G12: Níveis diferentes
B13: NÚMERO DE PAVIMENTOS TIPO | C13: NPT | D13: UN | E13: 3 | F13: 3
B14: NÚMERO DE PAVIMENTOS DIFERENCIADOS | C14: NPD | D14: UN | E14: 1 | F14: 0
B15: ÁREA DE PROJEÇÃO DO PAV DIFERENCIADO | C15: APD | D15: M2 | E15: 774.97 | F15: 0
B16: NÚMERO DE PAVIMENTOS DUPLEX | C16: ND | D16: UN | E16: 1 | F16: 1
B17: ÁREA DE PROJEÇÃO DA TORRE | C17: APT | D17: M2 | E17: =1469.1-174.91 -> 1294.19 | F17: =1502.76-126.91 -> 1375.85
B18: PERÍMETRO DE PROJEÇÃO DA TORRE | C18: PPT | D18: M | E18: 209.46 | F18: 239.41
B19: ÁREA DE LAZER INTERNA | C19: ALI | D19: M2 | E19: 343.39
B20: ÁREA DE LAZER EXTERNA | C20: ALE | D20: M2 | E20: 2661.29
B21: ÁREA DE SUBSOLOS | C21: S | D21: M2 | E21: 1879.83 | F21: 2024.31 | G21: ESTACIONAMENTO
B22: NÚMERO DE SUBSOLOS | C22: NS | D22: UN | E22: 1 | F22: 1
B23: ÁREA DE PROJEÇÃO DO EMBASAMENTO | C23: APE | D23: M2 | E23: 1879.83 | F23: 2024.31
B24: PERÍMETRO DE PROJEÇÃO DE EMBAMENTO | C24: PE | D24: M | E24: 176.28 | F24: 215.72
B25: NÚMERO DE PAVIMENTOS DE EMBASAMENTO | C25: NE | D25: UN | E25: 1 | F25: 1
B26: NÚMERO DE APARTAMENTOS | D26: UN | E26: 24
K44: =12224.04-301.82 -> 11922.22 | L44: =12469.72-K44 -> 547.5
K48: =3188.34+1879.83 -> 5068.17

Sheet MOVIMENTAÇÃO_DE_TERRA
A2: MOVIMENTAÇÃO DE TERRA
A4: ESCAVAÇÃO VERTICAL DE SUBSOLO
A6: Descrição | B6: Área de subsolo (m2) | C6: Altura do subsolo (m) | D6: Volume total de escavação (m3) | E6: Preço unitário de escavação (R$ / m3) | F6: Valor total
A7: Escavação Torre A | B7: =(DADOS_INICIAIS!F21)*1.1 -> 2226.741 | C7: 5.1 | D7: =C7*B7 -> 11356.379 | E7: 60 | F7: =E7*D7*1.1 -> 749521.02 | G7: VIVA4
A8: Escavação Torre B | B8: =(DADOS_INICIAIS!E21)*1.1 -> 2067.813 | C8: 1 | D8: =C8*B8 -> 2067.813 | E8: 60 | F8: =E8*D8*1.1 -> 136475.66 | G8: VIVA4
A9: Reaterro | B9: =B8*0.2 -> 413.5626 | C9: 0.6 | D9: =C9*B9 -> 248.13756 | E9: 25 | F9: =E9*D9*1.1 -> 6823.7829 | G9: VIVA4
A10: Movimentação de bota-fora Torre A | B10: =B7 -> 2226.741 | C10: =C7 -> 5.1 | D10: =C10*B10*1.3 -> 14763.293 | E10: 35 | F10: =E10*D10*1.1 -> 568386.77
A11: Movimentação de bota-fora Torre B | B11: - | C11: - | D11: =((B8*C8)-(B9*C9))*1.3 -> 2365.5781 | E11: 35 | F11: =E11*D11*1.1 -> 91074.756
A12: TOTAL | F12: =SUM(F7:F11) -> 1552282
A14: REBAIXAMENTO DE LENÇOL FREÁTICO
A16: Descrição | B16: Quantidade (dias) | E16: Preço unitário de rebaixamento (R$ / dias) | F16: Valor total
A17: Rebaixamento provisório de lençol | B17: =6*30 -> 180 | E17: 200 | F17: =B17*E17*1.1 -> 39600
A18: TOTAL | F18: =SUM(F17:F17) -> 39600
A20: ESCAVAÇÃO E REATERRO DE VALAS
A22: Descrição | B22: Parâmetro | D22: Volume total de escavação (m3) | E22: Preço unitário (R$ / m3) | F22: Valor total
A23: Escavação mecanizada para blocos e baldrames | B23: 1.2 | C23: m³ / APE | D23: =B23*(DADOS_INICIAIS!E21+DADOS_INICIAIS!F21) -> 4684.968 | E23: 50 | F23: =E23*D23*1.1 -> 257673.24 | G23: VIVA4
A24: Reaterro para blocos e baldrames | B24: 0.6 | C24: m³ / Vol Escavação | D24: =B24*D23 -> 2810.9808 | E24: 25 | F24: =E24*D24*1.1 -> 77301.972 | G24: VIVA4
A25: Movimentação de bota-fora | B25: 1.4 | C25: m³ | D25: =(D23-D24)*B25 -> 2623.5821 | E25: 40 | F25: =E25*D25*1.1 -> 115437.61 | G25: Conforme solicitado em 18/07 via whatsapp: considerar 40% | M25: Estava 30 reais
A26: Movimentação de terra das estacas | B26: 1.4 | C26: m³ | D26: ='INFRAESTRUTURA REV01'!D15 -> 1275.7945 | E26: 40 | F26: =E26*D26*1.1 -> 56134.958 | G26: Conforme solicitado em 18/07 via whatsapp: considerar 40% | M26: Estava 30 reais
A27: TOTAL | F27: =SUM(F23:F26) -> 506547.78
A29: REGULARIZAÇÃO E APILOAMENTO DE FUNDO DE VALAS
A31: Descrição | B31: Parâmetro | D31: Área de lastro (m²) | E31: Preço unitário (R$ / m2) | F31: Valor total
A32: Lastro de concreto magro | B32: 0.4 | C32: m² / APE | D32: =B32*(DADOS_INICIAIS!F23+DADOS_INICIAIS!E23) -> 1561.656 | E32: =230+30 -> 260 | F32: =E32*D32*1.1 -> 446633.62
A33: TOTAL | F33: =SUM(F32:F32) -> 446633.62
A35: TOTAL MOVIMENTAÇÃO DE TERRA | F35: =F12+F18+F27+F33 -> 2545063.4 | G35: =F35/DADOS_INICIAIS!E11 -> 173.2111

Sheet TERRAPLENAGEM

Sheet CONTENÇÕES
A3: CONTENÇÃO
A5: CORTINA DE ESTACAS
A7: Descrição | B7: Parâmetro | D7: Quantidade | F7: Preço unitário | G7: Valor total
A8: Número de Estacas | B8: 0.15 | C8: un / APE | D8: =B8*DADOS_INICIAIS!F23 -> 303.6465 | E8: un
A9: Estaca Hélice Continua Diâmetro 40 | B9: 0.1 | D9: =B9*$D$8 -> 30.36465 | E9: un
B10: 20 | C10: m/un | D10: =B10*D9 -> 607.293 | E10: m | G10: =F10*D10 -> 0
A11: Estaca Hélice Continua Diâmetro 50 | B11: 0.5 | D11: =B11*$D$8 -> 151.82325 | E11: un
B12: 20 | C12: m/un | D12: =B12*D11 -> 3036.465 | E12: m | G12: =F12*D12 -> 0
A13: Estaca Hélice Continua Diâmetro 60 | B13: 0.4 | C13: un / APE | D13: =B13*$D$8 -> 121.4586 | E13: un
B14: 20 | C14: m/un | D14: =B14*D13 -> 2429.172 | E14: m | G14: =F14*D14 -> 0
A15: Concreto | B15: =(PI()*0.4^2)/4*D12+(PI()*0.5^2)/4*D14+(PI()*0.6^2)/4*D10 -> 1030.2483 | C15: un / APE | D15: =(PI()*0.4^2)/4*D12+(PI()*0.5^2)/4*D14+(PI()*0.6^2)/4*D10 -> 1030.2483 | E15: m³ | G15: =F15*D15 -> 0
A16: Armação 6,3mm | B16: 1.6575131 | C16: kg / m³ | D16: =B16*D15 -> 1707.6501 | E16: kg | G16: =F16*D16 -> 0
A17: Armação 16mm | B17: 10.178338 | C17: kg / m³ | D17: =B17*D15 -> 10486.215 | E17: kg | G17: =F17*D17 -> 0
A18: Mobilização | B18: 1 | C18: vb | D18: 1 | E18: vb | G18: =F18*D18 -> 0
A19: TOTAL | G19: =SUM(G8:G18) -> 0
A21: PAREDE DE CONCRETO
A23: Descrição | B23: Parâmetro | D23: Quantidade | F23: Preço unitário | G23: Valor total
A24: Área de Contenção | D24: 1163.48 | H24: quantitativo de modelo (ambos subsolos)
A25: Fabricação, montagem e desmontagem de forma - resinado | B25: 2 | C25: m² | D25: =B25*D24 -> 2326.96 | E25: m² | F25: =206.56+0.130939 -> 206.69094 | G25: =F25*D25*1.1 -> 529057.7
A26: Concreto | B26: 0.4 | C26: m | D26: =D24*B26 -> 465.392 | E26: m³ | F26: =(650+45)*1.05 -> 729.75 | G26: =F26*D26*1.1 -> 373581.79 | H26: Custo Viva 4
A27: Armação | B27: 100 | C27: kg / m³ | D27: =B27*D26 -> 46539.2 | E27: kg | F27: 8 | G27: =F27*D27*1.1 -> 409544.96 | H27: Custo Viva 4
A28: Estrutura - drenagem | D28: 343.28 | E28: m | F28: 260 | G28: =F28*D28 -> 89252.8
A29: Mão de obra | B29: - | D29: =D24 -> 1163.48 | E29: m² | F29: 190 | G29: =F29*D29*1.1 -> 243167.32
A30: TOTAL | G30: =SUM(G25:G29) -> 1644604.6
A33: TOTAL INFRAESTRUTURA | G33: =G19+G30 -> 1644604.6 | H33: =G33/DADOS_INICIAIS!E11 -> 111.92796
B36: ATALAIA | C36: MONOLYT
A37: Projeção embasamento | B37: 659.3 | C37: =DADOS_INICIAIS!E23+DADOS_INICIAIS!F23 -> 3904.14
A38: Perímetro contenção | B38: 80 | C38: 343
A39: Área forma | B39: 610.01 | C39: 2326.96
A40: Altura média | B40: =(B39/2)/B38 -> 3.8125625 | C40: =(C39/2)/C38 -> 3.39207
A41: AC | B41: 7374 | C41: 12469.72
A42: Índice | B42: =B39/B41 -> 0.082724437 | C42: =C39/C41 -> 0.18660884 | E42: =B40*B38*2 -> 610.01
A43: Custo total | B43: 386506.36 | C43: =G30 -> 1644604.6
A44: Custo / m | B44: =B43/B38 -> 4831.3295 | C44: =C43/C38 -> 4794.7655
A45: Custo / m² | B45: =B43/B39 -> 633.6066 | C45: =C43/C39 -> 706.761
A46: Custo / AC | B46: =B43/B41 -> 52.414749 | C46: =C43/C41 -> 131.88785

Sheet INFRAESTRUTURA REV01
A3: INFRAESTRUTURA
A5: FUNDAÇÃO PROFUNDA
A7: Descrição | B7: Parâmetro | D7: Quantidade | F7: Preço unitário | G7: Valor total
A8: Número de Estacas | B8: 0.15 | C8: un / APE | D8: =ROUNDUP(B8*(DADOS_INICIAIS!F23+DADOS_INICIAIS!E23),0) -> 586 | E8: un
A9: Estaca Hélice Continua Diâmetro 40 | B9: 0.1 | D9: =B9*$D$8 -> 58.6 | E9: un
B10: 14 | C10: m/un | D10: =B10*D9 -> 820.4 | E10: m | F10: 70 | G10: =F10*D10*1.1 -> 63170.8 | H10: Gran Torino
A11: Estaca Hélice Continua Diâmetro 50 | B11: 0.7 | D11: =B11*$D$8 -> 410.2 | E11: un
B12: 14 | C12: m/un | D12: =B12*D11 -> 5742.8 | E12: m | F12: 100 | G12: =F12*D12*1.1 -> 631708 | H12: Gran Torino
A13: Estaca Hélice Continua Diâmetro 60 | B13: 0.2 | C13: un / APE | D13: =B13*$D$8 -> 117.2 | E13: un
B14: 14 | C14: m/un | D14: =B14*D13 -> 1640.8 | E14: m | F14: 120 | G14: =F14*D14*1.1 -> 216585.6 | H14: Gran Torino
A15: Concreto | B15: =(PI()*0.4^2)/4*D12+(PI()*0.5^2)/4*D14+(PI()*0.6^2)/4*D10 -> 1275.7945 | C15: un / APE | D15: =(PI()*0.4^2)/4*D12+(PI()*0.5^2)/4*D14+(PI()*0.6^2)/4*D10 -> 1275.7945 | E15: m³ | F15: =(650+45)*1.3 -> 903.5 | G15: =F15*D15*1.1 -> 1267948.4 | H15: Considerado 30% de perda
A16: Armação 6,3mm | B16: 1.6575131 | C16: kg / m³ | D16: =B16*D15 -> 2114.6461 | E16: kg | F16: 8 | G16: =F16*D16*1.1 -> 18608.886
A17: Armação 16mm | B17: 10.178338 | C17: kg / m³ | D17: =B17*D15 -> 12985.467 | E17: kg | F17: 8.5 | G17: =F17*D17*1.1 -> 121414.12
A18: Mobilização e arrasamento de estacas | B18: 1 | C18: vb | D18: 1 | E18: vb | F18: =15000+(586*300) -> 190800 | G18: =F18*D18*1.1 -> 209880 | H18: Não considerado anteriormente
A19: TOTAL | G19: =SUM(G8:G18) -> 2529315.8
A21: BALDRAMES
A23: Descrição | B23: Parâmetro | D23: Quantidade | F23: Preço unitário | G23: Valor total
A24: Fabricação, montagem e desmontagem de forma para blocos e baldrames madeira serrada | B24: 0.76 | C24: m² / APE | D24: =B24*(DADOS_INICIAIS!F23+DADOS_INICIAIS!E23) -> 2967.1464 | E24: m² | F24: 72 | G24: =F24*D24*1.1 -> 234997.99 | H24: Índice ABC- Estaleiro | I24: Custo Malaga
A25: Armação | B25: 90 | C25: kg / m³ | D25: =B25*D26 -> 80815.698 | E25: kg | F25: 8 | G25: =F25*D25*1.1 -> 711178.14 | H25: Índice VIVA4
A26: Concreto 45MPa | B26: 0.23 | C26: m³ / APE | D26: =B26*(DADOS_INICIAIS!F23+DADOS_INICIAIS!E23) -> 897.9522 | E26: m³ | F26: =(650+45)*1.05 -> 729.75 | G26: =F26*D26*1.1 -> 720808.68 | H26: Índice VIVA4
A27: Mão de obra | B27: =SUPRAESTRUTURA!B22*1.5 -> 360 | C27: R$ / APE | D27: =(DADOS_INICIAIS!F23+DADOS_INICIAIS!E23) -> 3904.14 | E27: m² | F27: =B27 -> 360 | G27: =F27*D27*1.1 -> 1546039.4 | H27: *****
A28: TOTAL | G28: =SUM(G24:G27) -> 3213024.3
A31: TOTAL INFRAESTRUTURA | G31: =G19+G28 -> 5742340 | H31: =G31/DADOS_INICIAIS!E11 -> 390.81031
C34: LIVE - LUMIS (Sapatas) - NÃO FOI UTILIZADA NESSA INFRA
C35: Projeção | D35: =10345.89/4 -> 2586.4725
C36: Peso do aço +10 % (kg) | D36: 12387.1
C37: Volume de concreto (m³) | D37: 204.9
C38: Área de forma (m²) | D38: 213.6
C39: Consumo de aço (kg/m³) | D39: =D36/D37 -> 60.454368

Sheet SUPRAESTRUTURA
A3: SUPRAESTRUTURA
A5: SUPRAESTRUTURA
A6: * PARÂMETROS BASEADOS EM BRASIN - REDENTOR
A7: Descrição | B7: Parâmetro | D7: Quantidade | F7: Preço unitário | G7: Valor total | K7: 15974922
A8: Piso Armado | B8: =SUPRAESTRUTURA!B4*1.5 -> 0 | C8: R$ / APE | D8: =DADOS_INICIAIS!$F$23+DADOS_INICIAIS!$E$23 -> 3904.14 | E8: m² | F8: 228.24 | G8: =F8*D8*1.1 -> 980189 | K8: =G25-K7 -> 980468.45
A9: Fabricação forma | B9: 4 | C9: Reutilizações | D9: =D11/B9 -> 7714.0455 | E9: m² | F9: 115 | G9: =F9*D9*1.1 -> 975826.76 | H9: CUSTO DO PISO ARMADO DILUÍDO NA SUPRA
A10: Fabricação forma - paredes de concreto | B10: 2.1 | C10: Lados | D10: =(499.15+1024.44)*B10 -> 3199.539 | E10: m² | F10: 115 | G10: =F10*D10*1.1 -> 404741.68
A11: Montagem de forma | B11: 2.1 | C11: m² / AC | D11: =B11*DADOS_INICIAIS!E11 -> 30856.182 | E11: m² | F11: 4.75 | G11: =F11*D11*1.1 -> 161223.55 | J11: =D11/4 -> 7714.0455
A12: Montagem de forma - paredes de concreto | D12: =D10 -> 3199.539 | E12: m² | F12: 4.75 | G12: =F12*D12*1.1 -> 16717.591
A13: Escoramento - Torre | B13: 3 | C13: un / APT*NPT | D13: =B13*(DADOS_INICIAIS!E17*DADOS_INICIAIS!E13+DADOS_INICIAIS!F17*DADOS_INICIAIS!F13+816.228) -> 26479.044 | E13: un | F13: 19 | G13: =F13*D13*1.1 -> 553412.02
A14: Escoramento - Embasamento | B14: 3 | C14: un / AE | D14: =DADOS_INICIAIS!F21*B14 -> 6072.93 | E14: un | F14: 19 | G14: =F14*D14*1.1 -> 126924.24
A15: Escoramento - Paredes de concreto | B15: 5 | C15: un / m2 | D15: =B15*(499.15+1024.44) -> 7617.95 | E15: un | F15: 19 | G15: =F15*D15*1.1 -> 159215.16
A16: Protensão | B16: 16.78 | C16: kg / m³ | D16: =B16*D17 -> 61638.897 | E16: kg | F16: 35 | G16: =F16*D16*1.1 -> 2373097.5 | J16: =70506.16/2618.24 -> 26.928838 | K16: reais/AC Ingleses Spot
A17: Concreto 45MPa | B17: 0.25 | C17: m³ / AC | D17: =B17*DADOS_INICIAIS!E11 -> 3673.355 | E17: m³ | F17: =(650+45)*1.05 -> 729.75 | G17: =F17*D17*1.1 -> 2948693.9
A18: Concreto - paredes de concreto45MPa | D18: =499.15*0.14+1024.44*0.2 -> 274.769 | E18: m³ | F18: =(650*1.25+45)*1.05 -> 900.375 | G18: =F18*D18*1.05*1.1 -> 285741.38
A19: Armadura Convencional para Estrutura | B19: 112 | C19: kg / m³ | D19: =D17*$B$19 -> 411415.76 | E19: kg | F19: 8 | G19: =F19*D19*1.1 -> 3620458.7
A20: Armadura Convencional para paredes de concreto | B20: 112 | C20: kg / m³ | D20: =D18*$B$20 -> 30774.128 | E20: kg | F20: 8 | G20: =F20*D20*1.1 -> 270812.33
A21: Mão de obra - laje inclinada | D21: =(499.15+1024.44) -> 1523.59 | E21: m² | F21: 318 | G21: =F21*D21*1.1 -> 532951.78
A22: Mão de obra - estrutura em concreto armado | B22: 240 | C22: R$ / AC | D22: =DADOS_INICIAIS!E11 -> 14693.42 | E22: m² | F22: 280 | G22: =F22*D22*1.1 -> 4525573.4
A23: TOTAL | G23: =SUM(G9:G22) -> 16955390
A25: TOTAL SUPRAESTRUTURA | G25: =G23 -> 16955390 | H25: =G25/DADOS_INICIAIS!E11 -> 1153.9444

Sheet SUPRAESTRUTURA (2)
A3: SUPRAESTRUTURA
A5: SUPRAESTRUTURA
A6: * PARÂMETROS BASEADOS EM BRASIN - REDENTOR | E6: ÍNDICES OK, MAS FALTANDO PISO ARMADO!!!!
A7: Descrição | B7: Parâmetro | D7: Quantidade | F7: Preço unitário | G7: Valor total | K7: 16068422
A8: Fabricação forma | B8: 4 | C8: Reutilizações | D8: =D10/B8 -> 7714.0455 | E8: m² | F8: 85 | G8: =F8*D8*1.1 -> 721263.25
A9: Fabricação forma - paredes de concreto | B9: 2.1 | C9: Lados | D9: =(499.15+1024.44)*B9 -> 3199.539 | E9: m² | F9: 85 | G9: =F9*D9*1.1 -> 299156.9
A10: Montagem de forma | B10: 2.1 | C10: m² / AC | D10: =B10*DADOS_INICIAIS!E11 -> 30856.182 | E10: m² | F10: 4.75 | G10: =F10*D10*1.1 -> 161223.55 | H10: Custo M | J10: =D10/4 -> 7714.0455
A11: Montagem de forma - paredes de concreto | D11: =D9 -> 3199.539 | E11: m² | F11: 4.75 | G11: =F11*D11*1.1 -> 16717.591
A12: Escoramento - Torre | B12: 3 | C12: un / APT*NPT | D12: =B12*(DADOS_INICIAIS!E17*DADOS_INICIAIS!E13+DADOS_INICIAIS!F17*DADOS_INICIAIS!F13+816.228) -> 26479.044 | E12: un | F12: 17 | G12: =F12*D12*1.1 -> 495158.12
A13: Escoramento - Embasamento | B13: 3 | C13: un / AE | D13: =DADOS_INICIAIS!F21*B13 -> 6072.93 | E13: un | F13: 17 | G13: =F13*D13*1.1 -> 113563.79
A14: Escoramento - Paredes de concreto | B14: 5 | C14: un / m2 | D14: =B14*(499.15+1024.44) -> 7617.95 | E14: un | F14: 17 | G14: =F14*D14*1.1 -> 142455.67
A15: Protensão | B15: 16.78 | C15: kg / m³ | D15: =B15*D16 -> 61638.897 | E15: kg | F15: =(11.95+11.4)*1.1*1.1 -> 28.2535 | G15: =F15*D15*1.1 -> 1915666 | J15: =70506.16/2618.24 -> 26.928838 | K15: reais/AC Ingleses Spot
A16: Concreto 45MPa | B16: 0.25 | C16: m³ / AC | D16: =B16*DADOS_INICIAIS!E11 -> 3673.355 | E16: m³ | F16: =(650+45)*1.05 -> 729.75 | G16: =F16*D16*1.1 -> 2948693.9
A17: Concreto - paredes de concreto45MPa | D17: =499.15*0.14+1024.44*0.2 -> 274.769 | E17: m³ | F17: =(650*1.25+45)*1.05 -> 900.375 | G17: =F17*D17*1.05*1.1 -> 285741.38
A18: Armadura Convencional para Estrutura | B18: 110 | C18: kg / m³ | D18: =D16*$B$18 -> 404069.05 | E18: kg | F18: 8 | G18: =F18*D18*1.1 -> 3555807.6
A19: Armadura Convencional para paredes de concreto | B19: 110 | C19: kg / m³ | D19: =D17*$B$19 -> 30224.59 | E19: kg | F19: 8 | G19: =F19*D19*1.1 -> 265976.39
A20: Mão de obra - laje inclinada | D20: =(499.15+1024.44) -> 1523.59 | E20: m² | F20: =250*1.26 -> 315 | G20: =F20*D20*1.1 -> 527923.94
A21: Mão de obra - estrutura em concreto armado | B21: 240 | C21: R$ / AC | D21: =DADOS_INICIAIS!E11 -> 14693.42 | E21: m² | F21: 280 | G21: =F21*D21*1.1 -> 4525573.4 | H21: Antes R$240,00
A22: TOTAL | G22: =SUM(G8:G21) -> 15974922
A24: TOTAL SUPRAESTRUTURA | G24: =G22 -> 15974922 | H24: =G24/DADOS_INICIAIS!E11 -> 1087.216

Sheet Alvenaria
A2: ORÇAMENTO PARAMÉTRICO GERENCIAMENTO EXECUTIVO
A7: Cliente | B7: =DADOS_INICIAIS!B2 -> BLUE HEAVEN
A8: Obra | B8: =DADOS_INICIAIS!B1 -> MONOLYT
A9: Data | B9: 45443
A10: Revisão | B10: R00
A12: ALVENARIA
A14: Descrição | B14: Quantidade | D14: Parâmetro | F14: Referência | G14: Valor total
A15: Alvenaria | B15: =4992.75 -> 4992.75 | C15: m² | D15: 48 | E15: R$ / m² | F15: Média | G15: =+B15*D15*1.1 -> 263617.2
A16: Drywall | B16: =7551.67*1.05 -> 7929.2535 | C16: m² | D16: 220 | E16: R$ / m² | F16: Média | G16: =+B16*D16*1.1 -> 1918879.3
A17: Isolamento lã pet | B17: =B16 -> 7929.2535 | C17: m² | D17: 35 | E17: R$ / m² | F17: Média | G17: =+B17*D17*1.1 -> 305276.26
A18: Alvenaria escadas | B18: =D18*B15 -> 998.55 | C18: m² | D18: 0.2 | E18: m² / AC | F18: Média | G18: =+B18*180*1.1 -> 197712.9 | I18: =(B15+B16)/DADOS_INICIAIS!E11 -> 0.87944151
A19: Alvenaria refratárias | B19: =DADOS_INICIAIS!E26 -> 24 | C19: un | D19: 1.75 | E19: m² / un | F19: Média | G19: =+B19*320*1.1 -> 8448
A20: Serviços complementares | B20: =B15+B18 -> 5991.3 | C20: m² | D20: 25 | E20: R$ / m² | F20: Média | G20: =+B20*D20*1.1 -> 164760.75
A21: Mão de obra | B21: =B20 -> 5991.3 | C21: m² | D21: 44 | E21: R$ / m² | F21: Média | G21: =+B21*D21*1.1 -> 289978.92
A22: TOTAL | G22: =SUM(G15:G21) -> 3148673.4
A25: TOTAL ALVENARIA | G25: =G22 -> 3148673.4 | H25: =G25/DADOS_INICIAIS!E11 -> 214.29139
A27: Gran Torino mat+o
A28: Somauma | B28: 72,00 alvenaria
H34: TORRE A E B + EMBASAMENTO
H35: Alvenaria | I35: 4992.75 | J35: =I35/I37 -> 0.39800565
H36: Drywall | I36: 7551.67 | J36: =I36/I37 -> 0.60199435
I37: =SUM(I35:I36) -> 12544.42

Sheet REVESTIMENTO PISO
A1: Obra
A2: Empresa
A3: Revisão
A4: Data
A5: LEVANTAMENTO QUANTITATIVO
A7: REVESTIMENTOS E ACABAMENTOS DE PISO
B9: LEVANTAMENTO DE PROJETO | K9: CONTRAPISO
B10: Pavimento | C10: APT0 / A.C. | D10: Ambiente | E10: Material | F10: Área (m²) | G10: Contrapiso (Sim/Não) | H10: Repetição | I10: Total | K10: Revestimento | L10: Área total
B11: 1SS | C11: A.C. | D11: ÁREA TÉCNICA | E11: Pintura acrílica antiderrapante | F11: 456.33 | G11: Sim | H11: 1 | I11: =F11*H11 -> 456.33 | K11: Contrapiso | L11: =SUMIF(G:G,"Sim",I:I) -> 9592.09
B12: 1SS | C12: A.C. | D12: ÁREA PERMEÁVEL | F12: 26.38 | G12: Não | H12: 1 | I12: =F12*H12 -> 26.38 | K12: Manta acústica | L12: =SUMIFS(I:I,G:G,"Sim",C:C,"*APT*") -> 5559.67
B13: 1SS | C13: A.C. | D13: HALL | E13: Piso especial | F13: 33.58 | G13: Sim | H13: 1 | I13: =F13*H13 -> 33.58
B14: 1SS | C14: A.C. | D14: ESTACIONAMENTO | E14: Pintura piso epoxi | F14: 1500.84 | G14: Não | H14: 1 | I14: =F14*H14 -> 1500.84 | K14: ACABAMENTOS
B15: 1SS | C15: A.C. | D15: SALA DE ESPERA | E15: Piso especial | F15: 41.28 | G15: Sim | H15: 1 | I15: =F15*H15 -> 41.28 | K15: Material | L15: Área total
A16: =C16<>C14 -> TRUE | B16: TÉRREO | C16: APT01 - TB | D16: ESTAR | E16: Piso especial | F16: 24.87 | G16: Sim | H16: 1 | I16: =F16*H16 -> 24.87 | K16: Pintura acrílica antiderrapante | L16: =SUMIF(E:E,K16,I:I) -> 626.89
A17: =IF(C16="*&APTO&*","OK","") | B17: TÉRREO | C17: APT01 - TB | D17: JANTAR | E17: Piso especial | F17: 28.27 | G17: Sim | H17: 1 | I17: =F17*H17 -> 28.27 | K17: Porcelanato | L17: =SUMIF(E:E,K17,I:I) -> 0
B18: TÉRREO | C18: APT01 - TB | D18: LAVABO | E18: Piso especial | F18: 3.4 | G18: Sim | H18: 1 | I18: =F18*H18 -> 3.4 | K18: Pintura piso epoxi | L18: =SUMIF(E:E,K18,I:I) -> 2584.45
B19: TÉRREO | C19: APT01 - TB | D19: DECK | E19: Deck | F19: 27.53 | H19: 1 | I19: =F19*H19 -> 27.53 | K19: Deck | L19: =SUMIF(E:E,K19,I:I) -> 1341.17
B20: TÉRREO | C20: APT01 - TB | D20: PISCINA (PROF. 1,2m) | E20: Piscina | F20: 21.52 | H20: 1 | I20: =F20*H20 -> 21.52 | K20: Piscina | L20: =SUMIF(E:E,K20,I:I) -> 830.41
B21: TÉRREO | C21: APT01 - TB | D21: COZINHA | E21: Piso especial | F21: 15.72 | G21: Sim | H21: 1 | I21: =F21*H21 -> 15.72 | K21: Piso madeira engenheirada | L21: =SUMIF(E:E,K21,I:I) -> 2122.95
A22: Piso especial | B22: TÉRREO | C22: APT01 - TB | D22: A.S. | E22: Piso especial | F22: 7.6 | G22: Sim | H22: 1 | I22: =F22*H22 -> 7.6 | K22: Piso especial A.C. | L22: =SUMIF(E:E,K22,I:I) -> 0
B23: TÉRREO | C23: APT01 - TB | D23: BANHO SERV. | E23: Piso especial | F23: 4.22 | G23: Sim | H23: 1 | I23: =F23*H23 -> 4.22 | K23: Emborrachado | L23: =SUMIF(E:E,K23,I:I) -> 35.17
B24: TÉRREO | C24: APT01 - TB | D24: CIRC. | E24: Piso madeira engenheirada | F24: 12.36 | G24: Sim | H24: 1 | I24: =F24*H24 -> 12.36 | K24: Piso vinilico | L24: =SUMIF(E:E,K24,I:I) -> 77.76
B25: TÉRREO | C25: APT01 - TB | D25: SUÍTE MASTER | E25: Piso madeira engenheirada | F25: 27.24 | G25: Sim | H25: 1 | I25: =F25*H25 -> 27.24 | L25: =SUMIF(E:E,K25,I:I) -> 0
B26: TÉRREO | C26: APT01 - TB | D26: BANHO MASTER | E26: Piso especial | F26: 7.54 | G26: Sim | H26: 1 | I26: =F26*H26 -> 7.54 | L26: =SUMIF(E:E,K26,I:I) -> 0
B27: TÉRREO | C27: APT01 - TB | D27: SUÍTE 2 | E27: Piso madeira engenheirada | F27: 18.87 | G27: Sim | H27: 1 | I27: =F27*H27 -> 18.87 | L27: =SUMIF(E:E,K27,I:I) -> 0
B28: TÉRREO | C28: APT01 - TB | D28: BANHO 2 | E28: Piso especial | F28: 4.85 | G28: Sim | H28: 1 | I28: =F28*H28 -> 4.85 | L28: =SUMIF(E:E,K28,I:I) -> 0
B29: TÉRREO | C29: APT01 - TB | D29: SUÍTE 1 | E29: Piso madeira engenheirada | F29: 18.87 | G29: Sim | H29: 1 | I29: =F29*H29 -> 18.87 | L29: =SUMIF(E:E,K29,I:I) -> 0
B30: TÉRREO | C30: APT01 - TB | D30: BANHO 1 | E30: Piso especial | F30: 4.85 | G30: Sim | H30: 1 | I30: =F30*H30 -> 4.85 | L30: =SUMIF(E:E,K30,I:I) -> 0
B31: TÉRREO | C31: A.C. | D31: (ÁREA TÉCNICA) ESCADA EMERG. | E31: Pintura acrílica antiderrapante | F31: =18.79+1.5*0.18*20 -> 24.19 | G31: Sim | H31: 1 | I31: =F31*H31 -> 24.19 | L31: =SUMIF(E:E,K31,I:I) -> 0
B32: TÉRREO | C32: A.C. | D32: YOGA | E32: Piso especial | F32: 41.02 | G32: Sim | H32: 1 | I32: =F32*H32 -> 41.02 | L32: =SUMIF(E:E,K32,I:I) -> 0
B33: TÉRREO | C33: A.C. | D33: SALA DE ESPERA | E33: Piso especial | F33: 25.18 | G33: Sim | H33: 1 | I33: =F33*H33 -> 25.18 | L33: =SUMIF(E:E,K33,I:I) -> 0
B34: TÉRREO | C34: A.C. | D34: GOUMERT | E34: Piso especial | F34: 18.45 | G34: Sim | H34: 1 | I34: =F34*H34 -> 18.45 | L34: =SUMIF(E:E,K34,I:I) -> 0
B35: TÉRREO | C35: APT02 - TB | D35: ESTAR | E35: Piso especial | F35: 26.95 | G35: Sim | H35: 1 | I35: =F35*H35 -> 26.95 | L35: =SUMIF(E:E,K35,I:I) -> 0
B36: TÉRREO | C36: APT02 - TB | D36: JANTAR | E36: Piso especial | F36: 41.59 | G36: Sim | H36: 1 | I36: =F36*H36 -> 41.59
B37: TÉRREO | C37: APT02 - TB | D37: LAVABO | E37: Piso especial | F37: 3.67 | G37: Sim | H37: 1 | I37: =F37*H37 -> 3.67
B38: TÉRREO | C38: APT02 - TB | D38: DECK | E38: Deck | F38: 32.26 | H38: 1 | I38: =F38*H38 -> 32.26
B39: TÉRREO | C39: APT02 - TB | D39: PISCINA (PROF. 1,2m) | E39: Piscina | F39: 21.56 | G39: Sim | H39: 1 | I39: =F39*H39 -> 21.56
B40: TÉRREO | C40: APT02 - TB | D40: COZINHA | E40: Piso especial | F40: 15.02 | G40: Sim | H40: 1 | I40: =F40*H40 -> 15.02
B41: TÉRREO | C41: APT02 - TB | D41: DESPENSA | E41: Piso especial | F41: 3.12 | G41: Sim | H41: 1 | I41: =F41*H41 -> 3.12
B42: TÉRREO | C42: APT02 - TB | D42: A.S. | E42: Piso especial | F42: 9.49 | G42: Sim | H42: 1 | I42: =F42*H42 -> 9.49
B43: TÉRREO | C43: APT02 - TB | D43: DORM. SERV. | E43: Piso especial | F43: 6.96 | G43: Sim | H43: 1 | I43: =F43*H43 -> 6.96
B44: TÉRREO | C44: APT02 - TB | D44: BANHO SERV. | E44: Piso especial | F44: 4.09 | G44: Sim | H44: 1 | I44: =F44*H44 -> 4.09
B45: TÉRREO | C45: APT02 - TB | D45: CIRC. | E45: Piso madeira engenheirada | F45: 14.97 | G45: Sim | H45: 1 | I45: =F45*H45 -> 14.97
B46: TÉRREO | C46: APT02 - TB | D46: SUÍTE MASTER | E46: Piso madeira engenheirada | F46: 28.46 | G46: Sim | H46: 1 | I46: =F46*H46 -> 28.46
B47: TÉRREO | C47: APT02 - TB | D47: BANHO MASTER | E47: Piso especial | F47: 7.06 | G47: Sim | H47: 1 | I47: =F47*H47 -> 7.06
B48: TÉRREO | C48: APT02 - TB | D48: SUÍTE 3 | E48: Piso madeira engenheirada | F48: 18.87 | G48: Sim | H48: 1 | I48: =F48*H48 -> 18.87
B49: TÉRREO | C49: APT02 - TB | D49: BANHO 3 | E49: Piso especial | F49: 4.85 | G49: Sim | H49: 1 | I49: =F49*H49 -> 4.85
B50: TÉRREO | C50: APT02 - TB | D50: SUÍTE 2 | E50: Piso madeira engenheirada | F50: 18.85 | G50: Sim | H50: 1 | I50: =F50*H50 -> 18.85
... B56: TÉRREO | C56: APT03 - TB | D56: LAVABO | E56: Piso especial | F56: 3.4 | G56: Sim | H56: 1 | I56: =F56*H56 -> 3.4
B57: TÉRREO | C57: APT03 - TB | D57: DECK | E57: Deck | F57: 28.39 | H57: 1 | I57: =F57*H57 -> 28.39
B58: TÉRREO | C58: APT03 - TB | D58: PISCINA (PROF. 1,2m) | E58: Piscina | F58: 21.53 | G58: Sim | H58: 1 | I58: =F58*H58 -> 21.53
B59: TÉRREO | C59: APT03 - TB | D59: COZINHA | E59: Piso especial | F59: 15.72 | G59: Sim | H59: 1 | I59: =F59*H59 -> 15.72
B60: TÉRREO | C60: APT03 - TB | D60: A.S. | E60: Piso especial | F60: 7.59 | G60: Sim | H60: 1 | I60: =F60*H60 -> 7.59
B61: TÉRREO | C61: APT03 - TB | D61: BANHO SERV. | E61: Piso especial | F61: 4.22 | G61: Sim | H61: 1 | I61: =F61*H61 -> 4.22
B62: TÉRREO | C62: APT03 - TB | D62: CIRC. | E62: Piso madeira engenheirada | F62: 12.36 | G62: Sim | H62: 1 | I62: =F62*H62 -> 12.36
B63: TÉRREO | C63: APT03 - TB | D63: SUÍTE MASTER | E63: Piso madeira engenheirada | F63: 27.24 | G63: Sim | H63: 1 | I63: =F63*H63 -> 27.24
B64: TÉRREO | C64: APT03 - TB | D64: BANHO MASTER | E64: Piso especial | F64: 7.54 | G64: Sim | H64: 1 | I64: =F64*H64 -> 7.54
B65: TÉRREO | C65: APT03 - TB | D65: SUÍTE 2 | E65: Piso madeira engenheirada | F65: 18.87 | G65: Sim | H65: 1 | I65: =F65*H65 -> 18.87
B66: TÉRREO | C66: APT03 - TB | D66: BANHO 2 | E66: Piso especial | F66: 4.85 | G66: Sim | H66: 1 | I66: =F66*H66 -> 4.85
B67: TÉRREO | C67: APT03 - TB | D67: SUÍTE 1 | E67: Piso madeira engenheirada | F67: 18.87 | G67: Sim | H67: 1 | I67: =F67*H67 -> 18.87
B68: TÉRREO | C68: APT03 - TB | D68: BANHO 1 | E68: Piso especial | F68: 4.85 | G68: Sim | H68: 1 | I68: =F68*H68 -> 4.85
B69: TÉRREO | C69: APT04 - TB | D69: ESTAR | E69: Piso especial | F69: 27.02 | G69: Sim | H69: 1 | I69: =F69*H69 -> 27.02
... B71: TÉRREO | C71: APT04 - TB | D71: LAVABO | E71: Piso especial | F71: 3.77 | G71: Sim | H71: 1 | I71: =F71*H71 -> 3.77
B72: TÉRREO | C72: APT04 - TB | D72: DECK | E72: Deck | F72: 32.3 | H72: 1 | I72: =F72*H72 -> 32.3
B73: TÉRREO | C73: APT04 - TB | D73: PISCINA (PROF. 1,2m) | E73: Piscina | F73: 23.17 | G73: Sim | H73: 1 | I73: =F73*H73 -> 23.17
B74: TÉRREO | C74: APT04 - TB | D74: COZINHA | E74: Piso especial | F74: 15.19 | G74: Sim | H74: 1 | I74: =F74*H74 -> 15.19
B75: TÉRREO | C75: APT04 - TB | D75: A.S. | E75: Piso especial | F75: 9.49 | G75: Sim | H75: 1 | I75: =F75*H75 -> 9.49
B76: TÉRREO | C76: APT04 - TB | D76: DORM. SERV. | E76: Piso especial | F76: 6.96 | G76: Sim | H76: 1 | I76: =F76*H76 -> 6.96
B77: TÉRREO | C77: APT04 - TB | D77: BANHO SERV. | E77: Piso especial | F77: 4.09 | G77: Sim | H77: 1 | I77: =F77*H77 -> 4.09
B78: TÉRREO | C78: APT04 - TB | D78: CIRC. | E78: Piso madeira engenheirada | F78: 14.99 | G78: Sim | H78: 1 | I78: =F78*H78 -> 14.99
B79: TÉRREO | C79: APT04 - TB | D79: SUÍTE MASTER | E79: Piso madeira engenheirada | F79: 28.46 | G79: Sim | H79: 1 | I79: =F79*H79 -> 28.46
B80: TÉRREO | C80: APT04 - TB | D80: BANHO MASTER | E80: Piso especial | F80: 7.06 | G80: Sim | H80: 1 | I80: =F80*H80 -> 7.06
B81: TÉRREO | C81: APT04 - TB | D81: SUÍTE 3 | E81: Piso madeira engenheirada | F81: 18.87 | G81: Sim | H81: 1 | I81: =F81*H81 -> 18.87
B82: TÉRREO | C82: APT04 - TB | D82: BANHO 3 | E82: Piso especial | F82: 4.85 | G82: Sim | H82: 1 | I82: =F82*H82 -> 4.85
B83: TÉRREO | C83: APT04 - TB | D83: SUÍTE 2 | E83: Piso madeira engenheirada | F83: 18.85 | G83: Sim | H83: 1 | I83: =F83*H83 -> 18.85
B84: TÉRREO | C84: APT04 - TB | D84: BANHO 2 | E84: Piso especial | F84: 4.85 | G84: Sim | H84: 1 | I84: =F84*H84 -> 4.85
... B87: TÉRREO | C87: A.C. | D87: ESTACIONAMENTO | E87: Pintura piso epoxi | F87: 1083.61 | G87: Sim | H87: 1 | I87: =F87*H87 -> 1083.61
B88: TÉRREO | C88: A.C. | D88: ÁREA TÉCNICA / ESCADA | E88: Pintura acrílica antiderrapante | F88: =26.49+1.5*0.18*20 -> 31.89 | G88: Sim | H88: 1 | I88: =F88*H88 -> 31.89
B89: TÉRREO | C89: A.C. | D89: DEPÓSITO | E89: Piso especial | F89: 8.01 | G89: Sim | H89: 1 | I89: =F89*H89 -> 8.01
B90: TÉRREO | C90: A.C. | D90: HALL | E90: Piso especial | F90: 34.34 | G90: Sim | H90: 1 | I90: =F90*H90 -> 34.34
B91: TÉRREO | C91: A.C. | D91: PISCINA (PROF. 1,2m) | E91: Piscina | F91: 65.86 | G91: Sim | H91: 1 | I91: =F91*H91 -> 65.86
B92: TÉRREO | C92: A.C. | D92: ÁREA PERMEÁVEL | F92: 8.99 | H92: 1 | I92: =F92*H92 -> 8.99
B93: TÉRREO | C93: A.C. | D93: HALL ACESSO APTO | E93: Piso especial | F93: 24.93 | G93: Sim | H93: 1 | I93: =F93*H93 -> 24.93
B94: TÉRREO | C94: APT01 - TA | D94: ESTAR | E94: Piso especial | F94: 24.98 | G94: Sim | H94: 1 | I94: =F94*H94 -> 24.98
B95: TÉRREO | C95: APT01 - TA | D95: JANTAR | E95: Piso especial | F95: 25.92 | G95: Sim | H95: 1 | I95: =F95*H95 -> 25.92
B96: TÉRREO | C96: APT01 - TA | D96: LAVABO | E96: Piso especial | F96: 2.86 | G96: Sim | H96: 1 | I96: =F96*H96 -> 2.86
B97: TÉRREO | C97: APT01 - TA | D97: DECK | E97: Deck | F97: 29.26 | H97: 1 | I97: =F97*H97 -> 29.26
B98: TÉRREO | C98: APT01 - TA | D98: PISCINA (PROF. 1,2m) | E98: Piscina | F98: 22.93 | G98: Sim | H98: 1 | I98: =F98*H98 -> 22.93
B99: TÉRREO | C99: APT01 - TA | D99: COZINHA | E99: Piso especial | F99: 16.3 | G99: Sim | H99: 1 | I99: =F99*H99 -> 16.3
B100: TÉRREO | C100: APT01 - TA | D100: A.S. | E100: Piso especial | F100: 4.31 | G100: Sim | H100: 1 | I100: =F100*H100 -> 4.31
B101: TÉRREO | C101: APT01 - TA | D101: BANHO SERV. | E101: Piso especial | F101: 5.28 | G101: Sim | H101: 1 | I101: =F101*H101 -> 5.28
B102: TÉRREO | C102: APT01 - TA | D102: CIRC. | E102: Piso madeira engenheirada | F102: 10.66 | G102: Sim | H102: 1 | I102: =F102*H102 -> 10.66
B103: TÉRREO | C103: APT01 - TA | D103: SUÍTE MASTER | E103: Piso madeira engenheirada | F103: 19.49 | G103: Sim | H103: 1 | I103: =F103*H103 -> 19.49
B104: TÉRREO | C104: APT01 - TA | D104: BANHO MASTER | E104: Piso especial | F104: 7.37 | G104: Sim | H104: 1 | I104: =F104*H104 -> 7.37
B105: TÉRREO | C105: APT01 - TA | D105: SUÍTE 2 | E105: Piso madeira engenheirada | F105: 18.7 | G105: Sim | H105: 1 | I105: =F105*H105 -> 18.7
B106: TÉRREO | C106: APT01 - TA | D106: BANHO 2 | E106: Piso especial | F106: 4.76 | G106: Sim | H106: 1 | I106: =F106*H106 -> 4.76
B107: TÉRREO | C107: APT01 - TA | D107: SUÍTE 1 | E107: Piso madeira engenheirada | F107: 18.71 | G107: Sim | H107: 1 | I107: =F107*H107 -> 18.71
B108: TÉRREO | C108: APT01 - TA | D108: BANHO 1 | E108: Piso especial | F108: 4.78 | G108: Sim | H108: 1 | I108: =F108*H108 -> 4.78
B109: TÉRREO/1º PAVIMENTO | C109: APT04 (2 PAVIMENTOS) - TA | D109: ESTAR | E109: Piso especial | F109: 21.3 | G109: Sim | H109: 1 | I109: =F109*H109 -> 21.3
... B111: TÉRREO/1º PAVIMENTO | C111: APT04 (2 PAVIMENTOS) - TA | D111: LAVABO | E111: Piso especial | F111: 3.5 | G111: Sim | H111: 1 | I111: =F111*H111 -> 3.5
...

Sheet REVESTIMENTO PAREDE PISCINA
A1: Obra
A2: Empresa
A3: Revisão
A4: Data
A5: LEVANTAMENTO QUANTITATIVO
A7: REVESTIMENTOS E ACABAMENTOS DE PAREDE
B9: LEVANTAMENTO DE PROJETO | L9: REBOCO
B10: Pavimento | C10: Apto / A.C. | D10: Ambiente | E10: Material | F10: Perímetro (m) | G10: Altura (m) | H10: Reboco (Sim/Não) | I10: Repetição | J10: Total | L10: Revestimento | M10: Área total
B11: 1SS | C11: A.C. | D11: ÁREA TÉCNICA | E11: Pintura acrílica antiderrapante | I11: 1 | J11: =G11*I11 -> 0
B12: 1SS | C12: A.C. | D12: ÁREA PERMEÁVEL | I12: 1 | J12: =G12*I12 -> 0
B13: 1SS | C13: A.C. | D13: HALL | E13: Porcelanato | I13: 1 | J13: =G13*I13 -> 0
B14: 1SS | C14: A.C. | D14: ESTACIONAMENTO | E14: Pintura piso epoxi | I14: 1 | J14: =G14*I14 -> 0 | L14: ACABAMENTOS
B15: TÉRREO | C15: APTO1 | D15: ESTAR | E15: Porcelanato | I15: 1 | J15: =G15*I15 -> 0 | L15: Material | M15: Área total
B16: TÉRREO | C16: APTO1 | D16: JANTAR | E16: Porcelanato | I16: 1 | J16: =G16*I16 -> 0 | L16: Pintura acrílica antiderrapante | M16: =SUMIF(E:E,L16,J:J) -> 0
B17: TÉRREO | C17: APTO1 | D17: LAVABO | E17: Porcelanato | I17: 1 | J17: =G17*I17 -> 0 | L17: Porcelanato | M17: =SUMIF(E:E,L17,J:J) -> 0
B18: TÉRREO | C18: APTO1 | D18: DECK | E18: Deck | I18: 1 | J18: =G18*I18 -> 0 | L18: Pintura piso epoxi | M18: =SUMIF(E:E,L18,J:J) -> 0
B19: TÉRREO | C19: APTO1 | D19: PISCINA (PROF. 1,2m) | E19: Piscina | F19: 13.69 | G19: 1.2 | H19: Sim | I19: 1 | J19: =F19*G19 -> 16.428 | L19: Deck | M19: =SUMIF(E:E,L19,J:J) -> 0
B20: TÉRREO | C20: APTO1 | D20: COZINHA | E20: Porcelanato | I20: 1 | J20: =G20*I20 -> 0 | L20: Piscina | M20: =SUMIF(E:E,L20,J:J) -> 677.348
B21: TÉRREO | C21: APTO1 | D21: A.S. | E21: Porcelanato | I21: 1 | J21: =G21*I21 -> 0 | L21: Piso madeira engenheirada | M21: =SUMIF(E:E,L21,J:J) -> 0
B22: TÉRREO | C22: APTO1 | D22: BANHO SERV. | E22: Porcelanato | I22: 1 | J22: =G22*I22 -> 0 | L22: Piso especial A.C. | M22: =SUMIF(E:E,L22,J:J) -> 0
B23: TÉRREO | C23: APTO1 | D23: CIRC. | E23: Porcelanato | I23: 1 | J23: =G23*I23 -> 0 | L23: Emborrachado | M23: =SUMIF(E:E,L23,J:J) -> 0
B24: TÉRREO | C24: APTO1 | D24: SUÍTE MASTER | E24: Piso madeira engenheirada | I24: 1 | J24: =G24*I24 -> 0 | L24: Piso vinilico | M24: =SUMIF(E:E,L24,J:J) -> 0
B25: TÉRREO | C25: APTO1 | D25: BANHO MASTER | E25: Porcelanato | I25: 1 | J25: =G25*I25 -> 0 | M25: =SUMIF(E:E,L25,J:J) -> 0
B26: TÉRREO | C26: APTO1 | D26: SUÍTE 2 | E26: Piso madeira engenheirada | I26: 1 | J26: =G26*I26 -> 0 | M26: =SUMIF(E:E,L26,J:J) -> 0
B27: TÉRREO | C27: APTO1 | D27: BANHO 2 | E27: Porcelanato | I27: 1 | J27: =G27*I27 -> 0 | M27: =SUMIF(E:E,L27,J:J) -> 0
B28: TÉRREO | C28: APTO1 | D28: SUÍTE 1 | E28: Piso madeira engenheirada | I28: 1 | J28: =G28*I28 -> 0 | M28: =SUMIF(E:E,L28,J:J) -> 0
B29: TÉRREO | C29: APTO1 | D29: BANHO 1 | E29: Porcelanato | I29: 1 | J29: =G29*I29 -> 0 | M29: =SUMIF(E:E,L29,J:J) -> 0
B30: TÉRREO | C30: A.C. | D30: (ÁREA TÉCNICA) ESCADA EMERG. | E30: Pintura acrílica antiderrapante | I30: 1 | J30: =G30*I30 -> 0 | M30: =SUMIF(E:E,L30,J:J) -> 0
B31: TÉRREO | C31: A.C. | D31: CIRCULAÇÃO | E31: Porcelanato | I31: 1 | J31: =G31*I31 -> 0 | M31: =SUMIF(E:E,L31,J:J) -> 0
B32: TÉRREO | C32: A.C. | D32: ÁREA COMUM DESCOBERTA | E32: Piso especial A.C. | I32: 1 | J32: =G32*I32 -> 0 | M32: =SUMIF(E:E,L32,J:J) -> 0
B33: TÉRREO | C33: APTO2 | D33: ESTAR | E33: Porcelanato | I33: 1 | J33: =G33*I33 -> 0 | M33: =SUMIF(E:E,L33,J:J) -> 0
B34: TÉRREO | C34: APTO2 | D34: JANTAR | E34: Porcelanato | I34: 1 | J34: =G34*I34 -> 0 | M34: =SUMIF(E:E,L34,J:J) -> 0
B35: TÉRREO | C35: APTO2 | D35: LAVABO | E35: Porcelanato | I35: 1 | J35: =G35*I35 -> 0 | M35: =SUMIF(E:E,L35,J:J) -> 0
B36: TÉRREO | C36: APTO2 | D36: DECK | E36: Deck | I36: 1 | J36: =G36*I36 -> 0
B37: TÉRREO | C37: APTO2 | D37: PISCINA (PROF. 1,2m) | E37: Piscina | F37: 13.72 | G37: 1.2 | H37: Sim | I37: 1 | J37: =F37*G37 -> 16.464
B38: TÉRREO | C38: APTO2 | D38: COZINHA | E38: Porcelanato | I38: 1 | J38: =G38*I38 -> 0
B39: TÉRREO | C39: APTO2 | D39: DESPENSA | E39: Porcelanato | I39: 1 | J39: =G39*I39 -> 0
B40: TÉRREO | C40: APTO2 | D40: A.S. | E40: Porcelanato | I40: 1 | J40: =G40*I40 -> 0
B41: TÉRREO | C41: APTO2 | D41: DORM. SERV. | E41: Porcelanato | I41: 1 | J41: =G41*I41 -> 0
B42: TÉRREO | C42: APTO2 | D42: BANHO SERV. | E42: Porcelanato | I42: 1 | J42: =G42*I42 -> 0
B43: TÉRREO | C43: APTO2 | D43: CIRC. | E43: Porcelanato | I43: 1 | J43: =G43*I43 -> 0
B44: TÉRREO | C44: APTO2 | D44: SUÍTE MASTER | E44: Piso madeira engenheirada | I44: 1 | J44: =G44*I44 -> 0
B45: TÉRREO | C45: APTO2 | D45: BANHO MASTER | E45: Porcelanato | I45: 1 | J45: =G45*I45 -> 0
B46: TÉRREO | C46: APTO2 | D46: SUÍTE 3 | E46: Piso madeira engenheirada | I46: 1 | J46: =G46*I46 -> 0
B47: TÉRREO | C47: APTO2 | D47: BANHO 3 | E47: Porcelanato | I47: 1 | J47: =G47*I47 -> 0
B48: TÉRREO | C48: APTO2 | D48: SUÍTE 2 | E48: Piso madeira engenheirada | I48: 1 | J48: =G48*I48 -> 0
B49: TÉRREO | C49: APTO2 | D49: BANHO 2 | E49: Porcelanato | I49: 1 | J49: =G49*I49 -> 0
... B55: TÉRREO | C55: APTO3 | D55: DECK | E55: Deck | I55: 1 | J55: =G55*I55 -> 0
B56: TÉRREO | C56: APTO3 | D56: PISCINA (PROF. 1,2m) | E56: Piscina | F56: 13.75 | G56: 1.2 | H56: Sim | I56: 1 | J56: =F56*G56 -> 16.5
B57: TÉRREO | C57: APTO3 | D57: COZINHA | E57: Porcelanato | I57: 1 | J57: =G57*I57 -> 0
B58: TÉRREO | C58: APTO3 | D58: A.S. | E58: Porcelanato | I58: 1 | J58: =G58*I58 -> 0
B59: TÉRREO | C59: APTO3 | D59: BANHO SERV. | E59: Porcelanato | I59: 1 | J59: =G59*I59 -> 0
B60: TÉRREO | C60: APTO3 | D60: CIRC. | E60: Porcelanato | I60: 1 | J60: =G60*I60 -> 0
B61: TÉRREO | C61: APTO3 | D61: SUÍTE MASTER | E61: Piso madeira engenheirada | I61: 1 | J61: =G61*I61 -> 0
B62: TÉRREO | C62: APTO3 | D62: BANHO MASTER | E62: Porcelanato | I62: 1 | J62: =G62*I62 -> 0
B63: TÉRREO | C63: APTO3 | D63: SUÍTE 2 | E63: Piso madeira engenheirada | I63: 1 | J63: =G63*I63 -> 0
B64: TÉRREO | C64: APTO3 | D64: BANHO 2 | E64: Porcelanato | I64: 1 | J64: =G64*I64 -> 0
B65: TÉRREO | C65: APTO3 | D65: SUÍTE 1 | E65: Piso madeira engenheirada | I65: 1 | J65: =G65*I65 -> 0
B66: TÉRREO | C66: APTO3 | D66: BANHO 1 | E66: Porcelanato | I66: 1 | J66: =G66*I66 -> 0
B67: TÉRREO | C67: APTO4 | D67: ESTAR | E67: Porcelanato | I67: 1 | J67: =G67*I67 -> 0
B68: TÉRREO | C68: APTO4 | D68: JANTAR | E68: Porcelanato | I68: 1 | J68: =G68*I68 -> 0
... B70: TÉRREO | C70: APTO4 | D70: DECK | E70: Deck | I70: 1 | J70: =G70*I70 -> 0
B71: TÉRREO | C71: APTO4 | D71: PISCINA (PROF. 1,2m) | E71: Piscina | F71: 14.28 | G71: 1.2 | H71: Sim | I71: 1 | J71: =F71*G71 -> 17.136
B72: TÉRREO | C72: APTO4 | D72: COZINHA | E72: Porcelanato | I72: 1 | J72: =G72*I72 -> 0
B73: TÉRREO | C73: APTO4 | D73: A.S. | E73: Porcelanato | I73: 1 | J73: =G73*I73 -> 0
B74: TÉRREO | C74: APTO4 | D74: DORM. SERV. | E74: Porcelanato | I74: 1 | J74: =G74*I74 -> 0
B75: TÉRREO | C75: APTO4 | D75: BANHO SERV. | E75: Porcelanato | I75: 1 | J75: =G75*I75 -> 0
B76: TÉRREO | C76: APTO4 | D76: CIRC. | E76: Porcelanato | I76: 1 | J76: =G76*I76 -> 0
B77: TÉRREO | C77: APTO4 | D77: SUÍTE MASTER | E77: Piso madeira engenheirada | I77: 1 | J77: =G77*I77 -> 0
B78: TÉRREO | C78: APTO4 | D78: BANHO MASTER | E78: Porcelanato | I78: 1 | J78: =G78*I78 -> 0
B79: TÉRREO | C79: APTO4 | D79: SUÍTE 3 | E79: Piso madeira engenheirada | I79: 1 | J79: =G79*I79 -> 0
B80: TÉRREO | C80: APTO4 | D80: BANHO 3 | E80: Porcelanato | I80: 1 | J80: =G80*I80 -> 0
B81: TÉRREO | C81: APTO4 | D81: SUÍTE 2 | E81: Piso madeira engenheirada | I81: 1 | J81: =G81*I81 -> 0
B82: TÉRREO | C82: APTO4 | D82: BANHO 2 | E82: Porcelanato | I82: 1 | J82: =G82*I82 -> 0
B83: TÉRREO | C83: APTO4 | D83: SUÍTE 1 | E83: Piso madeira engenheirada | I83: 1 | J83: =G83*I83 -> 0
... B88: TÉRREO | C88: A.C. | D88: HALL | E88: Porcelanato | I88: 1 | J88: =G88*I88 -> 0
B89: TÉRREO | C89: A.C. | D89: PISCINA (PROF. 1,4m) | E89: Piscina | F89: 39.22 | G89: 1.4 | H89: Sim | I89: 1 | J89: =F89*G89 -> 54.908
B90: TÉRREO | C90: A.C. | D90: ÁREA PERMEÁVEL | I90: 1 | J90: =G90*I90 -> 0
B91: TÉRREO | C91: A.C. | D91: HALL ACESSO APTO | E91: Porcelanato | I91: 1 | J91: =G91*I91 -> 0
B92: TÉRREO | C92: APTO1 | D92: ESTAR | E92: Porcelanato | I92: 1 | J92: =G92*I92 -> 0
B93: TÉRREO | C93: APTO1 | D93: JANTAR | E93: Porcelanato | I93: 1 | J93: =G93*I93 -> 0
B94: TÉRREO | C94: APTO1 | D94: LAVABO | E94: Porcelanato | I94: 1 | J94: =G94*I94 -> 0
B95: TÉRREO | C95: APTO1 | D95: DECK | E95: Deck | I95: 1 | J95: =G95*I95 -> 0
B96: TÉRREO | C96: APTO1 | D96: PISCINA (PROF. 1,2m) | E96: Piscina | F96: 14.66 | G96: 1.2 | H96: Sim | I96: 1 | J96: =F96*G96 -> 17.592
B97: TÉRREO | C97: APTO1 | D97: COZINHA | E97: Porcelanato | I97: 1 | J97: =G97*I97 -> 0
B98: TÉRREO | C98: APTO1 | D98: A.S. | E98: Porcelanato | I98: 1 | J98: =G98*I98 -> 0
B99: TÉRREO | C99: APTO1 | D99: BANHO SERV. | E99: Porcelanato | I99: 1 | J99: =G99*I99 -> 0
B100: TÉRREO | C100: APTO1 | D100: CIRC. | E100: Porcelanato | I100: 1 | J100: =G100*I100 -> 0
B101: TÉRREO | C101: APTO1 | D101: SUÍTE MASTER | E101: Piso madeira engenheirada | I101: 1 | J101: =G101*I101 -> 0
B102: TÉRREO | C102: APTO1 | D102: BANHO MASTER | E102: Porcelanato | I102: 1 | J102: =G102*I102 -> 0
B103: TÉRREO | C103: APTO1 | D103: SUÍTE 2 | E103: Piso madeira engenheirada | I103: 1 | J103: =G103*I103 -> 0
B104: TÉRREO | C104: APTO1 | D104: BANHO 2 | E104: Porcelanato | I104: 1 | J104: =G104*I104 -> 0
B105: TÉRREO | C105: APTO1 | D105: SUÍTE 1 | E105: Piso madeira engenheirada | I105: 1 | J105: =G105*I105 -> 0
B106: TÉRREO | C106: APTO1 | D106: BANHO 1 | E106: Porcelanato | I106: 1 | J106: =G106*I106 -> 0
B107: TÉRREO | C107: APTO4 | D107: ESTAR | E107: Porcelanato | I107: 1 | J107: =G107*I107 -> 0
B108: TÉRREO | C108: APTO4 | D108: JANTAR | E108: Porcelanato | I108: 1 | J108: =G108*I108 -> 0
... B110: TÉRREO | C110: APTO4 | D110: DECK | E110: Deck | I110: 1 | J110: =G110*I110 -> 0
B111: TÉRREO | C111: APTO4 | D111: PISCINA (PROF. 1,2m) | E111: Piscina | F111: 12.63 | G111: 1.2 | H111: Sim | I111: 1 | J111: =F111*G111 -> 15.156
B112: TÉRREO | C112: APTO4 | D112: COZINHA | E112: Porcelanato | I112: 1 | J112: =G112*I112 -> 0
B113: TÉRREO | C113: APTO4 | D113: A.S. | E113: Porcelanato | I113: 1 | J113: =G113*I113 -> 0
...

Sheet REVESTIMENTO TETO
A1: Obra
A2: Empresa
A3: Revisão
A4: Data
A5: LEVANTAMENTO QUANTITATIVO
A7: REVESTIMENTOS E ACABAMENTOS DE PISO
B9: LEVANTAMENTO DE PROJETO
B10: Pavimento | C10: Apto / A.C. | D10: Ambiente | E10: Material | F10: Área (m²) | G10: Forro (Sim/Não) | H10: Repetição | I10: Total
B11: 1SS | C11: A.C. | D11: ÁREA TÉCNICA | F11: 456.33 | H11: 1 | I11: =F11*H11 -> 456.33
B12: 1SS | C12: A.C. | D12: ÁREA PERMEÁVEL | F12: 26.38 | H12: 1 | I12: =F12*H12 -> 26.38
B13: 1SS | C13: A.C. | D13: HALL | F13: 33.58 | G13: Sim | H13: 1 | I13: =F13*H13 -> 33.58
B14: 1SS | C14: A.C. | D14: ESTACIONAMENTO | F14: 1500.84 | H14: 1 | I14: =F14*H14 -> 1500.84
B15: TÉRREO | C15: APTO1 | D15: ESTAR | F15: 24.87 | G15: Sim | H15: 1 | I15: =F15*H15 -> 24.87
B16: TÉRREO | C16: APTO1 | D16: JANTAR | F16: 28.27 | G16: Sim | H16: 1 | I16: =F16*H16 -> 28.27
B17: TÉRREO | C17: APTO1 | D17: LAVABO | F17: 3.4 | G17: Sim | H17: 1 | I17: =F17*H17 -> 3.4
B18: TÉRREO | C18: APTO1 | D18: DECK | F18: 27.53 | H18: 1 | I18: =F18*H18 -> 27.53
B19: TÉRREO | C19: APTO1 | D19: PISCINA (PROF. 1,2m) | F19: 21.52 | G19: Sim | H19: 1 | I19: =F19*H19 -> 21.52
B20: TÉRREO | C20: APTO1 | D20: COZINHA | F20: 15.72 | G20: Sim | H20: 1 | I20: =F20*H20 -> 15.72
B21: TÉRREO | C21: APTO1 | D21: A.S. | F21: 7.6 | G21: Sim | H21: 1 | I21: =F21*H21 -> 7.6
B22: TÉRREO | C22: APTO1 | D22: BANHO SERV. | F22: 4.22 | G22: Sim | H22: 1 | I22: =F22*H22 -> 4.22
B23: TÉRREO | C23: APTO1 | D23: CIRC. | F23: 12.36 | G23: Sim | H23: 1 | I23: =F23*H23 -> 12.36
B24: TÉRREO | C24: APTO1 | D24: SUÍTE MASTER | F24: 27.24 | G24: Sim | H24: 1 | I24: =F24*H24 -> 27.24
B25: TÉRREO | C25: APTO1 | D25: BANHO MASTER | F25: 7.54 | G25: Sim | H25: 1 | I25: =F25*H25 -> 7.54
B26: TÉRREO | C26: APTO1 | D26: SUÍTE 2 | F26: 18.87 | G26: Sim | H26: 1 | I26: =F26*H26 -> 18.87
B27: TÉRREO | C27: APTO1 | D27: BANHO 2 | F27: 4.85 | G27: Sim | H27: 1 | I27: =F27*H27 -> 4.85
B28: TÉRREO | C28: APTO1 | D28: SUÍTE 1 | F28: 18.87 | G28: Sim | H28: 1 | I28: =F28*H28 -> 18.87
B29: TÉRREO | C29: APTO1 | D29: BANHO 1 | F29: 4.85 | G29: Sim | H29: 1 | I29: =F29*H29 -> 4.85
B30: TÉRREO | C30: A.C. | D30: (ÁREA TÉCNICA) ESCADA EMERG. | F30: 18.79 | H30: 1 | I30: =F30*H30 -> 18.79
B31: TÉRREO | C31: APTO2 | D31: ESTAR | F31: 26.95 | G31: Sim | H31: 1 | I31: =F31*H31 -> 26.95
B32: TÉRREO | C32: APTO2 | D32: JANTAR | F32: 41.59 | G32: Sim | H32: 1 | I32: =F32*H32 -> 41.59
B33: TÉRREO | C33: APTO2 | D33: LAVABO | F33: 3.67 | G33: Sim | H33: 1 | I33: =F33*H33 -> 3.67
B34: TÉRREO | C34: APTO2 | D34: DECK | F34: 32.26 | H34: 1 | I34: =F34*H34 -> 32.26
B35: TÉRREO | C35: APTO2 | D35: PISCINA (PROF. 1,2m) | F35: 21.56 | G35: Sim | H35: 1 | I35: =F35*H35 -> 21.56
B36: TÉRREO | C36: APTO2 | D36: COZINHA | F36: 15.02 | G36: Sim | H36: 1 | I36: =F36*H36 -> 15.02
B37: TÉRREO | C37: APTO2 | D37: DESPENSA | F37: 3.12 | G37: Sim | H37: 1 | I37: =F37*H37 -> 3.12
B38: TÉRREO | C38: APTO2 | D38: A.S. | F38: 9.49 | G38: Sim | H38: 1 | I38: =F38*H38 -> 9.49
B39: TÉRREO | C39: APTO2 | D39: DORM. SERV. | F39: 6.96 | G39: Sim | H39: 1 | I39: =F39*H39 -> 6.96
B40: TÉRREO | C40: APTO2 | D40: BANHO SERV. | F40: 4.09 | G40: Sim | H40: 1 | I40: =F40*H40 -> 4.09
B41: TÉRREO | C41: APTO2 | D41: CIRC. | F41: 14.97 | G41: Sim | H41: 1 | I41: =F41*H41 -> 14.97
B42: TÉRREO | C42: APTO2 | D42: SUÍTE MASTER | F42: 28.46 | G42: Sim | H42: 1 | I42: =F42*H42 -> 28.46
B43: TÉRREO | C43: APTO2 | D43: BANHO MASTER | F43: 7.06 | G43: Sim | H43: 1 | I43: =F43*H43 -> 7.06
B44: TÉRREO | C44: APTO2 | D44: SUÍTE 3 | F44: 18.87 | G44: Sim | H44: 1 | I44: =F44*H44 -> 18.87
B45: TÉRREO | C45: APTO2 | D45: BANHO 3 | F45: 4.85 | G45: Sim | H45: 1 | I45: =F45*H45 -> 4.85
B46: TÉRREO | C46: APTO2 | D46: SUÍTE 2 | F46: 18.85 | G46: Sim | H46: 1 | I46: =F46*H46 -> 18.85
... B52: TÉRREO | C52: APTO3 | D52: LAVABO | F52: 3.4 | G52: Sim | H52: 1 | I52: =F52*H52 -> 3.4
B53: TÉRREO | C53: APTO3 | D53: DECK | F53: 28.39 | H53: 1 | I53: =F53*H53 -> 28.39
B54: TÉRREO | C54: APTO3 | D54: PISCINA (PROF. 1,2m) | F54: 21.53 | G54: Sim | H54: 1 | I54: =F54*H54 -> 21.53
B55: TÉRREO | C55: APTO3 | D55: COZINHA | F55: 15.72 | G55: Sim | H55: 1 | I55: =F55*H55 -> 15.72
B56: TÉRREO | C56: APTO3 | D56: A.S. | F56: 7.59 | G56: Sim | H56: 1 | I56: =F56*H56 -> 7.59
B57: TÉRREO | C57: APTO3 | D57: BANHO SERV. | F57: 4.22 | G57: Sim | H57: 1 | I57: =F57*H57 -> 4.22
B58: TÉRREO | C58: APTO3 | D58: CIRC. | F58: 12.36 | G58: Sim | H58: 1 | I58: =F58*H58 -> 12.36
B59: TÉRREO | C59: APTO3 | D59: SUÍTE MASTER | F59: 27.24 | G59: Sim | H59: 1 | I59: =F59*H59 -> 27.24
B60: TÉRREO | C60: APTO3 | D60: BANHO MASTER | F60: 7.54 | G60: Sim | H60: 1 | I60: =F60*H60 -> 7.54
B61: TÉRREO | C61: APTO3 | D61: SUÍTE 2 | F61: 18.87 | G61: Sim | H61: 1 | I61: =F61*H61 -> 18.87
B62: TÉRREO | C62: APTO3 | D62: BANHO 2 | F62: 4.85 | G62: Sim | H62: 1 | I62: =F62*H62 -> 4.85
B63: TÉRREO | C63: APTO3 | D63: SUÍTE 1 | F63: 18.87 | G63: Sim | H63: 1 | I63: =F63*H63 -> 18.87
B64: TÉRREO | C64: APTO3 | D64: BANHO 1 | F64: 4.85 | G64: Sim | H64: 1 | I64: =F64*H64 -> 4.85
B65: TÉRREO | C65: APTO4 | D65: ESTAR | F65: 27.02 | G65: Sim | H65: 1 | I65: =F65*H65 -> 27.02
... B67: TÉRREO | C67: APTO4 | D67: LAVABO | F67: 3.77 | G67: Sim | H67: 1 | I67: =F67*H67 -> 3.77
B68: TÉRREO | C68: APTO4 | D68: DECK | F68: 32.3 | H68: 1 | I68: =F68*H68 -> 32.3
B69: TÉRREO | C69: APTO4 | D69: PISCINA (PROF. 1,2m) | F69: 23.17 | G69: Sim | H69: 1 | I69: =F69*H69 -> 23.17
B70: TÉRREO | C70: APTO4 | D70: COZINHA | F70: 15.19 | G70: Sim | H70: 1 | I70: =F70*H70 -> 15.19
B71: TÉRREO | C71: APTO4 | D71: A.S. | F71: 9.49 | G71: Sim | H71: 1 | I71: =F71*H71 -> 9.49
B72: TÉRREO | C72: APTO4 | D72: DORM. SERV. | F72: 6.96 | G72: Sim | H72: 1 | I72: =F72*H72 -> 6.96
B73: TÉRREO | C73: APTO4 | D73: BANHO SERV. | F73: 4.09 | G73: Sim | H73: 1 | I73: =F73*H73 -> 4.09
B74: TÉRREO | C74: APTO4 | D74: CIRC. | F74: 14.99 | G74: Sim | H74: 1 | I74: =F74*H74 -> 14.99
B75: TÉRREO | C75: APTO4 | D75: SUÍTE MASTER | F75: 28.46 | G75: Sim | H75: 1 | I75: =F75*H75 -> 28.46
B76: TÉRREO | C76: APTO4 | D76: BANHO MASTER | F76: 7.06 | G76: Sim | H76: 1 | I76: =F76*H76 -> 7.06
B77: TÉRREO | C77: APTO4 | D77: SUÍTE 3 | F77: 18.87 | G77: Sim | H77: 1 | I77: =F77*H77 -> 18.87
B78: TÉRREO | C78: APTO4 | D78: BANHO 3 | F78: 4.85 | G78: Sim | H78: 1 | I78: =F78*H78 -> 4.85
B79: TÉRREO | C79: APTO4 | D79: SUÍTE 2 | F79: 18.85 | G79: Sim | H79: 1 | I79: =F79*H79 -> 18.85
B80: TÉRREO | C80: APTO4 | D80: BANHO 2 | F80: 4.85 | G80: Sim | H80: 1 | I80: =F80*H80 -> 4.85
... B82: TÉRREO | C82: APTO4 | D82: BANHO 1 | F82: 4.85 | G82: Sim | H82: 1 | I82: =F82*H82 -> 4.85
B83: TÉRREO | C83: A.C. | D83: ESTACIONAMENTO | F83: 1083.61 | H83: 1 | I83: =F83*H83 -> 1083.61
B84: TÉRREO | C84: A.C. | D84: ÁREA TÉCNICA / ESCADA | F84: 26.49 | H84: 1 | I84: =F84*H84 -> 26.49
B85: TÉRREO | C85: A.C. | D85: DEPÓSITO | F85: 8.01 | H85: 1 | I85: =F85*H85 -> 8.01
B86: TÉRREO | C86: A.C. | D86: HALL | F86: 34.34 | G86: Sim | H86: 1 | I86: =F86*H86 -> 34.34
B87: TÉRREO | C87: A.C. | D87: PISCINA (PROF. 1,2m) | F87: 65.86 | H87: 1 | I87: =F87*H87 -> 65.86
B88: TÉRREO | C88: A.C. | D88: ÁREA PERMEÁVEL | F88: 8.99 | H88: 1 | I88: =F88*H88 -> 8.99
B89: TÉRREO | C89: A.C. | D89: HALL ACESSO APTO | F89: 24.93 | G89: Sim | H89: 1 | I89: =F89*H89 -> 24.93
B90: TÉRREO | C90: APTO1 | D90: ESTAR | F90: 24.98 | G90: Sim | H90: 1 | I90: =F90*H90 -> 24.98
B91: TÉRREO | C91: APTO1 | D91: JANTAR | F91: 25.92 | G91: Sim | H91: 1 | I91: =F91*H91 -> 25.92
B92: TÉRREO | C92: APTO1 | D92: LAVABO | F92: 2.86 | G92: Sim | H92: 1 | I92: =F92*H92 -> 2.86
B93: TÉRREO | C93: APTO1 | D93: DECK | F93: 29.26 | H93: 1 | I93: =F93*H93 -> 29.26
B94: TÉRREO | C94: APTO1 | D94: PISCINA (PROF. 1,2m) | F94: 22.93 | G94: Sim | H94: 1 | I94: =F94*H94 -> 22.93
B95: TÉRREO | C95: APTO1 | D95: COZINHA | F95: 16.3 | G95: Sim | H95: 1 | I95: =F95*H95 -> 16.3
B96: TÉRREO | C96: APTO1 | D96: A.S. | F96: 4.31 | G96: Sim | H96: 1 | I96: =F96*H96 -> 4.31
B97: TÉRREO | C97: APTO1 | D97: BANHO SERV. | F97: 5.28 | G97: Sim | H97: 1 | I97: =F97*H97 -> 5.28
B98: TÉRREO | C98: APTO1 | D98: CIRC. | F98: 10.66 | G98: Sim | H98: 1 | I98: =F98*H98 -> 10.66
B99: TÉRREO | C99: APTO1 | D99: SUÍTE MASTER | F99: 19.49 | G99: Sim | H99: 1 | I99: =F99*H99 -> 19.49
B100: TÉRREO | C100: APTO1 | D100: BANHO MASTER | F100: 7.37 | G100: Sim | H100: 1 | I100: =F100*H100 -> 7.37
B101: TÉRREO | C101: APTO1 | D101: SUÍTE 2 | F101: 18.7 | G101: Sim | H101: 1 | I101: =F101*H101 -> 18.7
B102: TÉRREO | C102: APTO1 | D102: BANHO 2 | F102: 4.76 | G102: Sim | H102: 1 | I102: =F102*H102 -> 4.76
B103: TÉRREO | C103: APTO1 | D103: SUÍTE 1 | F103: 18.71 | G103: Sim | H103: 1 | I103: =F103*H103 -> 18.71
B104: TÉRREO | C104: APTO1 | D104: BANHO 1 | F104: 4.78 | G104: Sim | H104: 1 | I104: =F104*H104 -> 4.78
B105: TÉRREO | C105: APTO4 | D105: ESTAR | F105: 21.3 | G105: Sim | H105: 1 | I105: =F105*H105 -> 21.3
... B107: TÉRREO | C107: APTO4 | D107: LAVABO | F107: 3.5 | G107: Sim | H107: 1 | I107: =F107*H107 -> 3.5
B108: TÉRREO | C108: APTO4 | D108: DECK | F108: 37.4 | H108: 1 | I108: =F108*H108 -> 37.4
B109: TÉRREO | C109: APTO4 | D109: PISCINA (PROF. 1,2m) | F109: 19.48 | G109: Sim | H109: 1 | I109: =F109*H109 -> 19.48
B110: TÉRREO | C110: APTO4 | D110: COZINHA | F110: 13.44 | G110: Sim | H110: 1 | I110: =F110*H110 -> 13.44
...

Sheet Acabamentos de Piso
A2: ORÇAMENTO PARAMÉTRICO GERENCIAMENTO EXECUTIVO
A7: Cliente | B7: =DADOS_INICIAIS!B2 -> BLUE HEAVEN
A8: Obra | B8: =DADOS_INICIAIS!B1 -> MONOLYT
A9: Data | B9: 45441
A10: Revisão | B10: R00
A12: REVESTIMENTOS INTERNOS EM PISO
A14: Descrição | B14: Quantidade | D14: Parâmetro | F14: Referência | G14: Valor total
A15: Piso de concreto alisado | B15: ='Pintura Interna'!$B$15 -> 2584.45 | C15: m² | D15: 28 | E15: R$ / m² | F15: Média | G15: =D15*B15*1.1 -> 79601.06
A16: Piso de concreto alisado ranhurado | B16: ='Pintura Interna'!$B$16 -> 626.89 | C16: m² | D16: 30 | E16: R$ / m² | F16: Média | G16: =D16*B16*1.1 -> 20687.37
A17: Contrapiso | B17: ='REVESTIMENTO PISO'!L11 -> 9592.09 | C17: m² | D17: =B17/DADOS_INICIAIS!$E$11 -> 0.65281534 | E17: m² / AC | F17: Média | G17: =+B17*65*1.1 -> 685834.44
A18: Manta acústica + tela | B18: ='REVESTIMENTO PISO'!L12 -> 5559.67 | C18: m² | D18: =B18/DADOS_INICIAIS!$E$11 -> 0.37837821 | E18: m² / AC | F18: Média | G18: =+B18*25*1.1 -> 152890.93
A19: Piso Elevador | B19: =6*1.83*1.95 -> 21.411 | C19: m² | D19: 562.9458 | E19: m² / AC | F19: Média | G19: =+B19*D19*1.1*0 -> 0 | H19: Considerar no preliminar
A20: Porcelanato | B20: =SUMIF('REVESTIMENTO PISO'!E:E,'Acabamentos de Piso'!A20,'REVESTIMENTO PISO'!I:I) -> 0 | C20: m² | D20: 130 | E20: R$ / m² | F20: Média | G20: =+D20*B20*1.1 -> 0
A21: Piso vinilico | B21: =SUMIF('REVESTIMENTO PISO'!E:E,'Acabamentos de Piso'!A21,'REVESTIMENTO PISO'!I:I) -> 77.76 | C21: m² | D21: 250 | E21: R$ / m² | F21: Média | G21: =+D21*B21*1.1 -> 21384
A22: Piso madeira engenheirada | B22: =SUMIF('REVESTIMENTO PISO'!E:E,'Acabamentos de Piso'!A22,'REVESTIMENTO PISO'!I:I) -> 2122.95 | C22: m² | D22: =392.8+45 -> 437.8 | E22: R$ / m² | F22: Média | G22: =+D22*B22*1.1 -> 1022370.3
A23: Piso especial | B23: =SUMIF('REVESTIMENTO PISO'!E:E,'Acabamentos de Piso'!A23,'REVESTIMENTO PISO'!I:I) -> 965.36 | C23: m² | D23: 210 | E23: R$ / m² | F23: Média | G23: =+D23*B23*1.1 -> 222998.16 | H23: Pedra rústica em cacos
A24: Deck | B24: =SUMIF('REVESTIMENTO PISO'!E:E,'Acabamentos de Piso'!A24,'REVESTIMENTO PISO'!I:I) -> 1341.17 | C24: m² | D24: 300 | E24: R$ / m² | F24: Média | G24: =+D24*B24*1.1 -> 442586.1
A25: Piscina | B25: =SUMIF('REVESTIMENTO PISO'!E:E,'Acabamentos de Piso'!A25,'REVESTIMENTO PISO'!I:I) -> 830.41 | C25: m² | D25: =D23 -> 210 | E25: R$ / m² | F25: Média | G25: =+D25*B25*1.1 -> 191824.71 | H25: =H23 -> Pedra rústica em cacos
A26: Emborrachado | B26: =SUMIF('REVESTIMENTO PISO'!E:E,'Acabamentos de Piso'!A26,'REVESTIMENTO PISO'!I:I) -> 35.17 | C26: m² | D26: 230 | E26: R$ / m² | F26: Média | G26: =+D26*B26*1.1 -> 8898.01
A27: Paver fulget | B27: =SUMIF('REVESTIMENTO PISO'!E:E,'Acabamentos de Piso'!A27,'REVESTIMENTO PISO'!I:I) -> 171.49 | C27: m² | D27: 135 | E27: R$ / m² | F27: Média | G27: =+D27*B27*1.1 -> 25466.265 | H27: CALÇADA
A28: Rodapés Invertidos | B28: 1 | C28: vb | D28: =ROUNDUP(D49,0) -> 38 | E28: R$ / AC | F28: Média | G28: =D28*DADOS_INICIAIS!$E$11*1.1 -> 614184.96
A29: Soleiras e peitoris | B29: 1 | C29: vb | D29: 20 | E29: R$ / AC | F29: Média | G29: =D29*DADOS_INICIAIS!$E$11*1.1 -> 323255.24
G30: =SUM(G15:G29) -> 3811981.5
A33: TOTAL REVESTIMENTOS | G33: =SUM(G15:G18) -> 939013.79 | H33: =G33/DADOS_INICIAIS!$E$11 -> 63.907095
A34: TOTAL ACABAMENTOS | G34: =SUM(G20:G29) -> 2872967.7 | H34: =G34/DADOS_INICIAIS!$E$11 -> 195.5275 | I34: =G34+'Rev. Internos de Parede'!G24 -> 4311125.5
A35: TOTAL | G35: =G30 -> 3811981.5 | H35: =G35/DADOS_INICIAIS!$E$11 -> 259.4346
A40: ÍNDICE RODAPÉ INVERTIDO - BRAVA (CN)
D47: =1560.11+160.54+518.7871 -> 2239.4371
D48: =(224.88+487.65+266.03+43.04)*82.84 -> 84629.344
D49: =D48/D47 -> 37.790454 | E49: =D49*DADOS_INICIAIS!E11 -> 555271.01

Sheet Rev. Internos de Parede
A2: ORÇAMENTO PARAMÉTRICO GERENCIAMENTO EXECUTIVO
O5: =(Alvenaria!B15+Alvenaria!B16)*2 -> 25844.007
O6: =B16+B17+FACHADA!I11+FACHADA!I12+FACHADA!I13 -> 31215.194
A7: Cliente | B7: =DADOS_INICIAIS!B2 -> BLUE HEAVEN
A8: Obra | B8: =DADOS_INICIAIS!B1 -> MONOLYT
A9: Data
A10: Revisão | B10: R00
A12: REVESTIMENTOS INTERNOS EM PAREDE
A14: Descrição | B14: Quantidade | D14: Parâmetro | F14: Referência | G14: Valor total
A15: Chapisco | B15: =DADOS_INICIAIS!E11*'Rev. Internos de Parede'!D15 -> 12280.935 | C15: m² | D15: =2.1*Alvenaria!$J$35 -> 0.83581186 | E15: m² / AC | F15: Média | G15: =+B15*5*1.1 -> 67545.141 | H15: Paredes internas drywall
A16: Reboco | B16: =DADOS_INICIAIS!E11*'Rev. Internos de Parede'!D16 -> 12280.935 | C16: m² | D16: =2.1*Alvenaria!$J$35 -> 0.83581186 | E16: m² / AC | F16: Média | G16: =50*B16*1.1 -> 675451.41 | H16: Paredes internas drywall
A17: Estucamento | B17: =DADOS_INICIAIS!E21+DADOS_INICIAIS!F21 -> 3904.14 | C17: APE | D17: =542.84/772 -> 0.70316062 | E17: m² / m² | F17: Média | G17: =B17*D17*24*1.1 -> 72474.27
A18: Piscina | B18: =SUMIF('REVESTIMENTO PAREDE PISCINA'!E:E,A18,'REVESTIMENTO PAREDE PISCINA'!J:J) -> 677.348 | C18: m² | D18: 210 | E18: R$ / m² | F18: Média | G18: =+D18*B18*1.1 -> 156467.39 | H18: Pedra rústica em cacos
A19: Revestimentos de Parede | B19: 1 | C19: vb | D19: =D43 -> 79.298972 | E19: R$ / AC | F19: Média | G19: =D19*DADOS_INICIAIS!$E$11*1.1 -> 1281690.4
A20: TOTAL | G20: =SUM(G15:G19) -> 2253628.6
A23: TOTAL REVESTIMENTOS | G23: =SUM(G15:G17) -> 815470.82 | H23: =G23/DADOS_INICIAIS!$E$11 -> 55.499048
A24: TOTAL ACABAMENTOS | G24: =SUM(G18:G19) -> 1438157.8 | H24: =G24/DADOS_INICIAIS!$E$11 -> 97.877676
A25: TOTAL | G25: =G20 -> 2253628.6 | H25: =G25/DADOS_INICIAIS!E11 -> 153.37672
B30: LIVE - LUMIS | J30: LIVE - LUMIS (MUDANDO CUSTO REVESTIMENTO P/ PORCELANATO)
B31: Quant. | C31: Valor total | J31: Quant. | L31: Valor total
A32: Revest | B32: =3856.77 -> 3856.77 | C32: 216873.88 | E32: MO CHAPISCO/REBOCO JUNTO | I32: Revest | J32: =3856.77 -> 3856.77 | K32: 175 | L32: =J32*K32 -> 674934.75
A33: Revest | B33: 28.9 | C33: 440.95 | E33: =280859.09+2140564.22-437026.95-(31147.02*40) -> 738515.56 | I33: Revest | J33: 28.9 | K33: 175 | L33: =J33*K33 -> 5057.5
A34: Revest | B34: 49 | C34: 32181 | E34: 14888.46 | F34: AC | I34: Revest | J34: 49 | K34: 559.25 | L34: =J34*K34 -> 27403.25
A35: Revest | B35: =SUM(B32:B34) -> 3934.67 | C35: 327403.25 | E35: =E33/E34 -> 49.60322 | G35: 228 | I35: Revest | J35: =SUM(J32:J34) -> 3934.67 | L35: 327403.25
A36: Revest | C36: =2410564.22-(31147.02*50) -> 853213.22 | I36: Revest | L36: =2410564.22-(31147.02*50) -> 853213.22
A37: MO Revest | B37: =SUM(B32:B36) -> 7869.34 | C37: =SUM(C32:C36) -> 1430112.3 | I37: MO Revest | J37: =SUM(J32:J36) -> 7869.34 | L37: =SUM(L32:L36) -> 1888012
A38: Banheiros | B38: 175 | C38: 175 | I38: Banheiros | J38: 175 | L38: 175
B39: =B37/B38 -> 44.967657 | C39: =C37/C38 -> 8172.0703 | J39: =J37/J38 -> 44.967657 | L39: =L37/L38 -> 10788.64
B42: 108 | C42: 108
B43: =B42*B39 -> 4856.507 | C43: =C42*L39 -> 1165173.1 | D43: =C43/DADOS_INICIAIS!E11 -> 79.298972

Sheet Acabamentos de Teto
A2: ORÇAMENTO PARAMÉTRICO GERENCIAMENTO EXECUTIVO
A7: Cliente | B7: =DADOS_INICIAIS!B2 -> BLUE HEAVEN
A8: Obra | B8: =DADOS_INICIAIS!B1 -> MONOLYT
A9: Data
A10: Revisão | B10: R00
A12: ACABAMENTOS DE TETO
A14: Descrição | B14: Quantidade | D14: Parâmetro | F14: Referência | G14: Valor total
A15: Forro de gesso acartonado | B15: =D15*DADOS_INICIAIS!$E$11 -> 8816.052 | C15: m² | D15: 0.6 | E15: m² / AC | F15: Média | G15: =+B15*140*1.1 -> 1357672 | H15: Alterado índice COTAÇÃO SOMAUMA CONSIDERANDO A MAIS... SANCA E CHAPA RU
A16: Negativo | B16: =B15*1.2 -> 10579.262 | C16: m | D16: =B16/DADOS_INICIAIS!E11 -> 0.72 | E16: m / AC | F16: Média | G16: =+B16*25*1.1 -> 290929.72
A17: Estucamento | B17: =D17*DADOS_INICIAIS!$E$11 -> 4408.026 | C17: m² | D17: 0.3 | E17: m² / AC | F17: Média | G17: =B17*24*1.1 -> 116371.89 | H17: Não estava considerando garagem - Confirmar se devemos considerar
A18: TOTAL | G18: =SUM(G15:G17) -> 1764973.6
A21: TOTAL TETO | G21: =G18 -> 1764973.6 | H21: =G21/DADOS_INICIAIS!E11 -> 120.12

Sheet Ambientes
A1: Obra
A2: Empresa
A3: Revisão
A4: Data
A5: LEVANTAMENTO QUANTITATIVO
A7: AMBIENTES
B9: LEVANTAMENTO DE PROJETO | I9: Ar cond.
B10: Pavimento | C10: Apto / A.C. | D10: Ambiente | E10: Infra Ar Cond. | F10: Aparelho Ar cond. | G10: Enclausurado | I10: Descrição | J10: Quant. total
B11: 1SS | C11: A.C. | D11: ÁREA TÉCNICA | I11: Infra | J11: =COUNTIF(E:E,"Sim") -> 132
B12: 1SS | C12: A.C. | D12: ÁREA PERMEÁVEL | I12: Aparelho | J12: =COUNTIF(F:F,"Sim") -> 12
B13: 1SS | C13: A.C. | D13: HALL
B14: 1SS | C14: A.C. | D14: ESTACIONAMENTO
B15: TÉRREO | C15: APTO1 | D15: ESTAR | E15: Sim | I15: Material | J15: Área total
A16: =IF(C15="*&APTO&*","OK","") | B16: TÉRREO | C16: APTO1 | D16: JANTAR | J16: =SUMIF(E:E,I16,G:G) -> 0
B17: TÉRREO | C17: APTO1 | D17: LAVABO | G17: Sim | J17: =SUMIF(E:E,I17,G:G) -> 0
B18: TÉRREO | C18: APTO1 | D18: DECK | J18: =SUMIF(E:E,I18,G:G) -> 0
B19: TÉRREO | C19: APTO1 | D19: PISCINA (PROF. 1,2m) | J19: =SUMIF(E:E,I19,G:G) -> 0
B20: TÉRREO | C20: APTO1 | D20: COZINHA | J20: =SUMIF(E:E,I20,G:G) -> 0
B21: TÉRREO | C21: APTO1 | D21: A.S. | J21: =SUMIF(E:E,I21,G:G) -> 0
B22: TÉRREO | C22: APTO1 | D22: BANHO SERV. | G22: Sim | J22: =SUMIF(E:E,I22,G:G) -> 0
B23: TÉRREO | C23: APTO1 | D23: CIRC. | J23: =SUMIF(E:E,I23,G:G) -> 0
B24: TÉRREO | C24: APTO1 | D24: SUÍTE MASTER | E24: Sim | J24: =SUMIF(E:E,I24,G:G) -> 0
B25: TÉRREO | C25: APTO1 | D25: BANHO MASTER | G25: Sim | J25: =SUMIF(E:E,I25,G:G) -> 0
B26: TÉRREO | C26: APTO1 | D26: SUÍTE 2 | E26: Sim | J26: =SUMIF(E:E,I26,G:G) -> 0
B27: TÉRREO | C27: APTO1 | D27: BANHO 2 | G27: Sim | J27: =SUMIF(E:E,I27,G:G) -> 0
B28: TÉRREO | C28: APTO1 | D28: SUÍTE 1 | E28: Sim | J28: =SUMIF(E:E,I28,G:G) -> 0
B29: TÉRREO | C29: APTO1 | D29: BANHO 1 | G29: Sim | J29: =SUMIF(E:E,I29,G:G) -> 0
B30: TÉRREO | C30: A.C. | D30: (ÁREA TÉCNICA) ESCADA EMERG. | J30: =SUMIF(E:E,I30,G:G) -> 0
B31: TÉRREO | C31: APTO2 | D31: ESTAR | E31: Sim | J31: =SUMIF(E:E,I31,G:G) -> 0
B32: TÉRREO | C32: APTO2 | D32: JANTAR | J32: =SUMIF(E:E,I32,G:G) -> 0
B33: TÉRREO | C33: APTO2 | D33: LAVABO | G33: Sim | J33: =SUMIF(E:E,I33,G:G) -> 0
B34: TÉRREO | C34: APTO2 | D34: DECK
B35: TÉRREO | C35: APTO2 | D35: PISCINA (PROF. 1,2m)
B36: TÉRREO | C36: APTO2 | D36: COZINHA
B37: TÉRREO | C37: APTO2 | D37: DESPENSA
B38: TÉRREO | C38: APTO2 | D38: A.S.
B39: TÉRREO | C39: APTO2 | D39: DORM. SERV. | E39: Sim
B40: TÉRREO | C40: APTO2 | D40: BANHO SERV. | G40: Sim
B41: TÉRREO | C41: APTO2 | D41: CIRC.
B42: TÉRREO | C42: APTO2 | D42: SUÍTE MASTER | E42: Sim
B43: TÉRREO | C43: APTO2 | D43: BANHO MASTER | G43: Sim
B44: TÉRREO | C44: APTO2 | D44: SUÍTE 3 | E44: Sim
B45: TÉRREO | C45: APTO2 | D45: BANHO 3 | G45: Sim
B46: TÉRREO | C46: APTO2 | D46: SUÍTE 2 | E46: Sim
B47: TÉRREO | C47: APTO2 | D47: BANHO 2 | G47: Sim
B48: TÉRREO | C48: APTO2 | D48: SUÍTE 1 | E48: Sim
B49: TÉRREO | C49: APTO2 | D49: BANHO 1 | G49: Sim
B50: TÉRREO | C50: APTO3 | D50: ESTAR | E50: Sim
B51: TÉRREO | C51: APTO3 | D51: JANTAR
B52: TÉRREO | C52: APTO3 | D52: LAVABO | G52: Sim
B53: TÉRREO | C53: APTO3 | D53: DECK
B54: TÉRREO | C54: APTO3 | D54: PISCINA (PROF. 1,2m)
B55: TÉRREO | C55: APTO3 | D55: COZINHA
B56: TÉRREO | C56: APTO3 | D56: A.S.
B57: TÉRREO | C57: APTO3 | D57: BANHO SERV. | G57: Sim
B58: TÉRREO | C58: APTO3 | D58: CIRC.
B59: TÉRREO | C59: APTO3 | D59: SUÍTE MASTER | E59: Sim
B60: TÉRREO | C60: APTO3 | D60: BANHO MASTER | G60: Sim
B61: TÉRREO | C61: APTO3 | D61: SUÍTE 2 | E61: Sim
B62: TÉRREO | C62: APTO3 | D62: BANHO 2 | G62: Sim
B63: TÉRREO | C63: APTO3 | D63: SUÍTE 1 | E63: Sim
B64: TÉRREO | C64: APTO3 | D64: BANHO 1 | G64: Sim
B65: TÉRREO | C65: APTO4 | D65: ESTAR | E65: Sim
B66: TÉRREO | C66: APTO4 | D66: JANTAR
B67: TÉRREO | C67: APTO4 | D67: LAVABO | G67: Sim
B68: TÉRREO | C68: APTO4 | D68: DECK
B69: TÉRREO | C69: APTO4 | D69: PISCINA (PROF. 1,2m)
B70: TÉRREO | C70: APTO4 | D70: COZINHA
B71: TÉRREO | C71: APTO4 | D71: A.S.
B72: TÉRREO | C72: APTO4 | D72: DORM. SERV. | E72: Sim
B73: TÉRREO | C73: APTO4 | D73: BANHO SERV. | G73: Sim
B74: TÉRREO | C74: APTO4 | D74: CIRC.
B75: TÉRREO | C75: APTO4 | D75: SUÍTE MASTER | E75: Sim
B76: TÉRREO | C76: APTO4 | D76: BANHO MASTER | G76: Sim
B77: TÉRREO | C77: APTO4 | D77: SUÍTE 3 | E77: Sim
B78: TÉRREO | C78: APTO4 | D78: BANHO 3 | G78: Sim
B79: TÉRREO | C79: APTO4 | D79: SUÍTE 2 | E79: Sim
B80: TÉRREO | C80: APTO4 | D80: BANHO 2 | G80: Sim
B81: TÉRREO | C81: APTO4 | D81: SUÍTE 1 | E81: Sim
B82: TÉRREO | C82: APTO4 | D82: BANHO 1 | G82: Sim
B83: TÉRREO | C83: A.C. | D83: ESTACIONAMENTO
B84: TÉRREO | C84: A.C. | D84: ÁREA TÉCNICA / ESCADA
B85: TÉRREO | C85: A.C. | D85: DEPÓSITO
B86: TÉRREO | C86: A.C. | D86: HALL
B87: TÉRREO | C87: A.C. | D87: PISCINA (PROF. 1,2m)
B88: TÉRREO | C88: A.C. | D88: ÁREA PERMEÁVEL
B89: TÉRREO | C89: A.C. | D89: HALL ACESSO APTO | E89: Sim | F89: Sim
B90: TÉRREO | C90: APTO1 | D90: ESTAR | E90: Sim
B91: TÉRREO | C91: APTO1 | D91: JANTAR
B92: TÉRREO | C92: APTO1 | D92: LAVABO | G92: Sim
B93: TÉRREO | C93: APTO1 | D93: DECK
B94: TÉRREO | C94: APTO1 | D94: PISCINA (PROF. 1,2m)
B95: TÉRREO | C95: APTO1 | D95: COZINHA
B96: TÉRREO | C96: APTO1 | D96: A.S.
B97: TÉRREO | C97: APTO1 | D97: BANHO SERV. | G97: Sim
B98: TÉRREO | C98: APTO1 | D98: CIRC.
B99: TÉRREO | C99: APTO1 | D99: SUÍTE MASTER | E99: Sim
B100: TÉRREO | C100: APTO1 | D100: BANHO MASTER | G100: Sim
B101: TÉRREO | C101: APTO1 | D101: SUÍTE 2 | E101: Sim
B102: TÉRREO | C102: APTO1 | D102: BANHO 2 | G102: Sim
...

Sheet Pintura Interna
A2: ORÇAMENTO PARAMÉTRICO GERENCIAMENTO EXECUTIVO
A7: Cliente | B7: =DADOS_INICIAIS!B2 -> BLUE HEAVEN
A8: Obra | B8: =DADOS_INICIAIS!B1 -> MONOLYT
A9: Data | B9: 45441
A10: Revisão | B10: R00
A12: PINTURA INTERNA
A14: Descrição | B14: Quantidade | D14: Parâmetro | F14: Referência | G14: Valor total
A15: Pintura piso epoxi | B15: =SUMIF('REVESTIMENTO PISO'!E:E,'Pintura Interna'!A15,'REVESTIMENTO PISO'!I:I) -> 2584.45 | C15: m2 | D15: 110 | E15: R$ / m² | F15: Média | G15: =+D15*B15*1.1 -> 312718.45
A16: Pintura acrílica antiderrapante | B16: =SUMIF('REVESTIMENTO PISO'!E:E,'Pintura Interna'!A16,'REVESTIMENTO PISO'!I:I) -> 626.89 | C16: m2 | D16: 65 | E16: R$ / m² | F16: Média | G16: =+D16*B16*1.1 -> 44822.635
A17: Textura escadas | B17: 1 | C17: vb | D17: 30 | E17: R$ / AC | F17: Média | G17: =+D17*DADOS_INICIAIS!$E$11*1.1 -> 484882.86
A18: Pintura Interna | B18: 1 | C18: vb | D18: 90 | E18: R$ / AC | F18: Média | G18: =+D18*DADOS_INICIAIS!$E$11*1.1 -> 1454648.6
A19: TOTAL | G19: =SUM(G15:G18) -> 2297072.5
A21: TOTAL PINTURA | G21: =G19 -> 2297072.5 | H21: =G21/DADOS_INICIAIS!E11 -> 156.33341

Sheet Impermeabilização
A2: ORÇAMENTO PARAMÉTRICO GERENCIAMENTO EXECUTIVO
A7: Cliente | B7: =DADOS_INICIAIS!B2 -> BLUE HEAVEN
A8: Obra | B8: =DADOS_INICIAIS!B1 -> MONOLYT
A9: Data
A10: Revisão | B10: R00
A12: IMPERMEABILIZAÇÃO
A14: Descrição | B14: Quantidade | D14: Parâmetro | F14: Referência | G14: Valor total
A15: Regularização de Superfície | B15: =B19+B20 -> 11020.065 | C15: m² | D15: 25 | E15: R$ / m² | F15: Média | G15: =+B15*D15*1.1 -> 303051.79
A16: Poço do elevador | B16: =((1.83*1.95)+((1.83+1.95)*2*1.8))*6 -> 103.059 | C16: m² | D16: 45 | E16: R$ / m² | F16: Média | G16: =+B16*D16*1.1 -> 5101.4205 | H16: Estava 32,94m²
A17: Baldrames | B17: ='INFRAESTRUTURA REV01'!D24 -> 2967.1464 | C17: m² | D17: 30 | E17: R$ / m² | F17: Média | G17: =+B17*D17*1.1 -> 97915.831
A18: Ralos | B18: 1 | C18: vb | D18: 0.4 | E18: R$ / AC | F18: Média | G18: =D18*DADOS_INICIAIS!E11*1.1 -> 6465.1048
A19: Impermeabilizações cimenticias | B19: =D19*DADOS_INICIAIS!$E$11 -> 5877.368 | C19: m² | D19: 0.4 | E19: m² / AC | F19: Média | G19: =+B19*60*1.1 -> 387906.29
A20: Impermeabilizações com aditivo cristalizante | B20: =D20*DADOS_INICIAIS!$E$11 -> 5142.697 | C20: m² | D20: 0.35 | E20: m² / AC | F20: Média | G20: =+B20*28*1.1 -> 158395.07
A21: Impermeabilizações com aditivo cristalizante (telhado verde) | B21: =DADOS_INICIAIS!E20 -> 2661.29 | C21: m² | D21: 28 | E21: R$ / m² | F21: Média | G21: =+B21*D21*1.1 -> 81967.732 | H21: áreas laje descobertas - verdes
A22: Impermeabilizações com aditivo cristalizante (piscinas) | B22: ='Acabamentos de Piso'!B25+'Rev. Internos de Parede'!B18+Complementares!D11 -> 1559.758 | C22: m² | D22: 28 | E22: R$ / m² | F22: Média | G22: =+B22*D22*1.1 -> 48040.546 | H22: SOMAUMA (Argamassa com aditivo cristalizante)
A23: Impermeabilização de peitoril | B23: 1 | C23: vb | D23: 0.8 | E23: R$ / AC | F23: Média | G23: =+D23*DADOS_INICIAIS!E11*1.1 -> 12930.21
A24: Proteção Mecânica | B24: =B20 -> 5142.697 | C24: m² | D24: 28 | E24: R$ / m² | F24: Média | G24: =D24*B24*1.1 -> 158395.07
A25: TOTAL | G25: =SUM(G15:G24) -> 1260169.1
A28: TOTAL IMPERMEABILIZAÇÃO | G28: =G25 -> 1260169.1 | H28: =G28/DADOS_INICIAIS!E11 -> 85.764176

Sheet Instalações
A2: INSTALAÇÕES
A4: INSTALAÇÕES ELÉTRICAS
A6: Descrição | B6: Parâmetro | D6: Valor total
A7: Entrada de Energia | B7: 5 | C7: R$ / AC | D7: =B7*DADOS_INICIAIS!$E$11*1.1 -> 80813.81
A8: Eletrodutos e Eletrocalhas | B8: 23 | C8: R$ / AC | D8: =B8*DADOS_INICIAIS!$E$11*1.1 -> 371743.53
A9: Cabos e Fiações | B9: 40 | C9: R$ / AC | D9: =B9*DADOS_INICIAIS!$E$11*1.1 -> 646510.48
A10: Quadros e Disjuntores | B10: 25 | C10: R$ / AC | D10: =B10*DADOS_INICIAIS!$E$11*1.1 -> 404069.05
A11: Acabamentos Elétricos | B11: 30 | C11: R$ / AC | D11: =B11*DADOS_INICIAIS!$E$11*1.1 -> 484882.86
A12: Equipamentos e Iluminação | B12: 20 | C12: R$ / AC | D12: =B12*DADOS_INICIAIS!$E$11*1.1 -> 323255.24
A13: Mão de Obra para Instalações Elétricas | B13: 60 | C13: R$ / AC | D13: =B13*DADOS_INICIAIS!$E$11*1.1 -> 969765.72
A14: TOTAL | D14: =SUM(D7:D13) -> 3281040.7
A16: INSTALAÇÕES HIDROSSANITÁRIAS
A18: Descrição | B18: Parâmetro | D18: Valor total
A19: Instalações de Água Fria | B19: 25 | C19: R$ / AC | D19: =B19*DADOS_INICIAIS!$E$11*1.1 -> 404069.05
A20: Instalações de Água Quente | B20: 20 | C20: R$ / AC | D20: =B20*DADOS_INICIAIS!$E$11*1.1 -> 323255.24
A21: Instalações de Águas Pluviais | B21: 10 | C21: R$ / AC | D21: =B21*DADOS_INICIAIS!$E$11*1.1 -> 161627.62
A22: Instalações Sanitárias | B22: 15 | C22: R$ / AC | D22: =B22*DADOS_INICIAIS!$E$11*1.1 -> 242441.43
A23: Louças e Metais | B23: 15 | C23: R$ / AC | D23: =B23*DADOS_INICIAIS!$E$11*1.1 -> 242441.43
A24: Mão de Obra para Instalações Hidráulicas | B24: 55 | C24: R$ / AC | D24: =B24*DADOS_INICIAIS!$E$11*1.1 -> 888951.91
A25: TOTAL | D25: =SUM(D19:D24) -> 2262786.7
A27: INSTALAÇÕES PREVENTIVAS E GLP
A29: Descrição | B29: Parâmetro | D29: Valor total
A30: Instalações Preventivas | B30: 18 | C30: R$ / AC | D30: =B30*DADOS_INICIAIS!$E$11*1.1 -> 290929.72
A31: Instalações de GLP | B31: 15 | C31: R$ / AC | D31: =B31*DADOS_INICIAIS!$E$11*1.1 -> 242441.43
A32: Instalações de Proteção e Aterramento - SPDA | B32: 8 | C32: R$ / AC | D32: =B32*DADOS_INICIAIS!$E$11*1.1 -> 129302.1
A33: TOTAL | D33: =SUM(D30:D32) -> 662673.24
A35: TOTAL INSTALAÇÕES | D35: =D14+D25+D33 -> 6206500.6 | E35: =D35/DADOS_INICIAIS!$E$11 -> 422.4

Sheet Instalações Lumis
A1: Obra | B1: LIVE
A2: Empresa | B2: LUMIS
A3: Revisão | B3: R00
A4: ESTIMATIVA DE CUSTOS
A6: Instalações
A8: Área total
D10: Descrição | E10: Térreo
D11: Área (m²) | E11: 14790.93
A13: Sistemas e instalações elétricas
B15: R$/m² | D15: Descrição | E15: Total
B16: 25 | D16: Quadros elétricos e disjuntores | E16: =E$11*$B$16 -> 369773.25
B17: 23 | D17: Eletrodutos e Eletrocalhas | E17: =E11*$B$17 -> 340191.39
B18: 40 | D18: Fios e cabos elétricos | E18: =E11*$B$18 -> 591637.2
B19: 30 | D19: Pontos de tomadas e interruptores | E19: =E11*$B$19 -> 443727.9
B20: 20 | D20: Luminárias, lâmpadas e acessórios | E20: =E11*$B$20 -> 295818.6
D21: total | E21: =SUM(E16:E20) -> 2041148.3
A22: Sistemas e instalações hidrossanitárias e drenagem
B24: MÉDIA/M2 | D24: Descrição | E24: Total
B25: 25 | D25: Instalações de água fria | E25: =E11*$B$25 -> 369773.25
B26: 20 | D26: Instalações de água quente | E26: =E11*$B$26 -> 295818.6
B27: 42.5 | D27: Louças e metais | E27: =$B$27*E11 -> 628614.53
B28: 10 | D28: Instalações de água pluvial | E28: =E11*$B$28 -> 147909.3
B29: 15 | D29: Instalações de esgoto | E29: =E11*$B$29 -> 221863.95
E30: =SUM(E25:E29) -> 1663979.6
A31: Instalações preventivas e GLP
B33: MÉDIA/M2 | D33: Descrição | E33: Total
B34: 10 | D34: Instalações de gás | E34: =$B$34*E11 -> 147909.3
B35: 18 | D35: Instalações do sistema preventivo de Incêndio | E35: =$B$35*E11 -> 266236.74
B36: 8 | D36: Instalações de proteção e Aterramento - SPDA | E36: =$B$36*E11 -> 118327.44
E37: =SUM(E34:E36) -> 532473.48
A38: Mão de Obra
D40: Descrição | E40: Mão de Obra (R$/m²)
D41: Sistemas e instalações elétricas | E41: 55
D42: Sistemas e instalações hidrossanitárias e drenagem | E42: 50
D43: Instalações de gás | E43: 3
D44: Instalações do sistema preventivo de Incêndio | E44: 8
D45: Instalações de proteção e Aterramento - SPDA | E45: 3
A47: Entrada de Energia
C49: MÉDIA/M2 | D49: Ítem | E49: Valor
C50: 8 | D50: Entrada de Energia | E50: =C50*4410.5 -> 35284

Sheet Sistemas Especiais
A2: SISTEMAS ESPECIAIS
A4: CLIMATIZAÇÃO, EXAUSTÃO MECÂNICA E PRESSURIZAÇÃO
A6: Descrição | B6: Quantidade | C6: Preço Unitário | D6: Valor total
A7: Infraestrutura para Instalação de Ar Condicionado | B7: 0 | C7: 1200 | D7: =B7*C7 -> 0
A8: Infraestrutura para Instalação de Ar Condicionado - CASSETE | B8: =DADOS_INICIAIS!E11 -> 14693.42 | C8: 100 | D8: =B8*C8*1.1 -> 1616276.2
A9: Instalação de Ar Condicionado | B9: =Ambientes!J12 -> 12 | C9: 8000 | D9: =B9*C9*1.1 -> 105600
A10: Ventokit | B10: =COUNTIF(Ambientes!G:G,"SIM")-5 -> 133 | C10: 900 | D10: =B10*C10*1.1 -> 131670
A11: Churrasqueiras | B11: =DADOS_INICIAIS!E26 -> 24 | C11: 2600 | D11: =B11*C11*1.1 -> 68640
A12: TOTAL | D12: =SUM(D7:D11) -> 1922186.2
A14: COMUNICAÇÃO
A16: Descrição | B16: Parâmetro | D16: Valor total
A17: CFTV | B17: 2 | C17: R$ / AC | D17: =B17*DADOS_INICIAIS!$E$11*1.1 -> 32325.524
A18: Interfone | B18: 4 | C18: R$ / AC | D18: =B18*DADOS_INICIAIS!$E$11*1.1 -> 64651.048
A19: Controle de acesso | B19: 2 | C19: R$ / AC | D19: =B19*DADOS_INICIAIS!$E$11*1.1 -> 32325.524
A20: TV e internet | B20: 3 | C20: R$ / AC | D20: =B20*DADOS_INICIAIS!$E$11*1.1 -> 48488.286
A21: Automação, telecomunicação e sistemas de segurança | B21: 8 | C21: R$ / AC | D21: =B21*DADOS_INICIAIS!$E$11*1.1 -> 129302.1
A22: TOTAL | D22: =SUM(D17:D21) -> 307092.48
A24: EQUIPAMENTOS
A26: Descrição | B26: Quantidade | C26: Preço Unitário | D26: Valor total
A27: Elevadores | B27: 6 | C27: 210000 | D27: =B27*C27*1.1 -> 1386000 | E27: Proposta Atlas - ABC
A28: Elevador 1 parada | B28: 1 | C28: =C27/4 -> 52500 | D28: =C28*1.1 -> 57750
A29: Grupo de geradores | B29: 1 | C29: 80000 | D29: =B29*C29*1.1 -> 88000
A30: Subestação | B30: 0 | D30: =B30*C30 -> 0
A31: Infra de carro elétrico | B31: =DADOS_INICIAIS!E26 -> 24 | C31: 800 | D31: =B31*C31*1.1 -> 21120 | E31: Cliente informou para considerar 1/apto | J31: 30 | K31: vagas 1º SS
A32: Instalação carro elétrico | B32: =B31 -> 24 | C32: 10000 | D32: =B32*C32*1.1 -> 264000 | E32: Cliente informou para considerar 1/apto | J32: 58 | K32: vagas 2º SS
A33: Sistema de placas fotovoltaicas | B33: 1 | C33: ='Simulador Solar'!A21 -> 1244901.7 | D33: =B33*C33*1.1 -> 1369391.9
A34: Sauna | B34: ='REVESTIMENTO PISO'!F151 -> 5.48 | C34: 3900 | D34: =B34*C34*1.1 -> 23509.2
A35: Lago | B35: 1 | C35: 10000 | D35: =B35*C35*1.1 -> 11000
A36: Equipamentos para Piscina | B36: 33 | C36: =14913.3+15818+1100+5000 -> 36831.3 | D36: =B36*C36*1.1 -> 1336976.2 | E36: Custo Gran Torino + Sistema de aquecimento Sodramar
A37: TOTAL | D37: =SUM(D27:D36) -> 4557747.3
A39: OUTROS SISTEMAS ESPECIAIS
A41: Descrição | B41: Parâmetro | D41: Valor total
A42: Outros sistemas | B42: 30 | C42: R$ / AC | D42: =B42*DADOS_INICIAIS!E11 -> 440802.6
A43: TOTAL | D43: =SUM(D42:D42) -> 440802.6
A45: TOTAL SISTEMAS ESPECIAIS | D45: =D12+D22+D37+D43 -> 7227828.5 | E45: =D45/DADOS_INICIAIS!E11 -> 491.9092

Sheet Simulador Solar
A1: https://www.neosolar.com.br/simulador-solar-calculadora-fotovoltaica
A21: 1244901.7

Sheet Complementares
A2: COMPLEMENTARES
A4: SERVIÇOS COMPLEMENTARES
A6: Descrição | B6: Parâmetro | D6: Quantidade | F6: Valor total
A7: Móveis e decoração | B7: 3100 | C7: R$ / ALI | D7: =DADOS_INICIAIS!E19 -> 343.39 | E7: m² | F7: =D7*B7*1.1 -> 1170959.9
A8: Móveis e decoração jardim duplex e calçadas suspensas | B8: 150 | C8: R$ / ALI | D8: =I8+I9 -> 1361.26 | E8: m² | F8: =D8*B8*1.1 -> 224607.9 | H8: Circulação | I8: =SUMIF('REVESTIMENTO PISO'!D:D,"Circulação",'REVESTIMENTO PISO'!F:F) -> 443.96
A9: Comunicação visual | B9: 12 | C9: R$ / AC | D9: 1 | E9: vb | F9: =DADOS_INICIAIS!$E$11*B9*1.1 -> 193953.14 | H9: Jardim superior | I9: =SUMIF('REVESTIMENTO PISO'!D:D,"JARDIM (SUPERIOR)",'REVESTIMENTO PISO'!F:F) -> 917.3
A10: Paisagismo + mobiliário externo | B10: =C21+150 -> 440.66828 | C10: R$ / ALE | D10: =DADOS_INICIAIS!E20 -> 2661.29 | E10: m² | F10: =D10*B10*1.1 -> 1290020.7
A11: Lago | B11: 1500 | C11: R$ / m² | D11: 52 | E11: m² | F11: =D11*B11*1.1 -> 85800
A12: Ligações definitivas | B12: 5 | C12: R$ / AC | D12: 1 | E12: vb | F12: =DADOS_INICIAIS!$E$11*B12*1.1 -> 80813.81
A13: Desmobilização | B13: 10 | C13: R$ / AC | D13: 1 | E13: vb | F13: =DADOS_INICIAIS!$E$11*B13*1.1 -> 161627.62
A14: Limpeza | B14: 20 | C14: R$ / AC | D14: 1 | E14: vb | F14: =DADOS_INICIAIS!$E$11*B14*1.1 -> 323255.24
A15: TOTAL | F15: =SUM(F7:F14) -> 3531038.3
A17: TOTAL COMPLEMENTARES | F17: =F15 -> 3531038.3 | G17: =F17/DADOS_INICIAIS!E11 -> 240.31426
B20: PAISAGISMO - LIVE LUMIS
B21: CUSTO POR ÁREA DE PAISAGISMO | C21: =520877.56/1792 -> 290.66828 | D21: 2661.29 | E21: =C21*D21 -> 773552.59
B22: CUSTO POR ÁREA CONSTRUÍDA | C22: =520877.56/14888.46 -> 34.985322 | D22: =DADOS_INICIAIS!$E$11 -> 14693.42 | E22: =C22*D22 -> 514054.02

Sheet Canteiro
A1: Obra | B1: xxxx
A2: Empresa | B2: xxxx
A3: Revisão | B3: =#REF! -> #REF! | N3: Número de funcionários | R3: Produtividade média (h/m2)
A4: LEVANTAMENTO QUANTITATIVO | N4: Área construída | O4: 0 | R4: A.C/prazo | S4: =O4/O5 -> #DIV/0!
N5: Prazo da obra | O5: 0 | P5: meses | R5: Pm | S5: 49 | T5: h/m2
A6: Instalações de canteiro | N6: NF | O6: =ROUNDUP((O4*S5)/O5/180,) -> #DIV/0! | P6: funcionários
N7: Pavimentos | O7: 0
A8: Instalações de canteiro | N8: Equipe administrativa | O8: 5 | P8: funcionários
B10: Descrição | C10: Unidade | D10: Quantidade
B11: Produtividade média | C11: m2 / mês | D11: =#REF!/#REF! -> #REF! | N11: Barracão interno | O11: =450+(O4-13000)/1000*16 -> 242
B12: Pm | C12: h/m2 | D12: 49 | N12: Externo | O12: =O11*0.4 -> 96.8
B13: Numero de funcionários | C13: un | D13: =ROUNDUP((D12*#REF!)/#REF!/180,) -> #REF!
B14: Equipe administrativa | C14: un | D14: 5 | O14: =SUM(O11:O13) -> 338.8
B15: Pontos de água e esgoto | C15: un | D15: =ROUNDUP($D$13/20,0) -> #REF! | E15: 20 funcionários/ponto
B16: Bebedouro | C16: un | D16: =ROUNDUP(#REF!/5,0) -> #REF! | E16: 1 / 5 pav. | N16: Área refeitório | O16: 1 | P16: m²/funcionários
B17: Ferramentas | C17: R$ | D17: =800*D13 -> #REF! | E17: 800,00/func. | O17: =O16*O6 -> #DIV/0! | P17: m²
B18: EPI | C18: R$ | D18: =500*D13 -> #REF! | E18: 500,00/func.
B19: Banheiro | C19: un | D19: =ROUNDUP($D$13/20,0) -> #REF! | E19: 1/20 func | N19: Área de vestiário | O19: 1.5 | P19: m²/funcionários
O20: =O19*O6 -> #DIV/0! | P20: m²
A21: Mobiliário de canteiro
B23: Descrição | C23: Unidade | D23: Quantidade | E23: Custo unitário | F23: Custo total
B24: Cadeira | C24: un | D24: =28*1.5 -> 42 | E24: 200 | F24: =D24*E24 -> 8400
B25: Mesa | C25: un | D25: 7 | E25: 1000 | F25: =E25*D25 -> 7000
B26: Ar condicionado | C26: un | D26: 11 | E26: 5000 | F26: =E26*D26 -> 55000
B27: Armário | C27: m | D27: =7*2 -> 14 | E27: 900 | F27: =E27*D27 -> 12600
B28: Escrivaninha | C28: un | D28: =D14 -> 5 | E28: 800 | F28: =E28*D28 -> 4000
B29: TOTAL | F29: =F26+F27+F28+F25+F24 -> 87000
B30: Descrição | C30: Unidade | D30: Quantidade | E30: Custo unitário | F30: Custo total
B31: Computador pessoal | C31: un | D31: =D14 -> 5 | E31: 6000 | F31: =D31*E31 -> 30000 | N31: Área sanitários | O31: =1*ROUNDUP(O6/20,) -> #DIV/0! | P31: m²
B32: Impressora | C32: un | D32: 7 | E32: 2000 | F32: =E32*D32 -> 14000
B33: Roteador | C33: un | D33: 14 | E33: 500 | F33: =E33*D33 -> 7000 | N33: área lavatório | O33: =0.6*ROUNDUP(O6/20,) -> #DIV/0! | P33: m²
B34: TOTAL | F34: =+F31+F32+F33 -> 51000 | N34: Área de chuveiros | O34: =0.8*ROUNDUP(O6/10,) -> #DIV/0! | P34: m²
N36: Escritório | O36: 8 | P36: m²/pessoa
O37: =O36*O8 -> 40 | P37: m²
N39: Almoxarifado | O39: =IF(O4<20000,100,100+((O4-20000)/1000)*5) -> 100 | P39: m2
O41: =O39+O37+O34+O33+O31+O20+O17 -> #DIV/0!
N44: Pontos de água e esgoto | O44: 20 | P44: funcionários/ponto
N45: Pontos de água e esgoto | O45: =ROUNDUP(O6/O44,) -> #DIV/0! | P45: pontos
N48: Bebedouro | O48: 1 | P48: a cada 5 pav.
N49: Total | O49: =ROUNDUP(O7/5,) -> 0 | P49: bebedouros
N51: Ferramentas | O51: =O6*800 -> #DIV/0! | P51: 800 por funcionário
N53: EPI | O53: =O6*500 -> #DIV/0! | P53: 500,00 por funcionário | Q53: Considerando entrega de 2 uniformes, capacete, bota, óculos e cinto
N56: Banheiro | O56: 1 | P56: para cada | Q56: 20 | R56: pessoas
O57: =ROUNDUP(O6/Q56,) -> #DIV/0!

Sheet Bases
A1: Estimativas
B3: Área de Terreno | C3: Área Construída | D3: N° pavimentos | G3: Parâmetros | H3: Área de Terreno | I3: Área Construída | J3: N° pavimentos
A4: =#REF! -> #REF! | B4: =#REF! -> #REF! | C4: =#REF! -> #REF! | D4: =#REF! -> #REF! | G4: OBRA 1 | H4: 0 | I4: 13434.29 | K4: =C4/I4 -> #REF!
G5: OBRA 2 | H5: 0 | I5: 4498.66 | J5: 0
G6: OBRA 3 | H6: 0 | I6: 8366.5 | J6: 0
I8: =G4 -> OBRA 1 | J8: =G4 -> OBRA 1 | K8: =$G$5 -> OBRA 2 | L8: =$G$5 -> OBRA 2 | M8: =G6 -> OBRA 3 | N8: =G6 -> OBRA 3
A9: Descrição | F9: Unidade | G9: Quantidade | H9: Valor (R$) | I9: Valor | J9: Referencia | K9: Valor | L9: Referencia | M9: Valor | N9: Referencia
A10: ESTUDOS | H10: =$C$4*J10 -> #REF! | I10: =#REF! -> #REF! | J10: =I10/$I$4 -> #REF! | K10: =#REF! -> #REF! | L10: =K10/$I$5 -> #REF! | M10: =#REF! -> #REF! | N10: =M10/$I$6 -> #REF!
A11: PROJETOS | H11: =$C$4*J11 -> #REF! | I11: =#REF! -> #REF! | J11: =I11/$I$4 -> #REF! | K11: =#REF! -> #REF! | L11: =K11/$I$5 -> #REF! | M11: =#REF! -> #REF! | N11: =M11/$I$6 -> #REF!
A12: CONSULTORIAS | H12: =$C$4*J12 -> #REF! | I12: =#REF! -> #REF! | J12: =I12/$I$4 -> #REF! | K12: =#REF! -> #REF! | L12: =K12/$I$5 -> #REF! | M12: =#REF! -> #REF! | N12: =M12/$I$6 -> #REF!
A13: ENSAIOS E LAUDOS | H13: =$C$4*J13 -> #REF! | I13: =#REF! -> #REF! | J13: =I13/$I$4 -> #REF! | K13: =#REF! -> #REF! | L13: =K13/$I$5 -> #REF! | M13: =#REF! -> #REF! | N13: =M13/$I$6 -> #REF!
A14: TAXAS
A15: Despesas de Seguros | F15: vb | H15: =J15*$C$4 -> #REF! | I15: =#REF! -> #REF! | J15: =I15/$I$4 -> #REF! | K15: =#REF! -> #REF! | L15: =K15/$I$5 -> #REF! | M15: =#REF! -> #REF! | N15: =M15/$I$6 -> #REF!
A16: Licenciamentos, Taxas, Impostos | F16: vb | H16: =J16*$C$4 -> #REF! | I16: =#REF!-#REF! -> #REF! | J16: =I16/$I$4 -> #REF! | K16: =#REF!-#REF! -> #REF! | L16: =K16/$I$5 -> #REF! | M16: =#REF!-#REF! -> #REF! | N16: =M16/$I$6 -> #REF!
A17: DOCUMENTOS | H17: =J17*C4 -> #REF! | I17: =#REF! -> #REF! | J17: =I17/$I$4 -> #REF! | K17: =#REF! -> #REF! | L17: =K17/$I$5 -> #REF! | M17: =#REF! -> #REF! | N17: =M17/$I$6 -> #REF!
A18: SEGURANÇA DO TRABALHO
A19: Serviço segurança do trabalho terceirizado | F19: mês | H19: 2000 | I19: 1500 | J19: =I19/$I$4 -> 0.11165458 | K19: =#REF!+#REF! -> #REF! | L19: =K19/$I$5 -> #REF! | M19: =#REF!+#REF! -> #REF! | N19: =M19/$I$6 -> #REF!
A20: Placas de Sinalização de Obra | F20: vb | H20: =J20*$C$4 -> #REF! | I20: =#REF! -> #REF! | J20: =I20/$I$4 -> #REF! | K20: =#REF! -> #REF! | L20: =K20/$I$5 -> #REF! | M20: =#REF! -> #REF! | N20: =M20/$I$6 -> #REF!
A21: MEIO AMBIENTE | SAÚDE OCUPACIONAL | H21: =J21*C4 -> #REF! | I21: =#REF!+#REF! -> #REF! | J21: =I21/$I$4 -> #REF! | K21: =#REF!+#REF! -> #REF! | L21: =K21/$I$5 -> #REF! | M21: =#REF!+#REF! -> #REF! | N21: =M21/$I$6 -> #REF!
A22: EQUIPE
A23: Engenheiro Civil | F23: mês | H23: 7200 | I23: =#REF! -> #REF! | K23: =#REF! -> #REF! | M23: =#REF! -> #REF!
A24: Mestre Geral | F24: mês | H24: 5000 | I24: =#REF! -> #REF! | K24: =#REF! -> #REF! | M24: =#REF! -> #REF!
A25: Almoxarife | F25: mês | H25: 2500 | I25: =#REF! -> #REF! | K25: =#REF! -> #REF! | M25: =#REF! -> #REF!
A26: Auxiliar de Engenharia | F26: mês | H26: 9000 | I26: =#REF! -> #REF! | K26: =#REF! -> #REF! | M26: =#REF! -> #REF!
A27: Estagiário de Engenharia | F27: mês | H27: 1300 | I27: =#REF! -> #REF! | K27: =#REF! -> #REF! | M27: =#REF! -> #REF!
A28: Operador de Guincho | F28: mês | H28: 4500 | I28: =#REF! -> #REF! | K28: =#REF! -> #REF! | M28: =#REF! -> #REF!
A29: Servente | F29: mês | H29: 4200 | I29: =#REF! -> #REF! | K29: =#REF! -> #REF! | M29: =#REF! -> #REF!
A30: Setor de projetos | F30: mês | H30: 3000 | I30: =#REF! -> #REF! | K30: =#REF! -> #REF! | M30: =#REF! -> #REF!
A31: Serviço de vigilância | F31: vb | H31: =J31*$C$4 -> #REF! | I31: =#REF! -> #REF! | J31: =I31/$I$4 -> #REF! | K31: =#REF! -> #REF! | L31: =K31/$I$5 -> #REF! | M31: =#REF! -> #REF! | N31: =M31/$I$6 -> #REF!
A32: CANTEIRO DE OBRA
A33: Limpeza da camada vegetal | F33: m2 | H33: =2.5*B4 -> #REF! | I33: =#REF! -> #REF! | J33: =I33/$I$4 -> #REF! | K33: =#REF! -> #REF! | L33: =K33/$I$5 -> #REF! | M33: =#REF! -> #REF! | N33: =M33/$I$6 -> #REF!
A34: Demolições | H34: =N34*C4 -> #REF! | I34: =#REF! -> #REF! | J34: =I34/$I$4 -> #REF! | L34: =K34/$I$5 -> 0 | M34: =#REF! -> #REF! | N34: =M34/$I$6 -> #REF!
A35: Locação da obra | F35: m | J35: =I35/$I$4 -> 0 | L35: =K35/$I$5 -> 0 | N35: =M35/$I$6 -> 0
A36: Instalações Provisórias: Redes de Água Fria, Esgoto e Drenagem | F36: vb | H36: =J36*$C$4 -> #REF! | I36: =#REF! -> #REF! | J36: =I36/$I$4 -> #REF! | K36: =#REF! -> #REF! | L36: =K36/$I$5 -> #REF! | M36: =#REF! -> #REF! | N36: =M36/$I$6 -> #REF!
A37: Instalações Provisórias: Redes Elétrica, Comunicação e Dados | F37: vb | H37: =J37*$C$4 -> #REF! | I37: =#REF! -> #REF! | J37: =I37/$I$4 -> #REF! | K37: =#REF! -> #REF! | L37: =K37/$I$5 -> #REF! | M37: =#REF! -> #REF! | N37: =M37/$I$6 -> #REF!
A38: Locação de banheiro químico | F38: mês | H38: =J38*$C$4 -> #REF! | I38: =#REF! -> #REF! | J38: =I38/$I$4 -> #REF! | K38: =#REF! -> #REF! | L38: =K38/$I$5 -> #REF! | M38: =#REF! -> #REF! | N38: =M38/$I$6 -> #REF!
A39: Galpão provisório | F39: vb | H39: =L39*$C$4 -> #REF! | I39: =#REF!+#REF! -> #REF! | J39: =I39/$I$4 -> #REF! | K39: =#REF!+#REF! -> #REF! | L39: =K39/$I$5 -> #REF! | M39: =#REF!+#REF!+#REF! -> #REF! | N39: =M39/$I$6 -> #REF!
A40: Despesas de Consumo e manutenção | F40: vb | H40: =J40*$C$4 -> #REF! | I40: =#REF! -> #REF! | J40: =I40/$I$4 -> #REF! | K40: =#REF! -> #REF! | L40: =K40/$I$5 -> #REF! | M40: =#REF! -> #REF! | N40: =M40/$I$6 -> #REF!

Sheet EPCs
A1: Obra | B1: =DADOS_INICIAIS!B1 -> MONOLYT
A2: Empresa | B2: =DADOS_INICIAIS!B2 -> BLUE HEAVEN
A3: Revisão | B3: R00
A4: LEVANTAMENTO QUANTITATIVO
A6: Equipamentos de proteção coletiva
A8: Bandejas de proteção
B10: Descrição | C10: Unidade | D10: Quantidade
B11: Perímetro de projeção embasamneto | C11: m
B12: Perímetro de projeção torre | C12: m
B13: Número de montagens de bandeja primária | C13: un
B14: Número de montagens de bandeja secundária | C14: un
B15: Bandeja de proteção primária | C15: m | D15: =D11*D13+(D12-38.27)*D13 -> 0
B16: Bandeja de proteção secundária | C16: m | D16: =D12*D14 -> 0
A18: Guarda - corpo de desforma
B20: Descrição | C20: Unidade | D20: Quantidade
B21: Perímetro de projeção da torre | C21: m | D21: =D12 -> 0
B22: Repetições de pavimentos** | C22: un | D22: 4
B23: Proteção de periferia pós desforma torre | C23: m | D23: =(D21*D22) -> 0
A25: Tela fachadeira
B27: Descrição | C27: Unidade | D27: Quantidade
B28: Area da fachada | C28: m²
B29: Tela fachadeira | C29: m2 | D29: =D28 -> 0
A31: Fechamento removível de vãos em madeira
B33: Descrição | C33: Unidade | D33: Quantidade
B34: Área das portas de elevadores | C34: m2
B35: Quantidade de elevadores | C35: un
B36: Quantidade de portas de elevadores | C36: un | D36: =D35*12 -> 0
B37: Fechamento removível de vãos em madeira | C37: m2 | D37: =D34*D36 -> 0
A39: Tapume
B41: Descrição | C41: Unidade | D41: Quantidade
B42: Perímetro de encontro com pavimentação | C42: m
B43: Altura do tapume | C43: m | D43: 2.4
B44: Cobertura para proteção de pedestres | C44: m2 | D44: =D43*D42 -> 0

Sheet CUSTOS_INDIRETOS
A1: ORÇAMENTO PARAMÉTRICO - CUSTOS INDIRETOS
A7: Cliente | B7: =DADOS_INICIAIS!B2 -> BLUE HEAVEN
A8: Obra | B8: =DADOS_INICIAIS!B1 -> MONOLYT
A9: Data | B9: 45448
A10: Versão | B10: R00
A12: GERENCIAMENTO TÉCNICO
A13: Código | B13: Descrição | C13: Un. | D13: Quantidade orçada | E13: Preço unitário | F13: Preço total
A14: 01 | B14: GERENCIAMENTO TÉCNICO | F14: =F15+F20 -> #REF!
A15: 01.001 | B15: ESTUDOS, PROJETOS E CONSULTORIAS | F15: =SUM(F16:F19) -> #REF!
A16: 01.001.001 | B16: Estudos | F16: =Bases!H10 -> #REF!
A17: 01.001.002 | B17: Projetos | F17: =Bases!H11 -> #REF!
A18: 01.001.003 | B18: Consultorias | F18: =Bases!H12 -> #REF!
A19: 01.001.004 | B19: Ensaios e Laudos | F19: =Bases!H13 -> #REF!
A20: 01.002 | B20: TAXAS E DOCUMENTOS | F20: =SUM(F21:F23) -> #REF!
A21: 01.002.001 | B21: Seguros | F21: =Bases!H15 -> #REF!
A22: 01.002.002 | B22: Licenciamentos, Taxas, Impostos | F22: =Bases!H16 -> #REF!
A23: 01.002.003 | B23: Documentos | F23: =Bases!H17 -> #REF!
A24: 02 | B24: GERENCIAMENTO ADMINISTRATIVO | F24: =F25+F38+F60 -> #REF!
A25: 02.001 | B25: SEGURANÇA, MEIO AMBIENTE E SAÚDE | F25: =F26+F28+F37 -> #REF!
A26: 02.001.001 | B26: Segurança do Trabalho | F26: =F27 -> #REF!
A27: 02.001.001.001 | B27: Serviço de segurança do trabalho terceirizado | C27: mes | D27: =#REF! -> #REF! | E27: =Bases!H19 -> 2000 | F27: =E27*D27 -> #REF!
A28: 02.001.002 | B28: Equipamentos de proteção | F28: =SUM(F29:F36) -> #REF!
A29: 02.001.002.001 | B29: Bandeja de proteção primária | C29: m | D29: =EPCs!D15 -> 0 | E29: 294.33 | F29: =E29*D29 -> 0
B30: Bandeja de proteção secundária | C30: m | D30: =EPCs!D16 -> 0 | E30: 210.06 | F30: =E30*D30 -> 0
A31: 02.001.002.002 | B31: Guarda corpo em laje pós - desforma | C31: m | D31: =EPCs!D23 -> 0 | E31: =39.19+7.55+0.63+1.63 -> 49 | F31: =E31*D31 -> 0
A32: 02.001.002.003 | B32: Fechamento removível de vãos de porta de elevador em madeira | C32: m2 | D32: =EPCs!D37 -> 0 | E32: 19.89 | F32: =E32*D32 -> 0
A33: 02.001.002.004 | B33: Varal de segurança com cabo de aço | C33: m | D33: =D31 -> 0 | E33: 244 | F33: =E33*D33 -> 0
B34: Tela fachadeira reforçada com impressão digital | C34: m2 | D34: =EPCs!D29 -> 0 | E34: 15 | F34: =E34*D34 -> 0
A35: 02.001.002.005 | B35: Sinalização com placa indicativa fixada na estrutura | C35: vb | D35: 1 | E35: =Bases!H20 -> #REF! | F35: =E35*D35 -> #REF!
A36: 02.001.002.007 | B36: Equipamentos de proteção individual | C36: vb | D36: 1 | E36: =Canteiro!D18 -> #REF! | F36: =E36*D36 -> #REF!
A37: 02.001.003 | B37: Meio Ambiente | F37: =Bases!H21 -> #REF!
A38: 02.002 | B38: ADMINISTRAÇÃO E CANTEIRO DE OBRA | F38: =F39+F49+F51+F59 -> #REF!
A39: 02.002.001 | B39: Equipe de Gestão e Apoio | F39: =SUM(F40:F48) -> #REF!
A40: 02.002.001.001 | B40: Engenheiro Civil | C40: mes | D40: =#REF! -> #REF! | E40: =Bases!H23 -> 7200 | F40: =E40*D40 -> #REF!
A41: 02.002.001.002 | B41: Mestre Geral | C41: mes | D41: =#REF! -> #REF! | E41: =Bases!H24 -> 5000 | F41: =E41*D41 -> #REF!
A42: 02.002.001.003 | B42: Almoxarife | C42: mes | D42: =#REF! -> #REF! | E42: =Bases!H25 -> 2500 | F42: =E42*D42 -> #REF!
A43: 02.002.001.004 | B43: Auxiliar de Engenharia | C43: mes | D43: =#REF! -> #REF! | E43: =Bases!H26 -> 9000 | F43: =E43*D43 -> #REF!
A44: 02.002.001.005 | B44: Estagiário de Engenharia | C44: mes | D44: =#REF! -> #REF! | E44: =Bases!H27 -> 1300 | F44: =E44*D44 -> #REF!
A45: 02.002.001.006 | B45: Operador de Guincho | C45: mes | D45: =#REF! -> #REF! | E45: =Bases!H28 -> 4500 | F45: =E45*D45 -> #REF!
A46: 02.002.001.007 | B46: Servente | C46: mes | D46: =#REF! -> #REF! | E46: =Bases!H29 -> 4200 | F46: =E46*D46 -> #REF!
A47: 02.002.001.008 | B47: Setor de projetos | C47: mes | D47: =#REF! -> #REF! | E47: =Bases!H30 -> 3000 | F47: =E47*D47 -> #REF!
A48: 02.002.001.009 | B48: Serviço de vigilância | C48: mes | D48: =#REF! -> #REF! | E48: =Bases!H31 -> #REF! | F48: =E48*D48 -> #REF!
A49: 02.002.002 | B49: Operação Inicial do Canteiro | F49: =SUM(F50) -> #REF!
A50: 02.002.002.001 | B50: Limpeza mecanizada de camada vegetal | C50: m2 | D50: =#REF! -> #REF! | E50: 12.5 | F50: =E50*D50 -> #REF!
A51: 02.002.003 | B51: Instalações Provisórias | F51: =SUM(F52:F58) -> #REF!
A52: 02.002.003.001 | B52: Locação de banheiro químico | C52: mes | D52: =#REF! -> #REF! | E52: 2850 | F52: =E52*D52 -> #REF!
A53: 02.002.003.002 | B53: Instalações de canteiro | C53: vb | D53: 1 | E53: =Bases!H39 -> #REF! | F53: =E53*D53 -> #REF!
A54: 02.002.003.003 | B54: Instalações Provisórias: Redes de Água Fria, Esgoto e Drenagem | C54: vb | D54: 1 | E54: =Bases!H36 -> #REF! | F54: =E54*D54 -> #REF!
A55: 02.002.003.004 | B55: Instalações Provisórias: Redes Elétrica, Comunicação e Dados | C55: vb | D55: 1 | E55: =Bases!H37 -> #REF! | F55: =E55*D55 -> #REF!
A56: 02.002.003.005 | B56: Mobiliário de apoio a obra | C56: vb | D56: 1 | E56: =Canteiro!F29 -> 87000 | F56: =E56*D56 -> 87000
A57: 02.002.003.006 | B57: Equipamentos escritório - aquisição | C57: vb | D57: 1 | E57: =Canteiro!F34 -> 51000 | F57: =E57*D57 -> 51000
A58: 02.002.003.007 | B58: Tapume com telha metálica | C58: m2 | D58: =EPCs!D44 -> 0 | E58: 119.41 | F58: =E58*D58 -> 0
A59: 02.002.005 | B59: Despesas de Consumo e Manutenção | F59: =Bases!H40 -> #REF!
A60: 02.003 | B60: EQUIPAMENTOS | F60: =F61+F71 -> #REF!
A61: 02.003.001 | B61: Equipamentos de Obra | F61: =SUM(F62:F70) -> #REF!
A62: 02.003.001.001 | B62: Ferramentas - aquisição/manutenção | C62: vb | D62: 1 | E62: =Canteiro!D17 -> #REF! | F62: =E62*D62 -> #REF!
A63: 02.003.001.002 | B63: Condutor de Entulho-Aquisição | C63: Un. | D63: 1 | E63: =#REF! -> #REF! | F63: =E63*D63 -> #REF!
A64: 02.003.001.003 | B64: Manutenção de veículo de apoio - Kia Bongo | C64: mes | D64: =#REF! -> #REF! | E64: 166.665 | F64: =E64*D64 -> #REF!
A65: 02.003.001.005 | B65: Manutenção inicial de elevador cremalheira | C65: Un. | D65: 1 | E65: 70000 | F65: =E65*D65 -> 70000
A66: 02.003.001.006 | B66: Manutenção periódica de elevador cremalheira | C66: Un. | D66: 16 | E66: 2100 | F66: =E66*D66 -> 33600
A67: 02.003.001.007 | B67: Montagem e desmontagem de elevador cremalheira | C67: mes | D67: 1 | E67: 17600 | F67: =E67*D67 -> 17600
A68: 02.003.001.009 | B68: Manutenção periódica de de Mini-grua | C68: Un. | D68: 12 | E68: 950 | F68: =E68*D68 -> 11400
A69: 02.003.001.010 | B69: Montagem e Desmontagem de Mini-grua | C69: Un. | D69: 1 | E69: 7000 | F69: =E69*D69 -> 7000
A70: 02.003.001.011 | B70: Mobilização e desmobilização de Mini-grua | C70: mes | D70: 1 | E70: 9756 | F70: =E70*D70 -> 9756
A71: 02.003.002 | B71: Balancim | F71: =SUM(F72:F75) -> 45600
A72: 02.003.002.001 | B72: Locação de balancim | C72: mes | D72: 10 | E72: =1800 -> 1800 | F72: =E72*D72 -> 18000
A73: 02.003.002.002 | B73: Montagem e desmontagem de balancim | C73: Un. | D73: =14*2 -> 28 | E73: 450 | F73: =E73*D73 -> 12600
A74: 02.003.002.003 | B74: Manutenção periódica de balancim | C74: mes | D74: 10 | E74: 1500 | F74: =E74*D74 -> 15000
A75: 02.003.002.004 | B75: Locação de andaime | C75: mes | D75: 6 | F75: =E75*D75 -> 0
A76: Total | F76: =F24+F14 -> #REF!

Sheet Esquadrias
A2: ORÇAMENTO PARAMÉTRICO GERENCIAMENTO EXECUTIVO
A7: Cliente | B7: =DADOS_INICIAIS!B2 -> BLUE HEAVEN
A8: Obra | B8: =DADOS_INICIAIS!B1 -> MONOLYT
A9: Data | B9: 45448
A10: Revisão | B10: R00
A12: ESQUADRIAS
A14: Descrição | B14: Quantidade | D14: Parâmetro | F14: Referência | G14: Valor total
A15: Esquadrias de Alumínio | B15: =SUM(ESQUADRIAS_DE_ALUMÍNIO!D11) -> 3088 | C15: m² | D15: =1500*1.1 -> 1650 | E15: R$ / m² | F15: Média | G15: =D15*B15*1.1 -> 5604720 | H15: KZA
A16: PELE DE VIDRO 8mm | B16: =SUM(ESQUADRIAS_DE_ALUMÍNIO!D12) -> 191.19 | C16: m² | D16: 1600 | E16: R$ / m² | F16: Média | G16: =D16*B16*1.1 -> 336494.4 | H16: ABC - Estaleiro
A17: VIDRO PISCINA 0,3cm | B17: =SUM(ESQUADRIAS_DE_ALUMÍNIO!D13) -> 516.49 | C17: m² | D17: =ESQUADRIAS_DE_ALUMÍNIO!F13 -> 2300 | E17: R$ / m² | F17: Média | G17: =D17*B17*1.1 -> 1306719.7
A18: CLARABOIA | B18: =SUM(ESQUADRIAS_DE_ALUMÍNIO!D14) -> 12.09 | C18: m² | D18: =ESQUADRIAS_DE_ALUMÍNIO!F14 -> 2100 | E18: R$ / m² | F18: Média | G18: =D18*B18*1.1 -> 27927.9
A19: PCF | B19: =PORTA_CORTA_FOGO!F11 -> 8 | C19: un | D19: =PORTA_CORTA_FOGO!H11 -> 1750 | E19: R$ / un | F19: Média | G19: =D19*B19*1.1 -> 15400
A20: Serralherias | B20: 1 | C20: vb | D20: 10 | E20: R$ / AC | F20: Média | G20: =D20*B20*DADOS_INICIAIS!E11*1.1 -> 161627.62
A21: Guarda-corpo - vidro | B21: =GUARDA_CORPO!D11+GUARDA_CORPO!D12 -> 557.2985 | C21: m² | D21: =GUARDA_CORPO!F11 -> 2100 | E21: R$ / m² | F21: Média | G21: =+D21*B21*1.1 -> 1287359.5 | H21: 2100 Lumis 1600 ABC | K21: =B21/1.1 -> 506.635
A22: Corrimão inox | B22: =GUARDA_CORPO!D13 -> 121.23 | C22: m | D22: =GUARDA_CORPO!F13 -> 150 | E22: R$ / m² | F22: Média | G22: =+D22*B22*1.1 -> 20002.95
A23: Portão de alumínio | B23: 1 | C23: un | D23: 20000 | E23: R$ / un | F23: Média | G23: =+D23*B23*1.1 -> 22000 | H23: Consideração
A24: Esquadrias de Madeira | B24: =SUM(ESQUADRIAS_MADEIRA!F11:F15) -> 328 | C24: un | D24: =SUM(ESQUADRIAS_MADEIRA!I11:I15)/SUM(ESQUADRIAS_MADEIRA!F11:F15) -> 1535.2392 | E24: R$ / un | F24: Média | G24: =D24*B24*1.1 -> 553914.29
A25: Fechadura eletrônica | B25: =ESQUADRIAS_MADEIRA!G16 -> 24 | C25: un | D25: =ESQUADRIAS_MADEIRA!H16 -> 2500 | E25: R$ / un | F25: Média | G25: =D25*B25*1.1 -> 66000
A26: TOTAL | G26: =SUM(G15:G25) -> 9402166.4
A29: TOTAL ESQUADRIAS | G29: =G26 -> 9402166.4 | H29: =G29/DADOS_INICIAIS!E11 -> 639.88958

Sheet ESQUADRIAS_MADEIRA
A1: Obra | B1: =DADOS_INICIAIS!B1 -> MONOLYT
A2: Empresa | B2: =DADOS_INICIAIS!B2 -> BLUE HEAVEN
A3: Revisão | B3: R00
A4: Data | B4: 45447
A5: LEVANTAMENTO QUANTITATIVO
A7: ESQUADRIAS DE MADEIRA
B9: LEVANTAMENTO DE PROJETO | K9: ESQUADRIAS DE MADEIRA
B10: Pavimento | C10: Marca esquadria | D10: Largura (m) | E10: Altura (m) | F10: Quantidade | G10: Repetição | H10: VALOR R$ - MAT+MO | I10: Total | K10: Marca Esquadria | L10: Total
B11: - | C11: PORTA GIRO 1 FOLHA 110X210cm | D11: 1.1 | E11: 2.1 | F11: =5 -> 5 | G11: 1 | H11: =1938.7+130 -> 2068.7 | I11: =G11*ESQUADRIAS_MADEIRA!$F11*H11 -> 10343.5 | K11: {=_xlfn.UNIQUE(C11:C17)} -> PORTA GIRO 1 FOLHA 110X210cm | L11: =SUMIF(C:C,K11,I:I) -> 10343.5
B12: - | C12: PORTA GIRO 1 FOLHA 60X210cm | D12: 0.6 | E12: 2.1 | F12: 23 | G12: 1 | H12: =1317.48+130 -> 1447.48 | I12: =G12*ESQUADRIAS_MADEIRA!$F12*H12 -> 33292.04 | J12: Custo Gran Torino | K12: PORTA GIRO 1 FOLHA 60X210cm | L12: =SUMIF(C:C,K12,I:I) -> 33292.04
B13: - | C13: PORTA GIRO 1 FOLHA 70X210cm | D13: 0.7 | E13: 2.1 | F13: 45 | G13: 1 | H13: =1233.719+130 -> 1363.719 | I13: =G13*ESQUADRIAS_MADEIRA!$F13*H13 -> 61367.355 | K13: PORTA GIRO 1 FOLHA 70X210cm | L13: =SUMIF(C:C,K13,I:I) -> 61367.355
B14: - | C14: PORTA GIRO 1 FOLHA 80X210cm | D14: 0.8 | E14: 2.1 | F14: =211+14 -> 225 | G14: 1 | H14: =1412.53+130 -> 1542.53 | I14: =G14*ESQUADRIAS_MADEIRA!$F14*H14 -> 347069.25 | J14: Custo Gran Torino | K14: PORTA GIRO 1 FOLHA 80X210cm | L14: =SUMIF(C:C,K14,I:I) -> 347069.25
B15: - | C15: PORTA GIRO 1 FOLHA 90X210cm | D15: 0.9 | E15: 2.1 | F15: 30 | G15: 1 | H15: =1586.21+130 -> 1716.21 | I15: =G15*ESQUADRIAS_MADEIRA!$F15*H15 -> 51486.3 | J15: Custo Gran Torino | K15: PORTA GIRO 1 FOLHA 90X210cm | L15: =SUMIF(C:C,K15,I:I) -> 51486.3
C16: FECHADURA BIOMÉTRICA | F16: 1 | G16: =DADOS_INICIAIS!E26 -> 24 | H16: 2500 | I16: =G16*ESQUADRIAS_MADEIRA!$F16*H16 -> 60000 | J16: Custo KZA | K16: FECHADURA BIOMÉTRICA | L16: =SUMIF(C:C,K16,I:I) -> 60000
I17: =G17*ESQUADRIAS_MADEIRA!$F17*H17 -> 0 | K17: 0
I18: =SUM(I11:I17) -> 563558.45
I19: =I18*1.1 -> 619914.29

Sheet PORTA_CORTA_FOGO
A1: Obra | B1: =DADOS_INICIAIS!B1 -> MONOLYT
A2: Empresa | B2: =DADOS_INICIAIS!B2 -> BLUE HEAVEN
A3: Revisão | B3: R00
A4: Data | B4: 45447
A5: LEVANTAMENTO QUANTITATIVO
A7: PORTA CORTA FOGO
B9: LEVANTAMENTO DE PROJETO | K9: PORTAS CORTA - FOGO
B10: Pavimento | C10: Marca esquadria | D10: Largura (m) | E10: Altura (m) | F10: Quantidade | G10: Repetição | H10: VALOR R$ - MAT+MO | I10: Total | K10: Marca Esquadria | L10: Total
B11: - | C11: PORTA CORTA FOGO 90x210cm COM BARRA ANTIPÂNICO | D11: 0.9 | E11: 2.1 | F11: 8 | G11: 1 | H11: 1750 | I11: =G11*F11*H11 -> 14000 | J11: Custo Spotco | K11: {=_xlfn.UNIQUE(C11:C13)} -> PORTA CORTA FOGO 90x210cm COM BARRA ANTIPÂNICO | L11: =SUMIF(C:C,K11,I:I) -> 14000
I12: =G12*PORTA_CORTA_FOGO!$F12 -> 0 | K12: 0
I13: =G13*PORTA_CORTA_FOGO!$F13 -> 0
I14: =SUM(I11:I13) -> 14000
I15: =I14*1.1 -> 15400

Sheet ESQUADRIAS_DE_ALUMÍNIO
A1: Obra | B1: =DADOS_INICIAIS!B1 -> MONOLYT
A2: Empresa | B2: =DADOS_INICIAIS!B2 -> BLUE HEAVEN
A3: Revisão | B3: R00
A4: Data | B4: 45447
A5: LEVANTAMENTO QUANTITATIVO
A7: ESQUADRIAS DE ALUMÍNIO
B9: LEVANTAMENTO DE PROJETO | I9: PORTAS CORTA - FOGO
B10: Pavimento | C10: Marca esquadria | D10: Área (m2) | E10: Repetição | F10: VALOR R$ - MAT+MO | G10: Total | I10: Marca Esquadria | J10: Total (m2)
B11: - | C11: GOLD SLIM | D11: 3088 | E11: 1 | F11: =1500*1.1 -> 1650 | G11: =D11*E11*F11 -> 5095200 | H11: Custo KZA | I11: {=_xlfn.UNIQUE(C11:C15)} -> GOLD SLIM | J11: =SUMIF(C:C,I11,G:G) -> 5095200
B12: - | C12: PELE DE VIDRO 8mm | D12: =55.81+135.38 -> 191.19 | E12: 1 | F12: 1600 | G12: =D12*E12*F12 -> 305904 | H12: Custo Spotco | I12: PELE DE VIDRO 8mm | J12: =SUMIF(C:C,I12,G:G) -> 305904
B13: - | C13: VIDRO PISCINA 0,3cm | D13: 516.49 | E13: 1 | F13: 2300 | G13: =D13*E13*F13 -> 1187927 | H13: Custo Barra 4 | I13: VIDRO PISCINA 0,3cm | J13: =SUMIF(C:C,I13,G:G) -> 1187927
C14: CLARABOIA | D14: 12.09 | E14: 1 | F14: 2100 | G14: =D14*E14*F14 -> 25389 | I14: CLARABOIA | J14: =SUMIF(C:C,I14,G:G) -> 25389
G15: =D15*E15*F15 -> 0 | I15: 0
J17: =SUM(J11:J15)/SUM(D11:D15) -> 1737.085
J18: =SUM(J11:J15)*1.1 -> 7275862

Sheet GUARDA_CORPO
A1: Obra | B1: =DADOS_INICIAIS!B1 -> MONOLYT
A2: Empresa | B2: =DADOS_INICIAIS!B2 -> BLUE HEAVEN
A3: Revisão | B3: R00
A4: Data | B4: 45447
A5: LEVANTAMENTO QUANTITATIVO
A7: GUARDA CORPO
B9: LEVANTAMENTO DE PROJETO | I9: GUARDA CORPO
B10: Pavimento | C10: Marca esquadria | D10: Área(m²) | E10: Repetição | F10: VALOR R$ - MAT+MO | G10: Total | I10: Marca Esquadria | J10: Total
B11: Quantidade extraída do modelo | C11: GUARDA CORPO VIDRO H=1,10m | D11: =318.04*1.1 -> 349.844 | E11: 1 | F11: 2100 | G11: =D11*E11*F11 -> 734672.4 | H11: Lumis | I11: {=_xlfn.UNIQUE(C11:C17)} -> GUARDA CORPO VIDRO H=1,10m | J11: =SUMIF(C:C,I11,G:G) -> 734672.4
B12: Quantidade extraída do projeto dwg | C12: CORRIMÃO VIDRO+VERTICAL H=1,1m | D12: =171.45*1.1*1.1 -> 207.4545 | E12: 1 | F12: 2100 | G12: =D12*E12*F12 -> 435654.45 | I12: CORRIMÃO VIDRO+VERTICAL H=1,1m | J12: =SUMIF(C:C,I12,G:G) -> 435654.45
B13: Quant. em metro linear (Quantidade extraída do projeto dwg) | C13: CORRIMÃO ESCADAS | D13: 121.23 | E13: 1 | F13: 150 | G13: =D13*E13*F13 -> 18184.5 | H13: METRO LINEAR | I13: CORRIMÃO ESCADAS | J13: =SUMIF(C:C,I13,G:G) -> 18184.5
G14: =D14*E14*F14 -> 0 | I14: 0 | J14: =SUMIF(C:C,I14,G:G) -> 0
G15: =D15*E15 -> 0
G16: =D16*E16 -> 0
G17: =D17*E17 -> 0
J19: =SUM(J11:J17)*1.1 -> 1307362.5

Sheet BRISES
A1: Obra
A2: Empresa
A3: Revisão
A4: Data
A5: LEVANTAMENTO QUANTITATIVO
A7: BRISES
B9: LEVANTAMENTO DE PROJETO | J9: BRISES
B10: Pavimento | C10: Marca esquadria | D10: Largura (m) | E10: Altura (m) | F10: Quantidade | G10: Repetição | H10: Total (m2) | J10: Marca Esquadria | K10: Total (m2)
H11: =G11*BRISES!$F11*BRISES!$D11*BRISES!$E11 -> 0 | J11: =IFERROR(__xludf.DUMMYFUNCTION("ARRAY_CONSTRAIN(ARRAYFORMULA(UNIQUE(BRISES!$B$11:$B$220)), 1, 1)"),"") | K11: =SUMIF(C:C,J11,H:H) -> 0
H12: =G12*BRISES!$F12 -> 0
H13: =G13*BRISES!$F13 -> 0
H14: =G14*BRISES!$F14 -> 0
H15: =G15*BRISES!$F15 -> 0
H16: =G16*BRISES!$F16 -> 0
H17: =G17*BRISES!$F17 -> 0
H18: =G18*BRISES!$F18 -> 0
H19: =G19*BRISES!$F19 -> 0
H20: =G20*BRISES!$F20 -> 0
H21: =G21*BRISES!$F21 -> 0
H22: =G22*BRISES!$F22 -> 0
H23: =G23*BRISES!$F23 -> 0
... H220: =G220*BRISES!$F220 -> 0

Sheet Rev. Fachada
A2: ORÇAMENTO PARAMÉTRICO GERENCIAMENTO EXECUTIVO
A7: Cliente | B7: =DADOS_INICIAIS!B2 -> BLUE HEAVEN
A8: Obra | B8: =DADOS_INICIAIS!B1 -> MONOLYT
A9: Data | B9: 45448
A10: Revisão | B10: R00
A12: REVESTIMENTOS ARGAMASSADOS
A14: Descrição | B14: Quantidade | D14: Parâmetro | F14: Referência | G14: Valor total
A15: Chapisco e reboco | B15: =FACHADA!I12 -> 3968.0502 | C15: m² | D15: 102.82 | E15: R$ / m² | F15: - | G15: =B15*D15*1.1 -> 448794.42 | H15: =FACHADA!L12 -> CUSTO CHAPISCO + REBOCO GRAN TORINO / TEXTURA SPOTCO
A16: Concreto aparente | B16: =FACHADA!I11 -> 10610.366 | C16: m² | D16: =FACHADA!J11 -> 117.699 | E16: R$ / m² | G16: =B16*D16*1.1 -> 1373712.4 | H16: =FACHADA!L11 -> CUSTO ATALAIA, MUDANDO O ITEM DA COMPOSIÇÃO VERNIZ PARA RESINA
A17: TOTAL | G17: =SUM(G15:G16) -> 1822506.8
A19: PINTURA
A21: Descrição | B21: Quantidade | D21: Parâmetro | F21: Referência | G21: Valor total
A22: Textura padrão STO | B22: =B15 -> 3968.0502 | C22: m² | D22: 250 | E22: R$ / m² | F22: - | G22: =+B22*D22*1.1 -> 1091213.8
A23: TOTAL | G23: =SUM(G22) -> 1091213.8
A25: ACABAMENTOS ESPECIAIS
A27: Descrição | B27: Quantidade | D27: Parâmetro | F27: Referência | G27: Valor total
A28: Revestimentos especiais | B28: =FACHADA!I13 -> 451.70282 | C28: m² | D28: 350 | E28: R$ / m² | F28: - | G28: =B28*D28*1.1 -> 173905.59
G29: =SUM(G28:G28) -> 173905.59
A32: TOTAL FACHADA | G32: =G29+G23+G17 -> 3087626.2 | H32: =G32/DADOS_INICIAIS!E11 -> 210.13666

Sheet FACHADA
A1: Obra | B1: =DADOS_INICIAIS!B1 -> MONOLYT
A2: Empresa | B2: =DADOS_INICIAIS!B2 -> BLUE HEAVEN
A3: Revisão | B3: R00
A4: Data | B4: 45448
A5: LEVANTAMENTO QUANTITATIVO
A7: EQUIPAMENTOS ESPECIAIS DE FACHADA
B9: LEVANTAMENTO DE PROJETO | H9: LEVANTAMENTO DE PROJETO
B10: Pavimento | C10: Material | D10: Perímetro (m) | E10: Altura (m) | F10: Área (m²) | H10: Material | I10: Área (m²) | J10: Valor (mat+mo) | K10: Total
B11: 2S | C11: CONCRETO APARENTE | D11: 208.5592 | E11: =3.42*1.15 -> 3.933 | F11: =Table_1[[#This Row],[Perímetro (m)]]*Table_1[[#This Row],[Altura (m)]] -> 820.26333 | H11: {=_xlfn.UNIQUE(C11:C185)} -> CONCRETO APARENTE | I11: =SUMIF(C:C,H11,F:F) -> 10610.366 | J11: =SUM(R20:R24)+52 -> 117.699 | K11: =I11*J11*1.1 -> 1373712.4 | L11: CUSTO ATALAIA, MUDANDO O ITEM DA COMPOSIÇÃO VERNIZ PARA RESINA
B12: 2S - teto | C12: CONCRETO APARENTE | D12: 7.296 | E12: 9.189 | F12: =Table_1[[#This Row],[Perímetro (m)]]*Table_1[[#This Row],[Altura (m)]] -> 67.042944 | H12: CHAPISCO/REBOCO/TEXTURA | I12: =SUMIF(C:C,H12,F:F) -> 3968.0502 | J12: 352.82 | K12: =I12*J12*1.1 -> 1540008.2 | L12: CUSTO CHAPISCO + REBOCO GRAN TORINO / TEXTURA SPOTCO
B13: 2S - teto | C13: CONCRETO APARENTE | D13: 5.27 | E13: 36.339 | F13: =Table_1[[#This Row],[Perímetro (m)]]*Table_1[[#This Row],[Altura (m)]] -> 191.50653 | H13: PEDRA MACIÇA PILARES SACADAS | I13: =SUMIF(C:C,H13,F:F) -> 451.70282 | J13: 350 | K13: =I13*J13*1.1 -> 173905.59
B14: 1SS - MURETAS | C14: CHAPISCO/REBOCO/TEXTURA | D14: 132.9299 | E14: 1.1 | F14: =Table_1[[#This Row],[Perímetro (m)]]*Table_1[[#This Row],[Altura (m)]] -> 146.22289 | H14: 0 | I14: =SUMIF(C:C,H14,F:F) -> 0 | K14: =I14*J14*1.1 -> 0
B15: 1SS | C15: CONCRETO APARENTE | D15: 238.2649 | E15: =3.65*1.15 -> 4.1975 | F15: =Table_1[[#This Row],[Perímetro (m)]]*Table_1[[#This Row],[Altura (m)]] -> 1000.1169 | I15: =SUMIF(C:C,H15,F:F) -> 0 | K15: =I15*J15*1.1 -> 0
B16: 1SS | C16: PEDRA MACIÇA PILARES SACADAS | D16: 24.8928 | E16: 3.68 | F16: =Table_1[[#This Row],[Perímetro (m)]]*Table_1[[#This Row],[Altura (m)]] -> 91.605504 | I16: =SUMIF(C:C,H16,F:F) -> 0 | K16: =I16*J16*1.1 -> 0
B17: 1SS | C17: CHAPISCO/REBOCO/TEXTURA | D17: 143.1047 | E17: 3.68 | F17: =Table_1[[#This Row],[Perímetro (m)]]*Table_1[[#This Row],[Altura (m)]] -> 526.6253 | I17: =SUMIF(C:C,H17,F:F) -> 0 | K17: =I17*J17*1.1 -> 0
B18: 1SS - PISCINAS | C18: CONCRETO APARENTE | D18: 6 | E18: =(25.9911+12.0218*0.2+1.838+0.85*0.2+2.16*0.2*2)*1.1 -> 34.394206 | F18: =Table_1[[#This Row],[Perímetro (m)]]*Table_1[[#This Row],[Altura (m)]] -> 206.36524 | I18: =SUMIF(C:C,H18,F:F) -> 0 | K18: =I18*J18*1.1 -> 0
B19: 1SS - PROJEÇÃO TORRE | C19: CONCRETO APARENTE | D19: =DADOS_INICIAIS!$E$18+DADOS_INICIAIS!$F$18 -> 448.87 | E19: 0.2 | F19: =Table_1[[#This Row],[Perímetro (m)]]*Table_1[[#This Row],[Altura (m)]] -> 89.774 | I19: =SUMIF(C:C,H19,F:F) -> 0 | K19: =I19*J19*1.1 -> 0
B20: TA - TERR / TB - 1º PAV | C20: CONCRETO APARENTE | D20: 482.6136 | E20: =3.65*1.15 -> 4.1975 | F20: =Table_1[[#This Row],[Perímetro (m)]]*Table_1[[#This Row],[Altura (m)]] -> 2025.7706 | I20: =SUMIF(C:C,H20,F:F) -> 0 | K20: =I20*J20*1.1 -> 0 | Q20: 0.36 | R20: =Q20*(300/1.8) -> 60 | S20: RESINA
B21: TA - TERR / TB - 1º PAV | C21: CHAPISCO/REBOCO/TEXTURA | D21: 378.11 | E21: 3.65 | F21: =Table_1[[#This Row],[Perímetro (m)]]*Table_1[[#This Row],[Altura (m)]] -> 1380.1015 | R21: 0.56 | S21: LIXA
B22: TA - TERR / TB - 1º PAV | C22: PEDRA MACIÇA PILARES SACADAS | D22: 35.0603 | E22: 3.65 | F22: =Table_1[[#This Row],[Perímetro (m)]]*Table_1[[#This Row],[Altura (m)]] -> 127.97009 | R22: 0.444 | S22: CIMENTO CPIIZ
B23: TA - TERR / TB - 1º PAV | C23: CONCRETO APARENTE | D23: 8 | E23: =(25.9911+12.0218*0.2+1.838+0.85*0.2+2.16*0.2*2)*1.1 -> 34.394206 | F23: =Table_1[[#This Row],[Perímetro (m)]]*Table_1[[#This Row],[Altura (m)]] -> 275.15365 | R23: 1.095 | S23: CIMENTO BRANCO
B24: TA - TERR / TB - 1º PAV | C24: CONCRETO APARENTE | D24: =DADOS_INICIAIS!$E$18+DADOS_INICIAIS!$F$18 -> 448.87 | E24: 0.2 | F24: =Table_1[[#This Row],[Perímetro (m)]]*Table_1[[#This Row],[Altura (m)]] -> 89.774 | R24: 3.6 | S24: ADESIVO PARA ARGAMASSAS
B25: TA - 1º PAV/ TB - 2º PAV | C25: CONCRETO APARENTE | D25: 344.7335 | E25: =3.65*1.15 -> 4.1975 | F25: =Table_1[[#This Row],[Perímetro (m)]]*Table_1[[#This Row],[Altura (m)]] -> 1447.0189
B26: TA - 1º PAV/ TB - 2º PAV | C26: PEDRA MACIÇA PILARES SACADAS | D26: 63.5965 | E26: 3.65 | F26: =Table_1[[#This Row],[Perímetro (m)]]*Table_1[[#This Row],[Altura (m)]] -> 232.12722
B27: TA - 1º PAV/ TB - 2º PAV | C27: CHAPISCO/REBOCO/TEXTURA | D27: 286.81 | E27: 3.65 | F27: =Table_1[[#This Row],[Perímetro (m)]]*Table_1[[#This Row],[Altura (m)]] -> 1046.8565
B28: TA - 1º PAV/ TB - 2º PAV | C28: CONCRETO APARENTE | D28: 8 | E28: =(25.9911+12.0218*0.2+1.838+0.85*0.2+2.16*0.2*2)*1.1 -> 34.394206 | F28: =Table_1[[#This Row],[Perímetro (m)]]*Table_1[[#This Row],[Altura (m)]] -> 275.15365
B29: TA - 1º PAV/ TB - 2º PAV | C29: CONCRETO APARENTE | D29: =DADOS_INICIAIS!$E$18+DADOS_INICIAIS!$F$18 -> 448.87 | E29: 0.2 | F29: =Table_1[[#This Row],[Perímetro (m)]]*Table_1[[#This Row],[Altura (m)]] -> 89.774
B30: TA - 2º PAV/ TB - COB | C30: CONCRETO APARENTE | D30: 44.7539 | E30: 3.65 | F30: =Table_1[[#This Row],[Perímetro (m)]]*Table_1[[#This Row],[Altura (m)]] -> 163.35173
B31: TA - 2º PAV/ TB - COB | C31: CONCRETO APARENTE | D31: 2 | E31: 524.604 | F31: =Table_1[[#This Row],[Perímetro (m)]]*Table_1[[#This Row],[Altura (m)]] -> 1049.208
B32: TA - 2º PAV/ TB - COB | C32: CONCRETO APARENTE | D32: 696.7863 | E32: 0.2 | F32: =Table_1[[#This Row],[Perímetro (m)]]*Table_1[[#This Row],[Altura (m)]] -> 139.35726
B33: TA - 2º PAV/ TB - COB | C33: CHAPISCO/REBOCO/TEXTURA | D33: 206.8479 | E33: =3.65*1.15 -> 4.1975 | F33: =Table_1[[#This Row],[Perímetro (m)]]*Table_1[[#This Row],[Altura (m)]] -> 868.24406
B34: TA - 2º PAV/ TB - COB - PISCINAS | C34: CONCRETO APARENTE | D34: 3 | E34: =(25.9911+12.0218*0.2+1.838+0.85*0.2+2.16*0.2*2)*1.1 -> 34.394206 | F34: =Table_1[[#This Row],[Perímetro (m)]]*Table_1[[#This Row],[Altura (m)]] -> 103.18262
B35: TA - 2º PAV/ TB - COB | C35: CONCRETO APARENTE | D35: =DADOS_INICIAIS!$E$18+DADOS_INICIAIS!$F$18 -> 448.87 | E35: 0.2 | F35: =Table_1[[#This Row],[Perímetro (m)]]*Table_1[[#This Row],[Altura (m)]] -> 89.774
B36: TA - 2º PAV/ TB - COB - PISCINAS MAIORES | C36: CONCRETO APARENTE | D36: 6 | E36: 21.059 | F36: =Table_1[[#This Row],[Perímetro (m)]]*Table_1[[#This Row],[Altura (m)]] -> 126.354
B37: COBERTURA | C37: CONCRETO APARENTE | D37: 2 | E37: 798.5921 | F37: =Table_1[[#This Row],[Perímetro (m)]]*Table_1[[#This Row],[Altura (m)]] -> 1597.1842
B38: COBERTURA | C38: CONCRETO APARENTE | D38: 378.6013 | E38: 0.2 | F38: =Table_1[[#This Row],[Perímetro (m)]]*Table_1[[#This Row],[Altura (m)]] -> 75.72026
B39: TETO DECK | C39: CONCRETO APARENTE | D39: 688.52 | E39: 1 | F39: =Table_1[[#This Row],[Perímetro (m)]]*Table_1[[#This Row],[Altura (m)]] -> 688.52
F40: =Table_1[[#This Row],[Perímetro (m)]]*Table_1[[#This Row],[Altura (m)]] -> 0
F41: =Table_1[[#This Row],[Perímetro (m)]]*Table_1[[#This Row],[Altura (m)]] -> 0
F42: =Table_1[[#This Row],[Perímetro (m)]]*Table_1[[#This Row],[Altura (m)]] -> 0
F43: =Table_1[[#This Row],[Perímetro (m)]]*Table_1[[#This Row],[Altura (m)]] -> 0
F44: =Table_1[[#This Row],[Perímetro (m)]]*Table_1[[#This Row],[Altura (m)]] -> 0
F45: =Table_1[[#This Row],[Perímetro (m)]]*Table_1[[#This Row],[Altura (m)]] -> 0
F46: =Table_1[[#This Row],[Perímetro (m)]]*Table_1[[#This Row],[Altura (m)]] -> 0
F47: =Table_1[[#This Row],[Perímetro (m)]]*Table_1[[#This Row],[Altura (m)]] -> 0
F48: =Table_1[[#This Row],[Perímetro (m)]]*Table_1[[#This Row],[Altura (m)]] -> 0
F49: =Table_1[[#This Row],[Perímetro (m)]]*Table_1[[#This Row],[Altura (m)]] -> 0
F50: =Table_1[[#This Row],[Perímetro (m)]]*Table_1[[#This Row],[Altura (m)]] -> 0
F51: =Table_1[[#This Row],[Perímetro (m)]]*Table_1[[#This Row],[Altura (m)]] -> 0
... F224: =Table_1[[#This Row],[Perímetro (m)]]*Table_1[[#This Row],[Altura (m)]] -> 0

Sheet ORÇAMENTO_EXECUTIVO_REV03
B1: REV03 | G1: REV02 | P1: REV01
B2: ETAPA | C2: VALOR ORÇADO | D2: % | E2: VALOR / m² | G2: ETAPA | H2: VALOR ORÇADO | I2: % | J2: VALOR / m² | P2: VALOR ORÇADO | Q2: % | R2: VALOR / m²
B3: GERENCIAMENTO TÉCNICO E ADMINISTRATIVO | C3: =[5]CUSTOS_INDIRETOS!$F$93 -> 14538860 | D3: =C3/C$20 -> 0.16525102 | E3: =C3/ORÇAMENTO_EXECUTIVO_REV03!$Z$3 -> 989.48101 | G3: GERENCIAMENTO TÉCNICO E ADMINISTRATIVO | H3: =[4]CUSTOS_INDIRETOS!$F$93 -> 13510709 | I3: =H3/H$20 -> 0.15543583 | J3: =H3/ORÇAMENTO_EXECUTIVO_REV03!Z$3 -> 919.50744 | P3: 8526873.7 | Q3: 0.11402738 | R3: 683.80635 | T3: =H3-P3 -> 4983835.4 | V3: =J3-R3 -> 235.7011 | Y3: ÁREA CONSTRUÍDA | Z3: =DADOS_INICIAIS!E11 -> 14693.42 | AA3: m²
B4: MOVIMENTAÇÃO DE TERRA | C4: =H4 -> 2545063.4 | D4: =C4/C$20 -> 0.0289276 | E4: =C4/ORÇAMENTO_EXECUTIVO_REV03!$Z$3 -> 173.2111 | G4: MOVIMENTAÇÃO DE TERRA | H4: =MOVIMENTAÇÃO_DE_TERRA!F35 -> 2545063.4 | I4: =H4/H$20 -> 0.029280035 | J4: =H4/ORÇAMENTO_EXECUTIVO_REV03!Z$3 -> 173.2111 | P4: 2450076.2 | Q4: 0.03276415 | R4: 196.48205 | T4: =H4-P4 -> 94987.21 | V4: =J4-R4 -> -23.270956
B5: INFRAESTRUTURA | C5: =H5 -> 5742340 | D5: =C5/C$20 -> 0.065268361 | E5: =C5/ORÇAMENTO_EXECUTIVO_REV03!$Z$3 -> 390.81031 | G5: INFRAESTRUTURA | H5: ='INFRAESTRUTURA REV01'!G31 -> 5742340 | I5: =H5/H$20 -> 0.066063549 | J5: =H5/ORÇAMENTO_EXECUTIVO_REV03!Z$3 -> 390.81031 | P5: 5278318.1 | Q5: 0.070585399 | R5: 423.29083 | T5: =H5-P5 -> 464021.92 | V5: =J5-R5 -> -32.480518
B6: CONTENÇÕES | C6: =H6 -> 1644604.6 | D6: =C6/C$20 -> 0.01869284 | E6: =C6/ORÇAMENTO_EXECUTIVO_REV03!$Z$3 -> 111.92796 | G6: CONTENÇÕES | H6: =CONTENÇÕES!G33 -> 1644604.6 | I6: =H6/H$20 -> 0.018920582 | J6: =H6/ORÇAMENTO_EXECUTIVO_REV03!Z$3 -> 111.92796 | P6: 1644604.6 | Q6: 0.021992815 | R6: 131.88785 | T6: =H6-P6 -> 0 | V6: =J6-R6 -> -19.959888
B7: SUPRAESTRUTURA | C7: =H7 -> 16955390 | D7: =C7/C$20 -> 0.19271769 | E7: =C7/ORÇAMENTO_EXECUTIVO_REV03!$Z$3 -> 1153.9444 | G7: SUPRAESTRUTURA | H7: =SUPRAESTRUTURA!G25 -> 16955390 | I7: =H7/H$20 -> 0.19506564 | J7: =H7/ORÇAMENTO_EXECUTIVO_REV03!Z$3 -> 1153.9444 | P7: 13332389 | Q7: 0.17829013 | R7: 1069.1811 | T7: =H7-P7 -> 3623001 | V7: =J7-R7 -> 84.763314
B8: ALVENARIA | C8: =H8 -> 3148673.4 | D8: =C8/C$20 -> 0.035788328 | E8: =C8/ORÇAMENTO_EXECUTIVO_REV03!$Z$3 -> 214.29139 | G8: ALVENARIA | H8: =Alvenaria!G25 -> 3148673.4 | I8: =H8/H$20 -> 0.03622435 | J8: =H8/ORÇAMENTO_EXECUTIVO_REV03!Z$3 -> 214.29139 | P8: 3148673.4 | Q8: 0.042106285 | R8: 252.50554 | T8: =H8-P8 -> 0 | V8: =J8-R8 -> -38.214151
B9: INSTALAÇÕES ELÉTRICAS, HIDRÁULICAS, GLP E PREVENTIVAS | C9: =H9 -> 6206500.6 | D9: =C9/C$20 -> 0.070544085 | E9: =C9/ORÇAMENTO_EXECUTIVO_REV03!$Z$3 -> 422.4 | G9: INSTALAÇÕES ELÉTRICAS, HIDRÁULICAS, GLP E PREVENTIVAS | H9: =Instalações!D35 -> 6206500.6 | I9: =H9/H$20 -> 0.071403549 | J9: =H9/ORÇAMENTO_EXECUTIVO_REV03!Z$3 -> 422.4 | P9: 5267209.7 | Q9: 0.070436851 | R9: 422.4 | T9: =H9-P9 -> 939290.88 | V9: =J9-R9 -> 0
B10: EQUIPAMENTOS E SISTEMAS ESPECIAIS | C10: =H10 -> 7227828.5 | D10: =C10/C$20 -> 0.082152662 | E10: =C10/ORÇAMENTO_EXECUTIVO_REV03!$Z$3 -> 491.9092 | G10: EQUIPAMENTOS E SISTEMAS ESPECIAIS | H10: ='Sistemas Especiais'!D45 -> 7227828.5 | I10: =H10/H$20 -> 0.083153558 | J10: =H10/ORÇAMENTO_EXECUTIVO_REV03!Z$3 -> 491.9092 | P10: 6870035.2 | Q10: 0.091870965 | R10: 550.93741 | T10: =H10-P10 -> 357793.33 | V10: =J10-R10 -> -59.028203
B11: IMPERMEABILIZAÇÃO | C11: =H11 -> 1260169.1 | D11: =C11/C$20 -> 0.014323284 | E11: =C11/ORÇAMENTO_EXECUTIVO_REV03!$Z$3 -> 85.764176 | G11: IMPERMEABILIZAÇÃO | H11: =Impermeabilização!G28 -> 1260169.1 | I11: =H11/H$20 -> 0.01449779 | J11: =H11/ORÇAMENTO_EXECUTIVO_REV03!Z$3 -> 85.764176 | P11: 1100757.3 | Q11: 0.014720105 | R11: 88.274423 | T11: =H11-P11 -> 159411.71 | V11: =J11-R11 -> -2.5102477
B12: REVESTIMENTOS INTERNOS EM PISO E PAREDE | C12: =H12 -> 1754484.6 | D12: =C12/C$20 -> 0.019941754 | E12: =C12/ORÇAMENTO_EXECUTIVO_REV03!$Z$3 -> 119.40614 | G12: REVESTIMENTOS INTERNOS EM PISO E PAREDE | H12: ='Acabamentos de Piso'!G33+'Rev. Internos de Parede'!G23 -> 1754484.6 | I12: =H12/H$20 -> 0.020184712 | J12: =H12/ORÇAMENTO_EXECUTIVO_REV03!Z$3 -> 119.40614 | P12: 1637724.6 | Q12: 0.02190081 | R12: 131.33611 | T12: =H12-P12 -> 116760.04 | V12: =J12-R12 -> -11.929971
B13: REVESTIMENTOS E ACABAMENTOS INTERNOS EM TETO | C13: =H13 -> 1764973.6 | D13: =C13/C$20 -> 0.020060974 | E13: =C13/ORÇAMENTO_EXECUTIVO_REV03!$Z$3 -> 120.12 | G13: REVESTIMENTOS E ACABAMENTOS INTERNOS EM TETO | H13: ='Acabamentos de Teto'!G21 -> 1764973.6 | I13: =H13/H$20 -> 0.020305384 | J13: =H13/ORÇAMENTO_EXECUTIVO_REV03!Z$3 -> 120.12 | P13: 1292981.4 | Q13: 0.017290661 | R13: 103.68969 | T13: =H13-P13 -> 471992.18 | V13: =J13-R13 -> 16.430308
B14: ACABAMENTOS EM PISO E PAREDE | C14: =H14 -> 4311125.5 | D14: =C14/C$20 -> 0.049000946 | E14: =C14/ORÇAMENTO_EXECUTIVO_REV03!$Z$3 -> 293.40518 | G14: ACABAMENTOS EM PISO E PAREDE | H14: ='Acabamentos de Piso'!G34+'Rev. Internos de Parede'!G24 -> 4311125.5 | I14: =H14/H$20 -> 0.049597942 | J14: =H14/ORÇAMENTO_EXECUTIVO_REV03!Z$3 -> 293.40518 | P14: 4169253.4 | Q14: 0.055754203 | R14: 334.35021 | T14: =H14-P14 -> 141872.06 | V14: =J14-R14 -> -40.945028
B15: PINTURA INTERNA | C15: =H15 -> 2297072.5 | D15: =C15/C$20 -> 0.026108896 | E15: =C15/ORÇAMENTO_EXECUTIVO_REV03!$Z$3 -> 156.33341 | G15: PINTURA INTERNA | H15: ='Pintura Interna'!G21 -> 2297072.5 | I15: =H15/H$20 -> 0.02642699 | J15: =H15/ORÇAMENTO_EXECUTIVO_REV03!Z$3 -> 156.33341 | P15: 2000841.4 | Q15: 0.026756665 | R15: 160.456 | T15: =H15-P15 -> 296231.1 | V15: =J15-R15 -> -4.1225877 | X15: Mais revestimentos parede banheiro
B16: ESQUADRIAS, VIDROS E FERRAGENS | C16: =H16 -> 9402166.4 | D16: =C16/C$20 -> 0.10686654 | E16: =C16/ORÇAMENTO_EXECUTIVO_REV03!$Z$3 -> 639.88958 | G16: ESQUADRIAS, VIDROS E FERRAGENS | H16: =Esquadrias!G29 -> 9402166.4 | I16: =H16/H$20 -> 0.10816853 | J16: =H16/ORÇAMENTO_EXECUTIVO_REV03!Z$3 -> 639.88958 | P16: 9377705.7 | Q16: 0.12540531 | R16: 752.03819 | T16: =H16-P16 -> 24460.7 | V16: =J16-R16 -> -112.14861
B17: REVESTIMENTOS E ACABAMENTOS DE FACHADA | C17: =H17 -> 3087626.2 | D17: =C17/C$20 -> 0.035094456 | E17: =C17/ORÇAMENTO_EXECUTIVO_REV03!$Z$3 -> 210.13666 | G17: REVESTIMENTOS E ACABAMENTOS DE FACHADA | H17: =SUM(FACHADA!K11:K20) -> 3087626.2 | I17: =H17/H$20 -> 0.035522025 | J17: =H17/ORÇAMENTO_EXECUTIVO_REV03!Z$3 -> 210.13666 | P17: 3087626.2 | Q17: 0.04128992 | R17: 247.60991 | T17: =H17-P17 -> 0 | V17: =J17-R17 -> -37.473247
B18: SERVIÇOS COMPLEMENTARES | C18: =H18 -> 3531038.3 | D18: =C18/C$20 -> 0.04013435 | E18: =C18/ORÇAMENTO_EXECUTIVO_REV03!$Z$3 -> 240.31426 | G18: SERVIÇOS COMPLEMENTARES | H18: =Complementares!F17 -> 3531038.3 | I18: =H18/H$20 -> 0.040623321 | J18: =H18/ORÇAMENTO_EXECUTIVO_REV03!Z$3 -> 240.31426 | P18: 3416073 | Q18: 0.045682142 | R18: 273.94946 | T18: =H18-P18 -> 114965.29 | V18: =J18-R18 -> -33.6352
B19: IMPREVISTOS E CONTINGENCIAS | C19: =SUM(C3:C18)*0.03 -> 2562537.5 | D19: =C19/C$20 -> 0.029126214 | E19: =C19/ORÇAMENTO_EXECUTIVO_REV03!$Z$3 -> 174.40034 | G19: IMPREVISTOS E CONTINGENCIAS | H19: =SUM(H3:H18)*0.03 -> 2531693 | I19: =H19/H$20 -> 0.029126214 | J19: =H19/ORÇAMENTO_EXECUTIVO_REV03!Z$3 -> 172.30114 | P19: 2178034.3 | Q19: 0.029126214 | R19: 174.66585 | T19: =H19-P19 -> 353658.68 | V19: =J19-R19 -> -2.3647166
B20: TOTAL | C20: =SUM(C3:C19) -> 87980454 | D20: =SUM(D3:D19) -> 1 | E20: =SUM(E3:E19) -> 5987.7451 | G20: TOTAL | H20: =SUM(H3:H19) -> 86921459 | I20: =SUM(I3:I19) -> 1 | J20: =SUM(J3:J19) -> 5915.6724 | P20: 74779177 | Q20: 1 | R20: 5996.861
B21: CUB/SC | C21: 2758.46 | D21: 45413 | E21: =+E20/C21 -> 2.1706841 | G21: CUB/SC | H21: 2758.46 | I21: 45413 | J21: =+J20/H21 -> 2.1445562 | P21: 2758.46 | Q21: 45413 | R21: 2.1739887
R23: =H20-P20 -> 12142282

Sheet ORÇAMENTO_EXECUTIVO_REV02
A1: REV02 | J1: REV01
A2: ETAPA | B2: VALOR ORÇADO | C2: % | D2: VALOR / m² | J2: VALOR ORÇADO | K2: % | L2: VALOR / m²
A3: GERENCIAMENTO TÉCNICO E ADMINISTRATIVO | B3: =[4]CUSTOS_INDIRETOS!$F$93 -> 13510709 | C3: =B3/B$20 -> 0.15543583 | D3: =B3/ORÇAMENTO_EXECUTIVO_REV02!T$3 -> 919.50744 | J3: 8526873.7 | K3: 0.11402738 | L3: 683.80635 | N3: =B3-J3 -> 4983835.4 | P3: =D3-L3 -> 235.7011 | S3: ÁREA CONSTRUÍDA | T3: =DADOS_INICIAIS!E11 -> 14693.42 | U3: m²
A4: MOVIMENTAÇÃO DE TERRA | B4: =MOVIMENTAÇÃO_DE_TERRA!F35 -> 2545063.4 | C4: =B4/B$20 -> 0.029280035 | D4: =B4/ORÇAMENTO_EXECUTIVO_REV02!T$3 -> 173.2111 | J4: 2450076.2 | K4: 0.03276415 | L4: 196.48205 | N4: =B4-J4 -> 94987.21 | P4: =D4-L4 -> -23.270956
A5: INFRAESTRUTURA | B5: ='INFRAESTRUTURA REV01'!G31 -> 5742340 | C5: =B5/B$20 -> 0.066063549 | D5: =B5/ORÇAMENTO_EXECUTIVO_REV02!T$3 -> 390.81031 | J5: 5278318.1 | K5: 0.070585399 | L5: 423.29083 | N5: =B5-J5 -> 464021.92 | P5: =D5-L5 -> -32.480518
A6: CONTENÇÕES | B6: =CONTENÇÕES!G33 -> 1644604.6 | C6: =B6/B$20 -> 0.018920582 | D6: =B6/ORÇAMENTO_EXECUTIVO_REV02!T$3 -> 111.92796 | J6: 1644604.6 | K6: 0.021992815 | L6: 131.88785 | N6: =B6-J6 -> 0 | P6: =D6-L6 -> -19.959888
A7: SUPRAESTRUTURA | B7: =SUPRAESTRUTURA!G25 -> 16955390 | C7: =B7/B$20 -> 0.19506564 | D7: =B7/ORÇAMENTO_EXECUTIVO_REV02!T$3 -> 1153.9444 | J7: 13332389 | K7: 0.17829013 | L7: 1069.1811 | N7: =B7-J7 -> 3623001 | P7: =D7-L7 -> 84.763314
A8: ALVENARIA | B8: =Alvenaria!G25 -> 3148673.4 | C8: =B8/B$20 -> 0.03622435 | D8: =B8/ORÇAMENTO_EXECUTIVO_REV02!T$3 -> 214.29139 | J8: 3148673.4 | K8: 0.042106285 | L8: 252.50554 | N8: =B8-J8 -> 0 | P8: =D8-L8 -> -38.214151
A9: INSTALAÇÕES ELÉTRICAS, HIDRÁULICAS, GLP E PREVENTIVAS | B9: =Instalações!D35 -> 6206500.6 | C9: =B9/B$20 -> 0.071403549 | D9: =B9/ORÇAMENTO_EXECUTIVO_REV02!T$3 -> 422.4 | J9: 5267209.7 | K9: 0.070436851 | L9: 422.4 | N9: =B9-J9 -> 939290.88 | P9: =D9-L9 -> 0
A10: EQUIPAMENTOS E SISTEMAS ESPECIAIS | B10: ='Sistemas Especiais'!D45 -> 7227828.5 | C10: =B10/B$20 -> 0.083153558 | D10: =B10/ORÇAMENTO_EXECUTIVO_REV02!T$3 -> 491.9092 | J10: 6870035.2 | K10: 0.091870965 | L10: 550.93741 | N10: =B10-J10 -> 357793.33 | P10: =D10-L10 -> -59.028203
A11: IMPERMEABILIZAÇÃO | B11: =Impermeabilização!G28 -> 1260169.1 | C11: =B11/B$20 -> 0.01449779 | D11: =B11/ORÇAMENTO_EXECUTIVO_REV02!T$3 -> 85.764176 | J11: 1100757.3 | K11: 0.014720105 | L11: 88.274423 | N11: =B11-J11 -> 159411.71 | P11: =D11-L11 -> -2.5102477
A12: REVESTIMENTOS INTERNOS EM PISO E PAREDE | B12: ='Acabamentos de Piso'!G33+'Rev. Internos de Parede'!G23 -> 1754484.6 | C12: =B12/B$20 -> 0.020184712 | D12: =B12/ORÇAMENTO_EXECUTIVO_REV02!T$3 -> 119.40614 | J12: 1637724.6 | K12: 0.02190081 | L12: 131.33611 | N12: =B12-J12 -> 116760.04 | P12: =D12-L12 -> -11.929971
A13: REVESTIMENTOS E ACABAMENTOS INTERNOS EM TETO | B13: ='Acabamentos de Teto'!G21 -> 1764973.6 | C13: =B13/B$20 -> 0.020305384 | D13: =B13/ORÇAMENTO_EXECUTIVO_REV02!T$3 -> 120.12 | J13: 1292981.4 | K13: 0.017290661 | L13: 103.68969 | N13: =B13-J13 -> 471992.18 | P13: =D13-L13 -> 16.430308
A14: ACABAMENTOS EM PISO E PAREDE | B14: ='Acabamentos de Piso'!G34+'Rev. Internos de Parede'!G24 -> 4311125.5 | C14: =B14/B$20 -> 0.049597942 | D14: =B14/ORÇAMENTO_EXECUTIVO_REV02!T$3 -> 293.40518 | J14: 4169253.4 | K14: 0.055754203 | L14: 334.35021 | N14: =B14-J14 -> 141872.06 | P14: =D14-L14 -> -40.945028
A15: PINTURA INTERNA | B15: ='Pintura Interna'!G21 -> 2297072.5 | C15: =B15/B$20 -> 0.02642699 | D15: =B15/ORÇAMENTO_EXECUTIVO_REV02!T$3 -> 156.33341 | J15: 2000841.4 | K15: 0.026756665 | L15: 160.456 | N15: =B15-J15 -> 296231.1 | P15: =D15-L15 -> -4.1225877 | R15: Mais revestimentos parede banheiro
A16: ESQUADRIAS, VIDROS E FERRAGENS | B16: =Esquadrias!G29 -> 9402166.4 | C16: =B16/B$20 -> 0.10816853 | D16: =B16/ORÇAMENTO_EXECUTIVO_REV02!T$3 -> 639.88958 | J16: 9377705.7 | K16: 0.12540531 | L16: 752.03819 | N16: =B16-J16 -> 24460.7 | P16: =D16-L16 -> -112.14861
A17: REVESTIMENTOS E ACABAMENTOS DE FACHADA | B17: =SUM(FACHADA!K11:K20) -> 3087626.2 | C17: =B17/B$20 -> 0.035522025 | D17: =B17/ORÇAMENTO_EXECUTIVO_REV02!T$3 -> 210.13666 | J17: 3087626.2 | K17: 0.04128992 | L17: 247.60991 | N17: =B17-J17 -> 0 | P17: =D17-L17 -> -37.473247
A18: SERVIÇOS COMPLEMENTARES | B18: =Complementares!F17 -> 3531038.3 | C18: =B18/B$20 -> 0.040623321 | D18: =B18/ORÇAMENTO_EXECUTIVO_REV02!T$3 -> 240.31426 | J18: 3416073 | K18: 0.045682142 | L18: 273.94946 | N18: =B18-J18 -> 114965.29 | P18: =D18-L18 -> -33.6352
A19: IMPREVISTOS E CONTINGENCIAS | B19: =SUM(B3:B18)*0.03 -> 2531693 | C19: =B19/B$20 -> 0.029126214 | D19: =B19/ORÇAMENTO_EXECUTIVO_REV02!T$3 -> 172.30114 | J19: 2178034.3 | K19: 0.029126214 | L19: 174.66585 | N19: =B19-J19 -> 353658.68 | P19: =D19-L19 -> -2.3647166
A20: TOTAL | B20: =SUM(B3:B19) -> 86921459 | C20: =SUM(C3:C19) -> 1 | D20: =SUM(D3:D19) -> 5915.6724 | J20: 74779177 | K20: 1 | L20: 5996.861
A21: CUB/SC | B21: 2758.46 | C21: 45413 | D21: =+D20/B21 -> 2.1445562 | J21: 2758.46 | K21: 45413 | L21: 2.1739887
L23: =B20-J20 -> 12142282

Sheet ORÇAMENTO_EXECUTIVO_REV01
A1: ETAPA | B1: VALOR ORÇADO | C1: % | D1: VALOR / m²
A2: GERENCIAMENTO TÉCNICO E ADMINISTRATIVO | B2: 8526873.7 | C2: 0.11402738 | D2: 683.80635 | F2: ÁREA CONSTRUÍDA | G2: 12469.72 | H2: m²
A3: MOVIMENTAÇÃO DE TERRA | B3: 2450076.2 | C3: 0.03276415 | D3: 196.48205
A4: INFRAESTRUTURA | B4: 5278318.1 | C4: 0.070585399 | D4: 423.29083
A5: CONTENÇÕES | B5: 1644604.6 | C5: 0.021992815 | D5: 131.88785
A6: SUPRAESTRUTURA | B6: 13332389 | C6: 0.17829013 | D6: 1069.1811
A7: ALVENARIA | B7: 3148673.4 | C7: 0.042106285 | D7: 252.50554
A8: INSTALAÇÕES ELÉTRICAS, HIDRÁULICAS, GLP E PREVENTIVAS | B8: 5267209.7 | C8: 0.070436851 | D8: 422.4
A9: EQUIPAMENTOS E SISTEMAS ESPECIAIS | B9: 6870035.2 | C9: 0.091870965 | D9: 550.93741
A10: IMPERMEABILIZAÇÃO | B10: 1100757.3 | C10: 0.014720105 | D10: 88.274423
A11: REVESTIMENTOS INTERNOS EM PISO E PAREDE | B11: 1637724.6 | C11: 0.02190081 | D11: 131.33611
A12: REVESTIMENTOS E ACABAMENTOS INTERNOS EM TETO | B12: 1292981.4 | C12: 0.017290661 | D12: 103.68969
A13: ACABAMENTOS EM PISO E PAREDE | B13: 4169253.4 | C13: 0.055754203 | D13: 334.35021
A14: PINTURA INTERNA | B14: 2000841.4 | C14: 0.026756665 | D14: 160.456 | E14: Mais revestimentos parede banheiro
A15: ESQUADRIAS, VIDROS E FERRAGENS | B15: 9377705.7 | C15: 0.12540531 | D15: 752.03819
A16: REVESTIMENTOS E ACABAMENTOS DE FACHADA | B16: 3087626.2 | C16: 0.04128992 | D16: 247.60991
A17: SERVIÇOS COMPLEMENTARES | B17: 3416073 | C17: 0.045682142 | D17: 273.94946
A18: IMPREVISTOS E CONTINGENCIAS | B18: 2178034.3 | C18: 0.029126214 | D18: 174.66585
A19: TOTAL | B19: 74779177 | C19: 1 | D19: 5996.861
A20: CUB/SC | B20: 2758.46 | C20: 45413 | D20: 2.1739887

Sheet ANÁLISE_CUSTOS
A1: ETAPA | B1: OBRA | D1: OBRA SIMILAR | E1: JUSTIFICATIVA
B2: VALOR | C2: VALOR / m² | D2: VALOR / m²
A3: =ORÇAMENTO_EXECUTIVO_REV02!A4 -> MOVIMENTAÇÃO DE TERRA | B3: =ORÇAMENTO_EXECUTIVO_REV02!B4 -> 2545063.4 | C3: =ORÇAMENTO_EXECUTIVO_REV02!D4 -> 173.2111 | D3: =FIXED(CÁLCULO_MÉDIAS!P14,2,FALSE)&" "&"-"&FIXED(CÁLCULO_MÉDIAS!Q14,2,FALSE) -> 110,00 -160,00 | E3: MAIOR ÁREA DE ESCAVAÇÃO E BOTA-FORA EM RELAÇÃO A ÁREA CONSTRUÍDA
A4: =ORÇAMENTO_EXECUTIVO_REV02!A5 -> INFRAESTRUTURA | B4: =ORÇAMENTO_EXECUTIVO_REV02!B5 -> 5742340 | C4: =ORÇAMENTO_EXECUTIVO_REV02!D5 -> 390.81031 | D4: =FIXED(CÁLCULO_MÉDIAS!P15,2,FALSE)&" "&"-"&FIXED(CÁLCULO_MÉDIAS!Q15,2,FALSE) -> 180,00 -250,00 | E4: MAIOR PROPORÇÃO DE PROJEÇÃO DE EMBASAMETO DEVIDO A HORIZONTALIDADE
A5: =ORÇAMENTO_EXECUTIVO_REV02!A6 -> CONTENÇÕES | B5: =ORÇAMENTO_EXECUTIVO_REV02!B6 -> 1644604.6 | C5: =ORÇAMENTO_EXECUTIVO_REV02!D6 -> 111.92796 | D5: =FIXED(CÁLCULO_MÉDIAS!P16,2,FALSE)&" "&"-"&FIXED(CÁLCULO_MÉDIAS!Q16,2,FALSE) -> 70,00 -110,00 | E5: MAIOR PROPORÇÃO DE PROJEÇÃO DO SUBSOLO / ESPESSURA DA PAREDE
A6: =ORÇAMENTO_EXECUTIVO_REV02!A7 -> SUPRAESTRUTURA | B6: =ORÇAMENTO_EXECUTIVO_REV02!B7 -> 16955390 | C6: =ORÇAMENTO_EXECUTIVO_REV02!D7 -> 1153.9444 | D6: =FIXED(CÁLCULO_MÉDIAS!P17,2,FALSE)&" "&"-"&FIXED(CÁLCULO_MÉDIAS!Q17,2,FALSE) -> 760,00 -1.050,00 | E6: PAREDES DE CONCRETO / RESISTÊNCIA E ADITIVO DO CONCRETO
A7: =ORÇAMENTO_EXECUTIVO_REV02!A8 -> ALVENARIA | B7: =ORÇAMENTO_EXECUTIVO_REV02!B8 -> 3148673.4 | C7: =ORÇAMENTO_EXECUTIVO_REV02!D8 -> 214.29139 | D7: =FIXED(CÁLCULO_MÉDIAS!P18,2,FALSE)&" "&"-"&FIXED(CÁLCULO_MÉDIAS!Q18,2,FALSE) -> 190,00 -280,00
A8: =ORÇAMENTO_EXECUTIVO_REV02!A9 -> INSTALAÇÕES ELÉTRICAS, HIDRÁULICAS, GLP E PREVENTIVAS | B8: =ORÇAMENTO_EXECUTIVO_REV02!B9 -> 6206500.6 | C8: =ORÇAMENTO_EXECUTIVO_REV02!D9 -> 422.4 | D8: =FIXED(CÁLCULO_MÉDIAS!P19,2,FALSE)&" "&"-"&FIXED(CÁLCULO_MÉDIAS!Q19,2,FALSE) -> 400,00 -530,00
A9: =ORÇAMENTO_EXECUTIVO_REV02!A10 -> EQUIPAMENTOS E SISTEMAS ESPECIAIS | B9: =ORÇAMENTO_EXECUTIVO_REV02!B10 -> 7227828.5 | C9: =ORÇAMENTO_EXECUTIVO_REV02!D10 -> 491.9092 | D9: =FIXED(CÁLCULO_MÉDIAS!P20,2,FALSE)&" "&"-"&FIXED(CÁLCULO_MÉDIAS!Q20,2,FALSE) -> 330,00 -370,00 | E9: EQUIPAMENTOS E QUANTIDADE DE PISCINAS AQUECIDAS, LAGO E CARREGAMENTO CARRO
A10: =ORÇAMENTO_EXECUTIVO_REV02!A11 -> IMPERMEABILIZAÇÃO | B10: =ORÇAMENTO_EXECUTIVO_REV02!B11 -> 1260169.1 | C10: =ORÇAMENTO_EXECUTIVO_REV02!D11 -> 85.764176 | D10: =FIXED(CÁLCULO_MÉDIAS!P21,2,FALSE)&" "&"-"&FIXED(CÁLCULO_MÉDIAS!Q21,2,FALSE) -> 70,00 -110,00 | E10: QUANTIDADE DE BANHEIROS, PISCINAS, LAGO E TELHADO VERDE
A11: =ORÇAMENTO_EXECUTIVO_REV02!A12 -> REVESTIMENTOS INTERNOS EM PISO E PAREDE | B11: =ORÇAMENTO_EXECUTIVO_REV02!B12 -> 1754484.6 | C11: =ORÇAMENTO_EXECUTIVO_REV02!D12 -> 119.40614 | D11: =FIXED(CÁLCULO_MÉDIAS!P22,2,FALSE)&" "&"-"&FIXED(CÁLCULO_MÉDIAS!Q22,2,FALSE) -> 110,00 -250,00 | E11: DRYWALL
A12: =ORÇAMENTO_EXECUTIVO_REV02!A13 -> REVESTIMENTOS E ACABAMENTOS INTERNOS EM TETO | B12: =ORÇAMENTO_EXECUTIVO_REV02!B13 -> 1764973.6 | C12: =ORÇAMENTO_EXECUTIVO_REV02!D13 -> 120.12 | D12: =FIXED(CÁLCULO_MÉDIAS!P23,2,FALSE)&" "&"-"&FIXED(CÁLCULO_MÉDIAS!Q23,2,FALSE) -> 80,00 -110,00
A13: =ORÇAMENTO_EXECUTIVO_REV02!A14 -> ACABAMENTOS EM PISO E PAREDE | B13: =ORÇAMENTO_EXECUTIVO_REV02!B14 -> 4311125.5 | C13: =ORÇAMENTO_EXECUTIVO_REV02!D14 -> 293.40518 | D13: =FIXED(CÁLCULO_MÉDIAS!P24,2,FALSE)&" "&"-"&FIXED(CÁLCULO_MÉDIAS!Q24,2,FALSE) -> 210,00 -280,00 | E13: CUSTO DOS REVESTIMENTOS: PEDRA RÚSTICA EM CACOS E MADEIRA ENGENHEIRADA / QUANTIDADE DE BANHEIROS COM REVESTIMENTO
A14: =ORÇAMENTO_EXECUTIVO_REV02!A15 -> PINTURA INTERNA | B14: =ORÇAMENTO_EXECUTIVO_REV02!B15 -> 2297072.5 | C14: =ORÇAMENTO_EXECUTIVO_REV02!D15 -> 156.33341 | D14: =FIXED(CÁLCULO_MÉDIAS!P25,2,FALSE)&" "&"-"&FIXED(CÁLCULO_MÉDIAS!Q25,2,FALSE) -> 100,00 -190,00
A15: =ORÇAMENTO_EXECUTIVO_REV02!A16 -> ESQUADRIAS, VIDROS E FERRAGENS | B15: =ORÇAMENTO_EXECUTIVO_REV02!B16 -> 9402166.4 | C15: =ORÇAMENTO_EXECUTIVO_REV02!D16 -> 639.88958 | D15: =FIXED(CÁLCULO_MÉDIAS!P26,2,FALSE)&" "&"-"&FIXED(CÁLCULO_MÉDIAS!Q26,2,FALSE) -> 580,00 -290,00 | E15: ALTA DENSIDADE DE ESQUADRIAS - PADRÃO SLIM
A16: =ORÇAMENTO_EXECUTIVO_REV02!A17 -> REVESTIMENTOS E ACABAMENTOS DE FACHADA | B16: ='Rev. Fachada'!G32 -> 3087626.2 | C16: =ORÇAMENTO_EXECUTIVO_REV02!D17 -> 210.13666 | D16: =FIXED(CÁLCULO_MÉDIAS!P27,2,FALSE)&" "&"-"&FIXED(CÁLCULO_MÉDIAS!Q27,2,FALSE) -> 110,00 -210,00 | E16: ACABAMENTOS DIFERENCIADOS
A17: =ORÇAMENTO_EXECUTIVO_REV02!A18 -> SERVIÇOS COMPLEMENTARES | B17: =ORÇAMENTO_EXECUTIVO_REV02!B18 -> 3531038.3 | C17: =ORÇAMENTO_EXECUTIVO_REV02!D18 -> 240.31426 | D17: =FIXED(CÁLCULO_MÉDIAS!P28,2,FALSE)&" "&"-"&FIXED(CÁLCULO_MÉDIAS!Q28,2,FALSE) -> 180,00 -310,00 | E17: MAIOR ÁREA DE PAISAGISMO, MAS MENOR QUANTIDADE ÁREAS MOBILIADAS
A18: TOTAL | B18: =SUM(B3:B17) -> 70879057 | C18: =SUM(C3:C17) -> 4823.8638 | D18: =FIXED(CÁLCULO_MÉDIAS!P30,2,FALSE)&" "&"-"&FIXED(CÁLCULO_MÉDIAS!Q30,2,FALSE) -> 3.480,00 -4.500,00
B22: 2007.57
B23: 2461.35
B24: =B23/B22 -> 1.2260345
C27: 1.1023
A29: 900,00 - 1100 | B29: 900
A30: 25,00 - 30,00 | B30: 25
A31: 15,00 - 22,00 | B31: 15
A32: 150,00 - 200,00 | B32: 150
A33: 440,00 - 510,00 | B33: 440
A34: -
A35: 55,00 - 70,00 | B35: 55
A36: 170,00 - 200,00 | B36: 170
A37: 165,00 - 230,00 | B37: 165
A38: 40,00 - 70,00 | B38: 40
A39: 55,00 - 77,00 | B39: 55
A40: 35,00 - 50,00 | B40: 35
A41: 130,00 - 175,00 | B41: 130
A42: 35,00 - 65,00 | B42: 35
A43: 35,00 - 55,00 | B43: 35
A44: 430,00 - 550,00 | B44: 430
A45: 35,00 - 50,00 | B45: 35
A46: 150,00 - 220,00 | B46: 150

Sheet AREAS_PRIVATIVAS
A1: ETAPA | B1: VALOR ORÇADO | C1: % | D1: VALOR / m²
A2: GERENCIAMENTO TÉCNICO E ADMINISTRATIVO | B2: =ORÇAMENTO_EXECUTIVO_REV03!C3 -> 14538860 | C2: =B2/B$19 -> 0.16525102 | D2: =B2/AREAS_PRIVATIVAS!G$2 -> 1621.3468 | F2: ÁREA PRIVATIVA | G2: =B24 -> 8967.15 | I2: m²
A3: MOVIMENTAÇÃO DE TERRA | B3: =ORÇAMENTO_EXECUTIVO_REV03!C4 -> 2545063.4 | C3: =B3/B$19 -> 0.0289276 | D3: =B3/AREAS_PRIVATIVAS!G$2 -> 283.82077
A4: CONTENÇÃO | B4: =ORÇAMENTO_EXECUTIVO_REV03!C5 -> 5742340 | C4: =B4/B$19 -> 0.065268361 | D4: =B4/AREAS_PRIVATIVAS!G$2 -> 640.37515
A5: INFRAESTRUTURA | B5: =ORÇAMENTO_EXECUTIVO_REV03!C6 -> 1644604.6 | C5: =B5/B$19 -> 0.01869284 | D5: =B5/AREAS_PRIVATIVAS!G$2 -> 183.40326
A6: SUPRAESTRUTURA | B6: =ORÇAMENTO_EXECUTIVO_REV03!C7 -> 16955390 | C6: =B6/B$19 -> 0.19271769 | D6: =B6/AREAS_PRIVATIVAS!G$2 -> 1890.8338
A7: ALVENARIA | B7: =ORÇAMENTO_EXECUTIVO_REV03!C8 -> 3148673.4 | C7: =B7/B$19 -> 0.035788328 | D7: =B7/AREAS_PRIVATIVAS!G$2 -> 351.13424
A8: INSTALAÇÕES ELÉTRICAS, HIDRÁULICAS, GLP E PREVENTIVAS | B8: =ORÇAMENTO_EXECUTIVO_REV03!C9 -> 6206500.6 | C8: =B8/B$19 -> 0.070544085 | D8: =B8/AREAS_PRIVATIVAS!G$2 -> 692.13748
A9: EQUIPAMENTOS E SISTEMAS ESPECIAIS | B9: =ORÇAMENTO_EXECUTIVO_REV03!C10 -> 7227828.5 | C9: =B9/B$19 -> 0.082152662 | D9: =B9/AREAS_PRIVATIVAS!G$2 -> 806.03408
A10: IMPERMEABILIZAÇÃO | B10: =ORÇAMENTO_EXECUTIVO_REV03!C11 -> 1260169.1 | C10: =B10/B$19 -> 0.014323284 | D10: =B10/AREAS_PRIVATIVAS!G$2 -> 140.53172
A11: REVESTIMENTOS INTERNOS EM PISO E PAREDE | B11: =ORÇAMENTO_EXECUTIVO_REV03!C12 -> 1754484.6 | C11: =B11/B$19 -> 0.019941754 | D11: =B11/AREAS_PRIVATIVAS!G$2 -> 195.65688
A12: REVESTIMENTOS E ACABAMENTOS INTERNOS EM TETO | B12: =ORÇAMENTO_EXECUTIVO_REV03!C13 -> 1764973.6 | C12: =B12/B$19 -> 0.020060974 | D12: =B12/AREAS_PRIVATIVAS!G$2 -> 196.8266
A13: ACABAMENTOS EM PISO E PAREDE | B13: =ORÇAMENTO_EXECUTIVO_REV03!C14 -> 4311125.5 | C13: =B13/B$19 -> 0.049000946 | D13: =B13/AREAS_PRIVATIVAS!G$2 -> 480.76875
A14: PINTURA INTERNA | B14: =ORÇAMENTO_EXECUTIVO_REV03!C15 -> 2297072.5 | C14: =B14/B$19 -> 0.026108896 | D14: =B14/AREAS_PRIVATIVAS!G$2 -> 256.16528
... A18: IMPREVISTOS E CONTINGENCIAS | B18: =ORÇAMENTO_EXECUTIVO_REV03!C19 -> 2562537.5 | C18: =B18/B$19 -> 0.029126214 | D18: =B18/AREAS_PRIVATIVAS!G$2 -> 285.76945
A19: TOTAL | B19: =SUM(B2:B18) -> 87980454 | C19: =SUM(C2:C18) -> 1 | D19: =SUM(D2:D18) -> 9811.4177
A22: INFORMAÇÕES DE ÁREAS ENVIADAS PELO CLIENTE
A23: DESCRIÇÃO | B23: ÁREA (m²) | C23: QUANT. | D23: VALOR TOTAL
A24: VALOR POR ÁREA PRIVATIVA (R$/m²) | B24: =SUMPRODUCT(B25:B48,C25:C48) -> 8967.15 | D24: =B19/AREAS_PRIVATIVAS!B24 -> 9811.4177
A25: JD 01 (CAVE ÁGUA) | B25: 440.5 | C25: 1 | D25: =B25*$D$24 -> 4321929.5
A26: JD 02 (CAVE ÁGUA) | B26: 283.59 | C26: 1 | D26: =B26*$D$24 -> 2782419.9
A27: D 01 (CAVE ÁGUA) | B27: 400.29 | C27: 1 | D27: =B27*$D$24 -> 3927412.4
A28: JD 04 (CAVE ÁGUA) | B28: 299.6 | C28: 1 | D28: =B28*$D$24 -> 2939500.7
A29: M 01 (CAVE ÁGUA) | B29: 316.11 | C29: 1 | D29: =B29*$D$24 -> 3101487.2
A30: M 02 (CAVE FOGO) | B30: 258.86 | C30: 1 | D30: =B30*$D$24 -> 2539783.6
A31: D 02 (CAVE ÁGUA) | B31: 313.82 | C31: 1 | D31: =B31*$D$24 -> 3079019.1
A32: M 04 (CAVE ÁGUA) | B32: 240.94 | C32: 1 | D32: =B32*$D$24 -> 2363963 | I32: REPETE UNIDADE M 04 AO INVES DE MOSTRAR COB 04 CAVE FOGO
A33: COB 01 (CAVE ÁGUA) | B33: 547.47 | C33: 1 | D33: =B33*$D$24 -> 5371456.8 | I33: PAG 25 = PAG 21
A34: COB 02 (CAVE FOGO) | B34: 441.27 | C34: 1 | D34: =B34*$D$24 -> 4329484.3
A35: D 03 (CAVE ÁGUA) | B35: 429.88 | C35: 1 | D35: =B35*$D$24 -> 4217732.2 | I35: REPETE UNIDADE D 03 AO INVES DE MOSTRAR D 01 CAVE ÁGUA
A36: COB 04 (CAVE ÁGUA) | B36: 410.08 | C36: 1 | D36: =B36*$D$24 -> 4023466.2 | I36: PAG 4=PAG 12
A37: JD 01 (CAVE FOGO) | B37: 420.3 | C37: 1 | D37: =B37*$D$24 -> 4123738.9
A38: JD 02 (CAVE FOGO) | B38: 347.94 | C38: 1 | D38: =B38*$D$24 -> 3413784.7
A39: JD 03 (CAVE FOGO) | B39: 397.34 | C39: 1 | D39: =B39*$D$24 -> 3898468.7
A40: JD 04 (CAVE FOGO) | B40: 326.96 | C40: 1 | D40: =B40*$D$24 -> 3207941.1
A41: M 01 (CAVE FOGO) | B41: 316.11 | C41: 1 | D41: =B41*$D$24 -> 3101487.2
A42: M 02 (CAVE ÁGUA) | B42: 258.86 | C42: 1 | D42: =B42*$D$24 -> 2539783.6
A43: M 03 (CAVE FOGO) | B43: 308.81 | C43: 1 | D43: =B43*$D$24 -> 3029863.9
A44: M 04 (CAVE FOGO) | B44: 253.57 | C44: 1 | D44: =B44*$D$24 -> 2487881.2
A45: COB 01 (CAVE FOGO) | B45: 547.47 | C45: 1 | D45: =B45*$D$24 -> 5371456.8
A46: COB 02 (CAVE ÁGUA) | B46: 441.27 | C46: 1 | D46: =B46*$D$24 -> 4329484.3
A47: COB 03 (CAVE FOGO) | B47: 543.03 | C47: 1 | D47: =B47*$D$24 -> 5327894.2
A48: COB 04 (CAVE FOGO) | B48: 423.08 | C48: 1 | D48: =B48*D24 -> 4151014.6
A51: ÁREA DE LAZER

Sheet CÁLCULO_MÉDIAS
C3: DATA BASE | D3: 45231 | E3: DATA BASE | F3: 44958 | G3: DATA BASE | H3: 45047 | I3: DATA BASE | J3: 44652 | K3: DATA BASE | L3: 45078 | M3: DATA BASE | N3: 45231
C4: CUB | D4: 2754.98 | E4: CUB | F4: 2662.47 | G4: CUB | H4: 2688.94 | I4: CUB | J4: 2461.35 | K4: CUB | L4: 2725.79 | M4: CUB | N4: 2754.98
C5: ÁREA TERRENO | D5: 2394.02 | E5: ÁREA TERRENO | G5: ÁREA TERRENO | I5: ÁREA TERRENO | K5: ÁREA TERRENO | M5: ÁREA TERRENO
C6: ÁREA CONSTRUÍDA | D6: 7642.76 | E6: ÁREA CONSTRUÍDA | F6: 14888.46 | G6: ÁREA CONSTRUÍDA | H6: 3282.64 | I6: ÁREA CONSTRUÍDA | J6: 4811.62 | K6: ÁREA CONSTRUÍDA | L6: 7305.16 | M6: ÁREA CONSTRUÍDA | N6: 7642.76
C7: PAVTOS | D7: Subsolo com vagas de garagem Térreo, 2º e 3º PVTO com 2 aptos por andar Cobertura com Rooftop | E7: PAVTOS | G7: PAVTOS | I7: PAVTOS | K7: PAVTOS | M7: PAVTOS
C8: ESPECIFICAÇÕES | D8: 6 apartamentos 3 Elevadores Salão de festas e academia Pavimento Rooftop | E8: ESPECIFICAÇÕES | G8: ESPECIFICAÇÕES | I8: ESPECIFICAÇÕES | K8: ESPECIFICAÇÕES | M8: ESPECIFICAÇÕES
C9: DIFERENCIAIS | D9: -Uma piscina por apartamento - Padrão elevado de esquadrias - Alto investimento em paisagismo | E9: DIFERENCIAIS | G9: DIFERENCIAIS | H9: Hélice | I9: DIFERENCIAIS | J9: Hélice | K9: DIFERENCIAIS | M9: DIFERENCIAIS
G10: Médias extraídas da apresentação KSA | P10: *considerando 1,1 de majoração de médias
C11: ESTALEIRO - ABC EMPREENDIMENTOS (PRELIMINAR) | E11: LIVE - LUMIS (EXECUTIVO) | G11: MENDES - BRAVA SIXTEEN | I11: MENDES - BRAVA MUNDO | K11: COTA - AFONSO PENA | M11: ABC - ESTALEIRO | P11: MÉDIAS
C12: VALOR / M2 | D12: INDEXADO | F12: INDEXADO | G12: VALOR / M2 | H12: INDEXADO | I12: VALOR / M2 | J12: INDEXADO | K12: VALOR / M2 | L12: INDEXADO | M12: VALOR / M2 | N12: INDEXADO | P12: MÍNIMA | Q12: MÁXIMA
B13: GERENCIAMENTO TECNICO E ADMINISTRATIVO | C13: 400.87571 | D13: =ORÇAMENTO_EXECUTIVO_REV02!$B$21/CÁLCULO_MÉDIAS!D$4*C13 -> 401.38208 | E13: 194.2328 | F13: =ORÇAMENTO_EXECUTIVO_REV02!$B$21/CÁLCULO_MÉDIAS!F$4*E13 -> 201.23547 | G13: 750.56 | H13: =ORÇAMENTO_EXECUTIVO_REV02!$B$21/CÁLCULO_MÉDIAS!H$4*G13 -> 769.96502 | I13: 647.1 | J13: =ORÇAMENTO_EXECUTIVO_REV02!$B$21/CÁLCULO_MÉDIAS!J$4*I13 -> 725.21156 | K13: 186.67 | L13: =ORÇAMENTO_EXECUTIVO_REV02!$B$21/CÁLCULO_MÉDIAS!L$4*K13 -> 188.90734 | M13: 400.88 | N13: =ORÇAMENTO_EXECUTIVO_REV02!$B$21/CÁLCULO_MÉDIAS!N$4*M13 -> 401.38638 | P13: 220 | Q13: 440 | R13: GERENCIAMENTO TECNICO E ADMINISTRATIVO
B14: MOVIMENTAÇÃO DE TERRA | C14: 38.001581 | D14: =ORÇAMENTO_EXECUTIVO_REV02!$B$21/CÁLCULO_MÉDIAS!D$4*C14 -> 38.049583 | E14: 131.35298 | F14: =ORÇAMENTO_EXECUTIVO_REV02!$B$21/CÁLCULO_MÉDIAS!F$4*E14 -> 136.08865 | G14: 40.84 | H14: =ORÇAMENTO_EXECUTIVO_REV02!$B$21/CÁLCULO_MÉDIAS!H$4*G14 -> 41.89588 | I14: 93.34 | J14: =ORÇAMENTO_EXECUTIVO_REV02!$B$21/CÁLCULO_MÉDIAS!J$4*I14 -> 104.60709 | K14: 89.11 | L14: =ORÇAMENTO_EXECUTIVO_REV02!$B$21/CÁLCULO_MÉDIAS!L$4*K14 -> 90.178029 | M14: 38 | N14: =ORÇAMENTO_EXECUTIVO_REV02!$B$21/CÁLCULO_MÉDIAS!N$4*M14 -> 38.048 | P14: 110 | Q14: 160 | R14: MOVIMENTAÇÃO DE TERRA
B15: INFRAESTRUTURA | C15: 160.6985 | D15: =ORÇAMENTO_EXECUTIVO_REV02!$B$21/CÁLCULO_MÉDIAS!D$4*C15 -> 160.90149 | E15: 99.325701 | F15: =ORÇAMENTO_EXECUTIVO_REV02!$B$21/CÁLCULO_MÉDIAS!F$4*E15 -> 102.90669 | G15: 134.84 | H15: =ORÇAMENTO_EXECUTIVO_REV02!$B$21/CÁLCULO_MÉDIAS!H$4*G15 -> 138.32616 | I15: 316.11 | J15: =ORÇAMENTO_EXECUTIVO_REV02!$B$21/CÁLCULO_MÉDIAS!J$4*I15 -> 354.26769 | K15: 630.69 | L15: =ORÇAMENTO_EXECUTIVO_REV02!$B$21/CÁLCULO_MÉDIAS!L$4*K15 -> 638.24915 | M15: 160.7 | N15: =ORÇAMENTO_EXECUTIVO_REV02!$B$21/CÁLCULO_MÉDIAS!N$4*M15 -> 160.90299 | P15: 180 | Q15: 250 | R15: INFRAESTRUTURA
B16: CONTENÇÕES | P16: 70 | Q16: 110 | R16: CONTENÇÕES
B17: SUPRAESTRUTURA | C17: 678.58014 | D17: =ORÇAMENTO_EXECUTIVO_REV02!$B$21/CÁLCULO_MÉDIAS!D$4*C17 -> 679.4373 | E17: 670.8352 | F17: =ORÇAMENTO_EXECUTIVO_REV02!$B$21/CÁLCULO_MÉDIAS!F$4*E17 -> 695.02082 | G17: 769.54 | H17: =ORÇAMENTO_EXECUTIVO_REV02!$B$21/CÁLCULO_MÉDIAS!H$4*G17 -> 789.43573 | I17: 749.05 | J17: =ORÇAMENTO_EXECUTIVO_REV02!$B$21/CÁLCULO_MÉDIAS!J$4*I17 -> 839.46796 | K17: 939.15 | L17: =ORÇAMENTO_EXECUTIVO_REV02!$B$21/CÁLCULO_MÉDIAS!L$4*K17 -> 950.4062 | M17: 678.58 | N17: =ORÇAMENTO_EXECUTIVO_REV02!$B$21/CÁLCULO_MÉDIAS!N$4*M17 -> 679.43716 | P17: 760 | Q17: 1050 | R17: SUPRAESTRUTURA
B18: ALVENARIA | C18: 81.675557 | D18: =ORÇAMENTO_EXECUTIVO_REV02!$B$21/CÁLCULO_MÉDIAS!D$4*C18 -> 81.778727 | E18: 150.14829 | F18: =ORÇAMENTO_EXECUTIVO_REV02!$B$21/CÁLCULO_MÉDIAS!F$4*E18 -> 155.56159 | G18: 161.68 | H18: =ORÇAMENTO_EXECUTIVO_REV02!$B$21/CÁLCULO_MÉDIAS!H$4*G18 -> 165.86008 | I18: 151.59 | J18: =ORÇAMENTO_EXECUTIVO_REV02!$B$21/CÁLCULO_MÉDIAS!J$4*I18 -> 169.88846 | K18: 249.15 | L18: =ORÇAMENTO_EXECUTIVO_REV02!$B$21/CÁLCULO_MÉDIAS!L$4*K18 -> 252.13619 | M18: 81.68 | N18: =ORÇAMENTO_EXECUTIVO_REV02!$B$21/CÁLCULO_MÉDIAS!N$4*M18 -> 81.783175 | P18: 190 | Q18: 280 | R18: ALVENARIA
B19: INSTALAÇÕES ELÉTRICAS, HIDRÁULICAS, GLP E PREVENTIVAS | C19: 361.2 | D19: =ORÇAMENTO_EXECUTIVO_REV02!$B$21/CÁLCULO_MÉDIAS!D$4*C19 -> 361.65626 | E19: 301.65243 | F19: =ORÇAMENTO_EXECUTIVO_REV02!$B$21/CÁLCULO_MÉDIAS!F$4*E19 -> 312.5279 | G19: 475.97 | H19: =ORÇAMENTO_EXECUTIVO_REV02!$B$21/CÁLCULO_MÉDIAS!H$4*G19 -> 488.27575 | I19: 374.08 | J19: =ORÇAMENTO_EXECUTIVO_REV02!$B$21/CÁLCULO_MÉDIAS!J$4*I19 -> 419.23526 | K19: 581.27 | L19: =ORÇAMENTO_EXECUTIVO_REV02!$B$21/CÁLCULO_MÉDIAS!L$4*K19 -> 588.23682 | M19: 361.2 | N19: =ORÇAMENTO_EXECUTIVO_REV02!$B$21/CÁLCULO_MÉDIAS!N$4*M19 -> 361.65626 | P19: 400 | Q19: 530 | R19: INSTALAÇÕES ELÉTRICAS, HIDRÁULICAS, GLP E PREVENTIVAS
B20: EQUIPAMENTOS E SISTEMAS ESPECIAIS | C20: 329.029 | D20: =ORÇAMENTO_EXECUTIVO_REV02!$B$21/CÁLCULO_MÉDIAS!D$4*C20 -> 329.44462 | E20: 121.62815 | F20: =ORÇAMENTO_EXECUTIVO_REV02!$B$21/CÁLCULO_MÉDIAS!F$4*E20 -> 126.01321 | G20: 292.98 | H20: =ORÇAMENTO_EXECUTIVO_REV02!$B$21/CÁLCULO_MÉDIAS!H$4*G20 -> 300.55472 | I20: 277.64 | J20: =ORÇAMENTO_EXECUTIVO_REV02!$B$21/CÁLCULO_MÉDIAS!J$4*I20 -> 311.15397 | K20: 207.96 | L20: =ORÇAMENTO_EXECUTIVO_REV02!$B$21/CÁLCULO_MÉDIAS!L$4*K20 -> 210.45251 | M20: 329.03 | N20: =ORÇAMENTO_EXECUTIVO_REV02!$B$21/CÁLCULO_MÉDIAS!N$4*M20 -> 329.44562 | P20: 330 | Q20: 370 | R20: EQUIPAMENTOS E SISTEMAS ESPECIAIS
B21: IMPERMEABILIZAÇÃO | C21: 64.341352 | D21: =ORÇAMENTO_EXECUTIVO_REV02!$B$21/CÁLCULO_MÉDIAS!D$4*C21 -> 64.422626 | E21: 61.191658 | F21: =ORÇAMENTO_EXECUTIVO_REV02!$B$21/CÁLCULO_MÉDIAS!F$4*E21 -> 63.3978 | G21: 45.54 | H21: =ORÇAMENTO_EXECUTIVO_REV02!$B$21/CÁLCULO_MÉDIAS!H$4*G21 -> 46.717394 | I21: 61.96 | J21: =ORÇAMENTO_EXECUTIVO_REV02!$B$21/CÁLCULO_MÉDIAS!J$4*I21 -> 69.439203 | K21: 48.93 | L21: =ORÇAMENTO_EXECUTIVO_REV02!$B$21/CÁLCULO_MÉDIAS!L$4*K21 -> 49.516451 | M21: 64.34 | N21: =ORÇAMENTO_EXECUTIVO_REV02!$B$21/CÁLCULO_MÉDIAS!N$4*M21 -> 64.421272 | P21: 70 | Q21: 110 | R21: IMPERMEABILIZAÇÃO
B22: REVESTIMENTOS INTERNOS EM PISO E PAREDE | C22: 81.847539 | D22: =ORÇAMENTO_EXECUTIVO_REV02!$B$21/CÁLCULO_MÉDIAS!D$4*C22 -> 81.950926 | E22: 395.23514 | F22: =ORÇAMENTO_EXECUTIVO_REV02!$B$21/CÁLCULO_MÉDIAS!F$4*E22 -> 409.48455 | G22: 219.39 | H22: =ORÇAMENTO_EXECUTIVO_REV02!$B$21/CÁLCULO_MÉDIAS!H$4*G22 -> 225.06212 | I22: 94.96 | J22: =ORÇAMENTO_EXECUTIVO_REV02!$B$21/CÁLCULO_MÉDIAS!J$4*I22 -> 106.42264 | K22: 269.06 | L22: =ORÇAMENTO_EXECUTIVO_REV02!$B$21/CÁLCULO_MÉDIAS!L$4*K22 -> 272.28482 | M22: 81.85 | N22: =ORÇAMENTO_EXECUTIVO_REV02!$B$21/CÁLCULO_MÉDIAS!N$4*M22 -> 81.95339 | P22: 110 | Q22: 250 | R22: REVESTIMENTOS INTERNOS EM PISO E PAREDE
B23: REVESTIMENTOS E ACABAMENTOS INTERNOS EM TETO | C23: 33.843157 | D23: =ORÇAMENTO_EXECUTIVO_REV02!$B$21/CÁLCULO_MÉDIAS!D$4*C23 -> 33.885907 | E23: 38.140863 | F23: =ORÇAMENTO_EXECUTIVO_REV02!$B$21/CÁLCULO_MÉDIAS!F$4*E23 -> 39.515956 | G23: 80.68 | H23: =ORÇAMENTO_EXECUTIVO_REV02!$B$21/CÁLCULO_MÉDIAS!H$4*G23 -> 82.765905 | I23: 59.11 | J23: =ORÇAMENTO_EXECUTIVO_REV02!$B$21/CÁLCULO_MÉDIAS!J$4*I23 -> 66.245179 | K23: 88.42 | L23: =ORÇAMENTO_EXECUTIVO_REV02!$B$21/CÁLCULO_MÉDIAS!L$4*K23 -> 89.479759 | M23: 12.04 | N23: =ORÇAMENTO_EXECUTIVO_REV02!$B$21/CÁLCULO_MÉDIAS!N$4*M23 -> 12.055209 | P23: 80 | Q23: 110 | R23: REVESTIMENTOS E ACABAMENTOS INTERNOS EM TETO
B24: ACABAMENTOS EM PISO E PAREDE | C24: 253.39718 | D24: =ORÇAMENTO_EXECUTIVO_REV02!$B$21/CÁLCULO_MÉDIAS!D$4*C24 -> 253.71726 | E24: 0 | F24: =ORÇAMENTO_EXECUTIVO_REV02!$B$21/CÁLCULO_MÉDIAS!F$4*E24 -> 0 | G24: 258.11 | H24: =ORÇAMENTO_EXECUTIVO_REV02!$B$21/CÁLCULO_MÉDIAS!H$4*G24 -> 264.78319 | I24: 221.98 | J24: =ORÇAMENTO_EXECUTIVO_REV02!$B$21/CÁLCULO_MÉDIAS!J$4*I24 -> 248.77525 | K24: 393.31 | L24: =ORÇAMENTO_EXECUTIVO_REV02!$B$21/CÁLCULO_MÉDIAS!L$4*K24 -> 398.02402 | M24: 237.36 | N24: =ORÇAMENTO_EXECUTIVO_REV02!$B$21/CÁLCULO_MÉDIAS!N$4*M24 -> 237.65983 | P24: 210 | Q24: 280 | R24: ACABAMENTOS EM PISO E PAREDE
B25: PINTURA INTERNA | C25: 75.431687 | D25: =ORÇAMENTO_EXECUTIVO_REV02!$B$21/CÁLCULO_MÉDIAS!D$4*C25 -> 75.52697 | E25: 90.863379 | F25: =ORÇAMENTO_EXECUTIVO_REV02!$B$21/CÁLCULO_MÉDIAS!F$4*E25 -> 94.139275 | G25: 168.13 | H25: =ORÇAMENTO_EXECUTIVO_REV02!$B$21/CÁLCULO_MÉDIAS!H$4*G25 -> 172.47684 | I25: 88.9 | J25: =ORÇAMENTO_EXECUTIVO_REV02!$B$21/CÁLCULO_MÉDIAS!J$4*I25 -> 99.631135 | K25: 188.22 | L25: =ORÇAMENTO_EXECUTIVO_REV02!$B$21/CÁLCULO_MÉDIAS!L$4*K25 -> 190.47591 | M25: 75.43 | N25: =ORÇAMENTO_EXECUTIVO_REV02!$B$21/CÁLCULO_MÉDIAS!N$4*M25 -> 75.525281 | P25: 100 | Q25: 190 | R25: PINTURA INTERNA
B26: ESQUADRIAS, VIDROS E FERRAGENS | C26: 563.3688 | D26: =ORÇAMENTO_EXECUTIVO_REV02!$B$21/CÁLCULO_MÉDIAS!D$4*C26 -> 564.08042 | E26: 393.73193 | F26: =ORÇAMENTO_EXECUTIVO_REV02!$B$21/CÁLCULO_MÉDIAS!F$4*E26 -> 407.92714 | G26: 695.51 | H26: =ORÇAMENTO_EXECUTIVO_REV02!$B$21/CÁLCULO_MÉDIAS!H$4*G26 -> 713.49175 | I26: 557.55 | J26: =ORÇAMENTO_EXECUTIVO_REV02!$B$21/CÁLCULO_MÉDIAS!J$4*I26 -> 624.85196 | K26: 523.75 | L26: =ORÇAMENTO_EXECUTIVO_REV02!$B$21/CÁLCULO_MÉDIAS!L$4*K26 -> 530.02741 | M26: 563.37 | N26: =ORÇAMENTO_EXECUTIVO_REV02!$B$21/CÁLCULO_MÉDIAS!N$4*M26 -> 564.08163 | P26: 580 | Q26: 290 | R26: ESQUADRIAS, VIDROS E FERRAGENS
B27: REVESTIMENTOS E ACABAMENTOS DE FACHADA | C27: 106.61098 | D27: =ORÇAMENTO_EXECUTIVO_REV02!$B$21/CÁLCULO_MÉDIAS!D$4*C27 -> 106.74565 | E27: 120.60015 | F27: =ORÇAMENTO_EXECUTIVO_REV02!$B$21/CÁLCULO_MÉDIAS!F$4*E27 -> 124.94814 | G27: 273.88 | H27: =ORÇAMENTO_EXECUTIVO_REV02!$B$21/CÁLCULO_MÉDIAS!H$4*G27 -> 280.96091 | I27: 155.33 | J27: =ORÇAMENTO_EXECUTIVO_REV02!$B$21/CÁLCULO_MÉDIAS!J$4*I27 -> 174.07991 | K27: 183.05 | L27: =ORÇAMENTO_EXECUTIVO_REV02!$B$21/CÁLCULO_MÉDIAS!L$4*K27 -> 185.24395 | M27: 106.61 | N27: =ORÇAMENTO_EXECUTIVO_REV02!$B$21/CÁLCULO_MÉDIAS!N$4*M27 -> 106.74467 | P27: 110 | Q27: 210 | R27: REVESTIMENTOS E ACABAMENTOS DE FACHADA
B28: SERVIÇOS COMPLEMENTARES | C28: 371.14469 | D28: =ORÇAMENTO_EXECUTIVO_REV02!$B$21/CÁLCULO_MÉDIAS!D$4*C28 -> 371.61351 | E28: 152.5097 | F28: =ORÇAMENTO_EXECUTIVO_REV02!$B$21/CÁLCULO_MÉDIAS!F$4*E28 -> 158.00813 | G28: 334.34 | H28: =ORÇAMENTO_EXECUTIVO_REV02!$B$21/CÁLCULO_MÉDIAS!H$4*G28 -> 342.98404 | I28: 82.14 | J28: =ORÇAMENTO_EXECUTIVO_REV02!$B$21/CÁLCULO_MÉDIAS!J$4*I28 -> 92.055134 | K28: 270.04 | L28: =ORÇAMENTO_EXECUTIVO_REV02!$B$21/CÁLCULO_MÉDIAS!L$4*K28 -> 273.27657 | M28: 371.14 | N28: =ORÇAMENTO_EXECUTIVO_REV02!$B$21/CÁLCULO_MÉDIAS!N$4*M28 -> 371.60881 | P28: 180 | Q28: 310 | R28: SERVIÇOS COMPLEMENTARES
B29: IMPREVISTOS | C29: 54.035034 | D29: =ORÇAMENTO_EXECUTIVO_REV02!$B$21/CÁLCULO_MÉDIAS!D$4*C29 -> 54.10329 | E29: 0 | F29: =ORÇAMENTO_EXECUTIVO_REV02!$B$21/CÁLCULO_MÉDIAS!F$4*E29 -> 0 | H29: =ORÇAMENTO_EXECUTIVO_REV02!$B$21/CÁLCULO_MÉDIAS!H$4*G29 -> 0 | J29: =ORÇAMENTO_EXECUTIVO_REV02!$B$21/CÁLCULO_MÉDIAS!J$4*I29 -> 0 | L29: =ORÇAMENTO_EXECUTIVO_REV02!$B$21/CÁLCULO_MÉDIAS!L$4*K29 -> 0 | M29: 54.035034 | N29: =ORÇAMENTO_EXECUTIVO_REV02!$B$21/CÁLCULO_MÉDIAS!N$4*M29 -> 54.10329 | R29: IMPREVISTOS
B30: TOTAL | C30: =SUM(C13:C29) -> 3654.0809 | D30: =SUM(D13:D28) -> 3604.5933 | E30: =SUM(E13:E29) -> 2921.4484 | F30: =SUM(F13:F28) -> 3026.7753 | G30: =SUM(G13:G29) -> 4701.99 | H30: =SUM(H13:H28) -> 4823.5555 | I30: =SUM(I13:I29) -> 3930.84 | J30: =SUM(J13:J28) -> 4405.3324 | K30: =SUM(K13:K29) -> 4848.78 | L30: =SUM(L13:L28) -> 4906.8951 | M30: =SUM(M13:M29) -> 3616.245 | N30: =SUM(N13:N28) -> 3566.7097 | P30: =SUM(P14:P29) -> 3480 | Q30: =SUM(Q14:Q29) -> 4500

Sheet ATALAIA
S1: 7374.18
Q2: Quant. | S2: Valor
P3: Bloco cerâmico | Q3: =3465.59+22.9+489.69+1518.57 -> 5496.75 | R3: =Q3/$S$1 -> 0.74540491 | S3: =320755.87 -> 320755.87 | T3: =S3/$S$1 -> 43.497158
P4: Bloco concreto celular | Q4: =173.28+886.05+548.52 -> 1607.85 | R4: =Q4/$S$1 -> 0.2180378 | S4: =215405.71 -> 215405.71 | T4: =S4/$S$1 -> 29.210802
P5: Serviços complementares | Q5: =3778.82+3553+1154+604.64 -> 9090.46 | R5: =Q5/$S$1 -> 1.2327418 | S5: =107370 -> 107370 | T5: =S5/$S$1 -> 14.560263
P6: Mão de obra | Q6: =5496.75+1607.82 -> 7104.57 | R6: =Q6/$S$1 -> 0.96343865 | S6: 267282 | T6: =S6/$S$1 -> 36.245657
P9: Pintura teto | Q9: =71866.97/S1 -> 9.7457575
P10: Pintura parede | Q10: =235867.21/S1 -> 31.985551
P11: Pintura Piso | Q11: =66988.1/S1 -> 9.0841422

Sheet Spotico
A1: ORÇAMENTO PARAMÉTRICO - ORÇAMENTO PARAMÉTRICO
A7: Cliente | B7: Spotco
A8: Obra | B8: 54 Park Square
A9: Data | B9: 45275
A10: Versão | B10: TOTAL - R07
A11: CUB/PR - JUN/23 | B11: 2774.87
A12: CUB/PR - atual | B12: 2836.93
A14: CÓDIGO | B14: ITEM | C14: Quantidade | D14: Unidade | E14: Valor unitário | F14: Valor Orçado | G14: Valor indexado | H14: Considerações | I14: Observações/Duvidas | J14: RETORNO CARTESIAN
A15: 1 | B15: GERENCIAMENTO TÉCNICO E ADMINISTRATIVO | F15: 31315259 | G15: 31866647
A16: 1.1 | B16: GERENCIAMENTO TÉCNICO E ADMINISTRATIVO | F16: 31315259 | G16: 31866647
A17: 1.1.1 | B17: Gerenciamento técnico e administrativo | C17: 1 | D17: vb | E17: 31315259 | F17: 31315259 | G17: 31866647
A18: 2 | B18: MOVIMENTAÇÃO DE TERRA | F18: 4513723.6 | G18: 4614673.1
A19: 2.1 | B19: MOVIMENTAÇÃO DE TERRA | F19: 4513723.6 | G19: 4614673.1
A20: 2.1.1 | B20: Escavação subsolo | C20: 94932 | D20: m3 | E20: 30 | F20: 2847960 | G20: 2911654.7 | H20: Volume previsto no projeto de terraplanagem
A21: 2.1.2 | B21: Escavação mecanizada para blocos e baldrames | C21: 5998.175 | D21: m3 | E21: 70.000125 | F21: 419873 | G21: 429263.46
A22: 2.1.3 | B22: Reaterro para blocos e baldrames | C22: 1199.635 | D22: m3 | E22: 25.000104 | F22: 29991 | G22: 30661.749
A23: 2.1.4 | B23: Movimentação de terra (30% de empolamento) | C23: 12976.818 | D23: m3 | E23: 90 | F23: 1167913.6 | G23: 1194034 | H23: 81.790224
A24: 2.1.5 | B24: Lastro de concreto magro e= 10cm - Blocos | C24: 5998.175 | D24: m2 | E24: 8.0001 | F24: 47986 | G24: 49059.207 | H24: 599.8175 | I24: O lastro de concreto sendo um custo de 480/m³, sendo 10 cm de espessura de 10 cm daria 48/m² | J24: A consideração aqui é um lastro de brita 2 na verdade, considerando 80/m³ -> 8/m² (houve um equivoco no nome do serviço)
A25: 3 | B25: INFRAESTRUTURA | F25: 17109406 | G25: 17492058
A26: 3.1 | B26: FUNDAÇÃO PROFUNDA | F26: 7785843 | G26: 7959973.5
A27: 3.1.1 | B27: Estaca escavada, diâmetro 100cm | C27: 6600 | D27: m | E27: 75 | F27: 495000 | G27: 506070.68 | H27: 330 estacas - duas por pilar de embasamento
A28: 3.1.2 | B28: Estaca escavada em rocha, diâmetro 100cm | C28: 5600 | D28: m | E28: 120 | F28: 672000 | G28: 687029.29 | H28: 280 estacas - 3,5 por pilar da torre
A29: 3.1.3 | B29: Armação | C29: 362853.95 | D29: kg | E29: 7.3000004 | F29: 2648834 | G29: 2708075.2 | H29: Consideração de R$ 7,30/kg com 7% de perda | I29: Só material?
A30: 3.1.4 | B30: Concreto | C30: 5183.6279 | D30: m3 | E30: 708.00009 | F30: 3670009 | G30: 3752088.8 | H30: Consideração de R$ 590,00/m³ com 20% de perda | I30: Com o lançamento?
A31: 3.1.5 | B31: Mobilização | C31: 1 | D31: vb | E31: 300000 | F31: 300000 | G31: 306709.5 | H31: Previsão de mobilização de maquinários | I31: A mão de obra da fundação profunda está também no item 3.2.5? | J31: Sim, os itens da fundação profunda se referem apenas a material, estando a mão de obra inclusa no item 3.2.5
A32: 3.2 | B32: FUNDAÇÃO RASA | F32: 9323563.2 | G32: 9532084.8
A33: 3.2.1 | B33: Fabricação, montagem e desmontagem de forma para blocos e baldrames | C33: 5998.175 | D33: m² | E33: 50 | F33: 299908.75 | G33: 306616.21 | H33: Forma de compensado resinado com 2 reutilizações
A34: 3.2.2 | B34: Armação | C34: 335897.8 | D34: kg | E34: 7.3 | F34: 2452053.9 | G34: 2506894.2 | H34: Consideração de R$ 7,30/kg com 7% de perda | I34: Só material?
A35: 3.2.3 | B35: Concreto | C35: 4798.54 | D35: m³ | E35: 619.5 | F35: 2972695.5 | G35: 3039179.9 | H35: Consideração de R$ 590,00/m³ com 5% de perda | I35: Com o lançamento?
A36: 3.2.5 | B36: Mão de obra infraestrutura | C36: 17994.525 | D36: vb | E36: 200 | F36: 3598905 | G36: 3679394.6 | H36: Valor estimado por área de projeção do embasamento x 1,5 | I36: É para mão de obra de forma, armação e concretagem?
A37: 4 | B37: CONTENÇÃO | F37: 4072621.7 | G37: 4163706
A38: 4.1 | B38: CONTENÇÃO | F38: 4072621.7 | G38: 4163706
A39: 4.1.1 | B39: Estaca hélice contínua, diâmetro 50cm | C39: 2628 | D39: m | E39: 80 | F39: 210240 | G39: 214942.02 | H39: Previsão de 1,25 estacas de 50cm por metro de contenção
A40: 4.1.2 | B40: Armação | C40: 183960 | D40: kg | E40: 7.3 | F40: 1342908 | G40: 1372942.2 | H40: Consideração de R$ 7,30/kg com 7% de perda
A41: 4.1.3 | B41: Concreto | C41: 516.00659 | D41: m³ | E41: 708 | F41: 365332.67 | G41: 373503.34 | H41: Consideração de R$ 590,00/m³ com 20% de perda
A42: 4.1.4 | B42: Tirantes | C42: 175.18 | D42: m | E42: 6163.26 | F42: 1079679.9 | G42: 1103826.9 | H42: Previsão de duas linhas de tirantes
A43: 4.1.5 | B43: Drenagem de contenção | C43: 175.18 | D43: m | E43: 400 | F43: 70072 | G43: 71639.161 | H43: Verba estimada para estrutura de drenagem
A44: 4.1.6 | B44: Mão de obra armação | C44: 183960 | D44: kg | E44: 2.5 | F44: 459900 | G44: 470185.67
A45: 4.1.7 | B45: Mão de obra concretagem | C45: 516.00659 | D45: m³ | E45: 600 | F45: 309603.96 | G45: 316528.25
A46: 4.1.8 | B46: Mão de obra drenagem | C46: 175.18 | D46: m | E46: 100 | F46: 17518 | G46: 17909.79
A47: 4.1.9 | B47: Mobilização | C47: 1 | D47: vb | E47: 150000 | F47: 150000 | G47: 153354.75 | H47: Previsão de mobilização de maquinários
A48: 4.1.10 | B48: Forma para viga de coroamento - 40x40 | C48: 140.144 | D48: m2 | E48: 50 | F48: 7007.2 | G48: 7163.9161 | H48: Forma de compensado resinado com 2 reutilizações
A49: 4.1.11 | B49: Concreto para viga de coroamento | C49: 28.0288 | D49: m3 | E49: 619.5 | F49: 17363.842 | G49: 17752.184 | H49: Consideração de R$ 590,00/m³ com 5% de perda
A50: 4.1.12 | B50: Armação para viga de coroamento | C50: 2242.304 | D50: vb | E50: 7.3 | F50: 16368.819 | G50: 16734.908 | H50: Consideração de R$ 7,30/kg com 7% de perda
A51: 4.1.13 | B51: Mão de obra para viga de coroamento | C51: 28.0288 | D51: m³ | E51: 950 | F51: 26627.36 | G51: 27222.881
A52: 5 | B52: SUPRAESTRUTURA | F52: 53675068 | G52: 54875511
A53: 5.1 | B53: FORMA | F53: 3543821 | G53: 3623078.6
A54: 5.1.1 | B54: Fabricação forma | C54: 27052.069 | D54: m² | E54: 95 | F54: 2569946.5 | G54: 2627423.4 | H54: Forma com compensado plastificado - 8 reutilizações
A55: 5.1.2 | B55: Montagem de forma | C55: 216416.55 | D55: m² | E55: 4.5 | F55: 973874.48 | G55: 995655.19
A56: 5.2 | B56: ESCORAMENTO | F56: 3945644.1 | G56: 4033888.5
A57: 5.2.1 | B57: Escoramento - Torre | C57: 51981.6 | D57: m² | E57: 45 | F57: 2339172 | G57: 2391487.6 | H57: Locação de escoramento metálico
A58: 5.2.2 | B58: Escoramento - Embasamento | C58: 35699.38 | D58: m² | E58: 45 | F58: 1606472.1 | G58: 1642400.9 | H58: Locação de escoramento metálico
A59: 5.3 | B59: ARMADURA | F59: 14218567 | G59: 14536566
A60: 5.3.1 | B60: Armadura Convencional para Estrutura | C60: 1947749 | D60: kg | E60: 7.3 | F60: 14218567 | G60: 14536566 | H60: Consideração de R$ 7,00/kg
A61: 5.4 | B61: CONCRETO | F61: 14088717 | G61: 14403812
A62: 5.4.1 | B62: Concreto | C62: 21641.655 | D62: m³ | E62: 651 | F62: 14088717 | G62: 14403812 | H62: Consideração de 620,00/m³ com 5% de perda
A63: 5.5 | B63: COMPLEMENTARES | F63: 564993.9 | G63: 577630
A64: 5.5.1 | B64: Junta de dilatação | C64: 748.59 | D64: m | E64: 80 | F64: 59887.2 | G64: 61226.578 | H64: Perímetro de projeção torre
A65: 5.5.1 | B65: Estrutura metálica lazer | C65: 687.22 | D65: m² | E65: 735 | F65: 505106.7 | G65: 516403.42 | H65: Valor estimado com base na área do detalhe
A66: 5.6 | B66: MÃO DE OBRA | F66: 17313324 | G66: 17700537
A67: 5.6.1 | B67: Mão de obra supraestrutura | C67: 86566.62 | D67: m² | E67: 200 | F67: 17313324 | G67: 17700537 | H67: Valor estimado com base na área construida | I67: É para mão de obra de armação e para a concretagem? | J67: Mão de obra para fabricação e montagem de forma, armação, concretagem, transporte e todos demias itens previstos para execução da estrutura
A68: 6 | B68: ALVENARIA | F68: 10102861 | G68: 10328811 | H68: Quantitativos extraídos do modelo preliminar .rvt
A69: 6.1 | B69: ALVENARIA | F69: 10102861 | G69: 10328811
A70: 6.1.1 | B70: Alvenaria externa | C70: 36045.94 | D70: m² | E70: 41 | F70: 1477883.5 | G70: 1510936.4 | H70: Fechamento com bloco 19cm e assentamento com argamassa usinada
A71: 6.1.2 | B71: Alvenaria interna | C71: 53117.56 | D71: m² | E71: 30 | F71: 1593526.8 | G71: 1629166 | H71: Fechamento com bloco 11.5cm e assentamento com argamassa usinada
A72: 6.1.3 | B72: Tijolo refratário | C72: 2860.42 | D72: m² | E72: 320 | F72: 915334.4 | G72: 935805.86 | H72: Em churrasqueiras
A73: 6.1.4 | B73: Serviços complementares | C73: 89163.5 | D73: m² | E73: 8.2 | F73: 731140.7 | G73: 747492.67
A74: 6.1.5 | B74: Fechamento parede contenção | C74: 2102.16 | D74: m² | E74: 635.5 | F74: 1335922.7 | G74: 1365800.6 | H74: Concreto com tela e manta geotextil
A75: 6.1.6 | B75: Mão de obra | C75: 48823.795 | D75: m² | E75: 82.931949 | F75: 4049052.5 | G75: 4139609.6
A76: 7 | B76: INSTALAÇÕES ELÉTRICAS, HIDRÁULICAS E GLP | F76: 27961018 | G76: 28586367 | H76: Valores estimados com base em índices históricos por área construida
A77: 7.1 | B77: INSTALAÇÕES ELÉTRICAS | F77: 13461109 | G77: 13762167
A78: 7.1.1 | B78: Entrada de Energia | C78: 1 | D78: vb | E78: 476116.41 | F78: 476116.41 | G78: 486764.76
A79: 7.1.2 | B79: Eletrodutos e Eletrocalhas | C79: 1 | D79: vb | E79: 865666.2 | F79: 865666.2 | G79: 885026.83
A80: 7.1.3 | B80: Instalações Embutidas e Aparentes | C80: 1 | D80: vb | E80: 1298499.3 | F80: 1298499.3 | G80: 1327540.3
A81: 7.1.4 | B81: Cabos e Fiações | C81: 1 | D81: vb | E81: 2596998.6 | F81: 2596998.6 | G81: 2655080.5
A82: 7.1.5 | B82: Quadros e Disjuntores | C82: 1 | D82: vb | E82: 1298499.3 | F82: 1298499.3 | G82: 1327540.3
A83: 7.1.6 | B83: Acabamentos Elétricos | C83: 1 | D83: vb | E83: 1298499.3 | F83: 1298499.3 | G83: 1327540.3
A84: 7.1.7 | B84: Equipamentos e Iluminação | C84: 1 | D84: vb | E84: 1298499.3 | F84: 1298499.3 | G84: 1327540.3
A85: 7.1.8 | B85: Mão de Obra para Instalações Elétricas | C85: 1 | D85: vb | E85: 4328331 | F85: 4328331 | G85: 4425134.2
A86: 7.2 | B86: INSTALAÇÕES HIDRÁULICAS | F86: 11946194 | G86: 12213370
A87: 7.2.1 | B87: Instalações de Água Fria | C87: 1 | D87: vb | E87: 1731332.4 | F87: 1731332.4 | G87: 1770053.7
A88: 7.2.2 | B88: Instalações de Água Quente | C88: 1 | D88: vb | E88: 1558199.2 | F88: 1558199.2 | G88: 1593048.3
A89: 7.2.3 | B89: Instalações de Águas Pluviais | C89: 1 | D89: vb | E89: 865666.2 | F89: 865666.2 | G89: 885026.83
A90: 7.2.4 | B90: Instalações Sanitárias | C90: 1 | D90: vb | E90: 1298499.3 | F90: 1298499.3 | G90: 1327540.3
A91: 7.2.5 | B91: Louças e Metais | C91: 1 | D91: vb | E91: 2596998.6 | F91: 2596998.6 | G91: 2655080.5 | I91: Lançado em verba, já tem quantitativo? | J91: Todos os itens de instalações (etapa 7) foram estimados com base em índices por ainda não termos previsão de quantitativo
A92: 7.2.6 | B92: Mão de Obra para Instalações Hidráulicas | C92: 1 | D92: vb | E92: 3895497.9 | F92: 3895497.9 | G92: 3982620.8
A93: 7.3 | B93: INSTALAÇÕES PREVENTIVAS E GLP | F93: 2553715.3 | G93: 2610829.2
A94: 7.3.1 | B94: Instalações Preventivas | C94: 1 | D94: vb | E94: 822382.89 | F94: 822382.89 | G94: 840775.49
A95: 7.3.2 | B95: Instalações de GLP | C95: 1 | D95: vb | E95: 432833.1 | F95: 432833.1 | G95: 442513.42
A96: 7.3.3 | B96: Instalações de Proteção e Aterramento - SPDA | C96: 1 | D96: vb | E96: 259699.86 | F96: 259699.86 | G96: 265508.05
A97: 7.3.4 | B97: Mão de Obra | C97: 1 | D97: vb | E97: 1038799.4 | F97: 1038799.4 | G97: 1062032.2
A98: 8 | B98: SISTEMAS ESPECIAIS | F98: 26550840 | G98: 27144650
A99: 8.1 | B99: CLIMATIZAÇÃO, EXAUSTÃO MECÂNICA E PRESSURIZAÇÃO | F99: 10604665 | G99: 10841838
A100: 8.1.1 | B100: Infraestrutura para Instalação de Ar Condicionado | C100: 63963.1 | D100: m² | E100: 150 | F100: 9594465 | G100: 9809045.3 | H100: Infraestrutura para ar-condicionado tipo K7 em quartos, escritórios, livings e áreas comuns
A101: 8.1.2 | B101: Instalação de Ar Condicionado | C101: 29 | D101: un | E101: 6000 | F101: 174000 | G101: 177891.51 | H101: Instalação de ar-codicionado tipo K7 em áreas comuns
A102: 8.1.3 | B102: Ventokit | C102: 378 | D102: un | E102: 900 | F102: 340200 | G102: 347808.58 | H102: Ventilação mecânica em banheiros enclausurados;
A103: 8.1.4 | B103: Churrasqueiras | C103: 248 | D103: un | E103: 2000 | F103: 496000 | G103: 507093.05 | H103: Exaustão de churrasqueiras;
A104: 8.2 | B104: COMUNICAÇÃO | F104: 1471632.5 | G104: 1504545.6
A105: 8.2.1 | B105: CFTV | C105: 1 | D105: vb | E105: 173133.24 | F105: 173133.24 | G105: 177005.37
A106: 8.2.2 | B106: Interfone | C106: 1 | D106: vb | E106: 605966.34 | F106: 605966.34 | G106: 619518.78
...

Sheet Índices
D3: DATA BASE | E3: 45231 | F3: DATA BASE | G3: 44958 | H3: DATA BASE | I3: 45047 | J3: DATA BASE | K3: 44652 | L3: DATA BASE | M3: 45078 | N3: DATA BASE
D4: CUB | E4: 2754.98 | F4: CUB | G4: 2662.47 | H4: CUB | I4: 2688.94 | J4: CUB | K4: 2461.35 | L4: CUB | M4: 2725.79 | N4: CUB
D5: ÁREA TERRENO | E5: 2394.02 | F5: ÁREA TERRENO | H5: ÁREA TERRENO | J5: ÁREA TERRENO | L5: ÁREA TERRENO | N5: ÁREA TERRENO
D6: ÁREA CONSTRUÍDA | E6: 7642.76 | F6: ÁREA CONSTRUÍDA | G6: 14888.46 | H6: ÁREA CONSTRUÍDA | I6: 3282.64 | J6: ÁREA CONSTRUÍDA | K6: 4811.62 | L6: ÁREA CONSTRUÍDA | M6: 7305.16 | N6: ÁREA CONSTRUÍDA | O6: 61763.96
D7: PAVTOS | E7: Subsolo com vagas de garagem Térreo, 2º e 3º PVTO com 2 aptos por andar Cobertura com Rooftop | F7: PAVTOS | H7: PAVTOS | J7: PAVTOS | L7: PAVTOS | N7: PAVTOS
D8: ESPECIFICAÇÕES | E8: 6 apartamentos 3 Elevadores Salão de festas e academia Pavimento Rooftop | F8: ESPECIFICAÇÕES | H8: ESPECIFICAÇÕES | J8: ESPECIFICAÇÕES | L8: ESPECIFICAÇÕES | N8: ESPECIFICAÇÕES
D9: DIFERENCIAIS | E9: -Uma piscina por apartamento - Padrão elevado de esquadrias - Alto investimento em paisagismo | F9: DIFERENCIAIS | H9: DIFERENCIAIS | J9: DIFERENCIAIS | L9: DIFERENCIAIS | N9: DIFERENCIAIS
H10: Médias extraídas da apresentação KSA
D11: ESTALEIRO - ABC EMPREENDIMENTOS | F11: LIVE - LUMIS | H11: MENDES - BRAVA SIXTEEN | J11: MENDES - BRAVA MUNDO | L11: COTA - AFONSO PENA | N11: CN - BRAVA | Q11: MÉDIAS
D12: VALOR / M2 | E12: INDEXADO | G12: INDEXADO | H12: VALOR / M2 | I12: INDEXADO | J12: VALOR / M2 | K12: INDEXADO | L12: VALOR / M2 | M12: INDEXADO | N12: VALOR / M2 | O12: INDEXADO | Q12: MÍNIMA | R12: MÁXIMA
E13: =ORÇAMENTO_EXECUTIVO_REV02!$B$21/Índices!E$4*D13 -> 0 | G13: =ORÇAMENTO_EXECUTIVO_REV02!$B$21/Índices!G$4*F13 -> 0 | I13: =ORÇAMENTO_EXECUTIVO_REV02!$B$21/Índices!I$4*H13 -> 0 | K13: =ORÇAMENTO_EXECUTIVO_REV02!$B$21/Índices!K$4*J13 -> 0 | M13: =ORÇAMENTO_EXECUTIVO_REV02!$B$21/Índices!M$4*L13 -> 0 | O13: =ORÇAMENTO_EXECUTIVO_REV02!$B$21/Índices!O$4*N13 -> #DIV/0!
B14: Rodapé | C14: Custo | D14: =152855.27/E6 -> 20.000009 | E14: =ORÇAMENTO_EXECUTIVO_REV02!$B$21/Índices!E$4*D14 -> 20.025273 | F14: =(124904.93+4141.76)/G6 -> 8.6675647 | G14: =ORÇAMENTO_EXECUTIVO_REV02!$B$21/Índices!G$4*F14 -> 8.9800563 | I14: =ORÇAMENTO_EXECUTIVO_REV02!$B$21/Índices!I$4*H14 -> 0 | K14: =ORÇAMENTO_EXECUTIVO_REV02!$B$21/Índices!K$4*J14 -> 0 | M14: =ORÇAMENTO_EXECUTIVO_REV02!$B$21/Índices!M$4*L14 -> 0 | N14: =7998.69+84770.54 -> 92769.23 | O14: =ORÇAMENTO_EXECUTIVO_REV02!$B$21/Índices!O$4*N14 -> #DIV/0!
B15: Rodapé | C15: índice | E15: =ORÇAMENTO_EXECUTIVO_REV02!$B$21/Índices!E$4*D15 -> 0 | F15: =(5065+440.36)/G6 -> 0.36977364 | G15: =ORÇAMENTO_EXECUTIVO_REV02!$B$21/Índices!G$4*F15 -> 0.38310508 | I15: =ORÇAMENTO_EXECUTIVO_REV02!$B$21/Índices!I$4*H15 -> 0 | K15: =ORÇAMENTO_EXECUTIVO_REV02!$B$21/Índices!K$4*J15 -> 0 | M15: =ORÇAMENTO_EXECUTIVO_REV02!$B$21/Índices!M$4*L15 -> 0 | N15: =162+909.3 -> 1071.3 | O15: =ORÇAMENTO_EXECUTIVO_REV02!$B$21/Índices!O$4*N15 -> #DIV/0!
E16: =ORÇAMENTO_EXECUTIVO_REV02!$B$21/Índices!E$4*D16 -> 0 | G16: =ORÇAMENTO_EXECUTIVO_REV02!$B$21/Índices!G$4*F16 -> 0 | I16: =ORÇAMENTO_EXECUTIVO_REV02!$B$21/Índices!I$4*H16 -> 0 | K16: =ORÇAMENTO_EXECUTIVO_REV02!$B$21/Índices!K$4*J16 -> 0 | M16: =ORÇAMENTO_EXECUTIVO_REV02!$B$21/Índices!M$4*L16 -> 0 | N16: =245.27 -> 245.27 | O16: =ORÇAMENTO_EXECUTIVO_REV02!$B$21/Índices!O$4*N16 -> #DIV/0!
E17: =ORÇAMENTO_EXECUTIVO_REV02!$B$21/Índices!E$4*D17 -> 0 | G17: =ORÇAMENTO_EXECUTIVO_REV02!$B$21/Índices!G$4*F17 -> 0 | I17: =ORÇAMENTO_EXECUTIVO_REV02!$B$21/Índices!I$4*H17 -> 0 | K17: =ORÇAMENTO_EXECUTIVO_REV02!$B$21/Índices!K$4*J17 -> 0 | M17: =ORÇAMENTO_EXECUTIVO_REV02!$B$21/Índices!M$4*L17 -> 0 | N17: =79.65 -> 79.65 | O17: =ORÇAMENTO_EXECUTIVO_REV02!$B$21/Índices!O$4*N17 -> #DIV/0!
E18: =ORÇAMENTO_EXECUTIVO_REV02!$B$21/Índices!E$4*D18 -> 0 | G18: =ORÇAMENTO_EXECUTIVO_REV02!$B$21/Índices!G$4*F18 -> 0 | I18: =ORÇAMENTO_EXECUTIVO_REV02!$B$21/Índices!I$4*H18 -> 0 | K18: =ORÇAMENTO_EXECUTIVO_REV02!$B$21/Índices!K$4*J18 -> 0 | M18: =ORÇAMENTO_EXECUTIVO_REV02!$B$21/Índices!M$4*L18 -> 0 | O18: =ORÇAMENTO_EXECUTIVO_REV02!$B$21/Índices!O$4*N18 -> #DIV/0!
E19: =ORÇAMENTO_EXECUTIVO_REV02!$B$21/Índices!E$4*D19 -> 0 | G19: =ORÇAMENTO_EXECUTIVO_REV02!$B$21/Índices!G$4*F19 -> 0 | I19: =ORÇAMENTO_EXECUTIVO_REV02!$B$21/Índices!I$4*H19 -> 0 | K19: =ORÇAMENTO_EXECUTIVO_REV02!$B$21/Índices!K$4*J19 -> 0 | M19: =ORÇAMENTO_EXECUTIVO_REV02!$B$21/Índices!M$4*L19 -> 0 | O19: =ORÇAMENTO_EXECUTIVO_REV02!$B$21/Índices!O$4*N19 -> #DIV/0!
E20: =ORÇAMENTO_EXECUTIVO_REV02!$B$21/Índices!E$4*D20 -> 0 | G20: =ORÇAMENTO_EXECUTIVO_REV02!$B$21/Índices!G$4*F20 -> 0 | I20: =ORÇAMENTO_EXECUTIVO_REV02!$B$21/Índices!I$4*H20 -> 0 | K20: =ORÇAMENTO_EXECUTIVO_REV02!$B$21/Índices!K$4*J20 -> 0 | M20: =ORÇAMENTO_EXECUTIVO_REV02!$B$21/Índices!M$4*L20 -> 0 | O20: =ORÇAMENTO_EXECUTIVO_REV02!$B$21/Índices!O$4*N20 -> #DIV/0!
E21: =ORÇAMENTO_EXECUTIVO_REV02!$B$21/Índices!E$4*D21 -> 0 | G21: =ORÇAMENTO_EXECUTIVO_REV02!$B$21/Índices!G$4*F21 -> 0 | I21: =ORÇAMENTO_EXECUTIVO_REV02!$B$21/Índices!I$4*H21 -> 0 | K21: =ORÇAMENTO_EXECUTIVO_REV02!$B$21/Índices!K$4*J21 -> 0 | M21: =ORÇAMENTO_EXECUTIVO_REV02!$B$21/Índices!M$4*L21 -> 0 | O21: =ORÇAMENTO_EXECUTIVO_REV02!$B$21/Índices!O$4*N21 -> #DIV/0!
E22: =ORÇAMENTO_EXECUTIVO_REV02!$B$21/Índices!E$4*D22 -> 0 | G22: =ORÇAMENTO_EXECUTIVO_REV02!$B$21/Índices!G$4*F22 -> 0 | I22: =ORÇAMENTO_EXECUTIVO_REV02!$B$21/Índices!I$4*H22 -> 0 | K22: =ORÇAMENTO_EXECUTIVO_REV02!$B$21/Índices!K$4*J22 -> 0 | M22: =ORÇAMENTO_EXECUTIVO_REV02!$B$21/Índices!M$4*L22 -> 0 | O22: =ORÇAMENTO_EXECUTIVO_REV02!$B$21/Índices!O$4*N22 -> #DIV/0!
E23: =ORÇAMENTO_EXECUTIVO_REV02!$B$21/Índices!E$4*D23 -> 0 | G23: =ORÇAMENTO_EXECUTIVO_REV02!$B$21/Índices!G$4*F23 -> 0 | I23: =ORÇAMENTO_EXECUTIVO_REV02!$B$21/Índices!I$4*H23 -> 0 | K23: =ORÇAMENTO_EXECUTIVO_REV02!$B$21/Índices!K$4*J23 -> 0 | M23: =ORÇAMENTO_EXECUTIVO_REV02!$B$21/Índices!M$4*L23 -> 0 | O23: =ORÇAMENTO_EXECUTIVO_REV02!$B$21/Índices!O$4*N23 -> #DIV/0!
E24: =ORÇAMENTO_EXECUTIVO_REV02!$B$21/Índices!E$4*D24 -> 0 | G24: =ORÇAMENTO_EXECUTIVO_REV02!$B$21/Índices!G$4*F24 -> 0 | I24: =ORÇAMENTO_EXECUTIVO_REV02!$B$21/Índices!I$4*H24 -> 0 | K24: =ORÇAMENTO_EXECUTIVO_REV02!$B$21/Índices!K$4*J24 -> 0 | M24: =ORÇAMENTO_EXECUTIVO_REV02!$B$21/Índices!M$4*L24 -> 0 | O24: =ORÇAMENTO_EXECUTIVO_REV02!$B$21/Índices!O$4*N24 -> #DIV/0!
E25: =ORÇAMENTO_EXECUTIVO_REV02!$B$21/Índices!E$4*D25 -> 0 | G25: =ORÇAMENTO_EXECUTIVO_REV02!$B$21/Índices!G$4*F25 -> 0 | I25: =ORÇAMENTO_EXECUTIVO_REV02!$B$21/Índices!I$4*H25 -> 0 | K25: =ORÇAMENTO_EXECUTIVO_REV02!$B$21/Índices!K$4*J25 -> 0 | M25: =ORÇAMENTO_EXECUTIVO_REV02!$B$21/Índices!M$4*L25 -> 0 | O25: =ORÇAMENTO_EXECUTIVO_REV02!$B$21/Índices!O$4*N25 -> #DIV/0!
E26: =ORÇAMENTO_EXECUTIVO_REV02!$B$21/Índices!E$4*D26 -> 0 | G26: =ORÇAMENTO_EXECUTIVO_REV02!$B$21/Índices!G$4*F26 -> 0 | I26: =ORÇAMENTO_EXECUTIVO_REV02!$B$21/Índices!I$4*H26 -> 0 | K26: =ORÇAMENTO_EXECUTIVO_REV02!$B$21/Índices!K$4*J26 -> 0 | M26: =ORÇAMENTO_EXECUTIVO_REV02!$B$21/Índices!M$4*L26 -> 0 | O26: =ORÇAMENTO_EXECUTIVO_REV02!$B$21/Índices!O$4*N26 -> #DIV/0!
E27: =ORÇAMENTO_EXECUTIVO_REV02!$B$21/Índices!E$4*D27 -> 0 | G27: =ORÇAMENTO_EXECUTIVO_REV02!$B$21/Índices!G$4*F27 -> 0 | I27: =ORÇAMENTO_EXECUTIVO_REV02!$B$21/Índices!I$4*H27 -> 0 | K27: =ORÇAMENTO_EXECUTIVO_REV02!$B$21/Índices!K$4*J27 -> 0 | M27: =ORÇAMENTO_EXECUTIVO_REV02!$B$21/Índices!M$4*L27 -> 0 | O27: =ORÇAMENTO_EXECUTIVO_REV02!$B$21/Índices!O$4*N27 -> #DIV/0!
E28: =ORÇAMENTO_EXECUTIVO_REV02!$B$21/Índices!E$4*D28 -> 0 | G28: =ORÇAMENTO_EXECUTIVO_REV02!$B$21/Índices!G$4*F28 -> 0 | I28: =ORÇAMENTO_EXECUTIVO_REV02!$B$21/Índices!I$4*H28 -> 0 | K28: =ORÇAMENTO_EXECUTIVO_REV02!$B$21/Índices!K$4*J28 -> 0 | M28: =ORÇAMENTO_EXECUTIVO_REV02!$B$21/Índices!M$4*L28 -> 0 | O28: =ORÇAMENTO_EXECUTIVO_REV02!$B$21/Índices!O$4*N28 -> #DIV/0!
E29: =ORÇAMENTO_EXECUTIVO_REV02!$B$21/Índices!E$4*D29 -> 0 | G29: =ORÇAMENTO_EXECUTIVO_REV02!$B$21/Índices!G$4*F29 -> 0 | I29: =ORÇAMENTO_EXECUTIVO_REV02!$B$21/Índices!I$4*H29 -> 0 | K29: =ORÇAMENTO_EXECUTIVO_REV02!$B$21/Índices!K$4*J29 -> 0 | M29: =ORÇAMENTO_EXECUTIVO_REV02!$B$21/Índices!M$4*L29 -> 0 | O29: =ORÇAMENTO_EXECUTIVO_REV02!$B$21/Índices!O$4*N29 -> #DIV/0!

Sheet Auxiliar
A2: 2 Portões acesso garagem - Área: 9,2m² x 2 = 18,4m² | B2: 2 | C2: portão | D2: 18.4
A3: 2 portas corta-fogo 1 folha | B3: 2 | C3: pcf
A4: 1 porta de correr alumínio 2 folhas – Área: 3,465m² | B4: 1 | C4: porta alumínio | D4: 3.465
A5: 1 porta de correr alumínio 2 folhas – Área: 1,7325m² | B5: 1 | C5: porta alumínio | D5: 1.7325 | G5: Guarda alumínio | H5: =SUMIF(C:C,G5,D:D) -> 400.5221
A6: 2 portas de abrir alumínio 2 folhas – Área: 2,6376m² x 2 = 5,2752m² | B6: 2 | C6: porta alumínio | D6: 5.2752 | G6: janela | H6: =SUMIF(C:C,G6,D:D) -> 1895.06
A7: 1 porta de abrir alumínio 2 folhas – Área: 4,1916m² | B7: 1 | C7: porta alumínio | D7: 4.1916 | G7: madeira | H7: =SUMIF(C:C,G7,B:B) -> 218
A8: 1 porta pivotante | B8: 1 | C8: pivotante | G8: pcf | H8: =SUMIF(C:C,G8,B:B) -> 60
A9: 19 portas de abrir madeira 1 folha | B9: 19 | C9: madeira | G9: pivotante | H9: =SUMIF(C:C,G9,B:B) -> 1
A10: 3 portas de abrir vidro 1 folha – Área: 2,1m² x 3 = 6,3m² | B10: 3 | C10: porta alumínio | D10: 6.3 | G10: porta alumínio | H10: =SUMIF(C:C,G10,D:D) -> 46.62
A11: 2 portas de abrir vidro 1 folha – Área: 1,89m² x 2 = 3,78m² | B11: 2 | C11: porta alumínio | D11: 3.78 | G11: portão | H11: =SUMIF(C:C,G11,B:B) -> 2
A12: 1 porta de abrir alumínio 1 folha – Área: 2,0076m² | B12: 1 | C12: porta alumínio | D12: 2.0076 | G12: gradil | H12: =SUMIF(C:C,G12,D:D) -> 113.88
A13: Janelas – Área: 3,75 + 4,875 + 2,5 + 1,1 + 1,2 + 5,5402 + 4,4874 = 23,4526m² | C13: janela | D13: 23.4526 | G13: Brise | H13: 109.3146
A14: Muro de vidro – Área: 7,0774 + 5,485 + 3,43 + 4,8138 = 20,8062m² | C14: Guarda alumínio | D14: 20.8062
A15: 8 portas corta-fogo 1 folha | B15: 8 | C15: pcf
A16: Janelas – Area: (1,1 + 1,2 + 28,7391) x 4 = 124,1564m² | C16: janela | D16: 124.1564
A17: 2 portas corta-fogo 1 folha | B17: 2 | C17: pcf
A18: 2 portas de abrir alumínio 1 folha – Área: 1,47m² x 2 = 2,94m² | B18: 2 | C18: porta alumínio | D18: 2.94
A19: 2 portas de abrir vidro 1 folha – Área: 1,89m² x 2 = 3,78m² | B19: 2 | C19: porta alumínio | D19: 3.78
A20: 5 portas de abrir madeira 1 folha | B20: 5 | C20: madeira
A21: 1 janela-porta de correr vidro – Área: 14,7348m² | B21: 1 | C21: janela | D21: 14.7348
A22: Janelas – Área: 1,2894 + 1,2894 + 23,46 + 1,854 + 5,562 + 5,562 + 1,854 + 1,854 + 1,1 + 1,2 = 45,0248m² | C22: janela | D22: 45.0248
A23: Guarda corpo vidro – Área: 7,5299 + 5,7955 + 6,5555 = 19,8809m² | C23: Guarda alumínio | D23: 19.8809
A24: 38 portas corta-fogo 1 folha | B24: 38 | C24: pcf
A25: 171 portas de abrir madeira 1 folha | B25: 171 | C25: madeira
A26: 19 porta de abrir alumínio 1 folha – Área: 1,26m² x 19 = 23,94m² | B26: 19 | C26: porta alumínio | D26: 23.94
A27: 19 janela-porta de correr vidro 5 folhas - Área: 25,4205m² x 19 = 482,9895m² | B27: 19 | C27: janela | D27: 482.9895
A28: 19 janela-porta de correr vidro 5 folhas - Área: 17,8284m² x 19 = 338,7396m² | B28: 19 | C28: janela | D28: 338.7396
A29: Janelas – Área: 1,1 + 1,1 + 1,2 + 1,92 + 0,36 + 2,781 + 2,781 + 1,854 + 1,854 + 5,562 + 5,562 + 1,854 = 27,928m² x 19 = 530,632m² | C29: janela | D29: 530.632
A30: Guarda corpo metálico – Área: 4,745m² x 19 = 90,155m² - Perímetro: 3,65m x 19 = 69,35m | C30: gradil | D30: 90.155
A31: Guarda corpo vidro – Área: 15,645m² x 19 = 297,255m² - Perímetro: 14,9m x 19 = 283,1m | C31: Guarda alumínio | D31: 297.255
A32: 2 portas corta-fogo 1 folha | B32: 2 | C32: pcf
A33: 2 portas de abrir madeira 1 folha | B33: 2 | C33: madeira
A34: 1 porta de abrir alumínio 1 folha – Área: 1,26m² | B34: 1 | C34: porta alumínio | D34: 1.26
A35: 1 janela-porta de correr vidro 3 folhas - Área: 15,21m² | B35: 1 | C35: janela | D35: 15.21
A36: 1 janela-porta de correr vidro 5 folhas - Área: 25,4205m² | B36: 1 | C36: janela | D36: 25.4205
A37: 1 janela-porta de correr vidro 5 folhas - Área: 17,8284m² | B37: 1 | C37: janela | D37: 17.8284
A38: Janelas – Área: 1,1 + 1,2 + 1,1 + 1,92 + 0,36 + 2,781 + 2,781 + 1,854 + 1,854 + 5,562 + 5,562 + 1,854 = 27,928m² | C38: janela | D38: 27.928
A39: Guarda corpo metálico – Área: 4,745m² - Perímetro: 3,65m | C39: gradil | D39: 4.745
A40: Guarda corpo vidro – Área: 15,645m² - Perímetro: 14,9m | C40: Guarda alumínio | D40: 15.645
A41: 2 portas corta-fogo 1 folha | B41: 2 | C41: pcf
A42: 7 portas de abrir madeira 1 folha | B42: 7 | C42: madeira
A43: 2 portas de correr madeira 1 folha | B43: 2 | C43: madeira
A44: 1 janela-porta de correr vidro 5 folhas - Área: 25,4205m² | B44: 1 | C44: janela | D44: 25.4205
A45: 1 janela-porta de correr vidro 5 folhas - Área: 17,8284m² | B45: 1 | C45: janela | D45: 17.8284
A46: Janelas – Área: 1,1 + 1,2 + 1,92 + 0,36 + 2,781 + 2,781 + 1,854 + 1,854 + 5,562 + 5,562 + 1,854 = 26,828m² | C46: janela | D46: 26.828
A47: Guarda corpo metálico – Área: 4,745m² - Perímetro: 3,65m | C47: gradil | D47: 4.745
A48: Guarda corpo vidro – Área: 15,645m² - Perímetro: 14,9m | C48: Guarda alumínio | D48: 15.645
A49: 2 portas corta-fogo 1 folha | B49: 2 | C49: pcf
A50: 4 portas de abrir madeira 1 folha | B50: 4 | C50: madeira
A51: 1 porta de abrir alumínio 1 folha – Área: 1,26m² | B51: 1 | C51: porta alumínio | D51: 1.26
A52: 1 porta de correr madeira 1 folha | B52: 1 | C52: madeira
A53: 1 porta de correr vidro 3 folhas – Área: 10,5m² | B53: 1 | C53: porta alumínio | D53: 10.5
A54: 1 janela-porta de correr vidro 5 folhas - Área: 25,4205m² | B54: 1 | C54: janela | D54: 25.4205
A55: 1 janela-porta de correr vidro 5 folhas - Área: 17,8284m² | B55: 1 | C55: janela | D55: 17.8284
A56: Janelas – Área: 1,1 + 1,2 + 1,1 + 1,92 + 0,36 + 2,781 + 2,781 + 1,854 + 1,854 + 5,562 + 5,562 + 1,854 = 27,928m² | C56: janela | D56: 27.928
A57: Guarda corpo metálico – Área: 4,745m² - Perímetro: 3,65m | C57: gradil | D57: 4.745
A58: Guarda corpo vidro – Área: 15,645m² - Perímetro: 14,9m | C58: Guarda alumínio | D58: 15.645
A59: 2 portas corta-fogo 1 folha | B59: 2 | C59: pcf
A60: 7 portas de abrir madeira 1 folha | B60: 7 | C60: madeira
A61: 1 janela-porta de correr vidro – Área: 5,61m² | B61: 1 | C61: janela | D61: 5.61
A62: Janela – Área: 1,1 + 1,2 + 1,92 + 0,36 + 2,781 + 2,781 + 1,854 + 1,854 + 5,562 + 5,562 + 1,854 + 25,0512 + 17,8284 = 69,7076m² | C62: janela | D62: 69.7076
A63: Guarda corpo metálico – Área: 4,745m² - Perímetro: 3,65m | C63: gradil | D63: 4.745
A64: Guarda corpo vidro – Área: 15,645m² - Perímetro: 14,9m | C64: Guarda alumínio | D64: 15.645
A65: 2 portas corta-fogo 1 folha | B65: 2 | C65: pcf
A66: 2 portas de abrir alumínio 1 folha – Área: 1,47m² x 2 = 2,94m² | B66: 2 | C66: porta alumínio | D66: 2.94
A67: Janelas – Area: 1,1 + 1,2 + 0,84 + 0,84 + 3,549 + 3,549 + 10,647 + 10,647 = 32,372m² | C67: janela | D67: 32.372
A68: Guarda corpo metálico – Área: 4,745m² - Perímetro: 3,65m | C68: gradil | D68: 4.745
