Workbook
Name \0: #REF!
Name \a: #REF!
Name \m: #REF!
Name aa: #REF!
Name aaaa: [1]M.O.!#REF!
Name angelo: [2]Geral!#REF!
Name aux: #REF!
Name BDA: #REF!
Name BDI: #REF!
Name ca: #REF!
Name Capa: #REF!
Name cronograma: #REF!
Name D: #REF!
Name direto: #REF!
Name DRE: #REF!
Name ea: #REF!
Name FFFFFFF: #REF!
Name item_1: #REF!
Name LS: [1]M.O.!#REF!
Name MENU: #REF!
Name MENU1: #REF!
Name MENU2: #REF!
Name MENU3: #REF!
Name MENU4: #REF!
Name MENU5: #REF!
Name MENU6: #REF!
Name mo: #REF!
Name OAE: #REF!
Name PAV: #REF!
Name pr: #REF!
Name PRE: #REF!
Name Print_Area_MI: #REF!
Name qe: #REF!
Name qee: #REF!
Name reforsu: #REF!
Name ren: #REF!
Name REV: #REF!
Name sa: #REF!
Name SEG: #REF!
Name SIH: #REF!
Name SIV: #REF!
Name ss: #REF!
Name susref: #REF!
Name tania: #REF!
Name tc: #REF!
Name TOT: #REF!
Name Total: #REF!
Name TRP: #REF!
Name xxxx: #REF!

Sheet CUSTOS INDIRETOS
A1: ORÇAMENTO PARAMÉTRICO - CUSTOS INDIRETOS
A7: Cliente | B7: =[3]OBRA!B2 -> Neuhaus
A8: Obra | B8: =[3]OBRA!B1 -> Origem 3300
A9: Data | B9: 45462
A10: Versão | B10: R03
A12: GERENCIAMENTO TÉCNICO
A13: Código | B13: Descrição | C13: Un. | D13: Quantidade orçada | E13: Preço unitário | F13: Preço total | G13: observação
A14: 01 | B14: GERENCIAMENTO TÉCNICO | F14: =SUM(F20+F15) -> 1276327.1
A15: 01.001 | B15: ESTUDOS, PROJETOS E CONSULTORIAS | F15: =SUM(F16:F19) -> 584595.64
A16: 01.001.001 | B16: Estudos | F16: 28641.924
A17: 01.001.002 | B17: Projetos | F17: 466942.45
A18: 01.001.003 | B18: Consultorias | F18: 63138.444
A19: 01.001.004 | B19: Ensaios e Laudos | F19: 25872.825
A20: 01.002 | B20: TAXAS E DOCUMENTOS | F20: =SUM(F21:F23) -> 691731.43
A21: 01.002.001 | B21: Seguros | F21: 94382.854
A22: 01.002.002 | B22: Licenciamentos, Taxas, Impostos | F22: 529878.77
A23: 01.002.003 | B23: Documentos | F23: 67469.811
A24: 02 | B24: GERENCIAMENTO ADMINISTRATIVO | F24: =SUM(F25+F38+F61) -> 6238585.7
A25: 02.001 | B25: SEGURANÇA, MEIO AMBIENTE E SAÚDE | F25: =SUM(F26+F28+F37) -> 1052775.2
A26: 02.001.001 | B26: Segurança do Trabalho | F26: 168000
A27: 02.001.001.001 | B27: Serviço de segurança do trabalho terceirizado | C27: mes | D27: 48 | E27: 3500 | F27: 168000
A28: 02.001.002 | B28: Equipamentos de proteção | F28: 795976.47
A29: 02.001.002.001 | B29: Bandeja de proteção primária | C29: m | D29: 301.68 | E29: 350 | F29: 105588
A30: 02.001.002.002 | B30: Bandeja de proteção secundária | C30: m | D30: 779.67 | E30: 300 | F30: 233901
A31: 02.001.002.003 | B31: Guarda corpo em laje pós - desforma | C31: m | D31: 754.2 | E31: 49 | F31: 36955.8
A32: 02.001.002.004 | B32: Fechamento removível de vãos de porta de elevador em madeira | C32: m2 | D32: 638.55 | E32: 50 | F32: 31927.5
A33: 02.001.002.005 | B33: Varal de segurança com cabo de aço (linha de vida) | C33: m | D33: 754.2 | E33: 244 | F33: 184024.8
A34: 02.001.002.006 | B34: Sinalização com placa indicativa fixada na estrutura | C34: vb | D34: 1 | E34: 15968.018 | F34: 15968.018
A35: 02.001.002.007 | B35: Tela fachadeira reforçada com impressão digital | C35: m2 | D35: 9974.09 | E35: 15 | F35: 149611.35
A36: 02.001.002.008 | B36: Equipamentos de proteção individual | C36: vb | D36: 1 | E36: 38000 | F36: 38000
A37: 02.001.003 | B37: Meio Ambiente | F37: 88798.778
A38: 02.002 | B38: ADMINISTRAÇÃO E CANTEIRO DE OBRA | F38: =SUM(F39+F49+F60+F52) -> 3331912.5
A39: 02.002.001 | B39: Equipe de Gestão e Apoio | F39: =SUM(F40:F48) -> 2461893.1 | G39: falta adicionar o tecnico de segurança
A40: 02.002.001.001 | B40: Engenheiro civil | C40: mes | D40: 48 | E40: 12000 | F40: 576000
A41: 02.002.001.002 | B41: Almoxarife | C41: mes | D41: 48 | E41: 4254.448 | F41: 204213.5
A42: 02.002.001.003 | B42: Mestre de obras | C42: mes | D42: 48 | E42: 8369.792 | F42: 401750.02
A43: 02.002.001.004 | B43: Estagiário | C43: mes | D43: 48 | E43: 3000 | F43: 144000
A44: 02.002.001.005 | B44: Serviço de vigilância 24h | C44: mes | D44: 48 | E44: 5086.84 | F44: 244168.32 | G44: será contratado uma pessoa, ou somente empresa de vigilãncia?
A45: 02.002.001.006 | B45: Operador de grua | C45: mes | D45: 22 | E45: 7800 | F45: 171600
A46: 02.002.001.007 | B46: Servente para segurança | C46: mes | D46: 48 | E46: 3812.48 | F46: 182999.04
A47: 02.002.001.008 | B47: Carpinteiro para segurança | C47: mes | D47: 48 | E47: 7142.88 | F47: 342858.24
A48: 02.002.001.009 | B48: Portaria | C48: mes | D48: 48 | E48: 4048 | F48: 194304
A49: 02.002.002 | B49: Operação Inicial do Canteiro | F49: =SUM(F50:F51) -> 34191.804
A50: 02.002.002.001 | B50: Limpeza mecanizada de camada vegetal | C50: m2 | D50: 1294.4 | E50: 12.5 | F50: 16180
A51: 02.002.002.002 | B51: Locação da obra | C51: m | D51: 150.84 | E51: 119.41 | F51: 18011.804
A52: 02.002.003 | B52: Instalações Provisórias | F52: =SUM(F53:F59) -> 327754.23
A53: 02.002.003.001 | B53: Locação de banheiro químico | C53: mes | D53: 25 | E53: 1700 | F53: 85000 | G53: não teremos, adicionar em provisório de agua
A54: 02.002.003.002 | B54: Instalações de canteiro | C54: vb | D54: 1 | E54: 145163.8 | F54: 145163.8
A55: 02.002.003.003 | B55: Instalações Provisórias: Redes de Água Fria, Esgoto e Drenagem | C55: vb | D55: 1 | E55: 12355.57 | F55: 12355.57
A56: 02.002.003.004 | B56: Instalações Provisórias: Redes Elétrica, Comunicação e Dados | C56: vb | D56: 1 | E56: 12355.57 | F56: 12355.57
A57: 02.002.003.005 | B57: Mobiliário de apoio a obra | C57: vb | D57: 1 | E57: 14300 | F57: 14300
A58: 02.002.003.006 | B58: Equipamentos escritório - aquisição | C58: vb | D58: 1 | E58: 33000 | F58: 33000
A59: 02.002.003.007 | B59: Tapume com telha metálica | C59: m2 | D59: 214.214 | E59: 119.41 | F59: 25579.294
A60: 02.002.005 | B60: Despesas de Consumo e Manutenção | F60: 508073.3
A61: 02.003 | B61: EQUIPAMENTOS | F61: =F62+F77 -> 1853898
A62: 02.003.001 | B62: Equipamentos de Obra | F62: =SUM(F63:F76) -> 1794425
A63: 02.003.001.001 | B63: Ferramentas - aquisição/manutenção | C63: vb | D63: 1 | E63: 60800 | F63: 60800
A64: 02.003.001.002 | B64: Mobilização e desmobilização de grua | C64: Un. | D64: 1 | E64: 24000 | F64: 24000
A65: 02.003.001.003 | B65: Locação de grua | C65: mes | D65: 22 | E65: 22000 | F65: 484000
A66: 02.003.001.004 | B66: Serviço de montagem de grua | C66: Un. | D66: 1 | E66: 7500 | F66: 7500
A67: 02.003.001.005 | B67: Serviço de desmontagem de grua | C67: Un. | D67: 1 | E67: 20000 | F67: 20000
A68: 02.003.001.006 | B68: Ascensão da grua | C68: Un. | D68: 11 | E68: 4500 | F68: 49500
A69: 02.003.001.007 | B69: Manutenção preventiva de grua | C69: mes | D69: 22 | E69: 2100 | F69: 46200
A70: 02.003.001.008 | B70: Locação de elevador cremalheira | C70: mes | D70: 45 | E70: 20000 | F70: 900000
A71: 02.003.001.009 | B71: Montagem e ascenção de elevador cremalheira | C71: vb | D71: 1 | E71: 48000 | F71: 48000 | G71: reajustado valores, mais proximos dos executados
A72: 02.003.001.010 | B72: Desmontagem de elevador cremalheira | C72: Un. | D72: 2 | E72: 15000 | F72: 30000
A73: 02.003.001.011 | B73: Manutenção preventiva de elevador cremalheira | C73: mes | D73: 15 | E73: 3000 | F73: 45000 | G73: reajustado valores, mais proximos dos executados
A74: 02.003.001.012 | B74: Locação de balancim | C74: mes | D74: 12 | E74: 3800 | F74: 45600
A75: 02.003.001.013 | B75: Montagem e desmontagem de balancim | C75: Un. | D75: 51 | E75: 450 | F75: 22950
A76: 02.003.001.014 | B76: Manutenção periódica de balancim | C76: mes | D76: 10 | E76: 1087.5 | F76: 10875
A77: 02.003.001 | B77: Andaimes | F77: =SUM(F78:F80) -> 59473
A78: 02.003.001.001 | B78: Locação de andaime fachadeiro | C78: mes | D78: 10 | E78: 3000 | F78: 30000
A79: 02.003.001.002 | B79: Mão de obra de montagem de andaime fachadeiro | C79: m2 | D79: 514.04 | E79: 50 | F79: 25702
A80: 02.003.001.003 | B80: Plataformas de trabalho em madeira para andaime | C80: m | D80: 150.84 | E80: 25 | F80: 3771
A81: Total | F81: =F24+F14 -> 7514912.8

Sheet ORÇAMENTO RESUMO
A1: CÓDIGO | B1: ITEM | C1: Quantidade | D1: Unidade | E1: Valor Orçado | F1: Considerações
A2: 1 | B2: GERENCIAMENTO TÉCNICO E ADMINISTRATIVO | E2: ='CUSTOS INDIRETOS'!F81 -> 7514912.8 | F2: =E2/$E$187 -> 0.11527965
A3: 1.1 | B3: GERENCIAMENTO TÉCNICO E ADMINISTRATIVO | E3: =E2 -> 7514912.8
A4: 1.1.1 | B4: Gerenciamento técnico e administrativo | C4: 1 | D4: vb | E4: =E3 -> 7514912.8
A5: 2 | B5: MOVIMENTAÇÃO DE TERRA | E5: =E6 -> 334397.12 | F5: =E5/$E$187 -> 0.0051296913
A6: 2.1 | B6: MOVIMENTAÇÃO DE TERRA | E6: =SUM(E7:E12) -> 334397.12
A7: 2.1.1 | B7: Rebaixamento de lençol freático | C7: 10 | D7: dias | E7: ='[4]Movimentação de Terra'!$I$22 -> 5500
A8: 2.1.2 | B8: Escavação mecanizada para blocos e baldrames | C8: 512.02 | D8: m3 | E8: ='[4]Movimentação de Terra'!$I$29 -> 134618
A9: 2.1.3 | B9: Reaterro para blocos e baldrames | C9: 118.16 | D9: m3 | E9: ='[4]Movimentação de Terra'!$I$30 -> 13592
A10: 2.1.4 | B10: Movimentação de terra (30% de empolamento) | C10: 3014.01 | D10: m3 | E10: ='[4]Movimentação de Terra'!$I$31 -> 131906.25
A11: 2.1.5 | B11: Bota-fora da escavação | C11: 640.03 | D11: m3 | E11: ='[4]Movimentação de Terra'!$I$32 -> 19200.87
A12: 2.1.6 | B12: Lastro de concreto magro e= 10cm - Blocos | C12: 1035.52 | D12: m2 | E12: ='[4]Movimentação de Terra'!$I$39 -> 29580
A13: 3 | B13: INFRAESTRUTURA | E13: =E14+E20 -> 2808959.2 | F13: =E13/$E$187 -> 0.043089765
A14: 3.1 | B14: FUNDAÇÃO PROFUNDA | E14: =SUM(E15:E19) -> 1874063.4
A15: 3.1.1 | B15: Estaca hélice contínua diâmetro 50cm | C15: 608 | D15: m | E15: =[4]Infraestrutura!$I$17 -> 66880 | F15: 19 estacas com 32 metros de profundidade
A16: 3.1.2 | B16: Estaca hélice contínua diâmetro 60cm | C16: 4371 | D16: m | E16: =[4]Infraestrutura!$I$19 -> 502986.42 | F16: 141 estacas com 32 metros de profundidade
A17: 3.1.3 | B17: Armação | C17: 20729 | D17: kg | E17: =[4]Infraestrutura!$I$20 -> 176197 | F17: Consideração de R$ 8,50/kg
A18: 3.1.4 | B18: Concreto | C18: 1675 | D18: m3 | E18: =[4]Infraestrutura!$I$21 -> 1072000 | F18: Consideração de R$ 640,00/m³ com 10% de perda
A19: 3.1.5 | B19: Arrasamento de estacas | C19: 160 | D19: und | E19: =[4]Infraestrutura!$I$22 -> 56000
A20: 3.2 | B20: FUNDAÇÃO RASA | E20: =SUM(E21:E24) -> 934895.74
A21: 3.2.1 | B21: Fabricação, montagem e desmontagem de forma para blocos e baldrames | C21: 983.74 | D21: m² | E21: =[4]Infraestrutura!$I$29 -> 41809.12
A22: 3.2.2 | B22: Armação | C22: 39386.4 | D22: kg | E22: =[4]Infraestrutura!$I$30 -> 334784.4 | F22: Consideração de R$ 8,50/kg
A23: 3.2.3 | B23: Concreto | C23: 492.33 | D23: m³ | E23: =[4]Infraestrutura!$I$31 -> 196439.67 | F23: Consideração de R$ 640,00/m³ com 5% de perda
A24: 3.2.5 | B24: Mão de obra infraestrutura | C24: 984.66 | D24: vb | E24: =[4]Infraestrutura!$I$32 -> 361862.55 | F24: Consideração de área do térreo
A25: 5 | B25: SUPRAESTRUTURA | E25: =E26+E30+E33+E36+E38 -> 18837581 | F25: =E25/$E$187 -> 0.28897072
A26: 5.1 | B26: FORMA | E26: =E27+E28+E29 -> 5572992.1
A27: 5.1.1 | B27: Fabricação forma | C27: 14500 | D27: m² | E27: {=[5]Supraestrutura!$I$15:$J$15} -> 4970913.8 | F27: #REF! | G27: 158 reais o m2 da forma esta de acordo, porem se usarmos a metragem total de area do empreendimento já da um valor grande pois não estamos levando em conta as repetições . consideraria 5000 m2 de forma para o embasamento, pois 2 jogos fazer toda o embasamento. E para a torre 3 mil m2 de forma, por serão 3 jogos de formas com 2 jogos, levando em consideração 500m2 de area de laje. | H27: 1264000
A28: 5.1.2 | B28: Montagem de forma | C28: 36290.95 | D28: m² | E28: {=[5]Supraestrutura!$I$16:$J$16} -> 489927.82 | F28: #REF! | G28: mover verba para m.o. de supraestrutura | H28: excluir
A29: 5.1.3 | B29: Protensão | C29: 9117.92 | D29: m² | E29: =[5]Supraestrutura!$I$19 -> 112150.42 | F29: Consideração todas as lajes da torre | G29: desconsiderar este item.... Já incluso no fabricaçao de forma | H29: excluir
A30: 5.2 | B30: ESCORAMENTO | E30: =E31+E32 -> 638866.85
A31: 5.2.1 | B31: Escoramento - Torre | C31: 9117.92 | D31: m² | E31: =[4]Supraestrutura!$I$17 -> 322383.6 | F31: rever quantidade | G31: considerar 21 reais o m2
A32: 5.2.2 | B32: Escoramento - Embasamento | C32: 5188.25 | D32: m² | E32: =[4]Supraestrutura!$I$18 -> 316483.25 | F32: rever quantidade | G32: considerar 48 reais o m2 | J32: 3822.31
A33: 5.3 | B33: ARMADURA | E33: =E34+E35 -> 5113896.4 | J33: 484
A34: 5.3.1 | B34: Armadura Convencional para Estrutura | C34: 550544 | D34: kg | E34: =[5]Supraestrutura!$I$23 -> 4679624 | F34: Consideração de R$ 9,00/kg | G34: considerar 7,20 o kg do aço com arame e espaçadores | J34: =J33/J32 -> 0.126625
A35: 5.3.2 | B35: Cabos para protensão | C35: =25941.8+9364.9 -> 35306.7 | D35: kg | E35: =[6]Supraestrutura!$I$20+[6]Supraestrutura!$I$22 -> 434272.41 | F35: Consideração de 1,83 kg/m² de laje e 12,30/kg | G35: ok, verificaer somente quantidade | J35: =J32/J33 -> 7.8973347
A36: 5.4 | B36: CONCRETO | E36: =E37 -> 3748686.5
A37: 5.4.1 | B37: Concreto | C37: 5409.36 | D37: m³ | E37: =[5]Supraestrutura!$I$24 -> 3748686.5 | F37: Consideração de R$ 640,00/m³ com 5% de perda | G37: ok
A38: 5.5 | B38: MÃO DE OBRA | E38: =E39+E40 -> 3763139
A39: 5.5.1 | B39: Mão de obra supraestrutura | C39: 14516.38 | D39: m² | E39: =[6]Supraestrutura!$I$25 -> 3511139 | F39: Valor estimado com base na área construída | G39: ok
A40: 5.5.2 | B40: Serviços de protensão | C40: 28 | D40: und | E40: =[4]Supraestrutura!$I$21 -> 252000 | F40: Valor estimado por laje da torre | G40: ok
A41: 6 | B41: ALVENARIA | E41: =E42 -> 3060534.4 | F41: =E41/$E$187 -> 0.046948959
A42: 6.1 | B42: ALVENARIA | E42: =SUM(E43:E56) -> 3060534.4
A43: 6.1.1 | B43: Alvenaria embasamento | C43: 4136.11 | D43: m² | E43: =[4]Alvenaria!$I$15 -> 206805.5 | F43: Consideração de bloco cerâmico de 14x19x19cm
A44: 6.1.2 | B44: Alvenaria lazer | C44: 723.12022 | D44: m² | E44: =[4]Alvenaria!$I$16 -> 36156.011 | F44: Consideração de bloco cerâmico de 14x19x19cm
A45: 6.1.3 | B45: Drywall lazer | C45: 614.01044 | D45: m² | E45: =[4]Alvenaria!$I$17 -> 135082.3 | F45: Considerado material e mão de obra
A46: 6.1.4 | B46: Alvenaria tipo | C46: 5752.142 | D46: m² | E46: =[4]Alvenaria!$I$18 -> 287607.1 | F46: Consideração de bloco cerâmico de 14x19x19cm
A47: 6.1.5 | B47: Drywall tipo | C47: 6040.443 | D47: m² | E47: =[4]Alvenaria!$I$19 -> 1328897.5 | F47: Considerado material e mão de obra
A48: 6.1.6 | B48: Alvenaria dupla tipo | C48: 490.66552 | D48: m² | E48: =[4]Alvenaria!$I$20 -> 92245.118 | F48: Consideração de bloco cerâmico de 14x19x19cm
A49: 6.1.7 | B49: Alvenaria tipo diferenciado | C49: 288.1447 | D49: m² | E49: =[4]Alvenaria!$I$21 -> 14407.235 | F49: Consideração de bloco cerâmico de 14x19x19cm
A50: 6.1.8 | B50: Drywall Diferenciado | C50: 304.95388 | D50: m² | E50: =[4]Alvenaria!$I$22 -> 67089.853 | F50: Considerado material e mão de obra
A51: 6.1.9 | B51: Alvenaria dupla | C51: 24.77142 | D51: m² | E51: =[4]Alvenaria!$I$23 -> 4657.027 | F51: Consideração de bloco cerâmico de 14x19x19cm
A52: 6.1.10 | B52: Alvenaria cobertura / reservatório | C52: 307.64 | D52: m² | E52: =[4]Alvenaria!$I$24 -> 15382 | F52: Consideração de bloco cerâmico de 14x19x19cm
A53: 6.1.11 | B53: Bloco de concreto autoclavado | C53: 2096.07 | D53: m² | E53: =[4]Alvenaria!$I$25 -> 125764.2 | F53: Considerado área das escadas e churrasqueiras
A54: 6.1.12 | B54: Serviços complementares | C54: 13818.664 | D54: m² | E54: =[4]Alvenaria!$I$26 -> 172733.3 | F54: Considerado tela, encunhamento, verga e contraverga
A55: 6.1.13 | B55: Mão de obra - Bloco Cerâmico | C55: 11722.594 | D55: m² | E55: =[4]Alvenaria!$I$27 -> 468903.75
A56: 6.1.14 | B56: Mão de obra - Bloco Concreto | C56: 2096.07 | D56: m² | E56: =[4]Alvenaria!$I$28 -> 104803.5
A57: 7 | B57: INSTALAÇÕES ELÉTRICAS, HIDRÁULICAS E GLP | E57: =E58+E66+E75 -> 5636274.9 | F57: =E57/$E$187 -> 0.086461122
A58: 7.1 | B58: INSTALAÇÕES ELÉTRICAS | E58: =SUM(E59:E65) -> 2448913.3
A59: 7.1.1 | B59: Entrada de Energia | C59: 1 | D59: vb | E59: =[4]Instalações!$I$15 -> 72581.9
A60: 7.1.2 | B60: Eletrodutos e Eletrocalhas | C60: 1 | D60: vb | E60: =[4]Instalações!$I$16 -> 185809.66
A61: 7.1.3 | B61: Instalações Embutidas e Aparentes | C61: 1 | D61: vb | E61: =[4]Instalações!$I$17 -> 245326.82
A62: 7.1.4 | B62: Cabos e Fiações | C62: 1 | D62: vb | E62: =[4]Instalações!$I$18 -> 580655.2
A63: 7.1.5 | B63: Quadros e Disjuntores | C63: 1 | D63: vb | E63: =[4]Instalações!$I$19 -> 290327.6
A64: 7.1.7 | B64: Equipamentos e Iluminação | C64: 1 | D64: vb | E64: =[4]Instalações!$I$20 -> 275811.22
A65: 7.1.8 | B65: Mão de Obra para Instalações Elétricas | C65: 1 | D65: vb | E65: =[4]Instalações!$I$21 -> 798400.9
A66: 7.2 | B66: INSTALAÇÕES HIDRÁULICAS | E66: =SUM(E67:E74) -> 2359927.9
A67: 7.2.1 | B67: Instalações de Água Fria | C67: 1 | D67: vb | E67: =[4]Instalações!$I$27 -> 362909.5
A68: 7.2.2 | B68: Instalações de Água Quente | C68: 1 | D68: vb | E68: =[4]Instalações!$I$28 -> 217745.7
A69: 7.2.3 | B69: Instalações de Águas Pluviais | C69: 1 | D69: vb | E69: =[4]Instalações!$I$29 -> 145163.8
A70: 7.2.4 | B70: Instalações Sanitárias | C70: 1 | D70: vb | E70: =[4]Instalações!$I$30 -> 217745.7
A71: 7.2.5 | B71: Louças e Metais | C71: 1 | D71: vb | E71: =[4]Instalações!$I$31 -> 5371.0606
A72: 7.2.6 | B72: Cisterna | C72: 1 | D72: vb | E72: =[4]Instalações!$I$32 -> 31936.036
A73: 7.2.7 | B73: Sistemas de bombas | C73: 1 | D73: vb | E73: =[4]Instalações!$I$33 -> 653237.1
A74: 7.2.8 | B74: Mão de Obra para Instalações Hidráulicas | C74: 1 | D74: vb | E74: =[4]Instalações!$I$34 -> 725819
A75: 7.3 | B75: INSTALAÇÕES PREVENTIVAS E GLP | E75: =SUM(E76:E78) -> 827433.66
A76: 7.3.1 | B76: Instalações Preventivas | C76: 1 | D76: vb | E76: 362909.5
A77: 7.3.2 | B77: Instalações de GLP | C77: 1 | D77: vb | E77: 319360.36
A78: 7.3.3 | B78: Instalações de Proteção e Aterramento - SPDA | C78: 1 | D78: vb | E78: 145163.8
A79: 8 | B79: SISTEMAS ESPECIAIS | E79: =E80+E85+E91+E93+E87 -> 4015448.3 | F79: =E79/$E$187 -> 0.061597452
A80: 8.1 | B80: CLIMATIZAÇÃO, EXAUSTÃO MECÂNICA E PRESSURIZAÇÃO | E80: =SUM(E81:E84) -> 637000
A81: 8.1.1 | B81: Infraestrutura para Instalação de Ar Condicionado | C81: 226 | D81: und | E81: 339000 | F81: Consideração de áres comuns, aptos e salas comerciais
A82: 8.1.2 | B82: Instalação de Ar Condicionado | C82: 16 | D82: un | E82: ='[4]Sistemas especiais'!$I$16 -> 60000 | F82: Considerando somente as áreas comuns
A83: 8.1.3 | B83: Ventokit | C83: 54 | D83: un | E83: ='[4]Sistemas especiais'!$I$17 -> 184000 | F83: Ventilação mecânica em banheiros enclausurados
A84: 8.1.4 | B84: Churrasqueiras | C84: 46 | D84: un | E84: ='[4]Sistemas especiais'!$I$18 -> 54000 | F84: Considerado uma por apto e mais áreas comuns
A85: 8.2 | B85: AUTOMAÇÃO | E85: =SUM(E86) -> 116131.04
A86: 8.2.1 | B86: Automação, telecomunicação e sistemas de segurança | C86: 1 | D86: vb | E86: 116131.04
A87: 8.3 | B87: COMUNICAÇÃO | E87: =SUM(E88:E90) -> 377425.88
A88: 8.3.1 | B88: CFTV | C88: 1 | D88: vb | E88: 72581.9
A89: 8.3.2 | B89: Interfone | C89: 1 | D89: vb | E89: ='[4]Sistemas especiais'!$I$25 -> 130647.42
A90: 8.3.3 | B90: TV e internet | C90: 1 | D90: vb | E90: ='[4]Sistemas especiais'!$I$26 -> 174196.56
A91: 8.4 | B91: OUTROS SISTEMAS | E91: =SUM(E92) -> 435491.4
A92: 8.4.1 | B92: Outros sistemas | C92: 1 | D92: vb | E92: 435491.4
A93: 8.5 | B93: SISTEMAS ESPECIAIS | E93: =SUM(E94:E100) -> 2449400
A94: 8.5.1 | B94: Grupo de geradores | C94: 1 | D94: un | E94: ='[4]Sistemas especiais'!$I$49 -> 120000 | F94: 1 gerador no G1
A95: 8.5.2 | B95: Elevador | C95: 2 | D95: un | E95: ='[4]Sistemas especiais'!$I$44 -> 1320000 | F95: 2 elevadores sociais
A96: 8.5.3 | B96: Elevador de serviço | C96: 1 | D96: um | E96: ='[4]Sistemas especiais'!$I$45 -> 660000 | F96: 1 elevador para serviço
A97: 8.5.4 | B97: Saunas | C97: 2 | D97: un | E97: ='[4]Sistemas especiais'!$I$47 -> 40000 | F97: 1 sauna lazer e 1 pvto Penthouse
A98: 8.5.5 | B98: SPA | C98: 1 | D98: un | E98: ='[4]Sistemas especiais'!$I$48 -> 35000 | F98: Considerado no pvto Lazer 02
A99: 8.5.6 | B99: Equipamentos piscina | C99: 2 | D99: un | E99: ='[4]Sistemas especiais'!$I$46 -> 240000 | F99: Considerado 2 piscinas, 1 no lazer e 1 no pvto Penthouse
A100: 8.5.7 | B100: Infraestrutura de carro elétrico | C100: 43 | D100: un | E100: 34400 | F100: Considerado 1 ponto por apto
...
