Workbook
Name \0: #REF!
Name \a: #REF!
Name \m: #REF!
Name aa: #REF!
Name aa: #REF!
Name aa: #REF!
Name aaaa: '[1]M.O.'!#REF!
Name aaaa: '[1]M.O.'!#REF!
Name angelo: [2]Geral!#REF!
Name angelo: [2]Geral!#REF!
Name Área_Construída: #REF!
Name Área_Privativa: #REF!
Name Área_Terreno: #REF!
Name aux: #REF!
Name aux: #REF!
Name aux: #REF!
Name BDA: #REF!
Name BDA: #REF!
Name BDA: #REF!
Name BDI: #REF!
Name BDI: #REF!
Name BDI: #REF!
Name ca: #REF!
Name ca: #REF!
Name ca: #REF!
Name Capa: #REF!
Name Capa: #REF!
Name Capa: #REF!
Name cronograma: #REF!
Name cronograma: #REF!
Name cronograma: #REF!
Name D: #REF!
Name D: #REF!
Name D: #REF!
Name direto: #REF!
Name direto: #REF!
Name direto: #REF!
Name DRE: #REF!
Name DRE: #REF!
Name DRE: #REF!
Name ea: #REF!
Name ea: #REF!
Name ea: #REF!
Name eee: {#N/A,#N/A,FALSE,"ET-CAPA";#N/A,#N/A,FALSE,"ET-PAG1";#N/A,#N/A,FALSE,"ET-PAG2";#N/A,#N/A,FALSE,"ET-PAG3";#N/A,#N/A,FALSE,"ET-PAG4";#N/A,#N/A,FALSE,"ET-PAG5"}
Name eee: {#N/A,#N/A,FALSE,"ET-CAPA";#N/A,#N/A,FALSE,"ET-PAG1";#N/A,#N/A,FALSE,"ET-PAG2";#N/A,#N/A,FALSE,"ET-PAG3";#N/A,#N/A,FALSE,"ET-PAG4";#N/A,#N/A,FALSE,"ET-PAG5"}
Name FFFFFFF: #REF!
Name item_1: #REF!
Name item_1: #REF!
Name item_1: #REF!
Name LS: '[1]M.O.'!#REF!
Name LS: '[1]M.O.'!#REF!
Name MENU: #REF!
Name MENU: #REF!
Name MENU: #REF!
Name MENU1: #REF!
Name MENU1: #REF!
Name MENU1: #REF!
Name MENU2: #REF!
Name MENU2: #REF!
Name MENU2: #REF!

Sheet CAPA
A1: Obra | B1: ORIGEM 3003
A2: Empresa | B2: NEUHAUS INCORPORADORA
A3: Revisão | B3: R04
A4: DADOS OBRA
B8: ORÇAMENTO PARAMÉTRICO - R04
B9: ORIGEM 3300

Sheet Custos_Indiretos
A1: ORÇAMENTO PARAMÉTRICO - CUSTOS INDIRETOS
A7: Cliente | B7: =[3]OBRA!B2 -> Neuhaus
A8: Obra | B8: =[3]OBRA!B1 -> Origem 3300
A9: Data | B9: 45509
A10: Versão | B10: R04
A12: GERENCIAMENTO TÉCNICO
A13: Código | B13: Descrição | C13: Un. | D13: Quantidade orçada | E13: Preço unitário | F13: Preço total
A14: 01 | B14: GERENCIAMENTO TÉCNICO | F14: =SUM(F20+F15) -> 1276327.1
A15: 01.001 | B15: ESTUDOS, PROJETOS E CONSULTORIAS | F15: =SUM(F16:F19) -> 584595.64
A16: 01.001.001 | B16: Estudos | F16: 28641.924
A17: 01.001.002 | B17: Projetos | F17: 466942.45
A18: 01.001.003 | B18: Consultorias | F18: 63138.444
A19: 01.001.004 | B19: Ensaios e Laudos | F19: 25872.825
A20: 01.002 | B20: TAXAS E DOCUMENTOS | F20: =SUM(F21:F23) -> 691731.43
A21: 01.002.001 | B21: Seguros | F21: 94382.854
A22: 01.002.002 | B22: Licenciamentos, Taxas, Impostos | F22: 529878.77
A23: 01.002.003 | B23: Documentos | F23: 67469.811
A24: 02 | B24: GERENCIAMENTO ADMINISTRATIVO | F24: =SUM(F25+F39+F61) -> 6014676.6
A25: 02.001 | B25: SEGURANÇA, MEIO AMBIENTE E SAÚDE | F25: =SUM(F26+F28+F38) -> 850034.45
A26: 02.001.001 | B26: Segurança do Trabalho | F26: =F27 -> 19200
A27: 02.001.001.001 | B27: Serviço de segurança do trabalho terceirizado | C27: mes | D27: 48 | E27: 400 | F27: =E27*D27 -> 19200
A28: 02.001.002 | B28: Equipamentos de proteção | F28: =SUM(F29:F37) -> 742035.67
A29: 02.001.002.001 | B29: Bandeja de proteção primária | C29: m | D29: 301.68 | E29: 350 | F29: 105588
A30: 02.001.002.002 | B30: Bandeja de proteção secundária | C30: m | D30: 779.67 | E30: 300 | F30: 233901
A31: 02.001.002.003 | B31: Guarda corpo em laje pós - desforma | C31: m | D31: 754.2 | E31: 49 | F31: 36955.8
A32: 02.001.002.004 | B32: Fechamento removível de vãos de porta de elevador em madeira | C32: m2 | D32: 638.55 | E32: 50 | F32: 31927.5
A33: 02.001.002.005 | B33: Varal de segurança com cabo de aço | C33: m | D33: 754.2 | E33: 20 | F33: =E33*D33 -> 15084
A34: 02.001.002.006 | B34: Sinalização com placa indicativa fixada na estrutura | C34: vb | D34: 1 | E34: 15968.018 | F34: 15968.018
A35: 02.001.002.007 | B35: Tela fachadeira reforçada com impressão digital | C35: m2 | D35: 9974.09 | E35: 15 | F35: 149611.35
A36: 02.001.002.008 | B36: Equipamentos de proteção individual | C36: vb | D36: 1 | E36: 38000 | F36: 38000
A37: 02.001.002.009 | B37: Tela SLQA | C37: vb | D37: 1 | E37: 115000 | F37: =E37*D37 -> 115000
A38: 02.001.003 | B38: Meio Ambiente | F38: 88798.778
A39: 02.002 | B39: ADMINISTRAÇÃO E CANTEIRO DE OBRA | F39: =SUM(F40+F50+F60+F53) -> 3338744.1
A40: 02.002.001 | B40: Equipe de Gestão e Apoio | F40: =SUM(F41:F49) -> 2553724.8
A41: 02.002.001.001 | B41: Engenheiro civil | C41: mes | D41: 48 | E41: 12000 | F41: 576000
A42: 02.002.001.002 | B42: Almoxarife | C42: mes | D42: 48 | E42: 4254.448 | F42: 204213.5
A43: 02.002.001.003 | B43: Mestre de obras | C43: mes | D43: 48 | E43: 8369.792 | F43: 401750.02
A44: 02.002.001.004 | B44: Estagiário | C44: mes | D44: 48 | E44: 3000 | F44: 144000
A45: 02.002.001.006 | B45: Operador de grua | C45: mes | D45: 22 | E45: 7800 | F45: 171600
A46: 02.002.001.007 | B46: Servente para segurança | C46: mes | D46: 48 | E46: 3812.48 | F46: 182999.04
A47: 02.002.001.008 | B47: Carpinteiro para segurança | C47: mes | D47: 48 | E47: 7142.88 | F47: 342858.24
A48: 02.002.001.009 | B48: Portaria | C48: mes | D48: 48 | E48: 4048 | F48: 194304
A49: 02.002.001.010 | B49: Técnico de segurança do trabalho | C49: mes | D49: 48 | E49: 7000 | F49: =E49*D49 -> 336000
A50: 02.002.002 | B50: Operação Inicial do Canteiro | F50: =SUM(F51:F52) -> 34191.804
A51: 02.002.002.001 | B51: Limpeza mecanizada de camada vegetal | C51: m2 | D51: 1294.4 | E51: 12.5 | F51: 16180
A52: 02.002.002.002 | B52: Locação da obra | C52: m | D52: 150.84 | E52: 119.41 | F52: 18011.804
A53: 02.002.003 | B53: Instalações Provisórias | F53: =SUM(F54:F59) -> 242754.23
A54: 02.002.003.001 | B54: Instalações de canteiro | C54: vb | D54: 1 | E54: 145163.8 | F54: 145163.8
A55: 02.002.003.002 | B55: Instalações Provisórias: Redes de Água Fria, Esgoto e Drenagem | C55: vb | D55: 1 | E55: 12355.57 | F55: 12355.57
A56: 02.002.003.003 | B56: Instalações Provisórias: Redes Elétrica, Comunicação e Dados | C56: vb | D56: 1 | E56: 12355.57 | F56: 12355.57
A57: 02.002.003.004 | B57: Mobiliário de apoio a obra | C57: vb | D57: 1 | E57: 14300 | F57: 14300
A58: 02.002.003.005 | B58: Equipamentos escritório - aquisição | C58: vb | D58: 1 | E58: 33000 | F58: 33000
A59: 02.002.003.006 | B59: Tapume com telha metálica | C59: m2 | D59: 214.214 | E59: 119.41 | F59: 25579.294
A60: 02.002.005 | B60: Despesas de Consumo e Manutenção | F60: 508073.3
A61: 02.003 | B61: EQUIPAMENTOS | F61: =F62+F77 -> 1825898
A62: 02.003.001 | B62: Equipamentos de Obra | F62: =SUM(F63:F76) -> 1766425
A63: 02.003.001.001 | B63: Ferramentas - aquisição/manutenção | C63: vb | D63: 1 | E63: 60800 | F63: 60800
A64: 02.003.001.002 | B64: Mobilização e desmobilização de grua | C64: Un. | D64: 1 | E64: 24000 | F64: 24000
A65: 02.003.001.003 | B65: Locação de grua | C65: mes | D65: 22 | E65: 22000 | F65: 484000
A66: 02.003.001.004 | B66: Serviço de montagem de grua | C66: Un. | D66: 1 | E66: 7500 | F66: 7500
A67: 02.003.001.005 | B67: Serviço de desmontagem de grua | C67: Un. | D67: 1 | E67: 20000 | F67: 20000
A68: 02.003.001.006 | B68: Ascensão da grua | C68: Un. | D68: 11 | E68: 4500 | F68: 49500
A69: 02.003.001.007 | B69: Manutenção preventiva de grua | C69: mes | D69: 22 | E69: 2100 | F69: 46200
A70: 02.003.001.008 | B70: Locação de elevador cremalheira | C70: mes | D70: 45 | E70: 20000 | F70: 900000
A71: 02.003.001.009 | B71: Montagem de elevador cremalheira | C71: Un. | D71: 1 | E71: 20000 | F71: =E71*D71 -> 20000
A72: 02.003.001.010 | B72: Desmontagem de elevador cremalheira | C72: Un. | D72: 2 | E72: 15000 | F72: 30000
A73: 02.003.001.011 | B73: Manutenção preventiva de elevador cremalheira | C73: mes | D73: 15 | E73: 3000 | F73: =E73*D73 -> 45000
A74: 02.003.001.012 | B74: Locação de balancim | C74: mes | D74: 12 | E74: 3800 | F74: 45600
A75: 02.003.001.013 | B75: Montagem e desmontagem de balancim | C75: Un. | D75: 51 | E75: 450 | F75: 22950
A76: 02.003.001.014 | B76: Manutenção periódica de balancim | C76: mes | D76: 10 | E76: 1087.5 | F76: 10875
A77: 02.003.001 | B77: Andaimes | F77: =SUM(F78:F80) -> 59473
A78: 02.003.001.001 | B78: Locação de andaime fachadeiro | C78: mes | D78: 10 | E78: 3000 | F78: 30000
A79: 02.003.001.002 | B79: Mão de obra de montagem de andaime fachadeiro | C79: m2 | D79: 514.04 | E79: 50 | F79: 25702
A80: 02.003.001.003 | B80: Plataformas de trabalho em madeira para andaime | C80: m | D80: 150.84 | E80: 25 | F80: 3771
A81: Total | F81: =F24+F14 -> 7291003.7

Sheet Orçamento_Executivo
A1: CÓDIGO | B1: ITEM | C1: Quantidade | D1: Unidade | E1: Valor Orçado | F1: Considerações
A2: 1 | B2: GERENCIAMENTO TÉCNICO E ADMINISTRATIVO | E2: =E4 -> 7291003.7
A3: 1.1 | B3: GERENCIAMENTO TÉCNICO E ADMINISTRATIVO | E3: =E4 -> 7291003.7
A4: 1.1.1 | B4: Gerenciamento técnico e administrativo | C4: 1 | D4: vb | E4: =Custos_Indiretos!F81 -> 7291003.7
A5: 2 | B5: MOVIMENTAÇÃO DE TERRA | E5: =E6 -> 334397.12
A6: 2.1 | B6: MOVIMENTAÇÃO DE TERRA | E6: =SUM(E7:E12) -> 334397.12
A7: 2.1.1 | B7: Rebaixamento de lençol freático | C7: 10 | D7: dias | E7: ='[4]Movimentação de Terra'!$I$22 -> 5500
A8: 2.1.2 | B8: Escavação mecanizada para blocos e baldrames | C8: 512.02 | D8: m3 | E8: ='[4]Movimentação de Terra'!$I$29 -> 134618
A9: 2.1.3 | B9: Reaterro para blocos e baldrames | C9: 118.16 | D9: m3 | E9: ='[4]Movimentação de Terra'!$I$30 -> 13592
A10: 2.1.4 | B10: Movimentação de terra (30% de empolamento) | C10: 3014.01 | D10: m3 | E10: ='[4]Movimentação de Terra'!$I$31 -> 131906.25
A11: 2.1.5 | B11: Bota-fora da escavação | C11: 640.03 | D11: m3 | E11: ='[4]Movimentação de Terra'!$I$32 -> 19200.87
A12: 2.1.6 | B12: Lastro de concreto magro e= 10cm - Blocos | C12: 1035.52 | D12: m2 | E12: ='[4]Movimentação de Terra'!$I$39 -> 29580
A13: 3 | B13: INFRAESTRUTURA | E13: =E14+E20 -> 2808959.2
A14: 3.1 | B14: FUNDAÇÃO PROFUNDA | E14: =SUM(E15:E19) -> 1874063.4
A15: 3.1.1 | B15: Estaca hélice contínua diâmetro 50cm | C15: 608 | D15: m | E15: =[4]Infraestrutura!$I$17 -> 66880 | F15: 19 estacas com 32 metros de profundidade
A16: 3.1.2 | B16: Estaca hélice contínua diâmetro 60cm | C16: 4371 | D16: m | E16: =[4]Infraestrutura!$I$19 -> 502986.42 | F16: 141 estacas com 32 metros de profundidade
A17: 3.1.3 | B17: Armação | C17: 20729 | D17: kg | E17: =[4]Infraestrutura!$I$20 -> 176197 | F17: Consideração de R$ 8,50/kg
A18: 3.1.4 | B18: Concreto | C18: 1675 | D18: m3 | E18: =[4]Infraestrutura!$I$21 -> 1072000 | F18: Consideração de R$ 640,00/m³ com 10% de perda
A19: 3.1.5 | B19: Arrasamento de estacas | C19: 160 | D19: und | E19: =[4]Infraestrutura!$I$22 -> 56000
A20: 3.2 | B20: FUNDAÇÃO RASA | E20: =SUM(E21:E24) -> 934895.74
A21: 3.2.1 | B21: Fabricação, montagem e desmontagem de forma para blocos e baldrames | C21: 983.74 | D21: m² | E21: =[4]Infraestrutura!$I$29 -> 41809.12
A22: 3.2.2 | B22: Armação | C22: 39386.4 | D22: kg | E22: =[4]Infraestrutura!$I$30 -> 334784.4 | F22: Consideração de R$ 8,50/kg
A23: 3.2.3 | B23: Concreto | C23: 492.33 | D23: m³ | E23: =[4]Infraestrutura!$I$31 -> 196439.67 | F23: Consideração de R$ 640,00/m³ com 5% de perda
A24: 3.2.5 | B24: Mão de obra infraestrutura | C24: 984.66 | D24: vb | E24: =[4]Infraestrutura!$I$32 -> 361862.55 | F24: Consideração de área do térreo
A25: 5 | B25: SUPRAESTRUTURA | E25: =E26+E29+E32+E35+E37 -> 14216001
A26: 5.1 | B26: FORMA | E26: =E27+E28 -> 1154356.4
A27: 5.1.1 | B27: Fabricação forma - Embasamento | C27: 4196.66 | D27: m² | E27: 663072.28 | F27: Considerando as áreas de forma conforme solicitado pelo cliente com 2 jogos
A28: 5.1.2 | B28: Fabricação de forma - Torre | C28: 3109.3933 | D28: m² | E28: 491284.15 | F28: Considerando as áreas de forma conforme solicitado pelo cliente com 3 jogos
A29: 5.2 | B29: ESCORAMENTO | E29: =E30+E31 -> 661702.41
A30: 5.2.1 | B30: Escoramento - Torre | C30: 9328.18 | D30: m² | E30: 251748.28 | F30: Conforme memorial de cálculo na aba - Custo escoramento
A31: 5.2.2 | B31: Escoramento - Embasamento | C31: 4193.66 | D31: m² | E31: 409954.13 | F31: Conforme memorial de cálculo na aba - Custo escoramento
A32: 5.3 | B32: ARMADURA | E32: =E33+E34 -> 4398189.2
A33: 5.3.1 | B33: Armadura Convencional para Estrutura | C33: 550544 | D33: kg | E33: 3963916.8 | F33: Consideração de R$ 7,20/kg
A34: 5.3.2 | B34: Cabos para protensão | C34: =25941.8+9364.9 -> 35306.7 | D34: kg | E34: =[5]Supraestrutura!$I$20+[5]Supraestrutura!$I$22 -> 434272.41 | F34: Consideração de 1,83 kg/m² de laje e 12,30/kg
A35: 5.4 | B35: CONCRETO | E35: =E36 -> 3748686.5
A36: 5.4.1 | B36: Concreto | C36: 5409.36 | D36: m³ | E36: =[6]Supraestrutura!$I$24 -> 3748686.5 | F36: Consideração de R$ 640,00/m³ com 5% de perda
A37: 5.5 | B37: MÃO DE OBRA | E37: =E38+E39 -> 4253066.9
A38: 5.5.1 | B38: Mão de obra da supraestrutura (incluso montagem de forma) | C38: 14100.96 | D38: m³ | E38: 4001066.9 | F38: Valor estimado com base na área construída + verba para montagem das formas
A39: 5.5.2 | B39: Serviços de protensão | C39: 28 | D39: und | E39: =[4]Supraestrutura!$I$21 -> 252000 | F39: Valor estimado por laje da torre
A40: 6 | B40: ALVENARIA | E40: =E41 -> 3060534.4
A41: 6.1 | B41: ALVENARIA | E41: =SUM(E42:E55) -> 3060534.4
A42: 6.1.1 | B42: Alvenaria embasamento | C42: 4136.11 | D42: m² | E42: =[4]Alvenaria!$I$15 -> 206805.5 | F42: Consideração de bloco cerâmico de 14x19x19cm
A43: 6.1.2 | B43: Alvenaria lazer | C43: 723.12022 | D43: m² | E43: =[4]Alvenaria!$I$16 -> 36156.011 | F43: Consideração de bloco cerâmico de 14x19x19cm
A44: 6.1.3 | B44: Drywall lazer | C44: 614.01044 | D44: m² | E44: =[4]Alvenaria!$I$17 -> 135082.3 | F44: Considerado material e mão de obra
A45: 6.1.4 | B45: Alvenaria tipo | C45: 5752.142 | D45: m² | E45: =[4]Alvenaria!$I$18 -> 287607.1 | F45: Consideração de bloco cerâmico de 14x19x19cm
A46: 6.1.5 | B46: Drywall tipo | C46: 6040.443 | D46: m² | E46: =[4]Alvenaria!$I$19 -> 1328897.5 | F46: Considerado material e mão de obra
A47: 6.1.6 | B47: Alvenaria dupla tipo | C47: 490.66552 | D47: m² | E47: =[4]Alvenaria!$I$20 -> 92245.118 | F47: Consideração de bloco cerâmico de 14x19x19cm
A48: 6.1.7 | B48: Alvenaria tipo diferenciado | C48: 288.1447 | D48: m² | E48: =[4]Alvenaria!$I$21 -> 14407.235 | F48: Consideração de bloco cerâmico de 14x19x19cm
A49: 6.1.8 | B49: Drywall Diferenciado | C49: 304.95388 | D49: m² | E49: =[4]Alvenaria!$I$22 -> 67089.853 | F49: Considerado material e mão de obra
A50: 6.1.9 | B50: Alvenaria dupla | C50: 24.77142 | D50: m² | E50: =[4]Alvenaria!$I$23 -> 4657.027 | F50: Consideração de bloco cerâmico de 14x19x19cm
A51: 6.1.10 | B51: Alvenaria cobertura / reservatório | C51: 307.64 | D51: m² | E51: =[4]Alvenaria!$I$24 -> 15382 | F51: Consideração de bloco cerâmico de 14x19x19cm
A52: 6.1.11 | B52: Bloco de concreto autoclavado | C52: 2096.07 | D52: m² | E52: =[4]Alvenaria!$I$25 -> 125764.2 | F52: Considerado área das escadas e churrasqueiras
A53: 6.1.12 | B53: Serviços complementares | C53: 13818.664 | D53: m² | E53: =[4]Alvenaria!$I$26 -> 172733.3 | F53: Considerado tela, encunhamento, verga e contraverga
A54: 6.1.13 | B54: Mão de obra - Bloco Cerâmico | C54: 11722.594 | D54: m² | E54: =[4]Alvenaria!$I$27 -> 468903.75
A55: 6.1.14 | B55: Mão de obra - Bloco Concreto | C55: 2096.07 | D55: m² | E55: =[4]Alvenaria!$I$28 -> 104803.5
A56: 7 | B56: INSTALAÇÕES ELÉTRICAS, HIDRÁULICAS E GLP | E56: =E57+E65+E74 -> 5636274.9
A57: 7.1 | B57: INSTALAÇÕES ELÉTRICAS | E57: =SUM(E58:E64) -> 2448913.3
A58: 7.1.1 | B58: Entrada de Energia | C58: 1 | D58: vb | E58: =[4]Instalações!$I$15 -> 72581.9
A59: 7.1.2 | B59: Eletrodutos e Eletrocalhas | C59: 1 | D59: vb | E59: =[4]Instalações!$I$16 -> 185809.66
A60: 7.1.3 | B60: Instalações Embutidas e Aparentes | C60: 1 | D60: vb | E60: =[4]Instalações!$I$17 -> 245326.82
A61: 7.1.4 | B61: Cabos e Fiações | C61: 1 | D61: vb | E61: =[4]Instalações!$I$18 -> 580655.2
A62: 7.1.5 | B62: Quadros e Disjuntores | C62: 1 | D62: vb | E62: =[4]Instalações!$I$19 -> 290327.6
A63: 7.1.7 | B63: Equipamentos e Iluminação | C63: 1 | D63: vb | E63: =[4]Instalações!$I$20 -> 275811.22
A64: 7.1.8 | B64: Mão de Obra para Instalações Elétricas | C64: 1 | D64: vb | E64: =[4]Instalações!$I$21 -> 798400.9
A65: 7.2 | B65: INSTALAÇÕES HIDRÁULICAS | E65: =SUM(E66:E73) -> 2359927.9
A66: 7.2.1 | B66: Instalações de Água Fria | C66: 1 | D66: vb | E66: =[4]Instalações!$I$27 -> 362909.5
A67: 7.2.2 | B67: Instalações de Água Quente | C67: 1 | D67: vb | E67: =[4]Instalações!$I$28 -> 217745.7
A68: 7.2.3 | B68: Instalações de Águas Pluviais | C68: 1 | D68: vb | E68: =[4]Instalações!$I$29 -> 145163.8
A69: 7.2.4 | B69: Instalações Sanitárias | C69: 1 | D69: vb | E69: =[4]Instalações!$I$30 -> 217745.7
A70: 7.2.5 | B70: Cisterna | C70: 1 | D70: vb | E70: =[4]Instalações!$I$31 -> 5371.0606
A71: 7.2.6 | B71: Sistema de bombas | C71: 1 | D71: vb | E71: =[4]Instalações!$I$32 -> 31936.036
A72: 7.2.7 | B72: Louças e Metais | C72: 1 | D72: vb | E72: =[4]Instalações!$I$33 -> 653237.1
A73: 7.2.8 | B73: Mão de Obra para Instalações Hidráulicas | C73: 1 | D73: vb | E73: =[4]Instalações!$I$34 -> 725819
A74: 7.3 | B74: INSTALAÇÕES PREVENTIVAS E GLP | E74: =SUM(E75:E77) -> 827433.66
A75: 7.3.1 | B75: Instalações Preventivas | C75: 1 | D75: vb | E75: 362909.5
A76: 7.3.2 | B76: Instalações de GLP | C76: 1 | D76: vb | E76: 319360.36
A77: 7.3.3 | B77: Instalações de Proteção e Aterramento - SPDA | C77: 1 | D77: vb | E77: 145163.8
A78: 8 | B78: SISTEMAS ESPECIAIS | E78: =E79+E84+E90+E92+E86 -> 4015448.3
A79: 8.1 | B79: CLIMATIZAÇÃO, EXAUSTÃO MECÂNICA E PRESSURIZAÇÃO | E79: =SUM(E80:E83) -> 637000
A80: 8.1.1 | B80: Infraestrutura para Instalação de Ar Condicionado | C80: 226 | D80: und | E80: 339000 | F80: Consideração de áres comuns, aptos e salas comerciais
A81: 8.1.2 | B81: Instalação de Ar Condicionado | C81: 16 | D81: un | E81: ='[4]Sistemas especiais'!$I$16 -> 60000 | F81: Considerando somente as áreas comuns
A82: 8.1.3 | B82: Ventokit | C82: 54 | D82: un | E82: ='[4]Sistemas especiais'!$I$17 -> 184000 | F82: Ventilação mecânica em banheiros enclausurados
A83: 8.1.4 | B83: Churrasqueiras | C83: 46 | D83: un | E83: ='[4]Sistemas especiais'!$I$18 -> 54000 | F83: Considerado uma por apto e mais áreas comuns
A84: 8.2 | B84: AUTOMAÇÃO | E84: =SUM(E85) -> 116131.04
A85: 8.2.1 | B85: Automação, telecomunicação e sistemas de segurança | C85: 1 | D85: vb | E85: 116131.04
A86: 8.3 | B86: COMUNICAÇÃO | E86: =SUM(E87:E89) -> 377425.88
A87: 8.3.1 | B87: CFTV | C87: 1 | D87: vb | E87: 72581.9
A88: 8.3.2 | B88: Interfone | C88: 1 | D88: vb | E88: ='[4]Sistemas especiais'!$I$25 -> 130647.42
A89: 8.3.3 | B89: TV e internet | C89: 1 | D89: vb | E89: ='[4]Sistemas especiais'!$I$26 -> 174196.56
A90: 8.4 | B90: OUTROS SISTEMAS | E90: =SUM(E91) -> 435491.4
A91: 8.4.1 | B91: Outros sistemas | C91: 1 | D91: vb | E91: 435491.4
A92: 8.5 | B92: SISTEMAS ESPECIAIS | E92: =SUM(E93:E99) -> 2449400
A93: 8.5.1 | B93: Grupo de geradores | C93: 1 | D93: un | E93: ='[4]Sistemas especiais'!$I$49 -> 120000 | F93: 1 gerador no G1
A94: 8.5.2 | B94: Elevador | C94: 2 | D94: un | E94: ='[4]Sistemas especiais'!$I$44 -> 1320000 | F94: 2 elevadores sociais
A95: 8.5.3 | B95: Elevador de serviço | C95: 1 | D95: um | E95: ='[4]Sistemas especiais'!$I$45 -> 660000 | F95: 1 elevador para serviço
A96: 8.5.4 | B96: Saunas | C96: 2 | D96: un | E96: ='[4]Sistemas especiais'!$I$47 -> 40000 | F96: 1 sauna lazer e 1 pvto Penthouse
A97: 8.5.5 | B97: SPA | C97: 1 | D97: un | E97: ='[4]Sistemas especiais'!$I$48 -> 35000 | F97: Considerado no pvto Lazer 02
A98: 8.5.6 | B98: Equipamentos piscina | C98: 2 | D98: un | E98: ='[4]Sistemas especiais'!$I$46 -> 240000 | F98: Considerado 2 piscinas, 1 no lazer e 1 no pvto Penthouse
A99: 8.5.7 | B99: Infraestrutura de carro elétrico | C99: 43 | D99: un | E99: 34400 | F99: Considerado 1 ponto por apto
A100: 9 | B100: IMPERMEABILIZAÇÃO | E100: =E101 -> 1142037.2
...

Sheet SUPRA
A1: total
B3: formas | C3: superficie m2 | D3: volume m3 | E3: barras kg
A4: lajes maciça | B4: =SUM(B13,B21,B30,B38,B46,B54,B62,B70,B78,B86,B94) -> 0 | C4: =SUM(C13,C21,C30,C38,C46,C54,C62,C70,C78,C86,C94) -> 4958.71 | D4: =SUM(D13,D21,D30,D38,D46,D54,D62,D70,D78,D86,D94) -> 1150.93 | E4: =SUM(E13,E21,E30,E38,E46,E54,E62,E70,E78,E86,E94) -> 728980
A5: vigas | B5: =SUM(B14,B22,B31,B39,B47,B55,B63,B71,B79,B87,B95) -> 1946.86 | C5: =SUM(C14,C22,C31,C39,C47,C55,C63,C71,C79,C87,C95) -> 593.39 | D5: =SUM(D14,D22,D31,D39,D47,D55,D63,D71,D79,D87,D95) -> 314.92 | E5: =SUM(E14,E22,E31,E39,E47,E55,E63,E71,E79,E87,E95) -> 74356
A6: muros conc armado | B6: =B23 -> 0 | C6: =C23 -> 691.89 | D6: =D23 -> 103.784 | E6: =E23 -> 35762
A7: pilares | B7: =SUM(B15,B24,B32,B40,B48,B56,B64,B72,B80,B88,B96) -> 1373.37 | C7: =SUM(C15,C24,C32,C40,C48,C56,C64,C72,C80,C88,C96) -> 0 | D7: =SUM(D15,D24,D32,D40,D48,D56,D64,D72,D80,D88,D96) -> 103.16 | E7: =SUM(E15,E24,E32,E40,E48,E56,E64,E72,E80,E88,E96) -> 52781
A8: total | B8: =SUM(B4:B7) -> 3320.23 | C8: =SUM(C4:C7) -> 6243.99 | D8: =SUM(D4:D7) -> 1672.794 | E8: =SUM(E4:E7) -> 891879
A10: Subsolo
B12: formas | C12: superficie m2 | D12: volume m3 | E12: barras kg
A13: lajes maciça | C13: 557.61 | D13: 83.64 | E13: 97677
A14: vigas | B14: 237.71 | C14: 71.85 | D14: 36.73 | E14: 6603
A15: pilares
A16: total | B16: =SUM(B13:B15) -> 237.71 | C16: =SUM(C13:C15) -> 629.46 | D16: =SUM(D13:D15) -> 120.37 | E16: =SUM(E13:E15) -> 104280
A18: terreo
B20: formas | C20: superficie m2 | D20: volume m3 | E20: barras kg
A21: lajes maciça | C21: 504.54 | D21: 126.14 | E21: 104872
A22: vigas | B22: 141.15 | C22: 83.79 | D22: 28.5 | E22: 6109
A23: muros conc armado | C23: 691.89 | D23: 103.784 | E23: 35762
A24: pilares | B24: 72.96 | D24: 6.09 | E24: 4456
A25: total | B25: =SUM(B21:B24) -> 214.11 | C25: =SUM(C21:C24) -> 1280.22 | D25: =SUM(D21:D24) -> 264.514 | E25: =SUM(E21:E24) -> 151199
A27: 1o pavto
B29: formas | C29: superficie m2 | D29: volume m3 | E29: barras kg
A30: lajes maciça | C30: 314.91 | D30: 77.72 | E30: 56228
A31: vigas | B31: 187.86 | C31: 42.6 | D31: 26.78 | E31: 7305
A32: pilares | B32: 123.33 | D32: 10.31 | E32: 8367
A33: total | B33: =SUM(B30:B32) -> 311.19 | C33: =SUM(C30:C32) -> 357.51 | D33: =SUM(D30:D32) -> 114.81 | E33: =SUM(E30:E32) -> 71900
A35: 2o pavto
B37: formas | C37: superficie m2 | D37: volume m3 | E37: barras kg
A38: lajes maciça | C38: 474.43 | D38: 118.36 | E38: 262558
A39: vigas | B39: 158.3 | C39: 51.12 | D39: 28.15 | E39: 10243
A40: pilares | B40: 124.63 | D40: 10.58 | E40: 6811
A41: total | B41: =SUM(B38:B40) -> 282.93 | C41: =SUM(C38:C40) -> 525.55 | D41: =SUM(D38:D40) -> 157.09 | E41: =SUM(E38:E40) -> 279612
A43: 3o pavto
B45: formas | C45: superficie m2 | D45: volume m3 | E45: barras kg
A46: lajes maciça | C46: 463.04 | D46: 114.39 | E46: 44867
A47: vigas | B47: 145.52 | C47: 45.41 | D47: 24.59 | E47: 8194
A48: pilares | B48: 113.4 | D48: 7.66 | E48: 4038
A49: total | B49: =SUM(B46:B48) -> 258.92 | C49: =SUM(C46:C48) -> 508.45 | D49: =SUM(D46:D48) -> 146.64 | E49: =SUM(E46:E48) -> 57099
A51: 4o a 7o pavto
B53: formas | C53: superficie m2 | D53: volume m3 | E53: barras kg
A54: lajes maciça | C54: =4*465.71 -> 1862.84 | D54: =4*116.43 -> 465.72 | E54: =4*28470 -> 113880
A55: vigas | B55: =4*138.74 -> 554.96 | C55: =4*43.55 -> 174.2 | D55: =4*23.73 -> 94.92 | E55: =4*6856 -> 27424
A56: pilares | B56: 611.62 | D56: 44.2 | E56: 19776
A57: total | B57: =SUM(B54:B56) -> 1166.58 | C57: =SUM(C54:C56) -> 2037.04 | D57: =SUM(D54:D56) -> 604.84 | E57: =SUM(E54:E56) -> 161080
A59: cobertura
B61: formas | C61: superficie m2 | D61: volume m3 | E61: barras kg
A62: lajes maciça | C62: 444.7 | D62: 111.17 | E62: 20164
A63: vigas | B63: 159.63 | C63: 58.18 | D63: 29.59 | E63: 3652
A64: pilares | B64: 156.43 | D64: 11.28 | E64: 4038
A65: total | B65: =SUM(B62:B64) -> 316.06 | C65: =SUM(C62:C64) -> 502.88 | D65: =SUM(D62:D64) -> 152.04 | E65: =SUM(E62:E64) -> 27854
A67: barrilete
B69: formas | C69: superficie m2 | D69: volume m3 | E69: barras kg
A70: lajes maciça | C70: 265.07 | D70: 39.76 | E70: 23134
A71: vigas | B71: 266.3 | C71: 53.48 | D71: 33.93 | E71: 3629 | G71: =B73*3 -> 1184.73
A72: pilares | B72: 128.61 | D72: 9.38 | E72: 3243
A73: total | B73: =SUM(B70:B72) -> 394.91 | C73: =SUM(C70:C72) -> 318.55 | D73: =SUM(D70:D72) -> 83.07 | E73: =SUM(E70:E72) -> 30006
A75: CM
B77: formas | C77: superficie m2 | D77: volume m3 | E77: barras kg
A78: lajes maciça | C78: 5.77 | D78: 0.87 | E78: 4360
A79: vigas | B79: 5.61 | C79: 0.99 | D79: 0.58 | E79: 135
A80: pilares | B80: 25.69 | D80: 2.13 | E80: 1262
A81: total | B81: =SUM(B78:B80) -> 31.3 | C81: =SUM(C78:C80) -> 6.76 | D81: =SUM(D78:D80) -> 3.58 | E81: =SUM(E78:E80) -> 5757
A83: reservatório
B85: formas | C85: superficie m2 | D85: volume m3 | E85: barras kg
A86: lajes maciça | C86: 32.68 | D86: 6.54 | E86: 695
A87: vigas | B87: 26.65 | C87: 6.74 | D87: 3.62 | E87: 348
A88: pilares | B88: 9.7 | D88: 0.88 | E88: 365
A89: total | B89: =SUM(B86:B88) -> 36.35 | C89: =SUM(C86:C88) -> 39.42 | D89: =SUM(D86:D88) -> 11.04 | E89: =SUM(E86:E88) -> 1408
A91: tampa reserv
B93: formas | C93: superficie m2 | D93: volume m3 | E93: barras kg
A94: lajes maciça | C94: 33.12 | D94: 6.62 | E94: 545
A95: vigas | B95: 63.17 | C95: 5.03 | D95: 7.53 | E95: 714
A96: pilares | B96: 7 | D96: 0.65 | E96: 425
A97: total | B97: =SUM(B94:B96) -> 70.17 | C97: =SUM(C94:C96) -> 38.15 | D97: =SUM(D94:D96) -> 14.8 | E97: =SUM(E94:E96) -> 1684

Sheet Orçamento_Paramétrico
A1: ETAPA | B1: VALOR ORÇADO | C1: % | D1: VALOR / m²
A2: GERENCIAMENTO TÉCNICO E ADMINISTRATIVO | B2: 7291003.7 | C2: 0.12078414 | D2: 502.26046 | F2: ÁREA CONSTRUÍDA | G2: 14516.38
A3: MOVIMENTAÇÃO DE TERRA | B3: 334397.12 | C3: 0.0055396859 | D3: 23.035848
A4: INFRAESTRUTURA | B4: 2808959.2 | C4: 0.046533748 | D4: 193.50273
A5: SUPRAESTRUTURA | B5: 14216001 | C5: 0.23550497 | D5: 979.30761
A6: ALVENARIA | B6: 3060534.4 | C6: 0.050701391 | D6: 210.83317
A7: INSTALAÇÕES ELÉTRICAS, HIDRÁULICAS, GLP E PREVENTIVAS | B7: 5636274.9 | C7: 0.093371595 | D7: 388.27
A8: EQUIPAMENTOS E SISTEMAS ESPECIAIS | B8: 4015448.3 | C8: 0.066520676 | D8: 276.61499
A9: IMPERMEABILIZAÇÃO | B9: 1142037.2 | C9: 0.018919204 | D9: 78.672311
A10: REVESTIMENTOS INTERNOS EM PISO E PAREDE | B10: 1922134.1 | C10: 0.031842438 | D10: 132.4114
A11: REVESTIMENTOS E ACABAMENTOS INTERNOS EM TETO | B11: 1271472.7 | C11: 0.021063457 | D11: 87.588825
A12: ACABAMENTOS EM PISO E PAREDE | B12: 2915218.5 | C12: 0.048294061 | D12: 200.82269
A13: PINTURA INTERNA | B13: 1912985.7 | C13: 0.031690883 | D13: 131.78118 | F13: Imprevistos e contingências
A14: ESQUADRIAS, VIDROS E FERRAGENS | B14: 5559680.5 | C14: 0.092102718 | D14: 382.99359 | F14: =SUM(B2:B16) -> 59471836 | G14: 0.015
A15: REVESTIMENTOS E ACABAMENTOS DE FACHADA | B15: 2672331.3 | C15: 0.044270345 | D15: 184.09075 | F15: =F14*G14 -> 892077.54
A16: SERVIÇOS COMPLEMENTARES | B16: 4713357 | C16: 0.078082362 | D16: 324.69231
A17: IMPREVISTOS | B17: 892077.54 | C17: 0.015 | D17: 61.453168
A18: TOTAL | B18: =SUM(B2:B17) -> 60363913 | C18: =SUM(C2:C17) -> 1.0002217 | D18: =SUM(D2:D17) -> 4158.331
A19: CUB/SC | B19: 2.793,27 | C19: 45474 | D19: 1.61
A21: ETAPA | B21: VALOR ORÇADO | C21: % | D21: VALOR / m² | F21: ÁREA CONSTRUÍDA PRIVATIVA | G21: 5700.91
A22: GERENCIAMENTO TÉCNICO E ADMINISTRATIVO | B22: =B2 -> 7291003.7 | C22: =B22/B$18 -> 0.12078414 | D22: 1278.9193
A23: MOVIMENTAÇÃO DE TERRA | B23: =B3 -> 334397.12 | C23: =B23/B$18 -> 0.0055396859 | D23: 58.656797
A24: INFRAESTRUTURA | B24: =B4 -> 2808959.2 | C24: =B24/B$18 -> 0.046533748 | D24: 492.72119
A25: SUPRAESTRUTURA | B25: =B5 -> 14216001 | C25: =B25/B$18 -> 0.23550497 | D25: 2493.6372
A26: ALVENARIA | B26: =B6 -> 3060534.4 | C26: =B26/B$18 -> 0.050701391 | D26: 536.85015
A27: INSTALAÇÕES ELÉTRICAS, HIDRÁULICAS, GLP E PREVENTIVAS | B27: =B7 -> 5636274.9 | C27: =B27/B$18 -> 0.093371595 | D27: 988.66231
A28: EQUIPAMENTOS E SISTEMAS ESPECIAIS | B28: =B8 -> 4015448.3 | C28: =B28/B$18 -> 0.066520676 | D28: 704.35217
A29: IMPERMEABILIZAÇÃO | B29: =B9 -> 1142037.2 | C29: =B29/B$18 -> 0.018919204 | D29: 200.32542
A30: REVESTIMENTOS INTERNOS EM PISO E PAREDE | B30: =B10 -> 1922134.1 | C30: =B30/B$18 -> 0.031842438 | D30: 337.16269
A31: REVESTIMENTOS E ACABAMENTOS INTERNOS EM TETO | B31: =B11 -> 1271472.7 | C31: =B31/B$18 -> 0.021063457 | D31: 223.02977
A32: ACABAMENTOS EM PISO E PAREDE | B32: =B12 -> 2915218.5 | C32: =B32/B$18 -> 0.048294061 | D32: 511.36021
A33: PINTURA INTERNA | B33: =B13 -> 1912985.7 | C33: =B33/B$18 -> 0.031690883 | D33: 335.55795
... A36: SERVIÇOS COMPLEMENTARES | B36: =B16 -> 4713357 | C36: =B36/B$18 -> 0.078082362 | D36: 826.77273
A37: IMPREVISTOS | B37: =B17 -> 892077.54 | C37: 0.015 | D37: 156.47985
A38: TOTAL | B38: =SUM(B22:B37) -> 60363913 | C38: =SUM(C22:C37) -> 1.0002217 | D38: =SUM(D22:D37) -> 10588.47
A39: CUB/SC | B39: 2774.29 | C39: 45444 | D39: =+D38/B39 -> 3.8166413

Sheet Custo_Médias
A1: ETAPA | B1: OBRA | E1: OBRA SIMILAR
B2: VALOR | C2: % | D2: VALOR / m² | E2: VALOR / m²
A3: =[7]ORÇAMENTO_PARAMÉTRICO!A3 -> MOVIMENTAÇÃO DE TERRA | B3: 334397.12 | C3: 0.0055396859 | D3: 23.035848 | E3: 15,00 -25,00
A4: =[7]ORÇAMENTO_PARAMÉTRICO!A4 -> INFRAESTRUTURA | B4: 2808959.2 | C4: 0.046533748 | D4: 193.50273 | E4: 155,00 -200,00
A5: =[7]ORÇAMENTO_PARAMÉTRICO!A5 -> SUPRAESTRUTURA | B5: 14216001 | C5: 0.23550497 | D5: 979.30761 | E5: 750,00 -890,00
A6: =[7]ORÇAMENTO_PARAMÉTRICO!A6 -> ALVENARIA | B6: 3060534.4 | C6: 0.050701391 | D6: 210.83317 | E6: 100,00 -155,00
A7: =[7]ORÇAMENTO_PARAMÉTRICO!A7 -> INSTALAÇÕES ELÉTRICAS, HIDRÁULICAS, GLP E PREVENTIVAS | B7: 5636274.9 | C7: 0.093371595 | D7: 388.27 | E7: 300,00 -390,00
A8: =[7]ORÇAMENTO_PARAMÉTRICO!A8 -> EQUIPAMENTOS E SISTEMAS ESPECIAIS | B8: 4015448.3 | C8: 0.066520676 | D8: 276.61499 | E8: 170,00 -240,00
A9: =[7]ORÇAMENTO_PARAMÉTRICO!A9 -> IMPERMEABILIZAÇÃO | B9: 1142037.2 | C9: 0.018919204 | D9: 78.672311 | E9: 40,00 -90,00
A10: =[7]ORÇAMENTO_PARAMÉTRICO!A10 -> REVESTIMENTOS INTERNOS EM PISO E PAREDE | B10: 1922134.1 | C10: 0.031842438 | D10: 132.4114 | E10: 100,00 -190,00
A11: =[7]ORÇAMENTO_PARAMÉTRICO!A11 -> REVESTIMENTOS E ACABAMENTOS INTERNOS EM TETO | B11: 1271472.7 | C11: 0.021063457 | D11: 87.588825 | E11: 50,00 -90,00
A12: =[7]ORÇAMENTO_PARAMÉTRICO!A12 -> ACABAMENTOS EM PISO E PAREDE | B12: 2915218.5 | C12: 0.048294061 | D12: 200.82269 | E12: 150,00 -230,00
A13: =[7]ORÇAMENTO_PARAMÉTRICO!A13 -> PINTURA INTERNA | B13: 1912985.7 | C13: 0.031690883 | D13: 131.78118 | E13: 90,00 -140,00
A14: =[7]ORÇAMENTO_PARAMÉTRICO!A14 -> ESQUADRIAS, VIDROS E FERRAGENS | B14: 5559680.5 | C14: 0.092102718 | D14: 382.99359 | E14: 340,00 -420,00
... A16: =[7]ORÇAMENTO_PARAMÉTRICO!A16 -> SERVIÇOS COMPLEMENTARES | B16: 4713357 | C16: 0.078082362 | D16: 324.69231 | E16: 120,00 -200,00
A17: TOTAL | B17: =SUM(B3:B16) -> 52180832 | D17: =SUM(D3:D16) -> 3594.6174 | E17: =FIXED([7]CÁLCULO_MÉDIAS!N24,2,FALSE)&" "&"-"&FIXED([7]CÁLCULO_MÉDIAS!O24,2,FALSE) -> 2.845,00 -3.927,00
B22: 2461.35
B23: =B22/B21 -> #DIV/0!
D26: 1.1023
A28: 900,00 - 1100 | B28: 900
A29: 25,00 - 30,00 | B29: 25
A30: 15,00 - 22,00 | B30: 15
A31: 150,00 - 200,00 | B31: 150
A32: 440,00 - 510,00 | B32: 440
A33: -
A34: 55,00 - 70,00 | B34: 55
A35: 170,00 - 200,00 | B35: 170
A36: 165,00 - 230,00 | B36: 165
A37: 40,00 - 70,00 | B37: 40
A38: 55,00 - 77,00 | B38: 55
A39: 35,00 - 50,00 | B39: 35
A40: 130,00 - 175,00 | B40: 130
A41: 35,00 - 65,00 | B41: 35
A42: 35,00 - 55,00 | B42: 35
A43: 430,00 - 550,00 | B43: 430
A44: 35,00 - 50,00 | B44: 35
A45: 150,00 - 220,00 | B45: 150

Sheet Custo_Diferença
A1: ETAPA | B1: R02 | C1: R03 | D1: DIFERENÇA | E1: COMENTÁRIOS
A2: GERENCIAMENTO TÉCNICO E ADMINISTRATIVO | B2: 7621912.8 | C2: 7291003.7 | D2: =C2-B2 -> -330909.12 | E2: Revisão do custo de equipe técnica, segurança e equipamentos.
A3: MOVIMENTAÇÃO DE TERRA | B3: 334397.12 | C3: 334397.12 | D3: =C3-B3 -> 0
A4: INFRAESTRUTURA | B4: 2808959.2 | C4: 2808959.2 | D4: =C4-B4 -> 0
A5: SUPRAESTRUTURA | B5: 18837581 | C5: 14216001 | D5: =C5-B5 -> -4621579.5 | E5: Revisão do custo do aço, protensão da laje, quantitativo e proposta de escoramento.
A6: ALVENARIA | B6: 3060534.4 | C6: 3060534.4 | D6: =C6-B6 -> 0
A7: INSTALAÇÕES ELÉTRICAS, HIDRÁULICAS, GLP E PREVENTIVAS | B7: 5636274.9 | C7: 5636274.9 | D7: =C7-B7 -> 0
A8: EQUIPAMENTOS E SISTEMAS ESPECIAIS | B8: 4015448.3 | C8: 4015448.3 | D8: =C8-B8 -> 0
A9: IMPERMEABILIZAÇÃO | B9: 1142037.2 | C9: 1142037.2 | D9: =C9-B9 -> 0
A10: REVESTIMENTOS INTERNOS EM PISO E PAREDE | B10: 1922134.1 | C10: 1922134.1 | D10: =C10-B10 -> 0
A11: REVESTIMENTOS E ACABAMENTOS INTERNOS EM TETO | B11: 1271472.7 | C11: 1271472.7 | D11: =C11-B11 -> 0
A12: ACABAMENTOS EM PISO E PAREDE | B12: 2915218.5 | C12: 2915218.5 | D12: =C12-B12 -> 0
A13: PINTURA INTERNA | B13: 1912985.7 | C13: 1912985.7 | D13: =C13-B13 -> 0
A14: ESQUADRIAS, VIDROS E FERRAGENS | B14: 5559680.5 | C14: 5559680.5 | D14: =C14-B14 -> 0
A15: REVESTIMENTOS E ACABAMENTOS DE FACHADA | B15: 2672331.3 | C15: 2672331.3 | D15: =C15-B15 -> 0
A16: SERVIÇOS COMPLEMENTARES | B16: 4713357 | C16: 4713357 | D16: =C16-B16 -> 0
A17: IMPREVISTOS | B17: 875185.68 | C17: 892077.54 | D17: =C17-B17 -> 16891.856 | E17: Atualizado conforme custo total da obra (1,5% sobre o valor total da obra).
A18: TOTAL | B18: =SUM(B2:B17) -> 65299510 | C18: =SUM(C2:C17) -> 60363913 | D18: =SUM(D2:D17) -> -4935596.7
A19: CUB/SC | B19: 1.33 | C19: =[7]ORÇAMENTO_PARAMÉTRICO!D19 -> 1.61

Sheet R$_Escoramento
A1: ORÇAMENTO PARAMÉTRICO - CUSTOS INDIRETOS
A7: Cliente | B7: =[3]OBRA!B2 -> Neuhaus
A8: Obra | B8: =[3]OBRA!B1 -> Origem 3300
A9: Data | B9: 45509
A10: Versão | B10: R04
A13: LEVANTAMENTO DE CUSTO - ESCORAMENTO
A16: PAVIMENTO | B16: ÁREA | C16: Tempo escoramento | D16: UNID. | E16: CUSTO UNIT | F16: Tempo reescoramento | G16: UNID. | H16: CUSTO UNIT | I16: CUSTO total
A18: Mezanino | B18: 271.18 | C18: =Tempo!L4/30 -> 0.76666667 | D18: mês | E18: 48 | F18: =Tempo!P4/30 -> 1.0666667 | G18: mês | H18: =E18*0.5 -> 24 | I18: =(H18*F18+E18*C18)*B18 -> 16921.632
A19: G1 | B19: 980.62 | C19: =Tempo!L5/30 -> 1.4666667 | D19: mês | E19: 48 | F19: =Tempo!P5/30 -> 1.5666667 | G19: mês | H19: =E19*0.5 -> 24 | I19: =(H19*F19+E19*C19)*B19 -> 105906.96
A20: G2 | B20: 980.62 | C20: =Tempo!L6/30 -> 1.3 | D20: mês | E20: 48 | F20: =Tempo!P6/30 -> 1.2666667 | G20: mês | H20: =E20*0.5 -> 24 | I20: =(H20*F20+E20*C20)*B20 -> 91001.536
A21: G3 | B21: 980.62 | C21: =Tempo!L7/30 -> 1.5 | D21: mês | E21: 48 | F21: =Tempo!P7/30 -> 1.1666667 | G21: mês | H21: =E21*0.5 -> 24 | I21: =(H21*F21+E21*C21)*B21 -> 98062
A22: G4 | B22: 980.62 | C22: =Tempo!L8/30 -> 1.5333333 | D22: mês | E22: 48 | F22: =Tempo!P8/30 -> 1.1 | G22: mês | H22: =E22*0.5 -> 24 | I22: =(H22*F22+E22*C22)*B22 -> 98062
A23: Lazer 01 | B23: 979.79 | C23: =Tempo!L9/30 -> 2.0666667 | D23: mês | E23: 20 | F23: =Tempo!P9/30 -> 1.0666667 | G23: mês | H23: 10.82 | I23: =(H23*F23+E23*C23)*B23 -> 51806.07
A24: Lazer 02 | B24: 304.21 | C24: =Tempo!L10/30 -> 0.7 | D24: mês | E24: 20 | F24: =Tempo!P10/30 -> 1.0333333 | G24: mês | H24: =E24*0.5 -> 10 | I24: =(H24*F24+E24*C24)*B24 -> 7402.4433
A25: TIPO GARDEN 800 | B25: 394.74 | C25: =Tempo!L11/30 -> 0.7 | D25: mês | E25: 20 | F25: =Tempo!P11/30 -> 1.0333333 | G25: mês | H25: =E25*0.5 -> 10 | I25: =(H25*F25+E25*C25)*B25 -> 9605.34
A26: TIPO | B26: 322.07 | C26: =Tempo!L12/30 -> 0.7 | D26: mês | E26: 20 | F26: =Tempo!P12/30 -> 1.0333333 | G26: mês | H26: =E26*0.5 -> 10 | I26: =(H26*F26+E26*C26)*B26 -> 7837.0367
A27: TIPO | B27: 322.07 | C27: =Tempo!L13/30 -> 0.7 | D27: mês | E27: 20 | F27: =Tempo!P13/30 -> 1.0333333 | G27: mês | H27: =E27*0.5 -> 10 | I27: =(H27*F27+E27*C27)*B27 -> 7837.0367
A28: TIPO | B28: 322.07 | C28: =Tempo!L14/30 -> 0.56666667 | D28: mês | E28: 20 | F28: =Tempo!P14/30 -> 0.96666667 | G28: mês | H28: =E28*0.5 -> 10 | I28: =(H28*F28+E28*C28)*B28 -> 6763.47
A29: TIPO | B29: 322.07 | C29: =Tempo!L15/30 -> 0.56666667 | D29: mês | E29: 20 | F29: =Tempo!P15/30 -> 1.0333333 | G29: mês | H29: =E29*0.5 -> 10 | I29: =(H29*F29+E29*C29)*B29 -> 6978.1833
A30: TIPO | B30: 322.07 | C30: =Tempo!L16/30 -> 0.56666667 | D30: mês | E30: 20 | F30: =Tempo!P16/30 -> 1.5333333 | G30: mês | H30: =E30*0.5 -> 10 | I30: =(H30*F30+E30*C30)*B30 -> 8588.5333
A31: TIPO | B31: 322.07 | C31: =Tempo!L17/30 -> 0.56666667 | D31: mês | E31: 20 | F31: =Tempo!P17/30 -> 1.5333333 | G31: mês | H31: =E31*0.5 -> 10 | I31: =(H31*F31+E31*C31)*B31 -> 8588.5333
A32: TIPO | B32: 322.07 | C32: =Tempo!L18/30 -> 1.1333333 | D32: mês | E32: 20 | F32: =Tempo!P18/30 -> 0.96666667 | G32: mês | H32: =E32*0.5 -> 10 | I32: =(H32*F32+E32*C32)*B32 -> 10413.597
A33: TIPO | B33: 322.07 | C33: =Tempo!L19/30 -> 0.56666667 | D33: mês | E33: 20 | F33: =Tempo!P19/30 -> 1.1 | G33: mês | H33: =E33*0.5 -> 10 | I33: =(H33*F33+E33*C33)*B33 -> 7192.8967
A34: TIPO | B34: 322.07 | C34: =Tempo!L20/30 -> 0.56666667 | D34: mês | E34: 20 | F34: =Tempo!P20/30 -> 1.1 | G34: mês | H34: =E34*0.5 -> 10 | I34: =(H34*F34+E34*C34)*B34 -> 7192.8967
A35: TIPO | B35: 322.07 | C35: =Tempo!L21/30 -> 0.7 | D35: mês | E35: 20 | F35: =Tempo!P21/30 -> 1.0666667 | G35: mês | H35: =E35*0.5 -> 10 | I35: =(H35*F35+E35*C35)*B35 -> 7944.3933
... A51: RESERVATÓRIO | B51: 47.53 | C51: =Tempo!L37/30 -> 0.6 | D51: mês | E51: 20 | F51: =Tempo!P37/30 -> 1.5333333 | G51: mês | H51: =E51*0.5 -> 10 | I51: =(H51*F51+E51*C51)*B51 -> 1299.1533
A52: SOMA | B52: =SUM(B18:B51) -> 13521.84 | C52: =SUM(C18:C51) -> 26.9 | F52: =SUM(F18:F51) -> 38.7 | I52: =SUM(I18:I51) -> 661702.41

Sheet Tempo
A1: Projeto Origem 3300
A2: Planilha Gerada Em 05/08/2024
I3: Lote | J3: Tempo supra | K3: Tempo de desforma | L3: Tempo de escoramento | M3: Dias uteis | N3: Lote | O3: Tempo até desforma | P3: Tempo de reescoramento | Q3: Dias uteis
B4: Pacote de trabalho | C4: Serviço | D4: Lote | E4: Data de Início | F4: Data de Término | I4: 1º Pav - Mez Térreo | J4: =SUMIF($D$5:$D$77,I4,$G$5:$G$77) -> 22 | K4: =SUMIFS($G$5:$G$77,$D$5:$D$77,I4,$B$5:$B$77,"EST - Desforma") -> 2 | L4: =J4-K4+3 -> 23 | M4: =L4/30*22 -> 16.866667 | N4: 1º Pav - Mez Térreo | O4: =F8-E5 -> 55 | P4: =O4-L4 -> 32 | Q4: =P4/30*22 -> 23.466667
B5: EST - Supraestrutura | C5: - | D5: 1º Pav - Mez Térreo | E5: 45582 | F5: 45602 | G5: =F5-E5 -> 20 | I5: 2º Pav - G1 | J5: =SUMIF($D$5:$D$77,I5,$G$5:$G$77) -> 43 | K5: =SUMIFS($G$5:$G$77,$D$5:$D$77,I5,$B$5:$B$77,"EST - Desforma") -> 2 | L5: =J5-K5+3 -> 44 | M5: =L5/30*22 -> 32.266667 | N5: 2º Pav - G1 | O5: =F11-E6 -> 91 | P5: =O5-L5 -> 47 | Q5: =P5/30*22 -> 34.466667
B6: EST (1) - Supraestrutura | C6: - | D6: 2º Pav - G1 | E6: 45603 | F6: 45624 | G6: =F6-E6 -> 21 | I6: 3º Pav - G2 | J6: =SUMIF($D$5:$D$77,I6,$G$5:$G$77) -> 40 | K6: =SUMIFS($G$5:$G$77,$D$5:$D$77,I6,$B$5:$B$77,"EST - Desforma") -> 4 | L6: =J6-K6+3 -> 39 | M6: =L6/30*22 -> 28.6 | N6: 3º Pav - G2 | O6: =F14-E9 -> 77 | P6: =O6-L6 -> 38 | Q6: =P6/30*22 -> 27.866667
B7: EST (2) - Supraestrutura | C7: - | D7: 2º Pav - G1 | E7: 45625 | F7: 45645 | G7: =F7-E7 -> 20 | I7: 4º Pav - G3 | J7: =SUMIF($D$5:$D$77,I7,$G$5:$G$77) -> 44 | K7: =SUMIFS($G$5:$G$77,$D$5:$D$77,I7,$B$5:$B$77,"EST - Desforma") -> 2 | L7: =J7-K7+3 -> 45 | M7: =L7/30*22 -> 33 | N7: 4º Pav - G3 | O7: =F17-E12 -> 80 | P7: =O7-L7 -> 35 | Q7: =P7/30*22 -> 25.666667
B8: EST - Desforma | C8: - | D8: 1º Pav - Mez Térreo | E8: 45635 | F8: 45637 | G8: =F8-E8 -> 2 | I8: 5º Pav - G4 | J8: =SUMIF($D$5:$D$77,I8,$G$5:$G$77) -> 46 | K8: =SUMIFS($G$5:$G$77,$D$5:$D$77,I8,$B$5:$B$77,"EST - Desforma") -> 3 | L8: =J8-K8+3 -> 46 | M8: =L8/30*22 -> 33.733333 | N8: 5º Pav - G4 | O8: =F19-E15 -> 79 | P8: =O8-L8 -> 33 | Q8: =P8/30*22 -> 24.2
B9: EST (1) - Supraestrutura | C9: - | D9: 3º Pav - G2 | E9: 45663 | F9: 45681 | G9: =F9-E9 -> 18 | I9: 6º Pav - Lazer 01 | J9: =SUMIF($D$5:$D$77,I9,$G$5:$G$77) -> 61 | K9: =SUMIFS($G$5:$G$77,$D$5:$D$77,I9,$B$5:$B$77,"EST - Desforma") -> 2 | L9: =J9-K9+3 -> 62 | M9: =L9/30*22 -> 45.466667 | N9: 6º Pav - Lazer 01 | O9: =F23-E18 -> 94 | P9: =O9-L9 -> 32 | Q9: =P9/30*22 -> 23.466667
B10: EST (2) - Supraestrutura | C10: - | D10: 3º Pav - G2 | E10: 45684 | F10: 45702 | G10: =F10-E10 -> 18 | I10: 7º Pav - Lazer 02 | J10: =SUMIF($D$5:$D$77,I10,$G$5:$G$77) -> 20 | K10: =SUMIFS($G$5:$G$77,$D$5:$D$77,I10,$B$5:$B$77,"EST - Desforma") -> 2 | L10: =J10-K10+3 -> 21 | M10: =L10/30*22 -> 15.4 | N10: 7º Pav - Lazer 02 | O10: =F25-E21 -> 52 | P10: =O10-L10 -> 31 | Q10: =P10/30*22 -> 22.733333
B11: EST - Desforma | C11: - | D11: 2º Pav - G1 | E11: 45692 | F11: 45694 | G11: =F11-E11 -> 2 | I11: 8º Pav - Tipo 08 (Garden) | J11: =SUMIF($D$5:$D$77,I11,$G$5:$G$77) -> 20 | K11: =SUMIFS($G$5:$G$77,$D$5:$D$77,I11,$B$5:$B$77,"EST - Desforma") -> 2 | L11: =J11-K11+3 -> 21 | M11: =L11/30*22 -> 15.4 | N11: 8º Pav - Tipo 08 (Garden) | O11: =F27-E22 -> 52 | P11: =O11-L11 -> 31 | Q11: =P11/30*22 -> 22.733333
B12: EST (1) - Supraestrutura | C12: - | D12: 4º Pav - G3 | E12: 45705 | F12: 45727 | G12: =F12-E12 -> 22 | I12: 9º Pav - Tipo 09 | J12: =SUMIF($D$5:$D$77,I12,$G$5:$G$77) -> 20 | K12: =SUMIFS($G$5:$G$77,$D$5:$D$77,I12,$B$5:$B$77,"EST - Desforma") -> 2 | L12: =J12-K12+3 -> 21 | M12: =L12/30*22 -> 15.4 | N12: 9º Pav - Tipo 09 | O12: =F29-E24 -> 52 | P12: =O12-L12 -> 31 | Q12: =P12/30*22 -> 22.733333
B13: EST (2) - Supraestrutura | C13: - | D13: 4º Pav - G3 | E13: 45728 | F13: 45748 | G13: =F13-E13 -> 20 | I13: 10º Pav - Tipo 10 | J13: =SUMIF($D$5:$D$77,I13,$G$5:$G$77) -> 20 | K13: =SUMIFS($G$5:$G$77,$D$5:$D$77,I13,$B$5:$B$77,"EST - Desforma") -> 2 | L13: =J13-K13+3 -> 21 | M13: =L13/30*22 -> 15.4 | N13: 10º Pav - Tipo 10 | O13: =F31-E26 -> 52 | P13: =O13-L13 -> 31 | Q13: =P13/30*22 -> 22.733333
B14: EST - Desforma | C14: - | D14: 3º Pav - G2 | E14: 45736 | F14: 45740 | G14: =F14-E14 -> 4 | I14: 11º Pav - Tipo 11 | J14: =SUMIF($D$5:$D$77,I14,$G$5:$G$77) -> 16 | K14: =SUMIFS($G$5:$G$77,$D$5:$D$77,I14,$B$5:$B$77,"EST - Desforma") -> 2 | L14: =J14-K14+3 -> 17 | M14: =L14/30*22 -> 12.466667 | N14: 11º Pav - Tipo 11 | O14: =F33-E28 -> 46 | P14: =O14-L14 -> 29 | Q14: =P14/30*22 -> 21.266667
B15: EST (1) - Supraestrutura | C15: - | D15: 5º Pav - G4 | E15: 45749 | F15: 45771 | G15: =F15-E15 -> 22 | I15: 12º Pav - Tipo 12 | J15: =SUMIF($D$5:$D$77,I15,$G$5:$G$77) -> 18 | K15: =SUMIFS($G$5:$G$77,$D$5:$D$77,I15,$B$5:$B$77,"EST - Desforma") -> 4 | L15: =J15-K15+3 -> 17 | M15: =L15/30*22 -> 12.466667 | N15: 12º Pav - Tipo 12 | O15: =F35-E30 -> 48 | P15: =O15-L15 -> 31 | Q15: =P15/30*22 -> 22.733333
B16: EST (2) - Supraestrutura | C16: - | D16: 5º Pav - G4 | E16: 45772 | F16: 45793 | G16: =F16-E16 -> 21 | I16: 13º Pav - Tipo 13 | J16: =SUMIF($D$5:$D$77,I16,$G$5:$G$77) -> 16 | K16: =SUMIFS($G$5:$G$77,$D$5:$D$77,I16,$B$5:$B$77,"EST - Desforma") -> 2 | L16: =J16-K16+3 -> 17 | M16: =L16/30*22 -> 12.466667 | N16: 13º Pav - Tipo 13 | O16: =F37-E32 -> 63 | P16: =O16-L16 -> 46 | Q16: =P16/30*22 -> 33.733333
B17: EST - Desforma | C17: - | D17: 4º Pav - G3 | E17: 45783 | F17: 45785 | G17: =F17-E17 -> 2 | I17: 14º Pav - Tipo 14 | J17: =SUMIF($D$5:$D$77,I17,$G$5:$G$77) -> 16 | K17: =SUMIFS($G$5:$G$77,$D$5:$D$77,I17,$B$5:$B$77,"EST - Desforma") -> 2 | L17: =J17-K17+3 -> 17 | M17: =L17/30*22 -> 12.466667 | N17: 14º Pav - Tipo 14 | O17: =F39-E34 -> 63 | P17: =O17-L17 -> 46 | Q17: =P17/30*22 -> 33.733333
B18: EST (1) - Supraestrutura | C18: - | D18: 6º Pav - Lazer 01 | E18: 45796 | F18: 45825 | G18: =F18-E18 -> 29 | I18: 15º Pav - Tipo 15 | J18: =SUMIF($D$5:$D$77,I18,$G$5:$G$77) -> 33 | K18: =SUMIFS($G$5:$G$77,$D$5:$D$77,I18,$B$5:$B$77,"EST - Desforma") -> 2 | L18: =J18-K18+3 -> 34 | M18: =L18/30*22 -> 24.933333 | N18: 15º Pav - Tipo 15 | O18: =F41-E36 -> 63 | P18: =O18-L18 -> 29 | Q18: =P18/30*22 -> 21.266667
B19: EST - Desforma | C19: - | D19: 5º Pav - G4 | E19: 45825 | F19: 45828 | G19: =F19-E19 -> 3 | I19: 16º Pav - Tipo 16 | J19: =SUMIF($D$5:$D$77,I19,$G$5:$G$77) -> 16 | K19: =SUMIFS($G$5:$G$77,$D$5:$D$77,I19,$B$5:$B$77,"EST - Desforma") -> 2 | L19: =J19-K19+3 -> 17 | M19: =L19/30*22 -> 12.466667 | N19: 16º Pav - Tipo 16 | O19: =F43-E38 -> 50 | P19: =O19-L19 -> 33 | Q19: =P19/30*22 -> 24.2
B20: EST (2) - Supraestrutura | C20: - | D20: 6º Pav - Lazer 01 | E20: 45826 | F20: 45856 | G20: =F20-E20 -> 30 | I20: 17º Pav - Tipo 17 | J20: =SUMIF($D$5:$D$77,I20,$G$5:$G$77) -> 16 | K20: =SUMIFS($G$5:$G$77,$D$5:$D$77,I20,$B$5:$B$77,"EST - Desforma") -> 2 | L20: =J20-K20+3 -> 17 | M20: =L20/30*22 -> 12.466667 | N20: 17º Pav - Tipo 17 | O20: =F45-E40 -> 50 | P20: =O20-L20 -> 33 | Q20: =P20/30*22 -> 24.2
B21: EST - Supraestrutura | C21: - | D21: 7º Pav - Lazer 02 | E21: 45859 | F21: 45877 | G21: =F21-E21 -> 18 | I21: 18º Pav - Tipo 18 | J21: =SUMIF($D$5:$D$77,I21,$G$5:$G$77) -> 23 | K21: =SUMIFS($G$5:$G$77,$D$5:$D$77,I21,$B$5:$B$77,"EST - Desforma") -> 5 | L21: =J21-K21+3 -> 21 | M21: =L21/30*22 -> 15.4 | N21: 18º Pav - Tipo 18 | O21: =F47-E42 -> 53 | P21: =O21-L21 -> 32 | Q21: =P21/30*22 -> 23.466667
B22: EST - Supraestrutura | C22: - | D22: 8º Pav - Tipo 08 (Garden) | E22: 45880 | F22: 45898 | G22: =F22-E22 -> 18 | I22: 19º Pav - Tipo 19 | J22: =SUMIF($D$5:$D$77,I22,$G$5:$G$77) -> 19 | K22: =SUMIFS($G$5:$G$77,$D$5:$D$77,I22,$B$5:$B$77,"EST - Desforma") -> 5 | L22: =J22-K22+3 -> 17 | M22: =L22/30*22 -> 12.466667 | N22: 19º Pav - Tipo 19 | O22: =F49-E44 -> 50 | P22: =O22-L22 -> 33 | Q22: =P22/30*22 -> 24.2
B23: EST - Desforma | C23: - | D23: 6º Pav - Lazer 01 | E23: 45888 | F23: 45890 | G23: =F23-E23 -> 2 | I23: 20º Pav - Tipo 20 | J23: =SUMIF($D$5:$D$77,I23,$G$5:$G$77) -> 16 | K23: =SUMIFS($G$5:$G$77,$D$5:$D$77,I23,$B$5:$B$77,"EST - Desforma") -> 2 | L23: =J23-K23+3 -> 17 | M23: =L23/30*22 -> 12.466667 | N23: 20º Pav - Tipo 20 | O23: =F51-E46 -> 51 | P23: =O23-L23 -> 34 | Q23: =P23/30*22 -> 24.933333
B24: EST - Supraestrutura | C24: - | D24: 9º Pav - Tipo 09 | E24: 45901 | F24: 45919 | G24: =F24-E24 -> 18 | I24: 21º Pav - Tipo 21 | J24: =SUMIF($D$5:$D$77,I24,$G$5:$G$77) -> 19 | K24: =SUMIFS($G$5:$G$77,$D$5:$D$77,I24,$B$5:$B$77,"EST - Desforma") -> 4 | L24: =J24-K24+3 -> 18 | M24: =L24/30*22 -> 13.2 | N24: 21º Pav - Tipo 21 | O24: =F53-E48 -> 53 | P24: =O24-L24 -> 35 | Q24: =P24/30*22 -> 25.666667
B25: EST - Desforma | C25: - | D25: 7º Pav - Lazer 02 | E25: 45909 | F25: 45911 | G25: =F25-E25 -> 2 | I25: 22º Pav - Tipo 22 | J25: =SUMIF($D$5:$D$77,I25,$G$5:$G$77) -> 18 | K25: =SUMIFS($G$5:$G$77,$D$5:$D$77,I25,$B$5:$B$77,"EST - Desforma") -> 2 | L25: =J25-K25+3 -> 19 | M25: =L25/30*22 -> 13.933333 | N25: 22º Pav - Tipo 22 | O25: =F55-E50 -> 51 | P25: =O25-L25 -> 32 | Q25: =P25/30*22 -> 23.466667
B26: EST - Supraestrutura | C26: - | D26: 10º Pav - Tipo 10 | E26: 45922 | F26: 45940 | G26: =F26-E26 -> 18 | I26: 23º Pav - Tipo 23 | J26: =SUMIF($D$5:$D$77,I26,$G$5:$G$77) -> 16 | K26: =SUMIFS($G$5:$G$77,$D$5:$D$77,I26,$B$5:$B$77,"EST - Desforma") -> 2 | L26: =J26-K26+3 -> 17 | M26: =L26/30*22 -> 12.466667 | N26: 23º Pav - Tipo 23 | O26: =F57-E52 -> 49 | P26: =O26-L26 -> 32 | Q26: =P26/30*22 -> 23.466667
B27: EST - Desforma | C27: - | D27: 8º Pav - Tipo 08 (Garden) | E27: 45930 | F27: 45932 | G27: =F27-E27 -> 2 | I27: 24º Pav - Tipo 24 | J27: =SUMIF($D$5:$D$77,I27,$G$5:$G$77) -> 19 | K27: =SUMIFS($G$5:$G$77,$D$5:$D$77,I27,$B$5:$B$77,"EST - Desforma") -> 2 | L27: =J27-K27+3 -> 20 | M27: =L27/30*22 -> 14.666667 | N27: 24º Pav - Tipo 24 | O27: =F59-E54 -> 49 | P27: =O27-L27 -> 29 | Q27: =P27/30*22 -> 21.266667
B28: EST - Supraestrutura | C28: - | D28: 11º Pav - Tipo 11 | E28: 45943 | F28: 45957 | G28: =F28-E28 -> 14 | I28: 25º Pav - Tipo 25 | J28: =SUMIF($D$5:$D$77,I28,$G$5:$G$77) -> 18 | K28: =SUMIFS($G$5:$G$77,$D$5:$D$77,I28,$B$5:$B$77,"EST - Desforma") -> 4 | L28: =J28-K28+3 -> 17 | M28: =L28/30*22 -> 12.466667 | N28: 25º Pav - Tipo 25 | O28: =F61-E56 -> 49 | P28: =O28-L28 -> 32 | Q28: =P28/30*22 -> 23.466667
B29: EST - Desforma | C29: - | D29: 9º Pav - Tipo 09 | E29: 45951 | F29: 45953 | G29: =F29-E29 -> 2 | I29: 26º Pav - Tipo 26 | J29: =SUMIF($D$5:$D$77,I29,$G$5:$G$77) -> 16 | K29: =SUMIFS($G$5:$G$77,$D$5:$D$77,I29,$B$5:$B$77,"EST - Desforma") -> 2 | L29: =J29-K29+3 -> 17 | M29: =L29/30*22 -> 12.466667 | N29: 26º Pav - Tipo 26 | O29: =F63-E58 -> 49 | P29: =O29-L29 -> 32 | Q29: =P29/30*22 -> 23.466667
B30: EST - Supraestrutura | C30: - | D30: 12º Pav - Tipo 12 | E30: 45958 | F30: 45972 | G30: =F30-E30 -> 14 | I30: 27º Pav - Duplex Inferior 01 | J30: =SUMIF($D$5:$D$77,I30,$G$5:$G$77) -> 20 | K30: =SUMIFS($G$5:$G$77,$D$5:$D$77,I30,$B$5:$B$77,"EST - Desforma") -> 2 | L30: =J30-K30+3 -> 21 | M30: =L30/30*22 -> 15.4 | N30: 27º Pav - Duplex Inferior 01 | O30: =F65-E60 -> 50 | P30: =O30-L30 -> 29 | Q30: =P30/30*22 -> 21.266667
B31: EST - Desforma | C31: - | D31: 10º Pav - Tipo 10 | E31: 45972 | F31: 45974 | G31: =F31-E31 -> 2 | I31: 28º Pav - Duplex Superior 01 | J31: =SUMIF($D$5:$D$77,I31,$G$5:$G$77) -> 17 | K31: =SUMIFS($G$5:$G$77,$D$5:$D$77,I31,$B$5:$B$77,"EST - Desforma") -> 2 | L31: =J31-K31+3 -> 18 | M31: =L31/30*22 -> 13.2 | N31: 28º Pav - Duplex Superior 01 | O31: =F67-E62 -> 50 | P31: =O31-L31 -> 32 | Q31: =P31/30*22 -> 23.466667
B32: EST - Supraestrutura | C32: - | D32: 13º Pav - Tipo 13 | E32: 45973 | F32: 45987 | G32: =F32-E32 -> 14 | I32: 29º Pav - Duplex Inferior 02 | J32: =SUMIF($D$5:$D$77,I32,$G$5:$G$77) -> 17 | K32: =SUMIFS($G$5:$G$77,$D$5:$D$77,I32,$B$5:$B$77,"EST - Desforma") -> 2 | L32: =J32-K32+3 -> 18 | M32: =L32/30*22 -> 13.2 | N32: 29º Pav - Duplex Inferior 02 | O32: =F69-E64 -> 50 | P32: =O32-L32 -> 32 | Q32: =P32/30*22 -> 23.466667
B33: EST - Desforma | C33: - | D33: 11º Pav - Tipo 11 | E33: 45987 | F33: 45989 | G33: =F33-E33 -> 2 | I33: 30º Pav - Duplex Superior 02 | J33: =SUMIF($D$5:$D$77,I33,$G$5:$G$77) -> 18 | K33: =SUMIFS($G$5:$G$77,$D$5:$D$77,I33,$B$5:$B$77,"EST - Desforma") -> 2 | L33: =J33-K33+3 -> 19 | M33: =L33/30*22 -> 13.933333 | N33: 30º Pav - Duplex Superior 02 | O33: =F71-E66 -> 51 | P33: =O33-L33 -> 32 | Q33: =P33/30*22 -> 23.466667
B34: EST - Supraestrutura | C34: - | D34: 14º Pav - Tipo 14 | E34: 45988 | F34: 46002 | G34: =F34-E34 -> 14 | I34: 31º Pav - Penthouse Inferior | J34: =SUMIF($D$5:$D$77,I34,$G$5:$G$77) -> 22 | K34: =SUMIFS($G$5:$G$77,$D$5:$D$77,I34,$B$5:$B$77,"EST - Desforma") -> 2 | L34: =J34-K34+3 -> 23 | M34: =L34/30*22 -> 16.866667 | N34: 31º Pav - Penthouse Inferior | O34: =F73-E68 -> 56 | P34: =O34-L34 -> 33 | Q34: =P34/30*22 -> 24.2
B35: EST - Desforma | C35: - | D35: 12º Pav - Tipo 12 | E35: 46002 | F35: 46006 | G35: =F35-E35 -> 4 | I35: 32º Pav - Penthouse Superior | J35: =SUMIF($D$5:$D$77,I35,$G$5:$G$77) -> 23 | K35: =SUMIFS($G$5:$G$77,$D$5:$D$77,I35,$B$5:$B$77,"EST - Desforma") -> 2 | L35: =J35-K35+3 -> 24 | M35: =L35/30*22 -> 17.6 | N35: 32º Pav - Penthouse Superior | O35: =F75-E70 -> 56 | P35: =O35-L35 -> 32 | Q35: =P35/30*22 -> 23.466667
B36: EST - Supraestrutura | C36: - | D36: 15º Pav - Tipo 15 | E36: 46003 | F36: 46034 | G36: =F36-E36 -> 31 | I36: Cobertura/Barrilete | J36: =SUMIF($D$5:$D$77,I36,$G$5:$G$77) -> 23 | K36: =SUMIFS($G$5:$G$77,$D$5:$D$77,I36,$B$5:$B$77,"EST - Desforma") -> 2 | L36: =J36-K36+3 -> 24 | M36: =L36/30*22 -> 17.6 | N36: Cobertura/Barrilete | O36: =F76-E72 -> 70 | P36: =O36-L36 -> 46 | Q36: =P36/30*22 -> 33.733333
B37: EST - Desforma | C37: - | D37: 13º Pav - Tipo 13 | E37: 46034 | F37: 46036 | G37: =F37-E37 -> 2 | I37: Reservatório | J37: =SUMIF($D$5:$D$77,I37,$G$5:$G$77) -> 19 | K37: =SUMIFS($G$5:$G$77,$D$5:$D$77,I37,$B$5:$B$77,"EST - Desforma") -> 4 | L37: =J37-K37+3 -> 18 | M37: =L37/30*22 -> 13.2 | N37: Reservatório | O37: =F77-E74 -> 64 | P37: =O37-L37 -> 46 | Q37: =P37/30*22 -> 33.733333
B38: EST - Supraestrutura | C38: - | D38: 16º Pav - Tipo 16 | E38: 46035 | F38: 46049 | G38: =F38-E38 -> 14 | J38: =SUM(J4:J37) -> 790 | O38: =SUM(O4:O37) -> 1968
B39: EST - Desforma | C39: - | D39: 14º Pav - Tipo 14 | E39: 46049 | F39: 46051 | G39: =F39-E39 -> 2 | J39: =J38/30 -> 26.333333 | O39: =O38/30 -> 65.6
B40: EST - Supraestrutura | C40: - | D40: 17º Pav - Tipo 17 | E40: 46050 | F40: 46064 | G40: =F40-E40 -> 14
B41: EST - Desforma | C41: - | D41: 15º Pav - Tipo 15 | E41: 46064 | F41: 46066 | G41: =F41-E41 -> 2
B42: EST - Supraestrutura | C42: - | D42: 18º Pav - Tipo 18 | E42: 46065 | F42: 46083 | G42: =F42-E42 -> 18
B43: EST - Desforma | C43: - | D43: 16º Pav - Tipo 16 | E43: 46083 | F43: 46085 | G43: =F43-E43 -> 2
B44: EST - Supraestrutura | C44: - | D44: 19º Pav - Tipo 19 | E44: 46084 | F44: 46098 | G44: =F44-E44 -> 14
B45: EST - Desforma | C45: - | D45: 17º Pav - Tipo 17 | E45: 46098 | F45: 46100 | G45: =F45-E45 -> 2
B46: EST - Supraestrutura | C46: - | D46: 20º Pav - Tipo 20 | E46: 46099 | F46: 46113 | G46: =F46-E46 -> 14
B47: EST - Desforma | C47: - | D47: 18º Pav - Tipo 18 | E47: 46113 | F47: 46118 | G47: =F47-E47 -> 5
B48: EST - Supraestrutura | C48: - | D48: 21º Pav - Tipo 21 | E48: 46114 | F48: 46129 | G48: =F48-E48 -> 15
B49: EST - Desforma | C49: - | D49: 19º Pav - Tipo 19 | E49: 46129 | F49: 46134 | G49: =F49-E49 -> 5
B50: EST - Supraestrutura | C50: - | D50: 22º Pav - Tipo 22 | E50: 46132 | F50: 46148 | G50: =F50-E50 -> 16
B51: EST - Desforma | C51: - | D51: 20º Pav - Tipo 20 | E51: 46148 | F51: 46150 | G51: =F51-E51 -> 2
... B77: EST - Desforma | C77: - | D77: Reservatório | E77: 46409 | F77: 46413 | G77: =F77-E77 -> 4
F79: =F77-E5 -> 831 | G79: =F79/30 -> 27.7

Sheet Áreas
A1: Obra | B1: Origem 3300
A2: Empresa | B2: Neuhaus Incorporadora
A3: Revisão | B3: R04
A4: LEVANTAMENTO QUANTITATIVO
A6: ÁREAS COBERTAS - ESCORAMENTO
B8: PAVIMENTO | C8: ÁREA
B10: Mezanino | C10: 271.18
B11: G1 | C11: 980.62
B12: G2 | C12: 980.62
B13: G3 | C13: 980.62
B14: G4 | C14: 980.62
B15: Lazer 01 | C15: 979.79
B16: Lazer 02 | C16: 304.21
B17: TIPO GARDEN 800 | C17: 394.74
B18: TIPO | C18: 322.07
B19: TIPO | C19: 322.07
B20: TIPO | C20: 322.07
B21: TIPO | C21: 322.07
... B43: RESERVATÓRIO | C43: 47.53
B44: ÁREA TOTAL | C44: =SUM(C10:C43) -> 13521.84
