Workbook
Name \0: #REF!
Name \0: #REF!
Name \0: #REF!
Name \0: #REF!
Name \0: #REF!
Name \0: #REF!
Name \1: #REF!
Name \1: #REF!
Name \1: #REF!
Name \1: #REF!
Name \1: #REF!
Name \a: #REF!
Name \a: #REF!
Name \a: #REF!
Name \a: #REF!
Name \a: #REF!
Name \a: #REF!
Name \b: #REF!
Name \b: #REF!
Name \b: #REF!
Name \b: #REF!
Name \b: #REF!
Name \c: #REF!
Name \c: #REF!
Name \c: #REF!
Name \c: #REF!
Name \c: #REF!
Name \d: #REF!
Name \d: #REF!
Name \d: #REF!
Name \d: #REF!
Name \d: #REF!
Name \e: #REF!
Name \e: #REF!
Name \e: #REF!
Name \e: #REF!
Name \e: #REF!
Name \i: #REF!
Name \i: #REF!
Name \i: #REF!
Name \i: #REF!
Name \i: #REF!
Name \J: #REF!
Name \J: #REF!
Name \J: #REF!
Name \J: #REF!
Name \J: #REF!
Name \k: #REF!
Name \k: #REF!
Name \k: #REF!
Name \k: #REF!
Name \k: #REF!
Name \l: #N/A
Name \m: #REF!
Name \m: #REF!
Name \m: #REF!
Name \m: #REF!
Name \m: #REF!
Name \m: #REF!
Name \o: #REF!

Sheet PROJETOS
B1: Projeto | C1: ='Obra '!D1 -> Caio Prado
B2: Empresa | C2: ='Obra '!D2 -> Indepy
B3: Revisão | C3: ='Obra '!D3 -> R00 - Larissa
A5: INFRAESTRUTURA
A6: PAVIMENTO | B6: DISCIPLINA
B7: ARQUITETURA | C7: FUNDAÇÕES | D7: OBSERVAÇÃO
A8: Fundação Profunda | C8: BRS_RDT_FUN_EX_001_R03
A20: Caminho: | B20: https://qicloud.com.br/root/caroline.nunes@cartesianengenharia.com#Obras/BRS-MOD_REDENTOR/Estrutura/04%20-%20PROJETO%20EXECUTIVO/PDF
A22: INSTALAÇÕES ELETRICAS
A23: PAVIMENTO | B23: DISCIPLINA
B24: ARQUITETURA | C24: ELETRICA | D24: OBSERVAÇÃO
A25: GERAL
A26: ='Obra '!$B$17 -> Subsolo
A27: ='Obra '!$B$18 -> Térreo
A28: ='Obra '!$B$19 -> 1º Pavimento - HMP
A29: ='Obra '!$B$20 -> 2º Pavimento - HMP
A30: ='Obra '!$B$21 -> 3º Pavimento - R2V / HMP
A31: ='Obra '!$B$22 -> 5º/ 7º/ 9º E 11º Pavimento - R2V
A32: ='Obra '!$B$23 -> 4º/ 6º/ 8º/ 10º E 12º Pavimento - R2V
A33: ='Obra '!$B$24 -> 13º Pavimento - LAZER
A34: ='Obra '!$B$25 -> 14º E 16º Pavimento - R2V
A35: ='Obra '!$B$26 -> 15º E 17º Pavimento - R2V
A36: ='Obra '!$B$27 -> 18º Pavimento - LAZER
A37: Caminho: | B37: 2.Projetos em andamento/Empresa/Obra/Escopo/Extração de quantitativos/Projetos Considerados

Sheet Obra 
C1: Projeto | D1: Caio Prado | E1: ENDEREÇO DA OBRA: | F1: R. Caio Prado, 207 - Consolação, São Paulo - SP, 01303-001
C2: Empresa | D2: Indepy | E2: CNPJ:
C3: Revisão | D3: R00 - Larissa | E3: ARQUIVO:
A4: QUADRO DE ÁREAS
B6: Descrição | C6: Unidade | E6: Quantidade | G6: Imagens
B7: MESES DE OBRA | C7: MÊS | E7: 36
B8: ÁREA DO TERRENO | C8: M² | E8: 981.06
B9: ÁREA CONSTRUÍDA | C9: M² | E9: 6938.39
B10: NÚMERO DE UNIDADES HABITACIONAIS | C10: UN | E10: 135
B11: NÚMERO DE UNIDADES COMERCIAIS | C11: UN | E11: 1
B12: ÁREA PRIVATIVA | C12: M² | E12: =SUM(E66:E115) -> 4392.6
B13: NÚMERO DE PAVIMENTOS | C13: UN | E13: 23
B14: ÁREA DE LAZER | C14: M² | E14: =MOBILIÁRIO!C7 -> 1901.04
B15: TOTAL DORMITÓRIOS | C15: UN | E15: 135
B17: Subsolo | C17: M² | E17: 243.84
B18: Térreo | C18: M² | E18: 615.57 | F18: =E18*0.6 -> 369.342
B19: 1º Pavimento - HMP | C19: M² | E19: 380.61
B20: 2º Pavimento - HMP | C20: M² | E20: 478.98
B21: 3º Pavimento - R2V / HMP | C21: M² | E21: 412.99
B22: 5º/ 7º/ 9º E 11º Pavimento - R2V | C22: M² | E22: 1651.96
B23: 4º/ 6º/ 8º/ 10º E 12º Pavimento - R2V | C23: M² | E23: 1806.8
B24: 13º Pavimento - LAZER | C24: M² | E24: 294.68 | F24: =E24*0.9 -> 265.212
B25: 14º E 16º Pavimento - R2V | C25: M² | E25: 445.2
B26: 15º E 17º Pavimento - R2V | C26: M² | E26: 389.26
B27: 18º Pavimento - LAZER | C27: M² | E27: 82.25 | F27: =E27*0.9 -> 74.025
B28: BARRILETE | C28: M² | E28: 67.2
B29: CX D'ÁGUA | C29: M² | E29: 69.05 | F29: =59.88+3.11+78.87+47.22+27.7+5.97+2.985+1.84 -> 227.575
B30: TOPO | C30: M²
B35: CARTESIAN | G35: CARTESIAN
B36: ETAPA | C36: VALOR ORÇADO | D36: % | E36: VALOR / m² | G36: ETAPA | H36: VALOR ORÇADO | I36: % | J36: VALOR / m²
B37: GERENCIAMENTO TÉCNICO E ADMISTRATIVO | D37: =C37/C$60 -> 0 | E37: =C37/$E$9 -> 0 | G37: PAREDES E PAINÉIS | H37: =C42 -> 1994418.8 | I37: =H37/H$48 -> 0.12034852 | J37: =H37/$E$9 -> 287.44691
B38: MOVIMENTAÇÃO DE TERRA | C38: =SUMIFS(Ger_Executivo!N:N,Ger_Executivo!J:J,B38,Ger_Executivo!H:H,Ger_Executivo!$H$8) -> 0 | D38: =C38/C$60 -> 0 | E38: =C38/$E$9 -> 0 | G38: IMPERMEABILIZAÇÃO E TRATAMENTOS | H38: =C43 -> 703992.08 | I38: =H38/H$48 -> 0.042480748 | J38: =H38/$E$9 -> 101.46332
B39: INFRAESTRUTURA | C39: =SUMIFS(Ger_Executivo!N:N,Ger_Executivo!J:J,B39,Ger_Executivo!H:H,Ger_Executivo!$H$8) -> 0 | D39: =C39/C$60 -> 0 | E39: =C39/$E$9 -> 0 | G39: REVESTIMENTOS INTERNOS DE PAREDE | H39: =C51 -> 1323971.4 | I39: =H39/H$48 -> 0.079891944 | J39: =H39/$E$9 -> 190.81825
B40: CONTENÇÃO | C40: =SUMIFS(Ger_Executivo!N:N,Ger_Executivo!J:J,B40,Ger_Executivo!H:H,Ger_Executivo!$H$8) -> 0 | D40: =C40/C$60 -> 0 | E40: =C40/$E$9 -> 0 | G40: REVESTIMENTOS E ACABAMENTOS INTERNOS EM TETO | H40: =C52 -> 695689.43 | I40: =H40/H$48 -> 0.041979744 | J40: =H40/$E$9 -> 100.26669
B41: SUPRAESTRUTURA | C41: =SUMIFS(Ger_Executivo!N:N,Ger_Executivo!J:J,B41,Ger_Executivo!H:H,Ger_Executivo!$H$8) -> 0 | D41: =C41/C$60 -> 0 | E41: =C41/$E$9 -> 0 | G41: PISOS E PAVIMENTAÇÕES | H41: =C53 -> 1461780 | I41: =H41/H$48 -> 0.088207681 | J41: =H41/$E$9 -> 210.68
B42: PAREDES E PAINÉIS | C42: =SUMIFS(Ger_Executivo!N:N,Ger_Executivo!J:J,B42,Ger_Executivo!H:H,Ger_Executivo!$H$8) -> 1994418.8 | D42: =C42/C$60 -> 0.11798874 | E42: =C42/$E$9 -> 287.44691 | G42: SISTEMAS DE PINTURA INTERNA | H42: =C54 -> 1340430.3 | I42: =H42/H$48 -> 0.080885116 | J42: =H42/$E$9 -> 193.19039
B43: IMPERMEABILIZAÇÃO E TRATAMENTOS | C43: =SUMIFS(Ger_Executivo!N:N,Ger_Executivo!J:J,B43,Ger_Executivo!H:H,Ger_Executivo!$H$8) -> 703992.08 | D43: =C43/C$60 -> 0.041647792 | E43: =C43/$E$9 -> 101.46332 | G43: ESQUADRIAS, VIDROS E FERRAGENS | H43: =C55 -> 3691455.8 | I43: =H43/H$48 -> 0.22275223 | J43: =H43/$E$9 -> 532.03348
B44: SISTEMAS E INSTALAÇÕES ELÉTRICAS | C44: =SUMIFS(Ger_Executivo!N:N,Ger_Executivo!J:J,B44,Ger_Executivo!H:H,Ger_Executivo!$H$8) -> 0 | D44: =C44/C$60 -> 0 | E44: =C44/$E$9 -> 0 | G44: LOUÇAS E METAIS | H44: =C56 -> 326798.11 | I44: =H44/H$48 -> 0.019719864 | J44: =H44/$E$9 -> 47.099992
B45: SISTEMAS E INSTALAÇÕES HIDROSSANITÁRIAS E DRENAGEM | C45: =SUMIFS(Ger_Executivo!N:N,Ger_Executivo!J:J,B45,Ger_Executivo!H:H,Ger_Executivo!$H$8) -> 0 | D45: =C45/C$60 -> 0 | E45: =C45/$E$9 -> 0 | G45: REVESTIMENTOS E ACABAMENTOS EM FACHADA | H45: =C57 -> 1898087.7 | I45: =H45/H$48 -> 0.11453564 | J45: =H45/$E$9 -> 273.56313
B46: INSTALAÇÕES PREVENTIVAS | C46: =SUMIFS(Ger_Executivo!N:N,Ger_Executivo!J:J,B46,Ger_Executivo!H:H,Ger_Executivo!$H$8) -> 0 | D46: =C46/C$60 -> 0 | E46: =C46/$E$9 -> 0 | G46: SERVIÇOS COMPLEMENTARES E FINAIS | H46: =C58 -> 3135402.8 | I46: =H46/H$48 -> 0.18919852 | J46: =H46/$E$9 -> 451.89198
B47: INSTALAÇÕES DE GÁS | C47: =SUMIFS(Ger_Executivo!N:N,Ger_Executivo!J:J,B47,Ger_Executivo!H:H,Ger_Executivo!$H$8) -> 0 | D47: =C47/C$60 -> 0 | E47: =C47/$E$9 -> 0
B48: EQUIPAMENTOS E SISTEMAS ESPECIAIS | C48: =SUMIFS(Ger_Executivo!N:N,Ger_Executivo!J:J,B48,Ger_Executivo!H:H,Ger_Executivo!$H$8) -> 0 | D48: =C48/C$60 -> 0 | E48: =C48/$E$9 -> 0 | G48: TOTAL | H48: =SUM(H37:H47) -> 16572026 | I48: =SUM(I37:I47) -> 1 | J48: =SUM(J37:J47) -> 2388.4542
B49: CLIMATIZAÇÃO, EXAUSTÃO MECÂNICA | C49: =SUMIFS(Ger_Executivo!N:N,Ger_Executivo!J:J,B49,Ger_Executivo!H:H,Ger_Executivo!$H$8) -> 0 | D49: =C49/C$60 -> 0 | E49: =C49/$E$9 -> 0 | G49: CUB/SP R8-N | H49: 2481.34 | I49: 45931 | J49: =ROUNDUP(+J48/H49,2)&" CUB" -> 0,97 CUB
B50: INSTALAÇÕES ESPECIAIS | C50: =SUMIFS(Ger_Executivo!N:N,Ger_Executivo!J:J,B50,Ger_Executivo!H:H,Ger_Executivo!$H$8) -> 0 | D50: =C50/C$60 -> 0 | E50: =C50/$E$9 -> 0
B51: REVESTIMENTOS INTERNOS DE PAREDE | C51: =SUMIFS(Ger_Executivo!N:N,Ger_Executivo!J:J,B51,Ger_Executivo!H:H,Ger_Executivo!$H$8) -> 1323971.4 | D51: =C51/C$60 -> 0.078325435 | E51: =C51/$E$9 -> 190.81825
B52: REVESTIMENTOS E ACABAMENTOS INTERNOS EM TETO | C52: =SUMIFS(Ger_Executivo!N:N,Ger_Executivo!J:J,B52,Ger_Executivo!H:H,Ger_Executivo!$H$8) -> 695689.43 | D52: =C52/C$60 -> 0.041156612 | E52: =C52/$E$9 -> 100.26669
B53: PISOS E PAVIMENTAÇÕES | C53: =SUMIFS(Ger_Executivo!N:N,Ger_Executivo!J:J,B53,Ger_Executivo!H:H,Ger_Executivo!$H$8) -> 1461780 | D53: =C53/C$60 -> 0.086478119 | E53: =C53/$E$9 -> 210.68
B54: SISTEMAS DE PINTURA INTERNA | C54: =SUMIFS(Ger_Executivo!N:N,Ger_Executivo!J:J,B54,Ger_Executivo!H:H,Ger_Executivo!$H$8) -> 1340430.3 | D54: =C54/C$60 -> 0.079299133 | E54: =C54/$E$9 -> 193.19039
B55: ESQUADRIAS, VIDROS E FERRAGENS | C55: =SUMIFS(Ger_Executivo!N:N,Ger_Executivo!J:J,B55,Ger_Executivo!H:H,Ger_Executivo!$H$8) -> 3691455.8 | D55: =C55/C$60 -> 0.21838454 | E55: =C55/$E$9 -> 532.03348
B56: LOUÇAS E METAIS | C56: =SUMIFS(Ger_Executivo!N:N,Ger_Executivo!J:J,B56,Ger_Executivo!H:H,Ger_Executivo!$H$8) -> 326798.11 | D56: =C56/C$60 -> 0.0193332 | E56: =C56/$E$9 -> 47.099992
B57: REVESTIMENTOS E ACABAMENTOS EM FACHADA | C57: =SUMIFS(Ger_Executivo!N:N,Ger_Executivo!J:J,B57,Ger_Executivo!H:H,Ger_Executivo!$H$8) -> 1898087.7 | D57: =C57/C$60 -> 0.11228984 | E57: =C57/$E$9 -> 273.56313
B58: SERVIÇOS COMPLEMENTARES E FINAIS | C58: =SUMIFS(Ger_Executivo!N:N,Ger_Executivo!J:J,B58,Ger_Executivo!H:H,Ger_Executivo!$H$8) -> 3135402.8 | D58: =C58/C$60 -> 0.18548874 | E58: =C58/$E$9 -> 451.89198
B59: IMPREVISTOS E CONTINGÊNCIAS | C59: =SUMIFS(Ger_Executivo!N:N,Ger_Executivo!J:J,B59,Ger_Executivo!H:H,Ger_Executivo!$H$8) -> 331440.53 | D59: =C59/C$60 -> 0.019607843 | E59: =C59/$E$9 -> 47.769083
B60: TOTAL | C60: =SUM(C37:C59) -> 16903467 | D60: =SUM(D37:D59) -> 1 | E60: =SUM(E37:E59) -> 2436.2232
B61: CUB/SP R8-N | C61: 2481.34 | D61: 45931 | E61: =ROUNDUP(+E60/C61,2)&" CUB" -> 0,99 CUB
B64: Área Privativa
B65: Aptos | C65: Área Útil (m2) | D65: Qnt | E65: Total (m2) | F65: VENT. MEC. | G65: Dormitorios | H65: Banheiros
B66: APTO TIPO "E" - FINAL 06/07 - 1 Pav | C66: 27.14 | D66: 2 | E66: =D66*C66 -> 54.28 | F66: 0 | G66: 2 | H66: 2
B67: APTO TIPO "F" - FINAL 08/09 - 1 Pav | C67: 27.83 | D67: 2 | E67: =D67*C67 -> 55.66 | F67: 0 | G67: 2 | H67: 2
B68: APTO TIPO "G" - FINAL 10 - 1 Pav | C68: 27.58 | D68: 1 | E68: =D68*C68 -> 27.58 | F68: 0 | G68: 1 | H68: 1
B69: APTO TIPO "H" - FINAL 11 - 1 Pav | C69: 27.86 | D69: 1 | E69: =D69*C69 -> 27.86 | F69: 0 | G69: 1 | H69: 1
B70: APTO TIPO "J" - FINAL 01- 2 Pav | C70: 34.75 | D70: 1 | E70: =D70*C70 -> 34.75 | F70: 0 | G70: 1 | H70: 1
B71: APTO TIPO "B" - FINAL 02/03 - 2 Pav | C71: 29.97 | D71: 2 | E71: =D71*C71 -> 59.94 | F71: 0 | G71: 2 | H71: 2
B72: APTO TIPO "C" - FINAL 04 - 2 Pav | C72: 30.41 | D72: 1 | E72: =D72*C72 -> 30.41 | F72: 0 | G72: 1 | H72: 1
B73: APTO TIPO "I" - FINAL 05 - 2 Pav | C73: 29.05 | D73: 1 | E73: =D73*C73 -> 29.05 | F73: 0 | G73: 1 | H73: 1
B74: APTO TIPO "E" - FINAL 06/07- 2 Pav | C74: 27.14 | D74: 2 | E74: =D74*C74 -> 54.28 | F74: 0 | G74: 2 | H74: 2
B75: APTO TIPO "F" - FINAL 08/09 - 2 Pav | C75: 27.83 | D75: 2 | E75: =D75*C75 -> 55.66 | F75: 0 | G75: 2 | H75: 2
B76: APTO TIPO "G" - FINAL 10 - 2 Pav | C76: 27.58 | D76: 1 | E76: =D76*C76 -> 27.58 | F76: 0 | G76: 1 | H76: 1
B77: APTO TIPO "H" - FINAL 11 - 2 Pav | C77: 27.86 | D77: 1 | E77: =D77*C77 -> 27.86 | F77: 0 | G77: 1 | H77: 1
... B115: APTO TIPO "M" - FINAL 05(DUPLEX INFERIOR) - 16 Pav | C115: 37.61 | D115: 1 | E115: =D115*C115 -> 37.61 | F115: 0 | G115: 1 | H115: 1
E116: =SUM(E66:E115) -> 4392.6 | F116: =SUM(F66:F115) -> 0 | G116: =SUM(G66:G115) -> 149 | H116: =SUM(H66:H115) -> 149
H117: =E116/H116 -> 29.480537

Sheet EAP Análise
A1: ETAPA | B1: VALOR ORÇADO | C1: % | D1: VALOR / m²
A2: GERENCIAMENTO TÉCNICO E ADMINISTRATIVO | C2: =B2/$B$28 -> 0 | D2: =B2/'Obra '!$E$9 -> 0 | E2: ='[4]MÉDIAS CARTESIAN'!$C13-B2 -> 2406266.6
A3: MOVIMENTAÇÃO DE TERRA | B3: =SUMIF(Ger_Executivo!Q:Q,A3,Ger_Executivo!N:N) -> 0 | C3: =B3/$B$28 -> 0 | D3: =B3/'Obra '!$E$9 -> 0 | E3: ='[4]MÉDIAS CARTESIAN'!$C14-B3 -> 303296.04
A4: INFRAESTRUTURA | B4: =SUMIF(Ger_Executivo!Q:Q,A4,Ger_Executivo!N:N) -> 0 | C4: =B4/$B$28 -> 0 | D4: =B4/'Obra '!$E$9 -> 0 | E4: ='[4]MÉDIAS CARTESIAN'!$C15-B4 -> 1290666.1
A5: CONTENÇÃO | B5: =SUMIF(Ger_Executivo!Q:Q,A5,Ger_Executivo!N:N) -> 0 | C5: =B5/$B$28 -> 0 | D5: =B5/'Obra '!$E$9 -> 0 | E5: ='[4]MÉDIAS CARTESIAN'!$C18-B5 -> 168316.36
A6: SUPRAESTRUTURA | B6: =SUMIF(Ger_Executivo!Q:Q,A6,Ger_Executivo!N:N) -> 0 | C6: =B6/$B$28 -> 0 | D6: =B6/'Obra '!$E$9 -> 0 | E6: ='[4]MÉDIAS CARTESIAN'!$C19-B6 -> 3502945.8
A7: ALVENARIA | B7: =SUMIF(Ger_Executivo!Q:Q,A7,Ger_Executivo!N:N) -> 1994418.8 | C7: =B7/$B$28 -> 0.11798874 | D7: =B7/'Obra '!$E$9 -> 287.44691 | E7: ='[4]MÉDIAS CARTESIAN'!$C20-B7 -> -720693.13
A8: INSTALAÇÕES ELÉTRICAS, HIDRÁULICAS, GLP E PREVENTIVAS | B8: =SUMIF(Ger_Executivo!Q:Q,A8,Ger_Executivo!N:N) -> 0 | C8: =B8/$B$28 -> 0 | D8: =B8/'Obra '!$E$9 -> 0 | E8: ='[4]MÉDIAS CARTESIAN'!$C25+'[4]MÉDIAS CARTESIAN'!$C$24+'[4]MÉDIAS CARTESIAN'!$C$23+'[4]MÉDIAS CARTESIAN'!$C$22+'[4]MÉDIAS CARTESIAN'!$C$21-B8 -> 1861372.5
A9: CLIMATIZAÇÃO, EXAUSTÃO MECÂNICA E PRESSURIZAÇÃO | B9: =SUMIF(Ger_Executivo!Q:Q,A9,Ger_Executivo!N:N) -> 0 | C9: =B9/$B$28 -> 0 | D9: =B9/'Obra '!$E$9 -> 0 | E9: ='[4]MÉDIAS CARTESIAN'!$C26-B9 -> 623694.81
A10: EQUIPAMENTOS E SISTEMAS ESPECIAIS | B10: =SUMIF(Ger_Executivo!Q:Q,A10,Ger_Executivo!N:N) -> 0 | C10: =B10/$B$28 -> 0 | D10: =B10/'Obra '!$E$9 -> 0 | E10: ='[4]MÉDIAS CARTESIAN'!$C27-B10 -> 504732.66
A11: INSTALAÇÕES ESPECIAIS | B11: =SUMIF(Ger_Executivo!Q:Q,A11,Ger_Executivo!N:N) -> 0 | C11: =B11/$B$28 -> 0 | D11: =B11/'Obra '!$E$9 -> 0 | E11: ='[4]MÉDIAS CARTESIAN'!$C28-B11 -> 323409.52
A12: REVESTIMENTOS ARGAMASSADOS PISO | B12: =SUMIF(Ger_Executivo!Q:Q,A12,Ger_Executivo!N:N) -> 669260.84 | C12: =B12/$B$28 -> 0.039593111 | D12: =B12/'Obra '!$E$9 -> 96.457657 | E12: ='[4]MÉDIAS CARTESIAN'!$C29-B12 -> -215508.1
A13: REVESTIMENTOS ARGAMASSADOS PAREDE | B13: =SUMIF(Ger_Executivo!Q:Q,A13,Ger_Executivo!N:N) -> 428169.71 | C13: =B13/$B$28 -> 0.025330289 | D13: =B13/'Obra '!$E$9 -> 61.710239 | E13: ='[4]MÉDIAS CARTESIAN'!$C30-B13 -> -129346.75
A14: REVESTIMENTOS ARGAMASSADOS TETO | B14: =SUMIF(Ger_Executivo!Q:Q,A14,Ger_Executivo!N:N) -> 11353.315 | C14: =B14/$B$28 -> 0.000671656 | D14: =B14/'Obra '!$E$9 -> 1.636304 | E14: ='[4]MÉDIAS CARTESIAN'!$C31-B14 -> 54584.25
A15: IMPERMEABILIZAÇÃO | B15: =SUMIF(Ger_Executivo!Q:Q,A15,Ger_Executivo!N:N) -> 703992.08 | C15: =B15/$B$28 -> 0.041647792 | D15: =B15/'Obra '!$E$9 -> 101.46332 | E15: ='[4]MÉDIAS CARTESIAN'!$C32-B15 -> -115353.88
A16: ACABAMENTOS INTERNOS EM PAREDE | B16: =SUMIF(Ger_Executivo!Q:Q,A16,Ger_Executivo!N:N) -> 895801.7 | C16: =B16/$B$28 -> 0.052995146 | D16: =B16/'Obra '!$E$9 -> 129.10801 | E16: ='[4]MÉDIAS CARTESIAN'!$C33-B16 -> -501510.48
A17: ACABAMENTOS EM PISOS E PAVIMENTAÇÕES | B17: =SUMIF(Ger_Executivo!Q:Q,A17,Ger_Executivo!N:N) -> 792519.18 | C17: =B17/$B$28 -> 0.046885008 | D17: =B17/'Obra '!$E$9 -> 114.22235 | E17: ='[4]MÉDIAS CARTESIAN'!$C34-B17 -> 205885.82
A18: ACABAMENTOS INTERNOS EM TETO | B18: =SUMIF(Ger_Executivo!Q:Q,A18,Ger_Executivo!N:N) -> 684336.12 | C18: =B18/$B$28 -> 0.040484956 | D18: =B18/'Obra '!$E$9 -> 98.630391 | E18: ='[4]MÉDIAS CARTESIAN'!$C35-B18 -> -204418.8
A19: PINTURA INTERNA | B19: =SUMIF(Ger_Executivo!Q:Q,A19,Ger_Executivo!N:N) -> 1340430.3 | C19: =B19/$B$28 -> 0.079299133 | D19: =B19/'Obra '!$E$9 -> 193.19039 | E19: ='[4]MÉDIAS CARTESIAN'!$C36-B19 -> -515533.57
A20: PINTURA DE FACHADA | B20: =SUMIF(Ger_Executivo!Q:Q,A20,Ger_Executivo!N:N) -> 715371.88 | C20: =B20/$B$28 -> 0.042321015 | D20: =B20/'Obra '!$E$9 -> 103.10344 | E20: ='[4]MÉDIAS CARTESIAN'!$C37-B20 -> -143553.59
... A27: IMPREVISTOS | B27: =SUMIF(Ger_Executivo!Q:Q,A27,Ger_Executivo!N:N) -> 331440.53 | C27: =B27/$B$28 -> 0.019607843 | D27: =B27/'Obra '!$E$9 -> 47.769083 | E27: ='[4]MÉDIAS CARTESIAN'!$C44-B27 -> 61216.986
A28: TOTAL | B28: =SUM(B2:B27) -> 16903467 | C28: =SUM(C2:C27) -> 1 | D28: =SUM(D2:D27) -> 2436.2232
A29: CUB/SC | B29: ='Obra '!C61 -> 2481.34 | C29: ='Obra '!D61 -> 45931 | D29: =ROUNDUP(+D28/B29,2)&" CUB" -> 0,99 CUB
A33: ALVENARIA
A34: ALVENARIA | B34: =8065.3318*2 -> 16130.664
A35: DRYWALL | B35: =2807.94+822.07 -> 3630.01
B36: =B34+B35 -> 19760.674
A38: ARGAMASSADO INTERNO
A39: EST INT | B39: 253.75
A40: CHAP INT | B40: 2077.54
A41: REB INT | B41: 66.91
A42: MASSA GESSO INTERNO | B42: 12478.29 | C42: Tem itens aqui com estrutura, portanto, uma parte fica e argamassado e outra fica em alvenaria ali emcima
B43: =SUM(B39:B42) -> 14876.49
A44: ARGAMASSADO EXTERNO
A45: REB EXT | B45: 6418.996
A46: EST EXT | B46: 576.58
B47: =B45+B46 -> 6995.576 | C47: =B47+B43 -> 21872.066
A48: ACABAMENTO INTERNO
A49: PINT INT | B49: 16892.104
A50: ACAB INT | B50: 3346.4578
B51: =B49+B50 -> 20238.562 | F51: =69.39/2 -> 34.695
A52: ACABAMENTO EXTERNO | F52: =151.11/5 -> 30.222
A53: PINT EXT | B53: 6835.9717
A54: ACAB EXT | B54: 588
B55: =B53+B54 -> 7423.9717 | C55: =B55+B51 -> 27662.533

Sheet CPU
A1: Repetição | B1: Tipo | C1: Descrição | D1: Descrição | E1: Und | F1: Quantidade | G1: Custo unit. | H1: Custo Total. | I1: Observações
A2: =COUNTIFS($D$2:$D$3085,D2,$B$2:$B$3085,B2) -> 1 | B2: Etapa | D2: INSTALAÇÕES PROVISÓRIAS | G2: =IF(B2="insumo",_xlfn.XLOOKUP($D2,Insumos!$B$1:$B$764,Insumos!$D$1:$D$764),"") | H2: {=_xlfn.IFS(B2="Serviço",SUMIFS(H3:$H$3085,C3:$C$3085,$C2),B2="Insumo",F2*G2,B2="Etapa","")}
A3: =COUNTIFS($D$2:$D$3085,D3,$B$2:$B$3085,B3) -> 1 | B3: Serviço | C3: =IF(B3="serviço",D3,C2) -> Central de aço | D3: Central de aço | E3: M2 | G3: =IF(B3="insumo",_xlfn.XLOOKUP($D3,Insumos!$B$1:$B$764,Insumos!$D$1:$D$764),"") | H3: {=_xlfn.IFS(B3="Serviço",SUMIFS(H4:$H$3085,C4:$C$3085,$C3),B3="Insumo",F3*G3,B3="Etapa","")} -> 118.1045 | I3: Sim
A4: =COUNTIFS($D$2:$D$3085,D4,$B$2:$B$3085,B4) -> 3 | B4: Insumo | C4: =IF(B4="serviço",D4,C3) -> Central de aço | D4: LONA PLASTICA 120 MICRAS 4X100M PRETA | E4: =_xlfn.XLOOKUP(D4,Insumos!$B$1:$B$764,Insumos!$C$1:$C$764) -> M2 | F4: 1 | G4: =IF(B4="insumo",_xlfn.XLOOKUP($D4,Insumos!$B$1:$B$764,Insumos!$D$1:$D$764),"") -> 1.25 | H4: {=_xlfn.IFS(B4="Serviço",SUMIFS(H5:$H$3085,C5:$C$3085,$C4),B4="Insumo",F4*G4,B4="Etapa","")} -> 1.25
A5: =COUNTIFS($D$2:$D$3085,D5,$B$2:$B$3085,B5) -> 3 | B5: Insumo | C5: =IF(B5="serviço",D5,C4) -> Central de aço | D5: TELHA METALICA GALVANIZADA TRAPEZOIDAL 0,43MM NBR 14514 | E5: =_xlfn.XLOOKUP(D5,Insumos!$B$1:$B$764,Insumos!$C$1:$C$764) -> M2 | F5: 1 | G5: =IF(B5="insumo",_xlfn.XLOOKUP($D5,Insumos!$B$1:$B$764,Insumos!$D$1:$D$764),"") -> 31 | H5: {=_xlfn.IFS(B5="Serviço",SUMIFS(H6:$H$3085,C6:$C$3085,$C5),B5="Insumo",F5*G5,B5="Etapa","")} -> 31
A6: =COUNTIFS($D$2:$D$3085,D6,$B$2:$B$3085,B6) -> 9 | B6: Insumo | C6: =IF(B6="serviço",D6,C5) -> Central de aço | D6: Concreto Usinado bombeável 20MPa Convencional | E6: =_xlfn.XLOOKUP(D6,Insumos!$B$1:$B$764,Insumos!$C$1:$C$764) -> M3 | F6: 0.074 | G6: =IF(B6="insumo",_xlfn.XLOOKUP($D6,Insumos!$B$1:$B$764,Insumos!$D$1:$D$764),"") -> 490 | H6: {=_xlfn.IFS(B6="Serviço",SUMIFS(H7:$H$3085,C7:$C$3085,$C6),B6="Insumo",F6*G6,B6="Etapa","")} -> 36.26
A7: =COUNTIFS($D$2:$D$3085,D7,$B$2:$B$3085,B7) -> 3 | B7: Insumo | C7: =IF(B7="serviço",D7,C6) -> Central de aço | D7: PREGO GALVANIZADO LISO S/CABECA 17X21 NBR 6627 | E7: =_xlfn.XLOOKUP(D7,Insumos!$B$1:$B$764,Insumos!$C$1:$C$764) -> KG | F7: 0.15 | G7: =IF(B7="insumo",_xlfn.XLOOKUP($D7,Insumos!$B$1:$B$764,Insumos!$D$1:$D$764),"") -> 10.03 | H7: {=_xlfn.IFS(B7="Serviço",SUMIFS(H8:$H$3085,C8:$C$3085,$C7),B7="Insumo",F7*G7,B7="Etapa","")} -> 1.5045
A8: =COUNTIFS($D$2:$D$3085,D8,$B$2:$B$3085,B8) -> 3 | B8: Insumo | C8: =IF(B8="serviço",D8,C7) -> Central de aço | D8: BLOCO CONCRETO ESTRUTURAL 03MPA 14X19X39CM NBR 6136 | E8: =_xlfn.XLOOKUP(D8,Insumos!$B$1:$B$764,Insumos!$C$1:$C$764) -> UN | F8: 9 | G8: =IF(B8="insumo",_xlfn.XLOOKUP($D8,Insumos!$B$1:$B$764,Insumos!$D$1:$D$764),"") -> 2.95 | H8: {=_xlfn.IFS(B8="Serviço",SUMIFS(H9:$H$3085,C9:$C$3085,$C8),B8="Insumo",F8*G8,B8="Etapa","")} -> 26.55
A9: =COUNTIFS($D$2:$D$3085,D9,$B$2:$B$3085,B9) -> 3 | B9: Insumo | C9: =IF(B9="serviço",D9,C8) -> Central de aço | D9: ARGAMASSA ENSACADA P/ASSENTAMENTO BLOCO 04MPA NBR 13281 | E9: =_xlfn.XLOOKUP(D9,Insumos!$B$1:$B$764,Insumos!$C$1:$C$764) -> KG | F9: 24 | G9: =IF(B9="insumo",_xlfn.XLOOKUP($D9,Insumos!$B$1:$B$764,Insumos!$D$1:$D$764),"") -> 0.46 | H9: {=_xlfn.IFS(B9="Serviço",SUMIFS(H10:$H$3085,C10:$C$3085,$C9),B9="Insumo",F9*G9,B9="Etapa","")} -> 11.04
A10: =COUNTIFS($D$2:$D$3085,D10,$B$2:$B$3085,B10) -> 3 | B10: Insumo | C10: =IF(B10="serviço",D10,C9) -> Central de aço | D10: SERVICO EMP. - INST. PROVISORIA - CONFECCAO BAIA P/MATERIAL | E10: =_xlfn.XLOOKUP(D10,Insumos!$B$1:$B$764,Insumos!$C$1:$C$764) -> M2 | F10: 1 | G10: =IF(B10="insumo",_xlfn.XLOOKUP($D10,Insumos!$B$1:$B$764,Insumos!$D$1:$D$764),"") -> 10.5 | H10: {=_xlfn.IFS(B10="Serviço",SUMIFS(H11:$H$3085,C11:$C$3085,$C10),B10="Insumo",F10*G10,B10="Etapa","")} -> 10.5
A11: =COUNTIFS($D$2:$D$3085,D11,$B$2:$B$3085,B11) -> 1 | B11: Serviço | C11: =IF(B11="serviço",D11,C10) -> Central de fôrmas | D11: Central de fôrmas | E11: M2 | G11: =IF(B11="insumo",_xlfn.XLOOKUP($D11,Insumos!$B$1:$B$764,Insumos!$D$1:$D$764),"") | H11: {=_xlfn.IFS(B11="Serviço",SUMIFS(H12:$H$3085,C12:$C$3085,$C11),B11="Insumo",F11*G11,B11="Etapa","")} -> 118.1045 | I11: Sim
A12: =COUNTIFS($D$2:$D$3085,D12,$B$2:$B$3085,B12) -> 3 | B12: Insumo | C12: =IF(B12="serviço",D12,C11) -> Central de fôrmas | D12: LONA PLASTICA 120 MICRAS 4X100M PRETA | E12: =_xlfn.XLOOKUP(D12,Insumos!$B$1:$B$764,Insumos!$C$1:$C$764) -> M2 | F12: 1 | G12: =IF(B12="insumo",_xlfn.XLOOKUP($D12,Insumos!$B$1:$B$764,Insumos!$D$1:$D$764),"") -> 1.25 | H12: {=_xlfn.IFS(B12="Serviço",SUMIFS(H13:$H$3085,C13:$C$3085,$C12),B12="Insumo",F12*G12,B12="Etapa","")} -> 1.25
A13: =COUNTIFS($D$2:$D$3085,D13,$B$2:$B$3085,B13) -> 3 | B13: Insumo | C13: =IF(B13="serviço",D13,C12) -> Central de fôrmas | D13: TELHA METALICA GALVANIZADA TRAPEZOIDAL 0,43MM NBR 14514 | E13: =_xlfn.XLOOKUP(D13,Insumos!$B$1:$B$764,Insumos!$C$1:$C$764) -> M2 | F13: 1 | G13: =IF(B13="insumo",_xlfn.XLOOKUP($D13,Insumos!$B$1:$B$764,Insumos!$D$1:$D$764),"") -> 31 | H13: {=_xlfn.IFS(B13="Serviço",SUMIFS(H14:$H$3085,C14:$C$3085,$C13),B13="Insumo",F13*G13,B13="Etapa","")} -> 31
A14: =COUNTIFS($D$2:$D$3085,D14,$B$2:$B$3085,B14) -> 9 | B14: Insumo | C14: =IF(B14="serviço",D14,C13) -> Central de fôrmas | D14: Concreto Usinado bombeável 20MPa Convencional | E14: =_xlfn.XLOOKUP(D14,Insumos!$B$1:$B$764,Insumos!$C$1:$C$764) -> M3 | F14: 0.074 | G14: =IF(B14="insumo",_xlfn.XLOOKUP($D14,Insumos!$B$1:$B$764,Insumos!$D$1:$D$764),"") -> 490 | H14: {=_xlfn.IFS(B14="Serviço",SUMIFS(H15:$H$3085,C15:$C$3085,$C14),B14="Insumo",F14*G14,B14="Etapa","")} -> 36.26
A15: =COUNTIFS($D$2:$D$3085,D15,$B$2:$B$3085,B15) -> 3 | B15: Insumo | C15: =IF(B15="serviço",D15,C14) -> Central de fôrmas | D15: PREGO GALVANIZADO LISO S/CABECA 17X21 NBR 6627 | E15: =_xlfn.XLOOKUP(D15,Insumos!$B$1:$B$764,Insumos!$C$1:$C$764) -> KG | F15: 0.15 | G15: =IF(B15="insumo",_xlfn.XLOOKUP($D15,Insumos!$B$1:$B$764,Insumos!$D$1:$D$764),"") -> 10.03 | H15: {=_xlfn.IFS(B15="Serviço",SUMIFS(H16:$H$3085,C16:$C$3085,$C15),B15="Insumo",F15*G15,B15="Etapa","")} -> 1.5045
A16: =COUNTIFS($D$2:$D$3085,D16,$B$2:$B$3085,B16) -> 3 | B16: Insumo | C16: =IF(B16="serviço",D16,C15) -> Central de fôrmas | D16: BLOCO CONCRETO ESTRUTURAL 03MPA 14X19X39CM NBR 6136 | E16: =_xlfn.XLOOKUP(D16,Insumos!$B$1:$B$764,Insumos!$C$1:$C$764) -> UN | F16: 9 | G16: =IF(B16="insumo",_xlfn.XLOOKUP($D16,Insumos!$B$1:$B$764,Insumos!$D$1:$D$764),"") -> 2.95 | H16: {=_xlfn.IFS(B16="Serviço",SUMIFS(H17:$H$3085,C17:$C$3085,$C16),B16="Insumo",F16*G16,B16="Etapa","")} -> 26.55
A17: =COUNTIFS($D$2:$D$3085,D17,$B$2:$B$3085,B17) -> 3 | B17: Insumo | C17: =IF(B17="serviço",D17,C16) -> Central de fôrmas | D17: ARGAMASSA ENSACADA P/ASSENTAMENTO BLOCO 04MPA NBR 13281 | E17: =_xlfn.XLOOKUP(D17,Insumos!$B$1:$B$764,Insumos!$C$1:$C$764) -> KG | F17: 24 | G17: =IF(B17="insumo",_xlfn.XLOOKUP($D17,Insumos!$B$1:$B$764,Insumos!$D$1:$D$764),"") -> 0.46 | H17: {=_xlfn.IFS(B17="Serviço",SUMIFS(H18:$H$3085,C18:$C$3085,$C17),B17="Insumo",F17*G17,B17="Etapa","")} -> 11.04
A18: =COUNTIFS($D$2:$D$3085,D18,$B$2:$B$3085,B18) -> 3 | B18: Insumo | C18: =IF(B18="serviço",D18,C17) -> Central de fôrmas | D18: SERVICO EMP. - INST. PROVISORIA - CONFECCAO BAIA P/MATERIAL | E18: =_xlfn.XLOOKUP(D18,Insumos!$B$1:$B$764,Insumos!$C$1:$C$764) -> M2 | F18: 1 | G18: =IF(B18="insumo",_xlfn.XLOOKUP($D18,Insumos!$B$1:$B$764,Insumos!$D$1:$D$764),"") -> 10.5 | H18: {=_xlfn.IFS(B18="Serviço",SUMIFS(H19:$H$3085,C19:$C$3085,$C18),B18="Insumo",F18*G18,B18="Etapa","")} -> 10.5
A19: =COUNTIFS($D$2:$D$3085,D19,$B$2:$B$3085,B19) -> 1 | B19: Serviço | C19: =IF(B19="serviço",D19,C18) -> Central de Argamassa | D19: Central de Argamassa | E19: M2 | G19: =IF(B19="insumo",_xlfn.XLOOKUP($D19,Insumos!$B$1:$B$764,Insumos!$D$1:$D$764),"") | H19: {=_xlfn.IFS(B19="Serviço",SUMIFS(H20:$H$3085,C20:$C$3085,$C19),B19="Insumo",F19*G19,B19="Etapa","")} -> 118.1045 | I19: Sim
A20: =COUNTIFS($D$2:$D$3085,D20,$B$2:$B$3085,B20) -> 3 | B20: Insumo | C20: =IF(B20="serviço",D20,C19) -> Central de Argamassa | D20: LONA PLASTICA 120 MICRAS 4X100M PRETA | E20: =_xlfn.XLOOKUP(D20,Insumos!$B$1:$B$764,Insumos!$C$1:$C$764) -> M2 | F20: 1 | G20: =IF(B20="insumo",_xlfn.XLOOKUP($D20,Insumos!$B$1:$B$764,Insumos!$D$1:$D$764),"") -> 1.25 | H20: {=_xlfn.IFS(B20="Serviço",SUMIFS(H21:$H$3085,C21:$C$3085,$C20),B20="Insumo",F20*G20,B20="Etapa","")} -> 1.25
A21: =COUNTIFS($D$2:$D$3085,D21,$B$2:$B$3085,B21) -> 3 | B21: Insumo | C21: =IF(B21="serviço",D21,C20) -> Central de Argamassa | D21: TELHA METALICA GALVANIZADA TRAPEZOIDAL 0,43MM NBR 14514 | E21: =_xlfn.XLOOKUP(D21,Insumos!$B$1:$B$764,Insumos!$C$1:$C$764) -> M2 | F21: 1 | G21: =IF(B21="insumo",_xlfn.XLOOKUP($D21,Insumos!$B$1:$B$764,Insumos!$D$1:$D$764),"") -> 31 | H21: {=_xlfn.IFS(B21="Serviço",SUMIFS(H22:$H$3085,C22:$C$3085,$C21),B21="Insumo",F21*G21,B21="Etapa","")} -> 31
A22: =COUNTIFS($D$2:$D$3085,D22,$B$2:$B$3085,B22) -> 9 | B22: Insumo | C22: =IF(B22="serviço",D22,C21) -> Central de Argamassa | D22: Concreto Usinado bombeável 20MPa Convencional | E22: =_xlfn.XLOOKUP(D22,Insumos!$B$1:$B$764,Insumos!$C$1:$C$764) -> M3 | F22: 0.074 | G22: =IF(B22="insumo",_xlfn.XLOOKUP($D22,Insumos!$B$1:$B$764,Insumos!$D$1:$D$764),"") -> 490 | H22: {=_xlfn.IFS(B22="Serviço",SUMIFS(H23:$H$3085,C23:$C$3085,$C22),B22="Insumo",F22*G22,B22="Etapa","")} -> 36.26
A23: =COUNTIFS($D$2:$D$3085,D23,$B$2:$B$3085,B23) -> 3 | B23: Insumo | C23: =IF(B23="serviço",D23,C22) -> Central de Argamassa | D23: PREGO GALVANIZADO LISO S/CABECA 17X21 NBR 6627 | E23: =_xlfn.XLOOKUP(D23,Insumos!$B$1:$B$764,Insumos!$C$1:$C$764) -> KG | F23: 0.15 | G23: =IF(B23="insumo",_xlfn.XLOOKUP($D23,Insumos!$B$1:$B$764,Insumos!$D$1:$D$764),"") -> 10.03 | H23: {=_xlfn.IFS(B23="Serviço",SUMIFS(H24:$H$3085,C24:$C$3085,$C23),B23="Insumo",F23*G23,B23="Etapa","")} -> 1.5045
A24: =COUNTIFS($D$2:$D$3085,D24,$B$2:$B$3085,B24) -> 3 | B24: Insumo | C24: =IF(B24="serviço",D24,C23) -> Central de Argamassa | D24: BLOCO CONCRETO ESTRUTURAL 03MPA 14X19X39CM NBR 6136 | E24: =_xlfn.XLOOKUP(D24,Insumos!$B$1:$B$764,Insumos!$C$1:$C$764) -> UN | F24: 9 | G24: =IF(B24="insumo",_xlfn.XLOOKUP($D24,Insumos!$B$1:$B$764,Insumos!$D$1:$D$764),"") -> 2.95 | H24: {=_xlfn.IFS(B24="Serviço",SUMIFS(H25:$H$3085,C25:$C$3085,$C24),B24="Insumo",F24*G24,B24="Etapa","")} -> 26.55
A25: =COUNTIFS($D$2:$D$3085,D25,$B$2:$B$3085,B25) -> 3 | B25: Insumo | C25: =IF(B25="serviço",D25,C24) -> Central de Argamassa | D25: ARGAMASSA ENSACADA P/ASSENTAMENTO BLOCO 04MPA NBR 13281 | E25: =_xlfn.XLOOKUP(D25,Insumos!$B$1:$B$764,Insumos!$C$1:$C$764) -> KG | F25: 24 | G25: =IF(B25="insumo",_xlfn.XLOOKUP($D25,Insumos!$B$1:$B$764,Insumos!$D$1:$D$764),"") -> 0.46 | H25: {=_xlfn.IFS(B25="Serviço",SUMIFS(H26:$H$3085,C26:$C$3085,$C25),B25="Insumo",F25*G25,B25="Etapa","")} -> 11.04
A26: =COUNTIFS($D$2:$D$3085,D26,$B$2:$B$3085,B26) -> 3 | B26: Insumo | C26: =IF(B26="serviço",D26,C25) -> Central de Argamassa | D26: SERVICO EMP. - INST. PROVISORIA - CONFECCAO BAIA P/MATERIAL | E26: =_xlfn.XLOOKUP(D26,Insumos!$B$1:$B$764,Insumos!$C$1:$C$764) -> M2 | F26: 1 | G26: =IF(B26="insumo",_xlfn.XLOOKUP($D26,Insumos!$B$1:$B$764,Insumos!$D$1:$D$764),"") -> 10.5 | H26: {=_xlfn.IFS(B26="Serviço",SUMIFS(H27:$H$3085,C27:$C$3085,$C26),B26="Insumo",F26*G26,B26="Etapa","")} -> 10.5
A27: =COUNTIFS($D$2:$D$3085,D27,$B$2:$B$3085,B27) -> 1 | B27: Serviço | C27: =IF(B27="serviço",D27,C26) -> Armazenamento de cerâmicas* | D27: Armazenamento de cerâmicas* | E27: M2 | G27: =IF(B27="insumo",_xlfn.XLOOKUP($D27,Insumos!$B$1:$B$764,Insumos!$D$1:$D$764),"") | H27: {=_xlfn.IFS(B27="Serviço",SUMIFS(H28:$H$3085,C28:$C$3085,$C27),B27="Insumo",F27*G27,B27="Etapa","")} -> 376.71489 | I27: Sim
A28: =COUNTIFS($D$2:$D$3085,D28,$B$2:$B$3085,B28) -> 11 | B28: Insumo | C28: =IF(B28="serviço",D28,C27) -> Armazenamento de cerâmicas* | D28: MADEIRA PINUS/SIMILAR - TABUA PINUS 200X20MM NBR 11700 | E28: =_xlfn.XLOOKUP(D28,Insumos!$B$1:$B$764,Insumos!$C$1:$C$764) -> M2 | F28: 0.591 | G28: =IF(B28="insumo",_xlfn.XLOOKUP($D28,Insumos!$B$1:$B$764,Insumos!$D$1:$D$764),"") -> 46.5 | H28: {=_xlfn.IFS(B28="Serviço",SUMIFS(H29:$H$3085,C29:$C$3085,$C28),B28="Insumo",F28*G28,B28="Etapa","")} -> 27.4815
A29: =COUNTIFS($D$2:$D$3085,D29,$B$2:$B$3085,B29) -> 10 | B29: Insumo | C29: =IF(B29="serviço",D29,C28) -> Armazenamento de cerâmicas* | D29: COMPENSADO MADEIRA TIPO RESINADO COLA FENOLICA 2440X1220X10MM | E29: =_xlfn.XLOOKUP(D29,Insumos!$B$1:$B$764,Insumos!$C$1:$C$764) -> UN | F29: 0.404 | G29: =IF(B29="insumo",_xlfn.XLOOKUP($D29,Insumos!$B$1:$B$764,Insumos!$D$1:$D$764),"") -> 58.46 | H29: {=_xlfn.IFS(B29="Serviço",SUMIFS(H30:$H$3085,C30:$C$3085,$C29),B29="Insumo",F29*G29,B29="Etapa","")} -> 23.61784
A30: =COUNTIFS($D$2:$D$3085,D30,$B$2:$B$3085,B30) -> 24 | B30: Insumo | C30: =IF(B30="serviço",D30,C29) -> Armazenamento de cerâmicas* | D30: MADEIRA PINUS/SIMILAR - PONTALETE 75X75MM NBR 11700/15696 | E30: =_xlfn.XLOOKUP(D30,Insumos!$B$1:$B$764,Insumos!$C$1:$C$764) -> M | F30: 4.39 | G30: =IF(B30="insumo",_xlfn.XLOOKUP($D30,Insumos!$B$1:$B$764,Insumos!$D$1:$D$764),"") -> 7 | H30: {=_xlfn.IFS(B30="Serviço",SUMIFS(H31:$H$3085,C31:$C$3085,$C30),B30="Insumo",F30*G30,B30="Etapa","")} -> 30.73
A31: =COUNTIFS($D$2:$D$3085,D31,$B$2:$B$3085,B31) -> 11 | B31: Insumo | C31: =IF(B31="serviço",D31,C30) -> Armazenamento de cerâmicas* | D31: MADEIRA PINUS/SIMILAR - SARRAFO PINUS 50X20MM NBR 11700/15696 | E31: =_xlfn.XLOOKUP(D31,Insumos!$B$1:$B$764,Insumos!$C$1:$C$764) -> M2 | F31: 0.15 | G31: =IF(B31="insumo",_xlfn.XLOOKUP($D31,Insumos!$B$1:$B$764,Insumos!$D$1:$D$764),"") -> 46.5 | H31: {=_xlfn.IFS(B31="Serviço",SUMIFS(H32:$H$3085,C32:$C$3085,$C31),B31="Insumo",F31*G31,B31="Etapa","")} -> 6.975
A32: =COUNTIFS($D$2:$D$3085,D32,$B$2:$B$3085,B32) -> 10 | B32: Insumo | C32: =IF(B32="serviço",D32,C31) -> Armazenamento de cerâmicas* | D32: MADEIRA PINUS/SIMILAR - SARRAFO PINUS 50X10MM NBR 11700 | E32: =_xlfn.XLOOKUP(D32,Insumos!$B$1:$B$764,Insumos!$C$1:$C$764) -> M | F32: 1 | G32: =IF(B32="insumo",_xlfn.XLOOKUP($D32,Insumos!$B$1:$B$764,Insumos!$D$1:$D$764),"") -> 2 | H32: {=_xlfn.IFS(B32="Serviço",SUMIFS(H33:$H$3085,C33:$C$3085,$C32),B32="Insumo",F32*G32,B32="Etapa","")} -> 2
A33: =COUNTIFS($D$2:$D$3085,D33,$B$2:$B$3085,B33) -> 36 | B33: Insumo | C33: =IF(B33="serviço",D33,C32) -> Armazenamento de cerâmicas* | D33: PREGO DE ACO POLIDO COM CABECA 17 X 21 (2 X 11) | E33: =_xlfn.XLOOKUP(D33,Insumos!$B$1:$B$764,Insumos!$C$1:$C$764) -> KG | F33: 1 | G33: =IF(B33="insumo",_xlfn.XLOOKUP($D33,Insumos!$B$1:$B$764,Insumos!$D$1:$D$764),"") -> 18.13 | H33: {=_xlfn.IFS(B33="Serviço",SUMIFS(H34:$H$3085,C34:$C$3085,$C33),B33="Insumo",F33*G33,B33="Etapa","")} -> 18.13
A34: =COUNTIFS($D$2:$D$3085,D34,$B$2:$B$3085,B34) -> 10 | B34: Insumo | C34: =IF(B34="serviço",D34,C33) -> Armazenamento de cerâmicas* | D34: EXTINTOR INCENDIO PO QUIMICO 06KG CLASSE ABC (COMPLETO) NBR 15808 | E34: =_xlfn.XLOOKUP(D34,Insumos!$B$1:$B$764,Insumos!$C$1:$C$764) -> UN | F34: 0.015 | G34: =IF(B34="insumo",_xlfn.XLOOKUP($D34,Insumos!$B$1:$B$764,Insumos!$D$1:$D$764),"") -> 185.37 | H34: {=_xlfn.IFS(B34="Serviço",SUMIFS(H35:$H$3085,C35:$C$3085,$C34),B34="Insumo",F34*G34,B34="Etapa","")} -> 2.78055
A35: =COUNTIFS($D$2:$D$3085,D35,$B$2:$B$3085,B35) -> 10 | B35: Insumo | C35: =IF(B35="serviço",D35,C34) -> Armazenamento de cerâmicas* | D35: MATERIAL PARA INSTALAÇÃO ELÉTRICA | E35: =_xlfn.XLOOKUP(D35,Insumos!$B$1:$B$764,Insumos!$C$1:$C$764) -> VB | F35: 1 | G35: =IF(B35="insumo",_xlfn.XLOOKUP($D35,Insumos!$B$1:$B$764,Insumos!$D$1:$D$764),"") -> 215 | H35: {=_xlfn.IFS(B35="Serviço",SUMIFS(H36:$H$3085,C36:$C$3085,$C35),B35="Insumo",F35*G35,B35="Etapa","")} -> 215
A36: =COUNTIFS($D$2:$D$3085,D36,$B$2:$B$3085,B36) -> 10 | B36: Insumo | C36: =IF(B36="serviço",D36,C35) -> Armazenamento de cerâmicas* | D36: SERVICO INSTALAÇÃO BARRACAO ALMOXARIFADO | E36: =_xlfn.XLOOKUP(D36,Insumos!$B$1:$B$764,Insumos!$C$1:$C$764) -> M2 | F36: 1 | G36: =IF(B36="insumo",_xlfn.XLOOKUP($D36,Insumos!$B$1:$B$764,Insumos!$D$1:$D$764),"") -> 50 | H36: {=_xlfn.IFS(B36="Serviço",SUMIFS(H37:$H$3085,C37:$C$3085,$C36),B36="Insumo",F36*G36,B36="Etapa","")} -> 50
A37: =COUNTIFS($D$2:$D$3085,D37,$B$2:$B$3085,B37) -> 1 | B37: Serviço | C37: =IF(B37="serviço",D37,C36) -> Armazenamento de placas degesso* | D37: Armazenamento de placas degesso* | E37: M2 | G37: =IF(B37="insumo",_xlfn.XLOOKUP($D37,Insumos!$B$1:$B$764,Insumos!$D$1:$D$764),"") | H37: {=_xlfn.IFS(B37="Serviço",SUMIFS(H38:$H$3085,C38:$C$3085,$C37),B37="Insumo",F37*G37,B37="Etapa","")} -> 376.71489 | I37: Sim
A38: =COUNTIFS($D$2:$D$3085,D38,$B$2:$B$3085,B38) -> 11 | B38: Insumo | C38: =IF(B38="serviço",D38,C37) -> Armazenamento de placas degesso* | D38: MADEIRA PINUS/SIMILAR - TABUA PINUS 200X20MM NBR 11700 | E38: =_xlfn.XLOOKUP(D38,Insumos!$B$1:$B$764,Insumos!$C$1:$C$764) -> M2 | F38: 0.591 | G38: =IF(B38="insumo",_xlfn.XLOOKUP($D38,Insumos!$B$1:$B$764,Insumos!$D$1:$D$764),"") -> 46.5 | H38: {=_xlfn.IFS(B38="Serviço",SUMIFS(H39:$H$3085,C39:$C$3085,$C38),B38="Insumo",F38*G38,B38="Etapa","")} -> 27.4815
A39: =COUNTIFS($D$2:$D$3085,D39,$B$2:$B$3085,B39) -> 10 | B39: Insumo | C39: =IF(B39="serviço",D39,C38) -> Armazenamento de placas degesso* | D39: COMPENSADO MADEIRA TIPO RESINADO COLA FENOLICA 2440X1220X10MM | E39: =_xlfn.XLOOKUP(D39,Insumos!$B$1:$B$764,Insumos!$C$1:$C$764) -> UN | F39: 0.404 | G39: =IF(B39="insumo",_xlfn.XLOOKUP($D39,Insumos!$B$1:$B$764,Insumos!$D$1:$D$764),"") -> 58.46 | H39: {=_xlfn.IFS(B39="Serviço",SUMIFS(H40:$H$3085,C40:$C$3085,$C39),B39="Insumo",F39*G39,B39="Etapa","")} -> 23.61784
A40: =COUNTIFS($D$2:$D$3085,D40,$B$2:$B$3085,B40) -> 24 | B40: Insumo | C40: =IF(B40="serviço",D40,C39) -> Armazenamento de placas degesso* | D40: MADEIRA PINUS/SIMILAR - PONTALETE 75X75MM NBR 11700/15696 | E40: =_xlfn.XLOOKUP(D40,Insumos!$B$1:$B$764,Insumos!$C$1:$C$764) -> M | F40: 4.39 | G40: =IF(B40="insumo",_xlfn.XLOOKUP($D40,Insumos!$B$1:$B$764,Insumos!$D$1:$D$764),"") -> 7 | H40: {=_xlfn.IFS(B40="Serviço",SUMIFS(H41:$H$3085,C41:$C$3085,$C40),B40="Insumo",F40*G40,B40="Etapa","")} -> 30.73
A41: =COUNTIFS($D$2:$D$3085,D41,$B$2:$B$3085,B41) -> 11 | B41: Insumo | C41: =IF(B41="serviço",D41,C40) -> Armazenamento de placas degesso* | D41: MADEIRA PINUS/SIMILAR - SARRAFO PINUS 50X20MM NBR 11700/15696 | E41: =_xlfn.XLOOKUP(D41,Insumos!$B$1:$B$764,Insumos!$C$1:$C$764) -> M2 | F41: 0.15 | G41: =IF(B41="insumo",_xlfn.XLOOKUP($D41,Insumos!$B$1:$B$764,Insumos!$D$1:$D$764),"") -> 46.5 | H41: {=_xlfn.IFS(B41="Serviço",SUMIFS(H42:$H$3085,C42:$C$3085,$C41),B41="Insumo",F41*G41,B41="Etapa","")} -> 6.975
A42: =COUNTIFS($D$2:$D$3085,D42,$B$2:$B$3085,B42) -> 10 | B42: Insumo | C42: =IF(B42="serviço",D42,C41) -> Armazenamento de placas degesso* | D42: MADEIRA PINUS/SIMILAR - SARRAFO PINUS 50X10MM NBR 11700 | E42: =_xlfn.XLOOKUP(D42,Insumos!$B$1:$B$764,Insumos!$C$1:$C$764) -> M | F42: 1 | G42: =IF(B42="insumo",_xlfn.XLOOKUP($D42,Insumos!$B$1:$B$764,Insumos!$D$1:$D$764),"") -> 2 | H42: {=_xlfn.IFS(B42="Serviço",SUMIFS(H43:$H$3085,C43:$C$3085,$C42),B42="Insumo",F42*G42,B42="Etapa","")} -> 2
A43: =COUNTIFS($D$2:$D$3085,D43,$B$2:$B$3085,B43) -> 36 | B43: Insumo | C43: =IF(B43="serviço",D43,C42) -> Armazenamento de placas degesso* | D43: PREGO DE ACO POLIDO COM CABECA 17 X 21 (2 X 11) | E43: =_xlfn.XLOOKUP(D43,Insumos!$B$1:$B$764,Insumos!$C$1:$C$764) -> KG | F43: 1 | G43: =IF(B43="insumo",_xlfn.XLOOKUP($D43,Insumos!$B$1:$B$764,Insumos!$D$1:$D$764),"") -> 18.13 | H43: {=_xlfn.IFS(B43="Serviço",SUMIFS(H44:$H$3085,C44:$C$3085,$C43),B43="Insumo",F43*G43,B43="Etapa","")} -> 18.13
A44: =COUNTIFS($D$2:$D$3085,D44,$B$2:$B$3085,B44) -> 10 | B44: Insumo | C44: =IF(B44="serviço",D44,C43) -> Armazenamento de placas degesso* | D44: EXTINTOR INCENDIO PO QUIMICO 06KG CLASSE ABC (COMPLETO) NBR 15808 | E44: =_xlfn.XLOOKUP(D44,Insumos!$B$1:$B$764,Insumos!$C$1:$C$764) -> UN | F44: 0.015 | G44: =IF(B44="insumo",_xlfn.XLOOKUP($D44,Insumos!$B$1:$B$764,Insumos!$D$1:$D$764),"") -> 185.37 | H44: {=_xlfn.IFS(B44="Serviço",SUMIFS(H45:$H$3085,C45:$C$3085,$C44),B44="Insumo",F44*G44,B44="Etapa","")} -> 2.78055
A45: =COUNTIFS($D$2:$D$3085,D45,$B$2:$B$3085,B45) -> 10 | B45: Insumo | C45: =IF(B45="serviço",D45,C44) -> Armazenamento de placas degesso* | D45: MATERIAL PARA INSTALAÇÃO ELÉTRICA | E45: =_xlfn.XLOOKUP(D45,Insumos!$B$1:$B$764,Insumos!$C$1:$C$764) -> VB | F45: 1 | G45: =IF(B45="insumo",_xlfn.XLOOKUP($D45,Insumos!$B$1:$B$764,Insumos!$D$1:$D$764),"") -> 215 | H45: {=_xlfn.IFS(B45="Serviço",SUMIFS(H46:$H$3085,C46:$C$3085,$C45),B45="Insumo",F45*G45,B45="Etapa","")} -> 215
A46: =COUNTIFS($D$2:$D$3085,D46,$B$2:$B$3085,B46) -> 10 | B46: Insumo | C46: =IF(B46="serviço",D46,C45) -> Armazenamento de placas degesso* | D46: SERVICO INSTALAÇÃO BARRACAO ALMOXARIFADO | E46: =_xlfn.XLOOKUP(D46,Insumos!$B$1:$B$764,Insumos!$C$1:$C$764) -> M2 | F46: 1 | G46: =IF(B46="insumo",_xlfn.XLOOKUP($D46,Insumos!$B$1:$B$764,Insumos!$D$1:$D$764),"") -> 50 | H46: {=_xlfn.IFS(B46="Serviço",SUMIFS(H47:$H$3085,C47:$C$3085,$C46),B46="Insumo",F46*G46,B46="Etapa","")} -> 50
A47: =COUNTIFS($D$2:$D$3085,D47,$B$2:$B$3085,B47) -> 1 | B47: Serviço | C47: =IF(B47="serviço",D47,C46) -> Armazenamento de blocos* | D47: Armazenamento de blocos* | E47: M2 | G47: =IF(B47="insumo",_xlfn.XLOOKUP($D47,Insumos!$B$1:$B$764,Insumos!$D$1:$D$764),"") | H47: {=_xlfn.IFS(B47="Serviço",SUMIFS(H48:$H$3085,C48:$C$3085,$C47),B47="Insumo",F47*G47,B47="Etapa","")} -> 376.71489 | I47: Sim
A48: =COUNTIFS($D$2:$D$3085,D48,$B$2:$B$3085,B48) -> 11 | B48: Insumo | C48: =IF(B48="serviço",D48,C47) -> Armazenamento de blocos* | D48: MADEIRA PINUS/SIMILAR - TABUA PINUS 200X20MM NBR 11700 | E48: =_xlfn.XLOOKUP(D48,Insumos!$B$1:$B$764,Insumos!$C$1:$C$764) -> M2 | F48: 0.591 | G48: =IF(B48="insumo",_xlfn.XLOOKUP($D48,Insumos!$B$1:$B$764,Insumos!$D$1:$D$764),"") -> 46.5 | H48: {=_xlfn.IFS(B48="Serviço",SUMIFS(H49:$H$3085,C49:$C$3085,$C48),B48="Insumo",F48*G48,B48="Etapa","")} -> 27.4815
A49: =COUNTIFS($D$2:$D$3085,D49,$B$2:$B$3085,B49) -> 10 | B49: Insumo | C49: =IF(B49="serviço",D49,C48) -> Armazenamento de blocos* | D49: COMPENSADO MADEIRA TIPO RESINADO COLA FENOLICA 2440X1220X10MM | E49: =_xlfn.XLOOKUP(D49,Insumos!$B$1:$B$764,Insumos!$C$1:$C$764) -> UN | F49: 0.404 | G49: =IF(B49="insumo",_xlfn.XLOOKUP($D49,Insumos!$B$1:$B$764,Insumos!$D$1:$D$764),"") -> 58.46 | H49: {=_xlfn.IFS(B49="Serviço",SUMIFS(H50:$H$3085,C50:$C$3085,$C49),B49="Insumo",F49*G49,B49="Etapa","")} -> 23.61784
A50: =COUNTIFS($D$2:$D$3085,D50,$B$2:$B$3085,B50) -> 24 | B50: Insumo | C50: =IF(B50="serviço",D50,C49) -> Armazenamento de blocos* | D50: MADEIRA PINUS/SIMILAR - PONTALETE 75X75MM NBR 11700/15696 | E50: =_xlfn.XLOOKUP(D50,Insumos!$B$1:$B$764,Insumos!$C$1:$C$764) -> M | F50: 4.39 | G50: =IF(B50="insumo",_xlfn.XLOOKUP($D50,Insumos!$B$1:$B$764,Insumos!$D$1:$D$764),"") -> 7 | H50: {=_xlfn.IFS(B50="Serviço",SUMIFS(H51:$H$3085,C51:$C$3085,$C50),B50="Insumo",F50*G50,B50="Etapa","")} -> 30.73
A51: =COUNTIFS($D$2:$D$3085,D51,$B$2:$B$3085,B51) -> 11 | B51: Insumo | C51: =IF(B51="serviço",D51,C50) -> Armazenamento de blocos* | D51: MADEIRA PINUS/SIMILAR - SARRAFO PINUS 50X20MM NBR 11700/15696 | E51: =_xlfn.XLOOKUP(D51,Insumos!$B$1:$B$764,Insumos!$C$1:$C$764) -> M2 | F51: 0.15 | G51: =IF(B51="insumo",_xlfn.XLOOKUP($D51,Insumos!$B$1:$B$764,Insumos!$D$1:$D$764),"") -> 46.5 | H51: {=_xlfn.IFS(B51="Serviço",SUMIFS(H52:$H$3085,C52:$C$3085,$C51),B51="Insumo",F51*G51,B51="Etapa","")} -> 6.975
A52: =COUNTIFS($D$2:$D$3085,D52,$B$2:$B$3085,B52) -> 10 | B52: Insumo | C52: =IF(B52="serviço",D52,C51) -> Armazenamento de blocos* | D52: MADEIRA PINUS/SIMILAR - SARRAFO PINUS 50X10MM NBR 11700 | E52: =_xlfn.XLOOKUP(D52,Insumos!$B$1:$B$764,Insumos!$C$1:$C$764) -> M | F52: 1 | G52: =IF(B52="insumo",_xlfn.XLOOKUP($D52,Insumos!$B$1:$B$764,Insumos!$D$1:$D$764),"") -> 2 | H52: {=_xlfn.IFS(B52="Serviço",SUMIFS(H53:$H$3085,C53:$C$3085,$C52),B52="Insumo",F52*G52,B52="Etapa","")} -> 2
A53: =COUNTIFS($D$2:$D$3085,D53,$B$2:$B$3085,B53) -> 36 | B53: Insumo | C53: =IF(B53="serviço",D53,C52) -> Armazenamento de blocos* | D53: PREGO DE ACO POLIDO COM CABECA 17 X 21 (2 X 11) | E53: =_xlfn.XLOOKUP(D53,Insumos!$B$1:$B$764,Insumos!$C$1:$C$764) -> KG | F53: 1 | G53: =IF(B53="insumo",_xlfn.XLOOKUP($D53,Insumos!$B$1:$B$764,Insumos!$D$1:$D$764),"") -> 18.13 | H53: {=_xlfn.IFS(B53="Serviço",SUMIFS(H54:$H$3085,C54:$C$3085,$C53),B53="Insumo",F53*G53,B53="Etapa","")} -> 18.13
A54: =COUNTIFS($D$2:$D$3085,D54,$B$2:$B$3085,B54) -> 10 | B54: Insumo | C54: =IF(B54="serviço",D54,C53) -> Armazenamento de blocos* | D54: EXTINTOR INCENDIO PO QUIMICO 06KG CLASSE ABC (COMPLETO) NBR 15808 | E54: =_xlfn.XLOOKUP(D54,Insumos!$B$1:$B$764,Insumos!$C$1:$C$764) -> UN | F54: 0.015 | G54: =IF(B54="insumo",_xlfn.XLOOKUP($D54,Insumos!$B$1:$B$764,Insumos!$D$1:$D$764),"") -> 185.37 | H54: {=_xlfn.IFS(B54="Serviço",SUMIFS(H55:$H$3085,C55:$C$3085,$C54),B54="Insumo",F54*G54,B54="Etapa","")} -> 2.78055
A55: =COUNTIFS($D$2:$D$3085,D55,$B$2:$B$3085,B55) -> 10 | B55: Insumo | C55: =IF(B55="serviço",D55,C54) -> Armazenamento de blocos* | D55: MATERIAL PARA INSTALAÇÃO ELÉTRICA | E55: =_xlfn.XLOOKUP(D55,Insumos!$B$1:$B$764,Insumos!$C$1:$C$764) -> VB | F55: 1 | G55: =IF(B55="insumo",_xlfn.XLOOKUP($D55,Insumos!$B$1:$B$764,Insumos!$D$1:$D$764),"") -> 215 | H55: {=_xlfn.IFS(B55="Serviço",SUMIFS(H56:$H$3085,C56:$C$3085,$C55),B55="Insumo",F55*G55,B55="Etapa","")} -> 215
A56: =COUNTIFS($D$2:$D$3085,D56,$B$2:$B$3085,B56) -> 10 | B56: Insumo | C56: =IF(B56="serviço",D56,C55) -> Armazenamento de blocos* | D56: SERVICO INSTALAÇÃO BARRACAO ALMOXARIFADO | E56: =_xlfn.XLOOKUP(D56,Insumos!$B$1:$B$764,Insumos!$C$1:$C$764) -> M2 | F56: 1 | G56: =IF(B56="insumo",_xlfn.XLOOKUP($D56,Insumos!$B$1:$B$764,Insumos!$D$1:$D$764),"") -> 50 | H56: {=_xlfn.IFS(B56="Serviço",SUMIFS(H57:$H$3085,C57:$C$3085,$C56),B56="Insumo",F56*G56,B56="Etapa","")} -> 50
A57: =COUNTIFS($D$2:$D$3085,D57,$B$2:$B$3085,B57) -> 1 | B57: Serviço | C57: =IF(B57="serviço",D57,C56) -> Armazenamento de contramarcos* | D57: Armazenamento de contramarcos* | E57: M2 | G57: =IF(B57="insumo",_xlfn.XLOOKUP($D57,Insumos!$B$1:$B$764,Insumos!$D$1:$D$764),"") | H57: {=_xlfn.IFS(B57="Serviço",SUMIFS(H58:$H$3085,C58:$C$3085,$C57),B57="Insumo",F57*G57,B57="Etapa","")} -> 376.71489 | I57: Sim
A58: =COUNTIFS($D$2:$D$3085,D58,$B$2:$B$3085,B58) -> 11 | B58: Insumo | C58: =IF(B58="serviço",D58,C57) -> Armazenamento de contramarcos* | D58: MADEIRA PINUS/SIMILAR - TABUA PINUS 200X20MM NBR 11700 | E58: =_xlfn.XLOOKUP(D58,Insumos!$B$1:$B$764,Insumos!$C$1:$C$764) -> M2 | F58: 0.591 | G58: =IF(B58="insumo",_xlfn.XLOOKUP($D58,Insumos!$B$1:$B$764,Insumos!$D$1:$D$764),"") -> 46.5 | H58: {=_xlfn.IFS(B58="Serviço",SUMIFS(H59:$H$3085,C59:$C$3085,$C58),B58="Insumo",F58*G58,B58="Etapa","")} -> 27.4815
A59: =COUNTIFS($D$2:$D$3085,D59,$B$2:$B$3085,B59) -> 10 | B59: Insumo | C59: =IF(B59="serviço",D59,C58) -> Armazenamento de contramarcos* | D59: COMPENSADO MADEIRA TIPO RESINADO COLA FENOLICA 2440X1220X10MM | E59: =_xlfn.XLOOKUP(D59,Insumos!$B$1:$B$764,Insumos!$C$1:$C$764) -> UN | F59: 0.404 | G59: =IF(B59="insumo",_xlfn.XLOOKUP($D59,Insumos!$B$1:$B$764,Insumos!$D$1:$D$764),"") -> 58.46 | H59: {=_xlfn.IFS(B59="Serviço",SUMIFS(H60:$H$3085,C60:$C$3085,$C59),B59="Insumo",F59*G59,B59="Etapa","")} -> 23.61784
A60: =COUNTIFS($D$2:$D$3085,D60,$B$2:$B$3085,B60) -> 24 | B60: Insumo | C60: =IF(B60="serviço",D60,C59) -> Armazenamento de contramarcos* | D60: MADEIRA PINUS/SIMILAR - PONTALETE 75X75MM NBR 11700/15696 | E60: =_xlfn.XLOOKUP(D60,Insumos!$B$1:$B$764,Insumos!$C$1:$C$764) -> M | F60: 4.39 | G60: =IF(B60="insumo",_xlfn.XLOOKUP($D60,Insumos!$B$1:$B$764,Insumos!$D$1:$D$764),"") -> 7 | H60: {=_xlfn.IFS(B60="Serviço",SUMIFS(H61:$H$3085,C61:$C$3085,$C60),B60="Insumo",F60*G60,B60="Etapa","")} -> 30.73
A61: =COUNTIFS($D$2:$D$3085,D61,$B$2:$B$3085,B61) -> 11 | B61: Insumo | C61: =IF(B61="serviço",D61,C60) -> Armazenamento de contramarcos* | D61: MADEIRA PINUS/SIMILAR - SARRAFO PINUS 50X20MM NBR 11700/15696 | E61: =_xlfn.XLOOKUP(D61,Insumos!$B$1:$B$764,Insumos!$C$1:$C$764) -> M2 | F61: 0.15 | G61: =IF(B61="insumo",_xlfn.XLOOKUP($D61,Insumos!$B$1:$B$764,Insumos!$D$1:$D$764),"") -> 46.5 | H61: {=_xlfn.IFS(B61="Serviço",SUMIFS(H62:$H$3085,C62:$C$3085,$C61),B61="Insumo",F61*G61,B61="Etapa","")} -> 6.975
A62: =COUNTIFS($D$2:$D$3085,D62,$B$2:$B$3085,B62) -> 10 | B62: Insumo | C62: =IF(B62="serviço",D62,C61) -> Armazenamento de contramarcos* | D62: MADEIRA PINUS/SIMILAR - SARRAFO PINUS 50X10MM NBR 11700 | E62: =_xlfn.XLOOKUP(D62,Insumos!$B$1:$B$764,Insumos!$C$1:$C$764) -> M | F62: 1 | G62: =IF(B62="insumo",_xlfn.XLOOKUP($D62,Insumos!$B$1:$B$764,Insumos!$D$1:$D$764),"") -> 2 | H62: {=_xlfn.IFS(B62="Serviço",SUMIFS(H63:$H$3085,C63:$C$3085,$C62),B62="Insumo",F62*G62,B62="Etapa","")} -> 2
A63: =COUNTIFS($D$2:$D$3085,D63,$B$2:$B$3085,B63) -> 36 | B63: Insumo | C63: =IF(B63="serviço",D63,C62) -> Armazenamento de contramarcos* | D63: PREGO DE ACO POLIDO COM CABECA 17 X 21 (2 X 11) | E63: =_xlfn.XLOOKUP(D63,Insumos!$B$1:$B$764,Insumos!$C$1:$C$764) -> KG | F63: 1 | G63: =IF(B63="insumo",_xlfn.XLOOKUP($D63,Insumos!$B$1:$B$764,Insumos!$D$1:$D$764),"") -> 18.13 | H63: {=_xlfn.IFS(B63="Serviço",SUMIFS(H64:$H$3085,C64:$C$3085,$C63),B63="Insumo",F63*G63,B63="Etapa","")} -> 18.13
A64: =COUNTIFS($D$2:$D$3085,D64,$B$2:$B$3085,B64) -> 10 | B64: Insumo | C64: =IF(B64="serviço",D64,C63) -> Armazenamento de contramarcos* | D64: EXTINTOR INCENDIO PO QUIMICO 06KG CLASSE ABC (COMPLETO) NBR 15808 | E64: =_xlfn.XLOOKUP(D64,Insumos!$B$1:$B$764,Insumos!$C$1:$C$764) -> UN | F64: 0.015 | G64: =IF(B64="insumo",_xlfn.XLOOKUP($D64,Insumos!$B$1:$B$764,Insumos!$D$1:$D$764),"") -> 185.37 | H64: {=_xlfn.IFS(B64="Serviço",SUMIFS(H65:$H$3085,C65:$C$3085,$C64),B64="Insumo",F64*G64,B64="Etapa","")} -> 2.78055
A65: =COUNTIFS($D$2:$D$3085,D65,$B$2:$B$3085,B65) -> 10 | B65: Insumo | C65: =IF(B65="serviço",D65,C64) -> Armazenamento de contramarcos* | D65: MATERIAL PARA INSTALAÇÃO ELÉTRICA | E65: =_xlfn.XLOOKUP(D65,Insumos!$B$1:$B$764,Insumos!$C$1:$C$764) -> VB | F65: 1 | G65: =IF(B65="insumo",_xlfn.XLOOKUP($D65,Insumos!$B$1:$B$764,Insumos!$D$1:$D$764),"") -> 215 | H65: {=_xlfn.IFS(B65="Serviço",SUMIFS(H66:$H$3085,C66:$C$3085,$C65),B65="Insumo",F65*G65,B65="Etapa","")} -> 215
A66: =COUNTIFS($D$2:$D$3085,D66,$B$2:$B$3085,B66) -> 10 | B66: Insumo | C66: =IF(B66="serviço",D66,C65) -> Armazenamento de contramarcos* | D66: SERVICO INSTALAÇÃO BARRACAO ALMOXARIFADO | E66: =_xlfn.XLOOKUP(D66,Insumos!$B$1:$B$764,Insumos!$C$1:$C$764) -> M2 | F66: 1 | G66: =IF(B66="insumo",_xlfn.XLOOKUP($D66,Insumos!$B$1:$B$764,Insumos!$D$1:$D$764),"") -> 50 | H66: {=_xlfn.IFS(B66="Serviço",SUMIFS(H67:$H$3085,C67:$C$3085,$C66),B66="Insumo",F66*G66,B66="Etapa","")} -> 50
A67: =COUNTIFS($D$2:$D$3085,D67,$B$2:$B$3085,B67) -> 1 | B67: Serviço | C67: =IF(B67="serviço",D67,C66) -> Armazenamento de portas e rodapés* | D67: Armazenamento de portas e rodapés* | E67: M2 | G67: =IF(B67="insumo",_xlfn.XLOOKUP($D67,Insumos!$B$1:$B$764,Insumos!$D$1:$D$764),"") | H67: {=_xlfn.IFS(B67="Serviço",SUMIFS(H68:$H$3085,C68:$C$3085,$C67),B67="Insumo",F67*G67,B67="Etapa","")} -> 376.71489 | I67: Sim
A68: =COUNTIFS($D$2:$D$3085,D68,$B$2:$B$3085,B68) -> 11 | B68: Insumo | C68: =IF(B68="serviço",D68,C67) -> Armazenamento de portas e rodapés* | D68: MADEIRA PINUS/SIMILAR - TABUA PINUS 200X20MM NBR 11700 | E68: =_xlfn.XLOOKUP(D68,Insumos!$B$1:$B$764,Insumos!$C$1:$C$764) -> M2 | F68: 0.591 | G68: =IF(B68="insumo",_xlfn.XLOOKUP($D68,Insumos!$B$1:$B$764,Insumos!$D$1:$D$764),"") -> 46.5 | H68: {=_xlfn.IFS(B68="Serviço",SUMIFS(H69:$H$3085,C69:$C$3085,$C68),B68="Insumo",F68*G68,B68="Etapa","")} -> 27.4815
A69: =COUNTIFS($D$2:$D$3085,D69,$B$2:$B$3085,B69) -> 10 | B69: Insumo | C69: =IF(B69="serviço",D69,C68) -> Armazenamento de portas e rodapés* | D69: COMPENSADO MADEIRA TIPO RESINADO COLA FENOLICA 2440X1220X10MM | E69: =_xlfn.XLOOKUP(D69,Insumos!$B$1:$B$764,Insumos!$C$1:$C$764) -> UN | F69: 0.404 | G69: =IF(B69="insumo",_xlfn.XLOOKUP($D69,Insumos!$B$1:$B$764,Insumos!$D$1:$D$764),"") -> 58.46 | H69: {=_xlfn.IFS(B69="Serviço",SUMIFS(H70:$H$3085,C70:$C$3085,$C69),B69="Insumo",F69*G69,B69="Etapa","")} -> 23.61784
A70: =COUNTIFS($D$2:$D$3085,D70,$B$2:$B$3085,B70) -> 24 | B70: Insumo | C70: =IF(B70="serviço",D70,C69) -> Armazenamento de portas e rodapés* | D70: MADEIRA PINUS/SIMILAR - PONTALETE 75X75MM NBR 11700/15696 | E70: =_xlfn.XLOOKUP(D70,Insumos!$B$1:$B$764,Insumos!$C$1:$C$764) -> M | F70: 4.39 | G70: =IF(B70="insumo",_xlfn.XLOOKUP($D70,Insumos!$B$1:$B$764,Insumos!$D$1:$D$764),"") -> 7 | H70: {=_xlfn.IFS(B70="Serviço",SUMIFS(H71:$H$3085,C71:$C$3085,$C70),B70="Insumo",F70*G70,B70="Etapa","")} -> 30.73
A71: =COUNTIFS($D$2:$D$3085,D71,$B$2:$B$3085,B71) -> 11 | B71: Insumo | C71: =IF(B71="serviço",D71,C70) -> Armazenamento de portas e rodapés* | D71: MADEIRA PINUS/SIMILAR - SARRAFO PINUS 50X20MM NBR 11700/15696 | E71: =_xlfn.XLOOKUP(D71,Insumos!$B$1:$B$764,Insumos!$C$1:$C$764) -> M2 | F71: 0.15 | G71: =IF(B71="insumo",_xlfn.XLOOKUP($D71,Insumos!$B$1:$B$764,Insumos!$D$1:$D$764),"") -> 46.5 | H71: {=_xlfn.IFS(B71="Serviço",SUMIFS(H72:$H$3085,C72:$C$3085,$C71),B71="Insumo",F71*G71,B71="Etapa","")} -> 6.975
A72: =COUNTIFS($D$2:$D$3085,D72,$B$2:$B$3085,B72) -> 10 | B72: Insumo | C72: =IF(B72="serviço",D72,C71) -> Armazenamento de portas e rodapés* | D72: MADEIRA PINUS/SIMILAR - SARRAFO PINUS 50X10MM NBR 11700 | E72: =_xlfn.XLOOKUP(D72,Insumos!$B$1:$B$764,Insumos!$C$1:$C$764) -> M | F72: 1 | G72: =IF(B72="insumo",_xlfn.XLOOKUP($D72,Insumos!$B$1:$B$764,Insumos!$D$1:$D$764),"") -> 2 | H72: {=_xlfn.IFS(B72="Serviço",SUMIFS(H73:$H$3085,C73:$C$3085,$C72),B72="Insumo",F72*G72,B72="Etapa","")} -> 2
A73: =COUNTIFS($D$2:$D$3085,D73,$B$2:$B$3085,B73) -> 36 | B73: Insumo | C73: =IF(B73="serviço",D73,C72) -> Armazenamento de portas e rodapés* | D73: PREGO DE ACO POLIDO COM CABECA 17 X 21 (2 X 11) | E73: =_xlfn.XLOOKUP(D73,Insumos!$B$1:$B$764,Insumos!$C$1:$C$764) -> KG | F73: 1 | G73: =IF(B73="insumo",_xlfn.XLOOKUP($D73,Insumos!$B$1:$B$764,Insumos!$D$1:$D$764),"") -> 18.13 | H73: {=_xlfn.IFS(B73="Serviço",SUMIFS(H74:$H$3085,C74:$C$3085,$C73),B73="Insumo",F73*G73,B73="Etapa","")} -> 18.13
A74: =COUNTIFS($D$2:$D$3085,D74,$B$2:$B$3085,B74) -> 10 | B74: Insumo | C74: =IF(B74="serviço",D74,C73) -> Armazenamento de portas e rodapés* | D74: EXTINTOR INCENDIO PO QUIMICO 06KG CLASSE ABC (COMPLETO) NBR 15808 | E74: =_xlfn.XLOOKUP(D74,Insumos!$B$1:$B$764,Insumos!$C$1:$C$764) -> UN | F74: 0.015 | G74: =IF(B74="insumo",_xlfn.XLOOKUP($D74,Insumos!$B$1:$B$764,Insumos!$D$1:$D$764),"") -> 185.37 | H74: {=_xlfn.IFS(B74="Serviço",SUMIFS(H75:$H$3085,C75:$C$3085,$C74),B74="Insumo",F74*G74,B74="Etapa","")} -> 2.78055
A75: =COUNTIFS($D$2:$D$3085,D75,$B$2:$B$3085,B75) -> 10 | B75: Insumo | C75: =IF(B75="serviço",D75,C74) -> Armazenamento de portas e rodapés* | D75: MATERIAL PARA INSTALAÇÃO ELÉTRICA | E75: =_xlfn.XLOOKUP(D75,Insumos!$B$1:$B$764,Insumos!$C$1:$C$764) -> VB | F75: 1 | G75: =IF(B75="insumo",_xlfn.XLOOKUP($D75,Insumos!$B$1:$B$764,Insumos!$D$1:$D$764),"") -> 215 | H75: {=_xlfn.IFS(B75="Serviço",SUMIFS(H76:$H$3085,C76:$C$3085,$C75),B75="Insumo",F75*G75,B75="Etapa","")} -> 215
A76: =COUNTIFS($D$2:$D$3085,D76,$B$2:$B$3085,B76) -> 10 | B76: Insumo | C76: =IF(B76="serviço",D76,C75) -> Armazenamento de portas e rodapés* | D76: SERVICO INSTALAÇÃO BARRACAO ALMOXARIFADO | E76: =_xlfn.XLOOKUP(D76,Insumos!$B$1:$B$764,Insumos!$C$1:$C$764) -> M2 | F76: 1 | G76: =IF(B76="insumo",_xlfn.XLOOKUP($D76,Insumos!$B$1:$B$764,Insumos!$D$1:$D$764),"") -> 50 | H76: {=_xlfn.IFS(B76="Serviço",SUMIFS(H77:$H$3085,C77:$C$3085,$C76),B76="Insumo",F76*G76,B76="Etapa","")} -> 50
A77: =COUNTIFS($D$2:$D$3085,D77,$B$2:$B$3085,B77) -> 1 | B77: Serviço | C77: =IF(B77="serviço",D77,C76) -> Armazenamento de esquadrias* | D77: Armazenamento de esquadrias* | E77: M2 | G77: =IF(B77="insumo",_xlfn.XLOOKUP($D77,Insumos!$B$1:$B$764,Insumos!$D$1:$D$764),"") | H77: {=_xlfn.IFS(B77="Serviço",SUMIFS(H78:$H$3085,C78:$C$3085,$C77),B77="Insumo",F77*G77,B77="Etapa","")} -> 376.71489 | I77: Sim
A78: =COUNTIFS($D$2:$D$3085,D78,$B$2:$B$3085,B78) -> 11 | B78: Insumo | C78: =IF(B78="serviço",D78,C77) -> Armazenamento de esquadrias* | D78: MADEIRA PINUS/SIMILAR - TABUA PINUS 200X20MM NBR 11700 | E78: =_xlfn.XLOOKUP(D78,Insumos!$B$1:$B$764,Insumos!$C$1:$C$764) -> M2 | F78: 0.591 | G78: =IF(B78="insumo",_xlfn.XLOOKUP($D78,Insumos!$B$1:$B$764,Insumos!$D$1:$D$764),"") -> 46.5 | H78: {=_xlfn.IFS(B78="Serviço",SUMIFS(H79:$H$3085,C79:$C$3085,$C78),B78="Insumo",F78*G78,B78="Etapa","")} -> 27.4815
A79: =COUNTIFS($D$2:$D$3085,D79,$B$2:$B$3085,B79) -> 10 | B79: Insumo | C79: =IF(B79="serviço",D79,C78) -> Armazenamento de esquadrias* | D79: COMPENSADO MADEIRA TIPO RESINADO COLA FENOLICA 2440X1220X10MM | E79: =_xlfn.XLOOKUP(D79,Insumos!$B$1:$B$764,Insumos!$C$1:$C$764) -> UN | F79: 0.404 | G79: =IF(B79="insumo",_xlfn.XLOOKUP($D79,Insumos!$B$1:$B$764,Insumos!$D$1:$D$764),"") -> 58.46 | H79: {=_xlfn.IFS(B79="Serviço",SUMIFS(H80:$H$3085,C80:$C$3085,$C79),B79="Insumo",F79*G79,B79="Etapa","")} -> 23.61784
A80: =COUNTIFS($D$2:$D$3085,D80,$B$2:$B$3085,B80) -> 24 | B80: Insumo | C80: =IF(B80="serviço",D80,C79) -> Armazenamento de esquadrias* | D80: MADEIRA PINUS/SIMILAR - PONTALETE 75X75MM NBR 11700/15696 | E80: =_xlfn.XLOOKUP(D80,Insumos!$B$1:$B$764,Insumos!$C$1:$C$764) -> M | F80: 4.39 | G80: =IF(B80="insumo",_xlfn.XLOOKUP($D80,Insumos!$B$1:$B$764,Insumos!$D$1:$D$764),"") -> 7 | H80: {=_xlfn.IFS(B80="Serviço",SUMIFS(H81:$H$3085,C81:$C$3085,$C80),B80="Insumo",F80*G80,B80="Etapa","")} -> 30.73
A81: =COUNTIFS($D$2:$D$3085,D81,$B$2:$B$3085,B81) -> 11 | B81: Insumo | C81: =IF(B81="serviço",D81,C80) -> Armazenamento de esquadrias* | D81: MADEIRA PINUS/SIMILAR - SARRAFO PINUS 50X20MM NBR 11700/15696 | E81: =_xlfn.XLOOKUP(D81,Insumos!$B$1:$B$764,Insumos!$C$1:$C$764) -> M2 | F81: 0.15 | G81: =IF(B81="insumo",_xlfn.XLOOKUP($D81,Insumos!$B$1:$B$764,Insumos!$D$1:$D$764),"") -> 46.5 | H81: {=_xlfn.IFS(B81="Serviço",SUMIFS(H82:$H$3085,C82:$C$3085,$C81),B81="Insumo",F81*G81,B81="Etapa","")} -> 6.975
A82: =COUNTIFS($D$2:$D$3085,D82,$B$2:$B$3085,B82) -> 10 | B82: Insumo | C82: =IF(B82="serviço",D82,C81) -> Armazenamento de esquadrias* | D82: MADEIRA PINUS/SIMILAR - SARRAFO PINUS 50X10MM NBR 11700 | E82: =_xlfn.XLOOKUP(D82,Insumos!$B$1:$B$764,Insumos!$C$1:$C$764) -> M | F82: 1 | G82: =IF(B82="insumo",_xlfn.XLOOKUP($D82,Insumos!$B$1:$B$764,Insumos!$D$1:$D$764),"") -> 2 | H82: {=_xlfn.IFS(B82="Serviço",SUMIFS(H83:$H$3085,C83:$C$3085,$C82),B82="Insumo",F82*G82,B82="Etapa","")} -> 2
A83: =COUNTIFS($D$2:$D$3085,D83,$B$2:$B$3085,B83) -> 36 | B83: Insumo | C83: =IF(B83="serviço",D83,C82) -> Armazenamento de esquadrias* | D83: PREGO DE ACO POLIDO COM CABECA 17 X 21 (2 X 11) | E83: =_xlfn.XLOOKUP(D83,Insumos!$B$1:$B$764,Insumos!$C$1:$C$764) -> KG | F83: 1 | G83: =IF(B83="insumo",_xlfn.XLOOKUP($D83,Insumos!$B$1:$B$764,Insumos!$D$1:$D$764),"") -> 18.13 | H83: {=_xlfn.IFS(B83="Serviço",SUMIFS(H84:$H$3085,C84:$C$3085,$C83),B83="Insumo",F83*G83,B83="Etapa","")} -> 18.13
A84: =COUNTIFS($D$2:$D$3085,D84,$B$2:$B$3085,B84) -> 10 | B84: Insumo | C84: =IF(B84="serviço",D84,C83) -> Armazenamento de esquadrias* | D84: EXTINTOR INCENDIO PO QUIMICO 06KG CLASSE ABC (COMPLETO) NBR 15808 | E84: =_xlfn.XLOOKUP(D84,Insumos!$B$1:$B$764,Insumos!$C$1:$C$764) -> UN | F84: 0.015 | G84: =IF(B84="insumo",_xlfn.XLOOKUP($D84,Insumos!$B$1:$B$764,Insumos!$D$1:$D$764),"") -> 185.37 | H84: {=_xlfn.IFS(B84="Serviço",SUMIFS(H85:$H$3085,C85:$C$3085,$C84),B84="Insumo",F84*G84,B84="Etapa","")} -> 2.78055
A85: =COUNTIFS($D$2:$D$3085,D85,$B$2:$B$3085,B85) -> 10 | B85: Insumo | C85: =IF(B85="serviço",D85,C84) -> Armazenamento de esquadrias* | D85: MATERIAL PARA INSTALAÇÃO ELÉTRICA | E85: =_xlfn.XLOOKUP(D85,Insumos!$B$1:$B$764,Insumos!$C$1:$C$764) -> VB | F85: 1 | G85: =IF(B85="insumo",_xlfn.XLOOKUP($D85,Insumos!$B$1:$B$764,Insumos!$D$1:$D$764),"") -> 215 | H85: {=_xlfn.IFS(B85="Serviço",SUMIFS(H86:$H$3085,C86:$C$3085,$C85),B85="Insumo",F85*G85,B85="Etapa","")} -> 215
A86: =COUNTIFS($D$2:$D$3085,D86,$B$2:$B$3085,B86) -> 10 | B86: Insumo | C86: =IF(B86="serviço",D86,C85) -> Armazenamento de esquadrias* | D86: SERVICO INSTALAÇÃO BARRACAO ALMOXARIFADO | E86: =_xlfn.XLOOKUP(D86,Insumos!$B$1:$B$764,Insumos!$C$1:$C$764) -> M2 | F86: 1 | G86: =IF(B86="insumo",_xlfn.XLOOKUP($D86,Insumos!$B$1:$B$764,Insumos!$D$1:$D$764),"") -> 50 | H86: {=_xlfn.IFS(B86="Serviço",SUMIFS(H87:$H$3085,C87:$C$3085,$C86),B86="Insumo",F86*G86,B86="Etapa","")} -> 50
A87: =COUNTIFS($D$2:$D$3085,D87,$B$2:$B$3085,B87) -> 1 | B87: Serviço | C87: =IF(B87="serviço",D87,C86) -> Armazenamento de instalações complementares* | D87: Armazenamento de instalações complementares* | E87: M2 | G87: =IF(B87="insumo",_xlfn.XLOOKUP($D87,Insumos!$B$1:$B$764,Insumos!$D$1:$D$764),"") | H87: {=_xlfn.IFS(B87="Serviço",SUMIFS(H88:$H$3085,C88:$C$3085,$C87),B87="Insumo",F87*G87,B87="Etapa","")} -> 376.71489 | I87: Sim
A88: =COUNTIFS($D$2:$D$3085,D88,$B$2:$B$3085,B88) -> 11 | B88: Insumo | C88: =IF(B88="serviço",D88,C87) -> Armazenamento de instalações complementares* | D88: MADEIRA PINUS/SIMILAR - TABUA PINUS 200X20MM NBR 11700 | E88: =_xlfn.XLOOKUP(D88,Insumos!$B$1:$B$764,Insumos!$C$1:$C$764) -> M2 | F88: 0.591 | G88: =IF(B88="insumo",_xlfn.XLOOKUP($D88,Insumos!$B$1:$B$764,Insumos!$D$1:$D$764),"") -> 46.5 | H88: {=_xlfn.IFS(B88="Serviço",SUMIFS(H89:$H$3085,C89:$C$3085,$C88),B88="Insumo",F88*G88,B88="Etapa","")} -> 27.4815
A89: =COUNTIFS($D$2:$D$3085,D89,$B$2:$B$3085,B89) -> 10 | B89: Insumo | C89: =IF(B89="serviço",D89,C88) -> Armazenamento de instalações complementares* | D89: COMPENSADO MADEIRA TIPO RESINADO COLA FENOLICA 2440X1220X10MM | E89: =_xlfn.XLOOKUP(D89,Insumos!$B$1:$B$764,Insumos!$C$1:$C$764) -> UN | F89: 0.404 | G89: =IF(B89="insumo",_xlfn.XLOOKUP($D89,Insumos!$B$1:$B$764,Insumos!$D$1:$D$764),"") -> 58.46 | H89: {=_xlfn.IFS(B89="Serviço",SUMIFS(H90:$H$3085,C90:$C$3085,$C89),B89="Insumo",F89*G89,B89="Etapa","")} -> 23.61784
A90: =COUNTIFS($D$2:$D$3085,D90,$B$2:$B$3085,B90) -> 24 | B90: Insumo | C90: =IF(B90="serviço",D90,C89) -> Armazenamento de instalações complementares* | D90: MADEIRA PINUS/SIMILAR - PONTALETE 75X75MM NBR 11700/15696 | E90: =_xlfn.XLOOKUP(D90,Insumos!$B$1:$B$764,Insumos!$C$1:$C$764) -> M | F90: 4.39 | G90: =IF(B90="insumo",_xlfn.XLOOKUP($D90,Insumos!$B$1:$B$764,Insumos!$D$1:$D$764),"") -> 7 | H90: {=_xlfn.IFS(B90="Serviço",SUMIFS(H91:$H$3085,C91:$C$3085,$C90),B90="Insumo",F90*G90,B90="Etapa","")} -> 30.73
A91: =COUNTIFS($D$2:$D$3085,D91,$B$2:$B$3085,B91) -> 11 | B91: Insumo | C91: =IF(B91="serviço",D91,C90) -> Armazenamento de instalações complementares* | D91: MADEIRA PINUS/SIMILAR - SARRAFO PINUS 50X20MM NBR 11700/15696 | E91: =_xlfn.XLOOKUP(D91,Insumos!$B$1:$B$764,Insumos!$C$1:$C$764) -> M2 | F91: 0.15 | G91: =IF(B91="insumo",_xlfn.XLOOKUP($D91,Insumos!$B$1:$B$764,Insumos!$D$1:$D$764),"") -> 46.5 | H91: {=_xlfn.IFS(B91="Serviço",SUMIFS(H92:$H$3085,C92:$C$3085,$C91),B91="Insumo",F91*G91,B91="Etapa","")} -> 6.975
A92: =COUNTIFS($D$2:$D$3085,D92,$B$2:$B$3085,B92) -> 10 | B92: Insumo | C92: =IF(B92="serviço",D92,C91) -> Armazenamento de instalações complementares* | D92: MADEIRA PINUS/SIMILAR - SARRAFO PINUS 50X10MM NBR 11700 | E92: =_xlfn.XLOOKUP(D92,Insumos!$B$1:$B$764,Insumos!$C$1:$C$764) -> M | F92: 1 | G92: =IF(B92="insumo",_xlfn.XLOOKUP($D92,Insumos!$B$1:$B$764,Insumos!$D$1:$D$764),"") -> 2 | H92: {=_xlfn.IFS(B92="Serviço",SUMIFS(H93:$H$3085,C93:$C$3085,$C92),B92="Insumo",F92*G92,B92="Etapa","")} -> 2
A93: =COUNTIFS($D$2:$D$3085,D93,$B$2:$B$3085,B93) -> 36 | B93: Insumo | C93: =IF(B93="serviço",D93,C92) -> Armazenamento de instalações complementares* | D93: PREGO DE ACO POLIDO COM CABECA 17 X 21 (2 X 11) | E93: =_xlfn.XLOOKUP(D93,Insumos!$B$1:$B$764,Insumos!$C$1:$C$764) -> KG | F93: 1 | G93: =IF(B93="insumo",_xlfn.XLOOKUP($D93,Insumos!$B$1:$B$764,Insumos!$D$1:$D$764),"") -> 18.13 | H93: {=_xlfn.IFS(B93="Serviço",SUMIFS(H94:$H$3085,C94:$C$3085,$C93),B93="Insumo",F93*G93,B93="Etapa","")} -> 18.13
A94: =COUNTIFS($D$2:$D$3085,D94,$B$2:$B$3085,B94) -> 10 | B94: Insumo | C94: =IF(B94="serviço",D94,C93) -> Armazenamento de instalações complementares* | D94: EXTINTOR INCENDIO PO QUIMICO 06KG CLASSE ABC (COMPLETO) NBR 15808 | E94: =_xlfn.XLOOKUP(D94,Insumos!$B$1:$B$764,Insumos!$C$1:$C$764) -> UN | F94: 0.015 | G94: =IF(B94="insumo",_xlfn.XLOOKUP($D94,Insumos!$B$1:$B$764,Insumos!$D$1:$D$764),"") -> 185.37 | H94: {=_xlfn.IFS(B94="Serviço",SUMIFS(H95:$H$3085,C95:$C$3085,$C94),B94="Insumo",F94*G94,B94="Etapa","")} -> 2.78055
A95: =COUNTIFS($D$2:$D$3085,D95,$B$2:$B$3085,B95) -> 10 | B95: Insumo | C95: =IF(B95="serviço",D95,C94) -> Armazenamento de instalações complementares* | D95: MATERIAL PARA INSTALAÇÃO ELÉTRICA | E95: =_xlfn.XLOOKUP(D95,Insumos!$B$1:$B$764,Insumos!$C$1:$C$764) -> VB | F95: 1 | G95: =IF(B95="insumo",_xlfn.XLOOKUP($D95,Insumos!$B$1:$B$764,Insumos!$D$1:$D$764),"") -> 215 | H95: {=_xlfn.IFS(B95="Serviço",SUMIFS(H96:$H$3085,C96:$C$3085,$C95),B95="Insumo",F95*G95,B95="Etapa","")} -> 215
A96: =COUNTIFS($D$2:$D$3085,D96,$B$2:$B$3085,B96) -> 10 | B96: Insumo | C96: =IF(B96="serviço",D96,C95) -> Armazenamento de instalações complementares* | D96: SERVICO INSTALAÇÃO BARRACAO ALMOXARIFADO | E96: =_xlfn.XLOOKUP(D96,Insumos!$B$1:$B$764,Insumos!$C$1:$C$764) -> M2 | F96: 1 | G96: =IF(B96="insumo",_xlfn.XLOOKUP($D96,Insumos!$B$1:$B$764,Insumos!$D$1:$D$764),"") -> 50 | H96: {=_xlfn.IFS(B96="Serviço",SUMIFS(H97:$H$3085,C97:$C$3085,$C96),B96="Insumo",F96*G96,B96="Etapa","")} -> 50
A97: =COUNTIFS($D$2:$D$3085,D97,$B$2:$B$3085,B97) -> 1 | B97: Serviço | C97: =IF(B97="serviço",D97,C96) -> Armazenamento para estoque geral* | D97: Armazenamento para estoque geral* | E97: M2 | G97: =IF(B97="insumo",_xlfn.XLOOKUP($D97,Insumos!$B$1:$B$764,Insumos!$D$1:$D$764),"") | H97: {=_xlfn.IFS(B97="Serviço",SUMIFS(H98:$H$3085,C98:$C$3085,$C97),B97="Insumo",F97*G97,B97="Etapa","")} -> 376.71489 | I97: Sim
A98: =COUNTIFS($D$2:$D$3085,D98,$B$2:$B$3085,B98) -> 11 | B98: Insumo | C98: =IF(B98="serviço",D98,C97) -> Armazenamento para estoque geral* | D98: MADEIRA PINUS/SIMILAR - TABUA PINUS 200X20MM NBR 11700 | E98: =_xlfn.XLOOKUP(D98,Insumos!$B$1:$B$764,Insumos!$C$1:$C$764) -> M2 | F98: 0.591 | G98: =IF(B98="insumo",_xlfn.XLOOKUP($D98,Insumos!$B$1:$B$764,Insumos!$D$1:$D$764),"") -> 46.5 | H98: {=_xlfn.IFS(B98="Serviço",SUMIFS(H99:$H$3085,C99:$C$3085,$C98),B98="Insumo",F98*G98,B98="Etapa","")} -> 27.4815
A99: =COUNTIFS($D$2:$D$3085,D99,$B$2:$B$3085,B99) -> 10 | B99: Insumo | C99: =IF(B99="serviço",D99,C98) -> Armazenamento para estoque geral* | D99: COMPENSADO MADEIRA TIPO RESINADO COLA FENOLICA 2440X1220X10MM | E99: =_xlfn.XLOOKUP(D99,Insumos!$B$1:$B$764,Insumos!$C$1:$C$764) -> UN | F99: 0.404 | G99: =IF(B99="insumo",_xlfn.XLOOKUP($D99,Insumos!$B$1:$B$764,Insumos!$D$1:$D$764),"") -> 58.46 | H99: {=_xlfn.IFS(B99="Serviço",SUMIFS(H100:$H$3085,C100:$C$3085,$C99),B99="Insumo",F99*G99,B99="Etapa","")} -> 23.61784
A100: =COUNTIFS($D$2:$D$3085,D100,$B$2:$B$3085,B100) -> 24 | B100: Insumo | C100: =IF(B100="serviço",D100,C99) -> Armazenamento para estoque geral* | D100: MADEIRA PINUS/SIMILAR - PONTALETE 75X75MM NBR 11700/15696 | E100: =_xlfn.XLOOKUP(D100,Insumos!$B$1:$B$764,Insumos!$C$1:$C$764) -> M | F100: 4.39 | G100: =IF(B100="insumo",_xlfn.XLOOKUP($D100,Insumos!$B$1:$B$764,Insumos!$D$1:$D$764),"") -> 7 | H100: {=_xlfn.IFS(B100="Serviço",SUMIFS(H101:$H$3085,C101:$C$3085,$C100),B100="Insumo",F100*G100,B100="Etapa","")} -> 30.73
...

Sheet Insumos
A1: Repetição | B1: Descrição | C1: Und | D1: 1 | E1: Custo Unitário | F1: Grupo insumo | G1: Sub Grupo | H1: Observações | I1: Grupo Sienge
A2: =COUNTIFS($B$2:$B$764,B2) -> 1 | B2: Arame Galvanizado | C2: KG | D2: =E2*$D$1 -> 13.69 | E2: 13.69 | F2: Aço | G2: Arame | I2: Armadura
A3: =COUNTIFS($B$2:$B$764,B3) -> 1 | B3: Arame Recozido BWG 18 | C3: KG | D3: =E3*$D$1 -> 16.71 | E3: 16.71 | F3: Aço | G3: Arame | I3: Armadura
A4: =COUNTIFS($B$2:$B$764,B4) -> 1 | B4: Barras de transferencia lisa 12,5mm 50 cm | C4: pc | D4: =E4*$D$1 -> 3.82 | E4: 3.82 | F4: Aço | G4: Barra de Aço CA50 / CA60 | I4: Armadura
A5: =COUNTIFS($B$2:$B$764,B5) -> 1 | B5: Monocordoalha engraxada CP - 190 RB (12,7mm) | C5: KG | D5: =E5*$D$1 -> 15.5 | E5: 15.5 | F5: Aço | G5: Barra de Aço CA50 / CA60 | I5: Armadura
A6: =COUNTIFS($B$2:$B$764,B6) -> 1 | B6: Armação aço Média para estaca (Corte e Dobra em Obra) | C6: KG | D6: =E6*$D$1 -> 7.6873385 | E6: 7.6873385 | F6: Aço | G6: Barra de Aço CA50 / CA60 | I6: Armadura
A7: =COUNTIFS($B$2:$B$764,B7) -> 1 | B7: Armação aço Média para estaca (Corte e Dobra em Indústria) | C7: KG | D7: =E7*$D$1 -> 8.2873385 | E7: 8.2873385 | F7: Aço | G7: Barra de Aço CA50 / CA60 | I7: Armadura
A8: =COUNTIFS($B$2:$B$764,B8) -> 1 | B8: CORTE E DOBRA ARMADO ESTACA Ø50CM 5F 16,0 4MTS ESP75 PS20 | C8: KG | D8: =E8*$D$1 -> 302.922 | E8: 302.922 | F8: Aço | G8: Barra de Aço CA50 / CA60 | I8: Armadura
A9: =COUNTIFS($B$2:$B$764,B9) -> 1 | B9: CORTE E DOBRA ARMADO ESTACA Ø60CM 5F 20,0 4MTS ESP75 PS20 | C9: KG | D9: =E9*$D$1 -> 466.337 | E9: 466.337 | F9: Aço | G9: Barra de Aço CA50 / CA60 | I9: Armadura
A10: =COUNTIFS($B$2:$B$764,B10) -> 1 | B10: CORTE E DOBRA ARMADO ESTACA Ø60CM 7F 20,0 6MTS ESP75 PS20 | C10: KG | D10: =E10*$D$1 -> 937.639 | E10: 937.639 | F10: Aço | G10: Barra de Aço CA50 / CA60 | I10: Armadura
A11: =COUNTIFS($B$2:$B$764,B11) -> 1 | B11: CORTE E DOBRA ARMADO ESTACA Ø60CM 9F 20,0 8MTS ESP75 PS20 | C11: KG | D11: =E11*$D$1 -> 1609.666 | E11: 1609.666 | F11: Aço | G11: Barra de Aço CA50 / CA60 | I11: Armadura
A12: =COUNTIFS($B$2:$B$764,B12) -> 1 | B12: Aço CA50 10,0 mm | C12: KG | D12: =E12*$D$1 -> 5.76 | E12: 5.76 | F12: Aço | G12: Barra de Aço CA50 / CA60 | I12: Armadura
A13: =COUNTIFS($B$2:$B$764,B13) -> 1 | B13: Aço CA50 12,5 mm | C13: KG | D13: =E13*$D$1 -> 5.59 | E13: 5.59 | F13: Aço | G13: Barra de Aço CA50 / CA60 | I13: Armadura
... A24: =COUNTIFS($B$2:$B$764,B24) -> 1 | B24: TELA ACO CARBONO CA60 M.150X150MM F.04,2MM 245X600CM Q92 (21,8KG/UN) | C24: KG | D24: =E24*$D$1 -> 4.88 | E24: 4.88 | F24: Aço | G24: Tela de Aço CA60 | I24: Armadura
A25: =COUNTIFS($B$2:$B$764,B25) -> 1 | B25: TELA ACO CARBONO CA60 M.100X100MM F.04,2MM 245X600CM Q113 (26,46KG/UN) | C25: KG | D25: =E25*$D$1 -> 8.537037 | E25: =225.89/26.46 -> 8.537037 | F25: Aço | G25: Tela de Aço CA60 | I25: Armadura
A26: =COUNTIFS($B$2:$B$764,B26) -> 1 | B26: TELA ACO CARBONO CA60 M.100X100MM F.04,2MM 245X600CM Q138 (32,34KG/UN) | C26: KG | D26: =E26*$D$1 -> 9.1447124 | E26: 9.1447124 | F26: Aço | G26: Tela de Aço CA60 | I26: Armadura
A27: =COUNTIFS($B$2:$B$764,B27) -> 1 | B27: TELA DE ACO SOLDADA GALVANIZADA/ZINCADA PARA ALVENARIA, FIO D = *1,20 A 1,70* MM, MALHA 15 X 15 MM, (C X L) *50 X 17,5* CM | C27: UN | D27: =E27*$D$1 -> 2.5 | E27: 2.5 | F27: Aço | G27: Tela de Aço Carbono | I27: Armadura
A28: =COUNTIFS($B$2:$B$764,B28) -> 1 | B28: Tela de arame galvanizada, hexagonal, fio 0,56 mm (24 bwg), malha 1/2", h = 1 m | C28: M2 | D28: =E28*$D$1 -> 14.27 | E28: 14.27 | F28: Aço | G28: Tela de Aço Carbono | I28: Armadura
A29: =COUNTIFS($B$2:$B$764,B29) -> 1 | B29: TIJOLO REFRATÁRIO 5 X 11,5 X 23 CM | C29: UN | D29: =E29*$D$1 -> 7 | E29: 7 | F29: Alvenaria | G29: Alvenaria Refratária | I29: Pintura
A30: =COUNTIFS($B$2:$B$764,B30) -> 1 | B30: TIJOLO REFRATÁRIO 2,5 X 11,5 X 23 CM | C30: UN | D30: =E30*$D$1 -> 5.95 | E30: 5.95 | F30: Alvenaria | G30: Alvenaria Refratária | I30: Pintura
A31: =COUNTIFS($B$2:$B$764,B31) -> 1 | B31: BLOCO CONCRETO ESTRUTURAL 03MPA 14X19X39CM NBR 6136 | C31: UN | D31: =E31*$D$1 -> 2.95 | E31: 2.95 | F31: Alvenaria | G31: Alvenaria Estrutural | I31: Elementos de Vedação (Cerâmica)
A32: =COUNTIFS($B$2:$B$764,B32) -> 1 | B32: BLOCO CONCRETO ESTRUTURAL 04MPA 14X19X04CM NBR 6136 | C32: UN | D32: =E32*$D$1 -> 4.1861538 | E32: 4.1861538 | F32: Alvenaria | G32: Alvenaria Estrutural | I32: Elementos de Vedação (Cerâmica)
A33: =COUNTIFS($B$2:$B$764,B33) -> 1 | B33: BLOCO CONCRETO ESTRUTURAL 04MPA 14X19X09CM NBR 6136 | C33: UN | D33: =E33*$D$1 -> 3.9889744 | E33: 3.9889744 | F33: Alvenaria | G33: Alvenaria Estrutural | I33: Elementos de Vedação (Cerâmica)
A34: =COUNTIFS($B$2:$B$764,B34) -> 1 | B34: BLOCO CONCRETO ESTRUTURAL 04MPA 14X19X14CM NBR 6136 | C34: UN | D34: =E34*$D$1 -> 1.376 | E34: 1.376 | F34: Alvenaria | G34: Alvenaria Estrutural | I34: Elementos de Vedação (Cerâmica)
A35: =COUNTIFS($B$2:$B$764,B35) -> 1 | B35: BLOCO CONCRETO ESTRUTURAL 04MPA 11,5X19X29CM NBR 6136 | C35: UN | D35: =E35*$D$1 -> 1.998 | E35: 1.998 | F35: Alvenaria | G35: Alvenaria Estrutural | I35: Elementos de Vedação (Cerâmica)
A36: =COUNTIFS($B$2:$B$764,B36) -> 1 | B36: BLOCO CONCRETO ESTRUTURAL 04MPA 14X19X29CM NBR 6136 | C36: UN | D36: =E36*$D$1 -> 1.998 | E36: 1.998 | F36: Alvenaria | G36: Alvenaria Estrutural | I36: Elementos de Vedação (Cerâmica)
A37: =COUNTIFS($B$2:$B$764,B37) -> 1 | B37: BLOCO CONCRETO ESTRUTURAL 04MPA 14X19X44CM NBR 6136 | C37: UN | D37: =E37*$D$1 -> 4.02 | E37: 4.02 | F37: Alvenaria | G37: Alvenaria Estrutural | I37: Elementos de Vedação (Cerâmica)
... A83: =COUNTIFS($B$2:$B$764,B83) -> 1 | B83: Argamassa ACIII | C83: KG | D83: =E83*$D$1 -> 2.55 | E83: 2.55 | F83: Argamassa | G83: Argamassa de Assentamento de Revestimentos | I83: Argamassa
A84: =COUNTIFS($B$2:$B$764,B84) -> 1 | B84: MASSA JUNTA DRYWALL | C84: KG | D84: =E84*$D$1 -> 5.5 | E84: =33/6 -> 5.5 | F84: Argamassa | G84: Argamassa de Assentamento de Revestimentos | I84: Argamassa
A85: =COUNTIFS($B$2:$B$764,B85) -> 1 | B85: ARGAMASSA COLANTE AC II | C85: KG | D85: =E85*$D$1 -> 1.36 | E85: 1.36 | F85: Argamassa | G85: Argamassa de Assentamento de Revestimentos | I85: Argamassa
A86: =COUNTIFS($B$2:$B$764,B86) -> 1 | B86: Argamassa industrializada para Para Chapisco Colante | C86: KG | D86: =E86*$D$1 -> 2.295 | E86: 2.295 | F86: Argamassa | G86: Argamassa Diversas | I86: Argamassa
A87: =COUNTIFS($B$2:$B$764,B87) -> 1 | B87: Massa Dundun Para Assentamento De Tijolos E Blocos | C87: KG | D87: =E87*$D$1 -> 19.116 | E87: 19.116 | F87: Argamassa | G87: Argamassa Diversas | I87: Argamassa
A88: =COUNTIFS($B$2:$B$764,B88) -> 1 | B88: ARGAMASSA REFRATÁRIA | C88: M3 | D88: =E88*$D$1 -> 1.75 | E88: 1.75 | F88: Argamassa | G88: Argamassa Diversas | I88: Argamassa
A89: =COUNTIFS($B$2:$B$764,B89) -> 1 | B89: Argamassa Usinada para emboço/massa única | C89: M3 | D89: =E89*$D$1 -> 605.66 | E89: 605.66 | F89: Argamassa | G89: Argamassa Diversas | I89: Argamassa
A90: =COUNTIFS($B$2:$B$764,B90) -> 1 | B90: Argamassa usninada para contrapiso | C90: M3 | D90: =E90*$D$1 -> 550 | E90: 550 | F90: Argamassa | G90: Argamassa Diversas | I90: Argamassa
A91: =COUNTIFS($B$2:$B$764,B91) -> 1 | B91: Argila expandida | C91: KG | D91: =E91*$D$1 -> 2.945 | E91: 2.945 | F91: Argamassa | G91: Argamassa Diversas | I91: Argamassa
A92: =COUNTIFS($B$2:$B$764,B92) -> 1 | B92: ARGAMASSA ESTABILIZADA PARA ASSENTAMENTO | C92: M3 | D92: =E92*$D$1 -> 425 | E92: 425 | F92: Argamassa | G92: Argamassa Usinada | I92: Argamassa
A93: =COUNTIFS($B$2:$B$764,B93) -> 1 | B93: ARGAMASSA ESTABILIZADA PARA CHAPISCO | C93: M3 | D93: =E93*$D$1 -> 480 | E93: 480 | F93: Argamassa | G93: Argamassa Usinada | I93: Argamassa
A94: =COUNTIFS($B$2:$B$764,B94) -> 1 | B94: ARGAMASSA INDUSTRIALIZADA MULTIUSO, PARA REVESTIMENTO INTERNO E EXTERNO E ASSENTAMENTO DE BLOCOS DIVERSOS | C94: M3 | D94: =E94*$D$1 -> 425 | E94: 425 | F94: Argamassa | G94: Argamassa Usinada | I94: Argamassa
A95: =COUNTIFS($B$2:$B$764,B95) -> 1 | B95: PISO INTERTRAVADO CONCRETO SEXTAVADO 35MPA 30X30X06CM NATURAL | C95: M2 | D95: =E95*$D$1 -> 75.9 | E95: 75.9 | F95: Artefatos de concreto | G95: Artefatos de concreto | I95: Concretos
A96: =COUNTIFS($B$2:$B$764,B96) -> 1 | B96: Piso Intertravado Retangular 10x20x08 | C96: M2 | D96: =E96*$D$1 -> 65.9 | E96: 65.9 | F96: Artefatos de concreto | G96: Artefatos de concreto | I96: Concretos
... A148: =COUNTIFS($B$2:$B$764,B148) -> 1 | B148: PLACA / CHAPA DE GESSO ACARTONADO, STANDARD (ST), COR BRANCA, E = 10,0 MM, 1200 X 2400 MM (L X C) | C148: M2 | D148: =E148*$D$1 -> 14.73 | E148: 14.73 | F148: Drywall/Shaft/Forro | G148: Diversos | I148: Diversos
A149: =COUNTIFS($B$2:$B$764,B149) -> 1 | B149: PLACA / CHAPA DE GESSO ACARTONADO, RESISTENTE A UMIDADE (RU), COR VERDE, E = 12,5 MM, 1200 X 2400 MM (L X C) | C149: M2 | D149: =E149*$D$1 -> 29.194444 | E149: =84.08/2.88 -> 29.194444 | F149: Drywall/Shaft/Forro | G149: Diversos | I149: Diversos
A150: =COUNTIFS($B$2:$B$764,B150) -> 1 | B150: PLACA / CHAPA DE GESSO ACARTONADO, STANDARD (ST), COR BRANCA, E = 12,5 MM, 1200 X 2400 MM (L X C) | C150: M2 | D150: =E150*$D$1 -> 18.40625 | E150: =53.01/2.88 -> 18.40625 | F150: Drywall/Shaft/Forro | G150: Diversos | I150: Diversos
A151: =COUNTIFS($B$2:$B$764,B151) -> 1 | B151: LÂ DE VIDRO PARA ISOLAMENTO 50mm | C151: M2 | D151: =E151*$D$1 -> 12.828667 | E151: 12.828667 | F151: Drywall/Shaft/Forro | G151: Drywall/Shaft/Forro | I151: Diversos
A152: =COUNTIFS($B$2:$B$764,B152) -> 1 | B152: PARAFUSO DRY WALL, EM ACO FOSFATIZADO, CABECA TROMBETA E PONTA AGULHA (TA), COMPRIMENTO 25 MM | C152: UN | D152: =E152*$D$1 -> 0.09 | E152: 0.09 | F152: Drywall/Shaft/Forro | G152: Drywall/Shaft/Forro | I152: Diversos
A153: =COUNTIFS($B$2:$B$764,B153) -> 1 | B153: PARAFUSO DRY WALL, EM ACO ZINCADO, CABECA LENTILHA E PONTA BROCA (LB), LARGURA 4,2 MM, COMPRIMENTO 13 MM | C153: UN | D153: =E153*$D$1 -> 0.2 | E153: 0.2 | F153: Drywall/Shaft/Forro | G153: Drywall/Shaft/Forro | I153: Diversos
A154: =COUNTIFS($B$2:$B$764,B154) -> 1 | B154: PERFIL GUIA, FORMATO U, EM ACO ZINCADO, PARA ESTRUTURA PAREDE DRYWALL, E = 0,5 MM, 48 X 3000 MM (L X C) | C154: M | D154: =E154*$D$1 -> 7.03 | E154: 7.03 | F154: Drywall/Shaft/Forro | G154: Drywall/Shaft/Forro | I154: Diversos
A155: =COUNTIFS($B$2:$B$764,B155) -> 1 | B155: PERFIL GUIA, FORMATO U, EM ACO ZINCADO, PARA ESTRUTURA PAREDE DRYWALL, E = 0,5 MM, 70 X 3000 MM (L X C) | C155: M | D155: =E155*$D$1 -> 7.03 | E155: 7.03 | F155: Drywall/Shaft/Forro | G155: Drywall/Shaft/Forro | I155: Diversos
A156: =COUNTIFS($B$2:$B$764,B156) -> 1 | B156: PERFIL GUIA, FORMATO U, EM ACO ZINCADO, PARA ESTRUTURA PAREDE DRYWALL, E = 0,5 MM, 90 X 3000 MM (L X C) | C156: M | D156: =E156*$D$1 -> 16.8 | E156: 16.8 | F156: Drywall/Shaft/Forro | G156: Drywall/Shaft/Forro | I156: Diversos
A157: =COUNTIFS($B$2:$B$764,B157) -> 1 | B157: PERFIL MONTANTE, FORMATO C, EM ACO ZINCADO, PARA ESTRUTURA PAREDE DRYWALL, E = 0,5 MM, 48 X 3000 MM (L X C) | C157: M | D157: =E157*$D$1 -> 7.98 | E157: 7.98 | F157: Drywall/Shaft/Forro | G157: Drywall/Shaft/Forro | I157: Diversos
A158: =COUNTIFS($B$2:$B$764,B158) -> 1 | B158: PERFIL MONTANTE, FORMATO C, EM ACO ZINCADO, PARA ESTRUTURA PAREDE DRYWALL, E = 0,5 MM, 70 X 3000 MM (L X C) | C158: M | D158: =E158*$D$1 -> 7.98 | E158: 7.98 | F158: Drywall/Shaft/Forro | G158: Drywall/Shaft/Forro | I158: Diversos
A159: =COUNTIFS($B$2:$B$764,B159) -> 1 | B159: PERFIL MONTANTE, FORMATO C, EM ACO ZINCADO, PARA ESTRUTURA PAREDE DRYWALL, E = 0,5 MM, 90 X 3000 MM (L X C) | C159: M | D159: =E159*$D$1 -> 18.09 | E159: 18.09 | F159: Drywall/Shaft/Forro | G159: Drywall/Shaft/Forro | I159: Diversos
A160: =COUNTIFS($B$2:$B$764,B160) -> 1 | B160: PINO DE ACO COM ARRUELA CONICA, DIAMETRO ARRUELA = *23* MM E COMP HASTE = *27* MM (ACAO INDIRETA) | C160: UN | D160: =E160*$D$1 -> 0.504 | E160: 0.504 | F160: Drywall/Shaft/Forro | G160: Drywall/Shaft/Forro | I160: Diversos
A161: =COUNTIFS($B$2:$B$764,B161) -> 1 | B161: PINO DE ACO COM FURO, HASTE = 27 MM (ACAO DIRETA) | C161: UN | D161: =E161*$D$1 -> 0.4336 | E161: 0.4336 | F161: Drywall/Shaft/Forro | G161: Drywall/Shaft/Forro | I161: Diversos
A162: =COUNTIFS($B$2:$B$764,B162) -> 1 | B162: Estrutura e fechamento em drywall Parede Drywall | C162: UN | D162: =E162*$D$1 -> 377.83639 | E162: 377.83639 | F162: Drywall/Shaft/Forro | G162: Drywall/Shaft/Forro | I162: Diversos
... A170: =COUNTIFS($B$2:$B$764,B170) -> 1 | B170: SUPORTE ACO CARBONO P/PLACA - REQ. CANTONEIRA 1.1/4"X1/8" 160X250CM | C170: UN | D170: =E170*$D$1 -> 520.85 | E170: 520.85 | F170: EPC/EPI | G170: EPC/EPI | I170: Material Segurança
A171: =COUNTIFS($B$2:$B$764,B171) -> 1 | B171: TUBO GALV. 3" X 2,65MM - 8M C/ RUPTURA: 40 MPA (LINHA DE VIDA) | C171: UN | D171: =E171*$D$1 -> 33.81 | E171: 33.81 | F171: EPC/EPI | G171: EPC/EPI | H171: Cotação | I171: Material Segurança
A172: =COUNTIFS($B$2:$B$764,B172) -> 1 | B172: CABO DE AÇO GALVANIZADO 3/8 | C172: M | D172: =E172*$D$1 -> 5.2 | E172: 5.2 | F172: EPC/EPI | G172: EPC/EPI | I172: Material Segurança
A173: =COUNTIFS($B$2:$B$764,B173) -> 1 | B173: Tela com impressão digital UV | C173: M2 | D173: =E173*$D$1 -> 5.763 | E173: =1728.9/300 -> 5.763 | F173: EPC/EPI | G173: EPC/EPI | H173: https://www.leroymerlin.com.br/kit-3-rolos-de-tela-fachadeira-6x3-3x100-300m2_1571811772?srsltid=AfmBOorqa8qCk4Y_veiSFWZArBrvWDNFifl_-S-G8oMTeThy9bTGNSQOT_Y | I173: Material Segurança
A174: =COUNTIFS($B$2:$B$764,B174) -> 1 | B174: TELA FACHADEIRA POLIETILENO MALHA 1,5X1,5MM | C174: M2 | D174: =E174*$D$1 -> 3.5 | E174: 3.5 | F174: EPC/EPI | G174: EPC/EPI | I174: Material Segurança
A175: =COUNTIFS($B$2:$B$764,B175) -> 1 | B175: TELA PLASTICA TECIDA LISTRADA BRANCA E LARANJA, EM POLIETILENO MONOFILADO | C175: M | D175: =E175*$D$1 -> 2.73 | E175: 2.73 | F175: EPC/EPI | G175: EPC/EPI | I175: Material Segurança
A176: =COUNTIFS($B$2:$B$764,B176) -> 1 | B176: Locação 30 dias de cada equipamento de rebaixamento com 22,5 HP, vazão máxima = 100 m³/h, em operação ou a disposição. | C176: MÊS | D176: =E176*$D$1 -> 6500 | E176: 6500 | F176: Equipamentos | G176: Equipamentos | I176: Equipamentos Aluguel
A177: =COUNTIFS($B$2:$B$764,B177) -> 1 | B177: Locação 30 dias de cada mangote de descarga CDF-A com lance de 50,00 metros cada. | C177: MÊS | D177: =E177*$D$1 -> 900 | E177: 900 | F177: Equipamentos | G177: Equipamentos | I177: Equipamentos Aluguel
A178: =COUNTIFS($B$2:$B$764,B178) -> 1 | B178: Instalação e entrega técnica do(s) equipamento(s) de rebaixamento temporário de aquíferos AQ-EL 44-100. (Previsão de 04 dias) | C178: VB | D178: =E178*$D$1 -> 1200 | E178: 1200 | F178: Equipamentos | G178: Equipamentos | I178: Equipamentos Aluguel
A179: =COUNTIFS($B$2:$B$764,B179) -> 1 | B179: Mobilização e desmobilização de equipamentos - Para execução de estaca Escavada | C179: VB | D179: =E179*$D$1 -> 26000 | E179: 26000 | F179: Equipamentos | G179: Equipamentos | I179: Equipamentos Aluguel
A180: =COUNTIFS($B$2:$B$764,B180) -> 1 | B180: Mobilização e desmobilização de equipamentos - Para execução de estaca hélice monitorada | C180: VB | D180: =E180*$D$1 -> 32000 | E180: 32000 | F180: Equipamentos | G180: Equipamentos | I180: Equipamentos Aluguel
A181: =COUNTIFS($B$2:$B$764,B181) -> 1 | B181: Mobilização e desmobilização de equipamentos - Para execução de estaca hélice | C181: VB | D181: =E181*$D$1 -> 18500 | E181: 18500 | F181: Equipamentos | G181: Equipamentos | I181: Equipamentos Aluguel
A182: =COUNTIFS($B$2:$B$764,B182) -> 1 | B182: Caminhao pipa ford f.14.000 1997 | C182: MÊS | D182: =E182*$D$1 -> 1500 | E182: 1500 | F182: Equipamentos | G182: Equipamentos | I182: Equipamentos Aluguel
A183: =COUNTIFS($B$2:$B$764,B183) -> 1 | B183: Escavadeira 8T link belt 80SA BANYNN | C183: MÊS | D183: =E183*$D$1 -> 3200 | E183: 3200 | F183: Equipamentos | G183: Equipamentos | I183: Equipamentos Aluguel
A184: =COUNTIFS($B$2:$B$764,B184) -> 1 | B184: Escavadeira DOOSAN DX225 (terceirizado) | C184: MÊS | D184: =E184*$D$1 -> 33660 | E184: 33660 | F184: Equipamentos | G184: Equipamentos | I184: Equipamentos Aluguel
A185: =COUNTIFS($B$2:$B$764,B185) -> 1 | B185: Escaveideira 320 CAT 2019 | C185: MÊS | D185: =E185*$D$1 -> 15000 | E185: 15000 | F185: Equipamentos | G185: Equipamentos | I185: Equipamentos Aluguel
... A228: =COUNTIFS($B$2:$B$764,B228) -> 1 | B228: Porta de madeira de Correr - 70x210cm (kit completo) | C228: M2 | D228: =E228*$D$1 -> 1358.5 | E228: 1358.5 | F228: Esquadrias | G228: Madeira | I228: Esquadrias de Madeira
A229: =COUNTIFS($B$2:$B$764,B229) -> 1 | B229: Porta de madeira de Correr - 110x210cm (kit completo) | C229: M2 | D229: =E229*$D$1 -> 1494.35 | E229: =1358.5*1.1 -> 1494.35 | F229: Esquadrias | G229: Madeira | I229: Esquadrias de Madeira
A230: =COUNTIFS($B$2:$B$764,B230) -> 1 | B230: Porta de madeira de Correr - 120x210cm (kit completo) | C230: M2 | D230: =E230*$D$1 -> 1494.35 | E230: =1358.5*1.1 -> 1494.35 | F230: Esquadrias | G230: Madeira | I230: Esquadrias de Madeira
A231: =COUNTIFS($B$2:$B$764,B231) -> 1 | B231: Porta de madeira de Correr - 135x210cm (kit completo) | C231: M2 | D231: =E231*$D$1 -> 1833.975 | E231: =1358.5*1.35 -> 1833.975 | F231: Esquadrias | G231: Madeira | I231: Esquadrias de Madeira
A232: =COUNTIFS($B$2:$B$764,B232) -> 1 | B232: Porta de madeira de Correr - 150x210cm (kit completo) | C232: M2 | D232: =E232*$D$1 -> 2037.75 | E232: =1358.5*1.5 -> 2037.75 | F232: Esquadrias | G232: Madeira | I232: Esquadrias de Madeira
A233: =COUNTIFS($B$2:$B$764,B233) -> 1 | B233: Porta de madeira de abrir - 90x215cm (kit completo) | C233: M2 | D233: =E233*$D$1 -> 1300 | E233: 1300 | F233: Esquadrias | G233: Madeira | I233: Esquadrias de Madeira
A234: =COUNTIFS($B$2:$B$764,B234) -> 1 | B234: Claraboia em vidro laminado | C234: M2 | D234: =E234*$D$1 -> 1014 | E234: 1014 | F234: Esquadrias | G234: Vidro | I234: Vidros
A235: =COUNTIFS($B$2:$B$764,B235) -> 1 | B235: Pele de vidro | C235: M2 | D235: =E235*$D$1 -> 1533.99 | E235: 1533.99 | F235: Esquadrias | G235: Vidro | I235: Vidros
A236: =COUNTIFS($B$2:$B$764,B236) -> 1 | B236: Portão de vidro - 85x280 cm | C236: M2 | D236: =E236*$D$1 -> 3893.2833 | E236: 3893.2833 | F236: Esquadrias | G236: Vidro | I236: Vidros
A237: =COUNTIFS($B$2:$B$764,B237) -> 1 | B237: Gradil metálico | C237: M2 | D237: =E237*$D$1 -> 568.92672 | E237: 568.92672 | F237: Esquadrias | G237: Metálicas
A238: =COUNTIFS($B$2:$B$764,B238) -> 1 | B238: Porta corta-fogo, 1 folha, 80x210 cm | C238: un | D238: =E238*$D$1 -> 1100 | E238: 1100 | F238: Esquadrias | G238: Metálicas | I238: Esquadrias de Ferro
A239: =COUNTIFS($B$2:$B$764,B239) -> 1 | B239: Porta corta-fogo, 1 folha, 90x210 cm | C239: un | D239: =E239*$D$1 -> 1237.5 | E239: =1100*90/80 -> 1237.5 | F239: Esquadrias | G239: Metálicas | I239: Esquadrias de Ferro
A240: =COUNTIFS($B$2:$B$764,B240) -> 1 | B240: Guarda Corpo metálico (gradil) - fornecimento e instalação | C240: M2 | D240: =E240*$D$1 -> 600 | E240: 600 | F240: Esquadrias | G240: Metálicas | I240: Esquadrias de Ferro
A241: =COUNTIFS($B$2:$B$764,B241) -> 1 | B241: Porta corta-fogo, 1 folha, 96x210 cm | C241: un | D241: =E241*$D$1 -> 2530 | E241: 2530 | F241: Esquadrias | G241: Metálicas | I241: Esquadrias de Ferro
A242: =COUNTIFS($B$2:$B$764,B242) -> 1 | B242: Portão, 1 folha, 500x235 cm | C242: un | D242: =E242*$D$1 -> 13011.726 | E242: 13011.726 | F242: Esquadrias | G242: Metálicas | I242: Esquadrias de Ferro
A243: =COUNTIFS($B$2:$B$764,B243) -> 1 | B243: Portão, 1 folha, 320x245 cm | C243: un | D243: =E243*$D$1 -> 8681.8667 | E243: =9302*(3.2*2.45)/(3.5*2.4) -> 8681.8667 | F243: Esquadrias | G243: Metálicas | I243: Esquadrias de Ferro
A244: =COUNTIFS($B$2:$B$764,B244) -> 1 | B244: Portão, 1 folha, 320x220 cm | C244: un | D244: =E244*$D$1 -> 7795.9619 | E244: =9302*(3.2*2.2)/(3.5*2.4) -> 7795.9619 | F244: Esquadrias | G244: Metálicas | I244: Esquadrias de Ferro
A245: =COUNTIFS($B$2:$B$764,B245) -> 1 | B245: Portão, 1 folha, 90x220 cm | C245: un | D245: =E245*$D$1 -> 2192.6143 | E245: =9302*(0.9*2.2)/(3.5*2.4) -> 2192.6143 | F245: Esquadrias | G245: Metálicas | I245: Esquadrias de Ferro
A246: =COUNTIFS($B$2:$B$764,B246) -> 1 | B246: Portão, 2 folha, 150x112 cm | C246: un | D246: =E246*$D$1 -> 1860.4 | E246: =9302*(1.5*1.12)/(3.5*2.4) -> 1860.4 | F246: Esquadrias | G246: Metálicas | I246: Esquadrias de Ferro
A247: =COUNTIFS($B$2:$B$764,B247) -> 1 | B247: Portão, 1 folha, 320x295 cm | C247: un | D247: =E247*$D$1 -> 10453.676 | E247: =9302*(3.2*2.95)/(3.5*2.4) -> 10453.676 | F247: Esquadrias | G247: Metálicas | I247: Esquadrias de Ferro
A248: =COUNTIFS($B$2:$B$764,B248) -> 1 | B248: Portão, 1 folha, 350x240 cm | C248: un | D248: =E248*$D$1 -> 9302 | E248: 9302 | F248: Esquadrias | G248: Metálicas | I248: Esquadrias de Ferro
A249: =COUNTIFS($B$2:$B$764,B249) -> 1 | B249: Porta corta-fogo, 2 folha, 152x126 cm | C249: un | D249: =E249*$D$1 -> 1089.6085 | E249: 1089.6085 | F249: Esquadrias | G249: Metálicas | I249: Esquadrias de Ferro
A250: =COUNTIFS($B$2:$B$764,B250) -> 1 | B250: Escada marinheiro com gaiola de proteção, h=6 m | C250: un | D250: =E250*$D$1 -> 6500 | E250: 6500 | F250: Esquadrias | G250: Metálicas | I250: Esquadrias de Ferro
A251: =COUNTIFS($B$2:$B$764,B251) -> 1 | B251: Escada de marinheiro | C251: un | D251: =E251*$D$1 -> 2405 | E251: 2405 | F251: Esquadrias | G251: Metálicas | I251: Esquadrias de Ferro
A252: =COUNTIFS($B$2:$B$764,B252) -> 1 | B252: Porta venezianada metálica, 1 folha, 60x80 cm | C252: un | D252: =E252*$D$1 -> 975 | E252: 975 | F252: Esquadrias | G252: Metálicas | I252: Esquadrias de Ferro
A253: =COUNTIFS($B$2:$B$764,B253) -> 1 | B253: Porta metálica, 1 folha, 80x150 cm | C253: un | D253: =E253*$D$1 -> 2968 | E253: 2968 | F253: Esquadrias | G253: Metálicas | I253: Esquadrias de Ferro
A254: =COUNTIFS($B$2:$B$764,B254) -> 1 | B254: Chapa de Aço Galvanizada 1,55mm (Chapa 16) x 1200mm x 3000mm | C254: M2 | D254: =E254*$D$1 -> 135.35556 | E254: 135.35556 | F254: Esquadrias | G254: Metálicas | I254: Esquadrias de Ferro
A255: =COUNTIFS($B$2:$B$764,B255) -> 1 | B255: Fechadura Arouca para Porta do Quarto Preto 55mm | C255: un | D255: =E255*$D$1 -> 232.46 | E255: 232.46 | F255: Esquadrias | G255: Fechaduras e acessórios | I255: Vidros
...

Sheet Ger_Executivo
G4: PROJETO: | I4: ='Obra '!D1 -> Caio Prado | O4: REVISÃO: | P4: DATA
G5: EMPRESA: | I5: ='Obra '!D2 -> Indepy | O5: R00 | P5: 45980
A6: Unidade Construtiva | B6: Célula Construtiva | C6: Etapa | D6: Subetapa | E6: Serviço | G6: GERENCIAMENTO EXECUTIVO
A7: 0 | B7: 0 | C7: 0 | D7: 0 | E7: 0 | G7: Atalho | H7: NIVEL | I7: Item | J7: Descrição | K7: Unidade | L7: Quant. | M7: Preço un | N7: Total | O7: Considerações | P7: Situação
A8: =IF($H8="UNIDADE CONSTRUTIVA",OFFSET(A8,-1,0)+1,LARGE(A$3:A7,1)) -> 0 | B8: =IF(H8="UNIDADE CONSTRUTIVA",0,IF(H8="CÉLULA CONSTRUTIVA",OFFSET(B8,-1,0)+1,OFFSET(B8,-1,0))) -> 1 | C8: =IF(H8="CÉLULA CONSTRUTIVA",0,IF(H8="ETAPA",OFFSET(C8,-1,0)+1,OFFSET(C8,-1,0))) -> 0 | D8: =IF(H8="ETAPA",0,IF(H8="SUBETAPA",OFFSET(D8,-1,0)+1,OFFSET(D8,-1,0))) -> 0 | E8: =IF(H8="Subetapa",0,IF(H8="serviço",OFFSET(E8,-1,0)+1,OFFSET(E8,-1,0))) -> 0 | H8: CÉLULA CONSTRUTIVA | I8: =IF(H8="Unidade Construtiva",TEXT(A8,"00"),IF(H8="Célula Construtiva",TEXT(B8,"00"),IF(H8="Etapa",CONCATENATE(TEXT(B8,"00"),".",TEXT(C8,"000")),IF(H8="Subetapa",CONCATENATE(TEXT(B8,"00"),".",TEXT(C8,"000"),".",TEXT(D8,"000")),IF(H8="Serviço",CONCATENATE(TEXT(B8,"00"),".",TEXT(C8,"000"),".",TEXT(D8,"000"),".",TEXT(E8,"000")),""))))) -> 01 | J8: MOVIMENTAÇÃO DE TERRA | K8: PEGAR CONTENÇÃO TBM | N8: =IF(H8="Serviço",M8*L8,IF(H8="CÉLULA CONSTRUTIVA",SUMIFS($N$8:$N$452,$B$8:$B$452,B8,$H$8:$H$452,"Serviço"),IF(H8="ETAPA",SUMIFS($N$8:$N$452,$B$8:$B$452,B8,$C$8:$C$452,C8,$H$8:$H$452,"Serviço"),IF(H8="SUBETAPA",SUMIFS($N$8:$N$452,$B$8:$B$452,B8,$C$8:$C$452,C8,$D$8:$D$452,D8,$H$8:$H$452,"Serviço"),0)))) -> 0 | O8: =N8/'Obra '!$E$9 -> 0 | Q8: MOVIMENTAÇÃO DE TERRA
A9: =IF($H9="UNIDADE CONSTRUTIVA",OFFSET(A9,-1,0)+1,LARGE(A$3:A8,1)) -> 0 | B9: =IF(H9="UNIDADE CONSTRUTIVA",0,IF(H9="CÉLULA CONSTRUTIVA",OFFSET(B9,-1,0)+1,OFFSET(B9,-1,0))) -> 1 | C9: =IF(H9="CÉLULA CONSTRUTIVA",0,IF(H9="ETAPA",OFFSET(C9,-1,0)+1,OFFSET(C9,-1,0))) -> 1 | D9: =IF(H9="ETAPA",0,IF(H9="SUBETAPA",OFFSET(D9,-1,0)+1,OFFSET(D9,-1,0))) -> 0 | E9: =IF(H9="Subetapa",0,IF(H9="serviço",OFFSET(E9,-1,0)+1,OFFSET(E9,-1,0))) -> 0 | H9: ETAPA | I9: =IF(H9="Unidade Construtiva",TEXT(A9,"00"),IF(H9="Célula Construtiva",TEXT(B9,"00"),IF(H9="Etapa",CONCATENATE(TEXT(B9,"00"),".",TEXT(C9,"000")),IF(H9="Subetapa",CONCATENATE(TEXT(B9,"00"),".",TEXT(C9,"000"),".",TEXT(D9,"000")),IF(H9="Serviço",CONCATENATE(TEXT(B9,"00"),".",TEXT(C9,"000"),".",TEXT(D9,"000"),".",TEXT(E9,"000")),""))))) -> 01.001 | J9: MOVIMENTAÇÃO DE TERRA | N9: =IF(H9="Serviço",M9*L9,IF(H9="CÉLULA CONSTRUTIVA",SUMIFS($N$8:$N$452,$B$8:$B$452,B9,$H$8:$H$452,"Serviço"),IF(H9="ETAPA",SUMIFS($N$8:$N$452,$B$8:$B$452,B9,$C$8:$C$452,C9,$H$8:$H$452,"Serviço"),IF(H9="SUBETAPA",SUMIFS($N$8:$N$452,$B$8:$B$452,B9,$C$8:$C$452,C9,$D$8:$D$452,D9,$H$8:$H$452,"Serviço"),0)))) -> 0 | O9: =N9/'Obra '!$E$9 -> 0
A10: =IF($H10="UNIDADE CONSTRUTIVA",OFFSET(A10,-1,0)+1,LARGE(A$3:A9,1)) -> 0 | B10: =IF(H10="UNIDADE CONSTRUTIVA",0,IF(H10="CÉLULA CONSTRUTIVA",OFFSET(B10,-1,0)+1,OFFSET(B10,-1,0))) -> 1 | C10: =IF(H10="CÉLULA CONSTRUTIVA",0,IF(H10="ETAPA",OFFSET(C10,-1,0)+1,OFFSET(C10,-1,0))) -> 1 | D10: =IF(H10="ETAPA",0,IF(H10="SUBETAPA",OFFSET(D10,-1,0)+1,OFFSET(D10,-1,0))) -> 1 | E10: =IF(H10="Subetapa",0,IF(H10="serviço",OFFSET(E10,-1,0)+1,OFFSET(E10,-1,0))) -> 0 | H10: SUBETAPA | I10: =IF(H10="Unidade Construtiva",TEXT(A10,"00"),IF(H10="Célula Construtiva",TEXT(B10,"00"),IF(H10="Etapa",CONCATENATE(TEXT(B10,"00"),".",TEXT(C10,"000")),IF(H10="Subetapa",CONCATENATE(TEXT(B10,"00"),".",TEXT(C10,"000"),".",TEXT(D10,"000")),IF(H10="Serviço",CONCATENATE(TEXT(B10,"00"),".",TEXT(C10,"000"),".",TEXT(D10,"000"),".",TEXT(E10,"000")),""))))) -> 01.001.001 | J10: Corte e aterro | N10: =IF(H10="Serviço",M10*L10,IF(H10="CÉLULA CONSTRUTIVA",SUMIFS($N$8:$N$452,$B$8:$B$452,B10,$H$8:$H$452,"Serviço"),IF(H10="ETAPA",SUMIFS($N$8:$N$452,$B$8:$B$452,B10,$C$8:$C$452,C10,$H$8:$H$452,"Serviço"),IF(H10="SUBETAPA",SUMIFS($N$8:$N$452,$B$8:$B$452,B10,$C$8:$C$452,C10,$D$8:$D$452,D10,$H$8:$H$452,"Serviço"),0)))) -> 0 | O10: =N10/'Obra '!$E$9 -> 0
A11: =IF($H11="UNIDADE CONSTRUTIVA",OFFSET(A11,-1,0)+1,LARGE(A$3:A10,1)) -> 0 | B11: =IF(H11="UNIDADE CONSTRUTIVA",0,IF(H11="CÉLULA CONSTRUTIVA",OFFSET(B11,-1,0)+1,OFFSET(B11,-1,0))) -> 1 | C11: =IF(H11="CÉLULA CONSTRUTIVA",0,IF(H11="ETAPA",OFFSET(C11,-1,0)+1,OFFSET(C11,-1,0))) -> 1 | D11: =IF(H11="ETAPA",0,IF(H11="SUBETAPA",OFFSET(D11,-1,0)+1,OFFSET(D11,-1,0))) -> 1 | E11: =IF(H11="Subetapa",0,IF(H11="serviço",OFFSET(E11,-1,0)+1,OFFSET(E11,-1,0))) -> 1 | H11: SERVIÇO | I11: =IF(H11="Unidade Construtiva",TEXT(A11,"00"),IF(H11="Célula Construtiva",TEXT(B11,"00"),IF(H11="Etapa",CONCATENATE(TEXT(B11,"00"),".",TEXT(C11,"000")),IF(H11="Subetapa",CONCATENATE(TEXT(B11,"00"),".",TEXT(C11,"000"),".",TEXT(D11,"000")),IF(H11="Serviço",CONCATENATE(TEXT(B11,"00"),".",TEXT(C11,"000"),".",TEXT(D11,"000"),".",TEXT(E11,"000")),""))))) -> 01.001.001.001 | J11: Terraplanagem - Corte e Desaterro Solo | K11: m3 | M11: =_xlfn.XLOOKUP($J11,CPU!$D$1:$D$3085,CPU!$H$1:$H$3085) -> 2.7132 | N11: =IF(H11="Serviço",M11*L11,IF(H11="CÉLULA CONSTRUTIVA",SUMIFS($N$111:$N$554,$B$111:$B$554,B11,$H$111:$H$554,"Serviço"),IF(H11="ETAPA",SUMIFS($N$111:$N$554,$B$111:$B$554,B11,$C$111:$C$554,C11,$H$111:$H$554,"Serviço"),IF(H11="SUBETAPA",SUMIFS($N$111:$N$554,$B$111:$B$554,B11,$C$111:$C$554,C11,$D$111:$D$554,D11,$H$111:$H$554,"Serviço"),0)))) -> 0 | O11: Corte do subsolo | P11: Finalizado
A12: =IF($H12="UNIDADE CONSTRUTIVA",OFFSET(A12,-1,0)+1,LARGE(A$3:A11,1)) -> 0 | B12: =IF(H12="UNIDADE CONSTRUTIVA",0,IF(H12="CÉLULA CONSTRUTIVA",OFFSET(B12,-1,0)+1,OFFSET(B12,-1,0))) -> 1 | C12: =IF(H12="CÉLULA CONSTRUTIVA",0,IF(H12="ETAPA",OFFSET(C12,-1,0)+1,OFFSET(C12,-1,0))) -> 1 | D12: =IF(H12="ETAPA",0,IF(H12="SUBETAPA",OFFSET(D12,-1,0)+1,OFFSET(D12,-1,0))) -> 1 | E12: =IF(H12="Subetapa",0,IF(H12="serviço",OFFSET(E12,-1,0)+1,OFFSET(E12,-1,0))) -> 2 | H12: SERVIÇO | I12: =IF(H12="Unidade Construtiva",TEXT(A12,"00"),IF(H12="Célula Construtiva",TEXT(B12,"00"),IF(H12="Etapa",CONCATENATE(TEXT(B12,"00"),".",TEXT(C12,"000")),IF(H12="Subetapa",CONCATENATE(TEXT(B12,"00"),".",TEXT(C12,"000"),".",TEXT(D12,"000")),IF(H12="Serviço",CONCATENATE(TEXT(B12,"00"),".",TEXT(C12,"000"),".",TEXT(D12,"000"),".",TEXT(E12,"000")),""))))) -> 01.001.001.002 | J12: Terraplanagem - Aterro material de 1º categoria | K12: m3 | M12: =_xlfn.XLOOKUP($J12,CPU!$D$1:$D$3085,CPU!$H$1:$H$3085) -> 9.2718 | N12: =IF(H12="Serviço",M12*L12,IF(H12="CÉLULA CONSTRUTIVA",SUMIFS($N$111:$N$554,$B$111:$B$554,B12,$H$111:$H$554,"Serviço"),IF(H12="ETAPA",SUMIFS($N$111:$N$554,$B$111:$B$554,B12,$C$111:$C$554,C12,$H$111:$H$554,"Serviço"),IF(H12="SUBETAPA",SUMIFS($N$111:$N$554,$B$111:$B$554,B12,$C$111:$C$554,C12,$D$111:$D$554,D12,$H$111:$H$554,"Serviço"),0)))) -> 0 | O12: Aterro do subsolo | P12: Finalizado
A13: =IF($H13="UNIDADE CONSTRUTIVA",OFFSET(A13,-1,0)+1,LARGE(A$3:A12,1)) -> 0 | B13: =IF(H13="UNIDADE CONSTRUTIVA",0,IF(H13="CÉLULA CONSTRUTIVA",OFFSET(B13,-1,0)+1,OFFSET(B13,-1,0))) -> 1 | C13: =IF(H13="CÉLULA CONSTRUTIVA",0,IF(H13="ETAPA",OFFSET(C13,-1,0)+1,OFFSET(C13,-1,0))) -> 1 | D13: =IF(H13="ETAPA",0,IF(H13="SUBETAPA",OFFSET(D13,-1,0)+1,OFFSET(D13,-1,0))) -> 2 | E13: =IF(H13="Subetapa",0,IF(H13="serviço",OFFSET(E13,-1,0)+1,OFFSET(E13,-1,0))) -> 0 | H13: SUBETAPA | I13: =IF(H13="Unidade Construtiva",TEXT(A13,"00"),IF(H13="Célula Construtiva",TEXT(B13,"00"),IF(H13="Etapa",CONCATENATE(TEXT(B13,"00"),".",TEXT(C13,"000")),IF(H13="Subetapa",CONCATENATE(TEXT(B13,"00"),".",TEXT(C13,"000"),".",TEXT(D13,"000")),IF(H13="Serviço",CONCATENATE(TEXT(B13,"00"),".",TEXT(C13,"000"),".",TEXT(D13,"000"),".",TEXT(E13,"000")),""))))) -> 01.001.002 | J13: Escavação e Reaterro de Valas | N13: =IF(H13="Serviço",M13*L13,IF(H13="CÉLULA CONSTRUTIVA",SUMIFS($N$8:$N$452,$B$8:$B$452,B13,$H$8:$H$452,"Serviço"),IF(H13="ETAPA",SUMIFS($N$8:$N$452,$B$8:$B$452,B13,$C$8:$C$452,C13,$H$8:$H$452,"Serviço"),IF(H13="SUBETAPA",SUMIFS($N$8:$N$452,$B$8:$B$452,B13,$C$8:$C$452,C13,$D$8:$D$452,D13,$H$8:$H$452,"Serviço"),0)))) -> 0 | O13: =N13/'Obra '!$E$9 -> 0
A14: =IF($H14="UNIDADE CONSTRUTIVA",OFFSET(A14,-1,0)+1,LARGE(A$3:A13,1)) -> 0 | B14: =IF(H14="UNIDADE CONSTRUTIVA",0,IF(H14="CÉLULA CONSTRUTIVA",OFFSET(B14,-1,0)+1,OFFSET(B14,-1,0))) -> 1 | C14: =IF(H14="CÉLULA CONSTRUTIVA",0,IF(H14="ETAPA",OFFSET(C14,-1,0)+1,OFFSET(C14,-1,0))) -> 1 | D14: =IF(H14="ETAPA",0,IF(H14="SUBETAPA",OFFSET(D14,-1,0)+1,OFFSET(D14,-1,0))) -> 2 | E14: =IF(H14="Subetapa",0,IF(H14="serviço",OFFSET(E14,-1,0)+1,OFFSET(E14,-1,0))) -> 1 | H14: SERVIÇO | I14: =IF(H14="Unidade Construtiva",TEXT(A14,"00"),IF(H14="Célula Construtiva",TEXT(B14,"00"),IF(H14="Etapa",CONCATENATE(TEXT(B14,"00"),".",TEXT(C14,"000")),IF(H14="Subetapa",CONCATENATE(TEXT(B14,"00"),".",TEXT(C14,"000"),".",TEXT(D14,"000")),IF(H14="Serviço",CONCATENATE(TEXT(B14,"00"),".",TEXT(C14,"000"),".",TEXT(D14,"000"),".",TEXT(E14,"000")),""))))) -> 01.001.002.001 | J14: Escavação mecanizada para estacas de fundação, com retroescavadeira | K14: m3 | M14: =_xlfn.XLOOKUP($J14,CPU!$D$1:$D$3085,CPU!$H$1:$H$3085) -> 36.36 | N14: =IF(H14="Serviço",M14*L14,IF(H14="CÉLULA CONSTRUTIVA",SUMIFS($N$8:$N$452,$B$8:$B$452,B14,$H$8:$H$452,"Serviço"),IF(H14="ETAPA",SUMIFS($N$8:$N$452,$B$8:$B$452,B14,$C$8:$C$452,C14,$H$8:$H$452,"Serviço"),IF(H14="SUBETAPA",SUMIFS($N$8:$N$452,$B$8:$B$452,B14,$C$8:$C$452,C14,$D$8:$D$452,D14,$H$8:$H$452,"Serviço"),0)))) -> 0 | O14: Considerado estacas e contenção, conforme repassado pelo projetista | P14: Finalizado
A15: =IF($H15="UNIDADE CONSTRUTIVA",OFFSET(A15,-1,0)+1,LARGE(A$3:A14,1)) -> 0 | B15: =IF(H15="UNIDADE CONSTRUTIVA",0,IF(H15="CÉLULA CONSTRUTIVA",OFFSET(B15,-1,0)+1,OFFSET(B15,-1,0))) -> 1 | C15: =IF(H15="CÉLULA CONSTRUTIVA",0,IF(H15="ETAPA",OFFSET(C15,-1,0)+1,OFFSET(C15,-1,0))) -> 1 | D15: =IF(H15="ETAPA",0,IF(H15="SUBETAPA",OFFSET(D15,-1,0)+1,OFFSET(D15,-1,0))) -> 2 | E15: =IF(H15="Subetapa",0,IF(H15="serviço",OFFSET(E15,-1,0)+1,OFFSET(E15,-1,0))) -> 2 | H15: SERVIÇO | I15: =IF(H15="Unidade Construtiva",TEXT(A15,"00"),IF(H15="Célula Construtiva",TEXT(B15,"00"),IF(H15="Etapa",CONCATENATE(TEXT(B15,"00"),".",TEXT(C15,"000")),IF(H15="Subetapa",CONCATENATE(TEXT(B15,"00"),".",TEXT(C15,"000"),".",TEXT(D15,"000")),IF(H15="Serviço",CONCATENATE(TEXT(B15,"00"),".",TEXT(C15,"000"),".",TEXT(D15,"000"),".",TEXT(E15,"000")),""))))) -> 01.001.002.002 | J15: Escavação mecanizada para blocos de fundação, vigas de fundação e poço de elevador, com retroescavadeira | K15: m3 | M15: =_xlfn.XLOOKUP($J15,CPU!$D$1:$D$3085,CPU!$H$1:$H$3085) -> 36.36 | N15: =IF(H15="Serviço",M15*L15,IF(H15="CÉLULA CONSTRUTIVA",SUMIFS($N$8:$N$452,$B$8:$B$452,B15,$H$8:$H$452,"Serviço"),IF(H15="ETAPA",SUMIFS($N$8:$N$452,$B$8:$B$452,B15,$C$8:$C$452,C15,$H$8:$H$452,"Serviço"),IF(H15="SUBETAPA",SUMIFS($N$8:$N$452,$B$8:$B$452,B15,$C$8:$C$452,C15,$D$8:$D$452,D15,$H$8:$H$452,"Serviço"),0)))) -> 0 | O15: Considerado estimativa de blocos, vigas de fundação e pilares, devido a ausencia de projeto | P15: Finalizado
A16: =IF($H16="UNIDADE CONSTRUTIVA",OFFSET(A16,-1,0)+1,LARGE(A$3:A15,1)) -> 0 | B16: =IF(H16="UNIDADE CONSTRUTIVA",0,IF(H16="CÉLULA CONSTRUTIVA",OFFSET(B16,-1,0)+1,OFFSET(B16,-1,0))) -> 1 | C16: =IF(H16="CÉLULA CONSTRUTIVA",0,IF(H16="ETAPA",OFFSET(C16,-1,0)+1,OFFSET(C16,-1,0))) -> 1 | D16: =IF(H16="ETAPA",0,IF(H16="SUBETAPA",OFFSET(D16,-1,0)+1,OFFSET(D16,-1,0))) -> 2 | E16: =IF(H16="Subetapa",0,IF(H16="serviço",OFFSET(E16,-1,0)+1,OFFSET(E16,-1,0))) -> 3 | H16: SERVIÇO | I16: =IF(H16="Unidade Construtiva",TEXT(A16,"00"),IF(H16="Célula Construtiva",TEXT(B16,"00"),IF(H16="Etapa",CONCATENATE(TEXT(B16,"00"),".",TEXT(C16,"000")),IF(H16="Subetapa",CONCATENATE(TEXT(B16,"00"),".",TEXT(C16,"000"),".",TEXT(D16,"000")),IF(H16="Serviço",CONCATENATE(TEXT(B16,"00"),".",TEXT(C16,"000"),".",TEXT(D16,"000"),".",TEXT(E16,"000")),""))))) -> 01.001.002.003 | J16: Reaterro mecanizado de valas para blocos e vigas de fundação, com retroescavadeira | K16: m3 | M16: =_xlfn.XLOOKUP($J16,CPU!$D$1:$D$3085,CPU!$H$1:$H$3085) -> 14.55 | N16: =IF(H16="Serviço",M16*L16,IF(H16="CÉLULA CONSTRUTIVA",SUMIFS($N$8:$N$452,$B$8:$B$452,B16,$H$8:$H$452,"Serviço"),IF(H16="ETAPA",SUMIFS($N$8:$N$452,$B$8:$B$452,B16,$C$8:$C$452,C16,$H$8:$H$452,"Serviço"),IF(H16="SUBETAPA",SUMIFS($N$8:$N$452,$B$8:$B$452,B16,$C$8:$C$452,C16,$D$8:$D$452,D16,$H$8:$H$452,"Serviço"),0)))) -> 0 | P16: Finalizado
A17: =IF($H17="UNIDADE CONSTRUTIVA",OFFSET(A17,-1,0)+1,LARGE(A$3:A16,1)) -> 0 | B17: =IF(H17="UNIDADE CONSTRUTIVA",0,IF(H17="CÉLULA CONSTRUTIVA",OFFSET(B17,-1,0)+1,OFFSET(B17,-1,0))) -> 1 | C17: =IF(H17="CÉLULA CONSTRUTIVA",0,IF(H17="ETAPA",OFFSET(C17,-1,0)+1,OFFSET(C17,-1,0))) -> 1 | D17: =IF(H17="ETAPA",0,IF(H17="SUBETAPA",OFFSET(D17,-1,0)+1,OFFSET(D17,-1,0))) -> 3 | E17: =IF(H17="Subetapa",0,IF(H17="serviço",OFFSET(E17,-1,0)+1,OFFSET(E17,-1,0))) -> 0 | H17: SUBETAPA | I17: =IF(H17="Unidade Construtiva",TEXT(A17,"00"),IF(H17="Célula Construtiva",TEXT(B17,"00"),IF(H17="Etapa",CONCATENATE(TEXT(B17,"00"),".",TEXT(C17,"000")),IF(H17="Subetapa",CONCATENATE(TEXT(B17,"00"),".",TEXT(C17,"000"),".",TEXT(D17,"000")),IF(H17="Serviço",CONCATENATE(TEXT(B17,"00"),".",TEXT(C17,"000"),".",TEXT(D17,"000"),".",TEXT(E17,"000")),""))))) -> 01.001.003 | J17: Lastro de estrutura de concreto | N17: =IF(H17="Serviço",M17*L17,IF(H17="CÉLULA CONSTRUTIVA",SUMIFS($N$8:$N$452,$B$8:$B$452,B17,$H$8:$H$452,"Serviço"),IF(H17="ETAPA",SUMIFS($N$8:$N$452,$B$8:$B$452,B17,$C$8:$C$452,C17,$H$8:$H$452,"Serviço"),IF(H17="SUBETAPA",SUMIFS($N$8:$N$452,$B$8:$B$452,B17,$C$8:$C$452,C17,$D$8:$D$452,D17,$H$8:$H$452,"Serviço"),0)))) -> 0 | O17: =N17/'Obra '!$E$9 -> 0
A18: =IF($H18="UNIDADE CONSTRUTIVA",OFFSET(A18,-1,0)+1,LARGE(A$3:A17,1)) -> 0 | B18: =IF(H18="UNIDADE CONSTRUTIVA",0,IF(H18="CÉLULA CONSTRUTIVA",OFFSET(B18,-1,0)+1,OFFSET(B18,-1,0))) -> 1 | C18: =IF(H18="CÉLULA CONSTRUTIVA",0,IF(H18="ETAPA",OFFSET(C18,-1,0)+1,OFFSET(C18,-1,0))) -> 1 | D18: =IF(H18="ETAPA",0,IF(H18="SUBETAPA",OFFSET(D18,-1,0)+1,OFFSET(D18,-1,0))) -> 3 | E18: =IF(H18="Subetapa",0,IF(H18="serviço",OFFSET(E18,-1,0)+1,OFFSET(E18,-1,0))) -> 1 | H18: SERVIÇO | I18: =IF(H18="Unidade Construtiva",TEXT(A18,"00"),IF(H18="Célula Construtiva",TEXT(B18,"00"),IF(H18="Etapa",CONCATENATE(TEXT(B18,"00"),".",TEXT(C18,"000")),IF(H18="Subetapa",CONCATENATE(TEXT(B18,"00"),".",TEXT(C18,"000"),".",TEXT(D18,"000")),IF(H18="Serviço",CONCATENATE(TEXT(B18,"00"),".",TEXT(C18,"000"),".",TEXT(D18,"000"),".",TEXT(E18,"000")),""))))) -> 01.001.003.001 | J18: Lastro de Concreto Magro, Aplicado em Blocos de Fundação | K18: m3 | M18: =_xlfn.XLOOKUP($J18,CPU!$D$1:$D$3085,CPU!$H$1:$H$3085) -> 518.794 | N18: =IF(H18="Serviço",M18*L18,IF(H18="CÉLULA CONSTRUTIVA",SUMIFS($N$8:$N$452,$B$8:$B$452,B18,$H$8:$H$452,"Serviço"),IF(H18="ETAPA",SUMIFS($N$8:$N$452,$B$8:$B$452,B18,$C$8:$C$452,C18,$H$8:$H$452,"Serviço"),IF(H18="SUBETAPA",SUMIFS($N$8:$N$452,$B$8:$B$452,B18,$C$8:$C$452,C18,$D$8:$D$452,D18,$H$8:$H$452,"Serviço"),0)))) -> 0 | O18: Quantidades referentes ao levantamento cartesiano, com base nnos projetos e adicionado o levantado pelo projetista nas áres de piso armado | P18: Finalizado
A19: =IF($H19="UNIDADE CONSTRUTIVA",OFFSET(A19,-1,0)+1,LARGE(A$3:A18,1)) -> 0 | B19: =IF(H19="UNIDADE CONSTRUTIVA",0,IF(H19="CÉLULA CONSTRUTIVA",OFFSET(B19,-1,0)+1,OFFSET(B19,-1,0))) -> 1 | C19: =IF(H19="CÉLULA CONSTRUTIVA",0,IF(H19="ETAPA",OFFSET(C19,-1,0)+1,OFFSET(C19,-1,0))) -> 1 | D19: =IF(H19="ETAPA",0,IF(H19="SUBETAPA",OFFSET(D19,-1,0)+1,OFFSET(D19,-1,0))) -> 4 | E19: =IF(H19="Subetapa",0,IF(H19="serviço",OFFSET(E19,-1,0)+1,OFFSET(E19,-1,0))) -> 0 | H19: SUBETAPA | I19: =IF(H19="Unidade Construtiva",TEXT(A19,"00"),IF(H19="Célula Construtiva",TEXT(B19,"00"),IF(H19="Etapa",CONCATENATE(TEXT(B19,"00"),".",TEXT(C19,"000")),IF(H19="Subetapa",CONCATENATE(TEXT(B19,"00"),".",TEXT(C19,"000"),".",TEXT(D19,"000")),IF(H19="Serviço",CONCATENATE(TEXT(B19,"00"),".",TEXT(C19,"000"),".",TEXT(D19,"000"),".",TEXT(E19,"000")),""))))) -> 01.001.004 | J19: Movimentação de bota - fora | N19: =IF(H19="Serviço",M19*L19,IF(H19="CÉLULA CONSTRUTIVA",SUMIFS($N$8:$N$452,$B$8:$B$452,B19,$H$8:$H$452,"Serviço"),IF(H19="ETAPA",SUMIFS($N$8:$N$452,$B$8:$B$452,B19,$C$8:$C$452,C19,$H$8:$H$452,"Serviço"),IF(H19="SUBETAPA",SUMIFS($N$8:$N$452,$B$8:$B$452,B19,$C$8:$C$452,C19,$D$8:$D$452,D19,$H$8:$H$452,"Serviço"),0)))) -> 0 | O19: =N19/'Obra '!$E$9 -> 0
A20: =IF($H20="UNIDADE CONSTRUTIVA",OFFSET(A20,-1,0)+1,LARGE(A$3:A19,1)) -> 0 | B20: =IF(H20="UNIDADE CONSTRUTIVA",0,IF(H20="CÉLULA CONSTRUTIVA",OFFSET(B20,-1,0)+1,OFFSET(B20,-1,0))) -> 1 | C20: =IF(H20="CÉLULA CONSTRUTIVA",0,IF(H20="ETAPA",OFFSET(C20,-1,0)+1,OFFSET(C20,-1,0))) -> 1 | D20: =IF(H20="ETAPA",0,IF(H20="SUBETAPA",OFFSET(D20,-1,0)+1,OFFSET(D20,-1,0))) -> 4 | E20: =IF(H20="Subetapa",0,IF(H20="serviço",OFFSET(E20,-1,0)+1,OFFSET(E20,-1,0))) -> 1 | H20: SERVIÇO | I20: =IF(H20="Unidade Construtiva",TEXT(A20,"00"),IF(H20="Célula Construtiva",TEXT(B20,"00"),IF(H20="Etapa",CONCATENATE(TEXT(B20,"00"),".",TEXT(C20,"000")),IF(H20="Subetapa",CONCATENATE(TEXT(B20,"00"),".",TEXT(C20,"000"),".",TEXT(D20,"000")),IF(H20="Serviço",CONCATENATE(TEXT(B20,"00"),".",TEXT(C20,"000"),".",TEXT(D20,"000"),".",TEXT(E20,"000")),""))))) -> 01.001.004.001 | J20: Movimentação de terra para bota-fora - Escavação Vertical Terraplenagem | K20: m3 | M20: =_xlfn.XLOOKUP($J20,CPU!$D$1:$D$3085,CPU!$H$1:$H$3085) -> 45.45 | N20: =IF(H20="Serviço",M20*L20,IF(H20="CÉLULA CONSTRUTIVA",SUMIFS($N$8:$N$452,$B$8:$B$452,B20,$H$8:$H$452,"Serviço"),IF(H20="ETAPA",SUMIFS($N$8:$N$452,$B$8:$B$452,B20,$C$8:$C$452,C20,$H$8:$H$452,"Serviço"),IF(H20="SUBETAPA",SUMIFS($N$8:$N$452,$B$8:$B$452,B20,$C$8:$C$452,C20,$D$8:$D$452,D20,$H$8:$H$452,"Serviço"),0)))) -> 0 | O20: Bota fora do subsolo | P20: Finalizado
A21: =IF($H21="UNIDADE CONSTRUTIVA",OFFSET(A21,-1,0)+1,LARGE(A$3:A20,1)) -> 0 | B21: =IF(H21="UNIDADE CONSTRUTIVA",0,IF(H21="CÉLULA CONSTRUTIVA",OFFSET(B21,-1,0)+1,OFFSET(B21,-1,0))) -> 1 | C21: =IF(H21="CÉLULA CONSTRUTIVA",0,IF(H21="ETAPA",OFFSET(C21,-1,0)+1,OFFSET(C21,-1,0))) -> 1 | D21: =IF(H21="ETAPA",0,IF(H21="SUBETAPA",OFFSET(D21,-1,0)+1,OFFSET(D21,-1,0))) -> 4 | E21: =IF(H21="Subetapa",0,IF(H21="serviço",OFFSET(E21,-1,0)+1,OFFSET(E21,-1,0))) -> 2 | H21: SERVIÇO | I21: =IF(H21="Unidade Construtiva",TEXT(A21,"00"),IF(H21="Célula Construtiva",TEXT(B21,"00"),IF(H21="Etapa",CONCATENATE(TEXT(B21,"00"),".",TEXT(C21,"000")),IF(H21="Subetapa",CONCATENATE(TEXT(B21,"00"),".",TEXT(C21,"000"),".",TEXT(D21,"000")),IF(H21="Serviço",CONCATENATE(TEXT(B21,"00"),".",TEXT(C21,"000"),".",TEXT(D21,"000"),".",TEXT(E21,"000")),""))))) -> 01.001.004.002 | J21: Movimentação de terra para bota-fora - Escavação de Valas | K21: m3 | M21: =_xlfn.XLOOKUP($J21,CPU!$D$1:$D$3085,CPU!$H$1:$H$3085) -> 45.45 | N21: =IF(H21="Serviço",M21*L21,IF(H21="CÉLULA CONSTRUTIVA",SUMIFS($N$8:$N$452,$B$8:$B$452,B21,$H$8:$H$452,"Serviço"),IF(H21="ETAPA",SUMIFS($N$8:$N$452,$B$8:$B$452,B21,$C$8:$C$452,C21,$H$8:$H$452,"Serviço"),IF(H21="SUBETAPA",SUMIFS($N$8:$N$452,$B$8:$B$452,B21,$C$8:$C$452,C21,$D$8:$D$452,D21,$H$8:$H$452,"Serviço"),0)))) -> 0 | P21: Finalizado
A22: =IF($H22="UNIDADE CONSTRUTIVA",OFFSET(A22,-1,0)+1,LARGE(A$3:A21,1)) -> 0 | B22: =IF(H22="UNIDADE CONSTRUTIVA",0,IF(H22="CÉLULA CONSTRUTIVA",OFFSET(B22,-1,0)+1,OFFSET(B22,-1,0))) -> 1 | C22: =IF(H22="CÉLULA CONSTRUTIVA",0,IF(H22="ETAPA",OFFSET(C22,-1,0)+1,OFFSET(C22,-1,0))) -> 1 | D22: =IF(H22="ETAPA",0,IF(H22="SUBETAPA",OFFSET(D22,-1,0)+1,OFFSET(D22,-1,0))) -> 4 | E22: =IF(H22="Subetapa",0,IF(H22="serviço",OFFSET(E22,-1,0)+1,OFFSET(E22,-1,0))) -> 3 | H22: SERVIÇO | I22: =IF(H22="Unidade Construtiva",TEXT(A22,"00"),IF(H22="Célula Construtiva",TEXT(B22,"00"),IF(H22="Etapa",CONCATENATE(TEXT(B22,"00"),".",TEXT(C22,"000")),IF(H22="Subetapa",CONCATENATE(TEXT(B22,"00"),".",TEXT(C22,"000"),".",TEXT(D22,"000")),IF(H22="Serviço",CONCATENATE(TEXT(B22,"00"),".",TEXT(C22,"000"),".",TEXT(D22,"000"),".",TEXT(E22,"000")),""))))) -> 01.001.004.003 | J22: Movimentação de terra para bota-fora - Estacas | K22: m3 | M22: =_xlfn.XLOOKUP($J22,CPU!$D$1:$D$3085,CPU!$H$1:$H$3085) -> 68.18 | N22: =IF(H22="Serviço",M22*L22,IF(H22="CÉLULA CONSTRUTIVA",SUMIFS($N$8:$N$452,$B$8:$B$452,B22,$H$8:$H$452,"Serviço"),IF(H22="ETAPA",SUMIFS($N$8:$N$452,$B$8:$B$452,B22,$C$8:$C$452,C22,$H$8:$H$452,"Serviço"),IF(H22="SUBETAPA",SUMIFS($N$8:$N$452,$B$8:$B$452,B22,$C$8:$C$452,C22,$D$8:$D$452,D22,$H$8:$H$452,"Serviço"),0)))) -> 0 | O22: Considerado estacas e contenção, conforme repassado pelo projetista | P22: Finalizado
A23: =IF($H23="UNIDADE CONSTRUTIVA",OFFSET(A23,-1,0)+1,LARGE(A$3:A22,1)) -> 0 | B23: =IF(H23="UNIDADE CONSTRUTIVA",0,IF(H23="CÉLULA CONSTRUTIVA",OFFSET(B23,-1,0)+1,OFFSET(B23,-1,0))) -> 2 | C23: =IF(H23="CÉLULA CONSTRUTIVA",0,IF(H23="ETAPA",OFFSET(C23,-1,0)+1,OFFSET(C23,-1,0))) -> 0 | D23: =IF(H23="ETAPA",0,IF(H23="SUBETAPA",OFFSET(D23,-1,0)+1,OFFSET(D23,-1,0))) -> 4 | E23: =IF(H23="Subetapa",0,IF(H23="serviço",OFFSET(E23,-1,0)+1,OFFSET(E23,-1,0))) -> 3 | H23: CÉLULA CONSTRUTIVA | I23: =IF(H23="Unidade Construtiva",TEXT(A23,"00"),IF(H23="Célula Construtiva",TEXT(B23,"00"),IF(H23="Etapa",CONCATENATE(TEXT(B23,"00"),".",TEXT(C23,"000")),IF(H23="Subetapa",CONCATENATE(TEXT(B23,"00"),".",TEXT(C23,"000"),".",TEXT(D23,"000")),IF(H23="Serviço",CONCATENATE(TEXT(B23,"00"),".",TEXT(C23,"000"),".",TEXT(D23,"000"),".",TEXT(E23,"000")),""))))) -> 02 | J23: INFRAESTRUTURA | N23: =IF(H23="Serviço",M23*L23,IF(H23="CÉLULA CONSTRUTIVA",SUMIFS($N$8:$N$452,$B$8:$B$452,B23,$H$8:$H$452,"Serviço"),IF(H23="ETAPA",SUMIFS($N$8:$N$452,$B$8:$B$452,B23,$C$8:$C$452,C23,$H$8:$H$452,"Serviço"),IF(H23="SUBETAPA",SUMIFS($N$8:$N$452,$B$8:$B$452,B23,$C$8:$C$452,C23,$D$8:$D$452,D23,$H$8:$H$452,"Serviço"),0)))) -> 0 | O23: =N23/'Obra '!$E$9 -> 0 | Q23: INFRAESTRUTURA
A24: =IF($H24="UNIDADE CONSTRUTIVA",OFFSET(A24,-1,0)+1,LARGE(A$3:A23,1)) -> 0 | B24: =IF(H24="UNIDADE CONSTRUTIVA",0,IF(H24="CÉLULA CONSTRUTIVA",OFFSET(B24,-1,0)+1,OFFSET(B24,-1,0))) -> 2 | C24: =IF(H24="CÉLULA CONSTRUTIVA",0,IF(H24="ETAPA",OFFSET(C24,-1,0)+1,OFFSET(C24,-1,0))) -> 1 | D24: =IF(H24="ETAPA",0,IF(H24="SUBETAPA",OFFSET(D24,-1,0)+1,OFFSET(D24,-1,0))) -> 0 | E24: =IF(H24="Subetapa",0,IF(H24="serviço",OFFSET(E24,-1,0)+1,OFFSET(E24,-1,0))) -> 3 | H24: ETAPA | I24: =IF(H24="Unidade Construtiva",TEXT(A24,"00"),IF(H24="Célula Construtiva",TEXT(B24,"00"),IF(H24="Etapa",CONCATENATE(TEXT(B24,"00"),".",TEXT(C24,"000")),IF(H24="Subetapa",CONCATENATE(TEXT(B24,"00"),".",TEXT(C24,"000"),".",TEXT(D24,"000")),IF(H24="Serviço",CONCATENATE(TEXT(B24,"00"),".",TEXT(C24,"000"),".",TEXT(D24,"000"),".",TEXT(E24,"000")),""))))) -> 02.001 | J24: FUNDAÇÃO PROFUNDA | N24: =IF(H24="Serviço",M24*L24,IF(H24="CÉLULA CONSTRUTIVA",SUMIFS($N$8:$N$452,$B$8:$B$452,B24,$H$8:$H$452,"Serviço"),IF(H24="ETAPA",SUMIFS($N$8:$N$452,$B$8:$B$452,B24,$C$8:$C$452,C24,$H$8:$H$452,"Serviço"),IF(H24="SUBETAPA",SUMIFS($N$8:$N$452,$B$8:$B$452,B24,$C$8:$C$452,C24,$D$8:$D$452,D24,$H$8:$H$452,"Serviço"),0)))) -> 0 | O24: =N24/'Obra '!$E$9 -> 0
A25: =IF($H25="UNIDADE CONSTRUTIVA",OFFSET(A25,-1,0)+1,LARGE(A$3:A24,1)) -> 0 | B25: =IF(H25="UNIDADE CONSTRUTIVA",0,IF(H25="CÉLULA CONSTRUTIVA",OFFSET(B25,-1,0)+1,OFFSET(B25,-1,0))) -> 2 | C25: =IF(H25="CÉLULA CONSTRUTIVA",0,IF(H25="ETAPA",OFFSET(C25,-1,0)+1,OFFSET(C25,-1,0))) -> 1 | D25: =IF(H25="ETAPA",0,IF(H25="SUBETAPA",OFFSET(D25,-1,0)+1,OFFSET(D25,-1,0))) -> 1 | E25: =IF(H25="Subetapa",0,IF(H25="serviço",OFFSET(E25,-1,0)+1,OFFSET(E25,-1,0))) -> 0 | H25: SUBETAPA | I25: =IF(H25="Unidade Construtiva",TEXT(A25,"00"),IF(H25="Célula Construtiva",TEXT(B25,"00"),IF(H25="Etapa",CONCATENATE(TEXT(B25,"00"),".",TEXT(C25,"000")),IF(H25="Subetapa",CONCATENATE(TEXT(B25,"00"),".",TEXT(C25,"000"),".",TEXT(D25,"000")),IF(H25="Serviço",CONCATENATE(TEXT(B25,"00"),".",TEXT(C25,"000"),".",TEXT(D25,"000"),".",TEXT(E25,"000")),""))))) -> 02.001.001 | J25: Perfuração | N25: =IF(H25="Serviço",M25*L25,IF(H25="CÉLULA CONSTRUTIVA",SUMIFS($N$8:$N$452,$B$8:$B$452,B25,$H$8:$H$452,"Serviço"),IF(H25="ETAPA",SUMIFS($N$8:$N$452,$B$8:$B$452,B25,$C$8:$C$452,C25,$H$8:$H$452,"Serviço"),IF(H25="SUBETAPA",SUMIFS($N$8:$N$452,$B$8:$B$452,B25,$C$8:$C$452,C25,$D$8:$D$452,D25,$H$8:$H$452,"Serviço"),0)))) -> 0
A26: =IF($H26="UNIDADE CONSTRUTIVA",OFFSET(A26,-1,0)+1,LARGE(A$3:A25,1)) -> 0 | B26: =IF(H26="UNIDADE CONSTRUTIVA",0,IF(H26="CÉLULA CONSTRUTIVA",OFFSET(B26,-1,0)+1,OFFSET(B26,-1,0))) -> 2 | C26: =IF(H26="CÉLULA CONSTRUTIVA",0,IF(H26="ETAPA",OFFSET(C26,-1,0)+1,OFFSET(C26,-1,0))) -> 1 | D26: =IF(H26="ETAPA",0,IF(H26="SUBETAPA",OFFSET(D26,-1,0)+1,OFFSET(D26,-1,0))) -> 1 | E26: =IF(H26="Subetapa",0,IF(H26="serviço",OFFSET(E26,-1,0)+1,OFFSET(E26,-1,0))) -> 1 | H26: SERVIÇO | I26: =IF(H26="Unidade Construtiva",TEXT(A26,"00"),IF(H26="Célula Construtiva",TEXT(B26,"00"),IF(H26="Etapa",CONCATENATE(TEXT(B26,"00"),".",TEXT(C26,"000")),IF(H26="Subetapa",CONCATENATE(TEXT(B26,"00"),".",TEXT(C26,"000"),".",TEXT(D26,"000")),IF(H26="Serviço",CONCATENATE(TEXT(B26,"00"),".",TEXT(C26,"000"),".",TEXT(D26,"000"),".",TEXT(E26,"000")),""))))) -> 02.001.001.001 | J26: Execucao Estaca Escavada 030Cm | K26: m | M26: =_xlfn.XLOOKUP($J26,CPU!$D$1:$D$3085,CPU!$H$1:$H$3085) -> 39 | N26: =IF(H26="Serviço",M26*L26,IF(H26="CÉLULA CONSTRUTIVA",SUMIFS($N$8:$N$452,$B$8:$B$452,B26,$H$8:$H$452,"Serviço"),IF(H26="ETAPA",SUMIFS($N$8:$N$452,$B$8:$B$452,B26,$C$8:$C$452,C26,$H$8:$H$452,"Serviço"),IF(H26="SUBETAPA",SUMIFS($N$8:$N$452,$B$8:$B$452,B26,$C$8:$C$452,C26,$D$8:$D$452,D26,$H$8:$H$452,"Serviço"),0)))) -> 0 | P26: Finalizado
A27: =IF($H27="UNIDADE CONSTRUTIVA",OFFSET(A27,-1,0)+1,LARGE(A$3:A26,1)) -> 0 | B27: =IF(H27="UNIDADE CONSTRUTIVA",0,IF(H27="CÉLULA CONSTRUTIVA",OFFSET(B27,-1,0)+1,OFFSET(B27,-1,0))) -> 2 | C27: =IF(H27="CÉLULA CONSTRUTIVA",0,IF(H27="ETAPA",OFFSET(C27,-1,0)+1,OFFSET(C27,-1,0))) -> 1 | D27: =IF(H27="ETAPA",0,IF(H27="SUBETAPA",OFFSET(D27,-1,0)+1,OFFSET(D27,-1,0))) -> 1 | E27: =IF(H27="Subetapa",0,IF(H27="serviço",OFFSET(E27,-1,0)+1,OFFSET(E27,-1,0))) -> 2 | H27: SERVIÇO | I27: =IF(H27="Unidade Construtiva",TEXT(A27,"00"),IF(H27="Célula Construtiva",TEXT(B27,"00"),IF(H27="Etapa",CONCATENATE(TEXT(B27,"00"),".",TEXT(C27,"000")),IF(H27="Subetapa",CONCATENATE(TEXT(B27,"00"),".",TEXT(C27,"000"),".",TEXT(D27,"000")),IF(H27="Serviço",CONCATENATE(TEXT(B27,"00"),".",TEXT(C27,"000"),".",TEXT(D27,"000"),".",TEXT(E27,"000")),""))))) -> 02.001.001.002 | J27: Execucao Estaca Escavada 040Cm | K27: m | M27: =_xlfn.XLOOKUP($J27,CPU!$D$1:$D$3085,CPU!$H$1:$H$3085) -> 52.8 | N27: =IF(H27="Serviço",M27*L27,IF(H27="CÉLULA CONSTRUTIVA",SUMIFS($N$8:$N$452,$B$8:$B$452,B27,$H$8:$H$452,"Serviço"),IF(H27="ETAPA",SUMIFS($N$8:$N$452,$B$8:$B$452,B27,$C$8:$C$452,C27,$H$8:$H$452,"Serviço"),IF(H27="SUBETAPA",SUMIFS($N$8:$N$452,$B$8:$B$452,B27,$C$8:$C$452,C27,$D$8:$D$452,D27,$H$8:$H$452,"Serviço"),0)))) -> 0 | P27: Finalizado
A28: =IF($H28="UNIDADE CONSTRUTIVA",OFFSET(A28,-1,0)+1,LARGE(A$3:A27,1)) -> 0 | B28: =IF(H28="UNIDADE CONSTRUTIVA",0,IF(H28="CÉLULA CONSTRUTIVA",OFFSET(B28,-1,0)+1,OFFSET(B28,-1,0))) -> 2 | C28: =IF(H28="CÉLULA CONSTRUTIVA",0,IF(H28="ETAPA",OFFSET(C28,-1,0)+1,OFFSET(C28,-1,0))) -> 1 | D28: =IF(H28="ETAPA",0,IF(H28="SUBETAPA",OFFSET(D28,-1,0)+1,OFFSET(D28,-1,0))) -> 1 | E28: =IF(H28="Subetapa",0,IF(H28="serviço",OFFSET(E28,-1,0)+1,OFFSET(E28,-1,0))) -> 3 | H28: SERVIÇO | I28: =IF(H28="Unidade Construtiva",TEXT(A28,"00"),IF(H28="Célula Construtiva",TEXT(B28,"00"),IF(H28="Etapa",CONCATENATE(TEXT(B28,"00"),".",TEXT(C28,"000")),IF(H28="Subetapa",CONCATENATE(TEXT(B28,"00"),".",TEXT(C28,"000"),".",TEXT(D28,"000")),IF(H28="Serviço",CONCATENATE(TEXT(B28,"00"),".",TEXT(C28,"000"),".",TEXT(D28,"000"),".",TEXT(E28,"000")),""))))) -> 02.001.001.003 | J28: Execucao Estaca Escavada 050Cm | K28: m | M28: =_xlfn.XLOOKUP($J28,CPU!$D$1:$D$3085,CPU!$H$1:$H$3085) -> 66 | N28: =IF(H28="Serviço",M28*L28,IF(H28="CÉLULA CONSTRUTIVA",SUMIFS($N$8:$N$452,$B$8:$B$452,B28,$H$8:$H$452,"Serviço"),IF(H28="ETAPA",SUMIFS($N$8:$N$452,$B$8:$B$452,B28,$C$8:$C$452,C28,$H$8:$H$452,"Serviço"),IF(H28="SUBETAPA",SUMIFS($N$8:$N$452,$B$8:$B$452,B28,$C$8:$C$452,C28,$D$8:$D$452,D28,$H$8:$H$452,"Serviço"),0)))) -> 0 | P28: Finalizado
A29: =IF($H29="UNIDADE CONSTRUTIVA",OFFSET(A29,-1,0)+1,LARGE(A$3:A28,1)) -> 0 | B29: =IF(H29="UNIDADE CONSTRUTIVA",0,IF(H29="CÉLULA CONSTRUTIVA",OFFSET(B29,-1,0)+1,OFFSET(B29,-1,0))) -> 2 | C29: =IF(H29="CÉLULA CONSTRUTIVA",0,IF(H29="ETAPA",OFFSET(C29,-1,0)+1,OFFSET(C29,-1,0))) -> 1 | D29: =IF(H29="ETAPA",0,IF(H29="SUBETAPA",OFFSET(D29,-1,0)+1,OFFSET(D29,-1,0))) -> 1 | E29: =IF(H29="Subetapa",0,IF(H29="serviço",OFFSET(E29,-1,0)+1,OFFSET(E29,-1,0))) -> 4 | H29: SERVIÇO | I29: =IF(H29="Unidade Construtiva",TEXT(A29,"00"),IF(H29="Célula Construtiva",TEXT(B29,"00"),IF(H29="Etapa",CONCATENATE(TEXT(B29,"00"),".",TEXT(C29,"000")),IF(H29="Subetapa",CONCATENATE(TEXT(B29,"00"),".",TEXT(C29,"000"),".",TEXT(D29,"000")),IF(H29="Serviço",CONCATENATE(TEXT(B29,"00"),".",TEXT(C29,"000"),".",TEXT(D29,"000"),".",TEXT(E29,"000")),""))))) -> 02.001.001.004 | J29: Execucao Estaca Escavada 060Cm | K29: m | M29: =_xlfn.XLOOKUP($J29,CPU!$D$1:$D$3085,CPU!$H$1:$H$3085) -> 79.2 | N29: =IF(H29="Serviço",M29*L29,IF(H29="CÉLULA CONSTRUTIVA",SUMIFS($N$8:$N$452,$B$8:$B$452,B29,$H$8:$H$452,"Serviço"),IF(H29="ETAPA",SUMIFS($N$8:$N$452,$B$8:$B$452,B29,$C$8:$C$452,C29,$H$8:$H$452,"Serviço"),IF(H29="SUBETAPA",SUMIFS($N$8:$N$452,$B$8:$B$452,B29,$C$8:$C$452,C29,$D$8:$D$452,D29,$H$8:$H$452,"Serviço"),0)))) -> 0 | P29: Finalizado
A30: =IF($H30="UNIDADE CONSTRUTIVA",OFFSET(A30,-1,0)+1,LARGE(A$3:A29,1)) -> 0 | B30: =IF(H30="UNIDADE CONSTRUTIVA",0,IF(H30="CÉLULA CONSTRUTIVA",OFFSET(B30,-1,0)+1,OFFSET(B30,-1,0))) -> 2 | C30: =IF(H30="CÉLULA CONSTRUTIVA",0,IF(H30="ETAPA",OFFSET(C30,-1,0)+1,OFFSET(C30,-1,0))) -> 1 | D30: =IF(H30="ETAPA",0,IF(H30="SUBETAPA",OFFSET(D30,-1,0)+1,OFFSET(D30,-1,0))) -> 1 | E30: =IF(H30="Subetapa",0,IF(H30="serviço",OFFSET(E30,-1,0)+1,OFFSET(E30,-1,0))) -> 5 | H30: SERVIÇO | I30: =IF(H30="Unidade Construtiva",TEXT(A30,"00"),IF(H30="Célula Construtiva",TEXT(B30,"00"),IF(H30="Etapa",CONCATENATE(TEXT(B30,"00"),".",TEXT(C30,"000")),IF(H30="Subetapa",CONCATENATE(TEXT(B30,"00"),".",TEXT(C30,"000"),".",TEXT(D30,"000")),IF(H30="Serviço",CONCATENATE(TEXT(B30,"00"),".",TEXT(C30,"000"),".",TEXT(D30,"000"),".",TEXT(E30,"000")),""))))) -> 02.001.001.005 | J30: Execucao Estaca Escavada 070Cm | K30: m | M30: =_xlfn.XLOOKUP($J30,CPU!$D$1:$D$3085,CPU!$H$1:$H$3085) -> 92.4 | N30: =IF(H30="Serviço",M30*L30,IF(H30="CÉLULA CONSTRUTIVA",SUMIFS($N$8:$N$452,$B$8:$B$452,B30,$H$8:$H$452,"Serviço"),IF(H30="ETAPA",SUMIFS($N$8:$N$452,$B$8:$B$452,B30,$C$8:$C$452,C30,$H$8:$H$452,"Serviço"),IF(H30="SUBETAPA",SUMIFS($N$8:$N$452,$B$8:$B$452,B30,$C$8:$C$452,C30,$D$8:$D$452,D30,$H$8:$H$452,"Serviço"),0)))) -> 0 | P30: Finalizado
A31: =IF($H31="UNIDADE CONSTRUTIVA",OFFSET(A31,-1,0)+1,LARGE(A$3:A30,1)) -> 0 | B31: =IF(H31="UNIDADE CONSTRUTIVA",0,IF(H31="CÉLULA CONSTRUTIVA",OFFSET(B31,-1,0)+1,OFFSET(B31,-1,0))) -> 2 | C31: =IF(H31="CÉLULA CONSTRUTIVA",0,IF(H31="ETAPA",OFFSET(C31,-1,0)+1,OFFSET(C31,-1,0))) -> 1 | D31: =IF(H31="ETAPA",0,IF(H31="SUBETAPA",OFFSET(D31,-1,0)+1,OFFSET(D31,-1,0))) -> 1 | E31: =IF(H31="Subetapa",0,IF(H31="serviço",OFFSET(E31,-1,0)+1,OFFSET(E31,-1,0))) -> 6 | H31: SERVIÇO | I31: =IF(H31="Unidade Construtiva",TEXT(A31,"00"),IF(H31="Célula Construtiva",TEXT(B31,"00"),IF(H31="Etapa",CONCATENATE(TEXT(B31,"00"),".",TEXT(C31,"000")),IF(H31="Subetapa",CONCATENATE(TEXT(B31,"00"),".",TEXT(C31,"000"),".",TEXT(D31,"000")),IF(H31="Serviço",CONCATENATE(TEXT(B31,"00"),".",TEXT(C31,"000"),".",TEXT(D31,"000"),".",TEXT(E31,"000")),""))))) -> 02.001.001.006 | J31: Execucao Estaca Escavada 080Cm | K31: m | M31: =_xlfn.XLOOKUP($J31,CPU!$D$1:$D$3085,CPU!$H$1:$H$3085) -> 105.6 | N31: =IF(H31="Serviço",M31*L31,IF(H31="CÉLULA CONSTRUTIVA",SUMIFS($N$8:$N$452,$B$8:$B$452,B31,$H$8:$H$452,"Serviço"),IF(H31="ETAPA",SUMIFS($N$8:$N$452,$B$8:$B$452,B31,$C$8:$C$452,C31,$H$8:$H$452,"Serviço"),IF(H31="SUBETAPA",SUMIFS($N$8:$N$452,$B$8:$B$452,B31,$C$8:$C$452,C31,$D$8:$D$452,D31,$H$8:$H$452,"Serviço"),0)))) -> 0 | P31: Finalizado
A32: =IF($H32="UNIDADE CONSTRUTIVA",OFFSET(A32,-1,0)+1,LARGE(A$3:A31,1)) -> 0 | B32: =IF(H32="UNIDADE CONSTRUTIVA",0,IF(H32="CÉLULA CONSTRUTIVA",OFFSET(B32,-1,0)+1,OFFSET(B32,-1,0))) -> 2 | C32: =IF(H32="CÉLULA CONSTRUTIVA",0,IF(H32="ETAPA",OFFSET(C32,-1,0)+1,OFFSET(C32,-1,0))) -> 1 | D32: =IF(H32="ETAPA",0,IF(H32="SUBETAPA",OFFSET(D32,-1,0)+1,OFFSET(D32,-1,0))) -> 1 | E32: =IF(H32="Subetapa",0,IF(H32="serviço",OFFSET(E32,-1,0)+1,OFFSET(E32,-1,0))) -> 7 | H32: SERVIÇO | I32: =IF(H32="Unidade Construtiva",TEXT(A32,"00"),IF(H32="Célula Construtiva",TEXT(B32,"00"),IF(H32="Etapa",CONCATENATE(TEXT(B32,"00"),".",TEXT(C32,"000")),IF(H32="Subetapa",CONCATENATE(TEXT(B32,"00"),".",TEXT(C32,"000"),".",TEXT(D32,"000")),IF(H32="Serviço",CONCATENATE(TEXT(B32,"00"),".",TEXT(C32,"000"),".",TEXT(D32,"000"),".",TEXT(E32,"000")),""))))) -> 02.001.001.007 | J32: Mobilização e desmobilização de equipamentos - Para execução de estaca Escavada | K32: vb | M32: =_xlfn.XLOOKUP($J32,CPU!$D$1:$D$3085,CPU!$H$1:$H$3085) -> 26000 | N32: =IF(H32="Serviço",M32*L32,IF(H32="CÉLULA CONSTRUTIVA",SUMIFS($N$8:$N$452,$B$8:$B$452,B32,$H$8:$H$452,"Serviço"),IF(H32="ETAPA",SUMIFS($N$8:$N$452,$B$8:$B$452,B32,$C$8:$C$452,C32,$H$8:$H$452,"Serviço"),IF(H32="SUBETAPA",SUMIFS($N$8:$N$452,$B$8:$B$452,B32,$C$8:$C$452,C32,$D$8:$D$452,D32,$H$8:$H$452,"Serviço"),0)))) -> 0 | P32: Finalizado
A33: =IF($H33="UNIDADE CONSTRUTIVA",OFFSET(A33,-1,0)+1,LARGE(A$3:A32,1)) -> 0 | B33: =IF(H33="UNIDADE CONSTRUTIVA",0,IF(H33="CÉLULA CONSTRUTIVA",OFFSET(B33,-1,0)+1,OFFSET(B33,-1,0))) -> 2 | C33: =IF(H33="CÉLULA CONSTRUTIVA",0,IF(H33="ETAPA",OFFSET(C33,-1,0)+1,OFFSET(C33,-1,0))) -> 1 | D33: =IF(H33="ETAPA",0,IF(H33="SUBETAPA",OFFSET(D33,-1,0)+1,OFFSET(D33,-1,0))) -> 2 | E33: =IF(H33="Subetapa",0,IF(H33="serviço",OFFSET(E33,-1,0)+1,OFFSET(E33,-1,0))) -> 0 | H33: SUBETAPA | I33: =IF(H33="Unidade Construtiva",TEXT(A33,"00"),IF(H33="Célula Construtiva",TEXT(B33,"00"),IF(H33="Etapa",CONCATENATE(TEXT(B33,"00"),".",TEXT(C33,"000")),IF(H33="Subetapa",CONCATENATE(TEXT(B33,"00"),".",TEXT(C33,"000"),".",TEXT(D33,"000")),IF(H33="Serviço",CONCATENATE(TEXT(B33,"00"),".",TEXT(C33,"000"),".",TEXT(D33,"000"),".",TEXT(E33,"000")),""))))) -> 02.001.002 | J33: Armadura | N33: =IF(H33="Serviço",M33*L33,IF(H33="CÉLULA CONSTRUTIVA",SUMIFS($N$8:$N$452,$B$8:$B$452,B33,$H$8:$H$452,"Serviço"),IF(H33="ETAPA",SUMIFS($N$8:$N$452,$B$8:$B$452,B33,$C$8:$C$452,C33,$H$8:$H$452,"Serviço"),IF(H33="SUBETAPA",SUMIFS($N$8:$N$452,$B$8:$B$452,B33,$C$8:$C$452,C33,$D$8:$D$452,D33,$H$8:$H$452,"Serviço"),0)))) -> 0
A34: =IF($H34="UNIDADE CONSTRUTIVA",OFFSET(A34,-1,0)+1,LARGE(A$3:A33,1)) -> 0 | B34: =IF(H34="UNIDADE CONSTRUTIVA",0,IF(H34="CÉLULA CONSTRUTIVA",OFFSET(B34,-1,0)+1,OFFSET(B34,-1,0))) -> 2 | C34: =IF(H34="CÉLULA CONSTRUTIVA",0,IF(H34="ETAPA",OFFSET(C34,-1,0)+1,OFFSET(C34,-1,0))) -> 1 | D34: =IF(H34="ETAPA",0,IF(H34="SUBETAPA",OFFSET(D34,-1,0)+1,OFFSET(D34,-1,0))) -> 2 | E34: =IF(H34="Subetapa",0,IF(H34="serviço",OFFSET(E34,-1,0)+1,OFFSET(E34,-1,0))) -> 1 | H34: SERVIÇO | I34: =IF(H34="Unidade Construtiva",TEXT(A34,"00"),IF(H34="Célula Construtiva",TEXT(B34,"00"),IF(H34="Etapa",CONCATENATE(TEXT(B34,"00"),".",TEXT(C34,"000")),IF(H34="Subetapa",CONCATENATE(TEXT(B34,"00"),".",TEXT(C34,"000"),".",TEXT(D34,"000")),IF(H34="Serviço",CONCATENATE(TEXT(B34,"00"),".",TEXT(C34,"000"),".",TEXT(D34,"000"),".",TEXT(E34,"000")),""))))) -> 02.001.002.001 | J34: Armação aço CA-50 ø 6,3mm para estaca (corte e dobra em obra) | K34: kg | M34: =_xlfn.XLOOKUP($J34,CPU!$D$1:$D$3085,CPU!$H$1:$H$3085) -> 6.938145 | N34: =IF(H34="Serviço",M34*L34,IF(H34="CÉLULA CONSTRUTIVA",SUMIFS($N$8:$N$452,$B$8:$B$452,B34,$H$8:$H$452,"Serviço"),IF(H34="ETAPA",SUMIFS($N$8:$N$452,$B$8:$B$452,B34,$C$8:$C$452,C34,$H$8:$H$452,"Serviço"),IF(H34="SUBETAPA",SUMIFS($N$8:$N$452,$B$8:$B$452,B34,$C$8:$C$452,C34,$D$8:$D$452,D34,$H$8:$H$452,"Serviço"),0)))) -> 0 | P34: Finalizado
A35: =IF($H35="UNIDADE CONSTRUTIVA",OFFSET(A35,-1,0)+1,LARGE(A$3:A34,1)) -> 0 | B35: =IF(H35="UNIDADE CONSTRUTIVA",0,IF(H35="CÉLULA CONSTRUTIVA",OFFSET(B35,-1,0)+1,OFFSET(B35,-1,0))) -> 2 | C35: =IF(H35="CÉLULA CONSTRUTIVA",0,IF(H35="ETAPA",OFFSET(C35,-1,0)+1,OFFSET(C35,-1,0))) -> 1 | D35: =IF(H35="ETAPA",0,IF(H35="SUBETAPA",OFFSET(D35,-1,0)+1,OFFSET(D35,-1,0))) -> 2 | E35: =IF(H35="Subetapa",0,IF(H35="serviço",OFFSET(E35,-1,0)+1,OFFSET(E35,-1,0))) -> 2 | H35: SERVIÇO | I35: =IF(H35="Unidade Construtiva",TEXT(A35,"00"),IF(H35="Célula Construtiva",TEXT(B35,"00"),IF(H35="Etapa",CONCATENATE(TEXT(B35,"00"),".",TEXT(C35,"000")),IF(H35="Subetapa",CONCATENATE(TEXT(B35,"00"),".",TEXT(C35,"000"),".",TEXT(D35,"000")),IF(H35="Serviço",CONCATENATE(TEXT(B35,"00"),".",TEXT(C35,"000"),".",TEXT(D35,"000"),".",TEXT(E35,"000")),""))))) -> 02.001.002.002 | J35: Armação aço CA-50 ø 12,5mm para estaca (corte e dobra em obra) | K35: kg | M35: =_xlfn.XLOOKUP($J35,CPU!$D$1:$D$3085,CPU!$H$1:$H$3085) -> 6.443145 | N35: =IF(H35="Serviço",M35*L35,IF(H35="CÉLULA CONSTRUTIVA",SUMIFS($N$8:$N$452,$B$8:$B$452,B35,$H$8:$H$452,"Serviço"),IF(H35="ETAPA",SUMIFS($N$8:$N$452,$B$8:$B$452,B35,$C$8:$C$452,C35,$H$8:$H$452,"Serviço"),IF(H35="SUBETAPA",SUMIFS($N$8:$N$452,$B$8:$B$452,B35,$C$8:$C$452,C35,$D$8:$D$452,D35,$H$8:$H$452,"Serviço"),0)))) -> 0 | P35: Finalizado
A36: =IF($H36="UNIDADE CONSTRUTIVA",OFFSET(A36,-1,0)+1,LARGE(A$3:A35,1)) -> 0 | B36: =IF(H36="UNIDADE CONSTRUTIVA",0,IF(H36="CÉLULA CONSTRUTIVA",OFFSET(B36,-1,0)+1,OFFSET(B36,-1,0))) -> 2 | C36: =IF(H36="CÉLULA CONSTRUTIVA",0,IF(H36="ETAPA",OFFSET(C36,-1,0)+1,OFFSET(C36,-1,0))) -> 1 | D36: =IF(H36="ETAPA",0,IF(H36="SUBETAPA",OFFSET(D36,-1,0)+1,OFFSET(D36,-1,0))) -> 3 | E36: =IF(H36="Subetapa",0,IF(H36="serviço",OFFSET(E36,-1,0)+1,OFFSET(E36,-1,0))) -> 0 | H36: SUBETAPA | I36: =IF(H36="Unidade Construtiva",TEXT(A36,"00"),IF(H36="Célula Construtiva",TEXT(B36,"00"),IF(H36="Etapa",CONCATENATE(TEXT(B36,"00"),".",TEXT(C36,"000")),IF(H36="Subetapa",CONCATENATE(TEXT(B36,"00"),".",TEXT(C36,"000"),".",TEXT(D36,"000")),IF(H36="Serviço",CONCATENATE(TEXT(B36,"00"),".",TEXT(C36,"000"),".",TEXT(D36,"000"),".",TEXT(E36,"000")),""))))) -> 02.001.003 | J36: Concreto | N36: =IF(H36="Serviço",M36*L36,IF(H36="CÉLULA CONSTRUTIVA",SUMIFS($N$8:$N$452,$B$8:$B$452,B36,$H$8:$H$452,"Serviço"),IF(H36="ETAPA",SUMIFS($N$8:$N$452,$B$8:$B$452,B36,$C$8:$C$452,C36,$H$8:$H$452,"Serviço"),IF(H36="SUBETAPA",SUMIFS($N$8:$N$452,$B$8:$B$452,B36,$C$8:$C$452,C36,$D$8:$D$452,D36,$H$8:$H$452,"Serviço"),0)))) -> 0
A37: =IF($H37="UNIDADE CONSTRUTIVA",OFFSET(A37,-1,0)+1,LARGE(A$3:A36,1)) -> 0 | B37: =IF(H37="UNIDADE CONSTRUTIVA",0,IF(H37="CÉLULA CONSTRUTIVA",OFFSET(B37,-1,0)+1,OFFSET(B37,-1,0))) -> 2 | C37: =IF(H37="CÉLULA CONSTRUTIVA",0,IF(H37="ETAPA",OFFSET(C37,-1,0)+1,OFFSET(C37,-1,0))) -> 1 | D37: =IF(H37="ETAPA",0,IF(H37="SUBETAPA",OFFSET(D37,-1,0)+1,OFFSET(D37,-1,0))) -> 3 | E37: =IF(H37="Subetapa",0,IF(H37="serviço",OFFSET(E37,-1,0)+1,OFFSET(E37,-1,0))) -> 1 | H37: SERVIÇO | I37: =IF(H37="Unidade Construtiva",TEXT(A37,"00"),IF(H37="Célula Construtiva",TEXT(B37,"00"),IF(H37="Etapa",CONCATENATE(TEXT(B37,"00"),".",TEXT(C37,"000")),IF(H37="Subetapa",CONCATENATE(TEXT(B37,"00"),".",TEXT(C37,"000"),".",TEXT(D37,"000")),IF(H37="Serviço",CONCATENATE(TEXT(B37,"00"),".",TEXT(C37,"000"),".",TEXT(D37,"000"),".",TEXT(E37,"000")),""))))) -> 02.001.003.001 | J37: Concreto Usinado bombeável para estacas 25MPa - incluindo serviço de bombeamento | K37: m3 | M37: =_xlfn.XLOOKUP($J37,CPU!$D$1:$D$3085,CPU!$H$1:$H$3085) -> 693.66 | N37: =IF(H37="Serviço",M37*L37,IF(H37="CÉLULA CONSTRUTIVA",SUMIFS($N$8:$N$452,$B$8:$B$452,B37,$H$8:$H$452,"Serviço"),IF(H37="ETAPA",SUMIFS($N$8:$N$452,$B$8:$B$452,B37,$C$8:$C$452,C37,$H$8:$H$452,"Serviço"),IF(H37="SUBETAPA",SUMIFS($N$8:$N$452,$B$8:$B$452,B37,$C$8:$C$452,C37,$D$8:$D$452,D37,$H$8:$H$452,"Serviço"),0)))) -> 0 | P37: Finalizado
A38: =IF($H38="UNIDADE CONSTRUTIVA",OFFSET(A38,-1,0)+1,LARGE(A$3:A37,1)) -> 0 | B38: =IF(H38="UNIDADE CONSTRUTIVA",0,IF(H38="CÉLULA CONSTRUTIVA",OFFSET(B38,-1,0)+1,OFFSET(B38,-1,0))) -> 2 | C38: =IF(H38="CÉLULA CONSTRUTIVA",0,IF(H38="ETAPA",OFFSET(C38,-1,0)+1,OFFSET(C38,-1,0))) -> 1 | D38: =IF(H38="ETAPA",0,IF(H38="SUBETAPA",OFFSET(D38,-1,0)+1,OFFSET(D38,-1,0))) -> 4 | E38: =IF(H38="Subetapa",0,IF(H38="serviço",OFFSET(E38,-1,0)+1,OFFSET(E38,-1,0))) -> 0 | H38: SUBETAPA | I38: =IF(H38="Unidade Construtiva",TEXT(A38,"00"),IF(H38="Célula Construtiva",TEXT(B38,"00"),IF(H38="Etapa",CONCATENATE(TEXT(B38,"00"),".",TEXT(C38,"000")),IF(H38="Subetapa",CONCATENATE(TEXT(B38,"00"),".",TEXT(C38,"000"),".",TEXT(D38,"000")),IF(H38="Serviço",CONCATENATE(TEXT(B38,"00"),".",TEXT(C38,"000"),".",TEXT(D38,"000"),".",TEXT(E38,"000")),""))))) -> 02.001.004 | J38: Mão de Obra | N38: =IF(H38="Serviço",M38*L38,IF(H38="CÉLULA CONSTRUTIVA",SUMIFS($N$8:$N$452,$B$8:$B$452,B38,$H$8:$H$452,"Serviço"),IF(H38="ETAPA",SUMIFS($N$8:$N$452,$B$8:$B$452,B38,$C$8:$C$452,C38,$H$8:$H$452,"Serviço"),IF(H38="SUBETAPA",SUMIFS($N$8:$N$452,$B$8:$B$452,B38,$C$8:$C$452,C38,$D$8:$D$452,D38,$H$8:$H$452,"Serviço"),0)))) -> 0
A39: =IF($H39="UNIDADE CONSTRUTIVA",OFFSET(A39,-1,0)+1,LARGE(A$3:A38,1)) -> 0 | B39: =IF(H39="UNIDADE CONSTRUTIVA",0,IF(H39="CÉLULA CONSTRUTIVA",OFFSET(B39,-1,0)+1,OFFSET(B39,-1,0))) -> 2 | C39: =IF(H39="CÉLULA CONSTRUTIVA",0,IF(H39="ETAPA",OFFSET(C39,-1,0)+1,OFFSET(C39,-1,0))) -> 1 | D39: =IF(H39="ETAPA",0,IF(H39="SUBETAPA",OFFSET(D39,-1,0)+1,OFFSET(D39,-1,0))) -> 4 | E39: =IF(H39="Subetapa",0,IF(H39="serviço",OFFSET(E39,-1,0)+1,OFFSET(E39,-1,0))) -> 1 | H39: SERVIÇO | I39: =IF(H39="Unidade Construtiva",TEXT(A39,"00"),IF(H39="Célula Construtiva",TEXT(B39,"00"),IF(H39="Etapa",CONCATENATE(TEXT(B39,"00"),".",TEXT(C39,"000")),IF(H39="Subetapa",CONCATENATE(TEXT(B39,"00"),".",TEXT(C39,"000"),".",TEXT(D39,"000")),IF(H39="Serviço",CONCATENATE(TEXT(B39,"00"),".",TEXT(C39,"000"),".",TEXT(D39,"000"),".",TEXT(E39,"000")),""))))) -> 02.001.004.001 | J39: Corte e Preparo de Cabeça de Estaca | K39: un | M39: =_xlfn.XLOOKUP($J39,CPU!$D$1:$D$3085,CPU!$H$1:$H$3085) -> 300 | N39: =IF(H39="Serviço",M39*L39,IF(H39="CÉLULA CONSTRUTIVA",SUMIFS($N$8:$N$452,$B$8:$B$452,B39,$H$8:$H$452,"Serviço"),IF(H39="ETAPA",SUMIFS($N$8:$N$452,$B$8:$B$452,B39,$C$8:$C$452,C39,$H$8:$H$452,"Serviço"),IF(H39="SUBETAPA",SUMIFS($N$8:$N$452,$B$8:$B$452,B39,$C$8:$C$452,C39,$D$8:$D$452,D39,$H$8:$H$452,"Serviço"),0)))) -> 0 | P39: Finalizado
A40: =IF($H40="UNIDADE CONSTRUTIVA",OFFSET(A40,-1,0)+1,LARGE(A$3:A39,1)) -> 0 | B40: =IF(H40="UNIDADE CONSTRUTIVA",0,IF(H40="CÉLULA CONSTRUTIVA",OFFSET(B40,-1,0)+1,OFFSET(B40,-1,0))) -> 2 | C40: =IF(H40="CÉLULA CONSTRUTIVA",0,IF(H40="ETAPA",OFFSET(C40,-1,0)+1,OFFSET(C40,-1,0))) -> 2 | D40: =IF(H40="ETAPA",0,IF(H40="SUBETAPA",OFFSET(D40,-1,0)+1,OFFSET(D40,-1,0))) -> 0 | E40: =IF(H40="Subetapa",0,IF(H40="serviço",OFFSET(E40,-1,0)+1,OFFSET(E40,-1,0))) -> 1 | H40: ETAPA | I40: =IF(H40="Unidade Construtiva",TEXT(A40,"00"),IF(H40="Célula Construtiva",TEXT(B40,"00"),IF(H40="Etapa",CONCATENATE(TEXT(B40,"00"),".",TEXT(C40,"000")),IF(H40="Subetapa",CONCATENATE(TEXT(B40,"00"),".",TEXT(C40,"000"),".",TEXT(D40,"000")),IF(H40="Serviço",CONCATENATE(TEXT(B40,"00"),".",TEXT(C40,"000"),".",TEXT(D40,"000"),".",TEXT(E40,"000")),""))))) -> 02.002 | J40: FUNDAÇÃO RASA | N40: =IF(H40="Serviço",M40*L40,IF(H40="CÉLULA CONSTRUTIVA",SUMIFS($N$8:$N$452,$B$8:$B$452,B40,$H$8:$H$452,"Serviço"),IF(H40="ETAPA",SUMIFS($N$8:$N$452,$B$8:$B$452,B40,$C$8:$C$452,C40,$H$8:$H$452,"Serviço"),IF(H40="SUBETAPA",SUMIFS($N$8:$N$452,$B$8:$B$452,B40,$C$8:$C$452,C40,$D$8:$D$452,D40,$H$8:$H$452,"Serviço"),0)))) -> 0 | O40: =N40/'Obra '!$E$9 -> 0
A41: =IF($H41="UNIDADE CONSTRUTIVA",OFFSET(A41,-1,0)+1,LARGE(A$3:A40,1)) -> 0 | B41: =IF(H41="UNIDADE CONSTRUTIVA",0,IF(H41="CÉLULA CONSTRUTIVA",OFFSET(B41,-1,0)+1,OFFSET(B41,-1,0))) -> 2 | C41: =IF(H41="CÉLULA CONSTRUTIVA",0,IF(H41="ETAPA",OFFSET(C41,-1,0)+1,OFFSET(C41,-1,0))) -> 2 | D41: =IF(H41="ETAPA",0,IF(H41="SUBETAPA",OFFSET(D41,-1,0)+1,OFFSET(D41,-1,0))) -> 1 | E41: =IF(H41="Subetapa",0,IF(H41="serviço",OFFSET(E41,-1,0)+1,OFFSET(E41,-1,0))) -> 0 | H41: SUBETAPA | I41: =IF(H41="Unidade Construtiva",TEXT(A41,"00"),IF(H41="Célula Construtiva",TEXT(B41,"00"),IF(H41="Etapa",CONCATENATE(TEXT(B41,"00"),".",TEXT(C41,"000")),IF(H41="Subetapa",CONCATENATE(TEXT(B41,"00"),".",TEXT(C41,"000"),".",TEXT(D41,"000")),IF(H41="Serviço",CONCATENATE(TEXT(B41,"00"),".",TEXT(C41,"000"),".",TEXT(D41,"000"),".",TEXT(E41,"000")),""))))) -> 02.002.001 | J41: Forma | N41: =IF(H41="Serviço",M41*L41,IF(H41="CÉLULA CONSTRUTIVA",SUMIFS($N$8:$N$452,$B$8:$B$452,B41,$H$8:$H$452,"Serviço"),IF(H41="ETAPA",SUMIFS($N$8:$N$452,$B$8:$B$452,B41,$C$8:$C$452,C41,$H$8:$H$452,"Serviço"),IF(H41="SUBETAPA",SUMIFS($N$8:$N$452,$B$8:$B$452,B41,$C$8:$C$452,C41,$D$8:$D$452,D41,$H$8:$H$452,"Serviço"),0)))) -> 0
A42: =IF($H42="UNIDADE CONSTRUTIVA",OFFSET(A42,-1,0)+1,LARGE(A$3:A41,1)) -> 0 | B42: =IF(H42="UNIDADE CONSTRUTIVA",0,IF(H42="CÉLULA CONSTRUTIVA",OFFSET(B42,-1,0)+1,OFFSET(B42,-1,0))) -> 2 | C42: =IF(H42="CÉLULA CONSTRUTIVA",0,IF(H42="ETAPA",OFFSET(C42,-1,0)+1,OFFSET(C42,-1,0))) -> 2 | D42: =IF(H42="ETAPA",0,IF(H42="SUBETAPA",OFFSET(D42,-1,0)+1,OFFSET(D42,-1,0))) -> 1 | E42: =IF(H42="Subetapa",0,IF(H42="serviço",OFFSET(E42,-1,0)+1,OFFSET(E42,-1,0))) -> 1 | H42: SERVIÇO | I42: =IF(H42="Unidade Construtiva",TEXT(A42,"00"),IF(H42="Célula Construtiva",TEXT(B42,"00"),IF(H42="Etapa",CONCATENATE(TEXT(B42,"00"),".",TEXT(C42,"000")),IF(H42="Subetapa",CONCATENATE(TEXT(B42,"00"),".",TEXT(C42,"000"),".",TEXT(D42,"000")),IF(H42="Serviço",CONCATENATE(TEXT(B42,"00"),".",TEXT(C42,"000"),".",TEXT(D42,"000"),".",TEXT(E42,"000")),""))))) -> 02.002.001.001 | J42: Forma para infraestrutura em Tábuas de Madeira Serrada 2x reaproveitamento | K42: m2 | M42: =_xlfn.XLOOKUP($J42,CPU!$D$1:$D$3085,CPU!$H$1:$H$3085) -> 59.956229 | N42: =IF(H42="Serviço",M42*L42,IF(H42="CÉLULA CONSTRUTIVA",SUMIFS($N$8:$N$452,$B$8:$B$452,B42,$H$8:$H$452,"Serviço"),IF(H42="ETAPA",SUMIFS($N$8:$N$452,$B$8:$B$452,B42,$C$8:$C$452,C42,$H$8:$H$452,"Serviço"),IF(H42="SUBETAPA",SUMIFS($N$8:$N$452,$B$8:$B$452,B42,$C$8:$C$452,C42,$D$8:$D$452,D42,$H$8:$H$452,"Serviço"),0)))) -> 0 | O42: Considerado blocos e vigas (levantamento cartesian) e pilares e lajes do projetista - considerando 2 usos | P42: Finalizado
A43: =IF($H43="UNIDADE CONSTRUTIVA",OFFSET(A43,-1,0)+1,LARGE(A$3:A42,1)) -> 0 | B43: =IF(H43="UNIDADE CONSTRUTIVA",0,IF(H43="CÉLULA CONSTRUTIVA",OFFSET(B43,-1,0)+1,OFFSET(B43,-1,0))) -> 2 | C43: =IF(H43="CÉLULA CONSTRUTIVA",0,IF(H43="ETAPA",OFFSET(C43,-1,0)+1,OFFSET(C43,-1,0))) -> 2 | D43: =IF(H43="ETAPA",0,IF(H43="SUBETAPA",OFFSET(D43,-1,0)+1,OFFSET(D43,-1,0))) -> 2 | E43: =IF(H43="Subetapa",0,IF(H43="serviço",OFFSET(E43,-1,0)+1,OFFSET(E43,-1,0))) -> 0 | H43: SUBETAPA | I43: =IF(H43="Unidade Construtiva",TEXT(A43,"00"),IF(H43="Célula Construtiva",TEXT(B43,"00"),IF(H43="Etapa",CONCATENATE(TEXT(B43,"00"),".",TEXT(C43,"000")),IF(H43="Subetapa",CONCATENATE(TEXT(B43,"00"),".",TEXT(C43,"000"),".",TEXT(D43,"000")),IF(H43="Serviço",CONCATENATE(TEXT(B43,"00"),".",TEXT(C43,"000"),".",TEXT(D43,"000"),".",TEXT(E43,"000")),""))))) -> 02.002.002 | J43: Armadura | N43: =IF(H43="Serviço",M43*L43,IF(H43="CÉLULA CONSTRUTIVA",SUMIFS($N$8:$N$452,$B$8:$B$452,B43,$H$8:$H$452,"Serviço"),IF(H43="ETAPA",SUMIFS($N$8:$N$452,$B$8:$B$452,B43,$C$8:$C$452,C43,$H$8:$H$452,"Serviço"),IF(H43="SUBETAPA",SUMIFS($N$8:$N$452,$B$8:$B$452,B43,$C$8:$C$452,C43,$D$8:$D$452,D43,$H$8:$H$452,"Serviço"),0)))) -> 0
A44: =IF($H44="UNIDADE CONSTRUTIVA",OFFSET(A44,-1,0)+1,LARGE(A$3:A43,1)) -> 0 | B44: =IF(H44="UNIDADE CONSTRUTIVA",0,IF(H44="CÉLULA CONSTRUTIVA",OFFSET(B44,-1,0)+1,OFFSET(B44,-1,0))) -> 2 | C44: =IF(H44="CÉLULA CONSTRUTIVA",0,IF(H44="ETAPA",OFFSET(C44,-1,0)+1,OFFSET(C44,-1,0))) -> 2 | D44: =IF(H44="ETAPA",0,IF(H44="SUBETAPA",OFFSET(D44,-1,0)+1,OFFSET(D44,-1,0))) -> 2 | E44: =IF(H44="Subetapa",0,IF(H44="serviço",OFFSET(E44,-1,0)+1,OFFSET(E44,-1,0))) -> 1 | H44: SERVIÇO | I44: =IF(H44="Unidade Construtiva",TEXT(A44,"00"),IF(H44="Célula Construtiva",TEXT(B44,"00"),IF(H44="Etapa",CONCATENATE(TEXT(B44,"00"),".",TEXT(C44,"000")),IF(H44="Subetapa",CONCATENATE(TEXT(B44,"00"),".",TEXT(C44,"000"),".",TEXT(D44,"000")),IF(H44="Serviço",CONCATENATE(TEXT(B44,"00"),".",TEXT(C44,"000"),".",TEXT(D44,"000"),".",TEXT(E44,"000")),""))))) -> 02.002.002.001 | J44: Armação aço CA-50 ø 6,3mm para infraestrutura (corte e dobra em obra) | K44: kg | M44: =(_xlfn.XLOOKUP($J44,CPU!$D$1:$D$3085,CPU!$H$1:$H$3085))*1.1 -> 7.6319595 | N44: =IF(H44="Serviço",M44*L44,IF(H44="CÉLULA CONSTRUTIVA",SUMIFS($N$8:$N$452,$B$8:$B$452,B44,$H$8:$H$452,"Serviço"),IF(H44="ETAPA",SUMIFS($N$8:$N$452,$B$8:$B$452,B44,$C$8:$C$452,C44,$H$8:$H$452,"Serviço"),IF(H44="SUBETAPA",SUMIFS($N$8:$N$452,$B$8:$B$452,B44,$C$8:$C$452,C44,$D$8:$D$452,D44,$H$8:$H$452,"Serviço"),0)))) -> 0 | O44: Considerado conforme valor de projetos | P44: Finalizado
A45: =IF($H45="UNIDADE CONSTRUTIVA",OFFSET(A45,-1,0)+1,LARGE(A$3:A44,1)) -> 0 | B45: =IF(H45="UNIDADE CONSTRUTIVA",0,IF(H45="CÉLULA CONSTRUTIVA",OFFSET(B45,-1,0)+1,OFFSET(B45,-1,0))) -> 2 | C45: =IF(H45="CÉLULA CONSTRUTIVA",0,IF(H45="ETAPA",OFFSET(C45,-1,0)+1,OFFSET(C45,-1,0))) -> 2 | D45: =IF(H45="ETAPA",0,IF(H45="SUBETAPA",OFFSET(D45,-1,0)+1,OFFSET(D45,-1,0))) -> 2 | E45: =IF(H45="Subetapa",0,IF(H45="serviço",OFFSET(E45,-1,0)+1,OFFSET(E45,-1,0))) -> 2 | H45: SERVIÇO | I45: =IF(H45="Unidade Construtiva",TEXT(A45,"00"),IF(H45="Célula Construtiva",TEXT(B45,"00"),IF(H45="Etapa",CONCATENATE(TEXT(B45,"00"),".",TEXT(C45,"000")),IF(H45="Subetapa",CONCATENATE(TEXT(B45,"00"),".",TEXT(C45,"000"),".",TEXT(D45,"000")),IF(H45="Serviço",CONCATENATE(TEXT(B45,"00"),".",TEXT(C45,"000"),".",TEXT(D45,"000"),".",TEXT(E45,"000")),""))))) -> 02.002.002.002 | J45: Armação aço CA-50 ø 8,0mm para infraestrutura (corte e dobra em obra) | K45: kg | M45: =(_xlfn.XLOOKUP($J45,CPU!$D$1:$D$3085,CPU!$H$1:$H$3085))*1.1 -> 7.6319595 | N45: =IF(H45="Serviço",M45*L45,IF(H45="CÉLULA CONSTRUTIVA",SUMIFS($N$8:$N$452,$B$8:$B$452,B45,$H$8:$H$452,"Serviço"),IF(H45="ETAPA",SUMIFS($N$8:$N$452,$B$8:$B$452,B45,$C$8:$C$452,C45,$H$8:$H$452,"Serviço"),IF(H45="SUBETAPA",SUMIFS($N$8:$N$452,$B$8:$B$452,B45,$C$8:$C$452,C45,$D$8:$D$452,D45,$H$8:$H$452,"Serviço"),0)))) -> 0 | O45: Considerado conforme valor de projetos | P45: Finalizado
A46: =IF($H46="UNIDADE CONSTRUTIVA",OFFSET(A46,-1,0)+1,LARGE(A$3:A45,1)) -> 0 | B46: =IF(H46="UNIDADE CONSTRUTIVA",0,IF(H46="CÉLULA CONSTRUTIVA",OFFSET(B46,-1,0)+1,OFFSET(B46,-1,0))) -> 2 | C46: =IF(H46="CÉLULA CONSTRUTIVA",0,IF(H46="ETAPA",OFFSET(C46,-1,0)+1,OFFSET(C46,-1,0))) -> 2 | D46: =IF(H46="ETAPA",0,IF(H46="SUBETAPA",OFFSET(D46,-1,0)+1,OFFSET(D46,-1,0))) -> 2 | E46: =IF(H46="Subetapa",0,IF(H46="serviço",OFFSET(E46,-1,0)+1,OFFSET(E46,-1,0))) -> 3 | H46: SERVIÇO | I46: =IF(H46="Unidade Construtiva",TEXT(A46,"00"),IF(H46="Célula Construtiva",TEXT(B46,"00"),IF(H46="Etapa",CONCATENATE(TEXT(B46,"00"),".",TEXT(C46,"000")),IF(H46="Subetapa",CONCATENATE(TEXT(B46,"00"),".",TEXT(C46,"000"),".",TEXT(D46,"000")),IF(H46="Serviço",CONCATENATE(TEXT(B46,"00"),".",TEXT(C46,"000"),".",TEXT(D46,"000"),".",TEXT(E46,"000")),""))))) -> 02.002.002.003 | J46: Armação aço CA-50 ø 10,0mm para infraestrutura (corte e dobra em obra) | K46: kg | M46: =(_xlfn.XLOOKUP($J46,CPU!$D$1:$D$3085,CPU!$H$1:$H$3085))*1.1 -> 7.2931595 | N46: =IF(H46="Serviço",M46*L46,IF(H46="CÉLULA CONSTRUTIVA",SUMIFS($N$8:$N$452,$B$8:$B$452,B46,$H$8:$H$452,"Serviço"),IF(H46="ETAPA",SUMIFS($N$8:$N$452,$B$8:$B$452,B46,$C$8:$C$452,C46,$H$8:$H$452,"Serviço"),IF(H46="SUBETAPA",SUMIFS($N$8:$N$452,$B$8:$B$452,B46,$C$8:$C$452,C46,$D$8:$D$452,D46,$H$8:$H$452,"Serviço"),0)))) -> 0 | O46: Considerado conforme valor de projetos | P46: Finalizado
A47: =IF($H47="UNIDADE CONSTRUTIVA",OFFSET(A47,-1,0)+1,LARGE(A$3:A46,1)) -> 0 | B47: =IF(H47="UNIDADE CONSTRUTIVA",0,IF(H47="CÉLULA CONSTRUTIVA",OFFSET(B47,-1,0)+1,OFFSET(B47,-1,0))) -> 2 | C47: =IF(H47="CÉLULA CONSTRUTIVA",0,IF(H47="ETAPA",OFFSET(C47,-1,0)+1,OFFSET(C47,-1,0))) -> 2 | D47: =IF(H47="ETAPA",0,IF(H47="SUBETAPA",OFFSET(D47,-1,0)+1,OFFSET(D47,-1,0))) -> 2 | E47: =IF(H47="Subetapa",0,IF(H47="serviço",OFFSET(E47,-1,0)+1,OFFSET(E47,-1,0))) -> 4 | H47: SERVIÇO | I47: =IF(H47="Unidade Construtiva",TEXT(A47,"00"),IF(H47="Célula Construtiva",TEXT(B47,"00"),IF(H47="Etapa",CONCATENATE(TEXT(B47,"00"),".",TEXT(C47,"000")),IF(H47="Subetapa",CONCATENATE(TEXT(B47,"00"),".",TEXT(C47,"000"),".",TEXT(D47,"000")),IF(H47="Serviço",CONCATENATE(TEXT(B47,"00"),".",TEXT(C47,"000"),".",TEXT(D47,"000"),".",TEXT(E47,"000")),""))))) -> 02.002.002.004 | J47: Armação aço CA-50 ø 12,5mm para infraestrutura (corte e dobra em obra) | K47: kg | M47: =(_xlfn.XLOOKUP($J47,CPU!$D$1:$D$3085,CPU!$H$1:$H$3085))*1.1 -> 7.0874595 | N47: =IF(H47="Serviço",M47*L47,IF(H47="CÉLULA CONSTRUTIVA",SUMIFS($N$8:$N$452,$B$8:$B$452,B47,$H$8:$H$452,"Serviço"),IF(H47="ETAPA",SUMIFS($N$8:$N$452,$B$8:$B$452,B47,$C$8:$C$452,C47,$H$8:$H$452,"Serviço"),IF(H47="SUBETAPA",SUMIFS($N$8:$N$452,$B$8:$B$452,B47,$C$8:$C$452,C47,$D$8:$D$452,D47,$H$8:$H$452,"Serviço"),0)))) -> 0 | O47: Considerado conforme valor de projetos | P47: Finalizado
A48: =IF($H48="UNIDADE CONSTRUTIVA",OFFSET(A48,-1,0)+1,LARGE(A$3:A47,1)) -> 0 | B48: =IF(H48="UNIDADE CONSTRUTIVA",0,IF(H48="CÉLULA CONSTRUTIVA",OFFSET(B48,-1,0)+1,OFFSET(B48,-1,0))) -> 2 | C48: =IF(H48="CÉLULA CONSTRUTIVA",0,IF(H48="ETAPA",OFFSET(C48,-1,0)+1,OFFSET(C48,-1,0))) -> 2 | D48: =IF(H48="ETAPA",0,IF(H48="SUBETAPA",OFFSET(D48,-1,0)+1,OFFSET(D48,-1,0))) -> 2 | E48: =IF(H48="Subetapa",0,IF(H48="serviço",OFFSET(E48,-1,0)+1,OFFSET(E48,-1,0))) -> 5 | H48: SERVIÇO | I48: =IF(H48="Unidade Construtiva",TEXT(A48,"00"),IF(H48="Célula Construtiva",TEXT(B48,"00"),IF(H48="Etapa",CONCATENATE(TEXT(B48,"00"),".",TEXT(C48,"000")),IF(H48="Subetapa",CONCATENATE(TEXT(B48,"00"),".",TEXT(C48,"000"),".",TEXT(D48,"000")),IF(H48="Serviço",CONCATENATE(TEXT(B48,"00"),".",TEXT(C48,"000"),".",TEXT(D48,"000"),".",TEXT(E48,"000")),""))))) -> 02.002.002.005 | J48: Armação aço CA-50 ø 16,0mm para infraestrutura (corte e dobra em obra) | K48: kg | M48: =(_xlfn.XLOOKUP($J48,CPU!$D$1:$D$3085,CPU!$H$1:$H$3085))*1.1 -> 7.0874595 | N48: =IF(H48="Serviço",M48*L48,IF(H48="CÉLULA CONSTRUTIVA",SUMIFS($N$8:$N$452,$B$8:$B$452,B48,$H$8:$H$452,"Serviço"),IF(H48="ETAPA",SUMIFS($N$8:$N$452,$B$8:$B$452,B48,$C$8:$C$452,C48,$H$8:$H$452,"Serviço"),IF(H48="SUBETAPA",SUMIFS($N$8:$N$452,$B$8:$B$452,B48,$C$8:$C$452,C48,$D$8:$D$452,D48,$H$8:$H$452,"Serviço"),0)))) -> 0 | O48: Considerado conforme valor de projetos | P48: Finalizado
A49: =IF($H49="UNIDADE CONSTRUTIVA",OFFSET(A49,-1,0)+1,LARGE(A$3:A48,1)) -> 0 | B49: =IF(H49="UNIDADE CONSTRUTIVA",0,IF(H49="CÉLULA CONSTRUTIVA",OFFSET(B49,-1,0)+1,OFFSET(B49,-1,0))) -> 2 | C49: =IF(H49="CÉLULA CONSTRUTIVA",0,IF(H49="ETAPA",OFFSET(C49,-1,0)+1,OFFSET(C49,-1,0))) -> 2 | D49: =IF(H49="ETAPA",0,IF(H49="SUBETAPA",OFFSET(D49,-1,0)+1,OFFSET(D49,-1,0))) -> 2 | E49: =IF(H49="Subetapa",0,IF(H49="serviço",OFFSET(E49,-1,0)+1,OFFSET(E49,-1,0))) -> 6 | H49: SERVIÇO | I49: =IF(H49="Unidade Construtiva",TEXT(A49,"00"),IF(H49="Célula Construtiva",TEXT(B49,"00"),IF(H49="Etapa",CONCATENATE(TEXT(B49,"00"),".",TEXT(C49,"000")),IF(H49="Subetapa",CONCATENATE(TEXT(B49,"00"),".",TEXT(C49,"000"),".",TEXT(D49,"000")),IF(H49="Serviço",CONCATENATE(TEXT(B49,"00"),".",TEXT(C49,"000"),".",TEXT(D49,"000"),".",TEXT(E49,"000")),""))))) -> 02.002.002.006 | J49: Armação aço CA-50 ø 20,0mm para infraestrutura (corte e dobra em obra) | K49: kg | M49: =(_xlfn.XLOOKUP($J49,CPU!$D$1:$D$3085,CPU!$H$1:$H$3085))*1.1 -> 7.0874595 | N49: =IF(H49="Serviço",M49*L49,IF(H49="CÉLULA CONSTRUTIVA",SUMIFS($N$8:$N$452,$B$8:$B$452,B49,$H$8:$H$452,"Serviço"),IF(H49="ETAPA",SUMIFS($N$8:$N$452,$B$8:$B$452,B49,$C$8:$C$452,C49,$H$8:$H$452,"Serviço"),IF(H49="SUBETAPA",SUMIFS($N$8:$N$452,$B$8:$B$452,B49,$C$8:$C$452,C49,$D$8:$D$452,D49,$H$8:$H$452,"Serviço"),0)))) -> 0 | O49: Considerado conforme valor de projetos | P49: Finalizado
A50: =IF($H50="UNIDADE CONSTRUTIVA",OFFSET(A50,-1,0)+1,LARGE(A$3:A49,1)) -> 0 | B50: =IF(H50="UNIDADE CONSTRUTIVA",0,IF(H50="CÉLULA CONSTRUTIVA",OFFSET(B50,-1,0)+1,OFFSET(B50,-1,0))) -> 2 | C50: =IF(H50="CÉLULA CONSTRUTIVA",0,IF(H50="ETAPA",OFFSET(C50,-1,0)+1,OFFSET(C50,-1,0))) -> 2 | D50: =IF(H50="ETAPA",0,IF(H50="SUBETAPA",OFFSET(D50,-1,0)+1,OFFSET(D50,-1,0))) -> 2 | E50: =IF(H50="Subetapa",0,IF(H50="serviço",OFFSET(E50,-1,0)+1,OFFSET(E50,-1,0))) -> 7 | H50: SERVIÇO | I50: =IF(H50="Unidade Construtiva",TEXT(A50,"00"),IF(H50="Célula Construtiva",TEXT(B50,"00"),IF(H50="Etapa",CONCATENATE(TEXT(B50,"00"),".",TEXT(C50,"000")),IF(H50="Subetapa",CONCATENATE(TEXT(B50,"00"),".",TEXT(C50,"000"),".",TEXT(D50,"000")),IF(H50="Serviço",CONCATENATE(TEXT(B50,"00"),".",TEXT(C50,"000"),".",TEXT(D50,"000"),".",TEXT(E50,"000")),""))))) -> 02.002.002.007 | J50: Armação aço CA-50 ø 25,0mm para infraestrutura (corte e dobra em obra) | K50: kg | M50: =(_xlfn.XLOOKUP($J50,CPU!$D$1:$D$3085,CPU!$H$1:$H$3085))*1.1 -> 7.3778595 | N50: =IF(H50="Serviço",M50*L50,IF(H50="CÉLULA CONSTRUTIVA",SUMIFS($N$8:$N$452,$B$8:$B$452,B50,$H$8:$H$452,"Serviço"),IF(H50="ETAPA",SUMIFS($N$8:$N$452,$B$8:$B$452,B50,$C$8:$C$452,C50,$H$8:$H$452,"Serviço"),IF(H50="SUBETAPA",SUMIFS($N$8:$N$452,$B$8:$B$452,B50,$C$8:$C$452,C50,$D$8:$D$452,D50,$H$8:$H$452,"Serviço"),0)))) -> 0 | O50: Considerado conforme valor de projetos | P50: Finalizado
A51: =IF($H51="UNIDADE CONSTRUTIVA",OFFSET(A51,-1,0)+1,LARGE(A$3:A50,1)) -> 0 | B51: =IF(H51="UNIDADE CONSTRUTIVA",0,IF(H51="CÉLULA CONSTRUTIVA",OFFSET(B51,-1,0)+1,OFFSET(B51,-1,0))) -> 2 | C51: =IF(H51="CÉLULA CONSTRUTIVA",0,IF(H51="ETAPA",OFFSET(C51,-1,0)+1,OFFSET(C51,-1,0))) -> 2 | D51: =IF(H51="ETAPA",0,IF(H51="SUBETAPA",OFFSET(D51,-1,0)+1,OFFSET(D51,-1,0))) -> 2 | E51: =IF(H51="Subetapa",0,IF(H51="serviço",OFFSET(E51,-1,0)+1,OFFSET(E51,-1,0))) -> 8 | H51: SERVIÇO | I51: =IF(H51="Unidade Construtiva",TEXT(A51,"00"),IF(H51="Célula Construtiva",TEXT(B51,"00"),IF(H51="Etapa",CONCATENATE(TEXT(B51,"00"),".",TEXT(C51,"000")),IF(H51="Subetapa",CONCATENATE(TEXT(B51,"00"),".",TEXT(C51,"000"),".",TEXT(D51,"000")),IF(H51="Serviço",CONCATENATE(TEXT(B51,"00"),".",TEXT(C51,"000"),".",TEXT(D51,"000"),".",TEXT(E51,"000")),""))))) -> 02.002.002.008 | J51: Armação aço CA-60 ø 5,00mm para infraestrutura (corte e dobra em obra) | K51: kg | M51: =(_xlfn.XLOOKUP($J51,CPU!$D$1:$D$3085,CPU!$H$1:$H$3085))*1.1 -> 8.2369595 | N51: =IF(H51="Serviço",M51*L51,IF(H51="CÉLULA CONSTRUTIVA",SUMIFS($N$8:$N$452,$B$8:$B$452,B51,$H$8:$H$452,"Serviço"),IF(H51="ETAPA",SUMIFS($N$8:$N$452,$B$8:$B$452,B51,$C$8:$C$452,C51,$H$8:$H$452,"Serviço"),IF(H51="SUBETAPA",SUMIFS($N$8:$N$452,$B$8:$B$452,B51,$C$8:$C$452,C51,$D$8:$D$452,D51,$H$8:$H$452,"Serviço"),0)))) -> 0 | O51: Considerado conforme valor de projetos | P51: Finalizado
A52: =IF($H52="UNIDADE CONSTRUTIVA",OFFSET(A52,-1,0)+1,LARGE(A$3:A51,1)) -> 0 | B52: =IF(H52="UNIDADE CONSTRUTIVA",0,IF(H52="CÉLULA CONSTRUTIVA",OFFSET(B52,-1,0)+1,OFFSET(B52,-1,0))) -> 2 | C52: =IF(H52="CÉLULA CONSTRUTIVA",0,IF(H52="ETAPA",OFFSET(C52,-1,0)+1,OFFSET(C52,-1,0))) -> 2 | D52: =IF(H52="ETAPA",0,IF(H52="SUBETAPA",OFFSET(D52,-1,0)+1,OFFSET(D52,-1,0))) -> 3 | E52: =IF(H52="Subetapa",0,IF(H52="serviço",OFFSET(E52,-1,0)+1,OFFSET(E52,-1,0))) -> 0 | H52: SUBETAPA | I52: =IF(H52="Unidade Construtiva",TEXT(A52,"00"),IF(H52="Célula Construtiva",TEXT(B52,"00"),IF(H52="Etapa",CONCATENATE(TEXT(B52,"00"),".",TEXT(C52,"000")),IF(H52="Subetapa",CONCATENATE(TEXT(B52,"00"),".",TEXT(C52,"000"),".",TEXT(D52,"000")),IF(H52="Serviço",CONCATENATE(TEXT(B52,"00"),".",TEXT(C52,"000"),".",TEXT(D52,"000"),".",TEXT(E52,"000")),""))))) -> 02.002.003 | J52: Concreto | N52: =IF(H52="Serviço",M52*L52,IF(H52="CÉLULA CONSTRUTIVA",SUMIFS($N$8:$N$452,$B$8:$B$452,B52,$H$8:$H$452,"Serviço"),IF(H52="ETAPA",SUMIFS($N$8:$N$452,$B$8:$B$452,B52,$C$8:$C$452,C52,$H$8:$H$452,"Serviço"),IF(H52="SUBETAPA",SUMIFS($N$8:$N$452,$B$8:$B$452,B52,$C$8:$C$452,C52,$D$8:$D$452,D52,$H$8:$H$452,"Serviço"),0)))) -> 0
A53: =IF($H53="UNIDADE CONSTRUTIVA",OFFSET(A53,-1,0)+1,LARGE(A$3:A52,1)) -> 0 | B53: =IF(H53="UNIDADE CONSTRUTIVA",0,IF(H53="CÉLULA CONSTRUTIVA",OFFSET(B53,-1,0)+1,OFFSET(B53,-1,0))) -> 2 | C53: =IF(H53="CÉLULA CONSTRUTIVA",0,IF(H53="ETAPA",OFFSET(C53,-1,0)+1,OFFSET(C53,-1,0))) -> 2 | D53: =IF(H53="ETAPA",0,IF(H53="SUBETAPA",OFFSET(D53,-1,0)+1,OFFSET(D53,-1,0))) -> 3 | E53: =IF(H53="Subetapa",0,IF(H53="serviço",OFFSET(E53,-1,0)+1,OFFSET(E53,-1,0))) -> 1 | H53: SERVIÇO | I53: =IF(H53="Unidade Construtiva",TEXT(A53,"00"),IF(H53="Célula Construtiva",TEXT(B53,"00"),IF(H53="Etapa",CONCATENATE(TEXT(B53,"00"),".",TEXT(C53,"000")),IF(H53="Subetapa",CONCATENATE(TEXT(B53,"00"),".",TEXT(C53,"000"),".",TEXT(D53,"000")),IF(H53="Serviço",CONCATENATE(TEXT(B53,"00"),".",TEXT(C53,"000"),".",TEXT(D53,"000"),".",TEXT(E53,"000")),""))))) -> 02.002.003.001 | J53: Concreto armado no piso do térreo | K53: m2 | N53: =IF(H53="Serviço",M53*L53,IF(H53="CÉLULA CONSTRUTIVA",SUMIFS($N$8:$N$452,$B$8:$B$452,B53,$H$8:$H$452,"Serviço"),IF(H53="ETAPA",SUMIFS($N$8:$N$452,$B$8:$B$452,B53,$C$8:$C$452,C53,$H$8:$H$452,"Serviço"),IF(H53="SUBETAPA",SUMIFS($N$8:$N$452,$B$8:$B$452,B53,$C$8:$C$452,C53,$D$8:$D$452,D53,$H$8:$H$452,"Serviço"),0)))) -> 0 | O53: Considerado no contrapiso armado, considerado formas, armação, lona e concreto | P53: Lançado ERP
A54: =IF($H54="UNIDADE CONSTRUTIVA",OFFSET(A54,-1,0)+1,LARGE(A$3:A53,1)) -> 0 | B54: =IF(H54="UNIDADE CONSTRUTIVA",0,IF(H54="CÉLULA CONSTRUTIVA",OFFSET(B54,-1,0)+1,OFFSET(B54,-1,0))) -> 2 | C54: =IF(H54="CÉLULA CONSTRUTIVA",0,IF(H54="ETAPA",OFFSET(C54,-1,0)+1,OFFSET(C54,-1,0))) -> 2 | D54: =IF(H54="ETAPA",0,IF(H54="SUBETAPA",OFFSET(D54,-1,0)+1,OFFSET(D54,-1,0))) -> 3 | E54: =IF(H54="Subetapa",0,IF(H54="serviço",OFFSET(E54,-1,0)+1,OFFSET(E54,-1,0))) -> 2 | H54: SERVIÇO | I54: =IF(H54="Unidade Construtiva",TEXT(A54,"00"),IF(H54="Célula Construtiva",TEXT(B54,"00"),IF(H54="Etapa",CONCATENATE(TEXT(B54,"00"),".",TEXT(C54,"000")),IF(H54="Subetapa",CONCATENATE(TEXT(B54,"00"),".",TEXT(C54,"000"),".",TEXT(D54,"000")),IF(H54="Serviço",CONCATENATE(TEXT(B54,"00"),".",TEXT(C54,"000"),".",TEXT(D54,"000"),".",TEXT(E54,"000")),""))))) -> 02.002.003.002 | J54: Concreto Usinado bombeável 30MPa para infraestrutura - incluindo serviço de bombeamento | K54: m3 | M54: =_xlfn.XLOOKUP($J54,CPU!$D$1:$D$3085,CPU!$H$1:$H$3085) -> 578.26 | N54: =IF(H54="Serviço",M54*L54,IF(H54="CÉLULA CONSTRUTIVA",SUMIFS($N$8:$N$452,$B$8:$B$452,B54,$H$8:$H$452,"Serviço"),IF(H54="ETAPA",SUMIFS($N$8:$N$452,$B$8:$B$452,B54,$C$8:$C$452,C54,$H$8:$H$452,"Serviço"),IF(H54="SUBETAPA",SUMIFS($N$8:$N$452,$B$8:$B$452,B54,$C$8:$C$452,C54,$D$8:$D$452,D54,$H$8:$H$452,"Serviço"),0)))) -> 0 | O54: Considerado blocos e vigas (levantamento cartesian) e pilares e lajes do projetista | P54: Finalizado
A55: =IF($H55="UNIDADE CONSTRUTIVA",OFFSET(A55,-1,0)+1,LARGE(A$3:A54,1)) -> 0 | B55: =IF(H55="UNIDADE CONSTRUTIVA",0,IF(H55="CÉLULA CONSTRUTIVA",OFFSET(B55,-1,0)+1,OFFSET(B55,-1,0))) -> 2 | C55: =IF(H55="CÉLULA CONSTRUTIVA",0,IF(H55="ETAPA",OFFSET(C55,-1,0)+1,OFFSET(C55,-1,0))) -> 2 | D55: =IF(H55="ETAPA",0,IF(H55="SUBETAPA",OFFSET(D55,-1,0)+1,OFFSET(D55,-1,0))) -> 3 | E55: =IF(H55="Subetapa",0,IF(H55="serviço",OFFSET(E55,-1,0)+1,OFFSET(E55,-1,0))) -> 3 | H55: SERVIÇO | I55: =IF(H55="Unidade Construtiva",TEXT(A55,"00"),IF(H55="Célula Construtiva",TEXT(B55,"00"),IF(H55="Etapa",CONCATENATE(TEXT(B55,"00"),".",TEXT(C55,"000")),IF(H55="Subetapa",CONCATENATE(TEXT(B55,"00"),".",TEXT(C55,"000"),".",TEXT(D55,"000")),IF(H55="Serviço",CONCATENATE(TEXT(B55,"00"),".",TEXT(C55,"000"),".",TEXT(D55,"000"),".",TEXT(E55,"000")),""))))) -> 02.002.003.003 | J55: Junta serrada de 4 mm e 10 cm de altura, com tarucel | K55: m | M55: =_xlfn.XLOOKUP($J55,CPU!$D$1:$D$3085,CPU!$H$1:$H$3085) -> 5.1066667 | N55: =IF(H55="Serviço",M55*L55,IF(H55="CÉLULA CONSTRUTIVA",SUMIFS($N$8:$N$452,$B$8:$B$452,B55,$H$8:$H$452,"Serviço"),IF(H55="ETAPA",SUMIFS($N$8:$N$452,$B$8:$B$452,B55,$C$8:$C$452,C55,$H$8:$H$452,"Serviço"),IF(H55="SUBETAPA",SUMIFS($N$8:$N$452,$B$8:$B$452,B55,$C$8:$C$452,C55,$D$8:$D$452,D55,$H$8:$H$452,"Serviço"),0)))) -> 0 | P55: Finalizado
A56: =IF($H56="UNIDADE CONSTRUTIVA",OFFSET(A56,-1,0)+1,LARGE(A$3:A55,1)) -> 0 | B56: =IF(H56="UNIDADE CONSTRUTIVA",0,IF(H56="CÉLULA CONSTRUTIVA",OFFSET(B56,-1,0)+1,OFFSET(B56,-1,0))) -> 2 | C56: =IF(H56="CÉLULA CONSTRUTIVA",0,IF(H56="ETAPA",OFFSET(C56,-1,0)+1,OFFSET(C56,-1,0))) -> 2 | D56: =IF(H56="ETAPA",0,IF(H56="SUBETAPA",OFFSET(D56,-1,0)+1,OFFSET(D56,-1,0))) -> 4 | E56: =IF(H56="Subetapa",0,IF(H56="serviço",OFFSET(E56,-1,0)+1,OFFSET(E56,-1,0))) -> 0 | H56: SUBETAPA | I56: =IF(H56="Unidade Construtiva",TEXT(A56,"00"),IF(H56="Célula Construtiva",TEXT(B56,"00"),IF(H56="Etapa",CONCATENATE(TEXT(B56,"00"),".",TEXT(C56,"000")),IF(H56="Subetapa",CONCATENATE(TEXT(B56,"00"),".",TEXT(C56,"000"),".",TEXT(D56,"000")),IF(H56="Serviço",CONCATENATE(TEXT(B56,"00"),".",TEXT(C56,"000"),".",TEXT(D56,"000"),".",TEXT(E56,"000")),""))))) -> 02.002.004 | J56: Mão de Obra | N56: =IF(H56="Serviço",M56*L56,IF(H56="CÉLULA CONSTRUTIVA",SUMIFS($N$8:$N$452,$B$8:$B$452,B56,$H$8:$H$452,"Serviço"),IF(H56="ETAPA",SUMIFS($N$8:$N$452,$B$8:$B$452,B56,$C$8:$C$452,C56,$H$8:$H$452,"Serviço"),IF(H56="SUBETAPA",SUMIFS($N$8:$N$452,$B$8:$B$452,B56,$C$8:$C$452,C56,$D$8:$D$452,D56,$H$8:$H$452,"Serviço"),0)))) -> 0
A57: =IF($H57="UNIDADE CONSTRUTIVA",OFFSET(A57,-1,0)+1,LARGE(A$3:A56,1)) -> 0 | B57: =IF(H57="UNIDADE CONSTRUTIVA",0,IF(H57="CÉLULA CONSTRUTIVA",OFFSET(B57,-1,0)+1,OFFSET(B57,-1,0))) -> 2 | C57: =IF(H57="CÉLULA CONSTRUTIVA",0,IF(H57="ETAPA",OFFSET(C57,-1,0)+1,OFFSET(C57,-1,0))) -> 2 | D57: =IF(H57="ETAPA",0,IF(H57="SUBETAPA",OFFSET(D57,-1,0)+1,OFFSET(D57,-1,0))) -> 4 | E57: =IF(H57="Subetapa",0,IF(H57="serviço",OFFSET(E57,-1,0)+1,OFFSET(E57,-1,0))) -> 1 | H57: SERVIÇO | I57: =IF(H57="Unidade Construtiva",TEXT(A57,"00"),IF(H57="Célula Construtiva",TEXT(B57,"00"),IF(H57="Etapa",CONCATENATE(TEXT(B57,"00"),".",TEXT(C57,"000")),IF(H57="Subetapa",CONCATENATE(TEXT(B57,"00"),".",TEXT(C57,"000"),".",TEXT(D57,"000")),IF(H57="Serviço",CONCATENATE(TEXT(B57,"00"),".",TEXT(C57,"000"),".",TEXT(D57,"000"),".",TEXT(E57,"000")),""))))) -> 02.002.004.001 | J57: Mão de obra para execução de fundação | K57: m2 | M57: 360 | N57: =IF(H57="Serviço",M57*L57,IF(H57="CÉLULA CONSTRUTIVA",SUMIFS($N$8:$N$452,$B$8:$B$452,B57,$H$8:$H$452,"Serviço"),IF(H57="ETAPA",SUMIFS($N$8:$N$452,$B$8:$B$452,B57,$C$8:$C$452,C57,$H$8:$H$452,"Serviço"),IF(H57="SUBETAPA",SUMIFS($N$8:$N$452,$B$8:$B$452,B57,$C$8:$C$452,C57,$D$8:$D$452,D57,$H$8:$H$452,"Serviço"),0)))) -> 0 | P57: Finalizado
A58: =IF($H58="UNIDADE CONSTRUTIVA",OFFSET(A58,-1,0)+1,LARGE(A$3:A57,1)) -> 0 | B58: =IF(H58="UNIDADE CONSTRUTIVA",0,IF(H58="CÉLULA CONSTRUTIVA",OFFSET(B58,-1,0)+1,OFFSET(B58,-1,0))) -> 3 | C58: =IF(H58="CÉLULA CONSTRUTIVA",0,IF(H58="ETAPA",OFFSET(C58,-1,0)+1,OFFSET(C58,-1,0))) -> 0 | D58: =IF(H58="ETAPA",0,IF(H58="SUBETAPA",OFFSET(D58,-1,0)+1,OFFSET(D58,-1,0))) -> 4 | E58: =IF(H58="Subetapa",0,IF(H58="serviço",OFFSET(E58,-1,0)+1,OFFSET(E58,-1,0))) -> 1 | H58: CÉLULA CONSTRUTIVA | I58: =IF(H58="Unidade Construtiva",TEXT(A58,"00"),IF(H58="Célula Construtiva",TEXT(B58,"00"),IF(H58="Etapa",CONCATENATE(TEXT(B58,"00"),".",TEXT(C58,"000")),IF(H58="Subetapa",CONCATENATE(TEXT(B58,"00"),".",TEXT(C58,"000"),".",TEXT(D58,"000")),IF(H58="Serviço",CONCATENATE(TEXT(B58,"00"),".",TEXT(C58,"000"),".",TEXT(D58,"000"),".",TEXT(E58,"000")),""))))) -> 03 | J58: CONTENÇÃO | N58: =IF(H58="Serviço",M58*L58,IF(H58="CÉLULA CONSTRUTIVA",SUMIFS($N$8:$N$452,$B$8:$B$452,B58,$H$8:$H$452,"Serviço"),IF(H58="ETAPA",SUMIFS($N$8:$N$452,$B$8:$B$452,B58,$C$8:$C$452,C58,$H$8:$H$452,"Serviço"),IF(H58="SUBETAPA",SUMIFS($N$8:$N$452,$B$8:$B$452,B58,$C$8:$C$452,C58,$D$8:$D$452,D58,$H$8:$H$452,"Serviço"),0)))) -> 0 | O58: =N58/'Obra '!$E$9 -> 0 | Q58: CONTENÇÃO
A59: =IF($H59="UNIDADE CONSTRUTIVA",OFFSET(A59,-1,0)+1,LARGE(A$3:A58,1)) -> 0 | B59: =IF(H59="UNIDADE CONSTRUTIVA",0,IF(H59="CÉLULA CONSTRUTIVA",OFFSET(B59,-1,0)+1,OFFSET(B59,-1,0))) -> 3 | C59: =IF(H59="CÉLULA CONSTRUTIVA",0,IF(H59="ETAPA",OFFSET(C59,-1,0)+1,OFFSET(C59,-1,0))) -> 1 | D59: =IF(H59="ETAPA",0,IF(H59="SUBETAPA",OFFSET(D59,-1,0)+1,OFFSET(D59,-1,0))) -> 0 | E59: =IF(H59="Subetapa",0,IF(H59="serviço",OFFSET(E59,-1,0)+1,OFFSET(E59,-1,0))) -> 1 | H59: ETAPA | I59: =IF(H59="Unidade Construtiva",TEXT(A59,"00"),IF(H59="Célula Construtiva",TEXT(B59,"00"),IF(H59="Etapa",CONCATENATE(TEXT(B59,"00"),".",TEXT(C59,"000")),IF(H59="Subetapa",CONCATENATE(TEXT(B59,"00"),".",TEXT(C59,"000"),".",TEXT(D59,"000")),IF(H59="Serviço",CONCATENATE(TEXT(B59,"00"),".",TEXT(C59,"000"),".",TEXT(D59,"000"),".",TEXT(E59,"000")),""))))) -> 03.001 | J59: CONTENÇÃO | N59: =IF(H59="Serviço",M59*L59,IF(H59="CÉLULA CONSTRUTIVA",SUMIFS($N$8:$N$452,$B$8:$B$452,B59,$H$8:$H$452,"Serviço"),IF(H59="ETAPA",SUMIFS($N$8:$N$452,$B$8:$B$452,B59,$C$8:$C$452,C59,$H$8:$H$452,"Serviço"),IF(H59="SUBETAPA",SUMIFS($N$8:$N$452,$B$8:$B$452,B59,$C$8:$C$452,C59,$D$8:$D$452,D59,$H$8:$H$452,"Serviço"),0)))) -> 0 | O59: =N59/'Obra '!$E$9 -> 0
A60: =IF($H60="UNIDADE CONSTRUTIVA",OFFSET(A60,-1,0)+1,LARGE(A$3:A59,1)) -> 0 | B60: =IF(H60="UNIDADE CONSTRUTIVA",0,IF(H60="CÉLULA CONSTRUTIVA",OFFSET(B60,-1,0)+1,OFFSET(B60,-1,0))) -> 3 | C60: =IF(H60="CÉLULA CONSTRUTIVA",0,IF(H60="ETAPA",OFFSET(C60,-1,0)+1,OFFSET(C60,-1,0))) -> 1 | D60: =IF(H60="ETAPA",0,IF(H60="SUBETAPA",OFFSET(D60,-1,0)+1,OFFSET(D60,-1,0))) -> 1 | E60: =IF(H60="Subetapa",0,IF(H60="serviço",OFFSET(E60,-1,0)+1,OFFSET(E60,-1,0))) -> 0 | H60: SUBETAPA | I60: =IF(H60="Unidade Construtiva",TEXT(A60,"00"),IF(H60="Célula Construtiva",TEXT(B60,"00"),IF(H60="Etapa",CONCATENATE(TEXT(B60,"00"),".",TEXT(C60,"000")),IF(H60="Subetapa",CONCATENATE(TEXT(B60,"00"),".",TEXT(C60,"000"),".",TEXT(D60,"000")),IF(H60="Serviço",CONCATENATE(TEXT(B60,"00"),".",TEXT(C60,"000"),".",TEXT(D60,"000"),".",TEXT(E60,"000")),""))))) -> 03.001.001 | J60: Perfuração | N60: =IF(H60="Serviço",M60*L60,IF(H60="CÉLULA CONSTRUTIVA",SUMIFS($N$8:$N$452,$B$8:$B$452,B60,$H$8:$H$452,"Serviço"),IF(H60="ETAPA",SUMIFS($N$8:$N$452,$B$8:$B$452,B60,$C$8:$C$452,C60,$H$8:$H$452,"Serviço"),IF(H60="SUBETAPA",SUMIFS($N$8:$N$452,$B$8:$B$452,B60,$C$8:$C$452,C60,$D$8:$D$452,D60,$H$8:$H$452,"Serviço"),0)))) -> 0
A61: =IF($H61="UNIDADE CONSTRUTIVA",OFFSET(A61,-1,0)+1,LARGE(A$3:A60,1)) -> 0 | B61: =IF(H61="UNIDADE CONSTRUTIVA",0,IF(H61="CÉLULA CONSTRUTIVA",OFFSET(B61,-1,0)+1,OFFSET(B61,-1,0))) -> 3 | C61: =IF(H61="CÉLULA CONSTRUTIVA",0,IF(H61="ETAPA",OFFSET(C61,-1,0)+1,OFFSET(C61,-1,0))) -> 1 | D61: =IF(H61="ETAPA",0,IF(H61="SUBETAPA",OFFSET(D61,-1,0)+1,OFFSET(D61,-1,0))) -> 1 | E61: =IF(H61="Subetapa",0,IF(H61="serviço",OFFSET(E61,-1,0)+1,OFFSET(E61,-1,0))) -> 1 | H61: SERVIÇO | I61: =IF(H61="Unidade Construtiva",TEXT(A61,"00"),IF(H61="Célula Construtiva",TEXT(B61,"00"),IF(H61="Etapa",CONCATENATE(TEXT(B61,"00"),".",TEXT(C61,"000")),IF(H61="Subetapa",CONCATENATE(TEXT(B61,"00"),".",TEXT(C61,"000"),".",TEXT(D61,"000")),IF(H61="Serviço",CONCATENATE(TEXT(B61,"00"),".",TEXT(C61,"000"),".",TEXT(D61,"000"),".",TEXT(E61,"000")),""))))) -> 03.001.001.001 | J61: Perfuração de estaca Escavada para contenção Ø 40cm | K61: m | M61: =_xlfn.XLOOKUP($J61,CPU!$D$1:$D$3085,CPU!$H$1:$H$3085) -> 52.8 | N61: =IF(H61="Serviço",M61*L61,IF(H61="CÉLULA CONSTRUTIVA",SUMIFS($N$8:$N$452,$B$8:$B$452,B61,$H$8:$H$452,"Serviço"),IF(H61="ETAPA",SUMIFS($N$8:$N$452,$B$8:$B$452,B61,$C$8:$C$452,C61,$H$8:$H$452,"Serviço"),IF(H61="SUBETAPA",SUMIFS($N$8:$N$452,$B$8:$B$452,B61,$C$8:$C$452,C61,$D$8:$D$452,D61,$H$8:$H$452,"Serviço"),0)))) -> 0 | P61: Finalizado
A62: =IF($H62="UNIDADE CONSTRUTIVA",OFFSET(A62,-1,0)+1,LARGE(A$3:A61,1)) -> 0 | B62: =IF(H62="UNIDADE CONSTRUTIVA",0,IF(H62="CÉLULA CONSTRUTIVA",OFFSET(B62,-1,0)+1,OFFSET(B62,-1,0))) -> 3 | C62: =IF(H62="CÉLULA CONSTRUTIVA",0,IF(H62="ETAPA",OFFSET(C62,-1,0)+1,OFFSET(C62,-1,0))) -> 1 | D62: =IF(H62="ETAPA",0,IF(H62="SUBETAPA",OFFSET(D62,-1,0)+1,OFFSET(D62,-1,0))) -> 1 | E62: =IF(H62="Subetapa",0,IF(H62="serviço",OFFSET(E62,-1,0)+1,OFFSET(E62,-1,0))) -> 2 | H62: SERVIÇO | I62: =IF(H62="Unidade Construtiva",TEXT(A62,"00"),IF(H62="Célula Construtiva",TEXT(B62,"00"),IF(H62="Etapa",CONCATENATE(TEXT(B62,"00"),".",TEXT(C62,"000")),IF(H62="Subetapa",CONCATENATE(TEXT(B62,"00"),".",TEXT(C62,"000"),".",TEXT(D62,"000")),IF(H62="Serviço",CONCATENATE(TEXT(B62,"00"),".",TEXT(C62,"000"),".",TEXT(D62,"000"),".",TEXT(E62,"000")),""))))) -> 03.001.001.002 | J62: Mobilização e desmobilização de equipamentos - Para execução de estaca Escavada | K62: vb | M62: =_xlfn.XLOOKUP($J62,CPU!$D$1:$D$3085,CPU!$H$1:$H$3085) -> 26000 | N62: =IF(H62="Serviço",M62*L62,IF(H62="CÉLULA CONSTRUTIVA",SUMIFS($N$8:$N$452,$B$8:$B$452,B62,$H$8:$H$452,"Serviço"),IF(H62="ETAPA",SUMIFS($N$8:$N$452,$B$8:$B$452,B62,$C$8:$C$452,C62,$H$8:$H$452,"Serviço"),IF(H62="SUBETAPA",SUMIFS($N$8:$N$452,$B$8:$B$452,B62,$C$8:$C$452,C62,$D$8:$D$452,D62,$H$8:$H$452,"Serviço"),0)))) -> 0 | P62: Finalizado
A63: =IF($H63="UNIDADE CONSTRUTIVA",OFFSET(A63,-1,0)+1,LARGE(A$3:A62,1)) -> 0 | B63: =IF(H63="UNIDADE CONSTRUTIVA",0,IF(H63="CÉLULA CONSTRUTIVA",OFFSET(B63,-1,0)+1,OFFSET(B63,-1,0))) -> 3 | C63: =IF(H63="CÉLULA CONSTRUTIVA",0,IF(H63="ETAPA",OFFSET(C63,-1,0)+1,OFFSET(C63,-1,0))) -> 1 | D63: =IF(H63="ETAPA",0,IF(H63="SUBETAPA",OFFSET(D63,-1,0)+1,OFFSET(D63,-1,0))) -> 2 | E63: =IF(H63="Subetapa",0,IF(H63="serviço",OFFSET(E63,-1,0)+1,OFFSET(E63,-1,0))) -> 0 | H63: SUBETAPA | I63: =IF(H63="Unidade Construtiva",TEXT(A63,"00"),IF(H63="Célula Construtiva",TEXT(B63,"00"),IF(H63="Etapa",CONCATENATE(TEXT(B63,"00"),".",TEXT(C63,"000")),IF(H63="Subetapa",CONCATENATE(TEXT(B63,"00"),".",TEXT(C63,"000"),".",TEXT(D63,"000")),IF(H63="Serviço",CONCATENATE(TEXT(B63,"00"),".",TEXT(C63,"000"),".",TEXT(D63,"000"),".",TEXT(E63,"000")),""))))) -> 03.001.002 | J63: Forma | N63: =IF(H63="Serviço",M63*L63,IF(H63="CÉLULA CONSTRUTIVA",SUMIFS($N$8:$N$452,$B$8:$B$452,B63,$H$8:$H$452,"Serviço"),IF(H63="ETAPA",SUMIFS($N$8:$N$452,$B$8:$B$452,B63,$C$8:$C$452,C63,$H$8:$H$452,"Serviço"),IF(H63="SUBETAPA",SUMIFS($N$8:$N$452,$B$8:$B$452,B63,$C$8:$C$452,C63,$D$8:$D$452,D63,$H$8:$H$452,"Serviço"),0)))) -> 0
A64: =IF($H64="UNIDADE CONSTRUTIVA",OFFSET(A64,-1,0)+1,LARGE(A$3:A63,1)) -> 0 | B64: =IF(H64="UNIDADE CONSTRUTIVA",0,IF(H64="CÉLULA CONSTRUTIVA",OFFSET(B64,-1,0)+1,OFFSET(B64,-1,0))) -> 3 | C64: =IF(H64="CÉLULA CONSTRUTIVA",0,IF(H64="ETAPA",OFFSET(C64,-1,0)+1,OFFSET(C64,-1,0))) -> 1 | D64: =IF(H64="ETAPA",0,IF(H64="SUBETAPA",OFFSET(D64,-1,0)+1,OFFSET(D64,-1,0))) -> 2 | E64: =IF(H64="Subetapa",0,IF(H64="serviço",OFFSET(E64,-1,0)+1,OFFSET(E64,-1,0))) -> 1 | H64: SERVIÇO | I64: =IF(H64="Unidade Construtiva",TEXT(A64,"00"),IF(H64="Célula Construtiva",TEXT(B64,"00"),IF(H64="Etapa",CONCATENATE(TEXT(B64,"00"),".",TEXT(C64,"000")),IF(H64="Subetapa",CONCATENATE(TEXT(B64,"00"),".",TEXT(C64,"000"),".",TEXT(D64,"000")),IF(H64="Serviço",CONCATENATE(TEXT(B64,"00"),".",TEXT(C64,"000"),".",TEXT(D64,"000"),".",TEXT(E64,"000")),""))))) -> 03.001.002.001 | J64: Forma para Contenções em Tábuas de Madeira Serrada 17mm 4x reaproveitamento | K64: m2 | M64: =_xlfn.XLOOKUP($J64,CPU!$D$1:$D$3085,CPU!$H$1:$H$3085) -> 59.956229 | N64: =IF(H64="Serviço",M64*L64,IF(H64="CÉLULA CONSTRUTIVA",SUMIFS($N$8:$N$452,$B$8:$B$452,B64,$H$8:$H$452,"Serviço"),IF(H64="ETAPA",SUMIFS($N$8:$N$452,$B$8:$B$452,B64,$C$8:$C$452,C64,$H$8:$H$452,"Serviço"),IF(H64="SUBETAPA",SUMIFS($N$8:$N$452,$B$8:$B$452,B64,$C$8:$C$452,C64,$D$8:$D$452,D64,$H$8:$H$452,"Serviço"),0)))) -> 0 | P64: Finalizado
A65: =IF($H65="UNIDADE CONSTRUTIVA",OFFSET(A65,-1,0)+1,LARGE(A$3:A64,1)) -> 0 | B65: =IF(H65="UNIDADE CONSTRUTIVA",0,IF(H65="CÉLULA CONSTRUTIVA",OFFSET(B65,-1,0)+1,OFFSET(B65,-1,0))) -> 3 | C65: =IF(H65="CÉLULA CONSTRUTIVA",0,IF(H65="ETAPA",OFFSET(C65,-1,0)+1,OFFSET(C65,-1,0))) -> 1 | D65: =IF(H65="ETAPA",0,IF(H65="SUBETAPA",OFFSET(D65,-1,0)+1,OFFSET(D65,-1,0))) -> 3 | E65: =IF(H65="Subetapa",0,IF(H65="serviço",OFFSET(E65,-1,0)+1,OFFSET(E65,-1,0))) -> 0 | H65: SUBETAPA | I65: =IF(H65="Unidade Construtiva",TEXT(A65,"00"),IF(H65="Célula Construtiva",TEXT(B65,"00"),IF(H65="Etapa",CONCATENATE(TEXT(B65,"00"),".",TEXT(C65,"000")),IF(H65="Subetapa",CONCATENATE(TEXT(B65,"00"),".",TEXT(C65,"000"),".",TEXT(D65,"000")),IF(H65="Serviço",CONCATENATE(TEXT(B65,"00"),".",TEXT(C65,"000"),".",TEXT(D65,"000"),".",TEXT(E65,"000")),""))))) -> 03.001.003 | J65: Armadura | N65: =IF(H65="Serviço",M65*L65,IF(H65="CÉLULA CONSTRUTIVA",SUMIFS($N$8:$N$452,$B$8:$B$452,B65,$H$8:$H$452,"Serviço"),IF(H65="ETAPA",SUMIFS($N$8:$N$452,$B$8:$B$452,B65,$C$8:$C$452,C65,$H$8:$H$452,"Serviço"),IF(H65="SUBETAPA",SUMIFS($N$8:$N$452,$B$8:$B$452,B65,$C$8:$C$452,C65,$D$8:$D$452,D65,$H$8:$H$452,"Serviço"),0)))) -> 0
A66: =IF($H66="UNIDADE CONSTRUTIVA",OFFSET(A66,-1,0)+1,LARGE(A$3:A65,1)) -> 0 | B66: =IF(H66="UNIDADE CONSTRUTIVA",0,IF(H66="CÉLULA CONSTRUTIVA",OFFSET(B66,-1,0)+1,OFFSET(B66,-1,0))) -> 3 | C66: =IF(H66="CÉLULA CONSTRUTIVA",0,IF(H66="ETAPA",OFFSET(C66,-1,0)+1,OFFSET(C66,-1,0))) -> 1 | D66: =IF(H66="ETAPA",0,IF(H66="SUBETAPA",OFFSET(D66,-1,0)+1,OFFSET(D66,-1,0))) -> 3 | E66: =IF(H66="Subetapa",0,IF(H66="serviço",OFFSET(E66,-1,0)+1,OFFSET(E66,-1,0))) -> 1 | H66: SERVIÇO | I66: =IF(H66="Unidade Construtiva",TEXT(A66,"00"),IF(H66="Célula Construtiva",TEXT(B66,"00"),IF(H66="Etapa",CONCATENATE(TEXT(B66,"00"),".",TEXT(C66,"000")),IF(H66="Subetapa",CONCATENATE(TEXT(B66,"00"),".",TEXT(C66,"000"),".",TEXT(D66,"000")),IF(H66="Serviço",CONCATENATE(TEXT(B66,"00"),".",TEXT(C66,"000"),".",TEXT(D66,"000"),".",TEXT(E66,"000")),""))))) -> 03.001.003.001 | J66: Armação aço CA-60 ø 5,00mm para Contenções (corte e dobra em obra) | K66: kg | M66: =_xlfn.XLOOKUP($J66,CPU!$D$1:$D$3085,CPU!$H$1:$H$3085) -> 7.488145 | N66: =IF(H66="Serviço",M66*L66,IF(H66="CÉLULA CONSTRUTIVA",SUMIFS($N$8:$N$452,$B$8:$B$452,B66,$H$8:$H$452,"Serviço"),IF(H66="ETAPA",SUMIFS($N$8:$N$452,$B$8:$B$452,B66,$C$8:$C$452,C66,$H$8:$H$452,"Serviço"),IF(H66="SUBETAPA",SUMIFS($N$8:$N$452,$B$8:$B$452,B66,$C$8:$C$452,C66,$D$8:$D$452,D66,$H$8:$H$452,"Serviço"),0)))) -> 0 | P66: Finalizado
A67: =IF($H67="UNIDADE CONSTRUTIVA",OFFSET(A67,-1,0)+1,LARGE(A$3:A66,1)) -> 0 | B67: =IF(H67="UNIDADE CONSTRUTIVA",0,IF(H67="CÉLULA CONSTRUTIVA",OFFSET(B67,-1,0)+1,OFFSET(B67,-1,0))) -> 3 | C67: =IF(H67="CÉLULA CONSTRUTIVA",0,IF(H67="ETAPA",OFFSET(C67,-1,0)+1,OFFSET(C67,-1,0))) -> 1 | D67: =IF(H67="ETAPA",0,IF(H67="SUBETAPA",OFFSET(D67,-1,0)+1,OFFSET(D67,-1,0))) -> 3 | E67: =IF(H67="Subetapa",0,IF(H67="serviço",OFFSET(E67,-1,0)+1,OFFSET(E67,-1,0))) -> 2 | H67: SERVIÇO | I67: =IF(H67="Unidade Construtiva",TEXT(A67,"00"),IF(H67="Célula Construtiva",TEXT(B67,"00"),IF(H67="Etapa",CONCATENATE(TEXT(B67,"00"),".",TEXT(C67,"000")),IF(H67="Subetapa",CONCATENATE(TEXT(B67,"00"),".",TEXT(C67,"000"),".",TEXT(D67,"000")),IF(H67="Serviço",CONCATENATE(TEXT(B67,"00"),".",TEXT(C67,"000"),".",TEXT(D67,"000"),".",TEXT(E67,"000")),""))))) -> 03.001.003.002 | J67: Armação aço CA-50 ø 6,3mm para Contenções (corte e dobra em obra) | K67: kg | M67: =_xlfn.XLOOKUP($J67,CPU!$D$1:$D$3085,CPU!$H$1:$H$3085) -> 6.938145 | N67: =IF(H67="Serviço",M67*L67,IF(H67="CÉLULA CONSTRUTIVA",SUMIFS($N$8:$N$452,$B$8:$B$452,B67,$H$8:$H$452,"Serviço"),IF(H67="ETAPA",SUMIFS($N$8:$N$452,$B$8:$B$452,B67,$C$8:$C$452,C67,$H$8:$H$452,"Serviço"),IF(H67="SUBETAPA",SUMIFS($N$8:$N$452,$B$8:$B$452,B67,$C$8:$C$452,C67,$D$8:$D$452,D67,$H$8:$H$452,"Serviço"),0)))) -> 0 | P67: Finalizado
A68: =IF($H68="UNIDADE CONSTRUTIVA",OFFSET(A68,-1,0)+1,LARGE(A$3:A67,1)) -> 0 | B68: =IF(H68="UNIDADE CONSTRUTIVA",0,IF(H68="CÉLULA CONSTRUTIVA",OFFSET(B68,-1,0)+1,OFFSET(B68,-1,0))) -> 3 | C68: =IF(H68="CÉLULA CONSTRUTIVA",0,IF(H68="ETAPA",OFFSET(C68,-1,0)+1,OFFSET(C68,-1,0))) -> 1 | D68: =IF(H68="ETAPA",0,IF(H68="SUBETAPA",OFFSET(D68,-1,0)+1,OFFSET(D68,-1,0))) -> 3 | E68: =IF(H68="Subetapa",0,IF(H68="serviço",OFFSET(E68,-1,0)+1,OFFSET(E68,-1,0))) -> 3 | H68: SERVIÇO | I68: =IF(H68="Unidade Construtiva",TEXT(A68,"00"),IF(H68="Célula Construtiva",TEXT(B68,"00"),IF(H68="Etapa",CONCATENATE(TEXT(B68,"00"),".",TEXT(C68,"000")),IF(H68="Subetapa",CONCATENATE(TEXT(B68,"00"),".",TEXT(C68,"000"),".",TEXT(D68,"000")),IF(H68="Serviço",CONCATENATE(TEXT(B68,"00"),".",TEXT(C68,"000"),".",TEXT(D68,"000"),".",TEXT(E68,"000")),""))))) -> 03.001.003.003 | J68: Armação aço CA-50 ø 12,5mm para Contenções (corte e dobra em obra) | K68: kg | M68: =_xlfn.XLOOKUP($J68,CPU!$D$1:$D$3085,CPU!$H$1:$H$3085) -> 6.443145 | N68: =IF(H68="Serviço",M68*L68,IF(H68="CÉLULA CONSTRUTIVA",SUMIFS($N$8:$N$452,$B$8:$B$452,B68,$H$8:$H$452,"Serviço"),IF(H68="ETAPA",SUMIFS($N$8:$N$452,$B$8:$B$452,B68,$C$8:$C$452,C68,$H$8:$H$452,"Serviço"),IF(H68="SUBETAPA",SUMIFS($N$8:$N$452,$B$8:$B$452,B68,$C$8:$C$452,C68,$D$8:$D$452,D68,$H$8:$H$452,"Serviço"),0)))) -> 0 | P68: Finalizado
A69: =IF($H69="UNIDADE CONSTRUTIVA",OFFSET(A69,-1,0)+1,LARGE(A$3:A68,1)) -> 0 | B69: =IF(H69="UNIDADE CONSTRUTIVA",0,IF(H69="CÉLULA CONSTRUTIVA",OFFSET(B69,-1,0)+1,OFFSET(B69,-1,0))) -> 3 | C69: =IF(H69="CÉLULA CONSTRUTIVA",0,IF(H69="ETAPA",OFFSET(C69,-1,0)+1,OFFSET(C69,-1,0))) -> 1 | D69: =IF(H69="ETAPA",0,IF(H69="SUBETAPA",OFFSET(D69,-1,0)+1,OFFSET(D69,-1,0))) -> 3 | E69: =IF(H69="Subetapa",0,IF(H69="serviço",OFFSET(E69,-1,0)+1,OFFSET(E69,-1,0))) -> 4 | H69: SERVIÇO | I69: =IF(H69="Unidade Construtiva",TEXT(A69,"00"),IF(H69="Célula Construtiva",TEXT(B69,"00"),IF(H69="Etapa",CONCATENATE(TEXT(B69,"00"),".",TEXT(C69,"000")),IF(H69="Subetapa",CONCATENATE(TEXT(B69,"00"),".",TEXT(C69,"000"),".",TEXT(D69,"000")),IF(H69="Serviço",CONCATENATE(TEXT(B69,"00"),".",TEXT(C69,"000"),".",TEXT(D69,"000"),".",TEXT(E69,"000")),""))))) -> 03.001.003.004 | J69: Armação aço CA-50 ø 16,0mm para Contenções (corte e dobra em obra) | K69: kg | M69: =_xlfn.XLOOKUP($J69,CPU!$D$1:$D$3085,CPU!$H$1:$H$3085) -> 6.443145 | N69: =IF(H69="Serviço",M69*L69,IF(H69="CÉLULA CONSTRUTIVA",SUMIFS($N$8:$N$452,$B$8:$B$452,B69,$H$8:$H$452,"Serviço"),IF(H69="ETAPA",SUMIFS($N$8:$N$452,$B$8:$B$452,B69,$C$8:$C$452,C69,$H$8:$H$452,"Serviço"),IF(H69="SUBETAPA",SUMIFS($N$8:$N$452,$B$8:$B$452,B69,$C$8:$C$452,C69,$D$8:$D$452,D69,$H$8:$H$452,"Serviço"),0)))) -> 0 | P69: Finalizado
A70: =IF($H70="UNIDADE CONSTRUTIVA",OFFSET(A70,-1,0)+1,LARGE(A$3:A69,1)) -> 0 | B70: =IF(H70="UNIDADE CONSTRUTIVA",0,IF(H70="CÉLULA CONSTRUTIVA",OFFSET(B70,-1,0)+1,OFFSET(B70,-1,0))) -> 3 | C70: =IF(H70="CÉLULA CONSTRUTIVA",0,IF(H70="ETAPA",OFFSET(C70,-1,0)+1,OFFSET(C70,-1,0))) -> 1 | D70: =IF(H70="ETAPA",0,IF(H70="SUBETAPA",OFFSET(D70,-1,0)+1,OFFSET(D70,-1,0))) -> 4 | E70: =IF(H70="Subetapa",0,IF(H70="serviço",OFFSET(E70,-1,0)+1,OFFSET(E70,-1,0))) -> 0 | H70: SUBETAPA | I70: =IF(H70="Unidade Construtiva",TEXT(A70,"00"),IF(H70="Célula Construtiva",TEXT(B70,"00"),IF(H70="Etapa",CONCATENATE(TEXT(B70,"00"),".",TEXT(C70,"000")),IF(H70="Subetapa",CONCATENATE(TEXT(B70,"00"),".",TEXT(C70,"000"),".",TEXT(D70,"000")),IF(H70="Serviço",CONCATENATE(TEXT(B70,"00"),".",TEXT(C70,"000"),".",TEXT(D70,"000"),".",TEXT(E70,"000")),""))))) -> 03.001.004 | J70: Concreto | N70: =IF(H70="Serviço",M70*L70,IF(H70="CÉLULA CONSTRUTIVA",SUMIFS($N$8:$N$452,$B$8:$B$452,B70,$H$8:$H$452,"Serviço"),IF(H70="ETAPA",SUMIFS($N$8:$N$452,$B$8:$B$452,B70,$C$8:$C$452,C70,$H$8:$H$452,"Serviço"),IF(H70="SUBETAPA",SUMIFS($N$8:$N$452,$B$8:$B$452,B70,$C$8:$C$452,C70,$D$8:$D$452,D70,$H$8:$H$452,"Serviço"),0)))) -> 0
A71: =IF($H71="UNIDADE CONSTRUTIVA",OFFSET(A71,-1,0)+1,LARGE(A$3:A70,1)) -> 0 | B71: =IF(H71="UNIDADE CONSTRUTIVA",0,IF(H71="CÉLULA CONSTRUTIVA",OFFSET(B71,-1,0)+1,OFFSET(B71,-1,0))) -> 3 | C71: =IF(H71="CÉLULA CONSTRUTIVA",0,IF(H71="ETAPA",OFFSET(C71,-1,0)+1,OFFSET(C71,-1,0))) -> 1 | D71: =IF(H71="ETAPA",0,IF(H71="SUBETAPA",OFFSET(D71,-1,0)+1,OFFSET(D71,-1,0))) -> 4 | E71: =IF(H71="Subetapa",0,IF(H71="serviço",OFFSET(E71,-1,0)+1,OFFSET(E71,-1,0))) -> 1 | H71: SERVIÇO | I71: =IF(H71="Unidade Construtiva",TEXT(A71,"00"),IF(H71="Célula Construtiva",TEXT(B71,"00"),IF(H71="Etapa",CONCATENATE(TEXT(B71,"00"),".",TEXT(C71,"000")),IF(H71="Subetapa",CONCATENATE(TEXT(B71,"00"),".",TEXT(C71,"000"),".",TEXT(D71,"000")),IF(H71="Serviço",CONCATENATE(TEXT(B71,"00"),".",TEXT(C71,"000"),".",TEXT(D71,"000"),".",TEXT(E71,"000")),""))))) -> 03.001.004.001 | J71: Concreto Usinado bombeável para estacas 25MPa - incluindo serviço de bombeamento | K71: m3 | M71: =_xlfn.XLOOKUP($J71,CPU!$D$1:$D$3085,CPU!$H$1:$H$3085) -> 693.66 | N71: =IF(H71="Serviço",M71*L71,IF(H71="CÉLULA CONSTRUTIVA",SUMIFS($N$8:$N$452,$B$8:$B$452,B71,$H$8:$H$452,"Serviço"),IF(H71="ETAPA",SUMIFS($N$8:$N$452,$B$8:$B$452,B71,$C$8:$C$452,C71,$H$8:$H$452,"Serviço"),IF(H71="SUBETAPA",SUMIFS($N$8:$N$452,$B$8:$B$452,B71,$C$8:$C$452,C71,$D$8:$D$452,D71,$H$8:$H$452,"Serviço"),0)))) -> 0 | P71: Finalizado
A72: =IF($H72="UNIDADE CONSTRUTIVA",OFFSET(A72,-1,0)+1,LARGE(A$3:A71,1)) -> 0 | B72: =IF(H72="UNIDADE CONSTRUTIVA",0,IF(H72="CÉLULA CONSTRUTIVA",OFFSET(B72,-1,0)+1,OFFSET(B72,-1,0))) -> 3 | C72: =IF(H72="CÉLULA CONSTRUTIVA",0,IF(H72="ETAPA",OFFSET(C72,-1,0)+1,OFFSET(C72,-1,0))) -> 1 | D72: =IF(H72="ETAPA",0,IF(H72="SUBETAPA",OFFSET(D72,-1,0)+1,OFFSET(D72,-1,0))) -> 5 | E72: =IF(H72="Subetapa",0,IF(H72="serviço",OFFSET(E72,-1,0)+1,OFFSET(E72,-1,0))) -> 0 | H72: SUBETAPA | I72: =IF(H72="Unidade Construtiva",TEXT(A72,"00"),IF(H72="Célula Construtiva",TEXT(B72,"00"),IF(H72="Etapa",CONCATENATE(TEXT(B72,"00"),".",TEXT(C72,"000")),IF(H72="Subetapa",CONCATENATE(TEXT(B72,"00"),".",TEXT(C72,"000"),".",TEXT(D72,"000")),IF(H72="Serviço",CONCATENATE(TEXT(B72,"00"),".",TEXT(C72,"000"),".",TEXT(D72,"000"),".",TEXT(E72,"000")),""))))) -> 03.001.005 | J72: Mão de Obra | N72: =IF(H72="Serviço",M72*L72,IF(H72="CÉLULA CONSTRUTIVA",SUMIFS($N$8:$N$452,$B$8:$B$452,B72,$H$8:$H$452,"Serviço"),IF(H72="ETAPA",SUMIFS($N$8:$N$452,$B$8:$B$452,B72,$C$8:$C$452,C72,$H$8:$H$452,"Serviço"),IF(H72="SUBETAPA",SUMIFS($N$8:$N$452,$B$8:$B$452,B72,$C$8:$C$452,C72,$D$8:$D$452,D72,$H$8:$H$452,"Serviço"),0)))) -> 0
A73: =IF($H73="UNIDADE CONSTRUTIVA",OFFSET(A73,-1,0)+1,LARGE(A$3:A72,1)) -> 0 | B73: =IF(H73="UNIDADE CONSTRUTIVA",0,IF(H73="CÉLULA CONSTRUTIVA",OFFSET(B73,-1,0)+1,OFFSET(B73,-1,0))) -> 3 | C73: =IF(H73="CÉLULA CONSTRUTIVA",0,IF(H73="ETAPA",OFFSET(C73,-1,0)+1,OFFSET(C73,-1,0))) -> 1 | D73: =IF(H73="ETAPA",0,IF(H73="SUBETAPA",OFFSET(D73,-1,0)+1,OFFSET(D73,-1,0))) -> 5 | E73: =IF(H73="Subetapa",0,IF(H73="serviço",OFFSET(E73,-1,0)+1,OFFSET(E73,-1,0))) -> 1 | H73: SERVIÇO | I73: =IF(H73="Unidade Construtiva",TEXT(A73,"00"),IF(H73="Célula Construtiva",TEXT(B73,"00"),IF(H73="Etapa",CONCATENATE(TEXT(B73,"00"),".",TEXT(C73,"000")),IF(H73="Subetapa",CONCATENATE(TEXT(B73,"00"),".",TEXT(C73,"000"),".",TEXT(D73,"000")),IF(H73="Serviço",CONCATENATE(TEXT(B73,"00"),".",TEXT(C73,"000"),".",TEXT(D73,"000"),".",TEXT(E73,"000")),""))))) -> 03.001.005.001 | J73: Corte e Preparo de Cabeça de Estaca | K73: un | M73: =_xlfn.XLOOKUP($J73,CPU!$D$1:$D$3085,CPU!$H$1:$H$3085) -> 300 | N73: =IF(H73="Serviço",M73*L73,IF(H73="CÉLULA CONSTRUTIVA",SUMIFS($N$8:$N$452,$B$8:$B$452,B73,$H$8:$H$452,"Serviço"),IF(H73="ETAPA",SUMIFS($N$8:$N$452,$B$8:$B$452,B73,$C$8:$C$452,C73,$H$8:$H$452,"Serviço"),IF(H73="SUBETAPA",SUMIFS($N$8:$N$452,$B$8:$B$452,B73,$C$8:$C$452,C73,$D$8:$D$452,D73,$H$8:$H$452,"Serviço"),0)))) -> 0 | P73: Finalizado
A74: =IF($H74="UNIDADE CONSTRUTIVA",OFFSET(A74,-1,0)+1,LARGE(A$3:A73,1)) -> 0 | B74: =IF(H74="UNIDADE CONSTRUTIVA",0,IF(H74="CÉLULA CONSTRUTIVA",OFFSET(B74,-1,0)+1,OFFSET(B74,-1,0))) -> 4 | C74: =IF(H74="CÉLULA CONSTRUTIVA",0,IF(H74="ETAPA",OFFSET(C74,-1,0)+1,OFFSET(C74,-1,0))) -> 0 | D74: =IF(H74="ETAPA",0,IF(H74="SUBETAPA",OFFSET(D74,-1,0)+1,OFFSET(D74,-1,0))) -> 5 | E74: =IF(H74="Subetapa",0,IF(H74="serviço",OFFSET(E74,-1,0)+1,OFFSET(E74,-1,0))) -> 1 | H74: CÉLULA CONSTRUTIVA | I74: =IF(H74="Unidade Construtiva",TEXT(A74,"00"),IF(H74="Célula Construtiva",TEXT(B74,"00"),IF(H74="Etapa",CONCATENATE(TEXT(B74,"00"),".",TEXT(C74,"000")),IF(H74="Subetapa",CONCATENATE(TEXT(B74,"00"),".",TEXT(C74,"000"),".",TEXT(D74,"000")),IF(H74="Serviço",CONCATENATE(TEXT(B74,"00"),".",TEXT(C74,"000"),".",TEXT(D74,"000"),".",TEXT(E74,"000")),""))))) -> 04 | J74: SUPRAESTRUTURA | N74: =IF(H74="Serviço",M74*L74,IF(H74="CÉLULA CONSTRUTIVA",SUMIFS($N$8:$N$452,$B$8:$B$452,B74,$H$8:$H$452,"Serviço"),IF(H74="ETAPA",SUMIFS($N$8:$N$452,$B$8:$B$452,B74,$C$8:$C$452,C74,$H$8:$H$452,"Serviço"),IF(H74="SUBETAPA",SUMIFS($N$8:$N$452,$B$8:$B$452,B74,$C$8:$C$452,C74,$D$8:$D$452,D74,$H$8:$H$452,"Serviço"),0)))) -> 0 | O74: =N74/'Obra '!$E$9 -> 0 | Q74: SUPRAESTRUTURA
A75: =IF($H75="UNIDADE CONSTRUTIVA",OFFSET(A75,-1,0)+1,LARGE(A$3:A74,1)) -> 0 | B75: =IF(H75="UNIDADE CONSTRUTIVA",0,IF(H75="CÉLULA CONSTRUTIVA",OFFSET(B75,-1,0)+1,OFFSET(B75,-1,0))) -> 4 | C75: =IF(H75="CÉLULA CONSTRUTIVA",0,IF(H75="ETAPA",OFFSET(C75,-1,0)+1,OFFSET(C75,-1,0))) -> 1 | D75: =IF(H75="ETAPA",0,IF(H75="SUBETAPA",OFFSET(D75,-1,0)+1,OFFSET(D75,-1,0))) -> 0 | E75: =IF(H75="Subetapa",0,IF(H75="serviço",OFFSET(E75,-1,0)+1,OFFSET(E75,-1,0))) -> 1 | H75: ETAPA | I75: =IF(H75="Unidade Construtiva",TEXT(A75,"00"),IF(H75="Célula Construtiva",TEXT(B75,"00"),IF(H75="Etapa",CONCATENATE(TEXT(B75,"00"),".",TEXT(C75,"000")),IF(H75="Subetapa",CONCATENATE(TEXT(B75,"00"),".",TEXT(C75,"000"),".",TEXT(D75,"000")),IF(H75="Serviço",CONCATENATE(TEXT(B75,"00"),".",TEXT(C75,"000"),".",TEXT(D75,"000"),".",TEXT(E75,"000")),""))))) -> 04.001 | J75: SUPRAESTRUTURA | N75: =IF(H75="Serviço",M75*L75,IF(H75="CÉLULA CONSTRUTIVA",SUMIFS($N$8:$N$452,$B$8:$B$452,B75,$H$8:$H$452,"Serviço"),IF(H75="ETAPA",SUMIFS($N$8:$N$452,$B$8:$B$452,B75,$C$8:$C$452,C75,$H$8:$H$452,"Serviço"),IF(H75="SUBETAPA",SUMIFS($N$8:$N$452,$B$8:$B$452,B75,$C$8:$C$452,C75,$D$8:$D$452,D75,$H$8:$H$452,"Serviço"),0)))) -> 0 | O75: =N74-N269-N279 -> -38912.619
A76: =IF($H76="UNIDADE CONSTRUTIVA",OFFSET(A76,-1,0)+1,LARGE(A$3:A75,1)) -> 0 | B76: =IF(H76="UNIDADE CONSTRUTIVA",0,IF(H76="CÉLULA CONSTRUTIVA",OFFSET(B76,-1,0)+1,OFFSET(B76,-1,0))) -> 4 | C76: =IF(H76="CÉLULA CONSTRUTIVA",0,IF(H76="ETAPA",OFFSET(C76,-1,0)+1,OFFSET(C76,-1,0))) -> 1 | D76: =IF(H76="ETAPA",0,IF(H76="SUBETAPA",OFFSET(D76,-1,0)+1,OFFSET(D76,-1,0))) -> 1 | E76: =IF(H76="Subetapa",0,IF(H76="serviço",OFFSET(E76,-1,0)+1,OFFSET(E76,-1,0))) -> 0 | H76: SUBETAPA | I76: =IF(H76="Unidade Construtiva",TEXT(A76,"00"),IF(H76="Célula Construtiva",TEXT(B76,"00"),IF(H76="Etapa",CONCATENATE(TEXT(B76,"00"),".",TEXT(C76,"000")),IF(H76="Subetapa",CONCATENATE(TEXT(B76,"00"),".",TEXT(C76,"000"),".",TEXT(D76,"000")),IF(H76="Serviço",CONCATENATE(TEXT(B76,"00"),".",TEXT(C76,"000"),".",TEXT(D76,"000"),".",TEXT(E76,"000")),""))))) -> 04.001.001 | J76: Forma | N76: =IF(H76="Serviço",M76*L76,IF(H76="CÉLULA CONSTRUTIVA",SUMIFS($N$8:$N$452,$B$8:$B$452,B76,$H$8:$H$452,"Serviço"),IF(H76="ETAPA",SUMIFS($N$8:$N$452,$B$8:$B$452,B76,$C$8:$C$452,C76,$H$8:$H$452,"Serviço"),IF(H76="SUBETAPA",SUMIFS($N$8:$N$452,$B$8:$B$452,B76,$C$8:$C$452,C76,$D$8:$D$452,D76,$H$8:$H$452,"Serviço"),0)))) -> 0
A77: =IF($H77="UNIDADE CONSTRUTIVA",OFFSET(A77,-1,0)+1,LARGE(A$3:A76,1)) -> 0 | B77: =IF(H77="UNIDADE CONSTRUTIVA",0,IF(H77="CÉLULA CONSTRUTIVA",OFFSET(B77,-1,0)+1,OFFSET(B77,-1,0))) -> 4 | C77: =IF(H77="CÉLULA CONSTRUTIVA",0,IF(H77="ETAPA",OFFSET(C77,-1,0)+1,OFFSET(C77,-1,0))) -> 1 | D77: =IF(H77="ETAPA",0,IF(H77="SUBETAPA",OFFSET(D77,-1,0)+1,OFFSET(D77,-1,0))) -> 1 | E77: =IF(H77="Subetapa",0,IF(H77="serviço",OFFSET(E77,-1,0)+1,OFFSET(E77,-1,0))) -> 1 | H77: SERVIÇO | I77: =IF(H77="Unidade Construtiva",TEXT(A77,"00"),IF(H77="Célula Construtiva",TEXT(B77,"00"),IF(H77="Etapa",CONCATENATE(TEXT(B77,"00"),".",TEXT(C77,"000")),IF(H77="Subetapa",CONCATENATE(TEXT(B77,"00"),".",TEXT(C77,"000"),".",TEXT(D77,"000")),IF(H77="Serviço",CONCATENATE(TEXT(B77,"00"),".",TEXT(C77,"000"),".",TEXT(D77,"000"),".",TEXT(E77,"000")),""))))) -> 04.001.001.001 | J77: Fabricação de Fôrma para Pilares, em Chapa de Madeira Compensada Resinada, E=17mm | K77: m² | M77: =_xlfn.XLOOKUP($J77,CPU!$D$1:$D$3085,CPU!$H$1:$H$3085) -> 88.6471 | N77: =IF(H77="Serviço",M77*L77,IF(H77="CÉLULA CONSTRUTIVA",SUMIFS($N$8:$N$452,$B$8:$B$452,B77,$H$8:$H$452,"Serviço"),IF(H77="ETAPA",SUMIFS($N$8:$N$452,$B$8:$B$452,B77,$C$8:$C$452,C77,$H$8:$H$452,"Serviço"),IF(H77="SUBETAPA",SUMIFS($N$8:$N$452,$B$8:$B$452,B77,$C$8:$C$452,C77,$D$8:$D$452,D77,$H$8:$H$452,"Serviço"),0)))) -> 0 | O77: Considerado 2 jogos, com 6 reaproveitamentos, conforme solicitado no formulario | P77: Lançado ERP
A78: =IF($H78="UNIDADE CONSTRUTIVA",OFFSET(A78,-1,0)+1,LARGE(A$3:A77,1)) -> 0 | B78: =IF(H78="UNIDADE CONSTRUTIVA",0,IF(H78="CÉLULA CONSTRUTIVA",OFFSET(B78,-1,0)+1,OFFSET(B78,-1,0))) -> 4 | C78: =IF(H78="CÉLULA CONSTRUTIVA",0,IF(H78="ETAPA",OFFSET(C78,-1,0)+1,OFFSET(C78,-1,0))) -> 1 | D78: =IF(H78="ETAPA",0,IF(H78="SUBETAPA",OFFSET(D78,-1,0)+1,OFFSET(D78,-1,0))) -> 1 | E78: =IF(H78="Subetapa",0,IF(H78="serviço",OFFSET(E78,-1,0)+1,OFFSET(E78,-1,0))) -> 2 | H78: SERVIÇO | I78: =IF(H78="Unidade Construtiva",TEXT(A78,"00"),IF(H78="Célula Construtiva",TEXT(B78,"00"),IF(H78="Etapa",CONCATENATE(TEXT(B78,"00"),".",TEXT(C78,"000")),IF(H78="Subetapa",CONCATENATE(TEXT(B78,"00"),".",TEXT(C78,"000"),".",TEXT(D78,"000")),IF(H78="Serviço",CONCATENATE(TEXT(B78,"00"),".",TEXT(C78,"000"),".",TEXT(D78,"000"),".",TEXT(E78,"000")),""))))) -> 04.001.001.002 | J78: Fabricação de Fôrma para Vigas, em Chapa de Madeira Compensada Resinada, E=17mm | K78: m² | M78: =_xlfn.XLOOKUP($J78,CPU!$D$1:$D$3085,CPU!$H$1:$H$3085) -> 72.19483 | N78: =IF(H78="Serviço",M78*L78,IF(H78="CÉLULA CONSTRUTIVA",SUMIFS($N$8:$N$452,$B$8:$B$452,B78,$H$8:$H$452,"Serviço"),IF(H78="ETAPA",SUMIFS($N$8:$N$452,$B$8:$B$452,B78,$C$8:$C$452,C78,$H$8:$H$452,"Serviço"),IF(H78="SUBETAPA",SUMIFS($N$8:$N$452,$B$8:$B$452,B78,$C$8:$C$452,C78,$D$8:$D$452,D78,$H$8:$H$452,"Serviço"),0)))) -> 0 | O78: Considerado 2 jogos, com 6 reaproveitamentos, conforme solicitado no formulario | P78: Lançado ERP
A79: =IF($H79="UNIDADE CONSTRUTIVA",OFFSET(A79,-1,0)+1,LARGE(A$3:A78,1)) -> 0 | B79: =IF(H79="UNIDADE CONSTRUTIVA",0,IF(H79="CÉLULA CONSTRUTIVA",OFFSET(B79,-1,0)+1,OFFSET(B79,-1,0))) -> 4 | C79: =IF(H79="CÉLULA CONSTRUTIVA",0,IF(H79="ETAPA",OFFSET(C79,-1,0)+1,OFFSET(C79,-1,0))) -> 1 | D79: =IF(H79="ETAPA",0,IF(H79="SUBETAPA",OFFSET(D79,-1,0)+1,OFFSET(D79,-1,0))) -> 1 | E79: =IF(H79="Subetapa",0,IF(H79="serviço",OFFSET(E79,-1,0)+1,OFFSET(E79,-1,0))) -> 3 | H79: SERVIÇO | I79: =IF(H79="Unidade Construtiva",TEXT(A79,"00"),IF(H79="Célula Construtiva",TEXT(B79,"00"),IF(H79="Etapa",CONCATENATE(TEXT(B79,"00"),".",TEXT(C79,"000")),IF(H79="Subetapa",CONCATENATE(TEXT(B79,"00"),".",TEXT(C79,"000"),".",TEXT(D79,"000")),IF(H79="Serviço",CONCATENATE(TEXT(B79,"00"),".",TEXT(C79,"000"),".",TEXT(D79,"000"),".",TEXT(E79,"000")),""))))) -> 04.001.001.003 | J79: Fabricação de Fôrma para Lajes, em Chapa de Madeira Compensada Resinada, E=17mm | K79: m² | M79: =_xlfn.XLOOKUP($J79,CPU!$D$1:$D$3085,CPU!$H$1:$H$3085) -> 46.38483 | N79: =IF(H79="Serviço",M79*L79,IF(H79="CÉLULA CONSTRUTIVA",SUMIFS($N$8:$N$452,$B$8:$B$452,B79,$H$8:$H$452,"Serviço"),IF(H79="ETAPA",SUMIFS($N$8:$N$452,$B$8:$B$452,B79,$C$8:$C$452,C79,$H$8:$H$452,"Serviço"),IF(H79="SUBETAPA",SUMIFS($N$8:$N$452,$B$8:$B$452,B79,$C$8:$C$452,C79,$D$8:$D$452,D79,$H$8:$H$452,"Serviço"),0)))) -> 0 | O79: Considerado 2 jogos, com 6 reaproveitamentos, conforme solicitado no formulario | P79: Lançado ERP
A80: =IF($H80="UNIDADE CONSTRUTIVA",OFFSET(A80,-1,0)+1,LARGE(A$3:A79,1)) -> 0 | B80: =IF(H80="UNIDADE CONSTRUTIVA",0,IF(H80="CÉLULA CONSTRUTIVA",OFFSET(B80,-1,0)+1,OFFSET(B80,-1,0))) -> 4 | C80: =IF(H80="CÉLULA CONSTRUTIVA",0,IF(H80="ETAPA",OFFSET(C80,-1,0)+1,OFFSET(C80,-1,0))) -> 1 | D80: =IF(H80="ETAPA",0,IF(H80="SUBETAPA",OFFSET(D80,-1,0)+1,OFFSET(D80,-1,0))) -> 1 | E80: =IF(H80="Subetapa",0,IF(H80="serviço",OFFSET(E80,-1,0)+1,OFFSET(E80,-1,0))) -> 4 | H80: SERVIÇO | I80: =IF(H80="Unidade Construtiva",TEXT(A80,"00"),IF(H80="Célula Construtiva",TEXT(B80,"00"),IF(H80="Etapa",CONCATENATE(TEXT(B80,"00"),".",TEXT(C80,"000")),IF(H80="Subetapa",CONCATENATE(TEXT(B80,"00"),".",TEXT(C80,"000"),".",TEXT(D80,"000")),IF(H80="Serviço",CONCATENATE(TEXT(B80,"00"),".",TEXT(C80,"000"),".",TEXT(D80,"000"),".",TEXT(E80,"000")),""))))) -> 04.001.001.004 | J80: Fabricação de Fôrma para Escadas, em Chapa de Madeira Compensada Resinada, E=17mm | K80: m² | M80: =_xlfn.XLOOKUP($J80,CPU!$D$1:$D$3085,CPU!$H$1:$H$3085) -> 104.30944 | N80: =IF(H80="Serviço",M80*L80,IF(H80="CÉLULA CONSTRUTIVA",SUMIFS($N$8:$N$452,$B$8:$B$452,B80,$H$8:$H$452,"Serviço"),IF(H80="ETAPA",SUMIFS($N$8:$N$452,$B$8:$B$452,B80,$C$8:$C$452,C80,$H$8:$H$452,"Serviço"),IF(H80="SUBETAPA",SUMIFS($N$8:$N$452,$B$8:$B$452,B80,$C$8:$C$452,C80,$D$8:$D$452,D80,$H$8:$H$452,"Serviço"),0)))) -> 0 | O80: Considerado 2 jogos, com 6 reaproveitamentos, conforme solicitado no formulario | P80: Lançado ERP
A81: =IF($H81="UNIDADE CONSTRUTIVA",OFFSET(A81,-1,0)+1,LARGE(A$3:A80,1)) -> 0 | B81: =IF(H81="UNIDADE CONSTRUTIVA",0,IF(H81="CÉLULA CONSTRUTIVA",OFFSET(B81,-1,0)+1,OFFSET(B81,-1,0))) -> 4 | C81: =IF(H81="CÉLULA CONSTRUTIVA",0,IF(H81="ETAPA",OFFSET(C81,-1,0)+1,OFFSET(C81,-1,0))) -> 1 | D81: =IF(H81="ETAPA",0,IF(H81="SUBETAPA",OFFSET(D81,-1,0)+1,OFFSET(D81,-1,0))) -> 1 | E81: =IF(H81="Subetapa",0,IF(H81="serviço",OFFSET(E81,-1,0)+1,OFFSET(E81,-1,0))) -> 5 | H81: SERVIÇO | I81: =IF(H81="Unidade Construtiva",TEXT(A81,"00"),IF(H81="Célula Construtiva",TEXT(B81,"00"),IF(H81="Etapa",CONCATENATE(TEXT(B81,"00"),".",TEXT(C81,"000")),IF(H81="Subetapa",CONCATENATE(TEXT(B81,"00"),".",TEXT(C81,"000"),".",TEXT(D81,"000")),IF(H81="Serviço",CONCATENATE(TEXT(B81,"00"),".",TEXT(C81,"000"),".",TEXT(D81,"000"),".",TEXT(E81,"000")),""))))) -> 04.001.001.005 | J81: Montagem e Desmontagem de Fôrma de Pilares | K81: m² | M81: =_xlfn.XLOOKUP($J81,CPU!$D$1:$D$3085,CPU!$H$1:$H$3085) -> 0.69166 | N81: =IF(H81="Serviço",M81*L81,IF(H81="CÉLULA CONSTRUTIVA",SUMIFS($N$8:$N$452,$B$8:$B$452,B81,$H$8:$H$452,"Serviço"),IF(H81="ETAPA",SUMIFS($N$8:$N$452,$B$8:$B$452,B81,$C$8:$C$452,C81,$H$8:$H$452,"Serviço"),IF(H81="SUBETAPA",SUMIFS($N$8:$N$452,$B$8:$B$452,B81,$C$8:$C$452,C81,$D$8:$D$452,D81,$H$8:$H$452,"Serviço"),0)))) -> 0 | P81: Lançado ERP
A82: =IF($H82="UNIDADE CONSTRUTIVA",OFFSET(A82,-1,0)+1,LARGE(A$3:A81,1)) -> 0 | B82: =IF(H82="UNIDADE CONSTRUTIVA",0,IF(H82="CÉLULA CONSTRUTIVA",OFFSET(B82,-1,0)+1,OFFSET(B82,-1,0))) -> 4 | C82: =IF(H82="CÉLULA CONSTRUTIVA",0,IF(H82="ETAPA",OFFSET(C82,-1,0)+1,OFFSET(C82,-1,0))) -> 1 | D82: =IF(H82="ETAPA",0,IF(H82="SUBETAPA",OFFSET(D82,-1,0)+1,OFFSET(D82,-1,0))) -> 1 | E82: =IF(H82="Subetapa",0,IF(H82="serviço",OFFSET(E82,-1,0)+1,OFFSET(E82,-1,0))) -> 6 | H82: SERVIÇO | I82: =IF(H82="Unidade Construtiva",TEXT(A82,"00"),IF(H82="Célula Construtiva",TEXT(B82,"00"),IF(H82="Etapa",CONCATENATE(TEXT(B82,"00"),".",TEXT(C82,"000")),IF(H82="Subetapa",CONCATENATE(TEXT(B82,"00"),".",TEXT(C82,"000"),".",TEXT(D82,"000")),IF(H82="Serviço",CONCATENATE(TEXT(B82,"00"),".",TEXT(C82,"000"),".",TEXT(D82,"000"),".",TEXT(E82,"000")),""))))) -> 04.001.001.006 | J82: Montagem e Desmontagem de Fôrma de Vigas | K82: m² | M82: =_xlfn.XLOOKUP($J82,CPU!$D$1:$D$3085,CPU!$H$1:$H$3085) -> 4.6844188 | N82: =IF(H82="Serviço",M82*L82,IF(H82="CÉLULA CONSTRUTIVA",SUMIFS($N$8:$N$452,$B$8:$B$452,B82,$H$8:$H$452,"Serviço"),IF(H82="ETAPA",SUMIFS($N$8:$N$452,$B$8:$B$452,B82,$C$8:$C$452,C82,$H$8:$H$452,"Serviço"),IF(H82="SUBETAPA",SUMIFS($N$8:$N$452,$B$8:$B$452,B82,$C$8:$C$452,C82,$D$8:$D$452,D82,$H$8:$H$452,"Serviço"),0)))) -> 0 | P82: Lançado ERP
A83: =IF($H83="UNIDADE CONSTRUTIVA",OFFSET(A83,-1,0)+1,LARGE(A$3:A82,1)) -> 0 | B83: =IF(H83="UNIDADE CONSTRUTIVA",0,IF(H83="CÉLULA CONSTRUTIVA",OFFSET(B83,-1,0)+1,OFFSET(B83,-1,0))) -> 4 | C83: =IF(H83="CÉLULA CONSTRUTIVA",0,IF(H83="ETAPA",OFFSET(C83,-1,0)+1,OFFSET(C83,-1,0))) -> 1 | D83: =IF(H83="ETAPA",0,IF(H83="SUBETAPA",OFFSET(D83,-1,0)+1,OFFSET(D83,-1,0))) -> 1 | E83: =IF(H83="Subetapa",0,IF(H83="serviço",OFFSET(E83,-1,0)+1,OFFSET(E83,-1,0))) -> 7 | H83: SERVIÇO | I83: =IF(H83="Unidade Construtiva",TEXT(A83,"00"),IF(H83="Célula Construtiva",TEXT(B83,"00"),IF(H83="Etapa",CONCATENATE(TEXT(B83,"00"),".",TEXT(C83,"000")),IF(H83="Subetapa",CONCATENATE(TEXT(B83,"00"),".",TEXT(C83,"000"),".",TEXT(D83,"000")),IF(H83="Serviço",CONCATENATE(TEXT(B83,"00"),".",TEXT(C83,"000"),".",TEXT(D83,"000"),".",TEXT(E83,"000")),""))))) -> 04.001.001.007 | J83: Montagem e Desmontagem de Fôrma de Lajes | K83: m² | M83: =_xlfn.XLOOKUP($J83,CPU!$D$1:$D$3085,CPU!$H$1:$H$3085) -> 0.69166 | N83: =IF(H83="Serviço",M83*L83,IF(H83="CÉLULA CONSTRUTIVA",SUMIFS($N$8:$N$452,$B$8:$B$452,B83,$H$8:$H$452,"Serviço"),IF(H83="ETAPA",SUMIFS($N$8:$N$452,$B$8:$B$452,B83,$C$8:$C$452,C83,$H$8:$H$452,"Serviço"),IF(H83="SUBETAPA",SUMIFS($N$8:$N$452,$B$8:$B$452,B83,$C$8:$C$452,C83,$D$8:$D$452,D83,$H$8:$H$452,"Serviço"),0)))) -> 0 | P83: Lançado ERP
A84: =IF($H84="UNIDADE CONSTRUTIVA",OFFSET(A84,-1,0)+1,LARGE(A$3:A83,1)) -> 0 | B84: =IF(H84="UNIDADE CONSTRUTIVA",0,IF(H84="CÉLULA CONSTRUTIVA",OFFSET(B84,-1,0)+1,OFFSET(B84,-1,0))) -> 4 | C84: =IF(H84="CÉLULA CONSTRUTIVA",0,IF(H84="ETAPA",OFFSET(C84,-1,0)+1,OFFSET(C84,-1,0))) -> 1 | D84: =IF(H84="ETAPA",0,IF(H84="SUBETAPA",OFFSET(D84,-1,0)+1,OFFSET(D84,-1,0))) -> 1 | E84: =IF(H84="Subetapa",0,IF(H84="serviço",OFFSET(E84,-1,0)+1,OFFSET(E84,-1,0))) -> 8 | H84: SERVIÇO | I84: =IF(H84="Unidade Construtiva",TEXT(A84,"00"),IF(H84="Célula Construtiva",TEXT(B84,"00"),IF(H84="Etapa",CONCATENATE(TEXT(B84,"00"),".",TEXT(C84,"000")),IF(H84="Subetapa",CONCATENATE(TEXT(B84,"00"),".",TEXT(C84,"000"),".",TEXT(D84,"000")),IF(H84="Serviço",CONCATENATE(TEXT(B84,"00"),".",TEXT(C84,"000"),".",TEXT(D84,"000"),".",TEXT(E84,"000")),""))))) -> 04.001.001.008 | J84: Montagem e Desmontagem de Fôrma de Escadas | K84: m² | M84: =_xlfn.XLOOKUP($J84,CPU!$D$1:$D$3085,CPU!$H$1:$H$3085) -> 0.98718 | N84: =IF(H84="Serviço",M84*L84,IF(H84="CÉLULA CONSTRUTIVA",SUMIFS($N$8:$N$452,$B$8:$B$452,B84,$H$8:$H$452,"Serviço"),IF(H84="ETAPA",SUMIFS($N$8:$N$452,$B$8:$B$452,B84,$C$8:$C$452,C84,$H$8:$H$452,"Serviço"),IF(H84="SUBETAPA",SUMIFS($N$8:$N$452,$B$8:$B$452,B84,$C$8:$C$452,C84,$D$8:$D$452,D84,$H$8:$H$452,"Serviço"),0)))) -> 0 | P84: Lançado ERP
A85: =IF($H85="UNIDADE CONSTRUTIVA",OFFSET(A85,-1,0)+1,LARGE(A$3:A84,1)) -> 0 | B85: =IF(H85="UNIDADE CONSTRUTIVA",0,IF(H85="CÉLULA CONSTRUTIVA",OFFSET(B85,-1,0)+1,OFFSET(B85,-1,0))) -> 4 | C85: =IF(H85="CÉLULA CONSTRUTIVA",0,IF(H85="ETAPA",OFFSET(C85,-1,0)+1,OFFSET(C85,-1,0))) -> 1 | D85: =IF(H85="ETAPA",0,IF(H85="SUBETAPA",OFFSET(D85,-1,0)+1,OFFSET(D85,-1,0))) -> 2 | E85: =IF(H85="Subetapa",0,IF(H85="serviço",OFFSET(E85,-1,0)+1,OFFSET(E85,-1,0))) -> 0 | H85: SUBETAPA | I85: =IF(H85="Unidade Construtiva",TEXT(A85,"00"),IF(H85="Célula Construtiva",TEXT(B85,"00"),IF(H85="Etapa",CONCATENATE(TEXT(B85,"00"),".",TEXT(C85,"000")),IF(H85="Subetapa",CONCATENATE(TEXT(B85,"00"),".",TEXT(C85,"000"),".",TEXT(D85,"000")),IF(H85="Serviço",CONCATENATE(TEXT(B85,"00"),".",TEXT(C85,"000"),".",TEXT(D85,"000"),".",TEXT(E85,"000")),""))))) -> 04.001.002 | J85: Armadura | N85: =IF(H85="Serviço",M85*L85,IF(H85="CÉLULA CONSTRUTIVA",SUMIFS($N$8:$N$452,$B$8:$B$452,B85,$H$8:$H$452,"Serviço"),IF(H85="ETAPA",SUMIFS($N$8:$N$452,$B$8:$B$452,B85,$C$8:$C$452,C85,$H$8:$H$452,"Serviço"),IF(H85="SUBETAPA",SUMIFS($N$8:$N$452,$B$8:$B$452,B85,$C$8:$C$452,C85,$D$8:$D$452,D85,$H$8:$H$452,"Serviço"),0)))) -> 0
A86: =IF($H86="UNIDADE CONSTRUTIVA",OFFSET(A86,-1,0)+1,LARGE(A$3:A85,1)) -> 0 | B86: =IF(H86="UNIDADE CONSTRUTIVA",0,IF(H86="CÉLULA CONSTRUTIVA",OFFSET(B86,-1,0)+1,OFFSET(B86,-1,0))) -> 4 | C86: =IF(H86="CÉLULA CONSTRUTIVA",0,IF(H86="ETAPA",OFFSET(C86,-1,0)+1,OFFSET(C86,-1,0))) -> 1 | D86: =IF(H86="ETAPA",0,IF(H86="SUBETAPA",OFFSET(D86,-1,0)+1,OFFSET(D86,-1,0))) -> 2 | E86: =IF(H86="Subetapa",0,IF(H86="serviço",OFFSET(E86,-1,0)+1,OFFSET(E86,-1,0))) -> 1 | H86: SERVIÇO | I86: =IF(H86="Unidade Construtiva",TEXT(A86,"00"),IF(H86="Célula Construtiva",TEXT(B86,"00"),IF(H86="Etapa",CONCATENATE(TEXT(B86,"00"),".",TEXT(C86,"000")),IF(H86="Subetapa",CONCATENATE(TEXT(B86,"00"),".",TEXT(C86,"000"),".",TEXT(D86,"000")),IF(H86="Serviço",CONCATENATE(TEXT(B86,"00"),".",TEXT(C86,"000"),".",TEXT(D86,"000"),".",TEXT(E86,"000")),""))))) -> 04.001.002.001 | J86: Armação Aço CA-60, Diâmetro de 5,0mm para Supraestrutura, Corte e Dobra em Obra | K86: kg | M86: =_xlfn.XLOOKUP($J86,CPU!$D$1:$D$3085,CPU!$H$1:$H$3085) -> 7.550055 | N86: =IF(H86="Serviço",M86*L86,IF(H86="CÉLULA CONSTRUTIVA",SUMIFS($N$8:$N$452,$B$8:$B$452,B86,$H$8:$H$452,"Serviço"),IF(H86="ETAPA",SUMIFS($N$8:$N$452,$B$8:$B$452,B86,$C$8:$C$452,C86,$H$8:$H$452,"Serviço"),IF(H86="SUBETAPA",SUMIFS($N$8:$N$452,$B$8:$B$452,B86,$C$8:$C$452,C86,$D$8:$D$452,D86,$H$8:$H$452,"Serviço"),0)))) -> 0 | P86: Lançado ERP
A87: =IF($H87="UNIDADE CONSTRUTIVA",OFFSET(A87,-1,0)+1,LARGE(A$3:A86,1)) -> 0 | B87: =IF(H87="UNIDADE CONSTRUTIVA",0,IF(H87="CÉLULA CONSTRUTIVA",OFFSET(B87,-1,0)+1,OFFSET(B87,-1,0))) -> 4 | C87: =IF(H87="CÉLULA CONSTRUTIVA",0,IF(H87="ETAPA",OFFSET(C87,-1,0)+1,OFFSET(C87,-1,0))) -> 1 | D87: =IF(H87="ETAPA",0,IF(H87="SUBETAPA",OFFSET(D87,-1,0)+1,OFFSET(D87,-1,0))) -> 2 | E87: =IF(H87="Subetapa",0,IF(H87="serviço",OFFSET(E87,-1,0)+1,OFFSET(E87,-1,0))) -> 2 | H87: SERVIÇO | I87: =IF(H87="Unidade Construtiva",TEXT(A87,"00"),IF(H87="Célula Construtiva",TEXT(B87,"00"),IF(H87="Etapa",CONCATENATE(TEXT(B87,"00"),".",TEXT(C87,"000")),IF(H87="Subetapa",CONCATENATE(TEXT(B87,"00"),".",TEXT(C87,"000"),".",TEXT(D87,"000")),IF(H87="Serviço",CONCATENATE(TEXT(B87,"00"),".",TEXT(C87,"000"),".",TEXT(D87,"000"),".",TEXT(E87,"000")),""))))) -> 04.001.002.002 | J87: Armação Aço CA-50, Diâmetro de 6,3mm para Supraestrutura, Corte e Dobra em Obra | K87: kg | M87: =_xlfn.XLOOKUP($J87,CPU!$D$1:$D$3085,CPU!$H$1:$H$3085) -> 7.000055 | N87: =IF(H87="Serviço",M87*L87,IF(H87="CÉLULA CONSTRUTIVA",SUMIFS($N$8:$N$452,$B$8:$B$452,B87,$H$8:$H$452,"Serviço"),IF(H87="ETAPA",SUMIFS($N$8:$N$452,$B$8:$B$452,B87,$C$8:$C$452,C87,$H$8:$H$452,"Serviço"),IF(H87="SUBETAPA",SUMIFS($N$8:$N$452,$B$8:$B$452,B87,$C$8:$C$452,C87,$D$8:$D$452,D87,$H$8:$H$452,"Serviço"),0)))) -> 0 | P87: Lançado ERP
A88: =IF($H88="UNIDADE CONSTRUTIVA",OFFSET(A88,-1,0)+1,LARGE(A$3:A87,1)) -> 0 | B88: =IF(H88="UNIDADE CONSTRUTIVA",0,IF(H88="CÉLULA CONSTRUTIVA",OFFSET(B88,-1,0)+1,OFFSET(B88,-1,0))) -> 4 | C88: =IF(H88="CÉLULA CONSTRUTIVA",0,IF(H88="ETAPA",OFFSET(C88,-1,0)+1,OFFSET(C88,-1,0))) -> 1 | D88: =IF(H88="ETAPA",0,IF(H88="SUBETAPA",OFFSET(D88,-1,0)+1,OFFSET(D88,-1,0))) -> 2 | E88: =IF(H88="Subetapa",0,IF(H88="serviço",OFFSET(E88,-1,0)+1,OFFSET(E88,-1,0))) -> 3 | H88: SERVIÇO | I88: =IF(H88="Unidade Construtiva",TEXT(A88,"00"),IF(H88="Célula Construtiva",TEXT(B88,"00"),IF(H88="Etapa",CONCATENATE(TEXT(B88,"00"),".",TEXT(C88,"000")),IF(H88="Subetapa",CONCATENATE(TEXT(B88,"00"),".",TEXT(C88,"000"),".",TEXT(D88,"000")),IF(H88="Serviço",CONCATENATE(TEXT(B88,"00"),".",TEXT(C88,"000"),".",TEXT(D88,"000"),".",TEXT(E88,"000")),""))))) -> 04.001.002.003 | J88: Armação Aço CA-50, Diâmetro de 8,0mm para Supraestrutura, Corte e Dobra em Obra | K88: kg | M88: =_xlfn.XLOOKUP($J88,CPU!$D$1:$D$3085,CPU!$H$1:$H$3085) -> 7.000055 | N88: =IF(H88="Serviço",M88*L88,IF(H88="CÉLULA CONSTRUTIVA",SUMIFS($N$8:$N$452,$B$8:$B$452,B88,$H$8:$H$452,"Serviço"),IF(H88="ETAPA",SUMIFS($N$8:$N$452,$B$8:$B$452,B88,$C$8:$C$452,C88,$H$8:$H$452,"Serviço"),IF(H88="SUBETAPA",SUMIFS($N$8:$N$452,$B$8:$B$452,B88,$C$8:$C$452,C88,$D$8:$D$452,D88,$H$8:$H$452,"Serviço"),0)))) -> 0 | P88: Lançado ERP
A89: =IF($H89="UNIDADE CONSTRUTIVA",OFFSET(A89,-1,0)+1,LARGE(A$3:A88,1)) -> 0 | B89: =IF(H89="UNIDADE CONSTRUTIVA",0,IF(H89="CÉLULA CONSTRUTIVA",OFFSET(B89,-1,0)+1,OFFSET(B89,-1,0))) -> 4 | C89: =IF(H89="CÉLULA CONSTRUTIVA",0,IF(H89="ETAPA",OFFSET(C89,-1,0)+1,OFFSET(C89,-1,0))) -> 1 | D89: =IF(H89="ETAPA",0,IF(H89="SUBETAPA",OFFSET(D89,-1,0)+1,OFFSET(D89,-1,0))) -> 2 | E89: =IF(H89="Subetapa",0,IF(H89="serviço",OFFSET(E89,-1,0)+1,OFFSET(E89,-1,0))) -> 4 | H89: SERVIÇO | I89: =IF(H89="Unidade Construtiva",TEXT(A89,"00"),IF(H89="Célula Construtiva",TEXT(B89,"00"),IF(H89="Etapa",CONCATENATE(TEXT(B89,"00"),".",TEXT(C89,"000")),IF(H89="Subetapa",CONCATENATE(TEXT(B89,"00"),".",TEXT(C89,"000"),".",TEXT(D89,"000")),IF(H89="Serviço",CONCATENATE(TEXT(B89,"00"),".",TEXT(C89,"000"),".",TEXT(D89,"000"),".",TEXT(E89,"000")),""))))) -> 04.001.002.004 | J89: Armação Aço CA-50, Diâmetro de 10,0mm para Supraestrutura, Corte e Dobra em Obra | K89: kg | M89: =_xlfn.XLOOKUP($J89,CPU!$D$1:$D$3085,CPU!$H$1:$H$3085) -> 6.692055 | N89: =IF(H89="Serviço",M89*L89,IF(H89="CÉLULA CONSTRUTIVA",SUMIFS($N$8:$N$452,$B$8:$B$452,B89,$H$8:$H$452,"Serviço"),IF(H89="ETAPA",SUMIFS($N$8:$N$452,$B$8:$B$452,B89,$C$8:$C$452,C89,$H$8:$H$452,"Serviço"),IF(H89="SUBETAPA",SUMIFS($N$8:$N$452,$B$8:$B$452,B89,$C$8:$C$452,C89,$D$8:$D$452,D89,$H$8:$H$452,"Serviço"),0)))) -> 0 | P89: Lançado ERP
A90: =IF($H90="UNIDADE CONSTRUTIVA",OFFSET(A90,-1,0)+1,LARGE(A$3:A89,1)) -> 0 | B90: =IF(H90="UNIDADE CONSTRUTIVA",0,IF(H90="CÉLULA CONSTRUTIVA",OFFSET(B90,-1,0)+1,OFFSET(B90,-1,0))) -> 4 | C90: =IF(H90="CÉLULA CONSTRUTIVA",0,IF(H90="ETAPA",OFFSET(C90,-1,0)+1,OFFSET(C90,-1,0))) -> 1 | D90: =IF(H90="ETAPA",0,IF(H90="SUBETAPA",OFFSET(D90,-1,0)+1,OFFSET(D90,-1,0))) -> 2 | E90: =IF(H90="Subetapa",0,IF(H90="serviço",OFFSET(E90,-1,0)+1,OFFSET(E90,-1,0))) -> 5 | H90: SERVIÇO | I90: =IF(H90="Unidade Construtiva",TEXT(A90,"00"),IF(H90="Célula Construtiva",TEXT(B90,"00"),IF(H90="Etapa",CONCATENATE(TEXT(B90,"00"),".",TEXT(C90,"000")),IF(H90="Subetapa",CONCATENATE(TEXT(B90,"00"),".",TEXT(C90,"000"),".",TEXT(D90,"000")),IF(H90="Serviço",CONCATENATE(TEXT(B90,"00"),".",TEXT(C90,"000"),".",TEXT(D90,"000"),".",TEXT(E90,"000")),""))))) -> 04.001.002.005 | J90: Armação Aço CA-50, Diâmetro de 12,5mm para Supraestrutura, Corte e Dobra em Obra | K90: kg | M90: =_xlfn.XLOOKUP($J90,CPU!$D$1:$D$3085,CPU!$H$1:$H$3085) -> 6.505055 | N90: =IF(H90="Serviço",M90*L90,IF(H90="CÉLULA CONSTRUTIVA",SUMIFS($N$8:$N$452,$B$8:$B$452,B90,$H$8:$H$452,"Serviço"),IF(H90="ETAPA",SUMIFS($N$8:$N$452,$B$8:$B$452,B90,$C$8:$C$452,C90,$H$8:$H$452,"Serviço"),IF(H90="SUBETAPA",SUMIFS($N$8:$N$452,$B$8:$B$452,B90,$C$8:$C$452,C90,$D$8:$D$452,D90,$H$8:$H$452,"Serviço"),0)))) -> 0 | P90: Lançado ERP
A91: =IF($H91="UNIDADE CONSTRUTIVA",OFFSET(A91,-1,0)+1,LARGE(A$3:A90,1)) -> 0 | B91: =IF(H91="UNIDADE CONSTRUTIVA",0,IF(H91="CÉLULA CONSTRUTIVA",OFFSET(B91,-1,0)+1,OFFSET(B91,-1,0))) -> 4 | C91: =IF(H91="CÉLULA CONSTRUTIVA",0,IF(H91="ETAPA",OFFSET(C91,-1,0)+1,OFFSET(C91,-1,0))) -> 1 | D91: =IF(H91="ETAPA",0,IF(H91="SUBETAPA",OFFSET(D91,-1,0)+1,OFFSET(D91,-1,0))) -> 2 | E91: =IF(H91="Subetapa",0,IF(H91="serviço",OFFSET(E91,-1,0)+1,OFFSET(E91,-1,0))) -> 6 | H91: SERVIÇO | I91: =IF(H91="Unidade Construtiva",TEXT(A91,"00"),IF(H91="Célula Construtiva",TEXT(B91,"00"),IF(H91="Etapa",CONCATENATE(TEXT(B91,"00"),".",TEXT(C91,"000")),IF(H91="Subetapa",CONCATENATE(TEXT(B91,"00"),".",TEXT(C91,"000"),".",TEXT(D91,"000")),IF(H91="Serviço",CONCATENATE(TEXT(B91,"00"),".",TEXT(C91,"000"),".",TEXT(D91,"000"),".",TEXT(E91,"000")),""))))) -> 04.001.002.006 | J91: Armação Aço CA-50, Diâmetro de 16,0mm para Supraestrutura, Corte e Dobra em Obra | K91: kg | M91: =_xlfn.XLOOKUP($J91,CPU!$D$1:$D$3085,CPU!$H$1:$H$3085) -> 6.505055 | N91: =IF(H91="Serviço",M91*L91,IF(H91="CÉLULA CONSTRUTIVA",SUMIFS($N$8:$N$452,$B$8:$B$452,B91,$H$8:$H$452,"Serviço"),IF(H91="ETAPA",SUMIFS($N$8:$N$452,$B$8:$B$452,B91,$C$8:$C$452,C91,$H$8:$H$452,"Serviço"),IF(H91="SUBETAPA",SUMIFS($N$8:$N$452,$B$8:$B$452,B91,$C$8:$C$452,C91,$D$8:$D$452,D91,$H$8:$H$452,"Serviço"),0)))) -> 0 | P91: Lançado ERP
A92: =IF($H92="UNIDADE CONSTRUTIVA",OFFSET(A92,-1,0)+1,LARGE(A$3:A91,1)) -> 0 | B92: =IF(H92="UNIDADE CONSTRUTIVA",0,IF(H92="CÉLULA CONSTRUTIVA",OFFSET(B92,-1,0)+1,OFFSET(B92,-1,0))) -> 4 | C92: =IF(H92="CÉLULA CONSTRUTIVA",0,IF(H92="ETAPA",OFFSET(C92,-1,0)+1,OFFSET(C92,-1,0))) -> 1 | D92: =IF(H92="ETAPA",0,IF(H92="SUBETAPA",OFFSET(D92,-1,0)+1,OFFSET(D92,-1,0))) -> 2 | E92: =IF(H92="Subetapa",0,IF(H92="serviço",OFFSET(E92,-1,0)+1,OFFSET(E92,-1,0))) -> 7 | H92: SERVIÇO | I92: =IF(H92="Unidade Construtiva",TEXT(A92,"00"),IF(H92="Célula Construtiva",TEXT(B92,"00"),IF(H92="Etapa",CONCATENATE(TEXT(B92,"00"),".",TEXT(C92,"000")),IF(H92="Subetapa",CONCATENATE(TEXT(B92,"00"),".",TEXT(C92,"000"),".",TEXT(D92,"000")),IF(H92="Serviço",CONCATENATE(TEXT(B92,"00"),".",TEXT(C92,"000"),".",TEXT(D92,"000"),".",TEXT(E92,"000")),""))))) -> 04.001.002.007 | J92: Armação Aço CA-50, Diâmetro de 20,0mm para Supraestrutura, Corte e Dobra em Obra | K92: kg | M92: =_xlfn.XLOOKUP($J92,CPU!$D$1:$D$3085,CPU!$H$1:$H$3085) -> 6.505055 | N92: =IF(H92="Serviço",M92*L92,IF(H92="CÉLULA CONSTRUTIVA",SUMIFS($N$8:$N$452,$B$8:$B$452,B92,$H$8:$H$452,"Serviço"),IF(H92="ETAPA",SUMIFS($N$8:$N$452,$B$8:$B$452,B92,$C$8:$C$452,C92,$H$8:$H$452,"Serviço"),IF(H92="SUBETAPA",SUMIFS($N$8:$N$452,$B$8:$B$452,B92,$C$8:$C$452,C92,$D$8:$D$452,D92,$H$8:$H$452,"Serviço"),0)))) -> 0 | P92: Lançado ERP
