Workbook
Name \0: #REF!
Name \0: #REF!
Name \0: #REF!
Name \0: #REF!
Name \0: #REF!
Name \0: #REF!
Name \0: #REF!
Name \0: #REF!
Name \a: #REF!
Name \a: #REF!
Name \a: #REF!
Name \m: #REF!
Name \m: #REF!
Name \m: #REF!
Name _akhnsdkjsdb: #REF!
Name aa: #REF!
Name aa: #REF!
Name aa: #REF!
Name aa: #REF!
Name aa: #REF!
Name aa: #REF!
Name aa: #REF!
Name aa: #REF!
Name aaaa: #REF!
Name aaaa: #REF!
Name aaaa: #REF!
Name aaaa: #REF!
Name aaaa: #REF!
Name aaaa: #REF!
Name aaaa: #REF!
Name aaaa: #REF!
Name angelo: #REF!
Name angelo: #REF!
Name angelo: #REF!
Name angelo: #REF!
Name angelo: #REF!
Name angelo: #REF!
Name angelo: #REF!
Name area: #REF!
Name area: #REF!
Name area: #REF!
Name area: #REF!
Name area: #REF!
Name Areaimpresso: #REF!
Name Areaimpresso: #REF!
Name Areaimpresso: #REF!
Name Areaimpresso: #REF!
Name Areaimpresso: #REF!
Name aux: #REF!
Name aux: #REF!
Name aux: #REF!
Name BDA: #REF!
Name BDA: #REF!
Name BDA: #REF!
Name BDI: #REF!
Name ca: #REF!
Name Capa: #REF!
Name Composição: BASES!$I$72
Name cronograma: #REF!
Name cronograma: #REF!

Sheet EQUIPA FACHADA
A1: Obra | B1: ATALAIA
A2: Empresa | B2: GMF
A3: Revisão | B3: R00
A4: QUANTIFICAÇÃO
A6: Fachada
A8: Geral
B10: Opção | C10: Tempo de locação (mês) | D10: Ancoragens (un) | E10: Custo unitário locação (R$) | F10: Locação (R$) | G10: Custo unitário ancoragens (R$) | H10: Custo ancoragens (R$) | I10: Custo total (R$) | J10: Custo mensal (R$/mes)
B11: FCHADA SIMPLES (1 BALANCIM) | C11: 11.5 | D11: =4+4+5+5+6+6+6+7 -> 43 | E11: 1850 | F11: =C11*E11*1 -> 21275 | G11: 450 | H11: =G11*D11 -> 19350 | I11: =H11+F11+600+120 -> 41345 | J11: =I11/C11 -> 3595.2174
B12: *consideração de balancim com 4 metros
A14: Geral
B16: Opção | C16: Tempo de locação (mês) | D16: Custo unitário locação (R$) | E16: Locação (R$) | F16: Custo total (R$) | G16: Custo mensal (R$/mes)
B17: FCHADA SIMPLES (3 metros andaime) | C17: 2.5 | D17: 365 | E17: =C17*D17*1 -> 912.5 | F17: =E17+E18 -> 2100 | G17: =F17/5 -> 420
B18: FCHADA SIMPLES (7 metros andaime) | C18: =2.5 -> 2.5 | D18: 475 | E18: =C18*D18*1 -> 1187.5
B19: *consideração de balancim com 4 metros

Sheet OBRA
A1: Obra | B1: Viva Perequê Residencial
A2: Empresa | B2: Ferazzo e Correa Incorporadora
A3: Revisão | B3: R00
A4: DADOS OBRA
A6: ARQUITETURA
B8: Descrição | C8: Unidade | D8: Quantidade
B9: ÁREA DO TERRENO | C9: M2 | D9: 600
B10: ÁREA CONSTRUÍDA | C10: M2 | D10: 5576.17
B11: NÚMERO DE UNIDADES HABITACIONAIS | C11: UN | D11: 34
B12: MESES DE OBRA | C12: MÊS | D12: 35
B13: NÚMERO DE PAVIMENTOS | C13: UN | D13: 15

Sheet EPC's
A1: Obra | B1: =OBRA!B1 -> Viva Perequê Residencial
A2: Empresa | B2: =OBRA!B2 -> Ferazzo e Correa Incorporadora
A3: Revisão | B3: R00
A4: LEVANTAMENTO QUANTITATIVO
A6: Equipamentos de proteção coletiva
A8: Bandejas de proteção
B10: Descrição | C10: Unidade | D10: Quantidade
B11: Perímetro de projeção embasamento | C11: m | D11: =[9]DADOS_INICIAIS!$E$26 -> 93.06
B12: Perímetro de projeção torre | C12: m | D12: =[9]DADOS_INICIAIS!$E$20 -> 73.29
B13: Bandeja de proteção primária | C13: m | D13: =D11+(25-3.7)*2+(24-3.7*2) -> 152.26
B14: Bandeja de proteção secundária | C14: m | D14: =D12 -> 73.29
A16: Guarda - corpo de desforma
B18: Descrição | C18: Unidade | D18: Quantidade
B19: Perímetro de projeção da torre + vão do elevador | C19: m | D19: =#REF!+((1.75+1.75+1.75+1.75)*2) -> #REF!
B20: Repetições de pavimentos** | C20: un | D20: 19 | E20: (3 TIPOS + COBERTURA COM APRT)
B21: Proteção de periferia pós desforma torre | C21: m | D21: =(D19*D20) -> #REF!
A23: Tela fachadeira
B25: Descrição | C25: Unidade | D25: Quantidade
B26: Perímetro de projeção torre | C26: m | D26: =D19 -> #REF!
B27: Altura de cobrimento da tela | C27: m² | D27: 66.88
B28: Tela fachadeira | C28: m2 | D28: =D26*D27 -> #REF!
A29: Tela SLQA
B31: Descrição | C31: Unidade | D31: Quantidade
B32: Perímetro de projeção torre | C32: m | D32: =D19 -> #REF!
B33: Altura de cobrimento da tela | C33: m | D33: =D27-60.4 -> 6.48 | E33: ALTURA DOS 3 ULTIMOS PAVS
B34: Tela fachadeira | C34: m2 | D34: =D32*D33 -> #REF!
A36: Fechamento removível de vãos em madeira
B38: Descrição | C38: Unidade | D38: Quantidade
B39: Área das portas de elevadores | C39: m2 | D39: =11*1.935 -> 21.285
B40: Quantidade de elevadores | C40: un | D40: 2
B41: Quantidade de portas de elevadores | C41: un | D41: =D40*19 -> 38
B42: Fechamento removível de vãos em madeira | C42: m2 | D42: =D39*D41 -> 808.83
B43: Área das portas de aptos | C43: m2
B44: Quantidade de aptos | C44: un
B45: Quantidade de portas de aptos | C45: un
B46: =BASES!A77 -> Fechamento removível de vãos de porta de entrada dos aptos. em madeira | C46: m2 | D46: =(0.9*2.17)*(6+(4*6)+(4*6)+(4*2)+5) -> 130.851
B47: =BASES!A78 -> Fechamento removível de abertura no piso do elevador em madeira | C47: m2 | D47: =(D40*D41)*3.06 -> 232.56
A48: Guarda - corpo de vãos
B50: Descrição | C50: Unidade | D50: Quantidade
B51: Perímetro de vãos | C51: m | D51: =(1.59*28)+(1.95*17)+(5.13*28)+(1.6*11)+(3.32*15)+23.99+10.4 -> 323.1
B52: Guarda - corpo de vãos | C52: m | D52: =D51 -> 323.1
A54: Tapume
B56: Descrição | C56: Unidade | D56: Quantidade
B57: Perímetro terreno | C57: m | D57: =26+26+24+24 -> 100
B58: Altura do tapume | C58: m | D58: 2.2
B59: Cobertura para proteção de pedestres | C59: m2 | D59: =D58*D57 -> 220
A61: Fechamento de fossos
B63: Descrição | C63: Unidade | D63: Quantidade
B64: Area de fossos | C64: m2 | D64: =(1.75*1.75)*2 -> 6.125
B65: Numero de pavimentos | C65: un | D65: =D20 -> 19
B66: Cobertura para proteção de pedestres | C66: m2 | D66: =D65*D64 -> 116.375

Sheet CANTEIRO
A1: Obra | B1: =OBRA!B1 -> Viva Perequê Residencial
A2: Empresa | B2: =OBRA!B2 -> Ferazzo e Correa Incorporadora
A3: Revisão | B3: R00 | N3: Número de funcionários | R3: Produtividade média (h/m2)
A4: LEVANTAMENTO QUANTITATIVO | N4: Área construída | O4: =OBRA!D10 -> 5576.17 | R4: A.C/prazo | S4: =O4/O5 -> 159.31914
N5: Prazo da obra | O5: =OBRA!D12 -> 35 | P5: meses | R5: Pm | S5: 49 | T5: h/m2
A6: Instalações de canteiro | N6: NF | O6: =ROUNDUP((O4*S5)/O5/180,) -> 44 | P6: funcionários
N7: Pavimentos | O7: 9
A8: Instalações de canteiro | N8: Equipe administrativa | O8: 4 | P8: funcionários
B10: Descrição | C10: Unidade | D10: Quantidade
B11: Produtividade média | C11: h/m2 | D11: =OBRA!D10/OBRA!D12 -> 159.31914 | N11: Barracão interno | O11: =450+(O4-13000)/1000*16 -> 331.21872
B12: Pm | C12: h/m2 | D12: 49 | N12: Externo | O12: =O11*0.4 -> 132.48749
B13: Numero de funcionários | C13: un | D13: =ROUNDUP((D12*OBRA!D10)/OBRA!D12/180,) -> 44
B14: Equipe administrativa | C14: un | D14: 4 | O14: =SUM(O11:O13) -> 463.70621
B15: Pontos de água e esgoto | C15: un | D15: 3 | E15: 20 funcionários/ponto
B16: Bebedouro | C16: un | D16: =ROUNDUP(OBRA!$D$13/5,0) -> 3 | E16: 1 / 5 pav. | N16: Área refeitório | O16: 1 | P16: m²/funcionários
B17: Ferramentas | C17: R$ | D17: =800*(D13+D14) -> 38400 | E17: 800,00/func. | O17: =O16*O6 -> 44 | P17: m²
B18: EPI | C18: R$ | D18: =500*(D13+D14) -> 24000 | E18: 500,00/func. | H18: https://www.sienge.com.br/blog/dimensione-o-canteiro-de-obras-corretamente/
B19: Banheiro | C19: un | D19: =ROUNDUP(($D$13+D14)/20,0) -> 3 | E19: 1/20 func | N19: Área de vestiário | O19: 1.5 | P19: m²/funcionários
O20: =O19*O6 -> 66 | P20: m²
A21: Mobiliário de canteiro
B23: Descrição | C23: Unidade | D23: Quantidade | E23: Custo unitário | F23: Custo total
B24: Cadeira | C24: un | D24: =ROUNDUP(D25*1.5,0) -> 62 | E24: 200 | F24: =D24*E24 -> 12400
B25: Mesa | C25: un | D25: 41 | E25: 1000 | F25: =E25*D25 -> 41000
B26: Ar condicionado | C26: un | D26: 6 | E26: 5000 | F26: =E26*D26 -> 30000
B27: Armário | C27: m | D27: 13 | E27: 900 | F27: =E27*D27 -> 11700
B28: Cadeira | C28: un | D28: =ROUNDUP(D29*1.5,0) -> 48 | E28: 200 | F28: =D28*E28 -> 9600
B29: Escrivaninha | C29: un | D29: 32 | E29: 800 | F29: =E29*D29 -> 25600
B30: TOTAL | F30: =F26+F27+F29+F25+F24 -> 120700
B31: Descrição | C31: Unidade | D31: Quantidade | E31: Custo unitário | F31: Custo total
B32: Computador pessoal | C32: un | D32: 6 | E32: 6000 | F32: =D32*E32 -> 36000 | N32: Área sanitários | O32: =1*ROUNDUP(O6/20,) -> 3 | P32: m²
B33: Impressora | C33: un | D33: 1 | E33: 2000 | F33: =E33*D33 -> 2000
B34: Roteador | C34: un | D34: 6 | E34: 500 | F34: =E34*D34 -> 3000 | N34: área lavatório | O34: =0.6*ROUNDUP(O6/20,) -> 1.8 | P34: m²
B35: TOTAL | F35: =+F32+F33+F34 -> 41000 | N35: Área de chuveiros | O35: =0.8*ROUNDUP(O6/10,) -> 4 | P35: m²
N37: Escritório | O37: 8 | P37: m²/pessoa
O38: =O37*O8 -> 32 | P38: m²
N40: Almoxarifado | O40: =IF(O4<20000,100,100+((O4-20000)/1000)*5) -> 100 | P40: m2
O42: =O40+O38+O35+O34+O32+O20+O17 -> 250.8
N45: Pontos de água e esgoto | O45: 20 | P45: funcionários/ponto
N46: Pontos de água e esgoto | O46: =ROUNDUP(O6/O45,) -> 3 | P46: pontos
N49: Bebedouro | O49: 1 | P49: a cada 5 pav.
N50: Total | O50: =ROUNDUP(O7/5,) -> 2 | P50: bebedouros
N52: Ferramentas | O52: =O6*800 -> 35200 | P52: 800 por funcionário
N54: EPI | O54: =O6*500 -> 22000 | P54: 500,00 por funcionário | Q54: Considerando entrega de 2 uniformes, capacete, bota, óculos e cinto
N57: Banheiro | O57: 1 | P57: para cada | Q57: 20 | R57: pessoas
O58: =ROUNDUP(O6/Q57,) -> 3

Sheet RESPOSTAS
A2: Carimbo de data/hora
A4: Endereço de e-mail
A5: Cliente
A6: Obra
A7: Responsável pelo questionário
A8: Data de preenchimento do formulário
A9: Memorial descritivo
A10: Levantamento topográfico
A11: Estudo geológico
A12: Estudo ambiental
A13: Sondagem do terreno
A14: Projeto de canteiro
... A16: Legalização de incorporação
A17: Projeto arquitetônico legal | C17: (legal e executivo)
A18: Projeto arquitetônico executivo
A19: Projeto arquitetônico interiores/ambientação
A20: Projeto arquitetônico de fachada
A21: Projeto técnico de fachada
A22: Projeto de terraplanagem
A23: Projeto de fundação
A24: Projeto estrutural em concreto armado | C24: (já com fundação)
A25: Projeto de estrutura metálica
A26: Projeto de alvenaria estrutural
A27: Projeto elétrico | C27: (elétrico / comunicação / telefonia)
A28: Projeto comunicação e dados
A29: Projeto de telefonia
A30: Projeto luminotécnico
A31: Projeto de automação | C31: (automação / segurança / cftv )
A32: Projeto hidrossanitário | C32: (hidráulico e sanitário)
A33: Projeto de drenagem
A34: Projeto pluvial
A35: Projeto de irrigação
A36: Projeto preventivo (PPCI - Plano de Prevenção e Proteção Contra Incêndios)
A37: Projeto de climatização | C37: (climatização e exaustão)
A38: Projeto de exaustão
A39: Projeto de gás
A40: Projeto de segurança
A41: Projeto de impermeabilização
A42: Projeto de esquadrias
A43: Projeto de forro
A44: Projeto acústico
A45: Projeto de sonorização
A46: Projeto de piscina
A47: Projeto de comunicação visual
A48: Projeto de paisagismo
A49: Projeto de pavimentação
... A51: Modelagem BIM de complementares
A52: Compatibilização de projetos BIM | C52: (coordenação e compatibilização)
A53: Informações complementares
A54: Consultoria técnica de esquadrias
A55: Consultoria técnica de fachada
A56: Consultoria técnica de legalização
A57: Consultorias técnicas diversas
A58: Orçamento e planejamento
A59: Consultoria técnica de qualidade
A60: Auditoria de qualidade
A61: Informações complementares
A62: Despesas de seguro de obra
A63: Aprovação e legalização ambiental
A64: Aprovação e legalização prefeitura
... A69: Taxas de Alvará
A70: Despesas cartório, licenças, certidões e jurídicas | C70: 0,00 já temos pago custos de advogados o valor de
A71: Incorporação
A72: IPTU
A73: Taxa Habite-se
A74: As Built
A75: Laudo técnico de vistoria de entrega
A76: Manuais técnicos condomínio/proprietários
A77: Certidão INSS
A78: Informações complementares
A79: Quantidade
A80: Salário/mês (R$)
A81: Encargos (%)
A82: Informações complementares
... A88: Verba (R$)
A89: Plataformas de proteção - Tipo [Trama de madeira forrada em painel compensado - Primária] | B89: 1 montagem por obra
A90: Plataformas de proteção - Tipo [Trama de madeira forrada em painel compensado - Secundária]
A91: Plataformas de proteção - Tipo [Trama de madeira forrada em painel compensado - Terciária]
A92: Plataformas de proteção - Tipo [Fundação em tábua de madeira serrada - Primária]
A93: Plataformas de proteção - Tipo [Fundação em tábua de madeira serrada - Secundária]
A94: Plataformas de proteção - Tipo [Fundação em tábua de madeira serrada - Terciária]
A95: Outros (especifique)
A96: Guarda-corpo de vãos | B96: Guarda-corpo de vãos, fixado em fôrma de madeira, em trama de madeira com tela de polipropileno
A97: Outros
A98: Outros (especifique)
A99: Guarda-corpo de laje após desforma | B99: Guarda-corpo de laje após desforma - Escora metálica, travessões e tela
A100: Outros (especifique)
A101: Outros tipos de proteção que serão utilizados na obra | B101: Fechamento removível de vãos de porta de elevador em madeira,
A102: Outros | B102: Fechamento removível de vãos de porta de entrada dos aptos. em madeira
A103: Linha de vida | B103: Varal de segurança com cabo de aço
A104: Outros (especifique)
A105: Sinalização | B105: Placa indicativa fixada em totem
A106: Outros (especifique)
A107: Rede de proteção tipo SLQA(Sistemas Limitadores para Quedas de Alturas) | B107: Não se aplica
A108: Tela fachadeira - Material | B108: Tela de polietileno reforçada simples
A109: Outros (especifique)
A110: Informações complementares
A111: Elaboração do Programa de Prevenção dos Riscos Ambientais (PPRA)
A112: Elaboração do Programa de Controle Médico de Saúde Ocupacional (PCMSO)
A113: Elaboração do Programa de Condições e Meio Ambiente de Trabalho na indústria da construção (PCMAT)
...

Sheet COMPOSIÇÃO
F2: UNIDADE | G2: QUANT. | H2: PREÇO
D3: SERVIÇO | E3: Bandeja primaria - 1 montagem | F3: =BASES!E41 -> vb | G3: =BASES!F41 -> 1 | H3: =(G4*H4)+(G6*H6)+(G9*H9)+(G5*H5)+(G7*H7)+(G8*H8) -> 524.26322
D4: COMPOSIÇÃO | E4: Prego de aço polido com cabeça 17x21 | F4: kg | G4: 0.1238 | H4: 14.65
E5: tabua pinus 3a construção 2,5x30 cm | F5: m | G5: 3.903005 | H5: 21.3
E6: Suporte de plataforma de proteção primaria principal perfil em u em aço de 3 mm 2500x800x40x75x40 mm com caibro e pino de fixação | F6: UNIDADE | G6: 0.4 | H6: 218
E7: Chapa/painel de madeira compensada plastificada ( madeirite plastificado) para forma de concreto, de 2200 x 1100 mm, e = 14 mm | F7: m² | G7: 4.0201 | H7: 57.28
E8: Tábua Pinus 2,5x15 cm | F8: m | G8: 1.831333 | H8: 11.96
E9: Aço CA-50 Ø 16,00 mm - Vergalhão | F9: kg | G9: 1.3676 | H9: 73.078
F32: UNIDADE | G32: QUANT. | H32: PREÇO
D33: SERVIÇO | E33: =BASES!A77 -> Fechamento removível de vãos de porta de entrada dos aptos. em madeira | F33: M² | G33: =BASES!F77 -> 130.851 | H33: =(G34*H34)+(G35*H35) -> 6.14475
D34: COMPOSIÇÃO | E34: Prego de aço polido com cabeça 17x21 | F34: KG | G34: 0.015 | H34: 14.65
E35: Sarrafo 2,5x7,5 em pinus | F35: M | G35: 1.975 | H35: 3
F39: UNIDADE | G39: QUANT. | H39: PREÇO
D40: SERVIÇO | E40: =BASES!A75 -> Guarda-corpo de laje após desforma - Escora metálica, travessões e tela | F40: =BASES!E75 -> m | G40: =BASES!F75 -> #REF! | H40: =(G41*H41)+(G43*H43)+(G44*H44)+(G42*H42) -> 36.92914
D41: COMPOSIÇÃO | E41: TELA PLASTICA TECIDA LISTRADA BRANCA E LARANJA, TIPO GUARDA CORPO, EM POLIETILENO MONOFILADO, ROLO 1,20 X 50 M (L X C) | F41: M | G41: 0.55 | H41: 2.73
E42: TABUA APARELHADA *2,5 X 15* CM, EM MACARANDUBA/MASSARANDUBA, ANGELIM OU EQUIVALENTE DA REGIAO | F42: M² | G42: 0.233 | H42: 144.68
E43: LOCACAO DE ESCORA METALICA TELESCOPICA, COM ALTURA REGULAVEL DE *1,80* A *3,20* M, COM CAPACIDADE DE CARGA DE NO MINIMO 1000 KGF (10 KN), INCLUSO TRIPE E FORCADO | F43: UNXMES | G43: 0.1 | H43: 16
E44: Prego de aço polido com cabeça 17x21 | F44: KG | G44: 0.008 | H44: 14.65
F47: UNIDADE | G47: QUANT. | H47: PREÇO
D48: SERVIÇO | E48: TOTEM EM MADEIRA COM PLACA INDICATIVA POSICIONADA NO TERRENO | F48: =BASES!#REF! -> #REF! | G48: =BASES!F87 -> 1 | H48: =(G49*H49)+(G51*H51)+(G52*H52)+(G50*H50) -> 360.9236
D49: COMPOSIÇÃO | E49: CHAPA/PAINEL DE MADEIRA COMPENSADA RESINADA (MADEIRITE RESINADO ROSA) PARA FORMA DE CONCRETO, DE 2200 x 1100 MM, E = 14 MMROLO 1,20 X 50 M (L X C) | F49: M² | G49: 5.9392 | H49: 57.28
E50: PLACA DE SINALIZACAO DE SEGURANCA, FOTOLUMINESCENTE, EM PVC *2* MM ANTI-CHAMAS (SIMBOLOS, CORES E PICTOGRAMAS CONFORME NBR 13434) | F50: M² | G50: 1 | H50: 12
E51: GRAMPO PARA GRAMPEADOR PNEUMATICO 13 X 16 MM | F51: UNIDADE | G51: 0.011 | H51: =1113.63/18000 -> 0.061868333
E52: Prego de aço polido com cabeça 17x21 | F52: KG | G52: 0.5956 | H52: 14.65
F55: UNIDADE | G55: QUANT. | H55: PREÇO
D56: SERVIÇO | E56: =BASES!A125 -> Tapume de TELHA METÁLICA TRAPEZOIDAL | F56: =BASES!E125 -> m2 | G56: =BASES!F125 -> 220 | H56: =(G57*H57)+(G60*H60)+(G61*H61)+(G58*H58)+(G59*H59) -> 132.54723
D57: COMPOSIÇÃO | E57: Prego de aço 18x27 com cabeça | F57: kg | G57: 0.0428 | H57: 12.12
E58: Tábua de madeira 2,5x30 | F58: m | G58: 1 | H58: 21.3
E59: Telha aço zincado trapezoidal | F59: m² | G59: 1.05 | H59: 97
E60: vigota 7,5x7,5 cm | F60: m | G60: 1.2273 | H60: 6.89
E61: Concreto magro 150 kg cim/m³ | F61: m³ | G61: 0.0012 | H61: 352

Sheet BASES
A1: ="ORÇAMENTO EXECUTIVO - "&UPPER(OBRA!B1) -> ORÇAMENTO EXECUTIVO - VIVA PEREQUÊ RESIDENCIAL
L2: Área Const. | M2: =NOUVE!B9 -> 5438.9 | N2: Área Const. | O2: =VANCOUVER!B6 -> 5554.12 | P2: Área Const. | Q2: ='VILLA LOBOS'!B7 -> 6001.7 | R2: Área Const. | S2: ='GRAN TOWER'!B8 -> 6245.48 | T2: Área Const. | U2: =[3]OBRA!D10 -> 6348.51
A3: Empresa: | B3: =OBRA!B2 -> Ferazzo e Correa Incorporadora | L3: Data base | M3: =NOUVE!B10 -> 44805 | N3: Data base | O3: =VANCOUVER!B7 -> 44621 | P3: Data base | Q3: ='VILLA LOBOS'!B8 -> 45108 | R3: Data base | S3: ='GRAN TOWER'!B9 -> 45383 | T3: Data base | U3: =[3]OBRA!D14 -> 45413
A4: Obra: | B4: =OBRA!B1 -> Viva Perequê Residencial | L4: cub | M4: =NOUVE!B11 -> 2623.42 | N4: cub | O4: =VANCOUVER!B8 -> 2444.3 | P4: cub | Q4: ='VILLA LOBOS'!B9 -> 2747.9 | R4: cub | S4: ='GRAN TOWER'!B10 -> 2757.56 | T4: cub | U4: 2755.41 | W4: MABREM - GRAN TORINO | X4: =U4/[4]ORÇAMENTO_EXECUTIVO!$B$19 -> 0.99922033
A5: Revisão | L5: Index | M5: =($U$4/M4) -> 1.0503122 | N5: Index | O5: =($U$4/O4) -> 1.1272798 | P5: Index | Q5: =($U$4/Q4) -> 1.002733 | R5: Index | S5: =($U$4/S4) -> 0.99922033 | T5: Index | W5: GMF - ATALAIA | X5: =U4/[5]ORÇAMENTO_EXECUTIVO!$F$22 -> 0.99922033
A6: Data: | B6: 45441 | L6: Á. Terreno | M6: =NOUVE!B8 -> 0 | N6: Á. Terreno | O6: =VANCOUVER!B5 -> 0 | P6: Á. Terreno | Q6: ='VILLA LOBOS'!B6 -> 553.46 | R6: Á. Terreno | S6: ='GRAN TOWER'!B7 -> 859.95 | T6: Á. Terreno | U6: =[3]OBRA!D9 -> 624 | W6: AS RAMOS - PAESSAGIO | X6: =U4/[6]BASES!$Q$4 -> 1.0278159
L7: HOLZE | N7: =VANCOUVER!B4 -> PASS-E | P7: ='[3]VILLA LOBOS'!B5 -> MACOM | R7: ='GRAN TOWER'!B5 -> GRANDEZZA | T7: =B3 -> Ferazzo e Correa Incorporadora
A8: DESPESAS INDIRETAS | L8: =NOUVE!B5 -> NOUVE 354 | N8: =VANCOUVER!B3 -> VANCOUVER | P8: ='[3]VILLA LOBOS'!B4 -> VILLA LOBOS | R8: ='GRAN TOWER'!B4 -> GRAN TOWER | T8: =B4 -> Viva Perequê Residencial
A9: Descrição | E9: Unidade | F9: Quantidade | G9: Valor (R$) | H9: Total | I9: Consideração | J9: Status | L9: Valor | M9: Referencia | N9: Valor | O9: Referencia | P9: Valor | Q9: Referencia | R9: Valor | S9: Referencia | T9: m² | U9: Total
A10: TERRENO
A11: Memorial descritivo | E11: vb | F11: 1 | G11: =U11 -> 6867.9583 | H11: =F11*G11 -> 6867.9583 | I11: Média | J11: Lançado Sienge | L11: =NOUVE!E19 -> 0 | M11: =(L11*$M$5)/$M$2 -> 0 | O11: =(N11*$O$5)/$O$2 -> 0 | P11: ='VILLA LOBOS'!E16 -> 6449 | Q11: =(P11*$Q$5)/$Q$2 -> 1.0774656 | R11: ='GRAN TOWER'!E17 -> 6789 | S11: =(R11*$S$5)/$S$2 -> 1.0861786 | T11: =(Q11+S11)/2 -> 1.0818221 | U11: =T11*$U$2 -> 6867.9583
A12: Estudo ambiental | E12: vb | F12: 1 | G12: 3866.34 | H12: =F12*G12 -> 3866.34 | I12: Informado no Formulário | J12: Lançado Sienge | L12: =NOUVE!E21 -> 3600 | M12: =(L12*$M$5)/$M$2 -> 0.69520011 | N12: =VANCOUVER!E15 -> 5100 | O12: =(N12*$O$5)/$O$2 -> 1.0351103 | P12: ='VILLA LOBOS'!E19 -> 3794 | Q12: =(P12*$Q$5)/$Q$2 -> 0.6338819 | R12: ='VILLA LOBOS'!G19 -> 0 | S12: =(R12*$S$5)/$S$2 -> 0 | T12: =(Q12+M12+O12)/3 -> 0.78806411 | U12: =T12*$U$2 -> 5003.0329
A13: Levantamento topográfico | E13: vb | F13: 1 | G13: 900 | H13: =F13*G13 -> 900 | I13: Informado no Formulário | J13: Lançado Sienge | L13: =NOUVE!E20 -> 1021 | M13: =(L13*$M$5)/$M$2 -> 0.19716648 | N13: =VANCOUVER!E14 -> 400 | O13: =(N13*$O$5)/$O$2 -> 0.081185123 | P13: ='VILLA LOBOS'!E17 -> 1200 | Q13: =(P13*$Q$5)/$Q$2 -> 0.20048979 | R13: ='VILLA LOBOS'!G17 -> 0 | S13: =(R13*$S$5)/$S$2 -> 0 | T13: =(Q13+M13+O13)/3 -> 0.1596138 | U13: =T13*$U$2 -> 1013.3098
A14: Estudo geológico | E14: vb | F14: 1 | G14: =U14 -> 5459.9107 | H14: =F14*G14 -> 5459.9107 | I14: Média | J14: Lançado Sienge | M14: =(L14*$M$5)/$M$2 -> 0 | O14: =(N14*$O$5)/$O$2 -> 0 | P14: ='VILLA LOBOS'!E18 -> 3794 | Q14: =(P14*$Q$5)/$Q$2 -> 0.6338819 | R14: ='GRAN TOWER'!E19 -> 6789 | S14: =(R14*$S$5)/$S$2 -> 1.0861786 | T14: =(Q14+S14)/2 -> 0.86003025 | U14: =T14*$U$2 -> 5459.9107
A15: Sondagem do terreno | E15: vb | F15: 1 | G15: 6586 | H15: =F15*G15 -> 6586 | I15: Informado no Formulário | J15: Lançado Sienge | L15: =NOUVE!E22 -> 8204 | M15: =(L15*$M$5)/$M$2 -> 1.5842838 | N15: =VANCOUVER!E16 -> 4369.97 | O15: =(N15*$O$5)/$O$2 -> 0.88694138 | P15: ='VILLA LOBOS'!E20 -> 9000 | Q15: =(P15*$Q$5)/$Q$2 -> 1.5036735 | R15: ='VILLA LOBOS'!G20 -> 0 | S15: =(R15*$S$5)/$S$2 -> 0 | T15: =(Q15+M15+O15)/3 -> 1.3249662 | U15: =T15*$U$2 -> 8411.5613
A16: =RESPOSTAS!A14 -> Projeto de canteiro | E16: vb | F16: 1 | G16: =U16 -> 6895.6158 | H16: =F16*G16 -> 6895.6158 | I16: Média | J16: Lançado Sienge | L16: =NOUVE!E23 -> 0 | M16: =(L16*$M$5)/$M$2 -> 0 | O16: =(N16*$O$5)/$O$2 -> 0 | Q16: =(P16*$Q$5)/$Q$2 -> 0 | R16: ='GRAN TOWER'!E22 -> 6789 | S16: =(R16*$S$5)/$S$2 -> 1.0861786 | T16: =S16 -> 1.0861786 | U16: =T16*$U$2 -> 6895.6158 | X16: =$W$4 -> MABREM - GRAN TORINO | Y16: =( 3600*$X$5)/[4]ORÇAMENTO_EXECUTIVO!$G$2 -> 0.28733962
A17: =RESPOSTAS!A16 -> Legalização de incorporação | E17: vb | F17: 1 | G17: 14611.4 | H17: =F17*G17 -> 14611.4 | I17: Informado no Formulário | J17: Lançado Sienge | M17: =(L17*$M$5)/$M$2 -> 0 | N17: =VANCOUVER!E18 -> 8000 | O17: =(N17*$O$5)/$O$2 -> 1.6237025 | P17: ='VILLA LOBOS'!E22 -> 11291 | Q17: =(P17*$Q$5)/$Q$2 -> 1.8864419 | R17: ='VILLA LOBOS'!G22 -> 0 | S17: =(R17*$S$5)/$S$2 -> 0 | T17: =(Q17+O17)/2 -> 1.7550722 | U17: =T17*$U$2 -> 11142.093 | V17: =W5 -> GMF - ATALAIA | W17: =(12000*$X$5)/[5]ORÇAMENTO_EXECUTIVO!$N$4 -> 1.6260308 | Z17: =$W$4 -> MABREM - GRAN TORINO | AA17: =( 12000*$X$5)/[4]ORÇAMENTO_EXECUTIVO!$G$2 -> 0.95779872
A18: PROJETOS
A19: Projeto arquitetôico executivo | E19: vb | F19: 1 | G19: 80000 | H19: =F19*G19 -> 80000 | I19: Informado no Formulário | J19: Lançado Sienge | M19: =(L19*$M$5)/$M$2 -> 0 | N19: =VANCOUVER!E20+VANCOUVER!E21 -> 62064.16 | O19: =(N19*$O$5)/$O$2 -> 12.596716 | P19: ='VILLA LOBOS'!E24 -> 25629 | Q19: =(P19*$Q$5)/$Q$2 -> 4.2819608 | R19: ='VILLA LOBOS'!G24 -> 0 | S19: =(R19*$S$5)/$S$2 -> 0 | T19: =(Q19+O19)/2 -> 8.4393385 | U19: =T19*$U$2 -> 53577.225
A20: Projeto arquitetôico legal + executivo + elétrico+ comunicação + telefonia+luminotécnico+hidrosanitario+drenagem+pluvial+gás | E20: vb | F20: 1 | I20: Informado no Formulário | J20: Lançado Sienge | L20: =NOUVE!E25 -> 100000 | M20: =(L20*$M$5)/$M$2 -> 19.311114 | N20: =VANCOUVER!E19 -> 20297.38 | O20: =(N20*$O$5)/$O$2 -> 4.1196132 | P20: ='VILLA LOBOS'!E23 -> 22991 | Q20: =(P20*$Q$5)/$Q$2 -> 3.8412174 | R20: ='VILLA LOBOS'!G23 -> 0 | S20: =(R20*$S$5)/$S$2 -> 0 | T20: =(Q20+M20+O20)/3 -> 9.0906483 | U20: =T20*$U$2 -> 57712.071
A21: Projeto fachada | E21: vb | F21: 1 | G21: =U21 -> 2721.4845 | H21: =F21*G21 -> 2721.4845 | I21: Média | J21: Lançado Sienge | M21: =(L21*$M$5)/$M$2 -> 0 | N21: =VANCOUVER!E22 -> 2500 | O21: =(N21*$O$5)/$O$2 -> 0.50740702 | Q21: =(P21*$Q$5)/$Q$2 -> 0 | R21: ='GRAN TOWER'!E28 -> 2187.34 | S21: =(R21*$S$5)/$S$2 -> 0.34995462 | T21: =(O21+S21)/2 -> 0.42868082 | U21: =T21*$U$2 -> 2721.4845
A22: Projeto de interiores - interiores | E22: vb | F22: 1 | G22: =U22 -> 68955.142 | H22: =F22*G22 -> 68955.142 | I22: Média | J22: Lançado Sienge | M22: =(L22*$M$5)/$M$2 -> 0 | O22: =(N22*$O$5)/$O$2 -> 0 | Q22: =(P22*$Q$5)/$Q$2 -> 0 | R22: ='GRAN TOWER'!E27 -> 67889 | S22: =(R22*$S$5)/$S$2 -> 10.861626 | T22: =S22 -> 10.861626 | U22: =T22*$U$2 -> 68955.142
A23: Projeto fundação | E23: vb | F23: 1 | G23: =U23 -> 14739.662 | H23: =F23*G23 -> 14739.662 | I23: Informado no Formulário | J23: Lançado Sienge | L23: =NOUVE!E26 -> 11200 | M23: =(L23*$M$5)/$M$2 -> 2.1628448 | N23: =VANCOUVER!E23 -> 12222.23 | O23: =(N23*$O$5)/$O$2 -> 2.4806581 | Q23: =(P23*$Q$5)/$Q$2 -> 0 | S23: =(R23*$S$5)/$S$2 -> 0 | T23: =(M23+O23)/2 -> 2.3217515 | U23: =T23*$U$2 -> 14739.662
A24: Projeto terraplanagem | E24: vb | F24: 1 | G24: =U24 -> 0 | H24: =F24*G24 -> 0 | I24: Informado no Formulário | J24: Lançado Sienge | M24: =(L24*$M$5)/$M$2 -> 0 | O24: =(N24*$O$5)/$O$2 -> 0 | Q24: =(P24*$Q$5)/$Q$2 -> 0 | S24: =(R24*$S$5)/$S$2 -> 0 | T24: =(M24+O24)/2 -> 0 | U24: =T24*$U$2 -> 0
A25: Projeto estrutural | E25: vb | F25: 1 | G25: =U25 -> 72163.128 | H25: =F25*G25 -> 72163.128 | I25: Informado no Formulário | J25: Lançado Sienge | L25: =NOUVE!E27 -> 52450 | M25: =(L25*$M$5)/$M$2 -> 10.128679 | N25: =VANCOUVER!E24 -> 48634.64 | O25: =(N25*$O$5)/$O$2 -> 9.8710231 | P25: ='VILLA LOBOS'!E28 -> 84400 | Q25: =(P25*$Q$5)/$Q$2 -> 14.101115 | R25: ='VILLA LOBOS'!G28 -> 0 | S25: =(R25*$S$5)/$S$2 -> 0 | T25: =(Q25+M25+O25)/3 -> 11.366939 | U25: =T25*$U$2 -> 72163.128
A26: Projeto estrutura metálica | E26: vb | F26: 1 | G26: =U26 -> 30471.126 | H26: =F26*G26 -> 30471.126 | I26: Média | J26: Lançado Sienge | L26: =NOUVE!E28 -> 0 | M26: =(L26*$M$5)/$M$2 -> 0 | O26: =(N26*$O$5)/$O$2 -> 0 | Q26: =(P26*$Q$5)/$Q$2 -> 0 | R26: ='GRAN TOWER'!E31 -> 30000 | S26: =(R26*$S$5)/$S$2 -> 4.7997287 | T26: =S26 -> 4.7997287 | U26: =T26*$U$2 -> 30471.126
A27: Projeto de alvenaria estrutural | E27: vb | F27: 1 | G27: 1385000 | H27: =F27*G27 -> 1385000 | I27: Informado no Formulário | J27: Lançado Sienge | L27: =NOUVE!E29 -> 0 | M27: =(L27*$M$5)/$M$2 -> 0 | O27: =(N27*$O$5)/$O$2 -> 0 | Q27: =(P27*$Q$5)/$Q$2 -> 0 | S27: =(R27*$S$5)/$S$2 -> 0 | T27: =(Q27+M27+O27)/3 -> 0 | U27: =T27*$U$2 -> 0
A28: Projeto automação | E28: vb | F28: 1 | G28: =U28 -> 2031.4084 | H28: =F28*G28 -> 2031.4084 | I28: Média | J28: Lançado Sienge | M28: =(L28*$M$5)/$M$2 -> 0 | O28: =(N28*$O$5)/$O$2 -> 0 | Q28: =(P28*$Q$5)/$Q$2 -> 0 | R28: ='GRAN TOWER'!E33 -> 2000 | S28: =(R28*$S$5)/$S$2 -> 0.31998191 | T28: =S28 -> 0.31998191 | U28: =T28*$U$2 -> 2031.4084
A29: Projeto irrigação | E29: vb | F29: 1 | G29: =U29 -> 0 | H29: =F29*G29 -> 0 | I29: Média | J29: Pendente | M29: =(L29*$M$5)/$M$2 -> 0 | O29: =(N29*$O$5)/$O$2 -> 0 | Q29: =(P29*$Q$5)/$Q$2 -> 0 | S29: =(R29*$S$5)/$S$2 -> 0 | U29: =T29*$U$2 -> 0
A30: Projeto paisagismo | E30: vb | F30: 1 | G30: =U30 -> 3990.4104 | H30: =F30*G30 -> 3990.4104 | I30: Média | J30: Lançado Sienge | M30: =(L30*$M$5)/$M$2 -> 0 | N30: =VANCOUVER!E28 -> 5000 | O30: =(N30*$O$5)/$O$2 -> 1.014814 | Q30: =(P30*$Q$5)/$Q$2 -> 0 | R30: ='GRAN TOWER'!E39 -> 1514.48 | S30: =(R30*$S$5)/$S$2 -> 0.24230311 | T30: =(O30+S30)/2 -> 0.62855857 | U30: =T30*$U$2 -> 3990.4104
A31: Projeto preventivo | E31: vb | F31: 1 | G31: =U31 -> 8226.7037 | H31: =F31*G31 -> 8226.7037 | I31: Informado no Formulário | J31: Lançado Sienge | M31: =(L31*$M$5)/$M$2 -> 0 | N31: =VANCOUVER!E27 -> 8850 | O31: =(N31*$O$5)/$O$2 -> 1.7962209 | Q31: =(P31*$Q$5)/$Q$2 -> 0 | R31: ='GRAN TOWER'!E35 -> 4972 | S31: =(R31*$S$5)/$S$2 -> 0.79547504 | T31: =(O31+S31)/2 -> 1.2958479 | U31: =T31*$U$2 -> 8226.7037
A32: Projeto comunicação visual | E32: vb | F32: 1 | G32: =U32 -> 5154.0457 | H32: =F32*G32 -> 5154.0457 | I32: Média | J32: Lançado Sienge | M32: =(L32*$M$5)/$M$2 -> 0 | N32: =VANCOUVER!E29 -> 4000 | O32: =(N32*$O$5)/$O$2 -> 0.81185123 | Q32: =(P32*$Q$5)/$Q$2 -> 0 | S32: =(R32*$S$5)/$S$2 -> 0 | T32: =O32 -> 0.81185123 | U32: =T32*$U$2 -> 5154.0457
A33: Projeto de climatização | E33: vb | F33: 1 | G33: =U33 -> 5477.6928 | H33: =F33*G33 -> 5477.6928 | I33: Média | J33: Lançado Sienge | M33: =(L33*$M$5)/$M$2 -> 0 | O33: =(N33*$O$5)/$O$2 -> 0 | P33: ='VILLA LOBOS'!E26 -> 3000 | Q33: =(P33*$Q$5)/$Q$2 -> 0.50122448 | R33: ='GRAN TOWER'!E36 -> 7653.17 | S33: =(R33*$S$5)/$S$2 -> 1.224438 | T33: =(Q33+S33)/2 -> 0.86283124 | U33: =T33*$U$2 -> 5477.6928
A34: Projeto de exaustão | E34: vb | F34: 1 | G34: =U34 -> 3182.0287 | H34: =F34*G34 -> 3182.0287 | I34: Média | J34: Lançado Sienge | M34: =(L34*$M$5)/$M$2 -> 0 | O34: =(N34*$O$5)/$O$2 -> 0 | P34: ='VILLA LOBOS'!E27 -> 3000 | Q34: =(P34*$Q$5)/$Q$2 -> 0.50122448 | R34: ='VILLA LOBOS'!G27 -> 0 | S34: =(R34*$S$5)/$S$2 -> 0 | T34: =Q34 -> 0.50122448 | U34: =T34*$U$2 -> 3182.0287
A35: Projeto de impermeabilização | E35: vb | F35: 1 | G35: =U35 -> 29119.213 | H35: =F35*G35 -> 29119.213 | I35: Média | J35: Lançado Sienge | M35: =(L35*$M$5)/$M$2 -> 0 | O35: =(N35*$O$5)/$O$2 -> 0 | Q35: =(P35*$Q$5)/$Q$2 -> 0 | R35: ='GRAN TOWER'!E37 -> 28668.99 | S35: =(R35*$S$5)/$S$2 -> 4.5867792 | T35: =S35 -> 4.5867792 | U35: =T35*$U$2 -> 29119.213
A36: Projeto de acústico | E36: vb | F36: 1 | G36: =U36 -> 0 | H36: =F36*G36 -> 0 | I36: Média | J36: Pendente | M36: =(L36*$M$5)/$M$2 -> 0 | O36: =(N36*$O$5)/$O$2 -> 0 | Q36: =(P36*$Q$5)/$Q$2 -> 0 | S36: =(R36*$S$5)/$S$2 -> 0 | U36: =T36*$U$2 -> 0
A37: Projeto de esquadrias | E37: vb | F37: 1 | G37: =U37 -> 0 | H37: =F37*G37 -> 0 | I37: Média | J37: Pendente | M37: =(L37*$M$5)/$M$2 -> 0 | O37: =(N37*$O$5)/$O$2 -> 0 | Q37: =(P37*$Q$5)/$Q$2 -> 0 | R37: ='VILLA LOBOS'!G30 -> 0 | S37: =(R37*$S$5)/$S$2 -> 0 | T37: =Q37 -> 0 | U37: =T37*$U$2 -> 0
A38: Projeto de forro | E38: vb | F38: 1 | G38: =U38 -> 0 | H38: =F38*G38 -> 0 | I38: Média | J38: Pendente | M38: =(L38*$M$5)/$M$2 -> 0 | O38: =(N38*$O$5)/$O$2 -> 0 | Q38: =(P38*$Q$5)/$Q$2 -> 0 | S38: =(R38*$S$5)/$S$2 -> 0 | U38: =T38*$U$2 -> 0
A39: Projeto de sonorização | E39: vb | F39: 1 | G39: =U39 -> 0 | H39: =F39*G39 -> 0 | I39: Média | J39: Pendente | M39: =(L39*$M$5)/$M$2 -> 0 | O39: =(N39*$O$5)/$O$2 -> 0 | Q39: =(P39*$Q$5)/$Q$2 -> 0 | S39: =(R39*$S$5)/$S$2 -> 0 | U39: =T39*$U$2 -> 0
A40: Projeto de piscina | E40: vb | F40: 1 | G40: =U40 -> 2582.0521 | H40: =F40*G40 -> 2582.0521 | I40: Média | J40: Lançado Sienge | M40: =(L40*$M$5)/$M$2 -> 0 | O40: =(N40*$O$5)/$O$2 -> 0 | Q40: =(P40*$Q$5)/$Q$2 -> 0 | R40: ='GRAN TOWER'!E38 -> 2542.13 | S40: =(R40*$S$5)/$S$2 -> 0.40671781 | T40: =S40 -> 0.40671781 | U40: =T40*$U$2 -> 2582.0521
A41: Projeto de pavimentação | E41: vb | F41: 1 | G41: =U41 -> 0 | H41: =F41*G41 -> 0 | I41: Média | J41: Pendente | M41: =(L41*$M$5)/$M$2 -> 0 | O41: =(N41*$O$5)/$O$2 -> 0 | Q41: =(P41*$Q$5)/$Q$2 -> 0 | S41: =(R41*$S$5)/$S$2 -> 0 | U41: =T41*$U$2 -> 0
A42: =RESPOSTAS!A114 -> Projetos de segurança do trabalho | E42: vb | F42: 1 | G42: 3000 | H42: =F42*G42 -> 3000 | I42: Informado no Formulário | J42: Lançado Sienge | M42: =(L42*$M$5)/$M$2 -> 0 | O42: =(N42*$O$5)/$O$2 -> 0 | Q42: =(P42*$Q$5)/$Q$2 -> 0 | S42: =(R42*$S$5)/$S$2 -> 0 | T42: =Q42 -> 0 | U42: =T42*$U$2 -> 0
A43: CONSULTORIAS
A44: Consultoria técnicas diversas | E44: vb | F44: 1 | G44: =U44 -> 16492.946 | H44: =F44*G44 -> 16492.946 | I44: Média | J44: Lançado Sienge | M44: =(L44*$M$5)/$M$2 -> 0 | N44: =VANCOUVER!E34 -> 12800 | O44: =(N44*$O$5)/$O$2 -> 2.5979239 | Q44: =(P44*$Q$5)/$Q$2 -> 0 | S44: =(R44*$S$5)/$S$2 -> 0 | T44: =O44 -> 2.5979239 | U44: =T44*$U$2 -> 16492.946
A45: Auditoria de qualidade | E45: vb | F45: 1 | G45: =U45 -> 10308.091 | H45: =F45*G45 -> 10308.091 | I45: Média | J45: Lançado Sienge | M45: =(L45*$M$5)/$M$2 -> 0 | N45: =VANCOUVER!E33 -> 8000 | O45: =(N45*$O$5)/$O$2 -> 1.6237025 | Q45: =(P45*$Q$5)/$Q$2 -> 0 | S45: =(R45*$S$5)/$S$2 -> 0 | T45: =O45 -> 1.6237025 | U45: =T45*$U$2 -> 10308.091
A46: =RESPOSTAS!A56 -> Consultoria técnica de legalização | E46: vb | F46: 1 | G46: =U46 -> 37872.562 | H46: =F46*G46 -> 37872.562 | I46: Média | J46: Lançado Sienge | M46: =(L46*$M$5)/$M$2 -> 0 | O46: =(N46*$O$5)/$O$2 -> 0 | Q46: =(P46*$Q$5)/$Q$2 -> 0 | R46: ='GRAN TOWER'!E41 -> 37287 | S46: =(R46*$S$5)/$S$2 -> 5.9655828 | T46: =S46 -> 5.9655828 | U46: =T46*$U$2 -> 37872.562 | V46: =$W$4 -> MABREM - GRAN TORINO | W46: =( 27955.98*$X$5)/[4]ORÇAMENTO_EXECUTIVO!$G$2 -> 2.2313502 | X46: =W6 -> AS RAMOS - PAESSAGIO | Y46: =([7]Relatório!$W$28:$AB$28*$X$6)/'[8]Executivo '!$P$13 -> 0
A47: =RESPOSTAS!A58 -> Orçamento e planejamento | E47: vb | F47: 1 | G47: =U47 -> 31269.294 | H47: =F47*G47 -> 31269.294 | I47: Média | J47: Lançado Sienge | L47: =NOUVE!E32 -> 27500 | M47: =(L47*$M$5)/$M$2 -> 5.3105564 | N47: =VANCOUVER!E32 -> 11941.36 | O47: =(N47*$O$5)/$O$2 -> 2.423652 | P47: ='VILLA LOBOS'!E32 -> 42149.7 | Q47: =(P47*$Q$5)/$Q$2 -> 7.0421539 | R47: ='VILLA LOBOS'!G32 -> 0 | S47: =(R47*$S$5)/$S$2 -> 0 | T47: =(Q47+M47+O47)/3 -> 4.9254541 | U47: =T47*$U$2 -> 31269.294
A48: Consultoria técnica de esquadrias | E48: vb | F48: 1 | G48: =U48 -> 0 | H48: =F48*G48 -> 0 | I48: Média | J48: Pendente | M48: =(L48*$M$5)/$M$2 -> 0 | O48: =(N48*$O$5)/$O$2 -> 0 | Q48: =(P48*$Q$5)/$Q$2 -> 0 | S48: =(R48*$S$5)/$S$2 -> 0 | T48: =O48 -> 0 | U48: =T48*$U$2 -> 0
A49: Consultoria técnica de fachada | E49: vb | F49: 1 | G49: =U49 -> 0 | H49: =F49*G49 -> 0 | I49: Média | J49: Pendente | M49: =(L49*$M$5)/$M$2 -> 0 | O49: =(N49*$O$5)/$O$2 -> 0 | Q49: =(P49*$Q$5)/$Q$2 -> 0 | S49: =(R49*$S$5)/$S$2 -> 0 | T49: =W49 -> 0 | U49: =T49*$U$2 -> 0
A50: Consultoria técnica de qualidade | E50: vb | F50: 1 | G50: =RESPOSTAS!B61 -> 0 | H50: =F50*G50 -> 0 | I50: Média | J50: Pendente | L50: =NOUVE!E35 -> 0 | M50: =(L50*$M$5)/$M$2 -> 0 | N50: =VANCOUVER!E35 -> 0 | O50: =(N50*$O$5)/$O$2 -> 0 | P50: ='VILLA LOBOS'!E35 -> 0 | Q50: =(P50*$Q$5)/$Q$2 -> 0 | R50: ='VILLA LOBOS'!G35 -> 0 | S50: =(R50*$S$5)/$S$2 -> 0 | T50: =(Q50+M50+O50)/3 -> 0 | U50: =T50*$U$2 -> 0
A51: ENSAIOS
A52: Controle tecnológico de concreto | E52: vb | F52: 1 | G52: =U52 -> 28464.898 | H52: =F52*G52 -> 28464.898 | I52: Média | J52: Pendente | L52: =NOUVE!F34 -> 32074.5 | M52: =(L52*$M$5)/$M$2 -> 6.1939433 | N52: =VANCOUVER!F36 -> 10776.08 | O52: =(N52*$O$5)/$O$2 -> 2.1871435 | P52: ='VILLA LOBOS'!E34 -> 30346 | Q52: =(P52*$Q$5)/$Q$2 -> 5.0700527 | R52: ='VILLA LOBOS'!G34 -> 0 | S52: =(R52*$S$5)/$S$2 -> 0 | T52: =(Q52+M52+O52)/3 -> 4.4837132 | U52: =T52*$U$2 -> 28464.898
A53: LICENCIAMENTOS, TAXAS, IMPOSTOS, APROVAÇÕES E SEGUROS
A54: =RESPOSTAS!A72 -> IPTU | E54: vb | F54: 1 | G54: 3047.18 | H54: =F54*G54 -> 3047.18 | I54: Informado no Formulário | J54: Lançado Sienge | M54: =(L54*$M$5)/$M$2 -> 0 | N54: =VANCOUVER!E51 -> 3000 | O54: =(N54*$O$5)/$O$2 -> 0.60888843 | P54: ='VILLA LOBOS'!E47 -> 5030.7 | Q54: =(P54*$Q$5)/$Q$2 -> 0.84050334 | R54: ='VILLA LOBOS'!G47 -> 0 | S54: =(R54*$S$5)/$S$2 -> 0 | T54: =(Q54+O54)/2 -> 0.72469588 | U54: =T54*$U$2 -> 4600.7391
A55: =RESPOSTAS!A74 -> As Built | E55: vb | F55: 1 | G55: =U55 -> 8302.0089 | H55: =F55*G55 -> 8302.0089 | I55: Média | J55: Lançado Sienge | M55: =(L55*$M$5)/$M$2 -> 0 | O55: =(N55*$O$5)/$O$2 -> 0 | Q55: =(P55*$Q$5)/$Q$2 -> 0 | S55: =(R55*$S$5)/$S$2 -> 0 | T55: =W55 -> 1.3077098 | U55: =T55*$U$2 -> 8302.0089 | V55: =$W$6 -> AS RAMOS - PAESSAGIO | W55: =( 20800*$X$6)/[6]BASES!$Q$2 -> 1.3077098
A56: Certidão INSS | E56: vb | F56: 1 | G56: =U56 -> 28384.895 | H56: =F56*G56 -> 28384.895 | I56: Média | J56: Lançado Sienge | L56: =NOUVE!E48 -> 40000 | M56: =(L56*$M$5)/$M$2 -> 7.7244457 | N56: =VANCOUVER!E53 -> 6000 | O56: =(N56*$O$5)/$O$2 -> 1.2177769 | Q56: =(P56*$Q$5)/$Q$2 -> 0 | S56: =(R56*$S$5)/$S$2 -> 0 | T56: =(M56+O56)/2 -> 4.4711113 | U56: =T56*$U$2 -> 28384.895
A57: Incorporação | E57: vb | F57: 1 | G57: 6611.4 | H57: =F57*G57 -> 6611.4 | I57: Média | J57: Lançado Sienge | M57: =(L57*$M$5)/$M$2 -> 0 | N57: =VANCOUVER!E50 -> 4200 | O57: =(N57*$O$5)/$O$2 -> 0.8524438 | P57: ='VILLA LOBOS'!E46 -> 7700 | Q57: =(P57*$Q$5)/$Q$2 -> 1.2864762 | R57: ='VILLA LOBOS'!G46 -> 0 | S57: =(R57*$S$5)/$S$2 -> 0 | T57: =(Q57+O57)/2 -> 1.06946 | U57: =T57*$U$2 -> 6789.4774
A58: =RESPOSTAS!A73 -> Taxa Habite-se | E58: vb | F58: 1 | G58: =U58 -> 7606.7584 | H58: =F58*G58 -> 7606.7584 | I58: Média | J58: Lançado Sienge | M58: =(L58*$M$5)/$M$2 -> 0 | N58: =VANCOUVER!E52 -> 5555 | O58: =(N58*$O$5)/$O$2 -> 1.1274584 | P58: ='VILLA LOBOS'!E48 -> 7595 | Q58: =(P58*$Q$5)/$Q$2 -> 1.2689333 | R58: ='VILLA LOBOS'!G48 -> 0 | S58: =(R58*$S$5)/$S$2 -> 0 | T58: =(Q58+O58)/2 -> 1.1981959 | U58: =T58*$U$2 -> 7606.7584 | W58: =2800*2 -> 5600
A59: =RESPOSTAS!A68 -> Taxas de ART | E59: vb | F59: 1 | G59: 600 | H59: =F59*G59 -> 600 | I59: Informado no Formulário | J59: Lançado Sienge | L59: =NOUVE!E44 -> 1414.9 | M59: =(L59*$M$5)/$M$2 -> 0.27323295 | N59: =VANCOUVER!E47 -> 500 | O59: =(N59*$O$5)/$O$2 -> 0.1014814 | P59: ='VILLA LOBOS'!E44 -> 1897 | Q59: =(P59*$Q$5)/$Q$2 -> 0.31694095 | R59: ='VILLA LOBOS'!G44 -> 0 | S59: =(R59*$S$5)/$S$2 -> 0 | T59: =(Q59+M59+O59)/3 -> 0.23055177 | U59: =T59*$U$2 -> 1463.6602 | V59: + 0,00
A60: =RESPOSTAS!A69 -> Taxas de Alvará | E60: vb | F60: 1 | G60: 11758.71 | H60: =F60*G60 -> 11758.71 | I60: Informado no Formulário | J60: Lançado Sienge | L60: =NOUVE!E45 -> 51458.79 | M60: =(L60*$M$5)/$M$2 -> 9.9372657 | N60: =VANCOUVER!E48 -> 7200 | O60: =(N60*$O$5)/$O$2 -> 1.4613322 | P60: ='VILLA LOBOS'!E45 -> 12999.52 | Q60: =(P60*$Q$5)/$Q$2 -> 2.1718926 | R60: ='VILLA LOBOS'!G45 -> 0 | S60: =(R60*$S$5)/$S$2 -> 0 | T60: =(Q60+M60+O60)/3 -> 4.5234968 | U60: =T60*$U$2 -> 28717.465
A61: =RESPOSTAS!A63 -> Aprovação e legalização ambiental | E61: vb | F61: 1 | G61: 5683.51 | H61: =F61*G61 -> 5683.51 | I61: Informado no Formulário | J61: Lançado Sienge | L61: =NOUVE!E39 -> 7000 | M61: =(L61*$M$5)/$M$2 -> 1.351778 | N61: =VANCOUVER!E46 -> 2683.93 | O61: =(N61*$O$5)/$O$2 -> 0.54473797 | P61: ='VILLA LOBOS'!E39 -> 4563 | Q61: =(P61*$Q$5)/$Q$2 -> 0.76236244 | R61: ='VILLA LOBOS'!G39 -> 0 | S61: =(R61*$S$5)/$S$2 -> 0 | T61: =(Q61+M61+O61)/3 -> 0.8862928 | U61: =T61*$U$2 -> 5626.6387
A62: =RESPOSTAS!A64 -> Aprovação e legalização prefeitura | E62: vb | F62: 1 | G62: =U62 -> 23251.171 | H62: =F62*G62 -> 23251.171 | I62: Média | J62: Lançado Sienge | L62: =NOUVE!E40 -> 12500 | M62: =(L62*$M$5)/$M$2 -> 2.4138893 | N62: =VANCOUVER!E43 -> 20297.38 | O62: =(N62*$O$5)/$O$2 -> 4.1196132 | P62: ='VILLA LOBOS'!E40 -> 26658 | Q62: =(P62*$Q$5)/$Q$2 -> 4.4538808 | R62: ='VILLA LOBOS'!G40 -> 0 | S62: =(R62*$S$5)/$S$2 -> 0 | T62: =(Q62+M62+O62)/3 -> 3.6624611 | U62: =T62*$U$2 -> 23251.171
A63: =RESPOSTAS!A67 -> Aprovação e legalização bombeiros | E63: vb | F63: 1 | G63: =U63 -> 4881.639 | H63: =F63*G63 -> 4881.639 | I63: Média | J63: Lançado Sienge | L63: =NOUVE!E43 -> 4000 | M63: =(L63*$M$5)/$M$2 -> 0.77244457 | N63: =VANCOUVER!E44 -> 3500 | O63: =(N63*$O$5)/$O$2 -> 0.71036983 | P63: ='VILLA LOBOS'!E43 -> 4932 | Q63: =(P63*$Q$5)/$Q$2 -> 0.82401305 | R63: ='VILLA LOBOS'!G43 -> 0 | S63: =(R63*$S$5)/$S$2 -> 0 | T63: =(Q63+M63+O63)/3 -> 0.76894248 | U63: =T63*$U$2 -> 4881.639
A64: =RESPOSTAS!A62 -> Despesas de seguro de obra | E64: vb | F64: 1 | G64: 11316.52 | H64: =F64*G64 -> 11316.52 | I64: Informado no Formulário | J64: Lançado Sienge | L64: =NOUVE!E42 -> 3537.26 | M64: =(L64*$M$5)/$M$2 -> 0.68308432 | N64: =VANCOUVER!E42 -> 9600 | O64: =(N64*$O$5)/$O$2 -> 1.948443 | P64: ='VILLA LOBOS'!E37 -> 9825.24 | Q64: =(P64*$Q$5)/$Q$2 -> 1.6415503 | R64: ='VILLA LOBOS'!G37 -> 0 | S64: =(R64*$S$5)/$S$2 -> 0 | T64: =(Q64+M64+O64)/3 -> 1.4243592 | U64: =T64*$U$2 -> 9042.5585
A65: Despesas de cartório, licenças, certidões e juridicas | E65: vb | F65: 1 | G65: =U65+RESPOSTAS!B70 -> 12489.876 | H65: =F65*G65 -> 12489.876 | I65: Média | J65: Lançado Sienge | L65: =NOUVE!E47 -> 25000 | M65: =(L65*$M$5)/$M$2 -> 4.8277785 | N65: =VANCOUVER!E49 -> 2450 | O65: =(N65*$O$5)/$O$2 -> 0.49725888 | P65: ='VILLA LOBOS'!E38 -> 3454 | Q65: =(P65*$Q$5)/$Q$2 -> 0.57707646 | R65: ='VILLA LOBOS'!G38 -> 0 | S65: =(R65*$S$5)/$S$2 -> 0 | T65: =(Q65+M65+O65)/3 -> 1.9673713 | U65: =T65*$U$2 -> 12489.876 | V65: =W4 -> MABREM - GRAN TORINO | W65: =( 5701.15*$X$5)/[4]ORÇAMENTO_EXECUTIVO!$G$2 -> 0.45504618
A66: =RESPOSTAS!A66 -> Aprovação e legalização elétrico | E66: vb | F66: 1 | G66: =U66 -> 4488.9017 | H66: =F66*G66 -> 4488.9017 | I66: Média | J66: Lançado Sienge | L66: =NOUVE!E42 -> 3537.26 | M66: =(L66*$M$5)/$M$2 -> 0.68308432 | N66: =VANCOUVER!E45 -> 3300 | O66: =(N66*$O$5)/$O$2 -> 0.66977727 | P66: ='VILLA LOBOS'!E42 -> 4599 | Q66: =(P66*$Q$5)/$Q$2 -> 0.76837713 | R66: ='VILLA LOBOS'!G42 -> 0 | S66: =(R66*$S$5)/$S$2 -> 0 | T66: =(Q66+M66+O66)/3 -> 0.70707957 | U66: =T66*$U$2 -> 4488.9017
A67: =RESPOSTAS!A65 -> Aprovação e legalização água e esgoto | E67: vb | F67: 1 | G67: =U67 -> 5503.945 | H67: =F67*G67 -> 5503.945 | I67: Média | J67: Lançado Sienge | L67: =NOUVE!E41 -> 5000 | M67: =(L67*$M$5)/$M$2 -> 0.96555571 | O67: =(N67*$O$5)/$O$2 -> 0 | P67: ='VILLA LOBOS'!E41 -> 4599 | Q67: =(P67*$Q$5)/$Q$2 -> 0.76837713 | R67: ='VILLA LOBOS'!G41 -> 0 | S67: =(R67*$S$5)/$S$2 -> 0 | T67: =(Q67+M67)/2 -> 0.86696642 | U67: =T67*$U$2 -> 5503.945
A68: DOCUMENTOS
A69: =RESPOSTAS!A76 -> Manuais técnicos condomínio/proprietários | E69: vb | F69: 1 | G69: =U69 -> 6348.51 | H69: =F69*G69 -> 6348.51 | I69: Média | J69: Lançado Sienge | M69: =(L69*$M$5)/$M$2 -> 0 | O69: =(N69*$O$5)/$O$2 -> 0 | P69: ='VILLA LOBOS'!E50 -> 133 | Q69: =(P69*$Q$5)/$Q$2 -> 0.022220952 | R69: ='VILLA LOBOS'!G50 -> 0 | S69: =(R69*$S$5)/$S$2 -> 0 | T69: 1 | U69: =T69*$U$2 -> 6348.51
A70: Laudo técnico de vistoria de entrega | E70: vb | F70: 1 | G70: =U70 -> 11335.435 | H70: =F70*G70 -> 11335.435 | I70: Média | J70: Lançado Sienge | M70: =(L70*$M$5)/$M$2 -> 0 | O70: =(N70*$O$5)/$O$2 -> 0 | Q70: =(P70*$Q$5)/$Q$2 -> 0 | S70: =(R70*$S$5)/$S$2 -> 0 | T70: =W70 -> 1.7855269 | U70: =T70*$U$2 -> 11335.435 | V70: =$W$6 -> AS RAMOS - PAESSAGIO | W70: =( 28400*$X$6)/[6]BASES!$Q$2 -> 1.7855269
A71: EQUIPAMENTOS DE PROTEÇÃO | S71: =(R71*$S$5)/$S$2 -> 0
A72: Bandeja primária - 1 montagens | E72: m | F72: ='EPC''s'!D13 -> 152.26 | G72: =U72 -> 524.26322 | H72: =F72*G72 -> 79824.318 | I72: Média | J72: Lançado Sienge | M72: =(L72*$M$5)/$M$2 -> 0 | O72: =(N72*$O$5)/$O$2 -> 0 | Q72: =(P72*$Q$5)/$Q$2 -> 0 | S72: =(R72*$S$5)/$S$2 -> 0 | T72: =(Q72+M72)/2 -> 0 | U72: =COMPOSIÇÃO!H3 -> 524.26322
A73: Bandeja secundária - 2 montagens | E73: m | F73: ='EPC''s'!D14 -> 73.29 | G73: =U73 -> 385.0282 | H73: =F73*G73 -> 28218.717 | I73: Média | J73: Lançado Sienge | M73: =(L73*$M$5)/$M$2 -> 0 | O73: =(N73*$O$5)/$O$2 -> 0 | Q73: =(P73*$Q$5)/$Q$2 -> 0 | S73: =(R73*$S$5)/$S$2 -> 0 | T73: =(Q73+M73)/2 -> 0 | U73: 385.0282
A74: Guarda-corpo vãos tela prolipopileno (fixado em fôrma de madeira) | E74: m | F74: ='EPC''s'!D52 -> 323.1 | G74: =U74 -> 22.2244 | H74: =F74*G74 -> 7180.7036 | I74: Média | J74: Lançado Sienge | M74: =(L74*$M$5)/$M$2 -> 0 | O74: =(N74*$O$5)/$O$2 -> 0 | Q74: =(P74*$Q$5)/$Q$2 -> 0 | S74: =(R74*$S$5)/$S$2 -> 0 | T74: =(Q74+M74)/2 -> 0 | U74: 22.2244
A75: =RESPOSTAS!B99 -> Guarda-corpo de laje após desforma - Escora metálica, travessões e tela | E75: m | F75: ='EPC''s'!D21 -> #REF! | G75: =COMPOSIÇÃO!H40 -> 36.92914 | H75: =F75*G75 -> #REF! | I75: Média | J75: Lançado Sienge | M75: =(L75*$M$5)/$M$2 -> 0 | O75: =(N75*$O$5)/$O$2 -> 0 | Q75: =(P75*$Q$5)/$Q$2 -> 0 | S75: =(R75*$S$5)/$S$2 -> 0 | T75: =(Q75+M75)/2 -> 0 | U75: =T75*$U$2 -> 0
A76: =RESPOSTAS!B101 -> Fechamento removível de vãos de porta de elevador em madeira, | E76: m² | F76: ='EPC''s'!D42 -> 808.83 | G76: =U76 -> 38.9177 | H76: =F76*G76 -> 31477.803 | I76: Média | J76: Lançado Sienge | M76: =(L76*$M$5)/$M$2 -> 0 | O76: =(N76*$O$5)/$O$2 -> 0 | Q76: =(P76*$Q$5)/$Q$2 -> 0 | S76: =(R76*$S$5)/$S$2 -> 0 | T76: =(Q76+M76)/2 -> 0 | U76: 38.9177
A77: =RESPOSTAS!B102 -> Fechamento removível de vãos de porta de entrada dos aptos. em madeira | E77: m² | F77: ='EPC''s'!D46 -> 130.851 | G77: =COMPOSIÇÃO!H33 -> 6.14475 | H77: =F77*G77 -> 804.04668 | I77: Média | J77: Lançado Sienge | M77: =(L77*$M$5)/$M$2 -> 0 | O77: =(N77*$O$5)/$O$2 -> 0 | Q77: =(P77*$Q$5)/$Q$2 -> 0 | S77: =(R77*$S$5)/$S$2 -> 0 | T77: =(Q77+M77)/2 -> 0 | U77: =T77*$U$2 -> 0
A78: Fechamento removível de abertura no piso do elevador em madeira | E78: m² | F78: ='EPC''s'!D47 -> 232.56 | G78: 200.3249 | H78: =F78*G78 -> 46587.559 | I78: Média | J78: Lançado Sienge | M78: =(L78*$M$5)/$M$2 -> 0 | O78: =(N78*$O$5)/$O$2 -> 0 | Q78: =(P78*$Q$5)/$Q$2 -> 0 | S78: =(R78*$S$5)/$S$2 -> 0 | T78: =(Q78+M78)/2 -> 0 | U78: =T78*$U$2 -> 0
A79: Rede de proteção, SLQA, Intermediário | E79: m² | F79: ='EPC''s'!D34 -> #REF! | G79: 396.9657 | H79: =F79*G79 -> #REF! | I79: Média | J79: Lançado Sienge | M79: =(L79*$M$5)/$M$2 -> 0 | O79: =(N79*$O$5)/$O$2 -> 0 | Q79: =(P79*$Q$5)/$Q$2 -> 0 | S79: =(R79*$S$5)/$S$2 -> 0 | T79: =(Q79+M79)/2 -> 0 | U79: =T79*$U$2 -> 0
A80: Instalações Provisórias (central de aço, formas, argamassa, almoxarifado geral, construções temporárias) | E80: vb | F80: 1 | G80: =577.85*CANTEIRO!O14 -> 267952.63 | H80: =F80*G80 -> 267952.63 | I80: Média | J80: Pendente | M80: =(L80*$M$5)/$M$2 -> 0 | O80: =(N80*$O$5)/$O$2 -> 0 | Q80: =(P80*$Q$5)/$Q$2 -> 0 | S80: =(R80*$S$5)/$S$2 -> 0 | T80: =(Q80+M80)/2 -> 0
A81: Tela fachadeira mosqueteiro reforçada simples | E81: m2 | F81: ='EPC''s'!D28 -> #REF! | G81: =U81 -> 6.735 | H81: =F81*G81 -> #REF! | I81: Média | J81: Lançado Sienge | M81: =(L81*$M$5)/$M$2 -> 0 | O81: =(N81*$O$5)/$O$2 -> 0 | Q81: =(P81*$Q$5)/$Q$2 -> 0 | S81: =(R81*$S$5)/$S$2 -> 0 | T81: =(Q81+M81)/2 -> 0 | U81: 6.735
A82: EPI seguindo projeto de segurança | E82: vb | F82: 1 | G82: =CANTEIRO!D18 -> 24000 | H82: =F82*G82 -> 24000 | I82: Média | J82: Lançado Sienge | M82: =(L82*$M$5)/$M$2 -> 0 | O82: =(N82*$O$5)/$O$2 -> 0 | Q82: =(P82*$Q$5)/$Q$2 -> 0 | S82: =(R82*$S$5)/$S$2 -> 0 | T82: =(Q82+M82)/2 -> 0 | U82: =T82*$U$2 -> 0
A83: Ferramentas | G83: =CANTEIRO!D17 -> 38400 | S83: =(R83*$S$5)/$S$2 -> 0
A84: SEGURANÇA DO TRABALHO | S84: =(R84*$S$5)/$S$2 -> 0
A85: Serviço de segurança do trabalho - Terceirizado | E85: vb | F85: 1 | G85: =660+550 -> 1210 | H85: =F85*G85 -> 1210 | I85: Informado no Formulário | J85: Lançado Sienge | L85: =NOUVE!E52 -> 1058.8235 | M85: =(L85*$M$5)/$M$2 -> 0.20447061 | N85: =VANCOUVER!E68 -> 654.72 | O85: =(N85*$O$5)/$O$2 -> 0.13288381 | P85: ='VILLA LOBOS'!E59 -> 600 | Q85: =(P85*$Q$5)/$Q$2 -> 0.1002449 | R85: ='VILLA LOBOS'!G59 -> 0 | S85: =(R85*$S$5)/$S$2 -> 0 | T85: =(Q85+M85+O85)/3 -> 0.14586644 | U85: =T85*$U$2 -> 926.03456
A86: MEIO AMBIENTE | S86: =(R86*$S$5)/$S$2 -> 0
A87: =RESPOSTAS!A111 -> Elaboração do Programa de Prevenção dos Riscos Ambientais (PPRA) | E87: vb | F87: 1 | G87: 1000 | H87: =F87*G87 -> 1000 | I87: Informado no Formulário | J87: Lançado Sienge | L87: =NOUVE!E64 -> 3500 | M87: =(L87*$M$5)/$M$2 -> 0.675889 | O87: =(N87*$O$5)/$O$2 -> 0 | P87: ='VILLA LOBOS'!E75 -> 600 | Q87: =(P87*$Q$5)/$Q$2 -> 0.1002449 | R87: ='VILLA LOBOS'!G75 -> 0 | S87: =(R87*$S$5)/$S$2 -> 0 | T87: =(Q87+M87)/2 -> 0.38806695 | U87: =T87*$U$2 -> 2463.6469
A88: =RESPOSTAS!A112 -> Elaboração do Programa de Controle Médico de Saúde Ocupacional (PCMSO) | E88: vb | F88: 1 | G88: 1000 | H88: =F88*G88 -> 1000 | I88: Informado no Formulário | J88: Lançado Sienge | M88: =(L88*$M$5)/$M$2 -> 0 | O88: =(N88*$O$5)/$O$2 -> 0 | P88: ='VILLA LOBOS'!E76 -> 600 | Q88: =(P88*$Q$5)/$Q$2 -> 0.1002449 | R88: ='VILLA LOBOS'!G76 -> 0 | S88: =(R88*$S$5)/$S$2 -> 0 | T88: =Q88 -> 0.1002449 | U88: =T88*$U$2 -> 636.40573 | V88: =W6 -> AS RAMOS - PAESSAGIO | W88: =(2799*$X$6)/'[8]Executivo '!$P$13 -> 0.88130623
A89: =RESPOSTAS!A113 -> Elaboração do Programa de Condições e Meio Ambiente de Trabalho na indústria da construção (PCMAT) | E89: vb | F89: 1 | G89: 1000 | H89: =F89*G89 -> 1000 | I89: Informado no Formulário | J89: Lançado Sienge | M89: =(L89*$M$5)/$M$2 -> 0 | N89: =VANCOUVER!E82 -> 2500 | O89: =(N89*$O$5)/$O$2 -> 0.50740702 | P89: ='VILLA LOBOS'!E77 -> 2500 | Q89: =(P89*$Q$5)/$Q$2 -> 0.41768707 | R89: ='VILLA LOBOS'!G77 -> 0 | S89: =(R89*$S$5)/$S$2 -> 0 | T89: =(Q89+O89)/2 -> 0.46254705 | U89: =T89*$U$2 -> 2936.4845
A90: =NOUVE!B67 -> Projetos de Segurança do Trabalho | E90: vb | F90: 1 | G90: 1000 | H90: =F90*G90 -> 1000 | I90: Informado no Formulário | J90: Lançado Sienge | L90: =NOUVE!E67 -> 1070.41 | M90: =(L90*$M$5)/$M$2 -> 0.2067081 | O90: =(N90*$O$5)/$O$2 -> 0 | Q90: =(P90*$Q$5)/$Q$2 -> 0 | S90: =(R90*$S$5)/$S$2 -> 0 | T90: =M90 -> 0.2067081 | U90: =T90*$U$2 -> 1312.2884
A91: SAÚDE OCUPACIONAL | S91: =(R91*$S$5)/$S$2 -> 0
A92: =RESPOSTAS!A117 -> Medicamentos preventivos e de emergência | E92: vb | F92: 1 | G92: =U92 -> 381.43932 | H92: =F92*G92 -> 381.43932 | I92: Média | J92: Lançado Sienge | L92: =NOUVE!E70 -> 147.0588 | M92: =(L92*$M$5)/$M$2 -> 0.028398693 | N92: =VANCOUVER!E85 -> 600 | O92: =(N92*$O$5)/$O$2 -> 0.12177769 | P92: ='VILLA LOBOS'!E80 -> 180 | Q92: =(P92*$Q$5)/$Q$2 -> 0.030073469 | R92: ='VILLA LOBOS'!G80 -> 0 | S92: =(R92*$S$5)/$S$2 -> 0 | T92: =(Q92+M92+O92)/3 -> 0.060083282 | U92: =T92*$U$2 -> 381.43932 | V92: =$W$6 -> AS RAMOS - PAESSAGIO | W92: =(500*$X$6)/'[8]Executivo '!$P$13 -> 0.15743234
A93: =RESPOSTAS!A118 -> Kit socorrista | E93: vb | F93: 1 | G93: =U93 -> 1617.6385 | H93: =F93*G93 -> 1617.6385 | I93: Média | J93: Lançado Sienge | L93: =NOUVE!E71 -> 2122.36 | M93: =(L93*$M$5)/$M$2 -> 0.40985136 | N93: =VANCOUVER!E86 -> 1500 | O93: =(N93*$O$5)/$O$2 -> 0.30444421 | P93: ='VILLA LOBOS'!E81 -> 300 | Q93: =(P93*$Q$5)/$Q$2 -> 0.050122448 | R93: ='VILLA LOBOS'!G81 -> 0 | S93: =(R93*$S$5)/$S$2 -> 0 | T93: =(Q93+M93+O93)/3 -> 0.25480601 | U93: =T93*$U$2 -> 1617.6385 | V93: =$W$6 -> AS RAMOS - PAESSAGIO | W93: =(350*$X$6)/'[8]Executivo '!$P$13 -> 0.11020264
A94: =RESPOSTAS!A119 -> Dedetização, desratização e sanitização dos ambientes | E94: vb | F94: 1 | G94: =U94 -> 2852.2431 | H94: =F94*G94 -> 2852.2431 | I94: Média | J94: Lançado Sienge | L94: =NOUVE!E72 -> 1500 | M94: =(L94*$M$5)/$M$2 -> 0.28966671 | N94: =VANCOUVER!E87 -> 3000 | O94: =(N94*$O$5)/$O$2 -> 0.60888843 | Q94: =(P94*$Q$5)/$Q$2 -> 0 | S94: =(R94*$S$5)/$S$2 -> 0 | T94: =(M94+O94)/2 -> 0.44927757 | U94: =T94*$U$2 -> 2852.2431
A95: EQUIPE DE GESTÃO E APOIO | S95: =(R95*$S$5)/$S$2 -> 0
A96: Engenheiro civil | E96: mês | F96: 48 | G96: =((9000*108.08)/100)+250+9000 -> 18977.2 | H96: =F96*G96 -> 910905.6 | I96: Informado no Formulário | J96: Lançado Sienge | L96: =NOUVE!E76 -> 8823.5294 | M96: =(L96*$M$5)/$M$2 -> 1.7039218 | N96: =VANCOUVER!E91 -> 5000 | O96: =(N96*$O$5)/$O$2 -> 1.014814 | P96: ='VILLA LOBOS'!E84 -> 2800 | Q96: =(P96*$Q$5)/$Q$2 -> 0.46780952 | R96: ='VILLA LOBOS'!G84 -> 0 | S96: =(R96*$S$5)/$S$2 -> 0 | T96: =(Q96+M96+O96)/3 -> 1.0621818 | U96: =T96*$U$2 -> 6743.2718
A97: Almoxarifado | E97: mês | F97: 48 | G97: =3500*1.57 -> 5495 | H97: =F97*G97 -> 263760 | I97: Informado no Formulário | J97: Lançado Sienge | L97: =NOUVE!E77 -> 0 | M97: =(L97*$M$5)/$M$2 -> 0 | N97: =VANCOUVER!E92 -> 3000 | O97: =(N97*$O$5)/$O$2 -> 0.60888843 | P97: ='VILLA LOBOS'!E86 -> 3136.88 | Q97: =(P97*$Q$5)/$Q$2 -> 0.52409369 | R97: ='VILLA LOBOS'!G86 -> 0 | S97: =(R97*$S$5)/$S$2 -> 0 | T97: =(Q97+O97)/2 -> 0.56649106 | U97: =T97*$U$2 -> 3596.3741
A98: Mestre de obras | E98: mês | F98: 48 | G98: =((7000*108.08)/100)+250+7000 -> 14815.6 | H98: =F98*G98 -> 711148.8 | I98: Informado no Formulário | J98: Lançado Sienge | M98: =(L98*$M$5)/$M$2 -> 0 | O98: =(N98*$O$5)/$O$2 -> 0 | P98: ='VILLA LOBOS'!E85 -> 3175.35 | Q98: =(P98*$Q$5)/$Q$2 -> 0.53052106 | R98: ='VILLA LOBOS'!G85 -> 0 | S98: =(R98*$S$5)/$S$2 -> 0 | T98: =Q98 -> 0.53052106 | U98: =T98*$U$2 -> 3368.0182
A99: SINALIZAÇÃO | S99: =(R99*$S$5)/$S$2 -> 0
A100: Sinalização obra | E100: vb | F100: 1 | G100: =U100 -> 3667.3954 | H100: =F100*G100 -> 3667.3954 | I100: Média | J100: Lançado Sienge | L100: =NOUVE!E89 -> 2829.81 | M100: =(L100*$M$5)/$M$2 -> 0.54646784 | N100: =VANCOUVER!E104 -> 3000 | O100: =(N100*$O$5)/$O$2 -> 0.60888843 | Q100: =(P100*$Q$5)/$Q$2 -> 0 | S100: =(R100*$S$5)/$S$2 -> 0 | T100: =(O100+M100)/2 -> 0.57767813 | U100: =T100*$U$2 -> 3667.3954
...

Sheet NOUVE
A5: Obra | B5: NOUVE 354
A6: CONSTRUTORA | B6: HOUZE
A7: Endereço da obra
A8: AREA TERRENO
A9: Unidade construtiva M² | B9: 5438.9
A10: ANO | B10: 44805
A11: CUB | B11: 2623.42
A15: Código | B15: Descrição | C15: Un. | D15: Quantidade orçada | E15: Preço unitário | F15: Preço total
A16: 01 | B16: ESTUDOS, PROJETOS E CONSULTORIAS | F16: 236049.5
A17: 01.001 | B17: ESTUDOS, PROJETOS E CONSULTORIAS | F17: 236049.5
A18: 01.001.001 | B18: Estudos | F18: 12825
A19: 01.001.001.001 | B19: Memorial descritivo | C19: vb | D19: 0 | E19: 0 | F19: 0
A20: 01.001.001.002 | B20: Levantamento Topográfico | C20: vb | D20: 1 | E20: 1021 | F20: 1021
A21: 01.001.001.003 | B21: Estudo ambiental | C21: vb | D21: 1 | E21: 3600 | F21: 3600
A22: 01.001.001.004 | B22: Sondagem do terreno | C22: vb | D22: 1 | E22: 8204 | F22: 8204
A23: 01.001.001.005 | B23: Projeto de canteiro | C23: vb | D23: 0 | E23: 0 | F23: 0
A24: 01.001.002 | B24: Projetos | F24: 163650
A25: 01.001.002.001 | B25: Projeto Arquitetônico legal | C25: vb | D25: 1 | E25: 100000 | F25: 100000
A26: 01.001.002.002 | B26: Projeto Fundações | C26: vb | D26: 1 | E26: 11200 | F26: 11200
A27: 01.001.002.003 | B27: Projeto Estrutural | C27: vb | D27: 1 | E27: 52450 | F27: 52450
A28: 01.001.002.004 | B28: Projeto de automação | C28: vb | D28: 0 | E28: 0 | F28: 0
A29: 01.001.002.005 | B29: Projeto de climatização, exaustão e acústico | C29: vb | D29: 0 | E29: 0 | F29: 0
A30: 01.001.002.006 | B30: Projeto de impermeabilização | C30: vb | D30: 0 | E30: 0 | F30: 0
A31: 01.001.003 | B31: Consultorias | F31: 27500
A32: 01.001.003.001 | B32: Orçamento e planejamento | C32: vb | D32: 1 | E32: 27500 | F32: 27500
A33: 01.001.004 | B33: Ensaios e Laudos | F33: 32074.5
A34: 01.001.004.001 | B34: Controle Tecnologico de Concreto | C34: m3 | D34: 2138.3 | E34: 15 | F34: 32074.5
A35: 02 | B35: TAXAS, DOCUMENTOS | F35: 659910.95
A36: 02.001 | B36: TAXAS, DOCUMENTOS | F36: 659910.95
A37: 02.001.001 | B37: Taxas e Documentos | F37: 659910.95
A38: 02.001.001.001 | B38: Despesas de Seguros | C38: vb | D38: 1 | E38: 10000 | F38: 10000
A39: 02.001.001.002 | B39: Aprovação e legalização ambiental | C39: vb | D39: 1 | E39: 7000 | F39: 7000
A40: 02.001.001.003 | B40: Aprovação e legalização prefeitura | C40: vb | D40: 1 | E40: 12500 | F40: 12500
A41: 02.001.001.004 | B41: Aprovação e legalização água e esgoto | C41: vb | D41: 1 | E41: 5000 | F41: 5000
A42: 02.001.001.005 | B42: Aprovação e legalização elétrico | C42: vb | D42: 1 | E42: 3537.26 | F42: 3537.26
A43: 02.001.001.006 | B43: Aprovação e legalização Bombeiros | C43: vb | D43: 1 | E43: 4000 | F43: 4000
A44: 02.001.001.007 | B44: Taxas de ART | C44: vb | D44: 1 | E44: 1414.9 | F44: 1414.9
A45: 02.001.001.008 | B45: Taxas de Alvará | C45: vb | D45: 1 | E45: 51458.79 | F45: 51458.79
A46: 02.001.001.009 | B46: Outorga | C46: vb | D46: 1 | E46: 500000 | F46: 500000
A47: 02.001.001.010 | B47: Despesas de cartório / taxas gerais | C47: vb | D47: 1 | E47: 25000 | F47: 25000
A48: 02.001.001.011 | B48: ISS/ INSS | C48: vb | D48: 1 | E48: 40000 | F48: 40000
A49: 03 | B49: SEGURANÇA, MEIO AMBIENTE E SAÚDE | F49: 229208.18
A50: 03.001 | B50: SEGURANÇA, MEIO AMBIENTE E SAÚDE | F50: 229208.18
A51: 03.001.001 | B51: Segurança do trabalho | F51: 36000
A52: 03.001.001.001 | B52: Serviço terceirizado de segurança do trabalho | C52: mes | D52: 34 | E52: 1058.8235 | F52: 36000
A53: 03.001.002 | B53: Equipamentos de proteção | F53: 158515.41
A54: 03.001.002.001 | B54: Equipamento de proteção individual - EPI | C54: vb | D54: 1 | E54: 5000 | F54: 5000
A55: 03.001.002.002 | B55: Bandejas Primarias | C55: m | D55: 94 | E55: 343.084 | F55: 32249.9
A56: 03.001.002.003 | B56: Bandejas Secundarias | C56: m | D56: 131.24 | E56: 176.344 | F56: 23143.39
A57: 03.001.002.004 | B57: Guarda-corpo de vãos, fixado em forma de madeira, em trama de madeira com tela de polipropileno | C57: m | D57: 268.83 | E57: 19.497 | F57: 5241.38
A58: 03.001.002.005 | B58: Fechamento removível de vãos de porta de elevador em madeira | C58: m2 | D58: 100.32 | E58: 129.2125 | F58: 12962.6
A59: 03.001.002.006 | B59: Ferramentas | C59: vb | D59: 1 | E59: 13200 | F59: 13200
A60: 03.001.002.007 | B60: Guarda corpo de laje apos desforma | C60: m | D60: 316.28 | E60: 9.5033 | F60: 3005.7
A61: 03.001.002.008 | B61: Tela em polietileno para fachada | C61: m2 | D61: 4244.96 | E61: 3.3465 | F61: 14205.76
A62: 03.001.002.009 | B62: Linha de vida | C62: m | D62: 316.28 | E62: 156.528 | F62: 49506.68
A63: 03.001.003 | B63: Meio ambiente | F63: 4570.41
A64: 03.001.003.001 | B64: Elaboração do Programa de Prevenção dos Riscos Ambientais (PPRA) | C64: vb | D64: 1 | E64: 3500 | F64: 3500
A65: 03.001.003.002 | B65: Elaboração do Programa de Controle Médico de Saúde Ocupacional (PCMSO) | C65: vb | D65: 0 | E65: 0 | F65: 0
A66: 03.001.003.003 | B66: Elaboração do Programa de Condições e meio Ambiente de Trabalho na Indústria de Construção (PCMAT) | C66: vb | D66: 0 | E66: 0 | F66: 0
A67: 03.001.003.004 | B67: Projetos de Segurança do Trabalho | C67: vb | D67: 1 | E67: 1070.41 | F67: 1070.41
A68: 03.001.004 | B68: Saúde ocupacional | F68: 30122.36
A69: 03.001.004.001 | B69: Remoção de entulhos | C69: mes | D69: 34 | E69: 500 | F69: 17000
A70: 03.001.004.002 | B70: Medicamentos preventivos e de emergência | C70: mes | D70: 34 | E70: 147.0588 | F70: 5000
A71: 03.001.004.003 | B71: Kit socorrista | C71: vb | D71: 1 | E71: 2122.36 | F71: 2122.36
A72: 03.001.004.004 | B72: Dedetização, desratização e sanitização dos ambientes | C72: vb | D72: 4 | E72: 1500 | F72: 6000
A73: 04 | B73: ADMINISTRAÇÃO E CANTEIRO DE OBRA | F73: 791658.2
A74: 04.001 | B74: ADMINISTRAÇÃO E CANTEIRO DE OBRA | F74: 791658.2
A75: 04.001.001 | B75: Equipe de gestão e apoio | F75: 540000
A76: 04.001.001.001 | B76: Engenheiro | C76: mes | D76: 34 | E76: 8823.5294 | F76: 300000
A77: 04.001.001.002 | B77: Almoxarife | C77: mes | D77: 0 | E77: 0 | F77: 0
A78: 04.001.001.003 | B78: Estagiário | C78: mes | D78: 34 | E78: 1588.2353 | F78: 54000
A79: 04.001.001.004 | B79: Guincheiro | C79: mes | D79: 34 | E79: 2941.1765 | F79: 100000
A80: 04.001.001.005 | B80: Limpeza de obra | C80: mes | D80: 34 | E80: 1470.5882 | F80: 50000
A81: 04.001.001.006 | B81: Vigilância / portaria | C81: mes | D81: 34 | E81: 1058.8235 | F81: 36000
A82: 04.001.002 | B82: Canteiro de obras | F82: 125567.58
A83: 04.001.002.001 | B83: Limpeza mecanizada de camada vegetal | C83: m2 | D83: 600.35 | E83: 5.5 | F83: 3301.93
A84: 04.001.002.002 | B84: Demolições | C84: vb | D84: 1 | E84: 11500 | F84: 11500
A85: 04.001.002.003 | B85: Galpão provisório para canteiro de obra | C85: vb | D85: 1 | E85: 60000 | F85: 60000
A86: 04.001.002.004 | B86: Rede provisória de água fria, esgoto e drenagem | C86: vb | D86: 1 | E86: 2815 | F86: 2815
A87: 04.001.002.005 | B87: Redes provisória elétricas, comunicação e dados | C87: vb | D87: 1 | E87: 5188 | F87: 5188
A88: 04.001.002.006 | B88: Locação de banheiro químico | C88: mes | D88: 0 | E88: 0 | F88: 0
A89: 04.001.002.007 | B89: Sinalização geral da obra | C89: vb | D89: 1 | E89: 2829.81 | F89: 2829.81
A90: 04.001.002.008 | B90: Mobiliário de apoio a obra | C90: vb | D90: 1 | E90: 8100 | F90: 8100
A91: 04.001.002.009 | B91: Equipamentos de escritório | C91: vb | D91: 1 | E91: 20000 | F91: 20000
A92: 04.001.002.010 | B92: Tapume em telha metálica trapezoidal | C92: m2 | D92: 66 | E92: 179.2855 | F92: 11832.84
A93: 04.001.003 | B93: Despesas de consumo e manutenção | F93: 126090.62
A94: 04.001.003.001 | B94: Despesas de consumo - água e esgoto | C94: mes | D94: 34 | E94: 571.95 | F94: 19446.3
A95: 04.001.003.002 | B95: Despesas de consumo - luz/energia | C95: mes | D95: 34 | E95: 743.53 | F95: 25280.02
A96: 04.001.003.003 | B96: Despesas de consumo - internet | C96: mes | D96: 34 | E96: 136.18 | F96: 4630.12
A97: 04.001.003.004 | B97: Despesas de consumo - coleta de lixo | C97: mes | D97: 34 | E97: 24.51 | F97: 833.34
A98: 04.001.003.005 | B98: Despesas de consumo - material de expediente/escritório | C98: mes | D98: 34 | E98: 282.98 | F98: 9621.32
A99: 04.001.003.006 | B99: Despesas de consumo - material de higiene e limpeza | C99: mes | D99: 34 | E99: 272.36 | F99: 9260.24
A100: 04.001.003.007 | B100: Fretes e carretos* | C100: vb | D100: 1 | E100: 16507.21 | F100: 16507.21
A101: 04.001.003.008 | B101: Consumo de cópias | C101: vb | D101: 1 | E101: 4630.05 | F101: 4630.05
A102: 04.001.003.009 | B102: Despesas com vizinhos | C102: vb | D102: 1 | E102: 4716.34 | F102: 4716.34
A103: 04.001.003.010 | B103: Esgotamento de sistema sanitário temporário | C103: mes | D103: 1 | E103: 1500 | F103: 1500
A104: 04.001.003.011 | B104: Manutenção provisória do canteiro | C104: mes | D104: 34 | E104: 306.56 | F104: 10423.04
A105: 04.001.003.012 | B105: Manutenção provisória elétrica | C105: mes | D105: 34 | E105: 259.4 | F105: 8819.6
... A107: 04.001.003.014 | B107: Manutenção provisória de vigilância e acessos | C107: mes | D107: 34 | E107: 165.07 | F107: 5612.38
A108: 05 | B108: EQUIPAMENTOS | F108: 796985.14
...

Sheet VANCOUVER
A3: Obra | B3: VANCOUVER
A4: CONSTRUTORA | B4: PASS-E
A5: AREA TERRENO
A6: Unidade construtiva M² | B6: 5554.12
A7: ANO | B7: 44621
A8: CUB | B8: 2444.3
A10: Código | B10: Descrição | C10: Un. | D10: Quantidade orçada | E10: Preço unitário | F10: Preço total
A11: 01 | B11: ESTUDOS, PROJETOS E CONSULTORIAS | F11: 289667
A12: 01.001 | B12: ESTUDOS, PROJETOS E CONSULTORIAS | F12: 289667
A13: 01.001.001 | B13: Estudos | F13: 9869.97
A14: 01.001.001.001 | B14: Levantamento topográfico | C14: vb | D14: 1 | E14: 400 | F14: 400
A15: 01.001.001.002 | B15: Estudo ambiental | C15: vb | D15: 1 | E15: 5100 | F15: 5100
A16: 01.001.001.003 | B16: Sondagem do terreno | C16: vb | D16: 1 | E16: 4369.97 | F16: 4369.97
A17: 01.001.002 | B17: Projetos | F17: 225779.59
A18: 01.001.002.001 | B18: Legalização de incorporação* | C18: vb | D18: 1 | E18: 8000 | F18: 8000
A19: 01.001.002.002 | B19: Projeto arquitetônico legal* | C19: vb | D19: 1 | E19: 20297.38 | F19: 20297.38
A20: 01.001.002.003 | B20: Projeto arquitetônico | C20: vb | D20: 1 | E20: 44464.16 | F20: 44464.16
A21: 01.001.002.004 | B21: Projeto arquitetônico interiores/ambientação* | C21: vb | D21: 1 | E21: 17600 | F21: 17600
A22: 01.001.002.005 | B22: Projeto técnico de fachada* | C22: vb | D22: 1 | E22: 2500 | F22: 2500
A23: 01.001.002.006 | B23: Projeto de fundação* | C23: vb | D23: 1 | E23: 12222.23 | F23: 12222.23
A24: 01.001.002.007 | B24: Projeto estrutural em concreto armado* | C24: vb | D24: 1 | E24: 48634.64 | F24: 48634.64
A25: 01.001.002.008 | B25: Projeto elétrico* | C25: vb | D25: 1 | E25: 6605.59 | F25: 6605.59
A26: 01.001.002.009 | B26: Projeto hidrossanitário* | C26: vb | D26: 1 | E26: 6605.59 | F26: 6605.59
A27: 01.001.002.010 | B27: Projeto preventivo* | C27: vb | D27: 1 | E27: 8850 | F27: 8850
A28: 01.001.002.011 | B28: Projeto de paisagismo | C28: vb | D28: 1 | E28: 5000 | F28: 5000
A29: 01.001.002.012 | B29: Projeto de comunicação visual | C29: vb | D29: 1 | E29: 4000 | F29: 4000
A30: 01.001.002.013 | B30: Modelagem BIM de complementares | C30: vb | D30: 1 | E30: 41000 | F30: 41000
A31: 01.001.003 | B31: Consultorias | F31: 32741.36
A32: 01.001.003.001 | B32: Orçamento e planejamento* | C32: vb | D32: 1 | E32: 11941.36 | F32: 11941.36
A33: 01.001.003.002 | B33: Auditoria de qualidade* | C33: vb | D33: 1 | E33: 8000 | F33: 8000
A34: 01.001.003.003 | B34: Consultorias técnicas diversas | C34: vb | D34: 1 | E34: 12800 | F34: 12800
A35: 01.001.004 | B35: Ensaios e Laudos | F35: 21276.08
A36: 01.001.004.001 | B36: Controle tecnológico de concreto | C36: m3 | D36: 1436.81 | E36: 7.5 | F36: 10776.08
A37: 01.001.004.002 | B37: Laudo preventivo de danos à vizinhança | C37: vb | D37: 1 | E37: 1500 | F37: 1500
A38: 01.001.004.003 | B38: Ensaio/Laudo desempenho - NBR 15575 | C38: vb | D38: 1 | E38: 9000 | F38: 9000
A39: 02 | B39: TAXAS, DOCUMENTOS | F39: 68286.31
A40: 02.001 | B40: TAXAS, DOCUMENTOS | F40: 68286.31
A41: 02.001.001 | B41: Taxas e Documentos | F41: 68286.31
A42: 02.001.001.001 | B42: Despesas de seguro* | C42: vb | D42: 1 | E42: 9600 | F42: 9600
A43: 02.001.001.002 | B43: Aprovação e legalização prefeitura* | C43: vb | D43: 1 | E43: 20297.38 | F43: 20297.38
A44: 02.001.001.003 | B44: Aprovação e legalização bombeiros* | C44: vb | D44: 1 | E44: 3500 | F44: 3500
A45: 02.001.001.004 | B45: Aprovação e legalização elétrico | C45: vb | D45: 1 | E45: 3300 | F45: 3300
A46: 02.001.001.005 | B46: Aprovação e legalização ambiental* | C46: vb | D46: 1 | E46: 2683.93 | F46: 2683.93
A47: 02.001.001.006 | B47: Taxas de ART* | C47: vb | D47: 1 | E47: 500 | F47: 500
A48: 02.001.001.007 | B48: Taxas de alvará | C48: vb | D48: 1 | E48: 7200 | F48: 7200
A49: 02.001.001.008 | B49: Despesas cartório, licenças, certidões e jurídicas* | C49: vb | D49: 1 | E49: 2450 | F49: 2450
A50: 02.001.001.009 | B50: Incorporação | C50: vb | D50: 1 | E50: 4200 | F50: 4200
A51: 02.001.001.010 | B51: IPTU* | C51: vb | D51: 1 | E51: 3000 | F51: 3000
A52: 02.001.001.011 | B52: Habite-se* | C52: vb | D52: 1 | E52: 5555 | F52: 5555
A53: 02.001.001.012 | B53: Certidão INSS | C53: vb | D53: 1 | E53: 6000 | F53: 6000
A54: Total da unidade construtiva | F54: 357953.31
A56: Obra
A57: Unidade construtiva
A58: Tipo de obra
A59: Endereço da obra
A60: Versão do orçamento
A61: BDI
A62: Preços expressos em
A64: Código | B64: Descrição | C64: Un. | D64: Quantidade orçada | E64: Preço unitário | F64: Preço total
A65: 01 | B65: SEGURANÇA, MEIO AMBIENTE E SAÚDE | F65: 232369.97
A66: 01.001 | B66: SEGURANÇA, MEIO AMBIENTE E SAÚDE | F66: 232369.97
A67: 01.001.001 | B67: Segurança do trabalho | F67: 27498.24
A68: 01.001.001.001 | B68: Serviço terceirizado de segurança do trabalho | C68: mes | D68: 42 | E68: 654.72 | F68: 27498.24
A69: 01.001.002 | B69: Equipamentos de proteção | F69: 182571.73
A70: 01.001.002.001 | B70: Equipamentos de proteção individual | C70: vb | D70: 1 | E70: 12900 | F70: 12900
A71: 01.001.002.002 | B71: Bandeja de proteção primária | C71: m | D71: 147.14 | E71: 152.9206 | F71: 22500.74
A72: 01.001.002.003 | B72: Bandeja de proteção secundária | C72: m | D72: 207.02 | E72: 159.3634 | F72: 32991.41
A73: 01.001.002.004 | B73: Rede de proteção tipo SLQA* | C73: m2 | D73: 623.95 | E73: 53.1 | F73: 33131.75
A74: 01.001.002.005 | B74: Guarda-corpo de vãos, fixado em forma de madeira, em trama de madeira com tela de polipropileno | C74: m | D74: 268.98 | E74: 41.6224 | F74: 11195.59
A75: 01.001.002.006 | B75: Guarda-corpo de laje após desforma | C75: m | D75: 207.06 | E75: 41.6224 | F75: 8618.33
A76: 01.001.002.007 | B76: Varal de segurança com cabo de aço | C76: m | D76: 207.06 | E76: 174 | F76: 36028.44
A77: 01.001.002.008 | B77: Fechamento removível de vãos de porta de elevador em madeira | C77: m2 | D77: 88.2 | E77: 27.9406 | F77: 2464.36
A78: 01.001.002.009 | B78: Cobertura para proteção de pedestres | C78: m2 | D78: 36.25 | E78: 76.0566 | F78: 2757.05
A79: 01.001.002.010 | B79: Tela em polietileno para fachada | C79: m2 | D79: 4131.72 | E79: 4.4979 | F79: 18584.06
A80: 01.001.002.011 | B80: Placas de sinalização de obra | C80: vb | D80: 1 | E80: 1400 | F80: 1400
A81: 01.001.003 | B81: Meio ambiente | F81: 2500
A82: 01.001.003.001 | B82: Elaboração do programa de condições e meio ambiente de trabalho na indústria de construção (PCMAT)* | C82: vb | D82: 1 | E82: 2500 | F82: 2500
A83: 01.001.004 | B83: Saúde ocupacional | F83: 19800
A84: 01.001.004.001 | B84: Remoção ordinária de entulhos, com transporte para bota-fora* | C84: mes | D84: 42 | E84: 350 | F84: 14700
A85: 01.001.004.002 | B85: Medicamentos preventivos e de emergência | C85: vb | D85: 1 | E85: 600 | F85: 600
A86: 01.001.004.003 | B86: Kit socorrista | C86: vb | D86: 1 | E86: 1500 | F86: 1500
A87: 01.001.004.004 | B87: Dedetização, desratização e sanitarização dos ambientes | C87: vb | D87: 1 | E87: 3000 | F87: 3000
A88: 02 | B88: ADMINISTRAÇÃO E CANTEIRO DE OBRA | F88: 819823.2
A89: 02.001 | B89: ADMINISTRAÇÃO E CANTEIRO DE OBRA | F89: 819823.2
A90: 02.001.001 | B90: Equipe de gestão e apoio | F90: 634200
A91: 02.001.001.001 | B91: Engenheiro civil* | C91: mes | D91: 42 | E91: 5000 | F91: 210000
A92: 02.001.001.002 | B92: Almoxarife* | C92: mes | D92: 42 | E92: 3000 | F92: 126000
A93: 02.001.001.003 | B93: Auxiliar de engenharia* | C93: mes | D93: 42 | E93: 3000 | F93: 126000
A94: 02.001.001.004 | B94: Estagiário* | C94: mes | D94: 42 | E94: 700 | F94: 29400
A95: 02.001.001.005 | B95: Vigilância e portaria* | C95: mes | D95: 42 | E95: 1700 | F95: 71400
A96: 02.001.001.006 | B96: Equipe de T.I* | C96: mes | D96: 42 | E96: 1700 | F96: 71400
A97: 02.001.002 | B97: Canteiro de obras | F97: 41773.2
A98: 02.001.002.001 | B98: Limpeza mecanizada de camada vegetal | C98: m2 | D98: 576.28 | E98: 3.5 | F98: 2016.98
A99: 02.001.002.002 | B99: Instalações provisórias | C99: vb | D99: 1 | E99: 6700 | F99: 6700
A100: 02.001.002.003 | B100: Instalações provisórias: redes de água fria, esgoto e drenagem | C100: vb | D100: 1 | E100: 6400 | F100: 6400
A101: 02.001.002.004 | B101: Instalações provisórias: rede elétrica, comunicação e dados | C101: vb | D101: 1 | E101: 5200 | F101: 5200
A102: 02.001.002.005 | B102: Locação de banheiro químico | C102: mes | D102: 2 | E102: 400 | F102: 800
A103: 02.001.002.006 | B103: Tapume com telha metálica* | C103: m2 | D103: 53.18 | E103: 113.8815 | F103: 6056.22
A104: 02.001.002.007 | B104: Sinalização de obra | C104: vb | D104: 1 | E104: 3000 | F104: 3000
A105: 02.001.002.008 | B105: Equipamento de Escritório* | C105: vb | D105: 1 | E105: 5600 | F105: 5600
...

Sheet VILLA LOBOS
A4: Obra | B4: VILLA LOBOS
A5: CONSTRUTORA | B5: MACOM
A6: AREA TERRENO | B6: 553.46
A7: Unidade construtiva M² | B7: 6001.7
A8: ANO | B8: 45108
A9: CUB | B9: 2747.9
A12: Código | B12: Descrição | C12: Un. | D12: Quantidade orçada | E12: Preço unitário | F12: Preço total
A13: 1 | B13: SERVIÇOS TÉCNICOS | F13: 521607.16
A14: 1001 | B14: ESTUDOS, PROJETOS E CONSULTORIAS | F14: 365146.91
A15: 1001001 | B15: Estudos | F15: 24237
A16: 1001001001 | B16: MEMORIAL DESCRITIVO | C16: vb | D16: 1 | E16: 6449 | F16: 6449
A17: 1001001002 | B17: LEVANTAMENTO TOPOGRÁFICO | C17: vb | D17: 1 | E17: 1200 | F17: 1200
A18: 1001001003 | B18: ESTUDO GEOLÓGICO | C18: vb | D18: 1 | E18: 3794 | F18: 3794
A19: 1001001004 | B19: ESTUDO AMBIENTAL | C19: vb | D19: 1 | E19: 3794 | F19: 3794
A20: 1001001005 | B20: SONDAGEM DO TERRENO | C20: vb | D20: 1 | E20: 9000 | F20: 9000
A21: 1001002 | B21: Projetos | F21: 268414.21
A22: 1001002001 | B22: LEGALIZAÇÃO DE INCORPORAÇÃO | C22: vb | D22: 1 | E22: 11291 | F22: 11291
A23: 1001002002 | B23: PROJETO ARQUITETÔNICO LEGAL | C23: vb | D23: 1 | E23: 22991 | F23: 22991
A24: 1001002003 | B24: PROJETO ARQUITETÔNICO EXECUTIVO | C24: vb | D24: 1 | E24: 25629 | F24: 25629
A25: 1001002004 | B25: PROJETO DE TERRAPLANAGEM | C25: vb | D25: 1 | E25: 54300 | F25: 54300
A26: 1001002005 | B26: PROJETO DE CLIMATIZAÇÃO | C26: vb | D26: 1 | E26: 3000 | F26: 3000
A27: 1001002006 | B27: PROJETO DE ASPIRAÇÃO CENTRAL | C27: vb | D27: 1 | E27: 3000 | F27: 3000
A28: 1001002007 | B28: PROJETO ESTRUTURAL EM CONCRETO ARMADO | C28: vb | D28: 1 | E28: 84400 | F28: 84400
A29: 1001002008 | B29: PROJETOS COMPLEMENTARES | C29: vb | D29: 1 | E29: 45800 | F29: 45800
A30: 1001002009 | B30: COMPATIBILIZAÇÃO DE PROJETOS BIM | C30: vb | D30: 1 | E30: 18003.21 | F30: 18003.21
A31: 1001003 | B31: Consultorias | F31: 42149.7
A32: 1001003001 | B32: ORÇAMENTO E PLANEJAMENTO | C32: vb | D32: 1 | E32: 42149.7 | F32: 42149.7
A33: 1001004 | B33: Ensaios e laudos | F33: 30346
A34: 1001004001 | B34: CONTROLE TECNOLÓGICO DO CONCRETO | C34: vb | D34: 1 | E34: 30346 | F34: 30346
A35: 1002 | B35: CONSUMOS, TAXAS E DOCUMENTOS | F35: 156460.25
A36: 1002001 | B36: Licenciamentos, taxas, impostos, aprovações e seguros | F36: 93852.46
A37: 1002001001 | B37: DESPESAS DE SEGURO DE OBRA | C37: vb | D37: 1 | E37: 9825.24 | F37: 9825.24
A38: 1002001002 | B38: DESPESAS DE CARTÓRIO, LICENÇAS, CERTIDÕES E JURÍDICAS | C38: vb | D38: 1 | E38: 3454 | F38: 3454
A39: 1002001003 | B39: APROVAÇÃO E LEGALIZAÇÃO AMBIENTAL | C39: vb | D39: 1 | E39: 4563 | F39: 4563
A40: 1002001004 | B40: APROVAÇÃO E LEGALIZAÇÃO DE PREFEITURA | C40: vb | D40: 1 | E40: 26658 | F40: 26658
A41: 1002001005 | B41: APROVAÇÃO E LEGALIZAÇÃO DE ÁGUA E ESGOTO | C41: vb | D41: 1 | E41: 4599 | F41: 4599
A42: 1002001006 | B42: APROVAÇÃO E LEGALIZAÇÃO ELÉTRICO | C42: vb | D42: 1 | E42: 4599 | F42: 4599
A43: 1002001007 | B43: APROVAÇÃO E LEGALIZAÇÃO BOMBEIROS | C43: vb | D43: 1 | E43: 4932 | F43: 4932
A44: 1002001008 | B44: TAXAS DE ART | C44: vb | D44: 1 | E44: 1897 | F44: 1897
A45: 1002001009 | B45: TAXAS DE ALVARÁ | C45: vb | D45: 1 | E45: 12999.52 | F45: 12999.52
A46: 1002001010 | B46: INCORPORAÇÃO | C46: vb | D46: 1 | E46: 7700 | F46: 7700
A47: 1002001011 | B47: IPTU | C47: vb | D47: 1 | E47: 5030.7 | F47: 5030.7
A48: 1002001012 | B48: TAXA HABITE-SE | C48: vb | D48: 1 | E48: 7595 | F48: 7595
A49: 1002002 | B49: Documentos | F49: 13829
A50: 1002002001 | B50: MANUAIS TÉCNICOS | C50: un | D50: 21 | E50: 133 | F50: 2793
A51: 1002002002 | B51: CERTIDÃO NEGATIVA DE DÉBITOS (CND) | C51: vb | D51: 1 | E51: 11036 | F51: 11036
A52: 1002003 | B52: Outras despesas | F52: 48778.79
A53: 1002003001 | B53: LOCAÇÃO DE TERRENO DESTINADO A CANTEIRO DE OBRA | C53: mes | D53: 11 | E53: 3662.09 | F53: 40282.99
A54: 1002003002 | B54: SISTEMA DE ESCRITURAÇÃO DIGITAL DAS OBRIGAÇÕES FISCAIS, PREVIDENCIÁRIAS E TRABALHISTAS (ESOCIAL) | C54: mes | D54: 36 | E54: 171.55 | F54: 6175.8
A55: 1002003003 | B55: ADMISSÃO, DEMISSÃO E CURSOS DE FUNCIONÁRIOS | C55: vb | D55: 1 | E55: 2320 | F55: 2320
A56: 2 | B56: SERVIÇOS INICIAIS | F56: 833361.76
A57: 2001 | B57: SEGURANÇA, MEIO AMBIENTE, SAÚDE | F57: 249273.77
A58: 2001001 | B58: Segurança do trabalho | F58: 24100
A59: 2001001001 | B59: SERVIÇO DE SEGURANÇA DO TRABALHO | C59: mes | D59: 36 | E59: 600 | F59: 21600
A60: 2001001002 | B60: ELABORAÇÃO DO PROGRAMA DE GERENCIAMENTO DE RISCO (PGR) | C60: vb | D60: 1 | E60: 2500 | F60: 2500
A61: 2001002 | B61: Equipamentos de proteção | F61: 156193.77
A62: 2001002001 | B62: EQUIPAMENTOS DE PROTEÇÃO INDIVIDUAL (EPI) | C62: mes | D62: 36 | E62: 332.25 | F62: 11961
A63: 2001002002 | B63: PLACA DE OBRA E SINALIZAÇÃO | C63: un | D63: 270 | E63: 20 | F63: 5400
A64: 2001002003 | B64: BANDEJA DE PROTEÇÃO PRIMÁRIA | C64: m | D64: 91.24 | E64: 267.4385 | F64: 24401.09
A65: 2001002004 | B65: BANDEJA DE PROTEÇÃO SECUNDÁRIA | C65: m | D65: 108.34 | E65: 232.4195 | F65: 25180.33
A66: 2001002005 | B66: GUARDA-CORPO DE VÃOS | C66: m | D66: 375.44 | E66: 8.8504 | F66: 3322.79
A67: 2001002006 | B67: GUARDA-CORPO DE LAJE APÓS DESFORMA | C67: m | D67: 364.96 | E67: 4.1598 | F67: 1518.16
A68: 2001002007 | B68: FECHAMENTO REMOVÍVEL DE VÃOS DE PORTA DE ENTRADA DOS APARTAMENTOS | C68: m2 | D68: 48.51 | E68: 23.4003 | F68: 1135.15
A69: 2001002008 | B69: FECHAMENTO REMOVÍVEL DE VÃOS DE PORTA DE ELEVADOR | C69: m2 | D69: 91.52 | E69: 23.4003 | F69: 2141.6
A70: 2001002009 | B70: COBERTURA DE PROTEÇÃO PARA PEDESTRES | C70: m | D70: 31.64 | E70: 78.7205 | F70: 2490.72
A71: 2001002010 | B71: VARAL DE SEGURANÇA COM CABO DE AÇO | C71: m | D71: 364.96 | E71: 38 | F71: 13868.48
A72: 2001002011 | B72: REDE DE PROTEÇÃO TIPO SLQA | C72: m | D72: 54.17 | E72: 908.5132 | F72: 49214.16
A73: 2001002012 | B73: TELA FACHADEIRA COM LOGO | C73: m2 | D73: 4715.24 | E73: 3.3 | F73: 15560.29
A74: 2001003 | B74: Meio ambiente | F74: 68500
A75: 2001003001 | B75: AÇÃO DO PROGRAMA DE PREVENÇÃO DOS RISCOS AMBIENTAIS (PPRA) | C75: vb | D75: 1 | E75: 600 | F75: 600
A76: 2001003002 | B76: ELABORAÇÃO DO PROGRAMA DE CONTROLE MÉDICO DE SAÚDE OCUPACIONAL (PCMSO) | C76: vb | D76: 1 | E76: 600 | F76: 600
A77: 2001003003 | B77: ELABORAÇÃO DO PROGRAMA DE CONDIÇÕES E MEIO AMBIENTE DE TRABALHO NA INDÚSTRIA DA CONSTRUÇÃO ( PCMAT) | C77: vb | D77: 1 | E77: 2500 | F77: 2500
A78: 2001003004 | B78: REMOÇÃO DE ENTULHOS | C78: mes | D78: 36 | E78: 1800 | F78: 64800
A79: 2001004 | B79: Saúde ocupacional | F79: 480
A80: 2001004001 | B80: MEDICAMENTOS PREVENTIVOS E DE EMERGÊNCIA | C80: vb | D80: 1 | E80: 180 | F80: 180
A81: 2001004002 | B81: KIT SOCORRISTA | C81: vb | D81: 1 | E81: 300 | F81: 300
A82: 2002 | B82: ADMINISTRAÇÃO E CANTEIRO DE OBRA | F82: 566579.27
A83: 2002001 | B83: Equipe de gestão e apoio | F83: 395754.12
A84: 2002001001 | B84: ENGENHEIRO CIVIL | C84: mes | D84: 36 | E84: 2800 | F84: 100800
A85: 2002001002 | B85: MESTRE DE OBRAS | C85: mes | D85: 36 | E85: 3175.35 | F85: 114312.6
A86: 2002001003 | B86: ALMOXARIFE | C86: mes | D86: 36 | E86: 3136.88 | F86: 112927.68
A87: 2002001004 | B87: GUINCHEIRO | C87: mes | D87: 18 | E87: 3761.88 | F87: 67713.84
A88: 2002002 | B88: Despesas de consumo e manutenção | F88: 65297.36
A89: 2002002001 | B89: DESPESAS COM CONSUMO DE ÁGUA | C89: mes | D89: 36 | E89: 300 | F89: 10800
A90: 2002002002 | B90: DESPESAS COM CONSUMO DE ENERGIA ELÉTRICA | C90: mes | D90: 36 | E90: 300 | F90: 10800
A91: 2002002003 | B91: DESPESAS COM INTERNET | C91: mes | D91: 36 | E91: 320 | F91: 11520
A92: 2002002004 | B92: DESPESAS COM COLETA DE LIXO | C92: mes | D92: 36 | E92: 43.26 | F92: 1557.36
A93: 2002002005 | B93: DESPESAS COM CONSUMO DE MATERIAL DE LIMPEZA | C93: mes | D93: 36 | E93: 350 | F93: 12600
A94: 2002002006 | B94: DESPESAS COM CONSUMO DE CÓPIAS | C94: vb | D94: 1 | E94: 200 | F94: 200
A95: 2002002007 | B95: DESPESAS COM GERENCIAMENTO ELETRÔNICO | C95: mes | D95: 36 | E95: 495 | F95: 17820
A96: 2002003 | B96: Instalações provisórias | F96: 105527.79
A97: 2002003001 | B97: GALPÃO | C97: m2 | D97: 217.43 | E97: 290.77 | F97: 63222.12
A98: 2002003002 | B98: INSTALAÇÕES PROVISÓRIAS DE DIVISÓRIAS EM MADEIRA COMPENSADA SIMPLES | C98: vb | D98: 1 | E98: 26345 | F98: 26345
A99: 2002003003 | B99: INSTALAÇÕES ELÉTRICAS PROVISÓRIAS | C99: m | D99: 74.82 | E99: 42 | F99: 3142.44
A100: 2002003004 | B100: INSTALAÇÕES HIDROSSANITÁRIAS PROVISÓRIAS | C100: m | D100: 74.82 | E100: 42 | F100: 3142.44
A101: 2002003005 | B101: TAPUME COM TELHA METÁLICA | C101: m2 | D101: 69.61 | E101: 139 | F101: 9675.79
A102: 2003 | B102: SERVIÇOS PRELIMINARES | F102: 17508.72
A103: 2003001 | B103: Demolições | F103: 13795
A104: 2003001001 | B104: DEMOLIÇÕES | C104: vb | D104: 1 | E104: 13795 | F104: 13795
A105: 2003002 | B105: Limpeza de terreno | F105: 3713.72
...

Sheet GRAN TOWER
A4: Obra | B4: GRAN TOWER
A5: CONSTRUTORA | B5: GRANDEZZA
A6: Endereço da obra | B6: Av. Itapocoroy esq. com RuaAlfredo Brunetti (Lt. 18, 19A e 19B) CEP: 88385-000 Armação - Penha,SC
A7: AREA TERRENO | B7: 859.95
A8: Unidade construtiva M² | B8: 6245.48
A9: ANO | B9: 45383
A10: CUB | B10: 2757.56
A13: Código | B13: Descrição | C13: Un. | D13: Quantidade orçada | E13: Preço unitário | F13: Preço total
A14: 1 | B14: SERVIÇOS TÉCNICOS | F14: 704184.6
A15: 1001 | B15: ESTUDOS, PROJETOS E CONSULTORIAS | F15: 511004.81
A16: 1001001 | B16: Estudos | F16: 65491
A17: 1001001001 | B17: Memorial descritivo | C17: vb | D17: 1 | E17: 6789 | F17: 6789
A18: 1001001002 | B18: Levantamento topográfico | C18: vb | D18: 1 | E18: 6789 | F18: 6789
A19: 1001001003 | B19: Estudo geológico | C19: vb | D19: 1 | E19: 6789 | F19: 6789
A20: 1001001004 | B20: Estudo ambiental | C20: vb | D20: 1 | E20: 16158 | F20: 16158
A21: 1001001005 | B21: Sondagem do terreno | C21: vb | D21: 1 | E21: 22177 | F21: 22177
A22: 1001001006 | B22: Projeto de canteiro | C22: vb | D22: 1 | E22: 6789 | F22: 6789
A23: 1001002 | B23: Projetos | F23: 408226.81
A24: 1001002001 | B24: Legalização de incorporação | C24: vb | D24: 1 | E24: 11611.7 | F24: 11611.7
A25: 1001002002 | B25: Projeto arquitetônico legal | C25: vb | D25: 1 | E25: 79546 | F25: 79546
A26: 1001002003 | B26: Projeto arquitetônico executivo | C26: vb | D26: 1 | E26: 50000 | F26: 50000
A27: 1001002004 | B27: Projeto arquitetônico interiores | C27: vb | D27: 1 | E27: 67889 | F27: 67889
A28: 1001002005 | B28: Projeto arquitetônico de fachada | C28: vb | D28: 1 | E28: 2187.34 | F28: 2187.34
A29: 1001002006 | B29: Projeto de fundação | C29: vb | D29: 1 | E29: 3729 | F29: 3729
A30: 1001002007 | B30: Projeto estrutural de concreto armado | C30: vb | D30: 1 | E30: 41587 | F30: 41587
A31: 1001002008 | B31: Projeto de estrutura metálica | C31: vb | D31: 1 | E31: 30000 | F31: 30000
A32: 1001002009 | B32: Projeto elétrico | C32: vb | D32: 1 | E32: 33310 | F32: 33310
A33: 1001002010 | B33: Projeto de automação | C33: vb | D33: 1 | E33: 2000 | F33: 2000
A34: 1001002011 | B34: Projeto hidrossanitário | C34: vb | D34: 1 | E34: 41016 | F34: 41016
A35: 1001002012 | B35: Projeto preventivo | C35: vb | D35: 1 | E35: 4972 | F35: 4972
... A39: 1001002016 | B39: Projeto de paisagismo | C39: vb | D39: 1 | E39: 1514.48 | F39: 1514.48
A40: 1001003 | B40: Consultorias | F40: 37287
A41: 1001003001 | B41: Consultoria técnica de legalização | C41: vb | D41: 1 | E41: 37287 | F41: 37287
A42: 1001004 | B42: Ensaios | F42: 0
A43: 1002 | B43: TAXAS E DOCUMENTOS | F43: 193179.79
A44: 1002001 | B44: Licenciamentos, Taxas, Impostos, Aprovações e Seguros | F44: 193179.79
A45: 1002001001 | B45: Despesas de seguro de obra | C45: vb | D45: 1 | E45: 37287 | F45: 37287
A46: 1002001002 | B46: Aprovação e legalização ambiental | C46: vb | D46: 1 | E46: 4972 | F46: 4972
A47: 1002001003 | B47: Aprovação e legalização prefeitura | C47: vb | D47: 1 | E47: 8883 | F47: 8883
A48: 1002001004 | B48: Aprovação e legalização água e esgoto | C48: vb | D48: 1 | E48: 1134 | F48: 1134
A49: 1002001005 | B49: Aprovação e legalização elétrico | C49: vb | D49: 1 | E49: 1134 | F49: 1134
A50: 1002001006 | B50: Aprovação e legalização bombeiros | C50: vb | D50: 1 | E50: 4972 | F50: 4972
A51: 1002001007 | B51: Taxas de ART | C51: vb | D51: 1 | E51: 4535 | F51: 4535
A52: 1002001008 | B52: Taxas de alvará | C52: vb | D52: 1 | E52: 19598 | F52: 19598
A53: 1002001009 | B53: Despesas de cartório, licenças, certidões e jurídicas | C53: vb | D53: 1 | E53: 39773 | F53: 39773
A54: 1002001010 | B54: Incorporação | C54: vb | D54: 1 | E54: 11315 | F54: 11315
A55: 1002001011 | B55: IPTU | C55: vb | D55: 1 | E55: 32370.79 | F55: 32370.79
A56: 1002001012 | B56: Taxa Habite-se | C56: vb | D56: 1 | E56: 27206 | F56: 27206
A57: 1002002 | B57: Documentos | F57: 0
A58: 2 | B58: SERVIÇOS INICIAIS | F58: 953195.75
A59: 2001 | B59: SEGURANÇA, MEIO AMBIENTE, SAÚDE | F59: 267038.14
A60: 2001001 | B60: Segurança do trabalho | F60: 2500
A61: 2001001001 | B61: Projetos de segurança do trabalho | C61: vb | D61: 1 | E61: 2500 | F61: 2500
A62: 2001002 | B62: Equipamentos de proteção | F62: 202456.6
A63: 2001002001 | B63: Equipamentos de proteção individual - EPI | C63: mes | D63: 36 | E63: 250 | F63: 9000
A64: 2001002002 | B64: Guarda-corpo de vãos, fixado em forma de madeira, em trama de madeira oom tela de polipropileno | C64: m | D64: 763.69 | E64: 1.6601 | F64: 1267.8
A65: 2001002003 | B65: Bandeja de proteção primária | C65: m | D65: 107.43 | E65: 92.4 | F65: 9926.53
A66: 2001002004 | B66: Bandeja de proteção secundária | C66: m | D66: 71.49 | E66: 92.4 | F66: 6605.68
A67: 2001002005 | B67: Guarda-corpo de laje após desforma | C67: m | D67: 285.96 | E67: 495.2576 | F67: 141623.86
A68: 2001002006 | B68: Fechamento removível de vãos de porta de elevador em madeira | C68: m2 | D68: 110.88 | E68: 41.4883 | F68: 4600.22
A69: 2001002007 | B69: Varal de segurança com cabo de aço | C69: m | D69: 81.6 | E69: 153.9401 | F69: 12561.51
A70: 2001002008 | B70: Rede de proteção tipo SLQA | C70: m | D70: 71.49 | E70: 235.9911 | F70: 16871
A71: 2001003 | B71: Meio ambiente | F71: 62081.54
A72: 2001003001 | B72: Elaboração do Programa de Prevenção dos Riscos Ambientais ( | C72: vb | D72: 1 | E72: 2351.16 | F72: 2351.16
A73: 2001003002 | B73: Elaboração do Programa de Condições e Meio Ambiente de Trabalho na indústria da construção (PCMAT) | C73: vb | D73: 1 | E73: 2730.38 | F73: 2730.38
A74: 2001003003 | B74: Elaboração do Programa de Controle Médico de Saúde Ocupacional (PCMSO) | C74: vb | D74: 1 | E74: 3000 | F74: 3000
A75: 2001003004 | B75: Remoção de entulhos e resíduos | C75: mes | D75: 36 | E75: 1500 | F75: 54000
A76: 2001004 | B76: Saúde ocupacional | F76: 0
A77: 2002 | B77: ADMINISTRAÇÃO E CANTEIRO DE OBRA | F77: 285712
A78: 2002001 | B78: Equipe de Gestão e Apoio | F78: 0
A79: 2002002 | B79: Operação inicial de canteiro | F79: 0
A80: 2002003 | B80: Despesas de consumo e manutenção | F80: 224712
A81: 2002003001 | B81: Despesa de consumo - água | C81: mes | D81: 36 | E81: 657 | F81: 23652
A82: 2002003002 | B82: Despesas de consumo - luz | C82: mes | D82: 36 | E82: 860 | F82: 30960
A83: 2002003003 | B83: Despesas de consumo - internet | C83: mes | D83: 36 | E83: 373 | F83: 13428
A84: 2002003004 | B84: Despesas de consumo - alimentação | C84: mes | D84: 36 | E84: 2983 | F84: 107388
A85: 2002003005 | B85: Despesas de consumo - material de expediente | C85: mes | D85: 36 | E85: 498 | F85: 17928
A86: 2002003006 | B86: Despesas de consumo - material de limpeza | C86: mes | D86: 36 | E86: 498 | F86: 17928
A87: 2002003007 | B87: Consumo gerenciamento eletrônico | C87: mes | D87: 36 | E87: 373 | F87: 13428
A88: 2002004 | B88: Instalações provisórias | F88: 61000
A89: 2002004001 | B89: Locação de banheiro químico | C89: mes | D89: 36 | E89: 1500 | F89: 54000
A90: 2002004002 | B90: Divisórias em madeira compensada simples | C90: vb | D90: 1 | E90: 2500 | F90: 2500
A91: 2002004003 | B91: Mobiliário de apoio a obra | C91: vb | D91: 1 | E91: 4000 | F91: 4000
A92: 2002004004 | B92: Equipamentos de escritório | C92: vb | D92: 1 | E92: 500 | F92: 500
A93: 2002005 | B93: Ligações Provisórias | F93: 0
A94: 2003 | B94: SERVIÇOS PRELIMINARES | F94: 400445.61
A95: 2003001 | B95: DemoliçÕes | F95: 400000
A96: 2003001001 | B96: Demolição | C96: m2 | D96: 800 | E96: 500 | F96: 400000
A97: 2003002 | B97: Limpeza de terreno | F97: 445.61
A98: 2003002001 | B98: Limpeza manual de camada vegetal | C98: m2 | D98: 856.95 | E98: 0.52 | F98: 445.61
A99: 3 | B99: EQUIPAMENTOS | F99: 723541
A100: 3001 | B100: EQUIPAMENTOS | F100: 723541
A101: 3001001 | B101: Equipamentos de Carga e Transporte | F101: 0
A102: 3001002 | B102: Equipamentos de obra | F102: 414800
A103: 3001002001 | B103: Elevador cremalheira - aquisição | C103: vb | D103: 1 | E103: 300000 | F103: 300000
A104: 3001002002 | B104: Montagem e desmontagem de elevador cremalheira | C104: vb | D104: 1 | E104: 17600 | F104: 17600
A105: 3001002003 | B105: Manutenção de elevador cremalheira | C105: mes | D105: 17 | E105: 1600 | F105: 27200
A106: 3001002004 | B106: Manutenção inicial elevador cremalheira | C106: vb | D106: 1 | E106: 70000 | F106: 70000
A107: 3001003 | B107: Balancins e Andaimes | F107: 308741
A108: 3001003001 | B108: Andaime modular fachadeiro - locação | C108: mes | D108: 3 | E108: 3000 | F108: 9000
...
