Workbook
Name \0: #REF!
Name \0: #REF!
Name \0: #REF!
Name \0: #REF!
Name \0: #REF!
Name \0: #REF!
Name \0: #REF!
Name \0: #REF!
Name \0: #REF!
Name \0: #REF!
Name \0: #REF!
Name \0: #REF!
Name \0: #REF!
Name \0: #REF!
Name \0: #REF!
Name \0: #REF!
Name \0: #REF!
Name \0: #REF!
Name \0: #REF!
Name \a: #REF!
Name \a: #REF!
Name \a: #REF!
Name \a: #REF!
Name \a: #REF!
Name \a: #REF!
Name \a: #REF!
Name \a: #REF!
Name \a: #REF!
Name \a: #REF!
Name \a: #REF!
Name \a: #REF!
Name \a: #REF!
Name \a: #REF!
Name \a: #REF!
Name \a: #REF!
Name \a: #REF!
Name \a: #REF!
Name \a: #REF!
Name \m: #REF!
Name \m: #REF!
Name \m: #REF!
Name \m: #REF!
Name \m: #REF!
Name \m: #REF!
Name \m: #REF!
Name \m: #REF!
Name \m: #REF!
Name \m: #REF!
Name \m: #REF!
Name \m: #REF!
Name \m: #REF!
Name \m: #REF!
Name \m: #REF!
Name \m: #REF!
Name \m: #REF!
Name \m: #REF!
Name aa: #REF!
Name aa: #REF!
Name aa: #REF!
Name aa: #REF!

Sheet Resumo
A1: ETAPA | B1: R02 | E1: R03 | H1: DIFERENÇA
B2: VALOR ORÇADO | C2: % | D2: VALOR/M² | E2: VALOR ORÇADO | F2: % | G2: VALOR/M² | H2: VALOR ORÇADO | I2: VALOR/M² | K2: ÁREA CONSTRUÍDA | L2: 10722.5 | M2: M²
A3: ='CUSTOS DIRETOS'!A3 -> 1.1. GERENCIAMENTO TÉCNICO E ADMINISTRATIVO | B3: 2786052.3 | C3: =B3/$B$25 -> 0.095597832 | D3: =B3/$L$2 -> 259.83235 | E3: =SUMIF('CUSTOS DIRETOS'!$A$3:$A$352,A3,'CUSTOS DIRETOS'!$E$3:$E$352) -> 2786052.3 | F3: =E3/$E$25 -> 0.092272313 | G3: =E3/$L$2 -> 259.83235 | H3: =E3-B3 -> 0 | I3: =G3-D3 -> 0
A4: 1.2.1. MOVIMENTAÇÃO DE TERRA | B4: 110350.11 | C4: =B4/$B$25 -> 0.003786444 | D4: =B4/$L$2 -> 10.291453 | E4: =SUMIF('CUSTOS DIRETOS'!$A$3:$A$352,A4,'CUSTOS DIRETOS'!$E$3:$E$352) -> 110350.11 | F4: =E4/$E$25 -> 0.0036547267 | G4: =E4/$L$2 -> 10.291453 | H4: =E4-B4 -> 0 | I4: =G4-D4 -> 0
A5: ='CUSTOS DIRETOS'!A42 -> 1.2.2. INFRAESTRUTURA | B5: 2370948.9 | C5: =B5/$B$25 -> 0.081354383 | D5: =B5/$L$2 -> 221.11904 | E5: =SUMIF('CUSTOS DIRETOS'!$A$3:$A$352,A5,'CUSTOS DIRETOS'!$E$3:$E$352) -> 2370948.9 | F5: =E5/$E$25 -> 0.078524345 | G5: =E5/$L$2 -> 221.11904 | H5: =E5-B5 -> 0 | I5: =G5-D5 -> 0
A6: ='CUSTOS DIRETOS'!A69 -> 1.2.3. SUPRAESTRUTURA | B6: 5880203.6 | C6: =B6/$B$25 -> 0.20176746 | D6: =B6/$L$2 -> 548.39857 | E6: =SUMIF('CUSTOS DIRETOS'!$A$3:$A$352,A6,'CUSTOS DIRETOS'!$E$3:$E$352) -> 5880203.6 | F6: =E6/$E$25 -> 0.19474867 | G6: =E6/$L$2 -> 548.39857 | H6: =E6-B6 -> 0 | I6: =G6-D6 -> 0
A7: ='CUSTOS DIRETOS'!A103 -> 1.2.4. PAREDES E PAINÉIS | B7: 1469000.4 | C7: =B7/$B$25 -> 0.050405821 | D7: =B7/$L$2 -> 137.00167 | E7: =SUMIF('CUSTOS DIRETOS'!$A$3:$A$352,A7,'CUSTOS DIRETOS'!$E$3:$E$352) -> 1669970.1 | F7: =E7/$E$25 -> 0.055308366 | G7: =E7/$L$2 -> 155.74447 | H7: =E7-B7 -> 200969.66 | I7: =G7-D7 -> 18.742799 | J7: aumento na quantidade de alvenaria
A8: ='CUSTOS DIRETOS'!A118 -> 1.2.5. IMPERMEABILIZAÇÃO E TRATAMENTOS | B8: 717784.17 | C8: =B8/$B$25 -> 0.024629333 | D8: =B8/$L$2 -> 66.941867 | E8: =SUMIF('CUSTOS DIRETOS'!$A$3:$A$352,A8,'CUSTOS DIRETOS'!$E$3:$E$352) -> 717784.17 | F8: =E8/$E$25 -> 0.023772563 | G8: =E8/$L$2 -> 66.941867 | H8: =E8-B8 -> 0 | I8: =G8-D8 -> 0
A9: ='CUSTOS DIRETOS'!A137 -> 1.2.6. SISTEMAS E INSTALAÇÕES HIDROSSANITÁRIAS E DRENAGEM | B9: 933172.45 | C9: =B9/$B$25 -> 0.032019952 | D9: =B9/$L$2 -> 87.029372 | E9: =SUMIF('CUSTOS DIRETOS'!$A$3:$A$352,A9,'CUSTOS DIRETOS'!$E$3:$E$352) -> 933172.45 | F9: =E9/$E$25 -> 0.030906088 | G9: =E9/$L$2 -> 87.029372 | H9: =E9-B9 -> 0 | I9: =G9-D9 -> 0
A10: ='CUSTOS DIRETOS'!A151 -> 1.2.7. SISTEMAS E INSTALAÇÕES ELÉTRICAS | B10: 1092655.5 | C10: =B10/$B$25 -> 0.037492295 | D10: =B10/$L$2 -> 101.90305 | E10: =SUMIF('CUSTOS DIRETOS'!$A$3:$A$352,A10,'CUSTOS DIRETOS'!$E$3:$E$352) -> 1092655.5 | F10: =E10/$E$25 -> 0.036188067 | G10: =E10/$L$2 -> 101.90305 | H10: =E10-B10 -> 0 | I10: =G10-D10 -> 0
A11: ='CUSTOS DIRETOS'!A167 -> 1.2.8. INSTALAÇÕES PREVENTIVAS | B11: 255923.68 | C11: =B11/$B$25 -> 0.0087815109 | D11: =B11/$L$2 -> 23.867911 | E11: =SUMIF('CUSTOS DIRETOS'!$A$3:$A$352,A11,'CUSTOS DIRETOS'!$E$3:$E$352) -> 255923.68 | F11: =E11/$E$25 -> 0.0084760324 | G11: =E11/$L$2 -> 23.867911 | H11: =E11-B11 -> 0 | I11: =G11-D11 -> 0
A12: ='CUSTOS DIRETOS'!A177 -> 1.2.9. INSTALAÇÃO DE GÁS | B12: 149949.8 | C12: =B12/$B$25 -> 0.0051452285 | D12: =B12/$L$2 -> 13.984593 | E12: =SUMIF('CUSTOS DIRETOS'!$A$3:$A$352,A12,'CUSTOS DIRETOS'!$E$3:$E$352) -> 149949.8 | F12: =E12/$E$25 -> 0.0049662437 | G12: =E12/$L$2 -> 13.984593 | H12: =E12-B12 -> 0 | I12: =G12-D12 -> 0
A13: ='CUSTOS DIRETOS'!A181 -> 1.2.10. INSTALAÇÕES DE COMUNICAÇÕES | B13: 151300.45 | C13: =B13/$B$25 -> 0.0051915735 | D13: =B13/$L$2 -> 14.110558 | E13: =SUMIF('CUSTOS DIRETOS'!$A$3:$A$352,A13,'CUSTOS DIRETOS'!$E$3:$E$352) -> 151300.45 | F13: =E13/$E$25 -> 0.0050109766 | G13: =E13/$L$2 -> 14.110558 | H13: =E13-B13 -> 0 | I13: =G13-D13 -> 0
A14: ='CUSTOS DIRETOS'!A187 -> 1.2.11. EQUIPAMENTOS E SISTEMA ESPECIAIS | B14: 1034052 | C14: =B14/$B$25 -> 0.035481433 | D14: =B14/$L$2 -> 96.437584 | E14: =SUMIF('CUSTOS DIRETOS'!$A$3:$A$352,A14,'CUSTOS DIRETOS'!$E$3:$E$352) -> 1034052 | F14: =E14/$E$25 -> 0.034247156 | G14: =E14/$L$2 -> 96.437584 | H14: =E14-B14 -> 0 | I14: =G14-D14 -> 0
A15: ='CUSTOS DIRETOS'!A197 -> 1.2.12. CLIMATIZAÇÃO E EXAUSTÃO | B15: 269762.89 | C15: =B15/$B$25 -> 0.0092563758 | D15: =B15/$L$2 -> 25.158581 | E15: =SUMIF('CUSTOS DIRETOS'!$A$3:$A$352,A15,'CUSTOS DIRETOS'!$E$3:$E$352) -> 269762.89 | F15: =E15/$E$25 -> 0.0089343784 | G15: =E15/$L$2 -> 25.158581 | H15: =E15-B15 -> 0 | I15: =G15-D15 -> 0
A16: ='CUSTOS DIRETOS'!A205 -> 1.2.13. REVESTIMENTOS INTERNOS DE PAREDE | B16: 2033021.2 | C16: =B16/$B$25 -> 0.069759068 | D16: =B16/$L$2 -> 189.60328 | E16: =SUMIF('CUSTOS DIRETOS'!$A$3:$A$352,A16,'CUSTOS DIRETOS'!$E$3:$E$352) -> 2179759.2 | F16: =E16/$E$25 -> 0.072192262 | G16: =E16/$L$2 -> 203.28833 | H16: =E16-B16 -> 146737.99 | I16: =G16-D16 -> 13.685054 | J16: aumento da área de chapisco e reboco das novas alvenarias porém havia duplicação do reboco externo que foi corrigido]
A17: ='CUSTOS DIRETOS'!A222 -> 1.2.14. REVESTIMENTOS E ACABAMENTOS INTERNOS EM TETO | B17: 568584.16 | C17: =B17/$B$25 -> 0.019509832 | D17: =B17/$L$2 -> 53.027201 | E17: =SUMIF('CUSTOS DIRETOS'!$A$3:$A$352,A17,'CUSTOS DIRETOS'!$E$3:$E$352) -> 568584.16 | F17: =E17/$E$25 -> 0.018831152 | G17: =E17/$L$2 -> 53.027201 | H17: =E17-B17 -> 0 | I17: =G17-D17 -> 0
A18: ='CUSTOS DIRETOS'!A227 -> 1.2.15. PISOS E PAVIMENTAÇÕES | B18: 2316031.9 | C18: =B18/$B$25 -> 0.079470017 | D18: =B18/$L$2 -> 215.99738 | E18: =SUMIF('CUSTOS DIRETOS'!$A$3:$A$352,A18,'CUSTOS DIRETOS'!$E$3:$E$352) -> 2316031.9 | F18: =E18/$E$25 -> 0.07670553 | G18: =E18/$L$2 -> 215.99738 | H18: =E18-B18 -> 0 | I18: =G18-D18 -> 0
A19: ='CUSTOS DIRETOS'!A253 -> 1.2.16. SISTEMAS DE PINTURA INTERNA | B19: 1570798.2 | C19: =B19/$B$25 -> 0.053898809 | D19: =B19/$L$2 -> 146.49552 | E19: =SUMIF('CUSTOS DIRETOS'!$A$3:$A$352,A19,'CUSTOS DIRETOS'!$E$3:$E$352) -> 2128847.1 | F19: =E19/$E$25 -> 0.070506085 | G19: =E19/$L$2 -> 198.54018 | H19: =E19-B19 -> 558048.86 | I19: =G19-D19 -> 52.04466 | J19: aumento na quantidade de alvenaria
A20: ='CUSTOS DIRETOS'!A275 -> 1.2.17. ESQUADRIAS, VIDROS E FERRAGENS | B20: 2263600.2 | C20: =B20/$B$25 -> 0.077670928 | D20: =B20/$L$2 -> 211.1075 | E20: =SUMIF('CUSTOS DIRETOS'!$A$3:$A$352,A20,'CUSTOS DIRETOS'!$E$3:$E$352) -> 2263600.2 | F20: =E20/$E$25 -> 0.074969024 | G20: =E20/$L$2 -> 211.1075 | H20: =E20-B20 -> 0 | I20: =G20-D20 -> 0
A21: ='CUSTOS DIRETOS'!A300 -> 1.2.18. LOUÇAS E METAIS | B21: 351077.93 | C21: =B21/$B$25 -> 0.012046539 | D21: =B21/$L$2 -> 32.742171 | E21: =SUMIF('CUSTOS DIRETOS'!$A$3:$A$352,A21,'CUSTOS DIRETOS'!$E$3:$E$352) -> 351077.93 | F21: =E21/$E$25 -> 0.011627482 | G21: =E21/$L$2 -> 32.742171 | H21: =E21-B21 -> 0 | I21: =G21-D21 -> 0
A22: ='CUSTOS DIRETOS'!A308 -> 1.2.19. REVESTIMENTO E ACABAMENTOS EM FACHADA | B22: 1072274.3 | C22: =B22/$B$25 -> 0.036792954 | D22: =B22/$L$2 -> 100.00226 | E22: =SUMIF('CUSTOS DIRETOS'!$A$3:$A$352,A22,'CUSTOS DIRETOS'!$E$3:$E$352) -> 1201333.9 | F22: =E22/$E$25 -> 0.039787428 | G22: =E22/$L$2 -> 112.0386 | H22: =E22-B22 -> 129059.62 | I22: =G22-D22 -> 12.036337 | J22: aumento na quantidade de alvenaria
A23: ='CUSTOS DIRETOS'!A329 -> 1.2.20. SERVIÇOS COMPLEMENTARES E FINAIS | B23: 1316232.1 | C23: =B23/$B$25 -> 0.045163882 | D23: =B23/$L$2 -> 122.75422 | E23: =SUMIF('CUSTOS DIRETOS'!$A$3:$A$352,A23,'CUSTOS DIRETOS'!$E$3:$E$352) -> 1316232.1 | F23: =E23/$E$25 -> 0.043592786 | G23: =E23/$L$2 -> 122.75422 | H23: =E23-B23 -> 0 | I23: =G23-D23 -> 0
A24: ='CUSTOS DIRETOS'!A352 -> 1.2.21. IMPREVISTOS E CONTINGÊNCIAS | B24: 430691.64 | C24: =B24/$B$25 -> 0.014778325 | D24: =B24/$L$2 -> 40.167092 | E24: =E30 -> 446213.89 | F24: =E24/$E$25 -> 0.014778325 | G24: =E24/$L$2 -> 41.614725 | H24: =E24-B24 -> 15522.242 | I24: =G24-D24 -> 1.4476327
A25: TOTAL | B25: =SUM(B3:B24) -> 29143468 | C25: =SUM(C3:C24) -> 1 | D25: =SUM(D3:D24) -> 2717.9732 | E25: =SUM(E3:E24) -> 30193806 | F25: =SUM(F3:F24) -> 1 | G25: =SUM(G3:G24) -> 2815.9297 | H25: =SUM(H3:H24) -> 1050338.4 | I25: =SUM(I3:I24) -> 97.956483
A26: CUB | B26: 2752.67 | C26: DEZ/23 | D26: =ROUNDDOWN(D25/B26,2)&" CUB" -> 0,98 CUB | G26: =ROUNDDOWN(G25/B26,2)&" CUB" -> 1,02 CUB | H26: =H25/B25 -> 0.036040268 | I26: =ROUNDDOWN(I25/B26,2)&" CUB" -> 0,03 CUB
E29: =SUM(E3:E23) -> 29747592
E30: =E29*1.5% -> 446213.89

Sheet CUSTOS DIRETOS
A1: Etapa | B1: Quant. | C1: Unidade | D1: Valor Unitário | E1: Valor Total
A2: 1. West Village SPE | E2: =SUM(E3,E32) -> 30193806
A3: 1.1. GERENCIAMENTO TÉCNICO E ADMINISTRATIVO | E3: ='CUSTOS INDIRETOS'!E4 -> 2786052.3
A4: 1.1.1. SERVIÇOS TÉCNICOS | E4: 0
A5: 1.1.1.1. ESTUDOS, PROJETOS E CONSULTORIAS | E5: 0
A6: 1.1.1.1.1. ESTUDOS | E6: 0
A7: 1.1.1.1.2. PROJETOS | E7: 0
A8: 1.1.1.1.3. CONSULTORIAS | E8: 0
A9: 1.1.1.1.4. ENSAIOS | E9: 0
A10: 1.1.1.2. TAXAS E DOCUMENTOS | E10: 0
A11: 1.1.1.2.1. LICENCIAMENTOS, TAXAS, IMPOSTOS, APROVAÇÕES E SEGUROS | E11: 0
A12: 1.1.1.2.2. DOCUMENTOS | E12: 0
A13: 1.1.2. SERVIÇOS INICIAIS | E13: 0
A14: 1.1.2.1. SEGURANÇA, MEIO AMBIENTE E SAÚDE | E14: 0
A15: 1.1.2.1.1. SEGURANÇA DO TRABALHO | E15: 0
... A31: 1.1.3.1.3. BALANCINS E ANDAIMES | E31: 0
A32: 1.2. GERENCIAMENTO EXECUTIVO | E32: =SUM(E33,E42,E69,E103,E118,E137,E151,E167,E177,E181,E187,E197,E205,E222,E227,E253,E275,E300,E308,E329,E352) -> 27407754
A33: 1.2.1. MOVIMENTAÇÃO DE TERRA | E33: =E34 -> 110350.11
A34: 1.2.1.1. MOVIMENTAÇÃO DE TERRA | E34: =SUM(E35,E38,E40) -> 110350.11
A35: 1.2.1.1.1. ESCAVAÇÃO E REATERRO DE VALAS | E35: =SUM(E36:E37) -> 75830.02
A36: Escavação mecanizada para blocos e baldrames | B36: =ESCAVAÇÕES!D19 -> 1010.6474 | C36: m3 | D36: 69.21 | E36: 69947.09 | F36: QUANT. ESCAVAÇÕES
A37: Reaterro mecanizado para blocos e baldrames com retroescavadeira | B37: =ESCAVAÇÕES!E19 -> 431.29909 | C37: m3 | D37: 13.64 | E37: 5882.93 | F37: QUANT. ESCAVAÇÕES
A38: 1.2.1.1.2. LASTRO DE ESTRUTURA DE CONCRETO | E38: =SUM(E39) -> 1051.49
A39: Lastro de concreto magro, aplicado em blocos e baldrames, espessura 10cm | B39: =ESCAVAÇÕES!H19 -> 37.337076 | C39: m2 | D39: 28.16 | E39: 1051.49 | F39: QUANT. ESCAVAÇÕES
A40: 1.2.1.1.3. MOVIMENTAÇÃO DE BOTA-FORA | E40: =SUM(E41) -> 33468.6
A41: Movimentação de terra para bota-fora de escavação de blocos e baldrames | B41: =ESCAVAÇÕES!F19 -> 557.81145 | C41: m3 | D41: 60 | E41: 33468.6 | F41: QUANT. ESCAVAÇÕES
A42: 1.2.2. INFRAESTRUTURA | E42: =SUM(E43,E54) -> 2370948.9
A43: 1.2.2.1. FUNDAÇÃO PROFUNDA | E43: =SUM(E44,E47,E50,E52) -> 1279618.1
A44: 1.2.2.1.1. PERFURAÇÃO | E44: =SUM(E45:E46) -> 468060
A45: Perfuração de estacas em hélice contínuadiâmetro 50cm | B45: 1827 | C45: m | D45: 100 | E45: 182700 | F45: QUANT. ESTACAS
A46: Perfuração de estacas em hélice contínua diâmetro 60cm | B46: 2378 | C46: m | D46: 120 | E46: 285360 | F46: QUANT. ESTACAS
A47: 1.2.2.1.2. ARMADURA | E47: =SUM(E48:E49) -> 65595.16
A48: Armação aço CA-50, diâmetro 6,3mm para infraestrutura, corte e dobra em obra | B48: 1453 | C48: kg | D48: 6.12 | E48: =B48*D48 -> 8892.36 | F48: QUANT. ESTACAS | G48: Alterados preços de aço e arame recozido de acordo com valores passados pela Kirchner
A49: Armação aço CA-50, diâmetro 16,0mm para (+) | B49: 9205 | C49: kg | D49: 6.16 | E49: =B49*D49 -> 56702.8 | F49: QUANT. ESTACAS | G49: Alterados preços de aço e arame recozido de acordo com valores passados pela Kirchner
A50: 1.2.2.1.3. CONCRETO | E50: =SUM(E51) -> 730012.9
A51: Concreto usinado bombeável para estacas fck 40MPa, com bombeamento | B51: 1237.31 | C51: m3 | D51: 590 | E51: =B51*D51 -> 730012.9 | F51: QUANT. ESTACAS | G51: Alterado valor de concreto para R$500 + R$40 bombeamento, considerando o desperdício na composição
A52: 1.2.2.1.4. MÃO DE OBRA | E52: =SUM(E53) -> 15950
A53: Arrasamento mecanizado de estacas (MÃO D (+) | B53: 145 | C53: un | D53: 110 | E53: =B53*D53 -> 15950 | F53: QUANT. ESTACAS
A54: 1.2.2.2. FUNDAÇÃO RASA | E54: =SUM(E55,E57,E65,E67) -> 1091330.8
A55: 1.2.2.2.1. FORMA | E55: =SUM(E56) -> 196335.24
A56: Fabricação, montagem e desmontagem de fôrma para bloco, vigas de transição e baldrames, em tábua de madeira | B56: 2402.83 | C56: m2 | D56: 81.71 | E56: =B56*D56 -> 196335.24 | F56: QUANT. FUNDAÇÃO RASA
A57: 1.2.2.2.2. ARMADURA | E57: =SUM(E58:E64) -> 288038.98
A58: Armação aço CA-60, diâmetro 5,0mm para infraestrutura, corte e dobra em obra | B58: =BALDRAMES!G15 -> 499 | C58: kg | D58: 7.97 | E58: =B58*D58 -> 3977.03 | F58: QUANT. FUNDAÇÃO RASA | G58: Alterados preços de aço e arame recozido de acordo com valores passados pela Kirchner
A59: Armação aço CA-50, diâmetro 6,3mm parainfraestrutura, corte e dobra em obra | B59: =BALDRAMES!H15 -> 3871 | C59: kg | D59: 6.12 | E59: =B59*D59 -> 23690.52 | F59: QUANT. FUNDAÇÃO RASA | G59: Alterados preços de aço e arame recozido de acordo com valores passados pela Kirchner
A60: Armação aço CA-50, diâmetro 8,0mm para infraestrutura, corte e dobra em obra (+) | B60: =BALDRAMES!I15 -> 5528 | C60: kg | D60: 6.6 | E60: =B60*D60 -> 36484.8 | F60: QUANT. FUNDAÇÃO RASA | G60: Alterados preços de aço e arame recozido de acordo com valores passados pela Kirchner
A61: Armação aço CA-50, diâmetro 10,0mm para infraestrutura, corte e dobra em obra | B61: =BALDRAMES!J15 -> 6589 | C61: kg | D61: 6.35 | E61: =B61*D61 -> 41840.15 | F61: QUANT. FUNDAÇÃO RASA | G61: Alterados preços de aço e arame recozido de acordo com valores passados pela Kirchner
A62: Armação aço CA-50, diâmetro 12,5mm para infraestrutura, corte e dobra em obra | B62: =BALDRAMES!K15 -> 7914 | C62: kg | D62: 6.16 | E62: =B62*D62 -> 48750.24 | F62: QUANT. FUNDAÇÃO RASA | G62: Alterados preços de aço e arame recozido de acordo com valores passados pela Kirchner
A63: Armação aço CA-50, diâmetro 16,0mm para infraestrutura, corte e dobra em obra | B63: =BALDRAMES!L15 -> 4237 | C63: kg | D63: 6.16 | E63: =B63*D63 -> 26099.92 | F63: QUANT. FUNDAÇÃO RASA | G63: Alterados preços de aço e arame recozido de acordo com valores passados pela Kirchner
A64: Armação aço CA-50, diâmetro 20,0mm para infraestrutura, corte e dobra em obra | B64: =BALDRAMES!M15 -> 17402 | C64: kg | D64: 6.16 | E64: =B64*D64 -> 107196.32 | F64: QUANT. FUNDAÇÃO RASA | G64: Alterados preços de aço e arame recozido de acordo com valores passados pela Kirchner
A65: 1.2.2.2.3. CONCRETO | E65: =SUM(E66) -> 318506.58
A66: Concreto usinado bombeável para blocos d (+) | B66: 561.74 | C66: m3 | D66: 567 | E66: =D66*B66 -> 318506.58 | F66: QUANT. FUNDAÇÃO RASA
A67: 1.2.2.2.4. MÃO DE OBRA | E67: =SUM(E68) -> 288450
A68: Mão de obra para execução de infraestrutura | B68: 1153.8 | C68: m2 | D68: 250 | E68: =B68*D68 -> 288450 | F68: Área de laje do térreo
A69: 1.2.3. SUPRAESTRUTURA | E69: =E70 -> 5880203.6
A70: 1.2.3.1. SUPRAESTRUTURA | E70: =SUM(E71,E80,E88,E90,E100) -> 5880203.6
A71: 1.2.3.1.1. FORMA | E71: =SUM(E72:E79) -> 192047.97
A72: Fabricação de forma para pilares e estruturas similares, em chapa de madeira compensada plastificada 1,10x2,20m | B72: 586.11 | C72: m2 | D72: 119.01 | E72: =B72*D72 -> 69752.951 | F72: QUANT. SUPRAESTRUTURA | G72: Valor do madeirite plastificado 1,10x2,20m alterado para R$118, conforme passado pela Kircnher
A73: Fabricação de forma para vigas e estruturas similares, em chapa de madeira compensada plastificada 1,10x2,20m | B73: 512.45 | C73: m2 | D73: 76.25 | E73: =B73*D73 -> 39074.312 | F73: QUANT. SUPRAESTRUTURA | G73: Considerado 14 utilizações das formas, como são 20 pavimentos, para o cálculo da fabricação das formas: soma das fromas dividido por 20, multiplicado por 2 fabricações para atender todos os pavimentos
A74: Fabricação de forma para lajes e estruturas similares, em chapa de madeira compensada plastificada 1,10x2,20m | B74: 180.15 | C74: m2 | D74: 51.2 | E74: =B74*D74 -> 9223.68 | F74: QUANT. SUPRAESTRUTURA
A75: Fabricação de forma para escadas, rampas e estruturas similares, em chapa de madeira compensada plastificada 1,10x2,20m | B75: =40.11+116.33 -> 156.44 | C75: m2 | D75: 121.43 | E75: =B75*D75 -> 18996.509 | F75: QUANT. SUPRAESTRUTURA
A76: Montagem e desmontagem de forma para pilar, em chapa de madeira compensada | B76: 5861.11 | C76: m2 | D76: 2.81 | E76: 16469.72 | F76: QUANT. SUPRAESTRUTURA
A77: Montagem e desmontagem de forma para vigas, em chapa de madeira compensada | B77: 5124.5 | C77: m2 | D77: 4.57 | E77: 23418.97 | F77: QUANT. SUPRAESTRUTURA
A78: Montagem e desmontagem de forma para lajes, em chapa de madeira compensada | B78: 1801.52 | C78: m2 | D78: 6.59 | E78: 11872.02 | F78: QUANT. SUPRAESTRUTURA
A79: Montagem e desmontagem de forma para escadas e rampas, em chapa de madeira compensada | B79: 590.13 | C79: m2 | D79: 5.49 | E79: 3239.81 | F79: QUANT. SUPRAESTRUTURA
A80: 1.2.3.1.2. ARMADURA | E80: =SUM(E81:E87) -> 1362790.9
A81: Armação aço CA-60, diâmetro 5,0mm para supraestrutura, corte e dobra em obra | B81: 10724 | C81: kg | D81: 7.98 | E81: =B81*D81 -> 85577.52 | F81: QUANT. SUPRAESTRUTURA | G81: Valores de aço e arame recozido atualizados de acordo com preços disponibilizados pela Kirchner
A82: Armação aço CA-50, diâmetro 6,3mm para supraestrutura, corte e dobra em obra | B82: 9113 | C82: kg | D82: 6.87 | E82: =B82*D82 -> 62606.31 | F82: QUANT. SUPRAESTRUTURA
A83: Armação aço CA-50, diâmetro 8,0mm para supraestrutura, corte e dobra em obra (+) | B83: 23404 | C83: kg | D83: 6.69 | E83: =B83*D83 -> 156572.76 | F83: QUANT. SUPRAESTRUTURA
A84: Armação aço CA-50, diâmetro 10,0mm para supraestrutura, corte e dobra em obra | B84: 18027 | C84: kg | D84: 6.41 | E84: =B84*D84 -> 115553.07 | F84: QUANT. SUPRAESTRUTURA
A85: Armação aço CA-50, diâmetro 12,5 mm para supraestrutura, corte e dobra em obra | B85: 71118 | C85: kg | D85: 6.2 | E85: =B85*D85 -> 440931.6 | F85: QUANT. SUPRAESTRUTURA
A86: Armação aço CA-50, diâmetro 16,0 mm para supraestrutura, corte e dobra em obra | B86: 48396 | C86: kg | D86: 6.18 | E86: =B86*D86 -> 299087.28 | F86: QUANT. SUPRAESTRUTURA
A87: Armação aço CA-50, diâmetro 20,0 mm para supraestrutura, corte e dobra em obra | B87: 32814 | C87: kg | D87: 6.17 | E87: =B87*D87 -> 202462.38 | F87: QUANT. SUPRAESTRUTURA
A88: 1.2.3.1.3. CONCRETO | E88: =SUM(E89) -> 1471121.2
A89: Concreto usinado bombeável para supraest fck 35MPa, com bombeamento | B89: 2594.57 | C89: m3 | D89: 567 | E89: =D89*B89 -> 1471121.2 | F89: QUANT. SUPRAESTRUTURA
A90: 1.2.3.1.4. COMPLEMENTARES | E90: =SUM(E91:E99) -> 889802.41
A91: Tela soldada nervurada Q-92 (COMPOSIÇÃO) | B91: 860 | C91: un | D91: 211.28 | E91: =B91*D91 -> 181700.8 | F91: QUANT. SUPRAESTRUTURA | G91: Alterado o valor da tela soldada nervurada Q-92 de 277,25 para R$139. Considerado desperdício na composição
A92: Acabamento polido para piso de concreto armado - material e mão de obra | B92: 2625.09 | C92: m2 | D92: 49.4 | E92: =B92*D92 -> 129679.45 | F92: Garagens e rampas
A93: Piso de concreto polido sobre o solo (térreo) - espessura 10cm | B93: 337.78 | C93: m2 | D93: 572 | E93: =B93*D93 -> 193210.16 | F93: Garagem e rampa do térreo
A94: Cubetas 540x540x180 - Compra | B94: 671 | C94: un | D94: 116.72 | E94: =B94*D94 -> 78319.12 | F94: Item adicionado conforme custos passado pela Kirchner
A95: Cubetas 270x540x180 - Compra | B95: 123 | C95: un | D95: 107.56 | E95: =B95*D95 -> 13229.88 | F95: Item adicionado conforme custos passado pela Kirchner
A96: Cubetas 540x540x180 - Locação (6 meses) | B96: 492 | C96: un | D96: =6*6 -> 36 | E96: =B96*D96 -> 17712 | F96: Item adicionado conforme custos passado pela Kirchner | G96: R$6 por cubeta/mês * 6 meses de locação
A97: Cubetas 270x540x180 - Locação (6 meses) | B97: 88 | C97: un | D97: =3*6 -> 18 | E97: =B97*D97 -> 1584 | F97: Item adicionado conforme custos passado pela Kirchner | G97: R$3 por cubeta/mês * 6 meses de locação
A98: Escoras metálicas - Compra | B98: 1105 | C98: un | D98: 125 | E98: =B98*D98 -> 138125 | F98: Item adicionado conforme custos passado pela Kirchner
A99: Escoras metálicas - Locação (6 meses) | B99: 2523 | C99: un | D99: =9*6 -> 54 | E99: =B99*D99 -> 136242 | F99: Item adicionado conforme custos passado pela Kirchner | G99: R$9 por escora/mês * 6 meses de locação
A100: 1.2.3.1.5. MÃO DE OBRA | E100: =SUM(E101:E102) -> 1964441.1
A101: Mão de obra para execução de supraestrutura | B101: 8300.45 | C101: m2 | D101: 188 | E101: =B101*D101 -> 1560484.6 | F101: Áreas de lajes (Exceto G1 e Lazer) | G101: Mão de obra alterada de R$220/m2 para R$188/m2
A102: Mão de obra para execução de supraestrutura (Lajes G1 e Lazer) | B102: =825.55+827.3 -> 1652.85 | C102: m2 | D102: =188*1.3 -> 244.4 | E102: =B102*D102 -> 403956.54 | F102: Áreas de lajes - G1 e Lazer | G102: Adicionado as lajes G1 e Lazer separadas, valor R$188*1,3
A103: 1.2.4. PAREDES E PAINÉIS | E103: =SUM(E104) -> 1669970.1
A104: 1.2.4.1. PAREDES E PAINÉIS | E104: =SUM(E105,E108,E110,E115) -> 1669970.1
A105: 1.2.4.1.1. ALVENARIA DE VEDAÇÃO COM BLOCOS CERÂMICOS | E105: =SUM(E106:E107) -> 471832.79
A106: Alvenaria de vedação de blocos cerâmicos 09x19x19 cm (espessura 09cm) | B106: =ALVENARIA!D48+ALVENARIA!F20 -> 11728.941 | C106: m2 | D106: 31.77 | E106: =B106*D106 -> 372628.44 | F106: ALVENARIA | G106: Foi refeita a contagem da alvenaria em todos os pavimentos
A107: Alvenaria de vedação de blocos cerâmicos 14x19x19cm (espessura 14cm) | B107: =ALVENARIA!C48 -> 2101.3419 | C107: m2 | D107: 47.21 | E107: =B107*D107 -> 99204.35 | F107: ALVENARIA | G107: Foi refeita a contagem da alvenaria em todos os pavimentos
A108: 1.2.4.1.2. ALVENARIA DE VEDAÇÃO COM BLOCO DE SICAL | E108: =SUM(E109) -> 124697.14
A109: Alvenaria de vedação com blocos sical de 12,5x30x60cm (espessura 12,5cm) | B109: =ALVENARIA!E48 -> 851.46563 | C109: m2 | D109: 146.45 | E109: =B109*D109 -> 124697.14 | F109: ALVENARIA | G109: Foi refeita a contagem da alvenaria em todos os pavimentos
A110: 1.2.4.1.3. SERVIÇOS COMPLEMENTARES PARA ALVENARIA DE VEDAÇÃO | E110: =SUM(E111:E114) -> 541491.35
A111: Assentamento de tijolos refratários de 5x11,4x22,9 cm com argamassa refratária | B111: =ALVENARIA!F48 -> 694.612 | C111: m2 | D111: 479.44 | E111: =B111*D111 -> 333024.78 | F111: CHURRASQUEIRAS
A112: Encunhamento de alvenaria de vedação com (+) | B112: =ALVENARIA!G48 -> 6599.7529 | C112: m | D112: 1.83 | E112: =B112*D112 -> 12077.548 | F112: ALVENARIA | G112: Foi refeita a contagem da alvenaria em todos os pavimentos
A113: Verga/contraverga de concreto, moldada i (+) | B113: 3498.42 | C113: m | D113: 42.56 | E113: =B113*D113 -> 148892.76 | F113: VERGAS
A114: Tela soldada para ligação alvenaria/estr (+) | B114: =ROUNDUP((B106+B107+B109)/2,0) -> 7341 | C114: un | D114: 6.47 | E114: =B114*D114 -> 47496.27
A115: 1.2.4.1.5. MÃO DE OBRA | E115: =SUM(E116:E117) -> 531948.8
...

Sheet CUSTOS INDIRETOS
A1: Etapa | B1: Quant. | C1: Unidade | D1: Valor Unitário | E1: Valor Total
A3: 1. West Village SPE | E3: ='CUSTOS DIRETOS'!E2 -> 30193806
A4: 1.1. GERENCIAMENTO TÉCNICO E ADMINISTRATIVO | E4: =SUM(E5,E38,E83) -> 2786052.3
A5: 1.1.1. SERVIÇOS TÉCNICOS | E5: =SUM(E6,E25) -> 800277.37
A6: 1.1.1.1. ESTUDOS, PROJETOS E CONSULTORIAS | E6: =SUM(E7,E11,E20,E22) -> 540822.79
A7: 1.1.1.1.1. ESTUDOS | E7: =SUM(E8:E10) -> 19900
A8: Levantamento topográfico (COMPOSIÇÃO) | B8: 1 | C8: vb | D8: 7400 | E8: =B8*D8 -> 7400 | F8: Formulário de custos indiretos
A9: Sondagem do terreno (COMPOSIÇÃO) | B9: 1 | C9: vb | D9: 9500 | E9: =B9*D9 -> 9500 | F9: Formulário de custos indiretos
A10: Estudo ambiental (COMPOSIÇÃO) | B10: 1 | C10: vb | D10: 3000 | E10: =B10*D10 -> 3000 | F10: Formulário de custos indiretos
A11: 1.1.1.1.2. PROJETOS | E11: =SUM(E12:E19) -> 466031.66
A12: Projeto Arquitetônico (COMPOSIÇÃO) | B12: 1 | C12: vb | D12: 160000 | E12: =B12*D12 -> 160000 | F12: Formulário de custos indiretos
A13: Projeto Estrutural (COMPOSIÇÃO) | B13: 1 | C13: vb | D13: 117000 | E13: =B13*D13 -> 117000 | F13: Formulário de custos indiretos
A14: Projeto Elétrico (COMPOSIÇÃO) | B14: 1 | C14: vb | D14: 16000 | E14: =B14*D14 -> 16000 | F14: Formulário de custos indiretos
A15: Projeto Hidrossanitário (COMPOSIÇÃO) | B15: 1 | C15: vb | D15: 21500 | E15: =B15*D15 -> 21500 | F15: Formulário de custos indiretos
A16: Projeto Preventivo (COMPOSIÇÃO) | B16: 1 | C16: vb | D16: 23479.71 | E16: =B16*D16 -> 23479.71 | F16: Valor estimado por índices históricos
A17: Projeto Arquitetônico Executivo | B17: 1 | C17: vb | D17: 89165.06 | E17: =B17*D17 -> 89165.06 | F17: Valor estimado por índices históricos
A18: Projeto Interiores/ Ambientação | B18: 1 | C18: vb | D18: 33450 | E18: =B18*D18 -> 33450 | F18: Formulário de custos indiretos
A19: Projeto Telefonia | B19: 1 | C19: vb | D19: 5436.89 | E19: =B19*D19 -> 5436.89 | F19: Valor estimado por índices históricos
A20: 1.1.1.1.3. CONSULTORIAS | E20: =SUM(E21) -> 24972.29
A21: Consultoria de Orçamento e Planejamento | B21: 1 | C21: vb | D21: 24972.29 | E21: =D21*B21 -> 24972.29 | F21: Valor estimado por índices históricos
A22: 1.1.1.1.4. ENSAIOS | E22: =SUM(E23:E24) -> 29918.842
A23: Laudo preventivo de danos a vizinhança ( (+) | B23: 1 | C23: vb | D23: 11102.4 | E23: =B23*D23 -> 11102.4 | F23: Valor estimado por índices históricos
A24: Controle tecnológico de concreto (COMPOS (+) | B24: 1 | C24: vb | D24: =SUM('CUSTOS DIRETOS'!B51,'CUSTOS DIRETOS'!B66,'CUSTOS DIRETOS'!B89,'CUSTOS DIRETOS'!B93*0.1)*4.25 -> 18816.442 | E24: =B24*D24 -> 18816.442 | F24: Valor estimado por índices históricos
A25: 1.1.1.2. TAXAS E DOCUMENTOS | E25: =SUM(E26,E35) -> 259454.58
A26: 1.1.1.2.1. LICENCIAMENTOS, TAXAS, IMPOSTOS, APROVAÇÕES E SEGUROS | E26: =SUM(E27:E34) -> 241395.49
A27: Despesas cartoriais e jurídicas (COMPOSI (+) | B27: 1 | C27: vb | D27: 50000 | E27: =B27*D27 -> 50000 | F27: Valor estimado por índices históricos
A28: Taxas de ART (COMPOSIÇÃO) | B28: 1 | C28: vb | D28: 2594.62 | E28: =B28*D28 -> 2594.62 | F28: Valor estimado por índices históricos
A29: IPTU (COMPOSIÇÃO) | B29: 1 | C29: vb | D29: 26706.76 | E29: =B29*D29 -> 26706.76 | F29: Valor estimado por índices históricos
A30: Taxas de alvarás (+) | B30: 1 | C30: vb | D30: 23117.71 | E30: =B30*D30 -> 23117.71 | F30: Formulário de custos indiretos
A31: Taxa de aprovação ambiental (COMPOSIÇÃO) | B31: 1 | C31: vb | D31: =0.1*Resumo!L2 -> 1072.25 | E31: =B31*D31 -> 1072.25 | F31: Valor estimado por índices históricos
A32: Despesas de seguros (COMPOSIÇÃO) | B32: 1 | C32: vb | D32: =2850.95*7 -> 19956.65 | E32: =B32*D32 -> 19956.65 | F32: Formulário de custos indiretos
A33: Incorporação (COMPOSIÇÃO) | B33: 1 | C33: vb | D33: =4*Resumo!L2 -> 42890 | E33: =B33*D33 -> 42890 | F33: Valor estimado por índices históricos
A34: Taxa de aprovação de projetos | B34: 1 | C34: vb | D34: =7*Resumo!L2 -> 75057.5 | E34: =B34*D34 -> 75057.5 | F34: Valor estimado por índices históricos
A35: 1.1.1.2.2. DOCUMENTOS | E35: =SUM(E36:E37) -> 18059.09
A36: Laudo técnico de vistoria de entrega (CO (+) | B36: 1 | C36: vb | D36: 6264.34 | E36: =B36*D36 -> 6264.34 | F36: Valor estimado por índices históricos
A37: Certidão INSS | B37: 1 | C37: vb | D37: =1.1*Resumo!L2 -> 11794.75 | E37: =B37*D37 -> 11794.75 | F37: Valor estimado por índices históricos
A38: 1.1.2. SERVIÇOS INICIAIS | E38: =SUM(E39,E57,E79) -> 1288278.5
A39: 1.1.2.1. SEGURANÇA, MEIO AMBIENTE E SAÚDE | E39: =SUM(E40,E44,E54) -> 641275.51
A40: 1.1.2.1.1. SEGURANÇA DO TRABALHO | E40: =SUM(E41:E43) -> 156497.8
A41: Serviço de segurança do trabalho terceir (+) | B41: 35 | C41: mes | D41: 3337.8 | E41: =B41*D41 -> 116823 | F41: Valor estimado por índices históricos
A42: Uniforme e EPI's (COMPOSIÇÃO) | B42: 1 | C42: vb | D42: =37000 -> 37000 | E42: =B42*D42 -> 37000 | F42: Valor estimado por índices históricos
A43: Projeto de segurança do trabalho e PCMSO | B43: 1 | C43: vb | D43: 2674.8 | E43: =B43*D43 -> 2674.8 | F43: Formulário de custos indiretos
A44: 1.1.2.1.2. EQUIPAMENTOS DE PROTEÇÃO | E44: =SUM(E45:E53) -> 446128.68
A45: Bandeja de proteção primária (COMPOSIÇÃO (+) | B45: 212.44 | C45: m | D45: 313.56 | E45: =B45*D45 -> 66612.686 | F45: EPC's
A46: Bandeja de proteção secundária (COMPOSIÇ (+) | B46: 188.88 | C46: m | D46: 310.48 | E46: =B46*D46 -> 58643.462 | F46: EPC's
A47: Bandeja de proteção secundária (COMPOSIÇ (+) | B47: 188.88 | C47: m | D47: 310.48 | E47: =B47*D47 -> 58643.462 | F47: EPC's
A48: Guarda-corpo de laje, após deforma (COMP (+) | B48: 472 | C48: m | D48: 146.99 | E48: =B48*D48 -> 69379.28 | F48: EPC's
A49: Guarda-corpo de vaos, fixado em forma de (+) | B49: 441.75 | C49: m | D49: 17.83 | E49: =B49*D49 -> 7876.4025 | F49: EPC's
A50: Fechamento removível de vãos de porta de (+) | B50: 105.6 | C50: m2 | D50: 66.89 | E50: =B50*D50 -> 7063.584 | F50: EPC's
A51: Varal de segurança com cabo de aço (COMP (+) | B51: 472 | C51: m | D51: 95.67 | E51: =B51*D51 -> 45156.24 | F51: EPC's
A52: Tela fachadeira (COMPOSIÇÃO) | B52: 6331.02 | C52: m2 | D52: 12.43 | E52: =B52*D52 -> 78694.579 | F52: EPC's
A53: Rede de proteção tipo SLQA | B53: 1018.06 | C53: m2 | D53: 53.1 | E53: =B53*D53 -> 54058.986 | F53: EPC's
A54: 1.1.2.1.3. MEIO AMBIENTE | E54: =SUM(E55:E56) -> 38649.03
A55: Plano de gerenciamento de riscos (PGR) ( (+) | B55: 1 | C55: vb | D55: =7149.03 -> 7149.03 | E55: =B55*D55 -> 7149.03 | F55: Valor estimado por índices históricos
A56: Consumo de Caçamba para retirada de entulho | B56: 35 | C56: mes | D56: 900 | E56: =B56*D56 -> 31500 | F56: Considerando 3 caçambas por mês a R$300/ cada (preço unitário segundo formulário de indiretos)
A57: 1.1.2.2. ADMINISTRAÇÃO E CANTEIRO DE OBRA | E57: =SUM(E58,E60,E62,E72) -> 624280.01
A58: 1.1.2.2.1. EQUIPE DE GESTÃO E APOIO | E58: =SUM(E59:E59) -> 175000
A59: Engenheiro Civil (COMPOSIÇÃO) | B59: 35 | C59: mes | D59: 5000 | E59: =D59*B59 -> 175000 | F59: Formulário de custos indiretos
A60: 1.1.2.2.2. OPERAÇÃO INICIAL DE CANTEIRO | E60: =SUM(E61) -> 4206.38
A61: Sinalização geral da obra (COMPOSIÇÃO) | B61: 1 | C61: vb | D61: 4206.38 | E61: =B61*D61 -> 4206.38 | F61: Formulário de custos indiretos
A62: 1.1.2.2.3. DESPESAS DE CONSUMO E MANUTENÇÃO | E62: =SUM(E63:E71) -> 206718.72
A63: Despesas de consumo - Água (COMPOSIÇÃO) | B63: 35 | C63: mes | D63: 1136.52 | E63: =B63*D63 -> 39778.2 | F63: Valor estimado por índices históricos
A64: Despesas de consumo - Luz (COMPOSIÇÃO) | B64: 35 | C64: mes | D64: 2132 | E64: =B64*D64 -> 74620 | F64: Valor estimado por índices históricos
A65: Despesas de consumo - Internet (COMPOSIÇ (+) | B65: 35 | C65: mes | D65: 366.98 | E65: =B65*D65 -> 12844.3 | F65: Valor estimado por índices históricos
A66: Segurança patrimonial (COMPOSIÇÃO) | B66: 35 | C66: mes | D66: 530.51 | E66: =B66*D66 -> 18567.85 | F66: Valor estimado por índices históricos
A67: Despesas de consumo - Coleta de Lixo (CO (+) | B67: 35 | C67: mes | D67: 70 | E67: =B67*D67 -> 2450 | F67: Valor estimado por índices históricos
A68: Material de Higiene e Limpeza | B68: 35 | C68: mês | D68: 217.5 | E68: =B68*D68 -> 7612.5 | F68: Formulário de custos indiretos
A69: Material de expediente/ escritório | B69: 35 | C69: mes | D69: =387.59 -> 387.59 | E69: =B69*D69 -> 13565.65 | F69: Valor estimado por índices históricos
A70: Plotagens e cópias (COMPOSIÇÃO) | B70: 1 | C70: vb | D70: 7530.22 | E70: =B70*D70 -> 7530.22 | F70: Valor estimado por índices históricos
A71: Manutenção provisória de canteiro | B71: 35 | C71: mês | D71: =850 -> 850 | E71: =B71*D71 -> 29750 | F71: Valor estimado por índices históricos
A72: 1.1.2.2.4. INSTALAÇÕES PROVISÓRIAS | E72: =SUM(E73:E78) -> 238354.91
A73: Instalações provisórias rede de água (CO (+) | B73: 1 | C73: vb | D73: 12916.98 | E73: =B73*D73 -> 12916.98 | F73: Valor estimado por índices históricos
A74: Instalações provisórias rede elétrica (C (+) | B74: 1 | C74: vb | D74: 10960.93 | E74: =B74*D74 -> 10960.93 | F74: Valor estimado por índices históricos
A75: Instalações provisórias de canteiro (COM (+) | B75: 1 | C75: vb | D75: =12*Resumo!L2 -> 128670 | E75: =B75*D75 -> 128670 | F75: Valor estimado por índices históricos
A76: Locação de banheiro químico (COMPOSIÇÃO) | B76: 35 | C76: mes | D76: 1226.28 | E76: =B76*D76 -> 42919.8 | F76: Valor estimado por índices históricos
A77: Tapume em telha metálica (COMPOSIÇÃO) | B77: 259.6 | C77: m2 | D77: 100.49 | E77: =B77*D77 -> 26087.204 | F77: Valor estimado por índices históricos
A78: Esgotamento de sistema sanitário temporário | B78: 35 | C78: mes | D78: 480 | E78: =B78*D78 -> 16800 | F78: Formulário de custos indiretos
A79: 1.1.2.3. SERVIÇOS PRELIMINARES | E79: =SUM(E80) -> 22723
A80: 1.1.2.3.2. LIMPEZA DO TERRENO | E80: =SUM(E81:E82) -> 22723
A81: Limpeza mecanizada de camada vegetal (CO (+) | B81: 769.2 | C81: m2 | D81: 2.5 | E81: 1923 | F81: Valor estimado por índices históricos
A82: Remoção de concreto do solo | B82: 1 | C82: vb | D82: 20800 | E82: =B82*D82 -> 20800 | F82: Formulário de custos indiretos
A83: 1.1.3. EQUIPAMENTOS | E83: =SUM(E84) -> 697496.45
A84: 1.1.3.1. EQUIPAMENTOS | E84: =SUM(E85,E96,E99) -> 697496.45
A85: 1.1.3.1.1. EQUIPAMENTOS DE CARGA E TRANSPORTE | E85: =SUM(E86:E95) -> 516190.91
A86: Aquisição - Elevador Cremalheira | B86: 1 | C86: vb | D86: 287500 | E86: =B86*D86 -> 287500 | F86: Formulário de custos indiretos
A87: Aquisição - Mini Grua | B87: 1 | C87: vb | D87: 85000 | E87: =B87*D87 -> 85000 | F87: Formulário de custos indiretos
A88: Manutenção de Elevador Cremalheira (COMP (+) | B88: 18 | C88: mes | D88: 2652.63 | E88: =B88*D88 -> 47747.34 | F88: Valor estimado por índices históricos
A89: Montagem de Elevador Cremalheira | B89: 1 | C89: vb | D89: 8035.34 | E89: =B89*D89 -> 8035.34 | F89: Valor estimado por índices históricos
A90: Desmontagem de Elevador Cremalheira | B90: 1 | C90: vb | D90: 5739.53 | E90: =B90*D90 -> 5739.53 | F90: Valor estimado por índices históricos
A91: Manutenção de Mini grua | B91: 15 | C91: mês | D91: 1286.18 | E91: =B91*D91 -> 19292.7 | F91: Valor estimado por índices históricos
A92: Mobilização/ desmobilização de Elevador Cremalheira | B92: 1 | C92: vb | D92: 20120 | E92: =B92*D92 -> 20120 | F92: Valor estimado por índices históricos
A93: Montagem de Mini Grua | B93: 1 | C93: vb | D93: 18000 | E93: =B93*D93 -> 18000 | F93: Valor estimado por índices históricos
A94: Desmontagem de Mini Grua | B94: 1 | C94: vb | D94: 15000 | E94: =B94*D94 -> 15000 | F94: Valor estimado por índices históricos
A95: Mobilização/ desmobilização de Mini Grua | B95: 1 | C95: vb | D95: 9756 | E95: =B95*D95 -> 9756 | F95: Valor estimado por índices históricos
A96: 1.1.3.1.2. EQUIPAMENTOS DE OBRA | E96: =SUM(E97:E98) -> 69700
A97: Equipamentos para apoio ao canteiro de obra | B97: 1 | C97: vb | D97: 59200 | E97: =B97*D97 -> 59200 | F97: Valor estimado por índices históricos
A98: Manutenção para equipamentos próprios | B98: 35 | C98: mes | D98: 300 | E98: =B98*D98 -> 10500 | F98: Valor estimado por índices históricos
A99: 1.1.3.1.3. BALANCINS E ANDAIMES | E99: =SUM(E100:E103) -> 111605.54
A100: Andaime modular torre - locação (COMPOSI (+) | B100: 5 | C100: mes | D100: 1912.78 | E100: =B100*D100 -> 9563.9 | F100: Valor estimado por índices históricos
A101: Balancim - Locação (COMPOSIÇÃO) | B101: 9 | C101: mes | D101: 5737.96 | E101: =B101*D101 -> 51641.64 | F101: Valor estimado por índices históricos
...

Sheet CUSTOS DISPONIBILIZADOS

Sheet ESCAVAÇÕES
A1: Obra | B1: ='[7]RESUMO INFRA'!B1 -> WEST VILLAGE
A2: Empresa | B2: ='[7]RESUMO INFRA'!B2 -> KIRCHNER
A3: Revisão | B3: ='[7]RESUMO INFRA'!B3 -> 0
A4: QUANTIFICAÇÃO
A6: Quantitativo escavação
A9: RESUMO
B11: LOCAL | D11: Volume de escavação (m³) | E11: Volume de reaterro (m³) | F11: Volume de bota-fora (m³) | G11: Apiloamento de Vala (m²) | H11: Volume de lastro (m³)
C12: BLOCOS | D12: =SUM([7]BLOCOS_FUNDAÇÃO!AD30,[7]BLOCOS_FUNDAÇÃO!AF66) -> 406.40948 | E12: =SUM([7]BLOCOS_FUNDAÇÃO!AE30,[7]BLOCOS_FUNDAÇÃO!AG66) -> 94.42517 | F12: =SUM([7]BLOCOS_FUNDAÇÃO!AF30,[7]BLOCOS_FUNDAÇÃO!AH66) -> 311.98431 | G12: =SUM([7]BLOCOS_FUNDAÇÃO!AG30,[7]BLOCOS_FUNDAÇÃO!AI66) -> 217.8856 | H12: =SUM([7]BLOCOS_FUNDAÇÃO!AH30,[7]BLOCOS_FUNDAÇÃO!AJ66) -> 21.78856
C13: BALDRAMES | D13: ='[7]VIGAS - TÉRREO (BALDRAME)'!K71 -> 181.31761 | E13: ='[7]VIGAS - TÉRREO (BALDRAME)'!L71 -> 83.13489 | F13: ='[7]VIGAS - TÉRREO (BALDRAME)'!M71 -> 98.18272 | G13: ='[7]VIGAS - TÉRREO (BALDRAME)'!N71 -> 108.56386 | H13: ='[7]VIGAS - TÉRREO (BALDRAME)'!O71 -> 10.856386
C14: RESER. INFERIOR 01 | D14: ='[7]ESCAVAÇÃO - RESER. INFERIOR'!AD16 -> 125.1354 | E14: ='[7]ESCAVAÇÃO - RESER. INFERIOR'!AE16 -> 80.416638 | F14: ='[7]ESCAVAÇÃO - RESER. INFERIOR'!AF16 -> 44.718762 | G14: ='[7]ESCAVAÇÃO - RESER. INFERIOR'!AG16 -> 17.6754 | H14: ='[7]ESCAVAÇÃO - RESER. INFERIOR'!AH16 -> 1.76754
C15: RESER. INFERIOR 02 | D15: ='[7]ESCAVAÇÃO - RESER. INFERIOR'!AD17 -> 111.23006 | E15: ='[7]ESCAVAÇÃO - RESER. INFERIOR'!AE17 -> 72.910937 | F15: ='[7]ESCAVAÇÃO - RESER. INFERIOR'!AF17 -> 38.319127 | G15: ='[7]ESCAVAÇÃO - RESER. INFERIOR'!AG17 -> 15.1459 | H15: ='[7]ESCAVAÇÃO - RESER. INFERIOR'!AH17 -> 1.51459
C16: ='[7]ESCAVAÇÃO - RESER. INFERIOR'!C18 -> RESER. RETARDADO | D16: ='[7]ESCAVAÇÃO - RESER. INFERIOR'!AD18 -> 31.233897 | E16: ='[7]ESCAVAÇÃO - RESER. INFERIOR'!AE18 -> 18.840897 | F16: ='[7]ESCAVAÇÃO - RESER. INFERIOR'!AF18 -> 12.393 | G16: ='[7]ESCAVAÇÃO - RESER. INFERIOR'!AG18 -> 8.1 | H16: ='[7]ESCAVAÇÃO - RESER. INFERIOR'!AH18 -> 0.81
C17: ='[7]ESCAVAÇÃO - RESER. INFERIOR'!C19 -> RESER. PLUVIAL | D17: ='[7]ESCAVAÇÃO - RESER. INFERIOR'!AD19 -> 26.065167 | E17: ='[7]ESCAVAÇÃO - RESER. INFERIOR'!AE19 -> 16.885167 | F17: ='[7]ESCAVAÇÃO - RESER. INFERIOR'!AF19 -> 9.18 | G17: ='[7]ESCAVAÇÃO - RESER. INFERIOR'!AG19 -> 6 | H17: ='[7]ESCAVAÇÃO - RESER. INFERIOR'!AH19 -> 0.6
C18: TRATAMENTO DE ESGOTO | D18: ='[7]ESCAVAÇÃO - TRATAMENTO DE ESGOT'!J22 -> 129.25582 | E18: ='[7]ESCAVAÇÃO - TRATAMENTO DE ESGOT'!K22 -> 64.685393 | F18: ='[7]ESCAVAÇÃO - TRATAMENTO DE ESGOT'!L22 -> 43.033536
B19: TOTAL | D19: =SUM(D12:D18) -> 1010.6474 | E19: =SUM(E12:E18) -> 431.29909 | F19: =SUM(F12:F18) -> 557.81145 | G19: =SUM(G12:G17) -> 373.37076 | H19: =SUM(H12:H17) -> 37.337076

Sheet ESTACAS
A1: Obra | B1: WEST VILLAGE
A2: Empresa | B2: KIRCHNER
A3: Revisão | B3: R00
A4: QUANTIFICAÇÃO
A6: Quantitativo estacas
B9: LOCAL | C9: TIPO | D9: Quantidade | E9: Profundidade(m) | F9: Profundidade total (m) | G9: Concreto 40 Mpa + 20% (m³)
B10: 1139 - LOCAÇÃO DAS ESTACAS - R1. dwg | C10: Diâmetro 50cm | D10: 63 | E10: 29 | F10: =E10*D10 -> 1827 | G10: =PI()*(0.25^2)*F10*1.2 -> 430.47673
B11: 1139 - LOCAÇÃO DAS ESTACAS - R1. dwg | C11: Diâmetro 60cm | D11: 82 | E11: 29 | F11: =E11*D11 -> 2378 | G11: =PI()*(0.3^2)*F11*1.2 -> 806.83639
D12: =SUM(D10:D11) -> 145 | F12: =E12*D12 -> 0 | G12: =PI()*(0.35^2)*F12 -> 0
E13: TOTAL | F13: =SUM(F10:F12) -> 4205 | G13: =SUM(G10:G12) -> 1237.3131
B15: Aço | C15: Diâmetro | D15: Peso (kg)
B16: CA50 | C16: 6.3 | D16: 1453
B17: CA50 | C17: 16 | D17: 9205
C18: TOTAL | D18: =SUM(D16:D17) -> 10658

Sheet BALDRAMES
A1: Obra | B1: =[8]ARQUIVOS_BASE!B1 -> WEST VILLAGE
A2: Empresa | B2: =[8]ARQUIVOS_BASE!B2 -> KIRCHNER
A3: Revisão | B3: =[8]ARQUIVOS_BASE!B3 -> 0
A4: RESUMO DE QUANTITATIVO
A6: Quantitativo de Infraestrutura
A8: BLOCOS/ BALDRAME/ LAJE DE PISO/ RESERV. INFERIOR
B10: ELEMENTO | D10: FCK DE CONCRETO (MPa) | E10: VOLUME DE CONCRETO (m³) | F10: ÁREA DE FORMA (m²) | G10: Ø5,00 (kg) | H10: Ø6,30 (kg) | I10: Ø8,00 (kg) | J10: Ø10,00 (kg) | K10: Ø12,50 (kg) | L10: Ø16,00 (kg) | M10: Ø20,00 (kg) | N10: Ø25,00 (kg) | O10: KG DE AÇO (kg) | P10: TAXA DE AÇO (kg/m³)
B11: BLOCOS | D11: 35 | E11: =SUM([7]BLOCOS_FUNDAÇÃO!AE66,[7]BLOCOS_FUNDAÇÃO!L30) -> 311.98431 | F11: =SUM([7]BLOCOS_FUNDAÇÃO!K30,[7]BLOCOS_FUNDAÇÃO!AD66) -> 426.44216 | G11: 216 | H11: 527 | I11: 18 | J11: 3519 | K11: 6091 | L11: 966 | M11: 16892 | N11: 0 | O11: =SUM(G11:N11) -> 28229 | P11: =O11/E11 -> 90.482114
B12: BALDRAME | C12: L1 - TÉRREO | D12: 35 | E12: ='[7]VIGAS - TÉRREO (BALDRAME)'!J71 -> 80.785957 | F12: ='[7]VIGAS - TÉRREO (BALDRAME)'!I71 -> 804.43436 | G12: 275 | H12: 642 | I12: 1436 | J12: 602 | K12: 1797 | L12: 2234 | M12: 510 | N12: 0 | O12: =SUM(G12:N12) -> 7496 | P12: =O12/E12 -> 92.788404
B13: LAJE DE PISO | C13: L1 - TÉRREO | D13: 35 | E13: ='[7]LAJES_RESER. INFERIOR'!J7 -> 128.7 | F13: ='[7]LAJES_RESER. INFERIOR'!G7 -> 780 | G13: 0 | H13: 2545 | I13: 1839 | J13: 702 | K13: 0 | L13: 0 | M13: 0 | N13: 0 | O13: =SUM(G13:N13) -> 5086 | P13: =O13/E13 -> 39.51826
B14: RES. INFERIOR | D14: 35 | E14: =SUM('[7]VIGAS - RESER. INFERIOR'!J32,'[7]LAJES_RESER. INFERIOR'!J17) -> 40.270146 | F14: =SUM('[7]VIGAS - RESER. INFERIOR'!I32,'[7]LAJES_RESER. INFERIOR'!I17) -> 391.95044 | G14: 8 | H14: =17+140 -> 157 | I14: =1132+1103 -> 2235 | J14: =1693+73 -> 1766 | K14: =26 -> 26 | L14: =1037 -> 1037 | M14: 0 | N14: 0 | O14: =SUM(G14:N14) -> 5229 | P14: =O14/E14 -> 129.84805
B15: TOTAL | E15: =SUM(E11:E14) -> 561.74041 | F15: =SUM(F11:F14) -> 2402.827 | G15: =SUM(G11:G14) -> 499 | H15: =SUM(H11:H14) -> 3871 | I15: =SUM(I11:I14) -> 5528 | J15: =SUM(J11:J14) -> 6589 | K15: =SUM(K11:K14) -> 7914 | L15: =SUM(L11:L14) -> 4237 | ... O15: =SUM(O11:O14) -> 46040 | P15: =O15/E15 -> 81.959565

Sheet SUPRAESTRUTURA
A1: Obra | B1: =[8]ARQUIVOS_BASE!B1 -> WEST VILLAGE
A2: Empresa | B2: =[8]ARQUIVOS_BASE!B2 -> KIRCHNER
A3: Revisão | B3: =[8]ARQUIVOS_BASE!B3 -> 0
A4: RESUMO DE QUANTITATIVO
A6: Quantitativo de Supraestrutura
A8: VIGAS
B10: ELEMENTO | C10: PAVIMENTO | D10: FCK DE CONCRETO (MPa) | E10: VOLUME DE CONCRETO (m³) | F10: ÁREA DE FORMA (m²) | G10: Ø5,00 (kg) | H10: Ø6,30 (kg) | I10: Ø8,00 (kg) | J10: Ø10,00 (kg) | K10: Ø12,50 (kg) | L10: Ø16,00 (kg) | M10: Ø20,00 (kg) | N10: Ø25,00 (kg) | O10: KG DE AÇO (kg) | P10: TAXA DE AÇO (kg/m³)
B11: VIGAS | C11: L2 - MEZ G1 | D11: 35 | E11: ='[8]VIGAS - MEZ G1'!J51 -> 91.341087 | F11: ='[8]VIGAS - MEZ G1'!I51 -> 631.07026 | G11: 248 | H11: 514 | I11: 375 | J11: 675 | K11: 2217 | L11: 1899 | M11: 5501 | N11: 0 | O11: =SUM(G11:N11) -> 11429 | P11: =O11/E11 -> 125.12441
B12: VIGAS | C12: L3 - G2 | D12: 35 | E12: ='[8]VIGAS - G2'!J35 -> 18.49273 | F12: ='[8]VIGAS - G2'!I35 -> 279.89302 | G12: =156 -> 156 | H12: 310 | I12: 29 | J12: 208 | K12: 246 | L12: 502 | M12: 615 | N12: 0 | O12: =SUM(G12:N12) -> 2066 | P12: =O12/E12 -> 111.71958
B13: VIGAS | C13: L4 - MEZ G3 | D13: 35 | E13: ='[8]VIGAS - G3'!J35 -> 19.156573 | F13: ='[8]VIGAS - G3'!I35 -> 290.32429 | G13: 174 | H13: 309 | I13: 38 | J13: 188 | K13: 193 | L13: 475 | M13: 832 | N13: 0 | O13: =SUM(G13:N13) -> 2209 | P13: =O13/E13 -> 115.3129
B14: VIGAS | C14: L5 - LAZER | D14: 35 | E14: ='[8]VIGAS - LAZER'!J65 -> 222.09438 | F14: ='[8]VIGAS - LAZER'!I65 -> 976.36124 | G14: 211 | H14: 362 | I14: 2196 | J14: 1938 | K14: 5683 | L14: 10626 | M14: 2099 | N14: 0 | O14: =SUM(G14:N14) -> 23115 | P14: =O14/E14 -> 104.07738
B15: VIGAS | C15: L6 TIPO | D15: 35 | E15: ='[8]VIGAS - PAV TIPO'!J23 -> 11.799368 | F15: ='[8]VIGAS - PAV TIPO'!I23 -> 183.41024 | G15: 109 | H15: 207 | I15: 49 | J15: 32 | K15: 161 | L15: 513 | M15: 565 | N15: 0 | O15: =SUM(G15:N15) -> 1636 | P15: =O15/E15 -> 138.65149
B16: VIGAS | C16: L7 A L11 TIPO | D16: 35 | E16: =5*E15 -> 58.99684 | F16: ='[8]VIGAS - PAV TIPO'!I23*5 -> 917.0512 | G16: =106*5 -> 530 | H16: =5*207 -> 1035 | I16: =5*49 -> 245 | J16: =5*32 -> 160 | K16: =5*161 -> 805 | L16: =5*535 -> 2675 | M16: =5*565 -> 2825 | N16: 0 | O16: =SUM(G16:N16) -> 8275 | P16: =O16/E16 -> 140.26175
B17: VIGAS | C17: L12 A L16 TIPO | D17: 35 | E17: =5*E15 -> 58.99684 | F17: ='[8]VIGAS - PAV TIPO'!I23*5 -> 917.0512 | G17: =5*106 -> 530 | H17: =5*207 -> 1035 | I17: =5*44 -> 220 | J17: =5*55 -> 275 | K17: =5*151 -> 755 | L17: =5*477 -> 2385 | M17: =5*504 -> 2520 | N17: 0 | O17: =SUM(G17:N17) -> 7720 | P17: =O17/E17 -> 130.85447
B18: VIGAS | C18: L17 A L20 TIPO | D18: 35 | E18: =4*E15 -> 47.197472 | F18: =4*'[8]VIGAS - PAV TIPO'!I23 -> 733.64096 | G18: =4*105 -> 420 | H18: =4*207 -> 828 | I18: =4*25 -> 100 | J18: =4*86 -> 344 | K18: =4*141 -> 564 | L18: =4*619 -> 2476 | M18: 0 | N18: 0 | O18: =SUM(G18:N18) -> 4732 | P18: =O18/E18 -> 100.25961
B19: VIGAS | C19: L21 - TELHADO | D19: 35 | E19: ='[8]VIGAS - TELHADO'!J23 -> 11.812108 | F19: ='[8]VIGAS - TELHADO'!I23 -> 183.61044 | G19: 109 | H19: 207 | I19: 24 | J19: 142 | K19: 291 | L19: 140 | M19: 0 | N19: 0 | O19: =SUM(G19:N19) -> 913 | P19: =O19/E19 -> 77.29357
B20: VIGAS | C20: L22 - MÁQUINAS | D20: 35 | E20: ='[8]VIGAS - CASA DE MAQ'!J10 -> 0.742 | F20: ='[8]VIGAS - CASA DE MAQ'!I10 -> 12.084 | G20: 6 | H20: 0 | I20: 5 | J20: 29 | K20: 0 | L20: 0 | M20: 0 | N20: 0 | O20: =SUM(G20:N20) -> 40 | P20: =O20/E20 -> 53.908356
B21: VIGAS | C21: TOTAL | E21: =SUM(E11:E20) -> 540.6294 | F21: =SUM(F11:F20) -> 5124.4969 | G21: =SUM(G11:G20) -> 2493 | H21: =SUM(H11:H20) -> 4807 | I21: =SUM(I11:I20) -> 3281 | J21: =SUM(J11:J20) -> 3991 | K21: =SUM(K11:K20) -> 10915 | L21: =SUM(L11:L20) -> 21691 | ... O21: =SUM(O11:O20) -> 62135 | P21: =O21/E21 -> 114.93086
A23: PILARES
B25: ELEMENTO | C25: PAVIMENTO | D25: FCK DE CONCRETO (MPa) | E25: VOLUME DE CONCRETO (m³) | F25: ÁREA DE FORMA (m²) | G25: Ø5,00 (kg) | H25: Ø6,30 (kg) | I25: Ø8,00 (kg) | J25: Ø10,00 (kg) | K25: Ø12,50 (kg) | L25: Ø16,00 (kg) | M25: Ø20,00 (kg) | N25: Ø25,00 (kg) | O25: KG DE AÇO (kg) | P25: TAXA DE AÇO (kg/m³)
B26: PILARES | C26: L1 - TÉRREO | D26: 35 | E26: 0 | O26: =SUM(G26:N26) -> 0
B27: PILARES | C27: L2 - MEZ G1 | D27: 35 | E27: ='[8]PILARES - MEZ G1'!J53 -> 57.48336 | F27: ='[8]PILARES - MEZ G1'!I53 -> 497.1384 | G27: 425 | H27: 1093 | I27: 0 | J27: 0 | K27: 740 | L27: 1926 | M27: 6793 | N27: 0 | O27: =SUM(G27:N27) -> 10977 | P27: =O27/E27 -> 190.95961
B28: PILARES | C28: L3 - G2 | D28: 35 | E28: ='[8]PILARES - MEZ G2'!J53 -> 40.76928 | F28: ='[8]PILARES - MEZ G2'!I53 -> 361.5552 | G28: 277 | H28: 766 | I28: 0 | J28: 0 | K28: 836 | L28: 2665 | M28: 2989 | N28: 0 | O28: =SUM(G28:N28) -> 7533 | P28: =O28/E28 -> 184.77147
B29: PILARES | C29: L4 - MEZ G3 | D29: 35 | E29: ='[8]PILARES - MEZ G3'!J51 -> 40.76928 | F29: ='[8]PILARES - MEZ G3'!I51 -> 361.5552 | G29: 277 | H29: 667 | I29: 0 | J29: 0 | K29: 1401 | L29: 1402 | M29: 2693 | N29: 0 | O29: =SUM(G29:N29) -> 6440 | P29: =O29/E29 -> 157.96207
B30: PILARES | C30: L5 - LAZER | D30: 35 | E30: ='[8]PILARES - LAZER '!J51 -> 55.70136 | F30: ='[8]PILARES - LAZER '!I51 -> 491.7528 | G30: 369 | H30: 913 | I30: 0 | J30: 0 | K30: 1454 | L30: 1475 | M30: 2629 | N30: 0 | O30: =SUM(G30:N30) -> 6840 | P30: =O30/E30 -> 122.79772
B31: PILARES | C31: L6 TIPO | D31: 35 | E31: ='[8]PILARES - L6 TIPO 01'!J36 -> 33.21504 | F31: ='[8]PILARES - L6 TIPO 01'!I36 -> 281.124 | G31: 531 | H31: 87 | I31: 0 | J31: 0 | K31: 670 | L31: 1389 | M31: 2240 | N31: 0 | O31: =SUM(G31:N31) -> 4917 | P31: =O31/E31 -> 148.03535
B32: PILARES | C32: L7 TIPO | D32: 35 | E32: ='[8]PILARES - L7 A L21 TIPO'!J35 -> 29.71872 | F32: ='[8]PILARES - L7 A L21 TIPO'!I35 -> 246.636 | G32: =416 -> 416 | H32: =29 -> 29 | I32: 0 | J32: 0 | K32: =709 -> 709 | L32: =1187 -> 1187 | M32: =513 -> 513 | N32: 0 | O32: =SUM(G32:N32) -> 2854 | P32: =O32/E32 -> 96.033746
B33: PILARES | C33: L8 TIPO | D33: 35 | E33: =E32 -> 29.71872 | F33: =F32 -> 246.636 | G33: 415 | H33: 29 | I33: 0 | J33: 0 | K33: 894 | L33: 1212 | M33: 0 | N33: 0 | O33: =SUM(G33:N33) -> 2550 | P33: =O33/E33 -> 85.804503
B34: PILARES | C34: L9 TIPO | D34: 35 | E34: =E32 -> 29.71872 | F34: =F32 -> 246.636 | G34: 414 | H34: 29 | I34: 0 | J34: 0 | K34: 1187 | L34: 732 | M34: 0 | N34: 0 | O34: =SUM(G34:N34) -> 2362 | P34: =O34/E34 -> 79.478524
B35: PILARES | C35: L10 TIPO | D35: 35 | E35: =E32 -> 29.71872 | F35: =F32 -> 246.636 | G35: 413 | H35: 29 | I35: 0 | J35: 0 | K35: 1279 | L35: 581 | M35: 0 | N35: 0 | O35: =SUM(G35:N35) -> 2302 | P35: =O35/E35 -> 77.459594
B36: PILARES | C36: L11 TIPO | D36: 35 | E36: =E32 -> 29.71872 | F36: =F32 -> 246.636 | G36: 413 | H36: 29 | I36: 0 | J36: 0 | K36: 1372 | L36: 429 | M36: 0 | N36: 0 | O36: =SUM(G36:N36) -> 2243 | P36: =O36/E36 -> 75.474314
B37: PILARES | C37: L12 A L20 TIPO | D37: 35 | E37: =E32*9 -> 267.46848 | F37: =F32*9 -> 2219.724 | G37: =401*9 -> 3609 | H37: =9*29 -> 261 | I37: 0 | J37: 0 | K37: =9*1479 -> 13311 | L37: =9*126 -> 1134 | M37: 0 | N37: 0 | O37: =SUM(G37:N37) -> 18315 | P37: =O37/E37 -> 68.475358
B38: PILARES | C38: L21 - TELHADO | D38: 35 | E38: =E32 -> 29.71872 | F38: =F32 -> 246.636 | G38: 401 | H38: 29 | I38: 0 | J38: 0 | K38: 1330 | L38: 126 | M38: 0 | N38: 0 | O38: =SUM(G38:N38) -> 1886 | P38: =O38/E38 -> 63.461683
B39: PILARES | C39: L22 - MÁQUINAS L23/ L24 - RESERVATÓRIO SUPERIOR | D39: 35 | E39: ='[8]PILARES - L22 L23 L24'!J35 -> 19.95056 | F39: ='[8]PILARES - L22 L23 L24'!I35 -> 168.448 | G39: 271 | H39: 67 | I39: 0 | J39: 0 | K39: 941 | L39: 223 | M39: 0 | N39: 0 | O39: =SUM(G39:N39) -> 1502 | P39: =O39/E39 -> 75.286107
C40: TOTAL | D40: 35 | E40: =SUM(E26:E39) -> 693.66968 | F40: =SUM(F26:F39) -> 5861.1136 | G40: =SUM(G26:G39) -> 8231 | H40: =SUM(H26:H39) -> 4028 | I40: =SUM(I26:I39) -> 0 | J40: =SUM(J26:J39) -> 0 | K40: =SUM(K26:K39) -> 26124 | L40: =SUM(L26:L39) -> 14481 | ... O40: =SUM(O26:O39) -> 70721 | P40: =O40/E40 -> 101.95198
A42: LAJES
B44: ELEMENTO | C44: PAVIMENTO | D44: FCK DE CONCRETO (MPa) | E44: VOLUME DE CONCRETO (m³) | F44: ÁREA DE FORMA (m²) | G44: Ø5,00 (kg) | H44: Ø6,30 (kg) | I44: Ø8,00 (kg) | J44: Ø10,00 (kg) | K44: Ø12,50 (kg) | L44: Ø16,00 (kg) | M44: Ø20,00 (kg) | N44: Ø25,00 (kg) | O44: KG DE AÇO (kg) | P44: TAXA DE AÇO (kg/m³)
B45: LAJE | C45: L2 - MEZ G1 | D45: 35 | E45: 87 | F45: =[8]LAJES_FORMAS!G13 -> 91.83 | G45: 0 | H45: 92 | I45: 1045 | J45: 1371 | K45: 1374 | L45: 0 | M45: 0 | N45: 0 | O45: =SUM(G45:N45) -> 3882 | P45: =O45/E45 -> 44.62069
B46: LAJE | C46: L3 - G2 | D46: 35 | E46: 98 | F46: =[8]LAJES_FORMAS!G18 -> 140.32 | G46: 0 | H46: 62 | I46: 1157 | J46: 715 | K46: 2756 | L46: 77 | M46: 0 | N46: 0 | O46: =SUM(G46:N46) -> 4767 | P46: =O46/E46 -> 48.642857
B47: LAJE | C47: L4 - MEZ G3 | D47: 35 | E47: 98 | F47: =[8]LAJES_FORMAS!G23 -> 140.42 | G47: 0 | H47: 62 | I47: 1157 | J47: 715 | K47: 2756 | L47: 77 | M47: 0 | N47: 0 | O47: =SUM(G47:N47) -> 4767 | P47: =O47/E47 -> 48.642857
B48: LAJE | C48: L5 - LAZER | D48: 35 | E48: 77 | F48: =[8]LAJES_FORMAS!G28 -> 46.17 | G48: 0 | H48: 62 | I48: 1045 | J48: 2305 | K48: 317 | L48: 0 | M48: 0 | N48: 0 | O48: =SUM(G48:N48) -> 3729 | P48: =O48/E48 -> 48.428571
B49: LAJE | C49: L6 - TIPO 01 | D49: 35 | E49: 56 | F49: =[8]LAJES_FORMAS!G33 -> 81.76 | G49: 0 | H49: 0 | I49: 904 | J49: 202 | K49: 1745 | L49: 856 | M49: 0 | N49: 0 | O49: =SUM(G49:N49) -> 3707 | P49: =O49/E49 -> 66.196429
B50: LAJE | C50: L7 AO L20 - TIPO 02 AO TIPO 15 | D50: 35 | E50: =14*55 -> 770 | F50: =14*F49 -> 1144.64 | G50: 0 | H50: 0 | I50: =14*878 -> 12292 | J50: =14*391 -> 5474 | K50: =14*1691 -> 23674 | L50: =14*801 -> 11214 | M50: 0 | N50: 0 | O50: =SUM(G50:N50) -> 52654 | P50: =O50/E50 -> 68.381818
B51: LAJE | C51: L21 - TELHADO | D51: 35 | E51: 55 | F51: =[8]LAJES_FORMAS!G38 -> 79.16 | G51: 0 | H51: 0 | I51: 724 | J51: 739 | K51: 1047 | L51: 0 | M51: 0 | N51: 0 | O51: =SUM(G51:N51) -> 2510 | P51: =O51/E51 -> 45.636364
B52: LAJE | C52: L22 - MÁQUINAS L23/ L24 - RESERVATÓRIO SUPERIOR | D52: 35 | E52: =1+10 -> 11 | F52: =[8]LAJES_FORMAS!G42 -> 77.2162 | G52: 0 | H52: 0 | I52: =34+261 -> 295 | J52: =377 -> 377 | K52: 213 | L52: 0 | M52: 0 | N52: 0 | O52: =SUM(G52:N52) -> 885 | P52: =O52/E52 -> 80.454545
C53: TOTAL | E53: =SUM(E45:E52) -> 1252 | F53: =SUM(F45:F52) -> 1801.5162 | G53: =SUM(G45:G52) -> 0 | H53: =SUM(H45:H52) -> 278 | I53: =SUM(I45:I52) -> 18619 | J53: =SUM(J45:J52) -> 11898 | K53: =SUM(K45:K52) -> 33882 | L53: =SUM(L45:L52) -> 12224 | ... O53: =SUM(O45:O52) -> 76901 | P53: =O53/E53 -> 61.422524
A55: LAJES
B57: ELEMENTO | C57: PAVIMENTO | D57: Tela Q-92 (und) | E57: Tela Q-92 (kg) | F57: CUBETAS 54x54x18 (und) | G57: CUBETAS 27x54x18 (und)
B58: LAJE | C58: L1 - TÉRREO | D58: 64 | E58: 1384 | F58: 0 | G58: 0
B59: LAJE | C59: L2 - MEZ G1 | D59: 56 | E59: 1221 | F59: 1220 | G59: 211
B60: LAJE | C60: L3 - G2 | D60: 60 | E60: 1299 | F60: 1233 | G60: 191
B61: LAJE | C61: L4 - MEZ G3 | D61: 60 | E61: 1299 | F61: 1233 | G61: 191
B62: LAJE | C62: L5 - LAZER | D62: 52 | E62: 1144 | F62: 1103 | G62: 158
B63: LAJE | C63: L6 - TIPO 01 | D63: 35 | E63: 758 | F63: 732 | G63: 98
B64: LAJE | C64: L7 AO L20 - TIPO 02 AO TIPO 15 | D64: =14*34 -> 476 | E64: =14*745 -> 10430 | F64: =14*671 -> 9394 | G64: =14*123 -> 1722
B65: LAJE | C65: L21 - TELHADO | D65: 34 | E65: 745 | F65: 671 | G65: 123
B66: LAJE | C66: L22 - MÁQUINAS L23/ L24 - RESERVATÓRIO SUPERIOR | D66: =1+6 -> 7 | E66: =13+121 -> 134 | F66: 0 | G66: 0
C67: TOTAL | D67: =SUM(D58:D66) -> 844 | E67: =SUM(E58:E66) -> 18414 | F67: =SUM(F58:F66) -> 15586 | G67: =SUM(G58:G66) -> 2694
A69: ESCADAS
B71: ELEMENTO | C71: PAVIMENTO | D71: FCK DE CONCRETO (MPa) | E71: VOLUME DE CONCRETO (m³) | F71: ÁREA DE FORMA (m²) | G71: Ø5,00 (kg) | H71: Ø6,30 (kg) | I71: Ø8,00 (kg) | J71: Ø10,00 (kg) | K71: Ø12,50 (kg) | L71: Ø16,00 (kg) | M71: Ø20,00 (kg) | N71: Ø25,00 (kg) | O71: KG DE AÇO (kg) | P71: TAXA DE AÇO (kg/m³)
B72: ESCADA | C72: L1 - L2 | D72: 35 | E72: =[8]ESCADAS!AD7 -> 4.71159 | F72: =[8]ESCADAS!AC7 -> 24.2061 | G72: 0 | H72: 0 | I72: 96 | J72: 124 | K72: 0 | L72: 0 | M72: 0 | N72: 0 | O72: =SUM(H72:N72) -> 220 | P72: =O72/E72 -> 46.693367
B73: ESCADA | C73: L2 - L4 | D73: 35 | E73: =[8]ESCADAS!AD8 -> 7.83909 | F73: =[8]ESCADAS!AC8 -> 38.4951 | G73: 0 | H73: 0 | I73: =2*96 -> 192 | J73: =2*124 -> 248 | K73: 0 | L73: 0 | M73: 0 | N73: 0 | O73: =SUM(G73:N73) -> 440 | P73: =O73/E73 -> 56.128964
B74: ESCADA | C74: L4 - L5 | D74: 35 | E74: =[8]ESCADAS!AD9 -> 4.71159 | F74: =[8]ESCADAS!AC9 -> 24.2061 | G74: 0 | H74: 0 | I74: 54 | J74: 0 | K74: 76 | L74: 0 | M74: 0 | N74: 0 | O74: =SUM(G74:N74) -> 130 | P74: =O74/E74 -> 27.591535
B75: ESCADA | C75: L5 - L6 | D75: 35 | E75: =[8]ESCADAS!AD10 -> 4.42323 | F75: =[8]ESCADAS!AC10 -> 22.0857 | G75: 0 | H75: 0 | I75: 25 | J75: 0 | K75: 121 | L75: 0 | M75: 0 | N75: 0 | O75: =SUM(G75:N75) -> 146 | P75: =O75/E75 -> 33.007553
B76: ESCADA | C76: L6 - L21 | D76: 35 | E76: =[8]ESCADAS!AD11 -> 58.081725 | F76: =[8]ESCADAS!AC11 -> 292.13775 | G76: 0 | H76: 0 | I76: 719 | J76: 911 | K76: 0 | L76: 0 | M76: 0 | N76: 0 | O76: =SUM(G76:N76) -> 1630 | P76: =O76/E76 -> 28.063905
C77: TOTAL | E77: =SUM(E72:E76) -> 79.767225 | F77: =SUM(F72:F76) -> 401.13075 | G77: =SUM(G72:G76) -> 0 | H77: =SUM(H72:H76) -> 0 | I77: =SUM(I72:I76) -> 1086 | J77: =SUM(J72:J76) -> 1283 | K77: =SUM(K72:K76) -> 197 | L77: =SUM(L72:L76) -> 0 | ... O77: =SUM(O72:O76) -> 2566 | P77: =O77/E77 -> 32.168601
A78: RAMPAS
B80: ELEMENTO | C80: PAVIMENTO | D80: FCK DE CONCRETO (MPa) | E80: VOLUME DE CONCRETO (m³) | F80: ÁREA DE FORMA (m²) | G80: Ø5,00 (kg) | H80: Ø6,30 (kg) | I80: Ø8,00 (kg) | J80: Ø10,00 (kg) | K80: Ø12,50 (kg) | L80: Ø16,00 (kg) | M80: Ø20,00 (kg) | N80: Ø25,00 (kg) | O80: KG DE AÇO (kg) | P80: TAXA DE AÇO (kg/m³)
B81: RAMPA | C81: L1 - L2 | D81: 35 | E81: 11.5 | F81: =19.19*4 -> 76.76 | G81: 0 | H81: 0 | I81: 160 | J81: 347 | K81: 0 | L81: 0 | M81: 0 | N81: 0 | O81: =SUM(H81:N81) -> 507 | P81: =O81/E81 -> 44.086957
B82: RAMPA | C82: L2 - L3 | D82: 35 | E82: 8.5 | F82: =14.03*4 -> 56.12 | G82: 0 | H82: 0 | I82: 129 | J82: 254 | K82: 0 | L82: 0 | M82: 0 | N82: 0 | O82: =SUM(G82:N82) -> 383 | P82: =O82/E82 -> 45.058824
B83: RAMPA | C83: L3 - L4 | D83: 35 | E83: 8.5 | F83: =14.03*4 -> 56.12 | G83: 0 | H83: 0 | I83: 129 | J83: 254 | K83: 0 | L83: 0 | M83: 0 | N83: 0 | O83: =SUM(G83:N83) -> 383 | P83: =O83/E83 -> 45.058824
C84: TOTAL | E84: =SUM(E81:E83) -> 28.5 | F84: =SUM(F81:F83) -> 189 | G84: =SUM(G81:G83) -> 0 | H84: =SUM(H81:H83) -> 0 | I84: =SUM(I81:I83) -> 418 | J84: =SUM(J81:J83) -> 855 | K84: =SUM(K81:K83) -> 0 | L84: =SUM(L81:L83) -> 0 | ... O84: =SUM(O81:O83) -> 1273 | P84: =O84/E84 -> 44.666667
B86: ELEMENTO | C86: PAVIMENTO | D86: Tela Q-92 (und) | E86: Tela Q-92 (kg)
B87: RAMPA | C87: L1 - L2 | D87: 6 | E87: 131
B88: RAMPA | C88: L2 - L3 | D88: 5 | E88: 109
B89: RAMPA | C89: L3 - L4 | D89: 5 | E89: 109
C90: TOTAL | D90: =SUM(D87:D89) -> 16 | E90: =SUM(E87:E89) -> 349 | F90: =SUM(F87:F89) -> 0 | G90: =SUM(G87:G89) -> 0 | H90: =SUM(H87:H89) -> 0 | I90: =SUM(I87:I89) -> 0 | J90: =SUM(J87:J89) -> 0 | K90: =SUM(K87:K89) -> 0 | ... P90: =SUM(P87:P89) -> 0
A92: RESUMO QUANTITATIVOS SUPRAESTRUTURA
B94: ELEMENTO | C94: PAVIMENTO | D94: FCK DE CONCRETO (MPa) | E94: VOLUME DE CONCRETO (m³) | F94: ÁREA DE FORMA (m²) | G94: Ø5,00 (kg) | H94: Ø6,30 (kg) | I94: Ø8,00 (kg) | J94: Ø10,00 (kg) | K94: Ø12,50 (kg) | L94: Ø16,00 (kg) | M94: Ø20,00 (kg) | N94: Ø25,00 (kg) | O94: KG DE AÇO (kg) | P94: TAXA DE AÇO (kg/m³)
B95: VIGAS | C95: TOTAL | D95: 35 | E95: =E21 -> 540.6294 | F95: =F21 -> 5124.4969 | G95: =G21 -> 2493 | H95: =H21 -> 4807 | I95: =I21 -> 3281 | J95: =J21 -> 3991 | K95: =K21 -> 10915 | L95: =L21 -> 21691 | ... P95: =P21 -> 114.93086
B96: PILAR | C96: TOTAL | D96: 35 | E96: =E40 -> 693.66968 | F96: =F40 -> 5861.1136 | G96: =G40 -> 8231 | H96: =H40 -> 4028 | I96: =I40 -> 0 | J96: =J40 -> 0 | K96: =K40 -> 26124 | L96: =L40 -> 14481 | ... P96: =P40 -> 101.95198
B97: LAJE | C97: TOTAL | D97: 35 | E97: =E53 -> 1252 | F97: =F53 -> 1801.5162 | G97: =G53 -> 0 | H97: =H53 -> 278 | I97: =I53 -> 18619 | J97: =J53 -> 11898 | K97: =K53 -> 33882 | L97: =L53 -> 12224 | ... P97: =P53 -> 61.422524
B98: ESCADA | C98: TOTAL | D98: 35 | E98: =E77 -> 79.767225 | F98: =F77 -> 401.13075 | G98: =G77 -> 0 | H98: =H77 -> 0 | I98: =I77 -> 1086 | J98: =J77 -> 1283 | K98: =K77 -> 197 | L98: =L77 -> 0 | ... P98: =P77 -> 32.168601
B99: RAMPA | C99: TOTAL | D99: 35 | E99: =E84 -> 28.5 | F99: =F84 -> 189 | G99: =G84 -> 0 | H99: =H84 -> 0 | I99: =I84 -> 418 | J99: =J84 -> 855 | K99: =K84 -> 0 | L99: =L84 -> 0 | ... P99: =P84 -> 44.666667
C100: TOTAL | E100: =SUM(E95:E99) -> 2594.5663 | F100: =SUM(F95:F99) -> 13377.257 | G100: =SUM(G95:G99) -> 10724 | H100: =SUM(H95:H99) -> 9113 | I100: =SUM(I95:I99) -> 23404 | J100: =SUM(J95:J99) -> 18027 | K100: =SUM(K95:K99) -> 71118 | L100: =SUM(L95:L99) -> 48396 | ... O100: =SUM(O95:O99) -> 213596 | P100: =O100/E100 -> 82.324356
B103: ELEMENTO | C103: PAVIMENTO | D103: Tela Q-92 (und) | E103: Tela Q-92 (kg) | F103: CUBETAS 54x54x18 (und) | G103: CUBETAS 27x54x18 (und)
B104: LAJE | D104: =D67 -> 844 | E104: =E67 -> 18414 | F104: =F67 -> 15586 | G104: =G67 -> 2694
B105: RAMPA | D105: =D90 -> 16 | E105: =E90 -> 349 | F105: 0 | G105: 0
C106: TOTAL | D106: =SUM(D104:D105) -> 860 | E106: =SUM(E104:E105) -> 18763 | F106: =SUM(F104:F105) -> 15586 | G106: =SUM(G104:G105) -> 2694
B109: MÉDIA DE CUBETAS/PAV | F109: =F106/20 -> 779.3 | G109: =G106/20 -> 134.7
B110: CONSIDERANDO 3 JOGOS | F110: =F109*3 -> 2337.9 | G110: =G109*3 -> 404.1
B112: FABRICAÇÃO DAS FORMAS | F112: TOTAL
B113: VIGAS | F113: =(F95/20)*2 -> 512.44969
B114: PILAR | F114: =(F96/20)*2 -> 586.11136
B115: LAJE | F115: =(F97/20)*2 -> 180.15162
B116: ESCADA | F116: =(F98/20)*2 -> 40.113075
B117: RAMPA | F117: =E90/3 -> 116.33333
B119: CONSIDERANDO 14 UTILIZAÇÕES - 2 FABRIÇAÇÃO VISTO QUE SÃO 20 PAVIMENTOS

Sheet ESCORAMENTO
A1: PLANILHA DE ESCORAMENTO
A3: CLIENTE | B3: KIRCHNER
A4: OBRA | B4: WEST VILLAGE
A5: REVISÃO | B5: R00
A6: DATA | B6: 45274
A8: PAVIMENTO | B8: ÁREA | C8: R$ | D8: R$ | E8: INÍCIO | F8: FIM | I8: ESCORAMENTO (PARA 1 MÊS)
C9: ESCOR. / m2 | D9: DIA / m2 | G9: DIAS CORRIDOS | H9: DIFERENÇA ENTRE PAVIMENTOS | I9: 1 | J9: 0.75 | K9: 0.5 | L9: 0.25 | M9: TRAV/MÊS / M2 | N9: TRAV.
A10: Garagem 01 | B10: 825.55 | C10: =(20640)/B10 -> 25.001514 | D10: =C10/30 -> 0.8333838 | G10: 31 | H10: 0 | I10: =(B10+7)*G10*D10 -> 21508.844 | J10: 0
A11: Garagem 02 | B11: 825.55 | C11: =(20640)/B11 -> 25.001514 | D11: =C11/30 -> 0.8333838 | G11: 20 | H11: =E11-F10 -> 0 | I11: =(B11+7)*G11*D11 -> 13876.674 | J11: =(B10*D10*0.75)*7 -> 3612 | K11: =(B10*D10*0.5)*7 -> 2408 | L11: =(B10*D10*0.25)*7 -> 1204 | N11: =(M11*($G11)*B10)/30 -> 0
A12: Garagem 03 | B12: 825.55 | C12: =(20640)/B12 -> 25.001514 | D12: =C12/30 -> 0.8333838 | G12: 20 | H12: =E12-F10 -> 0 | I12: =(B12+7)*G12*D12 -> 13876.674 | J12: =(B11*D11*0.75)*7 -> 3612 | K12: =(B11*D11*0.5)*7 -> 2408 | L12: =(B11*D11*0.25)*7 -> 1204 | N12: =(M12*($G12)*B11)/30 -> 0
A13: Lazer | B13: 827.3 | C13: =(20640)/B13 -> 24.948628 | D13: =C13/30 -> 0.83162094 | G13: 37 | H13: =E13-F11 -> 0 | I13: =(B13+7)*G13*D13 -> 25671.39 | J13: =(B12*D12*0.75)*7 -> 3612 | K13: =(B12*D12*0.5)*7 -> 2408 | L13: =(B12*D12*0.25)*7 -> 1204
A14: Tipo 1 | B14: 439.35 | C14: =(11200)/B14 -> 25.492204 | D14: =C14/30 -> 0.84974015 | G14: 15 | H14: =E14-F12 -> 0 | I14: =(B14+7)*G14*D14 -> 5689.2227 | J14: =(B13*D13*0.75)*7 -> 3612 | K14: =(B13*D13*0.5)*7 -> 2408 | L14: =(B13*D13*0.25)*7 -> 1204 | N14: =(M14*($G14)*B13)/30 -> 0
A15: Tipo 2 | B15: 439.35 | C15: =(11200)/B15 -> 25.492204 | D15: =C15/30 -> 0.84974015 | G15: 12 | H15: =E15-F13 -> 0 | I15: =(B15+7)*G15*D15 -> 4551.3782 | J15: =(B14*D14*0.75)*7 -> 1960 | K15: =(B14*D14*0.5)*7 -> 1306.6667 | L15: =(B14*D14*0.25+B15*D15*0.25)*7 -> 1306.6667 | N15: =(M15*($G15)*B14)/30 -> 0
A16: Tipo 3 | B16: 439.35 | C16: =(11200)/B16 -> 25.492204 | D16: =C16/30 -> 0.84974015 | G16: 11 | H16: =E16-F14 -> 0 | I16: =(B16+7)*G16*D16 -> 4172.0967 | J16: =(B15*D15*0.75)*7 -> 1960 | K16: =(B15*D15*0.5)*7 -> 1306.6667 | L16: =(B15*D15*0.25+B16*D16*0.25)*7 -> 1306.6667 | N16: =(M16*($G16)*B15)/30 -> 0
A17: Tipo 4 | B17: 439.35 | C17: =(11200)/B17 -> 25.492204 | D17: =C17/30 -> 0.84974015 | G17: 11 | H17: =E17-F15 -> 0 | I17: =(B17+7)*G17*D17 -> 4172.0967 | J17: =(B16*D16*0.75)*7 -> 1960 | K17: =(B16*D16*0.5)*7 -> 1306.6667 | L17: =(B16*D16*0.25+B17*D17*0.25)*7 -> 1306.6667 | N17: =(M17*($G17)*B16)/30 -> 0
A18: Tipo 5 | B18: 439.35 | C18: =(11200)/B18 -> 25.492204 | D18: =C18/30 -> 0.84974015 | G18: 11 | H18: =E18-F16 -> 0 | I18: =(B18+7)*G18*D18 -> 4172.0967 | J18: =(B17*D17*0.75)*7 -> 1960 | K18: =(B17*D17*0.5)*7 -> 1306.6667 | L18: =(B17*D17*0.25+B18*D18*0.25)*7 -> 1306.6667 | N18: =(M18*($G18)*B17)/30 -> 0
A19: Tipo 6 | B19: 439.35 | C19: =(11200)/B19 -> 25.492204 | D19: =C19/30 -> 0.84974015 | G19: 11 | H19: =E19-F17 -> 0 | I19: =(B19+7)*G19*D19 -> 4172.0967 | J19: =(B18*D18*0.75)*7 -> 1960 | K19: =(B18*D18*0.5)*7 -> 1306.6667 | L19: =(B18*D18*0.25+B19*D19*0.25)*7 -> 1306.6667 | N19: =(M19*($G19)*B18)/30 -> 0
A20: Tipo 7 | B20: 439.35 | C20: =(11200)/B20 -> 25.492204 | D20: =C20/30 -> 0.84974015 | G20: 11 | H20: =E20-F18 -> 0 | I20: =(B20+7)*G20*D20 -> 4172.0967 | J20: =(B19*D19*0.75)*7 -> 1960 | K20: =(B19*D19*0.5)*7 -> 1306.6667 | L20: =(B19*D19*0.25+B20*D20*0.25)*7 -> 1306.6667 | N20: =(M20*($G20)*B19)/30 -> 0
A21: Tipo 8 | B21: 439.35 | C21: =(11200)/B21 -> 25.492204 | D21: =C21/30 -> 0.84974015 | G21: 11 | H21: =E21-F19 -> 0 | I21: =(B21+7)*G21*D21 -> 4172.0967 | J21: =(B20*D20*0.75)*7 -> 1960 | K21: =(B20*D20*0.5)*7 -> 1306.6667 | L21: =(B20*D20*0.25+B21*D21*0.25)*7 -> 1306.6667 | N21: =(M21*($G21)*B20)/30 -> 0
A22: Tipo 9 | B22: 439.35 | C22: =(11200)/B22 -> 25.492204 | D22: =C22/30 -> 0.84974015 | G22: 11 | H22: =E22-F20 -> 0 | I22: =(B22+7)*G22*D22 -> 4172.0967 | J22: =(B21*D21*0.75)*7 -> 1960 | K22: =(B21*D21*0.5)*7 -> 1306.6667 | L22: =(B21*D21*0.25+B22*D22*0.25)*7 -> 1306.6667 | N22: =(M22*($G22)*B21)/30 -> 0
A23: Tipo 10 | B23: 439.35 | C23: =(11200)/B23 -> 25.492204 | D23: =C23/30 -> 0.84974015 | G23: 11 | H23: =E23-F21 -> 0 | I23: =(B23+7)*G23*D23 -> 4172.0967 | J23: =(B22*D22*0.75)*7 -> 1960 | K23: =(B22*D22*0.5)*7 -> 1306.6667 | L23: =(B22*D22*0.25+B23*D23*0.25)*7 -> 1306.6667 | N23: =(M23*($G23)*B22)/30 -> 0
A24: Tipo 11 | B24: 439.35 | C24: =(11200)/B24 -> 25.492204 | D24: =C24/30 -> 0.84974015 | G24: 11 | H24: =E24-F22 -> 0 | I24: =(B24+7)*G24*D24 -> 4172.0967 | J24: =(B23*D23*0.75)*7 -> 1960 | K24: =(B23*D23*0.5)*7 -> 1306.6667 | L24: =(B23*D23*0.25+B24*D24*0.25)*7 -> 1306.6667 | N24: =(M24*($G24)*B23)/30 -> 0
A25: Tipo 12 | B25: 439.35 | C25: =(11200)/B25 -> 25.492204 | D25: =C25/30 -> 0.84974015 | G25: 11 | H25: =E25-F23 -> 0 | I25: =(B25+7)*G25*D25 -> 4172.0967 | J25: =(B24*D24*0.75)*7 -> 1960 | K25: =(B24*D24*0.5)*7 -> 1306.6667 | L25: =(B24*D24*0.25+B25*D25*0.25)*7 -> 1306.6667
A26: Tipo 13 | B26: 439.35 | C26: =(11200)/B26 -> 25.492204 | D26: =C26/30 -> 0.84974015 | G26: 11 | H26: =E26-F24 -> 0 | I26: =(B26+7)*G26*D26 -> 4172.0967 | J26: =(B25*D25*0.75)*7 -> 1960 | K26: =(B25*D25*0.5)*7 -> 1306.6667 | L26: =(B25*D25*0.25+B26*D26*0.25)*7 -> 1306.6667
A27: Tipo 14 | B27: 439.35 | C27: =(11200)/B27 -> 25.492204 | D27: =C27/30 -> 0.84974015 | G27: 11 | H27: =E27-F25 -> 0 | I27: =(B27+7)*G27*D27 -> 4172.0967 | J27: =(B26*D26*0.75)*7 -> 1960 | K27: =(B26*D26*0.5)*7 -> 1306.6667 | L27: =(B26*D26*0.25+B27*D27*0.25)*7 -> 1306.6667
A28: Tipo 15 | B28: 439.35 | C28: =(11200)/B28 -> 25.492204 | D28: =C28/30 -> 0.84974015 | G28: 11 | H28: =E28-F26 -> 0 | I28: =(B28+7)*G28*D28 -> 4172.0967 | J28: =(B27*D27*0.75)*7 -> 1960 | K28: =(B27*D27*0.5)*7 -> 1306.6667 | L28: =(B27*D27*0.25+B28*D28*0.25)*7 -> 1306.6667
A29: Casa de máquinas | B29: 39.9 | C29: =(60*16)/B29 -> 24.06015 | D29: =C29/30 -> 0.80200501 | G29: 14 | H29: =E29-F27 -> 0 | I29: =(B29+7)*G29*D29 -> 526.59649 | J29: =(B28*D28*0.75)*7 -> 1960 | K29: =(B28*D28*0.5)*7 -> 1306.6667 | L29: =(B28*D28*0.25+B29*D29*0.25)*7 -> 709.33333
A30: Reservatórios | B30: 19.2 | C30: =(30*16)/B30 -> 25 | D30: =C30/30 -> 0.83333333 | G30: 10 | H30: =E30-F28 -> 0 | I30: =(B30+7)*G30*D30 -> 218.33333 | J30: =(B29*D29*0.75)*7 -> 168 | K30: =(B29*D29*0.5)*7 -> 112 | L30: =(B29*D29*0.25+B30*D30*0.25)*7 -> 84
J31: =(B30*D30*0.75)*7 -> 84 | K31: =(B30*D30*0.5)*7 -> 56 | L31: =(B30*D30*0.25+B31*D31*0.25)*7 -> 28
K32: =A31*C31*F32*0.25 -> 0 | L32: =B23*D24*G32*0.25 -> 0
B34: =SUM(B10:B30) -> 9953.3 | I34: =SUM(I10:I32) -> 140156.37 | J34: =SUM(J11:J32) -> 44100 | K34: =SUM(K11:K32) -> 29400 | L34: =SUM(L11:L32) -> 23930.667 | N34: =SUM(N10:N32) -> 0
J36: PREÇO DO CIMBRAMENTO POR M2 | N36: =SUM(N34+I34+J34+L34+K34)/B34 -> 23.870177
J37: FRETE DE IDA | N37: 720
J38: FRETE DE VOLTA | N38: 720
J39: FRETE / M2 | N39: =(N37+N38)/B34 -> 0.14467564
J40: TOTAL / M2 | N40: =N39+N36 -> 24.014853
N41: =N40/10 -> 2.4014853 | O41: TOTAL/M²/MÊS
N44: =N40*B34 -> 239027.04

Sheet ALVENARIA
A1: Obra | B1: =[8]ARQUIVOS_BASE!B1 -> WEST VILLAGE
A2: Empresa | B2: =[8]ARQUIVOS_BASE!B2 -> KIRCHNER
A3: Revisão | B3: R03
A4: RESUMO DE QUANTITATIVO
A6: Quantitativo de alvenaria
A8: ALVENARIA INTERNA
B10: PAVIMENTO | C10: ÁREA DE PAREDE INTERNA (m2) | G10: ÁREA DE REBOCO E CHAPISCO EM ALVENARIA | H10: ENCUNHAMENTO (m)
C11: 20CM | D11: 15 CM | E11: ESCADA | F11: CHURRASQUEIRA
B12: TÉRREO | C12: 7.88 | D12: 539.91654 | E12: 55.178221 | F12: 0 | G12: =((C12+D12+E12)*2)+F12+C26+D26 -> 1514.9526 | H12: ='[9]KIRCHNER LEVANT TÉRREO'!$C$12+'[9]KIRCHNER LEVANT TÉRREO'!$D$12+'[9]KIRCHNER LEVANT TÉRREO'!$E$12+'[9]KIRCHNER LEVANT TÉRREO'!$F$12 -> 207.4206
B13: G1 | C13: 14.8044 | D13: 55.104746 | E13: 29.830661 | F13: 0 | G13: =((C13+D13+E13)*2)+F13+C27+D27 -> 412.28861 | H13: ='[9]KIRCHNER LEVANT GARAGEM'!$C$12+'[9]KIRCHNER LEVANT GARAGEM'!$D$12+'[9]KIRCHNER LEVANT GARAGEM'!$E$12+'[9]KIRCHNER LEVANT GARAGEM'!$F$12 -> 56.622907
B14: G2 | C14: 14.8044 | D14: 55.104746 | E14: 29.830661 | F14: 0 | G14: =((C14+D14+E14)*2)+F14+C28+D28 -> 412.28861 | H14: =H13 -> 56.622907
B15: G3 | C15: 20.8884 | D15: 73.373911 | E15: 42.866549 | F15: 0 | G15: =((C15+D15+E15)*2)+F15+C29+D29 -> 549.58472 | H15: ='[9]KIRCHNER LEVANT TÉRREO'!$C$12+'[9]KIRCHNER LEVANT TÉRREO'!$D$12+'[9]KIRCHNER LEVANT TÉRREO'!$E$12+'[9]KIRCHNER LEVANT TÉRREO'!$F$12 -> 207.4206
B16: LAZER | C16: 42.5866 | D16: 225.33254 | E16: 37.436291 | F16: 19.972 | G16: =((C16+D16+E16)*2)+F16+C30+D30 -> 935.85225 | H16: ='[9]KIRCHNER LEVANT LAZER'!$C$12+'[9]KIRCHNER LEVANT LAZER'!$D$12+'[9]KIRCHNER LEVANT LAZER'!$E$12+'[9]KIRCHNER LEVANT LAZER'!$F$12 -> 122.45317
B17: PAV. TIPO (15X) | C17: 1823.1735 | D17: 6248.4764 | E17: 593.02733 | F17: 674.64 | G17: =((C17+D17+E17)*2)+F17+C31+D31 -> 20331.822 | H17: =('[9]KIRCHNER LEVANT TIPO'!$C$12+'[9]KIRCHNER LEVANT TIPO'!$D$12+'[9]KIRCHNER LEVANT TIPO'!$E$12+'[9]KIRCHNER LEVANT TIPO'!$F$12)*15 -> 3852.8116
B18: CASA DE MÁQUINAS | C18: 8.772 | D18: 39.45 | E18: 63.295915 | F18: 0 | G18: =((C18+D18+E18)*2)+F18+C32+D32 -> 529.15476 | H18: ='[9]KIRCHNER LEVANT CASA MAQUINAS'!$C$12+'[9]KIRCHNER LEVANT CASA MAQUINAS'!$D$12+'[9]KIRCHNER LEVANT CASA MAQUINAS'!$E$12 -> 30.25694
B19: RESERVATÓRIO | C19: 0 | D19: 0 | E19: 0 | F19: 0 | G19: =((C19+D19+E19)*2)+F19+C33+D33 -> 16.938 | H19: 0
B20: TOTAL | C20: =SUM(C12:C19) -> 1932.9093 | D20: =SUM(D12:D19) -> 7236.7588 | E20: =SUM(E12:E19) -> 851.46563 | F20: =SUM(F12:F19) -> 694.612 | G20: =SUM(G12:G19) -> 24702.882 | H20: =SUM(H12:H19) -> 4533.6087
A22: ALVENARIA EXTERNA
B24: PAVIMENTO | C24: ÁREA DE PAREDE EXTERNA (m2) | E24: ÁREA DE REBOCO E CHAPISCO EM ALVENARIA | F24: ENCUNHAMENTO (m)
C25: 20CM | D25: 15 CM
B26: TÉRREO | C26: 0 | D26: 309.00304 | E26: =D26+C26 -> 309.00304 | F26: ='[9]KIRCHNER LEVANT TÉRREO'!$C$19 -> 106.4812
B27: G1 | C27: 15.548 | D27: 197.261 | E27: =D27+C27 -> 212.809 | F27: ='[9]KIRCHNER LEVANT GARAGEM'!$C$19+'[9]KIRCHNER LEVANT GARAGEM'!$D$19 -> 104.74
B28: G2 | C28: 15.548 | D28: 197.261 | E28: =D28+C28 -> 212.809 | F28: =F27 -> 104.74
B29: G3 | C29: 20.8884 | D29: 254.4386 | E29: =D29+C29 -> 275.327 | F29: ='[9]KIRCHNER LEVANT GARAGEM 3'!$C$19+'[9]KIRCHNER LEVANT GARAGEM 3'!$D$19 -> 104.74
B30: LAZER | C30: 20.0032 | D30: 285.1662 | E30: =D30+C30 -> 305.1694 | F30: ='[9]KIRCHNER LEVANT LAZER'!$C$19+'[9]KIRCHNER LEVANT LAZER'!$D$19 -> 141.99
B31: PAV. TIPO (15X) | C31: 71.1 | D31: 2256.7281 | E31: =D31+C31 -> 2327.8281 | F31: =('[9]KIRCHNER LEVANT TIPO'!$C$19+'[9]KIRCHNER LEVANT TIPO'!$D$19)*15 -> 1351.573
B32: CASA DE MÁQUINAS | C32: 19.745 | D32: 286.37393 | E32: =D32+C32 -> 306.11893 | F32: ='[9]KIRCHNER LEVANT CASA MAQUINAS'!$C$19+'[9]KIRCHNER LEVANT CASA MAQUINAS'!$D$19 -> 135.03002
B33: RESERVATÓRIO | C33: 5.6 | D33: 11.338 | E33: =D33+C33 -> 16.938 | F33: ='[9]KIRCHNER LEVANT RESERVATORIO'!$C$19+'[9]KIRCHNER LEVANT RESERVATORIO'!$D$19 -> 16.85
B34: TOTAL | C34: =SUM(C26:C33) -> 168.4326 | D34: =SUM(D26:D33) -> 3797.5698 | E34: =SUM(E26:E33) -> 3966.0024 | F34: =SUM(F26:F33) -> 2066.1442
A36: TOTAL
B38: PAVIMENTO | C38: ÁREA DE PAREDE (m2) | G38: ENCUNHAMENTO (m) | H38: ÁREA DE REBOCO E CHAPISCO EM ALVENARIA
C39: 20CM | D39: 15 CM | E39: ESCADA | F39: CHURRASQUEIRA
B40: TÉRREO | C40: =C12+C26 -> 7.88 | D40: =D12+D26 -> 848.91958 | E40: =E12 -> 55.178221 | F40: =F12 -> 0 | G40: =F26+H12 -> 313.9018 | H40: =G12+E26 -> 1823.9556
B41: G1 | C41: =C13+C27 -> 30.3524 | D41: =D13+D27 -> 252.36575 | E41: =E13 -> 29.830661 | F41: =F13 -> 0 | G41: =F27+H13 -> 161.36291 | H41: =G13+E27 -> 625.09761
B42: G2 | C42: =C14+C28 -> 30.3524 | D42: =D14+D28 -> 252.36575 | E42: =E14 -> 29.830661 | F42: =F14 -> 0 | G42: =F28+H14 -> 161.36291 | H42: =G14+E28 -> 625.09761
B43: G3 | C43: =C15+C29 -> 41.7768 | D43: =D15+D29 -> 327.81251 | E43: =E15 -> 42.866549 | F43: =F15 -> 0 | G43: =F29+H15 -> 312.1606 | H43: =G15+E29 -> 824.91172
B44: LAZER | C44: =C16+C30 -> 62.5898 | D44: =D16+D30 -> 510.49874 | E44: =E16 -> 37.436291 | F44: =F16 -> 19.972 | G44: =F30+H16 -> 264.44317 | H44: =G16+E30 -> 1241.0217
B45: PAV. TIPO (15X) | C45: =C17+C31 -> 1894.2735 | D45: =D17+D31 -> 8505.2044 | E45: =E17 -> 593.02733 | F45: =F17 -> 674.64 | G45: =F31+H17 -> 5204.3846 | H45: =G17+E31 -> 22659.65
B46: CASA DE MÁQUINAS | C46: =C18+C32 -> 28.517 | D46: =D18+D32 -> 325.82393 | E46: =E18 -> 63.295915 | F46: =F18 -> 0 | G46: =F32+H18 -> 165.28696 | H46: =G18+E32 -> 835.27369
B47: RESERVATÓRIO | C47: =C19+C33 -> 5.6 | D47: =D19+D33 -> 11.338 | E47: =E19 -> 0 | F47: =F19 -> 0 | G47: =F33+H19 -> 16.85 | H47: =G19+E33 -> 33.876
B48: TOTAL | C48: =SUM(C40:C47) -> 2101.3419 | D48: =SUM(D40:D47) -> 11034.329 | E48: =SUM(E40:E47) -> 851.46563 | F48: =SUM(F40:F47) -> 694.612 | G48: =SUM(G40:G47) -> 6599.7529 | H48: =SUM(H40:H47) -> 28668.884

Sheet Verga e contra
A1: Obra | B1: West village
A2: Empresa | B2: Kirchner
A3: Revisão
A4: LEVANTAMENTO QUANTITATIVO
A6: Verga e contraverga
A8: Verga e contraverga - Garagem 1
B10: Elemento | C10: Unidade | D10: Quantidade
B11: Verga/contraverga de concreto, moldada in loco | C11: m | D11: 17.07
A13: Verga e contraverga - Garagem 2
B15: Elemento | C15: Unidade | D15: Quantidade
B16: Verga/contraverga de concreto, moldada in loco | C16: m | D16: 17.07
A18: Verga e contraverga - Garagem 3
B20: Elemento | C20: Unidade | D20: Quantidade
B21: Verga/contraverga de concreto, moldada in loco | C21: m | D21: 17.07
A23: Verga e contraverga - Nivel 1
B25: Elemento | C25: Unidade | D25: Quantidade
B26: Verga/contraverga de concreto, moldada in loco | C26: m | D26: 185.78
A28: Verga e contraverga - Lazer
B30: Elemento | C30: Unidade | D30: Quantidade
B31: Verga/contraverga de concreto, moldada in loco | C31: m | D31: 67.39
A33: Verga e contraverga - Tipo 1
B35: Elemento | C35: Unidade | D35: Quantidade
B36: Verga/contraverga de concreto, moldada in loco | C36: m | D36: 3498.42
A38: Verga e contraverga - Cobertura
B40: Elemento | C40: Unidade | D40: Quantidade
B41: Verga/contraverga de concreto, moldada in loco | C41: m | D41: 21.18
A43: Verga e contraverga - Total
B45: Elemento | C45: Unidade | D45: Quantidade
B46: Verga/contraverga de concreto, moldada in loco | C46: m | D46: =SUMIF(B$8:B$41,B46,D$8:D$41) -> 3823.98

Sheet REVESTIMENTOS
A1: Obra | B1: =[8]ARQUIVOS_BASE!B1 -> WEST VILLAGE
A2: Empresa | B2: =[8]ARQUIVOS_BASE!B2 -> KIRCHNER
A3: Revisão | B3: R03
A4: RESUMO DE QUANTITATIVO
A6: Quantitativo de Revestimento em alvenaria
A8: REVESTIMENTOS INTERNOS
B10: PAVIMENTO | C10: ÁREA DE REBOCO E CHAPISCO EM ALVENARIA | D10: ÁREA DE REBOCO E CHAPISCO EM ESTRUTURA | E10: ÁREA DE REBOCO E CHAPISCO | F10: ÁREA DE PAREDE AZULEJO BANHEIRO (m²) | G10: AREA DE PINTURA (m²)
B11: TÉRREO | C11: =ALVENARIA!G12 -> 1514.9526 | D11: ='ARGAMASSADO EM ESTRUTURA'!J11:J12 -> 561.8615 | E11: =D11+C11 -> 2076.8141 | F11: 0 | G11: =E11-F11 -> 2076.8141
B12: G1 | C12: =ALVENARIA!G13 -> 412.28861 | D12: ='ARGAMASSADO EM ESTRUTURA'!J13 -> 475.0208 | E12: =D12+C12 -> 887.30941 | F12: 0 | G12: =E12-F12 -> 887.30941
B13: G2 | C13: =ALVENARIA!G14 -> 412.28861 | D13: ='ARGAMASSADO EM ESTRUTURA'!J15 -> 475.0208 | E13: =D13+C13 -> 887.30941 | F13: 0 | G13: =E13-F13 -> 887.30941
B14: G3 | C14: =ALVENARIA!G15 -> 549.58472 | D14: ='ARGAMASSADO EM ESTRUTURA'!J17 -> 328.74 | E14: =D14+C14 -> 878.32472 | F14: 0 | G14: =E14-F14 -> 878.32472
B15: LAZER | C15: =ALVENARIA!G16 -> 935.85225 | D15: ='ARGAMASSADO EM ESTRUTURA'!J21 -> 175.7262 | E15: =D15+C15 -> 1111.5785 | F15: 46.1552 | G15: =E15-F15 -> 1065.4233
B16: PAV. TIPO (15X) | C16: =ALVENARIA!G17 -> 20331.822 | D16: ='ARGAMASSADO EM ESTRUTURA'!J23 -> 1982.268 | E16: =D16+C16 -> 22314.09 | F16: 3525.522 | G16: =E16-F16 -> 18788.568
B17: CASA DE MÁQUINAS | C17: =ALVENARIA!G18 -> 529.15476 | D17: 0 | E17: =D17+C17 -> 529.15476 | F17: 0 | G17: =E17-F17 -> 529.15476
B18: RESERVATÓRIO | C18: =ALVENARIA!G19 -> 16.938 | D18: 0 | E18: =D18+C18 -> 16.938 | F18: 0 | G18: =E18-F18 -> 16.938
B19: TOTAL | C19: =SUM(C11:C18) -> 24702.882 | D19: =SUM(D11:D18) -> 3998.6373 | E19: =SUM(E11:E18) -> 28701.519 | F19: =SUM(F11:F18) -> 3571.6772 | G19: =SUM(G11:G18) -> 25129.842
A21: REVESTIMENTOS EXTERNOS
B23: PAVIMENTO | C23: ÁREA DE REBOCO E CHAPISCO EM ALVENARIA | D23: ÁREA DE REBOCO E CHAPISCO EM ESTRUTURA | E23: ÁREA DE REBOCO E CHAPISCO
B24: TÉRREO | C24: =ALVENARIA!E26 -> 309.00304 | D24: 285.796 | E24: =D24+C24 -> 594.79904
B25: G1 | C25: =ALVENARIA!E27 -> 212.809 | D25: 313.272 | E25: =D25+C25 -> 526.081
B26: G2 | C26: =ALVENARIA!E28 -> 212.809 | D26: 313.272 | E26: =D26+C26 -> 526.081
B27: G3 | C27: =ALVENARIA!E29 -> 275.327 | D27: 236.98 | E27: =D27+C27 -> 512.307
B28: LAZER | C28: =ALVENARIA!E30 -> 305.1694 | D28: 117.033 | E28: =D28+C28 -> 422.2024
B29: PAV. TIPO (15X) | C29: =ALVENARIA!E31 -> 2327.8281 | D29: 1638.315 | E29: =D29+C29 -> 3966.1431
B30: CASA DE MÁQUINAS | C30: =ALVENARIA!E32 -> 306.11893 | D30: 57.6726 | E30: =D30+C30 -> 363.79153
B31: RESERVATÓRIO | C31: =ALVENARIA!E33 -> 16.938 | D31: 68.4864 | E31: =D31+C31 -> 85.4244
B32: DETALHES DA FACHADA EXTERNA | C32: 0 | D32: =243.134+576.54 -> 819.674 | E32: =D32+C32 -> 819.674
B33: TOTAL | C33: =SUM(C24:C32) -> 3966.0024 | D33: =SUM(D24:D32) -> 3850.501 | E33: =SUM(E24:E32) -> 7816.5034

Sheet ARGAMASSADO EM ESTRUTURA
A1: Obra | B1: =[8]ARQUIVOS_BASE!B1 -> WEST VILLAGE
A2: Empresa | B2: =[8]ARQUIVOS_BASE!B2 -> KIRCHNER
A3: Revisão | B3: =[8]ARQUIVOS_BASE!B3 -> 0
A4: RESUMO DE QUANTITATIVO
A6: Quantitativo de Acabamento Argamassado - Estrutura
A8: REVESTIMENTO ARGAMASSADO EM ESTRUTURA INTERNO
B10: PAVIMENTO | C10: PERÍMETRO DE PILARES (m) | D10: ALTURA DE PILARES (m) | E10: ÁREA TOTAL PILARES INTERNO (m2) | F10: PERÍMETRO DE VIGAS (m) | G10: ALTURA DE VIGAS DE BORDA (m) | H10: ÁREA TOTAL DE VIGAS m2) | I10: ÁREA TOTAL DE REV. ARGAMASSADO EM ESTRUTURA - INTERNO (m2) | J10: ÁREA DE REBOCO E CHAPISCO EM ESTRUTURA | K10: ÁREA DE TEXTURA EM ESTRUTURA | L10: ÁREA DE EMASSAMENTO E PINTURA EM ESTRUTURA
B11: TÉRREO | C11: =(16*0.74)+(2*1.9)+(4*3.1)+3.2 -> 31.24 | D11: 3.52 | E11: =D11*C11 -> 109.9648 | F11: =(20+39+20)*2 -> 158 | G11: 0.7 | H11: =G11*F11 -> 110.6 | I11: =SUM(E11,H11,H12,E12) -> 561.8615 | J11: =I11 -> 561.8615 | K11: =J11 -> 561.8615
C12: =(8*3)+(2*3.6)+(4*3.4)+(2*1.2)+1.05+(2*2.85)+0.455 -> 54.405 | D12: 4.14 | E12: =D12*C12 -> 225.2367 | F12: =(16.95+1.5+4.5+1.5+17)*2 -> 82.9 | G12: 1.4 | H12: =G12*F12 -> 116.06
B13: G1 | C13: =(16*0.74)+(4*1.2)+(2*1.4) -> 19.44 | D13: 2.26 | E13: =D13*C13 -> 43.9344 | F13: =(F11+38)*2 -> 392 | G13: 0.7 | H13: =G13*F13 -> 274.4 | I13: =SUM(H13,E13,E14) -> 475.0208 | J13: =I13 -> 475.0208 | K13: =I13 -> 475.0208
C14: =C12 -> 54.405 | D14: 2.88 | E14: =D14*C14 -> 156.6864
B15: G2 | C15: =C13 -> 19.44 | D15: =D13 -> 2.26 | E15: =D15*C15 -> 43.9344 | F15: =F13 -> 392 | G15: 0.7 | H15: =G15*F15 -> 274.4 | I15: =SUM(H15,E15,E16) -> 475.0208 | J15: =I15 -> 475.0208 | K15: =I15 -> 475.0208
C16: =C14 -> 54.405 | D16: =D14 -> 2.88 | E16: =D16*C16 -> 156.6864
B17: G3 | C17: =4*0.7 -> 2.8 | D17: 2.6 | E17: =D17*C17 -> 7.28 | F17: =(10.75+5.5+10.49+10.75+22.54+21.49)*2 -> 163.04 | G17: 0.6 | H17: =F17*G17 -> 97.824 | I17: =SUM(H17:H20,E17:E19) -> 328.74 | J17: =I17 -> 328.74 | K17: =I17 -> 328.74
C18: =(6*3)+(4*3.1)+(2*3.3) -> 37 | D18: 2.48 | E18: =D18*C18 -> 91.76 | F18: =2*22.75 -> 45.5 | G18: 0.7 | H18: =F18*G18 -> 31.85
C19: =(0.6)+(11*0.7)+(4*1.2)+(2*1.4) -> 15.9 | D19: 2.99 | E19: =D19*C19 -> 47.541 | F19: =2*5.7 -> 11.4 | G19: 0.75 | H19: =F19*G19 -> 8.55
E20: =D20*C20 -> 0 | F20: =(11+4.15)*2 -> 30.3 | G20: 1.45 | H20: =F20*G20 -> 43.935
B21: LAZER | C21: =(6*1.5)+(2*2.4)+1.6+2.6+0.6+1.55+1.55 -> 21.7 | D21: 2.73 | E21: =D21*C21 -> 59.241 | G21: 0.7 | H21: =F21*G21 -> 0 | I21: =SUM(H21,E21,E22) -> 175.7262 | J21: =I21 -> 175.7262 | L21: =I21 -> 175.7262
C22: =(3*1.15)+(4*1.5)+(2*1.2)+(2*3)+(2*3.1)+(2*2.85)+(2*0.455)+1+(2.4) -> 34.06 | D22: 3.42 | E22: =D22*C22 -> 116.4852
B23: PAV. TIPO (15X) | C23: =C21 -> 21.7 | D23: 2.37 | E23: =D23*C23 -> 51.429 | G23: 0.7 | H23: =F23*G23 -> 0 | I23: =SUM(H23,E23:E24)*15 -> 1982.268 | J23: =I23 -> 1982.268 | L23: =I23 -> 1982.268
C24: =C22 -> 34.06 | D24: 2.37 | E24: =D24*C24 -> 80.7222
B25: CASA DE MÁQUINAS | E25: =D25*C25 -> 0
E26: =SUM(E11:E25) -> 1190.9015 | F26: =SUM(F11:F25) -> 1275.14 | G26: =SUM(G11:G25) -> 8.4 | H26: =SUM(H11:H25) -> 957.619 | I26: =SUM(I11:I25) -> 3998.6373 | J26: =SUM(J11:J25) -> 3998.6373 | K26: =SUM(K11:K25) -> 1840.6431 | L26: =SUM(L11:L25) -> 2157.9942 | M26: =SUM(M11:M25) -> 0
A29: REVESTIMENTO ARGAMASSADO EM ESTRUTURA EXTERNO
B31: PAVIMENTO | C31: PERÍMETRO DE PILARES (m) | D31: ALTURA DE PILARES (m) | E31: ÁREA TOTAL PILARES EXTERNOS (m2) | F31: PERÍMETRO DE VIGAS (m) | G31: ALTURA DE VIGAS DE BORDA (m) | H31: ÁREA TOTAL DE VIGAS m2) | I31: ÁREA DE BLOCOS DE FACHADA m2 | J31: ÁREA TOTAL DE VER. ARGAMASSADO EM ESTRUTURA - EXTERNO (m2) | K31: ÁREA DE REBOCO E CHAPISCO EM ESTRUTURA | L31: ÁREA DE TEXTURA EM ESTRUTURA | M31: ÁREA DE EMASSAMENTO E PINTURA EM ESTRUTURA
B32: TÉRREO | C32: =(16*0.6)+(6*1.2) -> 16.8 | D32: 3.52 | E32: =D32*C32 -> 59.136 | F32: =F11 -> 158 | G32: 0.7 | H32: =F32*G32 -> 110.6 | J32: =SUM(H32,H33,E32) -> 285.796 | K32: =J32 -> 285.796
F33: =F12 -> 82.9 | G33: 1.4 | H33: =G33*F33 -> 116.06
B34: G1 | C34: =(16*0.6)+(4*1.2)+(2*1.4) -> 17.2 | D34: 2.26 | E34: =D34*C34 -> 38.872 | F34: =F13 -> 392 | G34: =G13 -> 0.7 | H34: =G34*F34 -> 274.4 | J34: =SUM(H34,E34) -> 313.272 | K34: =J34 -> 313.272
B36: G2 | C36: =C34 -> 17.2 | D36: =D34 -> 2.26 | E36: =D36*C36 -> 38.872 | F36: =F15 -> 392 | G36: =G15 -> 0.7 | H36: =G36*F36 -> 274.4 | J36: =SUM(H36,E36) -> 313.272 | K36: =J36 -> 313.272
B38: G3 | C38: =(0.6)+(11*0.7)+(4*1.2)+(2*1.4) -> 15.9 | D38: 2.99 | E38: =D38*C38 -> 47.541 | F38: =F17 -> 163.04 | G38: =G17 -> 0.6 | H38: =F38*G38 -> 97.824 | J38: =SUM(H38:H41,E38:E39) -> 236.98 | K38: =J38 -> 236.98
C39: =C17 -> 2.8 | D39: 2.6 | E39: =D39*C39 -> 7.28 | F39: =F18 -> 45.5 | G39: =G18 -> 0.7 | H39: =F39*G39 -> 31.85
F40: =F19 -> 11.4 | G40: =G19 -> 0.75 | H40: =F40*G40 -> 8.55
F41: =F20 -> 30.3 | G41: =G20 -> 1.45 | H41: =F41*G41 -> 43.935
B42: LAZER | C42: =C21 -> 21.7 | D42: 2.73 | E42: =D42*C42 -> 59.241 | F42: 82.56 | G42: 0.7 | H42: =F42*G42 -> 57.792 | J42: =SUM(H42,E42) -> 117.033 | K42: =J42 -> 117.033
B43: PAV. TIPO (15X) | C43: =C42 -> 21.7 | D43: 2.37 | E43: =D43*C43 -> 51.429 | F43: 82.56 | G43: 0.7 | H43: =F43*G43 -> 57.792 | J43: =SUM(H43,E43)*15 -> 1638.315 | K43: =J43 -> 1638.315
B44: CASA DE MÁQUINAS | C44: 11.04 | D44: 3.59 | E44: =D44*C44 -> 39.6336 | F44: =0.87+5.57+0.87+2.03+0.6+2.6+0.25+7.5+0.25+2.6+0.6+2.03 -> 25.77 | G44: 0.7 | H44: =F44*G44 -> 18.039 | J44: =SUM(H44,E44) -> 57.6726 | K44: =J44 -> 57.6726
B45: RESERVATÓRIO | F45: 18.56 | G45: 3.69 | H45: =F45*G45 -> 68.4864 | J45: =SUM(H45,E45) -> 68.4864
E46: =SUM(E32:E44) -> 342.0046 | H46: =SUM(H32:H45) -> 1159.7284 | I46: ='[10]REV. FACHADA'!D16 -> 576.54 | J46: =SUM(J32:J45) -> 3030.827 | K46: =SUM(K32:K44) -> 2962.3406 | L46: =SUM(L32:L44) -> 0 | M46: =SUM(M32:M44) -> 0 | N46: =SUM(N32:N44) -> 0 | O46: =N46/D46 -> #DIV/0!

Sheet CHURRASQUEIRA
A1: Obra | B1: West Village
A2: Empresa | B2: Kirchner
A3: Revisão | B3: R03
A4: LEVANTAMENTO QUANTITATIVO
A6: Churrasqueira
A8: Churrasqueira - área unitária
B10: LAZER = 2 | C10: Unidade | D10: Quantidade
B11: Perímetro | C11: m | D11: =1.1+1.1+0.7+0.7 -> 3.6
B12: Altura | C12: m | D12: 1.2
B13: Área piso | C13: m² | D13: =(1.1*0.7) -> 0.77
B14: Área boca | C14: m² | D14: =(0.6*0.6) -> 0.36
B15: Área de refratário | C15: m² | D15: =D11*D12+D13-D14 -> 4.73
B16: Apartamentos =6*15 = 90 | C16: Unidade | D16: Quantidade
B17: Perímetro | C17: m | D17: =((0.6+0.7)*2) -> 2.6
B18: Altura | C18: m | D18: 1.2
B19: Área piso | C19: m² | D19: =(0.6*0.7) -> 0.42
B20: Área boca | C20: m² | D20: =(0.6*0.6) -> 0.36
B21: Área de refratário | C21: m² | D21: =D17*D18+D19-D20 -> 3.18
A23: Churrasqueira - total
B25: Descrição | C25: Quantidade | D25: Área (m²)
B26: LAZER | C26: 2 | D26: =D15*C26 -> 9.46
B27: APARTAMENTOS | C27: =6*15 -> 90 | D27: =C27*D21 -> 286.2
B29: Descrição | C29: Tamanho | D29: Área (m²)
B30: LAZER | C30: 5 cm | D30: =D26 -> 9.46
B31: APARTAMENTOS | C31: 5 cm | D31: =D27 -> 286.2

Sheet IMPER
B1: IMPERMEABILIZAÇÃO - KIRCHNER
E5: 1 | F5: 3 | G5: 1 | H5: 15 | I5: 1
B6: COZINHAS | D6: TOTAL | E6: TÉRREO | F6: GARAGEM (X3) | G6: LAZER | H6: tipo (x15) | I6: TELHADO
B7: Altura parede | C7: m | E7: 0.4 | F7: 0.4 | G7: 0.4 | H7: 0.4 | I7: 0.4
B8: Paredes - perimetro | C8: m | D8: =SUMPRODUCT(E8:I8,E5:I5) -> 276.58 | G8: =3.15+3.88 -> 7.03 | H8: =2.67+3+3+3+3.15+3.15 -> 17.97 | I8: 0
B9: Área parede | C9: m2 | D9: =SUMPRODUCT(E9:I9,E5:I5) -> 110.632 | E9: =E8*E7 -> 0 | F9: =F8*F7 -> 0 | G9: =G8*G7 -> 2.812 | H9: =H8*H7 -> 7.188 | I9: =I8*I7 -> 0
B10: Piso | C10: m2 | D10: =SUMPRODUCT(E10:I10,E5:I5) -> 276.58 | E10: =1*E8 -> 0 | F10: =1*F8 -> 0 | G10: =1*G8 -> 7.03 | H10: =1*H8 -> 17.97 | I10: =1*I8 -> 0
B11: IMPERMEABILIZANTE EM COZINHA | H11: m2 | I11: =SUM(D9:D10) -> 387.212
B12: * CONSIDERADO 1 METRO A FRENTE DA PAREDE
E13: 1 | F13: 3 | G13: 1 | H13: 15 | I13: 1
B14: BANHEIROS | D14: TOTAL | E14: TÉRREO | F14: GARAGEM (X3) | G14: =G6 -> LAZER | H14: =H6 -> tipo (x15) | I14: =I6 -> TELHADO
A15: BOX BANHEIRO | B15: Altura parede | C15: m | E15: 1.5 | F15: 1.5 | G15: 1.5 | H15: 1.5 | I15: 1.5
B16: Paredes - perimetro | C16: m | D16: =SUMPRODUCT(E16:I16,E13:I13) -> 399.14 | E16: 0 | G16: =(1.3*1)+(0.9*2)+1.57+ 1.36+1.36+2.35 -> 9.74 | H16: =(((1.2)+(1.18*2))*2)+((1.2)+(0.88*2)*6)+((1.1)+0.88)+1.08+0.92+((0.95*2)+1.2) -> 25.96
B17: Área parede | C17: m2 | D17: =SUMPRODUCT(E17:I17,E13:I13) -> 598.71 | E17: =E16*E15 -> 0 | F17: =F16*F15 -> 0 | G17: =G16*G15 -> 14.61 | H17: =H16*H15 -> 38.94 | I17: =I16*I15 -> 0
B18: Piso | C18: m2 | D18: =SUMPRODUCT(E18:I18,E13:I13) -> 188.234 | G18: =1.14+3.05 -> 4.19 | H18: =(1.2*1.18)+((1.2*0.88)*6)+(1.1*0.88)+(0.95*1.2)+(1.08*0.92)+(1.18*1.2) -> 12.2696
A19: BANHEIRO | B19: Altura parede | C19: m | E19: 0.4 | F19: 0.4 | G19: 0.4 | H19: 0.4 | I19: 0.4
B20: Paredes - perimetro | C20: m | D20: =SUMPRODUCT(E20:I20,E13:I13) -> 554.1 | E20: 0 | G20: =(1.3*1)+(1.45*2) -> 4.2 | H20: =1.95+1.95+1.2+1.6+1.6+1.2+0.8+1.7+1.96+0.75+1.6+1.6+1.2+1.58+1.58+1.2+1.58+1.58+1.58+1.58+1.2+1.2+1.6+1.6+1.2+0.78+1.91+0.94+0.82+1.6+1.6+1.2+1.94+1.94+1.2-13.86 -> 36.66
B21: Área parede | C21: m2 | D21: =SUMPRODUCT(E21:I21,E13:I13) -> 221.64 | E21: =E20*E19 -> 0 | F21: =F20*F19 -> 0 | G21: =G20*G19 -> 1.68 | H21: =H20*H19 -> 14.664 | I21: =I20*I19 -> 0
B22: Piso | C22: m2 | D22: =SUMPRODUCT(E22:I22,E13:I13) -> 573.99 | E22: 0 | G22: =1.89 -> 1.89 | H22: =3.78+3+3.23+3.06+3+3+3+3+3.78+3.06+3+3.23-I18 -> 38.14
B23: IMPERMEABILIZANTE EM BOX BANHEIRO | H23: m2 | I23: =SUM(D17:D18) -> 786.944
B24: IMPERMEABILIZANTE EM BANHEIRO | H24: m2 | I24: =SUM(D21:D22) -> 795.63 | K24: =SUM(I24,I23,I33,I11,I50) -> 2866.276
B25: *ÁREA PISO DE BANHEIRO, JÁ FOI DESCONTADA DA ÁREA DO BOX
B26: *ÁREA DE DUCHA FOI CONSIDERADA EM BOX DE BANHEIRO
E27: 1 | F27: 3 | G27: 1 | H27: 15 | I27: 1
B28: SACADAS | D28: TOTAL | E28: TÉRREO | F28: GARAGEM (X3) | G28: =G6 -> LAZER | H28: =H6 -> tipo (x15) | I28: =I6 -> TELHADO
B29: Altura parede | C29: m | E29: 0.4 | F29: 0.4 | G29: 0.4 | H29: 0.4 | I29: 0.4
B30: Paredes - perimetro | C30: m | D30: =SUMPRODUCT(E30:I30,E27:I27) -> 388.35 | H30: =0.57+0.2+2.52+2.1+2.1+0.2+2.65+1.94+0.76+2.65+1.94+0.76+2.1+2.1+0.15+2.4+0.75 -> 25.89 | I30: 0
B31: Área parede | C31: m2 | D31: =SUMPRODUCT(E31:I31,E27:I27) -> 155.34 | E31: =E30*E29 -> 0 | F31: =F30*F29 -> 0 | G31: =G30*G29 -> 0 | H31: =H30*H29 -> 10.356 | I31: =I30*I29 -> 0
B32: Piso | C32: m2 | D32: =SUMPRODUCT(E32:I32,E27:I27) -> 489 | H32: =6.05+5.65+4.6+4.6+6.05+5.65 -> 32.6 | I32: 0
B33: IMPERMEABILIZANTE EM SACADA | H33: m2 | I33: =SUM(D31:D32) -> 644.34
E35: 1 | F35: 3 | G35: 1 | H35: 15 | I35: 1
B36: TERRAÇOS | D36: TOTAL | E36: TÉRREO | F36: GARAGEM (X3) | G36: =G6 -> LAZER | H36: =H6 -> tipo (x15) | I36: =I6 -> TELHADO | K36: =I41 -> 888.874
B37: Altura parede | C37: m | E37: 0.4 | F37: 0.4 | G37: 0.4 | H37: 0.4 | I37: 0.4
B38: Paredes - perimetro | C38: m | D38: =SUMPRODUCT(E38:I38,E35:I35) -> 343.66 | G38: =11.05+4.45+0.3+2.95+0.5+3.95+3.95+1+1.6+4.45+10+2.9+4.4+6.5+5.35+5.35+9.3+5.35+2+2.2+0.15+22.6+5.38+ 1.45+2.4+2.7+0.7+3.1+ 0.65+ 2.8+ 2.25+0.7+2.45+1.2+ 21 -> 157.08 | I38: =27.3+17.03+99.39+28.86+14 -> 186.58
B39: Área parede | C39: m2 | D39: =SUMPRODUCT(E39:I39,E35:I35) -> 137.464 | E39: =E38*E37 -> 0 | G39: =G38*G37 -> 62.832 | H39: =H38*H37 -> 0 | I39: =I38*I37 -> 74.632 | K39: a | L39: p
B40: Piso | C40: m2 | D40: =SUMPRODUCT(E40:I40,E35:I35) -> 751.41 | G40: =23.8+31.3+49.75+59.65+134 -> 298.5 | I40: =26.14+15.77+(468.22-51.1-6.12) -> 452.91 | K40: 51.1 | L40: 28.86
B41: MANTA IMPERMEABILIZANTE À BASE DE ASFALTO EM TERRAÇOS | H41: m2 | I41: =SUM(D39:D40) -> 888.874 | K41: 468.22 | L41: 99.39
B42: *CONSIDERADA IMPER DA COBERTURA | K42: =2*3.06 -> 6.12 | L42: =2*7 -> 14
B43: *CONSIDERADO ÁREA ESPORTIVA, TERRAÇO PISCINA E PLAYGROUND
E44: 1 | F44: 3 | G44: 1 | H44: 15 | I44: 1
B45: LAJE SPLIT | D45: TOTAL | E45: TÉRREO | F45: GARAGEM (X3) | G45: =G6 -> LAZER | H45: =H6 -> tipo (x15) | I45: =I6 -> TELHADO
B46: Altura parede | C46: m | F46: 0.5 | G46: 0.5 | H46: 0.5 | I46: 0.5
B47: Paredes - perimetro | C47: m | D47: =SUMPRODUCT(E47:I47,E44:I44) -> 282.15 | H47: =2.95+1+4.45+1+4.46+1+2.95+1 -> 18.81 | I47: 0
B48: Área parede | C48: m2 | D48: =SUMPRODUCT(E48:I48,E44:I44) -> 141.075 | E48: =E47*E46 -> 0 | F48: =F47*F46 -> 0 | G48: =G47*G46 -> 0 | H48: =H47*H46 -> 9.405 | I48: =I47*I46 -> 0
B49: Piso | C49: m2 | D49: =SUMPRODUCT(E49:I49,E44:I44) -> 111.075 | H49: =(2.95*0.5)+(4.45*0.5)+(4.46*0.5)+(2.95*0.5) -> 7.405 | I49: 0
B50: MANTA IMPERMEABILIZANTE À BASE DE ASFALTO EM LAJE | H50: m2 | I50: =SUM(D48:D49) -> 252.15
E54: 1 | F54: 3 | G54: 1 | H54: 15 | I54: 1
B55: CAIXA D' ÁGUA | D55: TOTAL | E55: TÉRREO | F55: GARAGEM (X3) | G55: =G6 -> LAZER | H55: =H6 -> tipo (x15) | I55: =I6 -> TELHADO
B56: Altura parede | C56: m | E56: 1.75 | I56: 1.04
B57: Paredes - perimetro | C57: m | D57: =SUMPRODUCT(E57:I57,E54:I54) -> 56.03 | E57: =(5.2+3.3+4.3+0.9+2.8+0.5+8.5+8.5+2.5+2.5) -> 39 | I57: 17.03
B58: Área parede | C58: m2 | D58: =SUMPRODUCT(E58:I58,E54:I54) -> 85.9612 | E58: =E57*E56 -> 68.25 | F58: =F57*F56 -> 0 | G58: =G57*G56 -> 0 | H58: =H57*H56 -> 0 | I58: =I57*I56 -> 17.7112
B59: Piso | C59: m2 | D59: =SUMPRODUCT(E59:I59,E54:I54) -> 69.5 | E59: =16.71+21.25 -> 37.96 | I59: =15.77*2 -> 31.54
B60: IMPERMEABILIZANTE CAIXA DA ÁGUA | H60: m2 | I60: =SUM(D58:D59) -> 155.4612
B61: *CONSIDERADA ÁREA DE PISO x2 (CONSIDERANDO TAMPA)
E63: 1 | F63: 1 | G63: 1 | H63: 15 | I63: 1
B64: PISCINAS | D64: TOTAL | E64: TÉRREO | F64: LAZER | G64: =G6 -> LAZER | H64: =H6 -> tipo (x15) | I64: =I6 -> TELHADO
B65: Altura parede | C65: m | F65: 0.5 | G65: 1.4
B66: Paredes - perimetro | C66: m | D66: =SUMPRODUCT(E66:I66,E63:I63) -> 47.72 | F66: =10.37+6.6 -> 16.97 | G66: =2.2+3.25+12+3.5+9.8 -> 30.75
B67: Área parede | C67: m2 | D67: =SUMPRODUCT(E67:I67,E63:I63) -> 51.535 | E67: =E66*E65 -> 0 | F67: =F66*F65 -> 8.485 | G67: =G66*G65 -> 43.05 | H67: =H66*H65 -> 0 | I67: =I66*I65 -> 0
B68: Piso | C68: m2 | D68: =SUMPRODUCT(E68:I68,E63:I63) -> 56.6 | F68: 15.15 | G68: =41.45 -> 41.45
B69: MANTA IMPERMEABILIZANTE À BASE DE ASFALTO PISCINAS | H69: m2 | I69: =SUM(D67:D68) -> 108.135
E71: 1 | F71: 3 | G71: 1 | H71: 15 | I71: 1
B72: POÇO ELEVADOR | D72: TOTAL | E72: TÉRREO | F72: GARAGEM (X3) | G72: =G64 -> LAZER | H72: =H64 -> tipo (x15) | I72: =I64 -> TELHADO
B73: Altura parede | C73: m | E73: 0.8 | H73: 0 | I73: 0
B74: Paredes - perimetro | C74: m | D74: =SUMPRODUCT(E74:I74,E71:I71) -> 15 | E74: =((2+1.75)*2)*2 -> 15
B75: Área parede | C75: m2 | D75: =SUMPRODUCT(E75:I75,E71:I71) -> 12 | E75: =E74*E73 -> 12 | F75: =F74*F73 -> 0 | G75: =G74*G73 -> 0 | H75: =H74*H73 -> 0 | I75: =I74*I73 -> 0
B76: Piso | C76: m2 | D76: =SUMPRODUCT(E76:I76,E71:I71) -> 7 | E76: 7
B77: PINTURA ASFALTICA EM POÇOS | H77: m2 | I77: =SUM(D75:D76) -> 19
B78: *CONSIDERADO ÁREA DE PAREDES x2 (DENTRO E FORA)
E80: 1 | F80: 3 | G80: 1 | H80: 15 | I80: 1
B81: BALDRAMES | D81: TOTAL | E81: TÉRREO | F81: GARAGEM (X3) | G81: =G72 -> LAZER | H81: =H72 -> tipo (x15) | I81: =I72 -> TELHADO
B82: Altura parede | C82: m
B83: Paredes - perimetro | C83: m | D83: =SUMPRODUCT(E83:I83,E80:I80) -> 0
B84: Área parede | C84: m2 | D84: =SUMPRODUCT(E84:I84,E80:I80) -> 0 | E84: =E83*E82 -> 0 | F84: =F83*F82 -> 0 | G84: =G83*G82 -> 0 | H84: =H83*H82 -> 0 | I84: =I83*I82 -> 0
B86: PINTURA ASFALTICA EM BALDRAMES | H86: m2 | I86: 804.43
E89: 1 | F89: 3 | G89: 1 | H89: 15 | I89: 1
B90: GARAGEM | D90: TOTAL | E90: TÉRREO | F90: GARAGEM (X3) | G90: =G81 -> LAZER | H90: =H81 -> tipo (x15) | I90: =I81 -> TELHADO
B91: Altura parede | C91: m | E91: 0.4 | F91: 0.4 | H91: 0 | I91: 0
B92: Paredes - perimetro | C92: m | D92: =SUMPRODUCT(E92:I92,E89:I89) -> 699.88 | E92: =6.85+5+ 1.1+0.9+1+14.25+2.75+5+18.23+5+ 1.5+0.7+1.64+1.55+6.5+0.6+6.65+5.6+11.62+2 -> 98.44 | F92: =14.7+14.7+21.26+39+21.26+5.75+0.5+6.76+5.75+0.2+2.6+0.6+0.25+1.05+0.15+0.15+1.05+0.25+1.2+2.6+0.6+2.65+6.8+2.65+(3*16) -> 200.48
B93: Área parede | C93: m2 | D93: =SUMPRODUCT(E93:I93,E89:I89) -> 157.504 | E93: =E92*E91 -> 39.376 | F93: =E92*F91 -> 39.376 | G93: =G92*G91 -> 0 | H93: =H92*H91 -> 0 | I93: =I92*I91 -> 0
B94: Piso | C94: m2 | D94: =SUMPRODUCT(E94:I94,E89:I89) -> 1126.5 | E94: 116.7 | F94: 336.6
B95: MANTA IMPERMEABILIZANTE À BASE DE ASFALTO EM GARAGENS | H95: m2 | I95: =SUM(D93:D94) -> 1284.004
B96: *CONSIDERADA RAMPA GARAGENS, E ÁREA COBERTA GARAGENS,
E98: 1 | F98: 3 | G98: 1 | H98: 1 | I98: 1
B99: ESQUADRIAS | D99: TOTAL | E99: TÉRREO | F99: GARAGEM (X3) | G99: =G90 -> LAZER | H99: =H90 -> tipo (x15) | I99: =I90 -> TELHADO
B100: PEITORIL | C100: m2 | D100: =SUMPRODUCT(E100:I100,E98:I98) -> 72.77 | E100: 0 | F100: 0 | G100: 0.22 | H100: =4.95+27.1+27+13.5 -> 72.55 | I100: 0
B101: IMPERMEABILIZANTE EM ESQUADRIAS | H101: m2 | I101: =SUM(D100:D100) -> 72.77
B104: RALOS | D104: TOTAL | E104: TÉRREO | F104: GARAGEM (X3) | G104: LAZER | H104: TIPO 15X | I104: TELHADO
B105: RALOS | C105: UN | D105: =SUM(E105:I105) -> 370 | E105: 4 | F105: =6*3 -> 18 | G105: 10 | H105: =22*15 -> 330 | I105: 8
B106: TRATAMENTO DE RALOS - IMPERMEABILIZAÇÃO | H106: UN | I106: =SUM(D105:D105) -> 370

Sheet HIDRÁULICAS
A1: Obra | B1: WEST VILLAGE
A2: Empresa | B2: KIRCHNER
A3: Revisão | B3: R00
A4: QUANTIFICAÇÃO
A6: Instalações hidráulicas
A8: Geral
B10: Descrição quantitativo | D10: Quantidade | E10: Unidade | F10: Preço unitário | G10: Preço total
B11: AGUA FRIA | G11: =SUM(G12:G129) -> 203301.49
B12: Tubo de PPR PN20 | C12: 110 | D12: ='[11]Lista de Materiais'!$B$131 -> 14.75 | E12: m | F12: =539.72/3 -> 179.90667 | G12: =F12*D12 -> 2653.6233
B13: Tubo de PPR PN20 | C13: 25 | D13: ='[11]Lista de Materiais'!$B$132 -> 0.08 | E13: m | F13: =46.9/3 -> 15.633333 | G13: =F13*D13 -> 1.2506667
B14: Tubo de PPR PN20 | C14: 32 | D14: ='[11]Lista de Materiais'!$B$133 -> 4.58 | E14: m | F14: =79/3 -> 26.333333 | G14: =F14*D14 -> 120.60667
B15: Tubo de PPR PN20 | C15: 40 | D15: ='[11]Lista de Materiais'!$B$134 -> 32.04 | E15: m | F15: =104/3 -> 34.666667 | G15: =F15*D15 -> 1110.72
B16: Tubo de PPR PN20 | C16: 50 | D16: ='[11]Lista de Materiais'!$B$135 -> 44.91 | E16: m | F16: =141/3 -> 47 | G16: =F16*D16 -> 2110.77
B17: Tubo de PPR PN20 | C17: 63 | D17: ='[11]Lista de Materiais'!$B$136 -> 1.57 | E17: m | F17: =218.76/4 -> 54.69 | G17: =F17*D17 -> 85.8633
B18: Tubo de PPR PN20 | C18: 75 | D18: ='[11]Lista de Materiais'!$B$137 -> 68.98 | E18: m | F18: =292/3 -> 97.333333 | G18: =F18*D18 -> 6714.0533
B19: Tubo de PPR PN20 | C19: 90 | D19: ='[11]Lista de Materiais'!$B$138 -> 100.71 | E19: m | F19: =317.11/3 -> 105.70333 | G19: =F19*D19 -> 10645.383
B20: Tubo de cobre DN79 | D20: ='[11]Lista de Materiais'!$B$130 -> 10.51 | E20: m | F20: =1311.46/5 -> 262.292 | G20: =F20*D20 -> 2756.6889
B21: Tubo de PVC Rígido Soldável Marrom | C21: 25 | D21: ='[11]Lista de Materiais'!$B$140 -> 2913.09 | E21: m | F21: 3.08 | G21: =F21*D21 -> 8972.3172
B22: Tubo de PVC Rígido Soldável Marrom | C22: 32 | D22: ='[11]Lista de Materiais'!$B$141 -> 2089.99 | E22: m | F22: 7.91 | G22: =F22*D22 -> 16531.821
B23: Tubo de PVC Rígido Soldável Marrom | C23: 40 | D23: ='[11]Lista de Materiais'!$B$142 -> 22.96 | E23: m | F23: =40.9/3 -> 13.633333 | G23: =F23*D23 -> 313.02133
B24: Tubo de PVC Rígido Soldável Marrom | C24: 50 | D24: ='[11]Lista de Materiais'!$B$143 -> 36.85 | E24: m | F24: 11.85 | G24: =F24*D24 -> 436.6725
B25: Tubo de PVC Rígido Soldável Marrom | C25: 75 | D25: ='[11]Lista de Materiais'!$B$144 -> 6.37 | E25: m | F25: =260.25/6 -> 43.375 | G25: =F25*D25 -> 276.29875
B26: Tubo de PVC Rígido Soldável Marrom | C26: 85 | D26: ='[11]Lista de Materiais'!$B$145 -> 23.18 | E26: m | F26: =315.03/6 -> 52.505 | G26: =F26*D26 -> 1217.0659
B27: Tubo de PVC Rígido Soldável Marrom | C27: 110 | D27: ='[11]Lista de Materiais'!$B$139 -> 14.46 | E27: m | F27: =553/6 -> 92.166667 | G27: =F27*D27 -> 1332.73
B28: Adaptador Soldável Curto com Bolsa e Rosca, DN25x3/4'', PVC Marrom Soldável, conforme NBR 5648 | D28: ='[11]Lista de Materiais'!$B$10 -> 1006 | E28: pç | F28: 0.66 | G28: =F28*D28 -> 663.96
B29: Adaptador Soldável Curto com Bolsa e Rosca, DN32x1'', PVC Marrom Soldável, conforme NBR 5649 | D29: ='[11]Lista de Materiais'!$B$11 -> 553 | E29: pç | F29: 1.66 | G29: =F29*D29 -> 917.98
B30: Adaptador Soldável Curto com Bolsa e Rosca, DN40x1.1/4'', PVC Marrom Soldável, conforme NBR 5648 | D30: ='[11]Lista de Materiais'!$B$12 -> 3 | E30: pç | F30: 7.75 | G30: =F30*D30 -> 23.25
B31: Adaptador Soldável Curto com Bolsa e Rosca, DN50x1.1/2'', PVC Marrom Soldável, conforme NBR 5648 | D31: ='[11]Lista de Materiais'!$B$13 -> 1 | E31: pç | F31: 2.96 | G31: =F31*D31 -> 2.96
B32: Adaptador Soldável Curto com Bolsa e Rosca, DN60x2'', PVC Marrom Soldável, conforme NBR 5648 | D32: ='[11]Lista de Materiais'!$B$14 -> 1 | E32: pç | F32: 17.09 | G32: =F32*D32 -> 17.09
B33: Adaptador Soldável Curto com Bolsa e Rosca, DN75x2.1/2'', PVC Marrom Soldável, conforme NBR 5649 | D33: ='[11]Lista de Materiais'!$B$15 -> 3 | E33: pç | F33: 20.17 | G33: =F33*D33 -> 60.51
B34: Adaptador Soldável Curto com Bolsa e Rosca, DN85x3'', PVC Marrom Soldável, conforme NBR 5650 | D34: ='[11]Lista de Materiais'!$B$16 -> 2 | E34: pç | F34: 27.8 | G34: =F34*D34 -> 55.6
B35: Bucha de Redução, 40x32mm, PPR PN20 | D35: ='[11]Lista de Materiais'!$B$31 -> 2 | E35: pç | F35: 7.24 | G35: =F35*D35 -> 14.48
B36: Bucha de Redução, 50x32mm, PPR PN20 | D36: ='[11]Lista de Materiais'!$B$32 -> 2 | E36: pç | F36: 12 | G36: =F36*D36 -> 24
B37: Bucha de Redução, 63x40mm, PPR PN20 | D37: ='[11]Lista de Materiais'!$B$33 -> 12 | E37: pç | F37: 20.53 | G37: =F37*D37 -> 246.36
B38: Bucha de Redução, 63x50mm, PPR PN20 | D38: ='[11]Lista de Materiais'!$B$34 -> 4 | E38: pç | F38: 26.9 | G38: =F38*D38 -> 107.6
B39: Bucha de Redução, 75x50mm, PPR PN20 | D39: ='[11]Lista de Materiais'!$B$35 -> 4 | E39: pç | F39: 33.9 | G39: =F39*D39 -> 135.6
B40: Bucha de Redução, 90x63mm, PPR PN20 | D40: ='[11]Lista de Materiais'!$B$36 -> 2 | E40: pç | F40: 51.8 | G40: =F40*D40 -> 103.6
B41: Bucha de Redução, 90x75mm, PPR PN20 | D41: ='[11]Lista de Materiais'!$B$37 -> 3 | E41: pç | F41: 68.67 | G41: =F41*D41 -> 206.01
B42: Bucha de Redução, 110x90mm, PPR PN20 | D42: ='[11]Lista de Materiais'!$B$38 -> 2 | E42: pç | F42: 173.63 | G42: =F42*D42 -> 347.26
B43: Bucha de Redução Curta, DN32x25mm, PVC Marrom Soldável, conforme NBR 5648 | D43: ='[11]Lista de Materiais'!$B$39 -> 133 | E43: pç | F43: 0.73 | G43: =F43*D43 -> 97.09
B44: Bucha de Redução Longa, DN50 x 32mm, PVC Marrom Soldável, conforme NBR 5648 | D44: ='[11]Lista de Materiais'!$B$40 -> 1 | E44: pç | F44: 3.01 | G44: =F44*D44 -> 3.01
B45: Bucha de Redução Longa, DN85 x 60mm, PVC Marrom Soldável, conforme NBR 5648 | D45: ='[11]Lista de Materiais'!$B$41 -> 1 | E45: pç | F45: 23.9 | G45: =F45*D45 -> 23.9
B46: Conector Bolsa x rosca 3", cobre | D46: ='[11]Lista de Materiais'!$B$19 -> 2 | E46: pc | F46: 128.21 | G46: =F46*D46 -> 256.42
B47: Conector Fêmea 32x1", PPR PN 20 | D47: ='[11]Lista de Materiais'!$B$20 -> 3 | E47: pc | F47: 23.4 | G47: =F47*D47 -> 70.2
B48: Conector Fêmea 50x1.1/2", PPR PN 20 | D48: ='[11]Lista de Materiais'!$B$21 -> 3 | E48: pc | F48: 100.9 | G48: =F48*D48 -> 302.7
B49: Conector Macho 25x3/4", PPR PN 20 | D49: ='[11]Lista de Materiais'!$B$22 -> 2 | E49: pc | F49: 27.4 | G49: =F49*D49 -> 54.8
B50: Conector Macho 32x1", PPR PN 20 | D50: ='[11]Lista de Materiais'!$B$23 -> 96 | E50: pc | F50: 33.96 | G50: =F50*D50 -> 3260.16
B51: Conector Macho 50x1.1/2", PPR PN 20 | D51: ='[11]Lista de Materiais'!$B$24 -> 31 | E51: pc | F51: 124.11 | G51: =F51*D51 -> 3847.41
B52: Conector Macho 75x2.1/2", PPR PN 20 | D52: ='[11]Lista de Materiais'!$B$25 -> 9 | E52: pc | F52: 200.2 | G52: =F52*D52 -> 1801.8
B53: Conector Macho 90x3", PPR PN 20 | D53: ='[11]Lista de Materiais'!$B$26 -> 16 | E53: pc | F53: 436 | G53: =F53*D53 -> 6976
B54: Conector Macho 100x4", PPR PN 20 | D54: ='[11]Lista de Materiais'!$B$27 -> 4 | E54: pc | F54: 504.51 | G54: =F54*D54 -> 2018.04
B55: Curva 90°, DN32mm, PVC Marrom Soldável | D55: ='[11]Lista de Materiais'!$B$46 -> 23 | E55: pç | F55: 6.23 | G55: =F55*D55 -> 143.29
B56: Curva 90°, DN40mm, PVC Marrom Soldável | D56: ='[11]Lista de Materiais'!$B$47 -> 6 | E56: pç | F56: 12.74 | G56: =F56*D56 -> 76.44
B57: Curva de Transposição Soldável, DN25mm, PVC Marrom Soldável | D57: ='[11]Lista de Materiais'!$B$49 -> 346 | E57: pç | F57: 10.36 | G57: =F57*D57 -> 3584.56
B58: Curva de Transposição Soldável, DN32mm, PVC Marrom Soldável | D58: ='[11]Lista de Materiais'!$B$50 -> 105 | E58: pç | F58: 14.87 | G58: =F58*D58 -> 1561.35
B59: Joelho 45º, DN 40mm, PPR PN20 | D59: ='[11]Lista de Materiais'!$B$60 -> 6 | E59: pç | F59: 13.99 | G59: =F59*D59 -> 83.94
B60: Joelho 45º, DN 50mm, PPR PN20 | D60: ='[11]Lista de Materiais'!$B$61 -> 2 | E60: pç | F60: 20.3 | G60: =F60*D60 -> 40.6
B61: Joelho 45°, DN25mm, PVC Marrom Soldável | D61: ='[11]Lista de Materiais'!$B$62 -> 1 | E61: pç | F61: 1.23 | G61: =F61*D61 -> 1.23
B62: Joelho 45°, DN32mm, PVC Marrom Soldável | D62: ='[11]Lista de Materiais'!$B$63 -> 106 | E62: pç | F62: 4.74 | G62: =F62*D62 -> 502.44
B63: Joelho 45°, DN40mm, PVC Marrom Soldável | D63: ='[11]Lista de Materiais'!$B$64 -> 4 | E63: pç | F63: 6.9 | G63: =F63*D63 -> 27.6
B64: Joelho 45°, DN85mm, PVC Marrom Soldável | D64: ='[11]Lista de Materiais'!$B$65 -> 2 | E64: pç | F64: 67.22 | G64: =F64*D64 -> 134.44
B65: Joelho 90° 3", cobre | D65: ='[11]Lista de Materiais'!$B$66 -> 4 | E65: pç | F65: 339.9 | G65: =F65*D65 -> 1359.6
B66: Joelho 90º, DN 40mm, PPR PN20 | D66: ='[11]Lista de Materiais'!$B$67 -> 22 | E66: pç | F66: 6.4 | G66: =F66*D66 -> 140.8
B67: Joelho 90º, DN 50mm, PPR PN20 | D67: ='[11]Lista de Materiais'!$B$68 -> 14 | E67: pç | F67: 13.9 | G67: =F67*D67 -> 194.6
B68: Joelho 90º, DN 63mm, PPR PN20 | D68: ='[11]Lista de Materiais'!$B$69 -> 1 | E68: pç | F68: 21.67 | G68: =F68*D68 -> 21.67
B69: Joelho 90º, DN 75mm, PPR PN20 | D69: ='[11]Lista de Materiais'!$B$70 -> 13 | E69: pç | F69: 31.9 | G69: =F69*D69 -> 414.7
B70: Joelho 90º, DN 90mm, PPR PN20 | D70: ='[11]Lista de Materiais'!$B$71 -> 20 | E70: pç | F70: 45.21 | G70: =F70*D70 -> 904.2
B71: Joelho 90º, DN 110mm, PPR PN20 | D71: ='[11]Lista de Materiais'!$B$72 -> 6 | E71: pç | F71: 249.49 | G71: =F71*D71 -> 1496.94
B72: Joelho 90° de Latão, 3/4x1/2', Linha PVC branco | D72: ='[11]Lista de Materiais'!$B$73 -> 630 | E72: pç | F72: 8.1 | G72: =F72*D72 -> 5103
B73: Joelho 90°, DN25mm, PVC Marrom Soldável | D73: ='[11]Lista de Materiais'!$B$76 -> 2652 | E73: pç | F73: 0.53 | G73: =F73*D73 -> 1405.56
B74: Joelho 90°, DN32mm, PVC Marrom Soldável | D74: ='[11]Lista de Materiais'!$B$77 -> 510 | E74: pç | F74: 3.19 | G74: =F74*D74 -> 1626.9
B75: Joelho 90°, DN50mm, PVC Marrom Soldável | D75: ='[11]Lista de Materiais'!$B$78 -> 6 | E75: pç | F75: 6.65 | G75: =F75*D75 -> 39.9
B76: Joelho 90°, DN75mm, PVC Marrom Soldável | D76: ='[11]Lista de Materiais'!$B$79 -> 5 | E76: pç | F76: 49.88 | G76: =F76*D76 -> 249.4
B77: Joelho 90°, DN85mm, PVC Marrom Soldável | D77: ='[11]Lista de Materiais'!$B$80 -> 1 | E77: pç | F77: 61.71 | G77: =F77*D77 -> 61.71
B78: Joelho 90°, DN110mm, PVC Marrom Soldável | D78: ='[11]Lista de Materiais'!$B$81 -> 3 | E78: pç | F78: 137.21 | G78: =F78*D78 -> 411.63
B79: Joelho 90°, de Latão 25 x 1/2" PVC Soldável | D79: ='[11]Lista de Materiais'!$B$82 -> 82 | E79: pç | F79: 5.62 | G79: =F79*D79 -> 460.84
B80: Joelho 90°, de Latão 25 x 3/4" PVC Soldável | D80: ='[11]Lista de Materiais'!$B$83 -> 42 | E80: pç | F80: 8.9 | G80: =F80*D80 -> 373.8
B81: Luva de Redução soldável 25x20mm | D81: ='[11]Lista de Materiais'!$B$89 -> 1 | E81: pç | F81: 6.21 | G81: =F81*D81 -> 6.21
B82: Luva Soldável com Bucha de Latão, DN20x1/2'' | D82: ='[11]Lista de Materiais'!$B$92 -> 1 | E82: pç | F82: 3.61 | G82: =F82*D82 -> 3.61
B83: Luva Soldável com Bucha de Latão, DN25x3/4'' | D83: ='[11]Lista de Materiais'!$B$93 -> 1 | E83: pç | F83: 4.38 | G83: =F83*D83 -> 4.38
B84: Tê de redução 40x25x40mm, PPR PN20 | D84: ='[11]Lista de Materiais'!$B$117 -> 2 | E84: pç | F84: 11.1 | G84: =F84*D84 -> 22.2
B85: Tê de redução 40x32x40mm, PPR PN20 | D85: ='[11]Lista de Materiais'!$B$118 -> 90 | E85: pç | F85: 11.35 | G85: =F85*D85 -> 1021.5
B86: Tê de redução 50x32x50mm, PPR PN20 | D86: ='[11]Lista de Materiais'!$B$119 -> 3 | E86: pç | F86: 26.9 | G86: =F86*D86 -> 80.7
B87: Tê de redução 50x40x50mm, PPR PN20 | D87: ='[11]Lista de Materiais'!$B$120 -> 7 | E87: pç | F87: 30.74 | G87: =F87*D87 -> 215.18
B88: Tê de redução 75x50x75mm, PPR PN20 | D88: ='[11]Lista de Materiais'!$B$121 -> 1 | E88: pç | F88: 75.94 | G88: =F88*D88 -> 75.94
B89: Tê de redução 75x63x75mm, PPR PN20 | D89: ='[11]Lista de Materiais'!$B$122 -> 10 | E89: pç | F89: 109.9 | G89: =F89*D89 -> 1099
B90: Tê de redução 90x63x90mm, PPR PN20 | D90: ='[11]Lista de Materiais'!$B$123 -> 4 | E90: pç | F90: 167.47 | G90: =F90*D90 -> 669.88
B91: Tê de Redução, DN32x25mm, PVC Marrom Soldável, | D91: ='[11]Lista de Materiais'!$B$124 -> 343 | E91: pç | F91: 5.74 | G91: =F91*D91 -> 1968.82
B92: Tê de Redução, DN50x32mm, PVC Marrom Soldável | D92: ='[11]Lista de Materiais'!$B$125 -> 1 | E92: pç | F92: 18.6 | G92: =F92*D92 -> 18.6
B93: Tê 50x50x50mm, PPR PN20 | D93: ='[11]Lista de Materiais'!$B$108 -> 8 | E93: pç | F93: 30.1 | G93: =F93*D93 -> 240.8
B94: Tê 75x75x75mm, PPR PN20 | D94: ='[11]Lista de Materiais'!$B$109 -> 4 | E94: pç | F94: 58.91 | G94: =F94*D94 -> 235.64
B95: Tê 90x90x90mm, PPR PN20 | D95: ='[11]Lista de Materiais'!$B$110 -> 3 | E95: pç | F95: 71.21 | G95: =F95*D95 -> 213.63
B96: Tê 110x110x110mm, PPR PN20 | D96: ='[11]Lista de Materiais'!$B$111 -> 2 | E96: pç | F96: 119.18 | G96: =F96*D96 -> 238.36
B97: Tê, DN25mm, PVC Marrom Soldável | D97: ='[11]Lista de Materiais'!$B$112 -> 460 | E97: pç | F97: 1.03 | G97: =F97*D97 -> 473.8
B98: Tê, DN32mm, PVC Marrom Soldável | D98: ='[11]Lista de Materiais'!$B$113 -> 131 | E98: pç | F98: 2.73 | G98: =F98*D98 -> 357.63
B99: Tê, DN50mm, PVC Marrom Soldável | D99: ='[11]Lista de Materiais'!$B$114 -> 1 | E99: pç | F99: 8.32 | G99: =F99*D99 -> 8.32
B100: Tê, DN75mm, PVC Marrom Soldável | D100: ='[11]Lista de Materiais'!$B$115 -> 1 | E100: pç | F100: 32.9 | G100: =F100*D100 -> 32.9
B101: Registro de Esfera Azul 1" | D101: ='[11]Lista de Materiais'!$B$96 -> 4 | E101: pç | F101: 20.3 | G101: =F101*D101 -> 81.2
B102: Registro de Esfera Azul 1.1/4" | D102: ='[11]Lista de Materiais'!$B$97 -> 1 | E102: pç | F102: 27.37 | G102: =F102*D102 -> 27.37
B103: Registro de Gaveta 3/4" | D103: ='[11]Lista de Materiais'!$B$98 -> 840 | E103: pç | F103: 43.9 | G103: =F103*D103 -> 36876
...

Sheet ESGOTO E PLUVIAL
A1: Obra | B1: WEST VILLAGE
A2: Empresa | B2: KIRCHNER
A3: Revisão | B3: R00
A4: QUANTIFICAÇÃO
A6: Instalações sanitárias
A8: Geral
B10: Descrição quantitativo | D10: Quantidade | E10: unidade | F10: Preço unitário | G10: Preço total
B11: ESGOTO E PLUVIAL | G11: =SUM(G12:G68) -> 244387.86
B12: Tubo de PVC Rígido Branco, conforme NBR5688, Linha Série Normal | C12: 150 | D12: ='[12]Lista de Materiais'!$B$70 -> 87.25 | E12: m | F12: 32.78 | G12: =F12*D12 -> 2860.055
B13: Tubo de PVC Rígido Branco, conforme NBR5688, Linha Série Normal | C13: 100 | D13: ='[12]Lista de Materiais'!$B$71 -> 2488.38 | E13: m | F13: 12.52 | G13: =F13*D13 -> 31154.518
B14: Tubo de PVC Rígido Branco, conforme NBR5688, Linha Série Normal | C14: 75 | D14: ='[12]Lista de Materiais'!$B$72 -> 650 | E14: m | F14: 14.38 | G14: =F14*D14 -> 9347
B15: Tubo de PVC Rígido Branco, conforme NBR5688, Linha Série Normal | C15: 50 | D15: ='[12]Lista de Materiais'!$B$73 -> 1112.12 | E15: m | F15: 10.03 | G15: =F15*D15 -> 11154.564
B16: Tubo de PVC Rígido Branco, conforme NBR5688, Linha Série Normal | C16: 40 | D16: ='[12]Lista de Materiais'!$B$74 -> 749.4 | E16: m | F16: 0.37 | G16: =F16*D16 -> 277.278
B17: Tubo Série Reforçada (Série R) de PVC Rígido para Esgoto e Água Pluviais, conforme NBR-5688 | C17: 100 | D17: ='[12]Lista de Materiais'!$B$75 -> 1058.07 | E17: m | F17: 27.19 | G17: =F17*D17 -> 28768.923
B18: Tubo Série Reforçada (Série R) de PVC Rígido para Esgoto e Água Pluviais, conforme NBR-5688 | C18: 75 | D18: ='[12]Lista de Materiais'!$B$76 -> 136.69 | E18: m | F18: 18.41 | G18: =F18*D18 -> 2516.4629
B19: Tubo Série Reforçada (Série R) de PVC Rígido para Esgoto e Água Pluviais, conforme NBR-5689 | C19: 50 | D19: ='[12]Lista de Materiais'!$B$77 -> 705.08 | E19: m | F19: 10.905 | G19: =F19*D19 -> 7688.8974
B20: Cap, DN150mm, de PVC Rígido Branco Série Normal para Esgoto e Água Pluvial, conforme NBR 5688 | D20: ='[12]Lista de Materiais'!$B$80 -> 6 | E20: pç | F20: 17.77 | G20: =F20*D20 -> 106.62
B21: Cap, DN100mm, de PVC Rígido Branco Série Reforçada para Esgoto e Água Pluvial, conforme NBR 5689 | D21: ='[12]Lista de Materiais'!$B$81 -> 2 | E21: pç | F21: 16 | G21: =F21*D21 -> 32
B22: Cap, DN75mm, de PVC Rígido Branco Série Reforçada para Esgoto e Água Pluvial, conforme NBR 5690 | D22: ='[12]Lista de Materiais'!$B$82 -> 2 | E22: pç | F22: 14.9 | G22: =F22*D22 -> 29.8
B23: Joelho 45°, DN100mm, de PVC Rígido Branco Série Normal, conforme NBR 5688 | D23: ='[12]Lista de Materiais'!$B$15 -> 553 | E23: pç | F23: 6.7 | G23: =F23*D23 -> 3705.1
B24: Joelho 45°, DN100mm, de PVC Rígido Série R (Reforçada), conforme NBR 5688 | D24: ='[12]Lista de Materiais'!$B$19 -> 134 | E24: pç | F24: 14.77 | G24: =F24*D24 -> 1979.18
B25: Joelho 45°, DN150mm, de PVC Rígido Branco Série Normal, conforme NBR 5688 | D25: ='[12]Lista de Materiais'!$B$14 -> 26 | E25: pç | F25: 47.79 | G25: =F25*D25 -> 1242.54
B26: Joelho 45°, DN40mm, de PVC Rígido Branco Série Normal, conforme NBR 5688 | D26: ='[12]Lista de Materiais'!$B$18 -> 976 | E26: pç | F26: 2.85 | G26: =F26*D26 -> 2781.6
B27: Joelho 45°, DN50mm, de PVC Rígido Branco Série Normal, conforme NBR 5688 | D27: ='[12]Lista de Materiais'!$B$17 -> 1597 | E27: pç | F27: 3.18 | G27: =F27*D27 -> 5078.46
B28: Joelho 45°, DN50mm, de PVC Rígido Série R (Reforçada), conforme NBR 5688 | D28: ='[12]Lista de Materiais'!$B$21 -> 531 | E28: pç | F28: 5.29 | G28: =F28*D28 -> 2808.99
B29: Joelho 45°, DN75mm, de PVC Rígido Branco Série Normal, conforme NBR 5688 | D29: ='[12]Lista de Materiais'!$B$16 -> 305 | E29: pç | F29: 6.87 | G29: =F29*D29 -> 2095.35
B30: Joelho 45°, DN75mm, de PVC Rígido Série R (Reforçada), conforme NBR 5688 | D30: ='[12]Lista de Materiais'!$B$20 -> 42 | E30: pç | F30: 11.48 | G30: =F30*D30 -> 482.16
B31: Joelho 90°, DN100mm, de PVC Rígido Branco Série Normal, conforme NBR 5688 | D31: ='[12]Lista de Materiais'!$B$22 -> 322 | E31: pç | F31: 5.05 | G31: =F31*D31 -> 1626.1
B32: Joelho 90°, DN100mm, de PVC Rígido Série R (Reforçada), conforme NBR 5688 | D32: ='[12]Lista de Materiais'!$B$26 -> 58 | E32: pç | F32: 17.95 | G32: =F32*D32 -> 1041.1
B33: Joelho 90°, DN40mm, de PVC Rígido Branco Série Normal, conforme NBR 5688 | D33: ='[12]Lista de Materiais'!$B$25 -> 562 | E33: pç | F33: 1.63 | G33: =F33*D33 -> 916.06
B34: Joelho 90°, DN50mm, de PVC Rígido Branco Série Normal, conforme NBR 5688 | D34: ='[12]Lista de Materiais'!$B$24 -> 658 | E34: pç | F34: 2.57 | G34: =F34*D34 -> 1691.06
B35: Joelho 90°, DN50mm, de PVC Rígido Série R (Reforçada), conforme NBR 5688 | D35: ='[12]Lista de Materiais'!$B$28 -> 402 | E35: pç | F35: 14.26 | G35: =F35*D35 -> 5732.52
B36: Joelho 90°, DN75mm, de PVC Rígido Branco Série Normal, conforme NBR 5688 | D36: ='[12]Lista de Materiais'!$B$23 -> 24 | E36: pç | F36: 3.29 | G36: =F36*D36 -> 78.96
B37: Joelho 90°, DN75mm, de PVC Rígido Série R (Reforçada), conforme NBR 5688 | D37: ='[12]Lista de Materiais'!$B$27 -> 9 | E37: pç | F37: 15.16 | G37: =F37*D37 -> 136.44
B38: Junção 45° de Redução, DN100x50mm, de PVC Rígido Branco Série Normal, conforme NBR 5688 | D38: ='[12]Lista de Materiais'!$B$38 -> 689 | E38: pç | F38: 17.13 | G38: =F38*D38 -> 11802.57
B39: Junção 45° de Redução, DN100x50mm, de PVC Rígido Série R (Reforçada), conforme NBR 5688 | D39: ='[12]Lista de Materiais'!$B$42 -> 184 | E39: pç | F39: 36.05 | G39: =F39*D39 -> 6633.2
B40: Junção 45° de Redução, DN100x75mm, de PVC Rígido Branco Série Normal, conforme NBR 5688 | D40: ='[12]Lista de Materiais'!$B$39 -> 30 | E40: pç | F40: 21.96 | G40: =F40*D40 -> 658.8
B41: Junção 45° de Redução, DN100x75mm, de PVC Rígido Branco Série R, conforme NBR 5689 | D41: ='[12]Lista de Materiais'!$B$41 -> 4 | E41: pç | F41: 38.15 | G41: =F41*D41 -> 152.6
B42: Junção 45° de Redução, DN150x100mm, de PVC Rígido Branco Série Normal, conforme NBR 5688 | D42: ='[12]Lista de Materiais'!$B$37 -> 17 | E42: pç | F42: 46.95 | G42: =F42*D42 -> 798.15
B43: Junção 45° de Redução, DN75x50mm, de PVC Rígido Branco Série Normal, conforme NBR 5688 | D43: ='[12]Lista de Materiais'!$B$40 -> 14 | E43: pç | F43: 9.07 | G43: =F43*D43 -> 126.98
B44: Junção 45° de Redução, DN75x50mm, de PVC Rígido Série R (Reforçada), conforme NBR 5688 | D44: ='[12]Lista de Materiais'!$B$43 -> 6 | E44: pç | F44: 53.77 | G44: =F44*D44 -> 322.62
B45: Junção 45°, DN100x100mm, de PVC Rígido Branco Série Normal, conforme NBR 5688 | D45: ='[12]Lista de Materiais'!$B$31 -> 230 | E45: pç | F45: 33.05 | G45: =F45*D45 -> 7601.5
B46: Junção 45°, DN100x100mm, de PVC Rígido Série R (Reforçada), conforme NBR 5688 | D46: ='[12]Lista de Materiais'!$B$34 -> 20 | E46: pç | F46: 37.57 | G46: =F46*D46 -> 751.4
B47: Junção 45°, DN50x50mm, de PVC Rígido Branco Série Normal, conforme NBR 5688 | D47: ='[12]Lista de Materiais'!$B$33 -> 79 | E47: pç | F47: 9.93 | G47: =F47*D47 -> 784.47
B48: Junção 45°, DN50x50mm, de PVC Rígido Branco Série R, conforme NBR 5689 | D48: ='[12]Lista de Materiais'!$B$36 -> 90 | E48: pç | F48: 24.83 | G48: =F48*D48 -> 2234.7
B49: Junção 45°, DN75x75mm, de PVC Rígido Série N (Normal), conforme NBR 5688 | D49: ='[12]Lista de Materiais'!$B$32 -> 86 | E49: pç | F49: 18.99 | G49: =F49*D49 -> 1633.14
B50: Junção 45°, DN75x75mm, de PVC Rígido Série R (Reforçada), conforme NBR 5688 | D50: ='[12]Lista de Materiais'!$B$35 -> 1 | E50: pç | F50: 28 | G50: =F50*D50 -> 28
B51: Luva Simples, DN100mm, de PVC Rígido Branco Série Normal, conforme NBR 5688 | D51: ='[12]Lista de Materiais'!$B$47 -> 1808 | E51: pç | F51: 14.25 | G51: =F51*D51 -> 25764
B52: Luva Simples, DN100mm, de PVC Rígido Série R (Reforçada), conforme NBR 5688 | D52: ='[12]Lista de Materiais'!$B$50 -> 375 | E52: pç | F52: 17.95 | G52: =F52*D52 -> 6731.25
B53: Luva Simples, DN150mm, de PVC Rígido Branco Série Normal, conforme NBR 5688 | D53: ='[12]Lista de Materiais'!$B$46 -> 37 | E53: pç | F53: 27.75 | G53: =F53*D53 -> 1026.75
B54: Luva Simples, DN50mm, de PVC Rígido Branco Série Normal, conforme NBR 5688 | D54: ='[12]Lista de Materiais'!$B$49 -> 2522 | E54: pç | F54: 2.41 | G54: =F54*D54 -> 6078.02
B55: Luva Simples, DN50mm, de PVC Rígido Série R (Reforçada), conforme NBR 5688 | D55: ='[12]Lista de Materiais'!$B$52 -> 1076 | E55: pç | F55: 7.78 | G55: =F55*D55 -> 8371.28
B56: Luva Simples, DN75mm, de PVC Rígido Branco Série Normal, conforme NBR 5688 | D56: ='[12]Lista de Materiais'!$B$48 -> 451 | E56: pç | F56: 6.12 | G56: =F56*D56 -> 2760.12
B57: Luva Simples, DN75mm, de PVC Rígido Série R (Reforçada), conforme NBR 5688 | D57: ='[12]Lista de Materiais'!$B$51 -> 55 | E57: pç | F57: 9.7 | G57: =F57*D57 -> 533.5
B58: Redução Excêntrica, DN100x75mm, de PVC Rígido Série N (normal) para Esgoto e Água Pluvial, conforme NBR 5688 | D58: ='[12]Lista de Materiais'!$B$55 -> 10 | E58: pç | F58: 13.9 | G58: =F58*D58 -> 139
B59: Redução Excêntrica, DN100x75mm, de PVC Rígido Série R (Reforçada) para Esgoto e Água Pluvial, conforme NBR 5688 | D59: ='[12]Lista de Materiais'!$B$56 -> 9 | E59: pç | F59: 20.9 | G59: =F59*D59 -> 188.1
B60: Tê 90° de Redução, DN75x50mm, de PVC Rígido Branco Série Normal, conforme NBR 5688 | D60: ='[12]Lista de Materiais'!$B$62 -> 22 | E60: pç | F60: 14.76 | G60: =F60*D60 -> 324.72
B61: Tê 90° de Redução, DN100x50mm, de PVC Rígido Branco Série Normal, conforme NBR 5688 | D61: ='[12]Lista de Materiais'!$B$61 -> 1 | E61: pç | F61: 11.4 | G61: =F61*D61 -> 11.4
B62: Tê 90° de Redução, DN100x50mm, de PVC Rígido Série R (Reforçada), conforme NBR 5688 | D62: ='[12]Lista de Materiais'!$B$63 -> 2 | E62: pç | F62: 29.54 | G62: =F62*D62 -> 59.08
B63: Tê 90°, DN50x50mm, de PVC Rígido Branco Série Normal, conforme NBR 5688 | D63: ='[12]Lista de Materiais'!$B$59 -> 450 | E63: pç | F63: 6.39 | G63: =F63*D63 -> 2875.5
B64: Tê 90°, DN50x50mm, de PVC Rígido Branco Série Refroçada, conforme NBR 5688 | D64: ='[12]Lista de Materiais'!$B$60 -> 84 | E64: pç | F64: 24.83 | G64: =F64*D64 -> 2085.72
B65: Terminal de Ventilação, DN100mm, de PVC Rígido Branco Série Normal, conforme NBR 5688 | D65: ='[12]Lista de Materiais'!$B$66 -> 24 | E65: pç | F65: 17.24 | G65: =F65*D65 -> 413.76
B66: Terminal de Ventilação, DN75mm, de PVC Rígido Branco Série Normal, conforme NBR 5688 | D66: ='[12]Lista de Materiais'!$B$67 -> 7 | E66: pç | F66: 13.43 | G66: =F66*D66 -> 94.01
B67: Caixa Sifonada Montada com Grelha e Porta Grelha Quadrados Brancos 150x150x50mm | D67: ='[12]Lista de Materiais'!$B$10 -> 266 | E67: pç | F67: 64.35 | G67: =F67*D67 -> 17117.1
B68: Caixa Sifonada Montada com Grelha e Porta Grelha Quadrados Brancos 150x170x75mm | D68: ='[12]Lista de Materiais'!$B$11 -> 132 | E68: pç | F68: 82.99 | G68: =F68*D68 -> 10954.68

Sheet LOUÇAS E METAIS
A1: Obra | B1: WEST VILLAGE
A2: Empresa | B2: KIRCHNER
A3: Revisão | B3: R00
A4: QUANTIFICAÇÃO
A6: LOUÇAS E METAIS
A8: Geral
B10: Descrição quantitativo | C10: Quantidade | D10: unidade | E10: Preço unitário | F10: Preço total
B11: LOUÇAS | F11: =SUM(F12:F22) -> 187114.96
B12: Bacia Sanitária de louça com caixa acoplada | C12: =3+5+(12*15) -> 188 | D12: pc | E12: 769 | F12: =E12*C12 -> 144572
B13: Acabamento de registro de gaveta 3/4'' | C13: =4+8+(12*2*15)+(41*2*15) -> 1602 | D13: pc | E13: 23.98 | F13: =E13*C13 -> 38415.96 | J13: Contabilizado para as sacadas, cozinhas e área de serviço
B14: Torneira de cozinha | C14: 2 | D14: pc | E14: 250 | F14: =E14*C14 -> 500
B15: Torneira para lavatório | C15: =3+5 -> 8 | D15: pc | E15: 145 | F15: =E15*C15 -> 1160
B16: Torneira para tanque | C16: 1 | D16: pc | E16: 62 | F16: =E16*C16 -> 62
B17: Lavatório embutido | C17: 5 | D17: pc | E17: 109 | F17: =E17*C17 -> 545
B18: Lavatório PCD | C18: 3 | D18: pc | E18: 176 | F18: =E18*C18 -> 528
B19: Pia inox | C19: 2 | D19: pc | E19: 170 | F19: =E19*C19 -> 340
B20: Ducha | C20: 2 | D20: pc | E20: 150 | F20: =E20*C20 -> 300
B21: Tanque | C21: 1 | D21: pc | E21: 68 | F21: =E21*C21 -> 68
B22: Barra de apoio | C22: 12 | D22: pc | E22: 52 | F22: =E22*C22 -> 624
B23: ACESSORIOS | F23: =SUM(F24:F28) -> 5168.82
B24: Sifão de copo p/ pia e lavatório | C24: =10 -> 10 | D24: pç | E24: 23.9 | F24: =E24*C24 -> 239
B25: Sifão para pia e tanque | C25: =C21 -> 1 | D25: pç | E25: 8 | F25: =E25*C25 -> 8
B26: Válvula p/ lavatório e tanque | C26: 9 | D26: pç | E26: 29.9 | F26: =E26*C26 -> 269.1
B27: Válvula p/ pia | C27: 2 | D27: pç | E27: 29.9 | F27: =E27*C27 -> 59.8
B28: Engate flexível cobre cromado com canopla | C28: =188+2+8+1 -> 199 | D28: pç | E28: 23.08 | F28: =E28*C28 -> 4592.92
B29: MÃO DE OBRA | F29: =SUM(F30) -> 75057.5
B30: Mão de obra louças e metais | C30: 10722.5 | D30: m2 | E30: 7 | F30: =E30*C30 -> 75057.5
E31: TOTAL | F31: =SUM(F11,F23,F29) -> 267341.28

Sheet ELÉTRICA
A1: Obra | B1: WEST VILLAGE
A2: Empresa | B2: KIRCHNER
A3: Revisão | B3: R00
A4: QUANTIFICAÇÃO
A6: Intslações elétricas
A8: Geral
B10: Descrição quantitativo | D10: Quantidade | E10: Unidade | F10: Preço unitário | G10: Preço total
B11: ENTRADA DE ENERGIA | G11: =SUM(G12:G27) -> 50999.995
B12: TERMINAL SAPATA 16.00mm² | D12: 10 | E12: pç | F12: 2.65 | G12: =F12*D12 -> 26.5
B13: PARAFUSO COM PORCA E 02 ARRUELAS ¼ X 1” DE LATÃO | D13: 10 | E13: pç | F13: 2.7798 | G13: =F13*D13 -> 27.798
B14: HASTE TERRA 240cm | D14: 6 | E14: pç | F14: 35.506 | G14: =F14*D14 -> 213.036
B15: CONECTOR DUPLO TIPO U PARA HASTE TERRA | D15: 6 | E15: pç | F15: 12.59 | G15: =F15*D15 -> 75.54
B16: TAMPA DE FERRO FUNDIDO (900x700mm) - 400kN (CELESC) | D16: 2 | E16: pç | F16: 1671.406 | G16: =F16*D16 -> 3342.812
B17: BOX RETO C/ ARUELA EM ALUMINIO 4" | D17: 2 | E17: pç | F17: 61.048 | G17: =F17*D17 -> 122.096
B18: BUCHA EM ALUMINIO P/ BOX RETO 4" | D18: 2 | E18: pç | F18: 11.8408 | G18: =F18*D18 -> 23.6816
B19: BOX RETO C/ ARUELA EM ALUMINIO 3" | D19: 2 | E19: pç | F19: 38.3022 | G19: =F19*D19 -> 76.6044
B20: BUCHA EM ALUMINIO P/ BOX RETO 3" | D20: 2 | E20: pç | F20: 8.0278 | G20: =F20*D20 -> 16.0556
B21: FAIXA (PERIGO - CABOS ELÉTRICOS) NÃO ADESIVA (ROLO C/ 100M) | D21: 1 | E21: pç | F21: 44.28 | G21: =F21*D21 -> 44.28
B22: CINTA EM ALUMINIO COM PRESILHA TIPO FIVELA | D22: 10 | E22: pç | F22: 4.141 | G22: =F22*D22 -> 41.41
B23: TAMPA DE FERRO FUNDIDO (300X300) - (ATERRAMENTO - CELESC) | D23: 1 | E23: pç | F23: 145 | G23: =F23*D23 -> 145
... B27: VERBA EXTRA | D27: 1 | E27: vb | F27: 46670.62 | G27: =F27*D27 -> 46670.62
B28: QUADROS E DISJUNTORES | G28: =SUM(G29:G36) -> 147786.96
B29: CD - Condomínio | D29: 1 | E29: un | F29: 5301.01 | G29: =F29*D29 -> 5301.01
B30: CD - Lazer | D30: 1 | E30: un | F30: 4533.94 | G30: =F30*D30 -> 4533.94
B31: CD 01 - Emergência | D31: 1 | E31: un | F31: 639.61 | G31: =F31*D31 -> 639.61
B32: CD 02 - Emergência Bomba de incêndio | D32: 1 | E32: un | F32: 254.71 | G32: =F32*D32 -> 254.71
B33: CD - Sala Comerciais 01 | D33: 1 | E33: un | F33: 1329.15 | G33: =F33*D33 -> 1329.15
B34: CD - Sala Comerciais 02 | D34: 1 | E34: un | F34: 1338.57 | G34: =F34*D34 -> 1338.57
B35: CD - Garagem 01/02/03 | D35: 1 | E35: un | F35: 1166.55 | G35: =F35*D35 -> 1166.55
B36: CD - Apartamentos | D36: 1 | E36: un | F36: 133223.42 | G36: =F36*D36 -> 133223.42
B37: ELETRODUTOS, CAIXAS E ELTROCALHAS | G37: =SUM(G38:G110) -> 77801.771
B38: ELETRODUTO EM PVC CLASSE LEVE 3/4" (LINHA BRANCA) | D38: 56 | E38: m | F38: 12.4148 | G38: =F38*D38 -> 695.2288
B39: ADAPTADOR P/ ELETRODUTO 3/4" (LINHA BRANCA) | D39: 120 | E39: pç | F39: 0.6724 | G39: =F39*D39 -> 80.688
B40: COTOVELO 90° P/ ELETRODUTO 3/4" (LINHA BRANCA) | D40: 15 | E40: pç | F40: 2.8536 | G40: =F40*D40 -> 42.804
B41: LUVA P/ ELETRODUTO 3/4" (LINHA BRANCA) | D41: 10 | E41: pç | F41: 0.943 | G41: =F41*D41 -> 9.43
B42: ELETRODUTO CORRUGADO 1 1/4" (AMARELO) | D42: 300 | E42: m | F42: 2.1146 | G42: =F42*D42 -> 634.38
B43: ELETRODUTO CORRUGADO 1" | D43: 3580 | E43: m | F43: 1.178 | G43: =F43*D43 -> 4217.24
B44: ELETRODUTO CORRUGADO ¾" | D44: 23150 | E44: m | F44: 1.18 | G44: =F44*D44 -> 27317
B45: ELETRODUTO CORRUGADO TIPO PEAD, CINZA REFORÇADO COM GUIA DE ARAME, 4” | D45: 50 | E45: m | F45: 12.3082 | G45: =F45*D45 -> 615.41
B46: ELETRODUTO GALVANIZADO 4" (BARRA 6m) | D46: 3 | E46: pç | F46: 908.55 | G46: =F46*D46 -> 2725.65
B47: CURVA LONGA 90° P/ ELETRODUTO GALVANIZADO 4" (BARRA 6m) | D47: =2 -> 2 | E47: pç | F47: 326.524 | G47: =F47*D47 -> 653.048
B48: LUVA ELETRODUTO P/ GALVANIZADO 4" (BARRA 6m) | D48: 4 | E48: pç | F48: 52.2504 | G48: =F48*D48 -> 209.0016
B49: CABEÇOTE EM ALUMINIO P/ ELETRODUTO 4" | D49: 2 | E49: pç | F49: 23.575 | G49: =F49*D49 -> 47.15
B50: ELETRODUTO RÍGIDO PVC 4" (BARRA 3m) | D50: 2 | E50: pç | F50: 68.92 | G50: =F50*D50 -> 137.84
B51: ELETRODUTO RÍGIDO PVC 3" (BARRA 3m) | D51: 6 | E51: pç | F51: 45.1902 | G51: =F51*D51 -> 271.1412
B52: ELETRODUTO RÍGIDO PVC 2" (BARRA 3m) | D52: 2 | E52: pç | F52: 23.4274 | G52: =F52*D52 -> 46.8548
B53: ELETRODUTO RÍGIDO PVC 1" (BARRA 3m) | D53: 6 | E53: pç | F53: 10.086 | G53: =F53*D53 -> 60.516
B54: CURVA 90° P/ ELETRODUTO RÍGIDO PVC 4" | D54: 2 | E54: pç | F54: 42.4842 | G54: =F54*D54 -> 84.9684
B55: CURVA 90° P/ ELETRODUTO RÍGIDO PVC 3" | D55: 6 | E55: pç | F55: 23.5094 | G55: =F55*D55 -> 141.0564
B56: CURVA 90° P/ ELETRODUTO RÍGIDO PVC 2" | D56: 4 | E56: pç | F56: 5.6498 | G56: =F56*D56 -> 22.5992
B57: CURVA 90° P/ ELETRODUTO RÍGIDO PVC 1" | D57: 3 | E57: pç | F57: 1.7138 | G57: =F57*D57 -> 5.1414
B58: LUVA P/ ELETRODUTO RÍGIDO PVC 4" | D58: 4 | E58: pç | F58: 11.234 | G58: =F58*D58 -> 44.936
B59: LUVA P/ ELETRODUTO RÍGIDO PVC 3" | D59: 15 | E59: pç | F59: 6.8306 | G59: =F59*D59 -> 102.459
... B110: CHAVE BOIA ELETRICA DE NIVEL SUPERIOR/INFERIOR | D110: 3 | E110: pç | F110: 32.0866 | G110: =F110*D110 -> 96.2598
B111: ENFIAÇÃO | G111: =SUM(G112:G157) -> 426693.36
B112: CABO 1.5mm² FLEXÍVEL (750V) AMARELO | D112: 600 | E112: m | F112: 0.8956 | G112: =F112*D112 -> 537.36
B113: CABO 1.5mm² FLEXÍVEL (750V) AZUL | D113: 24100 | E113: m | F113: 0.9 | G113: =F113*D113 -> 21690
B114: CABO 1.5mm² FLEXÍVEL (750V) BRANCO | D114: 200 | E114: m | F114: 0.9 | G114: =F114*D114 -> 180
B115: CABO 1.5mm² FLEXÍVEL (750V) CINZA | D115: 400 | E115: m | F115: 0.8956 | G115: =F115*D115 -> 358.24
B116: CABO 1.5mm² FLEXÍVEL (750V) PRETO | D116: 23500 | E116: m | F116: 0.8956 | G116: =F116*D116 -> 21046.6
B117: CABO 1.5mm² FLEXÍVEL (750V) RETORNOS - Dividir m total em 1/5 BRANCO, 1/5 AMARELO, 1/5 VERMELHO, 2/5 CINZA | D117: 35400 | E117: m | F117: 0.9 | G117: =F117*D117 -> 31860
B118: CABO 1.5mm² FLEXÍVEL (750V) VERDE | D118: 24100 | E118: m | F118: 0.9 | G118: =F118*D118 -> 21690
B119: CABO 1.5mm² FLEXÍVEL (750V) VERMELHO | D119: 200 | E119: m | F119: 0.9 | G119: =F119*D119 -> 180
B120: CABO 1.5mm² FLEXIVEL (750V), ISOLAÇÃO EM SILICONE 300°C, BRANCO | D120: 1450 | E120: m | F120: 0.8956 | G120: =F120*D120 -> 1298.62
B121: CABO 1.5mm² FLEXÍVEL (1KV - EPR) PRETO | D121: 100 | E121: m | F121: 1.2956 | G121: =F121*D121 -> 129.56
B122: CABO 1.5mm² FLEXÍVEL (1KV - EPR) AZUL | D122: 100 | E122: m | F122: 1.2956 | G122: =F122*D122 -> 129.56
B123: CABO 1.5mm² FLEXÍVEL (1KV - EPR) VERDE | D123: 100 | E123: m | F123: 1.2956 | G123: =F123*D123 -> 129.56
... B157: CABO 120mm² FLEXÍVEL (1kV) EPR 90°C VERDE | D157: 45 | E157: m | F157: 73.472 | G157: =F157*D157 -> 3306.24
B158: ACABAMENTOS DE TOMADAS E INTERRUPTORES | G158: =SUM(G159:G186) -> 123444.24
B159: MÓDULO TOMADA (2P+T - 10A) | D159: 2235 | E159: pç | F159: 15.0388 | G159: =F159*D159 -> 33611.718
B160: MÓDULO TOMADA (2P+T - 20A) | D160: 820 | E160: pç | F160: 16.687 | G160: =F160*D160 -> 13683.34
B161: TAMPA P/ 01 TOMADA + 01 INTERRUPTOR PARALELO - 3/4" (LINHA BRANCA) | D161: 4 | E161: pç | F161: 14.9158 | G161: =F161*D161 -> 59.6632
B162: TOMADA (2P+T - 10A) P/ FIXAR CAIXA DE DERIVAÇÃO - 3/4" (LINHA BRANCA) | D162: 8 | E162: pç | F162: 8.9 | G162: =F162*D162 -> 71.2
B163: TAMPA P/ 01 TOMADA - 3/4" (LINHA BRANCA) | D163: 8 | E163: pç | F163: 1.353 | G163: =F163*D163 -> 10.824
B164: TOMADA (2P+T - 20A) SOBREPOR P/ MADEIRA | D164: 315 | E164: pç | F164: 9.3644 | G164: =F164*D164 -> 2949.786
B165: MÓDULO TOMADA P/ FIXAR CAIXA PISO INOX OU LATÃO (2P + T - 10A) | D165: 2 | E165: pç | F165: 10.45 | G165: =F165*D165 -> 20.9
B166: TOMADA (2P+T - 20A) SOBREPOR TIPO RÉGUA 3 MÓDULOS | D166: 1 | E166: pç | F166: 17.95 | G166: =F166*D166 -> 17.95
B167: TOMADA P/ FIXAR PLACA PISO - (2P+T 20A) | D167: 2 | E167: pç | F167: 15.75 | G167: =F167*D167 -> 31.5
B168: MÓDULO INTERRUPTOR SIMPLES | D168: 1055 | E168: pç | F168: 10.8322 | G168: =F168*D168 -> 11427.971
B169: MÓDULO INTERRUPTOR PARALELO | D169: 662 | E169: pç | F169: 15.8178 | G169: =F169*D169 -> 10471.384
B170: PLACA 4X2" | 01 MÓDULO | D170: 3378 | E170: pç | F170: 5.371 | G170: =F170*D170 -> 18143.238
... B186: SENSOR DE PRESENÇA C/ FOTOCÉLULA (FRONTAL) SOBREPOR - 4x2 | D186: 1 | E186: pç | F186: 46.9 | G186: =F186*D186 -> 46.9
B187: LUMINÁRIAS | G187: =SUM(G188:G190) -> 4300.1466
B188: LUMINÁRIA TIPO TARTARUGA (BRANCA) COM LÂMPADA 13W FRIA | D188: 50 | E188: pç | F188: =11.644+5.1332 -> 16.7772 | G188: =F188*D188 -> 838.86
B189: LUMINÁRIA DE EMERGÊNCIA LED 220V - 30 LED'S | D189: 4 | E189: pç | F189: 20.9 | G189: =F189*D189 -> 83.6
B190: LUMINÁRIA TIPO PLAFON (SOBREPOR) **C/ LÂMPADA | D190: 173 | E190: pç | F190: 19.5242 | G190: =F190*D190 -> 3377.6866
B191: EXAUSTÃO CHURRASQUEIRA | G191: =SUM(G192:G196) -> 21051.619
B192: BOCAL DE PORCELANA BASE GRANDE (CHURRASQUEIRA) | D192: 92 | E192: pç | F192: 8.5526 | G192: =F192*D192 -> 786.8392
B193: EXAUSTOR COMPACTO AXIAL (RENOVADOR DE AR) 96mm (220V) | D193: 3 | E193: pç | F193: 103.36 | G193: =F193*D193 -> 310.08
B194: VENTILADOR AXIAL TIPO EXAUSTOR 30cm (220V) | D194: 92 | E194: pç | F194: 199.9 | G194: =F194*D194 -> 18390.8
B195: COMANDO EXAUSTOR (HALL APTOS) | D195: 16 | E195: pç | F195: 44.9 | G195: =F195*D195 -> 718.4
B196: LÂMPADA INCANDSECENTE 40W (E27) | D196: 95 | E196: pç | F196: 8.9 | G196: =F196*D196 -> 845.5
D199: entrada de energia | F199: R$ 5,00 /m²

Sheet EXAUSTÃO
A1: Obra | B1: WEST VILLAGE
A2: Empresa | B2: KIRCHNER
A3: Revisão | B3: R00
A4: QUANTIFICAÇÃO
A6: Intslações elétricas
A8: Geral
B10: Descrição quantitativo | D10: Quantidade | E10: Unidade | F10: Preço unitário | G10: Preço total
B11: EXAUSTÃO CHURRASQUEIRA | G11: =SUM(G12:G16) -> 35810.739
B12: BOCAL DE PORCELANA BASE GRANDE (CHURRASQUEIRA) | D12: 92 | E12: pç | F12: 8.5526 | G12: =F12*D12 -> 786.8392
B13: VENTILADOR AXIAL TIPO EXAUSTOR 30cm (220V) | D13: 92 | E13: pç | F13: 350 | G13: =F13*D13 -> 32200
B14: COMANDO EXAUSTOR (HALL APTOS) | D14: 16 | E14: pç | F14: 44.9 | G14: =F14*D14 -> 718.4
B15: LÂMPADA INCANDSECENTE 40W (E27) | D15: 95 | E15: pç | F15: 8.9 | G15: =F15*D15 -> 845.5
B16: EXAUSTÃO DE BANHEIROS ENCLAUSURADOS | G16: =SUM(G17) -> 1260
B17: EXAUSTOR COMPACTO AXIAL (RENOVADOR DE AR) 96mm (220V) | D17: 6 | E17: pç | F17: 210 | G17: =F17*D17 -> 1260

Sheet TELECOM
A1: Obra | B1: WEST VILLAGE
A2: Empresa | B2: KIRCHNER
A3: Revisão | B3: R00
A4: QUANTIFICAÇÃO
A6: Intslações Telecomunicações
A8: Geral
B10: Descrição quantitativo | D10: Quantidade | E10: Unidade | F10: Preço unitário | G10: Preço total
B11: INSTALAÇÕES DE TELECOM | G11: =SUM(G12:G34) -> 39250.332
B12: ELETRODUTO CORRUGADO 1" | D12: 12525 | E12: m | F12: =[13]ELÉTRICA!F43 -> 1.178 | G12: =F12*D12 -> 14754.45
B13: ELETRODUTO CORRUGADO ¾" | D13: 300 | E13: m | F13: =[13]ELÉTRICA!F44 -> 1.18 | G13: =F13*D13 -> 354
B14: ELETRODUTO CORRUGADO 1 1/4" (AMARELO) | D14: 1350 | E14: m | F14: =[13]ELÉTRICA!F42 -> 2.1146 | G14: =F14*D14 -> 2854.71
B15: ELETRODUTO CORRUGADO TIPO PEAD, CINZA REFORÇADO COM GUIA DE ARAME, 3” | D15: 80 | E15: m | F15: 8.46 | G15: =F15*D15 -> 676.8
B16: ELETRODUTO PLANO FLEXÍVEL ø1" | D16: 440 | E16: m | F16: =[13]ELÉTRICA!F66 -> 2.424 | G16: =F16*D16 -> 1066.56
B17: ELETRODUTO RÍGIDO PVC 2" (BARRA 3m) | D17: 4 | E17: pç | F17: =[13]ELÉTRICA!F52 -> 23.4274 | G17: =F17*D17 -> 93.7096
B18: CURVA 90° P/ ELETRODUTO RÍGIDO PVC 2" | D18: 2 | E18: pç | F18: =[13]ELÉTRICA!F56 -> 5.6498 | G18: =F18*D18 -> 11.2996
B19: LUVA P/ ELETRODUTO RÍGIDO PVC 2" | D19: 6 | E19: pç | F19: =[13]ELÉTRICA!F60 -> 2.5502 | G19: =F19*D19 -> 15.3012
B20: CABEÇOTE EM ALUMINIO P/ ELETRODUTO 2" | D20: 2 | E20: pç | F20: 15.03 | G20: =F20*D20 -> 30.06
B21: CAIXA 4X2" DE EMBUTIR PVC (AMARELA) | D21: 542 | E21: pç | F21: =[13]ELÉTRICA!F76 -> 1.1562 | G21: =F21*D21 -> 626.6604
B22: CAIXA 4X4" DE EMBUTIR PVC (AMARELA) | D22: 332 | E22: pç | F22: 2.8126 | G22: =F22*D22 -> 933.7832
B23: TAMPA DE FERRO FUNDIDO (700x460mm) - 125kN (TELESC) | D23: 3 | E23: pç | F23: 789 | G23: =F23*D23 -> 2367
B24: BUCHA EM ALUMINIO P/ BOX RETO 3" | D24: 2 | E24: pç | F24: =[13]ELÉTRICA!F20 -> 8.0278 | G24: =F24*D24 -> 16.0556
B25: BOX RETO C/ ARUELA EM ALUMINIO 3" | D25: 2 | E25: pç | F25: =[13]ELÉTRICA!F19 -> 38.3022 | G25: =F25*D25 -> 76.6044
B26: MÓDULO TOMADA DE COMUNICAÇÃO - INFORMÁTICA (RJ45) | D26: 25 | E26: pç | F26: 15.89 | G26: =F26*D26 -> 397.25
B27: MÓDULO TOMADA DE COMUNICAÇÃO - P/ CABO COAXIAL TERMINAL | D27: 295 | E27: pç | F27: 8.74 | G27: =F27*D27 -> 2578.3
B28: MÓDULO TOMADA DE COMUNICAÇÃO - TELEFÔNICA (RJ11) | D28: 395 | E28: pç | F28: 10.17 | G28: =F28*D28 -> 4017.15
B29: PLACA 4X2" | 01 MÓDULO | D29: 390 | E29: pç | F29: =[13]ELÉTRICA!F170 -> 5.371 | G29: =F29*D29 -> 2094.69
B30: PLACA 4X2" | CEGA | D30: 67 | E30: pç | F30: =[13]ELÉTRICA!F174 -> 5.371 | G30: =F30*D30 -> 359.857
B31: PLACA 4X4" | 01 MÓDULOS | D31: 295 | E31: pç | F31: =[13]ELÉTRICA!F173 -> 13.038 | G31: =F31*D31 -> 3846.21
B32: PLACA 4X4" | 02 MÓDULOS | D32: 15 | E32: un | F32: =[13]ELÉTRICA!F173 -> 13.038 | G32: =F32*D32 -> 195.57
B33: SUPORTE PARA MÓDULOS 4X2" | 03 MÓDULOS | D33: 462 | E33: un | F33: =[13]ELÉTRICA!F177 -> 1.6974 | G33: =F33*D33 -> 784.1988
B34: SUPORTE PARA MÓDULOS 4X4" | 06 MÓDULOS | D34: 312 | E34: un | F34: =[13]ELÉTRICA!F178 -> 3.526 | G34: =F34*D34 -> 1100.112

Sheet SPDA
A1: Obra | B1: WEST VILLAGE
A2: Empresa | B2: KIRCHNER
A3: Revisão | B3: R00
A4: QUANTIFICAÇÃO
A6: Intslações SPDA
A8: Geral
B10: Descrição quantitativo | D10: Quantidade | E10: Unidade | F10: Preço unitário | G10: Preço total
B11: BARRAS DE AÇO DE ALUMINIO | G11: =SUM(G12:G26) -> 21247.652
B12: Barra redonda de aço, Ø8mm (50mm²), Re-bar, em barras de 3m | C12: Termotécnica Ref.TEL-762 | D12: 977.86 | E12: m | F12: =29/3 -> 9.6666667 | G12: =F12*D12 -> 9452.6467
B13: Barra redonda de aço, Ø10mm (80mm²), Re-bar, em barras de 3m | C13: Termotécnica Ref.TEL-768 | D13: 104.26 | E13: m | F13: =35.87/3 -> 11.956667 | G13: =F13*D13 -> 1246.6021
B14: Cabo de cobre nú #16mm², conforme NBR6524 | C14: Termotécnica Ref.TEL-5716 | D14: 66.03 | E14: m | F14: 13.89 | G14: =F14*D14 -> 917.1567
B15: Barras Chatas em Alumínio, 7/8″ x 1/8″ (70mm²), com Furos Ø7 mm | C15: Termotécnica Ref. TEL-771 | D15: 228.9 | E15: m | F15: 8.46 | G15: =F15*D15 -> 1936.494
B16: BARRAS DE AÇO DE ALUMINIO | G16: =SUM(G17:G31) -> 3847.3764
B17: Caixa de Equipotencialização com 5 Terminais para uso Interno e Externo, 180x150x90mm, em Polipropileno | C17: 180x150x90mm | D17: 6 | E17: m | F17: 397.86 | G17: =F17*D17 -> 2387.16
B18: Clip de aço galvanizado para conexão de barras de 8 a 10 mm de diâmetro | C18: 8 a 10 mm | D18: 189 | E18: pç | F18: 2.58 | G18: =F18*D18 -> 487.62
B19: Curva 90° de Barra Chata em Alumínio, 7/8″ x 1/8″ x 300 mm (70mm²) | C19: 7/8″ x 1/8″ x 300 mm (70mm²) | D19: 12 | E19: pç | F19: 3.92 | G19: =F19*D19 -> 47.04
B20: Curva 90° Horizontal de Barra Chata em Cobre, 7/8″ x 1/8″ x 300mm (70mm²) | C20: 7/8″ x 1/8″ x 300mm (70mm²) | D20: 12 | E20: pç | F20: 14.1 | G20: =F20*D20 -> 169.2
B21: Minicaptor em Barra Chata de Alumínio, 7/8″ x 1/8″ x 300 mm | C21: 7/8″ x 1/8″ x 300 mm | D21: 14 | E21: pç | F21: 15.03 | G21: =F21*D21 -> 210.42
B22: Parafuso Autoatarrachante em Aço Inox, Ø4,2 x 32mm, fornecido com bucha de nylon | C22: Ø4,2 x 32mm | D22: 324 | E22: pç | F22: 0.64 | G22: =F22*D22 -> 207.36
B23: Parafuso sextavado em Aço Inox, M6x60mm, fornecido com bucha de nylon | C23: M6x60mm | D23: 14 | E23: pç | F23: 2.8126 | G23: =F23*D23 -> 39.3764
B24: Parafusos Cabeça Chata para Emenda de Barras, Ø1/4″ x7/8″ | C24: Ø1/4″ x 7/8″ | D24: 202 | E24: pç | F24: 1.44 | G24: =F24*D24 -> 290.88
B25: Parafusos Cabeça Chata para Emenda de Barras, Ø1/4″ x 5/8″ | C25: Ø1/4″ x 5/8″ | D25: 8 | E25: pç | F25: 0.22 | G25: =F25*D25 -> 1.76
B26: Terminal Estanhado 1 Furo 1 Compressão, 50mm² | C26: 50mm² | D26: 8 | E26: pç | F26: 0.82 | G26: =F26*D26 -> 6.56

Sheet PISOS
A1: Obra | B1: =[8]ARQUIVOS_BASE!B1 -> WEST VILLAGE
A2: Empresa | B2: =[8]ARQUIVOS_BASE!B2 -> KIRCHNER
A3: Revisão | B3: =[8]ARQUIVOS_BASE!B3 -> 0
A4: RESUMO DE QUANTITATIVO
A6: Quantitativo de Revestimento em piso
A8: REVESTIMENTO PISO
B10: PAVIMENTO | C10: PORCELANATO RETIFICADO 60X60 POLIDO | D10: CERÂMICO | E10: LAMINADO | F10: RODAPÉ POLIESTIRENO RECICLADO BRANCO 10CM - M | G10: RODAPÉ EM PORCELANATO 10CM - M | H10: RODAPÉ EM CERÂMICA 10CM - M | I10: CONCRETO POLIDO | J10: PASTILHA PISCINA | K10: ESCADA | L10: ANTECAMARA | M10: DEMARCAÇÃO VAGAS - AMARELO | N10: PINTURA VAGA PNE - EPÓXI | O10: PINTURA VAGA - EPÓXI | P10: ANTIDERRAPANTE | Q10: GRAMA SINTÉTICA | R10: PINTURA EPÓXI - CIRCULAÇÃO | S10: PINTURA COBERTURA | T10: CONTRAPISO (M2) | U10: CONTRAPISO ACÚSTICO
B11: TÉRREO | C11: =33.65+8.895+35.65+6.8+6.8+3.04+3.04+110.7+122 -> 330.575 | D11: =4.18+4.08+2.5+2.05 -> 12.81 | F11: =(23.4-4.6-0.98-0.98-0.98-1.2-1.2)+(52.95-2.975-1.825)+(53.06-4.175) -> 110.495 | G11: =((3.1-0.65)*45)+(58.27-45*0.65)+10.88 -> 150.15 | H11: 4 | I11: =O11+R11 -> 333.78 | K11: 15.9 | L11: 2.05 | M11: 7.19 | O11: =14.3+14+13.14+12.5+14+13.75+12.75+12.75+12.75+12.5+12.5+14+17.1 -> 176.04 | Q11: 0 | R11: 157.74 | T11: =SUM(C11,D11,E11,K11,L11,P11) -> 361.335
B12: G1 | H12: 4 | I12: 780.83 | K12: 15.75 | L12: 2.05 | M12: 44.73 | O12: =103.75+53.62+39.05+105.34+44.8+40.6 -> 387.16 | P12: =(F12)*I12 -> 0 | Q12: 0 | R12: 385.98 | T12: =SUM(C12,D12,E12,K12,L12,P12) -> 17.8
B13: G2 | H13: 4 | I13: =I12 -> 780.83 | K13: 15.75 | L13: 2.05 | M13: =7.19+42.38+((1.4*6.8)) -> 59.09 | N13: 40.6 | O13: 346.56 | P13: =(F13)*I13 -> 0 | Q13: 0 | R13: 385.98 | T13: =SUM(C13,D13,E13,K13,L13,P13) -> 17.8
B14: G3 | H14: 4 | I14: =320.85+18.5+14+12.5+12.5+12.75+12.75+12.75+12.75+16+28+16.8+14.3+14+13.45+12.5+12.5+13.45+14+40.8+14+12.5+12.5+12.75+12.75+12.75+12.75+14.5 -> 729.65 | K14: 15.75 | L14: 2.05 | M14: =7.19+42.38+(1.2*5)+((1.4*6.8)) -> 65.09 | N14: =40.6+18.5 -> 59.1 | P14: =(F14)*I14 -> 0 | Q14: 0 | R14: 385.98 | T14: =SUM(C14,D14,E14,K14,L14,P14) -> 17.8
B15: LAZER | C15: =50.15+48.5+50.15+112.65+3.21+43+3.25+3.76+3.05+2.2+3.05+3.05+10.2+16.7+35.85 -> 388.77 | F15: =(29.8-7.9)+27.75+(54.79-4.3-5.55)+(16.9-2.9-2)+12.9+(27.28-2-4.35)+(65.55-1.2-4.975-4.35-2.05-4.3-5.85)+(26.4-1.2-5.85-4) -> 198.595 | G15: =(97.51-3.55-1.8-2-2.9-2-2.05)+(29.3-4)+(22.6-2.5-1.85-0.9)+(20.6-1.2) -> 145.26 | H15: =5.8-1.8 -> 4 | J15: =15.15+41.45 -> 56.6 | K15: 15.75 | L15: 2.05 | N15: 0 | O15: =(E15)*I15 -> 0 | P15: =23.8+31.3+134 -> 189.1 | Q15: 49.75 | R15: 59.65 | T15: =SUM(C15,D15,J15,E15,K15,L15,P15,I15,R15,Q15) -> 761.67
B16: PAV. TIPO (15X) | C16: =(((3.78+3+2.9+3.06+5.65+14.55+3.23+1.95+15.7+9.35+6.05+8.8+10.6+4.6+2.15+3+3+7.4)*2)+25.05)*15 -> 3638.85 | D16: =(2.25+1.52+1.48+2.23+1.38+1.38)*15 -> 153.6 | E16: =((9.75+8+11.7+7.75+9.75+12.15)*2)*15 -> 1773 | F16: =(80.7+(251.27*2))*15 -> 8748.6 | H16: =9.92+9.92+4.84+4.84+6.9+6.9 -> 43.32 | K16: =15.75*15 -> 236.25 | L16: =15*2.4 -> 36 | N16: 0 | O16: =(E16)*I16 -> 0 | P16: =(F16)*I16 -> 0 | R16: =P22*I16 -> 0 | T16: =SUM(D16,K16,L16,947.85) -> 1373.7 | U16: =SUM(C16,E16-947.85) -> 4464
B17: CASA DE MÁQUINAS | D17: =6.3+6.2 -> 12.5 | H17: 10.9 | K17: 15.75 | L17: 2.4 | N17: 0 | O17: 0 | P17: =(F17)*I17 -> 0 | Q17: 0 | R17: 0 | S17: =406.77+7.84 -> 414.61 | T17: =SUM(C17,D17,E17,K17,L17,P17,I17) -> 30.65
B18: RESERVATÓRIO | D18: 15.75 | K18: 15.75 | N18: 0 | O18: 0 | P18: =(F18)*I18 -> 0 | Q18: 0 | R18: 0 | T18: =SUM(C18,D18,E18,K18,L18,P18,I18) -> 31.5
B19: TOTAL | C19: =SUM(C11:C18) -> 4358.195 | D19: =SUM(D11:D18) -> 194.66 | E19: =SUM(E11:E18) -> 1773 | F19: =SUM(F11:F18) -> 9057.69 | G19: =SUM(G11:G18) -> 295.41 | H19: =SUM(H11:H18) -> 74.22 | I19: =SUM(I11:I18) -> 2625.09 | J19: =SUM(J11:J18) -> 56.6 | ... L19: =SUM(L11:L18) -> 48.65 | N19: =SUM(N11:N18) -> 99.7 | O19: =SUM(O11:O18) -> 909.76 | P19: =SUM(P11:P18) -> 189.1 | Q19: =SUM(Q11:Q18) -> 49.75 | R19: =SUM(R11:R18) -> 1375.33 | T19: =SUM(T11:T18) -> 2612.255 | U19: =SUM(U11:U18) -> 4464
C22: ÁREA
B23: CALÇADA EM BLOCO INTERTRAVADO | C23: =225.25 -> 225.25
B24: PISO PODOTÁTIL DE ALERTA | C24: =47*0.25 -> 11.75

Sheet FORRO
A1: Obra | B1: =[8]ARQUIVOS_BASE!B1 -> WEST VILLAGE
A2: Empresa | B2: =[8]ARQUIVOS_BASE!B2 -> KIRCHNER
A3: Revisão | B3: =[8]ARQUIVOS_BASE!B3 -> 0
A4: RESUMO DE QUANTITATIVO
A6: Quantitativo de Forro
A8: Quantitativo de forro
B10: PAVIMENTO | C10: ÁREA DE FORRO COMPOSTO INTERNA SECO | D10: ÁREA DE FORRO COMPOSTO INTERNA MOLHADO | E10: ÁREA DE TINTA ESCADAS | F10: ÁREA DE TINTA DUTOS | G10: ÁREA DE TINTA ELEVOR | H10: ÁREA DE TINTA | I10: ÁREA ABERTA
B11: TÉRREO | C11: =122+110.7+33.65+6.8 -> 273.15 | D11: =6.8+35.65+3.04+3.04 -> 48.53 | E11: =15.9+2.05 -> 17.95 | H11: =(((0.58*18)+(0.63*27))*2)+157.38+14.3+14+13.45+12.5+14+13.75+12.75+12.75+12.75+12.5+12.5+14+4.18+4.08+2.5+2.5+8.95 -> 393.74
B12: G1 | E12: =15.9+2.05 -> 17.95 | H12: =818.15-37.32 -> 780.83
B13: G2 | E13: =15.9+2.05 -> 17.95 | H13: =818.15-37.32 -> 780.83
B14: G3 | E14: =15.9+2.05 -> 17.95 | H14: =825.55-37.32 -> 788.23
B15: LAZER | C15: =16.7+10.2+35.85+50.15+48.5+50.15+112.65+43 -> 367.2 | D15: =3.05+3.05+2.2+3.05+3.76+3.25+3.21 -> 21.57 | E15: =15.9+2.05 -> 17.95 | I15: =41.45+134+15.15+49.75+59.65+23.8+31.3 -> 355.1
B16: PAV. TIPO (15X) | C16: =(((7.4+12.15+2.15+9.75+10.6+4.6+8.8+9.35+6.05+15.7+1.95+7.75+11.7+9.75+8+2.9+14.55+5.65)*2)+25.05)*15 -> 4839.75 | D16: =((3.78+3+3.06+3.23+3+3)*2)*15 -> 572.1 | E16: =(15.9+2.05)*15 -> 269.25 | H16: =((5*4.45)+(2.95*0.5)+(1*1.5))*2 -> 50.45
B17: CASA DE MÁQUINAS | E17: =15.9+2.05 -> 17.95 | H17: =6.3+6.2+7.84 -> 20.34 | I17: 406.77
B18: RESERVATÓRIO | E18: =15.9+2.05 -> 17.95 | F18: =2.1+2.1 -> 4.2 | G18: =3.5+3.5 -> 7 | H18: 15.75
B19: TOTAL | C19: =SUM(C11:C18) -> 5480.1 | D19: =SUM(D11:D18) -> 642.2 | E19: =SUM(E11:E18) -> 394.9 | F19: =SUM(F11:F18) -> 4.2 | G19: =SUM(G11:G18) -> 7 | H19: =SUM(H11:H18) -> 2830.17 | I19: =SUM(I11:I18) -> 761.87
B23: RESUMO | C23: ÁREA TOTAL
B24: FORRO TETO | C24: =SUM(C11:D18) -> 6122.3
B25: TINTA TETO | C25: =SUM(E11:G18,H11:H14,H18,H17,H16) -> 3236.27
B26: ABERTO | C26: =SUM(I15:I17) -> 761.87

Sheet FACHADA
A1: Obra | B1: =[8]ARQUIVOS_BASE!B1 -> WEST VILLAGE
A2: Empresa | B2: =[8]ARQUIVOS_BASE!B2 -> KIRCHNER
A3: Revisão | B3: =[8]ARQUIVOS_BASE!B3 -> 0
A4: RESUMO DE QUANTITATIVO
A6: Quantitativo de Acabamento Fachada
A8: ACABAMENTO CERÂMICO DE FACHADA
B10: FACHADA | C10: REVESTIMENTO CERÂMICO - AMADEIRADO (m2) | D10: PASTILHA (m2) | E10: REVESTIMENTO CERÃMICO MARMORIZADO (m2) | F10: BRISE (m2)
B11: FRENTE | C11: =(49.05*2)+67.63+68.14 -> 233.87 | D11: =(34.85)*2+(51.19)+(23.45)+(33.59)+26.74+22.06+43.95+23.45+20.69+39.86+25.58+37.2 -> 417.46 | E11: 114 | F11: 176.4
B12: POSTERIOR | C12: 0 | D12: 0 | E12: 0
B13: DIREITA | C13: 27.27 | D13: =3.69+11.23+21.18+13.95+11.22+21.05 -> 82.32 | E13: 0
B14: ESQUERDA | C14: 27.27 | D14: =3.69+23.82+16.77+21.03+11.45 -> 76.76
B15: TOTAL | C15: =SUM(C11:C14) -> 288.41 | D15: =SUM(D11:D14) -> 576.54 | E15: =SUM(E11:E14) -> 114 | F15: =SUM(F11:F14) -> 176.4
A17: JUNTA DE DILATAÇÃO
B19: PAVIMENTO | C19: JUNTA DE DILATAÇÃO (m)
B20: TÉRREO | C20: 121
B21: G1 | C21: 121.82
B22: G2 | C22: 121.82
B23: G3 | C23: 121.82
B24: LAZER | C24: 95.95
B25: PAV. TIPO (15X) | C25: =95.95*15 -> 1439.25
B26: CASA DE MÁQUINAS | C26: 28.85
B27: TOTAL | C27: =SUM(C20:C26) -> 2050.51

Sheet SERVIÇOS COMPLEMENTARES
A1: Obra | B1: WEST VILLAGE
A2: Empresa | B2: KIRCHNER
A3: Revisão | B3: R00
A4: QUANTIFICAÇÃO
A6: SERVIÇOS COMPLEMENTARES
A8: ÁREA | B8: 10722.5 | C8: M2
B10: Descrição quantitativo | C10: Quantidade | D10: unidade | E10: Preço unitário | F10: Preço total
B11: PAISAGISMO | C11: 1 | D11: vb | E11: 5 | F11: =E11*B8 -> 53612.5
B12: REFORÇO DE REDE ELÉTRICA | C12: 1 | D12: vb | E12: 1.6 | F12: =E12*$B$8 -> 17156
B13: LIMPEZA FINAL DA OBRA | C13: 1 | D13: vb | E13: 15 | F13: =E13*$B$8 -> 160837.5
B14: DESMOBILIZAÇÃO E MOBILIZAÇÃO | C14: 1 | D14: vb | E14: 15 | F14: =E14*$B$8 -> 160837.5
B15: LIGAÇÕES DEFINITIVAS | C15: 1 | D15: vb | E15: 15 | F15: =E15*$B$8 -> 160837.5
B16: COMUNICAÇÃO VISUAL | C16: 1 | D16: vb | E16: 10 | F16: =E16*$B$8 -> 107225
B19: Utilizados índices de obras similares
B20: Imprevistos 1,5% do valor total do orçamento

Sheet MOBILIÁRIO E QUADRA
A1: Obra | B1: =[8]ARQUIVOS_BASE!B1 -> WEST VILLAGE
A2: Empresa | B2: =[8]ARQUIVOS_BASE!B2 -> KIRCHNER
A3: Revisão | B3: =[8]ARQUIVOS_BASE!B3 -> 0
A4: RESUMO DE QUANTITATIVO
A6: Quantitativo de Mobiliário
A8: MOBILIÁRIO
A10: PAVIMENTO | B10: AMBIENTE | C10: ITEM | D10: QUANTIDADE | E10: PREÇO | F10: TOTAL
A11: TÉRREO | B11: HALL DE SERVIÇO | C11: Poltrona Bruges Em Madeira Maciça | D11: 2 | E11: 1736 | F11: =E11*D11 -> 3472
C12: Tapete Indiano Artesanal em Algodão e Lã Estilo Kilim Auren | D12: 1 | E12: 3409.9 | F12: =E12*D12 -> 3409.9
C13: Conjunto Com 2 Mesas De Centro Veneza Cinamomo E Preto | D13: 1 | E13: 503.41 | F13: =E13*D13 -> 503.41
C14: Vaso de Chão (M) C/ Estrelicia 170cm | D14: 1 | E14: 1084 | F14: =E14*D14 -> 1084
C15: Planta natural para interior | D15: 1 | E15: 207.8 | F15: =E15*D15 -> 207.8
C16: Conjunto Enfeite Sala Cerâmico Centro de Mesa | D16: 1 | E16: 400 | F16: =E16*D16 -> 400
C17: Aparador Brest | D17: 1 | E17: 2120 | F17: =E17*D17 -> 2120
B18: FRENTE DO HALL | C18: Vaso de Chão (M) C/ Estrelicia 170cm | D18: 1 | E18: 1084 | F18: =E18*D18 -> 1084
A19: LAZER | B19: TERRAÇO PISCINA | C19: Jogo de Mesa Giratória + 6 Cadeiras Margarida + Guarda Sol | D19: 9 | E19: 8214 | F19: =E19*D19 -> 73926
C20: Espreguiçadeira Lagos em Alumínio e Tela Sintética | D20: 8 | E20: 3288.24 | F20: =E20*D20 -> 26305.92
B21: ESPAÇO GOURMET | C21: Mesa de Jantar Roma Retangular Base Madeira Maciça Design Contemporâneo | D21: 2 | E21: 6852.92 | F21: =E21*D21 -> 13705.84
C22: Cadeira Hillux Madeira Maciça Design Clássico Avi Móveis | D22: 12 | E22: 2472.03 | F22: =E22*D22 -> 29664.36
C23: Poltrona Bruges Em Madeira Maciça | D23: 2 | E23: 1736 | F23: =E23*D23 -> 3472
C24: Banqueta Giratória Zattini Estofada Estrutura Madeira de Manejo | D24: 8 | E24: 2091.01 | F24: =E24*D24 -> 16728.08
C25: Electrolux Cooktop de Indução IE60P 4 zonas e Painel Touch Preto 220V | D25: 1 | E25: 2399.9 | F25: =E25*D25 -> 2399.9
C26: Geladeira Brastemp Frost Free Evox - Duplex 429L Painel Externo BRW50NKANA | D26: 1 | E26: 2789.91 | F26: =E26*D26 -> 2789.91
C27: FORNO DE EMBUTIR ELÉTRICO ELECTROLUX 80L | D27: 1 | E27: 1808.9 | F27: =E27*D27 -> 1808.9
C28: Conjunto Com 2 Mesas De Centro Veneza Cinamomo E Preto | D28: 1 | E28: 503.41 | F28: =E28*D28 -> 503.41
C29: Planta natural para interior | D29: 1 | E29: 207.8 | F29: =E29*D29 -> 207.8
C30: Smart TV QLED 55" 4K UHD Samsung QN55LS03B - The Frame, Wifi, USB | D30: 1 | E30: 3999 | F30: =E30*D30 -> 3999
C31: Armário Aéreo Madesa Reims 2 Portas de Correr de Vidro Reflex Preto | D31: 2 | E31: 429.9 | F31: =E31*D31 -> 859.8
C32: Kit com 2 Balcões de Cozinha Madesa Agata 3 Gavetas 4 Portas (Sem Tampo e Pia) Rustic/Cinza | D32: 2 | E32: 1089.9 | F32: =E32*D32 -> 2179.8
C33: Kit Cuba de Inox 60x42 com Torneira Monocomando Gourmet Cromada 8024 | D33: 1 | E33: 499.9 | F33: =E33*D33 -> 499.9
... C43: Brinox, Conjunto Panelas, 8Pcs Ceramic Life Smart Plus, Vanilla | D43: 1 | E43: 800 | F43: =E43*D43 -> 800
B44: SALA DE JOGOS | C44: Smart TV QLED 55" 4K UHD Samsung QN55LS03B - The Frame, Wifi, USB | D44: 1 | E44: 3999 | F44: =E44*D44 -> 3999
C45: Mesa de Bilhar Versátil 2P Vintage | D45: 1 | E45: 5192 | F45: =E45*D45 -> 5192
C46: Mesa De Carteado 4 Lugares Redonda Madeira Maciça Jequitibá | D46: 1 | E46: 3999 | F46: =E46*D46 -> 3999
C47: Conjunto Com 2 Mesas De Centro Veneza Cinamomo E Preto | D47: 1 | E47: 503.41 | F47: =E47*D47 -> 503.41
C48: Poltrona Bruges Em Madeira Maciça | D48: 2 | E48: 1736 | F48: =E48*D48 -> 3472
C49: Banqueta Giratória Zattini Estofada Estrutura Madeira de Manejo | D49: 1 | E49: 2091.01 | F49: =E49*D49 -> 2091.01
C50: Aparador Brest | D50: 1 | E50: 2120 | F50: =E50*D50 -> 2120
C51: Poltrona Bruges Em Madeira Maciça | D51: 2 | E51: 1736 | F51: =E51*D51 -> 3472
C52: Mesa de Xadrez Luxo Madeira | D52: 1 | E52: 5025.79 | F52: =E52*D52 -> 5025.79
C53: Poltrona Bruges Em Madeira Maciça | D53: 6 | E53: 1736 | F53: =E53*D53 -> 10416
C54: Taqueira de Parede Bilharts | D54: 1 | E54: 500 | F54: =E54*D54 -> 500
C55: 5 Tacos De Bilhar | D55: 1 | E55: 1000 | F55: =E55*D55 -> 1000
C56: Jogo de Bolas Numeradas 54mm para Sinuca + Bolão Branco | D56: 1 | E56: 400 | F56: =E56*D56 -> 400
... C60: Uno | D60: 1 | E60: 18.9 | F60: =E60*D60 -> 18.9
B61: SALÃO DE FESTAS | C61: Mesa de Jantar Diamante Redonda Base Madeira | D61: 9 | E61: 3497.54 | F61: =E84*D84 -> 6995.08
C62: Noir Conrad Chair, Teak with Woven Rope AE-237T | D62: 54 | E62: 1182 | F62: =E62*D62 -> 63828
C63: Poltrona Bruges Em Madeira Maciça | D63: 2 | E63: 1736 | F63: =E63*D63 -> 3472
C64: Banqueta Giratória Zattini Estofada Estrutura Madeira de Manejo | D64: 8 | E64: 2091.01 | F64: =E64*D64 -> 16728.08
C65: Electrolux Cooktop de Indução IE60P 4 zonas e Painel Touch Preto 220V | D65: 1 | E65: 2399.9 | F65: =E65*D65 -> 2399.9
C66: Geladeira Brastemp Frost Free Evox - Duplex 429L Painel Externo BRW50NKANA | D66: 1 | E66: 2789.91 | F66: =E66*D66 -> 2789.91
C67: FORNO DE EMBUTIR ELÉTRICO ELECTROLUX 80L | D67: 1 | E67: 1808.9 | F67: =E67*D67 -> 1808.9
C68: Conjunto Com 2 Mesas De Centro Veneza Cinamomo E Preto | D68: 1 | E68: 503.41 | F68: =E68*D68 -> 503.41
C69: Planta natural para interior | D69: 1 | E69: 207.8 | F69: =E69*D69 -> 207.8
C70: Smart TV QLED 55" 4K UHD Samsung QN55LS03B - The Frame, Wifi, USB | D70: 1 | E70: 3999 | F70: =E70*D70 -> 3999
C71: Armário Aéreo Madesa Reims 2 Portas de Correr de Vidro Reflex Preto | D71: 3 | E71: 429.9 | F71: =E71*D71 -> 1289.7
C72: Kit com 2 Balcões de Cozinha Madesa Agata 3 Gavetas 4 Portas (Sem Tampo e Pia) Rustic/Cinza | D72: 3 | E72: 1089.9 | F72: =E72*D72 -> 3269.7
C73: Kit Cuba de Inox 60x42 com Torneira Monocomando Gourmet Cromada 8024 | D73: 1 | E73: 499.9 | F73: =E73*D73 -> 499.9
... C83: Conjunto Panelas | D83: 1 | E83: 1000 | F83: =E83*D83 -> 1000
B84: TERRAÇO EXTERNO | C84: Mesa de Jantar Diamante Redonda Base Madeira | D84: 2 | E84: 3497.54 | F84: =E84*D84 -> 6995.08
C85: Noir Conrad Chair, Teak with Woven Rope AE-237T | D85: 8 | E85: 1182 | F85: =E85*D85 -> 9456
C86: Sofá para Área Havana | D86: 1 | E86: 2773 | F86: =E86*D86 -> 2773
C87: Sofá para sala e área externa, sofá Londres Slin de aluminio e corda nautica preta | D87: 2 | E87: 2551.91 | F87: =E87*D87 -> 5103.82
C88: Vaso de Chão (M) C/ Estrelicia 170cm | D88: 2 | E88: 1084 | F88: =E88*D88 -> 2168
C89: Conjunto Com 2 Mesas De Centro Veneza Cinamomo E Preto | D89: 2 | E89: 503.41 | F89: =E89*D89 -> 1006.82
C90: Planta natural para interior | D90: 2 | E90: 207.8 | F90: =E90*D90 -> 415.6
C91: Lareira a Gás Externa - Fire Pit Retangular | D91: 1 | E91: 5262 | F91: =E91*D91 -> 5262
C92: BANCO DE JARDIM RENDADÃO ESTILO PRAÇA 150cm | D92: 3 | E92: 690 | F92: =E92*D92 -> 2070
C93: Conjunto Argentina - Mesa + 4 Cadeiras - Alumínio e Fibra Sintética - Original Móveis | D93: 2 | E93: 1555 | F93: =E93*D93 -> 3110
B94: PLAYGROUND | C94: Playground De Madeira Médio Com 12 Brinquedos - Cercado de Madeira | D94: 1 | E94: 7399 | F94: =E94*D94 -> 7399
C95: Combo de Brinquedos de Ferro | D95: 1 | E95: 4799 | F95: =E95*D95 -> 4799
C96: Poltrona Bruges Em Madeira Maciça | D96: 2 | E96: 1736 | F96: =E96*D96 -> 3472
C97: Conjunto Com 2 Mesas De Centro Veneza Cinamomo E Preto | D97: 1 | E97: 503.41 | F97: =E97*D97 -> 503.41
C98: Planta natural para interior | D98: 1 | E98: 207.8 | F98: =E98*D98 -> 207.8
B99: RECREAÇÃO INFANTIL | C99: Poltrona Bruges Em Madeira Maciça | D99: 2 | E99: 1736 | F99: =E99*D99 -> 3472
C100: Conjunto Com 2 Mesas De Centro Veneza Cinamomo E Preto | D100: 1 | E100: 503.41 | F100: =E100*D100 -> 503.41
C101: Planta natural para interior | D101: 1 | E101: 207.8 | F101: =E101*D101 -> 207.8
C102: Piscina de Bolinhas 1.50 Mts C/ 1500 Bolinhas11395 | D102: 1 | E102: 1395 | F102: =E102*D102 -> 1395
C103: Smart TV QLED 55" 4K UHD Samsung QN55LS03B - The Frame, Wifi, USB | D103: 1 | E103: 3999 | F103: =E103*D103 -> 3999
C104: Brinquedos | D104: 5 | E104: 200 | F104: =E104*D104 -> 1000
C105: Tapete Térmico Infantil 180cm x 120 cm | D105: 1 | E105: 83.33 | F105: =E105*D105 -> 83.33
C106: Kit 10 Tatames 50x50 20mm Econômico (Colorido) | D106: 1 | E106: 69.9 | F106: =E106*D106 -> 69.9
C107: Cadeira Plástica Infantil | D107: 12 | E107: 50 | F107: =E107*D107 -> 600
C108: Mesa Plástica Infantil Tramontina Dona Chica 64cm x 50cm Rosa | D108: 3 | E108: 121.15 | F108: =E108*D108 -> 363.45
B109: ESPAÇO FITNESS | C109: Smart TV QLED 55" 4K UHD Samsung QN55LS03B - The Frame, Wifi, USB | D109: 1 | E109: 3999 | F109: =E109*D109 -> 3999
C110: Dream Fitness CONCEPT 2.5 - Esteira Eletrônica BIVOLT, Preto | D110: 1 | E110: 2415.44 | F110: =E110*D110 -> 2415.44
C111: Leg Press 45º Profissional | D111: 1 | E111: 3470 | F111: =E111*D111 -> 3470
C112: Dream Fitness Vertical MAX V - Bicicleta Ergométrica, PRETO | D112: 1 | E112: 899.9 | F112: =E112*D112 -> 899.9
C113: Estação de musculação x2000/torre de peso 72 kg/ completa carenada/ linha condominios | D113: 1 | E113: 5390 | F113: =E113*D113 -> 5390
C114: Estação musculação, banco de supino gallant elite x gbs1h01a-pt- preto | D114: 1 | E114: 499.2 | F114: =E114*D114 -> 499.2
C115: Suporte de Anilha 500 kg | D115: 2 | E115: 690 | F115: =E115*D115 -> 1380
C116: Barra Guiada Smith Stander Móvel | D116: 1 | E116: 1960 | F116: =E116*D116 -> 1960
C117: Cross Over Profissional | D117: 1 | E117: 6980 | F117: =E117*D117 -> 6980
C118: Cadeira Flexora/ Extensora Profissional 120kg | D118: 1 | E118: 7850 | F118: =E118*D118 -> 7850
C119: Academia Particular Polimet Polimet Unissex Preto | D119: 1 | E119: 649.99 | F119: =E119*D119 -> 649.99
C120: Bola Pilates 65cm C/Bomba Cinza Yoga Abdominal Ginástica Fitness | D120: 2 | E120: 69.99 | F120: =E120*D120 -> 139.98
C121: Elíptico Transport L100 Podiumfit Magnético 8carga | D121: 1 | E121: 1890 | F121: =E121*D121 -> 1890
... C126: Suporte Torre para 5 Pares de Halteres | D126: 1 | E126: 199.99 | F126: =E126*D126 -> 199.99
B127: ESPAÇO FUNCIONAL | C127: Bola Pilates 65cm C/Bomba Cinza Yoga Abdominal Ginástica Fitness | D127: 3 | E127: 69.99 | F127: =E127*D127 -> 209.97
C128: Tapete (Yoga, Pilates, Fitness, Ginástica) - Preto Macio 1,70m x 60cm | D128: 3 | E128: 22.28 | F128: =E128*D128 -> 66.84
...

Sheet EPC's
A1: Obra | B1: WEST VILLAGE
A2: Empresa | B2: KIRCHNER
A3: Revisão | B3: R00
A4: LEVANTAMENTO QUANTITATIVO
A6: Equipamentos de proteção coletiva
A8: Bandejas de proteção
B10: Descrição | C10: Unidade | D10: Quantidade
B11: Perímetro de projeção do embasamento | C11: m | D11: 118
B12: Perímetro de projeção da torre | C12: m | D12: 94.44
B13: Número de montagens de bandeja primária | C13: un | D13: 1
B14: Número de montagens de bandeja secundária | C14: un | D14: 2
B15: Bandeja de proteção primária | C15: m | D15: =D11+D12 -> 212.44
B16: Bandeja de proteção secundária | C16: m | D16: =D12*2 -> 188.88
A18: Guarda - corpo de desforma
B20: Descrição | C20: Unidade | D20: Quantidade
B21: Perímetro de projeção do embasamento | C21: m | D21: =D11 -> 118
B22: Repetições de pavimentos | C22: un | D22: 4
B23: Proteção de periferia pós desforma | C23: m | D23: =D21*D22 -> 472
A25: Tela fachadeira
B27: Descrição | C27: Unidade | D27: Quantidade
B28: Perímetro de projeção embasamento | C28: m | D28: =D11 -> 118
B29: Perímetro de projeção torre | C29: m | D29: =D12 -> 94.44
B30: Altura do embasamento | C30: m | D30: 14.1
B31: Altura da torre | C31: m | D31: 49.42
B32: Tela fachadeira | C32: m2 | D32: =D28*D30+D29*D31 -> 6331.0248
A34: Fechamento removível de vãos em madeira
B36: Descrição | C36: Unidade | D36: Quantidade
B37: Largura das portas de elevadores | C37: m2 | D37: =1.2*2.2 -> 2.64
B38: Quantidade de portas de elevadores | C38: un | D38: 40
B39: Fechamento removível de vãos em madeira | C39: m2 | D39: =D38*D37 -> 105.6
A41: Sinalização com placa indicativa fixada na estrutura por pregos
B43: Descrição | C43: Unidade | D43: Quantidade
B44: Dimensão padrão da placa - 30x20cm | C44: m2 | D44: =0.3*0.2 -> 0.06
B45: Quantidade de placas por pavimento | C45: un | D45: 10
B46: Quantidade de pavimentos | C46: un | D46: 23
B47: Área total de placas | C47: m2 | D47: =D44*D45*D46 -> 13.8
A49: Tapume
B51: Descrição | C51: Unidade | D51: Quantidade
B52: Perímetro de embasamento | C52: m | D52: 118
B53: Altura do tapume | C53: m | D53: 2.2
B54: Cobertura para proteção de pedestres | C54: m2 | D54: =D53*D52 -> 259.6
A56: Guarda - corpo de vãos: aplicado em metragens de esquadrias periféricas (guarda - corpo de sacadas)
B58: Descrição | C58: Unidade | D58: Quantidade
B59: Perímetro de sacadas | C59: m | D59: =4.6+1.75+1.75+4.6+2.95+1.85+1.95+1.5+1.6+1.6+1.5+1.85+1.95 -> 29.45
B60: Repetições de pavimentos | C60: un | D60: 15
B61: Proteção de periferia pós desforma | C61: m | D61: =D59*D60 -> 441.75
A63: Rede de proteção tipo SQLA Leve
B65: Descrição | C65: Unidade | D65: Quantidade
B66: Perímetro da torre | C66: m | D66: 94.44
B67: Altura entre platibanda da cobertura e última bandeja secundária | C67: m | D67: 10.78
B68: Área de rede de proteção | C68: m2 | D68: =D67*D66 -> 1018.0632
